.source dalvik_source_VirusShare_32e70f448ebd75661a1cb12f9cd8e013.apk
.class public final  b
.super java/lang/Object
.implements  java/lang/Runnable
.field private "a" Lc;
.field private "b" Ld;
.field private volatile "c" Z
.field private "d" Ljava/lang/String;

.method <init>(Lc;Ld;)V
.limit locals 3
.limit stack 200
  nop
  aload_0
  invokespecial java/lang/Object/<init>()V
  aload_0
  aload_1
  putfield b/a Lc;
  aload_0
  aload_2
  putfield b/b Ld;
  return
  nop
.end <method>

.method final a()V
.limit locals 2
.limit stack 200
  nop
  iconst_1
  istore_1
  aload_0
  iload_1
  putfield b/c Z
  return
  nop
.end <method>

.method final a(Ljava/lang/String;)V
.limit locals 4
.limit stack 200
  nop
  aload_0
  aload_1
  putfield b/d Ljava/lang/String;
  iconst_0
  istore_2
  aload_0
  iload_2
  putfield b/c Z
  new java/lang/Thread
  astore_3
  aload_3
  aload_0
  invokespecial java/lang/Thread/<init>(Ljava/lang/Runnable;)V
  aload_3
  invokevirtual java/lang/Thread/start()V
  return
  nop
.end <method>

.method private a(Ljava/net/HttpURLConnection;)V
.limit locals 20
.limit stack 200
  nop
  ldc "X-Afma-Tracking-Urls"
  astore 5
  aload_1
  astore_2
  aload_2
  aload 5
  invokevirtual java/net/HttpURLConnection/getHeaderField(Ljava/lang/String;)Ljava/lang/String;
  astore 4
  new java/lang/NoClassDefFoundError
  dup
  invokespecial java/lang/NoClassDefFoundError/<init>()V
  athrow
  iload 4
  ifeq Label0
  new java/util/StringTokenizer
  astore 6
  aload 6
  aload 4
  invokespecial java/util/StringTokenizer/<init>(Ljava/lang/String;)V
Label1:
  aload 6
  invokevirtual java/util/StringTokenizer/hasMoreTokens()Z
  istore 7
  iload 7
  invokestatic app/DummyClass/invokeIfStmt(Z)V
  iload 7
  ifeq Label0
  aload 6
  invokevirtual java/util/StringTokenizer/nextToken()Ljava/lang/String;
  astore 4
  aload_0
  astore_2
  aload_2
  getfield b/b Ld;
  astore 8
  aload 8
  aload 4
  invokevirtual d/a(Ljava/lang/String;)V
  goto Label1
Label0:
  aload_0
  astore_2
  aload_1
  astore_3
  aload_2
  aload_3
  invokespecial b/b(Ljava/net/HttpURLConnection;)V
  ldc "X-Afma-Refresh-Rate"
  astore 5
  aload_1
  astore_2
  aload_2
  aload 5
  invokevirtual java/net/HttpURLConnection/getHeaderField(Ljava/lang/String;)Ljava/lang/String;
  astore 4
  aload 4
  invokestatic app/DummyClass/invokeIfStmt(Ljava/lang/Object;)V
  aload 4
  ifnull Label2
Label7:
  aload 4
  invokestatic java/lang/Float/parseFloat(Ljava/lang/String;)F
  fstore 9
  aload_0
  astore_2
  aload_2
  getfield b/b Ld;
  astore 8
  aload 8
  fload 9
  invokevirtual d/a(F)V
  aload_0
  astore_2
  aload_2
  getfield b/b Ld;
  astore 8
  aload 8
  invokevirtual d/p()Z
  istore 7
  iload 7
  invokestatic app/DummyClass/invokeIfStmt(Z)V
  iload 7
  ifne Label2
  aload_0
  astore_2
  aload_2
  getfield b/b Ld;
  astore 8
  aload 8
  invokevirtual d/d()V
Label2:
  ldc "X-Afma-Interstitial-Timeout"
  astore 5
  aload_1
  astore_2
  aload_2
  aload 5
  invokevirtual java/net/HttpURLConnection/getHeaderField(Ljava/lang/String;)Ljava/lang/String;
  astore 4
  aload 4
  invokestatic app/DummyClass/invokeIfStmt(Ljava/lang/Object;)V
  aload 4
  ifnull Label3
Label9:
  aload 4
  invokestatic java/lang/Float/parseFloat(Ljava/lang/String;)F
  fstore 10
  aload_0
  astore_2
  aload_2
  getfield b/b Ld;
  astore 8
  ldc 1000.000000
  fstore 11
  fload 10
  fload 11
  fmul
  fstore 10
  fload 10
  f2l
  lstore 12
  aload 8
  lload 12
  invokevirtual d/a(J)V
Label3:
  ldc "X-Afma-Orientation"
  astore 5
  aload_1
  astore_2
  aload_2
  aload 5
  invokevirtual java/net/HttpURLConnection/getHeaderField(Ljava/lang/String;)Ljava/lang/String;
  astore 4
  aload 4
  invokestatic app/DummyClass/invokeIfStmt(Ljava/lang/Object;)V
  aload 4
  ifnull Label4
  ldc "portrait"
  astore 5
  aload 4
  aload 5
  invokevirtual java/lang/String/equals(Ljava/lang/Object;)Z
  istore 7
  iload 7
  invokestatic app/DummyClass/invokeIfStmt(Z)V
  iload 7
  ifeq Label5
  aload_0
  astore_2
  aload_2
  getfield b/a Lc;
  astore 14
  invokestatic com/google/ads/util/AdUtil/b()I
  istore 15
  aload 14
  iload 15
  invokevirtual c/a(I)V
Label4:
  return
Label6:
  astore 16
  new java/lang/StringBuilder
  astore 17
  aload 17
  invokespecial java/lang/StringBuilder/<init>()V
  ldc "Could not get refresh value: "
  astore 5
  aload 17
  aload 5
  invokevirtual java/lang/StringBuilder/append(Ljava/lang/String;)Ljava/lang/StringBuilder;
  astore 17
  aload 17
  aload 4
  invokevirtual java/lang/StringBuilder/append(Ljava/lang/String;)Ljava/lang/StringBuilder;
  astore 17
  aload 17
  invokevirtual java/lang/StringBuilder/toString()Ljava/lang/String;
  astore 18
  aload 18
  astore_2
  aload_2
  aload 16
  invokestatic com/google/ads/util/a/b(Ljava/lang/String;Ljava/lang/Throwable;)V
  goto Label2
Label8:
  astore 19
  new java/lang/StringBuilder
  astore 17
  aload 17
  invokespecial java/lang/StringBuilder/<init>()V
  ldc "Could not get timeout value: "
  astore 5
  aload 17
  aload 5
  invokevirtual java/lang/StringBuilder/append(Ljava/lang/String;)Ljava/lang/StringBuilder;
  astore 17
  aload 17
  aload 4
  invokevirtual java/lang/StringBuilder/append(Ljava/lang/String;)Ljava/lang/StringBuilder;
  astore 17
  aload 17
  invokevirtual java/lang/StringBuilder/toString()Ljava/lang/String;
  astore 18
  aload 18
  astore_2
  aload 19
  astore_3
  aload_2
  aload_3
  invokestatic com/google/ads/util/a/b(Ljava/lang/String;Ljava/lang/Throwable;)V
  goto Label3
Label5:
  ldc "landscape"
  astore 5
  aload 4
  aload 5
  invokevirtual java/lang/String/equals(Ljava/lang/Object;)Z
  istore 7
  iload 7
  invokestatic app/DummyClass/invokeIfStmt(Z)V
  iload 7
  ifeq Label4
  aload_0
  astore_2
  aload_2
  getfield b/a Lc;
  astore 14
  invokestatic com/google/ads/util/AdUtil/a()I
  istore 15
  aload 14
  iload 15
  invokevirtual c/a(I)V
  goto Label4
  nop
.end <method>

.method private b(Ljava/net/HttpURLConnection;)V
.limit locals 7
.limit stack 200
  nop
  ldc "X-Afma-Click-Tracking-Urls"
  astore_3
  aload_1
  aload_3
  invokevirtual java/net/HttpURLConnection/getHeaderField(Ljava/lang/String;)Ljava/lang/String;
  astore_2
  new java/lang/NoClassDefFoundError
  dup
  invokespecial java/lang/NoClassDefFoundError/<init>()V
  athrow
  iload_2
  ifeq Label0
  new java/util/StringTokenizer
  astore 4
  aload 4
  aload_2
  invokespecial java/util/StringTokenizer/<init>(Ljava/lang/String;)V
Label1:
  aload 4
  invokevirtual java/util/StringTokenizer/hasMoreTokens()Z
  istore 5
  iload 5
  invokestatic app/DummyClass/invokeIfStmt(Z)V
  iload 5
  ifeq Label0
  aload 4
  invokevirtual java/util/StringTokenizer/nextToken()Ljava/lang/String;
  astore_2
  aload_0
  getfield b/a Lc;
  astore 6
  aload 6
  aload_2
  invokevirtual c/a(Ljava/lang/String;)V
  goto Label1
Label0:
  return
  nop
.end <method>

.method public final run()V
.limit locals 26
.limit stack 200
  .catch  java/lang/Exception <from> Label4 <to> Label12 <using> Label11
  .catch  java/lang/Exception <from> Label12 <to> Label15 <using> Label11
  .catch  java/lang/Exception <from> Label15 <to> Label16 <using> Label11
  .catch  java/lang/Exception <from> Label18 <to> Label0 <using> Label11
  .catch  java/lang/Exception <from> Label19 <to> Label20 <using> Label11
  .catch  java/lang/Exception <from> Label21 <to> Label22 <using> Label11
  .catch  java/lang/Exception <from> Label25 <to> Label11 <using> Label11
  .catch  java/lang/Exception <from> Label26 <to> Label27 <using> Label11
  .catch  java/lang/Exception <from> Label28 <to> Label29 <using> Label11
  .catch  java/lang/Exception <from> Label31 <to> Label32 <using> Label11
  .catch  java/lang/Exception <from> Label33 <to> Label34 <using> Label11
  nop
Label4:
  aload_0
  astore_1
  aload_1
  getfield b/c Z
  istore_3
  new java/lang/NoClassDefFoundError
  dup
  invokespecial java/lang/NoClassDefFoundError/<init>()V
  athrow
  iload_3
  ifne Label0
  new java/net/URL
  astore 4
  aload_0
  astore_1
  aload_1
  getfield b/d Ljava/lang/String;
  astore 5
Label12:
  aload 4
  aload 5
  invokespecial java/net/URL/<init>(Ljava/lang/String;)V
  aload 4
  invokevirtual java/net/URL/openConnection()Ljava/net/URLConnection;
  astore 6
Label15:
  aload 6
  astore 8
  aload 8
  checkcast java/net/HttpURLConnection
  astore 8
  aload 8
  astore 7
Label16:
  aload_0
  astore_1
  aload_1
  getfield b/b Ld;
  astore 9
  aload 9
  invokevirtual d/e()Landroid/app/Activity;
  astore 10
  aload 10
  invokestatic app/DummyClass/invokeIfStmt(Ljava/lang/Object;)V
  aload 10
  ifnonnull Label1
  ldc "activity was null in AdHtmlLoader."
  astore 11
  aload 11
  invokestatic com/google/ads/util/a/c(Ljava/lang/String;)V
  aload_0
  astore_1
  aload_1
  getfield b/a Lc;
  astore 12
  getstatic com/google/ads/AdRequest$ErrorCode/INTERNAL_ERROR Lcom/google/ads/AdRequest$ErrorCode;
  astore 13
  aload 12
  aload 13
  invokevirtual c/a(Lcom/google/ads/AdRequest$ErrorCode;)V
Label18:
  aload 7
  invokevirtual java/net/HttpURLConnection/disconnect()V
Label0:
  return
Label1:
  aload 10
  invokevirtual android/app/Activity/getApplicationContext()Landroid/content/Context;
  astore 14
  aload 7
  aload 14
  invokestatic com/google/ads/util/AdUtil/a(Ljava/net/HttpURLConnection;Landroid/content/Context;)V
  iconst_0
  istore 15
  aload 7
  iload 15
  invokevirtual java/net/HttpURLConnection/setInstanceFollowRedirects(Z)V
  aload 7
  invokevirtual java/net/HttpURLConnection/connect()V
  aload 7
  invokevirtual java/net/HttpURLConnection/getResponseCode()I
  istore 16
  dload 16
  invokestatic app/DummyClass/invokeIfStmt(D)V
  sipush 300
  istore 15
  iload 15
  iload 16
  if_icmpgt Label2
  dload 16
  invokestatic app/DummyClass/invokeIfStmt(D)V
  sipush 400
  istore 15
  iload 16
  iload 15
  if_icmpge Label2
  ldc "Location"
  astore 11
  aload 7
  aload 11
  invokevirtual java/net/HttpURLConnection/getHeaderField(Ljava/lang/String;)Ljava/lang/String;
  astore 5
  aload 5
  invokestatic app/DummyClass/invokeIfStmt(Ljava/lang/Object;)V
  aload 5
  ifnonnull Label3
  new java/lang/StringBuilder
  astore 17
  aload 17
  astore_1
  aload_1
  invokespecial java/lang/StringBuilder/<init>()V
  ldc "Could not get redirect location from a "
  astore 11
  aload 17
  astore_1
  aload_1
  aload 11
  invokevirtual java/lang/StringBuilder/append(Ljava/lang/String;)Ljava/lang/StringBuilder;
  astore 17
  aload 17
  astore_1
  aload_1
  iload 16
  invokevirtual java/lang/StringBuilder/append(I)Ljava/lang/StringBuilder;
  astore 17
  ldc " redirect."
  astore 11
  aload 17
  astore_1
  aload_1
  aload 11
  invokevirtual java/lang/StringBuilder/append(Ljava/lang/String;)Ljava/lang/StringBuilder;
  astore 17
  aload 17
  astore_1
  aload_1
  invokevirtual java/lang/StringBuilder/toString()Ljava/lang/String;
  astore 5
  aload 5
  invokestatic com/google/ads/util/a/c(Ljava/lang/String;)V
  aload_0
  astore_1
  aload_1
  getfield b/a Lc;
  astore 12
  getstatic com/google/ads/AdRequest$ErrorCode/INTERNAL_ERROR Lcom/google/ads/AdRequest$ErrorCode;
  astore 13
  aload 12
  aload 13
  invokevirtual c/a(Lcom/google/ads/AdRequest$ErrorCode;)V
Label19:
  aload 7
  invokevirtual java/net/HttpURLConnection/disconnect()V
Label20:
  goto Label0
Label14:
  astore 18
  ldc "Received malformed ad url from javascript."
  astore 11
  aload 18
  astore_1
  aload 11
  aload_1
  invokestatic com/google/ads/util/a/a(Ljava/lang/String;Ljava/lang/Throwable;)V
  aload_0
  astore_1
  aload_1
  getfield b/a Lc;
  astore 12
  getstatic com/google/ads/AdRequest$ErrorCode/INTERNAL_ERROR Lcom/google/ads/AdRequest$ErrorCode;
  astore 13
  aload 12
  aload 13
  invokevirtual c/a(Lcom/google/ads/AdRequest$ErrorCode;)V
  goto Label0
Label3:
  aload_0
  astore_1
  aload_1
  aload 7
  invokespecial b/a(Ljava/net/HttpURLConnection;)V
  aload_0
  astore_1
  aload_1
  aload 5
  putfield b/d Ljava/lang/String;
Label21:
  aload 7
  invokevirtual java/net/HttpURLConnection/disconnect()V
Label22:
  goto Label4
Label13:
  astore 19
  ldc "IOException connecting to ad url."
  astore 11
  aload 19
  astore_1
  aload 11
  aload_1
  invokestatic com/google/ads/util/a/b(Ljava/lang/String;Ljava/lang/Throwable;)V
  aload_0
  astore_1
  aload_1
  getfield b/a Lc;
  astore 12
  getstatic com/google/ads/AdRequest$ErrorCode/NETWORK_ERROR Lcom/google/ads/AdRequest$ErrorCode;
  astore 13
  aload 12
  aload 13
  invokevirtual c/a(Lcom/google/ads/AdRequest$ErrorCode;)V
  goto Label0
Label2:
  dload 16
  invokestatic app/DummyClass/invokeIfStmt(D)V
  sipush 200
  istore 15
  iload 16
  iload 15
  if_icmpne Label5
Label23:
  aload_0
  astore_1
  aload_1
  aload 7
  invokespecial b/a(Ljava/net/HttpURLConnection;)V
  aload 7
  invokevirtual java/net/HttpURLConnection/getInputStream()Ljava/io/InputStream;
  astore 20
  new java/io/BufferedReader
  astore 21
  new java/io/InputStreamReader
  astore 22
  aload 22
  astore_1
  aload 20
  astore_2
  aload_1
  aload_2
  invokespecial java/io/InputStreamReader/<init>(Ljava/io/InputStream;)V
  sipush 4096
  istore 15
  aload 21
  astore_1
  aload 22
  astore_2
  aload_1
  aload_2
  iload 15
  invokespecial java/io/BufferedReader/<init>(Ljava/io/Reader;I)V
  new java/lang/StringBuilder
  astore 17
  aload 17
  astore_1
  aload_1
  invokespecial java/lang/StringBuilder/<init>()V
Label7:
  aload_0
  astore_1
  aload_1
  getfield b/c Z
  istore_3
  iload_3
  invokestatic app/DummyClass/invokeIfStmt(Z)V
  iload_3
  ifne Label6
  aload 21
  astore_1
  aload_1
  invokevirtual java/io/BufferedReader/readLine()Ljava/lang/String;
  astore 5
  aload 5
  invokestatic app/DummyClass/invokeIfStmt(Ljava/lang/Object;)V
  aload 5
  ifnull Label6
  aload 17
  astore_1
  aload_1
  aload 5
  invokevirtual java/lang/StringBuilder/append(Ljava/lang/String;)Ljava/lang/StringBuilder;
  pop
  ldc "\n"
  astore 11
  aload 17
  astore_1
  aload_1
  aload 11
  invokevirtual java/lang/StringBuilder/append(Ljava/lang/String;)Ljava/lang/StringBuilder;
  pop
Label24:
  goto Label7
Label17:
  astore 23
Label25:
  aload 7
  invokevirtual java/net/HttpURLConnection/disconnect()V
  aload 23
  athrow
Label11:
  astore 24
  ldc "An unknown error occurred in AdHtmlLoader."
  astore 11
  aload 24
  astore_1
  aload 11
  aload_1
  invokestatic com/google/ads/util/a/a(Ljava/lang/String;Ljava/lang/Throwable;)V
  aload_0
  astore_1
  aload_1
  getfield b/a Lc;
  astore 12
  getstatic com/google/ads/AdRequest$ErrorCode/INTERNAL_ERROR Lcom/google/ads/AdRequest$ErrorCode;
  astore 13
  aload 12
  aload 13
  invokevirtual c/a(Lcom/google/ads/AdRequest$ErrorCode;)V
  goto Label0
Label6:
  aload 17
  astore_1
  aload_1
  invokevirtual java/lang/StringBuilder/toString()Ljava/lang/String;
  astore 5
  new java/lang/StringBuilder
  astore 17
  aload 17
  astore_1
  aload_1
  invokespecial java/lang/StringBuilder/<init>()V
  ldc "Response content is: "
  astore 11
  aload 17
  astore_1
  aload_1
  aload 11
  invokevirtual java/lang/StringBuilder/append(Ljava/lang/String;)Ljava/lang/StringBuilder;
  astore 17
  aload 17
  astore_1
  aload_1
  aload 5
  invokevirtual java/lang/StringBuilder/append(Ljava/lang/String;)Ljava/lang/StringBuilder;
  astore 17
  aload 17
  astore_1
  aload_1
  invokevirtual java/lang/StringBuilder/toString()Ljava/lang/String;
  astore 25
  aload 25
  astore_1
  aload_1
  invokestatic com/google/ads/util/a/a(Ljava/lang/String;)V
  aload 5
  invokestatic app/DummyClass/invokeIfStmt(Ljava/lang/Object;)V
  aload 5
  ifnull Label8
  aload 5
  invokevirtual java/lang/String/trim()Ljava/lang/String;
  astore 25
  aload 25
  astore_1
  aload_1
  invokevirtual java/lang/String/length()I
  istore 16
  dload 16
  invokestatic app/DummyClass/invokeIfStmt(D)V
  iload 16
  ifgt Label9
Label8:
  new java/lang/StringBuilder
  astore 17
  aload 17
  astore_1
  aload_1
  invokespecial java/lang/StringBuilder/<init>()V
  ldc "Response message is null or zero length: "
  astore 11
  aload 17
  astore_1
  aload_1
  aload 11
  invokevirtual java/lang/StringBuilder/append(Ljava/lang/String;)Ljava/lang/StringBuilder;
  astore 17
  aload 17
  astore_1
  aload_1
  aload 5
  invokevirtual java/lang/StringBuilder/append(Ljava/lang/String;)Ljava/lang/StringBuilder;
  astore 17
  aload 17
  astore_1
  aload_1
  invokevirtual java/lang/StringBuilder/toString()Ljava/lang/String;
  astore 25
  aload 25
  astore_1
  aload_1
  invokestatic com/google/ads/util/a/a(Ljava/lang/String;)V
  aload_0
  astore_1
  aload_1
  getfield b/a Lc;
  astore 12
  getstatic com/google/ads/AdRequest$ErrorCode/NO_FILL Lcom/google/ads/AdRequest$ErrorCode;
  astore 13
  aload 12
  aload 13
  invokevirtual c/a(Lcom/google/ads/AdRequest$ErrorCode;)V
Label26:
  aload 7
  invokevirtual java/net/HttpURLConnection/disconnect()V
Label27:
  goto Label0
Label9:
  aload_0
  astore_1
  aload_1
  getfield b/a Lc;
  astore 12
  aload_0
  astore_1
  aload_1
  getfield b/d Ljava/lang/String;
  astore_1
  aload_1
  astore 25
  aload 25
  astore_1
  aload 12
  aload 5
  aload_1
  invokevirtual c/a(Ljava/lang/String;Ljava/lang/String;)V
Label28:
  aload 7
  invokevirtual java/net/HttpURLConnection/disconnect()V
Label29:
  goto Label0
Label5:
  dload 16
  invokestatic app/DummyClass/invokeIfStmt(D)V
  sipush 400
  istore 15
  iload 16
  iload 15
  if_icmpne Label10
Label30:
  ldc "Bad request"
  astore 11
  aload 11
  invokestatic com/google/ads/util/a/c(Ljava/lang/String;)V
  aload_0
  astore_1
  aload_1
  getfield b/a Lc;
  astore 12
  getstatic com/google/ads/AdRequest$ErrorCode/INVALID_REQUEST Lcom/google/ads/AdRequest$ErrorCode;
  astore 13
  aload 12
  aload 13
  invokevirtual c/a(Lcom/google/ads/AdRequest$ErrorCode;)V
Label31:
  aload 7
  invokevirtual java/net/HttpURLConnection/disconnect()V
Label32:
  goto Label0
Label10:
  new java/lang/StringBuilder
  astore 17
  aload 17
  astore_1
  aload_1
  invokespecial java/lang/StringBuilder/<init>()V
  ldc "Invalid response code: "
  astore 11
  aload 17
  astore_1
  aload_1
  aload 11
  invokevirtual java/lang/StringBuilder/append(Ljava/lang/String;)Ljava/lang/StringBuilder;
  astore 17
  aload 17
  astore_1
  aload_1
  iload 16
  invokevirtual java/lang/StringBuilder/append(I)Ljava/lang/StringBuilder;
  astore 17
  aload 17
  astore_1
  aload_1
  invokevirtual java/lang/StringBuilder/toString()Ljava/lang/String;
  astore 25
  aload 25
  astore_1
  aload_1
  invokestatic com/google/ads/util/a/c(Ljava/lang/String;)V
  aload_0
  astore_1
  aload_1
  getfield b/a Lc;
  astore 12
  getstatic com/google/ads/AdRequest$ErrorCode/INTERNAL_ERROR Lcom/google/ads/AdRequest$ErrorCode;
  astore 13
  aload 12
  aload 13
  invokevirtual c/a(Lcom/google/ads/AdRequest$ErrorCode;)V
Label33:
  aload 7
  invokevirtual java/net/HttpURLConnection/disconnect()V
Label34:
  goto Label0
  nop
.end <method>

