.source dalvik_source_VirusShare_32e70f448ebd75661a1cb12f9cd8e013.apk
.class final  c$c
.super java/lang/Object
.implements  java/lang/Runnable
.field final "a" Lc;
.field private final "b" Ljava/lang/String;
.field private final "c" Ljava/lang/String;
.field private final "d" Landroid/webkit/WebView;

.method public <init>(Lc;Landroid/webkit/WebView;Ljava/lang/String;Ljava/lang/String;)V
.limit locals 5
.limit stack 200
  nop
  aload_0
  aload_1
  putfield c$c/a Lc;
  aload_0
  invokespecial java/lang/Object/<init>()V
  aload_0
  aload_2
  putfield c$c/d Landroid/webkit/WebView;
  aload_0
  aload_3
  putfield c$c/b Ljava/lang/String;
  aload_0
  aload 4
  putfield c$c/c Ljava/lang/String;
  return
  nop
.end <method>

.method public final run()V
.limit locals 7
.limit stack 200
  nop
  aload_0
  getfield c$c/d Landroid/webkit/WebView;
  astore_1
  aload_0
  getfield c$c/b Ljava/lang/String;
  astore_2
  aload_0
  getfield c$c/c Ljava/lang/String;
  astore_3
  ldc "text/html"
  astore 4
  ldc "utf-8"
  astore 5
  iconst_0
  istore 6
  new java/lang/NoClassDefFoundError
  dup
  invokespecial java/lang/NoClassDefFoundError/<init>()V
  athrow
  return
  nop
.end <method>

