.source dalvik_source_VirusShare_32e70f448ebd75661a1cb12f9cd8e013.apk
.class final  c$e
.super java/lang/Object
.implements  java/lang/Runnable
.field final "a" Lc;
.field private final "b" Ld;
.field private final "c" Ljava/util/LinkedList;
.field private final "d" I

.method public <init>(Lc;Ld;Ljava/util/LinkedList;I)V
  .signature_attr "(Ld;Ljava/util/LinkedList<Ljava/lang/String;>;I)V"
.limit locals 5
.limit stack 200
  nop
  aload_0
  aload_1
  putfield c$e/a Lc;
  aload_0
  invokespecial java/lang/Object/<init>()V
  aload_0
  aload_2
  putfield c$e/b Ld;
  aload_0
  aload_3
  putfield c$e/c Ljava/util/LinkedList;
  aload_0
  iload 4
  putfield c$e/d I
  return
  nop
.end <method>

.method public final run()V
.limit locals 4
.limit stack 200
  nop
  aload_0
  getfield c$e/b Ld;
  astore_1
  aload_0
  getfield c$e/c Ljava/util/LinkedList;
  astore_2
  aload_1
  aload_2
  invokevirtual d/a(Ljava/util/LinkedList;)V
  aload_0
  getfield c$e/b Ld;
  astore_1
  aload_0
  getfield c$e/d I
  istore_3
  aload_1
  iload_3
  invokevirtual d/a(I)V
  aload_0
  getfield c$e/b Ld;
  astore_1
  aload_1
  invokevirtual d/q()V
  return
  nop
.end <method>

