.source dalvik_source_VirusShare_32e70f448ebd75661a1cb12f9cd8e013.apk
.class public final  c
.super java/lang/Object
.implements  java/lang/Runnable
.field private "a" Ljava/lang/String;
.field private "b" Ljava/lang/String;
.field private "c" Lb;
.field private "d" Ld;
.field private "e" Lcom/google/ads/AdRequest;
.field private "f" Landroid/webkit/WebView;
.field private "g" Ljava/lang/String;
.field private "h" Ljava/util/LinkedList;
.field private volatile "i" Z
.field private "j" Lcom/google/ads/AdRequest$ErrorCode;
.field private "k" Z
.field private "l" I
.field private "m" Ljava/lang/Thread;

.method public <init>(Ld;)V
.limit locals 14
.limit stack 200
  nop
  aload_0
  invokespecial java/lang/Object/<init>()V
  aload_0
  aload_1
  putfield c/d Ld;
  aconst_null
  astore_2
  aload_0
  aload_2
  putfield c/g Ljava/lang/String;
  aconst_null
  astore_2
  aload_0
  aload_2
  putfield c/b Ljava/lang/String;
  new java/util/LinkedList
  astore_3
  aload_3
  invokespecial java/util/LinkedList/<init>()V
  aload_0
  aload_3
  putfield c/h Ljava/util/LinkedList;
  aconst_null
  astore_2
  aload_0
  aload_2
  putfield c/j Lcom/google/ads/AdRequest$ErrorCode;
  iconst_0
  istore 4
  aload_0
  iload 4
  putfield c/k Z
  iconst_m1
  istore 4
  aload_0
  iload 4
  putfield c/l I
  aload_1
  invokevirtual d/e()Landroid/app/Activity;
  astore 5
  new java/lang/NoClassDefFoundError
  dup
  invokespecial java/lang/NoClassDefFoundError/<init>()V
  athrow
  iload 5
  ifeq Label0
  new g
  astore 6
  aload 5
  invokevirtual android/app/Activity/getApplicationContext()Landroid/content/Context;
  astore 7
  aconst_null
  astore_2
  aload 6
  aload 7
  aload_2
  invokespecial g/<init>(Landroid/content/Context;Lcom/google/ads/AdSize;)V
  aload_0
  aload 6
  putfield c/f Landroid/webkit/WebView;
  aload_0
  getfield c/f Landroid/webkit/WebView;
  astore 8
  new h
  astore 9
  getstatic a/a Ljava/util/Map;
  astore 10
  iconst_0
  istore 4
  iconst_0
  istore 11
  aload 9
  aload_1
  aload 10
  iload 4
  iload 11
  invokespecial h/<init>(Ld;Ljava/util/Map;ZZ)V
  aload 8
  aload 9
  invokevirtual android/webkit/WebView/setWebViewClient(Landroid/webkit/WebViewClient;)V
  aload_0
  getfield c/f Landroid/webkit/WebView;
  astore 8
  bipush 8
  istore 4
  aload 8
  iload 4
  invokevirtual android/webkit/WebView/setVisibility(I)V
  aload_0
  getfield c/f Landroid/webkit/WebView;
  astore 8
  iconst_1
  istore 4
  aload 8
  iload 4
  invokevirtual android/webkit/WebView/setWillNotDraw(Z)V
  new b
  astore 12
  aload 12
  aload_0
  aload_1
  invokespecial b/<init>(Lc;Ld;)V
  aload_0
  aload 12
  putfield c/c Lb;
Label1:
  return
Label0:
  aconst_null
  astore_2
  aload_0
  aload_2
  putfield c/f Landroid/webkit/WebView;
  aconst_null
  astore_2
  aload_0
  aload_2
  putfield c/c Lb;
  ldc "activity was null while trying to create an AdLoader."
  astore 13
  aload 13
  invokestatic com/google/ads/util/a/e(Ljava/lang/String;)V
  goto Label1
  nop
.end <method>

.method private a(Lcom/google/ads/AdRequest;Landroid/app/Activity;)Ljava/lang/String;
.limit locals 40
.limit stack 200
  nop
  aload_2
  astore_3
  new java/lang/NoClassDefFoundError
  dup
  invokespecial java/lang/NoClassDefFoundError/<init>()V
  athrow
  nop
  aload_1
  astore_3
  aload_3
  aload 5
  invokevirtual com/google/ads/AdRequest/getRequestMap(Landroid/content/Context;)Ljava/util/Map;
  astore 6
  aload_0
  astore_3
  aload_3
  getfield c/d Ld;
  astore 7
  aload 7
  invokevirtual d/l()Lf;
  astore 8
  aload 8
  invokevirtual f/h()J
  lstore 9
  ldc2_w 0
  lstore 12
  lload 9
  lload 12
  lcmp
  istore 11
  dload 11
  invokestatic app/DummyClass/invokeIfStmt(D)V
  iload 11
  ifle Label0
  lload 9
  invokestatic java/lang/Long/valueOf(J)Ljava/lang/Long;
  astore 14
  ldc "prl"
  astore 15
  aload 6
  aload 15
  aload 14
  invokeinterface java/util/Map/put(Ljava/lang/Object;Ljava/lang/Object;)Ljava/lang/Object; 3
  pop
Label0:
  aload 8
  invokevirtual f/g()Ljava/lang/String;
  astore 16
  aload 16
  invokestatic app/DummyClass/invokeIfStmt(Ljava/lang/Object;)V
  aload 16
  ifnull Label1
  ldc "ppcl"
  astore 15
  aload 6
  aload 15
  aload 16
  invokeinterface java/util/Map/put(Ljava/lang/Object;Ljava/lang/Object;)Ljava/lang/Object; 3
  pop
Label1:
  aload 8
  invokevirtual f/f()Ljava/lang/String;
  astore 16
  aload 16
  invokestatic app/DummyClass/invokeIfStmt(Ljava/lang/Object;)V
  aload 16
  ifnull Label2
  ldc "pcl"
  astore 15
  aload 6
  aload 15
  aload 16
  invokeinterface java/util/Map/put(Ljava/lang/Object;Ljava/lang/Object;)Ljava/lang/Object; 3
  pop
Label2:
  aload 8
  invokevirtual f/e()J
  lstore 9
  ldc2_w 0
  lstore 12
  lload 9
  lload 12
  lcmp
  istore 11
  dload 11
  invokestatic app/DummyClass/invokeIfStmt(D)V
  iload 11
  ifle Label3
  lload 9
  invokestatic java/lang/Long/valueOf(J)Ljava/lang/Long;
  astore 14
  ldc "pcc"
  astore 15
  aload 6
  aload 15
  aload 14
  invokeinterface java/util/Map/put(Ljava/lang/Object;Ljava/lang/Object;)Ljava/lang/Object; 3
  pop
Label3:
  invokestatic f/i()J
  lstore 17
  lload 17
  invokestatic java/lang/Long/valueOf(J)Ljava/lang/Long;
  astore 14
  ldc "preqs"
  astore 15
  aload 6
  aload 15
  aload 14
  invokeinterface java/util/Map/put(Ljava/lang/Object;Ljava/lang/Object;)Ljava/lang/Object; 3
  pop
  aload 8
  invokevirtual f/j()Ljava/lang/String;
  astore 16
  aload 16
  invokestatic app/DummyClass/invokeIfStmt(Ljava/lang/Object;)V
  aload 16
  ifnull Label4
  ldc "pai"
  astore 15
  aload 6
  aload 15
  aload 16
  invokeinterface java/util/Map/put(Ljava/lang/Object;Ljava/lang/Object;)Ljava/lang/Object; 3
  pop
Label4:
  aload 8
  invokevirtual f/k()Z
  istore 19
  iload 19
  istore_3
  iload_3
  invokestatic app/DummyClass/invokeIfStmt(Z)V
  iload 19
  ifeq Label5
  ldc "aoi_timeout"
  astore 15
  ldc "true"
  astore 20
  aload 20
  astore_3
  aload 6
  aload 15
  aload_3
  invokeinterface java/util/Map/put(Ljava/lang/Object;Ljava/lang/Object;)Ljava/lang/Object; 3
  pop
Label5:
  aload 8
  invokevirtual f/m()Z
  istore 19
  iload 19
  istore_3
  iload_3
  invokestatic app/DummyClass/invokeIfStmt(Z)V
  iload 19
  ifeq Label6
  ldc "aoi_nofill"
  astore 15
  ldc "true"
  astore 20
  aload 20
  astore_3
  aload 6
  aload 15
  aload_3
  invokeinterface java/util/Map/put(Ljava/lang/Object;Ljava/lang/Object;)Ljava/lang/Object; 3
  pop
Label6:
  aload 8
  invokevirtual f/p()Ljava/lang/String;
  astore 16
  aload 16
  invokestatic app/DummyClass/invokeIfStmt(Ljava/lang/Object;)V
  aload 16
  ifnull Label7
  ldc "pit"
  astore 15
  aload 6
  aload 15
  aload 16
  invokeinterface java/util/Map/put(Ljava/lang/Object;Ljava/lang/Object;)Ljava/lang/Object; 3
  pop
Label7:
  aload 8
  invokevirtual f/a()V
  aload 8
  invokevirtual f/d()V
  aload_0
  astore_3
  aload_3
  getfield c/d Ld;
  astore 7
  aload 7
  invokevirtual d/f()Lcom/google/ads/Ad;
  astore 21
  aload 21
  astore_3
  aload_3
  instanceof com/google/ads/InterstitialAd
  istore_3
  iload_3
  istore 19
  iload_3
  invokestatic app/DummyClass/invokeIfStmt(Z)V
  iload 19
  ifeq Label8
  ldc "format"
  astore 15
  ldc "interstitial_mb"
  astore 20
  aload 20
  astore_3
  aload 6
  aload 15
  aload_3
  invokeinterface java/util/Map/put(Ljava/lang/Object;Ljava/lang/Object;)Ljava/lang/Object; 3
  pop
Label11:
  aload_0
  astore_3
  aload_3
  getfield c/d Ld;
  astore 7
  aload 7
  invokevirtual d/h()Ljava/lang/String;
  astore 22
  ldc "slotname"
  astore 15
  aload 22
  astore_3
  aload 6
  aload 15
  aload_3
  invokeinterface java/util/Map/put(Ljava/lang/Object;Ljava/lang/Object;)Ljava/lang/Object; 3
  pop
  ldc "js"
  astore 15
  ldc "afma-sdk-a-v4.1.1"
  astore 20
  aload 20
  astore_3
  aload 6
  aload 15
  aload_3
  invokeinterface java/util/Map/put(Ljava/lang/Object;Ljava/lang/Object;)Ljava/lang/Object; 3
  pop
  aload 5
  invokevirtual android/content/Context/getPackageName()Ljava/lang/String;
  astore 16
Label15:
  aload 5
  invokevirtual android/content/Context/getPackageManager()Landroid/content/pm/PackageManager;
  astore 23
  iconst_0
  istore 25
  aload 23
  astore_3
  iload 25
  istore 4
  aload_3
  aload 16
  iload 4
  invokevirtual android/content/pm/PackageManager/getPackageInfo(Ljava/lang/String;I)Landroid/content/pm/PackageInfo;
  astore 24
Label16:
  aload 24
  astore_3
  aload_3
  getfield android/content/pm/PackageInfo/versionCode I
  istore_3
  iload_3
  istore 26
  aload 5
  invokevirtual android/content/Context/getPackageName()Ljava/lang/String;
  astore 22
  ldc "msid"
  astore 15
  aload 22
  astore_3
  aload 6
  aload 15
  aload_3
  invokeinterface java/util/Map/put(Ljava/lang/Object;Ljava/lang/Object;)Ljava/lang/Object; 3
  pop
  new java/lang/StringBuilder
  astore 27
  aload 27
  astore_3
  aload_3
  invokespecial java/lang/StringBuilder/<init>()V
  aload 27
  astore_3
  iload 26
  istore 4
  aload_3
  iload 4
  invokevirtual java/lang/StringBuilder/append(I)Ljava/lang/StringBuilder;
  astore 27
  ldc ".android."
  astore 15
  aload 27
  astore_3
  aload_3
  aload 15
  invokevirtual java/lang/StringBuilder/append(Ljava/lang/String;)Ljava/lang/StringBuilder;
  astore 27
  aload 5
  invokevirtual android/content/Context/getPackageName()Ljava/lang/String;
  astore 22
  aload 27
  astore_3
  aload 22
  astore 4
  aload_3
  aload 4
  invokevirtual java/lang/StringBuilder/append(Ljava/lang/String;)Ljava/lang/StringBuilder;
  astore 27
  aload 27
  astore_3
  aload_3
  invokevirtual java/lang/StringBuilder/toString()Ljava/lang/String;
  astore 22
  ldc "app_name"
  astore 15
  aload 22
  astore_3
  aload 6
  aload 15
  aload_3
  invokeinterface java/util/Map/put(Ljava/lang/Object;Ljava/lang/Object;)Ljava/lang/Object; 3
  pop
  aload 5
  invokestatic com/google/ads/util/AdUtil/a(Landroid/content/Context;)Ljava/lang/String;
  astore 22
  ldc "isu"
  astore 15
  aload 22
  astore_3
  aload 6
  aload 15
  aload_3
  invokeinterface java/util/Map/put(Ljava/lang/Object;Ljava/lang/Object;)Ljava/lang/Object; 3
  pop
  aload 5
  invokestatic com/google/ads/util/AdUtil/d(Landroid/content/Context;)Ljava/lang/String;
  astore 16
  aload 16
  invokestatic app/DummyClass/invokeIfStmt(Ljava/lang/Object;)V
  aload 16
  ifnonnull Label9
  new c$d
  astore 28
  ldc "NETWORK_ERROR"
  astore 15
  aload 28
  astore_3
  aload_0
  astore 4
  aload_3
  aload 4
  aload 15
  invokespecial c$d/<init>(Lc;Ljava/lang/String;)V
  aload 28
  athrow
Label8:
  aload_0
  astore_3
  aload_3
  getfield c/d Ld;
  astore 7
  aload 7
  invokevirtual d/k()Lcom/google/ads/AdSize;
  astore 29
  aload 29
  astore_3
  aload_3
  invokevirtual com/google/ads/AdSize/toString()Ljava/lang/String;
  astore 16
  aload 16
  invokestatic app/DummyClass/invokeIfStmt(Ljava/lang/Object;)V
  aload 16
  ifnull Label10
  ldc "format"
  astore 15
  aload 6
  aload 15
  aload 16
  invokeinterface java/util/Map/put(Ljava/lang/Object;Ljava/lang/Object;)Ljava/lang/Object; 3
  pop
  goto Label11
Label10:
  new java/util/HashMap
  astore 30
  aload 30
  astore_3
  aload_3
  invokespecial java/util/HashMap/<init>()V
  aload 29
  astore_3
  aload_3
  invokevirtual com/google/ads/AdSize/getWidth()I
  istore 26
  iload 26
  istore_3
  iload_3
  invokestatic java/lang/Integer/valueOf(I)Ljava/lang/Integer;
  astore 31
  ldc "w"
  astore 15
  aload 30
  astore_3
  aload 31
  astore 4
  aload_3
  aload 15
  aload 4
  invokeinterface java/util/Map/put(Ljava/lang/Object;Ljava/lang/Object;)Ljava/lang/Object; 3
  pop
  aload 29
  astore_3
  aload_3
  invokevirtual com/google/ads/AdSize/getHeight()I
  istore 26
  iload 26
  istore_3
  iload_3
  invokestatic java/lang/Integer/valueOf(I)Ljava/lang/Integer;
  astore 31
  ldc "h"
  astore 15
  aload 30
  astore_3
  aload 31
  astore 4
  aload_3
  aload 15
  aload 4
  invokeinterface java/util/Map/put(Ljava/lang/Object;Ljava/lang/Object;)Ljava/lang/Object; 3
  pop
  ldc "ad_frame"
  astore 15
  aload 30
  astore_3
  aload 6
  aload 15
  aload_3
  invokeinterface java/util/Map/put(Ljava/lang/Object;Ljava/lang/Object;)Ljava/lang/Object; 3
  pop
  goto Label11
Label14:
  astore 32
  new c$b
  astore 33
  ldc "NameNotFoundException"
  astore 15
  aload 33
  astore_3
  aload_0
  astore 4
  aload_3
  aload 4
  aload 15
  invokespecial c$b/<init>(Lc;Ljava/lang/String;)V
  aload 33
  athrow
Label9:
  ldc "net"
  astore 15
  aload 6
  aload 15
  aload 16
  invokeinterface java/util/Map/put(Ljava/lang/Object;Ljava/lang/Object;)Ljava/lang/Object; 3
  pop
  aload 5
  invokestatic com/google/ads/util/AdUtil/e(Landroid/content/Context;)Ljava/lang/String;
  astore 16
  aload 16
  invokestatic app/DummyClass/invokeIfStmt(Ljava/lang/Object;)V
  aload 16
  ifnull Label12
  aload 16
  invokevirtual java/lang/String/length()I
  istore 26
  iload 26
  istore_3
  dload_3
  invokestatic app/DummyClass/invokeIfStmt(D)V
  iload 26
  ifeq Label12
  ldc "cap"
  astore 15
  aload 6
  aload 15
  aload 16
  invokeinterface java/util/Map/put(Ljava/lang/Object;Ljava/lang/Object;)Ljava/lang/Object; 3
  pop
Label12:
  aload 5
  invokestatic com/google/ads/util/AdUtil/f(Landroid/content/Context;)Lcom/google/ads/util/AdUtil$a;
  astore 34
  aload 34
  astore_3
  aload_3
  invokevirtual com/google/ads/util/AdUtil$a/ordinal()I
  istore 26
  iload 26
  istore_3
  iload_3
  invokestatic java/lang/Integer/valueOf(I)Ljava/lang/Integer;
  astore 31
  ldc "u_audio"
  astore 15
  aload 31
  astore_3
  aload 6
  aload 15
  aload_3
  invokeinterface java/util/Map/put(Ljava/lang/Object;Ljava/lang/Object;)Ljava/lang/Object; 3
  pop
  aload_2
  astore_3
  aload_3
  invokestatic com/google/ads/util/AdUtil/a(Landroid/app/Activity;)Landroid/util/DisplayMetrics;
  astore 35
  aload 35
  astore_3
  aload_3
  getfield android/util/DisplayMetrics/density F
  fstore_3
  fload_3
  fstore 36
  fload_3
  invokestatic java/lang/Float/valueOf(F)Ljava/lang/Float;
  astore 37
  ldc "u_sd"
  astore 15
  aload 37
  astore_3
  aload 6
  aload 15
  aload_3
  invokeinterface java/util/Map/put(Ljava/lang/Object;Ljava/lang/Object;)Ljava/lang/Object; 3
  pop
  aload 35
  astore_3
  aload 5
  aload_3
  invokestatic com/google/ads/util/AdUtil/a(Landroid/content/Context;Landroid/util/DisplayMetrics;)I
  istore 26
  iload 26
  istore_3
  iload_3
  invokestatic java/lang/Integer/valueOf(I)Ljava/lang/Integer;
  astore 31
  ldc "u_h"
  astore 15
  aload 31
  astore_3
  aload 6
  aload 15
  aload_3
  invokeinterface java/util/Map/put(Ljava/lang/Object;Ljava/lang/Object;)Ljava/lang/Object; 3
  pop
  aload 35
  astore_3
  aload 5
  aload_3
  invokestatic com/google/ads/util/AdUtil/b(Landroid/content/Context;Landroid/util/DisplayMetrics;)I
  istore 26
  iload 26
  istore_3
  iload_3
  invokestatic java/lang/Integer/valueOf(I)Ljava/lang/Integer;
  astore 31
  ldc "u_w"
  astore 15
  aload 31
  astore_3
  aload 6
  aload 15
  aload_3
  invokeinterface java/util/Map/put(Ljava/lang/Object;Ljava/lang/Object;)Ljava/lang/Object; 3
  pop
  invokestatic java/util/Locale/getDefault()Ljava/util/Locale;
  astore 38
  aload 38
  astore_3
  aload_3
  invokevirtual java/util/Locale/getLanguage()Ljava/lang/String;
  astore 22
  ldc "hl"
  astore 15
  aload 22
  astore_3
  aload 6
  aload 15
  aload_3
  invokeinterface java/util/Map/put(Ljava/lang/Object;Ljava/lang/Object;)Ljava/lang/Object; 3
  pop
  invokestatic com/google/ads/util/AdUtil/c()Z
  istore 19
  iload 19
  istore_3
  iload_3
  invokestatic app/DummyClass/invokeIfStmt(Z)V
  iload 19
  ifeq Label13
  iconst_1
  istore 25
  iload 25
  istore_3
  iload_3
  invokestatic java/lang/Integer/valueOf(I)Ljava/lang/Integer;
  astore 31
  ldc "simulator"
  astore 15
  aload 31
  astore_3
  aload 6
  aload 15
  aload_3
  invokeinterface java/util/Map/put(Ljava/lang/Object;Ljava/lang/Object;)Ljava/lang/Object; 3
  pop
Label13:
  aload 6
  invokestatic com/google/ads/util/AdUtil/a(Ljava/util/Map;)Ljava/lang/String;
  astore 16
  new java/lang/StringBuilder
  astore 27
  aload 27
  astore_3
  aload_3
  invokespecial java/lang/StringBuilder/<init>()V
  ldc "<html><head><script src=\"http://www.gstatic.com/afma/sdk-core-v40.js\"></script><script>AFMA_buildAdURL("
  astore 15
  aload 27
  astore_3
  aload_3
  aload 15
  invokevirtual java/lang/StringBuilder/append(Ljava/lang/String;)Ljava/lang/StringBuilder;
  astore 27
  aload 27
  astore_3
  aload_3
  aload 16
  invokevirtual java/lang/StringBuilder/append(Ljava/lang/String;)Ljava/lang/StringBuilder;
  astore 27
  ldc ");"
  astore 15
  aload 27
  astore_3
  aload_3
  aload 15
  invokevirtual java/lang/StringBuilder/append(Ljava/lang/String;)Ljava/lang/StringBuilder;
  astore 27
  ldc "</script></head><body></body></html>"
  astore 15
  aload 27
  astore_3
  aload_3
  aload 15
  invokevirtual java/lang/StringBuilder/append(Ljava/lang/String;)Ljava/lang/StringBuilder;
  astore 27
  aload 27
  astore_3
  aload_3
  invokevirtual java/lang/StringBuilder/toString()Ljava/lang/String;
  astore 16
  new java/lang/StringBuilder
  astore 27
  aload 27
  astore_3
  aload_3
  invokespecial java/lang/StringBuilder/<init>()V
  ldc "adRequestUrlHtml: "
  astore 15
  aload 27
  astore_3
  aload_3
  aload 15
  invokevirtual java/lang/StringBuilder/append(Ljava/lang/String;)Ljava/lang/StringBuilder;
  astore 27
  aload 27
  astore_3
  aload_3
  aload 16
  invokevirtual java/lang/StringBuilder/append(Ljava/lang/String;)Ljava/lang/StringBuilder;
  astore 27
  aload 27
  astore_3
  aload_3
  invokevirtual java/lang/StringBuilder/toString()Ljava/lang/String;
  astore 39
  aload 39
  astore_3
  aload_3
  invokestatic com/google/ads/util/a/c(Ljava/lang/String;)V
  aload 16
  areturn
  nop
.end <method>

.method final a()V
.limit locals 7
.limit stack 200
  nop
  ldc "AdLoader cancelled."
  astore_1
  aload_1
  invokestatic com/google/ads/util/a/a(Ljava/lang/String;)V
  aload_0
  getfield c/f Landroid/webkit/WebView;
  astore_2
  new java/lang/NoClassDefFoundError
  dup
  invokespecial java/lang/NoClassDefFoundError/<init>()V
  athrow
  aload_0
  getfield c/f Landroid/webkit/WebView;
  astore_2
  aload_2
  invokevirtual android/webkit/WebView/destroy()V
  aload_0
  getfield c/m Ljava/lang/Thread;
  astore_3
  aload_3
  invokestatic app/DummyClass/invokeIfStmt(Ljava/lang/Object;)V
  aload_3
  ifnull Label0
  aload_0
  getfield c/m Ljava/lang/Thread;
  astore_3
  aload_3
  invokevirtual java/lang/Thread/interrupt()V
  aconst_null
  astore 4
  aload_0
  aload 4
  putfield c/m Ljava/lang/Thread;
Label0:
  aload_0
  getfield c/c Lb;
  astore 5
  aload 5
  invokevirtual b/a()V
  iconst_1
  istore 6
  aload_0
  iload 6
  putfield c/i Z
  return
  nop
.end <method>

.method public final a(I)V
.limit locals 3
.limit stack 200
  .catch  java/lang/Throwable <from> Label1 <to> Label2 <using> Label0
  nop
  aload_0
  monitorenter
Label1:
  aload_0
  iload_1
  putfield c/l I
Label2:
  aload_0
  monitorexit
  return
Label0:
  astore_2
  aload_0
  monitorexit
  aload_2
  athrow
  nop
.end <method>

.method public final a(Lcom/google/ads/AdRequest$ErrorCode;)V
.limit locals 3
.limit stack 200
  .catch  java/lang/Throwable <from> Label1 <to> Label2 <using> Label0
  nop
  aload_0
  monitorenter
Label1:
  aload_0
  aload_1
  putfield c/j Lcom/google/ads/AdRequest$ErrorCode;
  aload_0
  invokevirtual java/lang/Object/notify()V
Label2:
  aload_0
  monitorexit
  return
Label0:
  astore_2
  aload_0
  monitorexit
  aload_2
  athrow
  nop
.end <method>

.method private a(Lcom/google/ads/AdRequest$ErrorCode;Z)V
.limit locals 15
.limit stack 200
  nop
  aload_0
  getfield c/c Lb;
  astore 10
  aload 10
  invokevirtual b/a()V
  aload_0
  getfield c/d Ld;
  astore 11
  new c$a
  astore 12
  aload_0
  getfield c/d Ld;
  astore 13
  aload_0
  getfield c/f Landroid/webkit/WebView;
  astore 14
  aload_0
  getfield c/c Lb;
  astore 10
  aload 12
  astore_3
  aload_0
  astore 4
  aload 13
  astore 5
  aload 14
  astore 6
  aload 10
  astore 7
  aload_1
  astore 8
  iload_2
  istore 9
  aload_3
  aload 4
  aload 5
  aload 6
  aload 7
  aload 8
  iload 9
  invokespecial c$a/<init>(Lc;Ld;Landroid/webkit/WebView;Lb;Lcom/google/ads/AdRequest$ErrorCode;Z)V
  aload 11
  aload 12
  invokevirtual d/a(Ljava/lang/Runnable;)V
  return
  nop
.end <method>

.method final a(Lcom/google/ads/AdRequest;)V
.limit locals 4
.limit stack 200
  nop
  aload_0
  aload_1
  putfield c/e Lcom/google/ads/AdRequest;
  iconst_0
  istore_2
  aload_0
  iload_2
  putfield c/i Z
  new java/lang/Thread
  astore_3
  aload_3
  aload_0
  invokespecial java/lang/Thread/<init>(Ljava/lang/Runnable;)V
  aload_0
  aload_3
  putfield c/m Ljava/lang/Thread;
  aload_0
  getfield c/m Ljava/lang/Thread;
  astore_3
  aload_3
  invokevirtual java/lang/Thread/start()V
  return
  nop
.end <method>

.method final a(Ljava/lang/String;)V
.limit locals 4
.limit stack 200
  .catch  java/lang/Throwable <from> Label1 <to> Label2 <using> Label0
  nop
  aload_0
  monitorenter
Label1:
  aload_0
  getfield c/h Ljava/util/LinkedList;
  astore_2
  aload_2
  aload_1
  invokevirtual java/util/LinkedList/add(Ljava/lang/Object;)Z
  pop
Label2:
  aload_0
  monitorexit
  return
Label0:
  astore_3
  aload_0
  monitorexit
  aload_3
  athrow
  nop
.end <method>

.method final a(Ljava/lang/String;Ljava/lang/String;)V
.limit locals 4
.limit stack 200
  .catch  java/lang/Throwable <from> Label1 <to> Label2 <using> Label0
  nop
  aload_0
  monitorenter
Label1:
  aload_0
  aload_2
  putfield c/a Ljava/lang/String;
  aload_0
  aload_1
  putfield c/b Ljava/lang/String;
  aload_0
  invokevirtual java/lang/Object/notify()V
Label2:
  aload_0
  monitorexit
  return
Label0:
  astore_3
  aload_0
  monitorexit
  aload_3
  athrow
  nop
.end <method>

.method final b()V
.limit locals 3
.limit stack 200
  .catch  java/lang/Throwable <from> Label1 <to> Label2 <using> Label0
  nop
  aload_0
  monitorenter
Label1:
  iconst_1
  istore_1
  aload_0
  iload_1
  putfield c/k Z
  aload_0
  invokevirtual java/lang/Object/notify()V
Label2:
  aload_0
  monitorexit
  return
Label0:
  astore_2
  aload_0
  monitorexit
  aload_2
  athrow
  nop
.end <method>

.method public final b(Ljava/lang/String;)V
.limit locals 3
.limit stack 200
  .catch  java/lang/Throwable <from> Label1 <to> Label2 <using> Label0
  nop
  aload_0
  monitorenter
Label1:
  aload_0
  aload_1
  putfield c/g Ljava/lang/String;
  aload_0
  invokevirtual java/lang/Object/notify()V
Label2:
  aload_0
  monitorexit
  return
Label0:
  astore_2
  aload_0
  monitorexit
  aload_2
  athrow
  nop
.end <method>

.method public final run()V
.limit locals 42
.limit stack 200
  .catch  java/lang/Throwable <from> Label17 <to> Label18 <using> Label15
  .catch  java/lang/Exception <from> Label17 <to> Label18 <using> Label16
  .catch  java/lang/Throwable <from> Label18 <to> Label3 <using> Label15
  .catch  java/lang/Throwable <from> Label1 <to> Label19 <using> Label15
  .catch  java/lang/Exception <from> Label1 <to> Label19 <using> Label16
  .catch  java/lang/Throwable <from> Label19 <to> Label20 <using> Label15
  .catch  java/lang/Throwable <from> Label23 <to> Label24 <using> Label15
  .catch  java/lang/Exception <from> Label23 <to> Label24 <using> Label16
  .catch  java/lang/Throwable <from> Label24 <to> Label25 <using> Label15
  .catch  java/lang/Exception <from> Label24 <to> Label25 <using> Label16
  .catch  java/lang/Throwable <from> Label27 <to> Label4 <using> Label15
  .catch  java/lang/Exception <from> Label27 <to> Label4 <using> Label16
  .catch  java/lang/Throwable <from> Label4 <to> Label28 <using> Label15
  .catch  java/lang/Exception <from> Label4 <to> Label28 <using> Label16
  .catch  java/lang/Throwable <from> Label29 <to> Label30 <using> Label15
  .catch  java/lang/Throwable <from> Label31 <to> Label32 <using> Label15
  .catch  java/lang/Exception <from> Label31 <to> Label32 <using> Label16
  .catch  java/lang/Throwable <from> Label32 <to> Label33 <using> Label15
  .catch  java/lang/Throwable <from> Label34 <to> Label35 <using> Label15
  .catch  java/lang/Exception <from> Label34 <to> Label35 <using> Label16
  .catch  java/lang/Throwable <from> Label35 <to> Label36 <using> Label15
  .catch  java/lang/Throwable <from> Label37 <to> Label38 <using> Label15
  .catch  java/lang/Exception <from> Label37 <to> Label38 <using> Label16
  .catch  java/lang/Throwable <from> Label38 <to> Label39 <using> Label15
  .catch  java/lang/Throwable <from> Label5 <to> Label40 <using> Label15
  .catch  java/lang/Exception <from> Label5 <to> Label40 <using> Label16
  .catch  java/lang/Throwable <from> Label40 <to> Label41 <using> Label15
  .catch  java/lang/Throwable <from> Label6 <to> Label42 <using> Label15
  .catch  java/lang/Exception <from> Label6 <to> Label42 <using> Label16
  .catch  java/lang/Throwable <from> Label42 <to> Label43 <using> Label15
  .catch  java/lang/Throwable <from> Label7 <to> Label44 <using> Label15
  .catch  java/lang/Exception <from> Label7 <to> Label44 <using> Label16
  .catch  java/lang/Throwable <from> Label46 <to> Label8 <using> Label15
  .catch  java/lang/Exception <from> Label46 <to> Label8 <using> Label16
  .catch  java/lang/Throwable <from> Label8 <to> Label47 <using> Label15
  .catch  java/lang/Exception <from> Label8 <to> Label47 <using> Label16
  .catch  java/lang/Throwable <from> Label48 <to> Label49 <using> Label15
  .catch  java/lang/Throwable <from> Label50 <to> Label51 <using> Label15
  .catch  java/lang/Exception <from> Label50 <to> Label51 <using> Label16
  .catch  java/lang/Throwable <from> Label51 <to> Label52 <using> Label15
  .catch  java/lang/Throwable <from> Label9 <to> Label53 <using> Label15
  .catch  java/lang/Exception <from> Label9 <to> Label53 <using> Label16
  .catch  java/lang/Throwable <from> Label53 <to> Label54 <using> Label15
  .catch  java/lang/Throwable <from> Label10 <to> Label55 <using> Label15
  .catch  java/lang/Exception <from> Label10 <to> Label55 <using> Label16
  .catch  java/lang/Throwable <from> Label55 <to> Label56 <using> Label15
  .catch  java/lang/Throwable <from> Label11 <to> Label57 <using> Label15
  .catch  java/lang/Exception <from> Label11 <to> Label57 <using> Label16
  .catch  java/lang/Throwable <from> Label59 <to> Label12 <using> Label15
  .catch  java/lang/Exception <from> Label59 <to> Label12 <using> Label16
  .catch  java/lang/Throwable <from> Label12 <to> Label14 <using> Label15
  .catch  java/lang/Exception <from> Label12 <to> Label14 <using> Label16
  .catch  java/lang/Throwable <from> Label14 <to> Label60 <using> Label15
  .catch  java/lang/Throwable <from> Label61 <to> Label62 <using> Label15
  .catch  java/lang/Exception <from> Label61 <to> Label62 <using> Label16
  .catch  java/lang/Throwable <from> Label62 <to> Label63 <using> Label15
  .catch  java/lang/Throwable <from> Label64 <to> Label65 <using> Label15
  .catch  java/lang/Exception <from> Label64 <to> Label65 <using> Label16
  .catch  java/lang/Throwable <from> Label66 <to> Label67 <using> Label15
  nop
  aload_0
  monitorenter
Label17:
  aload_0
  astore_1
  aload_1
  getfield c/f Landroid/webkit/WebView;
  astore 6
  new java/lang/NoClassDefFoundError
  dup
  invokespecial java/lang/NoClassDefFoundError/<init>()V
  athrow
  iload 6
  ifeq Label0
  aload_0
  astore_1
  aload_1
  getfield c/c Lb;
  astore 7
  aload 7
  invokestatic app/DummyClass/invokeIfStmt(Ljava/lang/Object;)V
  aload 7
  ifnonnull Label1
Label0:
  ldc "adRequestWebView was null while trying to load an ad."
  astore 8
  aload 8
  invokestatic com/google/ads/util/a/e(Ljava/lang/String;)V
  getstatic com/google/ads/AdRequest$ErrorCode/INTERNAL_ERROR Lcom/google/ads/AdRequest$ErrorCode;
  astore 9
  iconst_0
  istore 10
  aload_0
  astore_1
  aload_1
  aload 9
  iload 10
  invokespecial c/a(Lcom/google/ads/AdRequest$ErrorCode;Z)V
Label18:
  aload_0
  monitorexit
Label3:
  return
Label1:
  aload_0
  astore_1
  aload_1
  getfield c/d Ld;
  astore 11
  aload 11
  invokevirtual d/e()Landroid/app/Activity;
  astore 12
  aload 12
  invokestatic app/DummyClass/invokeIfStmt(Ljava/lang/Object;)V
  aload 12
  ifnonnull Label2
  ldc "activity was null while forming an ad request."
  astore 8
  aload 8
  invokestatic com/google/ads/util/a/e(Ljava/lang/String;)V
  getstatic com/google/ads/AdRequest$ErrorCode/INTERNAL_ERROR Lcom/google/ads/AdRequest$ErrorCode;
  astore 9
  iconst_0
  istore 10
  aload_0
  astore_1
  aload_1
  aload 9
  iload 10
  invokespecial c/a(Lcom/google/ads/AdRequest$ErrorCode;Z)V
Label19:
  aload_0
  monitorexit
Label20:
  goto Label3
Label15:
  astore 13
  aload_0
  monitorexit
  aload 13
  athrow
Label2:
  aload_0
  astore_1
  aload_1
  getfield c/e Lcom/google/ads/AdRequest;
  astore 14
Label23:
  aload_0
  astore_1
  aload_1
  aload 14
  aload 12
  invokespecial c/a(Lcom/google/ads/AdRequest;Landroid/app/Activity;)Ljava/lang/String;
  astore 15
Label24:
  aload_0
  astore_1
  aload_1
  getfield c/d Ld;
  astore 11
  new c$c
  astore 16
  aload_0
  astore_1
  aload_1
  getfield c/f Landroid/webkit/WebView;
  astore 6
  aconst_null
  astore 17
  aload_0
  astore_1
  aload 17
  astore_2
  aload 16
  aload_1
  aload 6
  aload_2
  aload 15
  invokespecial c$c/<init>(Lc;Landroid/webkit/WebView;Ljava/lang/String;Ljava/lang/String;)V
  aload 11
  aload 16
  invokevirtual d/a(Ljava/lang/Runnable;)V
  aload_0
  astore_1
  aload_1
  getfield c/d Ld;
  astore 11
  aload 11
  invokevirtual d/n()J
  lstore 18
  invokestatic android/os/SystemClock/elapsedRealtime()J
  lstore 20
Label25:
  ldc2_w 0
  lstore 23
  lload 18
  lload 23
  lcmp
  istore 22
  iload 22
  istore_1
  dload_1
  invokestatic app/DummyClass/invokeIfStmt(D)V
  iload 22
  ifle Label4
Label27:
  aload_0
  astore_1
  lload 18
  lstore_2
  aload_1
  lload_2
  invokevirtual java/lang/Object/wait(J)V
Label4:
  aload_0
  astore_1
  aload_1
  getfield c/i Z
  istore_1
  iload_1
  istore 25
Label28:
  iload_1
  invokestatic app/DummyClass/invokeIfStmt(Z)V
  iload 25
  ifeq Label5
Label29:
  aload_0
  monitorexit
Label30:
  goto Label3
Label22:
  astore 26
  new java/lang/StringBuilder
  astore 27
Label31:
  aload 27
  astore_1
  aload_1
  invokespecial java/lang/StringBuilder/<init>()V
  ldc "Unable to connect to network: "
  astore 8
  aload 27
  astore_1
  aload_1
  aload 8
  invokevirtual java/lang/StringBuilder/append(Ljava/lang/String;)Ljava/lang/StringBuilder;
  astore 27
  aload 27
  astore_1
  aload 26
  astore_2
  aload_1
  aload_2
  invokevirtual java/lang/StringBuilder/append(Ljava/lang/Object;)Ljava/lang/StringBuilder;
  astore 27
  aload 27
  astore_1
  aload_1
  invokevirtual java/lang/StringBuilder/toString()Ljava/lang/String;
  astore 15
  aload 15
  invokestatic com/google/ads/util/a/c(Ljava/lang/String;)V
  getstatic com/google/ads/AdRequest$ErrorCode/NETWORK_ERROR Lcom/google/ads/AdRequest$ErrorCode;
  astore 9
  iconst_0
  istore 10
  aload_0
  astore_1
  aload_1
  aload 9
  iload 10
  invokespecial c/a(Lcom/google/ads/AdRequest$ErrorCode;Z)V
Label32:
  aload_0
  monitorexit
Label33:
  goto Label3
Label21:
  astore 28
  new java/lang/StringBuilder
  astore 27
Label34:
  aload 27
  astore_1
  aload_1
  invokespecial java/lang/StringBuilder/<init>()V
  ldc "Caught internal exception: "
  astore 8
  aload 27
  astore_1
  aload_1
  aload 8
  invokevirtual java/lang/StringBuilder/append(Ljava/lang/String;)Ljava/lang/StringBuilder;
  astore 27
  aload 27
  astore_1
  aload 28
  astore_2
  aload_1
  aload_2
  invokevirtual java/lang/StringBuilder/append(Ljava/lang/Object;)Ljava/lang/StringBuilder;
  astore 27
  aload 27
  astore_1
  aload_1
  invokevirtual java/lang/StringBuilder/toString()Ljava/lang/String;
  astore 15
  aload 15
  invokestatic com/google/ads/util/a/c(Ljava/lang/String;)V
  getstatic com/google/ads/AdRequest$ErrorCode/INTERNAL_ERROR Lcom/google/ads/AdRequest$ErrorCode;
  astore 9
  iconst_0
  istore 10
  aload_0
  astore_1
  aload_1
  aload 9
  iload 10
  invokespecial c/a(Lcom/google/ads/AdRequest$ErrorCode;Z)V
Label35:
  aload_0
  monitorexit
Label36:
  goto Label3
Label26:
  astore 29
  new java/lang/StringBuilder
  astore 27
Label37:
  aload 27
  astore_1
  aload_1
  invokespecial java/lang/StringBuilder/<init>()V
  ldc "AdLoader InterruptedException while getting the URL: "
  astore 8
  aload 27
  astore_1
  aload_1
  aload 8
  invokevirtual java/lang/StringBuilder/append(Ljava/lang/String;)Ljava/lang/StringBuilder;
  astore 27
  aload 27
  astore_1
  aload 29
  astore_2
  aload_1
  aload_2
  invokevirtual java/lang/StringBuilder/append(Ljava/lang/Object;)Ljava/lang/StringBuilder;
  astore 27
  aload 27
  astore_1
  aload_1
  invokevirtual java/lang/StringBuilder/toString()Ljava/lang/String;
  astore 15
  aload 15
  invokestatic com/google/ads/util/a/a(Ljava/lang/String;)V
Label38:
  aload_0
  monitorexit
Label39:
  goto Label3
Label5:
  aload_0
  astore_1
  aload_1
  getfield c/j Lcom/google/ads/AdRequest$ErrorCode;
  astore 9
  aload 9
  invokestatic app/DummyClass/invokeIfStmt(Ljava/lang/Object;)V
  aload 9
  ifnull Label6
  aload_0
  astore_1
  aload_1
  getfield c/j Lcom/google/ads/AdRequest$ErrorCode;
  astore 9
  iconst_0
  istore 10
  aload_0
  astore_1
  aload_1
  aload 9
  iload 10
  invokespecial c/a(Lcom/google/ads/AdRequest$ErrorCode;Z)V
Label40:
  aload_0
  monitorexit
Label41:
  goto Label3
Label6:
  aload_0
  astore_1
  aload_1
  getfield c/g Ljava/lang/String;
  astore 15
  aload 15
  invokestatic app/DummyClass/invokeIfStmt(Ljava/lang/Object;)V
  aload 15
  ifnonnull Label7
  new java/lang/StringBuilder
  astore 27
  aload 27
  astore_1
  aload_1
  invokespecial java/lang/StringBuilder/<init>()V
  ldc "AdLoader timed out after "
  astore 8
  aload 27
  astore_1
  aload_1
  aload 8
  invokevirtual java/lang/StringBuilder/append(Ljava/lang/String;)Ljava/lang/StringBuilder;
  astore 27
  aload 27
  astore_1
  lload 18
  lstore_2
  aload_1
  lload_2
  invokevirtual java/lang/StringBuilder/append(J)Ljava/lang/StringBuilder;
  astore 27
  ldc "ms while getting the URL."
  astore 8
  aload 27
  astore_1
  aload_1
  aload 8
  invokevirtual java/lang/StringBuilder/append(Ljava/lang/String;)Ljava/lang/StringBuilder;
  astore 27
  aload 27
  astore_1
  aload_1
  invokevirtual java/lang/StringBuilder/toString()Ljava/lang/String;
  astore 15
  aload 15
  invokestatic com/google/ads/util/a/c(Ljava/lang/String;)V
  getstatic com/google/ads/AdRequest$ErrorCode/NETWORK_ERROR Lcom/google/ads/AdRequest$ErrorCode;
  astore 9
  iconst_0
  istore 10
  aload_0
  astore_1
  aload_1
  aload 9
  iload 10
  invokespecial c/a(Lcom/google/ads/AdRequest$ErrorCode;Z)V
Label42:
  aload_0
  monitorexit
Label43:
  goto Label3
Label7:
  aload_0
  astore_1
  aload_1
  getfield c/c Lb;
  astore 7
  aload_0
  astore_1
  aload_1
  getfield c/g Ljava/lang/String;
  astore_1
  aload_1
  astore 30
  aload 30
  astore_1
  aload 7
  aload_1
  invokevirtual b/a(Ljava/lang/String;)V
  invokestatic android/os/SystemClock/elapsedRealtime()J
  lstore 31
Label44:
  lload 31
  lstore_1
  lload 20
  lstore_3
  lload_1
  lload_3
  lsub
  lstore_1
  lload_1
  lstore 31
  lload 18
  lload 31
  lsub
  lstore 31
  ldc2_w 0
  lstore 23
  lload 31
  lload 23
  lcmp
  istore 22
  iload 22
  istore_1
  dload_1
  invokestatic app/DummyClass/invokeIfStmt(D)V
  iload 22
  ifle Label8
Label46:
  aload_0
  astore_1
  lload 31
  lstore_2
  aload_1
  lload_2
  invokevirtual java/lang/Object/wait(J)V
Label8:
  aload_0
  astore_1
  aload_1
  getfield c/i Z
  istore_1
  iload_1
  istore 25
Label47:
  iload_1
  invokestatic app/DummyClass/invokeIfStmt(Z)V
  iload 25
  ifeq Label9
Label48:
  aload_0
  monitorexit
Label49:
  goto Label3
Label45:
  astore 33
  new java/lang/StringBuilder
  astore 27
Label50:
  aload 27
  astore_1
  aload_1
  invokespecial java/lang/StringBuilder/<init>()V
  ldc "AdLoader InterruptedException while getting the HTML: "
  astore 8
  aload 27
  astore_1
  aload_1
  aload 8
  invokevirtual java/lang/StringBuilder/append(Ljava/lang/String;)Ljava/lang/StringBuilder;
  astore 27
  aload 27
  astore_1
  aload 33
  astore_2
  aload_1
  aload_2
  invokevirtual java/lang/StringBuilder/append(Ljava/lang/Object;)Ljava/lang/StringBuilder;
  astore 27
  aload 27
  astore_1
  aload_1
  invokevirtual java/lang/StringBuilder/toString()Ljava/lang/String;
  astore 15
  aload 15
  invokestatic com/google/ads/util/a/a(Ljava/lang/String;)V
Label51:
  aload_0
  monitorexit
Label52:
  goto Label3
Label9:
  aload_0
  astore_1
  aload_1
  getfield c/j Lcom/google/ads/AdRequest$ErrorCode;
  astore 9
  aload 9
  invokestatic app/DummyClass/invokeIfStmt(Ljava/lang/Object;)V
  aload 9
  ifnull Label10
  aload_0
  astore_1
  aload_1
  getfield c/j Lcom/google/ads/AdRequest$ErrorCode;
  astore 9
  iconst_0
  istore 10
  aload_0
  astore_1
  aload_1
  aload 9
  iload 10
  invokespecial c/a(Lcom/google/ads/AdRequest$ErrorCode;Z)V
Label53:
  aload_0
  monitorexit
Label54:
  goto Label3
Label10:
  aload_0
  astore_1
  aload_1
  getfield c/b Ljava/lang/String;
  astore 15
  aload 15
  invokestatic app/DummyClass/invokeIfStmt(Ljava/lang/Object;)V
  aload 15
  ifnonnull Label11
  new java/lang/StringBuilder
  astore 27
  aload 27
  astore_1
  aload_1
  invokespecial java/lang/StringBuilder/<init>()V
  ldc "AdLoader timed out after "
  astore 8
  aload 27
  astore_1
  aload_1
  aload 8
  invokevirtual java/lang/StringBuilder/append(Ljava/lang/String;)Ljava/lang/StringBuilder;
  astore 27
  aload 27
  astore_1
  lload 18
  lstore_2
  aload_1
  lload_2
  invokevirtual java/lang/StringBuilder/append(J)Ljava/lang/StringBuilder;
  astore 27
  ldc "ms while getting the HTML."
  astore 8
  aload 27
  astore_1
  aload_1
  aload 8
  invokevirtual java/lang/StringBuilder/append(Ljava/lang/String;)Ljava/lang/StringBuilder;
  astore 27
  aload 27
  astore_1
  aload_1
  invokevirtual java/lang/StringBuilder/toString()Ljava/lang/String;
  astore 15
  aload 15
  invokestatic com/google/ads/util/a/c(Ljava/lang/String;)V
  getstatic com/google/ads/AdRequest$ErrorCode/NETWORK_ERROR Lcom/google/ads/AdRequest$ErrorCode;
  astore 9
  iconst_0
  istore 10
  aload_0
  astore_1
  aload_1
  aload 9
  iload 10
  invokespecial c/a(Lcom/google/ads/AdRequest$ErrorCode;Z)V
Label55:
  aload_0
  monitorexit
Label56:
  goto Label3
Label11:
  aload_0
  astore_1
  aload_1
  getfield c/d Ld;
  astore 11
  aload 11
  invokevirtual d/i()Lg;
  astore 34
  aload_0
  astore_1
  aload_1
  getfield c/d Ld;
  astore 11
  aload 11
  invokevirtual d/j()Lh;
  astore 35
  aload 35
  astore_1
  aload_1
  invokevirtual h/a()V
  aload_0
  astore_1
  aload_1
  getfield c/d Ld;
  astore 11
  new c$c
  astore 16
  aload_0
  astore_1
  aload_1
  getfield c/a Ljava/lang/String;
  astore_1
  aload_1
  astore 30
  aload_0
  astore_1
  aload_1
  getfield c/b Ljava/lang/String;
  astore 15
  aload_0
  astore_1
  aload 34
  astore_2
  aload 30
  astore_3
  aload 16
  aload_1
  aload_2
  aload_3
  aload 15
  invokespecial c$c/<init>(Lc;Landroid/webkit/WebView;Ljava/lang/String;Ljava/lang/String;)V
  aload 11
  aload 16
  invokevirtual d/a(Ljava/lang/Runnable;)V
  invokestatic android/os/SystemClock/elapsedRealtime()J
  lstore 31
Label57:
  lload 31
  lstore_1
  lload 20
  lstore_3
  lload_1
  lload_3
  lsub
  lstore_1
  lload_1
  lstore 31
  lload 18
  lload 31
  lsub
  lstore 31
  ldc2_w 0
  lstore 23
  lload 31
  lload 23
  lcmp
  istore 22
  iload 22
  istore_1
  dload_1
  invokestatic app/DummyClass/invokeIfStmt(D)V
  iload 22
  ifle Label12
Label59:
  aload_0
  astore_1
  lload 31
  lstore_2
  aload_1
  lload_2
  invokevirtual java/lang/Object/wait(J)V
Label12:
  aload_0
  astore_1
  aload_1
  getfield c/k Z
  istore_1
  iload_1
  istore 25
  iload_1
  invokestatic app/DummyClass/invokeIfStmt(Z)V
  iload 25
  ifeq Label13
  aload_0
  astore_1
  aload_1
  getfield c/d Ld;
  astore 11
  new c$e
  astore 36
  aload_0
  astore_1
  aload_1
  getfield c/d Ld;
  astore_1
  aload_1
  astore 37
  aload_0
  astore_1
  aload_1
  getfield c/h Ljava/util/LinkedList;
  astore_1
  aload_1
  astore 38
  aload_0
  astore_1
  aload_1
  getfield c/l I
  istore_1
  iload_1
  istore 39
  aload 36
  astore_1
  aload_0
  astore_2
  aload 37
  astore_3
  aload 38
  astore 4
  iload 39
  istore 5
  aload_1
  aload_2
  aload_3
  aload 4
  iload 5
  invokespecial c$e/<init>(Lc;Ld;Ljava/util/LinkedList;I)V
  aload 36
  astore_1
  aload 11
  aload_1
  invokevirtual d/a(Ljava/lang/Runnable;)V
Label14:
  aload_0
  monitorexit
Label60:
  goto Label3
Label58:
  astore 40
  new java/lang/StringBuilder
  astore 27
Label61:
  aload 27
  astore_1
  aload_1
  invokespecial java/lang/StringBuilder/<init>()V
  ldc "AdLoader InterruptedException while loading the HTML: "
  astore 8
  aload 27
  astore_1
  aload_1
  aload 8
  invokevirtual java/lang/StringBuilder/append(Ljava/lang/String;)Ljava/lang/StringBuilder;
  astore 27
  aload 27
  astore_1
  aload 40
  astore_2
  aload_1
  aload_2
  invokevirtual java/lang/StringBuilder/append(Ljava/lang/Object;)Ljava/lang/StringBuilder;
  astore 27
  aload 27
  astore_1
  aload_1
  invokevirtual java/lang/StringBuilder/toString()Ljava/lang/String;
  astore 15
  aload 15
  invokestatic com/google/ads/util/a/a(Ljava/lang/String;)V
Label62:
  aload_0
  monitorexit
Label63:
  goto Label3
Label13:
  new java/lang/StringBuilder
  astore 27
Label64:
  aload 27
  astore_1
  aload_1
  invokespecial java/lang/StringBuilder/<init>()V
  ldc "AdLoader timed out after "
  astore 8
  aload 27
  astore_1
  aload_1
  aload 8
  invokevirtual java/lang/StringBuilder/append(Ljava/lang/String;)Ljava/lang/StringBuilder;
  astore 27
  aload 27
  astore_1
  lload 18
  lstore_2
  aload_1
  lload_2
  invokevirtual java/lang/StringBuilder/append(J)Ljava/lang/StringBuilder;
  astore 27
  ldc "ms while loading the HTML."
  astore 8
  aload 27
  astore_1
  aload_1
  aload 8
  invokevirtual java/lang/StringBuilder/append(Ljava/lang/String;)Ljava/lang/StringBuilder;
  astore 27
  aload 27
  astore_1
  aload_1
  invokevirtual java/lang/StringBuilder/toString()Ljava/lang/String;
  astore 15
  aload 15
  invokestatic com/google/ads/util/a/c(Ljava/lang/String;)V
  getstatic com/google/ads/AdRequest$ErrorCode/NETWORK_ERROR Lcom/google/ads/AdRequest$ErrorCode;
  astore 9
  iconst_1
  istore 10
  aload_0
  astore_1
  aload_1
  aload 9
  iload 10
  invokespecial c/a(Lcom/google/ads/AdRequest$ErrorCode;Z)V
Label65:
  goto Label14
Label16:
  astore 41
Label66:
  ldc "An unknown error occurred in AdLoader."
  astore 8
  aload 41
  astore_1
  aload 8
  aload_1
  invokestatic com/google/ads/util/a/a(Ljava/lang/String;Ljava/lang/Throwable;)V
  getstatic com/google/ads/AdRequest$ErrorCode/INTERNAL_ERROR Lcom/google/ads/AdRequest$ErrorCode;
  astore 9
  iconst_1
  istore 10
  aload_0
  astore_1
  aload_1
  aload 9
  iload 10
  invokespecial c/a(Lcom/google/ads/AdRequest$ErrorCode;Z)V
Label67:
  goto Label14
  nop
.end <method>

