.source SourceFile
.class public  cn/domob/android/ads/I
.super java/lang/Object
.field static final "a" I =  0
.field static final "b" I =  1
.field static final "c" I =  2
.field static final "d" I =  0
.field static final "e" I =  1
.field static final "f" I =  3
.field private "g" Landroid/content/Context;

.method protected <init>(Landroid/content/Context;)V
.limit locals 2
.limit stack 200
  nop
  aload_0
  invokespecial java/lang/Object/<init>()V
  aload_0
  aload_1
  putfield cn/domob/android/ads/I/g Landroid/content/Context;
  return
  nop
.end <method>

.method private static a(Landroid/content/Context;Landroid/content/SharedPreferences;)Landroid/app/Dialog;
.limit locals 57
.limit stack 200
  nop
  aload_1
  astore_2
  new java/lang/NoSuchMethodError
  dup
  invokespecial java/lang/NoSuchMethodError/<init>()V
  athrow
  nop
  ldc "n"
  astore 12
  aconst_null
  astore 13
  aload_1
  astore_2
  aload_2
  aload 12
  aload 13
  invokeinterface android/content/SharedPreferences/getString(Ljava/lang/String;Ljava/lang/String;)Ljava/lang/String; 3
  astore 11
  ldc "vc"
  astore 12
  aconst_null
  astore 13
  aload_1
  astore_2
  aload_2
  aload 12
  aload 13
  invokeinterface android/content/SharedPreferences/getString(Ljava/lang/String;Ljava/lang/String;)Ljava/lang/String; 3
  astore 14
  ldc "vn"
  astore 12
  aconst_null
  astore 13
  aload_1
  astore_2
  aload_2
  aload 12
  aload 13
  invokeinterface android/content/SharedPreferences/getString(Ljava/lang/String;Ljava/lang/String;)Ljava/lang/String; 3
  astore 15
  ldc "u"
  astore 12
  aconst_null
  astore 13
  aload_1
  astore_2
  aload_2
  aload 12
  aload 13
  invokeinterface android/content/SharedPreferences/getString(Ljava/lang/String;Ljava/lang/String;)Ljava/lang/String; 3
  astore 16
  ldc "s"
  astore 12
  aconst_null
  astore 13
  aload_1
  astore_2
  aload_2
  aload 12
  aload 13
  invokeinterface android/content/SharedPreferences/getString(Ljava/lang/String;Ljava/lang/String;)Ljava/lang/String; 3
  astore 17
  ldc "md5"
  astore 12
  ldc ""
  astore 19
  aload_1
  astore_2
  aload 19
  astore_3
  aload_2
  aload 12
  aload_3
  invokeinterface android/content/SharedPreferences/getString(Ljava/lang/String;Ljava/lang/String;)Ljava/lang/String; 3
  astore 18
  ldc "ul"
  astore 12
  aconst_null
  astore 13
  aload_1
  astore_2
  aload_2
  aload 12
  aload 13
  invokeinterface android/content/SharedPreferences/getString(Ljava/lang/String;Ljava/lang/String;)Ljava/lang/String; 3
  astore 20
  ldc "f"
  astore 12
  iconst_0
  istore 22
  aload_1
  astore_2
  iload 22
  istore_3
  aload_2
  aload 12
  iload_3
  invokeinterface android/content/SharedPreferences/getBoolean(Ljava/lang/String;Z)Z 3
  istore 21
  ldc "sk"
  astore 12
  iconst_0
  istore 22
  aload_1
  astore_2
  iload 22
  istore_3
  aload_2
  aload 12
  iload_3
  invokeinterface android/content/SharedPreferences/getBoolean(Ljava/lang/String;Z)Z 3
  istore 23
  new android/app/Dialog
  astore 24
  aload 24
  astore_2
  aload_0
  astore_3
  aload_2
  aload_3
  invokespecial android/app/Dialog/<init>(Landroid/content/Context;)V
  iconst_0
  istore 22
  aload 24
  astore_2
  iload 22
  istore_3
  aload_2
  iload_3
  invokevirtual android/app/Dialog/setCancelable(Z)V
  aload 24
  astore_2
  aload_2
  invokevirtual android/app/Dialog/getWindow()Landroid/view/Window;
  astore 25
  iconst_1
  istore 22
  aload 25
  astore_2
  iload 22
  istore_3
  aload_2
  iload_3
  invokevirtual android/view/Window/requestFeature(I)Z
  pop
  new android/widget/LinearLayout
  astore 26
  aload 26
  astore_2
  aload_0
  astore_3
  aload_2
  aload_3
  invokespecial android/widget/LinearLayout/<init>(Landroid/content/Context;)V
  iconst_1
  istore 22
  aload 26
  astore_2
  iload 22
  istore_3
  aload_2
  iload_3
  invokevirtual android/widget/LinearLayout/setOrientation(I)V
  bipush 90
  istore 22
  bipush 90
  istore 28
  bipush 90
  istore 29
  iload 22
  istore_2
  iload 28
  istore_3
  iload 29
  istore 4
  iload_2
  iload_3
  iload 4
  invokestatic android/graphics/Color/rgb(III)I
  istore 27
  aload 26
  astore_2
  iload 27
  istore_3
  aload_2
  iload_3
  invokevirtual android/widget/LinearLayout/setBackgroundColor(I)V
  new android/widget/LinearLayout
  astore 30
  aload 30
  astore_2
  aload_0
  astore_3
  aload_2
  aload_3
  invokespecial android/widget/LinearLayout/<init>(Landroid/content/Context;)V
  iconst_0
  istore 22
  aload 30
  astore_2
  iload 22
  istore_3
  aload_2
  iload_3
  invokevirtual android/widget/LinearLayout/setOrientation(I)V
  sipush 230
  istore 22
  sipush 230
  istore 28
  sipush 230
  istore 29
  iload 22
  istore_2
  iload 28
  istore_3
  iload 29
  istore 4
  iload_2
  iload_3
  iload 4
  invokestatic android/graphics/Color/rgb(III)I
  istore 27
  aload 30
  astore_2
  iload 27
  istore_3
  aload_2
  iload_3
  invokevirtual android/widget/LinearLayout/setBackgroundColor(I)V
  new android/widget/LinearLayout$LayoutParams
  astore 31
  iconst_m1
  istore 22
  bipush -2
  istore 28
  aload 31
  astore_2
  iload 22
  istore_3
  iload 28
  istore 4
  aload_2
  iload_3
  iload 4
  invokespecial android/widget/LinearLayout$LayoutParams/<init>(II)V
  aload 30
  astore_2
  aload 31
  astore_3
  aload_2
  aload_3
  invokevirtual android/widget/LinearLayout/setLayoutParams(Landroid/view/ViewGroup$LayoutParams;)V
  bipush 16
  istore 22
  aload 30
  astore_2
  iload 22
  istore_3
  aload_2
  iload_3
  invokevirtual android/widget/LinearLayout/setGravity(I)V
  new android/widget/LinearLayout$LayoutParams
  astore 31
  iconst_m1
  istore 22
  bipush -2
  istore 28
  aload 31
  astore_2
  iload 22
  istore_3
  iload 28
  istore 4
  aload_2
  iload_3
  iload 4
  invokespecial android/widget/LinearLayout$LayoutParams/<init>(II)V
  new android/widget/TextView
  astore 32
  aload 32
  astore_2
  aload_0
  astore_3
  aload_2
  aload_3
  invokespecial android/widget/TextView/<init>(Landroid/content/Context;)V
  ldc "\u66f4\u65b0\u63d0\u9192"
  astore 12
  aload 32
  astore_2
  aload_2
  aload 12
  invokevirtual android/widget/TextView/setText(Ljava/lang/CharSequence;)V
  ldc 20.000000
  fstore 33
  aload 32
  astore_2
  fload 33
  fstore_3
  aload_2
  fload_3
  invokevirtual android/widget/TextView/setTextSize(F)V
  ldc -16777216
  istore 22
  aload 32
  astore_2
  iload 22
  istore_3
  aload_2
  iload_3
  invokevirtual android/widget/TextView/setTextColor(I)V
  new android/widget/LinearLayout$LayoutParams
  astore 34
  bipush -2
  istore 22
  bipush -2
  istore 28
  aload 34
  astore_2
  iload 22
  istore_3
  iload 28
  istore 4
  aload_2
  iload_3
  iload 4
  invokespecial android/widget/LinearLayout$LayoutParams/<init>(II)V
  new android/widget/ImageView
  astore 35
  aload 35
  astore_2
  aload_0
  astore_3
  aload_2
  aload_3
  invokespecial android/widget/ImageView/<init>(Landroid/content/Context;)V
  ldc 17301569
  istore 22
  aload 35
  astore_2
  iload 22
  istore_3
  aload_2
  iload_3
  invokevirtual android/widget/ImageView/setImageResource(I)V
  new android/widget/LinearLayout$LayoutParams
  astore 36
  bipush -2
  istore 22
  bipush -2
  istore 28
  aload 36
  astore_2
  iload 22
  istore_3
  iload 28
  istore 4
  aload_2
  iload_3
  iload 4
  invokespecial android/widget/LinearLayout$LayoutParams/<init>(II)V
  iconst_5
  istore 22
  iload 22
  istore_2
  aload 36
  astore_3
  aload_3
  iload_2
  putfield android/view/ViewGroup$MarginLayoutParams/leftMargin I
  iconst_5
  istore 22
  iload 22
  istore_2
  aload 36
  astore_3
  aload_3
  iload_2
  putfield android/view/ViewGroup$MarginLayoutParams/rightMargin I
  aload 30
  astore_2
  aload 35
  astore_3
  aload 36
  astore 4
  aload_2
  aload_3
  aload 4
  invokevirtual android/widget/LinearLayout/addView(Landroid/view/View;Landroid/view/ViewGroup$LayoutParams;)V
  aload 30
  astore_2
  aload 32
  astore_3
  aload 34
  astore 4
  aload_2
  aload_3
  aload 4
  invokevirtual android/widget/LinearLayout/addView(Landroid/view/View;Landroid/view/ViewGroup$LayoutParams;)V
  new android/widget/LinearLayout
  astore 37
  aload 37
  astore_2
  aload_0
  astore_3
  aload_2
  aload_3
  invokespecial android/widget/LinearLayout/<init>(Landroid/content/Context;)V
  iconst_1
  istore 22
  aload 37
  astore_2
  iload 22
  istore_3
  aload_2
  iload_3
  invokevirtual android/widget/LinearLayout/setOrientation(I)V
  iconst_0
  istore 22
  aload 37
  astore_2
  iload 22
  istore_3
  aload_2
  iload_3
  invokevirtual android/widget/LinearLayout/setBackgroundColor(I)V
  new android/widget/LinearLayout$LayoutParams
  astore 38
  iconst_m1
  istore 22
  bipush -2
  istore 28
  aload 38
  astore_2
  iload 22
  istore_3
  iload 28
  istore 4
  aload_2
  iload_3
  iload 4
  invokespecial android/widget/LinearLayout$LayoutParams/<init>(II)V
  aload 37
  astore_2
  aload 38
  astore_3
  aload_2
  aload_3
  invokevirtual android/widget/LinearLayout/setLayoutParams(Landroid/view/ViewGroup$LayoutParams;)V
  iconst_0
  istore 22
  bipush 10
  istore 28
  bipush 10
  istore 29
  bipush 10
  istore 39
  aload 37
  astore_2
  iload 22
  istore_3
  iload 28
  istore 4
  iload 29
  istore 5
  iload 39
  istore 6
  aload_2
  iload_3
  iload 4
  iload 5
  iload 6
  invokevirtual android/widget/LinearLayout/setPadding(IIII)V
  aload_0
  astore_2
  aload_2
  invokestatic cn/domob/android/ads/I/a(Landroid/content/Context;)Landroid/widget/TextView;
  astore 40
  aload_0
  astore_2
  aload_2
  invokestatic cn/domob/android/ads/I/a(Landroid/content/Context;)Landroid/widget/TextView;
  astore 32
  aload_0
  astore_2
  aload_2
  invokestatic cn/domob/android/ads/I/a(Landroid/content/Context;)Landroid/widget/TextView;
  astore 41
  aload_0
  astore_2
  aload_2
  invokestatic cn/domob/android/ads/I/a(Landroid/content/Context;)Landroid/widget/TextView;
  astore 42
  aload_0
  astore_2
  aload_2
  invokestatic cn/domob/android/ads/I/a(Landroid/content/Context;)Landroid/widget/TextView;
  astore 43
  new java/lang/StringBuilder
  astore 44
  aload 44
  astore_2
  aload_2
  invokespecial java/lang/StringBuilder/<init>()V
  ldc "\u540d\u79f0\uff1a "
  astore 12
  aload 44
  astore_2
  aload_2
  aload 12
  invokevirtual java/lang/StringBuilder/append(Ljava/lang/String;)Ljava/lang/StringBuilder;
  astore 44
  aload 44
  astore_2
  aload_2
  aload 11
  invokevirtual java/lang/StringBuilder/append(Ljava/lang/String;)Ljava/lang/StringBuilder;
  astore 44
  aload 44
  astore_2
  aload_2
  invokevirtual java/lang/StringBuilder/toString()Ljava/lang/String;
  astore 45
  aload 40
  astore_2
  aload 45
  astore_3
  aload_2
  aload_3
  invokevirtual android/widget/TextView/setText(Ljava/lang/CharSequence;)V
  new java/lang/StringBuilder
  astore 44
  aload 44
  astore_2
  aload_2
  invokespecial java/lang/StringBuilder/<init>()V
  ldc "\u5927\u5c0f\uff1a "
  astore 12
  aload 44
  astore_2
  aload_2
  aload 12
  invokevirtual java/lang/StringBuilder/append(Ljava/lang/String;)Ljava/lang/StringBuilder;
  astore 44
  aload 44
  astore_2
  aload_2
  aload 17
  invokevirtual java/lang/StringBuilder/append(Ljava/lang/String;)Ljava/lang/StringBuilder;
  astore 44
  aload 44
  astore_2
  aload_2
  invokevirtual java/lang/StringBuilder/toString()Ljava/lang/String;
  astore 17
  aload 32
  astore_2
  aload_2
  aload 17
  invokevirtual android/widget/TextView/setText(Ljava/lang/CharSequence;)V
  new java/lang/StringBuilder
  astore 44
  aload 44
  astore_2
  aload_2
  invokespecial java/lang/StringBuilder/<init>()V
  ldc "\u7248\u672c\uff1a "
  astore 12
  aload 44
  astore_2
  aload_2
  aload 12
  invokevirtual java/lang/StringBuilder/append(Ljava/lang/String;)Ljava/lang/StringBuilder;
  astore 44
  aload 44
  astore_2
  aload_2
  aload 15
  invokevirtual java/lang/StringBuilder/append(Ljava/lang/String;)Ljava/lang/StringBuilder;
  astore 44
  aload 44
  astore_2
  aload_2
  invokevirtual java/lang/StringBuilder/toString()Ljava/lang/String;
  astore 17
  aload 41
  astore_2
  aload_2
  aload 17
  invokevirtual android/widget/TextView/setText(Ljava/lang/CharSequence;)V
  ldc "\u63cf\u8ff0\uff1a"
  astore 12
  aload 42
  astore_2
  aload_2
  aload 12
  invokevirtual android/widget/TextView/setText(Ljava/lang/CharSequence;)V
  aload 43
  astore_2
  aload 20
  astore_3
  aload_2
  aload_3
  invokevirtual android/widget/TextView/setText(Ljava/lang/CharSequence;)V
  new android/widget/LinearLayout
  astore 46
  aload 46
  astore_2
  aload_0
  astore_3
  aload_2
  aload_3
  invokespecial android/widget/LinearLayout/<init>(Landroid/content/Context;)V
  iconst_0
  istore 22
  aload 46
  astore_2
  iload 22
  istore_3
  aload_2
  iload_3
  invokevirtual android/widget/LinearLayout/setBackgroundColor(I)V
  aload 46
  astore_2
  aload 42
  astore_3
  aload_2
  aload_3
  invokevirtual android/widget/LinearLayout/addView(Landroid/view/View;)V
  aload 46
  astore_2
  aload 43
  astore_3
  aload_2
  aload_3
  invokevirtual android/widget/LinearLayout/addView(Landroid/view/View;)V
  aload 37
  astore_2
  aload 40
  astore_3
  aload_2
  aload_3
  invokevirtual android/widget/LinearLayout/addView(Landroid/view/View;)V
  aload 37
  astore_2
  aload 41
  astore_3
  aload_2
  aload_3
  invokevirtual android/widget/LinearLayout/addView(Landroid/view/View;)V
  aload 37
  astore_2
  aload 32
  astore_3
  aload_2
  aload_3
  invokevirtual android/widget/LinearLayout/addView(Landroid/view/View;)V
  aload 37
  astore_2
  aload 46
  astore_3
  aload_2
  aload_3
  invokevirtual android/widget/LinearLayout/addView(Landroid/view/View;)V
  new android/widget/ScrollView
  astore 47
  aload 47
  astore_2
  aload_0
  astore_3
  aload_2
  aload_3
  invokespecial android/widget/ScrollView/<init>(Landroid/content/Context;)V
  aload 47
  astore_2
  aload 37
  astore_3
  aload_2
  aload_3
  invokevirtual android/widget/ScrollView/addView(Landroid/view/View;)V
  aload_0
  astore_2
  aload_2
  invokestatic cn/domob/android/ads/I/b(Landroid/content/Context;)Landroid/widget/Button;
  astore 48
  ldc "\u7acb\u5373\u66f4\u65b0"
  astore 12
  aload 48
  astore_2
  aload_2
  aload 12
  invokevirtual android/widget/Button/setText(Ljava/lang/CharSequence;)V
  new android/widget/LinearLayout$LayoutParams
  astore 38
  iconst_m1
  istore 22
  bipush -2
  istore 28
  aload 38
  astore_2
  iload 22
  istore_3
  iload 28
  istore 4
  aload_2
  iload_3
  iload 4
  invokespecial android/widget/LinearLayout$LayoutParams/<init>(II)V
  iconst_5
  istore 22
  iload 22
  istore_2
  aload 38
  astore_3
  aload_3
  iload_2
  putfield android/view/ViewGroup$MarginLayoutParams/leftMargin I
  iconst_5
  istore 22
  iload 22
  istore_2
  aload 38
  astore_3
  aload_3
  iload_2
  putfield android/view/ViewGroup$MarginLayoutParams/topMargin I
  iconst_5
  istore 22
  iload 22
  istore_2
  aload 38
  astore_3
  aload_3
  iload_2
  putfield android/view/ViewGroup$MarginLayoutParams/rightMargin I
  new cn/domob/android/ads/I$1
  astore 49
  aload 49
  astore_2
  aload 24
  astore_3
  aload_0
  astore 4
  aload 14
  astore 5
  aload 15
  astore 6
  aload 18
  astore 7
  aload 11
  astore 8
  aload 16
  astore 9
  aload_2
  aload_3
  aload 4
  aload 5
  aload 6
  aload 7
  aload 8
  aload 9
  invokespecial cn/domob/android/ads/I$1/<init>(Landroid/app/Dialog;Landroid/content/Context;Ljava/lang/String;Ljava/lang/String;Ljava/lang/String;Ljava/lang/String;Ljava/lang/String;)V
  aload 48
  astore_2
  aload 49
  astore_3
  aload_2
  aload_3
  invokevirtual android/widget/Button/setOnClickListener(Landroid/view/View$OnClickListener;)V
  new android/widget/RelativeLayout
  astore 50
  aload 50
  astore_2
  aload_0
  astore_3
  aload_2
  aload_3
  invokespecial android/widget/RelativeLayout/<init>(Landroid/content/Context;)V
  iconst_0
  istore 22
  aload 50
  astore_2
  iload 22
  istore_3
  aload_2
  iload_3
  invokevirtual android/widget/RelativeLayout/setBackgroundColor(I)V
  new android/widget/RelativeLayout$LayoutParams
  astore 51
  iconst_m1
  istore 22
  bipush -2
  istore 28
  aload 51
  astore_2
  iload 22
  istore_3
  iload 28
  istore 4
  aload_2
  iload_3
  iload 4
  invokespecial android/widget/RelativeLayout$LayoutParams/<init>(II)V
  aload 50
  astore_2
  aload 51
  astore_3
  aload_2
  aload_3
  invokevirtual android/widget/RelativeLayout/setLayoutParams(Landroid/view/ViewGroup$LayoutParams;)V
  new android/widget/LinearLayout$LayoutParams
  astore 36
  iconst_m1
  istore 22
  bipush -2
  istore 28
  aload 36
  astore_2
  iload 22
  istore_3
  iload 28
  istore 4
  aload_2
  iload_3
  iload 4
  invokespecial android/widget/LinearLayout$LayoutParams/<init>(II)V
  new android/widget/LinearLayout
  astore 52
  aload 52
  astore_2
  aload_0
  astore_3
  aload_2
  aload_3
  invokespecial android/widget/LinearLayout/<init>(Landroid/content/Context;)V
  iconst_0
  istore 22
  aload 52
  astore_2
  iload 22
  istore_3
  aload_2
  iload_3
  invokevirtual android/widget/LinearLayout/setOrientation(I)V
  aload_0
  astore_2
  aload_2
  invokestatic cn/domob/android/ads/I/c(Landroid/content/Context;)Landroid/widget/Button;
  astore 53
  ldc "\u6682\u65f6\u4e0d\u66f4\u65b0"
  astore 12
  aload 53
  astore_2
  aload_2
  aload 12
  invokevirtual android/widget/Button/setText(Ljava/lang/CharSequence;)V
  ldc 15.000000
  fstore 33
  aload 53
  astore_2
  fload 33
  fstore_3
  aload_2
  fload_3
  invokevirtual android/widget/Button/setTextSize(F)V
  new cn/domob/android/ads/I$2
  astore 54
  aload 54
  astore_2
  aload 24
  astore_3
  aload_0
  astore 4
  aload_2
  aload_3
  aload 4
  aload 14
  aload 15
  invokespecial cn/domob/android/ads/I$2/<init>(Landroid/app/Dialog;Landroid/content/Context;Ljava/lang/String;Ljava/lang/String;)V
  aload 53
  astore_2
  aload 54
  astore_3
  aload_2
  aload_3
  invokevirtual android/widget/Button/setOnClickListener(Landroid/view/View$OnClickListener;)V
  aload_0
  astore_2
  aload_2
  invokestatic cn/domob/android/ads/I/c(Landroid/content/Context;)Landroid/widget/Button;
  astore 55
  ldc "\u8df3\u8fc7\u6b64\u7248\u672c"
  astore 12
  aload 55
  astore_2
  aload_2
  aload 12
  invokevirtual android/widget/Button/setText(Ljava/lang/CharSequence;)V
  ldc 15.000000
  fstore 33
  aload 55
  astore_2
  fload 33
  fstore_3
  aload_2
  fload_3
  invokevirtual android/widget/Button/setTextSize(F)V
  new cn/domob/android/ads/I$3
  astore 56
  aload 56
  astore_2
  aload 24
  astore_3
  aload_0
  astore 4
  aload 14
  astore 5
  aload 15
  astore 6
  aload 10
  astore 7
  aload_2
  aload_3
  aload 4
  aload 5
  aload 6
  aload 7
  invokespecial cn/domob/android/ads/I$3/<init>(Landroid/app/Dialog;Landroid/content/Context;Ljava/lang/String;Ljava/lang/String;Landroid/content/SharedPreferences$Editor;)V
  aload 55
  astore_2
  aload 56
  astore_3
  aload_2
  aload_3
  invokevirtual android/widget/Button/setOnClickListener(Landroid/view/View$OnClickListener;)V
  iload 23
  istore_2
  iload_2
  invokestatic app/DummyClass/invokeIfStmt(Z)V
  iload 23
  ifeq Label0
  new android/widget/LinearLayout$LayoutParams
  astore 34
  iconst_m1
  istore 22
  bipush -2
  istore 28
  fconst_0
  fstore 33
  aload 34
  astore_2
  iload 22
  istore_3
  iload 28
  istore 4
  fload 33
  fstore 5
  aload_2
  iload_3
  iload 4
  fload 5
  invokespecial android/widget/LinearLayout$LayoutParams/<init>(IIF)V
  iconst_5
  istore 22
  iload 22
  istore_2
  aload 34
  astore_3
  aload_3
  iload_2
  putfield android/view/ViewGroup$MarginLayoutParams/leftMargin I
  iconst_5
  istore 22
  iload 22
  istore_2
  aload 34
  astore_3
  aload_3
  iload_2
  putfield android/view/ViewGroup$MarginLayoutParams/topMargin I
  iconst_5
  istore 22
  iload 22
  istore_2
  aload 34
  astore_3
  aload_3
  iload_2
  putfield android/view/ViewGroup$MarginLayoutParams/bottomMargin I
  iconst_5
  istore 22
  iload 22
  istore_2
  aload 34
  astore_3
  aload_3
  iload_2
  putfield android/view/ViewGroup$MarginLayoutParams/rightMargin I
  fconst_1
  fstore 33
  fload 33
  fstore_2
  aload 34
  astore_3
  aload_3
  fload_2
  putfield android/widget/LinearLayout$LayoutParams/weight F
  aload 52
  astore_2
  aload 55
  astore_3
  aload 34
  astore 4
  aload_2
  aload_3
  aload 4
  invokevirtual android/widget/LinearLayout/addView(Landroid/view/View;Landroid/view/ViewGroup$LayoutParams;)V
Label0:
  iload 21
  istore_2
  iload_2
  invokestatic app/DummyClass/invokeIfStmt(Z)V
  iload 21
  ifne Label1
  new android/widget/LinearLayout$LayoutParams
  astore 34
  iconst_m1
  istore 22
  bipush -2
  istore 28
  fconst_0
  fstore 33
  aload 34
  astore_2
  iload 22
  istore_3
  iload 28
  istore 4
  fload 33
  fstore 5
  aload_2
  iload_3
  iload 4
  fload 5
  invokespecial android/widget/LinearLayout$LayoutParams/<init>(IIF)V
  iconst_5
  istore 22
  iload 22
  istore_2
  aload 34
  astore_3
  aload_3
  iload_2
  putfield android/view/ViewGroup$MarginLayoutParams/leftMargin I
  iconst_5
  istore 22
  iload 22
  istore_2
  aload 34
  astore_3
  aload_3
  iload_2
  putfield android/view/ViewGroup$MarginLayoutParams/topMargin I
  iconst_5
  istore 22
  iload 22
  istore_2
  aload 34
  astore_3
  aload_3
  iload_2
  putfield android/view/ViewGroup$MarginLayoutParams/rightMargin I
  iconst_5
  istore 22
  iload 22
  istore_2
  aload 34
  astore_3
  aload_3
  iload_2
  putfield android/view/ViewGroup$MarginLayoutParams/bottomMargin I
  fconst_1
  fstore 33
  fload 33
  fstore_2
  aload 34
  astore_3
  aload_3
  fload_2
  putfield android/widget/LinearLayout$LayoutParams/weight F
  aload 52
  astore_2
  aload 53
  astore_3
  aload 34
  astore 4
  aload_2
  aload_3
  aload 4
  invokevirtual android/widget/LinearLayout/addView(Landroid/view/View;Landroid/view/ViewGroup$LayoutParams;)V
Label1:
  new android/widget/RelativeLayout$LayoutParams
  astore 51
  iconst_m1
  istore 22
  bipush -2
  istore 28
  aload 51
  astore_2
  iload 22
  istore_3
  iload 28
  istore 4
  aload_2
  iload_3
  iload 4
  invokespecial android/widget/RelativeLayout$LayoutParams/<init>(II)V
  bipush 13
  istore 22
  aload 51
  astore_2
  iload 22
  istore_3
  aload_2
  iload_3
  invokevirtual android/widget/RelativeLayout$LayoutParams/addRule(I)V
  aload 50
  astore_2
  aload 52
  astore_3
  aload 51
  astore 4
  aload_2
  aload_3
  aload 4
  invokevirtual android/widget/RelativeLayout/addView(Landroid/view/View;Landroid/view/ViewGroup$LayoutParams;)V
  new android/widget/LinearLayout$LayoutParams
  astore 34
  iconst_m1
  istore 22
  bipush -2
  istore 28
  aload 34
  astore_2
  iload 22
  istore_3
  iload 28
  istore 4
  aload_2
  iload_3
  iload 4
  invokespecial android/widget/LinearLayout$LayoutParams/<init>(II)V
  bipush 20
  istore 22
  iload 22
  istore_2
  aload 34
  astore_3
  aload_3
  iload_2
  putfield android/view/ViewGroup$MarginLayoutParams/leftMargin I
  iconst_0
  istore 22
  iload 22
  istore_2
  aload 34
  astore_3
  aload_3
  iload_2
  putfield android/view/ViewGroup$MarginLayoutParams/rightMargin I
  fconst_1
  fstore 33
  fload 33
  fstore_2
  aload 34
  astore_3
  aload_3
  fload_2
  putfield android/widget/LinearLayout$LayoutParams/weight F
  aload 26
  astore_2
  aload 30
  astore_3
  aload 31
  astore 4
  aload_2
  aload_3
  aload 4
  invokevirtual android/widget/LinearLayout/addView(Landroid/view/View;Landroid/view/ViewGroup$LayoutParams;)V
  aload 26
  astore_2
  aload 47
  astore_3
  aload 34
  astore 4
  aload_2
  aload_3
  aload 4
  invokevirtual android/widget/LinearLayout/addView(Landroid/view/View;Landroid/view/ViewGroup$LayoutParams;)V
  aload 26
  astore_2
  aload 48
  astore_3
  aload 38
  astore 4
  aload_2
  aload_3
  aload 4
  invokevirtual android/widget/LinearLayout/addView(Landroid/view/View;Landroid/view/ViewGroup$LayoutParams;)V
  aload 26
  astore_2
  aload 50
  astore_3
  aload 36
  astore 4
  aload_2
  aload_3
  aload 4
  invokevirtual android/widget/LinearLayout/addView(Landroid/view/View;Landroid/view/ViewGroup$LayoutParams;)V
  aload 24
  astore_2
  aload 26
  astore_3
  aload_2
  aload_3
  invokevirtual android/app/Dialog/setContentView(Landroid/view/View;)V
  aload 24
  areturn
  nop
.end <method>

.method private static a(Landroid/content/Context;)Landroid/widget/TextView;
.limit locals 3
.limit stack 200
  nop
  new java/lang/NoClassDefFoundError
  dup
  invokespecial java/lang/NoClassDefFoundError/<init>()V
  athrow
  aload_1
  aload_0
  invokespecial android/widget/TextView/<init>(Landroid/content/Context;)V
  iconst_m1
  istore_2
  aload_1
  iload_2
  invokevirtual android/widget/TextView/setTextColor(I)V
  aload_1
  areturn
  nop
.end <method>

.method protected a()V
.limit locals 33
.limit stack 200
  .catch  java/lang/Exception <from> Label12 <to> Label13 <using> Label11
  .catch  java/lang/Exception <from> Label2 <to> Label14 <using> Label11
  nop
  iconst_0
  istore 4
Label12:
  ldc "\u5f00\u59cb\u68c0\u67e5\u66f4\u65b0..."
  astore 5
  aload_0
  astore_1
  aload_1
  aload 5
  invokestatic cn/domob/android/ads/J/a(Ljava/lang/Object;Ljava/lang/String;)V
  aload_0
  astore_1
  aload_1
  getfield cn/domob/android/ads/I/g Landroid/content/Context;
  astore 6
  ldc "domob_update_info"
  astore 5
  iconst_0
  istore 8
  new java/lang/NoClassDefFoundError
  dup
  invokespecial java/lang/NoClassDefFoundError/<init>()V
  athrow
  nop
  aload 7
  invokeinterface android/content/SharedPreferences/edit()Landroid/content/SharedPreferences$Editor; 1
  astore 9
  ldc "vc"
  astore 5
  aconst_null
  astore 11
  aload 7
  aload 5
  aload 11
  invokeinterface android/content/SharedPreferences/getString(Ljava/lang/String;Ljava/lang/String;)Ljava/lang/String; 3
  astore 10
  ldc "nrt"
  astore 5
  iconst_0
  istore 8
  aload 7
  aload 5
  iload 8
  invokeinterface android/content/SharedPreferences/getInt(Ljava/lang/String;I)I 3
  istore 12
  new java/lang/StringBuilder
  astore 13
  aload 13
  invokespecial java/lang/StringBuilder/<init>()V
  ldc "\u5b58\u50a8\u7684\u5e94\u7528\u7248\u672c\uff1a"
  astore 5
  aload 13
  aload 5
  invokevirtual java/lang/StringBuilder/append(Ljava/lang/String;)Ljava/lang/StringBuilder;
  astore 13
  aload 13
  aload 10
  invokevirtual java/lang/StringBuilder/append(Ljava/lang/String;)Ljava/lang/StringBuilder;
  astore 13
  aload 13
  invokevirtual java/lang/StringBuilder/toString()Ljava/lang/String;
  astore 14
  aload_0
  astore_1
  aload_1
  aload 14
  invokestatic cn/domob/android/ads/J/d(Ljava/lang/Object;Ljava/lang/String;)V
  new java/lang/StringBuilder
  astore 13
  aload 13
  invokespecial java/lang/StringBuilder/<init>()V
  ldc "\u5b58\u50a8\u7684\u66f4\u65b0\u7c7b\u578b\uff1a"
  astore 5
  aload 13
  aload 5
  invokevirtual java/lang/StringBuilder/append(Ljava/lang/String;)Ljava/lang/StringBuilder;
  astore 13
  aload 13
  iload 12
  invokevirtual java/lang/StringBuilder/append(I)Ljava/lang/StringBuilder;
  astore 13
  aload 13
  invokevirtual java/lang/StringBuilder/toString()Ljava/lang/String;
  astore 14
  aload_0
  astore_1
  aload_1
  aload 14
  invokestatic cn/domob/android/ads/J/d(Ljava/lang/Object;Ljava/lang/String;)V
  dload 12
  invokestatic app/DummyClass/invokeIfStmt(D)V
  iload 12
  lookupswitch
  0 : Label1
  1 : Label2
  2 : Label3
  default : Label0
Label0:
  goto Label4
Label4:
  ldc "\u9ed8\u8ba4\u81ea\u7136\u5929\u6bcf\u5929\u63d0\u793a\u4e00\u6b21"
  astore 5
  aload_0
  astore_1
  aload_1
  aload 5
  invokestatic cn/domob/android/ads/J/d(Ljava/lang/Object;Ljava/lang/String;)V
Label7:
  aload_0
  astore_1
  aload_1
  getfield cn/domob/android/ads/I/g Landroid/content/Context;
  astore 6
  aload 6
  invokevirtual android/content/Context/getPackageManager()Landroid/content/pm/PackageManager;
  astore 15
  aload_0
  astore_1
  aload_1
  getfield cn/domob/android/ads/I/g Landroid/content/Context;
  astore 6
  aload 6
  invokevirtual android/content/Context/getPackageName()Ljava/lang/String;
  astore 14
  iconst_0
  istore 8
  aload 15
  aload 14
  iload 8
  invokevirtual android/content/pm/PackageManager/getPackageInfo(Ljava/lang/String;I)Landroid/content/pm/PackageInfo;
  astore 16
  aload 16
  getfield android/content/pm/PackageInfo/versionCode I
  istore 12
  new java/lang/StringBuilder
  astore 13
  aload 13
  invokespecial java/lang/StringBuilder/<init>()V
  ldc "\u5f53\u524d\u5df2\u5b89\u88c5\u7684\u5e94\u7528\u7248\u672c\uff1a"
  astore 5
  aload 13
  aload 5
  invokevirtual java/lang/StringBuilder/append(Ljava/lang/String;)Ljava/lang/StringBuilder;
  astore 13
  aload 13
  iload 12
  invokevirtual java/lang/StringBuilder/append(I)Ljava/lang/StringBuilder;
  astore 13
  aload 13
  invokevirtual java/lang/StringBuilder/toString()Ljava/lang/String;
  astore 14
  aload_0
  astore_1
  aload_1
  aload 14
  invokestatic cn/domob/android/ads/J/d(Ljava/lang/Object;Ljava/lang/String;)V
  aload 10
  invokestatic app/DummyClass/invokeIfStmt(Ljava/lang/Object;)V
  aload 10
  ifnull Label5
  aload 10
  invokestatic java/lang/Integer/parseInt(Ljava/lang/String;)I
  istore 17
  iload 17
  istore_1
  dload_1
  invokestatic app/DummyClass/invokeIfStmt(D)V
  dload 12
  invokestatic app/DummyClass/invokeIfStmt(D)V
  iload 17
  istore_1
  iload_1
  iload 12
  if_icmple Label5
  ldc "Need update"
  astore 5
  aload_0
  astore_1
  aload_1
  aload 5
  invokestatic cn/domob/android/ads/J/d(Ljava/lang/Object;Ljava/lang/String;)V
  aload 10
  aload 7
  invokestatic cn/domob/android/ads/I/a(Ljava/lang/String;Landroid/content/SharedPreferences;)Z
  istore 18
  iload 18
  istore_1
  iload_1
  invokestatic app/DummyClass/invokeIfStmt(Z)V
  iload 18
  ifeq Label5
  ldc "Need notice"
  astore 5
  aload_0
  astore_1
  aload_1
  aload 5
  invokestatic cn/domob/android/ads/J/d(Ljava/lang/Object;Ljava/lang/String;)V
  ldc "n"
  astore 5
  aconst_null
  astore 11
  aload 7
  aload 5
  aload 11
  invokeinterface android/content/SharedPreferences/getString(Ljava/lang/String;Ljava/lang/String;)Ljava/lang/String; 3
  astore 10
  ldc "vc"
  astore 5
  aconst_null
  astore 11
  aload 7
  aload 5
  aload 11
  invokeinterface android/content/SharedPreferences/getString(Ljava/lang/String;Ljava/lang/String;)Ljava/lang/String; 3
  astore 14
  ldc "vn"
  astore 5
  aconst_null
  astore 11
  aload 7
  aload 5
  aload 11
  invokeinterface android/content/SharedPreferences/getString(Ljava/lang/String;Ljava/lang/String;)Ljava/lang/String; 3
  astore 19
  ldc "u"
  astore 5
  aconst_null
  astore 11
  aload 7
  aload 5
  aload 11
  invokeinterface android/content/SharedPreferences/getString(Ljava/lang/String;Ljava/lang/String;)Ljava/lang/String; 3
  astore 20
  ldc "s"
  astore 5
  aconst_null
  astore 11
  aload 7
  aload 5
  aload 11
  invokeinterface android/content/SharedPreferences/getString(Ljava/lang/String;Ljava/lang/String;)Ljava/lang/String; 3
  astore 21
  ldc "ul"
  astore 5
  aconst_null
  astore 11
  aload 7
  aload 5
  aload 11
  invokeinterface android/content/SharedPreferences/getString(Ljava/lang/String;Ljava/lang/String;)Ljava/lang/String; 3
  astore 22
  aload 10
  invokestatic app/DummyClass/invokeIfStmt(Ljava/lang/Object;)V
  aload 10
  ifnull Label5
  aload 14
  invokestatic app/DummyClass/invokeIfStmt(Ljava/lang/Object;)V
  aload 14
  ifnull Label5
  aload 19
  astore_1
  aload_1
  invokestatic app/DummyClass/invokeIfStmt(Ljava/lang/Object;)V
  aload 19
  ifnull Label5
  aload 20
  astore_1
  aload_1
  invokestatic app/DummyClass/invokeIfStmt(Ljava/lang/Object;)V
  aload 20
  ifnull Label5
  aload 21
  astore_1
  aload_1
  invokestatic app/DummyClass/invokeIfStmt(Ljava/lang/Object;)V
  aload 21
  ifnull Label5
  aload 22
  astore_1
  aload_1
  invokestatic app/DummyClass/invokeIfStmt(Ljava/lang/Object;)V
  aload 22
  ifnull Label5
  aload_0
  astore_1
  aload_1
  getfield cn/domob/android/ads/I/g Landroid/content/Context;
  astore 6
  aload 6
  aload 7
  invokestatic cn/domob/android/ads/I/a(Landroid/content/Context;Landroid/content/SharedPreferences;)Landroid/app/Dialog;
  astore 23
  aload 23
  astore_1
  aload_1
  invokevirtual android/app/Dialog/show()V
  dload 4
  invokestatic app/DummyClass/invokeIfStmt(D)V
  iload 4
  ifne Label6
  new java/text/SimpleDateFormat
  astore 24
  ldc "yyyy-MM-dd 00:00:00"
  astore 5
  aload 24
  astore_1
  aload_1
  aload 5
  invokespecial java/text/SimpleDateFormat/<init>(Ljava/lang/String;)V
  invokestatic java/util/Calendar/getInstance()Ljava/util/Calendar;
  astore 25
  new java/util/Date
  astore 26
  aload 26
  astore_1
  aload_1
  invokespecial java/util/Date/<init>()V
  aload 25
  astore_1
  aload 26
  astore_2
  aload_1
  aload_2
  invokevirtual java/util/Calendar/setTime(Ljava/util/Date;)V
  iconst_5
  istore 8
  iconst_1
  istore 27
  aload 25
  astore_1
  iload 27
  istore_2
  aload_1
  iload 8
  iload_2
  invokevirtual java/util/Calendar/add(II)V
  aload 25
  astore_1
  aload_1
  invokevirtual java/util/Calendar/getTime()Ljava/util/Date;
  astore 26
  aload 24
  astore_1
  aload 26
  astore_2
  aload_1
  aload_2
  invokevirtual java/text/SimpleDateFormat/format(Ljava/util/Date;)Ljava/lang/String;
  astore 22
  new java/lang/StringBuilder
  astore 13
  aload 13
  invokespecial java/lang/StringBuilder/<init>()V
  ldc "\u4e0b\u6b21\u63d0\u9192\u65f6\u95f4\uff08\u5b57\u7b26\u4e32\uff09"
  astore 5
  aload 13
  aload 5
  invokevirtual java/lang/StringBuilder/append(Ljava/lang/String;)Ljava/lang/StringBuilder;
  astore 13
  aload 22
  astore_1
  aload 13
  aload_1
  invokevirtual java/lang/StringBuilder/append(Ljava/lang/String;)Ljava/lang/StringBuilder;
  astore 13
  aload 13
  invokevirtual java/lang/StringBuilder/toString()Ljava/lang/String;
  astore 21
  aload_0
  astore_1
  aload 21
  astore_2
  aload_1
  aload_2
  invokestatic cn/domob/android/ads/J/d(Ljava/lang/Object;Ljava/lang/String;)V
  aload 24
  astore_1
  aload 22
  astore_2
  aload_1
  aload_2
  invokevirtual java/text/SimpleDateFormat/parse(Ljava/lang/String;)Ljava/util/Date;
  astore 26
  aload 26
  astore_1
  aload_1
  invokevirtual java/util/Date/getTime()J
  lstore 28
  new java/lang/StringBuilder
  astore 13
  aload 13
  invokespecial java/lang/StringBuilder/<init>()V
  ldc "\u4e0b\u6b21\u63d0\u9192\u65f6\u95f4\uff08\u65f6\u95f4\u6233\uff09"
  astore 5
  aload 13
  aload 5
  invokevirtual java/lang/StringBuilder/append(Ljava/lang/String;)Ljava/lang/StringBuilder;
  astore 13
  lload 28
  lstore_1
  aload 13
  lload_1
  invokevirtual java/lang/StringBuilder/append(J)Ljava/lang/StringBuilder;
  astore 13
  aload 13
  invokevirtual java/lang/StringBuilder/toString()Ljava/lang/String;
  astore 22
  aload_0
  astore_1
  aload 22
  astore_2
  aload_1
  aload_2
  invokestatic cn/domob/android/ads/J/d(Ljava/lang/Object;Ljava/lang/String;)V
  ldc "next_time"
  astore 5
  lload 28
  lstore_1
  aload 9
  aload 5
  lload_1
  invokeinterface android/content/SharedPreferences$Editor/putLong(Ljava/lang/String;J)Landroid/content/SharedPreferences$Editor; 4
  pop
Label10:
  aload 9
  invokeinterface android/content/SharedPreferences$Editor/commit()Z 1
  pop
  aload_0
  astore_1
  aload_1
  getfield cn/domob/android/ads/I/g Landroid/content/Context;
  astore 6
  ldc "up_alert"
  astore 5
  aload 19
  astore_1
  aload 5
  aload 6
  aload 14
  aload_1
  invokestatic cn/domob/android/ads/I/b(Ljava/lang/String;Landroid/content/Context;Ljava/lang/String;Ljava/lang/String;)V
Label5:
  return
Label1:
  ldc "\u81ea\u7136\u5929\u6bcf\u5929\u63d0\u793a\u4e00\u6b21"
  astore 5
  aload_0
  astore_1
  aload_1
  aload 5
  invokestatic cn/domob/android/ads/J/d(Ljava/lang/Object;Ljava/lang/String;)V
Label13:
  goto Label7
Label11:
  astore 30
  aload 30
  astore_1
  aload_1
  invokestatic cn/domob/android/ads/J/a(Ljava/lang/Throwable;)V
  goto Label5
Label2:
  ldc "\u6bcf\u6b21\u6253\u5f00\u90fd\u63d0\u793a"
  astore 5
  aload_0
  astore_1
  aload_1
  aload 5
  invokestatic cn/domob/android/ads/J/d(Ljava/lang/Object;Ljava/lang/String;)V
  iconst_m1
  istore 4
  goto Label7
Label3:
  ldc "nri"
  astore 5
  iconst_3
  istore 8
  aload 7
  aload 5
  iload 8
  invokeinterface android/content/SharedPreferences/getInt(Ljava/lang/String;I)I 3
  istore 4
  dload 4
  invokestatic app/DummyClass/invokeIfStmt(D)V
  iconst_1
  istore 8
  iload 4
  iload 8
  if_icmpge Label8
  iconst_3
  istore 4
Label8:
  new java/lang/StringBuilder
  astore 13
  aload 13
  invokespecial java/lang/StringBuilder/<init>()V
  ldc "\u95f4\u9694\u63d0\u793a\uff0c\u65f6\u95f4\u95f4\u9694\u4e3a\uff1a"
  astore 5
  aload 13
  aload 5
  invokevirtual java/lang/StringBuilder/append(Ljava/lang/String;)Ljava/lang/StringBuilder;
  astore 13
  aload 13
  iload 4
  invokevirtual java/lang/StringBuilder/append(I)Ljava/lang/StringBuilder;
  astore 13
  ldc "\u5c0f\u65f6"
  astore 5
  aload 13
  aload 5
  invokevirtual java/lang/StringBuilder/append(Ljava/lang/String;)Ljava/lang/StringBuilder;
  astore 13
  aload 13
  invokevirtual java/lang/StringBuilder/toString()Ljava/lang/String;
  astore 22
  aload_0
  astore_1
  aload 22
  astore_2
  aload_1
  aload_2
  invokestatic cn/domob/android/ads/J/d(Ljava/lang/Object;Ljava/lang/String;)V
  goto Label7
Label6:
  dload 4
  invokestatic app/DummyClass/invokeIfStmt(D)V
  iconst_m1
  istore 8
  iload 4
  iload 8
  if_icmpne Label9
  ldc "\u6bcf\u6b21\u6253\u5f00\u5747\u63d0\u793a"
  astore 5
  aload_0
  astore_1
  aload_1
  aload 5
  invokestatic cn/domob/android/ads/J/d(Ljava/lang/Object;Ljava/lang/String;)V
  invokestatic java/lang/System/currentTimeMillis()J
  lstore 28
  ldc "next_time"
  astore 5
  lload 28
  lstore_1
  aload 9
  aload 5
  lload_1
  invokeinterface android/content/SharedPreferences$Editor/putLong(Ljava/lang/String;J)Landroid/content/SharedPreferences$Editor; 4
  pop
  goto Label10
Label9:
  new java/lang/StringBuilder
  astore 13
  aload 13
  invokespecial java/lang/StringBuilder/<init>()V
  aload 13
  iload 4
  invokevirtual java/lang/StringBuilder/append(I)Ljava/lang/StringBuilder;
  astore 13
  ldc "\u5c0f\u65f6\u540e\u63d0\u9192"
  astore 5
  aload 13
  aload 5
  invokevirtual java/lang/StringBuilder/append(Ljava/lang/String;)Ljava/lang/StringBuilder;
  astore 13
  aload 13
  invokevirtual java/lang/StringBuilder/toString()Ljava/lang/String;
  astore 22
  aload_0
  astore_1
  aload 22
  astore_2
  aload_1
  aload_2
  invokestatic cn/domob/android/ads/J/d(Ljava/lang/Object;Ljava/lang/String;)V
  invokestatic java/lang/System/currentTimeMillis()J
  lstore 28
  iload 4
  sipush 3600
  imul
  istore_1
  iload_1
  istore 17
  iload_1
  sipush 1000
  imul
  istore_1
  iload_1
  istore 17
  iload_1
  i2l
  lstore_1
  lload_1
  lstore 31
  lload 28
  lload 31
  ladd
  lstore 31
  ldc "next_time"
  astore 5
  lload 31
  lstore_1
  aload 9
  aload 5
  lload_1
  invokeinterface android/content/SharedPreferences$Editor/putLong(Ljava/lang/String;J)Landroid/content/SharedPreferences$Editor; 4
  pop
Label14:
  goto Label10
  nop
  nop
.end <method>

.method static a(Ljava/lang/String;Landroid/content/Context;Ljava/lang/String;Ljava/lang/String;)V
  .synthetic
.limit locals 4
.limit stack 200
  nop
  aload_0
  aload_1
  aload_2
  aload_3
  invokestatic cn/domob/android/ads/I/b(Ljava/lang/String;Landroid/content/Context;Ljava/lang/String;Ljava/lang/String;)V
  return
  nop
.end <method>

.method static a(Ljava/lang/String;Ljava/lang/String;Landroid/content/Context;Ljava/lang/String;Ljava/lang/String;Ljava/lang/String;)V
  .synthetic
.limit locals 6
.limit stack 200
  nop
  aload_0
  aload_1
  aload_2
  aload_3
  aload 4
  aload 5
  invokestatic cn/domob/android/ads/I/b(Ljava/lang/String;Ljava/lang/String;Landroid/content/Context;Ljava/lang/String;Ljava/lang/String;Ljava/lang/String;)V
  return
  nop
.end <method>

.method private static a(Ljava/lang/String;Landroid/content/SharedPreferences;)Z
.limit locals 22
.limit stack 200
  nop
  ldc "next_time"
  astore 5
  ldc2_w 0.000000000000000
  dstore 6
  aload_1
  astore_2
  new java/lang/NoSuchMethodError
  dup
  invokespecial java/lang/NoSuchMethodError/<init>()V
  athrow
  nop
  ldc "skip_vc"
  astore 5
  aconst_null
  astore 9
  aload_1
  astore_2
  aload_2
  aload 5
  aload 9
  invokeinterface android/content/SharedPreferences/getString(Ljava/lang/String;Ljava/lang/String;)Ljava/lang/String; 3
  astore 8
  ldc cn/domob/android/ads/I
  astore 10
  aload 10
  invokevirtual java/lang/Class/getSimpleName()Ljava/lang/String;
  astore 11
  new java/lang/StringBuilder
  astore 12
  aload 12
  invokespecial java/lang/StringBuilder/<init>()V
  ldc "\u4e0b\u6b21\u5141\u8bb8\u63d0\u793a\u65f6\u95f4\u4e3a\uff1a"
  astore 5
  aload 12
  aload 5
  invokevirtual java/lang/StringBuilder/append(Ljava/lang/String;)Ljava/lang/StringBuilder;
  astore 12
  new java/text/SimpleDateFormat
  astore 13
  ldc "yyyy-MM-dd HH:mm:ss"
  astore 5
  aload 13
  aload 5
  invokespecial java/text/SimpleDateFormat/<init>(Ljava/lang/String;)V
  new java/util/Date
  astore 14
  aload 14
  lload_3
  invokespecial java/util/Date/<init>(J)V
  aload 13
  aload 14
  invokevirtual java/text/SimpleDateFormat/format(Ljava/util/Date;)Ljava/lang/String;
  astore 15
  aload 12
  aload 15
  invokevirtual java/lang/StringBuilder/append(Ljava/lang/String;)Ljava/lang/StringBuilder;
  astore 12
  aload 12
  invokevirtual java/lang/StringBuilder/toString()Ljava/lang/String;
  astore 15
  aload 11
  aload 15
  invokestatic cn/domob/android/ads/J/d(Ljava/lang/Object;Ljava/lang/String;)V
  ldc2_w 0
  lstore 6
  lload_3
  lload 6
  lcmp
  istore 16
  dload 16
  invokestatic app/DummyClass/invokeIfStmt(D)V
  iload 16
  ifeq Label0
  invokestatic java/lang/System/currentTimeMillis()J
  lstore 17
  lload 17
  lload_3
  lcmp
  istore 16
  dload 16
  invokestatic app/DummyClass/invokeIfStmt(D)V
  iload 16
  iflt Label1
Label0:
  ldc cn/domob/android/ads/I
  astore 10
  aload 10
  invokevirtual java/lang/Class/getSimpleName()Ljava/lang/String;
  astore 11
  ldc "\u5230\u4e86\u5141\u8bb8\u63d0\u793a\u7684\u65f6\u95f4\u95f4\u9694\uff0c\u9700\u8981\u63d0\u793a"
  astore 5
  aload 11
  aload 5
  invokestatic cn/domob/android/ads/J/d(Ljava/lang/Object;Ljava/lang/String;)V
  iconst_1
  istore 19
Label5:
  aload 8
  invokestatic app/DummyClass/invokeIfStmt(Ljava/lang/Object;)V
  aload 8
  ifnull Label2
  aload_0
  astore_2
  aload 8
  aload_2
  invokevirtual java/lang/String/equals(Ljava/lang/Object;)Z
  istore 20
  iload 20
  istore_2
  iload_2
  invokestatic app/DummyClass/invokeIfStmt(Z)V
  iload 20
  ifne Label3
Label2:
  ldc cn/domob/android/ads/I
  astore 10
  aload 10
  invokevirtual java/lang/Class/getSimpleName()Ljava/lang/String;
  astore 11
  ldc "\u7528\u6237\u6ca1\u6709\u8df3\u8fc7\u8fd9\u4e2a\u7248\u672c\uff0c\u9700\u8981\u63d0\u793a"
  astore 5
  aload 11
  aload 5
  invokestatic cn/domob/android/ads/J/d(Ljava/lang/Object;Ljava/lang/String;)V
  iconst_1
  istore 20
Label6:
  iload 19
  istore_2
  iload_2
  invokestatic app/DummyClass/invokeIfStmt(Z)V
  iload 19
  ifeq Label4
  iload 20
  istore_2
  iload_2
  invokestatic app/DummyClass/invokeIfStmt(Z)V
  iload 20
  ifeq Label4
  iconst_1
  istore 21
  iload 21
  ireturn
Label1:
  ldc cn/domob/android/ads/I
  astore 10
  aload 10
  invokevirtual java/lang/Class/getSimpleName()Ljava/lang/String;
  astore 11
  ldc "\u672a\u5230\u5141\u8bb8\u63d0\u793a\u7684\u65f6\u95f4\u95f4\u9694\uff0c\u4e0d\u9700\u8981\u63d0\u793a"
  astore 5
  aload 11
  aload 5
  invokestatic cn/domob/android/ads/J/d(Ljava/lang/Object;Ljava/lang/String;)V
  iconst_0
  istore 19
  goto Label5
Label3:
  ldc cn/domob/android/ads/I
  astore 10
  aload 10
  invokevirtual java/lang/Class/getSimpleName()Ljava/lang/String;
  astore 11
  ldc "\u7528\u6237\u8df3\u8fc7\u4e86\u8fd9\u4e2a\u7248\u672c\uff0c\u4e0d\u9700\u8981\u63d0\u793a"
  astore 5
  aload 11
  aload 5
  invokestatic cn/domob/android/ads/J/d(Ljava/lang/Object;Ljava/lang/String;)V
  iconst_0
  istore 20
  goto Label6
Label4:
  iconst_0
  istore 21
  iload 21
  ireturn
  nop
.end <method>

.method private static b(Landroid/content/Context;)Landroid/widget/Button;
.limit locals 12
.limit stack 200
  nop
  new java/lang/NoClassDefFoundError
  dup
  invokespecial java/lang/NoClassDefFoundError/<init>()V
  athrow
  aload_1
  aload_0
  invokespecial android/widget/Button/<init>(Landroid/content/Context;)V
  ldc 20.000000
  fstore_2
  aload_1
  fload_2
  invokevirtual android/widget/Button/setTextSize(F)V
  iconst_m1
  istore_3
  aload_1
  iload_3
  invokevirtual android/widget/Button/setTextColor(I)V
  new android/graphics/drawable/GradientDrawable
  astore 4
  getstatic android/graphics/drawable/GradientDrawable$Orientation/BOTTOM_TOP Landroid/graphics/drawable/GradientDrawable$Orientation;
  astore 5
  iconst_2
  istore_3
  iload_3
  newarray int
  astore 6
  ldc "#3399ff"
  astore 8
  aload 8
  invokestatic android/graphics/Color/parseColor(Ljava/lang/String;)I
  istore 7
  iconst_0
  istore_3
  aload 6
  iload_3
  iload 7
  iastore
  ldc "#99bbff"
  astore 8
  aload 8
  invokestatic android/graphics/Color/parseColor(Ljava/lang/String;)I
  istore 7
  iconst_1
  istore_3
  aload 6
  iload_3
  iload 7
  iastore
  aload 4
  aload 5
  aload 6
  invokespecial android/graphics/drawable/GradientDrawable/<init>(Landroid/graphics/drawable/GradientDrawable$Orientation;[I)V
  iconst_1
  istore_3
  ldc -7829368
  istore 9
  aload 4
  iload_3
  iload 9
  invokevirtual android/graphics/drawable/GradientDrawable/setStroke(II)V
  ldc 5.000000
  fstore_2
  aload 4
  fload_2
  invokevirtual android/graphics/drawable/GradientDrawable/setCornerRadius(F)V
  new android/graphics/drawable/GradientDrawable
  astore 10
  getstatic android/graphics/drawable/GradientDrawable$Orientation/TOP_BOTTOM Landroid/graphics/drawable/GradientDrawable$Orientation;
  astore 5
  iconst_2
  istore_3
  iload_3
  newarray int
  astore 6
  ldc "#3399ff"
  astore 8
  aload 8
  invokestatic android/graphics/Color/parseColor(Ljava/lang/String;)I
  istore 7
  iconst_0
  istore_3
  aload 6
  iload_3
  iload 7
  iastore
  ldc "#99bbff"
  astore 8
  aload 8
  invokestatic android/graphics/Color/parseColor(Ljava/lang/String;)I
  istore 7
  iconst_1
  istore_3
  aload 6
  iload_3
  iload 7
  iastore
  aload 10
  aload 5
  aload 6
  invokespecial android/graphics/drawable/GradientDrawable/<init>(Landroid/graphics/drawable/GradientDrawable$Orientation;[I)V
  iconst_1
  istore_3
  ldc -7829368
  istore 9
  aload 10
  iload_3
  iload 9
  invokevirtual android/graphics/drawable/GradientDrawable/setStroke(II)V
  ldc 5.000000
  fstore_2
  aload 10
  fload_2
  invokevirtual android/graphics/drawable/GradientDrawable/setCornerRadius(F)V
  aload_1
  aload 4
  invokevirtual android/widget/Button/setBackgroundDrawable(Landroid/graphics/drawable/Drawable;)V
  new cn/domob/android/ads/I$4
  astore 11
  aload 11
  aload 10
  aload 4
  invokespecial cn/domob/android/ads/I$4/<init>(Landroid/graphics/drawable/GradientDrawable;Landroid/graphics/drawable/GradientDrawable;)V
  aload_1
  aload 11
  invokevirtual android/widget/Button/setOnTouchListener(Landroid/view/View$OnTouchListener;)V
  aload_1
  areturn
  nop
.end <method>

.method private static b(Ljava/lang/String;Landroid/content/Context;Ljava/lang/String;Ljava/lang/String;)V
.limit locals 11
.limit stack 200
  nop
  new cn/domob/android/ads/D
  astore 4
  aload 4
  aload_1
  invokespecial cn/domob/android/ads/D/<init>(Landroid/content/Context;)V
  new cn/domob/android/ads/D$c
  astore 5
  aload 4
  invokevirtual java/lang/Object/getClass()Ljava/lang/Class;
  pop
  aload 5
  aload 4
  invokespecial cn/domob/android/ads/D$c/<init>(Lcn/domob/android/ads/D;)V
  ldc "3"
  astore 6
  aload 5
  aload 6
  putfield cn/domob/android/ads/D$c/a Ljava/lang/String;
  aload 5
  aload_0
  putfield cn/domob/android/ads/D$c/b Ljava/lang/String;
  iconst_2
  istore 7
  aload 5
  iload 7
  putfield cn/domob/android/ads/D$c/c I
  new java/util/ArrayList
  astore 8
  aload 8
  invokespecial java/util/ArrayList/<init>()V
  aload 5
  aload 8
  putfield cn/domob/android/ads/D$c/d Ljava/util/ArrayList;
  aload 5
  getfield cn/domob/android/ads/D$c/d Ljava/util/ArrayList;
  astore 8
  new java/lang/NoClassDefFoundError
  dup
  invokespecial java/lang/NoClassDefFoundError/<init>()V
  athrow
  nop
  aload 8
  aload 9
  invokevirtual java/util/ArrayList/add(Ljava/lang/Object;)Z
  pop
  aconst_null
  astore 10
  aload 5
  aload 10
  putfield cn/domob/android/ads/D$c/e Ljava/lang/String;
  aconst_null
  astore 10
  aload 5
  aload 10
  putfield cn/domob/android/ads/D$c/f Ljava/lang/String;
  aload 5
  aload_2
  putfield cn/domob/android/ads/D$c/g Ljava/lang/String;
  aload 5
  aload_3
  putfield cn/domob/android/ads/D$c/h Ljava/lang/String;
  aload 4
  aload 5
  invokevirtual cn/domob/android/ads/D/a(Lcn/domob/android/ads/D$c;)V
  return
  nop
.end <method>

.method private static b(Ljava/lang/String;Ljava/lang/String;Landroid/content/Context;Ljava/lang/String;Ljava/lang/String;Ljava/lang/String;)V
.limit locals 20
.limit stack 200
  nop
  ldc cn/domob/android/ads/I
  astore 13
  aload 13
  invokevirtual java/lang/Class/getSimpleName()Ljava/lang/String;
  astore 14
  new java/lang/StringBuilder
  astore 15
  aload 15
  invokespecial java/lang/StringBuilder/<init>()V
  ldc "start udpate url:"
  astore 16
  aload 15
  aload 16
  invokevirtual java/lang/StringBuilder/append(Ljava/lang/String;)Ljava/lang/StringBuilder;
  astore 15
  aload 15
  aload_1
  invokevirtual java/lang/StringBuilder/append(Ljava/lang/String;)Ljava/lang/StringBuilder;
  astore 15
  aload 15
  invokevirtual java/lang/StringBuilder/toString()Ljava/lang/String;
  astore 17
  aload 14
  aload 17
  invokestatic cn/domob/android/ads/J/a(Ljava/lang/String;Ljava/lang/String;)V
  aload_2
  astore 6
  new java/lang/NoClassDefFoundError
  dup
  invokespecial java/lang/NoClassDefFoundError/<init>()V
  athrow
  nop
  new cn/domob/android/ads/I$6
  astore 18
  aload_2
  astore 6
  aload_3
  astore 7
  aload 4
  astore 8
  aload 18
  aload 6
  aload 7
  aload 8
  invokespecial cn/domob/android/ads/I$6/<init>(Landroid/content/Context;Ljava/lang/String;Ljava/lang/String;)V
  iconst_1
  istore 19
  aload_1
  astore 6
  aload_0
  astore 7
  aload 14
  astore 8
  aload_2
  astore 9
  aload 18
  astore 10
  aload 5
  astore 11
  iload 19
  istore 12
  aload 6
  aload 7
  aload 8
  aload 9
  aload 10
  aload 11
  iload 12
  invokestatic cn/domob/android/a/a/a(Ljava/lang/String;Ljava/lang/String;Ljava/lang/String;Landroid/content/Context;Lcn/domob/android/a/c;Ljava/lang/String;Z)V
  return
  nop
.end <method>

.method private static c(Landroid/content/Context;)Landroid/widget/Button;
.limit locals 10
.limit stack 200
  nop
  new java/lang/NoClassDefFoundError
  dup
  invokespecial java/lang/NoClassDefFoundError/<init>()V
  athrow
  aload_1
  aload_0
  invokespecial android/widget/Button/<init>(Landroid/content/Context;)V
  ldc 10.000000
  fstore_2
  aload_1
  fload_2
  invokevirtual android/widget/Button/setTextSize(F)V
  iconst_m1
  istore_3
  aload_1
  iload_3
  invokevirtual android/widget/Button/setTextColor(I)V
  new android/graphics/drawable/GradientDrawable
  astore 4
  getstatic android/graphics/drawable/GradientDrawable$Orientation/BOTTOM_TOP Landroid/graphics/drawable/GradientDrawable$Orientation;
  astore 5
  iconst_2
  istore_3
  iload_3
  newarray int
  astore 6
  iconst_0
  istore_3
  ldc -12303292
  istore 7
  aload 6
  iload_3
  iload 7
  iastore
  iconst_1
  istore_3
  ldc -7829368
  istore 7
  aload 6
  iload_3
  iload 7
  iastore
  aload 4
  aload 5
  aload 6
  invokespecial android/graphics/drawable/GradientDrawable/<init>(Landroid/graphics/drawable/GradientDrawable$Orientation;[I)V
  iconst_1
  istore_3
  ldc -7829368
  istore 7
  aload 4
  iload_3
  iload 7
  invokevirtual android/graphics/drawable/GradientDrawable/setStroke(II)V
  ldc 5.000000
  fstore_2
  aload 4
  fload_2
  invokevirtual android/graphics/drawable/GradientDrawable/setCornerRadius(F)V
  new android/graphics/drawable/GradientDrawable
  astore 8
  getstatic android/graphics/drawable/GradientDrawable$Orientation/TOP_BOTTOM Landroid/graphics/drawable/GradientDrawable$Orientation;
  astore 5
  iconst_2
  istore_3
  iload_3
  newarray int
  astore 6
  iconst_0
  istore_3
  ldc -12303292
  istore 7
  aload 6
  iload_3
  iload 7
  iastore
  iconst_1
  istore_3
  ldc -7829368
  istore 7
  aload 6
  iload_3
  iload 7
  iastore
  aload 8
  aload 5
  aload 6
  invokespecial android/graphics/drawable/GradientDrawable/<init>(Landroid/graphics/drawable/GradientDrawable$Orientation;[I)V
  iconst_1
  istore_3
  ldc -7829368
  istore 7
  aload 8
  iload_3
  iload 7
  invokevirtual android/graphics/drawable/GradientDrawable/setStroke(II)V
  ldc 5.000000
  fstore_2
  aload 8
  fload_2
  invokevirtual android/graphics/drawable/GradientDrawable/setCornerRadius(F)V
  aload_1
  aload 4
  invokevirtual android/widget/Button/setBackgroundDrawable(Landroid/graphics/drawable/Drawable;)V
  new cn/domob/android/ads/I$5
  astore 9
  aload 9
  aload 8
  aload 4
  invokespecial cn/domob/android/ads/I$5/<init>(Landroid/graphics/drawable/GradientDrawable;Landroid/graphics/drawable/GradientDrawable;)V
  aload_1
  aload 9
  invokevirtual android/widget/Button/setOnTouchListener(Landroid/view/View$OnTouchListener;)V
  aload_1
  areturn
  nop
.end <method>

