.source SourceFile
.class  cn/domob/android/ads/u
.super java/lang/Object
.field private static "a" Ljava/lang/String;
.field private static final "f" I =  5
.field private static final "h" I =  10000
.field private "b" Lcn/domob/android/ads/u$b;
.field private "c" Lcn/domob/android/ads/u$a;
.field private "d" Landroid/content/Context;
.field private "e" I
.field private "g" Z

.method static <clinit>()V
.limit locals 1
.limit stack 200
  nop
  ldc "https://api.domob.cn/d"
  astore_0
  aload_0
  putstatic cn/domob/android/ads/u/a Ljava/lang/String;
  return
  nop
.end <method>

.method public <init>(Landroid/content/Context;)V
.limit locals 13
.limit stack 200
  .catch  java/security/GeneralSecurityException <from> Label3 <to> Label1 <using> Label2
  nop
  iconst_0
  istore_2
  aload_0
  invokespecial java/lang/Object/<init>()V
  new cn/domob/android/ads/u$b
  astore_3
  aload_3
  aload_0
  invokespecial cn/domob/android/ads/u$b/<init>(Lcn/domob/android/ads/u;)V
  aload_0
  aload_3
  putfield cn/domob/android/ads/u/b Lcn/domob/android/ads/u$b;
  new cn/domob/android/ads/u$a
  astore 4
  aload 4
  aload_0
  invokespecial cn/domob/android/ads/u$a/<init>(Lcn/domob/android/ads/u;)V
  aload_0
  aload 4
  putfield cn/domob/android/ads/u/c Lcn/domob/android/ads/u$a;
  iconst_0
  istore 6
  iload 6
  istore 5
  aload_0
  iload 5
  putfield cn/domob/android/ads/u/e I
  iconst_0
  istore 6
  aload_0
  iload 6
  putfield cn/domob/android/ads/u/g Z
  aload_0
  aload_1
  putfield cn/domob/android/ads/u/d Landroid/content/Context;
Label3:
  ldc "TLS"
  astore 7
  aload 7
  invokestatic javax/net/ssl/SSLContext/getInstance(Ljava/lang/String;)Ljavax/net/ssl/SSLContext;
  astore_2
  iconst_1
  istore 6
  iload 6
  anewarray javax/net/ssl/X509TrustManager
  astore 8
  aload_0
  getfield cn/domob/android/ads/u/b Lcn/domob/android/ads/u$b;
  astore_3
  iconst_0
  istore 6
  aload 8
  iload 6
  aload_3
  aastore
  new java/security/SecureRandom
  astore 9
  aload 9
  invokespecial java/security/SecureRandom/<init>()V
  aconst_null
  astore 10
  aload_2
  aload 10
  aload 8
  aload 9
  invokevirtual javax/net/ssl/SSLContext/init([Ljavax/net/ssl/KeyManager;[Ljavax/net/ssl/TrustManager;Ljava/security/SecureRandom;)V
Label1:
  new java/lang/NoClassDefFoundError
  dup
  invokespecial java/lang/NoClassDefFoundError/<init>()V
  athrow
  iload_2
  ifeq Label0
  aload_2
  invokevirtual javax/net/ssl/SSLContext/getSocketFactory()Ljavax/net/ssl/SSLSocketFactory;
  astore 11
  aload 11
  invokestatic javax/net/ssl/HttpsURLConnection/setDefaultSSLSocketFactory(Ljavax/net/ssl/SSLSocketFactory;)V
Label0:
  aload_0
  getfield cn/domob/android/ads/u/c Lcn/domob/android/ads/u$a;
  astore 4
  aload 4
  invokestatic javax/net/ssl/HttpsURLConnection/setDefaultHostnameVerifier(Ljavax/net/ssl/HostnameVerifier;)V
  return
Label2:
  astore 12
  aload 12
  invokestatic cn/domob/android/ads/J/a(Ljava/lang/Throwable;)V
  goto Label1
  nop
.end <method>

.method protected a(Ljava/lang/String;)Ljava/lang/String;
.limit locals 3
.limit stack 200
  nop
  iconst_0
  istore_2
  aload_0
  iload_2
  putfield cn/domob/android/ads/u/e I
  iconst_0
  istore_2
  aload_0
  aload_1
  iload_2
  invokespecial cn/domob/android/ads/u/a(Ljava/lang/String;I)Ljava/lang/String;
  astore_1
  aload_1
  areturn
  nop
.end <method>

.method private a(Ljava/lang/String;I)Ljava/lang/String;
.limit locals 70
.limit stack 200
  .catch  java/lang/Throwable <from> Label33 <to> Label34 <using> Label32
  .catch  java/lang/Throwable <from> Label34 <to> Label37 <using> Label32
  .catch  java/io/IOException <from> Label34 <to> Label37 <using> Label35
  .catch  java/net/MalformedURLException <from> Label34 <to> Label37 <using> Label36
  .catch  java/lang/Throwable <from> Label37 <to> Label38 <using> Label32
  .catch  java/lang/Throwable <from> Label38 <to> Label42 <using> Label39
  .catch  java/io/IOException <from> Label38 <to> Label42 <using> Label40
  .catch  java/net/MalformedURLException <from> Label38 <to> Label42 <using> Label41
  .catch  java/lang/Throwable <from> Label46 <to> Label47 <using> Label43
  .catch  java/io/IOException <from> Label46 <to> Label47 <using> Label44
  .catch  java/net/MalformedURLException <from> Label46 <to> Label47 <using> Label45
  .catch  java/lang/Throwable <from> Label51 <to> Label1 <using> Label48
  .catch  java/io/IOException <from> Label51 <to> Label1 <using> Label49
  .catch  java/net/MalformedURLException <from> Label51 <to> Label1 <using> Label50
  .catch  java/lang/Throwable <from> Label55 <to> Label56 <using> Label52
  .catch  java/io/IOException <from> Label55 <to> Label56 <using> Label53
  .catch  java/net/MalformedURLException <from> Label55 <to> Label56 <using> Label54
  .catch  java/lang/Throwable <from> Label29 <to> Label58 <using> Label57
  .catch  java/lang/Throwable <from> Label61 <to> Label62 <using> Label52
  .catch  java/io/IOException <from> Label61 <to> Label62 <using> Label53
  .catch  java/net/MalformedURLException <from> Label61 <to> Label62 <using> Label54
  .catch  java/io/IOException <from> Label64 <to> Label66 <using> Label53
  .catch  java/lang/Throwable <from> Label28 <to> Label15 <using> Label69
  .catch  java/lang/Throwable <from> Label13 <to> Label73 <using> Label69
  nop
  aconst_null
  astore 6
  iload_2
  istore_3
  aload_0
  astore 4
  aload 4
  iload_3
  putfield cn/domob/android/ads/u/e I
  new java/lang/StringBuffer
  astore 7
  aload 7
  astore 8
  ldc ""
  astore 9
  aload 7
  aload 9
  invokespecial java/lang/StringBuffer/<init>(Ljava/lang/String;)V
Label33:
  new java/net/URL
  astore 10
  getstatic cn/domob/android/ads/u/a Ljava/lang/String;
  astore 11
Label34:
  aload 10
  aload 11
  invokespecial java/net/URL/<init>(Ljava/lang/String;)V
  aload 10
  invokevirtual java/net/URL/openConnection()Ljava/net/URLConnection;
  astore 12
Label37:
  aload 12
  astore 14
  aload 14
  checkcast javax/net/ssl/HttpsURLConnection
  astore 14
  aload 14
  astore 13
Label38:
  iconst_1
  istore 15
  aload 13
  iload 15
  invokevirtual javax/net/ssl/HttpsURLConnection/setDoOutput(Z)V
  iconst_0
  istore 15
  aload 13
  iload 15
  invokevirtual javax/net/ssl/HttpsURLConnection/setUseCaches(Z)V
  iconst_1
  istore 15
  aload 13
  iload 15
  invokevirtual javax/net/ssl/HttpsURLConnection/setDoInput(Z)V
  ldc "POST"
  astore 9
  aload 13
  aload 9
  invokevirtual javax/net/ssl/HttpsURLConnection/setRequestMethod(Ljava/lang/String;)V
  ldc "connection"
  astore 9
  ldc "close"
  astore 16
  aload 13
  aload 9
  aload 16
  invokevirtual javax/net/ssl/HttpsURLConnection/setRequestProperty(Ljava/lang/String;Ljava/lang/String;)V
  sipush 10000
  istore 15
  aload 13
  iload 15
  invokevirtual javax/net/ssl/HttpsURLConnection/setConnectTimeout(I)V
  sipush 10000
  istore 15
  aload 13
  iload 15
  invokevirtual javax/net/ssl/HttpsURLConnection/setReadTimeout(I)V
  aload 13
  invokevirtual javax/net/ssl/HttpsURLConnection/getOutputStream()Ljava/io/OutputStream;
  astore 17
Label42:
  aload 17
  astore 18
Label46:
  aload_1
  astore_3
  aload_3
  invokevirtual java/lang/String/getBytes()[B
  astore 19
  aload 17
  checkcast java/io/OutputStream
  astore 17
  aload 19
  astore_3
  aload 17
  aload_3
  invokevirtual java/io/OutputStream/write([B)V
  aload 18
  astore 20
  aload 20
  checkcast java/io/OutputStream
  astore 20
  aload 20
  astore 17
  aload 17
  invokevirtual java/io/OutputStream/flush()V
  aload 18
  astore 21
  aload 21
  checkcast java/io/OutputStream
  astore 21
  aload 21
  astore 17
  aload 17
  invokevirtual java/io/OutputStream/close()V
  aload 13
  invokevirtual javax/net/ssl/HttpsURLConnection/getInputStream()Ljava/io/InputStream;
  astore 22
Label47:
  aload 22
  astore 23
  new java/io/BufferedReader
  astore 24
  aload 24
  astore 25
  new java/io/InputStreamReader
  astore 26
  aload 22
  checkcast java/io/InputStream
  astore 22
Label51:
  aload 26
  astore_3
  aload 22
  astore 4
  aload_3
  aload 4
  invokespecial java/io/InputStreamReader/<init>(Ljava/io/InputStream;)V
  aload 24
  astore_3
  aload 26
  astore 4
  aload_3
  aload 4
  invokespecial java/io/BufferedReader/<init>(Ljava/io/Reader;)V
Label1:
  aload 25
  astore 27
  aload 27
  checkcast java/io/BufferedReader
  astore 27
  aload 27
  astore 24
Label55:
  aload 24
  astore_3
  aload_3
  invokevirtual java/io/BufferedReader/readLine()Ljava/lang/String;
  astore 28
  aload 28
  astore_3
  new java/lang/NoClassDefFoundError
  dup
  invokespecial java/lang/NoClassDefFoundError/<init>()V
  athrow
  iload 28
  ifeq Label0
  aload 28
  astore_3
  aload 8
  aload_3
  invokevirtual java/lang/StringBuffer/append(Ljava/lang/String;)Ljava/lang/StringBuffer;
  pop
Label56:
  goto Label1
Label54:
  astore 29
  aload 23
  astore 6
  aload 13
  astore 30
Label29:
  aload 29
  astore_3
  aload_3
  invokestatic cn/domob/android/ads/J/a(Ljava/lang/Throwable;)V
  aload_0
  astore_3
  aload_3
  getfield cn/domob/android/ads/u/d Landroid/content/Context;
  astore_3
  aload_3
  astore 31
  ldc "Https Get MalformedURLException"
  astore 9
  aload 31
  astore_3
  aload_3
  aload 9
  invokestatic cn/domob/android/ads/J/b(Ljava/lang/Object;Ljava/lang/String;)V
Label58:
  aload 30
  astore_3
  new java/lang/NoClassDefFoundError
  dup
  invokespecial java/lang/NoClassDefFoundError/<init>()V
  athrow
  iload 30
  ifeq Label2
  aload 30
  astore 32
  aload 32
  checkcast javax/net/ssl/HttpsURLConnection
  astore 32
  aload 32
  astore 13
  aload 13
  invokevirtual javax/net/ssl/HttpsURLConnection/disconnect()V
Label2:
  aload 18
  invokestatic app/DummyClass/invokeIfStmt(Ljava/lang/Object;)V
  iload 18
  ifeq Label3
Label60:
  aload 18
  astore 33
  aload 33
  checkcast java/io/OutputStream
  astore 33
  aload 33
  astore 17
  aload 17
  invokevirtual java/io/OutputStream/close()V
Label3:
  aload 6
  invokestatic app/DummyClass/invokeIfStmt(Ljava/lang/Object;)V
  iload 6
  ifeq Label4
  aload 6
  astore 34
  aload 34
  checkcast java/io/InputStream
  astore 34
  aload 34
  astore 22
  aload 22
  astore_3
  aload_3
  invokevirtual java/io/InputStream/close()V
Label4:
  aload 25
  astore_3
  aload_3
  invokestatic app/DummyClass/invokeIfStmt(Ljava/lang/Object;)V
  iload 25
  ifeq Label5
  aload 25
  astore 35
  aload 35
  checkcast java/io/BufferedReader
  astore 35
  aload 35
  astore 24
  aload 24
  astore_3
  aload_3
  invokevirtual java/io/BufferedReader/close()V
Label5:
  aload 8
  invokevirtual java/lang/StringBuffer/toString()Ljava/lang/String;
  astore 28
  aload 28
  areturn
Label0:
  new java/lang/StringBuilder
  astore 36
Label61:
  aload 36
  astore_3
  aload_3
  invokespecial java/lang/StringBuilder/<init>()V
  invokestatic java/lang/Thread/currentThread()Ljava/lang/Thread;
  astore 37
  aload 37
  astore_3
  aload_3
  invokevirtual java/lang/Thread/getName()Ljava/lang/String;
  astore 11
  aload 36
  astore_3
  aload_3
  aload 11
  invokevirtual java/lang/StringBuilder/append(Ljava/lang/String;)Ljava/lang/StringBuilder;
  astore 38
  ldc " "
  astore 9
  aload 38
  astore_3
  aload_3
  aload 9
  invokevirtual java/lang/StringBuilder/append(Ljava/lang/String;)Ljava/lang/StringBuilder;
  astore 38
  aload 13
  invokevirtual javax/net/ssl/HttpsURLConnection/getResponseCode()I
  istore_2
  aload 38
  astore_3
  iload_2
  istore 4
  aload_3
  iload 4
  invokevirtual java/lang/StringBuilder/append(I)Ljava/lang/StringBuilder;
  astore 38
  aload 38
  astore_3
  aload_3
  invokevirtual java/lang/StringBuilder/toString()Ljava/lang/String;
  astore 11
  ldc "inf"
  astore 9
  aload 9
  aload 11
  invokestatic cn/domob/android/ads/J/d(Ljava/lang/Object;Ljava/lang/String;)V
  aload_0
  astore_3
  aload_3
  getfield cn/domob/android/ads/u/e I
  istore_3
  iload_3
  istore_2
  dload_3
  invokestatic app/DummyClass/invokeIfStmt(D)V
  iconst_5
  istore 15
  iload_2
  istore_3
  iload_3
  iload 15
  if_icmpge Label6
  aload 13
  invokevirtual javax/net/ssl/HttpsURLConnection/getResponseCode()I
  istore_2
  iload_2
  istore_3
  dload_3
  invokestatic app/DummyClass/invokeIfStmt(D)V
  iconst_m1
  istore 15
  iload_2
  istore_3
  iload_3
  iload 15
  if_icmpne Label6
  aload_0
  astore_3
  aload_3
  getfield cn/domob/android/ads/u/e I
  istore_3
  iload_3
  istore_2
  iload_2
  iconst_1
  iadd
  istore_2
  iload_2
  istore_3
  aload_0
  astore 4
  aload 4
  iload_3
  putfield cn/domob/android/ads/u/e I
  new java/lang/StringBuilder
  astore 36
  aload 36
  astore_3
  aload_3
  invokespecial java/lang/StringBuilder/<init>()V
  ldc "ResponseCode is -1 retry to connect times="
  astore 9
  aload 36
  astore_3
  aload_3
  aload 9
  invokevirtual java/lang/StringBuilder/append(Ljava/lang/String;)Ljava/lang/StringBuilder;
  astore 38
  aload_0
  astore_3
  aload_3
  getfield cn/domob/android/ads/u/e I
  istore_3
  iload_3
  istore_2
  aload 38
  astore_3
  iload_2
  istore 4
  aload_3
  iload 4
  invokevirtual java/lang/StringBuilder/append(I)Ljava/lang/StringBuilder;
  astore 38
  aload 38
  astore_3
  aload_3
  invokevirtual java/lang/StringBuilder/toString()Ljava/lang/String;
  astore 11
  ldc "inf"
  astore 9
  aload 9
  aload 11
  invokestatic cn/domob/android/ads/J/d(Ljava/lang/Object;Ljava/lang/String;)V
  aload_0
  astore_3
  aload_3
  getfield cn/domob/android/ads/u/e I
  istore_3
  iload_3
  istore_2
  aload_0
  astore_3
  aload_1
  astore 4
  iload_2
  istore 5
  aload_3
  aload 4
  iload 5
  invokespecial cn/domob/android/ads/u/a(Ljava/lang/String;I)Ljava/lang/String;
  astore 28
  aload 28
  astore_3
  aload_3
  invokestatic app/DummyClass/invokeIfStmt(Ljava/lang/Object;)V
  aload 28
  ifnull Label7
  new java/lang/StringBuffer
  astore 39
  aload 39
  astore_3
  aload 28
  astore 4
  aload_3
  aload 4
  invokespecial java/lang/StringBuffer/<init>(Ljava/lang/String;)V
Label62:
  aload 39
  astore 8
Label7:
  aload_0
  astore_3
  aload_3
  getfield cn/domob/android/ads/u/e I
  istore_3
  iload_3
  istore_2
  dload_3
  invokestatic app/DummyClass/invokeIfStmt(D)V
  iconst_5
  istore 15
  iload_2
  istore_3
  iload_3
  iload 15
  if_icmpne Label8
  aload_0
  astore_3
  aload_3
  getfield cn/domob/android/ads/u/g Z
  istore_3
  iload_3
  istore 40
  iload_3
  invokestatic app/DummyClass/invokeIfStmt(Z)V
  iload 40
  ifne Label8
Label64:
  ldc "dd_report_error_01"
  astore 9
  aload_0
  astore_3
  aload_3
  aload 9
  invokespecial cn/domob/android/ads/u/b(Ljava/lang/String;)V
Label66:
  iconst_1
  istore 15
  aload_0
  astore_3
  aload_3
  iload 15
  putfield cn/domob/android/ads/u/g Z
Label8:
  aload 8
  astore 7
Label31:
  aload 13
  invokestatic app/DummyClass/invokeIfStmt(Ljava/lang/Object;)V
  iload 13
  ifeq Label9
  aload 13
  invokevirtual javax/net/ssl/HttpsURLConnection/disconnect()V
Label9:
  aload 18
  invokestatic app/DummyClass/invokeIfStmt(Ljava/lang/Object;)V
  iload 18
  ifeq Label10
Label68:
  aload 18
  astore 41
  aload 41
  checkcast java/io/OutputStream
  astore 41
  aload 41
  astore 17
  aload 17
  invokevirtual java/io/OutputStream/close()V
Label10:
  aload 23
  astore_3
  aload_3
  invokestatic app/DummyClass/invokeIfStmt(Ljava/lang/Object;)V
  iload 23
  ifeq Label11
  aload 23
  astore 42
  aload 42
  checkcast java/io/InputStream
  astore 42
  aload 42
  astore 22
  aload 22
  astore_3
  aload_3
  invokevirtual java/io/InputStream/close()V
Label11:
  aload 25
  astore_3
  aload_3
  invokestatic app/DummyClass/invokeIfStmt(Ljava/lang/Object;)V
  iload 25
  ifeq Label12
  aload 25
  astore 43
  aload 43
  checkcast java/io/BufferedReader
  astore 43
  aload 43
  astore 24
  aload 24
  astore_3
  aload_3
  invokevirtual java/io/BufferedReader/close()V
Label12:
  aload 7
  astore 8
  goto Label5
Label67:
  astore 44
  aload 7
  astore 8
  goto Label5
Label35:
  astore 45
  iconst_0
  istore 25
  iconst_0
  istore 23
  iconst_0
  istore 18
Label28:
  aload_0
  astore_3
  aload_3
  getfield cn/domob/android/ads/u/e I
  istore_3
  iload_3
  istore_2
  new java/lang/NoClassDefFoundError
  dup
  invokespecial java/lang/NoClassDefFoundError/<init>()V
  athrow
  iconst_5
  istore 15
  iload_2
  istore_3
  iload_3
  iload 15
  if_icmpge Label13
  aload_0
  astore_3
  aload_3
  getfield cn/domob/android/ads/u/e I
  istore_3
  iload_3
  istore_2
  iload_2
  iconst_1
  iadd
  istore_2
  iload_2
  istore_3
  aload_0
  astore 4
  aload 4
  iload_3
  putfield cn/domob/android/ads/u/e I
  new java/lang/StringBuilder
  astore 36
  aload 36
  astore_3
  aload_3
  invokespecial java/lang/StringBuilder/<init>()V
  ldc "connect get an IOException retry to connecttimes="
  astore 9
  aload 36
  astore_3
  aload_3
  aload 9
  invokevirtual java/lang/StringBuilder/append(Ljava/lang/String;)Ljava/lang/StringBuilder;
  astore 38
  aload_0
  astore_3
  aload_3
  getfield cn/domob/android/ads/u/e I
  istore_3
  iload_3
  istore_2
  aload 38
  astore_3
  iload_2
  istore 4
  aload_3
  iload 4
  invokevirtual java/lang/StringBuilder/append(I)Ljava/lang/StringBuilder;
  astore 38
  aload 38
  astore_3
  aload_3
  invokevirtual java/lang/StringBuilder/toString()Ljava/lang/String;
  astore 11
  ldc "inf"
  astore 9
  aload 9
  aload 11
  invokestatic cn/domob/android/ads/J/d(Ljava/lang/Object;Ljava/lang/String;)V
  aload_0
  astore_3
  aload_3
  getfield cn/domob/android/ads/u/e I
  istore_3
  iload_3
  istore_2
  aload_0
  astore_3
  aload_1
  astore 4
  iload_2
  istore 5
  aload_3
  aload 4
  iload 5
  invokespecial cn/domob/android/ads/u/a(Ljava/lang/String;I)Ljava/lang/String;
  astore 28
  aload 28
  astore_3
  aload_3
  invokestatic app/DummyClass/invokeIfStmt(Ljava/lang/Object;)V
  aload 28
  ifnull Label14
  new java/lang/StringBuffer
  astore 39
  aload 39
  astore 8
  aload 39
  astore_3
  aload 28
  astore 4
  aload_3
  aload 4
  invokespecial java/lang/StringBuffer/<init>(Ljava/lang/String;)V
Label30:
  aload_0
  astore_3
  aload_3
  getfield cn/domob/android/ads/u/e I
  istore_3
  iload_3
  istore_2
  dload_3
  invokestatic app/DummyClass/invokeIfStmt(D)V
  iconst_5
  istore 15
  iload_2
  istore_3
  iload_3
  iload 15
  if_icmpne Label15
  aload_0
  astore_3
  aload_3
  getfield cn/domob/android/ads/u/g Z
  istore_3
  iload_3
  istore 40
  iload_3
  invokestatic app/DummyClass/invokeIfStmt(Z)V
  iload 40
  ifne Label15
  ldc "dd_report_error_01"
  astore 9
  aload_0
  astore_3
  aload_3
  aload 9
  invokespecial cn/domob/android/ads/u/b(Ljava/lang/String;)V
  iconst_1
  istore 15
  aload_0
  astore_3
  aload_3
  iload 15
  putfield cn/domob/android/ads/u/g Z
Label15:
  aload 6
  invokestatic app/DummyClass/invokeIfStmt(Ljava/lang/Object;)V
  iload 6
  ifeq Label16
  aload 6
  astore 46
  aload 46
  checkcast javax/net/ssl/HttpsURLConnection
  astore 46
  aload 46
  astore 13
  aload 13
  invokevirtual javax/net/ssl/HttpsURLConnection/disconnect()V
Label16:
  aload 18
  invokestatic app/DummyClass/invokeIfStmt(Ljava/lang/Object;)V
  iload 18
  ifeq Label17
Label71:
  aload 18
  astore 47
  aload 47
  checkcast java/io/OutputStream
  astore 47
  aload 47
  astore 17
  aload 17
  invokevirtual java/io/OutputStream/close()V
Label17:
  aload 23
  astore_3
  aload_3
  invokestatic app/DummyClass/invokeIfStmt(Ljava/lang/Object;)V
  iload 23
  ifeq Label18
  aload 23
  astore 48
  aload 48
  checkcast java/io/InputStream
  astore 48
  aload 48
  astore 22
  aload 22
  astore_3
  aload_3
  invokevirtual java/io/InputStream/close()V
Label18:
  aload 25
  astore_3
  aload_3
  invokestatic app/DummyClass/invokeIfStmt(Ljava/lang/Object;)V
  iload 25
  ifeq Label5
  aload 25
  astore 49
  aload 49
  checkcast java/io/BufferedReader
  astore 49
  aload 49
  astore 24
  aload 24
  astore_3
  aload_3
  invokevirtual java/io/BufferedReader/close()V
Label72:
  goto Label5
Label70:
  astore 50
  goto Label5
Label13:
  aload 45
  astore_3
  aload_3
  invokestatic cn/domob/android/ads/J/a(Ljava/lang/Throwable;)V
  aload_0
  astore_3
  aload_3
  getfield cn/domob/android/ads/u/d Landroid/content/Context;
  astore_3
  aload_3
  astore 31
  new java/lang/StringBuilder
  astore 36
  aload 36
  astore_3
  aload_3
  invokespecial java/lang/StringBuilder/<init>()V
  ldc "Https Get IOException "
  astore 9
  aload 36
  astore_3
  aload_3
  aload 9
  invokevirtual java/lang/StringBuilder/append(Ljava/lang/String;)Ljava/lang/StringBuilder;
  astore 38
  aload 45
  astore_3
  aload_3
  invokevirtual java/io/IOException/getMessage()Ljava/lang/String;
  astore 28
  aload 38
  astore_3
  aload 28
  astore 4
  aload_3
  aload 4
  invokevirtual java/lang/StringBuilder/append(Ljava/lang/String;)Ljava/lang/StringBuilder;
  astore 38
  aload 38
  astore_3
  aload_3
  invokevirtual java/lang/StringBuilder/toString()Ljava/lang/String;
  astore 28
  aload 31
  astore_3
  aload 28
  astore 4
  aload_3
  aload 4
  invokestatic cn/domob/android/ads/J/b(Ljava/lang/Object;Ljava/lang/String;)V
  goto Label15
Label32:
  astore 51
  aload 51
  astore 52
  iconst_0
  istore 25
  iconst_0
  istore 23
  iconst_0
  istore 18
Label27:
  aload 52
  astore_3
  aload_3
  invokestatic cn/domob/android/ads/J/a(Ljava/lang/Throwable;)V
Label73:
  new java/lang/NoClassDefFoundError
  dup
  invokespecial java/lang/NoClassDefFoundError/<init>()V
  athrow
  iload 6
  ifeq Label19
  aload 6
  astore 53
  aload 53
  checkcast javax/net/ssl/HttpsURLConnection
  astore 53
  aload 53
  astore 13
  aload 13
  invokevirtual javax/net/ssl/HttpsURLConnection/disconnect()V
Label19:
  aload 18
  invokestatic app/DummyClass/invokeIfStmt(Ljava/lang/Object;)V
  iload 18
  ifeq Label20
Label75:
  aload 18
  astore 54
  aload 54
  checkcast java/io/OutputStream
  astore 54
  aload 54
  astore 17
  aload 17
  invokevirtual java/io/OutputStream/close()V
Label20:
  aload 23
  astore_3
  aload_3
  invokestatic app/DummyClass/invokeIfStmt(Ljava/lang/Object;)V
  iload 23
  ifeq Label21
  aload 23
  astore 55
  aload 55
  checkcast java/io/InputStream
  astore 55
  aload 55
  astore 22
  aload 22
  astore_3
  aload_3
  invokevirtual java/io/InputStream/close()V
Label21:
  aload 25
  astore_3
  aload_3
  invokestatic app/DummyClass/invokeIfStmt(Ljava/lang/Object;)V
  iload 25
  ifeq Label5
  aload 25
  astore 56
  aload 56
  checkcast java/io/BufferedReader
  astore 56
  aload 56
  astore 24
  aload 24
  astore_3
  aload_3
  invokevirtual java/io/BufferedReader/close()V
Label76:
  goto Label5
Label74:
  astore 57
  goto Label5
Label26:
  new java/lang/NoClassDefFoundError
  dup
  invokespecial java/lang/NoClassDefFoundError/<init>()V
  athrow
  iload 6
  ifeq Label22
  aload 6
  astore 58
  aload 58
  checkcast javax/net/ssl/HttpsURLConnection
  astore 58
  aload 58
  astore 13
  aload 13
  invokevirtual javax/net/ssl/HttpsURLConnection/disconnect()V
Label22:
  aload 18
  invokestatic app/DummyClass/invokeIfStmt(Ljava/lang/Object;)V
  iload 18
  ifeq Label23
Label78:
  aload 18
  astore 59
  aload 59
  checkcast java/io/OutputStream
  astore 59
  aload 59
  astore 17
  aload 17
  invokevirtual java/io/OutputStream/close()V
Label23:
  aload 23
  astore_3
  aload_3
  invokestatic app/DummyClass/invokeIfStmt(Ljava/lang/Object;)V
  iload 23
  ifeq Label24
  aload 23
  astore 60
  aload 60
  checkcast java/io/InputStream
  astore 60
  aload 60
  astore 22
  aload 22
  astore_3
  aload_3
  invokevirtual java/io/InputStream/close()V
Label24:
  aload 25
  astore_3
  aload_3
  invokestatic app/DummyClass/invokeIfStmt(Ljava/lang/Object;)V
  iload 25
  ifeq Label25
  aload 25
  astore 61
  aload 61
  checkcast java/io/BufferedReader
  astore 61
  aload 61
  astore 24
  aload 24
  astore_3
  aload_3
  invokevirtual java/io/BufferedReader/close()V
Label25:
  aload 62
  athrow
Label77:
  astore 63
  goto Label25
Label57:
  astore 62
  aload 6
  astore 23
  aload 30
  astore 6
  goto Label26
Label69:
  astore 62
  goto Label26
Label39:
  astore 52
  iconst_0
  istore 25
  iconst_0
  istore 23
  iconst_0
  istore 18
  aload 13
  astore 6
  goto Label27
Label43:
  astore 52
  iconst_0
  istore 25
  iconst_0
  istore 23
  aload 13
  astore 6
  goto Label27
Label48:
  astore 52
  iconst_0
  istore 25
  aload 13
  astore 6
  goto Label27
Label52:
  astore 52
  aload 13
  astore 6
  goto Label27
Label63:
  astore 52
  aload 13
  astore 6
  goto Label27
Label40:
  astore 64
  iconst_0
  istore 25
  iconst_0
  istore 23
  iconst_0
  istore 18
  aload 13
  astore 6
  aload 64
  astore 45
  goto Label28
Label44:
  astore 65
  iconst_0
  istore 25
  iconst_0
  istore 23
  aload 13
  astore 6
  aload 65
  astore 45
  goto Label28
Label49:
  astore 66
  iconst_0
  istore 25
  aload 13
  astore 6
  aload 66
  astore 45
  goto Label28
Label53:
  astore 67
  aload 13
  astore 6
  aload 67
  astore 45
  goto Label28
Label59:
  astore 68
  goto Label5
Label36:
  astore 69
  aload 69
  astore 29
  iconst_0
  istore 18
  aconst_null
  astore 30
  iconst_0
  istore 25
  goto Label29
Label41:
  astore 29
  iconst_0
  istore 18
  aload 13
  astore 30
  iconst_0
  istore 25
  goto Label29
Label45:
  astore 29
  aload 13
  astore 30
  iconst_0
  istore 25
  goto Label29
Label50:
  astore 29
  aload 23
  astore 6
  aload 13
  astore 30
  iconst_0
  istore 25
  goto Label29
Label65:
  astore 29
  aload 23
  astore 6
  aload 13
  astore 30
  goto Label29
Label14:
  goto Label30
Label6:
  aload 8
  astore 7
  goto Label31
  nop
.end <method>

.method private b(Ljava/lang/String;)V
.limit locals 8
.limit stack 200
  nop
  ldc "reportState"
  astore_2
  aload_0
  aload_2
  invokestatic cn/domob/android/ads/J/a(Ljava/lang/Object;Ljava/lang/String;)V
  new cn/domob/android/ads/D
  astore_3
  aload_0
  getfield cn/domob/android/ads/u/d Landroid/content/Context;
  astore 4
  aload_3
  aload 4
  invokespecial cn/domob/android/ads/D/<init>(Landroid/content/Context;)V
  new cn/domob/android/ads/D$c
  astore 5
  aload_3
  invokevirtual java/lang/Object/getClass()Ljava/lang/Class;
  pop
  aload 5
  aload_3
  invokespecial cn/domob/android/ads/D$c/<init>(Lcn/domob/android/ads/D;)V
  aload 5
  aload_1
  putfield cn/domob/android/ads/D$c/b Ljava/lang/String;
  new java/util/ArrayList
  astore 6
  aload 6
  invokespecial java/util/ArrayList/<init>()V
  aload 5
  aload 6
  putfield cn/domob/android/ads/D$c/d Ljava/util/ArrayList;
  iconst_1
  istore 7
  aload 5
  iload 7
  putfield cn/domob/android/ads/D$c/c I
  ldc ""
  astore_2
  aload 5
  aload_2
  putfield cn/domob/android/ads/D$c/e Ljava/lang/String;
  ldc ""
  astore_2
  aload 5
  aload_2
  putfield cn/domob/android/ads/D$c/f Ljava/lang/String;
  aload_3
  aload 5
  invokevirtual cn/domob/android/ads/D/a(Lcn/domob/android/ads/D$c;)V
  return
  nop
.end <method>

