.source SourceFile
.class  cn/domob/android/ads/m
.super java/lang/Object
.field private "a" Landroid/content/Context;

.method public <init>(Landroid/content/Context;)V
.limit locals 2
.limit stack 200
  nop
  aload_0
  invokespecial java/lang/Object/<init>()V
  aload_0
  aload_1
  putfield cn/domob/android/ads/m/a Landroid/content/Context;
  return
  nop
.end <method>

.method static a(Lcn/domob/android/ads/m;)Landroid/content/Context;
  .synthetic
.limit locals 2
.limit stack 200
  nop
  aload_0
  getfield cn/domob/android/ads/m/a Landroid/content/Context;
  astore_1
  aload_1
  areturn
  nop
.end <method>

.method static a(Lcn/domob/android/ads/m;Lorg/json/JSONObject;)Ljava/lang/String;
  .synthetic
.limit locals 3
.limit stack 200
  nop
  aload_0
  aload_1
  invokespecial cn/domob/android/ads/m/a(Lorg/json/JSONObject;)Ljava/lang/String;
  astore_2
  aload_2
  areturn
  nop
.end <method>

.method private a(Lorg/json/JSONObject;)Ljava/lang/String;
.limit locals 8
.limit stack 200
  nop
  new java/util/HashMap
  astore_2
  aload_2
  invokespecial java/util/HashMap/<init>()V
  new java/lang/NoClassDefFoundError
  dup
  invokespecial java/lang/NoClassDefFoundError/<init>()V
  athrow
  iload_1
  ifeq Label0
  aload_1
  invokevirtual org/json/JSONObject/toString()Ljava/lang/String;
  astore_3
  ldc "jstr"
  astore 4
  aload_2
  aload 4
  aload_3
  invokevirtual java/util/HashMap/put(Ljava/lang/Object;Ljava/lang/Object;)Ljava/lang/Object;
  pop
Label0:
  invokestatic cn/domob/android/ads/p/a()Lcn/domob/android/ads/p;
  astore 5
  aload_0
  getfield cn/domob/android/ads/m/a Landroid/content/Context;
  astore 6
  aload 5
  aload 6
  invokevirtual cn/domob/android/ads/p/x(Landroid/content/Context;)Ljava/lang/String;
  astore_3
  aload_3
  invokestatic app/DummyClass/invokeIfStmt(Ljava/lang/Object;)V
  aload_3
  ifnull Label1
  ldc "ua"
  astore 4
  aload_2
  aload 4
  aload_3
  invokevirtual java/util/HashMap/put(Ljava/lang/Object;Ljava/lang/Object;)Ljava/lang/Object;
  pop
Label1:
  invokestatic cn/domob/android/ads/h/a()Lcn/domob/android/ads/h;
  astore 7
  aload_0
  getfield cn/domob/android/ads/m/a Landroid/content/Context;
  astore 6
  aload 7
  aload 6
  invokevirtual cn/domob/android/ads/h/b(Landroid/content/Context;)Ljava/lang/String;
  astore_3
  aload_3
  invokestatic app/DummyClass/invokeIfStmt(Ljava/lang/Object;)V
  aload_3
  ifnull Label2
  ldc "cid"
  astore 4
  aload_2
  aload 4
  aload_3
  invokevirtual java/util/HashMap/put(Ljava/lang/Object;Ljava/lang/Object;)Ljava/lang/Object;
  pop
Label2:
  invokestatic cn/domob/android/ads/p/a()Lcn/domob/android/ads/p;
  astore 5
  aload_0
  getfield cn/domob/android/ads/m/a Landroid/content/Context;
  astore 6
  aload 5
  aload 6
  invokevirtual cn/domob/android/ads/p/d(Landroid/content/Context;)Ljava/lang/String;
  astore_3
  aload_3
  invokestatic app/DummyClass/invokeIfStmt(Ljava/lang/Object;)V
  aload_3
  ifnull Label3
  ldc "idv"
  astore 4
  aload_2
  aload 4
  aload_3
  invokevirtual java/util/HashMap/put(Ljava/lang/Object;Ljava/lang/Object;)Ljava/lang/Object;
  pop
Label3:
  aload_2
  invokestatic cn/domob/android/ads/J/a(Ljava/util/HashMap;)Ljava/lang/String;
  astore_3
  aload_3
  areturn
  nop
.end <method>

.method protected a(Ljava/lang/String;Lorg/json/JSONObject;)V
.limit locals 6
.limit stack 200
  nop
  ldc "Start to report click."
  astore_3
  aload_0
  aload_3
  invokestatic cn/domob/android/ads/J/a(Ljava/lang/Object;Ljava/lang/String;)V
  new java/lang/Thread
  astore 4
  new cn/domob/android/ads/m$1
  astore 5
  aload 5
  aload_0
  aload_2
  aload_1
  invokespecial cn/domob/android/ads/m$1/<init>(Lcn/domob/android/ads/m;Lorg/json/JSONObject;Ljava/lang/String;)V
  aload 4
  aload 5
  invokespecial java/lang/Thread/<init>(Ljava/lang/Runnable;)V
  aload 4
  invokevirtual java/lang/Thread/start()V
  return
  nop
.end <method>

