.source SourceFile
.class  cn/domob/android/ads/j$a
.super java/lang/Object
.field final "a" Lcn/domob/android/ads/j;
.field private "b" Ljava/lang/String;
.field private "c" Ljava/lang/String;
.field private "d" Ljava/lang/String;
.field private "e" Ljava/lang/String;
.field private "f" Ljava/lang/String;
.field private "g" Ljava/lang/String;
.field private "h" Ljava/lang/String;
.field private "i" Z
.field private "j" I
.field private "k" Z
.field private "l" Z
.field private "m" Landroid/content/Intent;
.field private "n" Z
.field private "o" Z

.method protected <init>(Lcn/domob/android/ads/j;Lorg/json/JSONObject;)V
.limit locals 12
.limit stack 200
  nop
  aload_0
  aload_1
  putfield cn/domob/android/ads/j$a/a Lcn/domob/android/ads/j;
  aload_0
  invokespecial java/lang/Object/<init>()V
  iconst_1
  istore_3
  aload_0
  iload_3
  putfield cn/domob/android/ads/j$a/n Z
  iconst_0
  istore_3
  aload_0
  iload_3
  putfield cn/domob/android/ads/j$a/o Z
  ldc "a"
  astore 5
  aconst_null
  astore 6
  aload_2
  aload 5
  aload 6
  invokevirtual org/json/JSONObject/optString(Ljava/lang/String;Ljava/lang/String;)Ljava/lang/String;
  astore 4
  aload_0
  aload 4
  putfield cn/domob/android/ads/j$a/b Ljava/lang/String;
  ldc "d"
  astore 5
  aconst_null
  astore 6
  aload_2
  aload 5
  aload 6
  invokevirtual org/json/JSONObject/optString(Ljava/lang/String;Ljava/lang/String;)Ljava/lang/String;
  astore 4
  aload_0
  aload 4
  putfield cn/domob/android/ads/j$a/c Ljava/lang/String;
  ldc "opentype"
  astore 5
  aconst_null
  astore 6
  aload_2
  aload 5
  aload 6
  invokevirtual org/json/JSONObject/optString(Ljava/lang/String;Ljava/lang/String;)Ljava/lang/String;
  astore 4
  aload_0
  aload 4
  putfield cn/domob/android/ads/j$a/d Ljava/lang/String;
  ldc "loadingtype"
  astore 5
  ldc "0"
  astore 8
  aload_2
  aload 5
  aload 8
  invokevirtual org/json/JSONObject/optString(Ljava/lang/String;Ljava/lang/String;)Ljava/lang/String;
  astore 7
  aload_0
  aload 7
  putfield cn/domob/android/ads/j$a/e Ljava/lang/String;
  ldc "b"
  astore 5
  aconst_null
  astore 6
  aload_2
  aload 5
  aload 6
  invokevirtual org/json/JSONObject/optString(Ljava/lang/String;Ljava/lang/String;)Ljava/lang/String;
  astore 7
  aload_0
  aload 7
  putfield cn/domob/android/ads/j$a/f Ljava/lang/String;
  ldc "s"
  astore 5
  aconst_null
  astore 6
  aload_2
  aload 5
  aload 6
  invokevirtual org/json/JSONObject/optString(Ljava/lang/String;Ljava/lang/String;)Ljava/lang/String;
  astore 7
  aload_0
  aload 7
  putfield cn/domob/android/ads/j$a/g Ljava/lang/String;
  ldc "name"
  astore 5
  ldc ""
  astore 8
  aload_2
  aload 5
  aload 8
  invokevirtual org/json/JSONObject/optString(Ljava/lang/String;Ljava/lang/String;)Ljava/lang/String;
  astore 7
  aload_0
  aload 7
  putfield cn/domob/android/ads/j$a/h Ljava/lang/String;
  ldc "click_confirm"
  astore 5
  iconst_1
  istore_3
  aload_2
  aload 5
  iload_3
  invokevirtual org/json/JSONObject/optBoolean(Ljava/lang/String;Z)Z
  istore 9
  aload_0
  iload 9
  putfield cn/domob/android/ads/j$a/i Z
  iconst_0
  istore_3
  iload_3
  istore 10
  ldc "confirm_type"
  astore 5
  aload_2
  aload 5
  iload 10
  invokevirtual org/json/JSONObject/optInt(Ljava/lang/String;I)I
  istore 10
  aload_0
  iload 10
  putfield cn/domob/android/ads/j$a/j I
  ldc "preload"
  astore 5
  iconst_0
  istore_3
  aload_2
  aload 5
  iload_3
  invokevirtual org/json/JSONObject/optBoolean(Ljava/lang/String;Z)Z
  istore 9
  aload_0
  iload 9
  putfield cn/domob/android/ads/j$a/k Z
  ldc "auto_run"
  astore 5
  iconst_0
  istore_3
  aload_2
  aload 5
  iload_3
  invokevirtual org/json/JSONObject/optBoolean(Ljava/lang/String;Z)Z
  istore 9
  aload_0
  iload 9
  putfield cn/domob/android/ads/j$a/l Z
  ldc "rc"
  astore 5
  iconst_0
  istore_3
  aload_2
  aload 5
  iload_3
  invokevirtual org/json/JSONObject/optBoolean(Ljava/lang/String;Z)Z
  istore 9
  aload_0
  iload 9
  putfield cn/domob/android/ads/j$a/o Z
  aload_0
  invokespecial cn/domob/android/ads/j$a/o()Landroid/content/Intent;
  astore 11
  aload_0
  aload 11
  putfield cn/domob/android/ads/j$a/m Landroid/content/Intent;
  return
  nop
.end <method>

.method private a(Landroid/net/Uri;)Landroid/content/Intent;
.limit locals 22
.limit stack 200
  nop
  aload_0
  astore_2
  aload_2
  getfield cn/domob/android/ads/j$a/a Lcn/domob/android/ads/j;
  astore_3
  aload_2
  astore_0
  new java/lang/StringBuilder
  astore 4
  aload 4
  invokespecial java/lang/StringBuilder/<init>()V
  ldc "Launch App Uri = "
  astore 5
  aload 4
  aload 5
  invokevirtual java/lang/StringBuilder/append(Ljava/lang/String;)Ljava/lang/StringBuilder;
  astore 4
  aload_1
  astore_2
  aload 4
  aload_2
  invokevirtual java/lang/StringBuilder/append(Ljava/lang/Object;)Ljava/lang/StringBuilder;
  astore 4
  aload 4
  invokevirtual java/lang/StringBuilder/toString()Ljava/lang/String;
  astore 6
  aload_3
  aload 6
  invokestatic cn/domob/android/ads/J/a(Ljava/lang/Object;Ljava/lang/String;)V
  ldc "domoblaunchapp"
  astore 6
  aload_1
  astore_2
  new java/lang/NoClassDefFoundError
  dup
  invokespecial java/lang/NoClassDefFoundError/<init>()V
  athrow
  nop
  aload 6
  aload 7
  invokevirtual java/lang/String/equalsIgnoreCase(Ljava/lang/String;)Z
  istore 8
  iload 8
  invokestatic app/DummyClass/invokeIfStmt(Z)V
  iload 8
  ifeq Label0
  aload_1
  astore_2
  aload_2
  invokevirtual android/net/Uri/getHost()Ljava/lang/String;
  astore 7
  aload_1
  astore_2
  aload_2
  invokevirtual android/net/Uri/getPath()Ljava/lang/String;
  astore 9
  aload_1
  astore_2
  aload_2
  invokevirtual android/net/Uri/getQuery()Ljava/lang/String;
  astore 10
  new java/lang/StringBuilder
  astore 4
  aload 4
  invokespecial java/lang/StringBuilder/<init>()V
  ldc "pkgName: "
  astore 5
  aload 4
  aload 5
  invokevirtual java/lang/StringBuilder/append(Ljava/lang/String;)Ljava/lang/StringBuilder;
  astore 4
  aload 4
  aload 7
  invokevirtual java/lang/StringBuilder/append(Ljava/lang/String;)Ljava/lang/StringBuilder;
  astore 4
  ldc "activityName: "
  astore 5
  aload 4
  aload 5
  invokevirtual java/lang/StringBuilder/append(Ljava/lang/String;)Ljava/lang/StringBuilder;
  astore 4
  aload 4
  aload 9
  invokevirtual java/lang/StringBuilder/append(Ljava/lang/String;)Ljava/lang/StringBuilder;
  astore 4
  ldc "queryParams: "
  astore 5
  aload 4
  aload 5
  invokevirtual java/lang/StringBuilder/append(Ljava/lang/String;)Ljava/lang/StringBuilder;
  astore 4
  aload 4
  aload 10
  invokevirtual java/lang/StringBuilder/append(Ljava/lang/String;)Ljava/lang/StringBuilder;
  astore 4
  aload 4
  invokevirtual java/lang/StringBuilder/toString()Ljava/lang/String;
  astore 6
  aload_0
  astore_2
  aload_2
  aload 6
  invokestatic cn/domob/android/ads/J/d(Ljava/lang/Object;Ljava/lang/String;)V
  aload 7
  invokestatic app/DummyClass/invokeIfStmt(Ljava/lang/Object;)V
  aload 7
  ifnull Label1
  ldc ""
  astore 5
  aload 7
  aload 5
  invokevirtual java/lang/String/equals(Ljava/lang/Object;)Z
  istore 8
  iload 8
  invokestatic app/DummyClass/invokeIfStmt(Z)V
  iload 8
  ifne Label1
  aload 9
  invokestatic app/DummyClass/invokeIfStmt(Ljava/lang/Object;)V
  aload 9
  ifnull Label2
  ldc ""
  astore 5
  aload 9
  aload 5
  invokevirtual java/lang/String/equals(Ljava/lang/Object;)Z
  istore 8
  iload 8
  invokestatic app/DummyClass/invokeIfStmt(Z)V
  iload 8
  ifne Label2
  aload_0
  astore_2
  aload_2
  getfield cn/domob/android/ads/j$a/a Lcn/domob/android/ads/j;
  astore_3
  aload_2
  astore_0
  ldc "Activity is not null"
  astore 5
  aload_3
  aload 5
  invokestatic cn/domob/android/ads/J/d(Ljava/lang/Object;Ljava/lang/String;)V
  iconst_1
  istore 11
  aload 9
  iload 11
  invokevirtual java/lang/String/substring(I)Ljava/lang/String;
  astore 9
  new android/content/Intent
  astore 12
  aload 12
  invokespecial android/content/Intent/<init>()V
  new android/content/ComponentName
  astore 13
  aload 13
  aload 7
  aload 9
  invokespecial android/content/ComponentName/<init>(Ljava/lang/String;Ljava/lang/String;)V
  aload 12
  aload 13
  invokevirtual android/content/Intent/setComponent(Landroid/content/ComponentName;)Landroid/content/Intent;
  pop
Label5:
  aload 10
  invokestatic app/DummyClass/invokeIfStmt(Ljava/lang/Object;)V
  aload 10
  ifnull Label3
  ldc ""
  astore 5
  aload 10
  aload 5
  invokevirtual java/lang/String/equals(Ljava/lang/Object;)Z
  istore 8
  iload 8
  invokestatic app/DummyClass/invokeIfStmt(Z)V
  iload 8
  ifne Label3
  aload_0
  astore_2
  aload_2
  getfield cn/domob/android/ads/j$a/a Lcn/domob/android/ads/j;
  astore_3
  aload_2
  astore_0
  new java/lang/StringBuilder
  astore 4
  aload 4
  invokespecial java/lang/StringBuilder/<init>()V
  ldc "QueryParams : "
  astore 5
  aload 4
  aload 5
  invokevirtual java/lang/StringBuilder/append(Ljava/lang/String;)Ljava/lang/StringBuilder;
  astore 4
  aload 4
  aload 10
  invokevirtual java/lang/StringBuilder/append(Ljava/lang/String;)Ljava/lang/StringBuilder;
  astore 4
  aload 4
  invokevirtual java/lang/StringBuilder/toString()Ljava/lang/String;
  astore 9
  aload_3
  aload 9
  invokestatic cn/domob/android/ads/J/a(Ljava/lang/Object;Ljava/lang/String;)V
  ldc "&"
  astore 5
  aload 10
  aload 5
  invokevirtual java/lang/String/split(Ljava/lang/String;)[Ljava/lang/String;
  astore 14
  aload 14
  arraylength
  istore 15
  iconst_0
  dstore 11
  dload 11
  dstore 16
Label4:
  dload 16
  invokestatic app/DummyClass/invokeIfStmt(D)V
  dload 15
  invokestatic app/DummyClass/invokeIfStmt(D)V
  iload 16
  iload 15
  if_icmpge Label3
  aload 14
  iload 16
  aaload
  astore 10
  ldc "="
  astore 5
  aload 10
  aload 5
  invokevirtual java/lang/String/split(Ljava/lang/String;)[Ljava/lang/String;
  astore 17
  iconst_0
  istore 11
  iload 11
  istore 18
  aload 17
  iload 18
  aaload
  astore 10
  iconst_1
  istore 11
  aload 17
  iload 11
  aaload
  astore 9
  aload 12
  aload 10
  aload 9
  invokevirtual android/content/Intent/putExtra(Ljava/lang/String;Ljava/lang/String;)Landroid/content/Intent;
  pop
  iload 16
  iconst_1
  iadd
  istore 16
  goto Label4
Label2:
  aload_0
  astore_2
  aload_2
  getfield cn/domob/android/ads/j$a/a Lcn/domob/android/ads/j;
  astore_3
  aload_2
  astore_0
  ldc "Activity is null"
  astore 5
  aload_3
  aload 5
  invokestatic cn/domob/android/ads/J/d(Ljava/lang/Object;Ljava/lang/String;)V
  aload_0
  astore_2
  aload_2
  getfield cn/domob/android/ads/j$a/a Lcn/domob/android/ads/j;
  astore_3
  aload_2
  astore_0
  aload_3
  invokestatic cn/domob/android/ads/j/a(Lcn/domob/android/ads/j;)Landroid/content/Context;
  astore 19
  aload 19
  astore_2
  aload_2
  invokevirtual android/content/Context/getPackageManager()Landroid/content/pm/PackageManager;
  astore 20
  aload 20
  astore_2
  aload_2
  aload 7
  invokevirtual android/content/pm/PackageManager/getLaunchIntentForPackage(Ljava/lang/String;)Landroid/content/Intent;
  astore 12
  aload 12
  invokestatic app/DummyClass/invokeIfStmt(Ljava/lang/Object;)V
  aload 12
  ifnull Label5
  ldc 268435456
  istore 11
  aload 12
  iload 11
  invokevirtual android/content/Intent/setFlags(I)Landroid/content/Intent;
  pop
  goto Label5
Label1:
  aload_0
  astore_2
  aload_2
  getfield cn/domob/android/ads/j$a/a Lcn/domob/android/ads/j;
  astore_3
  aload_2
  astore_0
  ldc "Package name is null or empty."
  astore 5
  aload_3
  aload 5
  invokestatic cn/domob/android/ads/J/b(Ljava/lang/Object;Ljava/lang/String;)V
  aconst_null
  astore 12
Label7:
  aload 12
  areturn
Label0:
  new android/content/Intent
  astore 12
  ldc "android.intent.action.VIEW"
  astore 5
  aload_1
  astore_2
  aload 12
  aload 5
  aload_2
  invokespecial android/content/Intent/<init>(Ljava/lang/String;Landroid/net/Uri;)V
Label3:
  aload 12
  invokestatic app/DummyClass/invokeIfStmt(Ljava/lang/Object;)V
  aload 12
  ifnull Label6
  aload_0
  astore_2
  aload_2
  getfield cn/domob/android/ads/j$a/a Lcn/domob/android/ads/j;
  astore_3
  aload_2
  astore_0
  aload_3
  invokestatic cn/domob/android/ads/j/a(Lcn/domob/android/ads/j;)Landroid/content/Context;
  astore 19
  aload 19
  astore_2
  aload_2
  invokevirtual android/content/Context/getPackageManager()Landroid/content/pm/PackageManager;
  astore 20
  ldc 65536
  istore 11
  aload 20
  astore_2
  aload_2
  aload 12
  iload 11
  invokevirtual android/content/pm/PackageManager/resolveActivity(Landroid/content/Intent;I)Landroid/content/pm/ResolveInfo;
  astore 21
  aload 21
  astore_2
  aload_2
  invokestatic app/DummyClass/invokeIfStmt(Ljava/lang/Object;)V
  aload 21
  ifnonnull Label7
Label6:
  iconst_0
  istore 11
  aload_0
  astore_2
  aload_2
  iload 11
  putfield cn/domob/android/ads/j$a/n Z
  aload 12
  areturn
  nop
.end <method>

.method protected a()Ljava/lang/String;
.limit locals 2
.limit stack 200
  nop
  aload_0
  getfield cn/domob/android/ads/j$a/b Ljava/lang/String;
  astore_1
  aload_1
  areturn
  nop
.end <method>

.method protected b()Ljava/lang/String;
.limit locals 2
.limit stack 200
  nop
  aload_0
  getfield cn/domob/android/ads/j$a/c Ljava/lang/String;
  astore_1
  aload_1
  areturn
  nop
.end <method>

.method protected c()Ljava/lang/String;
.limit locals 2
.limit stack 200
  nop
  aload_0
  getfield cn/domob/android/ads/j$a/d Ljava/lang/String;
  astore_1
  aload_1
  areturn
  nop
.end <method>

.method protected d()Ljava/lang/String;
.limit locals 2
.limit stack 200
  nop
  aload_0
  getfield cn/domob/android/ads/j$a/e Ljava/lang/String;
  astore_1
  aload_1
  areturn
  nop
.end <method>

.method protected e()Ljava/lang/String;
.limit locals 2
.limit stack 200
  nop
  aload_0
  getfield cn/domob/android/ads/j$a/f Ljava/lang/String;
  astore_1
  aload_1
  areturn
  nop
.end <method>

.method protected f()Ljava/lang/String;
.limit locals 2
.limit stack 200
  nop
  aload_0
  getfield cn/domob/android/ads/j$a/g Ljava/lang/String;
  astore_1
  aload_1
  areturn
  nop
.end <method>

.method protected g()Ljava/lang/String;
.limit locals 2
.limit stack 200
  nop
  aload_0
  getfield cn/domob/android/ads/j$a/h Ljava/lang/String;
  astore_1
  aload_1
  areturn
  nop
.end <method>

.method protected h()Z
.limit locals 2
.limit stack 200
  nop
  aload_0
  getfield cn/domob/android/ads/j$a/i Z
  istore_1
  iload_1
  ireturn
  nop
.end <method>

.method protected i()I
.limit locals 2
.limit stack 200
  nop
  aload_0
  getfield cn/domob/android/ads/j$a/j I
  istore_1
  iload_1
  ireturn
  nop
.end <method>

.method protected j()Z
.limit locals 2
.limit stack 200
  nop
  aload_0
  getfield cn/domob/android/ads/j$a/k Z
  istore_1
  iload_1
  ireturn
  nop
.end <method>

.method protected k()Z
.limit locals 2
.limit stack 200
  nop
  aload_0
  getfield cn/domob/android/ads/j$a/l Z
  istore_1
  iload_1
  ireturn
  nop
.end <method>

.method protected l()Landroid/content/Intent;
.limit locals 2
.limit stack 200
  nop
  aload_0
  getfield cn/domob/android/ads/j$a/m Landroid/content/Intent;
  astore_1
  aload_1
  areturn
  nop
.end <method>

.method protected m()Z
.limit locals 2
.limit stack 200
  nop
  aload_0
  getfield cn/domob/android/ads/j$a/n Z
  istore_1
  iload_1
  ireturn
  nop
.end <method>

.method protected n()Z
.limit locals 2
.limit stack 200
  nop
  aload_0
  getfield cn/domob/android/ads/j$a/o Z
  istore_1
  iload_1
  ireturn
  nop
.end <method>

.method private o()Landroid/content/Intent;
.limit locals 21
.limit stack 200
  nop
  iconst_0
  istore_2
  aload_0
  astore_1
  aload_1
  getfield cn/domob/android/ads/j$a/b Ljava/lang/String;
  astore_3
  new java/lang/NoClassDefFoundError
  dup
  invokespecial java/lang/NoClassDefFoundError/<init>()V
  athrow
  iload_3
  ifne Label0
  aload_0
  astore_1
  aload_1
  getfield cn/domob/android/ads/j$a/a Lcn/domob/android/ads/j;
  astore 4
  ldc "Invalid action type!"
  astore 5
  aload 4
  aload 5
  invokestatic cn/domob/android/ads/J/b(Ljava/lang/Object;Ljava/lang/String;)V
Label13:
  aload_2
  areturn
Label0:
  getstatic cn/domob/android/ads/j$1/a [I
  astore 6
  aload_0
  astore_1
  aload_1
  getfield cn/domob/android/ads/j$a/b Ljava/lang/String;
  astore_3
  aload_3
  invokestatic cn/domob/android/ads/j$b/a(Ljava/lang/String;)Lcn/domob/android/ads/j$b;
  astore 7
  aload 7
  invokevirtual cn/domob/android/ads/j$b/ordinal()I
  istore 8
  aload 6
  iload 8
  iaload
  istore 8
  dload 8
  invokestatic app/DummyClass/invokeIfStmt(D)V
  iload 8
  lookupswitch
  1 : Label2
  2 : Label3
  3 : Label4
  4 : Label5
  5 : Label5
  6 : Label6
  7 : Label7
  8 : Label7
  9 : Label8
  default : Label1
Label1:
  goto Label9
Label9:
  aload_0
  astore_1
  aload_1
  getfield cn/domob/android/ads/j$a/a Lcn/domob/android/ads/j;
  astore 4
  ldc "Unknown action type!"
  astore 5
  aload 4
  aload 5
  invokestatic cn/domob/android/ads/J/b(Ljava/lang/Object;Ljava/lang/String;)V
  aconst_null
  astore 9
  aload 9
  areturn
Label2:
  aload_0
  astore_1
  aload_1
  getfield cn/domob/android/ads/j$a/c Ljava/lang/String;
  astore_3
  aload_3
  invokestatic app/DummyClass/invokeIfStmt(Ljava/lang/Object;)V
  aload_3
  ifnonnull Label10
  aload_0
  astore_1
  aload_1
  getfield cn/domob/android/ads/j$a/a Lcn/domob/android/ads/j;
  astore 4
  ldc "Map data is null!"
  astore 5
  aload 4
  aload 5
  invokestatic cn/domob/android/ads/J/b(Ljava/lang/Object;Ljava/lang/String;)V
  aconst_null
  astore 9
  aload 9
  areturn
Label10:
  new java/lang/StringBuilder
  astore 10
  aload 10
  invokespecial java/lang/StringBuilder/<init>()V
  ldc "geo:"
  astore 5
  aload 10
  aload 5
  invokevirtual java/lang/StringBuilder/append(Ljava/lang/String;)Ljava/lang/StringBuilder;
  astore 11
  aload_0
  astore_1
  aload_1
  getfield cn/domob/android/ads/j$a/c Ljava/lang/String;
  astore_3
  aload 11
  aload_3
  invokevirtual java/lang/StringBuilder/append(Ljava/lang/String;)Ljava/lang/StringBuilder;
  astore 11
  ldc "android.intent.action.VIEW"
  astore 12
  aload 11
  invokevirtual java/lang/StringBuilder/toString()Ljava/lang/String;
  astore 13
  aconst_null
  astore 14
Label15:
  aload 13
  invokestatic android/net/Uri/parse(Ljava/lang/String;)Landroid/net/Uri;
  astore 15
  aload 15
  invokestatic app/DummyClass/invokeIfStmt(Ljava/lang/Object;)V
  aload 15
  ifnull Label11
  aload_0
  astore_1
  aload_1
  getfield cn/domob/android/ads/j$a/a Lcn/domob/android/ads/j;
  astore 4
  new java/lang/StringBuilder
  astore 10
  aload 10
  invokespecial java/lang/StringBuilder/<init>()V
  ldc "Intent uri:"
  astore 5
  aload 10
  aload 5
  invokevirtual java/lang/StringBuilder/append(Ljava/lang/String;)Ljava/lang/StringBuilder;
  astore 11
  aload 15
  invokevirtual android/net/Uri/toString()Ljava/lang/String;
  astore 13
  aload 11
  aload 13
  invokevirtual java/lang/StringBuilder/append(Ljava/lang/String;)Ljava/lang/StringBuilder;
  astore 11
  aload 11
  invokevirtual java/lang/StringBuilder/toString()Ljava/lang/String;
  astore 13
  aload 4
  aload 13
  invokestatic cn/domob/android/ads/J/a(Ljava/lang/Object;Ljava/lang/String;)V
  new android/content/Intent
  astore 16
  aload 16
  astore_2
  aload 12
  astore 17
  aload 17
  checkcast java/lang/String
  astore 17
  aload 17
  astore 13
  aload 16
  aload 13
  aload 15
  invokespecial android/content/Intent/<init>(Ljava/lang/String;Landroid/net/Uri;)V
  ldc 268435456
  istore 18
  iload 18
  istore_1
  aload 16
  iload_1
  invokevirtual android/content/Intent/addFlags(I)Landroid/content/Intent;
  pop
  aload_0
  astore_1
  aload_1
  getfield cn/domob/android/ads/j$a/f Ljava/lang/String;
  astore 13
  aload 13
  invokestatic app/DummyClass/invokeIfStmt(Ljava/lang/Object;)V
  aload 13
  ifnull Label12
  aload 14
  invokestatic app/DummyClass/invokeIfStmt(Ljava/lang/Object;)V
  aload 14
  ifnull Label12
  aload_0
  astore_1
  aload_1
  getfield cn/domob/android/ads/j$a/f Ljava/lang/String;
  astore 13
  aload 14
  astore 19
  aload 19
  checkcast java/lang/String
  astore 19
  aload 19
  astore_3
  aload 16
  aload_3
  aload 13
  invokevirtual android/content/Intent/putExtra(Ljava/lang/String;Ljava/lang/String;)Landroid/content/Intent;
  pop
Label12:
  aload_0
  astore_1
  aload_1
  getfield cn/domob/android/ads/j$a/g Ljava/lang/String;
  astore 13
  aload 13
  invokestatic app/DummyClass/invokeIfStmt(Ljava/lang/Object;)V
  aload 13
  ifnull Label13
  aload_0
  astore_1
  aload_1
  getfield cn/domob/android/ads/j$a/b Ljava/lang/String;
  astore 13
  getstatic cn/domob/android/ads/j$b/e Lcn/domob/android/ads/j$b;
  astore 7
  aload 7
  invokevirtual cn/domob/android/ads/j$b/a()Ljava/lang/String;
  astore_3
  aload 13
  aload_3
  invokevirtual java/lang/String/equals(Ljava/lang/Object;)Z
  istore 20
  iload 20
  istore_1
  iload_1
  invokestatic app/DummyClass/invokeIfStmt(Z)V
  iload 20
  ifeq Label13
  aload_0
  astore_1
  aload_1
  getfield cn/domob/android/ads/j$a/g Ljava/lang/String;
  astore_3
  ldc "android.intent.extra.SUBJECT"
  astore 5
  aload 16
  aload 5
  aload_3
  invokevirtual android/content/Intent/putExtra(Ljava/lang/String;Ljava/lang/String;)Landroid/content/Intent;
  pop
  aload 16
  areturn
Label3:
  ldc "android.intent.action.SENDTO"
  astore 12
  aload_0
  astore_1
  aload_1
  getfield cn/domob/android/ads/j$a/c Ljava/lang/String;
  astore 13
  aload 13
  invokestatic app/DummyClass/invokeIfStmt(Ljava/lang/Object;)V
  aload 13
  ifnonnull Label14
  aload_0
  astore_1
  aload_1
  getfield cn/domob/android/ads/j$a/a Lcn/domob/android/ads/j;
  astore 4
  ldc "SMS destination is null!"
  astore 5
  aload 4
  aload 5
  invokestatic cn/domob/android/ads/J/b(Ljava/lang/Object;Ljava/lang/String;)V
  aconst_null
  astore 9
  aload 9
  areturn
Label14:
  new java/lang/StringBuilder
  astore 10
  aload 10
  invokespecial java/lang/StringBuilder/<init>()V
  ldc "smsto:"
  astore 5
  aload 10
  aload 5
  invokevirtual java/lang/StringBuilder/append(Ljava/lang/String;)Ljava/lang/StringBuilder;
  astore 11
  aload_0
  astore_1
  aload_1
  getfield cn/domob/android/ads/j$a/c Ljava/lang/String;
  astore 13
  aload 11
  aload 13
  invokevirtual java/lang/StringBuilder/append(Ljava/lang/String;)Ljava/lang/StringBuilder;
  astore 11
  aload 11
  invokevirtual java/lang/StringBuilder/toString()Ljava/lang/String;
  astore 13
  ldc "sms_body"
  astore 14
  goto Label15
Label4:
  ldc "android.intent.action.SENDTO"
  astore 12
  aload_0
  astore_1
  aload_1
  getfield cn/domob/android/ads/j$a/c Ljava/lang/String;
  astore 13
  aload 13
  invokestatic app/DummyClass/invokeIfStmt(Ljava/lang/Object;)V
  aload 13
  ifnonnull Label16
  aload_0
  astore_1
  aload_1
  getfield cn/domob/android/ads/j$a/a Lcn/domob/android/ads/j;
  astore 4
  ldc "Mail destination is null!"
  astore 5
  aload 4
  aload 5
  invokestatic cn/domob/android/ads/J/b(Ljava/lang/Object;Ljava/lang/String;)V
  aconst_null
  astore 9
  aload 9
  areturn
Label16:
  new java/lang/StringBuilder
  astore 10
  aload 10
  invokespecial java/lang/StringBuilder/<init>()V
  ldc "mailto"
  astore 5
  aload 10
  aload 5
  invokevirtual java/lang/StringBuilder/append(Ljava/lang/String;)Ljava/lang/StringBuilder;
  astore 11
  aload_0
  astore_1
  aload_1
  getfield cn/domob/android/ads/j$a/c Ljava/lang/String;
  astore 13
  aload 11
  aload 13
  invokevirtual java/lang/StringBuilder/append(Ljava/lang/String;)Ljava/lang/StringBuilder;
  astore 11
  aload 11
  invokevirtual java/lang/StringBuilder/toString()Ljava/lang/String;
  astore 13
  ldc "android.intent.extra.TEXT"
  astore 14
  goto Label15
Label5:
  aload_0
  astore_1
  aload_1
  getfield cn/domob/android/ads/j$a/c Ljava/lang/String;
  astore_3
  aload_3
  invokestatic app/DummyClass/invokeIfStmt(Ljava/lang/Object;)V
  aload_3
  ifnonnull Label17
  aload_0
  astore_1
  aload_1
  getfield cn/domob/android/ads/j$a/a Lcn/domob/android/ads/j;
  astore 4
  ldc "URL is null!"
  astore 5
  aload 4
  aload 5
  invokestatic cn/domob/android/ads/J/b(Ljava/lang/Object;Ljava/lang/String;)V
  aconst_null
  astore 9
  aload 9
  areturn
Label17:
  ldc "android.intent.action.VIEW"
  astore 12
  aload_0
  astore_1
  aload_1
  getfield cn/domob/android/ads/j$a/c Ljava/lang/String;
  astore 13
  aconst_null
  astore 14
  goto Label15
Label6:
  aload_0
  astore_1
  aload_1
  getfield cn/domob/android/ads/j$a/c Ljava/lang/String;
  astore_3
  aload_3
  invokestatic app/DummyClass/invokeIfStmt(Ljava/lang/Object;)V
  aload_3
  ifnonnull Label18
  aload_0
  astore_1
  aload_1
  getfield cn/domob/android/ads/j$a/a Lcn/domob/android/ads/j;
  astore 4
  ldc "TEL number is null!"
  astore 5
  aload 4
  aload 5
  invokestatic cn/domob/android/ads/J/b(Ljava/lang/Object;Ljava/lang/String;)V
  aconst_null
  astore 9
  aload 9
  areturn
Label18:
  new java/lang/StringBuilder
  astore 10
  aload 10
  invokespecial java/lang/StringBuilder/<init>()V
  ldc "tel:"
  astore 5
  aload 10
  aload 5
  invokevirtual java/lang/StringBuilder/append(Ljava/lang/String;)Ljava/lang/StringBuilder;
  astore 11
  aload_0
  astore_1
  aload_1
  getfield cn/domob/android/ads/j$a/c Ljava/lang/String;
  astore_3
  aload 11
  aload_3
  invokevirtual java/lang/StringBuilder/append(Ljava/lang/String;)Ljava/lang/StringBuilder;
  astore 11
  ldc "android.intent.action.DIAL"
  astore 12
  aload 11
  invokevirtual java/lang/StringBuilder/toString()Ljava/lang/String;
  astore 13
  aconst_null
  astore 14
  goto Label15
Label7:
  aload_0
  astore_1
  aload_1
  getfield cn/domob/android/ads/j$a/c Ljava/lang/String;
  astore_3
  aload_3
  invokestatic app/DummyClass/invokeIfStmt(Ljava/lang/Object;)V
  aload_3
  ifnonnull Label19
  aload_0
  astore_1
  aload_1
  getfield cn/domob/android/ads/j$a/a Lcn/domob/android/ads/j;
  astore 4
  ldc "URL is null!"
  astore 5
  aload 4
  aload 5
  invokestatic cn/domob/android/ads/J/b(Ljava/lang/Object;Ljava/lang/String;)V
  aconst_null
  astore 9
  aload 9
  areturn
Label19:
  ldc "android.intent.action.VIEW"
  astore 12
  aload_0
  astore_1
  aload_1
  getfield cn/domob/android/ads/j$a/c Ljava/lang/String;
  astore 13
  aconst_null
  astore 14
  goto Label15
Label8:
  aload_0
  astore_1
  aload_1
  getfield cn/domob/android/ads/j$a/c Ljava/lang/String;
  astore 13
  aload 13
  invokestatic app/DummyClass/invokeIfStmt(Ljava/lang/Object;)V
  aload 13
  ifnonnull Label20
  aload_0
  astore_1
  aload_1
  getfield cn/domob/android/ads/j$a/a Lcn/domob/android/ads/j;
  astore 4
  ldc "URL is null!"
  astore 5
  aload 4
  aload 5
  invokestatic cn/domob/android/ads/J/b(Ljava/lang/Object;Ljava/lang/String;)V
  aconst_null
  astore 9
  aload 9
  areturn
Label20:
  aload_0
  astore_1
  aload_1
  getfield cn/domob/android/ads/j$a/c Ljava/lang/String;
  astore 13
  aload 13
  invokestatic android/net/Uri/parse(Ljava/lang/String;)Landroid/net/Uri;
  astore 15
  aload 15
  invokestatic app/DummyClass/invokeIfStmt(Ljava/lang/Object;)V
  aload 15
  ifnull Label21
  aload_0
  astore_1
  aload_1
  aload 15
  invokespecial cn/domob/android/ads/j$a/a(Landroid/net/Uri;)Landroid/content/Intent;
  astore_2
  aload_2
  areturn
Label11:
  aload_0
  astore_1
  aload_1
  getfield cn/domob/android/ads/j$a/a Lcn/domob/android/ads/j;
  astore 4
  ldc "Intent uri is null"
  astore 5
  aload 4
  aload 5
  invokestatic cn/domob/android/ads/J/b(Ljava/lang/Object;Ljava/lang/String;)V
  aconst_null
  astore 9
  aload 9
  areturn
Label21:
  aconst_null
  astore 12
  aconst_null
  astore 14
  goto Label15
  nop
  nop
  nop
.end <method>

.method public toString()Ljava/lang/String;
.limit locals 7
.limit stack 200
  nop
  new java/lang/StringBuilder
  astore_1
  aload_1
  invokespecial java/lang/StringBuilder/<init>()V
  ldc "Action [actionType="
  astore_3
  aload_1
  aload_3
  invokevirtual java/lang/StringBuilder/append(Ljava/lang/String;)Ljava/lang/StringBuilder;
  astore_2
  aload_0
  getfield cn/domob/android/ads/j$a/b Ljava/lang/String;
  astore 4
  aload_2
  aload 4
  invokevirtual java/lang/StringBuilder/append(Ljava/lang/String;)Ljava/lang/StringBuilder;
  astore_2
  ldc ", destination="
  astore_3
  aload_2
  aload_3
  invokevirtual java/lang/StringBuilder/append(Ljava/lang/String;)Ljava/lang/StringBuilder;
  astore_2
  aload_0
  getfield cn/domob/android/ads/j$a/c Ljava/lang/String;
  astore 4
  aload_2
  aload 4
  invokevirtual java/lang/StringBuilder/append(Ljava/lang/String;)Ljava/lang/StringBuilder;
  astore_2
  ldc ", openType="
  astore_3
  aload_2
  aload_3
  invokevirtual java/lang/StringBuilder/append(Ljava/lang/String;)Ljava/lang/StringBuilder;
  astore_2
  aload_0
  getfield cn/domob/android/ads/j$a/d Ljava/lang/String;
  astore 4
  aload_2
  aload 4
  invokevirtual java/lang/StringBuilder/append(Ljava/lang/String;)Ljava/lang/StringBuilder;
  astore_2
  ldc ", loadingType="
  astore_3
  aload_2
  aload_3
  invokevirtual java/lang/StringBuilder/append(Ljava/lang/String;)Ljava/lang/StringBuilder;
  astore_2
  aload_0
  getfield cn/domob/android/ads/j$a/e Ljava/lang/String;
  astore 4
  aload_2
  aload 4
  invokevirtual java/lang/StringBuilder/append(Ljava/lang/String;)Ljava/lang/StringBuilder;
  astore_2
  ldc ", body="
  astore_3
  aload_2
  aload_3
  invokevirtual java/lang/StringBuilder/append(Ljava/lang/String;)Ljava/lang/StringBuilder;
  astore_2
  aload_0
  getfield cn/domob/android/ads/j$a/f Ljava/lang/String;
  astore 4
  aload_2
  aload 4
  invokevirtual java/lang/StringBuilder/append(Ljava/lang/String;)Ljava/lang/StringBuilder;
  astore_2
  ldc ", subject="
  astore_3
  aload_2
  aload_3
  invokevirtual java/lang/StringBuilder/append(Ljava/lang/String;)Ljava/lang/StringBuilder;
  astore_2
  aload_0
  getfield cn/domob/android/ads/j$a/g Ljava/lang/String;
  astore 4
  aload_2
  aload 4
  invokevirtual java/lang/StringBuilder/append(Ljava/lang/String;)Ljava/lang/StringBuilder;
  astore_2
  ldc ", downloadAppName="
  astore_3
  aload_2
  aload_3
  invokevirtual java/lang/StringBuilder/append(Ljava/lang/String;)Ljava/lang/StringBuilder;
  astore_2
  aload_0
  getfield cn/domob/android/ads/j$a/h Ljava/lang/String;
  astore 4
  aload_2
  aload 4
  invokevirtual java/lang/StringBuilder/append(Ljava/lang/String;)Ljava/lang/StringBuilder;
  astore_2
  ldc ", clickConfirm="
  astore_3
  aload_2
  aload_3
  invokevirtual java/lang/StringBuilder/append(Ljava/lang/String;)Ljava/lang/StringBuilder;
  astore_2
  aload_0
  getfield cn/domob/android/ads/j$a/i Z
  istore 5
  aload_2
  iload 5
  invokevirtual java/lang/StringBuilder/append(Z)Ljava/lang/StringBuilder;
  astore_2
  ldc ", confirmType="
  astore_3
  aload_2
  aload_3
  invokevirtual java/lang/StringBuilder/append(Ljava/lang/String;)Ljava/lang/StringBuilder;
  astore_2
  aload_0
  getfield cn/domob/android/ads/j$a/j I
  istore 6
  aload_2
  iload 6
  invokevirtual java/lang/StringBuilder/append(I)Ljava/lang/StringBuilder;
  astore_2
  ldc ", preload="
  astore_3
  aload_2
  aload_3
  invokevirtual java/lang/StringBuilder/append(Ljava/lang/String;)Ljava/lang/StringBuilder;
  astore_2
  aload_0
  getfield cn/domob/android/ads/j$a/k Z
  istore 5
  aload_2
  iload 5
  invokevirtual java/lang/StringBuilder/append(Z)Ljava/lang/StringBuilder;
  astore_2
  ldc ", autoRun="
  astore_3
  aload_2
  aload_3
  invokevirtual java/lang/StringBuilder/append(Ljava/lang/String;)Ljava/lang/StringBuilder;
  astore_2
  aload_0
  getfield cn/domob/android/ads/j$a/l Z
  istore 5
  aload_2
  iload 5
  invokevirtual java/lang/StringBuilder/append(Z)Ljava/lang/StringBuilder;
  astore_2
  ldc "]"
  astore_3
  aload_2
  aload_3
  invokevirtual java/lang/StringBuilder/append(Ljava/lang/String;)Ljava/lang/StringBuilder;
  pop
  aload_1
  invokevirtual java/lang/StringBuilder/toString()Ljava/lang/String;
  astore 4
  aload 4
  areturn
  nop
.end <method>

