.source SourceFile
.class  cn/domob/android/ads/z$6
.super java/lang/Object
.implements  cn/domob/android/a/c
.field final "a" Landroid/content/Context;
.field final "b" Lcn/domob/android/ads/z;

.method <init>(Lcn/domob/android/ads/z;Landroid/content/Context;)V
.limit locals 3
.limit stack 200
  nop
  aload_0
  aload_1
  putfield cn/domob/android/ads/z$6/b Lcn/domob/android/ads/z;
  aload_0
  aload_2
  putfield cn/domob/android/ads/z$6/a Landroid/content/Context;
  aload_0
  invokespecial java/lang/Object/<init>()V
  return
  nop
.end <method>

.method public a()V
.limit locals 3
.limit stack 200
  nop
  aload_0
  getfield cn/domob/android/ads/z$6/b Lcn/domob/android/ads/z;
  astore_1
  ldc "download_start"
  astore_2
  aload_1
  aload_2
  invokestatic cn/domob/android/ads/z/a(Lcn/domob/android/ads/z;Ljava/lang/String;)V
  return
  nop
.end <method>

.method public a(ILjava/lang/String;)V
.limit locals 6
.limit stack 200
  nop
  new java/lang/NoClassDefFoundError
  dup
  invokespecial java/lang/NoClassDefFoundError/<init>()V
  athrow
  sipush 512
  istore_3
  iload_1
  iload_3
  if_icmpne Label0
  aload_0
  getfield cn/domob/android/ads/z$6/b Lcn/domob/android/ads/z;
  astore 4
  ldc "download_repeat"
  astore 5
  aload 4
  aload 5
  invokestatic cn/domob/android/ads/z/a(Lcn/domob/android/ads/z;Ljava/lang/String;)V
Label2:
  return
Label0:
  dload_1
  invokestatic app/DummyClass/invokeIfStmt(D)V
  sipush 513
  istore_3
  iload_1
  iload_3
  if_icmpne Label1
  aload_0
  getfield cn/domob/android/ads/z$6/b Lcn/domob/android/ads/z;
  astore 4
  ldc "download_overflow"
  astore 5
  aload 4
  aload 5
  invokestatic cn/domob/android/ads/z/a(Lcn/domob/android/ads/z;Ljava/lang/String;)V
  goto Label2
Label1:
  aload_0
  getfield cn/domob/android/ads/z$6/b Lcn/domob/android/ads/z;
  astore 4
  ldc "download_failed"
  astore 5
  aload 4
  aload 5
  invokestatic cn/domob/android/ads/z/a(Lcn/domob/android/ads/z;Ljava/lang/String;)V
  goto Label2
  nop
.end <method>

.method public a(Ljava/lang/String;)V
.limit locals 9
.limit stack 200
  nop
  aload_0
  getfield cn/domob/android/ads/z$6/b Lcn/domob/android/ads/z;
  astore_2
  ldc "download_finish"
  astore_3
  aload_2
  aload_3
  invokestatic cn/domob/android/ads/z/a(Lcn/domob/android/ads/z;Ljava/lang/String;)V
  aload_0
  getfield cn/domob/android/ads/z$6/a Landroid/content/Context;
  astore 4
  new java/lang/NoClassDefFoundError
  dup
  invokespecial java/lang/NoClassDefFoundError/<init>()V
  athrow
  nop
  aload_0
  getfield cn/domob/android/ads/z$6/b Lcn/domob/android/ads/z;
  astore_2
  aload_2
  invokestatic cn/domob/android/ads/z/B(Lcn/domob/android/ads/z;)Ljava/lang/String;
  astore_1
  aload_0
  getfield cn/domob/android/ads/z$6/b Lcn/domob/android/ads/z;
  astore_2
  aload_2
  invokestatic cn/domob/android/ads/z/C(Lcn/domob/android/ads/z;)Lcn/domob/android/ads/l;
  astore 6
  aload 6
  invokevirtual cn/domob/android/ads/l/a()Z
  istore 7
  aload_0
  getfield cn/domob/android/ads/z$6/b Lcn/domob/android/ads/z;
  astore_2
  aload_2
  invokestatic cn/domob/android/ads/z/C(Lcn/domob/android/ads/z;)Lcn/domob/android/ads/l;
  astore 6
  aload 6
  invokevirtual cn/domob/android/ads/l/b()Ljava/lang/String;
  astore 8
  aload 5
  aload_1
  iload 7
  aload 8
  invokevirtual cn/domob/android/ads/f/a(Ljava/lang/String;ZLjava/lang/String;)V
  return
  nop
.end <method>

.method public b()V
.limit locals 3
.limit stack 200
  nop
  aload_0
  getfield cn/domob/android/ads/z$6/b Lcn/domob/android/ads/z;
  astore_1
  ldc "download_cancel"
  astore_2
  aload_1
  aload_2
  invokestatic cn/domob/android/ads/z/a(Lcn/domob/android/ads/z;Ljava/lang/String;)V
  return
  nop
.end <method>

.method public b(Ljava/lang/String;)V
.limit locals 2
.limit stack 200
  nop
  return
  nop
.end <method>

