.source SourceFile
.class public  cn/domob/android/ads/h
.super java/lang/Object
.field private static "a" Lcn/domob/android/ads/h;
.field private "b" Ljava/lang/String;
.field private "c" Ljava/lang/String;
.field private "d" Ljava/lang/String;
.field private "e" Z
.field private "f" I
.field private "g" I
.field private "h" Ljava/lang/String;
.field private "i" Z
.field private "j" Ljava/lang/String;
.field private "k" Ljava/lang/String;
.field private "l" Ljava/util/GregorianCalendar;

.method public <init>()V
.limit locals 5
.limit stack 200
  nop
  aload_0
  invokespecial java/lang/Object/<init>()V
  ldc "http://r.domob.cn/a/"
  astore_1
  aload_0
  aload_1
  putfield cn/domob/android/ads/h/b Ljava/lang/String;
  aconst_null
  astore_2
  aload_0
  aload_2
  putfield cn/domob/android/ads/h/c Ljava/lang/String;
  aconst_null
  astore_2
  aload_0
  aload_2
  putfield cn/domob/android/ads/h/d Ljava/lang/String;
  iconst_0
  istore_3
  aload_0
  iload_3
  putfield cn/domob/android/ads/h/e Z
  iconst_0
  istore_3
  iload_3
  istore 4
  aload_0
  iload 4
  putfield cn/domob/android/ads/h/f I
  iconst_0
  istore_3
  iload_3
  istore 4
  aload_0
  iload 4
  putfield cn/domob/android/ads/h/g I
  aconst_null
  astore_2
  aload_0
  aload_2
  putfield cn/domob/android/ads/h/h Ljava/lang/String;
  iconst_1
  istore_3
  aload_0
  iload_3
  putfield cn/domob/android/ads/h/i Z
  aconst_null
  astore_2
  aload_0
  aload_2
  putfield cn/domob/android/ads/h/j Ljava/lang/String;
  aconst_null
  astore_2
  aload_0
  aload_2
  putfield cn/domob/android/ads/h/k Ljava/lang/String;
  return
  nop
.end <method>

.method public static a()Lcn/domob/android/ads/h;
.limit locals 3
.limit stack 200
  .catch  java/lang/Throwable <from> Label2 <to> Label3 <using> Label1
  nop
  ldc cn/domob/android/ads/h
  astore_0
  aload_0
  monitorenter
Label2:
  getstatic cn/domob/android/ads/h/a Lcn/domob/android/ads/h;
  astore_1
  new java/lang/NoClassDefFoundError
  dup
  invokespecial java/lang/NoClassDefFoundError/<init>()V
  athrow
  iload_1
  ifne Label0
  new cn/domob/android/ads/h
  astore_1
  aload_1
  invokespecial cn/domob/android/ads/h/<init>()V
  aload_1
  putstatic cn/domob/android/ads/h/a Lcn/domob/android/ads/h;
Label0:
  getstatic cn/domob/android/ads/h/a Lcn/domob/android/ads/h;
  astore_1
Label3:
  ldc cn/domob/android/ads/h
  astore_0
  aload_0
  monitorexit
  aload_1
  areturn
Label1:
  astore_2
  ldc cn/domob/android/ads/h
  astore_0
  aload_0
  monitorexit
  aload_2
  athrow
  nop
.end <method>

.method protected a(Landroid/content/Context;)Ljava/lang/String;
.limit locals 13
.limit stack 200
  nop
  aload_0
  getfield cn/domob/android/ads/h/c Ljava/lang/String;
  astore_2
  new java/lang/NoClassDefFoundError
  dup
  invokespecial java/lang/NoClassDefFoundError/<init>()V
  athrow
  iload_2
  ifne Label0
Label2:
  aload_1
  invokevirtual android/content/Context/getPackageManager()Landroid/content/pm/PackageManager;
  astore_3
  aload_3
  invokestatic app/DummyClass/invokeIfStmt(Ljava/lang/Object;)V
  aload_3
  ifnull Label0
  aload_1
  invokevirtual android/content/Context/getPackageName()Ljava/lang/String;
  astore_2
  sipush 128
  istore 5
  aload_3
  aload_2
  iload 5
  invokevirtual android/content/pm/PackageManager/getApplicationInfo(Ljava/lang/String;I)Landroid/content/pm/ApplicationInfo;
  astore 4
  aload 4
  invokestatic app/DummyClass/invokeIfStmt(Ljava/lang/Object;)V
  aload 4
  ifnull Label0
  aload 4
  getfield android/content/pm/PackageItemInfo/metaData Landroid/os/Bundle;
  astore 6
Label3:
  aload 6
  invokestatic app/DummyClass/invokeIfStmt(Ljava/lang/Object;)V
  aload 6
  ifnull Label0
Label5:
  aload 4
  getfield android/content/pm/PackageItemInfo/metaData Landroid/os/Bundle;
  astore 6
  ldc "DOMOB_PID"
  astore 7
  aload 6
  aload 7
  invokevirtual android/os/Bundle/getString(Ljava/lang/String;)Ljava/lang/String;
  astore_2
  aload_0
  getfield cn/domob/android/ads/h/c Ljava/lang/String;
  astore 8
  aload 8
  invokestatic app/DummyClass/invokeIfStmt(Ljava/lang/Object;)V
  aload 8
  ifnonnull Label0
  aload_2
  invokestatic app/DummyClass/invokeIfStmt(Ljava/lang/Object;)V
  aload_2
  ifnull Label0
  aload_0
  aload_2
  putfield cn/domob/android/ads/h/c Ljava/lang/String;
  aload_0
  getfield cn/domob/android/ads/h/c Ljava/lang/String;
  astore 8
  aload_0
  aload 8
  invokevirtual cn/domob/android/ads/h/b(Ljava/lang/String;)V
Label0:
  aload_0
  getfield cn/domob/android/ads/h/c Ljava/lang/String;
  astore_2
  aload_2
  areturn
Label4:
  astore 9
Label6:
  ldc "DomobSDK"
  astore 7
  ldc "DOMOB_PID is missed in AndroidManifest.xml!"
  astore 10
  aload 7
  aload 10
  invokestatic android/util/Log/e(Ljava/lang/String;Ljava/lang/String;)I
  pop
Label7:
  aconst_null
  astore 11
  aload 11
  areturn
Label1:
  astore 12
  ldc "DomobSDK"
  astore 7
  ldc "Failed to get applicationInfo."
  astore 10
  aload 7
  aload 10
  invokestatic android/util/Log/e(Ljava/lang/String;Ljava/lang/String;)I
  pop
  aload 12
  invokestatic cn/domob/android/ads/J/a(Ljava/lang/Throwable;)V
  aconst_null
  astore 11
  aload 11
  areturn
  nop
.end <method>

.method protected a(I)V
.limit locals 3
.limit stack 200
  nop
  new java/lang/NoClassDefFoundError
  dup
  invokespecial java/lang/NoClassDefFoundError/<init>()V
  athrow
  iload_1
  ifne Label0
  iconst_0
  istore_2
  aload_0
  iload_2
  putfield cn/domob/android/ads/h/f I
Label1:
  return
Label0:
  aload_0
  iload_1
  invokespecial cn/domob/android/ads/h/c(I)I
  istore_1
  aload_0
  iload_1
  putfield cn/domob/android/ads/h/f I
  goto Label1
  nop
.end <method>

.method protected a(Landroid/content/Context;Ljava/lang/String;)V
.limit locals 3
.limit stack 200
  nop
  return
  nop
.end <method>

.method protected a(Ljava/lang/String;)V
.limit locals 5
.limit stack 200
  nop
  new java/lang/NoClassDefFoundError
  dup
  invokespecial java/lang/NoClassDefFoundError/<init>()V
  athrow
  iload_1
  ifeq Label0
  new java/lang/StringBuilder
  astore_2
  aload_2
  invokespecial java/lang/StringBuilder/<init>()V
  ldc "Set AD server url:"
  astore_3
  aload_2
  aload_3
  invokevirtual java/lang/StringBuilder/append(Ljava/lang/String;)Ljava/lang/StringBuilder;
  astore_2
  aload_2
  aload_1
  invokevirtual java/lang/StringBuilder/append(Ljava/lang/String;)Ljava/lang/StringBuilder;
  astore_2
  aload_2
  invokevirtual java/lang/StringBuilder/toString()Ljava/lang/String;
  astore 4
  ldc "DomobRequest"
  astore_3
  aload_3
  aload 4
  invokestatic cn/domob/android/ads/J/a(Ljava/lang/String;Ljava/lang/String;)V
  aload_0
  aload_1
  putfield cn/domob/android/ads/h/b Ljava/lang/String;
Label0:
  return
  nop
.end <method>

.method protected a(Ljava/util/GregorianCalendar;)V
.limit locals 2
.limit stack 200
  nop
  aload_0
  aload_1
  putfield cn/domob/android/ads/h/l Ljava/util/GregorianCalendar;
  return
  nop
.end <method>

.method protected a(Z)V
.limit locals 2
.limit stack 200
  nop
  aload_0
  iload_1
  putfield cn/domob/android/ads/h/e Z
  return
  nop
.end <method>

.method protected b()Ljava/lang/String;
.limit locals 2
.limit stack 200
  nop
  aload_0
  getfield cn/domob/android/ads/h/b Ljava/lang/String;
  astore_1
  aload_1
  areturn
  nop
.end <method>

.method protected b(Landroid/content/Context;)Ljava/lang/String;
.limit locals 9
.limit stack 200
  .catch  java/lang/Throwable <from> Label7 <to> Label3 <using> Label5
  .catch  java/lang/Exception <from> Label7 <to> Label3 <using> Label6
  .catch  java/lang/Throwable <from> Label1 <to> Label8 <using> Label5
  .catch  java/lang/Exception <from> Label1 <to> Label8 <using> Label6
  .catch  java/lang/Throwable <from> Label9 <to> Label10 <using> Label5
  nop
  iconst_0
  istore_2
Label7:
  new java/lang/NoClassDefFoundError
  dup
  invokespecial java/lang/NoClassDefFoundError/<init>()V
  athrow
  nop
  aload_3
  invokevirtual cn/domob/android/ads/d/b()Landroid/database/Cursor;
  astore_2
  aload_2
  invokestatic app/DummyClass/invokeIfStmt(Ljava/lang/Object;)V
  aload_2
  ifnull Label0
  aload_2
  invokeinterface android/database/Cursor/getCount()I 1
  istore 4
  dload 4
  invokestatic app/DummyClass/invokeIfStmt(D)V
  iload 4
  ifne Label1
Label0:
  ldc "Conf db is empty!"
  astore 5
  aload_0
  aload 5
  invokestatic cn/domob/android/ads/J/a(Ljava/lang/Object;Ljava/lang/String;)V
Label3:
  aload_2
  invokestatic app/DummyClass/invokeIfStmt(Ljava/lang/Object;)V
  aload_2
  ifnull Label2
  aload_2
  invokeinterface android/database/Cursor/close()V 1
Label2:
  aload_0
  getfield cn/domob/android/ads/h/d Ljava/lang/String;
  astore 6
  aload 6
  areturn
Label1:
  aload_2
  invokeinterface android/database/Cursor/moveToFirst()Z 1
  pop
  ldc "_cid"
  astore 5
  aload_2
  aload 5
  invokeinterface android/database/Cursor/getColumnIndexOrThrow(Ljava/lang/String;)I 2
  istore 4
  aload_2
  iload 4
  invokeinterface android/database/Cursor/getString(I)Ljava/lang/String; 2
  astore 6
  aload_0
  aload 6
  putfield cn/domob/android/ads/h/d Ljava/lang/String;
Label8:
  goto Label3
Label6:
  astore 7
Label9:
  aload 7
  invokestatic cn/domob/android/ads/J/a(Ljava/lang/Throwable;)V
Label10:
  new java/lang/NoClassDefFoundError
  dup
  invokespecial java/lang/NoClassDefFoundError/<init>()V
  athrow
  iload_2
  ifeq Label2
  aload_2
  invokeinterface android/database/Cursor/close()V 1
  goto Label2
Label5:
  astore 8
  new java/lang/NoClassDefFoundError
  dup
  invokespecial java/lang/NoClassDefFoundError/<init>()V
  athrow
  iload_2
  ifeq Label4
  aload_2
  invokeinterface android/database/Cursor/close()V 1
Label4:
  aload 8
  athrow
  nop
.end <method>

.method protected b(I)V
.limit locals 8
.limit stack 200
  nop
  new java/lang/NoClassDefFoundError
  dup
  invokespecial java/lang/NoClassDefFoundError/<init>()V
  athrow
  iconst_1
  istore_2
  iload_1
  iload_2
  if_icmpne Label0
  aload_0
  getfield cn/domob/android/ads/h/f I
  istore_3
  dload_3
  invokestatic app/DummyClass/invokeIfStmt(D)V
  iload_3
  ifeq Label0
  ldc "Refresh Interval is 1, Use the default request interval"
  astore 4
  aload_0
  aload 4
  invokestatic cn/domob/android/ads/J/a(Ljava/lang/Object;Ljava/lang/String;)V
  aload_0
  getfield cn/domob/android/ads/h/f I
  istore_3
  aload_0
  iload_3
  putfield cn/domob/android/ads/h/g I
Label3:
  new java/lang/StringBuilder
  astore 5
  aload 5
  invokespecial java/lang/StringBuilder/<init>()V
  ldc "Set request interval:"
  astore 4
  aload 5
  aload 4
  invokevirtual java/lang/StringBuilder/append(Ljava/lang/String;)Ljava/lang/StringBuilder;
  astore 5
  aload_0
  getfield cn/domob/android/ads/h/g I
  istore_3
  aload 5
  iload_3
  invokevirtual java/lang/StringBuilder/append(I)Ljava/lang/StringBuilder;
  astore 5
  aload 5
  invokevirtual java/lang/StringBuilder/toString()Ljava/lang/String;
  astore 6
  aload_0
  aload 6
  invokestatic cn/domob/android/ads/J/a(Ljava/lang/Object;Ljava/lang/String;)V
  return
Label0:
  dload_1
  invokestatic app/DummyClass/invokeIfStmt(D)V
  iload_1
  ifeq Label1
  aload_0
  getfield cn/domob/android/ads/h/f I
  istore_3
  dload_3
  invokestatic app/DummyClass/invokeIfStmt(D)V
  iload_3
  ifne Label2
Label1:
  ldc "DomobSDK"
  astore 4
  ldc "Refresh Interval is 0, AD will not be refreshed any more."
  astore 7
  aload 4
  aload 7
  invokestatic android/util/Log/w(Ljava/lang/String;Ljava/lang/String;)I
  pop
  iconst_0
  istore_2
  aload_0
  iload_2
  putfield cn/domob/android/ads/h/g I
  goto Label3
Label2:
  aload_0
  iload_1
  invokespecial cn/domob/android/ads/h/c(I)I
  istore_3
  aload_0
  iload_3
  putfield cn/domob/android/ads/h/g I
  goto Label3
  nop
.end <method>

.method protected b(Ljava/lang/String;)V
.limit locals 7
.limit stack 200
  nop
  new java/lang/NoClassDefFoundError
  dup
  invokespecial java/lang/NoClassDefFoundError/<init>()V
  athrow
  iload_1
  ifeq Label0
  aload_1
  invokestatic app/DummyClass/invokeIfStmt(Ljava/lang/Object;)V
  iload_1
  ifeq Label1
  aload_1
  invokevirtual java/lang/String/length()I
  istore_2
  dload_2
  invokestatic app/DummyClass/invokeIfStmt(D)V
  iload_2
  ifne Label1
Label0:
  ldc "DomobSDK"
  astore_3
  ldc "Incorrect Domob publisher ID."
  astore 4
  aload_3
  aload 4
  invokestatic android/util/Log/e(Ljava/lang/String;Ljava/lang/String;)I
  pop
Label2:
  return
Label1:
  new java/lang/StringBuilder
  astore 5
  aload 5
  invokespecial java/lang/StringBuilder/<init>()V
  ldc "Current publisherID is "
  astore_3
  aload 5
  aload_3
  invokevirtual java/lang/StringBuilder/append(Ljava/lang/String;)Ljava/lang/StringBuilder;
  astore 5
  aload 5
  aload_1
  invokevirtual java/lang/StringBuilder/append(Ljava/lang/String;)Ljava/lang/StringBuilder;
  astore 5
  aload 5
  invokevirtual java/lang/StringBuilder/toString()Ljava/lang/String;
  astore 6
  ldc "DomobSDK"
  astore_3
  aload_3
  aload 6
  invokestatic android/util/Log/i(Ljava/lang/String;Ljava/lang/String;)I
  pop
  aload_0
  aload_1
  putfield cn/domob/android/ads/h/c Ljava/lang/String;
  goto Label2
  nop
.end <method>

.method protected b(Z)V
.limit locals 2
.limit stack 200
  nop
  aload_0
  iload_1
  putfield cn/domob/android/ads/h/i Z
  return
  nop
.end <method>

.method private c(I)I
.limit locals 6
.limit stack 200
  nop
  new java/lang/StringBuilder
  astore_2
  aload_2
  invokespecial java/lang/StringBuilder/<init>()V
  ldc "limitedInterval: "
  astore_3
  aload_2
  aload_3
  invokevirtual java/lang/StringBuilder/append(Ljava/lang/String;)Ljava/lang/StringBuilder;
  astore_2
  aload_2
  iload_1
  invokevirtual java/lang/StringBuilder/append(I)Ljava/lang/StringBuilder;
  astore_2
  ldc " s"
  astore_3
  aload_2
  aload_3
  invokevirtual java/lang/StringBuilder/append(Ljava/lang/String;)Ljava/lang/StringBuilder;
  astore_2
  aload_2
  invokevirtual java/lang/StringBuilder/toString()Ljava/lang/String;
  astore 4
  aload_0
  aload 4
  invokestatic cn/domob/android/ads/J/a(Ljava/lang/Object;Ljava/lang/String;)V
  new java/lang/NoClassDefFoundError
  dup
  invokespecial java/lang/NoClassDefFoundError/<init>()V
  athrow
  bipush 20
  istore 5
  iload_1
  iload 5
  if_icmpge Label0
  ldc "Request interval is smaller than minimal request interval, use 20 instead"
  astore_3
  aload_0
  aload_3
  invokestatic cn/domob/android/ads/J/a(Ljava/lang/Object;Ljava/lang/String;)V
  bipush 20
  istore 5
  iload 5
  ireturn
Label0:
  dload_1
  invokestatic app/DummyClass/invokeIfStmt(D)V
  sipush 600
  istore 5
  iload_1
  iload 5
  if_icmple Label1
  ldc "Request interval is larger than maximum request interval, use 600 instead"
  astore_3
  aload_0
  aload_3
  invokestatic cn/domob/android/ads/J/a(Ljava/lang/Object;Ljava/lang/String;)V
  sipush 600
  istore 5
  iload 5
  ireturn
Label1:
  new java/lang/StringBuilder
  astore_2
  aload_2
  invokespecial java/lang/StringBuilder/<init>()V
  ldc "Set request interval to: "
  astore_3
  aload_2
  aload_3
  invokevirtual java/lang/StringBuilder/append(Ljava/lang/String;)Ljava/lang/StringBuilder;
  astore_2
  aload_2
  iload_1
  invokevirtual java/lang/StringBuilder/append(I)Ljava/lang/StringBuilder;
  astore_2
  ldc " s"
  astore_3
  aload_2
  aload_3
  invokevirtual java/lang/StringBuilder/append(Ljava/lang/String;)Ljava/lang/StringBuilder;
  astore_2
  aload_2
  invokevirtual java/lang/StringBuilder/toString()Ljava/lang/String;
  astore 4
  aload_0
  aload 4
  invokestatic cn/domob/android/ads/J/a(Ljava/lang/Object;Ljava/lang/String;)V
  iload_1
  ireturn
  nop
.end <method>

.method protected c(Ljava/lang/String;)V
.limit locals 2
.limit stack 200
  nop
  aload_0
  aload_1
  putfield cn/domob/android/ads/h/h Ljava/lang/String;
  return
  nop
.end <method>

.method protected c()Z
.limit locals 2
.limit stack 200
  nop
  aload_0
  getfield cn/domob/android/ads/h/e Z
  istore_1
  iload_1
  ireturn
  nop
.end <method>

.method protected d()Ljava/lang/String;
.limit locals 2
.limit stack 200
  nop
  aload_0
  getfield cn/domob/android/ads/h/h Ljava/lang/String;
  astore_1
  aload_1
  areturn
  nop
.end <method>

.method protected d(Ljava/lang/String;)V
.limit locals 2
.limit stack 200
  nop
  aload_0
  aload_1
  putfield cn/domob/android/ads/h/j Ljava/lang/String;
  return
  nop
.end <method>

.method protected e()I
.limit locals 2
.limit stack 200
  nop
  aload_0
  getfield cn/domob/android/ads/h/g I
  istore_1
  iload_1
  ireturn
  nop
.end <method>

.method protected e(Ljava/lang/String;)V
.limit locals 2
.limit stack 200
  nop
  aload_0
  aload_1
  putfield cn/domob/android/ads/h/k Ljava/lang/String;
  return
  nop
.end <method>

.method protected f()Z
.limit locals 2
.limit stack 200
  nop
  aload_0
  getfield cn/domob/android/ads/h/i Z
  istore_1
  iload_1
  ireturn
  nop
.end <method>

.method protected g()Ljava/lang/String;
.limit locals 2
.limit stack 200
  nop
  aload_0
  getfield cn/domob/android/ads/h/j Ljava/lang/String;
  astore_1
  aload_1
  areturn
  nop
.end <method>

.method protected h()Ljava/lang/String;
.limit locals 2
.limit stack 200
  nop
  aload_0
  getfield cn/domob/android/ads/h/k Ljava/lang/String;
  astore_1
  aload_1
  areturn
  nop
.end <method>

.method protected i()Ljava/util/GregorianCalendar;
.limit locals 2
.limit stack 200
  nop
  aload_0
  getfield cn/domob/android/ads/h/l Ljava/util/GregorianCalendar;
  astore_1
  aload_1
  areturn
  nop
.end <method>

.method protected j()Ljava/lang/String;
.limit locals 8
.limit stack 200
  nop
  iconst_0
  istore_1
  aload_0
  getfield cn/domob/android/ads/h/l Ljava/util/GregorianCalendar;
  astore_2
  new java/lang/NoClassDefFoundError
  dup
  invokespecial java/lang/NoClassDefFoundError/<init>()V
  athrow
  iload_2
  ifeq Label0
  iconst_3
  istore 4
  iload 4
  anewarray java/lang/Object
  astore_3
  iconst_1
  istore 4
  aload_2
  iload 4
  invokevirtual java/util/GregorianCalendar/get(I)I
  istore 5
  iload 5
  invokestatic java/lang/Integer/valueOf(I)Ljava/lang/Integer;
  astore 6
  iconst_0
  istore 4
  aload_3
  iload 4
  aload 6
  aastore
  iconst_2
  istore 4
  aload_2
  iload 4
  invokevirtual java/util/GregorianCalendar/get(I)I
  istore 5
  iload 5
  iconst_1
  iadd
  istore 5
  iload 5
  invokestatic java/lang/Integer/valueOf(I)Ljava/lang/Integer;
  astore 6
  iconst_1
  istore 4
  aload_3
  iload 4
  aload 6
  aastore
  iconst_5
  istore 4
  aload_2
  iload 4
  invokevirtual java/util/GregorianCalendar/get(I)I
  istore 5
  iload 5
  invokestatic java/lang/Integer/valueOf(I)Ljava/lang/Integer;
  astore 6
  iconst_2
  istore 4
  aload_3
  iload 4
  aload 6
  aastore
  ldc "%04d%02d%02d"
  astore 7
  aload 7
  aload_3
  invokestatic java/lang/String/format(Ljava/lang/String;[Ljava/lang/Object;)Ljava/lang/String;
  astore_1
Label0:
  aload_1
  areturn
  nop
.end <method>

