.source SourceFile
.class  cn/domob/android/ads/f$a
.super java/lang/Object
.field final "a" Lcn/domob/android/ads/f;
.field private "b" Ljava/lang/String;
.field private "c" Z
.field private "d" Ljava/lang/String;

.method <init>(Lcn/domob/android/ads/f;Ljava/lang/String;ZLjava/lang/String;)V
.limit locals 5
.limit stack 200
  nop
  aload_0
  aload_1
  putfield cn/domob/android/ads/f$a/a Lcn/domob/android/ads/f;
  aload_0
  invokespecial java/lang/Object/<init>()V
  aload_0
  aload_2
  putfield cn/domob/android/ads/f$a/b Ljava/lang/String;
  aload_0
  iload_3
  putfield cn/domob/android/ads/f$a/c Z
  aload_0
  aload 4
  putfield cn/domob/android/ads/f$a/d Ljava/lang/String;
  return
  nop
.end <method>

.method a()Z
.limit locals 2
.limit stack 200
  nop
  aload_0
  getfield cn/domob/android/ads/f$a/c Z
  istore_1
  iload_1
  ireturn
  nop
.end <method>

.method b()Ljava/lang/String;
.limit locals 2
.limit stack 200
  nop
  aload_0
  getfield cn/domob/android/ads/f$a/d Ljava/lang/String;
  astore_1
  aload_1
  areturn
  nop
.end <method>

.method public toString()Ljava/lang/String;
.limit locals 6
.limit stack 200
  nop
  iconst_3
  istore_2
  iload_2
  anewarray java/lang/Object
  astore_1
  aload_0
  getfield cn/domob/android/ads/f$a/b Ljava/lang/String;
  astore_3
  iconst_0
  istore_2
  aload_1
  iload_2
  aload_3
  aastore
  aload_0
  getfield cn/domob/android/ads/f$a/c Z
  istore 4
  iload 4
  invokestatic java/lang/String/valueOf(Z)Ljava/lang/String;
  astore_3
  iconst_1
  istore_2
  aload_1
  iload_2
  aload_3
  aastore
  aload_0
  getfield cn/domob/android/ads/f$a/d Ljava/lang/String;
  astore_3
  iconst_2
  istore_2
  aload_1
  iload_2
  aload_3
  aastore
  ldc "pkgName = %s, isAutoRun = %s, rpURLMD5 = %s"
  astore 5
  aload 5
  aload_1
  invokestatic java/lang/String/format(Ljava/lang/String;[Ljava/lang/Object;)Ljava/lang/String;
  astore_3
  aload_3
  areturn
  nop
.end <method>

