.source SourceFile
.class public final  cn/domob/android/ads/a/c
.super java/lang/Object

.method public <init>()V
.limit locals 1
.limit stack 200
  nop
  aload_0
  invokespecial java/lang/Object/<init>()V
  return
  nop
.end <method>

.method public static a()Landroid/view/animation/AnimationSet;
.limit locals 10
.limit stack 200
  nop
  new java/lang/NoClassDefFoundError
  dup
  invokespecial java/lang/NoClassDefFoundError/<init>()V
  athrow
  ldc 100.000000
  fstore_1
  fconst_0
  fstore_2
  fconst_0
  fstore_3
  fconst_0
  fstore 4
  aload_0
  fload_1
  fload_2
  fload_3
  fload 4
  invokespecial android/view/animation/TranslateAnimation/<init>(FFFF)V
  ldc2_w 3000
  lstore 5
  aload_0
  lload 5
  invokevirtual android/view/animation/Animation/setDuration(J)V
  new android/view/animation/AccelerateInterpolator
  astore 7
  aload 7
  invokespecial android/view/animation/AccelerateInterpolator/<init>()V
  aload_0
  aload 7
  invokevirtual android/view/animation/Animation/setInterpolator(Landroid/view/animation/Interpolator;)V
  iconst_1
  istore 8
  aload_0
  iload 8
  invokevirtual android/view/animation/Animation/setFillAfter(Z)V
  new android/view/animation/AnimationSet
  astore 9
  iconst_1
  istore 8
  aload 9
  iload 8
  invokespecial android/view/animation/AnimationSet/<init>(Z)V
  aload 9
  aload_0
  invokevirtual android/view/animation/AnimationSet/addAnimation(Landroid/view/animation/Animation;)V
  aload 9
  areturn
  nop
.end <method>

.method public static b()Landroid/view/animation/AnimationSet;
.limit locals 10
.limit stack 200
  nop
  new java/lang/NoClassDefFoundError
  dup
  invokespecial java/lang/NoClassDefFoundError/<init>()V
  athrow
  ldc -100.000000
  fstore_1
  fconst_0
  fstore_2
  fconst_0
  fstore_3
  fconst_0
  fstore 4
  aload_0
  fload_1
  fload_2
  fload_3
  fload 4
  invokespecial android/view/animation/TranslateAnimation/<init>(FFFF)V
  ldc2_w 3000
  lstore 5
  aload_0
  lload 5
  invokevirtual android/view/animation/Animation/setDuration(J)V
  new android/view/animation/AccelerateInterpolator
  astore 7
  aload 7
  invokespecial android/view/animation/AccelerateInterpolator/<init>()V
  aload_0
  aload 7
  invokevirtual android/view/animation/Animation/setInterpolator(Landroid/view/animation/Interpolator;)V
  iconst_1
  istore 8
  aload_0
  iload 8
  invokevirtual android/view/animation/Animation/setFillAfter(Z)V
  new android/view/animation/AnimationSet
  astore 9
  iconst_1
  istore 8
  aload 9
  iload 8
  invokespecial android/view/animation/AnimationSet/<init>(Z)V
  aload 9
  aload_0
  invokevirtual android/view/animation/AnimationSet/addAnimation(Landroid/view/animation/Animation;)V
  aload 9
  areturn
  nop
.end <method>

.method public static c()Landroid/view/animation/AnimationSet;
.limit locals 11
.limit stack 200
  nop
  new java/lang/NoClassDefFoundError
  dup
  invokespecial java/lang/NoClassDefFoundError/<init>()V
  athrow
  fconst_0
  fstore_1
  fconst_0
  fstore_2
  ldc 50.000000
  fstore_3
  fconst_0
  fstore 4
  aload_0
  fload_1
  fload_2
  fload_3
  fload 4
  invokespecial android/view/animation/TranslateAnimation/<init>(FFFF)V
  ldc2_w 2500
  lstore 5
  aload_0
  lload 5
  invokevirtual android/view/animation/Animation/setDuration(J)V
  new android/view/animation/AccelerateInterpolator
  astore 7
  aload 7
  invokespecial android/view/animation/AccelerateInterpolator/<init>()V
  aload_0
  aload 7
  invokevirtual android/view/animation/Animation/setInterpolator(Landroid/view/animation/Interpolator;)V
  iconst_1
  istore 8
  aload_0
  iload 8
  invokevirtual android/view/animation/Animation/setFillAfter(Z)V
  new android/view/animation/AlphaAnimation
  astore 9
  fconst_0
  fstore_1
  fconst_1
  fstore_2
  aload 9
  fload_1
  fload_2
  invokespecial android/view/animation/AlphaAnimation/<init>(FF)V
  ldc2_w 500
  lstore 5
  aload 9
  lload 5
  invokevirtual android/view/animation/Animation/setDuration(J)V
  new android/view/animation/AccelerateInterpolator
  astore 7
  aload 7
  invokespecial android/view/animation/AccelerateInterpolator/<init>()V
  aload 9
  aload 7
  invokevirtual android/view/animation/Animation/setInterpolator(Landroid/view/animation/Interpolator;)V
  iconst_1
  istore 8
  aload 9
  iload 8
  invokevirtual android/view/animation/Animation/setFillAfter(Z)V
  new android/view/animation/AnimationSet
  astore 10
  iconst_1
  istore 8
  aload 10
  iload 8
  invokespecial android/view/animation/AnimationSet/<init>(Z)V
  aload 10
  aload_0
  invokevirtual android/view/animation/AnimationSet/addAnimation(Landroid/view/animation/Animation;)V
  aload 10
  aload 9
  invokevirtual android/view/animation/AnimationSet/addAnimation(Landroid/view/animation/Animation;)V
  aload 10
  areturn
  nop
.end <method>

.method public static d()Landroid/view/animation/AnimationSet;
.limit locals 11
.limit stack 200
  nop
  new java/lang/NoClassDefFoundError
  dup
  invokespecial java/lang/NoClassDefFoundError/<init>()V
  athrow
  fconst_0
  fstore_1
  fconst_0
  fstore_2
  ldc -50.000000
  fstore_3
  fconst_0
  fstore 4
  aload_0
  fload_1
  fload_2
  fload_3
  fload 4
  invokespecial android/view/animation/TranslateAnimation/<init>(FFFF)V
  ldc2_w 2500
  lstore 5
  aload_0
  lload 5
  invokevirtual android/view/animation/Animation/setDuration(J)V
  new android/view/animation/AccelerateInterpolator
  astore 7
  aload 7
  invokespecial android/view/animation/AccelerateInterpolator/<init>()V
  aload_0
  aload 7
  invokevirtual android/view/animation/Animation/setInterpolator(Landroid/view/animation/Interpolator;)V
  iconst_1
  istore 8
  aload_0
  iload 8
  invokevirtual android/view/animation/Animation/setFillAfter(Z)V
  new android/view/animation/AlphaAnimation
  astore 9
  fconst_0
  fstore_1
  fconst_1
  fstore_2
  aload 9
  fload_1
  fload_2
  invokespecial android/view/animation/AlphaAnimation/<init>(FF)V
  ldc2_w 500
  lstore 5
  aload 9
  lload 5
  invokevirtual android/view/animation/Animation/setDuration(J)V
  new android/view/animation/AccelerateInterpolator
  astore 7
  aload 7
  invokespecial android/view/animation/AccelerateInterpolator/<init>()V
  aload 9
  aload 7
  invokevirtual android/view/animation/Animation/setInterpolator(Landroid/view/animation/Interpolator;)V
  iconst_1
  istore 8
  aload 9
  iload 8
  invokevirtual android/view/animation/Animation/setFillAfter(Z)V
  new android/view/animation/AnimationSet
  astore 10
  iconst_1
  istore 8
  aload 10
  iload 8
  invokespecial android/view/animation/AnimationSet/<init>(Z)V
  aload 10
  aload_0
  invokevirtual android/view/animation/AnimationSet/addAnimation(Landroid/view/animation/Animation;)V
  aload 10
  aload 9
  invokevirtual android/view/animation/AnimationSet/addAnimation(Landroid/view/animation/Animation;)V
  aload 10
  areturn
  nop
.end <method>

