.source SourceFile
.class  cn/domob/android/ads/b/d$a
.super java/lang/Thread
.field final "a" Lcn/domob/android/ads/b/d;

.method private <init>(Lcn/domob/android/ads/b/d;)V
.limit locals 2
.limit stack 200
  nop
  aload_0
  aload_1
  putfield cn/domob/android/ads/b/d$a/a Lcn/domob/android/ads/b/d;
  aload_0
  invokespecial java/lang/Thread/<init>()V
  return
  nop
.end <method>

.method <init>(Lcn/domob/android/ads/b/d;Lcn/domob/android/ads/b/d$1;)V
  .synthetic
.limit locals 3
.limit stack 200
  nop
  aload_0
  aload_1
  invokespecial cn/domob/android/ads/b/d$a/<init>(Lcn/domob/android/ads/b/d;)V
  return
  nop
.end <method>

.method public run()V
.limit locals 12
.limit stack 200
  nop
  aload_0
  getfield cn/domob/android/ads/b/d$a/a Lcn/domob/android/ads/b/d;
  astore_1
  new java/lang/NoClassDefFoundError
  dup
  invokespecial java/lang/NoClassDefFoundError/<init>()V
  athrow
  nop
  aload_2
  invokestatic app/DummyClass/invokeIfStmt(Ljava/lang/Object;)V
  iload_2
  ifne Label0
Label1:
  return
Label3:
  aload_0
  getfield cn/domob/android/ads/b/d$a/a Lcn/domob/android/ads/b/d;
  astore_1
  aload 4
  getfield cn/domob/android/ads/b/c/a Landroid/graphics/Bitmap;
  astore_3
  aload_1
  aload_3
  invokestatic cn/domob/android/ads/b/d/a(Lcn/domob/android/ads/b/d;Landroid/graphics/Bitmap;)Landroid/graphics/Bitmap;
  pop
  aload 4
  getfield cn/domob/android/ads/b/c/b I
  istore 5
  iload 5
  i2l
  lstore 6
  aload_0
  getfield cn/domob/android/ads/b/d$a/a Lcn/domob/android/ads/b/d;
  astore_1
  aload_1
  invokestatic cn/domob/android/ads/b/d/d(Lcn/domob/android/ads/b/d;)Landroid/view/View;
  astore 8
  aload 8
  invokestatic app/DummyClass/invokeIfStmt(Ljava/lang/Object;)V
  aload 8
  ifnull Label1
  aload_0
  getfield cn/domob/android/ads/b/d$a/a Lcn/domob/android/ads/b/d;
  astore_1
  aload_1
  invokestatic cn/domob/android/ads/b/d/d(Lcn/domob/android/ads/b/d;)Landroid/view/View;
  astore 8
  aload 8
  invokevirtual android/view/View/postInvalidate()V
  lload 6
  invokestatic android/os/SystemClock/sleep(J)V
Label0:
  aload_0
  getfield cn/domob/android/ads/b/d$a/a Lcn/domob/android/ads/b/d;
  astore_1
  aload_1
  invokestatic cn/domob/android/ads/b/d/b(Lcn/domob/android/ads/b/d;)Z
  istore 9
  iload 9
  invokestatic app/DummyClass/invokeIfStmt(Z)V
  iload 9
  ifeq Label1
  aload_0
  getfield cn/domob/android/ads/b/d$a/a Lcn/domob/android/ads/b/d;
  astore_1
  aload_1
  invokestatic cn/domob/android/ads/b/d/c(Lcn/domob/android/ads/b/d;)Z
  istore 9
  iload 9
  invokestatic app/DummyClass/invokeIfStmt(Z)V
  iload 9
  ifne Label2
  aload_0
  getfield cn/domob/android/ads/b/d$a/a Lcn/domob/android/ads/b/d;
  astore_1
  aload_1
  invokestatic cn/domob/android/ads/b/d/a(Lcn/domob/android/ads/b/d;)Lcn/domob/android/ads/b/b;
  astore_2
  aload_2
  invokevirtual cn/domob/android/ads/b/b/j()Lcn/domob/android/ads/b/c;
  astore 4
  aload 4
  invokestatic app/DummyClass/invokeIfStmt(Ljava/lang/Object;)V
  aload 4
  ifnonnull Label3
  goto Label1
Label2:
  ldc2_w 50
  lstore 10
  lload 10
  invokestatic android/os/SystemClock/sleep(J)V
  goto Label0
  nop
.end <method>

