.source SourceFile
.class  cn/domob/android/ads/j$f
.super java/lang/Object
.field final "a" Lcn/domob/android/ads/j;
.field private "b" Ljava/lang/String;
.field private "c" Ljava/lang/String;
.field private "d" Ljava/lang/String;

.method protected <init>(Lcn/domob/android/ads/j;Ljava/lang/String;Lorg/json/JSONObject;)V
.limit locals 6
.limit stack 200
  nop
  aload_0
  aload_1
  putfield cn/domob/android/ads/j$f/a Lcn/domob/android/ads/j;
  aload_0
  invokespecial java/lang/Object/<init>()V
  aload_0
  aload_2
  putfield cn/domob/android/ads/j$f/b Ljava/lang/String;
  ldc "t"
  astore 4
  aconst_null
  astore 5
  aload_3
  aload 4
  aload 5
  invokevirtual org/json/JSONObject/optString(Ljava/lang/String;Ljava/lang/String;)Ljava/lang/String;
  astore_2
  aload_0
  aload_2
  putfield cn/domob/android/ads/j$f/c Ljava/lang/String;
  ldc "u"
  astore 4
  aconst_null
  astore 5
  aload_3
  aload 4
  aload 5
  invokevirtual org/json/JSONObject/optString(Ljava/lang/String;Ljava/lang/String;)Ljava/lang/String;
  astore_2
  aload_0
  aload_2
  putfield cn/domob/android/ads/j$f/d Ljava/lang/String;
  return
  nop
.end <method>

.method protected a()Ljava/lang/String;
.limit locals 2
.limit stack 200
  nop
  aload_0
  getfield cn/domob/android/ads/j$f/b Ljava/lang/String;
  astore_1
  aload_1
  areturn
  nop
.end <method>

.method protected b()Ljava/lang/String;
.limit locals 2
.limit stack 200
  nop
  aload_0
  getfield cn/domob/android/ads/j$f/c Ljava/lang/String;
  astore_1
  aload_1
  areturn
  nop
.end <method>

.method protected c()Ljava/lang/String;
.limit locals 2
.limit stack 200
  nop
  aload_0
  getfield cn/domob/android/ads/j$f/d Ljava/lang/String;
  astore_1
  aload_1
  areturn
  nop
.end <method>

.method public toString()Ljava/lang/String;
.limit locals 5
.limit stack 200
  nop
  new java/lang/StringBuilder
  astore_1
  aload_1
  invokespecial java/lang/StringBuilder/<init>()V
  ldc "Resource [tag="
  astore_3
  aload_1
  aload_3
  invokevirtual java/lang/StringBuilder/append(Ljava/lang/String;)Ljava/lang/StringBuilder;
  astore_2
  aload_0
  getfield cn/domob/android/ads/j$f/b Ljava/lang/String;
  astore 4
  aload_2
  aload 4
  invokevirtual java/lang/StringBuilder/append(Ljava/lang/String;)Ljava/lang/StringBuilder;
  astore_2
  ldc ", resouceType="
  astore_3
  aload_2
  aload_3
  invokevirtual java/lang/StringBuilder/append(Ljava/lang/String;)Ljava/lang/StringBuilder;
  astore_2
  aload_0
  getfield cn/domob/android/ads/j$f/c Ljava/lang/String;
  astore 4
  aload_2
  aload 4
  invokevirtual java/lang/StringBuilder/append(Ljava/lang/String;)Ljava/lang/StringBuilder;
  astore_2
  ldc ", resouceURL="
  astore_3
  aload_2
  aload_3
  invokevirtual java/lang/StringBuilder/append(Ljava/lang/String;)Ljava/lang/StringBuilder;
  astore_2
  aload_0
  getfield cn/domob/android/ads/j$f/d Ljava/lang/String;
  astore 4
  aload_2
  aload 4
  invokevirtual java/lang/StringBuilder/append(Ljava/lang/String;)Ljava/lang/StringBuilder;
  astore_2
  ldc "]"
  astore_3
  aload_2
  aload_3
  invokevirtual java/lang/StringBuilder/append(Ljava/lang/String;)Ljava/lang/StringBuilder;
  pop
  aload_1
  invokevirtual java/lang/StringBuilder/toString()Ljava/lang/String;
  astore 4
  aload 4
  areturn
  nop
.end <method>

