.source SourceFile
.class  cn/domob/android/ads/F
.super java/lang/Object
.implements  cn/domob/android/ads/M
.implements  cn/domob/android/ads/b
.field private static final "j" I =  0
.field private static final "k" I =  1
.field private static final "l" Ljava/lang/String; =  "def_"
.field private static final "m" Ljava/lang/String; =  ".gif"
.field private "a" Landroid/content/Context;
.field private "b" Lcn/domob/android/ads/e;
.field private "c" Ljava/util/HashSet;
.field private "d" Ljava/util/Hashtable;
.field private "e" Ljava/util/Hashtable;
.field private "f" Lcn/domob/android/ads/j;
.field private "g" Lcn/domob/android/ads/g;
.field private "h" Lcn/domob/android/ads/L;
.field private "i" Z

.method <init>()V
.limit locals 6
.limit stack 200
  nop
  aload_0
  invokespecial java/lang/Object/<init>()V
  new cn/domob/android/ads/e
  astore_1
  aload_1
  invokespecial cn/domob/android/ads/e/<init>()V
  aload_0
  aload_1
  putfield cn/domob/android/ads/F/b Lcn/domob/android/ads/e;
  new java/util/HashSet
  astore_2
  aload_2
  invokespecial java/util/HashSet/<init>()V
  aload_0
  aload_2
  putfield cn/domob/android/ads/F/c Ljava/util/HashSet;
  new java/util/Hashtable
  astore_3
  aload_3
  invokespecial java/util/Hashtable/<init>()V
  aload_0
  aload_3
  putfield cn/domob/android/ads/F/d Ljava/util/Hashtable;
  new java/util/Hashtable
  astore_3
  aload_3
  invokespecial java/util/Hashtable/<init>()V
  aload_0
  aload_3
  putfield cn/domob/android/ads/F/e Ljava/util/Hashtable;
  aconst_null
  astore 4
  aload_0
  aload 4
  putfield cn/domob/android/ads/F/h Lcn/domob/android/ads/L;
  iconst_0
  istore 5
  aload_0
  iload 5
  putfield cn/domob/android/ads/F/i Z
  return
  nop
.end <method>

.method private a(Ljava/lang/String;)Ljava/lang/String;
.limit locals 5
.limit stack 200
  nop
  new java/net/URI
  astore_2
  aload_2
  aload_1
  invokespecial java/net/URI/<init>(Ljava/lang/String;)V
  aload_2
  invokevirtual java/net/URI/getPath()Ljava/lang/String;
  astore_3
  ldc "UTF-8"
  astore 4
  aload_3
  aload 4
  invokestatic java/net/URLEncoder/encode(Ljava/lang/String;Ljava/lang/String;)Ljava/lang/String;
  astore_3
  aload_3
  areturn
  nop
.end <method>

.method private a()V
.limit locals 10
.limit stack 200
  .catch  java/lang/Throwable <from> Label4 <to> Label5 <using> Label3
  .catch  java/lang/Throwable <from> Label0 <to> Label6 <using> Label3
  nop
  aload_0
  getfield cn/domob/android/ads/F/c Ljava/util/HashSet;
  astore_1
  aload_1
  monitorenter
Label4:
  ldc "Do all requests"
  astore_2
  aload_0
  aload_2
  invokestatic cn/domob/android/ads/J/d(Ljava/lang/Object;Ljava/lang/String;)V
  aload_0
  getfield cn/domob/android/ads/F/c Ljava/util/HashSet;
  astore_3
  aload_3
  invokevirtual java/util/HashSet/iterator()Ljava/util/Iterator;
  astore 4
Label1:
  aload 4
  invokeinterface java/util/Iterator/hasNext()Z 1
  istore 5
  new java/lang/NoClassDefFoundError
  dup
  invokespecial java/lang/NoClassDefFoundError/<init>()V
  athrow
  iload 5
  ifeq Label0
  aload 4
  invokeinterface java/util/Iterator/next()Ljava/lang/Object; 1
  astore 6
  aload 6
  astore 8
  aload 8
  checkcast cn/domob/android/ads/n
  astore 8
  aload 8
  astore 7
  aload 7
  invokevirtual cn/domob/android/ads/n/c()V
  goto Label1
Label3:
  astore 9
  aload_1
  monitorexit
Label5:
  aload 9
  athrow
Label0:
  aload_1
  monitorexit
Label6:
  aload_0
  invokespecial cn/domob/android/ads/F/b()Z
  istore 5
  iload 5
  invokestatic app/DummyClass/invokeIfStmt(Z)V
  iload 5
  ifeq Label2
  aload_0
  invokespecial cn/domob/android/ads/F/c()V
Label2:
  return
  nop
.end <method>

.method public a(Lcn/domob/android/ads/L;Ljava/lang/String;)V
.limit locals 5
.limit stack 200
  nop
  iconst_0
  istore_3
  aload_0
  iload_3
  putfield cn/domob/android/ads/F/i Z
  aload_0
  aload_1
  putfield cn/domob/android/ads/F/h Lcn/domob/android/ads/L;
  aload_0
  invokespecial cn/domob/android/ads/F/b()Z
  istore 4
  new java/lang/NoClassDefFoundError
  dup
  invokespecial java/lang/NoClassDefFoundError/<init>()V
  athrow
  iload 4
  ifeq Label0
  aload_0
  invokespecial cn/domob/android/ads/F/c()V
Label0:
  return
  nop
.end <method>

.method protected a(Lcn/domob/android/ads/g;Lcn/domob/android/ads/j;)V
.limit locals 9
.limit stack 200
  nop
  new java/lang/NoClassDefFoundError
  dup
  invokespecial java/lang/NoClassDefFoundError/<init>()V
  athrow
  iload_2
  ifeq Label0
  aload_2
  invokevirtual cn/domob/android/ads/j/a()Landroid/content/Context;
  astore_3
  aload_0
  aload_3
  putfield cn/domob/android/ads/F/a Landroid/content/Context;
  aload_0
  aload_2
  putfield cn/domob/android/ads/F/f Lcn/domob/android/ads/j;
  aload_0
  aload_1
  putfield cn/domob/android/ads/F/g Lcn/domob/android/ads/g;
  aload_2
  invokevirtual cn/domob/android/ads/j/g()Lcn/domob/android/ads/j$d;
  astore 4
  aload 4
  invokevirtual cn/domob/android/ads/j$d/a()Ljava/util/ArrayList;
  astore 5
  aload 4
  invokevirtual cn/domob/android/ads/j$d/b()Ljava/util/ArrayList;
  astore 6
  aload 5
  invokevirtual java/util/ArrayList/isEmpty()Z
  istore 7
  iload 7
  invokestatic app/DummyClass/invokeIfStmt(Z)V
  iload 7
  ifne Label1
  aload 6
  invokevirtual java/util/ArrayList/isEmpty()Z
  istore 7
  iload 7
  invokestatic app/DummyClass/invokeIfStmt(Z)V
  iload 7
  ifne Label1
  aload_0
  aload 5
  invokespecial cn/domob/android/ads/F/a(Ljava/util/ArrayList;)Z
  istore 7
  iload 7
  invokestatic app/DummyClass/invokeIfStmt(Z)V
  iload 7
  ifeq Label2
  aload_0
  invokespecial cn/domob/android/ads/F/a()V
Label0:
  return
Label2:
  aload_1
  invokestatic app/DummyClass/invokeIfStmt(Ljava/lang/Object;)V
  iload_1
  ifeq Label0
  ldc "\u6dfb\u52a0\u8d44\u6e90\u65f6\u51fa\u73b0\u9519\u8bef\u3002"
  astore 8
  aload_0
  aload 8
  invokestatic cn/domob/android/ads/J/b(Ljava/lang/Object;Ljava/lang/String;)V
  ldc "\u6dfb\u52a0\u8d44\u6e90\u65f6\u51fa\u73b0\u9519\u8bef\u3002"
  astore 8
  aload_1
  aload 8
  invokevirtual cn/domob/android/ads/g/a(Ljava/lang/String;)V
  goto Label0
Label1:
  aload_1
  invokestatic app/DummyClass/invokeIfStmt(Ljava/lang/Object;)V
  iload_1
  ifeq Label0
  ldc "\u8d44\u6e90\u63cf\u8ff0\u6216\u754c\u9762\u7ed8\u5236\u63cf\u8ff0\u4e3a\u7a7a"
  astore 8
  aload_0
  aload 8
  invokestatic cn/domob/android/ads/J/b(Ljava/lang/Object;Ljava/lang/String;)V
  ldc "\u8d44\u6e90\u63cf\u8ff0\u6216\u754c\u9762\u7ed8\u5236\u63cf\u8ff0\u4e3a\u7a7a"
  astore 8
  aload_1
  aload 8
  invokevirtual cn/domob/android/ads/g/a(Ljava/lang/String;)V
  goto Label0
  nop
.end <method>

.method public a(Lcn/domob/android/ads/n;)V
.limit locals 35
.limit stack 200
  nop
  aload_1
  astore_2
  aload_2
  invokevirtual cn/domob/android/ads/n/e()Ljava/lang/String;
  astore 5
  aload_1
  astore_2
  aload_2
  invokevirtual cn/domob/android/ads/n/f()[B
  astore 6
  aload_0
  astore_2
  aload_2
  getfield cn/domob/android/ads/F/a Landroid/content/Context;
  astore 7
  new java/lang/NoClassDefFoundError
  dup
  invokespecial java/lang/NoClassDefFoundError/<init>()V
  athrow
  nop
  aload 6
  invokestatic app/DummyClass/invokeIfStmt(Ljava/lang/Object;)V
  iload 6
  ifeq Label0
  aload_0
  astore_2
  aload_2
  getfield cn/domob/android/ads/F/d Ljava/util/Hashtable;
  astore 9
  aload 9
  aload 5
  aload 6
  invokevirtual java/util/Hashtable/put(Ljava/lang/Object;Ljava/lang/Object;)Ljava/lang/Object;
  pop
  aload_0
  astore_2
  aload_2
  getfield cn/domob/android/ads/F/e Ljava/util/Hashtable;
  astore 9
  aload 9
  aload 5
  invokevirtual java/util/Hashtable/get(Ljava/lang/Object;)Ljava/lang/Object;
  astore 10
  aload 10
  astore 12
  aload 12
  checkcast [Ljava/lang/String;
  astore 12
  aload 12
  astore 11
  iconst_0
  istore 14
  aload 11
  iload 14
  aaload
  astore 13
  aload_0
  astore_2
  aload_2
  getfield cn/domob/android/ads/F/e Ljava/util/Hashtable;
  astore 9
  aload 9
  aload 5
  invokevirtual java/util/Hashtable/get(Ljava/lang/Object;)Ljava/lang/Object;
  astore 10
  aload 10
  astore 15
  aload 15
  checkcast [Ljava/lang/String;
  astore 15
  aload 15
  astore 11
  iconst_1
  istore 14
  aload 11
  iload 14
  aaload
  astore 16
  aload 13
  invokestatic app/DummyClass/invokeIfStmt(Ljava/lang/Object;)V
  aload 13
  ifnull Label1
Label7:
  aload_0
  astore_2
  aload_2
  aload 13
  invokespecial cn/domob/android/ads/F/a(Ljava/lang/String;)Ljava/lang/String;
  astore 17
  ldc "def_"
  astore 19
  aload 19
  astore_2
  aload 16
  aload_2
  invokevirtual java/lang/String/startsWith(Ljava/lang/String;)Z
  istore 18
  iload 18
  istore_2
  iload_2
  invokestatic app/DummyClass/invokeIfStmt(Z)V
  iload 18
  ifeq Label2
  new java/lang/StringBuilder
  astore 20
  aload 20
  astore_2
  aload_2
  invokespecial java/lang/StringBuilder/<init>()V
  ldc "Save image to res: "
  astore 19
  aload 20
  astore_2
  aload 19
  astore_3
  aload_2
  aload_3
  invokevirtual java/lang/StringBuilder/append(Ljava/lang/String;)Ljava/lang/StringBuilder;
  astore 20
  aload 20
  astore_2
  aload_2
  aload 17
  invokevirtual java/lang/StringBuilder/append(Ljava/lang/String;)Ljava/lang/StringBuilder;
  astore 20
  aload 20
  astore_2
  aload_2
  invokevirtual java/lang/StringBuilder/toString()Ljava/lang/String;
  astore 16
  aload_0
  astore_2
  aload_2
  aload 16
  invokestatic cn/domob/android/ads/J/d(Ljava/lang/Object;Ljava/lang/String;)V
  invokestatic java/lang/System/currentTimeMillis()J
  lstore 21
  lload 21
  lstore_2
  aload 8
  aload 17
  aload 6
  lload_2
  invokestatic cn/domob/android/ads/d/a(Lcn/domob/android/ads/d;Ljava/lang/String;[BJ)V
Label1:
  aload_0
  astore_2
  aload_2
  getfield cn/domob/android/ads/F/c Ljava/util/HashSet;
  astore_2
  aload_2
  astore 23
  aload 23
  monitorenter
Label9:
  aload_0
  astore_2
  aload_2
  getfield cn/domob/android/ads/F/c Ljava/util/HashSet;
  astore_2
  aload_2
  astore 24
  aload 24
  astore_2
  aload_1
  astore_3
  aload_2
  aload_3
  invokevirtual java/util/HashSet/remove(Ljava/lang/Object;)Z
  pop
  aload 23
  monitorexit
Label10:
  aload_0
  astore_2
  aload_2
  invokespecial cn/domob/android/ads/F/b()Z
  istore 18
  iload 18
  istore_2
  iload_2
  invokestatic app/DummyClass/invokeIfStmt(Z)V
  iload 18
  ifeq Label3
  aload_0
  astore_2
  aload_2
  invokespecial cn/domob/android/ads/F/c()V
Label3:
  return
Label2:
  new java/lang/StringBuilder
  astore 20
Label11:
  aload 20
  astore_2
  aload_2
  invokespecial java/lang/StringBuilder/<init>()V
  ldc "Save image to cache: "
  astore 19
  aload 20
  astore_2
  aload 19
  astore_3
  aload_2
  aload_3
  invokevirtual java/lang/StringBuilder/append(Ljava/lang/String;)Ljava/lang/StringBuilder;
  astore 20
  aload 20
  astore_2
  aload_2
  aload 17
  invokevirtual java/lang/StringBuilder/append(Ljava/lang/String;)Ljava/lang/StringBuilder;
  astore 20
  aload 20
  astore_2
  aload_2
  invokevirtual java/lang/StringBuilder/toString()Ljava/lang/String;
  astore 16
  aload_0
  astore_2
  aload_2
  aload 16
  invokestatic cn/domob/android/ads/J/d(Ljava/lang/Object;Ljava/lang/String;)V
  aload_0
  astore_2
  aload_2
  getfield cn/domob/android/ads/F/b Lcn/domob/android/ads/e;
  astore_2
  aload_2
  astore 25
  aload 25
  astore_2
  aload_2
  aload 8
  aload 17
  aload 6
  invokevirtual cn/domob/android/ads/e/a(Lcn/domob/android/ads/d;Ljava/lang/String;[B)V
Label12:
  goto Label1
Label6:
  astore 26
  new java/lang/StringBuilder
  astore 20
  aload 20
  astore_2
  aload_2
  invokespecial java/lang/StringBuilder/<init>()V
  ldc "\u8d44\u6e90\u5b58\u50a8\u5931\u8d25\uff0cURLEncode\u9519\u8bef\uff1a"
  astore 19
  aload 20
  astore_2
  aload 19
  astore_3
  aload_2
  aload_3
  invokevirtual java/lang/StringBuilder/append(Ljava/lang/String;)Ljava/lang/StringBuilder;
  astore 20
  aload 20
  astore_2
  aload_2
  aload 13
  invokevirtual java/lang/StringBuilder/append(Ljava/lang/String;)Ljava/lang/StringBuilder;
  astore 20
  aload 20
  astore_2
  aload_2
  invokevirtual java/lang/StringBuilder/toString()Ljava/lang/String;
  astore 17
  aload_0
  astore_2
  aload_2
  aload 17
  invokestatic cn/domob/android/ads/J/b(Ljava/lang/Object;Ljava/lang/String;)V
  goto Label1
Label0:
  aload_0
  astore_2
  aload_2
  getfield cn/domob/android/ads/F/f Lcn/domob/android/ads/j;
  astore_2
  aload_2
  astore 27
  aload 27
  astore_2
  aload_2
  invokevirtual cn/domob/android/ads/j/g()Lcn/domob/android/ads/j$d;
  astore 28
  aload 28
  astore_2
  aload_2
  invokevirtual cn/domob/android/ads/j$d/b()Ljava/util/ArrayList;
  astore 29
  aload 29
  astore_2
  aload_2
  invokevirtual java/util/ArrayList/iterator()Ljava/util/Iterator;
  astore 30
Label4:
  aload 30
  astore_2
  aload_2
  invokeinterface java/util/Iterator/hasNext()Z 1
  istore 18
  iload 18
  istore_2
  iload_2
  invokestatic app/DummyClass/invokeIfStmt(Z)V
  iload 18
  ifeq Label1
  aload 30
  astore_2
  aload_2
  invokeinterface java/util/Iterator/next()Ljava/lang/Object; 1
  astore 10
  aload 10
  astore 32
  aload 32
  checkcast cn/domob/android/ads/j$h
  astore 32
  aload 32
  astore 31
  aload 31
  astore_2
  aload_2
  invokevirtual cn/domob/android/ads/j$h/b()Ljava/lang/String;
  astore 17
  aload 5
  aload 17
  invokevirtual java/lang/String/equals(Ljava/lang/Object;)Z
  istore 18
  iload 18
  istore_2
  iload_2
  invokestatic app/DummyClass/invokeIfStmt(Z)V
  iload 18
  ifeq Label4
  aload 31
  astore_2
  aload_2
  invokevirtual cn/domob/android/ads/j$h/m()Ljava/lang/String;
  astore 17
  aload 17
  invokestatic app/DummyClass/invokeIfStmt(Ljava/lang/Object;)V
  aload 17
  ifnull Label5
  aload_0
  astore_2
  aload_2
  getfield cn/domob/android/ads/F/b Lcn/domob/android/ads/e;
  astore_2
  aload_2
  astore 25
  new java/lang/StringBuilder
  astore 20
  aload 20
  astore_2
  aload_2
  invokespecial java/lang/StringBuilder/<init>()V
  aload 20
  astore_2
  aload_2
  aload 17
  invokevirtual java/lang/StringBuilder/append(Ljava/lang/String;)Ljava/lang/StringBuilder;
  astore 20
  ldc ".png"
  astore 19
  aload 20
  astore_2
  aload 19
  astore_3
  aload_2
  aload_3
  invokevirtual java/lang/StringBuilder/append(Ljava/lang/String;)Ljava/lang/StringBuilder;
  astore 20
  aload 20
  astore_2
  aload_2
  invokevirtual java/lang/StringBuilder/toString()Ljava/lang/String;
  astore 17
  aload_0
  astore_2
  aload_2
  getfield cn/domob/android/ads/F/d Ljava/util/Hashtable;
  astore 9
  aload 25
  astore_2
  aload_2
  aload 8
  aload 5
  aload 17
  aload 9
  invokevirtual cn/domob/android/ads/e/b(Lcn/domob/android/ads/d;Ljava/lang/String;Ljava/lang/String;Ljava/util/Hashtable;)Z
  istore 18
  iload 18
  istore_2
  iload_2
  invokestatic app/DummyClass/invokeIfStmt(Z)V
  iload 18
  ifeq Label5
  ldc "\u4f7f\u7528backup\u8d44\u6e90\u3002"
  astore 19
  aload_0
  astore_2
  aload 19
  astore_3
  aload_2
  aload_3
  invokestatic cn/domob/android/ads/J/a(Ljava/lang/Object;Ljava/lang/String;)V
  goto Label4
Label5:
  ldc "Backup\u8d44\u6e90\u8bfb\u53d6\u5931\u8d25\u3002"
  astore 19
  aload_0
  astore_2
  aload 19
  astore_3
  aload_2
  aload_3
  invokestatic cn/domob/android/ads/J/b(Ljava/lang/Object;Ljava/lang/String;)V
  aload_0
  astore_2
  aload_2
  getfield cn/domob/android/ads/F/g Lcn/domob/android/ads/g;
  astore_2
  aload_2
  astore 33
  ldc "\u56fe\u7247\u4e0b\u8f7d\u5931\u8d25\u4e14Backup\u8d44\u6e90\u8bfb\u53d6\u5931\u8d25\u3002"
  astore 19
  aload 33
  astore_2
  aload 19
  astore_3
  aload_2
  aload_3
  invokevirtual cn/domob/android/ads/g/a(Ljava/lang/String;)V
  goto Label3
Label8:
  astore 34
Label13:
  aload 23
  monitorexit
Label14:
  aload 34
  athrow
  nop
.end <method>

.method public a(Lcn/domob/android/ads/n;Ljava/lang/Exception;)V
.limit locals 3
.limit stack 200
  nop
  return
  nop
.end <method>

.method private a(Ljava/util/ArrayList;)Z
  .signature_attr "(Ljava/util/ArrayList<Lcn/domob/android/ads/j$f;>;)Z"
.limit locals 35
.limit stack 200
  .catch  java/lang/Exception <from> Label11 <to> Label12 <using> Label10
  .catch  java/lang/Exception <from> Label14 <to> Label10 <using> Label10
  nop
Label11:
  aload_0
  astore_2
  aload_2
  getfield cn/domob/android/ads/F/c Ljava/util/HashSet;
  astore 5
  aload 5
  invokevirtual java/util/HashSet/isEmpty()Z
  istore 6
  new java/lang/NoClassDefFoundError
  dup
  invokespecial java/lang/NoClassDefFoundError/<init>()V
  athrow
  iload 6
  ifne Label0
  aload_0
  astore_2
  aload_2
  getfield cn/domob/android/ads/F/c Ljava/util/HashSet;
  astore 5
  aload 5
  invokevirtual java/util/HashSet/clear()V
Label0:
  aload_0
  astore_2
  aload_2
  getfield cn/domob/android/ads/F/c Ljava/util/HashSet;
  astore 5
  aload 5
  monitorenter
Label12:
  aload_0
  astore_2
  aload_2
  getfield cn/domob/android/ads/F/a Landroid/content/Context;
  astore 7
  aload 7
  invokestatic cn/domob/android/ads/d/a(Landroid/content/Context;)Lcn/domob/android/ads/d;
  astore 8
  aload_1
  astore_2
  aload_2
  invokevirtual java/util/ArrayList/iterator()Ljava/util/Iterator;
  astore 9
Label4:
  aload 9
  invokeinterface java/util/Iterator/hasNext()Z 1
  istore 6
  iload 6
  invokestatic app/DummyClass/invokeIfStmt(Z)V
  iload 6
  ifeq Label1
  aload 9
  invokeinterface java/util/Iterator/next()Ljava/lang/Object; 1
  astore 10
  aload 10
  astore 12
  aload 12
  checkcast cn/domob/android/ads/j$f
  astore 12
  aload 12
  astore 11
  aload 11
  invokevirtual cn/domob/android/ads/j$f/b()Ljava/lang/String;
  astore 13
  aload 11
  invokevirtual cn/domob/android/ads/j$f/a()Ljava/lang/String;
  astore 14
  aload 11
  invokevirtual cn/domob/android/ads/j$f/c()Ljava/lang/String;
  astore 15
  getstatic cn/domob/android/ads/F$1/a [I
  astore 16
  aload 13
  invokestatic cn/domob/android/ads/j$i/a(Ljava/lang/String;)Lcn/domob/android/ads/j$i;
  astore 17
  aload 17
  invokevirtual cn/domob/android/ads/j$i/ordinal()I
  istore 18
  aload 16
  iload 18
  iaload
  istore 18
  iload 18
  istore_2
  dload_2
  invokestatic app/DummyClass/invokeIfStmt(D)V
  iload 18
  lookupswitch
  1 : Label3
  2 : Label4
  3 : Label4
  4 : Label5
  default : Label2
Label2:
  goto Label6
Label6:
  goto Label4
Label3:
  aload 14
  invokestatic app/DummyClass/invokeIfStmt(Ljava/lang/Object;)V
  aload 14
  ifnull Label4
  aload 15
  invokestatic app/DummyClass/invokeIfStmt(Ljava/lang/Object;)V
  aload 15
  ifnull Label4
  ldc "/"
  astore 19
  aload 19
  astore_2
  aload 15
  aload_2
  invokevirtual java/lang/String/lastIndexOf(Ljava/lang/String;)I
  istore 18
  iload 18
  iconst_1
  iadd
  istore 18
  iload 18
  istore_2
  aload 15
  iload_2
  invokevirtual java/lang/String/substring(I)Ljava/lang/String;
  astore 13
  aload_0
  astore_2
  aload_2
  getfield cn/domob/android/ads/F/e Ljava/util/Hashtable;
  astore_2
  aload_2
  astore 20
  iconst_2
  istore 22
  iload 22
  istore_2
  iload_2
  anewarray java/lang/String
  astore_2
  aload_2
  astore 21
  iconst_0
  istore 22
  aload 21
  iload 22
  aload 15
  aastore
  iconst_1
  istore 22
  aload 21
  iload 22
  aload 13
  aastore
  aload 20
  astore_2
  aload 21
  astore_3
  aload_2
  aload 14
  aload_3
  invokevirtual java/util/Hashtable/put(Ljava/lang/Object;Ljava/lang/Object;)Ljava/lang/Object;
  pop
  new java/lang/StringBuilder
  astore 23
  aload 23
  astore_2
  aload_2
  invokespecial java/lang/StringBuilder/<init>()V
  ldc "Image name = "
  astore 19
  aload 23
  astore_2
  aload 19
  astore_3
  aload_2
  aload_3
  invokevirtual java/lang/StringBuilder/append(Ljava/lang/String;)Ljava/lang/StringBuilder;
  astore 23
  aload 23
  astore_2
  aload_2
  aload 13
  invokevirtual java/lang/StringBuilder/append(Ljava/lang/String;)Ljava/lang/StringBuilder;
  astore 23
  aload 23
  astore_2
  aload_2
  invokevirtual java/lang/StringBuilder/toString()Ljava/lang/String;
  astore 24
  aload_0
  astore_2
  aload 24
  astore_3
  aload_2
  aload_3
  invokestatic cn/domob/android/ads/J/d(Ljava/lang/Object;Ljava/lang/String;)V
  aload_0
  astore_2
  aload_2
  aload 15
  invokespecial cn/domob/android/ads/F/a(Ljava/lang/String;)Ljava/lang/String;
  astore 24
  new java/lang/StringBuilder
  astore 23
  aload 23
  astore_2
  aload_2
  invokespecial java/lang/StringBuilder/<init>()V
  ldc "dbKey(uri)"
  astore 19
  aload 23
  astore_2
  aload 19
  astore_3
  aload_2
  aload_3
  invokevirtual java/lang/StringBuilder/append(Ljava/lang/String;)Ljava/lang/StringBuilder;
  astore 23
  aload 23
  astore_2
  aload 24
  astore_3
  aload_2
  aload_3
  invokevirtual java/lang/StringBuilder/append(Ljava/lang/String;)Ljava/lang/StringBuilder;
  astore 23
  aload 23
  astore_2
  aload_2
  invokevirtual java/lang/StringBuilder/toString()Ljava/lang/String;
  astore 25
  aload_0
  astore_2
  aload 25
  astore_3
  aload_2
  aload_3
  invokestatic cn/domob/android/ads/J/d(Ljava/lang/Object;Ljava/lang/String;)V
  ldc "def_"
  astore 19
  aload 19
  astore_2
  aload 13
  aload_2
  invokevirtual java/lang/String/startsWith(Ljava/lang/String;)Z
  istore 6
  iload 6
  invokestatic app/DummyClass/invokeIfStmt(Z)V
  iload 6
  ifeq Label7
  aload_0
  astore_2
  aload_2
  getfield cn/domob/android/ads/F/b Lcn/domob/android/ads/e;
  astore_2
  aload_2
  astore 26
  aload_0
  astore_2
  aload_2
  getfield cn/domob/android/ads/F/d Ljava/util/Hashtable;
  astore_2
  aload_2
  astore 20
  aload 26
  astore_2
  aload 24
  astore_3
  aload 20
  astore 4
  aload_2
  aload 8
  aload 14
  aload_3
  aload 4
  invokevirtual cn/domob/android/ads/e/b(Lcn/domob/android/ads/d;Ljava/lang/String;Ljava/lang/String;Ljava/util/Hashtable;)Z
  istore 6
  iload 6
  invokestatic app/DummyClass/invokeIfStmt(Z)V
  iload 6
  ifeq Label8
  new java/lang/StringBuilder
  astore 23
  aload 23
  astore_2
  aload_2
  invokespecial java/lang/StringBuilder/<init>()V
  ldc "Load "
  astore 19
  aload 23
  astore_2
  aload 19
  astore_3
  aload_2
  aload_3
  invokevirtual java/lang/StringBuilder/append(Ljava/lang/String;)Ljava/lang/StringBuilder;
  astore 23
  aload 23
  astore_2
  aload_2
  aload 15
  invokevirtual java/lang/StringBuilder/append(Ljava/lang/String;)Ljava/lang/StringBuilder;
  astore 23
  ldc " from resource database."
  astore 19
  aload 23
  astore_2
  aload 19
  astore_3
  aload_2
  aload_3
  invokevirtual java/lang/StringBuilder/append(Ljava/lang/String;)Ljava/lang/StringBuilder;
  astore 23
  aload 23
  astore_2
  aload_2
  invokevirtual java/lang/StringBuilder/toString()Ljava/lang/String;
  astore 25
  aload_0
  astore_2
  aload 25
  astore_3
  aload_2
  aload_3
  invokestatic cn/domob/android/ads/J/d(Ljava/lang/Object;Ljava/lang/String;)V
  goto Label4
Label13:
  astore 27
  aload 5
  monitorexit
Label14:
  aload 27
  athrow
Label10:
  astore 28
  aload 28
  astore_2
  aload_2
  invokestatic cn/domob/android/ads/J/a(Ljava/lang/Throwable;)V
  iconst_0
  istore 22
  iload 22
  ireturn
Label7:
  aload_0
  astore_2
  aload_2
  getfield cn/domob/android/ads/F/b Lcn/domob/android/ads/e;
  astore_2
  aload_2
  astore 26
  aload_0
  astore_2
  aload_2
  getfield cn/domob/android/ads/F/d Ljava/util/Hashtable;
  astore_2
  aload_2
  astore 20
  aload 26
  astore_2
  aload 24
  astore_3
  aload 20
  astore 4
  aload_2
  aload 8
  aload 14
  aload_3
  aload 4
  invokevirtual cn/domob/android/ads/e/a(Lcn/domob/android/ads/d;Ljava/lang/String;Ljava/lang/String;Ljava/util/Hashtable;)Z
  istore 6
  iload 6
  invokestatic app/DummyClass/invokeIfStmt(Z)V
  iload 6
  ifeq Label8
  new java/lang/StringBuilder
  astore 23
  aload 23
  astore_2
  aload_2
  invokespecial java/lang/StringBuilder/<init>()V
  ldc "Load "
  astore 19
  aload 23
  astore_2
  aload 19
  astore_3
  aload_2
  aload_3
  invokevirtual java/lang/StringBuilder/append(Ljava/lang/String;)Ljava/lang/StringBuilder;
  astore 23
  aload 23
  astore_2
  aload_2
  aload 15
  invokevirtual java/lang/StringBuilder/append(Ljava/lang/String;)Ljava/lang/StringBuilder;
  astore 23
  ldc " from cache database."
  astore 19
  aload 23
  astore_2
  aload 19
  astore_3
  aload_2
  aload_3
  invokevirtual java/lang/StringBuilder/append(Ljava/lang/String;)Ljava/lang/StringBuilder;
  astore 23
  aload 23
  astore_2
  aload_2
  invokevirtual java/lang/StringBuilder/toString()Ljava/lang/String;
  astore 25
  aload_0
  astore_2
  aload 25
  astore_3
  aload_2
  aload_3
  invokestatic cn/domob/android/ads/J/d(Ljava/lang/Object;Ljava/lang/String;)V
  goto Label4
Label8:
  new java/lang/StringBuilder
  astore 23
  aload 23
  astore_2
  aload_2
  invokespecial java/lang/StringBuilder/<init>()V
  ldc "Should download resource:"
  astore 19
  aload 23
  astore_2
  aload 19
  astore_3
  aload_2
  aload_3
  invokevirtual java/lang/StringBuilder/append(Ljava/lang/String;)Ljava/lang/StringBuilder;
  astore 23
  aload 23
  astore_2
  aload_2
  aload 15
  invokevirtual java/lang/StringBuilder/append(Ljava/lang/String;)Ljava/lang/StringBuilder;
  astore 23
  aload 23
  astore_2
  aload_2
  invokevirtual java/lang/StringBuilder/toString()Ljava/lang/String;
  astore 25
  aload_0
  astore_2
  aload 25
  astore_3
  aload_2
  aload_3
  invokestatic cn/domob/android/ads/J/d(Ljava/lang/Object;Ljava/lang/String;)V
  invokestatic cn/domob/android/ads/p/a()Lcn/domob/android/ads/p;
  astore 29
  aload_0
  astore_2
  aload_2
  getfield cn/domob/android/ads/F/a Landroid/content/Context;
  astore 7
  aload 29
  astore_2
  aload_2
  aload 7
  invokevirtual cn/domob/android/ads/p/x(Landroid/content/Context;)Ljava/lang/String;
  astore 25
  invokestatic cn/domob/android/ads/p/a()Lcn/domob/android/ads/p;
  astore 29
  aload_0
  astore_2
  aload_2
  getfield cn/domob/android/ads/F/a Landroid/content/Context;
  astore 7
  aload 29
  astore_2
  aload_2
  aload 7
  invokevirtual cn/domob/android/ads/p/d(Landroid/content/Context;)Ljava/lang/String;
  astore 24
  aload 25
  astore_2
  aload 24
  astore_3
  aload_0
  astore 4
  aload 15
  aload 14
  aload_2
  aload_3
  aload 4
  invokestatic cn/domob/android/ads/a/a(Ljava/lang/String;Ljava/lang/String;Ljava/lang/String;Ljava/lang/String;Lcn/domob/android/ads/b;)Lcn/domob/android/ads/n;
  astore 30
  aload_0
  astore_2
  aload_2
  getfield cn/domob/android/ads/F/a Landroid/content/Context;
  astore 7
  aload 30
  astore_2
  aload_2
  aload 7
  invokevirtual cn/domob/android/ads/n/a(Landroid/content/Context;)V
  aload_0
  astore_2
  aload_2
  getfield cn/domob/android/ads/F/c Ljava/util/HashSet;
  astore_2
  aload_2
  astore 31
  aload 31
  astore_2
  aload 30
  astore_3
  aload_2
  aload_3
  invokevirtual java/util/HashSet/add(Ljava/lang/Object;)Z
  pop
  goto Label4
Label5:
  aload_0
  astore_2
  aload_2
  getfield cn/domob/android/ads/F/g Lcn/domob/android/ads/g;
  astore_2
  aload_2
  astore 32
  aload 32
  astore_2
  aload_2
  invokevirtual cn/domob/android/ads/g/v()Lcn/domob/android/ads/L;
  astore 33
  aload 33
  astore_2
  aload_2
  invokestatic app/DummyClass/invokeIfStmt(Ljava/lang/Object;)V
  aload 33
  ifnull Label9
  new cn/domob/android/ads/N
  astore 34
  aload_0
  astore_2
  aload_2
  getfield cn/domob/android/ads/F/a Landroid/content/Context;
  astore 7
  aload 34
  astore_2
  aload_0
  astore_3
  aload_2
  aload_3
  aload 7
  invokespecial cn/domob/android/ads/N/<init>(Lcn/domob/android/ads/M;Landroid/content/Context;)V
  aload 34
  astore_2
  aload 33
  astore_3
  aload_2
  aload_3
  aload 14
  aload 15
  invokevirtual cn/domob/android/ads/N/a(Lcn/domob/android/ads/L;Ljava/lang/String;Ljava/lang/String;)V
  iconst_1
  istore 22
  iload 22
  istore_2
  aload_0
  astore_3
  aload_3
  iload_2
  putfield cn/domob/android/ads/F/i Z
  goto Label4
Label9:
  ldc "There is no available webview."
  astore 19
  aload_0
  astore_2
  aload 19
  astore_3
  aload_2
  aload_3
  invokestatic cn/domob/android/ads/J/b(Ljava/lang/Object;Ljava/lang/String;)V
  aload 5
  monitorexit
  iconst_0
  istore 22
  iload 22
  ireturn
Label1:
  aload 5
  monitorexit
Label15:
  iconst_1
  istore 22
  iload 22
  ireturn
  nop
  nop
.end <method>

.method public b(Lcn/domob/android/ads/L;Ljava/lang/String;)V
.limit locals 5
.limit stack 200
  nop
  aload_0
  getfield cn/domob/android/ads/F/g Lcn/domob/android/ads/g;
  astore_3
  ldc "WebView \u52a0\u8f7d\u5931\u8d25\uff01"
  astore 4
  aload_3
  aload 4
  invokevirtual cn/domob/android/ads/g/a(Ljava/lang/String;)V
  return
  nop
.end <method>

.method private b()Z
.limit locals 11
.limit stack 200
  .catch  java/lang/Throwable <from> Label5 <to> Label2 <using> Label4
  .catch  java/lang/Throwable <from> Label0 <to> Label6 <using> Label4
  nop
  iconst_1
  istore_1
  aload_0
  monitorenter
Label5:
  aload_0
  getfield cn/domob/android/ads/F/c Ljava/util/HashSet;
  astore_2
  aload_2
  invokevirtual java/util/HashSet/isEmpty()Z
  istore_3
  new java/lang/NoClassDefFoundError
  dup
  invokespecial java/lang/NoClassDefFoundError/<init>()V
  athrow
  iload_3
  ifeq Label0
  aload_0
  getfield cn/domob/android/ads/F/i Z
  istore_3
  iload_3
  invokestatic app/DummyClass/invokeIfStmt(Z)V
  iload_3
  ifne Label0
  ldc "All resources are ok!"
  astore 4
  aload_0
  aload 4
  invokestatic cn/domob/android/ads/J/d(Ljava/lang/Object;Ljava/lang/String;)V
  new java/lang/StringBuilder
  astore 5
  aload 5
  invokespecial java/lang/StringBuilder/<init>()V
  ldc "Timestamp[Complete downloading resources]:"
  astore 4
  aload 5
  aload 4
  invokevirtual java/lang/StringBuilder/append(Ljava/lang/String;)Ljava/lang/StringBuilder;
  astore 5
  invokestatic java/lang/System/currentTimeMillis()J
  lstore 6
  aload 5
  lload 6
  invokevirtual java/lang/StringBuilder/append(J)Ljava/lang/StringBuilder;
  astore 5
  aload 5
  invokevirtual java/lang/StringBuilder/toString()Ljava/lang/String;
  astore 8
  aload_0
  aload 8
  invokestatic cn/domob/android/ads/J/a(Ljava/lang/Object;Ljava/lang/String;)V
Label2:
  aload_0
  monitorexit
  iload_1
  ireturn
Label0:
  new java/lang/StringBuilder
  astore 5
  aload 5
  invokespecial java/lang/StringBuilder/<init>()V
  ldc "There are "
  astore 4
  aload 5
  aload 4
  invokevirtual java/lang/StringBuilder/append(Ljava/lang/String;)Ljava/lang/StringBuilder;
  astore 5
  aload_0
  getfield cn/domob/android/ads/F/c Ljava/util/HashSet;
  astore_2
  aload_2
  invokevirtual java/util/HashSet/size()I
  istore 9
  aload 5
  iload 9
  invokevirtual java/lang/StringBuilder/append(I)Ljava/lang/StringBuilder;
  astore 5
  ldc " connection and "
  astore 4
  aload 5
  aload 4
  invokevirtual java/lang/StringBuilder/append(Ljava/lang/String;)Ljava/lang/StringBuilder;
  astore 5
  aload_0
  getfield cn/domob/android/ads/F/i Z
  istore_3
  iload_3
  invokestatic app/DummyClass/invokeIfStmt(Z)V
  iload_3
  ifeq Label1
Label3:
  iload_1
  istore 9
  aload 5
  iload 9
  invokevirtual java/lang/StringBuilder/append(I)Ljava/lang/StringBuilder;
  astore 5
  ldc " webview left."
  astore 4
  aload 5
  aload 4
  invokevirtual java/lang/StringBuilder/append(Ljava/lang/String;)Ljava/lang/StringBuilder;
  astore 5
  aload 5
  invokevirtual java/lang/StringBuilder/toString()Ljava/lang/String;
  astore 8
  aload_0
  aload 8
  invokestatic cn/domob/android/ads/J/d(Ljava/lang/Object;Ljava/lang/String;)V
Label6:
  iconst_0
  istore_1
  goto Label2
Label1:
  iconst_0
  istore_1
  goto Label3
Label4:
  astore 10
  aload_0
  monitorexit
  aload 10
  athrow
  nop
.end <method>

.method private c()V
.limit locals 31
.limit stack 200
  nop
  aload_0
  astore_1
  aload_1
  getfield cn/domob/android/ads/F/f Lcn/domob/android/ads/j;
  astore_3
  aload_3
  invokevirtual cn/domob/android/ads/j/g()Lcn/domob/android/ads/j$d;
  astore 4
  aload 4
  invokevirtual cn/domob/android/ads/j$d/b()Ljava/util/ArrayList;
  astore 5
  aload 5
  invokevirtual java/util/ArrayList/iterator()Ljava/util/Iterator;
  astore 6
Label7:
  aload 6
  invokeinterface java/util/Iterator/hasNext()Z 1
  istore 7
  new java/lang/NoClassDefFoundError
  dup
  invokespecial java/lang/NoClassDefFoundError/<init>()V
  athrow
  iload 7
  ifeq Label0
  aload 6
  invokeinterface java/util/Iterator/next()Ljava/lang/Object; 1
  astore 8
  aload 8
  astore 10
  aload 10
  checkcast cn/domob/android/ads/j$h
  astore 10
  aload 10
  astore 9
  aload 9
  invokevirtual cn/domob/android/ads/j$h/b()Ljava/lang/String;
  astore 11
  aload 9
  invokevirtual cn/domob/android/ads/j$h/a()Ljava/lang/String;
  astore 12
  getstatic cn/domob/android/ads/F$1/a [I
  astore 13
  aload 12
  invokestatic cn/domob/android/ads/j$i/a(Ljava/lang/String;)Lcn/domob/android/ads/j$i;
  astore 14
  aload 14
  invokevirtual cn/domob/android/ads/j$i/ordinal()I
  istore 15
  aload 13
  iload 15
  iaload
  istore 15
  dload 15
  invokestatic app/DummyClass/invokeIfStmt(D)V
  iload 15
  lookupswitch
  1 : Label2
  2 : Label3
  3 : Label4
  4 : Label5
  default : Label1
Label1:
  goto Label6
Label6:
  goto Label7
Label2:
  new java/lang/StringBuilder
  astore 16
  aload 16
  invokespecial java/lang/StringBuilder/<init>()V
  ldc "Complete image view description:"
  astore 17
  aload 17
  astore_1
  aload 16
  aload_1
  invokevirtual java/lang/StringBuilder/append(Ljava/lang/String;)Ljava/lang/StringBuilder;
  astore 16
  aload 16
  aload 11
  invokevirtual java/lang/StringBuilder/append(Ljava/lang/String;)Ljava/lang/StringBuilder;
  astore 16
  aload 16
  invokevirtual java/lang/StringBuilder/toString()Ljava/lang/String;
  astore 12
  aload_0
  astore_1
  aload_1
  aload 12
  invokestatic cn/domob/android/ads/J/d(Ljava/lang/Object;Ljava/lang/String;)V
  aload_0
  astore_1
  aload_1
  getfield cn/domob/android/ads/F/d Ljava/util/Hashtable;
  astore_1
  aload_1
  astore 18
  aload 18
  astore_1
  aload_1
  aload 11
  invokevirtual java/util/Hashtable/get(Ljava/lang/Object;)Ljava/lang/Object;
  astore 8
  aload 8
  astore 20
  aload 20
  checkcast [B
  astore 20
  aload 20
  astore 19
  aload 19
  astore_1
  aload 9
  aload_1
  invokevirtual cn/domob/android/ads/j$h/a([B)V
  aload_0
  astore_1
  aload_1
  getfield cn/domob/android/ads/F/e Ljava/util/Hashtable;
  astore_1
  aload_1
  astore 18
  aload 18
  astore_1
  aload_1
  aload 11
  invokevirtual java/util/Hashtable/get(Ljava/lang/Object;)Ljava/lang/Object;
  astore 8
  aload 8
  astore 22
  aload 22
  checkcast [Ljava/lang/String;
  astore 22
  aload 22
  astore 21
  iconst_0
  istore 23
  aload 21
  iload 23
  aaload
  astore 11
  ldc ".gif"
  astore 17
  aload 17
  astore_1
  aload 11
  aload_1
  invokevirtual java/lang/String/endsWith(Ljava/lang/String;)Z
  istore 7
  iload 7
  invokestatic app/DummyClass/invokeIfStmt(Z)V
  iload 7
  ifeq Label8
  iconst_1
  istore 23
  iload 23
  istore 15
Label9:
  aload 9
  iload 15
  invokevirtual cn/domob/android/ads/j$h/c(I)V
  goto Label7
Label8:
  iconst_0
  istore 15
  goto Label9
Label5:
  new java/lang/StringBuilder
  astore 16
  aload 16
  invokespecial java/lang/StringBuilder/<init>()V
  ldc "Complete webview view description:"
  astore 17
  aload 17
  astore_1
  aload 16
  aload_1
  invokevirtual java/lang/StringBuilder/append(Ljava/lang/String;)Ljava/lang/StringBuilder;
  astore 16
  aload 16
  aload 11
  invokevirtual java/lang/StringBuilder/append(Ljava/lang/String;)Ljava/lang/StringBuilder;
  astore 16
  aload 16
  invokevirtual java/lang/StringBuilder/toString()Ljava/lang/String;
  astore 11
  aload_0
  astore_1
  aload_1
  aload 11
  invokestatic cn/domob/android/ads/J/d(Ljava/lang/Object;Ljava/lang/String;)V
  aload_0
  astore_1
  aload_1
  getfield cn/domob/android/ads/F/h Lcn/domob/android/ads/L;
  astore_1
  aload_1
  astore 24
  aload 24
  astore_1
  aload_1
  invokestatic app/DummyClass/invokeIfStmt(Ljava/lang/Object;)V
  aload 24
  ifnull Label10
  new java/lang/StringBuilder
  astore 16
  aload 16
  invokespecial java/lang/StringBuilder/<init>()V
  ldc "WebView["
  astore 17
  aload 17
  astore_1
  aload 16
  aload_1
  invokevirtual java/lang/StringBuilder/append(Ljava/lang/String;)Ljava/lang/StringBuilder;
  astore 16
  aload 9
  invokevirtual cn/domob/android/ads/j$h/b()Ljava/lang/String;
  astore 11
  aload 16
  aload 11
  invokevirtual java/lang/StringBuilder/append(Ljava/lang/String;)Ljava/lang/StringBuilder;
  astore 16
  ldc "]\u52a0\u8f7d\u5b8c\u6210\uff0c\u4f20\u7ed9viewDescription"
  astore 17
  aload 17
  astore_1
  aload 16
  aload_1
  invokevirtual java/lang/StringBuilder/append(Ljava/lang/String;)Ljava/lang/StringBuilder;
  astore 16
  aload 16
  invokevirtual java/lang/StringBuilder/toString()Ljava/lang/String;
  astore 11
  aload_0
  astore_1
  aload_1
  aload 11
  invokestatic cn/domob/android/ads/J/d(Ljava/lang/Object;Ljava/lang/String;)V
  aload_0
  astore_1
  aload_1
  getfield cn/domob/android/ads/F/h Lcn/domob/android/ads/L;
  astore_1
  aload_1
  astore 24
  aload 24
  astore_1
  aload 9
  aload_1
  invokevirtual cn/domob/android/ads/j$h/a(Lcn/domob/android/ads/L;)V
  aconst_null
  astore 25
  aload 25
  astore_1
  aload_0
  astore_2
  aload_2
  aload_1
  putfield cn/domob/android/ads/F/h Lcn/domob/android/ads/L;
  goto Label7
Label10:
  aload_0
  astore_1
  aload_1
  getfield cn/domob/android/ads/F/g Lcn/domob/android/ads/g;
  astore_1
  aload_1
  astore 26
  ldc "WebView is null"
  astore 17
  aload 26
  astore_1
  aload 17
  astore_2
  aload_1
  aload_2
  invokevirtual cn/domob/android/ads/g/a(Ljava/lang/String;)V
  goto Label7
Label3:
  ldc "Complete background view description:"
  astore 17
  aload_0
  astore_1
  aload 17
  astore_2
  aload_1
  aload_2
  invokestatic cn/domob/android/ads/J/d(Ljava/lang/Object;Ljava/lang/String;)V
  aload_0
  astore_1
  aload_1
  getfield cn/domob/android/ads/F/g Lcn/domob/android/ads/g;
  astore_1
  aload_1
  astore 26
  aload 26
  astore_1
  aload_1
  invokevirtual cn/domob/android/ads/g/a()Lcn/domob/android/ads/k;
  astore 27
  aload 27
  astore_1
  aload_1
  invokevirtual cn/domob/android/ads/k/a()J
  lstore 28
  lload 28
  lstore_1
  lload_1
  l2i
  istore 15
  aload 9
  invokevirtual cn/domob/android/ads/j$h/d()Ljava/lang/String;
  astore 12
  new java/lang/StringBuilder
  astore 16
  aload 16
  invokespecial java/lang/StringBuilder/<init>()V
  ldc "\u53d6\u670d\u52a1\u5668\u989c\u8272\u8bbe\u7f6e:"
  astore 17
  aload 17
  astore_1
  aload 16
  aload_1
  invokevirtual java/lang/StringBuilder/append(Ljava/lang/String;)Ljava/lang/StringBuilder;
  astore 16
  aload 16
  aload 12
  invokevirtual java/lang/StringBuilder/append(Ljava/lang/String;)Ljava/lang/StringBuilder;
  astore 16
  aload 16
  invokevirtual java/lang/StringBuilder/toString()Ljava/lang/String;
  astore 11
  aload_0
  astore_1
  aload_1
  aload 11
  invokestatic cn/domob/android/ads/J/d(Ljava/lang/Object;Ljava/lang/String;)V
  aload 12
  invokestatic app/DummyClass/invokeIfStmt(Ljava/lang/Object;)V
  aload 12
  ifnull Label11
  ldc ""
  astore 17
  aload 17
  astore_1
  aload 12
  aload_1
  invokevirtual java/lang/String/equals(Ljava/lang/Object;)Z
  istore 7
  iload 7
  invokestatic app/DummyClass/invokeIfStmt(Z)V
  iload 7
  ifne Label11
  aload_0
  astore_1
  aload_1
  getfield cn/domob/android/ads/F/g Lcn/domob/android/ads/g;
  astore_1
  aload_1
  astore 26
  aload 26
  astore_1
  aload_1
  invokevirtual cn/domob/android/ads/g/a()Lcn/domob/android/ads/k;
  astore 27
  aload 27
  astore_1
  aload_1
  invokevirtual cn/domob/android/ads/k/b()Z
  istore 7
  iload 7
  invokestatic app/DummyClass/invokeIfStmt(Z)V
  iload 7
  ifne Label11
  bipush 16
  istore 23
  iload 23
  istore_1
  aload 12
  iload_1
  invokestatic java/lang/Long/parseLong(Ljava/lang/String;I)J
  lstore 28
  lload 28
  lstore_1
  lload_1
  l2i
  istore 15
  new java/lang/StringBuilder
  astore 16
  aload 16
  invokespecial java/lang/StringBuilder/<init>()V
  ldc "bgcolor is:"
  astore 17
  aload 17
  astore_1
  aload 16
  aload_1
  invokevirtual java/lang/StringBuilder/append(Ljava/lang/String;)Ljava/lang/StringBuilder;
  astore 16
  aload 16
  iload 15
  invokevirtual java/lang/StringBuilder/append(I)Ljava/lang/StringBuilder;
  astore 16
  aload 16
  invokevirtual java/lang/StringBuilder/toString()Ljava/lang/String;
  astore 11
  aload_0
  astore_1
  aload_1
  aload 11
  invokestatic cn/domob/android/ads/J/d(Ljava/lang/Object;Ljava/lang/String;)V
Label12:
  aload 9
  iload 15
  invokevirtual cn/domob/android/ads/j$h/a(I)V
  goto Label7
Label11:
  aload_0
  astore_1
  aload_1
  getfield cn/domob/android/ads/F/g Lcn/domob/android/ads/g;
  astore_1
  aload_1
  astore 26
  aload 26
  astore_1
  aload_1
  invokevirtual cn/domob/android/ads/g/a()Lcn/domob/android/ads/k;
  astore 27
  aload 27
  astore_1
  aload_1
  invokevirtual cn/domob/android/ads/k/b()Z
  istore 7
  iload 7
  invokestatic app/DummyClass/invokeIfStmt(Z)V
  iload 7
  ifeq Label12
  iconst_1
  istore 23
  iload 23
  istore_1
  aload 9
  iload_1
  invokevirtual cn/domob/android/ads/j$h/a(Z)V
  goto Label12
Label4:
  ldc "Complete textview view description:"
  astore 17
  aload_0
  astore_1
  aload 17
  astore_2
  aload_1
  aload_2
  invokestatic cn/domob/android/ads/J/d(Ljava/lang/Object;Ljava/lang/String;)V
  aload 9
  invokevirtual cn/domob/android/ads/j$h/k()I
  istore 15
  aload_0
  astore_1
  aload_1
  getfield cn/domob/android/ads/F/g Lcn/domob/android/ads/g;
  astore_1
  aload_1
  astore 26
  aload 26
  astore_1
  aload_1
  invokevirtual cn/domob/android/ads/g/a()Lcn/domob/android/ads/k;
  astore 27
  aload 27
  astore_1
  aload_1
  invokevirtual cn/domob/android/ads/k/c()J
  lstore 28
  lload 28
  lstore_1
  lload_1
  l2i
  istore_1
  iload_1
  istore 30
  aload_0
  astore_1
  aload_1
  getfield cn/domob/android/ads/F/g Lcn/domob/android/ads/g;
  astore_1
  aload_1
  astore 26
  aload 26
  astore_1
  aload_1
  invokevirtual cn/domob/android/ads/g/a()Lcn/domob/android/ads/k;
  astore 27
  aload 27
  astore_1
  aload_1
  invokevirtual cn/domob/android/ads/k/d()Z
  istore 7
  iload 7
  invokestatic app/DummyClass/invokeIfStmt(Z)V
  iload 7
  ifne Label13
  dload 15
  invokestatic app/DummyClass/invokeIfStmt(D)V
  iload 15
  ifne Label14
Label13:
  iload 30
  istore_1
  aload 9
  iload_1
  invokevirtual cn/domob/android/ads/j$h/b(I)V
  goto Label7
Label14:
  iload 15
  istore 30
  goto Label13
Label0:
  aload_0
  astore_1
  aload_1
  getfield cn/domob/android/ads/F/g Lcn/domob/android/ads/g;
  astore_1
  aload_1
  astore 26
  aload_0
  astore_1
  aload_1
  getfield cn/domob/android/ads/F/f Lcn/domob/android/ads/j;
  astore_3
  aload 26
  astore_1
  aload_1
  aload_3
  invokevirtual cn/domob/android/ads/g/b(Lcn/domob/android/ads/j;)V
  return
  nop
  nop
  nop
.end <method>

