.source SourceFile
.class  cn/domob/android/ads/l
.super java/lang/Object
.field protected static final "a" I =  0
.field protected static final "b" I =  1
.field private static final "o" Ljava/lang/String; =  "1"
.field private static final "p" Ljava/lang/String; =  "id"
.field private static final "q" Ljava/lang/String; =  "data"
.field private "c" Landroid/content/Context;
.field private "d" Lcn/domob/android/ads/g;
.field private "e" Lcn/domob/android/ads/j;
.field private "f" Lcn/domob/android/ads/C;
.field private "g" Lcn/domob/android/ads/L;
.field private "h" I
.field private "i" Landroid/os/Handler;
.field private "j" Z
.field private "k" Ljava/lang/String;
.field private "l" Z
.field private "m" Ljava/lang/String;
.field private "n" Ljava/lang/String;

.method <init>()V
.limit locals 5
.limit stack 200
  nop
  aload_0
  invokespecial java/lang/Object/<init>()V
  new cn/domob/android/ads/C
  astore_1
  aload_1
  invokespecial cn/domob/android/ads/C/<init>()V
  aload_0
  aload_1
  putfield cn/domob/android/ads/l/f Lcn/domob/android/ads/C;
  iconst_0
  istore_3
  iload_3
  istore_2
  aload_0
  iload_2
  putfield cn/domob/android/ads/l/h I
  iconst_0
  istore_3
  aload_0
  iload_3
  putfield cn/domob/android/ads/l/j Z
  aconst_null
  astore 4
  aload_0
  aload 4
  putfield cn/domob/android/ads/l/k Ljava/lang/String;
  iconst_0
  istore_3
  aload_0
  iload_3
  putfield cn/domob/android/ads/l/l Z
  aconst_null
  astore 4
  aload_0
  aload 4
  putfield cn/domob/android/ads/l/m Ljava/lang/String;
  aconst_null
  astore 4
  aload_0
  aload 4
  putfield cn/domob/android/ads/l/n Ljava/lang/String;
  return
  nop
.end <method>

.method static a(Lcn/domob/android/ads/l;I)I
  .synthetic
.limit locals 2
.limit stack 200
  nop
  aload_0
  iload_1
  putfield cn/domob/android/ads/l/h I
  iload_1
  ireturn
  nop
.end <method>

.method static a(Lcn/domob/android/ads/l;Landroid/os/Handler;)Landroid/os/Handler;
  .synthetic
.limit locals 2
.limit stack 200
  nop
  aload_0
  aload_1
  putfield cn/domob/android/ads/l/i Landroid/os/Handler;
  aload_1
  areturn
  nop
.end <method>

.method static a(Lcn/domob/android/ads/l;)Lcn/domob/android/ads/g;
  .synthetic
.limit locals 2
.limit stack 200
  nop
  aload_0
  getfield cn/domob/android/ads/l/d Lcn/domob/android/ads/g;
  astore_1
  aload_1
  areturn
  nop
.end <method>

.method static a(Lcn/domob/android/ads/l;Ljava/lang/String;)V
  .synthetic
.limit locals 2
.limit stack 200
  nop
  aload_0
  aload_1
  invokespecial cn/domob/android/ads/l/a(Ljava/lang/String;)V
  return
  nop
.end <method>

.method static a(Lcn/domob/android/ads/l;Ljava/lang/String;Ljava/util/HashMap;)V
  .synthetic
.limit locals 3
.limit stack 200
  nop
  aload_0
  aload_1
  aload_2
  invokespecial cn/domob/android/ads/l/a(Ljava/lang/String;Ljava/util/HashMap;)V
  return
  nop
.end <method>

.method private a(Ljava/lang/String;)V
.limit locals 12
.limit stack 200
  nop
  new java/lang/StringBuilder
  astore_2
  aload_2
  invokespecial java/lang/StringBuilder/<init>()V
  ldc "startDownload url:"
  astore_3
  aload_2
  aload_3
  invokevirtual java/lang/StringBuilder/append(Ljava/lang/String;)Ljava/lang/StringBuilder;
  astore_2
  aload_2
  aload_1
  invokevirtual java/lang/StringBuilder/append(Ljava/lang/String;)Ljava/lang/StringBuilder;
  astore_2
  aload_2
  invokevirtual java/lang/StringBuilder/toString()Ljava/lang/String;
  astore 4
  aload_0
  aload 4
  invokestatic cn/domob/android/ads/J/a(Ljava/lang/Object;Ljava/lang/String;)V
  aload_0
  getfield cn/domob/android/ads/l/f Lcn/domob/android/ads/C;
  astore 5
  aload 5
  invokevirtual cn/domob/android/ads/C/c()Ljava/util/HashMap;
  astore 6
  ldc "name"
  astore_3
  aload 6
  aload_3
  invokevirtual java/util/HashMap/get(Ljava/lang/Object;)Ljava/lang/Object;
  astore 7
  aload 7
  astore 8
  aload 8
  checkcast java/lang/String
  astore 8
  aload 8
  astore 4
  aload_0
  getfield cn/domob/android/ads/l/k Ljava/lang/String;
  astore 9
  aload_0
  getfield cn/domob/android/ads/l/c Landroid/content/Context;
  astore 10
  new cn/domob/android/ads/l$8
  astore 11
  aload 11
  aload_0
  invokespecial cn/domob/android/ads/l$8/<init>(Lcn/domob/android/ads/l;)V
  aload_1
  aload 4
  aload 9
  aload 10
  aload 11
  invokestatic cn/domob/android/a/a/a(Ljava/lang/String;Ljava/lang/String;Ljava/lang/String;Landroid/content/Context;Lcn/domob/android/a/c;)V
  return
  nop
.end <method>

.method private a(Ljava/lang/String;Ljava/util/HashMap;)V
  .signature_attr "(Ljava/lang/String;Ljava/util/HashMap<Ljava/lang/String;Ljava/lang/String;>;)V"
.limit locals 14
.limit stack 200
  nop
  new cn/domob/android/ads/D
  astore_3
  aload_0
  getfield cn/domob/android/ads/l/c Landroid/content/Context;
  astore 4
  aload_3
  aload 4
  invokespecial cn/domob/android/ads/D/<init>(Landroid/content/Context;)V
  new cn/domob/android/ads/D$c
  astore 5
  aload_3
  invokevirtual java/lang/Object/getClass()Ljava/lang/Class;
  pop
  aload 5
  aload_3
  invokespecial cn/domob/android/ads/D$c/<init>(Lcn/domob/android/ads/D;)V
  aload 5
  aload_1
  putfield cn/domob/android/ads/D$c/b Ljava/lang/String;
  iconst_1
  istore 6
  aload 5
  iload 6
  putfield cn/domob/android/ads/D$c/c I
  new java/util/ArrayList
  astore 7
  aload 7
  invokespecial java/util/ArrayList/<init>()V
  aload 5
  aload 7
  putfield cn/domob/android/ads/D$c/d Ljava/util/ArrayList;
  aload 5
  getfield cn/domob/android/ads/D$c/d Ljava/util/ArrayList;
  astore 7
  ldc "id"
  astore 9
  aload_2
  aload 9
  invokevirtual java/util/HashMap/get(Ljava/lang/Object;)Ljava/lang/Object;
  astore 8
  aload 7
  aload 8
  invokevirtual java/util/ArrayList/add(Ljava/lang/Object;)Z
  pop
  ldc "rp_md5"
  astore 9
  aload_2
  aload 9
  invokevirtual java/util/HashMap/get(Ljava/lang/Object;)Ljava/lang/Object;
  astore 8
  aload 8
  astore 10
  aload 10
  checkcast java/lang/String
  astore 10
  aload 10
  astore_1
  aload 5
  aload_1
  putfield cn/domob/android/ads/D$c/e Ljava/lang/String;
  ldc "data"
  astore 9
  aload_2
  aload 9
  invokevirtual java/util/HashMap/get(Ljava/lang/Object;)Ljava/lang/Object;
  astore 8
  aload 8
  astore 11
  aload 11
  checkcast java/lang/String
  astore 11
  aload 11
  astore_1
  aload 5
  aload_1
  putfield cn/domob/android/ads/D$c/i Ljava/lang/String;
  aload_0
  getfield cn/domob/android/ads/l/n Ljava/lang/String;
  astore_1
  aload 5
  aload_1
  putfield cn/domob/android/ads/D$c/j Ljava/lang/String;
  aload_0
  getfield cn/domob/android/ads/l/d Lcn/domob/android/ads/g;
  astore 12
  aload 12
  invokevirtual cn/domob/android/ads/g/a()Lcn/domob/android/ads/k;
  astore 13
  aload 13
  invokevirtual cn/domob/android/ads/k/f()Ljava/lang/String;
  astore_1
  aload 5
  aload_1
  putfield cn/domob/android/ads/D$c/f Ljava/lang/String;
  aload_3
  aload 5
  invokevirtual cn/domob/android/ads/D/a(Lcn/domob/android/ads/D$c;)V
  return
  nop
.end <method>

.method private a(Ljava/lang/String;ZI)V
.limit locals 28
.limit stack 200
  nop
  ldc "Download event start."
  astore 7
  aload_0
  astore 4
  aload 4
  aload 7
  invokestatic cn/domob/android/ads/J/d(Ljava/lang/Object;Ljava/lang/String;)V
  aload_0
  astore 4
  aload 4
  getfield cn/domob/android/ads/l/c Landroid/content/Context;
  astore 8
  aload_0
  astore 4
  aload 4
  getfield cn/domob/android/ads/l/f Lcn/domob/android/ads/C;
  astore 9
  aload 9
  invokevirtual cn/domob/android/ads/C/c()Ljava/util/HashMap;
  astore 10
  ldc "name"
  astore 7
  aload 10
  aload 7
  invokevirtual java/util/HashMap/get(Ljava/lang/Object;)Ljava/lang/Object;
  astore 11
  aload 11
  astore 13
  aload 13
  checkcast java/lang/String
  astore 13
  aload 13
  astore 12
  aload_1
  astore 4
  aload 8
  aload 4
  aload 12
  invokestatic cn/domob/android/a/a/a(Landroid/content/Context;Ljava/lang/String;Ljava/lang/String;)Landroid/content/Intent;
  astore 14
  new java/lang/NoClassDefFoundError
  dup
  invokespecial java/lang/NoClassDefFoundError/<init>()V
  athrow
  iload 14
  ifeq Label0
  new java/lang/StringBuilder
  astore 15
  aload 15
  invokespecial java/lang/StringBuilder/<init>()V
  aload_0
  astore 4
  aload 4
  getfield cn/domob/android/ads/l/f Lcn/domob/android/ads/C;
  astore 9
  aload 9
  invokevirtual cn/domob/android/ads/C/c()Ljava/util/HashMap;
  astore 10
  ldc "name"
  astore 7
  aload 10
  aload 7
  invokevirtual java/util/HashMap/get(Ljava/lang/Object;)Ljava/lang/Object;
  astore 11
  aload 11
  astore 16
  aload 16
  checkcast java/lang/String
  astore 16
  aload 16
  astore 12
  aload 15
  aload 12
  invokevirtual java/lang/StringBuilder/append(Ljava/lang/String;)Ljava/lang/StringBuilder;
  astore 15
  ldc "\uff1a\u5df2\u4e0b\u8f7d"
  astore 7
  aload 15
  aload 7
  invokevirtual java/lang/StringBuilder/append(Ljava/lang/String;)Ljava/lang/StringBuilder;
  astore 15
  aload 15
  invokevirtual java/lang/StringBuilder/toString()Ljava/lang/String;
  astore 12
  aload_0
  astore 4
  aload 4
  aload 12
  invokestatic cn/domob/android/ads/J/d(Ljava/lang/Object;Ljava/lang/String;)V
  iload_2
  istore 4
  iload 4
  invokestatic app/DummyClass/invokeIfStmt(Z)V
  iload_2
  ifeq Label1
  new android/app/AlertDialog$Builder
  astore 17
  aload_0
  astore 4
  aload 4
  getfield cn/domob/android/ads/l/c Landroid/content/Context;
  astore 8
  aload 17
  aload 8
  invokespecial android/app/AlertDialog$Builder/<init>(Landroid/content/Context;)V
  ldc "\u5b89\u88c5"
  astore 7
  aload 17
  aload 7
  invokevirtual android/app/AlertDialog$Builder/setTitle(Ljava/lang/CharSequence;)Landroid/app/AlertDialog$Builder;
  astore 17
  new java/lang/StringBuilder
  astore 15
  aload 15
  invokespecial java/lang/StringBuilder/<init>()V
  aload_0
  astore 4
  aload 4
  getfield cn/domob/android/ads/l/f Lcn/domob/android/ads/C;
  astore 9
  aload 9
  invokevirtual cn/domob/android/ads/C/c()Ljava/util/HashMap;
  astore 10
  ldc "name"
  astore 7
  aload 10
  aload 7
  invokevirtual java/util/HashMap/get(Ljava/lang/Object;)Ljava/lang/Object;
  astore 11
  aload 11
  astore 18
  aload 18
  checkcast java/lang/String
  astore 18
  aload 18
  astore 12
  aload 15
  aload 12
  invokevirtual java/lang/StringBuilder/append(Ljava/lang/String;)Ljava/lang/StringBuilder;
  astore 15
  ldc "\u5df2\u7ecf\u4e0b\u8f7d\u662f\u5426\u73b0\u5728\u5b89\u88c5?"
  astore 7
  aload 15
  aload 7
  invokevirtual java/lang/StringBuilder/append(Ljava/lang/String;)Ljava/lang/StringBuilder;
  astore 15
  aload 15
  invokevirtual java/lang/StringBuilder/toString()Ljava/lang/String;
  astore 12
  aload 17
  aload 12
  invokevirtual android/app/AlertDialog$Builder/setMessage(Ljava/lang/CharSequence;)Landroid/app/AlertDialog$Builder;
  astore 17
  new cn/domob/android/ads/l$4
  astore 19
  aload_0
  astore 4
  aload 19
  aload 4
  invokespecial cn/domob/android/ads/l$4/<init>(Lcn/domob/android/ads/l;)V
  ldc "\u5426"
  astore 7
  aload 17
  aload 7
  aload 19
  invokevirtual android/app/AlertDialog$Builder/setNegativeButton(Ljava/lang/CharSequence;Landroid/content/DialogInterface$OnClickListener;)Landroid/app/AlertDialog$Builder;
  astore 17
  new cn/domob/android/ads/l$3
  astore 20
  aload 20
  astore 4
  aload_0
  astore 5
  aload 4
  aload 5
  aload 14
  invokespecial cn/domob/android/ads/l$3/<init>(Lcn/domob/android/ads/l;Landroid/content/Intent;)V
  ldc "\u662f"
  astore 7
  aload 20
  astore 4
  aload 17
  aload 7
  aload 4
  invokevirtual android/app/AlertDialog$Builder/setPositiveButton(Ljava/lang/CharSequence;Landroid/content/DialogInterface$OnClickListener;)Landroid/app/AlertDialog$Builder;
  astore 17
  aload 17
  invokevirtual android/app/AlertDialog$Builder/show()Landroid/app/AlertDialog;
  pop
Label2:
  return
Label1:
  aload_0
  astore 4
  aload 4
  getfield cn/domob/android/ads/l/c Landroid/content/Context;
  astore 8
  aload 8
  invokestatic cn/domob/android/ads/f/a(Landroid/content/Context;)Lcn/domob/android/ads/f;
  astore 21
  aload_0
  astore 4
  aload 4
  getfield cn/domob/android/ads/l/k Ljava/lang/String;
  astore 12
  aload_0
  astore 4
  aload 4
  getfield cn/domob/android/ads/l/l Z
  istore 4
  iload 4
  istore_2
  aload_0
  astore 4
  aload 4
  getfield cn/domob/android/ads/l/m Ljava/lang/String;
  astore 4
  aload 4
  astore_1
  aload 21
  astore 4
  iload_2
  istore 5
  aload_1
  astore 6
  aload 4
  aload 12
  iload 5
  aload 6
  invokevirtual cn/domob/android/ads/f/a(Ljava/lang/String;ZLjava/lang/String;)V
  aload_0
  astore 4
  aload 4
  getfield cn/domob/android/ads/l/c Landroid/content/Context;
  astore 8
  aload 8
  aload 14
  invokevirtual android/content/Context/startActivity(Landroid/content/Intent;)V
  goto Label2
Label0:
  iload_2
  istore 4
  iload 4
  invokestatic app/DummyClass/invokeIfStmt(Z)V
  iload_2
  ifeq Label3
  dload_3
  dstore 4
  dload 4
  invokestatic app/DummyClass/invokeIfStmt(D)V
  iload_3
  lookupswitch
  0 : Label5
  default : Label4
Label4:
  goto Label6
Label6:
  new android/app/AlertDialog$Builder
  astore 17
  aload_0
  astore 4
  aload 4
  getfield cn/domob/android/ads/l/c Landroid/content/Context;
  astore 8
  aload 17
  aload 8
  invokespecial android/app/AlertDialog$Builder/<init>(Landroid/content/Context;)V
  new java/lang/StringBuilder
  astore 15
  aload 15
  invokespecial java/lang/StringBuilder/<init>()V
  ldc "\u662f\u5426\u4e0b\u8f7d"
  astore 7
  aload 15
  aload 7
  invokevirtual java/lang/StringBuilder/append(Ljava/lang/String;)Ljava/lang/StringBuilder;
  astore 15
  aload_0
  astore 4
  aload 4
  getfield cn/domob/android/ads/l/f Lcn/domob/android/ads/C;
  astore 9
  aload 9
  invokevirtual cn/domob/android/ads/C/c()Ljava/util/HashMap;
  astore 10
  ldc "name"
  astore 7
  aload 10
  aload 7
  invokevirtual java/util/HashMap/get(Ljava/lang/Object;)Ljava/lang/Object;
  astore 11
  aload 11
  astore 22
  aload 22
  checkcast java/lang/String
  astore 22
  aload 22
  astore 12
  aload 15
  aload 12
  invokevirtual java/lang/StringBuilder/append(Ljava/lang/String;)Ljava/lang/StringBuilder;
  astore 15
  ldc "?"
  astore 7
  aload 15
  aload 7
  invokevirtual java/lang/StringBuilder/append(Ljava/lang/String;)Ljava/lang/StringBuilder;
  astore 15
  aload 15
  invokevirtual java/lang/StringBuilder/toString()Ljava/lang/String;
  astore 12
  aload 17
  aload 12
  invokevirtual android/app/AlertDialog$Builder/setMessage(Ljava/lang/CharSequence;)Landroid/app/AlertDialog$Builder;
  astore 17
  new cn/domob/android/ads/l$7
  astore 23
  aload 23
  astore 4
  aload_0
  astore 5
  aload_1
  astore 6
  aload 4
  aload 5
  aload 6
  invokespecial cn/domob/android/ads/l$7/<init>(Lcn/domob/android/ads/l;Ljava/lang/String;)V
  ldc "\u786e\u5b9a"
  astore 7
  aload 23
  astore 4
  aload 17
  aload 7
  aload 4
  invokevirtual android/app/AlertDialog$Builder/setPositiveButton(Ljava/lang/CharSequence;Landroid/content/DialogInterface$OnClickListener;)Landroid/app/AlertDialog$Builder;
  astore 17
  new cn/domob/android/ads/l$6
  astore 24
  aload 24
  astore 4
  aload_0
  astore 5
  aload 4
  aload 5
  invokespecial cn/domob/android/ads/l$6/<init>(Lcn/domob/android/ads/l;)V
  ldc "\u53d6\u6d88"
  astore 7
  aload 24
  astore 4
  aload 17
  aload 7
  aload 4
  invokevirtual android/app/AlertDialog$Builder/setNegativeButton(Ljava/lang/CharSequence;Landroid/content/DialogInterface$OnClickListener;)Landroid/app/AlertDialog$Builder;
  astore 17
  aload 17
  invokevirtual android/app/AlertDialog$Builder/show()Landroid/app/AlertDialog;
  pop
  goto Label2
Label5:
  aload_0
  astore 4
  aload 4
  getfield cn/domob/android/ads/l/d Lcn/domob/android/ads/g;
  astore 4
  aload 4
  astore 25
  aload 25
  astore 4
  aload 4
  invokevirtual cn/domob/android/ads/g/s()Landroid/widget/Button;
  astore 26
  new cn/domob/android/ads/l$5
  astore 27
  aload 27
  astore 4
  aload_0
  astore 5
  aload_1
  astore 6
  aload 4
  aload 5
  aload 6
  invokespecial cn/domob/android/ads/l$5/<init>(Lcn/domob/android/ads/l;Ljava/lang/String;)V
  aload 26
  astore 4
  aload 27
  astore 5
  aload 4
  aload 5
  invokevirtual android/widget/Button/setOnClickListener(Landroid/view/View$OnClickListener;)V
  goto Label2
Label3:
  aload_0
  astore 4
  aload_1
  astore 5
  aload 4
  aload 5
  invokespecial cn/domob/android/ads/l/a(Ljava/lang/String;)V
  goto Label2
  nop
  nop
.end <method>

.method protected a()Z
.limit locals 2
.limit stack 200
  nop
  aload_0
  getfield cn/domob/android/ads/l/l Z
  istore_1
  iload_1
  ireturn
  nop
.end <method>

.method private a(Landroid/content/Intent;Lcn/domob/android/ads/j$a;)Z
.limit locals 32
.limit stack 200
  nop
  aload_0
  astore_3
  aload_3
  getfield cn/domob/android/ads/l/c Landroid/content/Context;
  astore 5
  new java/lang/NoClassDefFoundError
  dup
  invokespecial java/lang/NoClassDefFoundError/<init>()V
  athrow
  nop
  aload_2
  astore_3
  aload_3
  invokevirtual cn/domob/android/ads/j$a/d()Ljava/lang/String;
  astore 7
  aload_2
  astore_3
  aload_3
  invokevirtual cn/domob/android/ads/j$a/c()Ljava/lang/String;
  astore 8
  aload_2
  astore_3
  aload_3
  invokevirtual cn/domob/android/ads/j$a/a()Ljava/lang/String;
  astore 9
  aload_2
  astore_3
  aload_3
  invokevirtual cn/domob/android/ads/j$a/h()Z
  istore 10
  aload_2
  astore_3
  aload_3
  invokevirtual cn/domob/android/ads/j$a/i()I
  istore 11
  aload_2
  astore_3
  aload_3
  invokevirtual cn/domob/android/ads/j$a/j()Z
  istore 12
  aload_2
  astore_3
  aload_3
  invokevirtual cn/domob/android/ads/j$a/k()Z
  istore 13
  aload_0
  astore_3
  aload_3
  iload 13
  putfield cn/domob/android/ads/l/l Z
  new java/lang/StringBuilder
  astore 14
  aload 14
  invokespecial java/lang/StringBuilder/<init>()V
  ldc "doAction -> intent\'s opentype:"
  astore 15
  aload 14
  aload 15
  invokevirtual java/lang/StringBuilder/append(Ljava/lang/String;)Ljava/lang/StringBuilder;
  astore 14
  aload 14
  aload 8
  invokevirtual java/lang/StringBuilder/append(Ljava/lang/String;)Ljava/lang/StringBuilder;
  astore 14
  ldc "  intent:"
  astore 15
  aload 14
  aload 15
  invokevirtual java/lang/StringBuilder/append(Ljava/lang/String;)Ljava/lang/StringBuilder;
  astore 14
  aload_1
  astore_3
  aload_3
  invokevirtual android/content/Intent/toString()Ljava/lang/String;
  astore 16
  aload 14
  aload 16
  invokevirtual java/lang/StringBuilder/append(Ljava/lang/String;)Ljava/lang/StringBuilder;
  astore 14
  ldc ",click confirm:"
  astore 15
  aload 14
  aload 15
  invokevirtual java/lang/StringBuilder/append(Ljava/lang/String;)Ljava/lang/StringBuilder;
  astore 14
  aload 14
  iload 10
  invokevirtual java/lang/StringBuilder/append(Z)Ljava/lang/StringBuilder;
  astore 14
  ldc ", confirm type:"
  astore 15
  aload 14
  aload 15
  invokevirtual java/lang/StringBuilder/append(Ljava/lang/String;)Ljava/lang/StringBuilder;
  astore 14
  aload 14
  iload 11
  invokevirtual java/lang/StringBuilder/append(I)Ljava/lang/StringBuilder;
  astore 14
  ldc ", preload:"
  astore 15
  aload 14
  aload 15
  invokevirtual java/lang/StringBuilder/append(Ljava/lang/String;)Ljava/lang/StringBuilder;
  astore 14
  aload 14
  iload 12
  invokevirtual java/lang/StringBuilder/append(Z)Ljava/lang/StringBuilder;
  astore 14
  aload 14
  invokevirtual java/lang/StringBuilder/toString()Ljava/lang/String;
  astore 16
  aload_0
  astore_3
  aload_3
  aload 16
  invokestatic cn/domob/android/ads/J/a(Ljava/lang/Object;Ljava/lang/String;)V
  ldc 65536
  istore 18
  aload_1
  astore_3
  aload 6
  aload_3
  iload 18
  invokevirtual android/content/pm/PackageManager/resolveActivity(Landroid/content/Intent;I)Landroid/content/pm/ResolveInfo;
  astore 17
  aload 17
  invokestatic app/DummyClass/invokeIfStmt(Ljava/lang/Object;)V
  aload 17
  ifnull Label0
  ldc "url"
  astore 16
Label23:
  aload 16
  aload 9
  invokevirtual java/lang/String/equals(Ljava/lang/Object;)Z
  istore 13
  iload 13
  invokestatic app/DummyClass/invokeIfStmt(Z)V
  iload 13
  ifeq Label1
  aload_1
  astore_3
  aload_3
  invokevirtual android/content/Intent/getDataString()Ljava/lang/String;
  astore 16
  new java/lang/StringBuilder
  astore 14
  aload 14
  invokespecial java/lang/StringBuilder/<init>()V
  ldc "Open URL:"
  astore 15
  aload 14
  aload 15
  invokevirtual java/lang/StringBuilder/append(Ljava/lang/String;)Ljava/lang/StringBuilder;
  astore 14
  aload 14
  aload 16
  invokevirtual java/lang/StringBuilder/append(Ljava/lang/String;)Ljava/lang/StringBuilder;
  astore 14
  aload 14
  invokevirtual java/lang/StringBuilder/toString()Ljava/lang/String;
  astore 9
  aload_0
  astore_3
  aload_3
  aload 9
  invokestatic cn/domob/android/ads/J/a(Ljava/lang/Object;Ljava/lang/String;)V
  ldc "inapp_slider"
  astore 9
  aload 9
  aload 8
  invokevirtual java/lang/String/equals(Ljava/lang/Object;)Z
  istore 13
  iload 13
  invokestatic app/DummyClass/invokeIfStmt(Z)V
  iload 13
  ifeq Label2
  aload_0
  astore_3
  aload_3
  getfield cn/domob/android/ads/l/d Lcn/domob/android/ads/g;
  astore_3
  aload_3
  astore 19
  aload 19
  astore_3
  aload_3
  invokevirtual cn/domob/android/ads/g/p()Z
  istore 13
  new java/lang/StringBuilder
  astore 14
  aload 14
  invokespecial java/lang/StringBuilder/<init>()V
  ldc "isAtBottom:"
  astore 15
  aload 14
  aload 15
  invokevirtual java/lang/StringBuilder/append(Ljava/lang/String;)Ljava/lang/StringBuilder;
  astore 14
  aload 14
  iload 13
  invokevirtual java/lang/StringBuilder/append(Z)Ljava/lang/StringBuilder;
  astore 14
  aload 14
  invokevirtual java/lang/StringBuilder/toString()Ljava/lang/String;
  astore 8
  aload 8
  invokestatic cn/domob/android/ads/J/a(Ljava/lang/String;)V
  iload 13
  invokestatic app/DummyClass/invokeIfStmt(Z)V
  iload 13
  ifeq Label3
  ldc "inapp_slider"
  astore 8
Label13:
  invokestatic cn/domob/android/ads/p/a()Lcn/domob/android/ads/p;
  astore 20
  aload_0
  astore_3
  aload_3
  getfield cn/domob/android/ads/l/c Landroid/content/Context;
  astore 5
  aload 20
  astore_3
  aload_3
  aload 5
  invokevirtual cn/domob/android/ads/p/m(Landroid/content/Context;)I
  istore 21
  iload 21
  istore_3
  dload_3
  invokestatic app/DummyClass/invokeIfStmt(D)V
  sipush 350
  istore 18
  iload 21
  istore_3
  iload 18
  iload_3
  if_icmplt Label4
  ldc "inapp_fs"
  astore 8
Label4:
  invokestatic cn/domob/android/ads/p/a()Lcn/domob/android/ads/p;
  astore 20
  aload_0
  astore_3
  aload_3
  getfield cn/domob/android/ads/l/c Landroid/content/Context;
  astore 5
  aload 20
  astore_3
  aload_3
  aload 5
  invokevirtual cn/domob/android/ads/p/i(Landroid/content/Context;)Ljava/lang/String;
  astore 9
  aload 9
  invokestatic app/DummyClass/invokeIfStmt(Ljava/lang/Object;)V
  ldc "h"
  astore 15
  aload 9
  aload 15
  if_acmpne Label2
  ldc "inapp_fs"
  astore 22
Label21:
  aload_0
  astore_3
  aload_3
  getfield cn/domob/android/ads/l/e Lcn/domob/android/ads/j;
  astore_3
  aload_3
  astore 23
  aload 23
  astore_3
  aload_3
  invokevirtual cn/domob/android/ads/j/d()Ljava/lang/String;
  astore 8
  aload 8
  invokestatic app/DummyClass/invokeIfStmt(Ljava/lang/Object;)V
  aload 8
  ifnonnull Label5
  aload_0
  astore_3
  aload_3
  getfield cn/domob/android/ads/l/e Lcn/domob/android/ads/j;
  astore_3
  aload_3
  astore 23
  aload 23
  astore_3
  aload_3
  invokevirtual cn/domob/android/ads/j/c()Ljava/lang/String;
  astore 8
  aload 8
  invokestatic cn/domob/android/ads/J/c(Ljava/lang/String;)Ljava/lang/String;
  astore 8
Label14:
  aload_0
  astore_3
  aload_3
  aload 8
  putfield cn/domob/android/ads/l/m Ljava/lang/String;
  aload_0
  astore_3
  aload_3
  getfield cn/domob/android/ads/l/e Lcn/domob/android/ads/j;
  astore_3
  aload_3
  astore 23
  aload 23
  astore_3
  aload_3
  invokevirtual cn/domob/android/ads/j/h()Ljava/lang/String;
  astore 8
  aload_0
  astore_3
  aload_3
  aload 8
  putfield cn/domob/android/ads/l/k Ljava/lang/String;
  aload_0
  astore_3
  aload_3
  getfield cn/domob/android/ads/l/f Lcn/domob/android/ads/C;
  astore_3
  aload_3
  astore 24
  aload 24
  astore_3
  aload_3
  invokevirtual cn/domob/android/ads/C/c()Ljava/util/HashMap;
  astore 25
  aload_0
  astore_3
  aload_3
  getfield cn/domob/android/ads/l/e Lcn/domob/android/ads/j;
  astore_3
  aload_3
  astore 23
  aload 23
  astore_3
  aload_3
  invokevirtual cn/domob/android/ads/j/b()Ljava/lang/String;
  astore 9
  ldc "id"
  astore 15
  aload 25
  astore_3
  aload_3
  aload 15
  aload 9
  invokevirtual java/util/HashMap/put(Ljava/lang/Object;Ljava/lang/Object;)Ljava/lang/Object;
  pop
  aload_0
  astore_3
  aload_3
  getfield cn/domob/android/ads/l/f Lcn/domob/android/ads/C;
  astore_3
  aload_3
  astore 24
  aload 24
  astore_3
  aload_3
  invokevirtual cn/domob/android/ads/C/c()Ljava/util/HashMap;
  astore 25
  aload_0
  astore_3
  aload_3
  getfield cn/domob/android/ads/l/e Lcn/domob/android/ads/j;
  astore_3
  aload_3
  astore 23
  aload 23
  astore_3
  aload_3
  invokevirtual cn/domob/android/ads/j/d()Ljava/lang/String;
  astore 9
  aload 9
  invokestatic app/DummyClass/invokeIfStmt(Ljava/lang/Object;)V
  aload 9
  ifnonnull Label6
  aload_0
  astore_3
  aload_3
  getfield cn/domob/android/ads/l/e Lcn/domob/android/ads/j;
  astore_3
  aload_3
  astore 23
  aload 23
  astore_3
  aload_3
  invokevirtual cn/domob/android/ads/j/c()Ljava/lang/String;
  astore 9
  aload 9
  invokestatic cn/domob/android/ads/J/c(Ljava/lang/String;)Ljava/lang/String;
  astore 9
Label15:
  ldc "rp_md5"
  astore 15
  aload 25
  astore_3
  aload_3
  aload 15
  aload 9
  invokevirtual java/util/HashMap/put(Ljava/lang/Object;Ljava/lang/Object;)Ljava/lang/Object;
  pop
  aload_0
  astore_3
  aload_3
  getfield cn/domob/android/ads/l/f Lcn/domob/android/ads/C;
  astore_3
  aload_3
  astore 24
  aload_2
  astore_3
  aload_3
  invokevirtual cn/domob/android/ads/j$a/c()Ljava/lang/String;
  astore 8
  aload 24
  astore_3
  aload_3
  aload 8
  invokevirtual cn/domob/android/ads/C/b(Ljava/lang/String;)V
  aload_0
  astore_3
  aload_3
  getfield cn/domob/android/ads/l/f Lcn/domob/android/ads/C;
  astore_3
  aload_3
  astore 24
  aload_2
  astore_3
  aload_3
  invokevirtual cn/domob/android/ads/j$a/b()Ljava/lang/String;
  astore 8
  aload 24
  astore_3
  aload_3
  aload 8
  invokevirtual cn/domob/android/ads/C/a(Ljava/lang/String;)V
  aload_0
  astore_3
  aload_3
  getfield cn/domob/android/ads/l/f Lcn/domob/android/ads/C;
  astore_3
  aload_3
  astore 24
  aload 24
  astore_3
  aload_3
  invokevirtual cn/domob/android/ads/C/c()Ljava/util/HashMap;
  astore 25
  aload_2
  astore_3
  aload_3
  invokevirtual cn/domob/android/ads/j$a/g()Ljava/lang/String;
  astore 9
  ldc "name"
  astore 15
  aload 25
  astore_3
  aload_3
  aload 15
  aload 9
  invokevirtual java/util/HashMap/put(Ljava/lang/Object;Ljava/lang/Object;)Ljava/lang/Object;
  pop
  aload_0
  astore_3
  aload_3
  getfield cn/domob/android/ads/l/f Lcn/domob/android/ads/C;
  astore_3
  aload_3
  astore 24
  aload 24
  astore_3
  aload_3
  invokevirtual cn/domob/android/ads/C/c()Ljava/util/HashMap;
  astore 25
  aload_0
  astore_3
  aload_3
  getfield cn/domob/android/ads/l/k Ljava/lang/String;
  astore 9
  ldc "pkgName"
  astore 15
  aload 25
  astore_3
  aload_3
  aload 15
  aload 9
  invokevirtual java/util/HashMap/put(Ljava/lang/Object;Ljava/lang/Object;)Ljava/lang/Object;
  pop
  aload_0
  astore_3
  aload_3
  getfield cn/domob/android/ads/l/f Lcn/domob/android/ads/C;
  astore_3
  aload_3
  astore 24
  aload_2
  astore_3
  aload_3
  invokevirtual cn/domob/android/ads/j$a/n()Z
  istore 13
  aload 24
  astore_3
  aload_3
  iload 13
  invokevirtual cn/domob/android/ads/C/a(Z)V
  getstatic cn/domob/android/ads/l$9/a [I
  astore 26
  aload 22
  astore_3
  aload_3
  invokestatic cn/domob/android/ads/j$e/a(Ljava/lang/String;)Lcn/domob/android/ads/j$e;
  astore 27
  aload 27
  astore_3
  aload_3
  invokevirtual cn/domob/android/ads/j$e/ordinal()I
  istore 21
  aload 26
  iload 21
  iaload
  istore 21
  iload 21
  istore_3
  dload_3
  invokestatic app/DummyClass/invokeIfStmt(D)V
  iload 21
  lookupswitch
  1 : Label8
  2 : Label8
  3 : Label8
  4 : Label8
  5 : Label9
  6 : Label10
  7 : Label11
  default : Label7
Label7:
  goto Label12
Label12:
  aload_0
  astore_3
  aload_3
  getfield cn/domob/android/ads/l/c Landroid/content/Context;
  astore 5
  aload_1
  astore_3
  aload 5
  aload_3
  invokevirtual android/content/Context/startActivity(Landroid/content/Intent;)V
Label17:
  iconst_1
  istore 18
  iload 18
  ireturn
Label3:
  ldc "inapp_fs"
  astore 8
  goto Label13
Label5:
  aload_0
  astore_3
  aload_3
  getfield cn/domob/android/ads/l/e Lcn/domob/android/ads/j;
  astore_3
  aload_3
  astore 23
  aload 23
  astore_3
  aload_3
  invokevirtual cn/domob/android/ads/j/d()Ljava/lang/String;
  astore 8
  goto Label14
Label6:
  aload_0
  astore_3
  aload_3
  getfield cn/domob/android/ads/l/e Lcn/domob/android/ads/j;
  astore_3
  aload_3
  astore 23
  aload 23
  astore_3
  aload_3
  invokevirtual cn/domob/android/ads/j/d()Ljava/lang/String;
  astore 9
  goto Label15
Label8:
  ldc "1"
  astore 15
  aload 7
  aload 15
  invokevirtual java/lang/String/equals(Ljava/lang/Object;)Z
  istore 13
  iload 13
  invokestatic app/DummyClass/invokeIfStmt(Z)V
  iload 13
  ifeq Label16
  aload_0
  astore_3
  aload_3
  invokespecial cn/domob/android/ads/l/d()V
Label24:
  goto Label17
Label22:
  astore 28
  ldc "DomobSDK"
  astore 15
  ldc "Error happened in doAction!"
  astore 29
  aload 29
  astore_3
  aload 15
  aload_3
  invokestatic android/util/Log/e(Ljava/lang/String;Ljava/lang/String;)I
  pop
  aload 28
  astore_3
  aload_3
  invokestatic cn/domob/android/ads/J/a(Ljava/lang/Throwable;)V
  iconst_0
  istore 18
  iload 18
  ireturn
Label16:
  aload_0
  astore_3
  aload_3
  invokespecial cn/domob/android/ads/l/e()V
  goto Label17
Label9:
  aload_0
  astore_3
  aload_3
  aload 16
  iload 10
  iload 11
  invokespecial cn/domob/android/ads/l/a(Ljava/lang/String;ZI)V
  goto Label17
Label10:
  aload_0
  astore_3
  aload_3
  invokespecial cn/domob/android/ads/l/c()Z
  istore 13
  iload 13
  invokestatic app/DummyClass/invokeIfStmt(Z)V
  iload 13
  ifeq Label18
  ldc "Chrome exists"
  astore 15
  aload_0
  astore_3
  aload_3
  aload 15
  invokestatic cn/domob/android/ads/J/d(Ljava/lang/Object;Ljava/lang/String;)V
  ldc "com.android.browser"
  astore 15
  ldc "com.android.browser.BrowserActivity"
  astore 29
  aload_1
  astore_3
  aload 29
  astore 4
  aload_3
  aload 15
  aload 4
  invokevirtual android/content/Intent/setClassName(Ljava/lang/String;Ljava/lang/String;)Landroid/content/Intent;
  pop
Label18:
  aload_0
  astore_3
  aload_3
  getfield cn/domob/android/ads/l/c Landroid/content/Context;
  astore 5
  aload 5
  invokevirtual android/content/Context/getPackageManager()Landroid/content/pm/PackageManager;
  astore 6
  ldc 65536
  istore 18
  aload_1
  astore_3
  aload 6
  aload_3
  iload 18
  invokevirtual android/content/pm/PackageManager/resolveActivity(Landroid/content/Intent;I)Landroid/content/pm/ResolveInfo;
  astore 17
  aload 17
  invokestatic app/DummyClass/invokeIfStmt(Ljava/lang/Object;)V
  aload 17
  ifnonnull Label19
  ldc "BrowserActivity class not exist,set component null"
  astore 15
  aload 15
  invokestatic cn/domob/android/ads/J/a(Ljava/lang/String;)V
  aconst_null
  astore 30
  aload_1
  astore_3
  aload 30
  astore 4
  aload_3
  aload 4
  invokevirtual android/content/Intent/setComponent(Landroid/content/ComponentName;)Landroid/content/Intent;
  pop
Label19:
  aload_0
  astore_3
  aload_3
  getfield cn/domob/android/ads/l/c Landroid/content/Context;
  astore 5
  aload_1
  astore_3
  aload 5
  aload_3
  invokevirtual android/content/Context/startActivity(Landroid/content/Intent;)V
  goto Label17
Label11:
  aload_0
  astore_3
  aload_3
  getfield cn/domob/android/ads/l/c Landroid/content/Context;
  astore 5
  aload_1
  astore_3
  aload 5
  aload_3
  invokevirtual android/content/Context/startActivity(Landroid/content/Intent;)V
  goto Label17
Label1:
  ldc "la"
  astore 22
  aload 22
  astore_3
  aload_3
  aload 9
  invokevirtual java/lang/String/equals(Ljava/lang/Object;)Z
  istore 13
  iload 13
  invokestatic app/DummyClass/invokeIfStmt(Z)V
  iload 13
  ifeq Label20
  new java/lang/StringBuilder
  astore 14
  aload 14
  invokespecial java/lang/StringBuilder/<init>()V
  ldc "Try to open app with Intent:"
  astore 15
  aload 14
  aload 15
  invokevirtual java/lang/StringBuilder/append(Ljava/lang/String;)Ljava/lang/StringBuilder;
  astore 14
  aload_1
  astore_3
  aload_3
  invokevirtual android/content/Intent/toString()Ljava/lang/String;
  astore 22
  aload 22
  astore_3
  aload 14
  aload_3
  invokevirtual java/lang/StringBuilder/append(Ljava/lang/String;)Ljava/lang/StringBuilder;
  astore 14
  aload 14
  invokevirtual java/lang/StringBuilder/toString()Ljava/lang/String;
  astore 22
  aload_0
  astore_3
  aload 22
  astore 4
  aload_3
  aload 4
  invokestatic cn/domob/android/ads/J/a(Ljava/lang/Object;Ljava/lang/String;)V
Label25:
  aload_0
  astore_3
  aload_3
  getfield cn/domob/android/ads/l/c Landroid/content/Context;
  astore 5
  aload_1
  astore_3
  aload 5
  aload_3
  invokevirtual android/content/Context/startActivity(Landroid/content/Intent;)V
Label27:
  goto Label17
Label26:
  astore 31
Label28:
  ldc "Lauch App \u5f02\u5e38\uff0c\u53d1\u9001\u5931\u8d25\u62a5\u544a\u3002"
  astore 15
  aload_0
  astore_3
  aload_3
  aload 15
  invokestatic cn/domob/android/ads/J/b(Ljava/lang/Object;Ljava/lang/String;)V
  aload_0
  astore_3
  aload_3
  invokespecial cn/domob/android/ads/l/f()V
  aload 31
  astore_3
  aload_3
  invokestatic cn/domob/android/ads/J/a(Ljava/lang/Throwable;)V
  iconst_0
  istore 18
  iload 18
  ireturn
Label20:
  aload_0
  astore_3
  aload_3
  getfield cn/domob/android/ads/l/c Landroid/content/Context;
  astore 5
  aload_1
  astore_3
  aload 5
  aload_3
  invokevirtual android/content/Context/startActivity(Landroid/content/Intent;)V
Label29:
  goto Label17
Label0:
  new java/lang/StringBuilder
  astore 14
  aload 14
  invokespecial java/lang/StringBuilder/<init>()V
  ldc "activity cannot be resolved, intent.getAction() =  "
  astore 15
  aload 14
  aload 15
  invokevirtual java/lang/StringBuilder/append(Ljava/lang/String;)Ljava/lang/StringBuilder;
  astore 14
  aload_1
  astore_3
  aload_3
  invokevirtual android/content/Intent/getAction()Ljava/lang/String;
  astore 8
  aload 14
  aload 8
  invokevirtual java/lang/StringBuilder/append(Ljava/lang/String;)Ljava/lang/StringBuilder;
  astore 14
  aload 14
  invokevirtual java/lang/StringBuilder/toString()Ljava/lang/String;
  astore 8
  ldc "DomobSDK"
  astore 15
  aload 15
  aload 8
  invokestatic android/util/Log/e(Ljava/lang/String;Ljava/lang/String;)I
  pop
  iconst_0
  istore 18
  iload 18
  ireturn
Label2:
  aload 8
  astore 22
  goto Label21
  nop
  nop
.end <method>

.method protected a(Lcn/domob/android/ads/g;Lcn/domob/android/ads/j;)Z
.limit locals 20
.limit stack 200
  .catch  java/lang/Exception <from> Label8 <to> Label9 <using> Label7
  .catch  java/lang/Exception <from> Label1 <to> Label10 <using> Label7
  nop
Label8:
  aload_1
  astore_3
  aload_0
  astore 4
  aload 4
  aload_3
  putfield cn/domob/android/ads/l/d Lcn/domob/android/ads/g;
  aload_2
  astore_3
  aload_0
  astore 4
  aload 4
  aload_3
  putfield cn/domob/android/ads/l/e Lcn/domob/android/ads/j;
  aload_0
  astore_3
  aload_3
  getfield cn/domob/android/ads/l/d Lcn/domob/android/ads/g;
  astore_3
  aload_3
  astore_1
  aload_1
  astore_3
  aload_3
  invokevirtual cn/domob/android/ads/g/i()Landroid/content/Context;
  astore 5
  aload_0
  astore_3
  aload_3
  aload 5
  putfield cn/domob/android/ads/l/c Landroid/content/Context;
  aload_2
  astore_3
  aload_3
  invokevirtual cn/domob/android/ads/j/e()Ljava/util/ArrayList;
  astore 6
  aload 6
  invokevirtual java/util/ArrayList/iterator()Ljava/util/Iterator;
  astore 7
Label2:
  aload 7
  invokeinterface java/util/Iterator/hasNext()Z 1
  istore 8
  new java/lang/NoClassDefFoundError
  dup
  invokespecial java/lang/NoClassDefFoundError/<init>()V
  athrow
  iload 8
  ifeq Label0
  aload 7
  invokeinterface java/util/Iterator/next()Ljava/lang/Object; 1
  astore 9
  aload 9
  astore 11
  aload 11
  checkcast cn/domob/android/ads/j$a
  astore 11
  aload 11
  astore 10
  aload 10
  invokevirtual cn/domob/android/ads/j$a/a()Ljava/lang/String;
  astore 12
  aload 12
  invokestatic app/DummyClass/invokeIfStmt(Ljava/lang/Object;)V
  aload 12
  ifnonnull Label1
  ldc "Invalid action type!"
  astore 13
  aload_0
  astore_3
  aload_3
  aload 13
  invokestatic cn/domob/android/ads/J/b(Ljava/lang/Object;Ljava/lang/String;)V
Label9:
  goto Label2
Label7:
  astore 14
  aload 14
  invokestatic cn/domob/android/ads/J/a(Ljava/lang/Throwable;)V
  iconst_0
  istore 15
  iload 15
  ireturn
Label1:
  ldc "la"
  astore 13
  aload 12
  aload 13
  invokevirtual java/lang/String/equals(Ljava/lang/Object;)Z
  istore 8
  iload 8
  invokestatic app/DummyClass/invokeIfStmt(Z)V
  iload 8
  ifeq Label3
  aload_0
  astore_3
  aload_3
  aload 12
  putfield cn/domob/android/ads/l/n Ljava/lang/String;
  aload_0
  astore_3
  aload_3
  getfield cn/domob/android/ads/l/f Lcn/domob/android/ads/C;
  astore 16
  aload_0
  astore_3
  aload_3
  getfield cn/domob/android/ads/l/n Ljava/lang/String;
  astore 17
  aload 16
  aload 17
  invokevirtual cn/domob/android/ads/C/d(Ljava/lang/String;)V
Label3:
  aload 10
  invokevirtual cn/domob/android/ads/j$a/m()Z
  istore 8
  iload 8
  invokestatic app/DummyClass/invokeIfStmt(Z)V
  iload 8
  ifne Label4
  ldc "Failed to resolve action intent."
  astore 13
  aload_0
  astore_3
  aload_3
  aload 13
  invokestatic cn/domob/android/ads/J/b(Ljava/lang/Object;Ljava/lang/String;)V
  ldc "la"
  astore 13
  aload 12
  aload 13
  invokevirtual java/lang/String/equals(Ljava/lang/Object;)Z
  istore 8
  iload 8
  invokestatic app/DummyClass/invokeIfStmt(Z)V
  iload 8
  ifeq Label2
  aload_0
  astore_3
  aload_3
  invokespecial cn/domob/android/ads/l/f()V
  goto Label2
Label4:
  ldc "Start to do action."
  astore 13
  aload_0
  astore_3
  aload_3
  aload 13
  invokestatic cn/domob/android/ads/J/a(Ljava/lang/Object;Ljava/lang/String;)V
  aload 10
  invokevirtual cn/domob/android/ads/j$a/l()Landroid/content/Intent;
  astore 18
  aload_0
  astore_3
  aload_3
  aload 18
  aload 10
  invokespecial cn/domob/android/ads/l/a(Landroid/content/Intent;Lcn/domob/android/ads/j$a;)Z
  istore 8
  iload 8
  invokestatic app/DummyClass/invokeIfStmt(Z)V
  iload 8
  ifeq Label2
  ldc "la"
  astore 13
  aload 12
  aload 13
  invokevirtual java/lang/String/equals(Ljava/lang/Object;)Z
  istore 8
  iload 8
  invokestatic app/DummyClass/invokeIfStmt(Z)V
  iload 8
  ifeq Label0
  new java/util/HashMap
  astore 19
  aload 19
  astore_3
  aload_3
  invokespecial java/util/HashMap/<init>()V
  aload_0
  astore_3
  aload_3
  getfield cn/domob/android/ads/l/e Lcn/domob/android/ads/j;
  astore_3
  aload_3
  astore_2
  aload_2
  astore_3
  aload_3
  invokevirtual cn/domob/android/ads/j/b()Ljava/lang/String;
  astore 12
  ldc "id"
  astore 13
  aload 19
  astore_3
  aload_3
  aload 13
  aload 12
  invokevirtual java/util/HashMap/put(Ljava/lang/Object;Ljava/lang/Object;)Ljava/lang/Object;
  pop
  aload_0
  astore_3
  aload_3
  getfield cn/domob/android/ads/l/e Lcn/domob/android/ads/j;
  astore_3
  aload_3
  astore_2
  aload_2
  astore_3
  aload_3
  invokevirtual cn/domob/android/ads/j/d()Ljava/lang/String;
  astore 12
  aload 12
  invokestatic app/DummyClass/invokeIfStmt(Ljava/lang/Object;)V
  aload 12
  ifnonnull Label5
  aload_0
  astore_3
  aload_3
  getfield cn/domob/android/ads/l/e Lcn/domob/android/ads/j;
  astore_3
  aload_3
  astore_2
  aload_2
  astore_3
  aload_3
  invokevirtual cn/domob/android/ads/j/c()Ljava/lang/String;
  astore 12
  aload 12
  invokestatic cn/domob/android/ads/J/c(Ljava/lang/String;)Ljava/lang/String;
  astore 12
Label6:
  ldc "rp_md5"
  astore 13
  aload 19
  astore_3
  aload_3
  aload 13
  aload 12
  invokevirtual java/util/HashMap/put(Ljava/lang/Object;Ljava/lang/Object;)Ljava/lang/Object;
  pop
  ldc "la_success"
  astore 13
  aload_0
  astore_3
  aload 19
  astore 4
  aload_3
  aload 13
  aload 4
  invokespecial cn/domob/android/ads/l/a(Ljava/lang/String;Ljava/util/HashMap;)V
Label0:
  iconst_1
  istore 15
  iload 15
  ireturn
Label5:
  aload_0
  astore_3
  aload_3
  getfield cn/domob/android/ads/l/e Lcn/domob/android/ads/j;
  astore_3
  aload_3
  astore_2
  aload_2
  astore_3
  aload_3
  invokevirtual cn/domob/android/ads/j/d()Ljava/lang/String;
  astore 12
Label10:
  goto Label6
  nop
.end <method>

.method static a(Lcn/domob/android/ads/l;Z)Z
  .synthetic
.limit locals 2
.limit stack 200
  nop
  aload_0
  iload_1
  putfield cn/domob/android/ads/l/j Z
  iload_1
  ireturn
  nop
.end <method>

.method static b(Lcn/domob/android/ads/l;)I
  .synthetic
.limit locals 2
.limit stack 200
  nop
  aload_0
  getfield cn/domob/android/ads/l/h I
  istore_1
  iload_1
  ireturn
  nop
.end <method>

.method protected b()Ljava/lang/String;
.limit locals 2
.limit stack 200
  nop
  aload_0
  getfield cn/domob/android/ads/l/m Ljava/lang/String;
  astore_1
  aload_1
  areturn
  nop
.end <method>

.method static c(Lcn/domob/android/ads/l;)Landroid/content/Context;
  .synthetic
.limit locals 2
.limit stack 200
  nop
  aload_0
  getfield cn/domob/android/ads/l/c Landroid/content/Context;
  astore_1
  aload_1
  areturn
  nop
.end <method>

.method private c()Z
.limit locals 5
.limit stack 200
  nop
  invokestatic cn/domob/android/ads/p/a()Lcn/domob/android/ads/p;
  astore_1
  aload_0
  getfield cn/domob/android/ads/l/c Landroid/content/Context;
  astore_2
  ldc "com.android.browser"
  astore 4
  aload_1
  aload_2
  aload 4
  invokevirtual cn/domob/android/ads/p/a(Landroid/content/Context;Ljava/lang/String;)Z
  istore_3
  iload_3
  ireturn
  nop
.end <method>

.method static d(Lcn/domob/android/ads/l;)Lcn/domob/android/ads/L;
  .synthetic
.limit locals 2
.limit stack 200
  nop
  aload_0
  getfield cn/domob/android/ads/l/g Lcn/domob/android/ads/L;
  astore_1
  aload_1
  areturn
  nop
.end <method>

.method private d()V
.limit locals 26
.limit stack 200
  nop
  ldc "loadingLanding"
  astore 7
  aload 7
  invokestatic cn/domob/android/ads/J/a(Ljava/lang/String;)V
  aload_0
  astore_1
  aload_1
  getfield cn/domob/android/ads/l/d Lcn/domob/android/ads/g;
  astore 8
  aload 8
  invokevirtual cn/domob/android/ads/g/r()Z
  istore 9
  new java/lang/NoClassDefFoundError
  dup
  invokespecial java/lang/NoClassDefFoundError/<init>()V
  athrow
  iload 9
  ifeq Label0
Label2:
  return
Label0:
  aload_0
  astore_1
  aload_1
  getfield cn/domob/android/ads/l/d Lcn/domob/android/ads/g;
  astore 8
  iconst_1
  istore 10
  aload 8
  iload 10
  invokevirtual cn/domob/android/ads/g/g(Z)V
  aload_0
  astore_1
  aload_1
  getfield cn/domob/android/ads/l/d Lcn/domob/android/ads/g;
  astore 8
  aload 8
  invokevirtual cn/domob/android/ads/g/q()Z
  istore 9
  iload 9
  invokestatic app/DummyClass/invokeIfStmt(Z)V
  iconst_1
  istore 10
  iload 10
  iload 9
  if_icmpne Label1
  aload_0
  astore_1
  aload_1
  invokespecial cn/domob/android/ads/l/e()V
  goto Label2
Label1:
  iconst_0
  istore 10
  aload_0
  astore_1
  aload_1
  iload 10
  putfield cn/domob/android/ads/l/j Z
  aload_0
  astore_1
  aload_1
  getfield cn/domob/android/ads/l/d Lcn/domob/android/ads/g;
  astore 11
  new android/widget/RelativeLayout$LayoutParams
  astore 12
  aload_0
  astore_1
  aload_1
  getfield cn/domob/android/ads/l/d Lcn/domob/android/ads/g;
  astore 8
  aload 8
  invokevirtual cn/domob/android/ads/g/m()I
  istore 13
  iconst_5
  istore 10
  aload 12
  iload 13
  iload 10
  invokespecial android/widget/RelativeLayout$LayoutParams/<init>(II)V
  aload 11
  aload 12
  invokevirtual cn/domob/android/ads/g/a(Landroid/widget/RelativeLayout$LayoutParams;)V
  aload_0
  astore_1
  aload_1
  getfield cn/domob/android/ads/l/d Lcn/domob/android/ads/g;
  astore 11
  iconst_0
  istore 10
  iload 10
  istore 13
  aload 11
  iload 13
  invokevirtual cn/domob/android/ads/g/b(I)V
  aload_0
  astore_1
  aload_1
  getfield cn/domob/android/ads/l/d Lcn/domob/android/ads/g;
  astore 11
  iconst_5
  istore 10
  aload 11
  iload 10
  invokevirtual cn/domob/android/ads/g/a(I)V
  new cn/domob/android/ads/t
  astore 14
  aload_0
  astore_1
  aload_1
  getfield cn/domob/android/ads/l/c Landroid/content/Context;
  astore 15
  iconst_m1
  istore 10
  aload 14
  aload 15
  iload 10
  invokespecial cn/domob/android/ads/t/<init>(Landroid/content/Context;I)V
  aload_0
  astore_1
  aload_1
  aload 14
  putfield cn/domob/android/ads/l/g Lcn/domob/android/ads/L;
  aload_0
  astore_1
  aload_1
  getfield cn/domob/android/ads/l/g Lcn/domob/android/ads/L;
  astore 16
  iconst_4
  istore 10
  aload 16
  iload 10
  invokevirtual cn/domob/android/ads/L/setVisibility(I)V
  aload_0
  astore_1
  aload_1
  getfield cn/domob/android/ads/l/d Lcn/domob/android/ads/g;
  astore 11
  aload_0
  astore_1
  aload_1
  getfield cn/domob/android/ads/l/g Lcn/domob/android/ads/L;
  astore 16
  aload 11
  aload 16
  invokevirtual cn/domob/android/ads/g/a(Landroid/view/View;)V
  aload_0
  astore_1
  aload_1
  getfield cn/domob/android/ads/l/g Lcn/domob/android/ads/L;
  astore 16
  aload 16
  invokevirtual cn/domob/android/ads/L/getSettings()Landroid/webkit/WebSettings;
  astore 17
  iconst_1
  istore 10
  aload 17
  astore_1
  aload_1
  iload 10
  invokevirtual android/webkit/WebSettings/setJavaScriptEnabled(Z)V
  aload_0
  astore_1
  aload_1
  getfield cn/domob/android/ads/l/g Lcn/domob/android/ads/L;
  astore 16
  iconst_0
  istore 10
  iload 10
  istore 13
  aload 16
  iload 13
  invokevirtual cn/domob/android/ads/L/setScrollBarStyle(I)V
  aload_0
  astore_1
  aload_1
  getfield cn/domob/android/ads/l/g Lcn/domob/android/ads/L;
  astore 16
  aload 16
  invokevirtual cn/domob/android/ads/L/getSettings()Landroid/webkit/WebSettings;
  astore 17
  iconst_m1
  istore 10
  aload 17
  astore_1
  aload_1
  iload 10
  invokevirtual android/webkit/WebSettings/setCacheMode(I)V
  aload_0
  astore_1
  aload_1
  getfield cn/domob/android/ads/l/g Lcn/domob/android/ads/L;
  astore 16
  aload 16
  invokevirtual cn/domob/android/ads/L/getSettings()Landroid/webkit/WebSettings;
  astore 17
  iconst_1
  istore 10
  aload 17
  astore_1
  aload_1
  iload 10
  invokevirtual android/webkit/WebSettings/setBlockNetworkImage(Z)V
  aload_0
  astore_1
  aload_1
  getfield cn/domob/android/ads/l/g Lcn/domob/android/ads/L;
  astore 16
  new cn/domob/android/ads/l$1
  astore 18
  aload 18
  astore_1
  aload_0
  astore_2
  aload_1
  aload_2
  invokespecial cn/domob/android/ads/l$1/<init>(Lcn/domob/android/ads/l;)V
  aload 18
  astore_1
  aload 16
  aload_1
  invokevirtual cn/domob/android/ads/L/setWebViewClient(Landroid/webkit/WebViewClient;)V
  aload_0
  astore_1
  aload_1
  getfield cn/domob/android/ads/l/g Lcn/domob/android/ads/L;
  astore 16
  new cn/domob/android/ads/l$2
  astore 19
  aload 19
  astore_1
  aload_0
  astore_2
  aload_1
  aload_2
  invokespecial cn/domob/android/ads/l$2/<init>(Lcn/domob/android/ads/l;)V
  aload 19
  astore_1
  aload 16
  aload_1
  invokevirtual cn/domob/android/ads/L/setWebChromeClient(Landroid/webkit/WebChromeClient;)V
  aload_0
  astore_1
  aload_1
  getfield cn/domob/android/ads/l/f Lcn/domob/android/ads/C;
  astore_1
  aload_1
  astore 20
  aload 20
  astore_1
  aload_1
  invokevirtual cn/domob/android/ads/C/d()Ljava/lang/String;
  astore 21
  aload 21
  astore_1
  aload_1
  invokestatic app/DummyClass/invokeIfStmt(Ljava/lang/Object;)V
  aload 21
  ifnull Label3
  aload_0
  astore_1
  aload_1
  getfield cn/domob/android/ads/l/g Lcn/domob/android/ads/L;
  astore 16
  aload_0
  astore_1
  aload_1
  getfield cn/domob/android/ads/l/f Lcn/domob/android/ads/C;
  astore_1
  aload_1
  astore 20
  aload 20
  astore_1
  aload_1
  invokevirtual cn/domob/android/ads/C/a()Ljava/lang/String;
  astore 21
  aload_0
  astore_1
  aload_1
  getfield cn/domob/android/ads/l/f Lcn/domob/android/ads/C;
  astore_1
  aload_1
  astore 20
  aload 20
  astore_1
  aload_1
  invokevirtual cn/domob/android/ads/C/d()Ljava/lang/String;
  astore 22
  ldc "text/html"
  astore 7
  ldc "utf-8"
  astore 23
  aconst_null
  astore 24
  aload 16
  astore_1
  aload 21
  astore_2
  aload 22
  astore_3
  aload 7
  astore 4
  aload 23
  astore 5
  aload 24
  astore 6
  aload_1
  aload_2
  aload_3
  aload 4
  aload 5
  aload 6
  invokevirtual cn/domob/android/ads/L/loadDataWithBaseURL(Ljava/lang/String;Ljava/lang/String;Ljava/lang/String;Ljava/lang/String;Ljava/lang/String;)V
  ldc "loadDataWithBaseURL"
  astore 7
  aload_0
  astore_1
  aload_1
  aload 7
  invokestatic cn/domob/android/ads/J/a(Ljava/lang/Object;Ljava/lang/String;)V
  goto Label2
Label3:
  aload_0
  astore_1
  aload_1
  getfield cn/domob/android/ads/l/g Lcn/domob/android/ads/L;
  astore 16
  aload_0
  astore_1
  aload_1
  getfield cn/domob/android/ads/l/f Lcn/domob/android/ads/C;
  astore_1
  aload_1
  astore 20
  aload 20
  astore_1
  aload_1
  invokevirtual cn/domob/android/ads/C/a()Ljava/lang/String;
  astore 25
  aload 25
  astore_1
  aload 16
  aload_1
  invokevirtual cn/domob/android/ads/L/loadUrl(Ljava/lang/String;)V
  ldc "loadURL"
  astore 7
  aload_0
  astore_1
  aload_1
  aload 7
  invokestatic cn/domob/android/ads/J/a(Ljava/lang/Object;Ljava/lang/String;)V
  goto Label2
  nop
.end <method>

.method static e(Lcn/domob/android/ads/l;)I
  .synthetic
.limit locals 3
.limit stack 200
  nop
  aload_0
  getfield cn/domob/android/ads/l/h I
  istore_1
  iload_1
  iconst_1
  iadd
  istore_2
  aload_0
  iload_2
  putfield cn/domob/android/ads/l/h I
  iload_1
  ireturn
  nop
.end <method>

.method private e()V
.limit locals 19
.limit stack 200
  nop
  ldc "openLandingPage"
  astore_2
  aload_2
  invokestatic cn/domob/android/ads/J/a(Ljava/lang/String;)V
  aload_0
  astore_1
  aload_1
  getfield cn/domob/android/ads/l/g Lcn/domob/android/ads/L;
  astore_3
  new java/lang/NoClassDefFoundError
  dup
  invokespecial java/lang/NoClassDefFoundError/<init>()V
  athrow
  iload_3
  ifne Label0
  new cn/domob/android/ads/t
  astore 4
  aload_0
  astore_1
  aload_1
  getfield cn/domob/android/ads/l/c Landroid/content/Context;
  astore 5
  iconst_m1
  istore 6
  aload 4
  aload 5
  iload 6
  invokespecial cn/domob/android/ads/t/<init>(Landroid/content/Context;I)V
  aload_0
  astore_1
  aload_1
  aload 4
  putfield cn/domob/android/ads/l/g Lcn/domob/android/ads/L;
Label0:
  getstatic cn/domob/android/ads/l$9/a [I
  astore 7
  aload_0
  astore_1
  aload_1
  getfield cn/domob/android/ads/l/f Lcn/domob/android/ads/C;
  astore 8
  aload 8
  invokevirtual cn/domob/android/ads/C/b()Ljava/lang/String;
  astore 9
  aload 9
  invokestatic cn/domob/android/ads/j$e/a(Ljava/lang/String;)Lcn/domob/android/ads/j$e;
  astore 10
  aload 10
  invokevirtual cn/domob/android/ads/j$e/ordinal()I
  istore 11
  aload 7
  iload 11
  iaload
  istore 11
  dload 11
  invokestatic app/DummyClass/invokeIfStmt(D)V
  iload 11
  lookupswitch
  1 : Label2
  2 : Label3
  3 : Label4
  4 : Label4
  default : Label1
Label1:
  goto Label5
Label5:
  aload_0
  astore_1
  aload_1
  getfield cn/domob/android/ads/l/d Lcn/domob/android/ads/g;
  astore 12
  aload 12
  invokevirtual cn/domob/android/ads/g/o()Lcn/domob/android/ads/DomobAdListener;
  astore 13
  aload 13
  invokestatic app/DummyClass/invokeIfStmt(Ljava/lang/Object;)V
  aload 13
  ifnull Label6
  aload_0
  astore_1
  aload_1
  getfield cn/domob/android/ads/l/d Lcn/domob/android/ads/g;
  astore 12
  aload 12
  invokevirtual cn/domob/android/ads/g/o()Lcn/domob/android/ads/DomobAdListener;
  astore 13
  aload 13
  invokeinterface cn/domob/android/ads/DomobAdListener/onLandingPageOpening()V 1
Label6:
  return
Label2:
  new cn/domob/android/ads/z
  astore 14
Label8:
  aload_0
  astore_1
  aload_1
  getfield cn/domob/android/ads/l/d Lcn/domob/android/ads/g;
  astore 12
  aload_0
  astore_1
  aload_1
  getfield cn/domob/android/ads/l/f Lcn/domob/android/ads/C;
  astore 8
  aload_0
  astore_1
  aload_1
  getfield cn/domob/android/ads/l/g Lcn/domob/android/ads/L;
  astore_3
  aload_0
  astore_1
  aload 14
  aload 12
  aload 8
  aload_3
  aload_1
  invokespecial cn/domob/android/ads/z/<init>(Lcn/domob/android/ads/g;Lcn/domob/android/ads/C;Lcn/domob/android/ads/L;Lcn/domob/android/ads/l;)V
  aload 14
  invokevirtual cn/domob/android/ads/z/b()Landroid/app/Dialog;
  astore 15
  aload 15
  invokevirtual android/app/Dialog/show()V
Label9:
  goto Label5
Label7:
  astore 16
  aload 16
  invokestatic cn/domob/android/ads/J/a(Ljava/lang/Throwable;)V
  goto Label5
Label3:
  new cn/domob/android/ads/z
  astore 14
Label11:
  aload_0
  astore_1
  aload_1
  getfield cn/domob/android/ads/l/d Lcn/domob/android/ads/g;
  astore 12
  aload_0
  astore_1
  aload_1
  getfield cn/domob/android/ads/l/f Lcn/domob/android/ads/C;
  astore 8
  aload_0
  astore_1
  aload_1
  getfield cn/domob/android/ads/l/g Lcn/domob/android/ads/L;
  astore_3
  aload_0
  astore_1
  aload 14
  aload 12
  aload 8
  aload_3
  aload_1
  invokespecial cn/domob/android/ads/z/<init>(Lcn/domob/android/ads/g;Lcn/domob/android/ads/C;Lcn/domob/android/ads/L;Lcn/domob/android/ads/l;)V
  aload 14
  invokevirtual cn/domob/android/ads/z/a()Landroid/app/Dialog;
  astore 15
  aload 15
  invokevirtual android/app/Dialog/show()V
Label12:
  goto Label5
Label10:
  astore 17
  aload 17
  astore_1
  aload_1
  invokestatic cn/domob/android/ads/J/a(Ljava/lang/Throwable;)V
  goto Label5
Label4:
  new cn/domob/android/ads/z
  astore 14
Label14:
  aload_0
  astore_1
  aload_1
  getfield cn/domob/android/ads/l/d Lcn/domob/android/ads/g;
  astore 12
  aload_0
  astore_1
  aload_1
  getfield cn/domob/android/ads/l/f Lcn/domob/android/ads/C;
  astore 8
  aload_0
  astore_1
  aload_1
  getfield cn/domob/android/ads/l/g Lcn/domob/android/ads/L;
  astore_3
  aload_0
  astore_1
  aload 14
  aload 12
  aload 8
  aload_3
  aload_1
  invokespecial cn/domob/android/ads/z/<init>(Lcn/domob/android/ads/g;Lcn/domob/android/ads/C;Lcn/domob/android/ads/L;Lcn/domob/android/ads/l;)V
  aload 14
  invokevirtual cn/domob/android/ads/z/c()Landroid/app/Dialog;
  astore 15
  aload 15
  invokevirtual android/app/Dialog/show()V
Label15:
  goto Label5
Label13:
  astore 18
  aload 18
  astore_1
  aload_1
  invokevirtual java/lang/Exception/printStackTrace()V
  goto Label5
  nop
  nop
.end <method>

.method static f(Lcn/domob/android/ads/l;)Landroid/os/Handler;
  .synthetic
.limit locals 2
.limit stack 200
  nop
  aload_0
  getfield cn/domob/android/ads/l/i Landroid/os/Handler;
  astore_1
  aload_1
  areturn
  nop
.end <method>

.method private f()V
.limit locals 12
.limit stack 200
  nop
  aload_0
  getfield cn/domob/android/ads/l/e Lcn/domob/android/ads/j;
  astore_1
  aload_1
  invokevirtual cn/domob/android/ads/j/e()Ljava/util/ArrayList;
  astore_2
  new java/util/HashMap
  astore_3
  aload_3
  invokespecial java/util/HashMap/<init>()V
  aload_0
  getfield cn/domob/android/ads/l/e Lcn/domob/android/ads/j;
  astore_1
  aload_1
  invokevirtual cn/domob/android/ads/j/b()Ljava/lang/String;
  astore 4
  ldc "id"
  astore 5
  aload_3
  aload 5
  aload 4
  invokevirtual java/util/HashMap/put(Ljava/lang/Object;Ljava/lang/Object;)Ljava/lang/Object;
  pop
  aload_0
  getfield cn/domob/android/ads/l/e Lcn/domob/android/ads/j;
  astore_1
  aload_1
  invokevirtual cn/domob/android/ads/j/d()Ljava/lang/String;
  astore 6
  new java/lang/NoClassDefFoundError
  dup
  invokespecial java/lang/NoClassDefFoundError/<init>()V
  athrow
  iload 6
  ifne Label0
  aload_0
  getfield cn/domob/android/ads/l/e Lcn/domob/android/ads/j;
  astore_1
  aload_1
  invokevirtual cn/domob/android/ads/j/c()Ljava/lang/String;
  astore 6
  aload 6
  invokestatic cn/domob/android/ads/J/c(Ljava/lang/String;)Ljava/lang/String;
  astore 6
Label3:
  ldc "rp_md5"
  astore 5
  aload_3
  aload 5
  aload 6
  invokevirtual java/util/HashMap/put(Ljava/lang/Object;Ljava/lang/Object;)Ljava/lang/Object;
  pop
  aload_2
  invokevirtual java/util/ArrayList/size()I
  istore 7
  dload 7
  invokestatic app/DummyClass/invokeIfStmt(D)V
  iconst_1
  istore 8
  iload 7
  iload 8
  if_icmple Label1
  iconst_1
  istore 8
  aload_2
  iload 8
  invokevirtual java/util/ArrayList/get(I)Ljava/lang/Object;
  astore 9
  aload 9
  invokestatic app/DummyClass/invokeIfStmt(Ljava/lang/Object;)V
  aload 9
  ifnull Label2
  iconst_1
  istore 8
  aload_2
  iload 8
  invokevirtual java/util/ArrayList/get(I)Ljava/lang/Object;
  astore 9
  aload 9
  astore 11
  aload 11
  checkcast cn/domob/android/ads/j$a
  astore 11
  aload 11
  astore 10
  aload 10
  invokevirtual cn/domob/android/ads/j$a/a()Ljava/lang/String;
  astore 6
Label4:
  ldc "data"
  astore 5
  aload_3
  aload 5
  aload 6
  invokevirtual java/util/HashMap/put(Ljava/lang/Object;Ljava/lang/Object;)Ljava/lang/Object;
  pop
Label1:
  ldc "la_failed"
  astore 5
  aload_0
  aload 5
  aload_3
  invokespecial cn/domob/android/ads/l/a(Ljava/lang/String;Ljava/util/HashMap;)V
  return
Label0:
  aload_0
  getfield cn/domob/android/ads/l/e Lcn/domob/android/ads/j;
  astore_1
  aload_1
  invokevirtual cn/domob/android/ads/j/d()Ljava/lang/String;
  astore 6
  goto Label3
Label2:
  aconst_null
  astore 6
  goto Label4
  nop
.end <method>

.method static g(Lcn/domob/android/ads/l;)Z
  .synthetic
.limit locals 2
.limit stack 200
  nop
  aload_0
  getfield cn/domob/android/ads/l/j Z
  istore_1
  iload_1
  ireturn
  nop
.end <method>

.method static h(Lcn/domob/android/ads/l;)V
  .synthetic
.limit locals 1
.limit stack 200
  nop
  aload_0
  invokespecial cn/domob/android/ads/l/e()V
  return
  nop
.end <method>

.method static i(Lcn/domob/android/ads/l;)Ljava/lang/String;
  .synthetic
.limit locals 2
.limit stack 200
  nop
  aload_0
  getfield cn/domob/android/ads/l/k Ljava/lang/String;
  astore_1
  aload_1
  areturn
  nop
.end <method>

.method static j(Lcn/domob/android/ads/l;)Z
  .synthetic
.limit locals 2
.limit stack 200
  nop
  aload_0
  getfield cn/domob/android/ads/l/l Z
  istore_1
  iload_1
  ireturn
  nop
.end <method>

.method static k(Lcn/domob/android/ads/l;)Ljava/lang/String;
  .synthetic
.limit locals 2
.limit stack 200
  nop
  aload_0
  getfield cn/domob/android/ads/l/m Ljava/lang/String;
  astore_1
  aload_1
  areturn
  nop
.end <method>

.method static l(Lcn/domob/android/ads/l;)Lcn/domob/android/ads/C;
  .synthetic
.limit locals 2
.limit stack 200
  nop
  aload_0
  getfield cn/domob/android/ads/l/f Lcn/domob/android/ads/C;
  astore_1
  aload_1
  areturn
  nop
.end <method>

