.source SourceFile
.class final  cn/domob/android/ads/a
.super java/lang/Object

.method <init>()V
.limit locals 1
.limit stack 200
  nop
  aload_0
  invokespecial java/lang/Object/<init>()V
  return
  nop
.end <method>

.method protected static a(Ljava/lang/String;Ljava/lang/String;)Lcn/domob/android/ads/n;
.limit locals 17
.limit stack 200
  nop
  aconst_null
  astore 11
  aconst_null
  astore 12
  aconst_null
  astore 13
  aconst_null
  astore 14
  sipush 30000
  istore 15
  aconst_null
  astore 16
  aload_0
  astore_2
  aload 11
  astore_3
  aload 12
  astore 4
  aload 13
  astore 5
  aload 14
  astore 6
  iload 15
  istore 7
  aload 16
  astore 8
  aload_1
  astore 9
  aload_2
  aload_3
  aload 4
  aload 5
  aload 6
  iload 7
  aload 8
  aload 9
  invokestatic cn/domob/android/ads/a/a(Ljava/lang/String;Ljava/lang/String;Ljava/lang/String;Ljava/lang/String;Lcn/domob/android/ads/b;ILjava/util/Map;Ljava/lang/String;)Lcn/domob/android/ads/n;
  astore 10
  aload 10
  areturn
  nop
.end <method>

.method protected static a(Ljava/lang/String;Ljava/lang/String;Ljava/lang/String;Ljava/lang/String;)Lcn/domob/android/ads/n;
.limit locals 6
.limit stack 200
  nop
  aconst_null
  astore 5
  aload_0
  aload_1
  aload_2
  aload_3
  aload 5
  invokestatic cn/domob/android/ads/a/a(Ljava/lang/String;Ljava/lang/String;Ljava/lang/String;Ljava/lang/String;Lcn/domob/android/ads/b;)Lcn/domob/android/ads/n;
  astore 4
  aload 4
  areturn
  nop
.end <method>

.method protected static a(Ljava/lang/String;Ljava/lang/String;Ljava/lang/String;Ljava/lang/String;Lcn/domob/android/ads/b;)Lcn/domob/android/ads/n;
.limit locals 17
.limit stack 200
  nop
  sipush 30000
  istore 14
  aconst_null
  astore 15
  aconst_null
  astore 16
  aload_0
  astore 5
  aload_1
  astore 6
  aload_2
  astore 7
  aload_3
  astore 8
  aload 4
  astore 9
  iload 14
  istore 10
  aload 15
  astore 11
  aload 16
  astore 12
  aload 5
  aload 6
  aload 7
  aload 8
  aload 9
  iload 10
  aload 11
  aload 12
  invokestatic cn/domob/android/ads/a/a(Ljava/lang/String;Ljava/lang/String;Ljava/lang/String;Ljava/lang/String;Lcn/domob/android/ads/b;ILjava/util/Map;Ljava/lang/String;)Lcn/domob/android/ads/n;
  astore 13
  aload 13
  areturn
  nop
.end <method>

.method protected static a(Ljava/lang/String;Ljava/lang/String;Ljava/lang/String;Ljava/lang/String;Lcn/domob/android/ads/b;I)Lcn/domob/android/ads/n;
.limit locals 19
.limit stack 200
  nop
  aconst_null
  astore 15
  sipush 30000
  istore 16
  aconst_null
  astore 17
  aconst_null
  astore 18
  aload_0
  astore 6
  aload 15
  astore 7
  aload_2
  astore 8
  aload_3
  astore 9
  aload 4
  astore 10
  iload 16
  istore 11
  aload 17
  astore 12
  aload 18
  astore 13
  aload 6
  aload 7
  aload 8
  aload 9
  aload 10
  iload 11
  aload 12
  aload 13
  invokestatic cn/domob/android/ads/a/a(Ljava/lang/String;Ljava/lang/String;Ljava/lang/String;Ljava/lang/String;Lcn/domob/android/ads/b;ILjava/util/Map;Ljava/lang/String;)Lcn/domob/android/ads/n;
  astore 14
  new java/lang/NoClassDefFoundError
  dup
  invokespecial java/lang/NoClassDefFoundError/<init>()V
  athrow
  iload 14
  ifeq Label0
  iconst_1
  istore 16
  aload 14
  iload 16
  invokevirtual cn/domob/android/ads/n/a(I)V
Label0:
  aload 14
  areturn
  nop
.end <method>

.method protected static a(Ljava/lang/String;Ljava/lang/String;Ljava/lang/String;Ljava/lang/String;Lcn/domob/android/ads/b;ILjava/util/Map;Ljava/lang/String;)Lcn/domob/android/ads/n;
  .signature_attr "(Ljava/lang/String;Ljava/lang/String;Ljava/lang/String;Ljava/lang/String;Lcn/domob/android/ads/b;ILjava/util/Map<Ljava/lang/String;Ljava/lang/String;>;Ljava/lang/String;)Lcn/domob/android/ads/n;"
.limit locals 19
.limit stack 200
  nop
  new cn/domob/android/ads/Q
  astore 17
  aconst_null
  astore 18
  aload 17
  astore 8
  aload_0
  astore 9
  aload_1
  astore 10
  aload_2
  astore 11
  aload_3
  astore 12
  aload 4
  astore 13
  iload 5
  istore 14
  aload 18
  astore 15
  aload 7
  astore 16
  aload 8
  aload 9
  aload 10
  aload 11
  aload 12
  aload 13
  iload 14
  aload 15
  aload 16
  invokespecial cn/domob/android/ads/Q/<init>(Ljava/lang/String;Ljava/lang/String;Ljava/lang/String;Ljava/lang/String;Lcn/domob/android/ads/b;ILjava/util/Map;Ljava/lang/String;)V
  aload 17
  areturn
  nop
.end <method>

.method protected static a(Ljava/lang/String;Ljava/lang/String;Ljava/lang/String;Ljava/lang/String;Lcn/domob/android/ads/b;Ljava/lang/String;)Lcn/domob/android/ads/n;
.limit locals 17
.limit stack 200
  nop
  sipush 30000
  istore 15
  aconst_null
  astore 16
  aload_0
  astore 6
  aload_1
  astore 7
  aload_2
  astore 8
  aload_3
  astore 9
  aload 4
  astore 10
  iload 15
  istore 11
  aload 16
  astore 12
  aload 5
  astore 13
  aload 6
  aload 7
  aload 8
  aload 9
  aload 10
  iload 11
  aload 12
  aload 13
  invokestatic cn/domob/android/ads/a/a(Ljava/lang/String;Ljava/lang/String;Ljava/lang/String;Ljava/lang/String;Lcn/domob/android/ads/b;ILjava/util/Map;Ljava/lang/String;)Lcn/domob/android/ads/n;
  astore 14
  aload 14
  areturn
  nop
.end <method>

