.source SourceFile
.class  cn/domob/android/ads/N$1
.super java/lang/Object
.implements  java/lang/Runnable
.field final "a" Lcn/domob/android/ads/L;
.field final "b" Ljava/lang/String;
.field final "c" Lcn/domob/android/ads/N;

.method <init>(Lcn/domob/android/ads/N;Lcn/domob/android/ads/L;Ljava/lang/String;)V
.limit locals 4
.limit stack 200
  nop
  aload_0
  aload_1
  putfield cn/domob/android/ads/N$1/c Lcn/domob/android/ads/N;
  aload_0
  aload_2
  putfield cn/domob/android/ads/N$1/a Lcn/domob/android/ads/L;
  aload_0
  aload_3
  putfield cn/domob/android/ads/N$1/b Ljava/lang/String;
  aload_0
  invokespecial java/lang/Object/<init>()V
  return
  nop
.end <method>

.method public run()V
.limit locals 10
.limit stack 200
  nop
  aload_0
  getfield cn/domob/android/ads/N$1/a Lcn/domob/android/ads/L;
  astore_1
  new java/lang/NoClassDefFoundError
  dup
  invokespecial java/lang/NoClassDefFoundError/<init>()V
  athrow
  aload_2
  aload_0
  invokespecial cn/domob/android/ads/N$1$1/<init>(Lcn/domob/android/ads/N$1;)V
  aload_1
  aload_2
  invokevirtual cn/domob/android/ads/L/setWebViewClient(Landroid/webkit/WebViewClient;)V
  aload_0
  getfield cn/domob/android/ads/N$1/c Lcn/domob/android/ads/N;
  astore_3
  new java/lang/StringBuilder
  astore 4
  aload 4
  invokespecial java/lang/StringBuilder/<init>()V
  ldc "load URL time: "
  astore 5
  aload 4
  aload 5
  invokevirtual java/lang/StringBuilder/append(Ljava/lang/String;)Ljava/lang/StringBuilder;
  astore 4
  invokestatic java/lang/System/currentTimeMillis()J
  lstore 6
  aload 4
  lload 6
  invokevirtual java/lang/StringBuilder/append(J)Ljava/lang/StringBuilder;
  astore 4
  aload 4
  invokevirtual java/lang/StringBuilder/toString()Ljava/lang/String;
  astore 8
  aload_3
  aload 8
  invokestatic cn/domob/android/ads/J/d(Ljava/lang/Object;Ljava/lang/String;)V
  new cn/domob/android/ads/N$a
  astore 9
  aload_0
  getfield cn/domob/android/ads/N$1/c Lcn/domob/android/ads/N;
  astore_3
  aload 9
  aload_3
  invokespecial cn/domob/android/ads/N$a/<init>(Lcn/domob/android/ads/N;)V
  aload 9
  invokevirtual cn/domob/android/ads/N$a/start()V
  aload_0
  getfield cn/domob/android/ads/N$1/a Lcn/domob/android/ads/L;
  astore_1
  aload_0
  getfield cn/domob/android/ads/N$1/b Ljava/lang/String;
  astore 8
  aload_1
  aload 8
  invokevirtual cn/domob/android/ads/L/loadUrl(Ljava/lang/String;)V
  return
  nop
.end <method>

