.source SourceFile
.class  cn/domob/android/ads/j$h
.super java/lang/Object
.field final "a" Lcn/domob/android/ads/j;
.field private "b" Ljava/lang/String;
.field private "c" Ljava/lang/String;
.field private "d" F
.field private "e" Ljava/lang/String;
.field private "f" I
.field private "g" Z
.field private "h" F
.field private "i" Landroid/graphics/Rect;
.field private "j" Landroid/graphics/Typeface;
.field private "k" F
.field private "l" I
.field private "m" Ljava/lang/String;
.field private "n" Z
.field private "o" Ljava/lang/String;
.field private "p" Z
.field private "q" Z
.field private "r" F
.field private "s" Ljava/lang/String;
.field private "t" I
.field private "u" [B
.field private "v" Lcn/domob/android/ads/L;

.method protected <init>(Lcn/domob/android/ads/j;Lorg/json/JSONObject;)V
.limit locals 13
.limit stack 200
  nop
  aload_0
  aload_1
  putfield cn/domob/android/ads/j$h/a Lcn/domob/android/ads/j;
  aload_0
  invokespecial java/lang/Object/<init>()V
  iconst_0
  istore_3
  aload_0
  iload_3
  putfield cn/domob/android/ads/j$h/g Z
  ldc "f"
  astore 5
  aload_2
  aload 5
  invokevirtual org/json/JSONObject/optJSONArray(Ljava/lang/String;)Lorg/json/JSONArray;
  astore 4
  aload_0
  aload 4
  invokespecial cn/domob/android/ads/j$h/a(Lorg/json/JSONArray;)Landroid/graphics/Rect;
  astore 6
  aload_0
  aload 6
  putfield cn/domob/android/ads/j$h/i Landroid/graphics/Rect;
  ldc "t"
  astore 5
  aload_2
  aload 5
  invokevirtual org/json/JSONObject/optString(Ljava/lang/String;)Ljava/lang/String;
  astore 7
  aload_0
  aload 7
  putfield cn/domob/android/ads/j$h/b Ljava/lang/String;
  aload_0
  getfield cn/domob/android/ads/j$h/b Ljava/lang/String;
  astore 7
  new java/lang/NoClassDefFoundError
  dup
  invokespecial java/lang/NoClassDefFoundError/<init>()V
  athrow
  iload 7
  ifeq Label0
  getstatic cn/domob/android/ads/j$1/b [I
  astore 8
  aload_0
  getfield cn/domob/android/ads/j$h/b Ljava/lang/String;
  astore 7
  aload 7
  invokestatic cn/domob/android/ads/j$i/a(Ljava/lang/String;)Lcn/domob/android/ads/j$i;
  astore 9
  aload 9
  invokevirtual cn/domob/android/ads/j$i/ordinal()I
  istore 10
  aload 8
  iload 10
  iaload
  istore 10
  dload 10
  invokestatic app/DummyClass/invokeIfStmt(D)V
  iload 10
  lookupswitch
  1 : Label2
  2 : Label3
  3 : Label4
  4 : Label5
  default : Label1
Label1:
  goto Label6
Label6:
  new java/lang/Exception
  astore 11
  new java/lang/StringBuilder
  astore 12
  aload 12
  invokespecial java/lang/StringBuilder/<init>()V
  ldc "\u8d44\u6e90\u63cf\u8ff0\u7c7b\u578b\u6709\u8bef, viewType = "
  astore 5
  aload 12
  aload 5
  invokevirtual java/lang/StringBuilder/append(Ljava/lang/String;)Ljava/lang/StringBuilder;
  astore 12
  aload_0
  getfield cn/domob/android/ads/j$h/b Ljava/lang/String;
  astore 7
  aload 12
  aload 7
  invokevirtual java/lang/StringBuilder/append(Ljava/lang/String;)Ljava/lang/StringBuilder;
  astore 12
  aload 12
  invokevirtual java/lang/StringBuilder/toString()Ljava/lang/String;
  astore 7
  aload 11
  aload 7
  invokespecial java/lang/Exception/<init>(Ljava/lang/String;)V
  aload 11
  athrow
Label2:
  aload_0
  aload_2
  invokespecial cn/domob/android/ads/j$h/b(Lorg/json/JSONObject;)V
Label0:
  return
Label3:
  aload_0
  aload_2
  invokespecial cn/domob/android/ads/j$h/a(Lorg/json/JSONObject;)V
  goto Label0
Label4:
  aload_0
  aload_2
  invokespecial cn/domob/android/ads/j$h/c(Lorg/json/JSONObject;)V
  goto Label0
Label5:
  aload_0
  aload_2
  invokespecial cn/domob/android/ads/j$h/d(Lorg/json/JSONObject;)V
  goto Label0
  nop
  nop
  nop
.end <method>

.method private a(Lorg/json/JSONArray;)Landroid/graphics/Rect;
.limit locals 10
.limit stack 200
  nop
  iconst_0
  istore 4
  aload_1
  iload 4
  invokevirtual org/json/JSONArray/getDouble(I)D
  dstore_2
  dload_2
  d2i
  istore 5
  iconst_1
  istore 4
  aload_1
  iload 4
  invokevirtual org/json/JSONArray/getDouble(I)D
  dstore_2
  dload_2
  d2i
  istore 6
  iconst_2
  istore 4
  aload_1
  iload 4
  invokevirtual org/json/JSONArray/getDouble(I)D
  dstore_2
  dload_2
  d2i
  istore 7
  iload 7
  iload 5
  iadd
  istore 7
  iconst_3
  istore 4
  aload_1
  iload 4
  invokevirtual org/json/JSONArray/getDouble(I)D
  dstore_2
  dload_2
  d2i
  istore 8
  iload 8
  iload 6
  iadd
  istore 8
  new java/lang/NoClassDefFoundError
  dup
  invokespecial java/lang/NoClassDefFoundError/<init>()V
  athrow
  aload_0
  iload 5
  invokespecial cn/domob/android/ads/j$h/d(I)I
  istore 5
  aload_0
  iload 6
  invokespecial cn/domob/android/ads/j$h/d(I)I
  istore 6
  aload_0
  iload 7
  invokespecial cn/domob/android/ads/j$h/d(I)I
  istore 7
  aload_0
  iload 8
  invokespecial cn/domob/android/ads/j$h/d(I)I
  istore 8
  aload 9
  iload 5
  iload 6
  iload 7
  iload 8
  invokespecial android/graphics/Rect/<init>(IIII)V
  aload 9
  areturn
  nop
.end <method>

.method protected a()Ljava/lang/String;
.limit locals 2
.limit stack 200
  nop
  aload_0
  getfield cn/domob/android/ads/j$h/b Ljava/lang/String;
  astore_1
  aload_1
  areturn
  nop
.end <method>

.method protected a(I)V
.limit locals 2
.limit stack 200
  nop
  aload_0
  iload_1
  putfield cn/domob/android/ads/j$h/f I
  return
  nop
.end <method>

.method protected a(Lcn/domob/android/ads/L;)V
.limit locals 2
.limit stack 200
  nop
  aload_0
  aload_1
  putfield cn/domob/android/ads/j$h/v Lcn/domob/android/ads/L;
  return
  nop
.end <method>

.method private a(Lorg/json/JSONObject;)V
.limit locals 25
.limit stack 200
  nop
  ldc "fs"
  astore 6
  ldc2_w 14.000000000000000
  dstore 7
  aload_1
  astore_2
  aload_2
  aload 6
  dload 7
  invokevirtual org/json/JSONObject/optDouble(Ljava/lang/String;D)D
  dstore 4
  dload 4
  d2f
  fstore 9
  aload_0
  astore_2
  aload_2
  fload 9
  putfield cn/domob/android/ads/j$h/k F
  ldc "fc"
  astore 6
  aconst_null
  astore 11
  aload_1
  astore_2
  aload_2
  aload 6
  aload 11
  invokevirtual org/json/JSONObject/optString(Ljava/lang/String;Ljava/lang/String;)Ljava/lang/String;
  astore 10
  new java/lang/NoClassDefFoundError
  dup
  invokespecial java/lang/NoClassDefFoundError/<init>()V
  athrow
  iload 10
  ifeq Label0
  ldc ""
  astore 6
  aload 10
  aload 6
  invokevirtual java/lang/String/equals(Ljava/lang/Object;)Z
  istore 12
  iload 12
  invokestatic app/DummyClass/invokeIfStmt(Z)V
  iload 12
  ifne Label0
Label12:
  bipush 16
  istore 15
  aload 10
  iload 15
  invokestatic java/lang/Long/parseLong(Ljava/lang/String;I)J
  lstore 13
  lload 13
  l2i
  istore 16
  aload_0
  astore_2
  aload_2
  iload 16
  putfield cn/domob/android/ads/j$h/l I
Label0:
  ldc "dnv"
  astore 6
  iconst_1
  istore 15
  aload_1
  astore_2
  aload_2
  aload 6
  iload 15
  invokevirtual org/json/JSONObject/optBoolean(Ljava/lang/String;Z)Z
  istore 12
  aload_0
  astore_2
  aload_2
  iload 12
  putfield cn/domob/android/ads/j$h/q Z
  ldc "mfs"
  astore 6
  ldc2_w 12.000000000000000
  dstore 7
  aload_1
  astore_2
  aload_2
  aload 6
  dload 7
  invokevirtual org/json/JSONObject/optDouble(Ljava/lang/String;D)D
  dstore 4
  dload 4
  d2f
  fstore 9
  aload_0
  astore_2
  aload_2
  fload 9
  putfield cn/domob/android/ads/j$h/r F
  ldc "fa"
  astore 6
  aload_1
  astore_2
  aload_2
  aload 6
  invokevirtual org/json/JSONObject/optJSONArray(Ljava/lang/String;)Lorg/json/JSONArray;
  astore 17
  aload 17
  invokestatic app/DummyClass/invokeIfStmt(Ljava/lang/Object;)V
  aload 17
  ifnull Label1
  iconst_0
  istore 18
  iconst_0
  istore 19
Label10:
  aload 17
  invokevirtual org/json/JSONArray/length()I
  istore 16
  iload 18
  istore_2
  dload_2
  invokestatic app/DummyClass/invokeIfStmt(D)V
  dload 16
  invokestatic app/DummyClass/invokeIfStmt(D)V
  iload 18
  istore_2
  iload_2
  iload 16
  if_icmpge Label2
  iload 18
  istore_2
  aload 17
  iload_2
  invokevirtual org/json/JSONArray/getString(I)Ljava/lang/String;
  astore 20
  getstatic cn/domob/android/ads/j$1/c [I
  astore 21
  aload 20
  astore_2
  aload_2
  invokestatic cn/domob/android/ads/j$c/a(Ljava/lang/String;)Lcn/domob/android/ads/j$c;
  astore 22
  aload 22
  astore_2
  aload_2
  invokevirtual cn/domob/android/ads/j$c/ordinal()I
  istore 16
  aload 21
  iload 16
  iaload
  istore 16
  dload 16
  invokestatic app/DummyClass/invokeIfStmt(D)V
  iload 16
  lookupswitch
  1 : Label4
  2 : Label5
  3 : Label6
  4 : Label7
  5 : Label8
  default : Label3
Label3:
  goto Label9
Label9:
  iload 18
  iconst_1
  iadd
  istore 18
  goto Label10
Label11:
  astore 23
  aload 23
  astore_2
  aload_2
  invokestatic cn/domob/android/ads/J/a(Ljava/lang/Throwable;)V
  goto Label0
Label4:
  iconst_1
  istore 15
  iload 19
  istore_2
  iload_2
  iload 15
  ior
  istore_2
  iload_2
  istore 19
  goto Label9
Label5:
  iconst_2
  istore 15
  iload 19
  istore_2
  iload_2
  iload 15
  ior
  istore_2
  iload_2
  istore 19
  goto Label9
Label6:
  getstatic android/graphics/Typeface/MONOSPACE Landroid/graphics/Typeface;
  astore 24
  aload 24
  astore_2
  aload_0
  astore_3
  aload_3
  aload_2
  putfield cn/domob/android/ads/j$h/j Landroid/graphics/Typeface;
  goto Label9
Label7:
  getstatic android/graphics/Typeface/SERIF Landroid/graphics/Typeface;
  astore 24
  aload 24
  astore_2
  aload_0
  astore_3
  aload_3
  aload_2
  putfield cn/domob/android/ads/j$h/j Landroid/graphics/Typeface;
  goto Label9
Label8:
  getstatic android/graphics/Typeface/SANS_SERIF Landroid/graphics/Typeface;
  astore 24
  aload 24
  astore_2
  aload_0
  astore_3
  aload_3
  aload_2
  putfield cn/domob/android/ads/j$h/j Landroid/graphics/Typeface;
  goto Label9
Label2:
  aload_0
  astore_2
  aload_2
  getfield cn/domob/android/ads/j$h/j Landroid/graphics/Typeface;
  astore_2
  aload_2
  astore 24
  aload 24
  astore_2
  iload 19
  istore_3
  aload_2
  iload_3
  invokestatic android/graphics/Typeface/create(Landroid/graphics/Typeface;I)Landroid/graphics/Typeface;
  astore 24
  aload 24
  astore_2
  aload_0
  astore_3
  aload_3
  aload_2
  putfield cn/domob/android/ads/j$h/j Landroid/graphics/Typeface;
Label1:
  ldc "at"
  astore 6
  aconst_null
  astore 11
  aload_1
  astore_2
  aload_2
  aload 6
  aload 11
  invokevirtual org/json/JSONObject/optString(Ljava/lang/String;Ljava/lang/String;)Ljava/lang/String;
  astore 20
  aload 20
  astore_2
  aload_0
  astore_3
  aload_3
  aload_2
  putfield cn/domob/android/ads/j$h/s Ljava/lang/String;
  ldc "x"
  astore 6
  aload_1
  astore_2
  aload_2
  aload 6
  invokevirtual org/json/JSONObject/optJSONArray(Ljava/lang/String;)Lorg/json/JSONArray;
  astore 17
  iconst_0
  istore 15
  aload 17
  iload 15
  invokevirtual org/json/JSONArray/getString(I)Ljava/lang/String;
  astore 20
  aload 20
  astore_2
  aload_0
  astore_3
  aload_3
  aload_2
  putfield cn/domob/android/ads/j$h/m Ljava/lang/String;
  return
  nop
  nop
  nop
.end <method>

.method protected a(Z)V
.limit locals 2
.limit stack 200
  nop
  aload_0
  iload_1
  putfield cn/domob/android/ads/j$h/g Z
  return
  nop
.end <method>

.method protected a([B)V
.limit locals 2
.limit stack 200
  nop
  aload_0
  aload_1
  putfield cn/domob/android/ads/j$h/u [B
  return
  nop
.end <method>

.method protected b()Ljava/lang/String;
.limit locals 2
.limit stack 200
  nop
  aload_0
  getfield cn/domob/android/ads/j$h/c Ljava/lang/String;
  astore_1
  aload_1
  areturn
  nop
.end <method>

.method protected b(I)V
.limit locals 2
.limit stack 200
  nop
  aload_0
  iload_1
  putfield cn/domob/android/ads/j$h/l I
  return
  nop
.end <method>

.method private b(Lorg/json/JSONObject;)V
.limit locals 7
.limit stack 200
  nop
  ldc "$"
  astore_3
  aconst_null
  astore 4
  aload_1
  aload_3
  aload 4
  invokevirtual org/json/JSONObject/optString(Ljava/lang/String;Ljava/lang/String;)Ljava/lang/String;
  astore_2
  aload_0
  aload_2
  putfield cn/domob/android/ads/j$h/c Ljava/lang/String;
  ldc "b"
  astore_3
  iconst_0
  istore 6
  aload_1
  aload_3
  iload 6
  invokevirtual org/json/JSONObject/optBoolean(Ljava/lang/String;Z)Z
  istore 5
  aload_0
  iload 5
  putfield cn/domob/android/ads/j$h/n Z
  ldc "def"
  astore_3
  aconst_null
  astore 4
  aload_1
  aload_3
  aload 4
  invokevirtual org/json/JSONObject/optString(Ljava/lang/String;Ljava/lang/String;)Ljava/lang/String;
  astore_2
  aload_0
  aload_2
  putfield cn/domob/android/ads/j$h/o Ljava/lang/String;
  return
  nop
.end <method>

.method protected c()F
.limit locals 2
.limit stack 200
  nop
  aload_0
  getfield cn/domob/android/ads/j$h/d F
  fstore_1
  fload_1
  freturn
  nop
.end <method>

.method protected c(I)V
.limit locals 2
.limit stack 200
  nop
  aload_0
  iload_1
  putfield cn/domob/android/ads/j$h/t I
  return
  nop
.end <method>

.method private c(Lorg/json/JSONObject;)V
.limit locals 10
.limit stack 200
  nop
  ldc "ia"
  astore 4
  ldc2_w 1.000000000000000
  dstore 5
  aload_1
  aload 4
  dload 5
  invokevirtual org/json/JSONObject/optDouble(Ljava/lang/String;D)D
  dstore_2
  dload_2
  d2f
  fstore 7
  aload_0
  fload 7
  putfield cn/domob/android/ads/j$h/d F
  ldc "epy"
  astore 4
  ldc2_w 1.000000000000000
  dstore 5
  aload_1
  aload 4
  dload 5
  invokevirtual org/json/JSONObject/optDouble(Ljava/lang/String;D)D
  dstore_2
  dload_2
  d2f
  fstore 7
  aload_0
  fload 7
  putfield cn/domob/android/ads/j$h/h F
  ldc "bc"
  astore 4
  aconst_null
  astore 9
  aload_1
  aload 4
  aload 9
  invokevirtual org/json/JSONObject/optString(Ljava/lang/String;Ljava/lang/String;)Ljava/lang/String;
  astore 8
  aload_0
  aload 8
  putfield cn/domob/android/ads/j$h/e Ljava/lang/String;
  return
  nop
.end <method>

.method private d(I)I
.limit locals 7
.limit stack 200
  nop
  iload_1
  i2f
  fstore_2
  invokestatic cn/domob/android/ads/p/a()Lcn/domob/android/ads/p;
  astore_3
  aload_0
  getfield cn/domob/android/ads/j$h/a Lcn/domob/android/ads/j;
  astore 4
  aload 4
  invokestatic cn/domob/android/ads/j/a(Lcn/domob/android/ads/j;)Landroid/content/Context;
  astore 5
  aload_3
  aload 5
  invokevirtual cn/domob/android/ads/p/k(Landroid/content/Context;)F
  fstore 6
  fload_2
  fload 6
  fmul
  fstore 6
  fload 6
  f2i
  istore_1
  iload_1
  ireturn
  nop
.end <method>

.method protected d()Ljava/lang/String;
.limit locals 2
.limit stack 200
  nop
  aload_0
  getfield cn/domob/android/ads/j$h/e Ljava/lang/String;
  astore_1
  aload_1
  areturn
  nop
.end <method>

.method private d(Lorg/json/JSONObject;)V
.limit locals 5
.limit stack 200
  nop
  ldc "$"
  astore_3
  aconst_null
  astore 4
  aload_1
  aload_3
  aload 4
  invokevirtual org/json/JSONObject/optString(Ljava/lang/String;Ljava/lang/String;)Ljava/lang/String;
  astore_2
  aload_0
  aload_2
  putfield cn/domob/android/ads/j$h/c Ljava/lang/String;
  return
  nop
.end <method>

.method protected e()I
.limit locals 2
.limit stack 200
  nop
  aload_0
  getfield cn/domob/android/ads/j$h/f I
  istore_1
  iload_1
  ireturn
  nop
.end <method>

.method protected f()Z
.limit locals 2
.limit stack 200
  nop
  aload_0
  getfield cn/domob/android/ads/j$h/g Z
  istore_1
  iload_1
  ireturn
  nop
.end <method>

.method protected g()F
.limit locals 2
.limit stack 200
  nop
  aload_0
  getfield cn/domob/android/ads/j$h/h F
  fstore_1
  fload_1
  freturn
  nop
.end <method>

.method protected h()Landroid/graphics/Rect;
.limit locals 2
.limit stack 200
  nop
  aload_0
  getfield cn/domob/android/ads/j$h/i Landroid/graphics/Rect;
  astore_1
  aload_1
  areturn
  nop
.end <method>

.method protected i()Landroid/graphics/Typeface;
.limit locals 2
.limit stack 200
  nop
  aload_0
  getfield cn/domob/android/ads/j$h/j Landroid/graphics/Typeface;
  astore_1
  aload_1
  areturn
  nop
.end <method>

.method protected j()F
.limit locals 2
.limit stack 200
  nop
  aload_0
  getfield cn/domob/android/ads/j$h/k F
  fstore_1
  fload_1
  freturn
  nop
.end <method>

.method protected k()I
.limit locals 2
.limit stack 200
  nop
  aload_0
  getfield cn/domob/android/ads/j$h/l I
  istore_1
  iload_1
  ireturn
  nop
.end <method>

.method protected l()Ljava/lang/String;
.limit locals 2
.limit stack 200
  nop
  aload_0
  getfield cn/domob/android/ads/j$h/m Ljava/lang/String;
  astore_1
  aload_1
  areturn
  nop
.end <method>

.method protected m()Ljava/lang/String;
.limit locals 2
.limit stack 200
  nop
  aload_0
  getfield cn/domob/android/ads/j$h/o Ljava/lang/String;
  astore_1
  aload_1
  areturn
  nop
.end <method>

.method protected n()Z
.limit locals 2
.limit stack 200
  nop
  aload_0
  getfield cn/domob/android/ads/j$h/n Z
  istore_1
  iload_1
  ireturn
  nop
.end <method>

.method protected o()Z
.limit locals 2
.limit stack 200
  nop
  aload_0
  getfield cn/domob/android/ads/j$h/p Z
  istore_1
  iload_1
  ireturn
  nop
.end <method>

.method protected p()Z
.limit locals 2
.limit stack 200
  nop
  aload_0
  getfield cn/domob/android/ads/j$h/q Z
  istore_1
  iload_1
  ireturn
  nop
.end <method>

.method protected q()F
.limit locals 2
.limit stack 200
  nop
  aload_0
  getfield cn/domob/android/ads/j$h/r F
  fstore_1
  fload_1
  freturn
  nop
.end <method>

.method protected r()Ljava/lang/String;
.limit locals 2
.limit stack 200
  nop
  aload_0
  getfield cn/domob/android/ads/j$h/s Ljava/lang/String;
  astore_1
  aload_1
  areturn
  nop
.end <method>

.method protected s()[B
.limit locals 2
.limit stack 200
  nop
  aload_0
  getfield cn/domob/android/ads/j$h/u [B
  astore_1
  aload_1
  areturn
  nop
.end <method>

.method protected t()I
.limit locals 2
.limit stack 200
  nop
  aload_0
  getfield cn/domob/android/ads/j$h/t I
  istore_1
  iload_1
  ireturn
  nop
.end <method>

.method public toString()Ljava/lang/String;
.limit locals 10
.limit stack 200
  nop
  new java/lang/StringBuilder
  astore_1
  aload_1
  invokespecial java/lang/StringBuilder/<init>()V
  ldc "ViewDiscription [viewType="
  astore_3
  aload_1
  aload_3
  invokevirtual java/lang/StringBuilder/append(Ljava/lang/String;)Ljava/lang/StringBuilder;
  astore_2
  aload_0
  getfield cn/domob/android/ads/j$h/b Ljava/lang/String;
  astore 4
  aload_2
  aload 4
  invokevirtual java/lang/StringBuilder/append(Ljava/lang/String;)Ljava/lang/StringBuilder;
  astore_2
  ldc ", tagName="
  astore_3
  aload_2
  aload_3
  invokevirtual java/lang/StringBuilder/append(Ljava/lang/String;)Ljava/lang/StringBuilder;
  astore_2
  aload_0
  getfield cn/domob/android/ads/j$h/c Ljava/lang/String;
  astore 4
  aload_2
  aload 4
  invokevirtual java/lang/StringBuilder/append(Ljava/lang/String;)Ljava/lang/StringBuilder;
  astore_2
  ldc ", alphaFactor="
  astore_3
  aload_2
  aload_3
  invokevirtual java/lang/StringBuilder/append(Ljava/lang/String;)Ljava/lang/StringBuilder;
  astore_2
  aload_0
  getfield cn/domob/android/ads/j$h/d F
  fstore 5
  aload_2
  fload 5
  invokevirtual java/lang/StringBuilder/append(F)Ljava/lang/StringBuilder;
  astore_2
  ldc ", backgroundColorStr="
  astore_3
  aload_2
  aload_3
  invokevirtual java/lang/StringBuilder/append(Ljava/lang/String;)Ljava/lang/StringBuilder;
  astore_2
  aload_0
  getfield cn/domob/android/ads/j$h/e Ljava/lang/String;
  astore 4
  aload_2
  aload 4
  invokevirtual java/lang/StringBuilder/append(Ljava/lang/String;)Ljava/lang/StringBuilder;
  astore_2
  ldc ", epy="
  astore_3
  aload_2
  aload_3
  invokevirtual java/lang/StringBuilder/append(Ljava/lang/String;)Ljava/lang/StringBuilder;
  astore_2
  aload_0
  getfield cn/domob/android/ads/j$h/h F
  fstore 5
  aload_2
  fload 5
  invokevirtual java/lang/StringBuilder/append(F)Ljava/lang/StringBuilder;
  astore_2
  ldc ", viewArea="
  astore_3
  aload_2
  aload_3
  invokevirtual java/lang/StringBuilder/append(Ljava/lang/String;)Ljava/lang/StringBuilder;
  astore_2
  aload_0
  getfield cn/domob/android/ads/j$h/i Landroid/graphics/Rect;
  astore 6
  new java/lang/NoClassDefFoundError
  dup
  invokespecial java/lang/NoClassDefFoundError/<init>()V
  athrow
  nop
  aload_2
  aload 4
  invokevirtual java/lang/StringBuilder/append(Ljava/lang/String;)Ljava/lang/StringBuilder;
  astore_2
  ldc ", typeface="
  astore_3
  aload_2
  aload_3
  invokevirtual java/lang/StringBuilder/append(Ljava/lang/String;)Ljava/lang/StringBuilder;
  astore_2
  aload_0
  getfield cn/domob/android/ads/j$h/j Landroid/graphics/Typeface;
  astore 7
  aload_2
  aload 7
  invokevirtual java/lang/StringBuilder/append(Ljava/lang/Object;)Ljava/lang/StringBuilder;
  astore_2
  ldc ", fontSize="
  astore_3
  aload_2
  aload_3
  invokevirtual java/lang/StringBuilder/append(Ljava/lang/String;)Ljava/lang/StringBuilder;
  astore_2
  aload_0
  getfield cn/domob/android/ads/j$h/k F
  fstore 5
  aload_2
  fload 5
  invokevirtual java/lang/StringBuilder/append(F)Ljava/lang/StringBuilder;
  astore_2
  ldc ", fontColor="
  astore_3
  aload_2
  aload_3
  invokevirtual java/lang/StringBuilder/append(Ljava/lang/String;)Ljava/lang/StringBuilder;
  astore_2
  aload_0
  getfield cn/domob/android/ads/j$h/l I
  istore 8
  aload_2
  iload 8
  invokevirtual java/lang/StringBuilder/append(I)Ljava/lang/StringBuilder;
  astore_2
  ldc ", textContent="
  astore_3
  aload_2
  aload_3
  invokevirtual java/lang/StringBuilder/append(Ljava/lang/String;)Ljava/lang/StringBuilder;
  astore_2
  aload_0
  getfield cn/domob/android/ads/j$h/m Ljava/lang/String;
  astore 4
  aload_2
  aload 4
  invokevirtual java/lang/StringBuilder/append(Ljava/lang/String;)Ljava/lang/StringBuilder;
  astore_2
  ldc ", roundRect="
  astore_3
  aload_2
  aload_3
  invokevirtual java/lang/StringBuilder/append(Ljava/lang/String;)Ljava/lang/StringBuilder;
  astore_2
  aload_0
  getfield cn/domob/android/ads/j$h/n Z
  istore 9
  aload_2
  iload 9
  invokevirtual java/lang/StringBuilder/append(Z)Ljava/lang/StringBuilder;
  astore_2
  ldc ", clickAnimation="
  astore_3
  aload_2
  aload_3
  invokevirtual java/lang/StringBuilder/append(Ljava/lang/String;)Ljava/lang/StringBuilder;
  astore_2
  aload_0
  getfield cn/domob/android/ads/j$h/p Z
  istore 9
  aload_2
  iload 9
  invokevirtual java/lang/StringBuilder/append(Z)Ljava/lang/StringBuilder;
  astore_2
  ldc ", dynamicSizeEnable="
  astore_3
  aload_2
  aload_3
  invokevirtual java/lang/StringBuilder/append(Ljava/lang/String;)Ljava/lang/StringBuilder;
  astore_2
  aload_0
  getfield cn/domob/android/ads/j$h/q Z
  istore 9
  aload_2
  iload 9
  invokevirtual java/lang/StringBuilder/append(Z)Ljava/lang/StringBuilder;
  astore_2
  ldc ", minFontSize="
  astore_3
  aload_2
  aload_3
  invokevirtual java/lang/StringBuilder/append(Ljava/lang/String;)Ljava/lang/StringBuilder;
  astore_2
  aload_0
  getfield cn/domob/android/ads/j$h/r F
  fstore 5
  aload_2
  fload 5
  invokevirtual java/lang/StringBuilder/append(F)Ljava/lang/StringBuilder;
  astore_2
  ldc ", animationType="
  astore_3
  aload_2
  aload_3
  invokevirtual java/lang/StringBuilder/append(Ljava/lang/String;)Ljava/lang/StringBuilder;
  astore_2
  aload_0
  getfield cn/domob/android/ads/j$h/s Ljava/lang/String;
  astore 4
  aload_2
  aload 4
  invokevirtual java/lang/StringBuilder/append(Ljava/lang/String;)Ljava/lang/StringBuilder;
  astore_2
  ldc "]"
  astore_3
  aload_2
  aload_3
  invokevirtual java/lang/StringBuilder/append(Ljava/lang/String;)Ljava/lang/StringBuilder;
  pop
  aload_1
  invokevirtual java/lang/StringBuilder/toString()Ljava/lang/String;
  astore 4
  aload 4
  areturn
  nop
.end <method>

.method protected u()Lcn/domob/android/ads/L;
.limit locals 2
.limit stack 200
  nop
  aload_0
  getfield cn/domob/android/ads/j$h/v Lcn/domob/android/ads/L;
  astore_1
  aload_1
  areturn
  nop
.end <method>

