.source SourceFile
.class final  cn/domob/android/ads/I$6
.super java/lang/Object
.implements  cn/domob/android/a/c
.field final "a" Landroid/content/Context;
.field final "b" Ljava/lang/String;
.field final "c" Ljava/lang/String;

.method <init>(Landroid/content/Context;Ljava/lang/String;Ljava/lang/String;)V
.limit locals 4
.limit stack 200
  nop
  aload_0
  aload_1
  putfield cn/domob/android/ads/I$6/a Landroid/content/Context;
  aload_0
  aload_2
  putfield cn/domob/android/ads/I$6/b Ljava/lang/String;
  aload_0
  aload_3
  putfield cn/domob/android/ads/I$6/c Ljava/lang/String;
  aload_0
  invokespecial java/lang/Object/<init>()V
  return
  nop
.end <method>

.method public a()V
.limit locals 5
.limit stack 200
  nop
  aload_0
  getfield cn/domob/android/ads/I$6/a Landroid/content/Context;
  astore_1
  aload_0
  getfield cn/domob/android/ads/I$6/b Ljava/lang/String;
  astore_2
  aload_0
  getfield cn/domob/android/ads/I$6/c Ljava/lang/String;
  astore_3
  ldc "download_start"
  astore 4
  aload 4
  aload_1
  aload_2
  aload_3
  invokestatic cn/domob/android/ads/I/a(Ljava/lang/String;Landroid/content/Context;Ljava/lang/String;Ljava/lang/String;)V
  return
  nop
.end <method>

.method public a(ILjava/lang/String;)V
.limit locals 7
.limit stack 200
  nop
  aload_0
  getfield cn/domob/android/ads/I$6/a Landroid/content/Context;
  astore_3
  aload_0
  getfield cn/domob/android/ads/I$6/b Ljava/lang/String;
  astore 4
  aload_0
  getfield cn/domob/android/ads/I$6/c Ljava/lang/String;
  astore 5
  ldc "download_failed"
  astore 6
  aload 6
  aload_3
  aload 4
  aload 5
  invokestatic cn/domob/android/ads/I/a(Ljava/lang/String;Landroid/content/Context;Ljava/lang/String;Ljava/lang/String;)V
  return
  nop
.end <method>

.method public a(Ljava/lang/String;)V
.limit locals 6
.limit stack 200
  nop
  aload_0
  getfield cn/domob/android/ads/I$6/a Landroid/content/Context;
  astore_2
  aload_0
  getfield cn/domob/android/ads/I$6/b Ljava/lang/String;
  astore_3
  aload_0
  getfield cn/domob/android/ads/I$6/c Ljava/lang/String;
  astore 4
  ldc "download_finish"
  astore 5
  aload 5
  aload_2
  aload_3
  aload 4
  invokestatic cn/domob/android/ads/I/a(Ljava/lang/String;Landroid/content/Context;Ljava/lang/String;Ljava/lang/String;)V
  return
  nop
.end <method>

.method public b()V
.limit locals 5
.limit stack 200
  nop
  aload_0
  getfield cn/domob/android/ads/I$6/a Landroid/content/Context;
  astore_1
  aload_0
  getfield cn/domob/android/ads/I$6/b Ljava/lang/String;
  astore_2
  aload_0
  getfield cn/domob/android/ads/I$6/c Ljava/lang/String;
  astore_3
  ldc "download_cancel"
  astore 4
  aload 4
  aload_1
  aload_2
  aload_3
  invokestatic cn/domob/android/ads/I/a(Ljava/lang/String;Landroid/content/Context;Ljava/lang/String;Ljava/lang/String;)V
  return
  nop
.end <method>

.method public b(Ljava/lang/String;)V
.limit locals 11
.limit stack 200
  nop
  aload_0
  getfield cn/domob/android/ads/I$6/a Landroid/content/Context;
  astore_2
  new java/lang/NoClassDefFoundError
  dup
  invokespecial java/lang/NoClassDefFoundError/<init>()V
  athrow
  iload_2
  ifeq Label0
  new android/content/Intent
  astore_3
  aload_0
  getfield cn/domob/android/ads/I$6/a Landroid/content/Context;
  astore_2
  ldc cn/domob/android/ads/DomobActivity
  astore 4
  aload_3
  aload_2
  aload 4
  invokespecial android/content/Intent/<init>(Landroid/content/Context;Ljava/lang/Class;)V
  ldc "DomobActivityType"
  astore 5
  iconst_3
  istore 6
  aload_3
  aload 5
  iload 6
  invokevirtual android/content/Intent/putExtra(Ljava/lang/String;I)Landroid/content/Intent;
  pop
  ldc "msg"
  astore 5
  ldc "\u4e0b\u8f7d\u6587\u4ef6MD5\u4e0d\u5339\u914d\uff01"
  astore 7
  aload_3
  aload 5
  aload 7
  invokevirtual android/content/Intent/putExtra(Ljava/lang/String;Ljava/lang/String;)Landroid/content/Intent;
  pop
  aload_0
  getfield cn/domob/android/ads/I$6/a Landroid/content/Context;
  astore_2
  aload_2
  aload_3
  invokevirtual android/content/Context/startActivity(Landroid/content/Intent;)V
  ldc cn/domob/android/ads/I
  astore 8
  aload 8
  invokevirtual java/lang/Class/getSimpleName()Ljava/lang/String;
  astore 9
  ldc "\u4e0b\u8f7d\u6587\u4ef6MD5\u4e0d\u5339\u914d"
  astore 5
  aload 9
  aload 5
  invokestatic cn/domob/android/ads/J/b(Ljava/lang/Object;Ljava/lang/String;)V
  aload_0
  getfield cn/domob/android/ads/I$6/a Landroid/content/Context;
  astore_2
  aload_0
  getfield cn/domob/android/ads/I$6/b Ljava/lang/String;
  astore 10
  aload_0
  getfield cn/domob/android/ads/I$6/c Ljava/lang/String;
  astore_1
  ldc "download_md5_failed"
  astore 5
  aload 5
  aload_2
  aload 10
  aload_1
  invokestatic cn/domob/android/ads/I/a(Ljava/lang/String;Landroid/content/Context;Ljava/lang/String;Ljava/lang/String;)V
Label0:
  return
  nop
.end <method>

