.source SourceFile
.class public final enum  cn/domob/android/ads/b/d$b
.super java/lang/Enum
  .signature_attr "Ljava/lang/Enum<Lcn/domob/android/ads/b/d$b;>;"
.field public static final enum "a" Lcn/domob/android/ads/b/d$b;
.field public static final enum "b" Lcn/domob/android/ads/b/d$b;
.field public static final enum "c" Lcn/domob/android/ads/b/d$b;
.field private static final "e" [Lcn/domob/android/ads/b/d$b;
.field final "d" I

.method static <clinit>()V
.limit locals 5
.limit stack 200
  nop
  new cn/domob/android/ads/b/d$b
  astore_0
  ldc "WAIT_FINISH"
  astore_1
  iconst_0
  istore_2
  iconst_0
  istore_3
  aload_0
  aload_1
  iload_2
  iload_3
  invokespecial cn/domob/android/ads/b/d$b/<init>(Ljava/lang/String;II)V
  aload_0
  putstatic cn/domob/android/ads/b/d$b/a Lcn/domob/android/ads/b/d$b;
  new cn/domob/android/ads/b/d$b
  astore_0
  ldc "SYNC_DECODER"
  astore_1
  iconst_1
  istore_2
  iconst_1
  istore_3
  aload_0
  aload_1
  iload_2
  iload_3
  invokespecial cn/domob/android/ads/b/d$b/<init>(Ljava/lang/String;II)V
  aload_0
  putstatic cn/domob/android/ads/b/d$b/b Lcn/domob/android/ads/b/d$b;
  new cn/domob/android/ads/b/d$b
  astore_0
  ldc "COVER"
  astore_1
  iconst_2
  istore_2
  iconst_2
  istore_3
  aload_0
  aload_1
  iload_2
  iload_3
  invokespecial cn/domob/android/ads/b/d$b/<init>(Ljava/lang/String;II)V
  aload_0
  putstatic cn/domob/android/ads/b/d$b/c Lcn/domob/android/ads/b/d$b;
  iconst_3
  istore_2
  iload_2
  anewarray cn/domob/android/ads/b/d$b
  astore 4
  getstatic cn/domob/android/ads/b/d$b/a Lcn/domob/android/ads/b/d$b;
  astore_0
  iconst_0
  istore_2
  aload 4
  iload_2
  aload_0
  aastore
  getstatic cn/domob/android/ads/b/d$b/b Lcn/domob/android/ads/b/d$b;
  astore_0
  iconst_1
  istore_2
  aload 4
  iload_2
  aload_0
  aastore
  getstatic cn/domob/android/ads/b/d$b/c Lcn/domob/android/ads/b/d$b;
  astore_0
  iconst_2
  istore_2
  aload 4
  iload_2
  aload_0
  aastore
  aload 4
  putstatic cn/domob/android/ads/b/d$b/e [Lcn/domob/android/ads/b/d$b;
  return
  nop
.end <method>

.method private <init>(Ljava/lang/String;II)V
  .signature_attr "(I)V"
.limit locals 4
.limit stack 200
  nop
  aload_0
  aload_1
  iload_2
  invokespecial java/lang/Enum/<init>(Ljava/lang/String;I)V
  aload_0
  iload_3
  putfield cn/domob/android/ads/b/d$b/d I
  return
  nop
.end <method>

.method public static valueOf(Ljava/lang/String;)Lcn/domob/android/ads/b/d$b;
.limit locals 5
.limit stack 200
  nop
  ldc cn/domob/android/ads/b/d$b
  astore_2
  aload_2
  aload_0
  invokestatic java/lang/Enum/valueOf(Ljava/lang/Class;Ljava/lang/String;)Ljava/lang/Enum;
  astore_1
  aload_1
  astore 4
  aload 4
  checkcast cn/domob/android/ads/b/d$b
  astore 4
  aload 4
  astore_3
  aload_3
  areturn
  nop
.end <method>

.method public static values()[Lcn/domob/android/ads/b/d$b;
.limit locals 3
.limit stack 200
  nop
  getstatic cn/domob/android/ads/b/d$b/e [Lcn/domob/android/ads/b/d$b;
  astore_0
  aload_0
  invokevirtual java/lang/Object/clone()Ljava/lang/Object;
  astore_1
  aload_1
  astore_2
  aload_2
  checkcast [Lcn/domob/android/ads/b/d$b;
  astore_2
  aload_2
  astore_0
  aload_0
  areturn
  nop
.end <method>

