.source SourceFile
.class  cn/domob/android/ads/o
.super java/lang/Object
.field private "a" Landroid/content/Context;
.field private "b" Ljava/lang/String;
.field private "c" Ljava/lang/String;
.field private "d" I
.field private "e" Z
.field private "f" J
.field private "g" J
.field private "h" Ljava/lang/String;
.field private "i" Z

.method protected <init>(Landroid/content/Context;)V
.limit locals 5
.limit stack 200
  nop
  aload_0
  invokespecial java/lang/Object/<init>()V
  iconst_0
  istore_2
  aload_0
  iload_2
  putfield cn/domob/android/ads/o/e Z
  iconst_1
  istore_2
  aload_0
  iload_2
  putfield cn/domob/android/ads/o/i Z
  aload_0
  aload_1
  putfield cn/domob/android/ads/o/a Landroid/content/Context;
  ldc2_w 0
  lstore_3
  aload_0
  lload_3
  putfield cn/domob/android/ads/o/g J
  return
  nop
.end <method>

.method protected a()I
.limit locals 2
.limit stack 200
  nop
  aload_0
  getfield cn/domob/android/ads/o/d I
  istore_1
  iload_1
  ireturn
  nop
.end <method>

.method protected a(Ljava/lang/String;)J
.limit locals 10
.limit stack 200
  nop
  new java/lang/NoClassDefFoundError
  dup
  invokespecial java/lang/NoClassDefFoundError/<init>()V
  athrow
  iload_1
  ifne Label0
  ldc2_w 4294967295
  lstore_2
  lload_2
  lreturn
Label0:
  new java/text/SimpleDateFormat
  astore 4
  ldc "yyyy-mm-dd:hh:mm:ss"
  astore 5
  aload 4
  aload 5
  invokespecial java/text/SimpleDateFormat/<init>(Ljava/lang/String;)V
Label2:
  aload 4
  aload_1
  invokevirtual java/text/SimpleDateFormat/parse(Ljava/lang/String;)Ljava/util/Date;
  astore 6
  aload 6
  invokevirtual java/util/Date/getTime()J
  lstore 7
Label3:
  lload 7
  lreturn
Label1:
  astore 9
  aload 9
  invokestatic cn/domob/android/ads/J/a(Ljava/lang/Throwable;)V
  ldc2_w 4294967295
  lstore_2
  lload_2
  lreturn
  nop
.end <method>

.method protected static a(Landroid/content/Context;Lorg/json/JSONObject;)Lcn/domob/android/ads/o;
.limit locals 5
.limit stack 200
  nop
  new cn/domob/android/ads/o
  astore_2
  aload_2
  aload_0
  invokespecial cn/domob/android/ads/o/<init>(Landroid/content/Context;)V
  aload_2
  aload_1
  invokevirtual cn/domob/android/ads/o/a(Lorg/json/JSONObject;)Z
  istore_3
  new java/lang/NoClassDefFoundError
  dup
  invokespecial java/lang/NoClassDefFoundError/<init>()V
  athrow
  iload_3
  ifeq Label0
  aload_2
  areturn
Label0:
  aconst_null
  astore 4
  aload 4
  areturn
  nop
.end <method>

.method protected a(J)Ljava/lang/String;
.limit locals 12
.limit stack 200
  nop
  ldc2_w 4294967295
  lstore 4
  lload_1
  lload 4
  lcmp
  istore_3
  new java/lang/NoClassDefFoundError
  dup
  invokespecial java/lang/NoClassDefFoundError/<init>()V
  athrow
  iload_3
  ifne Label0
  aconst_null
  astore 6
  aload 6
  areturn
Label0:
  new java/text/SimpleDateFormat
  astore 7
  ldc "yyyy-mm-dd:hh:mm:ss"
  astore 8
  aload 7
  aload 8
  invokespecial java/text/SimpleDateFormat/<init>(Ljava/lang/String;)V
  new java/util/Date
  astore 9
Label2:
  aload 9
  lload_1
  invokespecial java/util/Date/<init>(J)V
  aload 7
  aload 9
  invokevirtual java/text/SimpleDateFormat/format(Ljava/util/Date;)Ljava/lang/String;
  astore 10
Label3:
  aload 10
  areturn
Label1:
  astore 11
  aload 11
  invokestatic cn/domob/android/ads/J/a(Ljava/lang/Throwable;)V
  aconst_null
  astore 6
  aload 6
  areturn
  nop
.end <method>

.method private a(Landroid/content/SharedPreferences;Ljava/lang/StringBuilder;)Z
.limit locals 12
.limit stack 200
  .catch  java/lang/Exception <from> Label3 <to> Label4 <using> Label2
  nop
  iconst_0
  istore_3
Label3:
  new java/lang/NoSuchMethodError
  dup
  invokespecial java/lang/NoSuchMethodError/<init>()V
  athrow
  nop
  ldc "info_md5"
  astore 6
  aconst_null
  astore 7
  aload_1
  aload 6
  aload 7
  invokeinterface android/content/SharedPreferences/getString(Ljava/lang/String;Ljava/lang/String;)Ljava/lang/String; 3
  astore 5
  aload_2
  invokevirtual java/lang/StringBuilder/toString()Ljava/lang/String;
  astore 8
  aload 8
  invokestatic cn/domob/android/ads/J/c(Ljava/lang/String;)Ljava/lang/String;
  astore 8
  aload 5
  invokestatic app/DummyClass/invokeIfStmt(Ljava/lang/Object;)V
  aload 5
  ifnull Label0
  aload 8
  invokestatic app/DummyClass/invokeIfStmt(Ljava/lang/Object;)V
  aload 8
  ifnull Label1
  aload 8
  aload 5
  invokevirtual java/lang/String/equals(Ljava/lang/Object;)Z
  istore 9
  iload 9
  invokestatic app/DummyClass/invokeIfStmt(Z)V
  iload 9
  ifne Label1
Label0:
  ldc "info_md5"
  astore 6
  aload 4
  aload 6
  aload 8
  invokeinterface android/content/SharedPreferences$Editor/putString(Ljava/lang/String;Ljava/lang/String;)Landroid/content/SharedPreferences$Editor; 3
  pop
  aload 4
  invokeinterface android/content/SharedPreferences$Editor/commit()Z 1
  pop
Label4:
  iconst_1
  istore_3
Label1:
  iload_3
  ireturn
Label2:
  astore 10
  iconst_0
  istore 11
  iload 11
  ireturn
  nop
.end <method>

.method private a(Lcn/domob/android/ads/d;Ljava/lang/String;)Z
.limit locals 10
.limit stack 200
  nop
  iconst_1
  istore_3
  new java/lang/NoClassDefFoundError
  dup
  invokespecial java/lang/NoClassDefFoundError/<init>()V
  athrow
  aload_1
  aload 4
  aload_2
  invokevirtual cn/domob/android/ads/d/a(Landroid/net/Uri;Ljava/lang/String;)Landroid/database/Cursor;
  astore 5
  aload 5
  invokestatic app/DummyClass/invokeIfStmt(Ljava/lang/Object;)V
  aload 5
  ifnull Label0
  aload 5
  invokeinterface android/database/Cursor/getCount()I 1
  istore 6
  dload 6
  invokestatic app/DummyClass/invokeIfStmt(D)V
  iload 6
  ifle Label0
  aload 5
  invokeinterface android/database/Cursor/moveToFirst()Z 1
  pop
  ldc "_name"
  astore 7
  aload 5
  aload 7
  invokeinterface android/database/Cursor/getColumnIndexOrThrow(Ljava/lang/String;)I 2
  istore 6
  new java/lang/StringBuilder
  astore 8
  aload 8
  invokespecial java/lang/StringBuilder/<init>()V
  ldc "_name=\""
  astore 7
  aload 8
  aload 7
  invokevirtual java/lang/StringBuilder/append(Ljava/lang/String;)Ljava/lang/StringBuilder;
  astore 8
  aload 5
  iload 6
  invokeinterface android/database/Cursor/getString(I)Ljava/lang/String; 2
  astore_2
  aload 8
  aload_2
  invokevirtual java/lang/StringBuilder/append(Ljava/lang/String;)Ljava/lang/StringBuilder;
  astore 8
  ldc "\""
  astore 7
  aload 8
  aload 7
  invokevirtual java/lang/StringBuilder/append(Ljava/lang/String;)Ljava/lang/StringBuilder;
  astore 8
  aload 8
  invokevirtual java/lang/StringBuilder/toString()Ljava/lang/String;
  astore_2
  getstatic cn/domob/android/ads/d/g Landroid/net/Uri;
  astore 4
  aconst_null
  astore 9
  aload_1
  aload 4
  aload_2
  aload 9
  invokevirtual cn/domob/android/ads/d/a(Landroid/net/Uri;Ljava/lang/String;[Ljava/lang/String;)I
  pop
  iconst_0
  istore_3
Label0:
  aload 5
  invokestatic app/DummyClass/invokeIfStmt(Ljava/lang/Object;)V
  aload 5
  ifnull Label1
  aload 5
  invokeinterface android/database/Cursor/close()V 1
Label1:
  iload_3
  ireturn
  nop
.end <method>

.method protected a(Lorg/json/JSONObject;)Z
.limit locals 42
.limit stack 200
  nop
  ldc "detection"
  astore 6
  aload_1
  astore_2
  aload_2
  aload 6
  invokevirtual org/json/JSONObject/optBoolean(Ljava/lang/String;)Z
  istore 5
  new java/lang/NoClassDefFoundError
  dup
  invokespecial java/lang/NoClassDefFoundError/<init>()V
  athrow
  iload 5
  ifne Label0
  ldc "DomobSDK"
  astore 6
  ldc "invalide detector response"
  astore 7
  aload 6
  aload 7
  invokestatic android/util/Log/e(Ljava/lang/String;Ljava/lang/String;)I
  pop
  iconst_0
  istore 8
  iload 8
  ireturn
Label0:
  ldc "lm[config]"
  astore 6
  aconst_null
  astore 10
  aload_1
  astore_2
  aload_2
  aload 6
  aload 10
  invokevirtual org/json/JSONObject/optString(Ljava/lang/String;Ljava/lang/String;)Ljava/lang/String;
  astore 9
  aload_0
  astore_2
  aload_2
  aload 9
  putfield cn/domob/android/ads/o/c Ljava/lang/String;
  aload_0
  astore_2
  aload_2
  getfield cn/domob/android/ads/o/c Ljava/lang/String;
  astore 9
  aload 9
  invokestatic app/DummyClass/invokeIfStmt(Ljava/lang/Object;)V
  aload 9
  ifnull Label1
  new java/lang/StringBuilder
  astore 11
  aload 11
  invokespecial java/lang/StringBuilder/<init>()V
  ldc "lm[config]:"
  astore 6
  aload 11
  aload 6
  invokevirtual java/lang/StringBuilder/append(Ljava/lang/String;)Ljava/lang/StringBuilder;
  astore 11
  aload_0
  astore_2
  aload_2
  getfield cn/domob/android/ads/o/c Ljava/lang/String;
  astore 9
  aload 11
  aload 9
  invokevirtual java/lang/StringBuilder/append(Ljava/lang/String;)Ljava/lang/StringBuilder;
  astore 11
  aload 11
  invokevirtual java/lang/StringBuilder/toString()Ljava/lang/String;
  astore 9
  aload_0
  astore_2
  aload_2
  aload 9
  invokestatic cn/domob/android/ads/J/d(Ljava/lang/Object;Ljava/lang/String;)V
Label1:
  ldc "lm[res]"
  astore 6
  aconst_null
  astore 10
  aload_1
  astore_2
  aload_2
  aload 6
  aload 10
  invokevirtual org/json/JSONObject/optString(Ljava/lang/String;Ljava/lang/String;)Ljava/lang/String;
  astore 9
  aload_0
  astore_2
  aload_2
  aload 9
  putfield cn/domob/android/ads/o/b Ljava/lang/String;
  aload_0
  astore_2
  aload_2
  getfield cn/domob/android/ads/o/b Ljava/lang/String;
  astore 9
  aload 9
  invokestatic app/DummyClass/invokeIfStmt(Ljava/lang/Object;)V
  aload 9
  ifnull Label2
  new java/lang/StringBuilder
  astore 11
  aload 11
  invokespecial java/lang/StringBuilder/<init>()V
  ldc "lm[res]:"
  astore 6
  aload 11
  aload 6
  invokevirtual java/lang/StringBuilder/append(Ljava/lang/String;)Ljava/lang/StringBuilder;
  astore 11
  aload_0
  astore_2
  aload_2
  getfield cn/domob/android/ads/o/b Ljava/lang/String;
  astore 9
  aload 11
  aload 9
  invokevirtual java/lang/StringBuilder/append(Ljava/lang/String;)Ljava/lang/StringBuilder;
  astore 11
  aload 11
  invokevirtual java/lang/StringBuilder/toString()Ljava/lang/String;
  astore 9
  aload_0
  astore_2
  aload_2
  aload 9
  invokestatic cn/domob/android/ads/J/d(Ljava/lang/Object;Ljava/lang/String;)V
Label2:
  ldc "refresh_interval"
  astore 6
  iconst_m1
  istore 8
  aload_1
  astore_2
  aload_2
  aload 6
  iload 8
  invokevirtual org/json/JSONObject/optInt(Ljava/lang/String;I)I
  istore 12
  aload_0
  astore_2
  aload_2
  iload 12
  putfield cn/domob/android/ads/o/d I
  new java/lang/StringBuilder
  astore 11
  aload 11
  invokespecial java/lang/StringBuilder/<init>()V
  ldc "Request interval:"
  astore 6
  aload 11
  aload 6
  invokevirtual java/lang/StringBuilder/append(Ljava/lang/String;)Ljava/lang/StringBuilder;
  astore 11
  aload_0
  astore_2
  aload_2
  getfield cn/domob/android/ads/o/d I
  istore 12
  aload 11
  iload 12
  invokevirtual java/lang/StringBuilder/append(I)Ljava/lang/StringBuilder;
  astore 11
  aload 11
  invokevirtual java/lang/StringBuilder/toString()Ljava/lang/String;
  astore 9
  aload_0
  astore_2
  aload_2
  aload 9
  invokestatic cn/domob/android/ads/J/d(Ljava/lang/Object;Ljava/lang/String;)V
  ldc "disabled"
  astore 6
  iconst_0
  istore 8
  aload_1
  astore_2
  aload_2
  aload 6
  iload 8
  invokevirtual org/json/JSONObject/optBoolean(Ljava/lang/String;Z)Z
  istore 5
  aload_0
  astore_2
  aload_2
  iload 5
  putfield cn/domob/android/ads/o/e Z
  new java/lang/StringBuilder
  astore 11
  aload 11
  invokespecial java/lang/StringBuilder/<init>()V
  ldc "AD disabled:"
  astore 6
  aload 11
  aload 6
  invokevirtual java/lang/StringBuilder/append(Ljava/lang/String;)Ljava/lang/StringBuilder;
  astore 11
  aload_0
  astore_2
  aload_2
  getfield cn/domob/android/ads/o/e Z
  istore 5
  aload 11
  iload 5
  invokevirtual java/lang/StringBuilder/append(Z)Ljava/lang/StringBuilder;
  astore 11
  aload 11
  invokevirtual java/lang/StringBuilder/toString()Ljava/lang/String;
  astore 9
  aload_0
  astore_2
  aload_2
  aload 9
  invokestatic cn/domob/android/ads/J/d(Ljava/lang/Object;Ljava/lang/String;)V
  ldc "dis_time"
  astore 6
  ldc2_w 0
  lstore 15
  aload_1
  astore_2
  aload_2
  aload 6
  lload 15
  invokevirtual org/json/JSONObject/optLong(Ljava/lang/String;J)J
  lstore 13
  aload_0
  astore_2
  aload_2
  lload 13
  putfield cn/domob/android/ads/o/f J
  new java/lang/StringBuilder
  astore 11
  aload 11
  invokespecial java/lang/StringBuilder/<init>()V
  ldc "AD disabled time:"
  astore 6
  aload 11
  aload 6
  invokevirtual java/lang/StringBuilder/append(Ljava/lang/String;)Ljava/lang/StringBuilder;
  astore 11
  aload_0
  astore_2
  aload_2
  getfield cn/domob/android/ads/o/f J
  lstore 13
  aload 11
  lload 13
  invokevirtual java/lang/StringBuilder/append(J)Ljava/lang/StringBuilder;
  astore 11
  aload 11
  invokevirtual java/lang/StringBuilder/toString()Ljava/lang/String;
  astore 9
  aload_0
  astore_2
  aload_2
  aload 9
  invokestatic cn/domob/android/ads/J/d(Ljava/lang/Object;Ljava/lang/String;)V
  ldc "allow_tm"
  astore 6
  iconst_1
  istore 8
  aload_1
  astore_2
  aload_2
  aload 6
  iload 8
  invokevirtual org/json/JSONObject/optBoolean(Ljava/lang/String;Z)Z
  istore 5
  aload_0
  astore_2
  aload_2
  iload 5
  putfield cn/domob/android/ads/o/i Z
  new java/lang/StringBuilder
  astore 11
  aload 11
  invokespecial java/lang/StringBuilder/<init>()V
  ldc "Allow test mode:"
  astore 6
  aload 11
  aload 6
  invokevirtual java/lang/StringBuilder/append(Ljava/lang/String;)Ljava/lang/StringBuilder;
  astore 11
  aload_0
  astore_2
  aload_2
  getfield cn/domob/android/ads/o/i Z
  istore 5
  aload 11
  iload 5
  invokevirtual java/lang/StringBuilder/append(Z)Ljava/lang/StringBuilder;
  astore 11
  aload 11
  invokevirtual java/lang/StringBuilder/toString()Ljava/lang/String;
  astore 9
  aload_0
  astore_2
  aload_2
  aload 9
  invokestatic cn/domob/android/ads/J/d(Ljava/lang/Object;Ljava/lang/String;)V
  ldc "cid"
  astore 6
  aconst_null
  astore 10
  aload_1
  astore_2
  aload_2
  aload 6
  aload 10
  invokevirtual org/json/JSONObject/optString(Ljava/lang/String;Ljava/lang/String;)Ljava/lang/String;
  astore 9
  aload_0
  astore_2
  aload_2
  aload 9
  putfield cn/domob/android/ads/o/h Ljava/lang/String;
  aload_0
  astore_2
  aload_2
  getfield cn/domob/android/ads/o/h Ljava/lang/String;
  astore 9
  aload 9
  invokestatic app/DummyClass/invokeIfStmt(Ljava/lang/Object;)V
  aload 9
  ifnull Label3
  new java/lang/StringBuilder
  astore 11
  aload 11
  invokespecial java/lang/StringBuilder/<init>()V
  ldc "CID:"
  astore 6
  aload 11
  aload 6
  invokevirtual java/lang/StringBuilder/append(Ljava/lang/String;)Ljava/lang/StringBuilder;
  astore 11
  aload_0
  astore_2
  aload_2
  getfield cn/domob/android/ads/o/h Ljava/lang/String;
  astore 9
  aload 11
  aload 9
  invokevirtual java/lang/StringBuilder/append(Ljava/lang/String;)Ljava/lang/StringBuilder;
  astore 11
  aload 11
  invokevirtual java/lang/StringBuilder/toString()Ljava/lang/String;
  astore 9
  aload_0
  astore_2
  aload_2
  aload 9
  invokestatic cn/domob/android/ads/J/d(Ljava/lang/Object;Ljava/lang/String;)V
Label3:
  ldc "markup"
  astore 6
  aload_1
  astore_2
  aload_2
  aload 6
  invokevirtual org/json/JSONObject/optJSONObject(Ljava/lang/String;)Lorg/json/JSONObject;
  astore 17
  aload 17
  invokestatic app/DummyClass/invokeIfStmt(Ljava/lang/Object;)V
  aload 17
  ifnull Label4
Label11:
  ldc "$"
  astore 6
  aload 17
  aload 6
  invokevirtual org/json/JSONObject/optJSONObject(Ljava/lang/String;)Lorg/json/JSONObject;
  astore 17
  aload 17
  invokestatic app/DummyClass/invokeIfStmt(Ljava/lang/Object;)V
  aload 17
  ifnull Label4
  aload_0
  astore_2
  aload_2
  getfield cn/domob/android/ads/o/a Landroid/content/Context;
  astore_2
  aload_2
  astore 18
  aload 18
  astore_2
  aload_2
  invokestatic cn/domob/android/ads/d/a(Landroid/content/Context;)Lcn/domob/android/ads/d;
  astore 19
  aload 17
  invokevirtual org/json/JSONObject/keys()Ljava/util/Iterator;
  astore 20
Label8:
  aload 20
  astore_2
  aload_2
  invokeinterface java/util/Iterator/hasNext()Z 1
  istore 5
Label12:
  iload 5
  invokestatic app/DummyClass/invokeIfStmt(Z)V
  iload 5
  ifne Label5
Label4:
  aload_0
  astore_2
  aload_2
  invokespecial cn/domob/android/ads/o/e()V
  aload_0
  astore_2
  aload_2
  getfield cn/domob/android/ads/o/a Landroid/content/Context;
  astore_2
  aload_2
  astore 18
  ldc "domob_update_info"
  astore 6
  iconst_0
  istore 8
  aload 18
  astore_2
  aload_2
  aload 6
  iload 8
  invokevirtual android/content/Context/getSharedPreferences(Ljava/lang/String;I)Landroid/content/SharedPreferences;
  astore 21
  aload 21
  monitorenter
Label14:
  aload 21
  astore_2
  aload_2
  invokeinterface android/content/SharedPreferences/edit()Landroid/content/SharedPreferences$Editor; 1
  astore 22
  invokestatic cn/domob/android/ads/h/a()Lcn/domob/android/ads/h;
  astore 23
  aload_0
  astore_2
  aload_2
  getfield cn/domob/android/ads/o/a Landroid/content/Context;
  astore_2
  aload_2
  astore 18
  aload 23
  astore_2
  aload 18
  astore_3
  aload_2
  aload_3
  invokevirtual cn/domob/android/ads/h/a(Landroid/content/Context;)Ljava/lang/String;
  astore 24
  ldc "ipb"
  astore 6
  aload 22
  astore_2
  aload 24
  astore_3
  aload_2
  aload 6
  aload_3
  invokeinterface android/content/SharedPreferences$Editor/putString(Ljava/lang/String;Ljava/lang/String;)Landroid/content/SharedPreferences$Editor; 3
  pop
  aload 22
  astore_2
  aload_2
  invokeinterface android/content/SharedPreferences$Editor/commit()Z 1
  pop
  ldc "pb[update]"
  astore 6
  aload_1
  astore_2
  aload_2
  aload 6
  invokevirtual org/json/JSONObject/optJSONObject(Ljava/lang/String;)Lorg/json/JSONObject;
  astore 17
  aload 17
  invokestatic app/DummyClass/invokeIfStmt(Ljava/lang/Object;)V
  aload 17
  ifnull Label6
  ldc "n"
  astore 6
  aconst_null
  astore 10
  aload 17
  aload 6
  aload 10
  invokevirtual org/json/JSONObject/optString(Ljava/lang/String;Ljava/lang/String;)Ljava/lang/String;
  astore 9
  ldc "nt"
  astore 6
  iconst_0
  istore 8
  aload 17
  aload 6
  iload 8
  invokevirtual org/json/JSONObject/optInt(Ljava/lang/String;I)I
  istore 12
  ldc "vc"
  astore 6
  aconst_null
  astore 10
  aload 17
  aload 6
  aload 10
  invokevirtual org/json/JSONObject/optString(Ljava/lang/String;Ljava/lang/String;)Ljava/lang/String;
  astore 25
  ldc "vn"
  astore 6
  aconst_null
  astore 10
  aload 17
  aload 6
  aload 10
  invokevirtual org/json/JSONObject/optString(Ljava/lang/String;Ljava/lang/String;)Ljava/lang/String;
  astore 26
  ldc "u"
  astore 6
  aconst_null
  astore 10
  aload 17
  aload 6
  aload 10
  invokevirtual org/json/JSONObject/optString(Ljava/lang/String;Ljava/lang/String;)Ljava/lang/String;
  astore 27
  ldc "s"
  astore 6
  aconst_null
  astore 10
  aload 17
  aload 6
  aload 10
  invokevirtual org/json/JSONObject/optString(Ljava/lang/String;Ljava/lang/String;)Ljava/lang/String;
  astore 28
  ldc "md5"
  astore 6
  ldc ""
  astore 7
  aload 17
  aload 6
  aload 7
  invokevirtual org/json/JSONObject/optString(Ljava/lang/String;Ljava/lang/String;)Ljava/lang/String;
  astore 29
  ldc "ul"
  astore 6
  aconst_null
  astore 10
  aload 17
  aload 6
  aload 10
  invokevirtual org/json/JSONObject/optString(Ljava/lang/String;Ljava/lang/String;)Ljava/lang/String;
  astore 24
  ldc "f"
  astore 6
  iconst_0
  istore 8
  aload 17
  aload 6
  iload 8
  invokevirtual org/json/JSONObject/optBoolean(Ljava/lang/String;Z)Z
  istore 30
  ldc "sk"
  astore 6
  iconst_0
  istore 8
  aload 17
  aload 6
  iload 8
  invokevirtual org/json/JSONObject/optBoolean(Ljava/lang/String;Z)Z
  istore 5
  ldc "nrt"
  astore 6
  iconst_0
  istore 8
  aload 17
  aload 6
  iload 8
  invokevirtual org/json/JSONObject/optInt(Ljava/lang/String;I)I
  istore 31
  ldc "nri"
  astore 6
  iconst_3
  istore 8
  aload 17
  aload 6
  iload 8
  invokevirtual org/json/JSONObject/optInt(Ljava/lang/String;I)I
  istore 32
  aload 9
  invokestatic app/DummyClass/invokeIfStmt(Ljava/lang/Object;)V
  aload 9
  ifnull Label6
  aload 25
  astore_2
  aload_2
  invokestatic app/DummyClass/invokeIfStmt(Ljava/lang/Object;)V
  aload 25
  ifnull Label6
  aload 26
  astore_2
  aload_2
  invokestatic app/DummyClass/invokeIfStmt(Ljava/lang/Object;)V
  aload 26
  ifnull Label6
  aload 27
  astore_2
  aload_2
  invokestatic app/DummyClass/invokeIfStmt(Ljava/lang/Object;)V
  aload 27
  ifnull Label6
  aload 28
  astore_2
  aload_2
  invokestatic app/DummyClass/invokeIfStmt(Ljava/lang/Object;)V
  aload 28
  ifnull Label6
  aload 24
  astore_2
  aload_2
  invokestatic app/DummyClass/invokeIfStmt(Ljava/lang/Object;)V
  aload 24
  ifnull Label6
  ldc "^(\\d)+$"
  astore 6
  aload 6
  invokestatic java/util/regex/Pattern/compile(Ljava/lang/String;)Ljava/util/regex/Pattern;
  astore 33
  aload 33
  astore_2
  aload 25
  astore_3
  aload_2
  aload_3
  invokevirtual java/util/regex/Pattern/matcher(Ljava/lang/CharSequence;)Ljava/util/regex/Matcher;
  astore 34
  aload 34
  astore_2
  aload_2
  invokevirtual java/util/regex/Matcher/find()Z
  istore 35
  iload 35
  istore_2
  iload_2
  invokestatic app/DummyClass/invokeIfStmt(Z)V
  iload 35
  ifne Label7
  new java/lang/StringBuilder
  astore 11
  aload 11
  invokespecial java/lang/StringBuilder/<init>()V
  ldc "version code\u5728\u5339\u914d\u6b63\u5219\u8868\u8fbe\u5f0f\u65f6\u5931\u8d25\uff0c\u4e0d\u7b26\u5408version code\u89c4\u5219\uff0cversion code\u4e3a\uff1a"
  astore 6
  aload 11
  aload 6
  invokevirtual java/lang/StringBuilder/append(Ljava/lang/String;)Ljava/lang/StringBuilder;
  astore 11
  aload 25
  astore_2
  aload 11
  aload_2
  invokevirtual java/lang/StringBuilder/append(Ljava/lang/String;)Ljava/lang/StringBuilder;
  astore 11
  aload 11
  invokevirtual java/lang/StringBuilder/toString()Ljava/lang/String;
  astore 36
  aload_0
  astore_2
  aload 36
  astore_3
  aload_2
  aload_3
  invokestatic cn/domob/android/ads/J/b(Ljava/lang/Object;Ljava/lang/String;)V
  aload 21
  monitorexit
  iconst_1
  istore 8
  iload 8
  ireturn
Label13:
  astore 37
  aload 21
  monitorexit
Label15:
  aload 37
  athrow
Label5:
  aload 20
  astore_2
  aload_2
  invokeinterface java/util/Iterator/next()Ljava/lang/Object; 1
  astore 38
  aload 38
  astore 39
  aload 39
  checkcast java/lang/String
  astore 39
  aload 39
  astore 36
  aload 36
  astore_2
  aload 17
  aload_2
  invokevirtual org/json/JSONObject/getJSONObject(Ljava/lang/String;)Lorg/json/JSONObject;
  astore 40
  ldc "u"
  astore 6
  aload 40
  astore_2
  aload_2
  aload 6
  invokevirtual org/json/JSONObject/getString(Ljava/lang/String;)Ljava/lang/String;
  astore 29
  aload 36
  astore_2
  aload_2
  invokestatic app/DummyClass/invokeIfStmt(Ljava/lang/Object;)V
  aload 36
  ifnull Label8
  aload 29
  astore_2
  aload_2
  invokestatic app/DummyClass/invokeIfStmt(Ljava/lang/Object;)V
  aload 29
  ifnull Label8
  bipush 47
  istore 8
  aload 29
  astore_2
  aload_2
  iload 8
  invokevirtual java/lang/String/lastIndexOf(I)I
  istore 32
  iload 32
  istore_2
  dload_2
  invokestatic app/DummyClass/invokeIfStmt(D)V
  iload 32
  ifle Label8
  iload 32
  iconst_1
  iadd
  istore 31
  aload 29
  astore_2
  aload_2
  invokevirtual java/lang/String/length()I
  istore 12
  iload 31
  istore_2
  dload_2
  invokestatic app/DummyClass/invokeIfStmt(D)V
  dload 12
  invokestatic app/DummyClass/invokeIfStmt(D)V
  iload 31
  istore_2
  iload_2
  iload 12
  if_icmpge Label8
  iload 32
  iconst_1
  iadd
  istore 32
  aload 29
  astore_2
  iload 32
  istore_3
  aload_2
  iload_3
  invokevirtual java/lang/String/substring(I)Ljava/lang/String;
  astore 36
  aload_0
  astore_2
  aload 19
  astore_3
  aload 36
  astore 4
  aload_2
  aload_3
  aload 4
  invokespecial cn/domob/android/ads/o/a(Lcn/domob/android/ads/d;Ljava/lang/String;)Z
  istore 35
  iload 35
  istore_2
  iload_2
  invokestatic app/DummyClass/invokeIfStmt(Z)V
  iload 35
  ifne Label8
  new java/lang/StringBuilder
  astore 11
  aload 11
  invokespecial java/lang/StringBuilder/<init>()V
  aload 36
  astore_2
  aload 11
  aload_2
  invokevirtual java/lang/StringBuilder/append(Ljava/lang/String;)Ljava/lang/StringBuilder;
  astore 11
  ldc ":old version existed, delete it."
  astore 6
  aload 11
  aload 6
  invokevirtual java/lang/StringBuilder/append(Ljava/lang/String;)Ljava/lang/StringBuilder;
  astore 11
  aload 11
  invokevirtual java/lang/StringBuilder/toString()Ljava/lang/String;
  astore 36
  aload_0
  astore_2
  aload 36
  astore_3
  aload_2
  aload_3
  invokestatic cn/domob/android/ads/J/d(Ljava/lang/Object;Ljava/lang/String;)V
Label16:
  goto Label8
Label10:
  astore 41
  aload 41
  astore_2
  aload_2
  invokestatic cn/domob/android/ads/J/a(Ljava/lang/Throwable;)V
  iconst_0
  istore 8
  iload 8
  ireturn
Label7:
  new java/lang/StringBuilder
  astore 11
  aload 11
  invokespecial java/lang/StringBuilder/<init>()V
  aload 11
  aload 9
  invokevirtual java/lang/StringBuilder/append(Ljava/lang/String;)Ljava/lang/StringBuilder;
  astore 11
  aload 11
  iload 12
  invokevirtual java/lang/StringBuilder/append(I)Ljava/lang/StringBuilder;
  astore 11
  aload 25
  astore_2
  aload 11
  aload_2
  invokevirtual java/lang/StringBuilder/append(Ljava/lang/String;)Ljava/lang/StringBuilder;
  astore 11
  aload 26
  astore_2
  aload 11
  aload_2
  invokevirtual java/lang/StringBuilder/append(Ljava/lang/String;)Ljava/lang/StringBuilder;
  astore 11
  aload 27
  astore_2
  aload 11
  aload_2
  invokevirtual java/lang/StringBuilder/append(Ljava/lang/String;)Ljava/lang/StringBuilder;
  astore 11
  aload 28
  astore_2
  aload 11
  aload_2
  invokevirtual java/lang/StringBuilder/append(Ljava/lang/String;)Ljava/lang/StringBuilder;
  astore 11
  aload 29
  astore_2
  aload 11
  aload_2
  invokevirtual java/lang/StringBuilder/append(Ljava/lang/String;)Ljava/lang/StringBuilder;
  astore 11
  aload 24
  astore_2
  aload 11
  aload_2
  invokevirtual java/lang/StringBuilder/append(Ljava/lang/String;)Ljava/lang/StringBuilder;
  astore 11
  iload 30
  istore_2
  aload 11
  iload_2
  invokevirtual java/lang/StringBuilder/append(Z)Ljava/lang/StringBuilder;
  astore 11
  aload 11
  iload 5
  invokevirtual java/lang/StringBuilder/append(Z)Ljava/lang/StringBuilder;
  astore 11
  iload 31
  istore_2
  aload 11
  iload_2
  invokevirtual java/lang/StringBuilder/append(I)Ljava/lang/StringBuilder;
  astore 11
  iload 32
  istore_2
  aload 11
  iload_2
  invokevirtual java/lang/StringBuilder/append(I)Ljava/lang/StringBuilder;
  astore 11
  aload_0
  astore_2
  aload 21
  astore_3
  aload_2
  aload_3
  aload 11
  invokespecial cn/domob/android/ads/o/a(Landroid/content/SharedPreferences;Ljava/lang/StringBuilder;)Z
  istore 35
  iload 35
  istore_2
  iload_2
  invokestatic app/DummyClass/invokeIfStmt(Z)V
  iload 35
  ifeq Label9
  ldc "\u66f4\u65b0\u672c\u5730\u66f4\u65b0\u4fe1\u606f"
  astore 6
  aload_0
  astore_2
  aload_2
  aload 6
  invokestatic cn/domob/android/ads/J/d(Ljava/lang/Object;Ljava/lang/String;)V
  ldc "n"
  astore 6
  aload 22
  astore_2
  aload_2
  aload 6
  aload 9
  invokeinterface android/content/SharedPreferences$Editor/putString(Ljava/lang/String;Ljava/lang/String;)Landroid/content/SharedPreferences$Editor; 3
  pop
  ldc "nt"
  astore 6
  aload 22
  astore_2
  aload_2
  aload 6
  iload 12
  invokeinterface android/content/SharedPreferences$Editor/putInt(Ljava/lang/String;I)Landroid/content/SharedPreferences$Editor; 3
  pop
  ldc "vc"
  astore 6
  aload 22
  astore_2
  aload 25
  astore_3
  aload_2
  aload 6
  aload_3
  invokeinterface android/content/SharedPreferences$Editor/putString(Ljava/lang/String;Ljava/lang/String;)Landroid/content/SharedPreferences$Editor; 3
  pop
  ldc "vn"
  astore 6
  aload 22
  astore_2
  aload 26
  astore_3
  aload_2
  aload 6
  aload_3
  invokeinterface android/content/SharedPreferences$Editor/putString(Ljava/lang/String;Ljava/lang/String;)Landroid/content/SharedPreferences$Editor; 3
  pop
  ldc "u"
  astore 6
  aload 22
  astore_2
  aload 27
  astore_3
  aload_2
  aload 6
  aload_3
  invokeinterface android/content/SharedPreferences$Editor/putString(Ljava/lang/String;Ljava/lang/String;)Landroid/content/SharedPreferences$Editor; 3
  pop
  ldc "s"
  astore 6
  aload 22
  astore_2
  aload 28
  astore_3
  aload_2
  aload 6
  aload_3
  invokeinterface android/content/SharedPreferences$Editor/putString(Ljava/lang/String;Ljava/lang/String;)Landroid/content/SharedPreferences$Editor; 3
  pop
  ldc "md5"
  astore 6
  aload 22
  astore_2
  aload 29
  astore_3
  aload_2
  aload 6
  aload_3
  invokeinterface android/content/SharedPreferences$Editor/putString(Ljava/lang/String;Ljava/lang/String;)Landroid/content/SharedPreferences$Editor; 3
  pop
  ldc "ul"
  astore 6
  aload 22
  astore_2
  aload 24
  astore_3
  aload_2
  aload 6
  aload_3
  invokeinterface android/content/SharedPreferences$Editor/putString(Ljava/lang/String;Ljava/lang/String;)Landroid/content/SharedPreferences$Editor; 3
  pop
  ldc "f"
  astore 6
  aload 22
  astore_2
  iload 30
  istore_3
  aload_2
  aload 6
  iload_3
  invokeinterface android/content/SharedPreferences$Editor/putBoolean(Ljava/lang/String;Z)Landroid/content/SharedPreferences$Editor; 3
  pop
  ldc "sk"
  astore 6
  aload 22
  astore_2
  aload_2
  aload 6
  iload 5
  invokeinterface android/content/SharedPreferences$Editor/putBoolean(Ljava/lang/String;Z)Landroid/content/SharedPreferences$Editor; 3
  pop
  ldc "nrt"
  astore 6
  aload 22
  astore_2
  iload 31
  istore_3
  aload_2
  aload 6
  iload_3
  invokeinterface android/content/SharedPreferences$Editor/putInt(Ljava/lang/String;I)Landroid/content/SharedPreferences$Editor; 3
  pop
  ldc "nri"
  astore 6
  aload 22
  astore_2
  iload 32
  istore_3
  aload_2
  aload 6
  iload_3
  invokeinterface android/content/SharedPreferences$Editor/putInt(Ljava/lang/String;I)Landroid/content/SharedPreferences$Editor; 3
  pop
  invokestatic java/lang/System/currentTimeMillis()J
  lstore 13
  ldc "next_time"
  astore 6
  aload 22
  astore_2
  aload_2
  aload 6
  lload 13
  invokeinterface android/content/SharedPreferences$Editor/putLong(Ljava/lang/String;J)Landroid/content/SharedPreferences$Editor; 4
  pop
  aload 22
  astore_2
  aload_2
  invokeinterface android/content/SharedPreferences$Editor/commit()Z 1
  pop
Label6:
  aload 21
  monitorexit
  iconst_1
  istore 8
  iload 8
  ireturn
Label9:
  ldc "\u4e0d\u9700\u8981\u9700\u8981\u66f4\u65b0\u672c\u5730\u66f4\u65b0\u4fe1\u606f"
  astore 6
  aload_0
  astore_2
  aload_2
  aload 6
  invokestatic cn/domob/android/ads/J/d(Ljava/lang/Object;Ljava/lang/String;)V
Label17:
  goto Label6
  nop
.end <method>

.method protected b()Z
.limit locals 2
.limit stack 200
  nop
  aload_0
  getfield cn/domob/android/ads/o/e Z
  istore_1
  iload_1
  ireturn
  nop
.end <method>

.method protected c()J
.limit locals 3
.limit stack 200
  nop
  aload_0
  getfield cn/domob/android/ads/o/f J
  lstore_1
  lload_1
  lreturn
  nop
.end <method>

.method protected d()J
.limit locals 3
.limit stack 200
  nop
  aload_0
  getfield cn/domob/android/ads/o/g J
  lstore_1
  lload_1
  lreturn
  nop
.end <method>

.method private e()V
.limit locals 16
.limit stack 200
  nop
  ldc "Update config to DB"
  astore_1
  aload_0
  aload_1
  invokestatic cn/domob/android/ads/J/a(Ljava/lang/Object;Ljava/lang/String;)V
  aload_0
  getfield cn/domob/android/ads/o/a Landroid/content/Context;
  astore_2
  new java/lang/NoClassDefFoundError
  dup
  invokespecial java/lang/NoClassDefFoundError/<init>()V
  athrow
  nop
  new android/content/ContentValues
  astore 4
  aload 4
  invokespecial android/content/ContentValues/<init>()V
  aload_0
  getfield cn/domob/android/ads/o/c Ljava/lang/String;
  astore 5
  aload 5
  invokestatic app/DummyClass/invokeIfStmt(Ljava/lang/Object;)V
  aload 5
  ifnull Label0
  aload_0
  getfield cn/domob/android/ads/o/c Ljava/lang/String;
  astore 5
  ldc "_conf_ver"
  astore_1
  aload 4
  aload_1
  aload 5
  invokevirtual android/content/ContentValues/put(Ljava/lang/String;Ljava/lang/String;)V
Label0:
  aload_0
  getfield cn/domob/android/ads/o/b Ljava/lang/String;
  astore 6
  aload 6
  invokestatic app/DummyClass/invokeIfStmt(Ljava/lang/Object;)V
  aload 6
  ifnull Label1
  aload_0
  getfield cn/domob/android/ads/o/b Ljava/lang/String;
  astore 5
  ldc "_res_ver"
  astore_1
  aload 4
  aload_1
  aload 5
  invokevirtual android/content/ContentValues/put(Ljava/lang/String;Ljava/lang/String;)V
Label1:
  aload_0
  getfield cn/domob/android/ads/o/d I
  istore 7
  dload 7
  invokestatic app/DummyClass/invokeIfStmt(D)V
  iconst_m1
  istore 8
  iload 7
  iload 8
  if_icmpeq Label2
  aload_0
  getfield cn/domob/android/ads/o/d I
  istore 7
  iload 7
  invokestatic java/lang/Integer/valueOf(I)Ljava/lang/Integer;
  astore 9
  ldc "_interval"
  astore_1
  aload 4
  aload_1
  aload 9
  invokevirtual android/content/ContentValues/put(Ljava/lang/String;Ljava/lang/Integer;)V
Label2:
  aload_0
  getfield cn/domob/android/ads/o/e Z
  istore 10
  iload 10
  invokestatic java/lang/Boolean/valueOf(Z)Ljava/lang/Boolean;
  astore 11
  ldc "_dis_flag"
  astore_1
  aload 4
  aload_1
  aload 11
  invokevirtual android/content/ContentValues/put(Ljava/lang/String;Ljava/lang/Boolean;)V
  aload_0
  getfield cn/domob/android/ads/o/f J
  lstore 12
  lload 12
  invokestatic java/lang/Long/valueOf(J)Ljava/lang/Long;
  astore 14
  ldc "_dis_time"
  astore_1
  aload 4
  aload_1
  aload 14
  invokevirtual android/content/ContentValues/put(Ljava/lang/String;Ljava/lang/Long;)V
  aload_0
  getfield cn/domob/android/ads/o/e Z
  istore 10
  iload 10
  invokestatic app/DummyClass/invokeIfStmt(Z)V
  iload 10
  ifeq Label3
  invokestatic java/lang/System/currentTimeMillis()J
  lstore 12
  aload_0
  lload 12
  putfield cn/domob/android/ads/o/g J
  aload_0
  getfield cn/domob/android/ads/o/g J
  lstore 12
  lload 12
  invokestatic java/lang/Long/valueOf(J)Ljava/lang/Long;
  astore 14
  ldc "_dis_timestamp"
  astore_1
  aload 4
  aload_1
  aload 14
  invokevirtual android/content/ContentValues/put(Ljava/lang/String;Ljava/lang/Long;)V
Label3:
  aload_0
  getfield cn/domob/android/ads/o/i Z
  istore 10
  iload 10
  invokestatic java/lang/Boolean/valueOf(Z)Ljava/lang/Boolean;
  astore 11
  ldc "_test_flag"
  astore_1
  aload 4
  aload_1
  aload 11
  invokevirtual android/content/ContentValues/put(Ljava/lang/String;Ljava/lang/Boolean;)V
  aload_0
  getfield cn/domob/android/ads/o/h Ljava/lang/String;
  astore 6
  aload 6
  invokestatic app/DummyClass/invokeIfStmt(Ljava/lang/Object;)V
  aload 6
  ifnull Label4
  ldc "DomobSDK"
  astore_1
  iconst_3
  istore 8
  aload_1
  iload 8
  invokestatic android/util/Log/isLoggable(Ljava/lang/String;I)Z
  istore 10
  iload 10
  invokestatic app/DummyClass/invokeIfStmt(Z)V
  iload 10
  ifeq Label5
  new java/lang/StringBuilder
  astore 15
  aload 15
  invokespecial java/lang/StringBuilder/<init>()V
  ldc "update cid:"
  astore_1
  aload 15
  aload_1
  invokevirtual java/lang/StringBuilder/append(Ljava/lang/String;)Ljava/lang/StringBuilder;
  astore 15
  aload_0
  getfield cn/domob/android/ads/o/h Ljava/lang/String;
  astore 5
  aload 15
  aload 5
  invokevirtual java/lang/StringBuilder/append(Ljava/lang/String;)Ljava/lang/StringBuilder;
  astore 15
  aload 15
  invokevirtual java/lang/StringBuilder/toString()Ljava/lang/String;
  astore 5
  ldc "DomobSDK"
  astore_1
  aload_1
  aload 5
  invokestatic android/util/Log/d(Ljava/lang/String;Ljava/lang/String;)I
  pop
Label5:
  aload_0
  getfield cn/domob/android/ads/o/h Ljava/lang/String;
  astore 5
  ldc "_cid"
  astore_1
  aload 4
  aload_1
  aload 5
  invokevirtual android/content/ContentValues/put(Ljava/lang/String;Ljava/lang/String;)V
Label4:
  aload_3
  aload 4
  invokevirtual cn/domob/android/ads/d/a(Landroid/content/ContentValues;)I
  pop
  return
  nop
.end <method>

