.source SourceFile
.class  cn/domob/android/ads/D$1
.super java/lang/Thread
.field final "a" Lcn/domob/android/ads/D$c;
.field final "b" Lcn/domob/android/ads/D;

.method <init>(Lcn/domob/android/ads/D;Lcn/domob/android/ads/D$c;)V
.limit locals 3
.limit stack 200
  nop
  aload_0
  aload_1
  putfield cn/domob/android/ads/D$1/b Lcn/domob/android/ads/D;
  aload_0
  aload_2
  putfield cn/domob/android/ads/D$1/a Lcn/domob/android/ads/D$c;
  aload_0
  invokespecial java/lang/Thread/<init>()V
  return
  nop
.end <method>

.method public run()V
.limit locals 10
.limit stack 200
  nop
  aload_0
  getfield cn/domob/android/ads/D$1/b Lcn/domob/android/ads/D;
  astore_1
  aload_0
  getfield cn/domob/android/ads/D$1/a Lcn/domob/android/ads/D$c;
  astore_2
  aload_1
  aload_2
  invokestatic cn/domob/android/ads/D/a(Lcn/domob/android/ads/D;Lcn/domob/android/ads/D$c;)Ljava/util/HashMap;
  astore_3
  aload_0
  getfield cn/domob/android/ads/D$1/b Lcn/domob/android/ads/D;
  astore_1
  aload_1
  aload_3
  invokestatic cn/domob/android/ads/D/a(Lcn/domob/android/ads/D;Ljava/util/HashMap;)Ljava/lang/String;
  astore 4
  ldc "http://e.domob.cn/report"
  astore 6
  aload 6
  aload 4
  invokestatic cn/domob/android/ads/a/a(Ljava/lang/String;Ljava/lang/String;)Lcn/domob/android/ads/n;
  astore 5
  aload_0
  getfield cn/domob/android/ads/D$1/b Lcn/domob/android/ads/D;
  astore_1
  aload_1
  invokestatic cn/domob/android/ads/D/a(Lcn/domob/android/ads/D;)Landroid/content/Context;
  astore 7
  aload 5
  aload 7
  invokevirtual cn/domob/android/ads/n/a(Landroid/content/Context;)V
  aload 5
  invokevirtual cn/domob/android/ads/n/a()Z
  istore 8
  new java/lang/NoClassDefFoundError
  dup
  invokespecial java/lang/NoClassDefFoundError/<init>()V
  athrow
  iload 8
  ifeq Label0
  aload_0
  getfield cn/domob/android/ads/D$1/b Lcn/domob/android/ads/D;
  astore_1
  new java/lang/StringBuilder
  astore 9
  aload 9
  invokespecial java/lang/StringBuilder/<init>()V
  ldc "send report:"
  astore 6
  aload 9
  aload 6
  invokevirtual java/lang/StringBuilder/append(Ljava/lang/String;)Ljava/lang/StringBuilder;
  astore 9
  aload_0
  getfield cn/domob/android/ads/D$1/a Lcn/domob/android/ads/D$c;
  astore_2
  aload_2
  getfield cn/domob/android/ads/D$c/b Ljava/lang/String;
  astore 4
  aload 9
  aload 4
  invokevirtual java/lang/StringBuilder/append(Ljava/lang/String;)Ljava/lang/StringBuilder;
  astore 9
  ldc " success"
  astore 6
  aload 9
  aload 6
  invokevirtual java/lang/StringBuilder/append(Ljava/lang/String;)Ljava/lang/StringBuilder;
  astore 9
  aload 9
  invokevirtual java/lang/StringBuilder/toString()Ljava/lang/String;
  astore 4
  aload_1
  aload 4
  invokestatic cn/domob/android/ads/J/a(Ljava/lang/Object;Ljava/lang/String;)V
Label1:
  return
Label0:
  aload_0
  getfield cn/domob/android/ads/D$1/b Lcn/domob/android/ads/D;
  astore_1
  new java/lang/StringBuilder
  astore 9
  aload 9
  invokespecial java/lang/StringBuilder/<init>()V
  ldc "send report:"
  astore 6
  aload 9
  aload 6
  invokevirtual java/lang/StringBuilder/append(Ljava/lang/String;)Ljava/lang/StringBuilder;
  astore 9
  aload_0
  getfield cn/domob/android/ads/D$1/a Lcn/domob/android/ads/D$c;
  astore_2
  aload_2
  getfield cn/domob/android/ads/D$c/b Ljava/lang/String;
  astore 4
  aload 9
  aload 4
  invokevirtual java/lang/StringBuilder/append(Ljava/lang/String;)Ljava/lang/StringBuilder;
  astore 9
  ldc " failed"
  astore 6
  aload 9
  aload 6
  invokevirtual java/lang/StringBuilder/append(Ljava/lang/String;)Ljava/lang/StringBuilder;
  astore 9
  aload 9
  invokevirtual java/lang/StringBuilder/toString()Ljava/lang/String;
  astore 4
  aload_1
  aload 4
  invokestatic cn/domob/android/ads/J/a(Ljava/lang/Object;Ljava/lang/String;)V
  goto Label1
  nop
.end <method>

