.source SourceFile
.class public  cn/domob/android/ads/DomobAdView$e
.super java/lang/Object
.implements  java/lang/Runnable
.field final "a" Lcn/domob/android/ads/DomobAdView;

.method protected <init>(Lcn/domob/android/ads/DomobAdView;)V
.limit locals 2
.limit stack 200
  nop
  aload_0
  aload_1
  putfield cn/domob/android/ads/DomobAdView$e/a Lcn/domob/android/ads/DomobAdView;
  aload_0
  invokespecial java/lang/Object/<init>()V
  return
  nop
.end <method>

.method public final run()V
.limit locals 5
.limit stack 200
  nop
  aload_0
  getfield cn/domob/android/ads/DomobAdView$e/a Lcn/domob/android/ads/DomobAdView;
  astore_1
  new java/lang/NoClassDefFoundError
  dup
  invokespecial java/lang/NoClassDefFoundError/<init>()V
  athrow
  iload_1
  ifeq Label0
  aload_0
  getfield cn/domob/android/ads/DomobAdView$e/a Lcn/domob/android/ads/DomobAdView;
  astore_1
  aload_1
  invokestatic cn/domob/android/ads/DomobAdView/c(Lcn/domob/android/ads/DomobAdView;)Lcn/domob/android/ads/g;
  astore_2
  aload_2
  invokevirtual cn/domob/android/ads/g/e()Z
  istore_3
  iload_3
  invokestatic app/DummyClass/invokeIfStmt(Z)V
  iload_3
  ifeq Label1
  aload_0
  getfield cn/domob/android/ads/DomobAdView$e/a Lcn/domob/android/ads/DomobAdView;
  astore_1
  bipush 8
  istore 4
  aload_1
  iload 4
  invokevirtual cn/domob/android/ads/DomobAdView/setVisibility(I)V
Label0:
  return
Label1:
  aload_0
  getfield cn/domob/android/ads/DomobAdView$e/a Lcn/domob/android/ads/DomobAdView;
  astore_1
  iconst_0
  istore 4
  aload_1
  iload 4
  invokevirtual cn/domob/android/ads/DomobAdView/setVisibility(I)V
  goto Label0
  nop
.end <method>

