.source SourceFile
.class  cn/domob/android/ads/z$b
.super java/lang/Object
.implements  java/lang/Runnable
.field final "a" Lcn/domob/android/ads/z;

.method <init>(Lcn/domob/android/ads/z;)V
.limit locals 2
.limit stack 200
  nop
  aload_0
  aload_1
  putfield cn/domob/android/ads/z$b/a Lcn/domob/android/ads/z;
  aload_0
  invokespecial java/lang/Object/<init>()V
  return
  nop
.end <method>

.method public run()V
.limit locals 12
.limit stack 200
  nop
  aload_0
  getfield cn/domob/android/ads/z$b/a Lcn/domob/android/ads/z;
  astore_1
  aload_1
  invokestatic cn/domob/android/ads/z/e(Lcn/domob/android/ads/z;)Landroid/widget/RelativeLayout;
  astore_2
  new java/lang/NoClassDefFoundError
  dup
  invokespecial java/lang/NoClassDefFoundError/<init>()V
  athrow
  aload_0
  getfield cn/domob/android/ads/z$b/a Lcn/domob/android/ads/z;
  astore_1
  aload_1
  invokestatic cn/domob/android/ads/z/i(Lcn/domob/android/ads/z;)Landroid/widget/RelativeLayout;
  astore_2
  aload_2
  invokestatic app/DummyClass/invokeIfStmt(Ljava/lang/Object;)V
  aload_2
  ifnull Label0
  aload_0
  getfield cn/domob/android/ads/z$b/a Lcn/domob/android/ads/z;
  astore_1
  aload_1
  invokestatic cn/domob/android/ads/z/i(Lcn/domob/android/ads/z;)Landroid/widget/RelativeLayout;
  astore_2
  aload_2
  invokevirtual android/widget/RelativeLayout/removeAllViews()V
Label0:
  aload_0
  getfield cn/domob/android/ads/z$b/a Lcn/domob/android/ads/z;
  astore_3
  new cn/domob/android/ads/L
  astore 4
  aload_0
  getfield cn/domob/android/ads/z$b/a Lcn/domob/android/ads/z;
  astore_1
  aload_1
  invokestatic cn/domob/android/ads/z/d(Lcn/domob/android/ads/z;)Landroid/content/Context;
  astore 5
  iconst_m1
  istore 6
  aload 4
  aload 5
  iload 6
  invokespecial cn/domob/android/ads/L/<init>(Landroid/content/Context;I)V
  aload_3
  aload 4
  invokestatic cn/domob/android/ads/z/a(Lcn/domob/android/ads/z;Lcn/domob/android/ads/L;)Lcn/domob/android/ads/L;
  pop
  aload_0
  getfield cn/domob/android/ads/z$b/a Lcn/domob/android/ads/z;
  astore_3
  aload_0
  getfield cn/domob/android/ads/z$b/a Lcn/domob/android/ads/z;
  astore_1
  aload_1
  invokestatic cn/domob/android/ads/z/l(Lcn/domob/android/ads/z;)Ljava/lang/String;
  astore 7
  aload 7
  invokestatic cn/domob/android/ads/z/a(Ljava/lang/String;)Ljava/lang/String;
  astore 7
  aload_3
  aload 7
  invokestatic cn/domob/android/ads/z/b(Lcn/domob/android/ads/z;Ljava/lang/String;)Ljava/lang/String;
  pop
  aload_0
  getfield cn/domob/android/ads/z$b/a Lcn/domob/android/ads/z;
  astore_3
  aload_0
  getfield cn/domob/android/ads/z$b/a Lcn/domob/android/ads/z;
  astore_1
  aload_1
  invokestatic cn/domob/android/ads/z/m(Lcn/domob/android/ads/z;)Ljava/lang/String;
  astore 7
  aload_3
  aload 7
  invokestatic cn/domob/android/ads/z/c(Lcn/domob/android/ads/z;Ljava/lang/String;)Ljava/lang/String;
  pop
  aload_0
  getfield cn/domob/android/ads/z$b/a Lcn/domob/android/ads/z;
  astore_3
  aload_3
  invokestatic cn/domob/android/ads/z/a(Lcn/domob/android/ads/z;)Lcn/domob/android/ads/L;
  astore 4
  aload_0
  getfield cn/domob/android/ads/z$b/a Lcn/domob/android/ads/z;
  astore_3
  aload_3
  invokestatic cn/domob/android/ads/z/n(Lcn/domob/android/ads/z;)Ljava/lang/String;
  astore 7
  aload 4
  aload 7
  invokevirtual cn/domob/android/ads/L/loadUrl(Ljava/lang/String;)V
  aload_0
  getfield cn/domob/android/ads/z$b/a Lcn/domob/android/ads/z;
  astore_3
  iconst_0
  istore 6
  aload_3
  iload 6
  invokestatic cn/domob/android/ads/z/a(Lcn/domob/android/ads/z;I)I
  pop
Label3:
  aload_0
  getfield cn/domob/android/ads/z$b/a Lcn/domob/android/ads/z;
  astore_3
  aload_3
  invokevirtual cn/domob/android/ads/z/b()Landroid/app/Dialog;
  astore 8
  aload 8
  invokevirtual android/app/Dialog/show()V
  aload_0
  getfield cn/domob/android/ads/z$b/a Lcn/domob/android/ads/z;
  astore_3
  aload_3
  invokestatic cn/domob/android/ads/z/f(Lcn/domob/android/ads/z;)Lcn/domob/android/ads/g;
  astore 9
  aload 9
  invokevirtual cn/domob/android/ads/g/o()Lcn/domob/android/ads/DomobAdListener;
  astore 10
  aload 10
  invokestatic app/DummyClass/invokeIfStmt(Ljava/lang/Object;)V
  aload 10
  ifnull Label1
  aload_0
  getfield cn/domob/android/ads/z$b/a Lcn/domob/android/ads/z;
  astore_3
  aload_3
  invokestatic cn/domob/android/ads/z/f(Lcn/domob/android/ads/z;)Lcn/domob/android/ads/g;
  astore 9
  aload 9
  invokevirtual cn/domob/android/ads/g/o()Lcn/domob/android/ads/DomobAdListener;
  astore 10
  aload 10
  invokeinterface cn/domob/android/ads/DomobAdListener/onLandingPageOpening()V 1
Label1:
  return
Label2:
  astore 11
  aload 11
  invokevirtual java/lang/Exception/printStackTrace()V
  goto Label1
  nop
.end <method>

