.source SourceFile
.class  cn/domob/android/a/h
.super java/lang/Thread
.field static "a" Ljava/lang/String;
.field static "b" Ljava/lang/String;
.field protected static final "c" Ljava/lang/String; =  ".temp"
.field static final "d" I =  2097152
.field static final "e" I =  5242880
.field private static final "h" Ljava/lang/String; =  "/DomobAppDownload/"
.field private "f" Lcn/domob/android/a/i;
.field private "g" Landroid/content/Context;
.field private "i" J
.field private "j" Ljava/lang/String;
.field private "k" Ljava/lang/String;
.field private final "l" Ljava/lang/String;
.field private "m" Z
.field private "n" Ljava/lang/String;

.method static <clinit>()V
.limit locals 1
.limit stack 200
  nop
  ldc "sd\u5361"
  astore_0
  aload_0
  putstatic cn/domob/android/a/h/a Ljava/lang/String;
  ldc "\u5185\u5b58\u5361"
  astore_0
  aload_0
  putstatic cn/domob/android/a/h/b Ljava/lang/String;
  return
  nop
.end <method>

.method protected <init>(Landroid/content/Context;Ljava/lang/String;Ljava/lang/String;Lcn/domob/android/a/i;)V
.limit locals 12
.limit stack 200
  nop
  aload_0
  invokespecial java/lang/Thread/<init>()V
  aconst_null
  astore 5
  aload_0
  aload 5
  putfield cn/domob/android/a/h/f Lcn/domob/android/a/i;
  aconst_null
  astore 5
  aload_0
  aload 5
  putfield cn/domob/android/a/h/g Landroid/content/Context;
  ldc2_w 0
  lstore 6
  aload_0
  lload 6
  putfield cn/domob/android/a/h/i J
  ldc ""
  astore 8
  aload_0
  aload 8
  putfield cn/domob/android/a/h/j Ljava/lang/String;
  ldc ""
  astore 8
  aload_0
  aload 8
  putfield cn/domob/android/a/h/k Ljava/lang/String;
  ldc ".apk"
  astore 8
  aload_0
  aload 8
  putfield cn/domob/android/a/h/l Ljava/lang/String;
  iconst_0
  istore 9
  aload_0
  iload 9
  putfield cn/domob/android/a/h/m Z
  ldc ""
  astore 8
  aload_0
  aload 8
  putfield cn/domob/android/a/h/n Ljava/lang/String;
  aload_0
  aload 4
  putfield cn/domob/android/a/h/f Lcn/domob/android/a/i;
  aload_0
  aload_1
  putfield cn/domob/android/a/h/g Landroid/content/Context;
  aload_0
  aload_3
  putfield cn/domob/android/a/h/n Ljava/lang/String;
  new java/lang/StringBuilder
  astore 10
  aload 10
  invokespecial java/lang/StringBuilder/<init>()V
  aload 10
  aload_2
  invokevirtual java/lang/StringBuilder/append(Ljava/lang/String;)Ljava/lang/StringBuilder;
  astore 10
  ldc ".apk"
  astore 8
  aload 10
  aload 8
  invokevirtual java/lang/StringBuilder/append(Ljava/lang/String;)Ljava/lang/StringBuilder;
  astore 10
  aload 10
  invokevirtual java/lang/StringBuilder/toString()Ljava/lang/String;
  astore 11
  aload_0
  aload 11
  putfield cn/domob/android/a/h/j Ljava/lang/String;
  return
  nop
.end <method>

.method private a(Ljava/lang/String;)J
.limit locals 16
.limit stack 200
  nop
  new java/net/URL
  astore_2
  aload_2
  aload_1
  invokespecial java/net/URL/<init>(Ljava/lang/String;)V
  aload_0
  getfield cn/domob/android/a/h/g Landroid/content/Context;
  astore_3
  aload_3
  invokestatic cn/domob/android/a/e/b(Landroid/content/Context;)Ljava/net/Proxy;
  astore 4
  new java/lang/NoClassDefFoundError
  dup
  invokespecial java/lang/NoClassDefFoundError/<init>()V
  athrow
  iload 4
  ifeq Label0
  aload_2
  aload 4
  invokevirtual java/net/URL/openConnection(Ljava/net/Proxy;)Ljava/net/URLConnection;
  astore 5
  aload 5
  astore 7
  aload 7
  checkcast java/net/HttpURLConnection
  astore 7
  aload 7
  astore 6
Label2:
  ldc "HEAD"
  astore 8
  aload 6
  aload 8
  invokevirtual java/net/HttpURLConnection/setRequestMethod(Ljava/lang/String;)V
  aload 6
  invokevirtual java/net/HttpURLConnection/getResponseCode()I
  istore 9
  dload 9
  invokestatic app/DummyClass/invokeIfStmt(D)V
  sipush 200
  istore 10
  iload 9
  iload 10
  if_icmplt Label1
  dload 9
  invokestatic app/DummyClass/invokeIfStmt(D)V
  sipush 300
  istore 10
  iload 9
  iload 10
  if_icmpge Label1
  aload 6
  invokevirtual java/net/HttpURLConnection/getContentLength()I
  istore 9
  iload 9
  i2l
  lstore 11
  lload 11
  lreturn
Label0:
  aload_2
  invokevirtual java/net/URL/openConnection()Ljava/net/URLConnection;
  astore 5
  aload 5
  astore 13
  aload 13
  checkcast java/net/HttpURLConnection
  astore 13
  aload 13
  astore 6
  goto Label2
Label1:
  ldc2_w 4294967295
  lstore 14
  lload 14
  lreturn
  nop
.end <method>

.method protected a()Ljava/lang/String;
.limit locals 7
.limit stack 200
  nop
  ldc "DomobSDK"
  astore_2
  iconst_3
  istore_3
  new java/lang/NoClassDefFoundError
  dup
  invokespecial java/lang/NoClassDefFoundError/<init>()V
  athrow
  nop
  iload_1
  invokestatic app/DummyClass/invokeIfStmt(Z)V
  iload_1
  ifeq Label0
  new java/lang/StringBuilder
  astore 4
  aload 4
  invokespecial java/lang/StringBuilder/<init>()V
  ldc "app is download:"
  astore_2
  aload 4
  aload_2
  invokevirtual java/lang/StringBuilder/append(Ljava/lang/String;)Ljava/lang/StringBuilder;
  astore 4
  aload_0
  invokespecial cn/domob/android/a/h/d()Z
  istore_1
  aload 4
  iload_1
  invokevirtual java/lang/StringBuilder/append(Z)Ljava/lang/StringBuilder;
  astore 4
  ldc " "
  astore_2
  aload 4
  aload_2
  invokevirtual java/lang/StringBuilder/append(Ljava/lang/String;)Ljava/lang/StringBuilder;
  astore 4
  ldc "is not complete:"
  astore_2
  aload 4
  aload_2
  invokevirtual java/lang/StringBuilder/append(Ljava/lang/String;)Ljava/lang/StringBuilder;
  astore 4
  aload_0
  getfield cn/domob/android/a/h/m Z
  istore_1
  aload 4
  iload_1
  invokevirtual java/lang/StringBuilder/append(Z)Ljava/lang/StringBuilder;
  astore 4
  aload 4
  invokevirtual java/lang/StringBuilder/toString()Ljava/lang/String;
  astore 5
  ldc "DomobSDK"
  astore_2
  aload_2
  aload 5
  invokestatic android/util/Log/d(Ljava/lang/String;Ljava/lang/String;)I
  pop
Label0:
  aload_0
  invokespecial cn/domob/android/a/h/d()Z
  istore_1
  iload_1
  invokestatic app/DummyClass/invokeIfStmt(Z)V
  iload_1
  ifeq Label1
  aload_0
  getfield cn/domob/android/a/h/m Z
  istore_1
  iload_1
  invokestatic app/DummyClass/invokeIfStmt(Z)V
  iload_1
  ifeq Label2
Label1:
  aconst_null
  astore 6
  aload 6
  areturn
Label2:
  aload_0
  getfield cn/domob/android/a/h/k Ljava/lang/String;
  astore 5
  aload 5
  areturn
  nop
.end <method>

.method private b()V
.limit locals 2
.limit stack 200
  nop
  aload_0
  invokespecial cn/domob/android/a/h/d()Z
  istore_1
  new java/lang/NoClassDefFoundError
  dup
  invokespecial java/lang/NoClassDefFoundError/<init>()V
  athrow
  iload_1
  ifeq Label0
Label1:
  return
Label0:
  aload_0
  invokespecial cn/domob/android/a/h/c()Z
  istore_1
  iload_1
  invokestatic app/DummyClass/invokeIfStmt(Z)V
  iload_1
  ifne Label1
  goto Label1
  nop
.end <method>

.method private b(Ljava/lang/String;)Z
.limit locals 13
.limit stack 200
  nop
  new java/io/File
  astore_2
  aload_2
  aload_1
  invokespecial java/io/File/<init>(Ljava/lang/String;)V
  new java/io/File
  astore_3
  new java/lang/StringBuilder
  astore 4
  aload 4
  invokespecial java/lang/StringBuilder/<init>()V
  aload 4
  aload_1
  invokevirtual java/lang/StringBuilder/append(Ljava/lang/String;)Ljava/lang/StringBuilder;
  astore 4
  ldc ".temp"
  astore 5
  aload 4
  aload 5
  invokevirtual java/lang/StringBuilder/append(Ljava/lang/String;)Ljava/lang/StringBuilder;
  astore 4
  aload 4
  invokevirtual java/lang/StringBuilder/toString()Ljava/lang/String;
  astore 6
  aload_3
  aload 6
  invokespecial java/io/File/<init>(Ljava/lang/String;)V
  aload_2
  invokevirtual java/io/File/exists()Z
  istore 7
  new java/lang/NoClassDefFoundError
  dup
  invokespecial java/lang/NoClassDefFoundError/<init>()V
  athrow
  iload 7
  ifeq Label0
  aload_0
  getfield cn/domob/android/a/h/f Lcn/domob/android/a/i;
  astore 8
  aload 8
  invokestatic app/DummyClass/invokeIfStmt(Ljava/lang/Object;)V
  aload 8
  ifnull Label1
  aload_0
  getfield cn/domob/android/a/h/f Lcn/domob/android/a/i;
  astore 8
  aload 8
  aload_1
  invokeinterface cn/domob/android/a/i/a(Ljava/lang/String;)V 2
Label1:
  iconst_1
  istore 9
  iload 9
  ireturn
Label0:
  aload_3
  invokevirtual java/io/File/exists()Z
  istore 7
  iload 7
  invokestatic app/DummyClass/invokeIfStmt(Z)V
  iload 7
  ifeq Label2
  ldc "DomobSDK"
  astore 5
  iconst_3
  istore 9
  aload 5
  iload 9
  invokestatic android/util/Log/isLoggable(Ljava/lang/String;I)Z
  istore 7
  iload 7
  invokestatic app/DummyClass/invokeIfStmt(Z)V
  iload 7
  ifeq Label3
  new java/lang/StringBuilder
  astore 4
  aload 4
  invokespecial java/lang/StringBuilder/<init>()V
  aload 4
  aload_1
  invokevirtual java/lang/StringBuilder/append(Ljava/lang/String;)Ljava/lang/StringBuilder;
  astore 4
  ldc "\u3000download size="
  astore 5
  aload 4
  aload 5
  invokevirtual java/lang/StringBuilder/append(Ljava/lang/String;)Ljava/lang/StringBuilder;
  astore 4
  aload_3
  invokevirtual java/io/File/length()J
  lstore 10
  aload 4
  lload 10
  invokevirtual java/lang/StringBuilder/append(J)Ljava/lang/StringBuilder;
  astore 4
  ldc " "
  astore 5
  aload 4
  aload 5
  invokevirtual java/lang/StringBuilder/append(Ljava/lang/String;)Ljava/lang/StringBuilder;
  astore 4
  ldc "softSize:"
  astore 5
  aload 4
  aload 5
  invokevirtual java/lang/StringBuilder/append(Ljava/lang/String;)Ljava/lang/StringBuilder;
  astore 4
  aload_0
  getfield cn/domob/android/a/h/i J
  lstore 10
  aload 4
  lload 10
  invokevirtual java/lang/StringBuilder/append(J)Ljava/lang/StringBuilder;
  astore 4
  aload 4
  invokevirtual java/lang/StringBuilder/toString()Ljava/lang/String;
  astore 12
  ldc "DomobSDK"
  astore 5
  aload 5
  aload 12
  invokestatic android/util/Log/d(Ljava/lang/String;Ljava/lang/String;)I
  pop
Label3:
  iconst_1
  istore 9
  aload_0
  iload 9
  putfield cn/domob/android/a/h/m Z
  aload_0
  getfield cn/domob/android/a/h/f Lcn/domob/android/a/i;
  astore 8
  aload 8
  invokestatic app/DummyClass/invokeIfStmt(Ljava/lang/Object;)V
  aload 8
  ifnull Label1
  aload_0
  getfield cn/domob/android/a/h/f Lcn/domob/android/a/i;
  astore 8
  new java/lang/StringBuilder
  astore 4
  aload 4
  invokespecial java/lang/StringBuilder/<init>()V
  aload 4
  aload_1
  invokevirtual java/lang/StringBuilder/append(Ljava/lang/String;)Ljava/lang/StringBuilder;
  astore 4
  ldc ".temp"
  astore 5
  aload 4
  aload 5
  invokevirtual java/lang/StringBuilder/append(Ljava/lang/String;)Ljava/lang/StringBuilder;
  astore 4
  aload 4
  invokevirtual java/lang/StringBuilder/toString()Ljava/lang/String;
  astore 12
  aload 8
  aload 12
  invokeinterface cn/domob/android/a/i/b(Ljava/lang/String;)V 2
  iconst_1
  istore 9
  iload 9
  ireturn
Label2:
  iconst_0
  istore 9
  iload 9
  ireturn
  nop
.end <method>

.method private c()Z
.limit locals 36
.limit stack 200
  .catch  java/lang/Exception <from> Label8 <to> Label9 <using> Label7
  nop
  ldc ""
  astore 8
  ldc2_w 0.000000000000000
  dstore 9
Label8:
  aload_0
  astore_1
  aload_1
  getfield cn/domob/android/a/h/n Ljava/lang/String;
  astore 11
  aload_0
  astore_1
  aload_1
  aload 11
  invokespecial cn/domob/android/a/h/a(Ljava/lang/String;)J
  lstore 12
  aload_0
  astore_1
  aload_1
  lload 12
  putfield cn/domob/android/a/h/i J
Label9:
  invokestatic cn/domob/android/a/h/e()Z
  istore 14
  new java/lang/NoClassDefFoundError
  dup
  invokespecial java/lang/NoClassDefFoundError/<init>()V
  athrow
  iload 14
  ifeq Label0
  new android/os/StatFs
  astore 15
  invokestatic android/os/Environment/getExternalStorageDirectory()Ljava/io/File;
  astore 16
  aload 16
  invokevirtual java/io/File/getPath()Ljava/lang/String;
  astore 11
  aload 15
  aload 11
  invokespecial android/os/StatFs/<init>(Ljava/lang/String;)V
  aload 15
  invokevirtual android/os/StatFs/getBlockSize()I
  istore 17
  iload 17
  istore_1
  iload_1
  i2l
  lstore 12
  aload 15
  invokevirtual android/os/StatFs/getAvailableBlocks()I
  istore 17
  iload 17
  istore_1
  iload_1
  i2l
  lstore 9
  lload 12
  lload 9
  lmul
  lstore 9
  ldc "DomobSDK"
  astore 18
  iconst_3
  istore 19
  aload 18
  astore_1
  iload 19
  istore_2
  aload_1
  iload_2
  invokestatic android/util/Log/isLoggable(Ljava/lang/String;I)Z
  istore 14
  iload 14
  invokestatic app/DummyClass/invokeIfStmt(Z)V
  iload 14
  ifeq Label1
  new java/lang/StringBuilder
  astore 20
  aload 20
  astore_1
  aload_1
  invokespecial java/lang/StringBuilder/<init>()V
  ldc "sd availaSize="
  astore 18
  aload 20
  astore_1
  aload 18
  astore_2
  aload_1
  aload_2
  invokevirtual java/lang/StringBuilder/append(Ljava/lang/String;)Ljava/lang/StringBuilder;
  astore 20
  aload 20
  astore_1
  aload_1
  lload 9
  invokevirtual java/lang/StringBuilder/append(J)Ljava/lang/StringBuilder;
  astore 20
  ldc "softsize="
  astore 18
  aload 20
  astore_1
  aload 18
  astore_2
  aload_1
  aload_2
  invokevirtual java/lang/StringBuilder/append(Ljava/lang/String;)Ljava/lang/StringBuilder;
  astore 20
  aload_0
  astore_1
  aload_1
  getfield cn/domob/android/a/h/i J
  lstore 12
  aload 20
  astore_1
  aload_1
  lload 12
  invokevirtual java/lang/StringBuilder/append(J)Ljava/lang/StringBuilder;
  astore 20
  aload 20
  astore_1
  aload_1
  invokevirtual java/lang/StringBuilder/toString()Ljava/lang/String;
  astore 11
  ldc "DomobSDK"
  astore 18
  aload 18
  astore_1
  aload_1
  aload 11
  invokestatic android/util/Log/d(Ljava/lang/String;Ljava/lang/String;)I
  pop
Label1:
  aload_0
  astore_1
  aload_1
  getfield cn/domob/android/a/h/i J
  lstore 12
  ldc2_w 2097152
  lstore 23
  lload 12
  lload 23
  ladd
  lstore 21
  lload 9
  lload 21
  lcmp
  istore 25
  iload 25
  istore_1
  dload_1
  invokestatic app/DummyClass/invokeIfStmt(D)V
  iload 25
  ifle Label0
  new java/lang/StringBuilder
  astore 20
  aload 20
  astore_1
  aload_1
  invokespecial java/lang/StringBuilder/<init>()V
  invokestatic android/os/Environment/getExternalStorageDirectory()Ljava/io/File;
  astore 16
  aload 20
  astore_1
  aload_1
  aload 16
  invokevirtual java/lang/StringBuilder/append(Ljava/lang/Object;)Ljava/lang/StringBuilder;
  astore 20
  ldc "/DomobAppDownload/"
  astore 18
  aload 20
  astore_1
  aload 18
  astore_2
  aload_1
  aload_2
  invokevirtual java/lang/StringBuilder/append(Ljava/lang/String;)Ljava/lang/StringBuilder;
  astore 20
  aload 20
  astore_1
  aload_1
  invokevirtual java/lang/StringBuilder/toString()Ljava/lang/String;
  astore 8
  aload_0
  astore_1
  aload_1
  aload 8
  invokespecial cn/domob/android/a/h/c(Ljava/lang/String;)Z
  pop
  iconst_1
  istore 14
Label6:
  iload 14
  invokestatic app/DummyClass/invokeIfStmt(Z)V
  iload 14
  ifne Label2
  invokestatic android/os/Environment/getDataDirectory()Ljava/io/File;
  astore 16
  new android/os/StatFs
  astore 15
  aload 16
  invokevirtual java/io/File/getPath()Ljava/lang/String;
  astore 26
  aload 26
  astore_1
  aload 15
  aload_1
  invokespecial android/os/StatFs/<init>(Ljava/lang/String;)V
  aload 15
  invokevirtual android/os/StatFs/getBlockSize()I
  istore 17
  iload 17
  istore_1
  iload_1
  i2l
  lstore_1
  lload_1
  lstore 21
  aload 15
  invokevirtual android/os/StatFs/getAvailableBlocks()I
  istore 17
  iload 17
  istore_1
  iload_1
  i2l
  lstore 12
  lload 21
  lstore_1
  lload_1
  lload 12
  lmul
  lstore_1
  lload_1
  lstore 21
  ldc "DomobSDK"
  astore 18
  iconst_3
  istore 19
  aload 18
  astore_1
  iload 19
  istore_2
  aload_1
  iload_2
  invokestatic android/util/Log/isLoggable(Ljava/lang/String;I)Z
  istore 14
  iload 14
  invokestatic app/DummyClass/invokeIfStmt(Z)V
  iload 14
  ifeq Label3
  new java/lang/StringBuilder
  astore 20
  aload 20
  astore_1
  aload_1
  invokespecial java/lang/StringBuilder/<init>()V
  ldc "rom"
  astore 18
  aload 20
  astore_1
  aload 18
  astore_2
  aload_1
  aload_2
  invokevirtual java/lang/StringBuilder/append(Ljava/lang/String;)Ljava/lang/StringBuilder;
  astore 20
  aload 20
  astore_1
  lload 21
  lstore_2
  aload_1
  lload_2
  invokevirtual java/lang/StringBuilder/append(J)Ljava/lang/StringBuilder;
  astore 20
  aload 20
  astore_1
  aload_1
  invokevirtual java/lang/StringBuilder/toString()Ljava/lang/String;
  astore 11
  ldc "DomobSDK"
  astore 18
  aload 18
  astore_1
  aload_1
  aload 11
  invokestatic android/util/Log/d(Ljava/lang/String;Ljava/lang/String;)I
  pop
Label3:
  aload_0
  astore_1
  aload_1
  getfield cn/domob/android/a/h/i J
  lstore 12
  ldc2_w 5242880
  lstore 23
  lload 12
  lload 23
  ladd
  lstore 27
  lload 21
  lload 27
  lcmp
  istore 25
  iload 25
  istore_1
  dload_1
  invokestatic app/DummyClass/invokeIfStmt(D)V
  iload 25
  ifge Label4
  aload_0
  astore_1
  aload_1
  getfield cn/domob/android/a/h/f Lcn/domob/android/a/i;
  astore_1
  aload_1
  astore 29
  aload_0
  astore_1
  aload_1
  getfield cn/domob/android/a/h/i J
  lstore_1
  lload_1
  lstore 27
  aload 29
  astore_1
  lload 27
  lstore_2
  lload 9
  lstore 4
  lload 21
  lstore 6
  aload_1
  lload_2
  lload 4
  lload 6
  invokeinterface cn/domob/android/a/i/a(JJJ)V 7
  iconst_0
  istore 19
  iload 19
  ireturn
Label7:
  astore 30
  aload_0
  astore_1
  aload_1
  getfield cn/domob/android/a/h/f Lcn/domob/android/a/i;
  astore_1
  aload_1
  astore 29
  ldc "\u8fde\u63a5\u4e0b\u8f7d\u5730\u5740\u9519\u8bef"
  astore 18
  aload 29
  astore_1
  aload 18
  astore_2
  aload_1
  aload_2
  invokeinterface cn/domob/android/a/i/d(Ljava/lang/String;)V 2
  iconst_0
  istore 19
  iload 19
  ireturn
Label4:
  new java/lang/StringBuilder
  astore 20
  aload 20
  astore_1
  aload_1
  invokespecial java/lang/StringBuilder/<init>()V
  aload_0
  astore_1
  aload_1
  getfield cn/domob/android/a/h/g Landroid/content/Context;
  astore_1
  aload_1
  astore 31
  aload 31
  astore_1
  aload_1
  invokevirtual android/content/Context/getFilesDir()Ljava/io/File;
  astore 16
  aload 16
  invokevirtual java/io/File/getAbsolutePath()Ljava/lang/String;
  astore 26
  aload 20
  astore_1
  aload 26
  astore_2
  aload_1
  aload_2
  invokevirtual java/lang/StringBuilder/append(Ljava/lang/String;)Ljava/lang/StringBuilder;
  astore 20
  ldc "/DomobAppDownload/"
  astore 18
  aload 20
  astore_1
  aload 18
  astore_2
  aload_1
  aload_2
  invokevirtual java/lang/StringBuilder/append(Ljava/lang/String;)Ljava/lang/StringBuilder;
  astore 20
  aload 20
  astore_1
  aload_1
  invokevirtual java/lang/StringBuilder/toString()Ljava/lang/String;
  astore 8
  aload_0
  astore_1
  aload_1
  aload 8
  invokespecial cn/domob/android/a/h/c(Ljava/lang/String;)Z
  pop
  new java/io/File
  astore 16
  aload 16
  aload 8
  invokespecial java/io/File/<init>(Ljava/lang/String;)V
  new java/lang/StringBuilder
  astore 20
  aload 20
  astore_1
  aload_1
  invokespecial java/lang/StringBuilder/<init>()V
  ldc "chmod 777 "
  astore 18
  aload 20
  astore_1
  aload 18
  astore_2
  aload_1
  aload_2
  invokevirtual java/lang/StringBuilder/append(Ljava/lang/String;)Ljava/lang/StringBuilder;
  astore 20
  aload 16
  invokevirtual java/io/File/getAbsolutePath()Ljava/lang/String;
  astore 26
  aload 20
  astore_1
  aload 26
  astore_2
  aload_1
  aload_2
  invokevirtual java/lang/StringBuilder/append(Ljava/lang/String;)Ljava/lang/StringBuilder;
  astore 20
  aload 20
  astore_1
  aload_1
  invokevirtual java/lang/StringBuilder/toString()Ljava/lang/String;
  astore 26
  invokestatic java/lang/Runtime/getRuntime()Ljava/lang/Runtime;
  astore 32
Label12:
  aload 32
  astore_1
  aload 26
  astore_2
  aload_1
  aload_2
  invokevirtual java/lang/Runtime/exec(Ljava/lang/String;)Ljava/lang/Process;
  astore 33
  aload 33
  astore_1
  aload_1
  invokevirtual java/lang/Process/waitFor()I
  istore 17
Label13:
  iload 17
  istore_1
  dload_1
  invokestatic app/DummyClass/invokeIfStmt(D)V
  iload 17
  ifne Label5
Label2:
  aload_0
  astore_1
  aload_1
  getfield cn/domob/android/a/h/f Lcn/domob/android/a/i;
  astore_1
  aload_1
  astore 29
  new java/lang/StringBuilder
  astore 20
  aload 20
  astore_1
  aload_1
  invokespecial java/lang/StringBuilder/<init>()V
  aload 20
  astore_1
  aload_1
  aload 8
  invokevirtual java/lang/StringBuilder/append(Ljava/lang/String;)Ljava/lang/StringBuilder;
  astore 20
  aload_0
  astore_1
  aload_1
  getfield cn/domob/android/a/h/j Ljava/lang/String;
  astore_1
  aload_1
  astore 26
  aload 20
  astore_1
  aload 26
  astore_2
  aload_1
  aload_2
  invokevirtual java/lang/StringBuilder/append(Ljava/lang/String;)Ljava/lang/StringBuilder;
  astore 20
  ldc ".temp"
  astore 18
  aload 20
  astore_1
  aload 18
  astore_2
  aload_1
  aload_2
  invokevirtual java/lang/StringBuilder/append(Ljava/lang/String;)Ljava/lang/StringBuilder;
  astore 20
  aload 20
  astore_1
  aload_1
  invokevirtual java/lang/StringBuilder/toString()Ljava/lang/String;
  astore 26
  aload 29
  astore_1
  aload 26
  astore_2
  aload_1
  aload_2
  invokeinterface cn/domob/android/a/i/c(Ljava/lang/String;)V 2
  iconst_1
  istore 19
  iload 19
  ireturn
Label5:
  aload_0
  astore_1
  aload_1
  getfield cn/domob/android/a/h/f Lcn/domob/android/a/i;
  astore_1
  aload_1
  astore 29
Label14:
  aload 29
  astore_1
  aload_1
  invokeinterface cn/domob/android/a/i/a()V 1
Label15:
  iconst_0
  istore 19
  iload 19
  ireturn
Label11:
  astore 34
  aload 34
  astore_1
  aload_1
  invokestatic cn/domob/android/ads/J/a(Ljava/lang/Throwable;)V
  goto Label2
Label10:
  astore 35
  aload 35
  astore_1
  aload_1
  invokestatic cn/domob/android/ads/J/a(Ljava/lang/Throwable;)V
  goto Label2
Label0:
  iconst_0
  istore 14
  goto Label6
  nop
.end <method>

.method private c(Ljava/lang/String;)Z
.limit locals 5
.limit stack 200
  nop
  new java/io/File
  astore_2
  aload_2
  aload_1
  invokespecial java/io/File/<init>(Ljava/lang/String;)V
  aload_2
  invokevirtual java/io/File/exists()Z
  istore_3
  new java/lang/NoClassDefFoundError
  dup
  invokespecial java/lang/NoClassDefFoundError/<init>()V
  athrow
  iload_3
  ifne Label0
  aload_2
  invokevirtual java/io/File/mkdirs()Z
  istore_3
  iload_3
  ireturn
Label0:
  iconst_1
  istore 4
  iload 4
  ireturn
  nop
.end <method>

.method private d()Z
.limit locals 8
.limit stack 200
  nop
  new java/lang/StringBuilder
  astore_1
  aload_1
  invokespecial java/lang/StringBuilder/<init>()V
  new java/lang/NoClassDefFoundError
  dup
  invokespecial java/lang/NoClassDefFoundError/<init>()V
  athrow
  nop
  aload_1
  aload_2
  invokevirtual java/lang/StringBuilder/append(Ljava/lang/Object;)Ljava/lang/StringBuilder;
  astore_1
  ldc "/DomobAppDownload/"
  astore_3
  aload_1
  aload_3
  invokevirtual java/lang/StringBuilder/append(Ljava/lang/String;)Ljava/lang/StringBuilder;
  astore_1
  aload_0
  getfield cn/domob/android/a/h/j Ljava/lang/String;
  astore 4
  aload_1
  aload 4
  invokevirtual java/lang/StringBuilder/append(Ljava/lang/String;)Ljava/lang/StringBuilder;
  astore_1
  aload_1
  invokevirtual java/lang/StringBuilder/toString()Ljava/lang/String;
  astore 4
  aload_0
  aload 4
  putfield cn/domob/android/a/h/k Ljava/lang/String;
  new java/lang/StringBuilder
  astore_1
  aload_1
  invokespecial java/lang/StringBuilder/<init>()V
  ldc "downloadPath: "
  astore_3
  aload_1
  aload_3
  invokevirtual java/lang/StringBuilder/append(Ljava/lang/String;)Ljava/lang/StringBuilder;
  astore_1
  aload_0
  getfield cn/domob/android/a/h/k Ljava/lang/String;
  astore 4
  aload_1
  aload 4
  invokevirtual java/lang/StringBuilder/append(Ljava/lang/String;)Ljava/lang/StringBuilder;
  astore_1
  aload_1
  invokevirtual java/lang/StringBuilder/toString()Ljava/lang/String;
  astore 4
  aload_0
  aload 4
  invokestatic cn/domob/android/ads/J/d(Ljava/lang/Object;Ljava/lang/String;)V
  aload_0
  getfield cn/domob/android/a/h/k Ljava/lang/String;
  astore 4
  aload_0
  aload 4
  invokespecial cn/domob/android/a/h/b(Ljava/lang/String;)Z
  istore 5
  iload 5
  invokestatic app/DummyClass/invokeIfStmt(Z)V
  iload 5
  ifeq Label0
Label1:
  iconst_1
  istore 6
  iload 6
  ireturn
Label0:
  new java/lang/StringBuilder
  astore_1
  aload_1
  invokespecial java/lang/StringBuilder/<init>()V
  aload_0
  getfield cn/domob/android/a/h/g Landroid/content/Context;
  astore 7
  aload 7
  invokevirtual android/content/Context/getFilesDir()Ljava/io/File;
  astore_2
  aload_2
  invokevirtual java/io/File/getAbsolutePath()Ljava/lang/String;
  astore 4
  aload_1
  aload 4
  invokevirtual java/lang/StringBuilder/append(Ljava/lang/String;)Ljava/lang/StringBuilder;
  astore_1
  ldc "/DomobAppDownload/"
  astore_3
  aload_1
  aload_3
  invokevirtual java/lang/StringBuilder/append(Ljava/lang/String;)Ljava/lang/StringBuilder;
  astore_1
  aload_0
  getfield cn/domob/android/a/h/j Ljava/lang/String;
  astore 4
  aload_1
  aload 4
  invokevirtual java/lang/StringBuilder/append(Ljava/lang/String;)Ljava/lang/StringBuilder;
  astore_1
  aload_1
  invokevirtual java/lang/StringBuilder/toString()Ljava/lang/String;
  astore 4
  aload_0
  aload 4
  putfield cn/domob/android/a/h/k Ljava/lang/String;
  aload_0
  getfield cn/domob/android/a/h/k Ljava/lang/String;
  astore 4
  aload_0
  aload 4
  invokespecial cn/domob/android/a/h/b(Ljava/lang/String;)Z
  istore 5
  iload 5
  invokestatic app/DummyClass/invokeIfStmt(Z)V
  iload 5
  ifne Label1
  iconst_0
  istore 6
  iload 6
  ireturn
  nop
.end <method>

.method private static e()Z
.limit locals 3
.limit stack 200
  nop
  new java/lang/NoClassDefFoundError
  dup
  invokespecial java/lang/NoClassDefFoundError/<init>()V
  athrow
  nop
  ldc "mounted"
  astore_2
  aload_0
  aload_2
  invokevirtual java/lang/String/equals(Ljava/lang/Object;)Z
  istore_1
  iload_1
  ireturn
  nop
.end <method>

.method public final run()V
.limit locals 1
.limit stack 200
  nop
  aload_0
  invokespecial cn/domob/android/a/h/b()V
  return
  nop
.end <method>

