.source SourceFile
.class  cn/domob/android/a/a$1
.super java/lang/Object
.implements  cn/domob/android/a/i
.field final "a" Lcn/domob/android/a/a;

.method <init>(Lcn/domob/android/a/a;)V
.limit locals 2
.limit stack 200
  nop
  aload_0
  aload_1
  putfield cn/domob/android/a/a$1/a Lcn/domob/android/a/a;
  aload_0
  invokespecial java/lang/Object/<init>()V
  return
  nop
.end <method>

.method public a()V
.limit locals 7
.limit stack 200
  nop
  new java/lang/StringBuilder
  astore_1
  aload_1
  invokespecial java/lang/StringBuilder/<init>()V
  aload_0
  getfield cn/domob/android/a/a$1/a Lcn/domob/android/a/a;
  astore_2
  aload_2
  invokestatic cn/domob/android/a/a/b(Lcn/domob/android/a/a;)Ljava/lang/String;
  astore_3
  aload_1
  aload_3
  invokevirtual java/lang/StringBuilder/append(Ljava/lang/String;)Ljava/lang/StringBuilder;
  astore_1
  ldc "rom can\'t chmod"
  astore 4
  aload_1
  aload 4
  invokevirtual java/lang/StringBuilder/append(Ljava/lang/String;)Ljava/lang/StringBuilder;
  astore_1
  aload_1
  invokevirtual java/lang/StringBuilder/toString()Ljava/lang/String;
  astore_3
  ldc "DomobSDK"
  astore 4
  new java/lang/NoClassDefFoundError
  dup
  invokespecial java/lang/NoClassDefFoundError/<init>()V
  athrow
  aload_0
  getfield cn/domob/android/a/a$1/a Lcn/domob/android/a/a;
  astore_2
  aload_2
  invokestatic cn/domob/android/a/a/j(Lcn/domob/android/a/a;)Lcn/domob/android/a/c;
  astore 5
  aload 5
  invokestatic app/DummyClass/invokeIfStmt(Ljava/lang/Object;)V
  aload 5
  ifnull Label0
  aload_0
  getfield cn/domob/android/a/a$1/a Lcn/domob/android/a/a;
  astore_2
  aload_2
  invokestatic cn/domob/android/a/a/j(Lcn/domob/android/a/a;)Lcn/domob/android/a/c;
  astore 5
  iconst_5
  istore 6
  ldc "sd\u5361\u4e0d\u5b58\u5728"
  astore 4
  aload 5
  iload 6
  aload 4
  invokeinterface cn/domob/android/a/c/a(ILjava/lang/String;)V 3
Label0:
  aload_0
  getfield cn/domob/android/a/a$1/a Lcn/domob/android/a/a;
  astore_2
  ldc "sd\u5361\u4e0d\u5b58\u5728"
  astore 4
  aload_2
  aload 4
  invokestatic cn/domob/android/a/a/b(Lcn/domob/android/a/a;Ljava/lang/String;)V
  return
  nop
.end <method>

.method public a(JJJ)V
.limit locals 13
.limit stack 200
  nop
  new java/lang/StringBuilder
  astore 7
  aload 7
  invokespecial java/lang/StringBuilder/<init>()V
  aload_0
  getfield cn/domob/android/a/a$1/a Lcn/domob/android/a/a;
  astore 8
  aload 8
  invokestatic cn/domob/android/a/a/b(Lcn/domob/android/a/a;)Ljava/lang/String;
  astore 9
  aload 7
  aload 9
  invokevirtual java/lang/StringBuilder/append(Ljava/lang/String;)Ljava/lang/StringBuilder;
  astore 7
  ldc "not enough size sdsize="
  astore 10
  aload 7
  aload 10
  invokevirtual java/lang/StringBuilder/append(Ljava/lang/String;)Ljava/lang/StringBuilder;
  astore 7
  aload 7
  lload_3
  invokevirtual java/lang/StringBuilder/append(J)Ljava/lang/StringBuilder;
  astore 7
  ldc " romsize="
  astore 10
  aload 7
  aload 10
  invokevirtual java/lang/StringBuilder/append(Ljava/lang/String;)Ljava/lang/StringBuilder;
  astore 7
  aload 7
  lload 5
  invokevirtual java/lang/StringBuilder/append(J)Ljava/lang/StringBuilder;
  astore 7
  aload 7
  invokevirtual java/lang/StringBuilder/toString()Ljava/lang/String;
  astore 9
  ldc "DomobSDK"
  astore 10
  new java/lang/NoClassDefFoundError
  dup
  invokespecial java/lang/NoClassDefFoundError/<init>()V
  athrow
  aload_0
  getfield cn/domob/android/a/a$1/a Lcn/domob/android/a/a;
  astore 8
  aload 8
  invokestatic cn/domob/android/a/a/j(Lcn/domob/android/a/a;)Lcn/domob/android/a/c;
  astore 11
  aload 11
  invokestatic app/DummyClass/invokeIfStmt(Ljava/lang/Object;)V
  aload 11
  ifnull Label0
  aload_0
  getfield cn/domob/android/a/a$1/a Lcn/domob/android/a/a;
  astore 8
  aload 8
  invokestatic cn/domob/android/a/a/j(Lcn/domob/android/a/a;)Lcn/domob/android/a/c;
  astore 11
  iconst_1
  istore 12
  ldc "\u7a7a\u95f4\u4e0d\u8db3"
  astore 10
  aload 11
  iload 12
  aload 10
  invokeinterface cn/domob/android/a/c/a(ILjava/lang/String;)V 3
Label0:
  aload_0
  getfield cn/domob/android/a/a$1/a Lcn/domob/android/a/a;
  astore 8
  ldc "\u7a7a\u95f4\u4e0d\u8db3"
  astore 10
  aload 8
  aload 10
  invokestatic cn/domob/android/a/a/b(Lcn/domob/android/a/a;Ljava/lang/String;)V
  return
  nop
.end <method>

.method public a(Ljava/lang/String;)V
.limit locals 10
.limit stack 200
  nop
  new java/lang/StringBuilder
  astore_2
  aload_2
  invokespecial java/lang/StringBuilder/<init>()V
  aload_0
  getfield cn/domob/android/a/a$1/a Lcn/domob/android/a/a;
  astore_3
  aload_3
  invokestatic cn/domob/android/a/a/b(Lcn/domob/android/a/a;)Ljava/lang/String;
  astore 4
  aload_2
  aload 4
  invokevirtual java/lang/StringBuilder/append(Ljava/lang/String;)Ljava/lang/StringBuilder;
  astore_2
  ldc " already exists in "
  astore 5
  aload_2
  aload 5
  invokevirtual java/lang/StringBuilder/append(Ljava/lang/String;)Ljava/lang/StringBuilder;
  astore_2
  aload_2
  aload_1
  invokevirtual java/lang/StringBuilder/append(Ljava/lang/String;)Ljava/lang/StringBuilder;
  astore_2
  aload_2
  invokevirtual java/lang/StringBuilder/toString()Ljava/lang/String;
  astore 4
  ldc cn/domob/android/a/a
  astore 6
  aload 6
  aload 4
  invokestatic cn/domob/android/ads/J/d(Ljava/lang/Object;Ljava/lang/String;)V
  aload_0
  getfield cn/domob/android/a/a$1/a Lcn/domob/android/a/a;
  astore_3
  aload_3
  aload_1
  invokestatic cn/domob/android/a/a/a(Lcn/domob/android/a/a;Ljava/lang/String;)Ljava/lang/String;
  pop
  aload_0
  getfield cn/domob/android/a/a$1/a Lcn/domob/android/a/a;
  astore_3
  aload_0
  getfield cn/domob/android/a/a$1/a Lcn/domob/android/a/a;
  astore 7
  aload 7
  invokestatic cn/domob/android/a/a/h(Lcn/domob/android/a/a;)Ljava/lang/String;
  astore 4
  ldc2_w 0
  lstore 8
  aload_3
  aload 4
  lload 8
  invokestatic cn/domob/android/a/a/a(Lcn/domob/android/a/a;Ljava/lang/String;J)V
  return
  nop
.end <method>

.method public b(Ljava/lang/String;)V
.limit locals 11
.limit stack 200
  nop
  new java/lang/StringBuilder
  astore_2
  aload_2
  invokespecial java/lang/StringBuilder/<init>()V
  aload_0
  getfield cn/domob/android/a/a$1/a Lcn/domob/android/a/a;
  astore_3
  aload_3
  invokestatic cn/domob/android/a/a/b(Lcn/domob/android/a/a;)Ljava/lang/String;
  astore 4
  aload_2
  aload 4
  invokevirtual java/lang/StringBuilder/append(Ljava/lang/String;)Ljava/lang/StringBuilder;
  astore_2
  ldc " is download but not finished in "
  astore 5
  aload_2
  aload 5
  invokevirtual java/lang/StringBuilder/append(Ljava/lang/String;)Ljava/lang/StringBuilder;
  astore_2
  aload_2
  aload_1
  invokevirtual java/lang/StringBuilder/append(Ljava/lang/String;)Ljava/lang/StringBuilder;
  astore_2
  aload_2
  invokevirtual java/lang/StringBuilder/toString()Ljava/lang/String;
  astore 4
  ldc cn/domob/android/a/a
  astore 6
  aload 6
  aload 4
  invokestatic cn/domob/android/ads/J/d(Ljava/lang/Object;Ljava/lang/String;)V
  aload_0
  getfield cn/domob/android/a/a$1/a Lcn/domob/android/a/a;
  astore_3
  aload_3
  aload_1
  invokestatic cn/domob/android/a/a/a(Lcn/domob/android/a/a;Ljava/lang/String;)Ljava/lang/String;
  pop
  new java/io/File
  astore 7
  aload_0
  getfield cn/domob/android/a/a$1/a Lcn/domob/android/a/a;
  astore_3
  aload_3
  invokestatic cn/domob/android/a/a/h(Lcn/domob/android/a/a;)Ljava/lang/String;
  astore 4
  aload 7
  aload 4
  invokespecial java/io/File/<init>(Ljava/lang/String;)V
  aload_0
  getfield cn/domob/android/a/a$1/a Lcn/domob/android/a/a;
  astore_3
  aload_0
  getfield cn/domob/android/a/a$1/a Lcn/domob/android/a/a;
  astore 8
  aload 8
  invokestatic cn/domob/android/a/a/h(Lcn/domob/android/a/a;)Ljava/lang/String;
  astore 4
  aload 7
  invokevirtual java/io/File/length()J
  lstore 9
  aload_3
  aload 4
  lload 9
  invokestatic cn/domob/android/a/a/a(Lcn/domob/android/a/a;Ljava/lang/String;J)V
  return
  nop
.end <method>

.method public c(Ljava/lang/String;)V
.limit locals 10
.limit stack 200
  nop
  new java/lang/StringBuilder
  astore_2
  aload_2
  invokespecial java/lang/StringBuilder/<init>()V
  aload_0
  getfield cn/domob/android/a/a$1/a Lcn/domob/android/a/a;
  astore_3
  aload_3
  invokestatic cn/domob/android/a/a/b(Lcn/domob/android/a/a;)Ljava/lang/String;
  astore 4
  aload_2
  aload 4
  invokevirtual java/lang/StringBuilder/append(Ljava/lang/String;)Ljava/lang/StringBuilder;
  astore_2
  ldc " is  not download,it will download in "
  astore 5
  aload_2
  aload 5
  invokevirtual java/lang/StringBuilder/append(Ljava/lang/String;)Ljava/lang/StringBuilder;
  astore_2
  aload_2
  aload_1
  invokevirtual java/lang/StringBuilder/append(Ljava/lang/String;)Ljava/lang/StringBuilder;
  astore_2
  aload_2
  invokevirtual java/lang/StringBuilder/toString()Ljava/lang/String;
  astore 4
  ldc cn/domob/android/a/a
  astore 6
  aload 6
  aload 4
  invokestatic cn/domob/android/ads/J/d(Ljava/lang/Object;Ljava/lang/String;)V
  aload_0
  getfield cn/domob/android/a/a$1/a Lcn/domob/android/a/a;
  astore_3
  aload_3
  aload_1
  invokestatic cn/domob/android/a/a/a(Lcn/domob/android/a/a;Ljava/lang/String;)Ljava/lang/String;
  pop
  aload_0
  getfield cn/domob/android/a/a$1/a Lcn/domob/android/a/a;
  astore_3
  aload_0
  getfield cn/domob/android/a/a$1/a Lcn/domob/android/a/a;
  astore 7
  aload 7
  invokestatic cn/domob/android/a/a/h(Lcn/domob/android/a/a;)Ljava/lang/String;
  astore 4
  ldc2_w 0
  lstore 8
  aload_3
  aload 4
  lload 8
  invokestatic cn/domob/android/a/a/a(Lcn/domob/android/a/a;Ljava/lang/String;J)V
  return
  nop
.end <method>

.method public d(Ljava/lang/String;)V
.limit locals 8
.limit stack 200
  nop
  new java/lang/StringBuilder
  astore_2
  aload_2
  invokespecial java/lang/StringBuilder/<init>()V
  aload_0
  getfield cn/domob/android/a/a$1/a Lcn/domob/android/a/a;
  astore_3
  aload_3
  invokestatic cn/domob/android/a/a/b(Lcn/domob/android/a/a;)Ljava/lang/String;
  astore 4
  aload_2
  aload 4
  invokevirtual java/lang/StringBuilder/append(Ljava/lang/String;)Ljava/lang/StringBuilder;
  astore_2
  ldc "\u65e0\u6cd5\u8fde\u63a5\u5230\u4e0b\u8f7d\u5730\u5740"
  astore 5
  aload_2
  aload 5
  invokevirtual java/lang/StringBuilder/append(Ljava/lang/String;)Ljava/lang/StringBuilder;
  astore_2
  aload_2
  invokevirtual java/lang/StringBuilder/toString()Ljava/lang/String;
  astore 4
  ldc "DomobSDK"
  astore 5
  new java/lang/NoClassDefFoundError
  dup
  invokespecial java/lang/NoClassDefFoundError/<init>()V
  athrow
  aload_0
  getfield cn/domob/android/a/a$1/a Lcn/domob/android/a/a;
  astore_3
  aload_3
  invokestatic cn/domob/android/a/a/j(Lcn/domob/android/a/a;)Lcn/domob/android/a/c;
  astore 6
  aload 6
  invokestatic app/DummyClass/invokeIfStmt(Ljava/lang/Object;)V
  aload 6
  ifnull Label0
  aload_0
  getfield cn/domob/android/a/a$1/a Lcn/domob/android/a/a;
  astore_3
  aload_3
  invokestatic cn/domob/android/a/a/j(Lcn/domob/android/a/a;)Lcn/domob/android/a/c;
  astore 6
  new java/lang/StringBuilder
  astore_2
  aload_2
  invokespecial java/lang/StringBuilder/<init>()V
  aload_0
  getfield cn/domob/android/a/a$1/a Lcn/domob/android/a/a;
  astore_3
  aload_3
  invokestatic cn/domob/android/a/a/b(Lcn/domob/android/a/a;)Ljava/lang/String;
  astore 4
  aload_2
  aload 4
  invokevirtual java/lang/StringBuilder/append(Ljava/lang/String;)Ljava/lang/StringBuilder;
  astore_2
  aload_2
  aload_1
  invokevirtual java/lang/StringBuilder/append(Ljava/lang/String;)Ljava/lang/StringBuilder;
  astore_2
  aload_2
  invokevirtual java/lang/StringBuilder/toString()Ljava/lang/String;
  astore 4
  iconst_5
  istore 7
  aload 6
  iload 7
  aload 4
  invokeinterface cn/domob/android/a/c/a(ILjava/lang/String;)V 3
Label0:
  aload_0
  getfield cn/domob/android/a/a$1/a Lcn/domob/android/a/a;
  astore_3
  ldc "\u65e0\u6cd5\u8fde\u63a5\u5230\u4e0b\u8f7d\u5730\u5740"
  astore 5
  aload_3
  aload 5
  invokestatic cn/domob/android/a/a/b(Lcn/domob/android/a/a;Ljava/lang/String;)V
  return
  nop
.end <method>

