.source SourceFile
.class  cn/domob/android/ads/l$8
.super java/lang/Object
.implements  cn/domob/android/a/c
.field final "a" Lcn/domob/android/ads/l;

.method <init>(Lcn/domob/android/ads/l;)V
.limit locals 2
.limit stack 200
  nop
  aload_0
  aload_1
  putfield cn/domob/android/ads/l$8/a Lcn/domob/android/ads/l;
  aload_0
  invokespecial java/lang/Object/<init>()V
  return
  nop
.end <method>

.method public a()V
.limit locals 6
.limit stack 200
  nop
  aload_0
  getfield cn/domob/android/ads/l$8/a Lcn/domob/android/ads/l;
  astore_1
  aload_0
  getfield cn/domob/android/ads/l$8/a Lcn/domob/android/ads/l;
  astore_2
  aload_2
  invokestatic cn/domob/android/ads/l/l(Lcn/domob/android/ads/l;)Lcn/domob/android/ads/C;
  astore_3
  aload_3
  invokevirtual cn/domob/android/ads/C/c()Ljava/util/HashMap;
  astore 4
  ldc "download_start"
  astore 5
  aload_1
  aload 5
  aload 4
  invokestatic cn/domob/android/ads/l/a(Lcn/domob/android/ads/l;Ljava/lang/String;Ljava/util/HashMap;)V
  return
  nop
.end <method>

.method public a(ILjava/lang/String;)V
.limit locals 9
.limit stack 200
  nop
  new java/lang/NoClassDefFoundError
  dup
  invokespecial java/lang/NoClassDefFoundError/<init>()V
  athrow
  sipush 512
  istore_3
  iload_1
  iload_3
  if_icmpne Label0
  aload_0
  getfield cn/domob/android/ads/l$8/a Lcn/domob/android/ads/l;
  astore 4
  aload_0
  getfield cn/domob/android/ads/l$8/a Lcn/domob/android/ads/l;
  astore 5
  aload 5
  invokestatic cn/domob/android/ads/l/l(Lcn/domob/android/ads/l;)Lcn/domob/android/ads/C;
  astore 6
  aload 6
  invokevirtual cn/domob/android/ads/C/c()Ljava/util/HashMap;
  astore 7
  ldc "download_repeat"
  astore 8
  aload 4
  aload 8
  aload 7
  invokestatic cn/domob/android/ads/l/a(Lcn/domob/android/ads/l;Ljava/lang/String;Ljava/util/HashMap;)V
Label2:
  return
Label0:
  dload_1
  invokestatic app/DummyClass/invokeIfStmt(D)V
  sipush 513
  istore_3
  iload_1
  iload_3
  if_icmpne Label1
  aload_0
  getfield cn/domob/android/ads/l$8/a Lcn/domob/android/ads/l;
  astore 4
  aload_0
  getfield cn/domob/android/ads/l$8/a Lcn/domob/android/ads/l;
  astore 5
  aload 5
  invokestatic cn/domob/android/ads/l/l(Lcn/domob/android/ads/l;)Lcn/domob/android/ads/C;
  astore 6
  aload 6
  invokevirtual cn/domob/android/ads/C/c()Ljava/util/HashMap;
  astore 7
  ldc "download_overflow"
  astore 8
  aload 4
  aload 8
  aload 7
  invokestatic cn/domob/android/ads/l/a(Lcn/domob/android/ads/l;Ljava/lang/String;Ljava/util/HashMap;)V
  goto Label2
Label1:
  aload_0
  getfield cn/domob/android/ads/l$8/a Lcn/domob/android/ads/l;
  astore 4
  aload_0
  getfield cn/domob/android/ads/l$8/a Lcn/domob/android/ads/l;
  astore 5
  aload 5
  invokestatic cn/domob/android/ads/l/l(Lcn/domob/android/ads/l;)Lcn/domob/android/ads/C;
  astore 6
  aload 6
  invokevirtual cn/domob/android/ads/C/c()Ljava/util/HashMap;
  astore 7
  ldc "download_failed"
  astore 8
  aload 4
  aload 8
  aload 7
  invokestatic cn/domob/android/ads/l/a(Lcn/domob/android/ads/l;Ljava/lang/String;Ljava/util/HashMap;)V
  goto Label2
  nop
.end <method>

.method public a(Ljava/lang/String;)V
.limit locals 11
.limit stack 200
  nop
  aload_0
  getfield cn/domob/android/ads/l$8/a Lcn/domob/android/ads/l;
  astore_2
  aload_0
  getfield cn/domob/android/ads/l$8/a Lcn/domob/android/ads/l;
  astore_3
  aload_3
  invokestatic cn/domob/android/ads/l/l(Lcn/domob/android/ads/l;)Lcn/domob/android/ads/C;
  astore 4
  aload 4
  invokevirtual cn/domob/android/ads/C/c()Ljava/util/HashMap;
  astore 5
  ldc "download_finish"
  astore 6
  aload_2
  aload 6
  aload 5
  invokestatic cn/domob/android/ads/l/a(Lcn/domob/android/ads/l;Ljava/lang/String;Ljava/util/HashMap;)V
  aload_0
  getfield cn/domob/android/ads/l$8/a Lcn/domob/android/ads/l;
  astore_3
  aload_3
  invokestatic cn/domob/android/ads/l/c(Lcn/domob/android/ads/l;)Landroid/content/Context;
  astore 7
  new java/lang/NoClassDefFoundError
  dup
  invokespecial java/lang/NoClassDefFoundError/<init>()V
  athrow
  nop
  aload_0
  getfield cn/domob/android/ads/l$8/a Lcn/domob/android/ads/l;
  astore_3
  aload_3
  invokestatic cn/domob/android/ads/l/i(Lcn/domob/android/ads/l;)Ljava/lang/String;
  astore_1
  aload_0
  getfield cn/domob/android/ads/l$8/a Lcn/domob/android/ads/l;
  astore_3
  aload_3
  invokestatic cn/domob/android/ads/l/j(Lcn/domob/android/ads/l;)Z
  istore 9
  aload_0
  getfield cn/domob/android/ads/l$8/a Lcn/domob/android/ads/l;
  astore_3
  aload_3
  invokestatic cn/domob/android/ads/l/k(Lcn/domob/android/ads/l;)Ljava/lang/String;
  astore 10
  aload 8
  aload_1
  iload 9
  aload 10
  invokevirtual cn/domob/android/ads/f/a(Ljava/lang/String;ZLjava/lang/String;)V
  return
  nop
.end <method>

.method public b()V
.limit locals 6
.limit stack 200
  nop
  aload_0
  getfield cn/domob/android/ads/l$8/a Lcn/domob/android/ads/l;
  astore_1
  aload_0
  getfield cn/domob/android/ads/l$8/a Lcn/domob/android/ads/l;
  astore_2
  aload_2
  invokestatic cn/domob/android/ads/l/l(Lcn/domob/android/ads/l;)Lcn/domob/android/ads/C;
  astore_3
  aload_3
  invokevirtual cn/domob/android/ads/C/c()Ljava/util/HashMap;
  astore 4
  ldc "download_cancel"
  astore 5
  aload_1
  aload 5
  aload 4
  invokestatic cn/domob/android/ads/l/a(Lcn/domob/android/ads/l;Ljava/lang/String;Ljava/util/HashMap;)V
  return
  nop
.end <method>

.method public b(Ljava/lang/String;)V
.limit locals 2
.limit stack 200
  nop
  return
  nop
.end <method>

