.source SourceFile
.class  cn/domob/android/ads/DomobAdView$3
.super java/lang/Object
.implements  java/lang/Runnable
.field final "a" I
.field final "b" I
.field final "c" Lcn/domob/android/ads/DomobAdView;

.method <init>(Lcn/domob/android/ads/DomobAdView;II)V
.limit locals 4
.limit stack 200
  nop
  aload_0
  aload_1
  putfield cn/domob/android/ads/DomobAdView$3/c Lcn/domob/android/ads/DomobAdView;
  aload_0
  iload_2
  putfield cn/domob/android/ads/DomobAdView$3/a I
  aload_0
  iload_3
  putfield cn/domob/android/ads/DomobAdView$3/b I
  aload_0
  invokespecial java/lang/Object/<init>()V
  return
  nop
.end <method>

.method public run()V
.limit locals 7
.limit stack 200
  nop
  aload_0
  getfield cn/domob/android/ads/DomobAdView$3/c Lcn/domob/android/ads/DomobAdView;
  astore_1
  new java/lang/NoClassDefFoundError
  dup
  invokespecial java/lang/NoClassDefFoundError/<init>()V
  athrow
  new android/widget/RelativeLayout$LayoutParams
  astore_3
  aload_0
  getfield cn/domob/android/ads/DomobAdView$3/a I
  istore 4
  aload_0
  getfield cn/domob/android/ads/DomobAdView$3/b I
  istore 5
  aload_3
  iload 4
  iload 5
  invokespecial android/widget/RelativeLayout$LayoutParams/<init>(II)V
  aload_2
  aload_3
  invokevirtual android/widget/RelativeLayout/setLayoutParams(Landroid/view/ViewGroup$LayoutParams;)V
  aload_0
  getfield cn/domob/android/ads/DomobAdView$3/c Lcn/domob/android/ads/DomobAdView;
  astore_1
  aload_1
  getfield cn/domob/android/ads/DomobAdView/f Landroid/widget/RelativeLayout;
  astore_2
  aload_0
  getfield cn/domob/android/ads/DomobAdView$3/c Lcn/domob/android/ads/DomobAdView;
  astore_1
  aload_0
  getfield cn/domob/android/ads/DomobAdView$3/a I
  istore 5
  aload_0
  getfield cn/domob/android/ads/DomobAdView$3/b I
  istore 4
  aload_1
  iload 5
  iload 4
  invokestatic cn/domob/android/ads/DomobAdView/a(Lcn/domob/android/ads/DomobAdView;II)Landroid/graphics/drawable/Drawable;
  astore 6
  aload_2
  aload 6
  invokevirtual android/widget/RelativeLayout/setBackgroundDrawable(Landroid/graphics/drawable/Drawable;)V
  return
  nop
.end <method>

