.source SourceFile
.class  cn/domob/android/ads/j$d
.super java/lang/Object
.field final "a" Lcn/domob/android/ads/j;
.field private "b" Ljava/util/ArrayList;
.field private "c" Ljava/util/ArrayList;
.field private "d" Ljava/lang/String;

.method protected <init>(Lcn/domob/android/ads/j;Lorg/json/JSONObject;)V
.limit locals 20
.limit stack 200
  nop
  aload_1
  astore_3
  aload_0
  astore 4
  aload 4
  aload_3
  putfield cn/domob/android/ads/j$d/a Lcn/domob/android/ads/j;
  aload_0
  astore_3
  aload_3
  invokespecial java/lang/Object/<init>()V
  new java/util/ArrayList
  astore 5
  aload 5
  invokespecial java/util/ArrayList/<init>()V
  aload_0
  astore_3
  aload_3
  aload 5
  putfield cn/domob/android/ads/j$d/b Ljava/util/ArrayList;
  new java/util/ArrayList
  astore 5
  aload 5
  invokespecial java/util/ArrayList/<init>()V
  aload_0
  astore_3
  aload_3
  aload 5
  putfield cn/domob/android/ads/j$d/c Ljava/util/ArrayList;
  ldc "$"
  astore 7
  aload_2
  astore_3
  aload_3
  aload 7
  invokevirtual org/json/JSONObject/optJSONObject(Ljava/lang/String;)Lorg/json/JSONObject;
  astore 6
  ldc "v"
  astore 7
  aload_2
  astore_3
  aload_3
  aload 7
  invokevirtual org/json/JSONObject/optJSONArray(Ljava/lang/String;)Lorg/json/JSONArray;
  astore 8
  new java/lang/NoClassDefFoundError
  dup
  invokespecial java/lang/NoClassDefFoundError/<init>()V
  athrow
  iload 6
  ifeq Label0
  aload 8
  invokestatic app/DummyClass/invokeIfStmt(Ljava/lang/Object;)V
  iload 8
  ifeq Label0
  aload 6
  invokevirtual org/json/JSONObject/keys()Ljava/util/Iterator;
  astore 9
Label4:
  aload 9
  invokeinterface java/util/Iterator/hasNext()Z 1
  istore 10
  iload 10
  invokestatic app/DummyClass/invokeIfStmt(Z)V
  iload 10
  ifne Label1
  iconst_0
  dstore 11
Label3:
  aload 8
  invokevirtual org/json/JSONArray/length()I
  istore 12
  dload 11
  invokestatic app/DummyClass/invokeIfStmt(D)V
  dload 12
  invokestatic app/DummyClass/invokeIfStmt(D)V
  iload 11
  iload 12
  if_icmpge Label0
  aload 8
  iload 11
  invokevirtual org/json/JSONArray/getJSONObject(I)Lorg/json/JSONObject;
  astore 13
  new cn/domob/android/ads/j$h
  astore 14
  aload_1
  astore_3
  aload 14
  aload_3
  aload 13
  invokespecial cn/domob/android/ads/j$h/<init>(Lcn/domob/android/ads/j;Lorg/json/JSONObject;)V
  aload 14
  invokestatic app/DummyClass/invokeIfStmt(Ljava/lang/Object;)V
  aload 14
  ifnull Label2
  aload_0
  astore_3
  aload_3
  getfield cn/domob/android/ads/j$d/c Ljava/util/ArrayList;
  astore 5
  aload 5
  aload 14
  invokevirtual java/util/ArrayList/add(Ljava/lang/Object;)Z
  pop
Label2:
  iload 11
  iconst_1
  iadd
  istore 11
  goto Label3
Label1:
  aload 9
  invokeinterface java/util/Iterator/next()Ljava/lang/Object; 1
  astore 15
  aload 15
  astore 17
  aload 17
  checkcast java/lang/String
  astore 17
  aload 17
  astore 16
  new cn/domob/android/ads/j$f
  astore 18
  aload 6
  aload 16
  invokevirtual org/json/JSONObject/getJSONObject(Ljava/lang/String;)Lorg/json/JSONObject;
  astore 13
  aload_1
  astore_3
  aload 18
  aload_3
  aload 16
  aload 13
  invokespecial cn/domob/android/ads/j$f/<init>(Lcn/domob/android/ads/j;Ljava/lang/String;Lorg/json/JSONObject;)V
  aload 18
  invokestatic app/DummyClass/invokeIfStmt(Ljava/lang/Object;)V
  aload 18
  ifnull Label4
  aload_0
  astore_3
  aload_3
  getfield cn/domob/android/ads/j$d/b Ljava/util/ArrayList;
  astore 5
  aload 5
  aload 18
  invokevirtual java/util/ArrayList/add(Ljava/lang/Object;)Z
  pop
  goto Label4
Label0:
  ldc "tat"
  astore 7
  aconst_null
  astore 19
  aload_2
  astore_3
  aload 19
  astore 4
  aload_3
  aload 7
  aload 4
  invokevirtual org/json/JSONObject/optString(Ljava/lang/String;Ljava/lang/String;)Ljava/lang/String;
  astore 16
  aload_0
  astore_3
  aload_3
  aload 16
  putfield cn/domob/android/ads/j$d/d Ljava/lang/String;
  return
  nop
.end <method>

.method protected a()Ljava/util/ArrayList;
  .signature_attr "()Ljava/util/ArrayList<Lcn/domob/android/ads/j$f;>;"
.limit locals 2
.limit stack 200
  nop
  aload_0
  getfield cn/domob/android/ads/j$d/b Ljava/util/ArrayList;
  astore_1
  aload_1
  areturn
  nop
.end <method>

.method protected b()Ljava/util/ArrayList;
  .signature_attr "()Ljava/util/ArrayList<Lcn/domob/android/ads/j$h;>;"
.limit locals 2
.limit stack 200
  nop
  aload_0
  getfield cn/domob/android/ads/j$d/c Ljava/util/ArrayList;
  astore_1
  aload_1
  areturn
  nop
.end <method>

.method protected c()Ljava/lang/String;
.limit locals 2
.limit stack 200
  nop
  aload_0
  getfield cn/domob/android/ads/j$d/d Ljava/lang/String;
  astore_1
  aload_1
  areturn
  nop
.end <method>

.method public toString()Ljava/lang/String;
.limit locals 6
.limit stack 200
  nop
  new java/lang/StringBuilder
  astore_1
  aload_1
  invokespecial java/lang/StringBuilder/<init>()V
  ldc "Markup [resources="
  astore_3
  aload_1
  aload_3
  invokevirtual java/lang/StringBuilder/append(Ljava/lang/String;)Ljava/lang/StringBuilder;
  astore_2
  aload_0
  getfield cn/domob/android/ads/j$d/b Ljava/util/ArrayList;
  astore 4
  aload_2
  aload 4
  invokevirtual java/lang/StringBuilder/append(Ljava/lang/Object;)Ljava/lang/StringBuilder;
  astore_2
  ldc ", viewDiscriptions="
  astore_3
  aload_2
  aload_3
  invokevirtual java/lang/StringBuilder/append(Ljava/lang/String;)Ljava/lang/StringBuilder;
  astore_2
  aload_0
  getfield cn/domob/android/ads/j$d/c Ljava/util/ArrayList;
  astore 4
  aload_2
  aload 4
  invokevirtual java/lang/StringBuilder/append(Ljava/lang/Object;)Ljava/lang/StringBuilder;
  astore_2
  ldc ", transAnimationType="
  astore_3
  aload_2
  aload_3
  invokevirtual java/lang/StringBuilder/append(Ljava/lang/String;)Ljava/lang/StringBuilder;
  astore_2
  aload_0
  getfield cn/domob/android/ads/j$d/d Ljava/lang/String;
  astore 5
  aload_2
  aload 5
  invokevirtual java/lang/StringBuilder/append(Ljava/lang/String;)Ljava/lang/StringBuilder;
  astore_2
  ldc "]"
  astore_3
  aload_2
  aload_3
  invokevirtual java/lang/StringBuilder/append(Ljava/lang/String;)Ljava/lang/StringBuilder;
  pop
  aload_1
  invokevirtual java/lang/StringBuilder/toString()Ljava/lang/String;
  astore 5
  aload 5
  areturn
  nop
.end <method>

