.source SourceFile
.class  cn/domob/android/ads/j$1
.super java/lang/Object
  .synthetic
.field static final "a" [I
.field static final "b" [I
.field static final "c" [I

.method static <clinit>()V
.limit locals 27
.limit stack 200
  .catch  java/lang/NoSuchFieldError <from> Label19 <to> Label20 <using> Label18
  .catch  java/lang/NoSuchFieldError <from> Label17 <to> Label22 <using> Label21
  .catch  java/lang/NoSuchFieldError <from> Label16 <to> Label24 <using> Label23
  .catch  java/lang/NoSuchFieldError <from> Label15 <to> Label26 <using> Label25
  .catch  java/lang/NoSuchFieldError <from> Label14 <to> Label28 <using> Label27
  .catch  java/lang/NoSuchFieldError <from> Label30 <to> Label31 <using> Label29
  .catch  java/lang/NoSuchFieldError <from> Label12 <to> Label33 <using> Label32
  .catch  java/lang/NoSuchFieldError <from> Label11 <to> Label35 <using> Label34
  .catch  java/lang/NoSuchFieldError <from> Label10 <to> Label37 <using> Label36
  .catch  java/lang/NoSuchFieldError <from> Label39 <to> Label40 <using> Label38
  .catch  java/lang/NoSuchFieldError <from> Label8 <to> Label42 <using> Label41
  .catch  java/lang/NoSuchFieldError <from> Label7 <to> Label44 <using> Label43
  .catch  java/lang/NoSuchFieldError <from> Label6 <to> Label46 <using> Label45
  .catch  java/lang/NoSuchFieldError <from> Label5 <to> Label48 <using> Label47
  .catch  java/lang/NoSuchFieldError <from> Label4 <to> Label50 <using> Label49
  .catch  java/lang/NoSuchFieldError <from> Label3 <to> Label52 <using> Label51
  .catch  java/lang/NoSuchFieldError <from> Label2 <to> Label54 <using> Label53
  .catch  java/lang/NoSuchFieldError <from> Label1 <to> Label56 <using> Label55
  nop
  invokestatic cn/domob/android/ads/j$c/values()[Lcn/domob/android/ads/j$c;
  astore_0
  aload_0
  arraylength
  istore_1
  iload_1
  newarray int
  astore_2
  aload_2
  putstatic cn/domob/android/ads/j$1/c [I
Label19:
  getstatic cn/domob/android/ads/j$1/c [I
  astore_2
  getstatic cn/domob/android/ads/j$c/a Lcn/domob/android/ads/j$c;
  astore_3
  aload_3
  invokevirtual cn/domob/android/ads/j$c/ordinal()I
  istore_1
Label20:
  iconst_1
  istore 4
  aload_2
  iload_1
  iload 4
  iastore
Label17:
  getstatic cn/domob/android/ads/j$1/c [I
  astore_2
  getstatic cn/domob/android/ads/j$c/b Lcn/domob/android/ads/j$c;
  astore_3
  aload_3
  invokevirtual cn/domob/android/ads/j$c/ordinal()I
  istore_1
Label22:
  iconst_2
  istore 4
  aload_2
  iload_1
  iload 4
  iastore
Label16:
  getstatic cn/domob/android/ads/j$1/c [I
  astore_2
  getstatic cn/domob/android/ads/j$c/c Lcn/domob/android/ads/j$c;
  astore_3
  aload_3
  invokevirtual cn/domob/android/ads/j$c/ordinal()I
  istore_1
Label24:
  iconst_3
  istore 4
  aload_2
  iload_1
  iload 4
  iastore
Label15:
  getstatic cn/domob/android/ads/j$1/c [I
  astore_2
  getstatic cn/domob/android/ads/j$c/d Lcn/domob/android/ads/j$c;
  astore_3
  aload_3
  invokevirtual cn/domob/android/ads/j$c/ordinal()I
  istore_1
Label26:
  iconst_4
  istore 4
  aload_2
  iload_1
  iload 4
  iastore
Label14:
  getstatic cn/domob/android/ads/j$1/c [I
  astore_2
  getstatic cn/domob/android/ads/j$c/e Lcn/domob/android/ads/j$c;
  astore_3
  aload_3
  invokevirtual cn/domob/android/ads/j$c/ordinal()I
  istore_1
Label28:
  iconst_5
  istore 4
  aload_2
  iload_1
  iload 4
  iastore
Label13:
  invokestatic cn/domob/android/ads/j$i/values()[Lcn/domob/android/ads/j$i;
  astore 5
  aload 5
  arraylength
  istore_1
  iload_1
  newarray int
  astore_2
  aload_2
  putstatic cn/domob/android/ads/j$1/b [I
Label30:
  getstatic cn/domob/android/ads/j$1/b [I
  astore_2
  getstatic cn/domob/android/ads/j$i/a Lcn/domob/android/ads/j$i;
  astore 6
  aload 6
  invokevirtual cn/domob/android/ads/j$i/ordinal()I
  istore_1
Label31:
  iconst_1
  istore 4
  aload_2
  iload_1
  iload 4
  iastore
Label12:
  getstatic cn/domob/android/ads/j$1/b [I
  astore_2
  getstatic cn/domob/android/ads/j$i/b Lcn/domob/android/ads/j$i;
  astore 6
  aload 6
  invokevirtual cn/domob/android/ads/j$i/ordinal()I
  istore_1
Label33:
  iconst_2
  istore 4
  aload_2
  iload_1
  iload 4
  iastore
Label11:
  getstatic cn/domob/android/ads/j$1/b [I
  astore_2
  getstatic cn/domob/android/ads/j$i/c Lcn/domob/android/ads/j$i;
  astore 6
  aload 6
  invokevirtual cn/domob/android/ads/j$i/ordinal()I
  istore_1
Label35:
  iconst_3
  istore 4
  aload_2
  iload_1
  iload 4
  iastore
Label10:
  getstatic cn/domob/android/ads/j$1/b [I
  astore_2
  getstatic cn/domob/android/ads/j$i/d Lcn/domob/android/ads/j$i;
  astore 6
  aload 6
  invokevirtual cn/domob/android/ads/j$i/ordinal()I
  istore_1
Label37:
  iconst_4
  istore 4
  aload_2
  iload_1
  iload 4
  iastore
Label9:
  invokestatic cn/domob/android/ads/j$b/values()[Lcn/domob/android/ads/j$b;
  astore 7
  aload 7
  arraylength
  istore_1
  iload_1
  newarray int
  astore_2
  aload_2
  putstatic cn/domob/android/ads/j$1/a [I
Label39:
  getstatic cn/domob/android/ads/j$1/a [I
  astore_2
  getstatic cn/domob/android/ads/j$b/c Lcn/domob/android/ads/j$b;
  astore 8
  aload 8
  invokevirtual cn/domob/android/ads/j$b/ordinal()I
  istore_1
Label40:
  iconst_1
  istore 4
  aload_2
  iload_1
  iload 4
  iastore
Label8:
  getstatic cn/domob/android/ads/j$1/a [I
  astore_2
  getstatic cn/domob/android/ads/j$b/d Lcn/domob/android/ads/j$b;
  astore 8
  aload 8
  invokevirtual cn/domob/android/ads/j$b/ordinal()I
  istore_1
Label42:
  iconst_2
  istore 4
  aload_2
  iload_1
  iload 4
  iastore
Label7:
  getstatic cn/domob/android/ads/j$1/a [I
  astore_2
  getstatic cn/domob/android/ads/j$b/e Lcn/domob/android/ads/j$b;
  astore 8
  aload 8
  invokevirtual cn/domob/android/ads/j$b/ordinal()I
  istore_1
Label44:
  iconst_3
  istore 4
  aload_2
  iload_1
  iload 4
  iastore
Label6:
  getstatic cn/domob/android/ads/j$1/a [I
  astore_2
  getstatic cn/domob/android/ads/j$b/a Lcn/domob/android/ads/j$b;
  astore 8
  aload 8
  invokevirtual cn/domob/android/ads/j$b/ordinal()I
  istore_1
Label46:
  iconst_4
  istore 4
  aload_2
  iload_1
  iload 4
  iastore
Label5:
  getstatic cn/domob/android/ads/j$1/a [I
  astore_2
  getstatic cn/domob/android/ads/j$b/f Lcn/domob/android/ads/j$b;
  astore 8
  aload 8
  invokevirtual cn/domob/android/ads/j$b/ordinal()I
  istore_1
Label48:
  iconst_5
  istore 4
  aload_2
  iload_1
  iload 4
  iastore
Label4:
  getstatic cn/domob/android/ads/j$1/a [I
  astore_2
  getstatic cn/domob/android/ads/j$b/g Lcn/domob/android/ads/j$b;
  astore 8
  aload 8
  invokevirtual cn/domob/android/ads/j$b/ordinal()I
  istore_1
Label50:
  bipush 6
  istore 4
  aload_2
  iload_1
  iload 4
  iastore
Label3:
  getstatic cn/domob/android/ads/j$1/a [I
  astore_2
  getstatic cn/domob/android/ads/j$b/h Lcn/domob/android/ads/j$b;
  astore 8
  aload 8
  invokevirtual cn/domob/android/ads/j$b/ordinal()I
  istore_1
Label52:
  bipush 7
  istore 4
  aload_2
  iload_1
  iload 4
  iastore
Label2:
  getstatic cn/domob/android/ads/j$1/a [I
  astore_2
  getstatic cn/domob/android/ads/j$b/i Lcn/domob/android/ads/j$b;
  astore 8
  aload 8
  invokevirtual cn/domob/android/ads/j$b/ordinal()I
  istore_1
Label54:
  bipush 8
  istore 4
  aload_2
  iload_1
  iload 4
  iastore
Label1:
  getstatic cn/domob/android/ads/j$1/a [I
  astore_2
  getstatic cn/domob/android/ads/j$b/j Lcn/domob/android/ads/j$b;
  astore 8
  aload 8
  invokevirtual cn/domob/android/ads/j$b/ordinal()I
  istore_1
Label56:
  bipush 9
  istore 4
  aload_2
  iload_1
  iload 4
  iastore
Label0:
  return
Label55:
  astore 9
  goto Label0
Label53:
  astore 10
  goto Label1
Label51:
  astore 11
  goto Label2
Label49:
  astore 12
  goto Label3
Label47:
  astore 13
  goto Label4
Label45:
  astore 14
  goto Label5
Label43:
  astore 15
  goto Label6
Label41:
  astore 16
  goto Label7
Label38:
  astore 17
  goto Label8
Label36:
  astore 18
  goto Label9
Label34:
  astore 19
  goto Label10
Label32:
  astore 20
  goto Label11
Label29:
  astore 21
  goto Label12
Label27:
  astore 22
  goto Label13
Label25:
  astore 23
  goto Label14
Label23:
  astore 24
  goto Label15
Label21:
  astore 25
  goto Label16
Label18:
  astore 26
  goto Label17
  nop
.end <method>

