.source SourceFile
.class  cn/domob/android/ads/l$9
.super java/lang/Object
  .synthetic
.field static final "a" [I

.method static <clinit>()V
.limit locals 12
.limit stack 200
  .catch  java/lang/NoSuchFieldError <from> Label8 <to> Label9 <using> Label7
  .catch  java/lang/NoSuchFieldError <from> Label6 <to> Label11 <using> Label10
  .catch  java/lang/NoSuchFieldError <from> Label5 <to> Label13 <using> Label12
  .catch  java/lang/NoSuchFieldError <from> Label4 <to> Label15 <using> Label14
  .catch  java/lang/NoSuchFieldError <from> Label3 <to> Label17 <using> Label16
  .catch  java/lang/NoSuchFieldError <from> Label2 <to> Label19 <using> Label18
  .catch  java/lang/NoSuchFieldError <from> Label1 <to> Label21 <using> Label20
  nop
  invokestatic cn/domob/android/ads/j$e/values()[Lcn/domob/android/ads/j$e;
  astore_0
  aload_0
  arraylength
  istore_1
  iload_1
  newarray int
  astore_2
  aload_2
  putstatic cn/domob/android/ads/l$9/a [I
Label8:
  getstatic cn/domob/android/ads/l$9/a [I
  astore_2
  getstatic cn/domob/android/ads/j$e/a Lcn/domob/android/ads/j$e;
  astore_3
  aload_3
  invokevirtual cn/domob/android/ads/j$e/ordinal()I
  istore_1
Label9:
  iconst_1
  istore 4
  aload_2
  iload_1
  iload 4
  iastore
Label6:
  getstatic cn/domob/android/ads/l$9/a [I
  astore_2
  getstatic cn/domob/android/ads/j$e/g Lcn/domob/android/ads/j$e;
  astore_3
  aload_3
  invokevirtual cn/domob/android/ads/j$e/ordinal()I
  istore_1
Label11:
  iconst_2
  istore 4
  aload_2
  iload_1
  iload 4
  iastore
Label5:
  getstatic cn/domob/android/ads/l$9/a [I
  astore_2
  getstatic cn/domob/android/ads/j$e/b Lcn/domob/android/ads/j$e;
  astore_3
  aload_3
  invokevirtual cn/domob/android/ads/j$e/ordinal()I
  istore_1
Label13:
  iconst_3
  istore 4
  aload_2
  iload_1
  iload 4
  iastore
Label4:
  getstatic cn/domob/android/ads/l$9/a [I
  astore_2
  getstatic cn/domob/android/ads/j$e/c Lcn/domob/android/ads/j$e;
  astore_3
  aload_3
  invokevirtual cn/domob/android/ads/j$e/ordinal()I
  istore_1
Label15:
  iconst_4
  istore 4
  aload_2
  iload_1
  iload 4
  iastore
Label3:
  getstatic cn/domob/android/ads/l$9/a [I
  astore_2
  getstatic cn/domob/android/ads/j$e/d Lcn/domob/android/ads/j$e;
  astore_3
  aload_3
  invokevirtual cn/domob/android/ads/j$e/ordinal()I
  istore_1
Label17:
  iconst_5
  istore 4
  aload_2
  iload_1
  iload 4
  iastore
Label2:
  getstatic cn/domob/android/ads/l$9/a [I
  astore_2
  getstatic cn/domob/android/ads/j$e/f Lcn/domob/android/ads/j$e;
  astore_3
  aload_3
  invokevirtual cn/domob/android/ads/j$e/ordinal()I
  istore_1
Label19:
  bipush 6
  istore 4
  aload_2
  iload_1
  iload 4
  iastore
Label1:
  getstatic cn/domob/android/ads/l$9/a [I
  astore_2
  getstatic cn/domob/android/ads/j$e/e Lcn/domob/android/ads/j$e;
  astore_3
  aload_3
  invokevirtual cn/domob/android/ads/j$e/ordinal()I
  istore_1
Label21:
  bipush 7
  istore 4
  aload_2
  iload_1
  iload 4
  iastore
Label0:
  return
Label20:
  astore 5
  goto Label0
Label18:
  astore 6
  goto Label1
Label16:
  astore 7
  goto Label2
Label14:
  astore 8
  goto Label3
Label12:
  astore 9
  goto Label4
Label10:
  astore 10
  goto Label5
Label7:
  astore 11
  goto Label6
  nop
.end <method>

