.source AdMogoLayout.java
.class public  com/admogo/AdMogoLayout$ViewAdRunnable
.super java/lang/Object
.implements  java/lang/Runnable
.field private "adMogoLayoutReference" Ljava/lang/ref/WeakReference;
.field private "nextView" Landroid/view/ViewGroup;

.method public <init>(Lcom/admogo/AdMogoLayout;Landroid/view/ViewGroup;I)V
.limit locals 5
.limit stack 200
  nop
  aload_0
  invokespecial java/lang/Object/<init>()V
  new java/lang/ref/WeakReference
  astore 4
  aload 4
  aload_1
  invokespecial java/lang/ref/WeakReference/<init>(Ljava/lang/Object;)V
  aload_0
  aload 4
  putfield com/admogo/AdMogoLayout$ViewAdRunnable/adMogoLayoutReference Ljava/lang/ref/WeakReference;
  aload_0
  aload_2
  putfield com/admogo/AdMogoLayout$ViewAdRunnable/nextView Landroid/view/ViewGroup;
  new java/lang/NoClassDefFoundError
  dup
  invokespecial java/lang/NoClassDefFoundError/<init>()V
  athrow
  return
  nop
.end <method>

.method public run()V
.limit locals 7
.limit stack 200
  nop
  aload_0
  getfield com/admogo/AdMogoLayout$ViewAdRunnable/adMogoLayoutReference Ljava/lang/ref/WeakReference;
  astore_1
  aload_1
  invokevirtual java/lang/ref/WeakReference/get()Ljava/lang/Object;
  astore_2
  aload_2
  astore 4
  new java/lang/NoClassDefFoundError
  dup
  invokespecial java/lang/NoClassDefFoundError/<init>()V
  athrow
  aload 4
  astore_3
  aload_3
  invokestatic app/DummyClass/invokeIfStmt(Ljava/lang/Object;)V
  iload_3
  ifeq Label0
  aload_0
  getfield com/admogo/AdMogoLayout$ViewAdRunnable/nextView Landroid/view/ViewGroup;
  astore 5
  invokestatic com/admogo/AdMogoLayout/access$16()I
  istore 6
  aload_3
  aload 5
  iload 6
  invokevirtual com/admogo/AdMogoLayout/pushSubView(Landroid/view/ViewGroup;I)V
Label0:
  return
  nop
.end <method>

