.source SourceFile
.class final  com/mobisage/android/w$a
.super java/lang/Object
.implements  com/mobisage/android/a
.field private "a" Lcom/mobisage/android/w;

.method private <init>(Lcom/mobisage/android/w;)V
.limit locals 2
.limit stack 200
  nop
  aload_0
  aload_1
  putfield com/mobisage/android/w$a/a Lcom/mobisage/android/w;
  aload_0
  invokespecial java/lang/Object/<init>()V
  return
  nop
.end <method>

.method <init>(Lcom/mobisage/android/w;B)V
  .synthetic
.limit locals 3
.limit stack 200
  nop
  aload_0
  aload_1
  invokespecial com/mobisage/android/w$a/<init>(Lcom/mobisage/android/w;)V
  return
  nop
.end <method>

.method public final a(Lcom/mobisage/android/b;)V
.limit locals 8
.limit stack 200
  nop
  aload_1
  getfield com/mobisage/android/b/d Landroid/os/Bundle;
  astore_2
  ldc "ResponseBody"
  astore 4
  new java/lang/NoClassDefFoundError
  dup
  invokespecial java/lang/NoClassDefFoundError/<init>()V
  athrow
  nop
  new org/json/JSONObject
  astore 5
Label2:
  aload 5
  aload_3
  invokespecial org/json/JSONObject/<init>(Ljava/lang/String;)V
  aload_0
  getfield com/mobisage/android/w$a/a Lcom/mobisage/android/w;
  astore 6
  aload 6
  aload 5
  invokestatic com/mobisage/android/w/a(Lcom/mobisage/android/w;Lorg/json/JSONObject;)Lorg/json/JSONObject;
  pop
Label0:
  return
Label1:
  astore 7
  goto Label0
  nop
.end <method>

.method public final b(Lcom/mobisage/android/b;)V
.limit locals 2
.limit stack 200
  nop
  return
  nop
.end <method>

