.source GetUserInfo.java
.class public  com/admogo/GetUserInfo
.super java/lang/Object

.method public <init>()V
.limit locals 1
.limit stack 200
  nop
  aload_0
  invokespecial java/lang/Object/<init>()V
  return
  nop
.end <method>

.method public static GetCPUInfo()Ljava/lang/String;
.limit locals 14
.limit stack 200
  .catch  java/io/IOException <from> Label5 <to> Label6 <using> Label4
  nop
  iconst_2
  istore_1
  iload_1
  anewarray java/lang/String
  astore_0
  iconst_0
  istore_1
  ldc "/system/bin/cat"
  astore_2
  aload_0
  iload_1
  aload_2
  aastore
  iconst_1
  istore_1
  ldc "/proc/cpuinfo"
  astore_2
  aload_0
  iload_1
  aload_2
  aastore
Label5:
  ldc "/system/bin/"
  astore_2
  aload_0
  aload_2
  invokestatic com/admogo/GetUserInfo/run([Ljava/lang/String;Ljava/lang/String;)Ljava/lang/String;
  astore_3
  ldc "\n"
  astore_2
  aload_3
  aload_2
  invokevirtual java/lang/String/split(Ljava/lang/String;)[Ljava/lang/String;
  astore 4
  iconst_0
  istore 5
  ldc ""
  astore_3
  iconst_0
  istore 6
Label3:
  aload 4
  arraylength
  istore 7
  new java/lang/NoClassDefFoundError
  dup
  invokespecial java/lang/NoClassDefFoundError/<init>()V
  athrow
  dload 7
  invokestatic app/DummyClass/invokeIfStmt(D)V
  iload 6
  iload 7
  if_icmplt Label0
  iload 5
  iconst_1
  iadd
  istore 7
  new java/lang/StringBuilder
  astore 8
  ldc "&cc="
  astore_2
  aload 8
  aload_2
  invokespecial java/lang/StringBuilder/<init>(Ljava/lang/String;)V
  aload 8
  iload 7
  invokevirtual java/lang/StringBuilder/append(I)Ljava/lang/StringBuilder;
  astore 8
  ldc "&cm="
  astore_2
  aload 8
  aload_2
  invokevirtual java/lang/StringBuilder/append(Ljava/lang/String;)Ljava/lang/StringBuilder;
  astore 8
  aload 8
  aload_3
  invokevirtual java/lang/StringBuilder/append(Ljava/lang/String;)Ljava/lang/StringBuilder;
  astore 8
  aload 8
  invokevirtual java/lang/StringBuilder/toString()Ljava/lang/String;
  astore 9
  aload 9
  areturn
Label0:
  aload 4
  iload 6
  aaload
  astore 9
  ldc "\t: "
  astore_2
  aload 9
  aload_2
  invokevirtual java/lang/String/split(Ljava/lang/String;)[Ljava/lang/String;
  astore_0
  iconst_0
  istore_1
  aload_0
  iload_1
  aaload
  astore 10
  ldc "processor"
  astore_2
  aload 10
  aload_2
  invokevirtual java/lang/String/equals(Ljava/lang/Object;)Z
  istore 11
  iload 11
  invokestatic app/DummyClass/invokeIfStmt(Z)V
  iload 11
  ifeq Label1
  iconst_1
  istore_1
  aload_0
  iload_1
  aaload
  astore 10
  aload 10
  invokestatic java/lang/Integer/parseInt(Ljava/lang/String;)I
  istore 5
Label1:
  iconst_0
  istore_1
  aload_0
  iload_1
  aaload
  astore 10
  ldc "BogoMIPS"
  astore_2
  aload 10
  aload_2
  invokevirtual java/lang/String/equals(Ljava/lang/Object;)Z
  istore 11
Label6:
  iload 11
  invokestatic app/DummyClass/invokeIfStmt(Z)V
  iload 11
  ifeq Label2
  iconst_1
  istore_1
  aload_0
  iload_1
  aaload
  astore_3
Label2:
  iload 6
  iconst_1
  iadd
  istore 6
  goto Label3
Label4:
  astore 12
  aload 12
  invokevirtual java/io/IOException/printStackTrace()V
  aconst_null
  astore 13
  aload 13
  areturn
  nop
.end <method>

.method public static getDeviceID(Landroid/content/Context;)Ljava/lang/String;
.limit locals 9
.limit stack 200
  nop
  ldc "phone"
  astore_2
  new java/lang/NoClassDefFoundError
  dup
  invokespecial java/lang/NoClassDefFoundError/<init>()V
  athrow
  nop
  aload_1
  astore 4
  aload 4
  checkcast android/telephony/TelephonyManager
  astore 4
  aload 4
  astore_3
  ldc ""
  astore 5
Label3:
  ldc "android.permission.READ_PHONE_STATE"
  astore_2
  aload_0
  aload_2
  invokestatic com/admogo/GetUserInfo/isPermission(Landroid/content/Context;Ljava/lang/String;)Z
  istore 6
  iload 6
  invokestatic app/DummyClass/invokeIfStmt(Z)V
  iload 6
  ifeq Label0
  aload_3
  invokevirtual android/telephony/TelephonyManager/getDeviceId()Ljava/lang/String;
  astore 7
Label4:
  aload 7
  astore 5
Label0:
  aload 5
  invokestatic android/text/TextUtils/isEmpty(Ljava/lang/CharSequence;)Z
  istore 6
  iload 6
  invokestatic app/DummyClass/invokeIfStmt(Z)V
  iload 6
  ifeq Label1
  getstatic com/admogo/util/AdMogoUtil/ADMOGO Ljava/lang/String;
  astore 7
  ldc "No IMEI"
  astore_2
  aload 7
  aload_2
  invokestatic android/util/Log/w(Ljava/lang/String;Ljava/lang/String;)I
  pop
  aload_0
  invokestatic com/admogo/GetUserInfo/getIDByMAC(Landroid/content/Context;)Ljava/lang/String;
  astore 5
  aload 5
  invokestatic app/DummyClass/invokeIfStmt(Ljava/lang/Object;)V
  aload 5
  ifnonnull Label1
  getstatic com/admogo/util/AdMogoUtil/ADMOGO Ljava/lang/String;
  astore 7
  ldc "Failed to take mac as IMEI"
  astore_2
  aload 7
  aload_2
  invokestatic android/util/Log/w(Ljava/lang/String;Ljava/lang/String;)I
  pop
  ldc ""
  astore_2
  aload_2
  areturn
Label2:
  astore 8
  aload 8
  invokevirtual java/lang/Exception/printStackTrace()V
  goto Label0
Label1:
  aload 5
  areturn
  nop
.end <method>

.method private static getIDByMAC(Landroid/content/Context;)Ljava/lang/String;
.limit locals 10
.limit stack 200
  .catch  java/lang/Exception <from> Label1 <to> Label2 <using> Label0
  nop
Label1:
  ldc "wifi"
  astore_2
  new java/lang/NoClassDefFoundError
  dup
  invokespecial java/lang/NoClassDefFoundError/<init>()V
  athrow
  nop
  aload_1
  astore 4
  aload 4
  checkcast android/net/wifi/WifiManager
  astore 4
  aload 4
  astore_3
  aload_3
  invokevirtual android/net/wifi/WifiManager/getConnectionInfo()Landroid/net/wifi/WifiInfo;
  astore 5
  aload 5
  invokevirtual android/net/wifi/WifiInfo/getMacAddress()Ljava/lang/String;
  astore 6
Label2:
  aload 6
  areturn
Label0:
  astore 7
  getstatic com/admogo/util/AdMogoUtil/ADMOGO Ljava/lang/String;
  astore 8
  ldc "Could not read MAC, forget to include ACCESS_WIFI_STATE permission?"
  astore_2
  new java/lang/NoClassDefFoundError
  dup
  invokespecial java/lang/NoClassDefFoundError/<init>()V
  athrow
  aconst_null
  astore 9
  aload 9
  areturn
  nop
.end <method>

.method public static getMemoryInfo(Landroid/content/Context;)Ljava/lang/String;
.limit locals 14
.limit stack 200
  nop
  ldc "activity"
  astore_2
  new java/lang/NoClassDefFoundError
  dup
  invokespecial java/lang/NoClassDefFoundError/<init>()V
  athrow
  nop
  aload_1
  astore 4
  aload 4
  checkcast android/app/ActivityManager
  astore 4
  aload 4
  astore_3
  new android/app/ActivityManager$MemoryInfo
  astore 5
  aload 5
  invokespecial android/app/ActivityManager$MemoryInfo/<init>()V
  aload_3
  aload 5
  invokevirtual android/app/ActivityManager/getMemoryInfo(Landroid/app/ActivityManager$MemoryInfo;)V
  iconst_2
  istore 7
  iload 7
  anewarray java/lang/String
  astore 6
  iconst_0
  istore 7
  ldc "/system/bin/cat"
  astore_2
  aload 6
  iload 7
  aload_2
  aastore
  iconst_1
  istore 7
  ldc "/proc/meminfo"
  astore_2
  aload 6
  iload 7
  aload_2
  aastore
Label1:
  ldc "/system/bin/"
  astore_2
  aload 6
  aload_2
  invokestatic com/admogo/GetUserInfo/run([Ljava/lang/String;Ljava/lang/String;)Ljava/lang/String;
  astore 8
  ldc "\n"
  astore_2
  aload 8
  aload_2
  invokevirtual java/lang/String/split(Ljava/lang/String;)[Ljava/lang/String;
  astore 6
  iconst_0
  istore 7
  aload 6
  iload 7
  aaload
  astore 9
  ldc ":"
  astore_2
  aload 9
  aload_2
  invokevirtual java/lang/String/split(Ljava/lang/String;)[Ljava/lang/String;
  astore 6
  iconst_1
  istore 7
  aload 6
  iload 7
  aaload
  astore 8
  ldc "\t"
  astore_2
  ldc ""
  astore 11
  aload 8
  aload_2
  aload 11
  invokevirtual java/lang/String/replace(Ljava/lang/CharSequence;Ljava/lang/CharSequence;)Ljava/lang/String;
  astore 10
  ldc " "
  astore_2
  ldc ""
  astore 11
  aload 10
  aload_2
  aload 11
  invokevirtual java/lang/String/replace(Ljava/lang/CharSequence;Ljava/lang/CharSequence;)Ljava/lang/String;
  astore 10
  aload 10
  invokevirtual java/lang/String/toLowerCase()Ljava/lang/String;
  astore 10
Label2:
  aload 10
  areturn
Label0:
  astore 12
  new java/lang/StringBuilder
  astore 13
  ldc "ex="
  astore_2
  aload 13
  aload_2
  invokespecial java/lang/StringBuilder/<init>(Ljava/lang/String;)V
  aload 12
  invokevirtual java/io/IOException/toString()Ljava/lang/String;
  astore 9
  aload 13
  aload 9
  invokevirtual java/lang/StringBuilder/append(Ljava/lang/String;)Ljava/lang/StringBuilder;
  astore 13
  aload 13
  invokevirtual java/lang/StringBuilder/toString()Ljava/lang/String;
  astore 9
  ldc "fetch_process_info"
  astore_2
  aload_2
  aload 9
  invokestatic android/util/Log/i(Ljava/lang/String;Ljava/lang/String;)I
  pop
  ldc ""
  astore_2
  aload_2
  areturn
  nop
.end <method>

.method public static getNetworkType(Landroid/content/Context;)Ljava/lang/String;
.limit locals 8
.limit stack 200
  nop
  ldc "connectivity"
  astore_2
  new java/lang/NoClassDefFoundError
  dup
  invokespecial java/lang/NoClassDefFoundError/<init>()V
  athrow
  nop
  aload_1
  astore 4
  aload 4
  checkcast android/net/ConnectivityManager
  astore 4
  aload 4
  astore_3
  aload_3
  invokevirtual android/net/ConnectivityManager/getActiveNetworkInfo()Landroid/net/NetworkInfo;
  astore 5
  aload 5
  invokestatic app/DummyClass/invokeIfStmt(Ljava/lang/Object;)V
  aload 5
  ifnull Label0
  aload 5
  invokevirtual android/net/NetworkInfo/getTypeName()Ljava/lang/String;
  astore 6
  ldc "mobile"
  astore_2
  aload 6
  aload_2
  invokevirtual java/lang/String/equalsIgnoreCase(Ljava/lang/String;)Z
  istore 7
  iload 7
  invokestatic app/DummyClass/invokeIfStmt(Z)V
  iload 7
  ifeq Label1
  ldc "1"
  astore 6
Label2:
  aload 6
  areturn
Label1:
  ldc "wifi"
  astore_2
  aload 6
  aload_2
  invokevirtual java/lang/String/equalsIgnoreCase(Ljava/lang/String;)Z
  istore 7
  iload 7
  invokestatic app/DummyClass/invokeIfStmt(Z)V
  iload 7
  ifeq Label2
  ldc "2"
  astore_2
  aload_2
  areturn
Label0:
  ldc "0"
  astore_2
  aload_2
  areturn
  nop
.end <method>

.method public static getOperators(Landroid/content/Context;)Ljava/lang/String;
.limit locals 7
.limit stack 200
  nop
  ldc "phone"
  astore_2
  new java/lang/NoClassDefFoundError
  dup
  invokespecial java/lang/NoClassDefFoundError/<init>()V
  athrow
  nop
  aload_1
  astore 4
  aload 4
  checkcast android/telephony/TelephonyManager
  astore 4
  aload 4
  astore_3
  aload_3
  invokevirtual android/telephony/TelephonyManager/getSimOperator()Ljava/lang/String;
  astore 5
  ldc ""
  astore_2
  aload 5
  aload_2
  invokevirtual java/lang/String/equals(Ljava/lang/Object;)Z
  istore 6
  iload 6
  invokestatic app/DummyClass/invokeIfStmt(Z)V
  iload 6
  ifne Label0
  aload 5
  invokestatic app/DummyClass/invokeIfStmt(Ljava/lang/Object;)V
  aload 5
  ifnonnull Label1
Label0:
  ldc "00000"
  astore 5
Label1:
  aload 5
  areturn
  nop
.end <method>

.method public static isPermission(Landroid/content/Context;Ljava/lang/String;)Z
.limit locals 6
.limit stack 200
  nop
  new java/lang/NoClassDefFoundError
  dup
  invokespecial java/lang/NoClassDefFoundError/<init>()V
  athrow
  nop
  aload_0
  invokevirtual android/content/Context/getPackageName()Ljava/lang/String;
  astore_3
  aload_2
  aload_1
  aload_3
  invokevirtual android/content/pm/PackageManager/checkPermission(Ljava/lang/String;Ljava/lang/String;)I
  istore 4
  dload 4
  invokestatic app/DummyClass/invokeIfStmt(D)V
  iload 4
  ifne Label0
  iconst_1
  istore 5
  iload 5
  ireturn
Label0:
  iconst_0
  istore 5
  iload 5
  ireturn
  nop
.end <method>

.method public static run([Ljava/lang/String;Ljava/lang/String;)Ljava/lang/String;
.limit locals 14
.limit stack 200
  .catch  java/lang/Throwable <from> Label5 <to> Label6 <using> Label4
  .catch  java/lang/Throwable <from> Label8 <to> Label2 <using> Label4
  .catch  java/lang/Exception <from> Label8 <to> Label2 <using> Label7
  .catch  java/lang/Throwable <from> Label9 <to> Label10 <using> Label4
  .catch  java/lang/Exception <from> Label9 <to> Label10 <using> Label7
  .catch  java/lang/Throwable <from> Label11 <to> Label12 <using> Label4
  nop
  ldc com/admogo/GetUserInfo
  astore_2
  aload_2
  monitorenter
Label5:
  ldc ""
  astore_3
Label6:
  new java/lang/ProcessBuilder
  astore 4
Label8:
  aload 4
  aload_0
  invokespecial java/lang/ProcessBuilder/<init>([Ljava/lang/String;)V
  new java/lang/NoClassDefFoundError
  dup
  invokespecial java/lang/NoClassDefFoundError/<init>()V
  athrow
  iload_1
  ifeq Label0
  new java/io/File
  astore 5
  aload 5
  aload_1
  invokespecial java/io/File/<init>(Ljava/lang/String;)V
  aload 4
  aload 5
  invokevirtual java/lang/ProcessBuilder/directory(Ljava/io/File;)Ljava/lang/ProcessBuilder;
  pop
Label0:
  iconst_1
  istore 6
  aload 4
  iload 6
  invokevirtual java/lang/ProcessBuilder/redirectErrorStream(Z)Ljava/lang/ProcessBuilder;
  pop
  aload 4
  invokevirtual java/lang/ProcessBuilder/start()Ljava/lang/Process;
  astore 7
  aload 7
  invokevirtual java/lang/Process/getInputStream()Ljava/io/InputStream;
  astore 8
  sipush 1024
  istore 6
  iload 6
  newarray byte
  astore 9
Label3:
  aload 8
  aload 9
  invokevirtual java/io/InputStream/read([B)I
  istore 10
  dload 10
  invokestatic app/DummyClass/invokeIfStmt(D)V
  iconst_m1
  istore 6
  iload 10
  iload 6
  if_icmpne Label1
  aload 8
  invokestatic app/DummyClass/invokeIfStmt(Ljava/lang/Object;)V
  aload 8
  ifnull Label2
  aload 8
  invokevirtual java/io/InputStream/close()V
Label2:
  ldc com/admogo/GetUserInfo
  astore_2
  aload_2
  monitorexit
  aload_3
  areturn
Label1:
  new java/lang/StringBuilder
  astore 11
Label9:
  aload_3
  invokestatic java/lang/String/valueOf(Ljava/lang/Object;)Ljava/lang/String;
  astore_1
  aload 11
  aload_1
  invokespecial java/lang/StringBuilder/<init>(Ljava/lang/String;)V
  new java/lang/String
  astore_1
  aload_1
  aload 9
  invokespecial java/lang/String/<init>([B)V
  aload 11
  aload_1
  invokevirtual java/lang/StringBuilder/append(Ljava/lang/String;)Ljava/lang/StringBuilder;
  astore 11
  aload 11
  invokevirtual java/lang/StringBuilder/toString()Ljava/lang/String;
  astore_1
Label10:
  aload_1
  astore_3
  goto Label3
Label7:
  astore 12
Label11:
  aload 12
  invokevirtual java/lang/Exception/printStackTrace()V
Label12:
  goto Label2
Label4:
  astore 13
  ldc com/admogo/GetUserInfo
  astore_2
  aload_2
  monitorexit
  aload 13
  athrow
  nop
.end <method>

