.source CaseeSourceAdapter.java
.class  com/admogo/adapters/CaseeSourceAdapter$FetchCaseeRunnable
.super java/lang/Object
.implements  java/lang/Runnable
.field private "adMogoLayout" Lcom/admogo/AdMogoLayout;
.field private "caseeAdAdapter" Lcom/admogo/adapters/CaseeSourceAdapter;
.field private "ration" Lcom/admogo/obj/Ration;

.method public <init>(Lcom/admogo/obj/Ration;Lcom/admogo/adapters/CaseeSourceAdapter;)V
.limit locals 3
.limit stack 200
  nop
  aload_0
  invokespecial java/lang/Object/<init>()V
  aload_0
  aload_1
  putfield com/admogo/adapters/CaseeSourceAdapter$FetchCaseeRunnable/ration Lcom/admogo/obj/Ration;
  aload_0
  aload_2
  putfield com/admogo/adapters/CaseeSourceAdapter$FetchCaseeRunnable/caseeAdAdapter Lcom/admogo/adapters/CaseeSourceAdapter;
  return
  nop
.end <method>

.method public run()V
.limit locals 12
.limit stack 200
  nop
  aload_0
  getfield com/admogo/adapters/CaseeSourceAdapter$FetchCaseeRunnable/caseeAdAdapter Lcom/admogo/adapters/CaseeSourceAdapter;
  astore_1
  aload_1
  getfield com/admogo/adapters/AdMogoAdapter/adMogoLayoutReference Ljava/lang/ref/WeakReference;
  astore_2
  aload_2
  invokevirtual java/lang/ref/WeakReference/get()Ljava/lang/Object;
  astore_3
  aload_3
  astore 5
  new java/lang/NoClassDefFoundError
  dup
  invokespecial java/lang/NoClassDefFoundError/<init>()V
  athrow
  aload 5
  astore 4
  aload_0
  aload 4
  putfield com/admogo/adapters/CaseeSourceAdapter$FetchCaseeRunnable/adMogoLayout Lcom/admogo/AdMogoLayout;
  aload_0
  getfield com/admogo/adapters/CaseeSourceAdapter$FetchCaseeRunnable/adMogoLayout Lcom/admogo/AdMogoLayout;
  astore 4
  aload 4
  invokestatic app/DummyClass/invokeIfStmt(Ljava/lang/Object;)V
  aload 4
  ifnonnull Label0
Label2:
  return
Label0:
  aload_0
  getfield com/admogo/adapters/CaseeSourceAdapter$FetchCaseeRunnable/adMogoLayout Lcom/admogo/AdMogoLayout;
  astore 4
  aload_0
  getfield com/admogo/adapters/CaseeSourceAdapter$FetchCaseeRunnable/ration Lcom/admogo/obj/Ration;
  astore 6
  aload 6
  getfield com/admogo/obj/Ration/key Ljava/lang/String;
  astore 7
  aload 4
  aload 7
  invokestatic com/admogo/adapters/CaseeSourceAdapter/access$0(Lcom/admogo/AdMogoLayout;Ljava/lang/String;)Lcom/admogo/obj/CaseeAD;
  astore 8
  aload 8
  invokestatic com/admogo/adapters/CaseeSourceAdapter/access$1(Lcom/admogo/obj/CaseeAD;)V
  invokestatic com/admogo/adapters/CaseeSourceAdapter/access$2()Lcom/admogo/obj/CaseeAD;
  astore 8
  aload 8
  invokestatic app/DummyClass/invokeIfStmt(Ljava/lang/Object;)V
  aload 8
  ifnonnull Label1
  aload_0
  getfield com/admogo/adapters/CaseeSourceAdapter$FetchCaseeRunnable/adMogoLayout Lcom/admogo/AdMogoLayout;
  astore 4
  aload 4
  invokevirtual com/admogo/AdMogoLayout/rollover()V
  goto Label2
Label1:
  getstatic com/admogo/util/AdMogoUtil/ADMOGO Ljava/lang/String;
  astore 7
  ldc "CaseeAD load success"
  astore 9
  aload 7
  aload 9
  invokestatic android/util/Log/d(Ljava/lang/String;Ljava/lang/String;)I
  pop
  aload_0
  getfield com/admogo/adapters/CaseeSourceAdapter$FetchCaseeRunnable/adMogoLayout Lcom/admogo/AdMogoLayout;
  astore 4
  aload 4
  getfield com/admogo/AdMogoLayout/handler Landroid/os/Handler;
  astore 10
  new com/admogo/adapters/CaseeSourceAdapter$DisplayCaseeADRunnable
  astore 11
  aload_0
  getfield com/admogo/adapters/CaseeSourceAdapter$FetchCaseeRunnable/caseeAdAdapter Lcom/admogo/adapters/CaseeSourceAdapter;
  astore_1
  aload 11
  aload_1
  invokespecial com/admogo/adapters/CaseeSourceAdapter$DisplayCaseeADRunnable/<init>(Lcom/admogo/adapters/CaseeSourceAdapter;)V
  aload 10
  aload 11
  invokevirtual android/os/Handler/post(Ljava/lang/Runnable;)Z
  pop
  goto Label2
  nop
.end <method>

