.source CryptUtils.java
.class public  com/admogo/encryption/CryptUtils
.super java/lang/Object

.method public <init>()V
.limit locals 1
.limit stack 200
  nop
  aload_0
  invokespecial java/lang/Object/<init>()V
  return
  nop
.end <method>

.method public static decrypt(Ljava/lang/String;Ljava/lang/String;Z)Ljava/lang/String;
.limit locals 5
.limit stack 200
  nop
  new java/lang/String
  astore_3
  aload_0
  aload_1
  invokestatic com/admogo/encryption/CryptUtils/decrypt(Ljava/lang/String;Ljava/lang/String;)[B
  astore 4
  aload_3
  aload 4
  invokespecial java/lang/String/<init>([B)V
  aload_3
  areturn
  nop
.end <method>

.method public static decrypt(Ljava/lang/String;Ljava/lang/String;)[B
.limit locals 12
.limit stack 200
  .catch  java/security/InvalidKeyException <from> Label3 <to> Label4 <using> Label1
  .catch  java/security/NoSuchAlgorithmException <from> Label3 <to> Label4 <using> Label2
  nop
  new javax/crypto/spec/SecretKeySpec
  astore_2
Label3:
  aload_1
  invokevirtual java/lang/String/getBytes()[B
  astore_3
  ldc "DES"
  astore 4
  aload_2
  aload_3
  aload 4
  invokespecial javax/crypto/spec/SecretKeySpec/<init>([BLjava/lang/String;)V
  ldc "DES"
  astore 4
  aload 4
  invokestatic javax/crypto/Cipher/getInstance(Ljava/lang/String;)Ljavax/crypto/Cipher;
  astore 5
  aload_0
  invokestatic com/admogo/encryption/Base64/decode(Ljava/lang/String;)[B
  astore_3
  aload_2
  astore 7
  aload 7
  checkcast java/security/Key
  astore 7
  aload 7
  astore 6
  iconst_2
  istore 8
  aload 5
  iload 8
  aload 6
  invokevirtual javax/crypto/Cipher/init(ILjava/security/Key;)V
  aload 5
  aload_3
  invokevirtual javax/crypto/Cipher/doFinal([B)[B
  astore_3
Label4:
  aload_3
  areturn
Label2:
  astore 9
  aload 9
  invokevirtual java/security/NoSuchAlgorithmException/printStackTrace()V
Label0:
  aconst_null
  astore 10
  aload 10
  areturn
Label1:
  astore 11
  aload 11
  invokevirtual java/security/InvalidKeyException/printStackTrace()V
  goto Label0
  nop
.end <method>

.method public static encrypt(Ljava/lang/String;Ljava/lang/String;Z)Ljava/lang/String;
.limit locals 4
.limit stack 200
  nop
  aload_0
  aload_1
  invokestatic com/admogo/encryption/CryptUtils/encrypt(Ljava/lang/String;Ljava/lang/String;)[B
  astore_3
  aload_3
  iload_2
  invokestatic com/admogo/encryption/Base64/encodeToString([BZ)Ljava/lang/String;
  astore_1
  aload_1
  areturn
  nop
.end <method>

.method public static encrypt(Ljava/lang/String;Ljava/lang/String;)[B
.limit locals 13
.limit stack 200
  .catch  java/io/UnsupportedEncodingException <from> Label4 <to> Label5 <using> Label1
  .catch  java/security/InvalidKeyException <from> Label4 <to> Label5 <using> Label2
  .catch  java/security/NoSuchAlgorithmException <from> Label4 <to> Label5 <using> Label3
  nop
  new javax/crypto/spec/SecretKeySpec
  astore_2
Label4:
  aload_1
  invokevirtual java/lang/String/getBytes()[B
  astore_3
  ldc "DES"
  astore 4
  aload_2
  aload_3
  aload 4
  invokespecial javax/crypto/spec/SecretKeySpec/<init>([BLjava/lang/String;)V
  ldc "DES"
  astore 4
  aload 4
  invokestatic javax/crypto/Cipher/getInstance(Ljava/lang/String;)Ljavax/crypto/Cipher;
  astore 5
  ldc "utf-8"
  astore 4
  aload_0
  aload 4
  invokevirtual java/lang/String/getBytes(Ljava/lang/String;)[B
  astore_3
  aload_2
  astore 7
  aload 7
  checkcast java/security/Key
  astore 7
  aload 7
  astore 6
  iconst_1
  istore 8
  aload 5
  iload 8
  aload 6
  invokevirtual javax/crypto/Cipher/init(ILjava/security/Key;)V
  aload 5
  aload_3
  invokevirtual javax/crypto/Cipher/doFinal([B)[B
  astore_3
Label5:
  aload_3
  areturn
Label3:
  astore 9
  aload 9
  invokevirtual java/security/NoSuchAlgorithmException/printStackTrace()V
Label0:
  aconst_null
  astore 10
  aload 10
  areturn
Label2:
  astore 11
  aload 11
  invokevirtual java/security/InvalidKeyException/printStackTrace()V
  goto Label0
Label1:
  astore 12
  aload 12
  invokevirtual java/io/UnsupportedEncodingException/printStackTrace()V
  goto Label0
  nop
.end <method>

.method public static getString(Ljava/lang/String;)Ljava/lang/String;
.limit locals 7
.limit stack 200
  nop
  iconst_0
  istore_2
  iconst_4
  istore_3
  aload_0
  iload_2
  iload_3
  invokevirtual java/lang/String/substring(II)Ljava/lang/String;
  astore_1
  aload_0
  invokevirtual java/lang/String/length()I
  istore 4
  iload 4
  bipush -4
  iadd
  istore 4
  aload_0
  invokevirtual java/lang/String/length()I
  istore 5
  aload_0
  iload 4
  iload 5
  invokevirtual java/lang/String/substring(II)Ljava/lang/String;
  astore_0
  new java/lang/StringBuilder
  astore 6
  aload_1
  invokestatic java/lang/String/valueOf(Ljava/lang/Object;)Ljava/lang/String;
  astore_1
  aload 6
  aload_1
  invokespecial java/lang/StringBuilder/<init>(Ljava/lang/String;)V
  aload 6
  aload_0
  invokevirtual java/lang/StringBuilder/append(Ljava/lang/String;)Ljava/lang/StringBuilder;
  astore 6
  aload 6
  invokevirtual java/lang/StringBuilder/toString()Ljava/lang/String;
  astore_1
  aload_1
  areturn
  nop
.end <method>

