.source dalvik_source_VirusShare_32e70f448ebd75661a1cb12f9cd8e013.apk
.class public  com/kuguo/b/b
.super java/lang/Object
.field private "a" Z
.field private "b" Ljava/util/List;

.method public <init>()V
.limit locals 3
.limit stack 200
  nop
  aload_0
  invokespecial java/lang/Object/<init>()V
  iconst_0
  istore_1
  aload_0
  iload_1
  putfield com/kuguo/b/b/a Z
  new java/util/ArrayList
  astore_2
  aload_2
  invokespecial java/util/ArrayList/<init>()V
  aload_0
  aload_2
  putfield com/kuguo/b/b/b Ljava/util/List;
  iconst_1
  istore_1
  aload_0
  iload_1
  invokevirtual com/kuguo/b/b/a(I)V
  return
  nop
.end <method>

.method private a()Lcom/kuguo/b/e;
.limit locals 10
.limit stack 200
  nop
  iconst_0
  istore_1
  aload_0
  getfield com/kuguo/b/b/b Ljava/util/List;
  astore_2
  aload_2
  invokeinterface java/util/List/iterator()Ljava/util/Iterator; 1
  astore_3
Label3:
  aload_3
  invokeinterface java/util/Iterator/hasNext()Z 1
  istore 4
  new java/lang/NoClassDefFoundError
  dup
  invokespecial java/lang/NoClassDefFoundError/<init>()V
  athrow
  iload 4
  ifeq Label0
  aload_3
  invokeinterface java/util/Iterator/next()Ljava/lang/Object; 1
  astore 5
  aload 5
  astore 7
  aload 7
  checkcast com/kuguo/b/e
  astore 7
  aload 7
  astore 6
  aload 6
  invokevirtual com/kuguo/b/e/a()V
  aload_1
  invokestatic app/DummyClass/invokeIfStmt(Ljava/lang/Object;)V
  iload_1
  ifeq Label1
  aload 6
  invokevirtual com/kuguo/b/e/size()I
  istore 8
  aload_1
  invokevirtual com/kuguo/b/e/size()I
  istore 9
  dload 8
  invokestatic app/DummyClass/invokeIfStmt(D)V
  dload 9
  invokestatic app/DummyClass/invokeIfStmt(D)V
  iload 8
  iload 9
  if_icmpge Label2
Label1:
  aload 6
  astore_1
  goto Label3
Label0:
  aload_1
  areturn
Label2:
  aload_1
  astore 6
  goto Label1
  nop
.end <method>

.method public a(I)V
.limit locals 5
.limit stack 200
  nop
  aload_0
  getfield com/kuguo/b/b/b Ljava/util/List;
  astore_2
  aload_2
  invokeinterface java/util/List/size()I 1
  istore_3
  new java/lang/NoClassDefFoundError
  dup
  invokespecial java/lang/NoClassDefFoundError/<init>()V
  athrow
  dload_1
  invokestatic app/DummyClass/invokeIfStmt(D)V
  iload_3
  iload_1
  if_icmpge Label0
  aload_0
  getfield com/kuguo/b/b/b Ljava/util/List;
  astore_2
  aload_2
  invokeinterface java/util/List/size()I 1
  istore_3
  iload_1
  iload_3
  isub
  istore_1
  iconst_0
  dstore_3
Label1:
  dload_3
  invokestatic app/DummyClass/invokeIfStmt(D)V
  dload_1
  invokestatic app/DummyClass/invokeIfStmt(D)V
  iload_3
  iload_1
  if_icmpge Label0
  new com/kuguo/b/e
  astore 4
  aload 4
  aload_0
  invokespecial com/kuguo/b/e/<init>(Lcom/kuguo/b/b;)V
  aload_0
  getfield com/kuguo/b/b/b Ljava/util/List;
  astore_2
  aload_2
  aload 4
  invokeinterface java/util/List/add(Ljava/lang/Object;)Z 2
  pop
  iload_3
  iconst_1
  iadd
  istore_3
  goto Label1
Label0:
  return
  nop
.end <method>

.method static a(Lcom/kuguo/b/b;Lcom/kuguo/b/d;)V
  .synthetic
.limit locals 2
.limit stack 200
  nop
  aload_0
  aload_1
  invokespecial com/kuguo/b/b/b(Lcom/kuguo/b/d;)V
  return
  nop
.end <method>

.method public a(Lcom/kuguo/b/d;)V
.limit locals 5
.limit stack 200
  nop
  iconst_m1
  istore_2
  aload_1
  iload_2
  invokevirtual com/kuguo/b/d/a(I)V
  aload_0
  getfield com/kuguo/b/b/a Z
  istore_3
  new java/lang/NoClassDefFoundError
  dup
  invokespecial java/lang/NoClassDefFoundError/<init>()V
  athrow
  iload_3
  ifeq Label0
  aload_0
  aload_1
  invokespecial com/kuguo/b/b/b(Lcom/kuguo/b/d;)V
Label1:
  return
Label0:
  aload_0
  invokespecial com/kuguo/b/b/a()Lcom/kuguo/b/e;
  astore 4
  aload 4
  invokestatic app/DummyClass/invokeIfStmt(Ljava/lang/Object;)V
  aload 4
  ifnull Label1
  aload 4
  aload_1
  invokevirtual com/kuguo/b/e/a(Lcom/kuguo/b/d;)Z
  pop
  goto Label1
  nop
.end <method>

.method private b(Lcom/kuguo/b/d;)V
.limit locals 2
.limit stack 200
  nop
  aload_1
  invokevirtual com/kuguo/b/d/a()V
  return
  nop
.end <method>

