.source dalvik_source_VirusShare_32e70f448ebd75661a1cb12f9cd8e013.apk
.class  com/kuguo/b/f
.super java/lang/Thread
.field final "a" Lcom/kuguo/b/e;

.method <init>(Lcom/kuguo/b/e;)V
.limit locals 2
.limit stack 200
  nop
  aload_0
  aload_1
  putfield com/kuguo/b/f/a Lcom/kuguo/b/e;
  aload_0
  invokespecial java/lang/Thread/<init>()V
  return
  nop
.end <method>

.method public run()V
.limit locals 9
.limit stack 200
  nop
Label2:
  aload_0
  getfield com/kuguo/b/f/a Lcom/kuguo/b/e;
  astore_1
  aload_1
  invokevirtual com/kuguo/b/e/peek()Ljava/lang/Object;
  astore_2
  aload_2
  astore 4
  aload 4
  checkcast com/kuguo/b/d
  astore 4
  aload 4
  astore_3
  new java/lang/NoClassDefFoundError
  dup
  invokespecial java/lang/NoClassDefFoundError/<init>()V
  athrow
  iload_3
  ifne Label0
  aload_0
  getfield com/kuguo/b/f/a Lcom/kuguo/b/e;
  astore_1
  aconst_null
  astore 5
  aload_1
  aload 5
  invokestatic com/kuguo/b/e/a(Lcom/kuguo/b/e;Ljava/lang/Thread;)Ljava/lang/Thread;
  pop
  return
Label0:
  aload_3
  invokevirtual com/kuguo/b/d/h()I
  istore 6
  dload 6
  invokestatic app/DummyClass/invokeIfStmt(D)V
  iconst_m1
  istore 7
  iload 6
  iload 7
  if_icmpne Label1
  aload_0
  getfield com/kuguo/b/f/a Lcom/kuguo/b/e;
  astore_1
  aload_1
  getfield com/kuguo/b/e/a Lcom/kuguo/b/b;
  astore 8
  aload 8
  aload_3
  invokestatic com/kuguo/b/b/a(Lcom/kuguo/b/b;Lcom/kuguo/b/d;)V
Label1:
  aload_0
  getfield com/kuguo/b/f/a Lcom/kuguo/b/e;
  astore_1
  aload_1
  invokevirtual com/kuguo/b/e/poll()Ljava/lang/Object;
  pop
  goto Label2
  nop
.end <method>

