.source SourceFile
.class public final  com/adwo/adsdk/X
.super java/lang/Object

.method static <clinit>()V
.limit locals 3
.limit stack 200
  nop
  iconst_4
  istore_1
  iload_1
  newarray byte
  astore_0
  iconst_0
  istore_1
  bipush 20
  istore_2
  aload_0
  iload_1
  iload_2
  bastore
  iconst_1
  istore_1
  bipush 10
  istore_2
  aload_0
  iload_1
  iload_2
  bastore
  iconst_2
  istore_1
  iconst_1
  istore_2
  aload_0
  iload_1
  iload_2
  bastore
  iconst_3
  istore_1
  bipush 20
  istore_2
  aload_0
  iload_1
  iload_2
  bastore
  return
  nop
.end <method>

.method public <init>()V
.limit locals 1
.limit stack 200
  nop
  aload_0
  invokespecial java/lang/Object/<init>()V
  return
  nop
.end <method>

.method private static a([BI)I
.limit locals 7
.limit stack 200
  nop
  iload_1
  iconst_0
  iadd
  istore_2
  aload_0
  iload_2
  baload
  istore_3
  sipush 255
  istore 5
  iload_3
  iload 5
  iand
  istore 4
  iload 4
  bipush 24
  ishl
  istore_2
  iload_2
  iconst_0
  iadd
  istore 6
  iload_1
  iconst_1
  iadd
  istore_2
  aload_0
  iload_2
  baload
  istore_3
  sipush 255
  istore 5
  iload_3
  iload 5
  iand
  istore 4
  iload 4
  bipush 16
  ishl
  istore_2
  iload 6
  iload_2
  iadd
  istore 6
  iload_1
  iconst_2
  iadd
  istore_2
  aload_0
  iload_2
  baload
  istore_3
  sipush 255
  istore 5
  iload_3
  iload 5
  iand
  istore 4
  iload 4
  bipush 8
  ishl
  istore_2
  iload 6
  iload_2
  iadd
  istore 6
  iload_1
  iconst_3
  iadd
  istore_2
  aload_0
  iload_2
  baload
  istore_3
  sipush 255
  istore 5
  iload_3
  iload 5
  iand
  istore 4
  iload 4
  iconst_0
  ishl
  istore_2
  iload 6
  iload_2
  iadd
  istore 6
  iload 6
  ireturn
  nop
.end <method>

.method protected static a([B)Lcom/adwo/adsdk/FSAd;
.limit locals 33
.limit stack 200
  nop
  bipush 9
  istore 5
  iconst_0
  istore 6
  new java/lang/NoClassDefFoundError
  dup
  invokespecial java/lang/NoClassDefFoundError/<init>()V
  athrow
  aload 7
  invokespecial com/adwo/adsdk/FSAd/<init>()V
  aload_0
  astore_1
  aload_1
  arraylength
  istore 8
  dload 8
  invokestatic app/DummyClass/invokeIfStmt(D)V
  iconst_1
  istore 9
  iload 8
  iload 9
  if_icmpne Label0
  iconst_0
  istore 9
  aload_0
  iload 9
  baload
  istore 10
  dload 10
  invokestatic app/DummyClass/invokeIfStmt(D)V
  bipush -29
  istore 9
  iload 10
  iload 9
  if_icmpne Label1
  ldc "Adwo SDK"
  astore 11
  ldc "Adwo_Pid inexist"
  astore 12
  aload 11
  aload 12
  invokestatic android/util/Log/e(Ljava/lang/String;Ljava/lang/String;)I
  pop
  new com/adwo/adsdk/ErrorCode
  astore 13
  iconst_0
  istore 9
  aload_0
  iload 9
  baload
  istore 10
  ldc "ERR_INEXIST_PID"
  astore 11
  aload 13
  iload 10
  aload 11
  invokespecial com/adwo/adsdk/ErrorCode/<init>(ILjava/lang/String;)V
Label3:
  aload 7
  aload 13
  invokevirtual com/adwo/adsdk/FSAd/setError(Lcom/adwo/adsdk/ErrorCode;)V
  aload 7
  areturn
Label1:
  iconst_0
  istore 9
  aload_0
  iload 9
  baload
  istore 10
  dload 10
  invokestatic app/DummyClass/invokeIfStmt(D)V
  bipush -32
  istore 9
  iload 10
  iload 9
  if_icmpne Label2
  ldc "Adwo SDK"
  astore 11
  ldc "Server busy"
  astore 12
  aload 11
  aload 12
  invokestatic android/util/Log/e(Ljava/lang/String;Ljava/lang/String;)I
  pop
  new com/adwo/adsdk/ErrorCode
  astore 13
  iconst_0
  istore 9
  aload_0
  iload 9
  baload
  istore 10
  ldc "ERR_SERVERBUSY"
  astore 11
  aload 13
  iload 10
  aload 11
  invokespecial com/adwo/adsdk/ErrorCode/<init>(ILjava/lang/String;)V
  goto Label3
Label2:
  iconst_0
  istore 9
  aload_0
  iload 9
  baload
  istore 10
  dload 10
  invokestatic app/DummyClass/invokeIfStmt(D)V
  bipush -28
  istore 9
  iload 10
  iload 9
  if_icmpne Label4
  ldc "Adwo SDK"
  astore 11
  ldc "Adwo_Pid inactive"
  astore 12
  aload 11
  aload 12
  invokestatic android/util/Log/e(Ljava/lang/String;Ljava/lang/String;)I
  pop
  new com/adwo/adsdk/ErrorCode
  astore 13
  iconst_0
  istore 9
  aload_0
  iload 9
  baload
  istore 10
  ldc "ERR_INACTIVATED_PID"
  astore 11
  aload 13
  iload 10
  aload 11
  invokespecial com/adwo/adsdk/ErrorCode/<init>(ILjava/lang/String;)V
  goto Label3
Label4:
  iconst_0
  istore 9
  aload_0
  iload 9
  baload
  istore 10
  dload 10
  invokestatic app/DummyClass/invokeIfStmt(D)V
  bipush -31
  istore 9
  iload 10
  iload 9
  if_icmpeq Label5
  iconst_0
  istore 9
  aload_0
  iload 9
  baload
  istore 10
  dload 10
  invokestatic app/DummyClass/invokeIfStmt(D)V
  bipush -24
  istore 9
  iload 10
  iload 9
  if_icmpne Label6
Label5:
  new java/lang/StringBuilder
  astore 14
  ldc "No ad available: "
  astore 11
  aload 14
  aload 11
  invokespecial java/lang/StringBuilder/<init>(Ljava/lang/String;)V
  iconst_0
  istore 9
  aload_0
  iload 9
  baload
  istore 10
  aload 14
  iload 10
  invokevirtual java/lang/StringBuilder/append(I)Ljava/lang/StringBuilder;
  astore 14
  aload 14
  invokevirtual java/lang/StringBuilder/toString()Ljava/lang/String;
  astore 15
  ldc "Adwo SDK"
  astore 11
  aload 11
  aload 15
  invokestatic android/util/Log/e(Ljava/lang/String;Ljava/lang/String;)I
  pop
  new com/adwo/adsdk/ErrorCode
  astore 13
  iconst_0
  istore 9
  aload_0
  iload 9
  baload
  istore 10
  ldc "ERR_NOAD_IP"
  astore 11
  aload 13
  iload 10
  aload 11
  invokespecial com/adwo/adsdk/ErrorCode/<init>(ILjava/lang/String;)V
  goto Label3
Label6:
  iconst_0
  istore 9
  aload_0
  iload 9
  baload
  istore 10
  dload 10
  invokestatic app/DummyClass/invokeIfStmt(D)V
  bipush -23
  istore 9
  iload 10
  iload 9
  if_icmpne Label7
  new java/lang/StringBuilder
  astore 14
  ldc "No ad available: "
  astore 11
  aload 14
  aload 11
  invokespecial java/lang/StringBuilder/<init>(Ljava/lang/String;)V
  iconst_0
  istore 9
  aload_0
  iload 9
  baload
  istore 10
  aload 14
  iload 10
  invokevirtual java/lang/StringBuilder/append(I)Ljava/lang/StringBuilder;
  astore 14
  aload 14
  invokevirtual java/lang/StringBuilder/toString()Ljava/lang/String;
  astore 15
  ldc "Adwo SDK"
  astore 11
  aload 11
  aload 15
  invokestatic android/util/Log/e(Ljava/lang/String;Ljava/lang/String;)I
  pop
  new com/adwo/adsdk/ErrorCode
  astore 13
  iconst_0
  istore 9
  aload_0
  iload 9
  baload
  istore 10
  ldc "ERR_NOAD_LOWRANK"
  astore 11
  aload 13
  iload 10
  aload 11
  invokespecial com/adwo/adsdk/ErrorCode/<init>(ILjava/lang/String;)V
  goto Label3
Label7:
  iconst_0
  istore 9
  aload_0
  iload 9
  baload
  istore 10
  dload 10
  invokestatic app/DummyClass/invokeIfStmt(D)V
  bipush -25
  istore 9
  iload 10
  iload 9
  if_icmpne Label8
  new java/lang/StringBuilder
  astore 14
  ldc "No ad available: "
  astore 11
  aload 14
  aload 11
  invokespecial java/lang/StringBuilder/<init>(Ljava/lang/String;)V
  iconst_0
  istore 9
  aload_0
  iload 9
  baload
  istore 10
  aload 14
  iload 10
  invokevirtual java/lang/StringBuilder/append(I)Ljava/lang/StringBuilder;
  astore 14
  aload 14
  invokevirtual java/lang/StringBuilder/toString()Ljava/lang/String;
  astore 15
  ldc "Adwo SDK"
  astore 11
  aload 11
  aload 15
  invokestatic android/util/Log/e(Ljava/lang/String;Ljava/lang/String;)I
  pop
  new com/adwo/adsdk/ErrorCode
  astore 13
  iconst_0
  istore 9
  aload_0
  iload 9
  baload
  istore 10
  ldc "ERR_NOAD_IP"
  astore 11
  aload 13
  iload 10
  aload 11
  invokespecial com/adwo/adsdk/ErrorCode/<init>(ILjava/lang/String;)V
  goto Label3
Label8:
  iconst_0
  istore 9
  aload_0
  iload 9
  baload
  istore 10
  dload 10
  invokestatic app/DummyClass/invokeIfStmt(D)V
  bipush -30
  istore 9
  iload 10
  iload 9
  if_icmpne Label9
  ldc "Adwo SDK"
  astore 11
  ldc "Unknown Error"
  astore 12
  aload 11
  aload 12
  invokestatic android/util/Log/e(Ljava/lang/String;Ljava/lang/String;)I
  pop
  new com/adwo/adsdk/ErrorCode
  astore 13
  iconst_0
  istore 9
  aload_0
  iload 9
  baload
  istore 10
  ldc "ERR_UNKNOWN"
  astore 11
  aload 13
  iload 10
  aload 11
  invokespecial com/adwo/adsdk/ErrorCode/<init>(ILjava/lang/String;)V
  goto Label3
Label9:
  iconst_0
  istore 9
  aload_0
  iload 9
  baload
  istore 10
  dload 10
  invokestatic app/DummyClass/invokeIfStmt(D)V
  bipush -26
  istore 9
  iload 10
  iload 9
  if_icmpne Label10
  ldc "Adwo SDK"
  astore 11
  ldc "Error in receiving data"
  astore 12
  aload 11
  aload 12
  invokestatic android/util/Log/e(Ljava/lang/String;Ljava/lang/String;)I
  pop
  new com/adwo/adsdk/ErrorCode
  astore 13
  iconst_0
  istore 9
  aload_0
  iload 9
  baload
  istore 10
  ldc "ERR_INCOMM"
  astore 11
  aload 13
  iload 10
  aload 11
  invokespecial com/adwo/adsdk/ErrorCode/<init>(ILjava/lang/String;)V
  goto Label3
Label10:
  iconst_0
  istore 9
  aload_0
  iload 9
  baload
  istore 10
  dload 10
  invokestatic app/DummyClass/invokeIfStmt(D)V
  bipush -27
  istore 9
  iload 10
  iload 9
  if_icmpne Label11
  ldc "Adwo SDK"
  astore 11
  ldc "Error in request data"
  astore 12
  aload 11
  aload 12
  invokestatic android/util/Log/e(Ljava/lang/String;Ljava/lang/String;)I
  pop
  new com/adwo/adsdk/ErrorCode
  astore 13
  iconst_0
  istore 9
  aload_0
  iload 9
  baload
  istore 10
  ldc "ERR_REQDATA"
  astore 11
  aload 13
  iload 10
  aload 11
  invokespecial com/adwo/adsdk/ErrorCode/<init>(ILjava/lang/String;)V
  goto Label3
Label11:
  new java/lang/StringBuilder
  astore 14
  ldc "Unknown Error "
  astore 11
  aload 14
  aload 11
  invokespecial java/lang/StringBuilder/<init>(Ljava/lang/String;)V
  iconst_0
  istore 9
  aload_0
  iload 9
  baload
  istore 10
  aload 14
  iload 10
  invokevirtual java/lang/StringBuilder/append(I)Ljava/lang/StringBuilder;
  astore 14
  aload 14
  invokevirtual java/lang/StringBuilder/toString()Ljava/lang/String;
  astore 15
  ldc "Adwo SDK"
  astore 11
  aload 11
  aload 15
  invokestatic android/util/Log/e(Ljava/lang/String;Ljava/lang/String;)I
  pop
  new com/adwo/adsdk/ErrorCode
  astore 13
  iconst_0
  istore 9
  aload_0
  iload 9
  baload
  istore 10
  ldc "OTHER_ERROR"
  astore 11
  aload 13
  iload 10
  aload 11
  invokespecial com/adwo/adsdk/ErrorCode/<init>(ILjava/lang/String;)V
  goto Label3
Label0:
  aload_0
  astore_1
  aload_1
  arraylength
  istore 8
  dload 8
  invokestatic app/DummyClass/invokeIfStmt(D)V
  bipush 7
  istore 9
  iload 8
  iload 9
  if_icmpge Label12
  new com/adwo/adsdk/ErrorCode
  astore 13
  iconst_0
  istore 9
  aload_0
  iload 9
  baload
  istore 10
  ldc "ERR_INCOMM"
  astore 11
  aload 13
  iload 10
  aload 11
  invokespecial com/adwo/adsdk/ErrorCode/<init>(ILjava/lang/String;)V
  ldc "Adwo SDK"
  astore 11
  ldc "Error in receiving data"
  astore 12
  aload 11
  aload 12
  invokestatic android/util/Log/e(Ljava/lang/String;Ljava/lang/String;)I
  pop
  aload 7
  aload 13
  invokevirtual com/adwo/adsdk/FSAd/setError(Lcom/adwo/adsdk/ErrorCode;)V
  aload 7
  areturn
Label12:
  new com/adwo/adsdk/FSAd
  astore 7
  aload 7
  invokespecial com/adwo/adsdk/FSAd/<init>()V
  iconst_0
  istore 9
  aload_0
  astore_1
  aload_1
  iload 9
  invokestatic com/adwo/adsdk/X/a([BI)I
  istore 8
  aload 7
  iload 8
  putfield com/adwo/adsdk/FSAd/a I
  bipush 7
  istore 9
  aload_0
  iload 9
  baload
  istore 16
  bipush 8
  istore 9
  aload_0
  iload 9
  baload
  istore 17
  iload 17
  istore_1
  iload 16
  iload_1
  invokestatic com/adwo/adsdk/X/a(BB)S
  istore 18
  new java/lang/String
  astore 19
Label34:
  bipush 9
  istore 9
  ldc "UTF-8"
  astore 11
  aload 19
  astore_1
  aload_0
  astore_2
  iload 18
  istore_3
  aload_1
  aload_2
  iload 9
  iload_3
  aload 11
  invokespecial java/lang/String/<init>([BIILjava/lang/String;)V
Label35:
  aload 19
  astore_1
  aload 7
  aload_1
  putfield com/adwo/adsdk/FSAd/c Ljava/lang/String;
  iload 18
  bipush 9
  iadd
  istore 5
Label24:
  iload 5
  iconst_1
  iadd
  istore 8
  aload_0
  iload 5
  baload
  istore 17
  iload 17
  istore_1
  aload 7
  iload_1
  putfield com/adwo/adsdk/FSAd/e B
  iload 8
  iconst_1
  iadd
  istore 5
  aload_0
  iload 8
  baload
  istore 17
  iload 17
  istore_1
  dload_1
  invokestatic app/DummyClass/invokeIfStmt(D)V
  bipush -95
  istore 9
  iload 17
  istore_1
  iload_1
  iload 9
  if_icmpne Label13
  iload 5
  iconst_1
  iadd
  istore 8
  aload_0
  iload 5
  baload
  istore 17
  sipush 255
  istore 9
  iload 17
  iload 9
  iand
  istore 18
  iload 18
  istore_1
  iload_1
  i2s
  istore_1
  iload_1
  istore 18
  dload_1
  invokestatic app/DummyClass/invokeIfStmt(D)V
  iload 18
  ifeq Label14
  new java/lang/String
  astore 19
Label37:
  ldc "UTF-8"
  astore 11
  aload 19
  astore_1
  aload_0
  astore_2
  iload 18
  istore_3
  aload_1
  aload_2
  iload 8
  iload_3
  aload 11
  invokespecial java/lang/String/<init>([BIILjava/lang/String;)V
  aload 19
  astore_1
  aload 7
  aload_1
  putfield com/adwo/adsdk/FSAd/b Ljava/lang/String;
Label38:
  iload 18
  istore_1
  iload 8
  iload_1
  iadd
  istore 8
Label14:
  iload 8
  iconst_1
  iadd
  istore 5
  aload_0
  iload 8
  baload
  istore 17
  iload 17
  istore_1
  dload_1
  invokestatic app/DummyClass/invokeIfStmt(D)V
  bipush -94
  istore 9
  iload 17
  istore_1
  iload_1
  iload 9
  if_icmpne Label15
  iload 5
  iconst_1
  iadd
  istore 8
  aload_0
  iload 5
  baload
  istore 17
  iload 8
  iconst_1
  iadd
  istore 5
  aload_0
  iload 8
  baload
  istore 16
  iload 17
  istore_1
  iload_1
  iload 16
  invokestatic com/adwo/adsdk/X/a(BB)S
  istore 18
  iload 18
  istore_1
  dload_1
  invokestatic app/DummyClass/invokeIfStmt(D)V
  iload 18
  ifeq Label16
  new java/lang/String
  astore 19
Label40:
  ldc "UTF-8"
  astore 11
  aload 19
  astore_1
  aload_0
  astore_2
  iload 18
  istore_3
  aload_1
  aload_2
  iload 5
  iload_3
  aload 11
  invokespecial java/lang/String/<init>([BIILjava/lang/String;)V
  aload 19
  astore_1
  aload 7
  aload_1
  putfield com/adwo/adsdk/FSAd/d Ljava/lang/String;
Label41:
  iload 18
  istore_1
  iload 5
  iload_1
  iadd
  istore 5
Label16:
  iload 5
  iconst_1
  iadd
  istore 8
  aload_0
  iload 5
  baload
  istore 17
  iload 17
  istore_1
  dload_1
  invokestatic app/DummyClass/invokeIfStmt(D)V
  bipush -93
  istore 9
  iload 17
  istore_1
  iload_1
  iload 9
  if_icmpne Label17
  iload 8
  iconst_1
  iadd
  istore 5
  aload_0
  iload 8
  baload
  istore 17
  iload 5
  iconst_1
  iadd
  istore 8
  aload_0
  iload 5
  baload
  istore 16
  iload 17
  istore_1
  iload_1
  iload 16
  invokestatic com/adwo/adsdk/X/a(BB)S
  istore 18
  iload 18
  istore_1
  dload_1
  invokestatic app/DummyClass/invokeIfStmt(D)V
  iload 18
  ifeq Label18
  new java/lang/String
  astore 19
Label43:
  ldc "UTF-8"
  astore 11
  aload 19
  astore_1
  aload_0
  astore_2
  iload 18
  istore_3
  aload_1
  aload_2
  iload 8
  iload_3
  aload 11
  invokespecial java/lang/String/<init>([BIILjava/lang/String;)V
  aload 19
  astore_1
  aload 7
  aload_1
  putfield com/adwo/adsdk/FSAd/g Ljava/lang/String;
Label44:
  iload 18
  istore_1
  iload 8
  iload_1
  iadd
  istore 8
Label18:
  iload 8
  iconst_1
  iadd
  istore 5
  aload_0
  iload 8
  baload
  istore 17
  iload 17
  istore_1
  dload_1
  invokestatic app/DummyClass/invokeIfStmt(D)V
  bipush -92
  istore 9
  iload 17
  istore_1
  iload_1
  iload 9
  if_icmpne Label19
  iload 5
  iconst_1
  iadd
  istore 8
  aload_0
  iload 5
  baload
  istore 17
  iload 8
  iconst_1
  iadd
  istore 5
  aload_0
  iload 8
  baload
  istore 16
  iload 17
  istore_1
  iload_1
  iload 16
  invokestatic com/adwo/adsdk/X/a(BB)S
  istore 18
  iload 18
  istore_1
  dload_1
  invokestatic app/DummyClass/invokeIfStmt(D)V
  iload 18
  ifeq Label20
  new java/lang/String
  astore 19
Label46:
  ldc "UTF-8"
  astore 11
  aload 19
  astore_1
  aload_0
  astore_2
  iload 18
  istore_3
  aload_1
  aload_2
  iload 5
  iload_3
  aload 11
  invokespecial java/lang/String/<init>([BIILjava/lang/String;)V
  aload 7
  getfield com/adwo/adsdk/FSAd/f Ljava/util/List;
  astore_1
  aload_1
  astore 20
  aload 20
  astore_1
  aload 19
  astore_2
  aload_1
  aload_2
  invokeinterface java/util/List/add(Ljava/lang/Object;)Z 2
  pop
Label47:
  iload 5
  iload 18
  iadd
  istore 8
Label25:
  iload 18
  istore_1
  dload_1
  invokestatic app/DummyClass/invokeIfStmt(D)V
  iconst_1
  istore 9
  iload 18
  istore_1
  iload_1
  iload 9
  if_icmple Label21
  iload 8
  iconst_1
  iadd
  istore 5
  aload_0
  iload 8
  baload
  istore 17
  iload 5
  iconst_1
  iadd
  istore 8
  aload_0
  iload 5
  baload
  istore 10
  iload 17
  istore_1
  iload_1
  iload 10
  invokestatic com/adwo/adsdk/X/a(BB)S
  istore 18
  iload 18
  istore_1
  dload_1
  invokestatic app/DummyClass/invokeIfStmt(D)V
  iload 18
  ifeq Label21
  iconst_0
  dstore 5
Label26:
  dload 5
  invokestatic app/DummyClass/invokeIfStmt(D)V
  iload 18
  istore_1
  dload_1
  invokestatic app/DummyClass/invokeIfStmt(D)V
  iload 18
  istore_1
  iload 5
  iload_1
  if_icmplt Label22
Label21:
  aload_0
  astore_1
  aload_1
  arraylength
  istore 5
  dload 8
  invokestatic app/DummyClass/invokeIfStmt(D)V
  dload 5
  invokestatic app/DummyClass/invokeIfStmt(D)V
  iload 8
  iload 5
  if_icmplt Label23
  aload 7
  areturn
Label33:
  astore 21
  aload 21
  astore_1
  aload_1
  invokevirtual java/io/UnsupportedEncodingException/printStackTrace()V
  goto Label24
Label36:
  astore 22
  aload 22
  astore_1
  aload_1
  invokevirtual java/lang/Exception/printStackTrace()V
  goto Label14
Label39:
  astore 23
  aload 23
  astore_1
  aload_1
  invokevirtual java/lang/Exception/printStackTrace()V
  goto Label16
Label42:
  astore 24
  aload 24
  astore_1
  aload_1
  invokevirtual java/lang/Exception/printStackTrace()V
  goto Label18
Label45:
  astore 25
  aload 25
  astore_1
  aload_1
  invokevirtual java/lang/Exception/printStackTrace()V
Label20:
  iload 5
  istore 8
  goto Label25
Label22:
  iload 8
  iconst_1
  iadd
  istore 26
Label49:
  aload_0
  iload 8
  baload
  istore 17
Label50:
  iload 26
  iconst_1
  iadd
  istore 8
Label52:
  aload_0
  iload 26
  baload
  istore 10
  iload 17
  istore_1
  iload_1
  iload 10
  invokestatic com/adwo/adsdk/X/a(BB)S
  istore 27
  new java/lang/String
  astore 19
  ldc "UTF-8"
  astore 11
  aload 19
  astore_1
  aload_0
  astore_2
  iload 27
  istore_3
  aload_1
  aload_2
  iload 8
  iload_3
  aload 11
  invokespecial java/lang/String/<init>([BIILjava/lang/String;)V
  aload 7
  getfield com/adwo/adsdk/FSAd/f Ljava/util/List;
  astore_1
  aload_1
  astore 20
  aload 20
  astore_1
  aload 19
  astore_2
  aload_1
  aload_2
  invokeinterface java/util/List/add(Ljava/lang/Object;)Z 2
  pop
Label53:
  iload 5
  iconst_1
  iadd
  istore 5
  iload 27
  iload 8
  iadd
  istore 8
  goto Label26
Label23:
  iload 8
  iconst_1
  iadd
  istore 26
  aload_0
  iload 8
  baload
  istore 17
  iload 17
  istore_1
  dload_1
  invokestatic app/DummyClass/invokeIfStmt(D)V
  bipush -91
  istore 9
  iload 17
  istore_1
  iload_1
  iload 9
  if_icmpne Label27
  iload 26
  iconst_1
  iadd
  istore 8
  aload_0
  iload 26
  baload
  istore 17
  iload 8
  iconst_1
  iadd
  istore 26
  aload_0
  iload 8
  baload
  istore 10
  iload 17
  istore_1
  iload_1
  iload 10
  invokestatic com/adwo/adsdk/X/a(BB)S
  istore 27
  iload 27
  istore_1
  dload_1
  invokestatic app/DummyClass/invokeIfStmt(D)V
  iload 27
  ifeq Label28
Label31:
  dload 6
  invokestatic app/DummyClass/invokeIfStmt(D)V
  iload 27
  istore_1
  dload_1
  invokestatic app/DummyClass/invokeIfStmt(D)V
  iload 27
  istore_1
  iload 6
  iload_1
  if_icmplt Label29
Label28:
  aload_0
  astore_1
  aload_1
  arraylength
  istore 6
  iload 26
  istore_1
  dload_1
  invokestatic app/DummyClass/invokeIfStmt(D)V
  dload 6
  invokestatic app/DummyClass/invokeIfStmt(D)V
  iload 26
  istore_1
  iload_1
  iload 6
  if_icmplt Label30
  aload 7
  areturn
Label29:
  iload 26
  iconst_1
  iadd
  istore 8
Label55:
  aload_0
  iload 26
  baload
  istore 17
Label56:
  iload 8
  iconst_1
  iadd
  istore 26
Label58:
  aload_0
  iload 8
  baload
  istore 10
  iload 17
  istore_1
  iload_1
  iload 10
  invokestatic com/adwo/adsdk/X/a(BB)S
  istore 18
  new java/lang/String
  astore 19
  ldc "UTF-8"
  astore 11
  aload 19
  astore_1
  aload_0
  astore_2
  iload 26
  istore_3
  iload 18
  istore 4
  aload_1
  aload_2
  iload_3
  iload 4
  aload 11
  invokespecial java/lang/String/<init>([BIILjava/lang/String;)V
  aload 7
  getfield com/adwo/adsdk/FSAd/h Ljava/util/List;
  astore_1
  aload_1
  astore 20
  aload 20
  astore_1
  aload 19
  astore_2
  aload_1
  aload_2
  invokeinterface java/util/List/add(Ljava/lang/Object;)Z 2
  pop
Label59:
  iload 6
  iconst_1
  iadd
  istore 6
  iload 18
  iload 26
  iadd
  istore 26
  goto Label31
Label30:
  iload 26
  iconst_1
  iadd
  istore 6
  aload_0
  iload 26
  baload
  istore 17
  iload 17
  istore_1
  dload_1
  invokestatic app/DummyClass/invokeIfStmt(D)V
  bipush -86
  istore 9
  iload 17
  istore_1
  iload_1
  iload 9
  if_icmpne Label32
  aload_0
  astore_1
  aload_1
  iload 6
  invokestatic com/adwo/adsdk/X/a([BI)I
  istore 26
  iload 6
  iconst_4
  iadd
  istore 6
  iload 26
  istore_1
  dload_1
  invokestatic app/DummyClass/invokeIfStmt(D)V
  iload 26
  ifeq Label32
  new java/lang/String
  astore 19
Label61:
  ldc "UTF-8"
  astore 11
  aload 19
  astore_1
  aload_0
  astore_2
  iload 26
  istore_3
  aload_1
  aload_2
  iload 6
  iload_3
  aload 11
  invokespecial java/lang/String/<init>([BIILjava/lang/String;)V
  aload 19
  astore_1
  aload 7
  aload_1
  putfield com/adwo/adsdk/FSAd/i Ljava/lang/String;
Label32:
  aload 7
  areturn
Label60:
  astore 28
  aload 28
  astore_1
  aload_1
  invokevirtual java/lang/Exception/printStackTrace()V
  goto Label32
Label57:
  astore 29
  goto Label28
Label54:
  astore 30
  iload 8
  istore 26
  goto Label28
Label48:
  astore 31
  iload 26
  istore 8
  goto Label21
Label51:
  astore 32
  goto Label21
Label27:
  goto Label28
Label19:
  iload 5
  istore 8
  goto Label21
Label17:
  goto Label18
Label15:
  goto Label16
Label13:
  iload 5
  istore 8
  goto Label14
  nop
.end <method>

.method private static a(BB)S
.limit locals 5
.limit stack 200
  nop
  iload_0
  bipush 8
  ishl
  istore_2
  sipush 255
  istore 4
  iload_1
  iload 4
  iand
  istore_3
  iload_2
  iload_3
  ior
  istore_2
  iload_2
  i2s
  istore_3
  iload_3
  ireturn
  nop
.end <method>

.method public static a(BBBBBZ[BBS[B[B[BSSSBB[B[BZDDBS[Ljava/lang/Integer;S)[B
.limit locals 39
.limit stack 200
  .catch  java/io/IOException <from> Label18 <to> Label9 <using> Label17
  .catch  java/io/IOException <from> Label0 <to> Label19 <using> Label17
  .catch  java/io/IOException <from> Label1 <to> Label20 <using> Label17
  nop
  new java/io/ByteArrayOutputStream
  astore 31
  aload 31
  invokespecial java/io/ByteArrayOutputStream/<init>()V
  iconst_2
  istore 33
  iload 33
  newarray byte
  astore 32
Label18:
  aload 31
  aload 32
  invokevirtual java/io/ByteArrayOutputStream/write([B)V
  iload 24
  istore 28
  aload 31
  iload 28
  invokevirtual java/io/ByteArrayOutputStream/write(I)V
  aload 31
  iload_0
  invokevirtual java/io/ByteArrayOutputStream/write(I)V
  aload 31
  iload_1
  invokevirtual java/io/ByteArrayOutputStream/write(I)V
  aload 31
  iload_2
  invokevirtual java/io/ByteArrayOutputStream/write(I)V
  aload 31
  iload_3
  invokevirtual java/io/ByteArrayOutputStream/write(I)V
  aload 31
  iload 4
  invokevirtual java/io/ByteArrayOutputStream/write(I)V
  iload 5
  istore 28
  new java/lang/NoClassDefFoundError
  dup
  invokespecial java/lang/NoClassDefFoundError/<init>()V
  athrow
  iload 5
  ifeq Label0
  iconst_0
  istore 33
  aload 31
  iload 33
  invokevirtual java/io/ByteArrayOutputStream/write(I)V
Label8:
  aload 6
  astore 28
  aload 31
  aload 28
  invokevirtual java/io/ByteArrayOutputStream/write([B)V
  iload 7
  istore 28
  aload 31
  iload 28
  invokevirtual java/io/ByteArrayOutputStream/write(I)V
  iload 8
  istore 28
  iload 28
  invokestatic com/adwo/adsdk/X/a(S)[B
  astore 32
  aload 31
  aload 32
  invokevirtual java/io/ByteArrayOutputStream/write([B)V
  aload 9
  astore 28
  aload 28
  invokestatic app/DummyClass/invokeIfStmt(Ljava/lang/Object;)V
  iload 9
  ifeq Label1
  bipush 73
  istore 33
  aload 31
  iload 33
  invokevirtual java/io/ByteArrayOutputStream/write(I)V
  aload 9
  astore 28
  aload 28
  arraylength
  istore 34
  iload 34
  i2b
  istore 35
  aload 31
  iload 35
  invokevirtual java/io/ByteArrayOutputStream/write(I)V
  aload 9
  astore 28
  aload 31
  aload 28
  invokevirtual java/io/ByteArrayOutputStream/write([B)V
Label10:
  iconst_0
  istore 33
  iload 33
  invokestatic com/adwo/adsdk/X/a(S)[B
  astore 32
  aload 31
  aload 32
  invokevirtual java/io/ByteArrayOutputStream/write([B)V
  iconst_0
  istore 33
  iload 33
  invokestatic com/adwo/adsdk/X/a(S)[B
  astore 32
  aload 31
  aload 32
  invokevirtual java/io/ByteArrayOutputStream/write([B)V
  aload 10
  astore 28
  aload 28
  invokestatic app/DummyClass/invokeIfStmt(Ljava/lang/Object;)V
  iload 10
  ifeq Label2
  bipush 77
  istore 33
  aload 31
  iload 33
  invokevirtual java/io/ByteArrayOutputStream/write(I)V
  aload 10
  astore 28
  aload 28
  arraylength
  istore 34
  iload 34
  i2b
  istore 35
  aload 31
  iload 35
  invokevirtual java/io/ByteArrayOutputStream/write(I)V
  aload 10
  astore 28
  aload 31
  aload 28
  invokevirtual java/io/ByteArrayOutputStream/write([B)V
Label11:
  aload 11
  astore 28
  aload 28
  invokestatic app/DummyClass/invokeIfStmt(Ljava/lang/Object;)V
  iload 11
  ifeq Label3
  bipush 66
  istore 33
  aload 31
  iload 33
  invokevirtual java/io/ByteArrayOutputStream/write(I)V
  aload 11
  astore 28
  aload 28
  arraylength
  istore 34
  iload 34
  i2b
  istore 35
  aload 31
  iload 35
  invokevirtual java/io/ByteArrayOutputStream/write(I)V
  aload 11
  astore 28
  aload 31
  aload 28
  invokevirtual java/io/ByteArrayOutputStream/write([B)V
Label12:
  iload 14
  istore 28
  iload 28
  invokestatic com/adwo/adsdk/X/a(S)[B
  astore 32
  aload 31
  aload 32
  invokevirtual java/io/ByteArrayOutputStream/write([B)V
  iload 15
  istore 28
  aload 31
  iload 28
  invokevirtual java/io/ByteArrayOutputStream/write(I)V
  iload 16
  istore 28
  aload 31
  iload 28
  invokevirtual java/io/ByteArrayOutputStream/write(I)V
  aload 17
  astore 28
  aload 28
  invokestatic app/DummyClass/invokeIfStmt(Ljava/lang/Object;)V
  iload 17
  ifeq Label4
  bipush 78
  istore 33
  aload 31
  iload 33
  invokevirtual java/io/ByteArrayOutputStream/write(I)V
  aload 17
  astore 28
  aload 28
  arraylength
  istore 34
  iload 34
  i2b
  istore 35
  aload 31
  iload 35
  invokevirtual java/io/ByteArrayOutputStream/write(I)V
  aload 17
  astore 28
  aload 31
  aload 28
  invokevirtual java/io/ByteArrayOutputStream/write([B)V
Label13:
  aload 18
  astore 28
  aload 28
  invokestatic app/DummyClass/invokeIfStmt(Ljava/lang/Object;)V
  iload 18
  ifeq Label5
  bipush 80
  istore 33
  aload 31
  iload 33
  invokevirtual java/io/ByteArrayOutputStream/write(I)V
  aload 18
  astore 28
  aload 28
  arraylength
  istore 34
  iload 34
  i2b
  istore 35
  aload 31
  iload 35
  invokevirtual java/io/ByteArrayOutputStream/write(I)V
  aload 18
  astore 28
  aload 31
  aload 28
  invokevirtual java/io/ByteArrayOutputStream/write([B)V
Label14:
  iload 19
  istore 28
  iload 28
  invokestatic app/DummyClass/invokeIfStmt(Z)V
  iload 19
  ifeq Label6
  bipush 76
  istore 33
  aload 31
  iload 33
  invokevirtual java/io/ByteArrayOutputStream/write(I)V
  dload 20
  dstore 28
  dload 28
  invokestatic com/adwo/adsdk/X/a(D)[B
  astore 32
  bipush 16
  istore 33
  aload 31
  iload 33
  invokevirtual java/io/ByteArrayOutputStream/write(I)V
  aload 31
  aload 32
  invokevirtual java/io/ByteArrayOutputStream/write([B)V
  dload 22
  dstore 28
  dload 28
  invokestatic com/adwo/adsdk/X/a(D)[B
  astore 32
  aload 31
  aload 32
  invokevirtual java/io/ByteArrayOutputStream/write([B)V
Label15:
  iload 25
  istore 28
  iload 28
  invokestatic com/adwo/adsdk/X/a(S)[B
  astore 32
  aload 31
  aload 32
  invokevirtual java/io/ByteArrayOutputStream/write([B)V
  iconst_0
  dstore 34
Label16:
  dload 34
  invokestatic app/DummyClass/invokeIfStmt(D)V
  dload 25
  dstore 28
  dload 28
  invokestatic app/DummyClass/invokeIfStmt(D)V
  iload 25
  istore 28
  iload 34
  iload 28
  if_icmplt Label7
  iload 27
  istore 28
  iload 28
  invokestatic com/adwo/adsdk/X/a(S)[B
  astore 32
  aload 31
  aload 32
  invokevirtual java/io/ByteArrayOutputStream/write([B)V
  getstatic com/adwo/adsdk/Y/d I
  istore 34
  iload 34
  invokestatic com/adwo/adsdk/X/a(I)[B
  astore 32
  aload 31
  aload 32
  invokevirtual java/io/ByteArrayOutputStream/write([B)V
Label9:
  aload 31
  invokevirtual java/io/ByteArrayOutputStream/toByteArray()[B
  astore 32
  aload 32
  arraylength
  istore 34
  iload 34
  bipush -2
  iadd
  istore 34
  iload 34
  i2s
  istore 28
  iload 28
  istore 27
  ldc 65280
  istore 33
  iload 33
  iload 27
  iand
  istore 34
  iload 34
  bipush 8
  ishr
  istore 34
  iload 34
  i2b
  istore 28
  iload 28
  istore 24
  iconst_0
  istore 33
  aload 32
  iload 33
  iload 24
  bastore
  sipush 255
  istore 33
  iload 27
  istore 28
  iload 28
  iload 33
  iand
  istore 28
  iload 28
  istore 27
  iload 28
  i2b
  istore 28
  iload 28
  istore 24
  iconst_1
  istore 33
  aload 32
  iload 33
  iload 24
  bastore
  aload 32
  areturn
Label0:
  iconst_1
  istore 33
  aload 31
  iload 33
  invokevirtual java/io/ByteArrayOutputStream/write(I)V
Label19:
  goto Label8
Label17:
  astore 36
  aload 36
  invokevirtual java/io/IOException/printStackTrace()V
  goto Label9
Label1:
  bipush 73
  istore 33
  aload 31
  iload 33
  invokevirtual java/io/ByteArrayOutputStream/write(I)V
  iconst_0
  istore 33
  aload 31
  iload 33
  invokevirtual java/io/ByteArrayOutputStream/write(I)V
  goto Label10
Label2:
  bipush 77
  istore 33
  aload 31
  iload 33
  invokevirtual java/io/ByteArrayOutputStream/write(I)V
  iconst_0
  istore 33
  aload 31
  iload 33
  invokevirtual java/io/ByteArrayOutputStream/write(I)V
  goto Label11
Label3:
  bipush 66
  istore 33
  aload 31
  iload 33
  invokevirtual java/io/ByteArrayOutputStream/write(I)V
  iconst_0
  istore 33
  aload 31
  iload 33
  invokevirtual java/io/ByteArrayOutputStream/write(I)V
  goto Label12
Label4:
  bipush 78
  istore 33
  aload 31
  iload 33
  invokevirtual java/io/ByteArrayOutputStream/write(I)V
  iconst_0
  istore 33
  aload 31
  iload 33
  invokevirtual java/io/ByteArrayOutputStream/write(I)V
  goto Label13
Label5:
  bipush 80
  istore 33
  aload 31
  iload 33
  invokevirtual java/io/ByteArrayOutputStream/write(I)V
  iconst_0
  istore 33
  aload 31
  iload 33
  invokevirtual java/io/ByteArrayOutputStream/write(I)V
  goto Label14
Label6:
  bipush 76
  istore 33
  aload 31
  iload 33
  invokevirtual java/io/ByteArrayOutputStream/write(I)V
  iconst_0
  istore 33
  aload 31
  iload 33
  invokevirtual java/io/ByteArrayOutputStream/write(I)V
  goto Label15
Label7:
  aload 26
  iload 34
  aaload
  astore 37
  aload 37
  invokevirtual java/lang/Integer/intValue()I
  istore 38
  iload 38
  invokestatic com/adwo/adsdk/X/a(I)[B
  astore 32
  aload 31
  aload 32
  invokevirtual java/io/ByteArrayOutputStream/write([B)V
Label20:
  iload 34
  iconst_1
  iadd
  istore 34
  goto Label16
  nop
.end <method>

.method private static a(D)[B
.limit locals 14
.limit stack 200
  nop
  dload_0
  invokestatic java/lang/Double/doubleToLongBits(D)J
  lstore_2
  bipush 8
  istore 5
  iload 5
  newarray byte
  astore 4
  bipush 56
  istore 5
  lload_2
  iload 5
  lshr
  lstore 6
  ldc2_w 255
  lstore 8
  lload 6
  lload 8
  land
  lstore 6
  lload 6
  l2i
  istore 10
  iload 10
  i2b
  istore 11
  iconst_0
  istore 5
  aload 4
  iload 5
  iload 11
  bastore
  bipush 48
  istore 5
  lload_2
  iload 5
  lshr
  lstore 6
  ldc2_w 255
  lstore 8
  lload 6
  lload 8
  land
  lstore 6
  lload 6
  l2i
  istore 10
  iload 10
  i2b
  istore 12
  iconst_1
  istore 5
  aload 4
  iload 5
  iload 12
  bastore
  bipush 40
  istore 5
  lload_2
  iload 5
  lshr
  lstore 6
  ldc2_w 255
  lstore 8
  lload 6
  lload 8
  land
  lstore 6
  lload 6
  l2i
  istore 10
  iload 10
  i2b
  istore 12
  iconst_2
  istore 5
  aload 4
  iload 5
  iload 12
  bastore
  bipush 32
  istore 5
  lload_2
  iload 5
  lshr
  lstore 6
  ldc2_w 255
  lstore 8
  lload 6
  lload 8
  land
  lstore 6
  lload 6
  l2i
  istore 10
  iload 10
  i2b
  istore 12
  iconst_3
  istore 5
  aload 4
  iload 5
  iload 12
  bastore
  bipush 24
  istore 5
  lload_2
  iload 5
  lshr
  lstore 6
  ldc2_w 255
  lstore 8
  lload 6
  lload 8
  land
  lstore 6
  lload 6
  l2i
  istore 10
  iload 10
  i2b
  istore 12
  iconst_4
  istore 5
  aload 4
  iload 5
  iload 12
  bastore
  bipush 16
  istore 5
  lload_2
  iload 5
  lshr
  lstore 6
  ldc2_w 255
  lstore 8
  lload 6
  lload 8
  land
  lstore 6
  lload 6
  l2i
  istore 10
  iload 10
  i2b
  istore 12
  iconst_5
  istore 5
  aload 4
  iload 5
  iload 12
  bastore
  bipush 8
  istore 5
  lload_2
  iload 5
  lshr
  lstore 6
  ldc2_w 255
  lstore 8
  lload 6
  lload 8
  land
  lstore 6
  lload 6
  l2i
  istore 10
  iload 10
  i2b
  istore 13
  bipush 6
  istore 5
  aload 4
  iload 5
  iload 13
  bastore
  ldc2_w 255
  lstore 8
  lload_2
  lload 8
  land
  lstore 6
  lload 6
  l2i
  istore 10
  iload 10
  i2b
  istore 11
  bipush 7
  istore 5
  aload 4
  iload 5
  iload 11
  bastore
  aload 4
  areturn
  nop
.end <method>

.method private static a(I)[B
.limit locals 6
.limit stack 200
  nop
  iconst_4
  istore_2
  iload_2
  newarray byte
  astore_1
  iload_0
  bipush 24
  iushr
  istore_3
  iload_3
  i2b
  istore 4
  iconst_0
  istore_2
  aload_1
  iload_2
  iload 4
  bastore
  iload_0
  bipush 16
  iushr
  istore_3
  iload_3
  i2b
  istore 5
  iconst_1
  istore_2
  aload_1
  iload_2
  iload 5
  bastore
  iload_0
  bipush 8
  iushr
  istore_3
  iload_3
  i2b
  istore 5
  iconst_2
  istore_2
  aload_1
  iload_2
  iload 5
  bastore
  iload_0
  i2b
  istore 5
  iconst_3
  istore_2
  aload_1
  iload_2
  iload 5
  bastore
  aload_1
  areturn
  nop
.end <method>

.method private static a(S)[B
.limit locals 6
.limit stack 200
  nop
  iconst_2
  istore_2
  iload_2
  newarray byte
  astore_1
  ldc 65280
  istore_2
  iload_2
  iload_0
  iand
  istore_3
  iload_3
  bipush 8
  ishr
  istore_3
  iload_3
  i2b
  istore 4
  iconst_0
  istore_2
  aload_1
  iload_2
  iload 4
  bastore
  sipush 255
  istore_2
  iload_0
  iload_2
  iand
  istore_0
  iload_0
  i2b
  istore 5
  iconst_1
  istore_2
  aload_1
  iload_2
  iload 5
  bastore
  aload_1
  areturn
  nop
.end <method>

.method protected static b([B)Lcom/adwo/adsdk/k;
.limit locals 44
.limit stack 200
  nop
  bipush 9
  istore 5
  iconst_0
  istore 6
  new com/adwo/adsdk/k
  astore 7
  aload 7
  invokespecial com/adwo/adsdk/k/<init>()V
  aload_0
  astore_1
  aload_1
  arraylength
  istore 8
  new java/lang/NoClassDefFoundError
  dup
  invokespecial java/lang/NoClassDefFoundError/<init>()V
  athrow
  iconst_1
  istore 9
  iload 8
  iload 9
  if_icmpne Label0
  iconst_0
  istore 9
  aload_0
  iload 9
  baload
  istore 10
  dload 10
  invokestatic app/DummyClass/invokeIfStmt(D)V
  bipush -29
  istore 9
  iload 10
  iload 9
  if_icmpne Label1
  ldc "Adwo SDK"
  astore 11
  ldc "Adwo_Pid inexist"
  astore 12
  aload 11
  aload 12
  invokestatic android/util/Log/e(Ljava/lang/String;Ljava/lang/String;)I
  pop
  new com/adwo/adsdk/ErrorCode
  astore 13
  iconst_0
  istore 9
  aload_0
  iload 9
  baload
  istore 10
  ldc "ERR_INEXIST_PID"
  astore 11
  aload 13
  iload 10
  aload 11
  invokespecial com/adwo/adsdk/ErrorCode/<init>(ILjava/lang/String;)V
Label3:
  aload 7
  aload 13
  putfield com/adwo/adsdk/k/c Lcom/adwo/adsdk/ErrorCode;
  aload 7
  areturn
Label1:
  iconst_0
  istore 9
  aload_0
  iload 9
  baload
  istore 10
  dload 10
  invokestatic app/DummyClass/invokeIfStmt(D)V
  bipush -32
  istore 9
  iload 10
  iload 9
  if_icmpne Label2
  ldc "Adwo SDK"
  astore 11
  ldc "Server busy"
  astore 12
  aload 11
  aload 12
  invokestatic android/util/Log/e(Ljava/lang/String;Ljava/lang/String;)I
  pop
  new com/adwo/adsdk/ErrorCode
  astore 13
  iconst_0
  istore 9
  aload_0
  iload 9
  baload
  istore 10
  ldc "ERR_SERVERBUSY"
  astore 11
  aload 13
  iload 10
  aload 11
  invokespecial com/adwo/adsdk/ErrorCode/<init>(ILjava/lang/String;)V
  goto Label3
Label2:
  iconst_0
  istore 9
  aload_0
  iload 9
  baload
  istore 10
  dload 10
  invokestatic app/DummyClass/invokeIfStmt(D)V
  bipush -28
  istore 9
  iload 10
  iload 9
  if_icmpne Label4
  ldc "Adwo SDK"
  astore 11
  ldc "Adwo_Pid inactive"
  astore 12
  aload 11
  aload 12
  invokestatic android/util/Log/e(Ljava/lang/String;Ljava/lang/String;)I
  pop
  new com/adwo/adsdk/ErrorCode
  astore 13
  iconst_0
  istore 9
  aload_0
  iload 9
  baload
  istore 10
  ldc "ERR_INACTIVATED_PID"
  astore 11
  aload 13
  iload 10
  aload 11
  invokespecial com/adwo/adsdk/ErrorCode/<init>(ILjava/lang/String;)V
  goto Label3
Label4:
  iconst_0
  istore 9
  aload_0
  iload 9
  baload
  istore 10
  dload 10
  invokestatic app/DummyClass/invokeIfStmt(D)V
  bipush -31
  istore 9
  iload 10
  iload 9
  if_icmpeq Label5
  iconst_0
  istore 9
  aload_0
  iload 9
  baload
  istore 10
  dload 10
  invokestatic app/DummyClass/invokeIfStmt(D)V
  bipush -24
  istore 9
  iload 10
  iload 9
  if_icmpne Label6
Label5:
  new java/lang/StringBuilder
  astore 14
  ldc "No ad available: "
  astore 11
  aload 14
  aload 11
  invokespecial java/lang/StringBuilder/<init>(Ljava/lang/String;)V
  iconst_0
  istore 9
  aload_0
  iload 9
  baload
  istore 10
  aload 14
  iload 10
  invokevirtual java/lang/StringBuilder/append(I)Ljava/lang/StringBuilder;
  astore 14
  aload 14
  invokevirtual java/lang/StringBuilder/toString()Ljava/lang/String;
  astore 15
  ldc "Adwo SDK"
  astore 11
  aload 11
  aload 15
  invokestatic android/util/Log/e(Ljava/lang/String;Ljava/lang/String;)I
  pop
  new com/adwo/adsdk/ErrorCode
  astore 13
  iconst_0
  istore 9
  aload_0
  iload 9
  baload
  istore 10
  ldc "ERR_NOAD_IP"
  astore 11
  aload 13
  iload 10
  aload 11
  invokespecial com/adwo/adsdk/ErrorCode/<init>(ILjava/lang/String;)V
  goto Label3
Label6:
  iconst_0
  istore 9
  aload_0
  iload 9
  baload
  istore 10
  dload 10
  invokestatic app/DummyClass/invokeIfStmt(D)V
  bipush -23
  istore 9
  iload 10
  iload 9
  if_icmpne Label7
  new java/lang/StringBuilder
  astore 14
  ldc "No ad available: "
  astore 11
  aload 14
  aload 11
  invokespecial java/lang/StringBuilder/<init>(Ljava/lang/String;)V
  iconst_0
  istore 9
  aload_0
  iload 9
  baload
  istore 10
  aload 14
  iload 10
  invokevirtual java/lang/StringBuilder/append(I)Ljava/lang/StringBuilder;
  astore 14
  aload 14
  invokevirtual java/lang/StringBuilder/toString()Ljava/lang/String;
  astore 15
  ldc "Adwo SDK"
  astore 11
  aload 11
  aload 15
  invokestatic android/util/Log/e(Ljava/lang/String;Ljava/lang/String;)I
  pop
  new com/adwo/adsdk/ErrorCode
  astore 13
  iconst_0
  istore 9
  aload_0
  iload 9
  baload
  istore 10
  ldc "ERR_NOAD_LOWRANK"
  astore 11
  aload 13
  iload 10
  aload 11
  invokespecial com/adwo/adsdk/ErrorCode/<init>(ILjava/lang/String;)V
  goto Label3
Label7:
  iconst_0
  istore 9
  aload_0
  iload 9
  baload
  istore 10
  dload 10
  invokestatic app/DummyClass/invokeIfStmt(D)V
  bipush -25
  istore 9
  iload 10
  iload 9
  if_icmpne Label8
  new java/lang/StringBuilder
  astore 14
  ldc "No ad available: "
  astore 11
  aload 14
  aload 11
  invokespecial java/lang/StringBuilder/<init>(Ljava/lang/String;)V
  iconst_0
  istore 9
  aload_0
  iload 9
  baload
  istore 10
  aload 14
  iload 10
  invokevirtual java/lang/StringBuilder/append(I)Ljava/lang/StringBuilder;
  astore 14
  aload 14
  invokevirtual java/lang/StringBuilder/toString()Ljava/lang/String;
  astore 15
  ldc "Adwo SDK"
  astore 11
  aload 11
  aload 15
  invokestatic android/util/Log/e(Ljava/lang/String;Ljava/lang/String;)I
  pop
  new com/adwo/adsdk/ErrorCode
  astore 13
  iconst_0
  istore 9
  aload_0
  iload 9
  baload
  istore 10
  ldc "ERR_NOAD_IP"
  astore 11
  aload 13
  iload 10
  aload 11
  invokespecial com/adwo/adsdk/ErrorCode/<init>(ILjava/lang/String;)V
  goto Label3
Label8:
  iconst_0
  istore 9
  aload_0
  iload 9
  baload
  istore 10
  dload 10
  invokestatic app/DummyClass/invokeIfStmt(D)V
  bipush -30
  istore 9
  iload 10
  iload 9
  if_icmpne Label9
  ldc "Adwo SDK"
  astore 11
  ldc "Unknown Error"
  astore 12
  aload 11
  aload 12
  invokestatic android/util/Log/e(Ljava/lang/String;Ljava/lang/String;)I
  pop
  new com/adwo/adsdk/ErrorCode
  astore 13
  iconst_0
  istore 9
  aload_0
  iload 9
  baload
  istore 10
  ldc "ERR_UNKNOWN"
  astore 11
  aload 13
  iload 10
  aload 11
  invokespecial com/adwo/adsdk/ErrorCode/<init>(ILjava/lang/String;)V
  goto Label3
Label9:
  iconst_0
  istore 9
  aload_0
  iload 9
  baload
  istore 10
  dload 10
  invokestatic app/DummyClass/invokeIfStmt(D)V
  bipush -26
  istore 9
  iload 10
  iload 9
  if_icmpne Label10
  ldc "Adwo SDK"
  astore 11
  ldc "Error in receiving data"
  astore 12
  aload 11
  aload 12
  invokestatic android/util/Log/e(Ljava/lang/String;Ljava/lang/String;)I
  pop
  new com/adwo/adsdk/ErrorCode
  astore 13
  iconst_0
  istore 9
  aload_0
  iload 9
  baload
  istore 10
  ldc "ERR_INCOMM"
  astore 11
  aload 13
  iload 10
  aload 11
  invokespecial com/adwo/adsdk/ErrorCode/<init>(ILjava/lang/String;)V
  goto Label3
Label10:
  iconst_0
  istore 9
  aload_0
  iload 9
  baload
  istore 10
  dload 10
  invokestatic app/DummyClass/invokeIfStmt(D)V
  bipush -27
  istore 9
  iload 10
  iload 9
  if_icmpne Label11
  ldc "Adwo SDK"
  astore 11
  ldc "Error in request data"
  astore 12
  aload 11
  aload 12
  invokestatic android/util/Log/e(Ljava/lang/String;Ljava/lang/String;)I
  pop
  new com/adwo/adsdk/ErrorCode
  astore 13
  iconst_0
  istore 9
  aload_0
  iload 9
  baload
  istore 10
  ldc "ERR_REQDATA"
  astore 11
  aload 13
  iload 10
  aload 11
  invokespecial com/adwo/adsdk/ErrorCode/<init>(ILjava/lang/String;)V
  goto Label3
Label11:
  new java/lang/StringBuilder
  astore 14
  ldc "Unknown Error "
  astore 11
  aload 14
  aload 11
  invokespecial java/lang/StringBuilder/<init>(Ljava/lang/String;)V
  iconst_0
  istore 9
  aload_0
  iload 9
  baload
  istore 10
  aload 14
  iload 10
  invokevirtual java/lang/StringBuilder/append(I)Ljava/lang/StringBuilder;
  astore 14
  aload 14
  invokevirtual java/lang/StringBuilder/toString()Ljava/lang/String;
  astore 15
  ldc "Adwo SDK"
  astore 11
  aload 11
  aload 15
  invokestatic android/util/Log/e(Ljava/lang/String;Ljava/lang/String;)I
  pop
  new com/adwo/adsdk/ErrorCode
  astore 13
  iconst_0
  istore 9
  aload_0
  iload 9
  baload
  istore 10
  ldc "OTHER_ERROR"
  astore 11
  aload 13
  iload 10
  aload 11
  invokespecial com/adwo/adsdk/ErrorCode/<init>(ILjava/lang/String;)V
  goto Label3
Label0:
  aload_0
  astore_1
  aload_1
  arraylength
  istore 8
  dload 8
  invokestatic app/DummyClass/invokeIfStmt(D)V
  bipush 7
  istore 9
  iload 8
  iload 9
  if_icmpge Label12
  new com/adwo/adsdk/ErrorCode
  astore 13
  iconst_0
  istore 9
  aload_0
  iload 9
  baload
  istore 10
  ldc "ERR_INCOMM"
  astore 11
  aload 13
  iload 10
  aload 11
  invokespecial com/adwo/adsdk/ErrorCode/<init>(ILjava/lang/String;)V
  ldc "Adwo SDK"
  astore 11
  ldc "Error in receiving data"
  astore 12
  aload 11
  aload 12
  invokestatic android/util/Log/e(Ljava/lang/String;Ljava/lang/String;)I
  pop
  aload 7
  aload 13
  putfield com/adwo/adsdk/k/c Lcom/adwo/adsdk/ErrorCode;
  aload 7
  areturn
Label12:
  iconst_0
  istore 9
  aload_0
  astore_1
  aload_1
  iload 9
  invokestatic com/adwo/adsdk/X/a([BI)I
  istore 8
  aload 7
  iload 8
  putfield com/adwo/adsdk/k/b I
  bipush 7
  istore 9
  aload_0
  iload 9
  baload
  istore 16
  bipush 8
  istore 9
  aload_0
  iload 9
  baload
  istore 17
  iload 17
  istore_1
  iload 16
  iload_1
  invokestatic com/adwo/adsdk/X/a(BB)S
  istore 18
  new java/lang/String
  astore 19
Label49:
  bipush 9
  istore 9
  ldc "UTF-8"
  astore 11
  aload 19
  astore_1
  aload_0
  astore_2
  iload 18
  istore_3
  aload_1
  aload_2
  iload 9
  iload_3
  aload 11
  invokespecial java/lang/String/<init>([BIILjava/lang/String;)V
Label50:
  aload 19
  astore_1
  aload 7
  aload_1
  putfield com/adwo/adsdk/k/e Ljava/lang/String;
  iload 18
  bipush 9
  iadd
  istore 5
Label20:
  iload 5
  iconst_1
  iadd
  istore 8
  aload_0
  iload 5
  baload
  istore 17
  iload 17
  istore_1
  aload 7
  iload_1
  putfield com/adwo/adsdk/k/h B
  iload 8
  iconst_1
  iadd
  istore 5
  aload_0
  iload 8
  baload
  istore 17
  iload 17
  istore_1
  dload_1
  invokestatic app/DummyClass/invokeIfStmt(D)V
  bipush -95
  istore 9
  iload 17
  istore_1
  iload_1
  iload 9
  if_icmpne Label13
  iload 5
  iconst_1
  iadd
  istore 8
  aload_0
  iload 5
  baload
  istore 17
  sipush 255
  istore 9
  iload 17
  iload 9
  iand
  istore 18
  iload 18
  istore_1
  iload_1
  i2s
  istore_1
  iload_1
  istore 18
  dload_1
  invokestatic app/DummyClass/invokeIfStmt(D)V
  iload 18
  ifeq Label14
  new java/lang/String
  astore 19
Label52:
  ldc "UTF-8"
  astore 11
  aload 19
  astore_1
  aload_0
  astore_2
  iload 18
  istore_3
  aload_1
  aload_2
  iload 8
  iload_3
  aload 11
  invokespecial java/lang/String/<init>([BIILjava/lang/String;)V
  aload 19
  astore_1
  aload 7
  aload_1
  putfield com/adwo/adsdk/k/d Ljava/lang/String;
Label53:
  iload 18
  istore_1
  iload 8
  iload_1
  iadd
  istore 8
Label14:
  iload 8
  iconst_1
  iadd
  istore 5
  aload_0
  iload 8
  baload
  istore 17
  iload 17
  istore_1
  dload_1
  invokestatic app/DummyClass/invokeIfStmt(D)V
  bipush -94
  istore 9
  iload 17
  istore_1
  iload_1
  iload 9
  if_icmpne Label15
  iload 5
  iconst_1
  iadd
  istore 8
  aload_0
  iload 5
  baload
  istore 17
  iload 8
  iconst_1
  iadd
  istore 5
  aload_0
  iload 8
  baload
  istore 16
  iload 17
  istore_1
  iload_1
  iload 16
  invokestatic com/adwo/adsdk/X/a(BB)S
  istore 18
  iload 18
  istore_1
  dload_1
  invokestatic app/DummyClass/invokeIfStmt(D)V
  iload 18
  ifeq Label16
  new java/lang/String
  astore 19
Label55:
  ldc "UTF-8"
  astore 11
  aload 19
  astore_1
  aload_0
  astore_2
  iload 18
  istore_3
  aload_1
  aload_2
  iload 5
  iload_3
  aload 11
  invokespecial java/lang/String/<init>([BIILjava/lang/String;)V
  aload 19
  astore_1
  aload 7
  aload_1
  putfield com/adwo/adsdk/k/f Ljava/lang/String;
Label56:
  iload 18
  istore_1
  iload 5
  iload_1
  iadd
  istore 5
Label16:
  iload 5
  iconst_1
  iadd
  istore 8
  aload_0
  iload 5
  baload
  istore 17
  iload 17
  istore_1
  dload_1
  invokestatic app/DummyClass/invokeIfStmt(D)V
  bipush -93
  istore 9
  iload 17
  istore_1
  iload_1
  iload 9
  if_icmpne Label17
  iload 8
  iconst_1
  iadd
  istore 5
  aload_0
  iload 8
  baload
  istore 17
  iload 5
  iconst_1
  iadd
  istore 8
  aload_0
  iload 5
  baload
  istore 16
  iload 17
  istore_1
  iload_1
  iload 16
  invokestatic com/adwo/adsdk/X/a(BB)S
  istore 18
  iload 18
  istore_1
  dload_1
  invokestatic app/DummyClass/invokeIfStmt(D)V
  iload 18
  ifeq Label18
  new java/lang/String
  astore 19
Label58:
  ldc "UTF-8"
  astore 11
  aload 19
  astore_1
  aload_0
  astore_2
  iload 18
  istore_3
  aload_1
  aload_2
  iload 8
  iload_3
  aload 11
  invokespecial java/lang/String/<init>([BIILjava/lang/String;)V
  aload 19
  astore_1
  aload 7
  aload_1
  putfield com/adwo/adsdk/k/l Ljava/lang/String;
Label59:
  iload 18
  istore_1
  iload 8
  iload_1
  iadd
  istore 8
Label18:
  aload_0
  astore_1
  aload_1
  arraylength
  istore 5
  dload 8
  invokestatic app/DummyClass/invokeIfStmt(D)V
  dload 5
  invokestatic app/DummyClass/invokeIfStmt(D)V
  iload 8
  iload 5
  if_icmplt Label19
  aload 7
  areturn
Label48:
  astore 20
  aload 20
  astore_1
  aload_1
  invokevirtual java/io/UnsupportedEncodingException/printStackTrace()V
  goto Label20
Label51:
  astore 21
  aload 21
  astore_1
  aload_1
  invokevirtual java/lang/Exception/printStackTrace()V
  goto Label14
Label54:
  astore 22
  aload 22
  astore_1
  aload_1
  invokevirtual java/lang/Exception/printStackTrace()V
  goto Label16
Label57:
  astore 23
  aload 23
  astore_1
  aload_1
  invokevirtual java/lang/Exception/printStackTrace()V
  goto Label18
Label19:
  iload 8
  iconst_1
  iadd
  istore 5
  aload_0
  iload 8
  baload
  istore 17
  iload 17
  istore_1
  dload_1
  invokestatic app/DummyClass/invokeIfStmt(D)V
  bipush -92
  istore 9
  iload 17
  istore_1
  iload_1
  iload 9
  if_icmpne Label21
  iload 5
  iconst_1
  iadd
  istore 8
  aload_0
  iload 5
  baload
  istore 17
  iload 8
  iconst_1
  iadd
  istore 5
  aload_0
  iload 8
  baload
  istore 16
  iload 17
  istore_1
  iload_1
  iload 16
  invokestatic com/adwo/adsdk/X/a(BB)S
  istore 18
  iload 18
  istore_1
  dload_1
  invokestatic app/DummyClass/invokeIfStmt(D)V
  iload 18
  ifeq Label22
  new java/lang/String
  astore 19
Label61:
  ldc "UTF-8"
  astore 11
  aload 19
  astore_1
  aload_0
  astore_2
  iload 18
  istore_3
  aload_1
  aload_2
  iload 5
  iload_3
  aload 11
  invokespecial java/lang/String/<init>([BIILjava/lang/String;)V
  aload 7
  getfield com/adwo/adsdk/k/i Ljava/util/List;
  astore_1
  aload_1
  astore 24
  aload 24
  astore_1
  aload 19
  astore_2
  aload_1
  aload_2
  invokeinterface java/util/List/add(Ljava/lang/Object;)Z 2
  pop
Label62:
  iload 5
  iload 18
  iadd
  istore 8
Label26:
  iload 18
  istore_1
  dload_1
  invokestatic app/DummyClass/invokeIfStmt(D)V
  iconst_1
  istore 9
  iload 18
  istore_1
  iload_1
  iload 9
  if_icmple Label23
  iload 8
  iconst_1
  iadd
  istore 5
  aload_0
  iload 8
  baload
  istore 17
  iload 5
  iconst_1
  iadd
  istore 8
  aload_0
  iload 5
  baload
  istore 16
  iload 17
  istore_1
  iload_1
  iload 16
  invokestatic com/adwo/adsdk/X/a(BB)S
  istore 18
  iload 18
  istore_1
  dload_1
  invokestatic app/DummyClass/invokeIfStmt(D)V
  iload 18
  ifeq Label23
  iconst_0
  dstore 5
Label27:
  dload 5
  invokestatic app/DummyClass/invokeIfStmt(D)V
  iload 18
  istore_1
  dload_1
  invokestatic app/DummyClass/invokeIfStmt(D)V
  iload 18
  istore_1
  iload 5
  iload_1
  if_icmplt Label24
Label23:
  aload_0
  astore_1
  aload_1
  arraylength
  istore 5
  dload 8
  invokestatic app/DummyClass/invokeIfStmt(D)V
  dload 5
  invokestatic app/DummyClass/invokeIfStmt(D)V
  iload 8
  iload 5
  if_icmplt Label25
  aload 7
  areturn
Label60:
  astore 25
  aload 25
  astore_1
  aload_1
  invokevirtual java/lang/Exception/printStackTrace()V
Label22:
  iload 5
  istore 8
  goto Label26
Label24:
  iload 8
  iconst_1
  iadd
  istore 26
Label64:
  aload_0
  iload 8
  baload
  istore 17
Label65:
  iload 26
  iconst_1
  iadd
  istore 8
Label67:
  aload_0
  iload 26
  baload
  istore 16
  iload 17
  istore_1
  iload_1
  iload 16
  invokestatic com/adwo/adsdk/X/a(BB)S
  istore 27
  new java/lang/String
  astore 19
  ldc "UTF-8"
  astore 11
  aload 19
  astore_1
  aload_0
  astore_2
  iload 27
  istore_3
  aload_1
  aload_2
  iload 8
  iload_3
  aload 11
  invokespecial java/lang/String/<init>([BIILjava/lang/String;)V
  aload 7
  getfield com/adwo/adsdk/k/i Ljava/util/List;
  astore_1
  aload_1
  astore 24
  aload 24
  astore_1
  aload 19
  astore_2
  aload_1
  aload_2
  invokeinterface java/util/List/add(Ljava/lang/Object;)Z 2
  pop
Label68:
  iload 5
  iconst_1
  iadd
  istore 5
  iload 27
  iload 8
  iadd
  istore 8
  goto Label27
Label25:
  iload 8
  iconst_1
  iadd
  istore 26
  aload_0
  iload 8
  baload
  istore 17
  iload 17
  istore_1
  dload_1
  invokestatic app/DummyClass/invokeIfStmt(D)V
  bipush -91
  istore 9
  iload 17
  istore_1
  iload_1
  iload 9
  if_icmpne Label28
  iload 26
  iconst_1
  iadd
  istore 8
  aload_0
  iload 26
  baload
  istore 17
  iload 8
  iconst_1
  iadd
  istore 26
  aload_0
  iload 8
  baload
  istore 16
  iload 17
  istore_1
  iload_1
  iload 16
  invokestatic com/adwo/adsdk/X/a(BB)S
  istore 27
  iload 27
  istore_1
  dload_1
  invokestatic app/DummyClass/invokeIfStmt(D)V
  iload 27
  ifeq Label28
  iconst_0
  dstore 8
Label31:
  dload 8
  invokestatic app/DummyClass/invokeIfStmt(D)V
  iload 27
  istore_1
  dload_1
  invokestatic app/DummyClass/invokeIfStmt(D)V
  iload 27
  istore_1
  iload 8
  iload_1
  if_icmplt Label29
Label28:
  aload_0
  astore_1
  aload_1
  arraylength
  istore 8
Label70:
  iload 26
  istore_1
  dload_1
  invokestatic app/DummyClass/invokeIfStmt(D)V
  dload 8
  invokestatic app/DummyClass/invokeIfStmt(D)V
  iload 26
  istore_1
  iload_1
  iload 8
  if_icmplt Label30
  aload 7
  areturn
Label29:
  iload 26
  iconst_1
  iadd
  istore 5
Label72:
  aload_0
  iload 26
  baload
  istore 17
Label73:
  iload 5
  iconst_1
  iadd
  istore 26
Label75:
  aload_0
  iload 5
  baload
  istore 16
  iload 17
  istore_1
  iload_1
  iload 16
  invokestatic com/adwo/adsdk/X/a(BB)S
  istore 18
  new java/lang/String
  astore 19
  ldc "UTF-8"
  astore 11
  aload 19
  astore_1
  aload_0
  astore_2
  iload 26
  istore_3
  iload 18
  istore 4
  aload_1
  aload_2
  iload_3
  iload 4
  aload 11
  invokespecial java/lang/String/<init>([BIILjava/lang/String;)V
  aload 7
  getfield com/adwo/adsdk/k/j Ljava/util/List;
  astore_1
  aload_1
  astore 24
  aload 24
  astore_1
  aload 19
  astore_2
  aload_1
  aload_2
  invokeinterface java/util/List/add(Ljava/lang/Object;)Z 2
  pop
Label76:
  iload 8
  iconst_1
  iadd
  istore 8
  iload 18
  iload 26
  iadd
  istore 26
  goto Label31
Label74:
  astore 28
Label47:
  goto Label28
Label30:
  iload 26
  iconst_1
  iadd
  istore 8
Label78:
  aload_0
  iload 26
  baload
  istore 17
Label79:
  iload 17
  istore_1
  dload_1
  invokestatic app/DummyClass/invokeIfStmt(D)V
  bipush 75
  istore 9
  iload 17
  istore_1
  iload_1
  iload 9
  if_icmpne Label32
  iload 8
  iconst_1
  iadd
  istore 26
Label80:
  aload_0
  iload 8
  baload
  istore 17
Label81:
  iload 26
  iconst_1
  iadd
  istore 8
Label82:
  aload_0
  iload 26
  baload
  istore 16
  iload 17
  istore_1
  iload_1
  iload 16
  invokestatic com/adwo/adsdk/X/a(BB)S
  istore 27
Label83:
  iload 27
  istore_1
  dload_1
  invokestatic app/DummyClass/invokeIfStmt(D)V
  iload 27
  ifeq Label32
Label85:
  iload 27
  istore_1
  iload_1
  newarray byte
  astore_1
  aload_1
  astore 29
Label86:
  iconst_0
  istore 26
  iload 8
  istore 5
Label40:
  aload 29
  astore_1
  aload_1
  arraylength
  istore 8
  iload 26
  istore_1
  dload_1
  invokestatic app/DummyClass/invokeIfStmt(D)V
  dload 8
  invokestatic app/DummyClass/invokeIfStmt(D)V
  iload 26
  istore_1
  iload_1
  iload 8
  if_icmplt Label33
  iload 27
  istore_1
  dload_1
  invokestatic app/DummyClass/invokeIfStmt(D)V
  iconst_1
  istore 9
  iload 27
  istore_1
  iload_1
  iload 9
  if_icmpne Label34
  iconst_0
  istore 9
  aload 29
  iload 9
  baload
  istore 17
  iload 17
  istore_1
  dload_1
  invokestatic app/DummyClass/invokeIfStmt(D)V
  iconst_1
  istore 9
  iload 17
  istore_1
  iload_1
  iload 9
  if_icmpne Label34
  iconst_1
  istore 9
  aload 7
  iload 9
  putfield com/adwo/adsdk/k/m Z
Label34:
  iload 27
  istore_1
  dload_1
  invokestatic app/DummyClass/invokeIfStmt(D)V
  iconst_2
  istore 9
  iload 27
  istore_1
  iload_1
  iload 9
  if_icmpne Label35
  iconst_0
  istore 9
  aload 29
  iload 9
  baload
  istore 17
  iload 17
  istore_1
  dload_1
  invokestatic app/DummyClass/invokeIfStmt(D)V
  iconst_1
  istore 9
  iload 17
  istore_1
  iload_1
  iload 9
  if_icmpne Label36
  iconst_1
  istore 9
  aload 7
  iload 9
  putfield com/adwo/adsdk/k/m Z
Label36:
  iconst_1
  istore 9
  aload 29
  iload 9
  baload
  istore 17
  iload 17
  istore_1
  dload_1
  invokestatic app/DummyClass/invokeIfStmt(D)V
  iconst_1
  istore 9
  iload 17
  istore_1
  iload_1
  iload 9
  if_icmpne Label35
  iconst_1
  istore 9
  aload 7
  iload 9
  putfield com/adwo/adsdk/k/n Z
Label35:
  iload 27
  istore_1
  dload_1
  invokestatic app/DummyClass/invokeIfStmt(D)V
  iconst_3
  istore 9
  iload 27
  istore_1
  iload_1
  iload 9
  if_icmpne Label37
  iconst_0
  istore 9
  aload 29
  iload 9
  baload
  istore 17
  iload 17
  istore_1
  dload_1
  invokestatic app/DummyClass/invokeIfStmt(D)V
  iconst_1
  istore 9
  iload 17
  istore_1
  iload_1
  iload 9
  if_icmpne Label38
  iconst_1
  istore 9
  aload 7
  iload 9
  putfield com/adwo/adsdk/k/m Z
Label38:
  iconst_1
  istore 9
  aload 29
  iload 9
  baload
  istore 17
  iload 17
  istore_1
  dload_1
  invokestatic app/DummyClass/invokeIfStmt(D)V
  iload 17
  ifne Label37
  iconst_0
  istore 9
  aload 7
  iload 9
  putfield com/adwo/adsdk/k/n Z
Label37:
  aload_0
  astore_1
  aload_1
  arraylength
  istore_1
  iload_1
  istore 26
Label89:
  dload 5
  invokestatic app/DummyClass/invokeIfStmt(D)V
  iload 26
  istore_1
  dload_1
  invokestatic app/DummyClass/invokeIfStmt(D)V
  iload 26
  istore_1
  iload 5
  iload_1
  if_icmplt Label39
  aload 7
  areturn
Label33:
  iload 5
  iconst_1
  iadd
  istore 8
Label90:
  aload_0
  iload 5
  baload
  istore 17
  aload 29
  iload 26
  iload 17
  bastore
Label91:
  iload 26
  iconst_1
  iadd
  istore 26
  iload 8
  istore 5
  goto Label40
Label84:
  astore 30
Label46:
  iload 8
  istore 5
  goto Label37
Label69:
  astore 31
  iload 26
  istore 8
Label32:
  iload 8
  istore 5
  goto Label37
Label39:
  iload 5
  iconst_1
  iadd
  istore 26
Label93:
  aload_0
  iload 5
  baload
  istore 17
Label94:
  iload 17
  istore_1
  dload_1
  invokestatic app/DummyClass/invokeIfStmt(D)V
  bipush -90
  istore 9
  iload 17
  istore_1
  iload_1
  iload 9
  if_icmpne Label41
  iload 26
  iconst_1
  iadd
  istore 5
Label95:
  aload_0
  iload 26
  baload
  istore 17
Label96:
  iload 5
  iconst_1
  iadd
  istore 26
Label97:
  aload_0
  iload 5
  baload
  istore 10
  iload 17
  istore_1
  iload_1
  iload 10
  invokestatic com/adwo/adsdk/X/a(BB)S
  istore 27
Label98:
  iload 27
  istore_1
  dload_1
  invokestatic app/DummyClass/invokeIfStmt(D)V
  iload 27
  ifeq Label41
Label44:
  dload 6
  invokestatic app/DummyClass/invokeIfStmt(D)V
  iload 27
  istore_1
  dload_1
  invokestatic app/DummyClass/invokeIfStmt(D)V
  iload 27
  istore_1
  iload 6
  iload_1
  if_icmplt Label42
Label41:
  aload_0
  astore_1
  aload_1
  arraylength
  istore 6
Label100:
  iload 26
  istore_1
  dload_1
  invokestatic app/DummyClass/invokeIfStmt(D)V
  dload 6
  invokestatic app/DummyClass/invokeIfStmt(D)V
  iload 26
  istore_1
  iload_1
  iload 6
  if_icmplt Label43
  aload 7
  areturn
Label42:
  iload 26
  iconst_1
  iadd
  istore 8
Label102:
  aload_0
  iload 26
  baload
  istore 17
Label103:
  iload 8
  iconst_1
  iadd
  istore 26
Label105:
  aload_0
  iload 8
  baload
  istore 10
  iload 17
  istore_1
  iload_1
  iload 10
  invokestatic com/adwo/adsdk/X/a(BB)S
  istore 18
  new java/lang/String
  astore 19
  ldc "UTF-8"
  astore 11
  aload 19
  astore_1
  aload_0
  astore_2
  iload 26
  istore_3
  iload 18
  istore 4
  aload_1
  aload_2
  iload_3
  iload 4
  aload 11
  invokespecial java/lang/String/<init>([BIILjava/lang/String;)V
  getstatic java/lang/System/out Ljava/io/PrintStream;
  astore 32
  new java/lang/StringBuilder
  astore 14
  ldc "packageName "
  astore 11
  aload 14
  aload 11
  invokespecial java/lang/StringBuilder/<init>(Ljava/lang/String;)V
  aload 19
  astore_1
  aload 14
  aload_1
  invokevirtual java/lang/StringBuilder/append(Ljava/lang/String;)Ljava/lang/StringBuilder;
  astore 14
  aload 14
  invokevirtual java/lang/StringBuilder/toString()Ljava/lang/String;
  astore 15
  aload 32
  astore_1
  aload_1
  aload 15
  invokevirtual java/io/PrintStream/println(Ljava/lang/String;)V
  aload 7
  getfield com/adwo/adsdk/k/k Ljava/util/List;
  astore_1
  aload_1
  astore 24
  aload 24
  astore_1
  aload 19
  astore_2
  aload_1
  aload_2
  invokeinterface java/util/List/add(Ljava/lang/Object;)Z 2
  pop
Label106:
  iload 6
  iconst_1
  iadd
  istore 6
  iload 18
  iload 26
  iadd
  istore 26
  goto Label44
Label43:
  iload 26
  iconst_1
  iadd
  istore 6
Label107:
  aload_0
  iload 26
  baload
  istore 17
  iload 17
  istore_1
  dload_1
  invokestatic app/DummyClass/invokeIfStmt(D)V
  bipush -89
  istore 9
  iload 17
  istore_1
  iload_1
  iload 9
  if_icmpne Label45
  iload 6
  iconst_1
  iadd
  istore 26
  aload_0
  iload 6
  baload
  istore 17
  iload 26
  iconst_1
  iadd
  istore 6
  aload_0
  iload 26
  baload
  istore 10
  iload 17
  istore_1
  iload_1
  iload 10
  invokestatic com/adwo/adsdk/X/a(BB)S
  istore 27
Label108:
  iload 27
  istore_1
  dload_1
  invokestatic app/DummyClass/invokeIfStmt(D)V
  iload 27
  ifeq Label45
  new java/lang/String
  astore 19
Label110:
  ldc "UTF-8"
  astore 11
  aload 19
  astore_1
  aload_0
  astore_2
  iload 27
  istore_3
  aload_1
  aload_2
  iload 6
  iload_3
  aload 11
  invokespecial java/lang/String/<init>([BIILjava/lang/String;)V
  aload 19
  astore_1
  aload 7
  aload_1
  putfield com/adwo/adsdk/k/g Ljava/lang/String;
Label45:
  aload 7
  areturn
Label109:
  astore 33
Label111:
  aload 33
  astore_1
  aload_1
  invokevirtual java/lang/Exception/printStackTrace()V
Label112:
  goto Label45
Label99:
  astore 34
  goto Label45
Label88:
  astore 35
  iload 5
  istore 26
  goto Label41
Label92:
  astore 36
  goto Label41
Label101:
  astore 37
  iload 8
  istore 26
  goto Label41
Label104:
  astore 38
  goto Label41
Label77:
  astore 39
  goto Label32
Label87:
  astore 40
  iload 5
  istore 8
  goto Label46
Label71:
  astore 41
  iload 5
  istore 26
  goto Label47
Label63:
  astore 42
  iload 26
  istore 8
  goto Label23
Label66:
  astore 43
  goto Label23
Label21:
  iload 5
  istore 8
  goto Label23
Label17:
  goto Label18
Label15:
  goto Label16
Label13:
  iload 5
  istore 8
  goto Label14
  nop
.end <method>

