.source dalvik_source_VirusShare_32e70f448ebd75661a1cb12f9cd8e013.apk
.class  com/wiyun/ad/m
.super java/lang/Object
.field private static "a" Ljava/lang/String;
.field private static "b" Ljava/lang/String;
.field private static "c" Ljava/lang/String;
.field private static "d" I =  0

.method static <clinit>()V
.limit locals 1
.limit stack 200
  nop
  iconst_m1
  istore_0
  iload_0
  putstatic com/wiyun/ad/m/d I
  return
  nop
.end <method>

.method <init>()V
.limit locals 1
.limit stack 200
  nop
  aload_0
  invokespecial java/lang/Object/<init>()V
  return
  nop
.end <method>

.method static a()Ljava/lang/String;
.limit locals 8
.limit stack 200
  nop
  getstatic com/wiyun/ad/m/a Ljava/lang/String;
  astore_0
  new java/lang/NoClassDefFoundError
  dup
  invokespecial java/lang/NoClassDefFoundError/<init>()V
  athrow
  iload_0
  ifne Label0
  new java/lang/StringBuffer
  astore_1
  aload_1
  invokespecial java/lang/StringBuffer/<init>()V
  getstatic android/os/Build$VERSION/RELEASE Ljava/lang/String;
  astore_0
  aload_0
  invokevirtual java/lang/String/length()I
  istore_2
  dload_2
  invokestatic app/DummyClass/invokeIfStmt(D)V
  iload_2
  ifle Label1
  aload_1
  aload_0
  invokevirtual java/lang/StringBuffer/append(Ljava/lang/String;)Ljava/lang/StringBuffer;
  pop
Label5:
  ldc "; "
  astore_3
  aload_1
  aload_3
  invokevirtual java/lang/StringBuffer/append(Ljava/lang/String;)Ljava/lang/StringBuffer;
  pop
  invokestatic java/util/Locale/getDefault()Ljava/util/Locale;
  astore 4
  aload 4
  invokevirtual java/util/Locale/getLanguage()Ljava/lang/String;
  astore_0
  aload_0
  invokestatic app/DummyClass/invokeIfStmt(Ljava/lang/Object;)V
  aload_0
  ifnull Label2
  aload_0
  invokevirtual java/lang/String/toLowerCase()Ljava/lang/String;
  astore_0
  aload_1
  aload_0
  invokevirtual java/lang/StringBuffer/append(Ljava/lang/String;)Ljava/lang/StringBuffer;
  pop
  aload 4
  invokevirtual java/util/Locale/getCountry()Ljava/lang/String;
  astore_0
  aload_0
  invokestatic app/DummyClass/invokeIfStmt(Ljava/lang/Object;)V
  aload_0
  ifnull Label3
  ldc "-"
  astore_3
  aload_1
  aload_3
  invokevirtual java/lang/StringBuffer/append(Ljava/lang/String;)Ljava/lang/StringBuffer;
  pop
  aload_0
  invokevirtual java/lang/String/toLowerCase()Ljava/lang/String;
  astore 5
  aload_1
  aload 5
  invokevirtual java/lang/StringBuffer/append(Ljava/lang/String;)Ljava/lang/StringBuffer;
  pop
Label3:
  getstatic android/os/Build/DEVICE Ljava/lang/String;
  astore 5
  aload 5
  invokevirtual java/lang/String/length()I
  istore_2
  dload_2
  invokestatic app/DummyClass/invokeIfStmt(D)V
  iload_2
  ifle Label4
  ldc "; "
  astore_3
  aload_1
  aload_3
  invokevirtual java/lang/StringBuffer/append(Ljava/lang/String;)Ljava/lang/StringBuffer;
  pop
  aload_1
  aload 5
  invokevirtual java/lang/StringBuffer/append(Ljava/lang/String;)Ljava/lang/StringBuffer;
  pop
Label4:
  iconst_1
  istore 7
  iload 7
  anewarray java/lang/Object
  astore 6
  iconst_0
  istore 7
  aload 6
  iload 7
  aload_1
  aastore
  ldc "Mozilla/5.0 (Linux; U; Android %s) AppleWebKit/525.10+ (KHTML, like Gecko) Version/3.0.4 Mobile Safari/523.12.2"
  astore_3
  aload_3
  aload 6
  invokestatic java/lang/String/format(Ljava/lang/String;[Ljava/lang/Object;)Ljava/lang/String;
  astore 5
  aload 5
  putstatic com/wiyun/ad/m/a Ljava/lang/String;
Label0:
  getstatic com/wiyun/ad/m/a Ljava/lang/String;
  astore 5
  aload 5
  areturn
Label1:
  ldc "1.0"
  astore_3
  aload_1
  aload_3
  invokevirtual java/lang/StringBuffer/append(Ljava/lang/String;)Ljava/lang/StringBuffer;
  pop
  goto Label5
Label2:
  ldc "en"
  astore_3
  aload_1
  aload_3
  invokevirtual java/lang/StringBuffer/append(Ljava/lang/String;)Ljava/lang/StringBuffer;
  pop
  goto Label3
  nop
.end <method>

.method static a(Landroid/content/Context;)Ljava/lang/String;
.limit locals 10
.limit stack 200
  nop
  getstatic com/wiyun/ad/m/c Ljava/lang/String;
  astore_1
  new java/lang/NoClassDefFoundError
  dup
  invokespecial java/lang/NoClassDefFoundError/<init>()V
  athrow
  iload_1
  ifne Label0
  aload_0
  invokestatic com/wiyun/ad/m/b(Landroid/content/Context;)Z
  istore_2
  iload_2
  invokestatic app/DummyClass/invokeIfStmt(Z)V
  iload_2
  ifeq Label1
  ldc "000000000000000"
  astore_3
  aload_3
  putstatic com/wiyun/ad/m/c Ljava/lang/String;
Label0:
  getstatic com/wiyun/ad/m/c Ljava/lang/String;
  astore_1
  aload_1
  areturn
Label1:
  aload_0
  invokestatic app/DummyClass/invokeIfStmt(Ljava/lang/Object;)V
  iload_0
  ifne Label2
  ldc "Context is not set"
  astore_3
  aload_3
  invokestatic com/wiyun/ad/m/a(Ljava/lang/String;)V
  goto Label0
Label2:
  ldc "android.permission.READ_PHONE_STATE"
  astore_3
  aload_0
  aload_3
  invokevirtual android/content/Context/checkCallingOrSelfPermission(Ljava/lang/String;)I
  istore 4
  dload 4
  invokestatic app/DummyClass/invokeIfStmt(D)V
  iconst_m1
  istore 5
  iload 4
  iload 5
  if_icmpne Label3
  ldc "Cannot get a device ID.  Open manifest.xml and just before the final </manifest> tag add:  <uses-permission android:name=\"android.permission.READ_PHONE_STATE\" />"
  astore_3
  aload_3
  invokestatic com/wiyun/ad/m/a(Ljava/lang/String;)V
  goto Label0
Label3:
  ldc "phone"
  astore_3
  aload_0
  aload_3
  invokevirtual android/content/Context/getSystemService(Ljava/lang/String;)Ljava/lang/Object;
  astore 6
  aload 6
  astore 8
  aload 8
  checkcast android/telephony/TelephonyManager
  astore 8
  aload 8
  astore 7
  aload 7
  invokestatic app/DummyClass/invokeIfStmt(Ljava/lang/Object;)V
  aload 7
  ifnull Label4
  aload 7
  invokevirtual android/telephony/TelephonyManager/getDeviceId()Ljava/lang/String;
  astore_1
  aload_1
  putstatic com/wiyun/ad/m/c Ljava/lang/String;
  getstatic com/wiyun/ad/m/c Ljava/lang/String;
  astore_1
  aload_1
  invokestatic com/wiyun/ad/m/b(Ljava/lang/String;)Z
  istore_2
  iload_2
  invokestatic app/DummyClass/invokeIfStmt(Z)V
  iload_2
  ifne Label0
  ldc "000000000000000"
  astore_3
  aload_3
  putstatic com/wiyun/ad/m/c Ljava/lang/String;
  goto Label0
Label4:
  ldc "000000000000000"
  astore_3
  aload_3
  putstatic com/wiyun/ad/m/c Ljava/lang/String;
  ldc "WiYun"
  astore_3
  ldc "No device ID available."
  astore 9
  aload_3
  aload 9
  invokestatic android/util/Log/w(Ljava/lang/String;Ljava/lang/String;)I
  pop
  goto Label0
  nop
.end <method>

.method protected static a(Ljava/lang/String;)V
.limit locals 3
.limit stack 200
  nop
  ldc "WiYun"
  astore_1
  new java/lang/NoClassDefFoundError
  dup
  invokespecial java/lang/NoClassDefFoundError/<init>()V
  athrow
  new java/lang/IllegalArgumentException
  astore_2
  aload_2
  aload_0
  invokespecial java/lang/IllegalArgumentException/<init>(Ljava/lang/String;)V
  aload_2
  athrow
  nop
.end <method>

.method static b(Landroid/content/Context;)Z
.limit locals 12
.limit stack 200
  nop
  getstatic com/wiyun/ad/m/d I
  istore_1
  new java/lang/NoClassDefFoundError
  dup
  invokespecial java/lang/NoClassDefFoundError/<init>()V
  athrow
  iconst_m1
  istore_2
  iload_1
  iload_2
  if_icmpne Label0
  aload_0
  invokestatic com/wiyun/ad/m/g(Landroid/content/Context;)Ljava/lang/String;
  astore_3
  getstatic android/os/Build/FINGERPRINT Ljava/lang/String;
  astore 4
  ldc "generic"
  astore 6
  aload 4
  aload 6
  invokevirtual java/lang/String/startsWith(Ljava/lang/String;)Z
  istore 5
  ldc "sdk"
  astore 4
  getstatic android/os/Build/MODEL Ljava/lang/String;
  astore 7
  aload 4
  aload 7
  invokevirtual java/lang/String/equalsIgnoreCase(Ljava/lang/String;)Z
  istore 8
  aload_0
  invokestatic com/wiyun/ad/m/h(Landroid/content/Context;)Z
  istore 9
  aload_3
  invokestatic android/text/TextUtils/isEmpty(Ljava/lang/CharSequence;)Z
  istore 10
  iload 10
  invokestatic app/DummyClass/invokeIfStmt(Z)V
  iload 10
  ifne Label1
  aload_3
  invokestatic com/wiyun/ad/m/b(Ljava/lang/String;)Z
  istore 10
  iload 10
  invokestatic app/DummyClass/invokeIfStmt(Z)V
  iload 10
  ifeq Label1
  bipush 30
  istore_1
Label8:
  iload 5
  invokestatic app/DummyClass/invokeIfStmt(Z)V
  iload 5
  ifne Label2
  iload_1
  bipush 30
  iadd
  istore_1
Label2:
  iload 8
  invokestatic app/DummyClass/invokeIfStmt(Z)V
  iload 8
  ifne Label3
  iload_1
  bipush 20
  iadd
  istore_1
Label3:
  iload 9
  invokestatic app/DummyClass/invokeIfStmt(Z)V
  iload 9
  ifeq Label4
  iload_1
  bipush 50
  iadd
  istore_1
Label4:
  dload_1
  invokestatic app/DummyClass/invokeIfStmt(D)V
  bipush 50
  istore_2
  iload_1
  iload_2
  if_icmplt Label5
  iconst_0
  istore_2
  iload_2
  istore 11
Label7:
  iload 11
  putstatic com/wiyun/ad/m/d I
Label0:
  getstatic com/wiyun/ad/m/d I
  istore 11
  dload 11
  invokestatic app/DummyClass/invokeIfStmt(D)V
  iload 11
  ifeq Label6
  iconst_1
  istore_2
  iload_2
  ireturn
Label5:
  iconst_1
  istore 11
  goto Label7
Label6:
  iconst_0
  istore_2
  iload_2
  ireturn
Label1:
  iconst_0
  istore_2
  iload_2
  istore_1
  goto Label8
  nop
.end <method>

.method private static b(Ljava/lang/String;)Z
.limit locals 5
.limit stack 200
  nop
  new java/lang/NoClassDefFoundError
  dup
  invokespecial java/lang/NoClassDefFoundError/<init>()V
  athrow
  iload_0
  ifne Label0
Label1:
  iconst_0
  istore_1
  iload_1
  ireturn
Label0:
  aload_0
  invokevirtual java/lang/String/length()I
  istore_2
  iconst_0
  dstore_3
Label3:
  dload_3
  invokestatic app/DummyClass/invokeIfStmt(D)V
  dload_2
  invokestatic app/DummyClass/invokeIfStmt(D)V
  iload_3
  iload_2
  if_icmpge Label1
  aload_0
  iload_3
  invokevirtual java/lang/String/charAt(I)C
  istore 4
  dload 4
  invokestatic app/DummyClass/invokeIfStmt(D)V
  bipush 48
  istore_1
  iload 4
  iload_1
  if_icmpeq Label2
  iconst_1
  istore_1
  iload_1
  ireturn
Label2:
  iload_3
  iconst_1
  iadd
  istore_3
  goto Label3
  nop
.end <method>

.method public static c(Landroid/content/Context;)I
.limit locals 8
.limit stack 200
  nop
  aload_0
  invokestatic com/wiyun/ad/m/d(Landroid/content/Context;)Z
  istore_1
  new java/lang/NoClassDefFoundError
  dup
  invokespecial java/lang/NoClassDefFoundError/<init>()V
  athrow
  iload_1
  ifeq Label0
  iconst_4
  istore_2
  iload_2
  ireturn
Label0:
  ldc "phone"
  astore 4
  aload_0
  aload 4
  invokevirtual android/content/Context/getSystemService(Ljava/lang/String;)Ljava/lang/Object;
  astore_3
  aload_3
  astore 6
  aload 6
  checkcast android/telephony/TelephonyManager
  astore 6
  aload 6
  astore 5
  aload 5
  invokestatic app/DummyClass/invokeIfStmt(Ljava/lang/Object;)V
  aload 5
  ifnonnull Label1
  iconst_0
  istore_2
  iload_2
  ireturn
Label1:
  aload 5
  invokevirtual android/telephony/TelephonyManager/getNetworkType()I
  istore 7
  dload 7
  invokestatic app/DummyClass/invokeIfStmt(D)V
  iconst_1
  istore_2
  iload 7
  iload_2
  if_icmpeq Label2
  dload 7
  invokestatic app/DummyClass/invokeIfStmt(D)V
  iconst_2
  istore_2
  iload 7
  iload_2
  if_icmpeq Label2
  dload 7
  invokestatic app/DummyClass/invokeIfStmt(D)V
  iload 7
  ifne Label3
Label2:
  iconst_2
  istore_2
  iload_2
  ireturn
Label3:
  iconst_3
  istore_2
  iload_2
  ireturn
  nop
.end <method>

.method static d(Landroid/content/Context;)Z
.limit locals 10
.limit stack 200
  nop
  ldc "android.permission.ACCESS_WIFI_STATE"
  astore_2
  new java/lang/NoClassDefFoundError
  dup
  invokespecial java/lang/NoClassDefFoundError/<init>()V
  athrow
  nop
  dload_1
  invokestatic app/DummyClass/invokeIfStmt(D)V
  iload_1
  ifne Label0
  ldc "wifi"
  astore_2
  aload_0
  aload_2
  invokevirtual android/content/Context/getSystemService(Ljava/lang/String;)Ljava/lang/Object;
  astore_3
  aload_3
  astore 5
  aload 5
  checkcast android/net/wifi/WifiManager
  astore 5
  aload 5
  astore 4
  aload 4
  invokestatic app/DummyClass/invokeIfStmt(Ljava/lang/Object;)V
  aload 4
  ifnull Label1
  aload 4
  invokevirtual android/net/wifi/WifiManager/getConnectionInfo()Landroid/net/wifi/WifiInfo;
  astore 6
  aload 6
  invokestatic app/DummyClass/invokeIfStmt(Ljava/lang/Object;)V
  aload 6
  ifnull Label2
  aload 6
  invokevirtual android/net/wifi/WifiInfo/getSupplicantState()Landroid/net/wifi/SupplicantState;
  astore 7
  getstatic android/net/wifi/SupplicantState/COMPLETED Landroid/net/wifi/SupplicantState;
  astore 8
  aload 7
  invokestatic app/DummyClass/invokeIfStmt(Ljava/lang/Object;)V
  aload 8
  invokestatic app/DummyClass/invokeIfStmt(Ljava/lang/Object;)V
  aload 7
  aload 8
  if_acmpne Label2
  iconst_1
  istore 9
  iload 9
  ireturn
Label2:
  iconst_0
  istore 9
  iload 9
  ireturn
Label1:
  iconst_0
  istore 9
  iload 9
  ireturn
Label0:
  iconst_0
  istore 9
  iload 9
  ireturn
  nop
.end <method>

.method static e(Landroid/content/Context;)Ljava/lang/String;
.limit locals 7
.limit stack 200
  nop
  getstatic com/wiyun/ad/m/b Ljava/lang/String;
  astore_1
  new java/lang/NoClassDefFoundError
  dup
  invokespecial java/lang/NoClassDefFoundError/<init>()V
  athrow
  nop
  iload_2
  invokestatic app/DummyClass/invokeIfStmt(Z)V
  iload_2
  ifeq Label0
  aload_0
  invokevirtual android/content/Context/getResources()Landroid/content/res/Resources;
  astore_3
  aload_3
  invokevirtual android/content/res/Resources/getConfiguration()Landroid/content/res/Configuration;
  astore 4
  aload 4
  getfield android/content/res/Configuration/mcc I
  istore 5
  iload 5
  bipush 100
  imul
  istore 5
  aload 4
  getfield android/content/res/Configuration/mnc I
  istore 6
  iload 6
  iload 5
  iadd
  istore 6
  iload 6
  invokestatic java/lang/String/valueOf(I)Ljava/lang/String;
  astore_1
  aload_1
  putstatic com/wiyun/ad/m/b Ljava/lang/String;
Label0:
  getstatic com/wiyun/ad/m/b Ljava/lang/String;
  astore_1
  aload_1
  areturn
  nop
.end <method>

.method static f(Landroid/content/Context;)Ljava/lang/String;
.limit locals 19
.limit stack 200
  nop
  aload_0
  astore_1
  new java/lang/NoClassDefFoundError
  dup
  invokespecial java/lang/NoClassDefFoundError/<init>()V
  athrow
  iload_0
  ifeq Label0
Label4:
  aload_0
  astore_1
  aload_1
  invokevirtual android/content/Context/getPackageManager()Landroid/content/pm/PackageManager;
  astore_2
  aload_0
  astore_1
  aload_1
  invokevirtual android/content/Context/getPackageName()Ljava/lang/String;
  astore_3
  sipush 128
  istore 5
  aload_2
  aload_3
  iload 5
  invokevirtual android/content/pm/PackageManager/getApplicationInfo(Ljava/lang/String;I)Landroid/content/pm/ApplicationInfo;
  astore 4
  aload 4
  getfield android/content/pm/PackageItemInfo/metaData Landroid/os/Bundle;
  astore 6
  ldc "com.wiyun.sdk.channel"
  astore 8
  aload 6
  aload 8
  invokevirtual android/os/Bundle/get(Ljava/lang/String;)Ljava/lang/Object;
  astore 7
  aload 7
  astore 9
  aload 9
  checkcast java/lang/String
  astore 9
  aload 9
  astore_3
Label2:
  aload_3
  invokestatic android/text/TextUtils/isEmpty(Ljava/lang/CharSequence;)Z
  istore 10
  iload 10
  invokestatic app/DummyClass/invokeIfStmt(Z)V
  iload 10
  ifeq Label1
Label6:
  ldc "android.os.SystemProperties"
  astore 8
  aload 8
  invokestatic java/lang/Class/forName(Ljava/lang/String;)Ljava/lang/Class;
  astore 11
  iconst_1
  istore 5
  iload 5
  anewarray java/lang/Class
  astore 12
  iconst_0
  istore 5
  ldc java/lang/String
  astore 13
  aload 12
  iload 5
  aload 13
  aastore
  ldc "get"
  astore 8
  aload 11
  aload 8
  aload 12
  invokevirtual java/lang/Class/getMethod(Ljava/lang/String;[Ljava/lang/Class;)Ljava/lang/reflect/Method;
  astore 14
  iconst_1
  istore 5
  iload 5
  anewarray java/lang/Object
  astore 15
  iconst_0
  istore 5
  ldc "ro.jq.channel.name"
  astore 8
  aload 15
  iload 5
  aload 8
  aastore
  aload 14
  aload 11
  aload 15
  invokevirtual java/lang/reflect/Method/invoke(Ljava/lang/Object;[Ljava/lang/Object;)Ljava/lang/Object;
  astore 7
  aload 7
  astore 16
  aload 16
  checkcast java/lang/String
  astore 16
  aload 16
  astore_3
Label1:
  aload_3
  areturn
Label3:
  astore 17
  aconst_null
  astore_3
  goto Label2
Label5:
  astore 18
  ldc "Unknown"
  astore 8
  aload 8
  areturn
Label0:
  aconst_null
  astore_3
  goto Label2
  nop
.end <method>

.method private static g(Landroid/content/Context;)Ljava/lang/String;
.limit locals 9
.limit stack 200
  nop
  new java/lang/NoClassDefFoundError
  dup
  invokespecial java/lang/NoClassDefFoundError/<init>()V
  athrow
  iload_0
  ifne Label0
  ldc "Context is not set"
  astore_1
  aload_1
  invokestatic com/wiyun/ad/m/a(Ljava/lang/String;)V
  aconst_null
  astore_2
  aload_2
  areturn
Label0:
  ldc "android.permission.READ_PHONE_STATE"
  astore_1
  aload_0
  aload_1
  invokevirtual android/content/Context/checkCallingOrSelfPermission(Ljava/lang/String;)I
  istore_3
  dload_3
  invokestatic app/DummyClass/invokeIfStmt(D)V
  iconst_m1
  istore 4
  iload_3
  iload 4
  if_icmpne Label1
  ldc "Cannot get a device ID.  Open manifest.xml and just before the final </manifest> tag add:  <uses-permission android:name=\"android.permission.READ_PHONE_STATE\" />"
  astore_1
  aload_1
  invokestatic com/wiyun/ad/m/a(Ljava/lang/String;)V
  aconst_null
  astore_2
  aload_2
  areturn
Label1:
  ldc "phone"
  astore_1
  aload_0
  aload_1
  invokevirtual android/content/Context/getSystemService(Ljava/lang/String;)Ljava/lang/Object;
  astore 5
  aload 5
  astore 7
  aload 7
  checkcast android/telephony/TelephonyManager
  astore 7
  aload 7
  astore 6
  aload 6
  invokestatic app/DummyClass/invokeIfStmt(Ljava/lang/Object;)V
  aload 6
  ifnull Label2
  aload 6
  invokevirtual android/telephony/TelephonyManager/getDeviceId()Ljava/lang/String;
  astore 8
  aload 8
  areturn
Label2:
  aconst_null
  astore_2
  aload_2
  areturn
  nop
.end <method>

.method private static h(Landroid/content/Context;)Z
.limit locals 7
.limit stack 200
  nop
  new java/lang/NoClassDefFoundError
  dup
  invokespecial java/lang/NoClassDefFoundError/<init>()V
  athrow
  iload_0
  ifne Label0
  iconst_0
  istore_1
  iload_1
  ireturn
Label0:
  ldc "sensor"
  astore_3
  aload_0
  aload_3
  invokevirtual android/content/Context/getSystemService(Ljava/lang/String;)Ljava/lang/Object;
  astore_2
  aload_2
  astore 5
  aload 5
  checkcast android/hardware/SensorManager
  astore 5
  aload 5
  astore 4
  aload 4
  invokestatic app/DummyClass/invokeIfStmt(Ljava/lang/Object;)V
  aload 4
  ifnonnull Label1
  iconst_0
  istore_1
  iload_1
  ireturn
Label1:
  iconst_2
  istore_1
  aload 4
  iload_1
  invokevirtual android/hardware/SensorManager/getDefaultSensor(I)Landroid/hardware/Sensor;
  astore 6
  aload 6
  invokestatic app/DummyClass/invokeIfStmt(Ljava/lang/Object;)V
  aload 6
  ifnull Label2
  iconst_1
  istore_1
  iload_1
  ireturn
Label2:
  iconst_0
  istore_1
  iload_1
  ireturn
  nop
.end <method>

