.source UniAttribute.java
.class public  com/qq/jce/wup/UniAttribute
.super com/qq/taf/jce/JceStruct
.field static final "$assertionsDisabled" Z =  0
.field protected "_data" Ljava/util/HashMap;
.field "_is" Lcom/qq/taf/jce/JceInputStream;
.field private "cachedClassName" Ljava/util/HashMap;
.field private "cachedData" Ljava/util/HashMap;
.field protected "encodeName" Ljava/lang/String;

.method static <clinit>()V
.limit locals 2
.limit stack 200
  nop
  ldc com/qq/jce/wup/UniAttribute
  astore_0
  aload_0
  invokevirtual java/lang/Class/desiredAssertionStatus()Z
  istore_1
  new java/lang/NoClassDefFoundError
  dup
  invokespecial java/lang/NoClassDefFoundError/<init>()V
  athrow
  iload_1
  ifne Label0
  iconst_1
  istore_1
Label1:
  iload_1
  putstatic com/qq/jce/wup/UniAttribute/$assertionsDisabled Z
  return
Label0:
  iconst_0
  istore_1
  goto Label1
  nop
.end <method>

.method public <init>()V
.limit locals 5
.limit stack 200
  nop
  aload_0
  invokespecial com/qq/taf/jce/JceStruct/<init>()V
  new java/util/HashMap
  astore_1
  aload_1
  invokespecial java/util/HashMap/<init>()V
  aload_0
  aload_1
  putfield com/qq/jce/wup/UniAttribute/_data Ljava/util/HashMap;
  new java/util/HashMap
  astore_1
  sipush 128
  istore_2
  aload_1
  iload_2
  invokespecial java/util/HashMap/<init>(I)V
  aload_0
  aload_1
  putfield com/qq/jce/wup/UniAttribute/cachedClassName Ljava/util/HashMap;
  new java/util/HashMap
  astore_1
  sipush 128
  istore_2
  aload_1
  iload_2
  invokespecial java/util/HashMap/<init>(I)V
  aload_0
  aload_1
  putfield com/qq/jce/wup/UniAttribute/cachedData Ljava/util/HashMap;
  ldc "GBK"
  astore_3
  aload_0
  aload_3
  putfield com/qq/jce/wup/UniAttribute/encodeName Ljava/lang/String;
  new com/qq/taf/jce/JceInputStream
  astore 4
  aload 4
  invokespecial com/qq/taf/jce/JceInputStream/<init>()V
  aload_0
  aload 4
  putfield com/qq/jce/wup/UniAttribute/_is Lcom/qq/taf/jce/JceInputStream;
  return
  nop
.end <method>

.method public <init>(Ljava/util/HashMap;)V
  .signature_attr "(Ljava/util/HashMap<Ljava/lang/String;Ljava/util/HashMap<Ljava/lang/String;[B>;>;)V"
.limit locals 6
.limit stack 200
  nop
  aload_0
  invokespecial com/qq/taf/jce/JceStruct/<init>()V
  new java/util/HashMap
  astore_2
  aload_2
  invokespecial java/util/HashMap/<init>()V
  aload_0
  aload_2
  putfield com/qq/jce/wup/UniAttribute/_data Ljava/util/HashMap;
  new java/util/HashMap
  astore_2
  sipush 128
  istore_3
  aload_2
  iload_3
  invokespecial java/util/HashMap/<init>(I)V
  aload_0
  aload_2
  putfield com/qq/jce/wup/UniAttribute/cachedClassName Ljava/util/HashMap;
  new java/util/HashMap
  astore_2
  sipush 128
  istore_3
  aload_2
  iload_3
  invokespecial java/util/HashMap/<init>(I)V
  aload_0
  aload_2
  putfield com/qq/jce/wup/UniAttribute/cachedData Ljava/util/HashMap;
  ldc "GBK"
  astore 4
  aload_0
  aload 4
  putfield com/qq/jce/wup/UniAttribute/encodeName Ljava/lang/String;
  new com/qq/taf/jce/JceInputStream
  astore 5
  aload 5
  invokespecial com/qq/taf/jce/JceInputStream/<init>()V
  aload_0
  aload 5
  putfield com/qq/jce/wup/UniAttribute/_is Lcom/qq/taf/jce/JceInputStream;
  aload_0
  aload_1
  putfield com/qq/jce/wup/UniAttribute/_data Ljava/util/HashMap;
  return
  nop
.end <method>

.method private checkObjectType(Ljava/util/ArrayList;Ljava/lang/Object;)V
  .signature_attr "(Ljava/util/ArrayList<Ljava/lang/String;>;Ljava/lang/Object;)V"
.limit locals 18
.limit stack 200
  nop
  aload_2
  astore_3
  aload_3
  invokevirtual java/lang/Object/getClass()Ljava/lang/Class;
  astore 4
  aload 4
  invokevirtual java/lang/Class/isArray()Z
  istore 5
  new java/lang/NoClassDefFoundError
  dup
  invokespecial java/lang/NoClassDefFoundError/<init>()V
  athrow
  iload 5
  ifeq Label0
  aload_2
  astore_3
  aload_3
  invokevirtual java/lang/Object/getClass()Ljava/lang/Class;
  astore 4
  aload 4
  invokevirtual java/lang/Class/getComponentType()Ljava/lang/Class;
  astore 4
  aload 4
  invokevirtual java/lang/Class/toString()Ljava/lang/String;
  astore 6
  ldc "byte"
  astore 7
  aload 6
  aload 7
  invokevirtual java/lang/String/equals(Ljava/lang/Object;)Z
  istore 5
  iload 5
  invokestatic app/DummyClass/invokeIfStmt(Z)V
  iload 5
  ifne Label1
  new java/lang/IllegalArgumentException
  astore 8
  ldc "only byte[] is supported"
  astore 7
  aload 8
  aload 7
  invokespecial java/lang/IllegalArgumentException/<init>(Ljava/lang/String;)V
  aload 8
  athrow
Label1:
  aload_2
  astore_3
  aload_3
  invokestatic java/lang/reflect/Array/getLength(Ljava/lang/Object;)I
  istore 9
  dload 9
  invokestatic app/DummyClass/invokeIfStmt(D)V
  iload 9
  ifle Label2
  ldc "java.util.List"
  astore 7
  aload_1
  astore_3
  aload_3
  aload 7
  invokevirtual java/util/ArrayList/add(Ljava/lang/Object;)Z
  pop
  iconst_0
  istore 11
  aload_2
  astore_3
  aload_3
  iload 11
  invokestatic java/lang/reflect/Array/get(Ljava/lang/Object;I)Ljava/lang/Object;
  astore 10
  aload_1
  astore_3
  aload_0
  aload_3
  aload 10
  invokespecial com/qq/jce/wup/UniAttribute/checkObjectType(Ljava/util/ArrayList;Ljava/lang/Object;)V
Label3:
  return
Label2:
  ldc "Array"
  astore 7
  aload_1
  astore_3
  aload_3
  aload 7
  invokevirtual java/util/ArrayList/add(Ljava/lang/Object;)Z
  pop
  ldc "?"
  astore 7
  aload_1
  astore_3
  aload_3
  aload 7
  invokevirtual java/util/ArrayList/add(Ljava/lang/Object;)Z
  pop
  goto Label3
Label0:
  aload_2
  astore_3
  aload_3
  instanceof java/lang/reflect/Array
  istore 5
  iload 5
  invokestatic app/DummyClass/invokeIfStmt(Z)V
  iload 5
  ifeq Label4
  new java/lang/IllegalArgumentException
  astore 8
  ldc "can not support Array, please use List"
  astore 7
  aload 8
  aload 7
  invokespecial java/lang/IllegalArgumentException/<init>(Ljava/lang/String;)V
  aload 8
  athrow
Label4:
  aload_2
  astore_3
  aload_3
  instanceof java/util/List
  istore 5
  iload 5
  invokestatic app/DummyClass/invokeIfStmt(Z)V
  iload 5
  ifeq Label5
  ldc "java.util.List"
  astore 7
  aload_1
  astore_3
  aload_3
  aload 7
  invokevirtual java/util/ArrayList/add(Ljava/lang/Object;)Z
  pop
  aload_2
  astore 13
  aload 13
  checkcast java/util/List
  astore 13
  aload 13
  astore 12
  aload 12
  invokeinterface java/util/List/size()I 1
  istore 9
  dload 9
  invokestatic app/DummyClass/invokeIfStmt(D)V
  iload 9
  ifle Label6
  iconst_0
  istore 11
  aload 12
  iload 11
  invokeinterface java/util/List/get(I)Ljava/lang/Object; 2
  astore 10
  aload_1
  astore_3
  aload_0
  aload_3
  aload 10
  invokespecial com/qq/jce/wup/UniAttribute/checkObjectType(Ljava/util/ArrayList;Ljava/lang/Object;)V
  goto Label3
Label6:
  ldc "?"
  astore 7
  aload_1
  astore_3
  aload_3
  aload 7
  invokevirtual java/util/ArrayList/add(Ljava/lang/Object;)Z
  pop
  goto Label3
Label5:
  aload_2
  astore_3
  aload_3
  instanceof java/util/Map
  istore 5
  iload 5
  invokestatic app/DummyClass/invokeIfStmt(Z)V
  iload 5
  ifeq Label7
  ldc "java.util.Map"
  astore 7
  aload_1
  astore_3
  aload_3
  aload 7
  invokevirtual java/util/ArrayList/add(Ljava/lang/Object;)Z
  pop
  aload_2
  astore 15
  aload 15
  checkcast java/util/Map
  astore 15
  aload 15
  astore 14
  aload 14
  invokeinterface java/util/Map/size()I 1
  istore 9
  dload 9
  invokestatic app/DummyClass/invokeIfStmt(D)V
  iload 9
  ifle Label8
  aload 14
  invokeinterface java/util/Map/keySet()Ljava/util/Set; 1
  astore 16
  aload 16
  invokeinterface java/util/Set/iterator()Ljava/util/Iterator; 1
  astore 17
  aload 17
  invokeinterface java/util/Iterator/next()Ljava/lang/Object; 1
  astore_2
  aload_2
  astore_3
  aload 14
  aload_3
  invokeinterface java/util/Map/get(Ljava/lang/Object;)Ljava/lang/Object; 2
  astore 10
  aload_2
  astore_3
  aload_3
  invokevirtual java/lang/Object/getClass()Ljava/lang/Class;
  astore 4
  aload 4
  invokevirtual java/lang/Class/getName()Ljava/lang/String;
  astore 6
  aload_1
  astore_3
  aload_3
  aload 6
  invokevirtual java/util/ArrayList/add(Ljava/lang/Object;)Z
  pop
  aload_1
  astore_3
  aload_0
  aload_3
  aload 10
  invokespecial com/qq/jce/wup/UniAttribute/checkObjectType(Ljava/util/ArrayList;Ljava/lang/Object;)V
  goto Label3
Label8:
  ldc "?"
  astore 7
  aload_1
  astore_3
  aload_3
  aload 7
  invokevirtual java/util/ArrayList/add(Ljava/lang/Object;)Z
  pop
  ldc "?"
  astore 7
  aload_1
  astore_3
  aload_3
  aload 7
  invokevirtual java/util/ArrayList/add(Ljava/lang/Object;)Z
  pop
  goto Label3
Label7:
  aload_2
  astore_3
  aload_3
  invokevirtual java/lang/Object/getClass()Ljava/lang/Class;
  astore 4
  aload 4
  invokevirtual java/lang/Class/getName()Ljava/lang/String;
  astore 6
  aload_1
  astore_3
  aload_3
  aload 6
  invokevirtual java/util/ArrayList/add(Ljava/lang/Object;)Z
  pop
  goto Label3
  nop
.end <method>

.method public clearCacheData()V
.limit locals 2
.limit stack 200
  nop
  aload_0
  getfield com/qq/jce/wup/UniAttribute/cachedData Ljava/util/HashMap;
  astore_1
  aload_1
  invokevirtual java/util/HashMap/clear()V
  return
  nop
.end <method>

.method public clone()Ljava/lang/Object;
.limit locals 6
.limit stack 200
  .catch  java/lang/CloneNotSupportedException <from> Label2 <to> Label3 <using> Label1
  nop
  iconst_0
  istore_1
Label2:
  aload_0
  invokespecial java/lang/Object/clone()Ljava/lang/Object;
  astore_2
Label3:
  aload_2
  astore_1
Label0:
  aload_1
  areturn
Label1:
  astore_3
  getstatic com/qq/jce/wup/UniAttribute/$assertionsDisabled Z
  istore 4
  new java/lang/NoClassDefFoundError
  dup
  invokespecial java/lang/NoClassDefFoundError/<init>()V
  athrow
  iload 4
  ifne Label0
  new java/lang/AssertionError
  astore 5
  aload 5
  invokespecial java/lang/AssertionError/<init>()V
  aload 5
  athrow
  nop
.end <method>

.method public containsKey(Ljava/lang/String;)Z
.limit locals 4
.limit stack 200
  nop
  aload_0
  getfield com/qq/jce/wup/UniAttribute/_data Ljava/util/HashMap;
  astore_2
  aload_2
  aload_1
  invokevirtual java/util/HashMap/containsKey(Ljava/lang/Object;)Z
  istore_3
  iload_3
  ireturn
  nop
.end <method>

.method public decode([B)V
.limit locals 9
.limit stack 200
  nop
  aload_0
  getfield com/qq/jce/wup/UniAttribute/_is Lcom/qq/taf/jce/JceInputStream;
  astore_2
  aload_2
  aload_1
  invokevirtual com/qq/taf/jce/JceInputStream/warp([B)V
  aload_0
  getfield com/qq/jce/wup/UniAttribute/_is Lcom/qq/taf/jce/JceInputStream;
  astore_2
  aload_0
  getfield com/qq/jce/wup/UniAttribute/encodeName Ljava/lang/String;
  astore_3
  aload_2
  aload_3
  invokevirtual com/qq/taf/jce/JceInputStream/setServerEncoding(Ljava/lang/String;)I
  pop
  new java/util/HashMap
  astore 4
  iconst_1
  istore 5
  aload 4
  iload 5
  invokespecial java/util/HashMap/<init>(I)V
  new java/util/HashMap
  astore 6
  iconst_1
  istore 5
  aload 6
  iload 5
  invokespecial java/util/HashMap/<init>(I)V
  iconst_0
  istore 5
  iload 5
  istore 7
  iload 7
  newarray byte
  astore_1
  ldc ""
  astore 8
  aload 6
  aload 8
  aload_1
  invokevirtual java/util/HashMap/put(Ljava/lang/Object;Ljava/lang/Object;)Ljava/lang/Object;
  pop
  ldc ""
  astore 8
  aload 4
  aload 8
  aload 6
  invokevirtual java/util/HashMap/put(Ljava/lang/Object;Ljava/lang/Object;)Ljava/lang/Object;
  pop
  aload_0
  getfield com/qq/jce/wup/UniAttribute/_is Lcom/qq/taf/jce/JceInputStream;
  astore_2
  iconst_0
  istore 5
  iload 5
  istore 7
  iconst_0
  istore 5
  aload_2
  aload 4
  iload 7
  iload 5
  invokevirtual com/qq/taf/jce/JceInputStream/readMap(Ljava/util/Map;IZ)Ljava/util/HashMap;
  astore 6
  aload_0
  aload 6
  putfield com/qq/jce/wup/UniAttribute/_data Ljava/util/HashMap;
  return
  nop
.end <method>

.method public display(Ljava/lang/StringBuilder;I)V
.limit locals 6
.limit stack 200
  nop
  new com/qq/taf/jce/JceDisplayer
  astore_3
  aload_3
  aload_1
  iload_2
  invokespecial com/qq/taf/jce/JceDisplayer/<init>(Ljava/lang/StringBuilder;I)V
  aload_0
  getfield com/qq/jce/wup/UniAttribute/_data Ljava/util/HashMap;
  astore 4
  ldc "_data"
  astore 5
  aload_3
  aload 4
  aload 5
  invokevirtual com/qq/taf/jce/JceDisplayer/display(Ljava/util/Map;Ljava/lang/String;)Lcom/qq/taf/jce/JceDisplayer;
  pop
  return
  nop
.end <method>

.method public encode()[B
.limit locals 7
.limit stack 200
  nop
  new com/qq/taf/jce/JceOutputStream
  astore_1
  iconst_0
  istore_2
  aload_1
  iload_2
  invokespecial com/qq/taf/jce/JceOutputStream/<init>(I)V
  aload_0
  getfield com/qq/jce/wup/UniAttribute/encodeName Ljava/lang/String;
  astore_3
  aload_1
  aload_3
  invokevirtual com/qq/taf/jce/JceOutputStream/setServerEncoding(Ljava/lang/String;)I
  pop
  aload_0
  getfield com/qq/jce/wup/UniAttribute/_data Ljava/util/HashMap;
  astore 4
  iconst_0
  istore_2
  aload_1
  aload 4
  iload_2
  invokevirtual com/qq/taf/jce/JceOutputStream/write(Ljava/util/Map;I)V
  aload_1
  invokevirtual com/qq/taf/jce/JceOutputStream/getByteBuffer()Ljava/nio/ByteBuffer;
  astore 5
  aload 5
  invokestatic com/qq/taf/jce/JceUtil/getJceBufArray(Ljava/nio/ByteBuffer;)[B
  astore 6
  aload 6
  areturn
  nop
.end <method>

.method public equals(Ljava/lang/Object;)Z
.limit locals 7
.limit stack 200
  nop
  aload_1
  astore_2
  aload_2
  checkcast com/qq/jce/wup/UniAttribute
  astore_2
  aload_2
  astore_0
  iconst_1
  istore 4
  iload 4
  invokestatic java/lang/Integer/valueOf(I)Ljava/lang/Integer;
  astore_3
  aload_0
  getfield com/qq/jce/wup/UniAttribute/_data Ljava/util/HashMap;
  astore 5
  aload_3
  aload 5
  invokestatic com/qq/taf/jce/JceUtil/equals(Ljava/lang/Object;Ljava/lang/Object;)Z
  istore 6
  iload 6
  ireturn
  nop
.end <method>

.method public get(Ljava/lang/String;)Ljava/lang/Object;
  .signature_attr "<T:Ljava/lang/Object;>(Ljava/lang/String;)TT;"
.limit locals 24
.limit stack 200
  nop
  aload_0
  astore_2
  aload_2
  getfield com/qq/jce/wup/UniAttribute/_data Ljava/util/HashMap;
  astore 5
  aload_1
  astore_2
  aload 5
  aload_2
  invokevirtual java/util/HashMap/containsKey(Ljava/lang/Object;)Z
  istore 6
  new java/lang/NoClassDefFoundError
  dup
  invokespecial java/lang/NoClassDefFoundError/<init>()V
  athrow
  iload 6
  ifne Label0
  aconst_null
  astore 7
  aload 7
  areturn
Label0:
  aload_0
  astore_2
  aload_2
  getfield com/qq/jce/wup/UniAttribute/cachedData Ljava/util/HashMap;
  astore 5
  aload_1
  astore_2
  aload 5
  aload_2
  invokevirtual java/util/HashMap/containsKey(Ljava/lang/Object;)Z
  istore 6
  iload 6
  invokestatic app/DummyClass/invokeIfStmt(Z)V
  iload 6
  ifeq Label1
  aload_0
  astore_2
  aload_2
  getfield com/qq/jce/wup/UniAttribute/cachedData Ljava/util/HashMap;
  astore 5
  aload_1
  astore_2
  aload 5
  aload_2
  invokevirtual java/util/HashMap/get(Ljava/lang/Object;)Ljava/lang/Object;
  astore 8
  aload 8
  areturn
Label1:
  aload_0
  astore_2
  aload_2
  getfield com/qq/jce/wup/UniAttribute/_data Ljava/util/HashMap;
  astore 5
  aload_1
  astore_2
  aload 5
  aload_2
  invokevirtual java/util/HashMap/get(Ljava/lang/Object;)Ljava/lang/Object;
  astore 8
  aload 8
  astore 9
  aload 9
  checkcast java/util/HashMap
  astore 9
  aload 9
  astore 5
  aconst_null
  astore 10
  iconst_0
  istore 12
  iload 12
  newarray byte
  astore 11
  aload 5
  invokevirtual java/util/HashMap/entrySet()Ljava/util/Set;
  astore 13
  aload 13
  invokeinterface java/util/Set/iterator()Ljava/util/Iterator; 1
  astore 14
  aload 14
  invokeinterface java/util/Iterator/hasNext()Z 1
  istore 6
  iload 6
  invokestatic app/DummyClass/invokeIfStmt(Z)V
  iload 6
  ifeq Label2
  aload 14
  invokeinterface java/util/Iterator/next()Ljava/lang/Object; 1
  astore 8
  aload 8
  astore 16
  aload 16
  checkcast java/util/Map$Entry
  astore 16
  aload 16
  astore 15
  aload 15
  invokeinterface java/util/Map$Entry/getKey()Ljava/lang/Object; 1
  astore 8
  aload 8
  astore 17
  aload 17
  checkcast java/lang/String
  astore 17
  aload 17
  astore 10
  aload 15
  invokeinterface java/util/Map$Entry/getValue()Ljava/lang/Object; 1
  astore 8
  aload 8
  astore 18
  aload 18
  checkcast [B
  astore 18
  aload 18
  astore 11
Label2:
  aload_0
  astore_2
  aload_2
  aload 10
  invokespecial com/qq/jce/wup/UniAttribute/getCacheProxy(Ljava/lang/String;)Ljava/lang/Object;
  astore 8
  aload_0
  astore_2
  aload_2
  getfield com/qq/jce/wup/UniAttribute/_is Lcom/qq/taf/jce/JceInputStream;
  astore_2
  aload_2
  astore 19
  aload 19
  astore_2
  aload_2
  aload 11
  invokevirtual com/qq/taf/jce/JceInputStream/warp([B)V
  aload_0
  astore_2
  aload_2
  getfield com/qq/jce/wup/UniAttribute/_is Lcom/qq/taf/jce/JceInputStream;
  astore_2
  aload_2
  astore 19
  aload_0
  astore_2
  aload_2
  getfield com/qq/jce/wup/UniAttribute/encodeName Ljava/lang/String;
  astore 10
  aload 19
  astore_2
  aload_2
  aload 10
  invokevirtual com/qq/taf/jce/JceInputStream/setServerEncoding(Ljava/lang/String;)I
  pop
  aload_0
  astore_2
  aload_2
  getfield com/qq/jce/wup/UniAttribute/_is Lcom/qq/taf/jce/JceInputStream;
  astore_2
  aload_2
  astore 19
  iconst_0
  istore 12
  iconst_1
  istore 21
  aload 19
  astore_2
  iload 21
  istore_3
  aload_2
  aload 8
  iload 12
  iload_3
  invokevirtual com/qq/taf/jce/JceInputStream/read(Ljava/lang/Object;IZ)Ljava/lang/Object;
  astore 20
  aload_0
  astore_2
  aload_1
  astore_3
  aload 20
  astore 4
  aload_2
  aload_3
  aload 4
  invokespecial com/qq/jce/wup/UniAttribute/saveDataCache(Ljava/lang/String;Ljava/lang/Object;)V
Label4:
  aload 20
  areturn
Label3:
  astore 22
  aload 22
  astore_2
  aload_2
  invokevirtual java/lang/Exception/printStackTrace()V
  new com/qq/jce/wup/ObjectCreateException
  astore 23
  aload 23
  astore_2
  aload 22
  astore_3
  aload_2
  aload_3
  invokespecial com/qq/jce/wup/ObjectCreateException/<init>(Ljava/lang/Exception;)V
  aload 23
  athrow
  nop
.end <method>

.method public get(Ljava/lang/String;Ljava/lang/Object;)Ljava/lang/Object;
  .signature_attr "<T:Ljava/lang/Object;>(Ljava/lang/String;Ljava/lang/Object;)TT;"
.limit locals 22
.limit stack 200
  nop
  aload_0
  astore_3
  aload_3
  getfield com/qq/jce/wup/UniAttribute/_data Ljava/util/HashMap;
  astore 6
  aload_1
  astore_3
  aload 6
  aload_3
  invokevirtual java/util/HashMap/containsKey(Ljava/lang/Object;)Z
  istore 7
  new java/lang/NoClassDefFoundError
  dup
  invokespecial java/lang/NoClassDefFoundError/<init>()V
  athrow
  iload 7
  ifne Label0
  aload_2
  areturn
Label0:
  aload_0
  astore_3
  aload_3
  getfield com/qq/jce/wup/UniAttribute/cachedData Ljava/util/HashMap;
  astore 6
  aload_1
  astore_3
  aload 6
  aload_3
  invokevirtual java/util/HashMap/containsKey(Ljava/lang/Object;)Z
  istore 7
  iload 7
  invokestatic app/DummyClass/invokeIfStmt(Z)V
  iload 7
  ifeq Label1
  aload_0
  astore_3
  aload_3
  getfield com/qq/jce/wup/UniAttribute/cachedData Ljava/util/HashMap;
  astore 6
  aload_1
  astore_3
  aload 6
  aload_3
  invokevirtual java/util/HashMap/get(Ljava/lang/Object;)Ljava/lang/Object;
  astore 8
  aload 8
  areturn
Label1:
  aload_0
  astore_3
  aload_3
  getfield com/qq/jce/wup/UniAttribute/_data Ljava/util/HashMap;
  astore 6
  aload_1
  astore_3
  aload 6
  aload_3
  invokevirtual java/util/HashMap/get(Ljava/lang/Object;)Ljava/lang/Object;
  astore 8
  aload 8
  astore 9
  aload 9
  checkcast java/util/HashMap
  astore 9
  aload 9
  astore 6
  ldc ""
  astore 10
  iconst_0
  istore 12
  iload 12
  newarray byte
  astore 11
  aload 6
  invokevirtual java/util/HashMap/entrySet()Ljava/util/Set;
  astore 13
  aload 13
  invokeinterface java/util/Set/iterator()Ljava/util/Iterator; 1
  astore 14
  aload 14
  invokeinterface java/util/Iterator/hasNext()Z 1
  istore 7
  iload 7
  invokestatic app/DummyClass/invokeIfStmt(Z)V
  iload 7
  ifeq Label2
  aload 14
  invokeinterface java/util/Iterator/next()Ljava/lang/Object; 1
  astore 8
  aload 8
  astore 16
  aload 16
  checkcast java/util/Map$Entry
  astore 16
  aload 16
  astore 15
  aload 15
  invokeinterface java/util/Map$Entry/getKey()Ljava/lang/Object; 1
  astore 8
  aload 8
  astore 17
  aload 17
  checkcast java/lang/String
  astore 17
  aload 17
  astore 10
  aload 15
  invokeinterface java/util/Map$Entry/getValue()Ljava/lang/Object; 1
  astore 8
  aload 8
  astore 18
  aload 18
  checkcast [B
  astore 18
  aload 18
  astore 11
Label2:
  aload_0
  astore_3
  aload_3
  aload 10
  invokespecial com/qq/jce/wup/UniAttribute/getCacheProxy(Ljava/lang/String;)Ljava/lang/Object;
  astore 8
  aload_0
  astore_3
  aload_3
  getfield com/qq/jce/wup/UniAttribute/_is Lcom/qq/taf/jce/JceInputStream;
  astore_3
  aload_3
  astore 19
  aload 19
  astore_3
  aload_3
  aload 11
  invokevirtual com/qq/taf/jce/JceInputStream/warp([B)V
  aload_0
  astore_3
  aload_3
  getfield com/qq/jce/wup/UniAttribute/_is Lcom/qq/taf/jce/JceInputStream;
  astore_3
  aload_3
  astore 19
  aload_0
  astore_3
  aload_3
  getfield com/qq/jce/wup/UniAttribute/encodeName Ljava/lang/String;
  astore 10
  aload 19
  astore_3
  aload_3
  aload 10
  invokevirtual com/qq/taf/jce/JceInputStream/setServerEncoding(Ljava/lang/String;)I
  pop
  aload_0
  astore_3
  aload_3
  getfield com/qq/jce/wup/UniAttribute/_is Lcom/qq/taf/jce/JceInputStream;
  astore_3
  aload_3
  astore 19
  iconst_0
  istore 12
  iconst_1
  istore 20
  aload 19
  astore_3
  iload 20
  istore 4
  aload_3
  aload 8
  iload 12
  iload 4
  invokevirtual com/qq/taf/jce/JceInputStream/read(Ljava/lang/Object;IZ)Ljava/lang/Object;
  astore 8
  aload_0
  astore_3
  aload_1
  astore 4
  aload_3
  aload 4
  aload 8
  invokespecial com/qq/jce/wup/UniAttribute/saveDataCache(Ljava/lang/String;Ljava/lang/Object;)V
Label4:
  aload 8
  areturn
Label3:
  astore 21
  aload 21
  astore_3
  aload_3
  invokevirtual java/lang/Exception/printStackTrace()V
  aload_0
  astore_3
  aload_1
  astore 4
  aload_2
  astore 5
  aload_3
  aload 4
  aload 5
  invokespecial com/qq/jce/wup/UniAttribute/saveDataCache(Ljava/lang/String;Ljava/lang/Object;)V
  aload_2
  areturn
  nop
.end <method>

.method public getByClass(Ljava/lang/String;Ljava/lang/Object;)Ljava/lang/Object;
  .signature_attr "<T:Ljava/lang/Object;>(Ljava/lang/String;TT;)TT;"
.limit locals 24
.limit stack 200
  nop
  aload_0
  astore_3
  aload_3
  getfield com/qq/jce/wup/UniAttribute/_data Ljava/util/HashMap;
  astore 6
  aload_1
  astore_3
  aload 6
  aload_3
  invokevirtual java/util/HashMap/containsKey(Ljava/lang/Object;)Z
  istore 7
  new java/lang/NoClassDefFoundError
  dup
  invokespecial java/lang/NoClassDefFoundError/<init>()V
  athrow
  iload 7
  ifne Label0
  aconst_null
  astore 8
  aload 8
  areturn
Label0:
  aload_0
  astore_3
  aload_3
  getfield com/qq/jce/wup/UniAttribute/cachedData Ljava/util/HashMap;
  astore 6
  aload_1
  astore_3
  aload 6
  aload_3
  invokevirtual java/util/HashMap/containsKey(Ljava/lang/Object;)Z
  istore 7
  iload 7
  invokestatic app/DummyClass/invokeIfStmt(Z)V
  iload 7
  ifeq Label1
  aload_0
  astore_3
  aload_3
  getfield com/qq/jce/wup/UniAttribute/cachedData Ljava/util/HashMap;
  astore 6
  aload_1
  astore_3
  aload 6
  aload_3
  invokevirtual java/util/HashMap/get(Ljava/lang/Object;)Ljava/lang/Object;
  astore 9
  aload 9
  areturn
Label1:
  aload_0
  astore_3
  aload_3
  getfield com/qq/jce/wup/UniAttribute/_data Ljava/util/HashMap;
  astore 6
  aload_1
  astore_3
  aload 6
  aload_3
  invokevirtual java/util/HashMap/get(Ljava/lang/Object;)Ljava/lang/Object;
  astore 9
  aload 9
  astore 10
  aload 10
  checkcast java/util/HashMap
  astore 10
  aload 10
  astore 6
  iconst_0
  istore 12
  iload 12
  newarray byte
  astore 11
  aload 6
  invokevirtual java/util/HashMap/entrySet()Ljava/util/Set;
  astore 13
  aload 13
  invokeinterface java/util/Set/iterator()Ljava/util/Iterator; 1
  astore 14
  aload 14
  invokeinterface java/util/Iterator/hasNext()Z 1
  istore 7
  iload 7
  invokestatic app/DummyClass/invokeIfStmt(Z)V
  iload 7
  ifeq Label2
  aload 14
  invokeinterface java/util/Iterator/next()Ljava/lang/Object; 1
  astore 9
  aload 9
  astore 16
  aload 16
  checkcast java/util/Map$Entry
  astore 16
  aload 16
  astore 15
  aload 15
  invokeinterface java/util/Map$Entry/getKey()Ljava/lang/Object; 1
  astore 9
  aload 9
  astore 18
  aload 18
  checkcast java/lang/String
  astore 18
  aload 18
  astore 17
  aload 15
  invokeinterface java/util/Map$Entry/getValue()Ljava/lang/Object; 1
  astore 9
  aload 9
  astore 19
  aload 19
  checkcast [B
  astore 19
  aload 19
  astore 11
Label2:
  aload_0
  astore_3
  aload_3
  getfield com/qq/jce/wup/UniAttribute/_is Lcom/qq/taf/jce/JceInputStream;
  astore_3
  aload_3
  astore 20
  aload 20
  astore_3
  aload_3
  aload 11
  invokevirtual com/qq/taf/jce/JceInputStream/warp([B)V
  aload_0
  astore_3
  aload_3
  getfield com/qq/jce/wup/UniAttribute/_is Lcom/qq/taf/jce/JceInputStream;
  astore_3
  aload_3
  astore 20
  aload_0
  astore_3
  aload_3
  getfield com/qq/jce/wup/UniAttribute/encodeName Ljava/lang/String;
  astore 17
  aload 20
  astore_3
  aload_3
  aload 17
  invokevirtual com/qq/taf/jce/JceInputStream/setServerEncoding(Ljava/lang/String;)I
  pop
  aload_0
  astore_3
  aload_3
  getfield com/qq/jce/wup/UniAttribute/_is Lcom/qq/taf/jce/JceInputStream;
  astore_3
  aload_3
  astore 20
  iconst_0
  istore 12
  iconst_1
  istore 21
  aload 20
  astore_3
  aload_2
  astore 4
  iload 21
  istore 5
  aload_3
  aload 4
  iload 12
  iload 5
  invokevirtual com/qq/taf/jce/JceInputStream/read(Ljava/lang/Object;IZ)Ljava/lang/Object;
  astore_2
  aload_0
  astore_3
  aload_1
  astore 4
  aload_2
  astore 5
  aload_3
  aload 4
  aload 5
  invokespecial com/qq/jce/wup/UniAttribute/saveDataCache(Ljava/lang/String;Ljava/lang/Object;)V
Label4:
  aload_2
  areturn
Label3:
  astore 22
  aload 22
  astore_3
  aload_3
  invokevirtual java/lang/Exception/printStackTrace()V
  new com/qq/jce/wup/ObjectCreateException
  astore 23
  aload 23
  astore_3
  aload 22
  astore 4
  aload_3
  aload 4
  invokespecial com/qq/jce/wup/ObjectCreateException/<init>(Ljava/lang/Exception;)V
  aload 23
  athrow
  nop
.end <method>

.method private getCacheProxy(Ljava/lang/String;)Ljava/lang/Object;
.limit locals 6
.limit stack 200
  nop
  aload_0
  getfield com/qq/jce/wup/UniAttribute/cachedClassName Ljava/util/HashMap;
  astore_2
  aload_2
  aload_1
  invokevirtual java/util/HashMap/containsKey(Ljava/lang/Object;)Z
  istore_3
  new java/lang/NoClassDefFoundError
  dup
  invokespecial java/lang/NoClassDefFoundError/<init>()V
  athrow
  iload_3
  ifeq Label0
  aload_0
  getfield com/qq/jce/wup/UniAttribute/cachedClassName Ljava/util/HashMap;
  astore_2
  aload_2
  aload_1
  invokevirtual java/util/HashMap/get(Ljava/lang/Object;)Ljava/lang/Object;
  astore 4
  aload 4
  areturn
Label0:
  aload_1
  invokestatic com/qq/jce/wup/BasicClassTypeUtil/createClassByUni(Ljava/lang/String;)Ljava/lang/Object;
  astore 5
  aload_0
  getfield com/qq/jce/wup/UniAttribute/cachedClassName Ljava/util/HashMap;
  astore_2
  aload_2
  aload_1
  aload 5
  invokevirtual java/util/HashMap/put(Ljava/lang/Object;Ljava/lang/Object;)Ljava/lang/Object;
  pop
  aload 5
  areturn
  nop
.end <method>

.method public getEncodeName()Ljava/lang/String;
.limit locals 2
.limit stack 200
  nop
  aload_0
  getfield com/qq/jce/wup/UniAttribute/encodeName Ljava/lang/String;
  astore_1
  aload_1
  areturn
  nop
.end <method>

.method public getJceStruct(Ljava/lang/String;)Ljava/lang/Object;
  .signature_attr "<T:Ljava/lang/Object;>(Ljava/lang/String;)TT;"
.limit locals 26
.limit stack 200
  nop
  aload_0
  astore_2
  aload_2
  getfield com/qq/jce/wup/UniAttribute/_data Ljava/util/HashMap;
  astore 5
  aload_1
  astore_2
  aload 5
  aload_2
  invokevirtual java/util/HashMap/containsKey(Ljava/lang/Object;)Z
  istore 6
  new java/lang/NoClassDefFoundError
  dup
  invokespecial java/lang/NoClassDefFoundError/<init>()V
  athrow
  iload 6
  ifne Label0
  aconst_null
  astore 7
  aload 7
  areturn
Label0:
  aload_0
  astore_2
  aload_2
  getfield com/qq/jce/wup/UniAttribute/cachedData Ljava/util/HashMap;
  astore 5
  aload_1
  astore_2
  aload 5
  aload_2
  invokevirtual java/util/HashMap/containsKey(Ljava/lang/Object;)Z
  istore 6
  iload 6
  invokestatic app/DummyClass/invokeIfStmt(Z)V
  iload 6
  ifeq Label1
  aload_0
  astore_2
  aload_2
  getfield com/qq/jce/wup/UniAttribute/cachedData Ljava/util/HashMap;
  astore 5
  aload_1
  astore_2
  aload 5
  aload_2
  invokevirtual java/util/HashMap/get(Ljava/lang/Object;)Ljava/lang/Object;
  astore 8
  aload 8
  areturn
Label1:
  aload_0
  astore_2
  aload_2
  getfield com/qq/jce/wup/UniAttribute/_data Ljava/util/HashMap;
  astore 5
  aload_1
  astore_2
  aload 5
  aload_2
  invokevirtual java/util/HashMap/get(Ljava/lang/Object;)Ljava/lang/Object;
  astore 8
  aload 8
  astore 9
  aload 9
  checkcast java/util/HashMap
  astore 9
  aload 9
  astore 5
  aconst_null
  astore 10
  iconst_0
  istore 12
  iload 12
  newarray byte
  astore 11
  aload 5
  invokevirtual java/util/HashMap/entrySet()Ljava/util/Set;
  astore 13
  aload 13
  invokeinterface java/util/Set/iterator()Ljava/util/Iterator; 1
  astore 14
  aload 14
  invokeinterface java/util/Iterator/hasNext()Z 1
  istore 6
  iload 6
  invokestatic app/DummyClass/invokeIfStmt(Z)V
  iload 6
  ifeq Label2
  aload 14
  invokeinterface java/util/Iterator/next()Ljava/lang/Object; 1
  astore 8
  aload 8
  astore 16
  aload 16
  checkcast java/util/Map$Entry
  astore 16
  aload 16
  astore 15
  aload 15
  invokeinterface java/util/Map$Entry/getKey()Ljava/lang/Object; 1
  astore 8
  aload 8
  astore 17
  aload 17
  checkcast java/lang/String
  astore 17
  aload 17
  astore 10
  aload 15
  invokeinterface java/util/Map$Entry/getValue()Ljava/lang/Object; 1
  astore 8
  aload 8
  astore 18
  aload 18
  checkcast [B
  astore 18
  aload 18
  astore 11
Label2:
  aload_0
  astore_2
  aload_2
  aload 10
  invokespecial com/qq/jce/wup/UniAttribute/getCacheProxy(Ljava/lang/String;)Ljava/lang/Object;
  astore 8
  aload_0
  astore_2
  aload_2
  getfield com/qq/jce/wup/UniAttribute/_is Lcom/qq/taf/jce/JceInputStream;
  astore_2
  aload_2
  astore 19
  aload 19
  astore_2
  aload_2
  aload 11
  invokevirtual com/qq/taf/jce/JceInputStream/warp([B)V
  aload_0
  astore_2
  aload_2
  getfield com/qq/jce/wup/UniAttribute/_is Lcom/qq/taf/jce/JceInputStream;
  astore_2
  aload_2
  astore 19
  aload_0
  astore_2
  aload_2
  getfield com/qq/jce/wup/UniAttribute/encodeName Ljava/lang/String;
  astore 10
  aload 19
  astore_2
  aload_2
  aload 10
  invokevirtual com/qq/taf/jce/JceInputStream/setServerEncoding(Ljava/lang/String;)I
  pop
  aload_0
  astore_2
  aload_2
  getfield com/qq/jce/wup/UniAttribute/_is Lcom/qq/taf/jce/JceInputStream;
  astore_2
  aload_2
  astore 19
  aload 8
  astore 21
  aload 21
  checkcast com/qq/taf/jce/JceStruct
  astore 21
  aload 21
  astore 20
  iconst_0
  istore 12
  iconst_1
  istore 23
  aload 19
  astore_2
  aload 20
  astore_3
  iload 23
  istore 4
  aload_2
  aload_3
  iload 12
  iload 4
  invokevirtual com/qq/taf/jce/JceInputStream/directRead(Lcom/qq/taf/jce/JceStruct;IZ)Lcom/qq/taf/jce/JceStruct;
  astore 22
  aload_0
  astore_2
  aload_1
  astore_3
  aload 22
  astore 4
  aload_2
  aload_3
  aload 4
  invokespecial com/qq/jce/wup/UniAttribute/saveDataCache(Ljava/lang/String;Ljava/lang/Object;)V
Label4:
  aload 22
  areturn
Label3:
  astore 24
  aload 24
  astore_2
  aload_2
  invokevirtual java/lang/Exception/printStackTrace()V
  new com/qq/jce/wup/ObjectCreateException
  astore 25
  aload 25
  astore_2
  aload 24
  astore_3
  aload_2
  aload_3
  invokespecial com/qq/jce/wup/ObjectCreateException/<init>(Ljava/lang/Exception;)V
  aload 25
  athrow
  nop
.end <method>

.method public getKeySet()Ljava/util/Set;
  .signature_attr "()Ljava/util/Set<Ljava/lang/String;>;"
.limit locals 3
.limit stack 200
  nop
  aload_0
  getfield com/qq/jce/wup/UniAttribute/_data Ljava/util/HashMap;
  astore_1
  aload_1
  invokevirtual java/util/HashMap/keySet()Ljava/util/Set;
  astore_2
  aload_2
  invokestatic java/util/Collections/unmodifiableSet(Ljava/util/Set;)Ljava/util/Set;
  astore_2
  aload_2
  areturn
  nop
.end <method>

.method public isEmpty()Z
.limit locals 3
.limit stack 200
  nop
  aload_0
  getfield com/qq/jce/wup/UniAttribute/_data Ljava/util/HashMap;
  astore_1
  aload_1
  invokevirtual java/util/HashMap/isEmpty()Z
  istore_2
  iload_2
  ireturn
  nop
.end <method>

.method public put(Ljava/lang/String;Ljava/lang/Object;)V
  .signature_attr "<T:Ljava/lang/Object;>(Ljava/lang/String;TT;)V"
.limit locals 14
.limit stack 200
  nop
  new java/lang/NoClassDefFoundError
  dup
  invokespecial java/lang/NoClassDefFoundError/<init>()V
  athrow
  iload_1
  ifne Label0
  new java/lang/IllegalArgumentException
  astore_3
  ldc "put key can not is null"
  astore 4
  aload_3
  aload 4
  invokespecial java/lang/IllegalArgumentException/<init>(Ljava/lang/String;)V
  aload_3
  athrow
Label0:
  aload_2
  invokestatic app/DummyClass/invokeIfStmt(Ljava/lang/Object;)V
  iload_2
  ifne Label1
  new java/lang/IllegalArgumentException
  astore_3
  ldc "put value can not is null"
  astore 4
  aload_3
  aload 4
  invokespecial java/lang/IllegalArgumentException/<init>(Ljava/lang/String;)V
  aload_3
  athrow
Label1:
  aload_2
  instanceof java/util/Set
  istore 5
  iload 5
  invokestatic app/DummyClass/invokeIfStmt(Z)V
  iload 5
  ifeq Label2
  new java/lang/IllegalArgumentException
  astore_3
  ldc "can not support Set"
  astore 4
  aload_3
  aload 4
  invokespecial java/lang/IllegalArgumentException/<init>(Ljava/lang/String;)V
  aload_3
  athrow
Label2:
  new com/qq/taf/jce/JceOutputStream
  astore 6
  aload 6
  invokespecial com/qq/taf/jce/JceOutputStream/<init>()V
  aload_0
  getfield com/qq/jce/wup/UniAttribute/encodeName Ljava/lang/String;
  astore 7
  aload 6
  aload 7
  invokevirtual com/qq/taf/jce/JceOutputStream/setServerEncoding(Ljava/lang/String;)I
  pop
  iconst_0
  istore 8
  aload 6
  aload_2
  iload 8
  invokevirtual com/qq/taf/jce/JceOutputStream/write(Ljava/lang/Object;I)V
  aload 6
  invokevirtual com/qq/taf/jce/JceOutputStream/getByteBuffer()Ljava/nio/ByteBuffer;
  astore 9
  aload 9
  invokestatic com/qq/taf/jce/JceUtil/getJceBufArray(Ljava/nio/ByteBuffer;)[B
  astore 10
  new java/util/HashMap
  astore 11
  iconst_1
  istore 8
  aload 11
  iload 8
  invokespecial java/util/HashMap/<init>(I)V
  new java/util/ArrayList
  astore 12
  iconst_1
  istore 8
  aload 12
  iload 8
  invokespecial java/util/ArrayList/<init>(I)V
  aload_0
  aload 12
  aload_2
  invokespecial com/qq/jce/wup/UniAttribute/checkObjectType(Ljava/util/ArrayList;Ljava/lang/Object;)V
  aload 12
  invokestatic com/qq/jce/wup/BasicClassTypeUtil/transTypeList(Ljava/util/ArrayList;)Ljava/lang/String;
  astore 7
  aload 11
  aload 7
  aload 10
  invokevirtual java/util/HashMap/put(Ljava/lang/Object;Ljava/lang/Object;)Ljava/lang/Object;
  pop
  aload_0
  getfield com/qq/jce/wup/UniAttribute/cachedData Ljava/util/HashMap;
  astore 13
  aload 13
  aload_1
  invokevirtual java/util/HashMap/remove(Ljava/lang/Object;)Ljava/lang/Object;
  pop
  aload_0
  getfield com/qq/jce/wup/UniAttribute/_data Ljava/util/HashMap;
  astore 13
  aload 13
  aload_1
  aload 11
  invokevirtual java/util/HashMap/put(Ljava/lang/Object;Ljava/lang/Object;)Ljava/lang/Object;
  pop
  return
  nop
.end <method>

.method public readFrom(Lcom/qq/taf/jce/JceInputStream;)V
.limit locals 15
.limit stack 200
  nop
  aload_0
  getfield com/qq/jce/wup/UniAttribute/_data Ljava/util/HashMap;
  astore_2
  aload_2
  invokevirtual java/util/HashMap/clear()V
  new java/util/HashMap
  astore_2
  aload_2
  invokespecial java/util/HashMap/<init>()V
  iconst_1
  istore 4
  iload 4
  istore_3
  iload_3
  newarray byte
  astore 5
  aload 5
  checkcast [B
  astore 5
  iconst_0
  istore 4
  iload 4
  invokestatic java/lang/Byte/valueOf(B)Ljava/lang/Byte;
  astore 6
  aload 5
  astore 8
  aload 8
  checkcast [B
  astore 8
  aload 8
  astore 7
  aload 6
  invokevirtual java/lang/Byte/byteValue()B
  istore 9
  iconst_0
  istore 4
  aload 7
  iload 4
  iload 9
  bastore
  ldc ""
  astore 10
  aload_2
  aload 10
  aload 5
  invokevirtual java/util/HashMap/put(Ljava/lang/Object;Ljava/lang/Object;)Ljava/lang/Object;
  pop
  aload_0
  getfield com/qq/jce/wup/UniAttribute/_data Ljava/util/HashMap;
  astore 11
  ldc ""
  astore 10
  aload 11
  aload 10
  aload_2
  invokevirtual java/util/HashMap/put(Ljava/lang/Object;Ljava/lang/Object;)Ljava/lang/Object;
  pop
  aload_0
  getfield com/qq/jce/wup/UniAttribute/_data Ljava/util/HashMap;
  astore 11
  iconst_0
  istore 4
  iconst_1
  istore 13
  aload_1
  aload 11
  iload 4
  iload 13
  invokevirtual com/qq/taf/jce/JceInputStream/read(Ljava/lang/Object;IZ)Ljava/lang/Object;
  astore 12
  aload 12
  astore 14
  aload 14
  checkcast java/util/HashMap
  astore 14
  aload 14
  astore 11
  aload_0
  aload 11
  putfield com/qq/jce/wup/UniAttribute/_data Ljava/util/HashMap;
  return
  nop
.end <method>

.method public remove(Ljava/lang/String;)Ljava/lang/Object;
  .signature_attr "<T:Ljava/lang/Object;>(Ljava/lang/String;)TT;"
.limit locals 21
.limit stack 200
  nop
  aload_0
  astore_2
  aload_2
  getfield com/qq/jce/wup/UniAttribute/_data Ljava/util/HashMap;
  astore 4
  aload_1
  astore_2
  aload 4
  aload_2
  invokevirtual java/util/HashMap/containsKey(Ljava/lang/Object;)Z
  istore 5
  new java/lang/NoClassDefFoundError
  dup
  invokespecial java/lang/NoClassDefFoundError/<init>()V
  athrow
  iload 5
  ifne Label0
  aconst_null
  astore 6
  aload 6
  areturn
Label0:
  aload_0
  astore_2
  aload_2
  getfield com/qq/jce/wup/UniAttribute/_data Ljava/util/HashMap;
  astore 4
  aload_1
  astore_2
  aload 4
  aload_2
  invokevirtual java/util/HashMap/remove(Ljava/lang/Object;)Ljava/lang/Object;
  astore 7
  aload 7
  astore 8
  aload 8
  checkcast java/util/HashMap
  astore 8
  aload 8
  astore 4
  ldc ""
  astore_1
  iconst_0
  istore 10
  iload 10
  newarray byte
  astore 9
  aload 4
  invokevirtual java/util/HashMap/entrySet()Ljava/util/Set;
  astore 11
  aload 11
  invokeinterface java/util/Set/iterator()Ljava/util/Iterator; 1
  astore 12
  aload 12
  invokeinterface java/util/Iterator/hasNext()Z 1
  istore 5
  iload 5
  invokestatic app/DummyClass/invokeIfStmt(Z)V
  iload 5
  ifeq Label1
  aload 12
  invokeinterface java/util/Iterator/next()Ljava/lang/Object; 1
  astore 7
  aload 7
  astore 14
  aload 14
  checkcast java/util/Map$Entry
  astore 14
  aload 14
  astore 13
  aload 13
  invokeinterface java/util/Map$Entry/getKey()Ljava/lang/Object; 1
  astore 7
  aload 7
  astore 15
  aload 15
  checkcast java/lang/String
  astore 15
  aload 15
  astore_1
  aload 13
  invokeinterface java/util/Map$Entry/getValue()Ljava/lang/Object; 1
  astore 7
  aload 7
  astore 16
  aload 16
  checkcast [B
  astore 16
  aload 16
  astore 9
Label1:
  aload_1
  astore_2
  aload_2
  invokestatic com/qq/jce/wup/BasicClassTypeUtil/createClassByUni(Ljava/lang/String;)Ljava/lang/Object;
  astore 7
  aload_0
  astore_2
  aload_2
  getfield com/qq/jce/wup/UniAttribute/_is Lcom/qq/taf/jce/JceInputStream;
  astore 17
  aload 17
  aload 9
  invokevirtual com/qq/taf/jce/JceInputStream/warp([B)V
  aload_0
  astore_2
  aload_2
  getfield com/qq/jce/wup/UniAttribute/_is Lcom/qq/taf/jce/JceInputStream;
  astore 17
  aload_0
  astore_2
  aload_2
  getfield com/qq/jce/wup/UniAttribute/encodeName Ljava/lang/String;
  astore_2
  aload_2
  astore_1
  aload_1
  astore_2
  aload 17
  aload_2
  invokevirtual com/qq/taf/jce/JceInputStream/setServerEncoding(Ljava/lang/String;)I
  pop
  aload_0
  astore_2
  aload_2
  getfield com/qq/jce/wup/UniAttribute/_is Lcom/qq/taf/jce/JceInputStream;
  astore 17
  iconst_0
  istore 10
  iconst_1
  istore 18
  iload 18
  istore_2
  aload 17
  aload 7
  iload 10
  iload_2
  invokevirtual com/qq/taf/jce/JceInputStream/read(Ljava/lang/Object;IZ)Ljava/lang/Object;
  astore 7
Label3:
  aload 7
  areturn
Label2:
  astore 19
  aload 19
  astore_2
  aload_2
  invokevirtual java/lang/Exception/printStackTrace()V
  new com/qq/jce/wup/ObjectCreateException
  astore 20
  aload 20
  astore_2
  aload 19
  astore_3
  aload_2
  aload_3
  invokespecial com/qq/jce/wup/ObjectCreateException/<init>(Ljava/lang/Exception;)V
  aload 20
  athrow
  nop
.end <method>

.method private saveDataCache(Ljava/lang/String;Ljava/lang/Object;)V
.limit locals 4
.limit stack 200
  nop
  aload_0
  getfield com/qq/jce/wup/UniAttribute/cachedData Ljava/util/HashMap;
  astore_3
  aload_3
  aload_1
  aload_2
  invokevirtual java/util/HashMap/put(Ljava/lang/Object;Ljava/lang/Object;)Ljava/lang/Object;
  pop
  return
  nop
.end <method>

.method public setEncodeName(Ljava/lang/String;)V
.limit locals 2
.limit stack 200
  nop
  aload_0
  aload_1
  putfield com/qq/jce/wup/UniAttribute/encodeName Ljava/lang/String;
  return
  nop
.end <method>

.method public size()I
.limit locals 3
.limit stack 200
  nop
  aload_0
  getfield com/qq/jce/wup/UniAttribute/_data Ljava/util/HashMap;
  astore_1
  aload_1
  invokevirtual java/util/HashMap/size()I
  istore_2
  iload_2
  ireturn
  nop
.end <method>

.method public writeTo(Lcom/qq/taf/jce/JceOutputStream;)V
.limit locals 4
.limit stack 200
  nop
  aload_0
  getfield com/qq/jce/wup/UniAttribute/_data Ljava/util/HashMap;
  astore_2
  iconst_0
  istore_3
  aload_1
  aload_2
  iload_3
  invokevirtual com/qq/taf/jce/JceOutputStream/write(Ljava/util/Map;I)V
  return
  nop
.end <method>

