.source dalvik_source_VirusShare_32e70f448ebd75661a1cb12f9cd8e013.apk
.class public  com/wiyun/ad/ae
.super java/lang/Object

.method public <init>()V
.limit locals 1
.limit stack 200
  nop
  aload_0
  invokespecial java/lang/Object/<init>()V
  return
  nop
.end <method>

.method private static a()Ljava/security/MessageDigest;
.limit locals 2
.limit stack 200
  nop
  ldc "MD5"
  astore_1
  aload_1
  invokestatic com/wiyun/ad/ae/a(Ljava/lang/String;)Ljava/security/MessageDigest;
  astore_0
  aload_0
  areturn
  nop
.end <method>

.method static a(Ljava/lang/String;)Ljava/security/MessageDigest;
.limit locals 4
.limit stack 200
  .catch  java/security/NoSuchAlgorithmException <from> Label1 <to> Label2 <using> Label0
  nop
Label1:
  aload_0
  invokestatic java/security/MessageDigest/getInstance(Ljava/lang/String;)Ljava/security/MessageDigest;
  astore_1
Label2:
  aload_1
  areturn
Label0:
  astore_2
  new java/lang/RuntimeException
  astore_3
  aload_2
  invokevirtual java/security/NoSuchAlgorithmException/getMessage()Ljava/lang/String;
  astore_0
  aload_3
  aload_0
  invokespecial java/lang/RuntimeException/<init>(Ljava/lang/String;)V
  aload_3
  athrow
  nop
.end <method>

.method public static a([B)[B
.limit locals 2
.limit stack 200
  nop
  invokestatic com/wiyun/ad/ae/a()Ljava/security/MessageDigest;
  astore_1
  aload_1
  aload_0
  invokevirtual java/security/MessageDigest/digest([B)[B
  astore_0
  aload_0
  areturn
  nop
.end <method>

.method public static b([B)Ljava/lang/String;
.limit locals 2
.limit stack 200
  nop
  aload_0
  invokestatic com/wiyun/ad/ae/a([B)[B
  astore_0
  aload_0
  invokestatic com/wiyun/ad/y/b([B)Ljava/lang/String;
  astore_1
  aload_1
  areturn
  nop
.end <method>

.method public static b(Ljava/lang/String;)[B
.limit locals 2
.limit stack 200
  nop
  aload_0
  invokestatic com/wiyun/ad/ae/d(Ljava/lang/String;)[B
  astore_1
  aload_1
  invokestatic com/wiyun/ad/ae/a([B)[B
  astore_1
  aload_1
  areturn
  nop
.end <method>

.method public static c(Ljava/lang/String;)Ljava/lang/String;
.limit locals 2
.limit stack 200
  nop
  aload_0
  invokestatic com/wiyun/ad/ae/b(Ljava/lang/String;)[B
  astore_1
  aload_1
  invokestatic com/wiyun/ad/y/b([B)Ljava/lang/String;
  astore_0
  aload_0
  areturn
  nop
.end <method>

.method private static d(Ljava/lang/String;)[B
.limit locals 2
.limit stack 200
  nop
  aload_0
  invokestatic com/wiyun/ad/r/a(Ljava/lang/String;)[B
  astore_1
  aload_1
  areturn
  nop
.end <method>

