.source BaiduJsonAdapter.java
.class public  com/admogo/adapters/BaiduJsonAdapter
.super com/admogo/adapters/AdMogoAdapter
.field static "AD_TYPE" I =  0
.field static "APP_ID" Ljava/lang/String;
.field static "APP_SEC" Ljava/lang/String;
.field public static "baiduAd" Lcom/baidu/Ad;
.field public static "baiduClick1" I =  0
.field public static "baiduClick2" I =  0
.field public static "baiduClick3" I =  0
.field public static "baiduImp" I =  0
.field static "imageAdList" Ljava/util/List;
.field static "imageIndex" I =  0
.field static "imageSize" I =  0
.field static "textAdList" Ljava/util/List;
.field static "textIndex" I =  0
.field static "textSize" I =  0
.field "activity" Landroid/app/Activity;
.field private "tempDrawable" Landroid/graphics/drawable/Drawable;

.method static <clinit>()V
.limit locals 3
.limit stack 200
  nop
  aconst_null
  astore_0
  aload_0
  putstatic com/admogo/adapters/BaiduJsonAdapter/textAdList Ljava/util/List;
  aconst_null
  astore_0
  aload_0
  putstatic com/admogo/adapters/BaiduJsonAdapter/imageAdList Ljava/util/List;
  ldc "debug"
  astore_1
  aload_1
  putstatic com/admogo/adapters/BaiduJsonAdapter/APP_ID Ljava/lang/String;
  ldc "debug"
  astore_1
  aload_1
  putstatic com/admogo/adapters/BaiduJsonAdapter/APP_SEC Ljava/lang/String;
  iconst_1
  istore_2
  iload_2
  putstatic com/admogo/adapters/BaiduJsonAdapter/AD_TYPE I
  iconst_0
  istore_2
  iload_2
  putstatic com/admogo/adapters/BaiduJsonAdapter/textIndex I
  iconst_0
  istore_2
  iload_2
  putstatic com/admogo/adapters/BaiduJsonAdapter/imageIndex I
  aconst_null
  astore_0
  aload_0
  putstatic com/admogo/adapters/BaiduJsonAdapter/baiduAd Lcom/baidu/Ad;
  iconst_0
  istore_2
  iload_2
  putstatic com/admogo/adapters/BaiduJsonAdapter/baiduImp I
  iconst_0
  istore_2
  iload_2
  putstatic com/admogo/adapters/BaiduJsonAdapter/baiduClick1 I
  iconst_0
  istore_2
  iload_2
  putstatic com/admogo/adapters/BaiduJsonAdapter/baiduClick2 I
  iconst_0
  istore_2
  iload_2
  putstatic com/admogo/adapters/BaiduJsonAdapter/baiduClick3 I
  return
  nop
.end <method>

.method public <init>(Lcom/admogo/AdMogoLayout;Lcom/admogo/obj/Ration;)V
.limit locals 6
.limit stack 200
  nop
  aload_0
  aload_1
  aload_2
  invokespecial com/admogo/adapters/AdMogoAdapter/<init>(Lcom/admogo/AdMogoLayout;Lcom/admogo/obj/Ration;)V
  new org/json/JSONObject
  astore_3
  aload_0
  getfield com/admogo/adapters/AdMogoAdapter/ration Lcom/admogo/obj/Ration;
  astore_2
  aload_2
  getfield com/admogo/obj/Ration/key Ljava/lang/String;
  astore 4
  aload_3
  aload 4
  invokespecial org/json/JSONObject/<init>(Ljava/lang/String;)V
  ldc "AppID"
  astore 5
  aload_3
  aload 5
  invokevirtual org/json/JSONObject/getString(Ljava/lang/String;)Ljava/lang/String;
  astore 4
  aload 4
  putstatic com/admogo/adapters/BaiduJsonAdapter/APP_ID Ljava/lang/String;
  ldc "AppSEC"
  astore 5
  aload_3
  aload 5
  invokevirtual org/json/JSONObject/getString(Ljava/lang/String;)Ljava/lang/String;
  astore 4
  aload 4
  putstatic com/admogo/adapters/BaiduJsonAdapter/APP_SEC Ljava/lang/String;
  return
  nop
.end <method>

.method public click()V
.limit locals 22
.limit stack 200
  nop
  getstatic com/admogo/adapters/BaiduJsonAdapter/baiduAd Lcom/baidu/Ad;
  astore 4
  new java/lang/NoClassDefFoundError
  dup
  invokespecial java/lang/NoClassDefFoundError/<init>()V
  athrow
  iload 4
  ifeq Label0
  getstatic com/admogo/adapters/BaiduJsonAdapter/baiduAd Lcom/baidu/Ad;
  astore 4
  aload 4
  invokevirtual com/baidu/Ad/getClickURL()Ljava/lang/String;
  astore 5
  aload 5
  invokestatic app/DummyClass/invokeIfStmt(Ljava/lang/Object;)V
  aload 5
  ifnull Label0
  aload_0
  astore_1
  aload_1
  getfield com/admogo/adapters/AdMogoAdapter/adMogoLayoutReference Ljava/lang/ref/WeakReference;
  astore 6
  aload 6
  invokevirtual java/lang/ref/WeakReference/get()Ljava/lang/Object;
  astore 7
  aload 7
  astore 9
  aload 9
  checkcast com/admogo/AdMogoLayout
  astore 9
  aload 9
  astore 8
  aload 8
  getfield com/admogo/AdMogoLayout/activityReference Ljava/lang/ref/WeakReference;
  astore 6
  aload 6
  invokevirtual java/lang/ref/WeakReference/get()Ljava/lang/Object;
  astore 7
  aload 7
  astore 11
  aload 11
  checkcast android/content/Context
  astore 11
  aload 11
  astore 10
  aload 8
  invokevirtual com/admogo/AdMogoLayout/countClick()V
  getstatic com/admogo/adapters/BaiduJsonAdapter/baiduAd Lcom/baidu/Ad;
  astore 4
  aload 4
  invokevirtual com/baidu/Ad/getClickType()Lcom/baidu/ClickType;
  astore 12
  getstatic com/baidu/ClickType/PHONE Lcom/baidu/ClickType;
  astore 13
  aload 12
  invokestatic app/DummyClass/invokeIfStmt(Ljava/lang/Object;)V
  aload 13
  invokestatic app/DummyClass/invokeIfStmt(Ljava/lang/Object;)V
  aload 12
  aload 13
  if_acmpne Label1
  iconst_1
  istore 14
  iload 14
  putstatic com/admogo/adapters/BaiduJsonAdapter/baiduClick2 I
Label5:
  getstatic com/admogo/adapters/BaiduJsonAdapter/baiduClick1 I
  istore 15
  dload 15
  invokestatic app/DummyClass/invokeIfStmt(D)V
  iconst_1
  istore 14
  iload 15
  iload 14
  if_icmpeq Label2
  getstatic com/admogo/adapters/BaiduJsonAdapter/baiduClick2 I
  istore 15
  dload 15
  invokestatic app/DummyClass/invokeIfStmt(D)V
  iconst_1
  istore 14
  iload 15
  iload 14
  if_icmpne Label3
Label2:
  new android/content/Intent
  astore 16
  ldc com/admogo/AdMogoWebView
  astore 17
  aload 17
  astore_1
  aload 16
  aload 10
  aload_1
  invokespecial android/content/Intent/<init>(Landroid/content/Context;Ljava/lang/Class;)V
  new android/os/Bundle
  astore 18
  aload 18
  astore_1
  aload_1
  invokespecial android/os/Bundle/<init>()V
  getstatic com/admogo/adapters/BaiduJsonAdapter/baiduAd Lcom/baidu/Ad;
  astore 4
  aload 4
  invokevirtual com/baidu/Ad/getClickURL()Ljava/lang/String;
  astore 19
  ldc "link"
  astore 20
  aload 18
  astore_1
  aload 20
  astore_2
  aload 19
  astore_3
  aload_1
  aload_2
  aload_3
  invokevirtual android/os/Bundle/putString(Ljava/lang/String;Ljava/lang/String;)V
  aload 18
  astore_1
  aload 16
  aload_1
  invokevirtual android/content/Intent/putExtras(Landroid/os/Bundle;)Landroid/content/Intent;
  pop
Label6:
  aload 10
  aload 16
  invokevirtual android/content/Context/startActivity(Landroid/content/Intent;)V
Label7:
  return
Label1:
  getstatic com/admogo/adapters/BaiduJsonAdapter/baiduAd Lcom/baidu/Ad;
  astore 4
  aload 4
  invokevirtual com/baidu/Ad/getClickType()Lcom/baidu/ClickType;
  astore 12
  getstatic com/baidu/ClickType/DOWNLOAD Lcom/baidu/ClickType;
  astore 13
  aload 12
  invokestatic app/DummyClass/invokeIfStmt(Ljava/lang/Object;)V
  aload 13
  invokestatic app/DummyClass/invokeIfStmt(Ljava/lang/Object;)V
  aload 12
  aload 13
  if_acmpne Label4
  iconst_1
  istore 14
  iload 14
  putstatic com/admogo/adapters/BaiduJsonAdapter/baiduClick3 I
  goto Label5
Label4:
  getstatic com/admogo/adapters/BaiduJsonAdapter/baiduAd Lcom/baidu/Ad;
  astore 4
  aload 4
  invokevirtual com/baidu/Ad/getClickType()Lcom/baidu/ClickType;
  astore 12
  getstatic com/baidu/ClickType/BROWSE Lcom/baidu/ClickType;
  astore 13
  aload 12
  invokestatic app/DummyClass/invokeIfStmt(Ljava/lang/Object;)V
  aload 13
  invokestatic app/DummyClass/invokeIfStmt(Ljava/lang/Object;)V
  aload 12
  aload 13
  if_acmpne Label5
  iconst_1
  istore 14
  iload 14
  putstatic com/admogo/adapters/BaiduJsonAdapter/baiduClick1 I
  goto Label5
Label3:
  new android/content/Intent
  astore 16
  getstatic com/admogo/adapters/BaiduJsonAdapter/baiduAd Lcom/baidu/Ad;
  astore 4
  aload 4
  invokevirtual com/baidu/Ad/getClickURL()Ljava/lang/String;
  astore 5
  aload 5
  invokestatic android/net/Uri/parse(Ljava/lang/String;)Landroid/net/Uri;
  astore 21
  ldc "android.intent.action.VIEW"
  astore 20
  aload 20
  astore_1
  aload 21
  astore_2
  aload 16
  aload_1
  aload_2
  invokespecial android/content/Intent/<init>(Ljava/lang/String;Landroid/net/Uri;)V
  ldc 268435456
  istore 14
  aload 16
  iload 14
  invokevirtual android/content/Intent/addFlags(I)Landroid/content/Intent;
  pop
  goto Label6
Label0:
  getstatic com/admogo/util/AdMogoUtil/ADMOGO Ljava/lang/String;
  astore 19
  ldc "In onInterceptTouchEvent(), but baiduAd or baiduAd.link is null"
  astore 20
  aload 19
  astore_1
  aload 20
  astore_2
  aload_1
  aload_2
  invokestatic android/util/Log/w(Ljava/lang/String;Ljava/lang/String;)I
  pop
  goto Label7
  nop
.end <method>

.method public displayBaidu()V
.limit locals 47
.limit stack 200
  nop
  aload_0
  astore_1
  aload_1
  getfield com/admogo/adapters/AdMogoAdapter/adMogoLayoutReference Ljava/lang/ref/WeakReference;
  astore 5
  aload 5
  invokevirtual java/lang/ref/WeakReference/get()Ljava/lang/Object;
  astore 6
  aload 6
  astore 8
  new java/lang/NoClassDefFoundError
  dup
  invokespecial java/lang/NoClassDefFoundError/<init>()V
  athrow
  aload 8
  astore 7
  aload 7
  invokestatic app/DummyClass/invokeIfStmt(Ljava/lang/Object;)V
  iload 7
  ifne Label0
Label1:
  return
Label0:
  aload 7
  getfield com/admogo/AdMogoLayout/activityReference Ljava/lang/ref/WeakReference;
  astore 5
  aload 5
  invokevirtual java/lang/ref/WeakReference/get()Ljava/lang/Object;
  astore 6
  aload 6
  astore 10
  aload 10
  checkcast android/app/Activity
  astore 10
  aload 10
  astore 9
  aload_0
  astore_1
  aload_1
  aload 9
  putfield com/admogo/adapters/BaiduJsonAdapter/activity Landroid/app/Activity;
  aload_0
  astore_1
  aload_1
  getfield com/admogo/adapters/BaiduJsonAdapter/activity Landroid/app/Activity;
  astore 9
  aload 9
  invokestatic app/DummyClass/invokeIfStmt(Ljava/lang/Object;)V
  aload 9
  ifnull Label1
  aload_0
  astore_1
  aload_1
  getfield com/admogo/adapters/BaiduJsonAdapter/activity Landroid/app/Activity;
  astore 9
  aload 9
  invokestatic com/admogo/util/AdMogoUtil/getDensity(Landroid/app/Activity;)D
  dstore 11
  sipush 320
  istore 14
  iload 14
  dload 11
  invokestatic com/admogo/util/AdMogoUtil/convertToScreenPixels(ID)I
  istore 13
  iload 13
  i2d
  dstore 15
  bipush 50
  istore 14
  iload 14
  dload 11
  invokestatic com/admogo/util/AdMogoUtil/convertToScreenPixels(ID)I
  istore 13
  iload 13
  i2d
  dstore 11
  getstatic com/admogo/adapters/BaiduJsonAdapter/AD_TYPE I
  istore 13
  dload 13
  invokestatic app/DummyClass/invokeIfStmt(D)V
  iload 13
  lookupswitch
  1 : Label3
  2 : Label4
  default : Label2
Label2:
  goto Label5
Label5:
  getstatic com/admogo/util/AdMogoUtil/ADMOGO Ljava/lang/String;
  astore 17
  ldc "Unknown baidu type!"
  astore 18
  aload 17
  astore_1
  aload 18
  astore_2
  aload_1
  aload_2
  invokestatic android/util/Log/w(Ljava/lang/String;Ljava/lang/String;)I
  pop
  aload 7
  invokevirtual com/admogo/AdMogoLayout/rotateThreadedNow()V
  goto Label1
Label3:
  new android/widget/RelativeLayout
  astore 19
  aload_0
  astore_1
  aload_1
  getfield com/admogo/adapters/BaiduJsonAdapter/activity Landroid/app/Activity;
  astore 9
  aload 19
  astore_1
  aload_1
  aload 9
  invokespecial android/widget/RelativeLayout/<init>(Landroid/content/Context;)V
  getstatic com/admogo/adapters/BaiduJsonAdapter/imageAdList Ljava/util/List;
  astore 20
  aload 20
  astore_1
  aload_1
  invokeinterface java/util/List/size()I 1
  istore 13
  iload 13
  iconst_m1
  iadd
  istore 13
  iload 13
  putstatic com/admogo/adapters/BaiduJsonAdapter/imageSize I
  getstatic com/admogo/adapters/BaiduJsonAdapter/imageSize I
  istore 13
  dload 13
  invokestatic app/DummyClass/invokeIfStmt(D)V
  iload 13
  ifge Label6
  aload 7
  invokevirtual com/admogo/AdMogoLayout/rollover()V
  goto Label1
Label6:
  getstatic com/admogo/adapters/BaiduJsonAdapter/imageAdList Ljava/util/List;
  astore 20
  getstatic com/admogo/adapters/BaiduJsonAdapter/imageIndex I
  istore 13
  aload 20
  astore_1
  aload_1
  iload 13
  invokeinterface java/util/List/get(I)Ljava/lang/Object; 2
  astore 6
  aload 6
  astore 22
  aload 22
  checkcast com/baidu/Ad
  astore 22
  aload 22
  astore 21
  aload 21
  putstatic com/admogo/adapters/BaiduJsonAdapter/baiduAd Lcom/baidu/Ad;
  getstatic com/admogo/adapters/BaiduJsonAdapter/imageIndex I
  istore 13
  getstatic com/admogo/adapters/BaiduJsonAdapter/imageSize I
  istore 23
  dload 13
  invokestatic app/DummyClass/invokeIfStmt(D)V
  iload 23
  istore_1
  dload_1
  invokestatic app/DummyClass/invokeIfStmt(D)V
  iload 23
  istore_1
  iload 13
  iload_1
  if_icmpge Label7
  getstatic com/admogo/adapters/BaiduJsonAdapter/imageIndex I
  istore 23
  iload 23
  iconst_1
  iadd
  istore 23
  iload 23
  putstatic com/admogo/adapters/BaiduJsonAdapter/imageIndex I
Label8:
  new android/widget/ImageView
  astore 24
  aload_0
  astore_1
  aload_1
  getfield com/admogo/adapters/BaiduJsonAdapter/activity Landroid/app/Activity;
  astore 9
  aload 24
  astore_1
  aload_1
  aload 9
  invokespecial android/widget/ImageView/<init>(Landroid/content/Context;)V
  getstatic com/admogo/adapters/BaiduJsonAdapter/baiduAd Lcom/baidu/Ad;
  astore 21
  aload 21
  astore_1
  aload_1
  invokevirtual com/baidu/Ad/getPicUrl()Ljava/lang/String;
  astore 17
  aload_0
  astore_1
  aload 17
  astore_2
  aload_1
  aload_2
  invokespecial com/admogo/adapters/BaiduJsonAdapter/fetchImage(Ljava/lang/String;)Landroid/graphics/drawable/Drawable;
  astore 25
  aload 24
  astore_1
  aload 25
  astore_2
  aload_1
  aload_2
  invokevirtual android/widget/ImageView/setImageDrawable(Landroid/graphics/drawable/Drawable;)V
  getstatic android/widget/ImageView$ScaleType/CENTER_CROP Landroid/widget/ImageView$ScaleType;
  astore 26
  aload 24
  astore_1
  aload 26
  astore_2
  aload_1
  aload_2
  invokevirtual android/widget/ImageView/setScaleType(Landroid/widget/ImageView$ScaleType;)V
  new android/widget/RelativeLayout$LayoutParams
  astore 27
  dload 15
  d2i
  istore_1
  iload_1
  istore 23
  dload 11
  d2i
  istore 13
  aload 27
  astore_1
  iload 23
  istore_2
  aload_1
  iload_2
  iload 13
  invokespecial android/widget/RelativeLayout$LayoutParams/<init>(II)V
  bipush 13
  istore 14
  aload 27
  astore_1
  aload_1
  iload 14
  invokevirtual android/widget/RelativeLayout$LayoutParams/addRule(I)V
  aload 19
  astore_1
  aload 24
  astore_2
  aload 27
  astore_3
  aload_1
  aload_2
  aload_3
  invokevirtual android/widget/RelativeLayout/addView(Landroid/view/View;Landroid/view/ViewGroup$LayoutParams;)V
  bipush 44
  istore 14
  aload 19
  astore_1
  aload 7
  aload_1
  iload 14
  invokevirtual com/admogo/AdMogoLayout/pushSubView(Landroid/view/ViewGroup;I)V
Label11:
  aconst_null
  astore 28
  aload 28
  astore_1
  aload_0
  astore_2
  aload_2
  aload_1
  putfield com/admogo/adapters/BaiduJsonAdapter/tempDrawable Landroid/graphics/drawable/Drawable;
  aload 7
  getfield com/admogo/AdMogoLayout/adMogoManager Lcom/admogo/AdMogoManager;
  astore_1
  aload_1
  astore 29
  aload 29
  astore_1
  aload_1
  invokevirtual com/admogo/AdMogoManager/resetRollover()V
  aload 7
  invokevirtual com/admogo/AdMogoLayout/rotateThreadedDelayed()V
  goto Label1
Label7:
  aload 7
  getfield com/admogo/AdMogoLayout/handler Landroid/os/Handler;
  astore_1
  aload_1
  astore 30
  new com/admogo/adapters/BaiduJsonAdapter$UpdateBaiduRunnable
  astore 31
  aload 31
  astore_1
  aload_0
  astore_2
  aload_1
  aload_2
  invokespecial com/admogo/adapters/BaiduJsonAdapter$UpdateBaiduRunnable/<init>(Lcom/admogo/adapters/BaiduJsonAdapter;)V
  aload 30
  astore_1
  aload 31
  astore_2
  aload_1
  aload_2
  invokevirtual android/os/Handler/post(Ljava/lang/Runnable;)Z
  pop
  iconst_0
  istore 14
  iload 14
  putstatic com/admogo/adapters/BaiduJsonAdapter/imageIndex I
  goto Label8
Label4:
  new android/widget/RelativeLayout
  astore 19
  aload_0
  astore_1
  aload_1
  getfield com/admogo/adapters/BaiduJsonAdapter/activity Landroid/app/Activity;
  astore 9
  aload 19
  astore_1
  aload_1
  aload 9
  invokespecial android/widget/RelativeLayout/<init>(Landroid/content/Context;)V
  getstatic com/admogo/adapters/BaiduJsonAdapter/textAdList Ljava/util/List;
  astore 20
  aload 20
  astore_1
  aload_1
  invokeinterface java/util/List/size()I 1
  istore 23
  iload 23
  iconst_m1
  iadd
  istore 23
  iload 23
  putstatic com/admogo/adapters/BaiduJsonAdapter/textSize I
  getstatic com/admogo/adapters/BaiduJsonAdapter/textSize I
  istore 23
  iload 23
  istore_1
  dload_1
  invokestatic app/DummyClass/invokeIfStmt(D)V
  iload 23
  ifge Label9
  aload 7
  invokevirtual com/admogo/AdMogoLayout/rollover()V
  goto Label1
Label9:
  getstatic com/admogo/adapters/BaiduJsonAdapter/textAdList Ljava/util/List;
  astore 20
  getstatic com/admogo/adapters/BaiduJsonAdapter/textIndex I
  istore 23
  aload 20
  astore_1
  iload 23
  istore_2
  aload_1
  iload_2
  invokeinterface java/util/List/get(I)Ljava/lang/Object; 2
  astore 6
  aload 6
  astore 32
  aload 32
  checkcast com/baidu/Ad
  astore 32
  aload 32
  astore 21
  aload 21
  putstatic com/admogo/adapters/BaiduJsonAdapter/baiduAd Lcom/baidu/Ad;
  getstatic com/admogo/adapters/BaiduJsonAdapter/textIndex I
  istore 23
  getstatic com/admogo/adapters/BaiduJsonAdapter/textSize I
  istore 13
  iload 23
  istore_1
  dload_1
  invokestatic app/DummyClass/invokeIfStmt(D)V
  dload 13
  invokestatic app/DummyClass/invokeIfStmt(D)V
  iload 23
  istore_1
  iload_1
  iload 13
  if_icmpge Label10
  getstatic com/admogo/adapters/BaiduJsonAdapter/textIndex I
  istore 23
  iload 23
  iconst_1
  iadd
  istore 23
  iload 23
  putstatic com/admogo/adapters/BaiduJsonAdapter/textIndex I
Label12:
  new android/widget/FrameLayout$LayoutParams
  astore 33
  dload 15
  d2i
  istore_1
  iload_1
  istore 23
  dload 11
  d2i
  istore 13
  aload 33
  astore_1
  iload 23
  istore_2
  aload_1
  iload_2
  iload 13
  invokespecial android/widget/FrameLayout$LayoutParams/<init>(II)V
  aload 19
  astore_1
  aload 33
  astore_2
  aload_1
  aload_2
  invokevirtual android/widget/RelativeLayout/setLayoutParams(Landroid/view/ViewGroup$LayoutParams;)V
  new android/widget/ImageView
  astore 24
  aload_0
  astore_1
  aload_1
  getfield com/admogo/adapters/BaiduJsonAdapter/activity Landroid/app/Activity;
  astore 9
  aload 24
  astore_1
  aload_1
  aload 9
  invokespecial android/widget/ImageView/<init>(Landroid/content/Context;)V
  aload 7
  getfield com/admogo/AdMogoLayout/extra Lcom/admogo/obj/Extra;
  astore_1
  aload_1
  astore 34
  aload 34
  astore_1
  aload_1
  getfield com/admogo/obj/Extra/bgRed I
  istore_1
  iload_1
  istore 23
  aload 7
  getfield com/admogo/AdMogoLayout/extra Lcom/admogo/obj/Extra;
  astore_1
  aload_1
  astore 34
  aload 34
  astore_1
  aload_1
  getfield com/admogo/obj/Extra/bgGreen I
  istore 13
  aload 7
  getfield com/admogo/AdMogoLayout/extra Lcom/admogo/obj/Extra;
  astore_1
  aload_1
  astore 34
  aload 34
  astore_1
  aload_1
  getfield com/admogo/obj/Extra/bgBlue I
  istore_1
  iload_1
  istore 35
  iload 23
  istore_1
  iload 35
  istore_2
  iload_1
  iload 13
  iload_2
  invokestatic android/graphics/Color/rgb(III)I
  istore 13
  new android/graphics/drawable/GradientDrawable
  astore 36
  getstatic android/graphics/drawable/GradientDrawable$Orientation/TOP_BOTTOM Landroid/graphics/drawable/GradientDrawable$Orientation;
  astore 37
  iconst_4
  istore 14
  iload 14
  newarray int
  astore_1
  aload_1
  astore 38
  sipush 180
  istore 14
  sipush 255
  istore 39
  sipush 255
  istore 40
  sipush 255
  istore 41
  iload 39
  istore_1
  iload 40
  istore_2
  iload 41
  istore_3
  iload 14
  iload_1
  iload_2
  iload_3
  invokestatic android/graphics/Color/argb(IIII)I
  istore 35
  iconst_0
  istore 14
  aload 38
  iload 14
  iload 35
  iastore
  iconst_1
  istore 14
  aload 38
  iload 14
  iload 13
  iastore
  iconst_2
  istore 14
  aload 38
  iload 14
  iload 13
  iastore
  iconst_3
  istore 14
  aload 38
  iload 14
  iload 13
  iastore
  aload 36
  astore_1
  aload 37
  astore_2
  aload 38
  astore_3
  aload_1
  aload_2
  aload_3
  invokespecial android/graphics/drawable/GradientDrawable/<init>(Landroid/graphics/drawable/GradientDrawable$Orientation;[I)V
  aload 24
  astore_1
  aload 36
  astore_2
  aload_1
  aload_2
  invokevirtual android/widget/ImageView/setBackgroundDrawable(Landroid/graphics/drawable/Drawable;)V
  new android/widget/RelativeLayout$LayoutParams
  astore 27
  iconst_m1
  istore 14
  iconst_m1
  istore 39
  aload 27
  astore_1
  iload 39
  istore_2
  aload_1
  iload 14
  iload_2
  invokespecial android/widget/RelativeLayout$LayoutParams/<init>(II)V
  aload 19
  astore_1
  aload 24
  astore_2
  aload 27
  astore_3
  aload_1
  aload_2
  aload_3
  invokevirtual android/widget/RelativeLayout/addView(Landroid/view/View;Landroid/view/ViewGroup$LayoutParams;)V
  new android/widget/ImageView
  astore 24
  aload_0
  astore_1
  aload_1
  getfield com/admogo/adapters/BaiduJsonAdapter/activity Landroid/app/Activity;
  astore 9
  aload 24
  astore_1
  aload_1
  aload 9
  invokespecial android/widget/ImageView/<init>(Landroid/content/Context;)V
  getstatic com/admogo/adapters/BaiduJsonAdapter/baiduAd Lcom/baidu/Ad;
  astore 21
  aload 21
  astore_1
  aload_1
  invokevirtual com/baidu/Ad/getPicUrl()Ljava/lang/String;
  astore 17
  aload_0
  astore_1
  aload 17
  astore_2
  aload_1
  aload_2
  invokespecial com/admogo/adapters/BaiduJsonAdapter/fetchImage(Ljava/lang/String;)Landroid/graphics/drawable/Drawable;
  astore 25
  aload 24
  astore_1
  aload 25
  astore_2
  aload_1
  aload_2
  invokevirtual android/widget/ImageView/setImageDrawable(Landroid/graphics/drawable/Drawable;)V
  bipush 10
  istore 14
  aload 24
  astore_1
  aload_1
  iload 14
  invokevirtual android/widget/ImageView/setId(I)V
  new android/widget/RelativeLayout$LayoutParams
  astore 27
  bipush 38
  istore 14
  bipush 38
  istore 39
  aload 27
  astore_1
  iload 39
  istore_2
  aload_1
  iload 14
  iload_2
  invokespecial android/widget/RelativeLayout$LayoutParams/<init>(II)V
  bipush 15
  istore 14
  aload 27
  astore_1
  aload_1
  iload 14
  invokevirtual android/widget/RelativeLayout$LayoutParams/addRule(I)V
  iconst_4
  istore 14
  iconst_0
  istore 39
  iconst_4
  istore 40
  iconst_0
  istore 41
  aload 27
  astore_1
  iload 39
  istore_2
  iload 40
  istore_3
  iload 41
  istore 4
  aload_1
  iload 14
  iload_2
  iload_3
  iload 4
  invokevirtual android/widget/RelativeLayout$LayoutParams/setMargins(IIII)V
  aload 19
  astore_1
  aload 24
  astore_2
  aload 27
  astore_3
  aload_1
  aload_2
  aload_3
  invokevirtual android/widget/RelativeLayout/addView(Landroid/view/View;Landroid/view/ViewGroup$LayoutParams;)V
  new android/widget/TextView
  astore 42
  aload_0
  astore_1
  aload_1
  getfield com/admogo/adapters/BaiduJsonAdapter/activity Landroid/app/Activity;
  astore 9
  aload 42
  astore_1
  aload_1
  aload 9
  invokespecial android/widget/TextView/<init>(Landroid/content/Context;)V
  ldc 16.000000
  fstore 43
  aload 42
  astore_1
  fload 43
  fstore_2
  aload_1
  fload_2
  invokevirtual android/widget/TextView/setTextSize(F)V
  new java/lang/StringBuilder
  astore 44
  getstatic com/admogo/adapters/BaiduJsonAdapter/baiduAd Lcom/baidu/Ad;
  astore 21
  aload 21
  astore_1
  aload_1
  invokevirtual com/baidu/Ad/getTitle()Ljava/lang/String;
  astore 17
  aload 17
  astore_1
  aload_1
  invokestatic java/lang/String/valueOf(Ljava/lang/Object;)Ljava/lang/String;
  astore 17
  aload 44
  astore_1
  aload 17
  astore_2
  aload_1
  aload_2
  invokespecial java/lang/StringBuilder/<init>(Ljava/lang/String;)V
  ldc "-"
  astore 18
  aload 44
  astore_1
  aload 18
  astore_2
  aload_1
  aload_2
  invokevirtual java/lang/StringBuilder/append(Ljava/lang/String;)Ljava/lang/StringBuilder;
  astore 44
  getstatic com/admogo/adapters/BaiduJsonAdapter/baiduAd Lcom/baidu/Ad;
  astore 21
  aload 21
  astore_1
  aload_1
  invokevirtual com/baidu/Ad/getDescription()Ljava/lang/String;
  astore 17
  aload 44
  astore_1
  aload 17
  astore_2
  aload_1
  aload_2
  invokevirtual java/lang/StringBuilder/append(Ljava/lang/String;)Ljava/lang/StringBuilder;
  astore 44
  aload 44
  astore_1
  aload_1
  invokevirtual java/lang/StringBuilder/toString()Ljava/lang/String;
  astore 17
  aload 42
  astore_1
  aload 17
  astore_2
  aload_1
  aload_2
  invokevirtual android/widget/TextView/setText(Ljava/lang/CharSequence;)V
  getstatic android/graphics/Typeface/DEFAULT_BOLD Landroid/graphics/Typeface;
  astore 45
  iconst_1
  istore 14
  aload 42
  astore_1
  aload 45
  astore_2
  aload_1
  aload_2
  iload 14
  invokevirtual android/widget/TextView/setTypeface(Landroid/graphics/Typeface;I)V
  aload 7
  getfield com/admogo/AdMogoLayout/extra Lcom/admogo/obj/Extra;
  astore_1
  aload_1
  astore 34
  aload 34
  astore_1
  aload_1
  getfield com/admogo/obj/Extra/fgRed I
  istore_1
  iload_1
  istore 35
  aload 7
  getfield com/admogo/AdMogoLayout/extra Lcom/admogo/obj/Extra;
  astore_1
  aload_1
  astore 34
  aload 34
  astore_1
  aload_1
  getfield com/admogo/obj/Extra/fgGreen I
  istore_1
  iload_1
  istore 23
  aload 7
  getfield com/admogo/AdMogoLayout/extra Lcom/admogo/obj/Extra;
  astore_1
  aload_1
  astore 34
  aload 34
  astore_1
  aload_1
  getfield com/admogo/obj/Extra/fgBlue I
  istore 13
  iload 35
  istore_1
  iload 23
  istore_2
  iload_1
  iload_2
  iload 13
  invokestatic android/graphics/Color/rgb(III)I
  istore 35
  aload 42
  astore_1
  iload 35
  istore_2
  aload_1
  iload_2
  invokevirtual android/widget/TextView/setTextColor(I)V
  new android/widget/RelativeLayout$LayoutParams
  astore 27
  iconst_m1
  istore 14
  iconst_m1
  istore 39
  aload 27
  astore_1
  iload 39
  istore_2
  aload_1
  iload 14
  iload_2
  invokespecial android/widget/RelativeLayout$LayoutParams/<init>(II)V
  aload 24
  astore_1
  aload_1
  invokevirtual android/widget/ImageView/getId()I
  istore 35
  iconst_1
  istore 14
  aload 27
  astore_1
  iload 35
  istore_2
  aload_1
  iload 14
  iload_2
  invokevirtual android/widget/RelativeLayout$LayoutParams/addRule(II)V
  bipush 10
  istore 14
  aload 27
  astore_1
  aload_1
  iload 14
  invokevirtual android/widget/RelativeLayout$LayoutParams/addRule(I)V
  bipush 12
  istore 14
  aload 27
  astore_1
  aload_1
  iload 14
  invokevirtual android/widget/RelativeLayout$LayoutParams/addRule(I)V
  bipush 15
  istore 14
  aload 27
  astore_1
  aload_1
  iload 14
  invokevirtual android/widget/RelativeLayout$LayoutParams/addRule(I)V
  bipush 13
  istore 14
  aload 27
  astore_1
  aload_1
  iload 14
  invokevirtual android/widget/RelativeLayout$LayoutParams/addRule(I)V
  bipush 16
  istore 14
  aload 42
  astore_1
  aload_1
  iload 14
  invokevirtual android/widget/TextView/setGravity(I)V
  aload 19
  astore_1
  aload 42
  astore_2
  aload 27
  astore_3
  aload_1
  aload_2
  aload_3
  invokevirtual android/widget/RelativeLayout/addView(Landroid/view/View;Landroid/view/ViewGroup$LayoutParams;)V
  bipush 44
  istore 14
  aload 19
  astore_1
  aload 7
  aload_1
  iload 14
  invokevirtual com/admogo/AdMogoLayout/pushSubView(Landroid/view/ViewGroup;I)V
  goto Label11
Label10:
  aload 7
  getfield com/admogo/AdMogoLayout/handler Landroid/os/Handler;
  astore_1
  aload_1
  astore 30
  new com/admogo/adapters/BaiduJsonAdapter$UpdateBaiduRunnable
  astore 46
  aload 46
  astore_1
  aload_0
  astore_2
  aload_1
  aload_2
  invokespecial com/admogo/adapters/BaiduJsonAdapter$UpdateBaiduRunnable/<init>(Lcom/admogo/adapters/BaiduJsonAdapter;)V
  aload 30
  astore_1
  aload 46
  astore_2
  aload_1
  aload_2
  invokevirtual android/os/Handler/post(Ljava/lang/Runnable;)Z
  pop
  iconst_0
  istore 14
  iload 14
  putstatic com/admogo/adapters/BaiduJsonAdapter/textIndex I
  goto Label12
  nop
  nop
.end <method>

.method private fetchImage(Ljava/lang/String;)Landroid/graphics/drawable/Drawable;
.limit locals 12
.limit stack 200
  .catch  java/lang/Exception <from> Label1 <to> Label2 <using> Label0
  nop
  new java/net/URL
  astore_2
Label1:
  aload_2
  aload_1
  invokespecial java/net/URL/<init>(Ljava/lang/String;)V
  aload_2
  invokevirtual java/net/URL/getContent()Ljava/lang/Object;
  astore_3
  aload_3
  astore 5
  aload 5
  checkcast java/io/InputStream
  astore 5
  aload 5
  astore 4
  ldc "src"
  astore 7
  new java/lang/NoClassDefFoundError
  dup
  invokespecial java/lang/NoClassDefFoundError/<init>()V
  athrow
  nop
  aload 4
  invokevirtual java/io/InputStream/close()V
Label2:
  aload 6
  areturn
Label0:
  astore 8
  ldc "Baidu"
  astore 7
  ldc "Unable to fetchImage()"
  astore 9
  new java/lang/NoClassDefFoundError
  dup
  invokespecial java/lang/NoClassDefFoundError/<init>()V
  athrow
  aload_0
  invokevirtual java/lang/Object/getClass()Ljava/lang/Class;
  astore 10
  ldc "/com/admogo/assets/baidu_icon.png"
  astore 7
  aload 10
  aload 7
  invokevirtual java/lang/Class/getResourceAsStream(Ljava/lang/String;)Ljava/io/InputStream;
  astore 4
  new android/graphics/drawable/BitmapDrawable
  astore 11
  aload 11
  aload 4
  invokespecial android/graphics/drawable/BitmapDrawable/<init>(Ljava/io/InputStream;)V
  aload_0
  aload 11
  putfield com/admogo/adapters/BaiduJsonAdapter/tempDrawable Landroid/graphics/drawable/Drawable;
  aload_0
  getfield com/admogo/adapters/BaiduJsonAdapter/tempDrawable Landroid/graphics/drawable/Drawable;
  astore 6
  aload 6
  areturn
  nop
.end <method>

.method public finish()V
.limit locals 3
.limit stack 200
  nop
  getstatic com/admogo/util/AdMogoUtil/ADMOGO Ljava/lang/String;
  astore_1
  ldc "Baidu Finished"
  astore_2
  new java/lang/NoClassDefFoundError
  dup
  invokespecial java/lang/NoClassDefFoundError/<init>()V
  athrow
  return
  nop
.end <method>

.method public handle()V
.limit locals 16
.limit stack 200
  nop
  aload_0
  getfield com/admogo/adapters/AdMogoAdapter/adMogoLayoutReference Ljava/lang/ref/WeakReference;
  astore_1
  aload_1
  invokevirtual java/lang/ref/WeakReference/get()Ljava/lang/Object;
  astore_2
  aload_2
  astore 4
  new java/lang/NoClassDefFoundError
  dup
  invokespecial java/lang/NoClassDefFoundError/<init>()V
  athrow
  aload 4
  astore_3
  aload_3
  invokestatic app/DummyClass/invokeIfStmt(Ljava/lang/Object;)V
  iload_3
  ifne Label0
Label2:
  return
Label0:
  invokestatic java/lang/Math/random()D
  dstore 5
  ldc2_w 2.000000000000000
  dstore 7
  dload 5
  dload 7
  dmul
  dstore 5
  dload 5
  d2i
  istore 9
  iload 9
  iconst_1
  iadd
  istore 9
  iload 9
  putstatic com/admogo/adapters/BaiduJsonAdapter/AD_TYPE I
  getstatic com/admogo/adapters/BaiduJsonAdapter/AD_TYPE I
  istore 10
  dload 10
  invokestatic app/DummyClass/invokeIfStmt(D)V
  iconst_1
  istore 11
  iload 10
  iload 11
  if_icmpne Label1
  getstatic com/admogo/adapters/BaiduJsonAdapter/imageAdList Ljava/util/List;
  astore 12
  aload 12
  invokestatic app/DummyClass/invokeIfStmt(Ljava/lang/Object;)V
  aload 12
  ifnonnull Label1
  aload_3
  getfield com/admogo/AdMogoLayout/handler Landroid/os/Handler;
  astore 13
  new com/admogo/adapters/BaiduJsonAdapter$FetchBaiduRunnable
  astore 14
  aload 14
  aload_0
  invokespecial com/admogo/adapters/BaiduJsonAdapter$FetchBaiduRunnable/<init>(Lcom/admogo/adapters/BaiduJsonAdapter;)V
  aload 13
  aload 14
  invokevirtual android/os/Handler/post(Ljava/lang/Runnable;)Z
  pop
  goto Label2
Label1:
  getstatic com/admogo/adapters/BaiduJsonAdapter/AD_TYPE I
  istore 10
  dload 10
  invokestatic app/DummyClass/invokeIfStmt(D)V
  iconst_2
  istore 11
  iload 10
  iload 11
  if_icmpne Label3
  getstatic com/admogo/adapters/BaiduJsonAdapter/textAdList Ljava/util/List;
  astore 12
  aload 12
  invokestatic app/DummyClass/invokeIfStmt(Ljava/lang/Object;)V
  aload 12
  ifnonnull Label3
  aload_3
  getfield com/admogo/AdMogoLayout/handler Landroid/os/Handler;
  astore 13
  new com/admogo/adapters/BaiduJsonAdapter$FetchBaiduRunnable
  astore 14
  aload 14
  aload_0
  invokespecial com/admogo/adapters/BaiduJsonAdapter$FetchBaiduRunnable/<init>(Lcom/admogo/adapters/BaiduJsonAdapter;)V
  aload 13
  aload 14
  invokevirtual android/os/Handler/post(Ljava/lang/Runnable;)Z
  pop
  goto Label2
Label3:
  aload_3
  getfield com/admogo/AdMogoLayout/handler Landroid/os/Handler;
  astore 13
  new com/admogo/adapters/BaiduJsonAdapter$DisplayBaiduRunnable
  astore 15
  aload 15
  aload_0
  invokespecial com/admogo/adapters/BaiduJsonAdapter$DisplayBaiduRunnable/<init>(Lcom/admogo/adapters/BaiduJsonAdapter;)V
  aload 13
  aload 15
  invokevirtual android/os/Handler/post(Ljava/lang/Runnable;)Z
  pop
  goto Label2
  nop
.end <method>

