.source SourceFile
.class final  com/adwo/adsdk/D
.super java/lang/Object
.implements  java/lang/Runnable
.field private "a" Lcom/adwo/adsdk/q;
.field private final "b" Ljava/lang/String;

.method <init>(Lcom/adwo/adsdk/q;Ljava/lang/String;)V
.limit locals 3
.limit stack 200
  nop
  aload_0
  aload_1
  putfield com/adwo/adsdk/D/a Lcom/adwo/adsdk/q;
  aload_0
  aload_2
  putfield com/adwo/adsdk/D/b Ljava/lang/String;
  aload_0
  invokespecial java/lang/Object/<init>()V
  return
  nop
.end <method>

.method public final run()V
.limit locals 14
.limit stack 200
  nop
  aload_0
  getfield com/adwo/adsdk/D/a Lcom/adwo/adsdk/q;
  astore 7
  new java/lang/NoClassDefFoundError
  dup
  invokespecial java/lang/NoClassDefFoundError/<init>()V
  athrow
  aload_0
  getfield com/adwo/adsdk/D/b Ljava/lang/String;
  astore 9
  aconst_null
  astore 10
  ldc "text/html"
  astore 11
  ldc "utf-8"
  astore 12
  aconst_null
  astore 13
  aload 8
  astore_1
  aload 10
  astore_2
  aload 9
  astore_3
  aload 11
  astore 4
  aload 12
  astore 5
  aload 13
  astore 6
  aload_1
  aload_2
  aload_3
  aload 4
  aload 5
  aload 6
  invokevirtual android/webkit/WebView/loadDataWithBaseURL(Ljava/lang/String;Ljava/lang/String;Ljava/lang/String;Ljava/lang/String;Ljava/lang/String;)V
  return
  nop
.end <method>

