.source dalvik_source_VirusShare_32e70f448ebd75661a1cb12f9cd8e013.apk
.class public  com/tencent/mobwin/core/a/a
.super java/lang/Object
.field public static "b" I =  0
.field public static "d" I =  0
.field public static "f" I =  0
.field public static "h" I =  0
.field public static final "i" I =  -2136298838
.field public static final "j" I =  80
.field public static final "k" I =  32
.field public static final "l" I =  36
.field public static final "m" I =  26
.field public static final "n" I =  24
.field public static final "o" I =  4
.field public static final "p" I =  12
.field public static final "q" I =  12
.field public static final "r" I =  18
.field public static final "s" I =  9
.field public static final "t" I =  9
.field public static final "u" F =  9.500000
.field public static final "v" Landroid/graphics/Typeface;
.field public "a" I
.field public "c" I
.field public "e" I
.field public "g" I

.method static <clinit>()V
.limit locals 2
.limit stack 200
  nop
  ldc -16777216
  istore_0
  iload_0
  putstatic com/tencent/mobwin/core/a/a/b I
  iconst_m1
  istore_0
  iload_0
  putstatic com/tencent/mobwin/core/a/a/d I
  ldc -2856704
  istore_0
  iload_0
  putstatic com/tencent/mobwin/core/a/a/f I
  sipush 255
  istore_0
  iload_0
  putstatic com/tencent/mobwin/core/a/a/h I
  new java/lang/NoClassDefFoundError
  dup
  invokespecial java/lang/NoClassDefFoundError/<init>()V
  athrow
  iconst_0
  istore_0
  aload_1
  iload_0
  invokestatic android/graphics/Typeface/create(Landroid/graphics/Typeface;I)Landroid/graphics/Typeface;
  astore_1
  aload_1
  putstatic com/tencent/mobwin/core/a/a/v Landroid/graphics/Typeface;
  return
  nop
.end <method>

.method public <init>()V
.limit locals 2
.limit stack 200
  nop
  aload_0
  invokespecial java/lang/Object/<init>()V
  ldc -16777216
  istore_1
  aload_0
  iload_1
  putfield com/tencent/mobwin/core/a/a/a I
  iconst_m1
  istore_1
  aload_0
  iload_1
  putfield com/tencent/mobwin/core/a/a/c I
  ldc -2856704
  istore_1
  aload_0
  iload_1
  putfield com/tencent/mobwin/core/a/a/e I
  sipush 255
  istore_1
  aload_0
  iload_1
  putfield com/tencent/mobwin/core/a/a/g I
  return
  nop
.end <method>

.method public static a()Lcom/tencent/mobwin/core/a/a;
.limit locals 1
.limit stack 200
  nop
  new com/tencent/mobwin/core/a/a
  astore_0
  aload_0
  invokespecial com/tencent/mobwin/core/a/a/<init>()V
  aload_0
  areturn
  nop
.end <method>

