.source dalvik_source_VirusShare_32e70f448ebd75661a1cb12f9cd8e013.apk
.class  com/wiyun/ad/af$1
.super java/lang/Thread
.field final "a" Lcom/wiyun/ad/af;
.field private final "b" Landroid/content/Intent;

.method <init>(Lcom/wiyun/ad/af;Landroid/content/Intent;)V
.limit locals 3
.limit stack 200
  nop
  aload_0
  aload_1
  putfield com/wiyun/ad/af$1/a Lcom/wiyun/ad/af;
  aload_0
  aload_2
  putfield com/wiyun/ad/af$1/b Landroid/content/Intent;
  aload_0
  invokespecial java/lang/Thread/<init>()V
  return
  nop
.end <method>

.method public run()V
.limit locals 13
.limit stack 200
  .catch  java/lang/Exception <from> Label5 <to> Label6 <using> Label4
  nop
Label5:
  aload_0
  getfield com/wiyun/ad/af$1/b Landroid/content/Intent;
  astore_1
  new java/lang/NoClassDefFoundError
  dup
  invokespecial java/lang/NoClassDefFoundError/<init>()V
  athrow
  nop
  aload_2
  invokevirtual android/net/Uri/getSchemeSpecificPart()Ljava/lang/String;
  astore_3
  invokestatic com/wiyun/ad/c/g()Ljava/util/List;
  astore 4
  aload 4
  invokeinterface java/util/List/size()I 1
  istore 5
  iconst_0
  dstore 6
Label3:
  dload 6
  invokestatic app/DummyClass/invokeIfStmt(D)V
  dload 5
  invokestatic app/DummyClass/invokeIfStmt(D)V
  iload 6
  iload 5
  if_icmplt Label0
Label2:
  return
Label0:
  invokestatic com/wiyun/ad/c/g()Ljava/util/List;
  astore 4
  aload 4
  iload 6
  invokeinterface java/util/List/get(I)Ljava/lang/Object; 2
  astore 7
  aload 7
  astore 9
  aload 9
  checkcast com/wiyun/ad/c$a
  astore 9
  aload 9
  astore 8
  aload 8
  getfield com/wiyun/ad/c$a/a Ljava/lang/String;
  astore 10
  aload_3
  aload 10
  invokevirtual java/lang/String/equals(Ljava/lang/Object;)Z
  istore 11
  iload 11
  invokestatic app/DummyClass/invokeIfStmt(Z)V
  iload 11
  ifeq Label1
  invokestatic com/wiyun/ad/c/g()Ljava/util/List;
  astore 4
  aload 4
  iload 6
  invokeinterface java/util/List/remove(I)Ljava/lang/Object; 2
  pop
  aload_3
  invokestatic com/wiyun/ad/g/a(Ljava/lang/String;)V
  aload 8
  getfield com/wiyun/ad/c$a/b Landroid/content/Intent;
  astore_1
  aload_3
  aload_1
  invokestatic com/wiyun/ad/c/a(Ljava/lang/String;Landroid/content/Intent;)V
Label6:
  goto Label2
Label4:
  astore 12
  goto Label2
Label1:
  iload 6
  iconst_1
  iadd
  istore 6
  goto Label3
  nop
.end <method>

