.source dalvik_source_VirusShare_32e70f448ebd75661a1cb12f9cd8e013.apk
.class public  com/kuguo/c/c
.super java/lang/Object
.field private static final "a" Ljava/util/regex/Pattern;

.method static <clinit>()V
.limit locals 2
.limit stack 200
  nop
  ldc "%(\\d*)"
  astore_1
  aload_1
  invokestatic java/util/regex/Pattern/compile(Ljava/lang/String;)Ljava/util/regex/Pattern;
  astore_0
  aload_0
  putstatic com/kuguo/c/c/a Ljava/util/regex/Pattern;
  return
  nop
.end <method>

.method public <init>()V
.limit locals 1
.limit stack 200
  nop
  aload_0
  invokespecial java/lang/Object/<init>()V
  return
  nop
.end <method>

.method public static a(Ljava/lang/String;)Ljava/lang/String;
.limit locals 10
.limit stack 200
  nop
  aload_0
  invokevirtual java/lang/String/getBytes()[B
  astore_1
  ldc "www.cooguo.com"
  astore_0
  aload_0
  invokevirtual java/lang/String/getBytes()[B
  astore_2
  new java/lang/StringBuilder
  astore_3
  aload_3
  invokespecial java/lang/StringBuilder/<init>()V
  iconst_0
  istore 4
Label1:
  aload_1
  arraylength
  istore 5
  new java/lang/NoClassDefFoundError
  dup
  invokespecial java/lang/NoClassDefFoundError/<init>()V
  athrow
  dload 5
  invokestatic app/DummyClass/invokeIfStmt(D)V
  iload 4
  iload 5
  if_icmpge Label0
  aload_1
  iload 4
  baload
  istore 6
  aload_2
  arraylength
  istore 5
  iload 4
  iload 5
  irem
  istore 5
  aload_2
  iload 5
  baload
  istore 7
  iload 6
  iload 7
  iadd
  istore 5
  new java/lang/StringBuilder
  astore 8
  aload 8
  invokespecial java/lang/StringBuilder/<init>()V
  ldc "%"
  astore 9
  aload 8
  aload 9
  invokevirtual java/lang/StringBuilder/append(Ljava/lang/String;)Ljava/lang/StringBuilder;
  astore 8
  aload 8
  iload 5
  invokevirtual java/lang/StringBuilder/append(I)Ljava/lang/StringBuilder;
  astore 8
  aload 8
  invokevirtual java/lang/StringBuilder/toString()Ljava/lang/String;
  astore_0
  aload_3
  aload_0
  invokevirtual java/lang/StringBuilder/append(Ljava/lang/String;)Ljava/lang/StringBuilder;
  pop
  iload 4
  iconst_1
  iadd
  istore 4
  goto Label1
Label0:
  aload_3
  invokevirtual java/lang/StringBuilder/toString()Ljava/lang/String;
  astore_0
  aload_0
  areturn
  nop
.end <method>

