.source AdMogoManager.java
.class  com/admogo/AdMogoManager$getCityNameRunnable
.super java/lang/Object
.implements  java/lang/Runnable
.field final "this$0" Lcom/admogo/AdMogoManager;

.method <init>(Lcom/admogo/AdMogoManager;DD)V
.limit locals 6
.limit stack 200
  nop
  aload_0
  aload_1
  putfield com/admogo/AdMogoManager$getCityNameRunnable/this$0 Lcom/admogo/AdMogoManager;
  aload_0
  invokespecial java/lang/Object/<init>()V
  aload_1
  dload_2
  invokestatic com/admogo/AdMogoManager/access$16(Lcom/admogo/AdMogoManager;D)V
  aload_1
  dload 4
  invokestatic com/admogo/AdMogoManager/access$17(Lcom/admogo/AdMogoManager;D)V
  return
  nop
.end <method>

.method public run()V
.limit locals 19
.limit stack 200
  .catch  java/lang/Exception <from> Label2 <to> Label0 <using> Label1
  nop
  new java/lang/StringBuilder
  astore_2
Label2:
  ldc "http://maps.google.com/maps/api/geocode/json?latlng="
  astore_3
  aload_2
  aload_3
  invokespecial java/lang/StringBuilder/<init>(Ljava/lang/String;)V
  aload_0
  astore_1
  aload_1
  getfield com/admogo/AdMogoManager$getCityNameRunnable/this$0 Lcom/admogo/AdMogoManager;
  astore 4
  aload 4
  invokestatic com/admogo/AdMogoManager/access$5(Lcom/admogo/AdMogoManager;)D
  dstore 5
  aload_2
  dload 5
  invokevirtual java/lang/StringBuilder/append(D)Ljava/lang/StringBuilder;
  astore_2
  ldc ","
  astore_3
  aload_2
  aload_3
  invokevirtual java/lang/StringBuilder/append(Ljava/lang/String;)Ljava/lang/StringBuilder;
  astore_2
  aload_0
  astore_1
  aload_1
  getfield com/admogo/AdMogoManager$getCityNameRunnable/this$0 Lcom/admogo/AdMogoManager;
  astore 4
  aload 4
  invokestatic com/admogo/AdMogoManager/access$6(Lcom/admogo/AdMogoManager;)D
  dstore 5
  aload_2
  dload 5
  invokevirtual java/lang/StringBuilder/append(D)Ljava/lang/StringBuilder;
  astore_2
  ldc "&sensor=false&language=zh-cn"
  astore_3
  aload_2
  aload_3
  invokevirtual java/lang/StringBuilder/append(Ljava/lang/String;)Ljava/lang/StringBuilder;
  astore_2
  aload_2
  invokevirtual java/lang/StringBuilder/toString()Ljava/lang/String;
  astore 7
  new java/lang/NoClassDefFoundError
  dup
  invokespecial java/lang/NoClassDefFoundError/<init>()V
  athrow
  aload 8
  aload 7
  invokespecial org/apache/http/client/methods/HttpGet/<init>(Ljava/lang/String;)V
  new org/apache/http/params/BasicHttpParams
  astore 9
  aload 9
  invokespecial org/apache/http/params/BasicHttpParams/<init>()V
  new org/apache/http/impl/client/DefaultHttpClient
  astore 10
  aload 10
  aload 9
  invokespecial org/apache/http/impl/client/DefaultHttpClient/<init>(Lorg/apache/http/params/HttpParams;)V
  aload 10
  aload 8
  invokevirtual org/apache/http/impl/client/DefaultHttpClient/execute(Lorg/apache/http/client/methods/HttpUriRequest;)Lorg/apache/http/HttpResponse;
  astore 11
  aload 11
  invokeinterface org/apache/http/HttpResponse/getEntity()Lorg/apache/http/HttpEntity; 1
  astore 12
  aload 12
  invokestatic app/DummyClass/invokeIfStmt(Ljava/lang/Object;)V
  aload 12
  ifnull Label0
  aload 11
  invokeinterface org/apache/http/HttpResponse/getStatusLine()Lorg/apache/http/StatusLine; 1
  astore 13
  aload 13
  invokeinterface org/apache/http/StatusLine/getStatusCode()I 1
  istore 14
  dload 14
  invokestatic app/DummyClass/invokeIfStmt(D)V
  sipush 200
  istore 15
  iload 14
  iload 15
  if_icmpne Label0
  aload 12
  invokeinterface org/apache/http/HttpEntity/getContent()Ljava/io/InputStream; 1
  astore 16
  aload_0
  astore_1
  aload_1
  getfield com/admogo/AdMogoManager$getCityNameRunnable/this$0 Lcom/admogo/AdMogoManager;
  astore 4
  aload 4
  aload 16
  invokevirtual com/admogo/AdMogoManager/convertStreamToString(Ljava/io/InputStream;)Ljava/lang/String;
  astore 7
  aload_0
  astore_1
  aload_1
  getfield com/admogo/AdMogoManager$getCityNameRunnable/this$0 Lcom/admogo/AdMogoManager;
  astore 4
  aload 4
  aload 7
  invokestatic com/admogo/AdMogoManager/access$18(Lcom/admogo/AdMogoManager;Ljava/lang/String;)Ljava/lang/String;
  astore 7
  aload 7
  invokestatic com/admogo/AdMogoManager/access$19(Ljava/lang/String;)V
  aload_0
  astore_1
  aload_1
  getfield com/admogo/AdMogoManager$getCityNameRunnable/this$0 Lcom/admogo/AdMogoManager;
  astore 4
  aload 4
  getfield com/admogo/AdMogoManager/ifGetInfo Z
  istore_1
  iload_1
  istore 17
  iload_1
  invokestatic app/DummyClass/invokeIfStmt(Z)V
  iload 17
  ifeq Label0
  aload_0
  astore_1
  aload_1
  getfield com/admogo/AdMogoManager$getCityNameRunnable/this$0 Lcom/admogo/AdMogoManager;
  astore 4
  iconst_1
  istore 15
  aload 4
  iload 15
  invokevirtual com/admogo/AdMogoManager/sendLocationData(Z)V
Label0:
  return
Label1:
  astore 18
  getstatic com/admogo/util/AdMogoUtil/ADMOGO Ljava/lang/String;
  astore 7
  ldc "Caught IOException in getCityName"
  astore_3
  new java/lang/NoClassDefFoundError
  dup
  invokespecial java/lang/NoClassDefFoundError/<init>()V
  athrow
  aload_0
  astore_1
  aload_1
  getfield com/admogo/AdMogoManager$getCityNameRunnable/this$0 Lcom/admogo/AdMogoManager;
  astore 4
  iconst_0
  istore 15
  aload 4
  iload 15
  invokevirtual com/admogo/AdMogoManager/sendLocationData(Z)V
  goto Label0
  nop
.end <method>

