.source PublicCustomAdapter.java
.class  com/admogo/adapters/PublicCustomAdapter$FetchPublicRunnable
.super java/lang/Object
.implements  java/lang/Runnable
.field private "publicCustomAdapter" Lcom/admogo/adapters/PublicCustomAdapter;

.method public <init>(Lcom/admogo/adapters/PublicCustomAdapter;)V
.limit locals 2
.limit stack 200
  nop
  aload_0
  invokespecial java/lang/Object/<init>()V
  aload_0
  aload_1
  putfield com/admogo/adapters/PublicCustomAdapter$FetchPublicRunnable/publicCustomAdapter Lcom/admogo/adapters/PublicCustomAdapter;
  return
  nop
.end <method>

.method public run()V
.limit locals 15
.limit stack 200
  nop
  aload_0
  getfield com/admogo/adapters/PublicCustomAdapter$FetchPublicRunnable/publicCustomAdapter Lcom/admogo/adapters/PublicCustomAdapter;
  astore_1
  aload_1
  getfield com/admogo/adapters/AdMogoAdapter/adMogoLayoutReference Ljava/lang/ref/WeakReference;
  astore_2
  aload_2
  invokevirtual java/lang/ref/WeakReference/get()Ljava/lang/Object;
  astore_3
  aload_3
  astore 5
  new java/lang/NoClassDefFoundError
  dup
  invokespecial java/lang/NoClassDefFoundError/<init>()V
  athrow
  aload 5
  astore 4
  aload 4
  invokestatic app/DummyClass/invokeIfStmt(Ljava/lang/Object;)V
  iload 4
  ifne Label0
Label2:
  return
Label0:
  aload 4
  getfield com/admogo/AdMogoLayout/adMogoManager Lcom/admogo/AdMogoManager;
  astore 6
  aload_0
  getfield com/admogo/adapters/PublicCustomAdapter$FetchPublicRunnable/publicCustomAdapter Lcom/admogo/adapters/PublicCustomAdapter;
  astore_1
  aload_1
  invokestatic com/admogo/adapters/PublicCustomAdapter/access$2(Lcom/admogo/adapters/PublicCustomAdapter;)Lcom/admogo/obj/Ration;
  astore 7
  aload 7
  getfield com/admogo/obj/Ration/nid Ljava/lang/String;
  astore 8
  aload_0
  getfield com/admogo/adapters/PublicCustomAdapter$FetchPublicRunnable/publicCustomAdapter Lcom/admogo/adapters/PublicCustomAdapter;
  astore_1
  aload_1
  invokestatic com/admogo/adapters/PublicCustomAdapter/access$2(Lcom/admogo/adapters/PublicCustomAdapter;)Lcom/admogo/obj/Ration;
  astore 7
  aload 7
  getfield com/admogo/obj/Ration/type I
  istore 9
  aload_0
  getfield com/admogo/adapters/PublicCustomAdapter$FetchPublicRunnable/publicCustomAdapter Lcom/admogo/adapters/PublicCustomAdapter;
  astore_1
  aload_1
  invokestatic com/admogo/adapters/PublicCustomAdapter/access$2(Lcom/admogo/adapters/PublicCustomAdapter;)Lcom/admogo/obj/Ration;
  astore 7
  aload 7
  getfield com/admogo/obj/Ration/bf I
  istore 10
  aload 6
  aload 8
  iload 9
  iload 10
  invokevirtual com/admogo/AdMogoManager/getPublicCustom(Ljava/lang/String;II)Lcom/admogo/obj/PublicCustom;
  astore 11
  aload 11
  invokestatic com/admogo/adapters/PublicCustomAdapter/access$4(Lcom/admogo/obj/PublicCustom;)V
  invokestatic com/admogo/adapters/PublicCustomAdapter/access$5()Lcom/admogo/obj/PublicCustom;
  astore 11
  aload 11
  invokestatic app/DummyClass/invokeIfStmt(Ljava/lang/Object;)V
  aload 11
  ifnonnull Label1
  getstatic com/admogo/util/AdMogoUtil/ADMOGO Ljava/lang/String;
  astore 8
  ldc "getPublicCustom fail publicCustom is null"
  astore 12
  aload 8
  aload 12
  invokestatic android/util/Log/w(Ljava/lang/String;Ljava/lang/String;)I
  pop
  aload 4
  invokevirtual com/admogo/AdMogoLayout/rollover()V
  goto Label2
Label1:
  aload 4
  getfield com/admogo/AdMogoLayout/handler Landroid/os/Handler;
  astore 13
  new com/admogo/adapters/PublicCustomAdapter$DisplayPublicRunnable
  astore 14
  aload_0
  getfield com/admogo/adapters/PublicCustomAdapter$FetchPublicRunnable/publicCustomAdapter Lcom/admogo/adapters/PublicCustomAdapter;
  astore_1
  aload 14
  aload_1
  invokespecial com/admogo/adapters/PublicCustomAdapter$DisplayPublicRunnable/<init>(Lcom/admogo/adapters/PublicCustomAdapter;)V
  aload 13
  aload 14
  invokevirtual android/os/Handler/post(Ljava/lang/Runnable;)Z
  pop
  goto Label2
  nop
.end <method>

