.source dalvik_source_VirusShare_32e70f448ebd75661a1cb12f9cd8e013.apk
.class public final enum  com/tencent/mobwin/core/y
.super java/lang/Enum
.field public static final enum "a" Lcom/tencent/mobwin/core/y;
.field public static final enum "b" Lcom/tencent/mobwin/core/y;
.field private static final "c" [Lcom/tencent/mobwin/core/y;

.method static <clinit>()V
.limit locals 4
.limit stack 200
  nop
  new com/tencent/mobwin/core/y
  astore_0
  ldc "SwitchAd"
  astore_1
  iconst_0
  istore_2
  aload_0
  aload_1
  iload_2
  invokespecial com/tencent/mobwin/core/y/<init>(Ljava/lang/String;I)V
  aload_0
  putstatic com/tencent/mobwin/core/y/a Lcom/tencent/mobwin/core/y;
  new com/tencent/mobwin/core/y
  astore_0
  ldc "SwitchText"
  astore_1
  iconst_1
  istore_2
  aload_0
  aload_1
  iload_2
  invokespecial com/tencent/mobwin/core/y/<init>(Ljava/lang/String;I)V
  aload_0
  putstatic com/tencent/mobwin/core/y/b Lcom/tencent/mobwin/core/y;
  iconst_2
  istore_2
  iload_2
  anewarray com/tencent/mobwin/core/y
  astore_3
  getstatic com/tencent/mobwin/core/y/a Lcom/tencent/mobwin/core/y;
  astore_0
  iconst_0
  istore_2
  aload_3
  iload_2
  aload_0
  aastore
  getstatic com/tencent/mobwin/core/y/b Lcom/tencent/mobwin/core/y;
  astore_0
  iconst_1
  istore_2
  aload_3
  iload_2
  aload_0
  aastore
  aload_3
  putstatic com/tencent/mobwin/core/y/c [Lcom/tencent/mobwin/core/y;
  return
  nop
.end <method>

.method private <init>(Ljava/lang/String;I)V
.limit locals 3
.limit stack 200
  nop
  aload_0
  aload_1
  iload_2
  invokespecial java/lang/Enum/<init>(Ljava/lang/String;I)V
  return
  nop
.end <method>

.method public static valueOf(Ljava/lang/String;)Lcom/tencent/mobwin/core/y;
.limit locals 5
.limit stack 200
  nop
  ldc com/tencent/mobwin/core/y
  astore_2
  aload_2
  aload_0
  invokestatic java/lang/Enum/valueOf(Ljava/lang/Class;Ljava/lang/String;)Ljava/lang/Enum;
  astore_1
  aload_1
  astore 4
  aload 4
  checkcast com/tencent/mobwin/core/y
  astore 4
  aload 4
  astore_3
  aload_3
  areturn
  nop
.end <method>

.method public static values()[Lcom/tencent/mobwin/core/y;
.limit locals 5
.limit stack 200
  nop
  getstatic com/tencent/mobwin/core/y/c [Lcom/tencent/mobwin/core/y;
  astore_0
  aload_0
  arraylength
  istore_1
  iload_1
  anewarray com/tencent/mobwin/core/y
  astore_2
  iconst_0
  istore_3
  iconst_0
  istore 4
  aload_0
  iload_3
  aload_2
  iload 4
  iload_1
  invokestatic java/lang/System/arraycopy(Ljava/lang/Object;ILjava/lang/Object;II)V
  aload_2
  areturn
  nop
.end <method>

