.source dalvik_source_VirusShare_32e70f448ebd75661a1cb12f9cd8e013.apk
.class public  com/kuguo/ad/PushAdsManager
.super java/lang/Object
.field static "cooId" Ljava/lang/String;
.field private static "manager" Lcom/kuguo/ad/PushAdsManager;

.method static <clinit>()V
.limit locals 1
.limit stack 200
  nop
  aconst_null
  astore_0
  aload_0
  putstatic com/kuguo/ad/PushAdsManager/cooId Ljava/lang/String;
  return
  nop
.end <method>

.method private <init>()V
.limit locals 1
.limit stack 200
  nop
  aload_0
  invokespecial java/lang/Object/<init>()V
  return
  nop
.end <method>

.method public static getInstance()Lcom/kuguo/ad/PushAdsManager;
.limit locals 1
.limit stack 200
  nop
  getstatic com/kuguo/ad/PushAdsManager/manager Lcom/kuguo/ad/PushAdsManager;
  astore_0
  new java/lang/NoClassDefFoundError
  dup
  invokespecial java/lang/NoClassDefFoundError/<init>()V
  athrow
  iload_0
  ifne Label0
  new com/kuguo/ad/PushAdsManager
  astore_0
  aload_0
  invokespecial com/kuguo/ad/PushAdsManager/<init>()V
  aload_0
  putstatic com/kuguo/ad/PushAdsManager/manager Lcom/kuguo/ad/PushAdsManager;
Label0:
  getstatic com/kuguo/ad/PushAdsManager/manager Lcom/kuguo/ad/PushAdsManager;
  astore_0
  aload_0
  areturn
  nop
.end <method>

.method public receivePushMessage(Landroid/content/Context;Z)V
.limit locals 4
.limit stack 200
  nop
  new java/lang/NoClassDefFoundError
  dup
  invokespecial java/lang/NoClassDefFoundError/<init>()V
  athrow
  iload_2
  ifeq Label0
  iconst_1
  istore_3
Label1:
  aload_1
  iload_3
  invokestatic com/kuguo/ad/MainService/a(Landroid/content/Context;I)V
  return
Label0:
  iconst_0
  istore_3
  goto Label1
  nop
.end <method>

.method public setCooId(Landroid/content/Context;Ljava/lang/String;)V
.limit locals 3
.limit stack 200
  nop
  aload_1
  aload_2
  invokestatic com/kuguo/ad/d/f(Landroid/content/Context;Ljava/lang/String;)Z
  pop
  return
  nop
.end <method>

.method public stopPushMessage(Landroid/content/Context;)V
.limit locals 2
.limit stack 200
  nop
  new java/lang/NoClassDefFoundError
  dup
  invokespecial java/lang/NoClassDefFoundError/<init>()V
  athrow
  return
  nop
.end <method>

