.source dalvik_source_VirusShare_32e70f448ebd75661a1cb12f9cd8e013.apk
.class  com/tencent/mobwin/core/v
.super java/lang/Object
.implements  com/tencent/mobwin/core/view/a
.field final "a" Lcom/tencent/mobwin/core/g;

.method <init>(Lcom/tencent/mobwin/core/g;)V
.limit locals 2
.limit stack 200
  nop
  aload_0
  aload_1
  putfield com/tencent/mobwin/core/v/a Lcom/tencent/mobwin/core/g;
  aload_0
  invokespecial java/lang/Object/<init>()V
  return
  nop
.end <method>

.method static a(Lcom/tencent/mobwin/core/v;)Lcom/tencent/mobwin/core/g;
  .synthetic
.limit locals 2
.limit stack 200
  nop
  aload_0
  getfield com/tencent/mobwin/core/v/a Lcom/tencent/mobwin/core/g;
  astore_1
  aload_1
  areturn
  nop
.end <method>

.method public a(ZI)V
.limit locals 14
.limit stack 200
  nop
  new java/lang/NoClassDefFoundError
  dup
  invokespecial java/lang/NoClassDefFoundError/<init>()V
  athrow
  iconst_m1
  istore_3
  iload_2
  iload_3
  if_icmpne Label0
  aload_0
  getfield com/tencent/mobwin/core/v/a Lcom/tencent/mobwin/core/g;
  astore 4
  aload 4
  invokestatic com/tencent/mobwin/core/g/b(Lcom/tencent/mobwin/core/g;)Lcom/tencent/mobwin/core/w;
  astore 5
  aload_0
  getfield com/tencent/mobwin/core/v/a Lcom/tencent/mobwin/core/g;
  astore 4
  aload 4
  invokestatic com/tencent/mobwin/core/g/b(Lcom/tencent/mobwin/core/g;)Lcom/tencent/mobwin/core/w;
  astore 6
  aload 6
  getfield com/tencent/mobwin/core/w/f Ljava/util/ArrayList;
  astore 7
  aload 5
  aload 7
  putfield com/tencent/mobwin/core/w/g Ljava/util/ArrayList;
  aload_0
  getfield com/tencent/mobwin/core/v/a Lcom/tencent/mobwin/core/g;
  astore 4
  aload 4
  invokestatic com/tencent/mobwin/core/g/b(Lcom/tencent/mobwin/core/g;)Lcom/tencent/mobwin/core/w;
  astore 6
  new java/util/ArrayList
  astore 7
  aload 7
  invokespecial java/util/ArrayList/<init>()V
  aload 6
  aload 7
  putfield com/tencent/mobwin/core/w/f Ljava/util/ArrayList;
  aload_0
  getfield com/tencent/mobwin/core/v/a Lcom/tencent/mobwin/core/g;
  astore 4
  aload 4
  invokestatic com/tencent/mobwin/core/g/a(Lcom/tencent/mobwin/core/g;)Lcom/tencent/mobwin/core/view/d;
  astore 8
  aload 8
  invokevirtual com/tencent/mobwin/core/view/d/h()Lcom/tencent/mobwin/core/view/c;
  astore 9
  iconst_0
  dstore 10
Label2:
  aload_0
  getfield com/tencent/mobwin/core/v/a Lcom/tencent/mobwin/core/g;
  astore 4
  aload 4
  invokestatic com/tencent/mobwin/core/g/a(Lcom/tencent/mobwin/core/g;)Lcom/tencent/mobwin/core/view/d;
  astore 8
  aload 8
  invokevirtual com/tencent/mobwin/core/view/d/e()I
  istore_2
  dload 10
  invokestatic app/DummyClass/invokeIfStmt(D)V
  dload_2
  invokestatic app/DummyClass/invokeIfStmt(D)V
  iload 10
  iload_2
  if_icmplt Label1
  aload_0
  getfield com/tencent/mobwin/core/v/a Lcom/tencent/mobwin/core/g;
  astore 4
  new com/tencent/mobwin/core/b
  astore 11
  aload 11
  aload_0
  invokespecial com/tencent/mobwin/core/b/<init>(Lcom/tencent/mobwin/core/v;)V
  aload 4
  aload 11
  invokevirtual com/tencent/mobwin/core/g/post(Ljava/lang/Runnable;)Z
  pop
Label0:
  return
Label1:
  aload 9
  getfield com/tencent/mobwin/core/view/c/a Landroid/graphics/Bitmap;
  astore 12
  aload_0
  getfield com/tencent/mobwin/core/v/a Lcom/tencent/mobwin/core/g;
  astore 4
  aload 4
  invokestatic com/tencent/mobwin/core/g/b(Lcom/tencent/mobwin/core/g;)Lcom/tencent/mobwin/core/w;
  astore 6
  aload 6
  getfield com/tencent/mobwin/core/w/f Ljava/util/ArrayList;
  astore 7
  new com/tencent/mobwin/core/view/c
  astore 13
  aload 9
  getfield com/tencent/mobwin/core/view/c/b I
  istore_2
  aload 13
  aload 12
  iload_2
  invokespecial com/tencent/mobwin/core/view/c/<init>(Landroid/graphics/Bitmap;I)V
  aload 7
  aload 13
  invokevirtual java/util/ArrayList/add(Ljava/lang/Object;)Z
  pop
  aload 9
  getfield com/tencent/mobwin/core/view/c/c Lcom/tencent/mobwin/core/view/c;
  astore 9
  iload 10
  iconst_1
  iadd
  istore 10
  goto Label2
  nop
.end <method>

