.source SourceFile
.class public final  com/mobisage/android/MobiSageManager
.super java/lang/Object
.field private static "a" Lcom/mobisage/android/MobiSageManager;
.field private "b" Z
.field private "c" Landroid/os/Handler;
.field private "d" Landroid/os/HandlerThread;
.field private "e" Lcom/mobisage/android/MobiSageManager$a;

.method static <clinit>()V
.limit locals 1
.limit stack 200
  nop
  new com/mobisage/android/MobiSageManager
  astore_0
  aload_0
  invokespecial com/mobisage/android/MobiSageManager/<init>()V
  aload_0
  putstatic com/mobisage/android/MobiSageManager/a Lcom/mobisage/android/MobiSageManager;
  return
  nop
.end <method>

.method private <init>()V
.limit locals 9
.limit stack 200
  nop
  aload_0
  invokespecial java/lang/Object/<init>()V
  iconst_0
  istore_1
  aload_0
  iload_1
  putfield com/mobisage/android/MobiSageManager/b Z
  new java/lang/NoClassDefFoundError
  dup
  invokespecial java/lang/NoClassDefFoundError/<init>()V
  athrow
  invokestatic java/util/UUID/randomUUID()Ljava/util/UUID;
  astore_3
  aload_3
  invokevirtual java/util/UUID/toString()Ljava/lang/String;
  astore 4
  bipush 10
  istore_1
  aload_2
  aload 4
  iload_1
  invokespecial android/os/HandlerThread/<init>(Ljava/lang/String;I)V
  aload_0
  aload_2
  putfield com/mobisage/android/MobiSageManager/d Landroid/os/HandlerThread;
  aload_0
  getfield com/mobisage/android/MobiSageManager/d Landroid/os/HandlerThread;
  astore_2
  aload_2
  invokevirtual android/os/HandlerThread/start()V
  new com/mobisage/android/MobiSageManager$a
  astore 5
  iconst_0
  istore_1
  iload_1
  i2b
  istore 6
  aload 5
  aload_0
  iload 6
  invokespecial com/mobisage/android/MobiSageManager$a/<init>(Lcom/mobisage/android/MobiSageManager;B)V
  aload_0
  aload 5
  putfield com/mobisage/android/MobiSageManager/e Lcom/mobisage/android/MobiSageManager$a;
  new android/os/Handler
  astore 7
  aload_0
  getfield com/mobisage/android/MobiSageManager/d Landroid/os/HandlerThread;
  astore_2
  aload_2
  invokevirtual android/os/HandlerThread/getLooper()Landroid/os/Looper;
  astore 8
  aload_0
  getfield com/mobisage/android/MobiSageManager/e Lcom/mobisage/android/MobiSageManager$a;
  astore 5
  aload 7
  aload 8
  aload 5
  invokespecial android/os/Handler/<init>(Landroid/os/Looper;Landroid/os/Handler$Callback;)V
  aload_0
  aload 7
  putfield com/mobisage/android/MobiSageManager/c Landroid/os/Handler;
  return
  nop
.end <method>

.method final a(Landroid/content/Context;)V
.limit locals 6
.limit stack 200
  nop
  aload_0
  getfield com/mobisage/android/MobiSageManager/b Z
  istore_2
  new java/lang/NoClassDefFoundError
  dup
  invokespecial java/lang/NoClassDefFoundError/<init>()V
  athrow
  iload_2
  ifeq Label0
Label1:
  return
Label0:
  aload_1
  invokestatic com/mobisage/android/r/a(Landroid/content/Context;)Z
  pop
  aload_1
  invokestatic com/mobisage/android/y/a(Landroid/content/Context;)V
  aload_0
  getfield com/mobisage/android/MobiSageManager/c Landroid/os/Handler;
  astore_3
  iconst_0
  istore 5
  aload_3
  iload 5
  invokevirtual android/os/Handler/obtainMessage(I)Landroid/os/Message;
  astore 4
  aload 4
  invokevirtual android/os/Message/sendToTarget()V
  iconst_1
  istore 5
  aload_0
  iload 5
  putfield com/mobisage/android/MobiSageManager/b Z
  goto Label1
  nop
.end <method>

.method static a(Lcom/mobisage/android/MobiSageManager;)V
  .synthetic
.limit locals 7
.limit stack 200
  nop
  invokestatic com/mobisage/android/H/a()Lcom/mobisage/android/H;
  pop
  invokestatic com/mobisage/android/R/a()Lcom/mobisage/android/R;
  pop
  new java/lang/NoClassDefFoundError
  dup
  invokespecial java/lang/NoClassDefFoundError/<init>()V
  athrow
  invokestatic com/mobisage/android/Y/a()Lcom/mobisage/android/Y;
  pop
  invokestatic com/mobisage/android/w/a()Lcom/mobisage/android/w;
  pop
  invokestatic com/mobisage/android/D/a()Lcom/mobisage/android/D;
  pop
  new com/mobisage/android/z
  astore_1
  aload_1
  invokespecial com/mobisage/android/z/<init>()V
  ldc2_w 5
  lstore_2
  aload_1
  lload_2
  putfield com/mobisage/android/Q/c J
  ldc2_w 86400
  lstore_2
  aload_1
  lload_2
  putfield com/mobisage/android/Q/e J
  invokestatic com/mobisage/android/R/a()Lcom/mobisage/android/R;
  astore 4
  aload 4
  aload_1
  invokevirtual com/mobisage/android/R/a(Lcom/mobisage/android/Q;)V
  new com/mobisage/android/t
  astore 5
  aload 5
  invokespecial com/mobisage/android/t/<init>()V
  ldc2_w 5
  lstore_2
  aload 5
  lload_2
  putfield com/mobisage/android/Q/c J
  ldc2_w 36000000
  lstore_2
  aload 5
  lload_2
  putfield com/mobisage/android/Q/e J
  iconst_1
  istore 6
  aload 5
  iload 6
  putfield com/mobisage/android/Q/d Z
  invokestatic com/mobisage/android/R/a()Lcom/mobisage/android/R;
  astore 4
  aload 4
  aload 5
  invokevirtual com/mobisage/android/R/a(Lcom/mobisage/android/Q;)V
  return
  nop
.end <method>

.method public final cancelMobiSageMessage(Lcom/mobisage/android/MobiSageMessage;)V
.limit locals 3
.limit stack 200
  nop
  invokestatic com/mobisage/android/H/a()Lcom/mobisage/android/H;
  astore_2
  aload_2
  aload_1
  invokevirtual com/mobisage/android/H/b(Lcom/mobisage/android/MobiSageMessage;)V
  return
  nop
.end <method>

.method protected final finalize()V
.limit locals 2
.limit stack 200
  nop
  aload_0
  invokespecial java/lang/Object/finalize()V
  aload_0
  getfield com/mobisage/android/MobiSageManager/d Landroid/os/HandlerThread;
  astore_1
  new java/lang/NoClassDefFoundError
  dup
  invokespecial java/lang/NoClassDefFoundError/<init>()V
  athrow
  return
  nop
.end <method>

.method public static getInstance()Lcom/mobisage/android/MobiSageManager;
.limit locals 1
.limit stack 200
  nop
  getstatic com/mobisage/android/MobiSageManager/a Lcom/mobisage/android/MobiSageManager;
  astore_0
  aload_0
  areturn
  nop
.end <method>

.method public final pushMobiSageMessage(Lcom/mobisage/android/MobiSageMessage;)V
.limit locals 3
.limit stack 200
  nop
  invokestatic com/mobisage/android/H/a()Lcom/mobisage/android/H;
  astore_2
  aload_2
  aload_1
  invokevirtual com/mobisage/android/H/a(Lcom/mobisage/android/MobiSageMessage;)V
  return
  nop
.end <method>

.method public final trackCustomEvent(Landroid/app/Activity;Ljava/lang/String;Ljava/lang/String;)V
.limit locals 12
.limit stack 200
  nop
  aload_0
  aload_1
  invokevirtual com/mobisage/android/MobiSageManager/a(Landroid/content/Context;)V
  new com/mobisage/android/b
  astore 4
  aload 4
  invokespecial com/mobisage/android/b/<init>()V
  aload_1
  invokestatic com/mobisage/android/y/c(Landroid/content/Context;)I
  istore 5
  aload 4
  getfield com/mobisage/android/b/c Landroid/os/Bundle;
  astore 6
  iload 5
  invokestatic com/mobisage/android/y/a(I)Ljava/lang/String;
  astore 7
  ldc "Network"
  astore 8
  new java/lang/NoClassDefFoundError
  dup
  invokespecial java/lang/NoClassDefFoundError/<init>()V
  athrow
  aload 4
  getfield com/mobisage/android/b/c Landroid/os/Bundle;
  astore 6
  aload_1
  invokestatic com/mobisage/android/y/d(Landroid/content/Context;)Ljava/lang/String;
  astore 9
  ldc "Carrier"
  astore 8
  aload 6
  aload 8
  aload 9
  invokevirtual android/os/Bundle/putString(Ljava/lang/String;Ljava/lang/String;)V
  aload 4
  getfield com/mobisage/android/b/c Landroid/os/Bundle;
  astore 6
  iconst_0
  istore 10
  iload 10
  invokestatic java/lang/String/valueOf(I)Ljava/lang/String;
  astore 9
  ldc "SystemEvent"
  astore 8
  aload 6
  aload 8
  aload 9
  invokevirtual android/os/Bundle/putString(Ljava/lang/String;Ljava/lang/String;)V
  aload 4
  getfield com/mobisage/android/b/c Landroid/os/Bundle;
  astore 6
  ldc "EventID"
  astore 8
  aload 6
  aload 8
  aload_2
  invokevirtual android/os/Bundle/putString(Ljava/lang/String;Ljava/lang/String;)V
  aload 4
  getfield com/mobisage/android/b/c Landroid/os/Bundle;
  astore 6
  ldc "EventObject"
  astore 8
  aload 6
  aload 8
  aload_3
  invokevirtual android/os/Bundle/putString(Ljava/lang/String;Ljava/lang/String;)V
  aload 4
  getfield com/mobisage/android/b/c Landroid/os/Bundle;
  astore 6
  getstatic com/mobisage/android/r/d Ljava/lang/String;
  astore 9
  ldc "AppVersion"
  astore 8
  aload 6
  aload 8
  aload 9
  invokevirtual android/os/Bundle/putString(Ljava/lang/String;Ljava/lang/String;)V
  invokestatic com/mobisage/android/Y/a()Lcom/mobisage/android/Y;
  astore 11
  sipush 2001
  istore 10
  aload 11
  iload 10
  aload 4
  invokevirtual com/mobisage/android/Y/a(ILcom/mobisage/android/b;)V
  return
  nop
.end <method>

.method public final trackStreamEvent(Landroid/app/Activity;Ljava/lang/String;)V
.limit locals 8
.limit stack 200
  nop
  aload_0
  aload_1
  invokevirtual com/mobisage/android/MobiSageManager/a(Landroid/content/Context;)V
  new com/mobisage/android/b
  astore_3
  aload_3
  invokespecial com/mobisage/android/b/<init>()V
  aload_3
  getfield com/mobisage/android/b/c Landroid/os/Bundle;
  astore 4
  ldc "TrackData"
  astore 5
  new java/lang/NoClassDefFoundError
  dup
  invokespecial java/lang/NoClassDefFoundError/<init>()V
  athrow
  invokestatic com/mobisage/android/Y/a()Lcom/mobisage/android/Y;
  astore 6
  sipush 2003
  istore 7
  aload 6
  iload 7
  aload_3
  invokevirtual com/mobisage/android/Y/a(ILcom/mobisage/android/b;)V
  return
  nop
.end <method>

.method public final trackSystemEvent(Landroid/app/Activity;I)V
.limit locals 12
.limit stack 200
  nop
  aload_0
  aload_1
  invokevirtual com/mobisage/android/MobiSageManager/a(Landroid/content/Context;)V
  new java/lang/NoClassDefFoundError
  dup
  invokespecial java/lang/NoClassDefFoundError/<init>()V
  athrow
  iconst_1
  istore_3
  iload_2
  iload_3
  if_icmpeq Label0
  dload_2
  invokestatic app/DummyClass/invokeIfStmt(D)V
  iconst_2
  istore_3
  iload_2
  iload_3
  if_icmpeq Label0
Label2:
  return
Label0:
  new com/mobisage/android/b
  astore 4
  aload 4
  invokespecial com/mobisage/android/b/<init>()V
  aload_1
  invokestatic com/mobisage/android/y/c(Landroid/content/Context;)I
  istore 5
  aload 4
  getfield com/mobisage/android/b/c Landroid/os/Bundle;
  astore 6
  iload 5
  invokestatic com/mobisage/android/y/a(I)Ljava/lang/String;
  astore 7
  ldc "Network"
  astore 8
  aload 6
  aload 8
  aload 7
  invokevirtual android/os/Bundle/putString(Ljava/lang/String;Ljava/lang/String;)V
  aload 4
  getfield com/mobisage/android/b/c Landroid/os/Bundle;
  astore 6
  aload_1
  invokestatic com/mobisage/android/y/d(Landroid/content/Context;)Ljava/lang/String;
  astore 9
  ldc "Carrier"
  astore 8
  aload 6
  aload 8
  aload 9
  invokevirtual android/os/Bundle/putString(Ljava/lang/String;Ljava/lang/String;)V
  aload 4
  getfield com/mobisage/android/b/c Landroid/os/Bundle;
  astore 6
  iload_2
  invokestatic java/lang/String/valueOf(I)Ljava/lang/String;
  astore 9
  ldc "SystemEvent"
  astore 8
  aload 6
  aload 8
  aload 9
  invokevirtual android/os/Bundle/putString(Ljava/lang/String;Ljava/lang/String;)V
  dload_2
  invokestatic app/DummyClass/invokeIfStmt(D)V
  iconst_1
  istore_3
  iload_2
  iload_3
  if_icmpne Label1
  aload 4
  getfield com/mobisage/android/b/c Landroid/os/Bundle;
  astore 6
  ldc "EventID"
  astore 8
  ldc "In"
  astore 10
  aload 6
  aload 8
  aload 10
  invokevirtual android/os/Bundle/putString(Ljava/lang/String;Ljava/lang/String;)V
Label3:
  aload 4
  getfield com/mobisage/android/b/c Landroid/os/Bundle;
  astore 6
  getstatic com/mobisage/android/r/c Ljava/lang/String;
  astore 9
  ldc "EventObject"
  astore 8
  aload 6
  aload 8
  aload 9
  invokevirtual android/os/Bundle/putString(Ljava/lang/String;Ljava/lang/String;)V
  aload 4
  getfield com/mobisage/android/b/c Landroid/os/Bundle;
  astore 6
  getstatic com/mobisage/android/r/d Ljava/lang/String;
  astore 9
  ldc "AppVersion"
  astore 8
  aload 6
  aload 8
  aload 9
  invokevirtual android/os/Bundle/putString(Ljava/lang/String;Ljava/lang/String;)V
  invokestatic com/mobisage/android/Y/a()Lcom/mobisage/android/Y;
  astore 11
  sipush 2001
  istore_3
  aload 11
  iload_3
  aload 4
  invokevirtual com/mobisage/android/Y/a(ILcom/mobisage/android/b;)V
  goto Label2
Label1:
  aload 4
  getfield com/mobisage/android/b/c Landroid/os/Bundle;
  astore 6
  ldc "EventID"
  astore 8
  ldc "Out"
  astore 10
  aload 6
  aload 8
  aload 10
  invokevirtual android/os/Bundle/putString(Ljava/lang/String;Ljava/lang/String;)V
  goto Label3
  nop
.end <method>

