.source dalvik_source_VirusShare_32e70f448ebd75661a1cb12f9cd8e013.apk
.class  com/wiyun/ad/aa
.super java/lang/Object

.method <init>()V
.limit locals 1
.limit stack 200
  nop
  aload_0
  invokespecial java/lang/Object/<init>()V
  return
  nop
.end <method>

.method public static a(Lcom/wiyun/ad/AdView;)I
.limit locals 11
.limit stack 200
  nop
  iconst_0
  istore_1
  iconst_0
  istore_2
Label3:
  new java/lang/NoClassDefFoundError
  dup
  invokespecial java/lang/NoClassDefFoundError/<init>()V
  athrow
  nop
  aload_3
  invokestatic app/DummyClass/invokeIfStmt(Ljava/lang/Object;)V
  iload_3
  ifeq Label0
  aload_3
  getfield android/view/ViewGroup$LayoutParams/width I
  istore 4
  dload 4
  invokestatic app/DummyClass/invokeIfStmt(D)V
  iload 4
  iflt Label0
  aload_3
  getfield android/view/ViewGroup$LayoutParams/width I
  istore 4
Label4:
  iload 4
  iload_2
  isub
  istore 4
  iload 4
  iload_1
  isub
  istore 4
  iconst_0
  istore 5
  iload 5
  iload 4
  invokestatic java/lang/Math/max(II)I
  istore 4
  iload 4
  ireturn
Label0:
  aload_3
  instanceof android/view/ViewGroup$MarginLayoutParams
  istore 6
  iload 6
  invokestatic app/DummyClass/invokeIfStmt(Z)V
  iload 6
  ifeq Label1
  aload_3
  astore 8
  aload 8
  checkcast android/view/ViewGroup$MarginLayoutParams
  astore 8
  aload 8
  astore 7
  aload 7
  getfield android/view/ViewGroup$MarginLayoutParams/leftMargin I
  istore 4
  iload_2
  iload 4
  iadd
  istore_2
  aload 7
  getfield android/view/ViewGroup$MarginLayoutParams/rightMargin I
  istore 4
  iload_1
  iload 4
  iadd
  istore_1
Label1:
  aload_0
  invokevirtual android/view/View/getParent()Landroid/view/ViewParent;
  astore 9
  aload 9
  instanceof android/view/View
  istore 6
  iload 6
  invokestatic app/DummyClass/invokeIfStmt(Z)V
  iload 6
  ifeq Label2
  aload 9
  astore 10
  aload 10
  checkcast android/view/View
  astore 10
  aload 10
  astore_0
Label5:
  aload_0
  invokestatic app/DummyClass/invokeIfStmt(Ljava/lang/Object;)V
  aload_0
  ifnonnull Label3
  iconst_0
  istore 4
  goto Label4
Label2:
  aconst_null
  astore_0
  goto Label5
  nop
.end <method>

