.source SourceFile
.class final  com/mobisage/android/x
.super com/mobisage/android/N

.method <init>(Lcom/mobisage/android/v;)V
.limit locals 2
.limit stack 200
  nop
  aload_0
  aload_1
  invokespecial com/mobisage/android/N/<init>(Lcom/mobisage/android/MobiSageMessage;)V
  return
  nop
.end <method>

.method public final run()V
.limit locals 14
.limit stack 200
  nop
  ldc "MobiSageSDK"
  astore_2
  new java/lang/NoClassDefFoundError
  dup
  invokespecial java/lang/NoClassDefFoundError/<init>()V
  athrow
  nop
Label4:
  aload_0
  getfield com/mobisage/android/N/a Lcom/mobisage/android/MobiSageMessage;
  astore_3
  aload_3
  invokevirtual com/mobisage/android/MobiSageMessage/createHttpRequest()Lorg/apache/http/client/methods/HttpRequestBase;
  astore 4
  aload_1
  aload 4
  invokevirtual android/net/http/AndroidHttpClient/execute(Lorg/apache/http/client/methods/HttpUriRequest;)Lorg/apache/http/HttpResponse;
  astore 5
  aload_0
  getfield com/mobisage/android/N/a Lcom/mobisage/android/MobiSageMessage;
  astore_3
  aload_3
  getfield com/mobisage/android/MobiSageMessage/result Landroid/os/Bundle;
  astore 6
  aload 5
  invokeinterface org/apache/http/HttpResponse/getStatusLine()Lorg/apache/http/StatusLine; 1
  astore 7
  aload 7
  invokeinterface org/apache/http/StatusLine/getStatusCode()I 1
  istore 8
  ldc "StatusCode"
  astore_2
  aload 6
  aload_2
  iload 8
  invokevirtual android/os/Bundle/putInt(Ljava/lang/String;I)V
  aload_0
  getfield com/mobisage/android/N/a Lcom/mobisage/android/MobiSageMessage;
  astore_3
  aload_3
  getfield com/mobisage/android/MobiSageMessage/result Landroid/os/Bundle;
  astore 6
  aload 5
  invokeinterface org/apache/http/HttpResponse/getEntity()Lorg/apache/http/HttpEntity; 1
  astore 9
  aload 9
  invokestatic org/apache/http/util/EntityUtils/toByteArray(Lorg/apache/http/HttpEntity;)[B
  astore 10
  ldc "ResponseBody"
  astore_2
  aload 6
  aload_2
  aload 10
  invokevirtual android/os/Bundle/putByteArray(Ljava/lang/String;[B)V
Label5:
  aload_1
  invokevirtual android/net/http/AndroidHttpClient/close()V
  aload_0
  getfield com/mobisage/android/N/a Lcom/mobisage/android/MobiSageMessage;
  astore_3
  aload_3
  getfield com/mobisage/android/MobiSageMessage/callback Lcom/mobisage/android/IMobiSageMessageCallback;
  astore 11
  aload 11
  invokestatic app/DummyClass/invokeIfStmt(Ljava/lang/Object;)V
  aload 11
  ifnull Label0
  aload_0
  getfield com/mobisage/android/N/a Lcom/mobisage/android/MobiSageMessage;
  astore_3
  aload_3
  getfield com/mobisage/android/MobiSageMessage/callback Lcom/mobisage/android/IMobiSageMessageCallback;
  astore 11
  aload_0
  getfield com/mobisage/android/N/a Lcom/mobisage/android/MobiSageMessage;
  astore_3
  aload 11
  aload_3
  invokeinterface com/mobisage/android/IMobiSageMessageCallback/onMobiSageMessageFinish(Lcom/mobisage/android/MobiSageMessage;)V 2
Label0:
  aload_0
  invokespecial com/mobisage/android/N/run()V
  return
Label3:
  astore 12
  aload_1
  invokevirtual android/net/http/AndroidHttpClient/close()V
  aload_0
  getfield com/mobisage/android/N/a Lcom/mobisage/android/MobiSageMessage;
  astore_3
  aload_3
  getfield com/mobisage/android/MobiSageMessage/callback Lcom/mobisage/android/IMobiSageMessageCallback;
  astore 11
  aload 11
  invokestatic app/DummyClass/invokeIfStmt(Ljava/lang/Object;)V
  aload 11
  ifnull Label0
  aload_0
  getfield com/mobisage/android/N/a Lcom/mobisage/android/MobiSageMessage;
  astore_3
  aload_3
  getfield com/mobisage/android/MobiSageMessage/callback Lcom/mobisage/android/IMobiSageMessageCallback;
  astore 11
  aload_0
  getfield com/mobisage/android/N/a Lcom/mobisage/android/MobiSageMessage;
  astore_3
  aload 11
  aload_3
  invokeinterface com/mobisage/android/IMobiSageMessageCallback/onMobiSageMessageFinish(Lcom/mobisage/android/MobiSageMessage;)V 2
  goto Label0
Label2:
  astore 13
  aload_1
  invokevirtual android/net/http/AndroidHttpClient/close()V
  aload_0
  getfield com/mobisage/android/N/a Lcom/mobisage/android/MobiSageMessage;
  astore_3
  aload_3
  getfield com/mobisage/android/MobiSageMessage/callback Lcom/mobisage/android/IMobiSageMessageCallback;
  astore 11
  aload 11
  invokestatic app/DummyClass/invokeIfStmt(Ljava/lang/Object;)V
  aload 11
  ifnull Label1
  aload_0
  getfield com/mobisage/android/N/a Lcom/mobisage/android/MobiSageMessage;
  astore_3
  aload_3
  getfield com/mobisage/android/MobiSageMessage/callback Lcom/mobisage/android/IMobiSageMessageCallback;
  astore 11
  aload_0
  getfield com/mobisage/android/N/a Lcom/mobisage/android/MobiSageMessage;
  astore_3
  aload 11
  aload_3
  invokeinterface com/mobisage/android/IMobiSageMessageCallback/onMobiSageMessageFinish(Lcom/mobisage/android/MobiSageMessage;)V 2
Label1:
  aload 13
  athrow
  nop
.end <method>

