.source SourceFile
.class final  com/mobisage/android/A
.super com/mobisage/android/P

.method <init>()V
.limit locals 1
.limit stack 200
  nop
  aload_0
  invokespecial com/mobisage/android/P/<init>()V
  return
  nop
.end <method>

.method public final a(I)Landroid/view/animation/Animation;
.limit locals 14
.limit stack 200
  nop
  new java/lang/NoClassDefFoundError
  dup
  invokespecial java/lang/NoClassDefFoundError/<init>()V
  athrow
  fconst_1
  fstore_3
  fconst_1
  fstore 4
  fconst_0
  fstore 5
  fconst_1
  fstore 6
  iconst_1
  istore 7
  ldc 0.500000
  fstore 8
  iconst_1
  istore 9
  ldc 0.500000
  fstore 10
  aload_2
  fload_3
  fload 4
  fload 5
  fload 6
  iload 7
  fload 8
  iload 9
  fload 10
  invokespecial android/view/animation/ScaleAnimation/<init>(FFFFIFIF)V
  ldc2_w 1000
  lstore 11
  aload_2
  lload 11
  invokevirtual android/view/animation/ScaleAnimation/setDuration(J)V
  new android/view/animation/DecelerateInterpolator
  astore 13
  aload 13
  invokespecial android/view/animation/DecelerateInterpolator/<init>()V
  aload_2
  aload 13
  invokevirtual android/view/animation/ScaleAnimation/setInterpolator(Landroid/view/animation/Interpolator;)V
  aload_2
  areturn
  nop
.end <method>

.method public final b(I)Landroid/view/animation/Animation;
.limit locals 14
.limit stack 200
  nop
  new java/lang/NoClassDefFoundError
  dup
  invokespecial java/lang/NoClassDefFoundError/<init>()V
  athrow
  fconst_1
  fstore_3
  fconst_1
  fstore 4
  fconst_1
  fstore 5
  fconst_0
  fstore 6
  iconst_1
  istore 7
  ldc 0.500000
  fstore 8
  iconst_1
  istore 9
  ldc 0.500000
  fstore 10
  aload_2
  fload_3
  fload 4
  fload 5
  fload 6
  iload 7
  fload 8
  iload 9
  fload 10
  invokespecial android/view/animation/ScaleAnimation/<init>(FFFFIFIF)V
  ldc2_w 1000
  lstore 11
  aload_2
  lload 11
  invokevirtual android/view/animation/ScaleAnimation/setDuration(J)V
  new android/view/animation/DecelerateInterpolator
  astore 13
  aload 13
  invokespecial android/view/animation/DecelerateInterpolator/<init>()V
  aload_2
  aload 13
  invokevirtual android/view/animation/ScaleAnimation/setInterpolator(Landroid/view/animation/Interpolator;)V
  aload_2
  areturn
  nop
.end <method>

