.source dalvik_source_VirusShare_32e70f448ebd75661a1cb12f9cd8e013.apk
.class public  com/tencent/lbsapi/QLBSService
.super java/lang/Object
.field private "a" Lcom/tencent/lbsapi/core/f;

.method public <init>(Landroid/content/Context;Lcom/tencent/lbsapi/QLBSNotification;Ljava/lang/String;Ljava/lang/String;Ljava/lang/String;)V
.limit locals 14
.limit stack 200
  nop
  aload_0
  invokespecial java/lang/Object/<init>()V
  aconst_null
  astore 12
  aload_0
  aload 12
  putfield com/tencent/lbsapi/QLBSService/a Lcom/tencent/lbsapi/core/f;
  new com/tencent/lbsapi/core/f
  astore 13
  aload 13
  astore 6
  aload_1
  astore 7
  aload_2
  astore 8
  aload_3
  astore 9
  aload 4
  astore 10
  aload 5
  astore 11
  aload 6
  aload 7
  aload 8
  aload 9
  aload 10
  aload 11
  invokespecial com/tencent/lbsapi/core/f/<init>(Landroid/content/Context;Lcom/tencent/lbsapi/QLBSNotification;Ljava/lang/String;Ljava/lang/String;Ljava/lang/String;)V
  aload_0
  aload 13
  putfield com/tencent/lbsapi/QLBSService/a Lcom/tencent/lbsapi/core/f;
  return
  nop
.end <method>

.method public getCarrierId()I
.limit locals 3
.limit stack 200
  nop
  aload_0
  getfield com/tencent/lbsapi/QLBSService/a Lcom/tencent/lbsapi/core/f;
  astore_1
  aload_1
  invokevirtual com/tencent/lbsapi/core/f/e()I
  istore_2
  iload_2
  ireturn
  nop
.end <method>

.method public getDeviceData()[B
.limit locals 3
.limit stack 200
  nop
  aload_0
  getfield com/tencent/lbsapi/QLBSService/a Lcom/tencent/lbsapi/core/f;
  astore_1
  aload_1
  invokevirtual com/tencent/lbsapi/core/f/c()[B
  astore_2
  aload_2
  areturn
  nop
.end <method>

.method public isGpsEnabled()Z
.limit locals 3
.limit stack 200
  nop
  aload_0
  getfield com/tencent/lbsapi/QLBSService/a Lcom/tencent/lbsapi/core/f;
  astore_1
  aload_1
  invokevirtual com/tencent/lbsapi/core/f/d()Z
  istore_2
  iload_2
  ireturn
  nop
.end <method>

.method public release()V
.limit locals 3
.limit stack 200
  nop
  aload_0
  getfield com/tencent/lbsapi/QLBSService/a Lcom/tencent/lbsapi/core/f;
  astore_1
  aload_1
  invokevirtual com/tencent/lbsapi/core/f/a()V
  aconst_null
  astore_2
  aload_0
  aload_2
  putfield com/tencent/lbsapi/QLBSService/a Lcom/tencent/lbsapi/core/f;
  return
  nop
.end <method>

.method public setGpsEnabled(Z)V
.limit locals 3
.limit stack 200
  nop
  aload_0
  getfield com/tencent/lbsapi/QLBSService/a Lcom/tencent/lbsapi/core/f;
  astore_2
  aload_2
  iload_1
  invokevirtual com/tencent/lbsapi/core/f/a(Z)V
  return
  nop
.end <method>

.method public startLocation(I)V
.limit locals 3
.limit stack 200
  nop
  aload_0
  getfield com/tencent/lbsapi/QLBSService/a Lcom/tencent/lbsapi/core/f;
  astore_2
  aload_2
  iload_1
  invokevirtual com/tencent/lbsapi/core/f/a(I)V
  return
  nop
.end <method>

.method public stopLocation()V
.limit locals 2
.limit stack 200
  nop
  aload_0
  getfield com/tencent/lbsapi/QLBSService/a Lcom/tencent/lbsapi/core/f;
  astore_1
  aload_1
  invokevirtual com/tencent/lbsapi/core/f/b()V
  return
  nop
.end <method>

