.source RequestPacket.java
.class public final  com/qq/taf/RequestPacket
.super com/qq/taf/jce/JceStruct
.field static final "$assertionsDisabled" Z =  0
.field static "cache_context" Ljava/util/Map;
.field static "cache_sBuffer" [B
.field public "cPacketType" B
.field public "context" Ljava/util/Map;
.field public "iMessageType" I
.field public "iRequestId" I
.field public "iTimeout" I
.field public "iVersion" S
.field public "sBuffer" [B
.field public "sFuncName" Ljava/lang/String;
.field public "sServantName" Ljava/lang/String;
.field public "status" Ljava/util/Map;

.method static <clinit>()V
.limit locals 3
.limit stack 200
  nop
  ldc com/qq/taf/RequestPacket
  astore_0
  aload_0
  invokevirtual java/lang/Class/desiredAssertionStatus()Z
  istore_1
  new java/lang/NoClassDefFoundError
  dup
  invokespecial java/lang/NoClassDefFoundError/<init>()V
  athrow
  iload_1
  ifne Label0
  iconst_1
  istore_1
Label1:
  iload_1
  putstatic com/qq/taf/RequestPacket/$assertionsDisabled Z
  aconst_null
  astore_2
  aload_2
  putstatic com/qq/taf/RequestPacket/cache_sBuffer [B
  aconst_null
  astore_2
  aload_2
  putstatic com/qq/taf/RequestPacket/cache_context Ljava/util/Map;
  return
Label0:
  iconst_0
  istore_1
  goto Label1
  nop
.end <method>

.method public <init>()V
.limit locals 3
.limit stack 200
  nop
  aload_0
  invokespecial com/qq/taf/jce/JceStruct/<init>()V
  iconst_0
  istore_1
  aload_0
  iload_1
  putfield com/qq/taf/RequestPacket/iVersion S
  iconst_0
  istore_1
  aload_0
  iload_1
  putfield com/qq/taf/RequestPacket/cPacketType B
  iconst_0
  istore_1
  aload_0
  iload_1
  putfield com/qq/taf/RequestPacket/iMessageType I
  iconst_0
  istore_1
  aload_0
  iload_1
  putfield com/qq/taf/RequestPacket/iRequestId I
  aconst_null
  astore_2
  aload_0
  aload_2
  putfield com/qq/taf/RequestPacket/sServantName Ljava/lang/String;
  aconst_null
  astore_2
  aload_0
  aload_2
  putfield com/qq/taf/RequestPacket/sFuncName Ljava/lang/String;
  iconst_0
  istore_1
  aload_0
  iload_1
  putfield com/qq/taf/RequestPacket/iTimeout I
  return
  nop
.end <method>

.method public <init>(SBIILjava/lang/String;Ljava/lang/String;[BILjava/util/Map;Ljava/util/Map;)V
  .signature_attr "(SBIILjava/lang/String;Ljava/lang/String;[BILjava/util/Map<Ljava/lang/String;Ljava/lang/String;>;Ljava/util/Map<Ljava/lang/String;Ljava/lang/String;>;)V"
.limit locals 13
.limit stack 200
  nop
  aload_0
  invokespecial com/qq/taf/jce/JceStruct/<init>()V
  iconst_0
  istore 11
  aload_0
  iload 11
  putfield com/qq/taf/RequestPacket/iVersion S
  iconst_0
  istore 11
  aload_0
  iload 11
  putfield com/qq/taf/RequestPacket/cPacketType B
  iconst_0
  istore 11
  aload_0
  iload 11
  putfield com/qq/taf/RequestPacket/iMessageType I
  iconst_0
  istore 11
  aload_0
  iload 11
  putfield com/qq/taf/RequestPacket/iRequestId I
  aconst_null
  astore 12
  aload_0
  aload 12
  putfield com/qq/taf/RequestPacket/sServantName Ljava/lang/String;
  aconst_null
  astore 12
  aload_0
  aload 12
  putfield com/qq/taf/RequestPacket/sFuncName Ljava/lang/String;
  iconst_0
  istore 11
  aload_0
  iload 11
  putfield com/qq/taf/RequestPacket/iTimeout I
  aload_0
  iload_1
  putfield com/qq/taf/RequestPacket/iVersion S
  aload_0
  iload_2
  putfield com/qq/taf/RequestPacket/cPacketType B
  aload_0
  iload_3
  putfield com/qq/taf/RequestPacket/iMessageType I
  aload_0
  iload 4
  putfield com/qq/taf/RequestPacket/iRequestId I
  aload_0
  aload 5
  putfield com/qq/taf/RequestPacket/sServantName Ljava/lang/String;
  aload_0
  aload 6
  putfield com/qq/taf/RequestPacket/sFuncName Ljava/lang/String;
  aload_0
  aload 7
  putfield com/qq/taf/RequestPacket/sBuffer [B
  aload_0
  iload 8
  putfield com/qq/taf/RequestPacket/iTimeout I
  aload_0
  aload 9
  putfield com/qq/taf/RequestPacket/context Ljava/util/Map;
  aload_0
  aload 10
  putfield com/qq/taf/RequestPacket/status Ljava/util/Map;
  return
  nop
.end <method>

.method public clone()Ljava/lang/Object;
.limit locals 6
.limit stack 200
  .catch  java/lang/CloneNotSupportedException <from> Label2 <to> Label3 <using> Label1
  nop
  iconst_0
  istore_1
Label2:
  aload_0
  invokespecial java/lang/Object/clone()Ljava/lang/Object;
  astore_2
Label3:
  aload_2
  astore_1
Label0:
  aload_1
  areturn
Label1:
  astore_3
  getstatic com/qq/taf/RequestPacket/$assertionsDisabled Z
  istore 4
  new java/lang/NoClassDefFoundError
  dup
  invokespecial java/lang/NoClassDefFoundError/<init>()V
  athrow
  iload 4
  ifne Label0
  new java/lang/AssertionError
  astore 5
  aload 5
  invokespecial java/lang/AssertionError/<init>()V
  aload 5
  athrow
  nop
.end <method>

.method public display(Ljava/lang/StringBuilder;I)V
.limit locals 11
.limit stack 200
  nop
  new com/qq/taf/jce/JceDisplayer
  astore_3
  aload_3
  aload_1
  iload_2
  invokespecial com/qq/taf/jce/JceDisplayer/<init>(Ljava/lang/StringBuilder;I)V
  aload_0
  getfield com/qq/taf/RequestPacket/iVersion S
  istore 4
  ldc "iVersion"
  astore 5
  aload_3
  iload 4
  aload 5
  invokevirtual com/qq/taf/jce/JceDisplayer/display(SLjava/lang/String;)Lcom/qq/taf/jce/JceDisplayer;
  pop
  aload_0
  getfield com/qq/taf/RequestPacket/cPacketType B
  istore 6
  ldc "cPacketType"
  astore 5
  aload_3
  iload 6
  aload 5
  invokevirtual com/qq/taf/jce/JceDisplayer/display(BLjava/lang/String;)Lcom/qq/taf/jce/JceDisplayer;
  pop
  aload_0
  getfield com/qq/taf/RequestPacket/iMessageType I
  istore_2
  ldc "iMessageType"
  astore 5
  aload_3
  iload_2
  aload 5
  invokevirtual com/qq/taf/jce/JceDisplayer/display(ILjava/lang/String;)Lcom/qq/taf/jce/JceDisplayer;
  pop
  aload_0
  getfield com/qq/taf/RequestPacket/iRequestId I
  istore_2
  ldc "iRequestId"
  astore 5
  aload_3
  iload_2
  aload 5
  invokevirtual com/qq/taf/jce/JceDisplayer/display(ILjava/lang/String;)Lcom/qq/taf/jce/JceDisplayer;
  pop
  aload_0
  getfield com/qq/taf/RequestPacket/sServantName Ljava/lang/String;
  astore 7
  ldc "sServantName"
  astore 5
  aload_3
  aload 7
  aload 5
  invokevirtual com/qq/taf/jce/JceDisplayer/display(Ljava/lang/String;Ljava/lang/String;)Lcom/qq/taf/jce/JceDisplayer;
  pop
  aload_0
  getfield com/qq/taf/RequestPacket/sFuncName Ljava/lang/String;
  astore 8
  ldc "sFuncName"
  astore 5
  aload_3
  aload 8
  aload 5
  invokevirtual com/qq/taf/jce/JceDisplayer/display(Ljava/lang/String;Ljava/lang/String;)Lcom/qq/taf/jce/JceDisplayer;
  pop
  aload_0
  getfield com/qq/taf/RequestPacket/sBuffer [B
  astore 9
  ldc "sBuffer"
  astore 5
  aload_3
  aload 9
  aload 5
  invokevirtual com/qq/taf/jce/JceDisplayer/display([BLjava/lang/String;)Lcom/qq/taf/jce/JceDisplayer;
  pop
  aload_0
  getfield com/qq/taf/RequestPacket/iTimeout I
  istore_2
  ldc "iTimeout"
  astore 5
  aload_3
  iload_2
  aload 5
  invokevirtual com/qq/taf/jce/JceDisplayer/display(ILjava/lang/String;)Lcom/qq/taf/jce/JceDisplayer;
  pop
  aload_0
  getfield com/qq/taf/RequestPacket/context Ljava/util/Map;
  astore 10
  ldc "context"
  astore 5
  aload_3
  aload 10
  aload 5
  invokevirtual com/qq/taf/jce/JceDisplayer/display(Ljava/util/Map;Ljava/lang/String;)Lcom/qq/taf/jce/JceDisplayer;
  pop
  aload_0
  getfield com/qq/taf/RequestPacket/status Ljava/util/Map;
  astore 10
  ldc "status"
  astore 5
  aload_3
  aload 10
  aload 5
  invokevirtual com/qq/taf/jce/JceDisplayer/display(Ljava/util/Map;Ljava/lang/String;)Lcom/qq/taf/jce/JceDisplayer;
  pop
  return
  nop
.end <method>

.method public equals(Ljava/lang/Object;)Z
.limit locals 12
.limit stack 200
  nop
  aload_1
  astore_2
  aload_2
  checkcast com/qq/taf/RequestPacket
  astore_2
  aload_2
  astore_0
  aload_0
  getfield com/qq/taf/RequestPacket/iVersion S
  istore_3
  iconst_1
  istore 5
  iload 5
  iload_3
  invokestatic com/qq/taf/jce/JceUtil/equals(II)Z
  istore 4
  new java/lang/NoClassDefFoundError
  dup
  invokespecial java/lang/NoClassDefFoundError/<init>()V
  athrow
  iload 4
  ifeq Label0
  aload_0
  getfield com/qq/taf/RequestPacket/cPacketType B
  istore 6
  iconst_1
  istore 5
  iload 5
  iload 6
  invokestatic com/qq/taf/jce/JceUtil/equals(II)Z
  istore 4
  iload 4
  invokestatic app/DummyClass/invokeIfStmt(Z)V
  iload 4
  ifeq Label0
  aload_0
  getfield com/qq/taf/RequestPacket/iMessageType I
  istore 7
  iconst_1
  istore 5
  iload 5
  iload 7
  invokestatic com/qq/taf/jce/JceUtil/equals(II)Z
  istore 4
  iload 4
  invokestatic app/DummyClass/invokeIfStmt(Z)V
  iload 4
  ifeq Label0
  aload_0
  getfield com/qq/taf/RequestPacket/iRequestId I
  istore 7
  iconst_1
  istore 5
  iload 5
  iload 7
  invokestatic com/qq/taf/jce/JceUtil/equals(II)Z
  istore 4
  iload 4
  invokestatic app/DummyClass/invokeIfStmt(Z)V
  iload 4
  ifeq Label0
  iconst_1
  istore 5
  iload 5
  invokestatic java/lang/Integer/valueOf(I)Ljava/lang/Integer;
  astore 8
  aload_0
  getfield com/qq/taf/RequestPacket/sServantName Ljava/lang/String;
  astore 9
  aload 8
  aload 9
  invokestatic com/qq/taf/jce/JceUtil/equals(Ljava/lang/Object;Ljava/lang/Object;)Z
  istore 4
  iload 4
  invokestatic app/DummyClass/invokeIfStmt(Z)V
  iload 4
  ifeq Label0
  iconst_1
  istore 5
  iload 5
  invokestatic java/lang/Integer/valueOf(I)Ljava/lang/Integer;
  astore 8
  aload_0
  getfield com/qq/taf/RequestPacket/sFuncName Ljava/lang/String;
  astore 9
  aload 8
  aload 9
  invokestatic com/qq/taf/jce/JceUtil/equals(Ljava/lang/Object;Ljava/lang/Object;)Z
  istore 4
  iload 4
  invokestatic app/DummyClass/invokeIfStmt(Z)V
  iload 4
  ifeq Label0
  iconst_1
  istore 5
  iload 5
  invokestatic java/lang/Integer/valueOf(I)Ljava/lang/Integer;
  astore 8
  aload_0
  getfield com/qq/taf/RequestPacket/sBuffer [B
  astore 10
  aload 8
  aload 10
  invokestatic com/qq/taf/jce/JceUtil/equals(Ljava/lang/Object;Ljava/lang/Object;)Z
  istore 4
  iload 4
  invokestatic app/DummyClass/invokeIfStmt(Z)V
  iload 4
  ifeq Label0
  aload_0
  getfield com/qq/taf/RequestPacket/iTimeout I
  istore 7
  iconst_1
  istore 5
  iload 5
  iload 7
  invokestatic com/qq/taf/jce/JceUtil/equals(II)Z
  istore 4
  iload 4
  invokestatic app/DummyClass/invokeIfStmt(Z)V
  iload 4
  ifeq Label0
  iconst_1
  istore 5
  iload 5
  invokestatic java/lang/Integer/valueOf(I)Ljava/lang/Integer;
  astore 8
  aload_0
  getfield com/qq/taf/RequestPacket/context Ljava/util/Map;
  astore 11
  aload 8
  aload 11
  invokestatic com/qq/taf/jce/JceUtil/equals(Ljava/lang/Object;Ljava/lang/Object;)Z
  istore 4
  iload 4
  invokestatic app/DummyClass/invokeIfStmt(Z)V
  iload 4
  ifeq Label0
  iconst_1
  istore 5
  iload 5
  invokestatic java/lang/Integer/valueOf(I)Ljava/lang/Integer;
  astore 8
  aload_0
  getfield com/qq/taf/RequestPacket/status Ljava/util/Map;
  astore 11
  aload 8
  aload 11
  invokestatic com/qq/taf/jce/JceUtil/equals(Ljava/lang/Object;Ljava/lang/Object;)Z
  istore 4
  iload 4
  invokestatic app/DummyClass/invokeIfStmt(Z)V
  iload 4
  ifeq Label0
  iconst_1
  istore 5
  iload 5
  ireturn
Label0:
  iconst_0
  istore 5
  iload 5
  ireturn
  nop
.end <method>

.method public readFrom(Lcom/qq/taf/jce/JceInputStream;)V
.limit locals 24
.limit stack 200
  .catch  java/lang/Exception <from> Label4 <to> Label5 <using> Label3
  nop
Label4:
  aload_0
  astore_2
  aload_2
  getfield com/qq/taf/RequestPacket/iVersion S
  istore 4
  iconst_1
  istore 5
  iconst_1
  istore 6
  aload_1
  astore_2
  aload_2
  iload 4
  iload 5
  iload 6
  invokevirtual com/qq/taf/jce/JceInputStream/read(SIZ)S
  istore 4
  aload_0
  astore_2
  aload_2
  iload 4
  putfield com/qq/taf/RequestPacket/iVersion S
  aload_0
  astore_2
  aload_2
  getfield com/qq/taf/RequestPacket/cPacketType B
  istore 7
  iconst_2
  istore 5
  iconst_1
  istore 6
  aload_1
  astore_2
  aload_2
  iload 7
  iload 5
  iload 6
  invokevirtual com/qq/taf/jce/JceInputStream/read(BIZ)B
  istore 8
  aload_0
  astore_2
  aload_2
  iload 8
  putfield com/qq/taf/RequestPacket/cPacketType B
  aload_0
  astore_2
  aload_2
  getfield com/qq/taf/RequestPacket/iMessageType I
  istore 9
  iconst_3
  istore 5
  iconst_1
  istore 6
  aload_1
  astore_2
  aload_2
  iload 9
  iload 5
  iload 6
  invokevirtual com/qq/taf/jce/JceInputStream/read(IIZ)I
  istore 9
  aload_0
  astore_2
  aload_2
  iload 9
  putfield com/qq/taf/RequestPacket/iMessageType I
  aload_0
  astore_2
  aload_2
  getfield com/qq/taf/RequestPacket/iRequestId I
  istore 9
  iconst_4
  istore 5
  iconst_1
  istore 6
  aload_1
  astore_2
  aload_2
  iload 9
  iload 5
  iload 6
  invokevirtual com/qq/taf/jce/JceInputStream/read(IIZ)I
  istore 9
  aload_0
  astore_2
  aload_2
  iload 9
  putfield com/qq/taf/RequestPacket/iRequestId I
  iconst_5
  istore 5
  iconst_1
  istore 6
  aload_1
  astore_2
  aload_2
  iload 5
  iload 6
  invokevirtual com/qq/taf/jce/JceInputStream/readString(IZ)Ljava/lang/String;
  astore 10
  aload_0
  astore_2
  aload_2
  aload 10
  putfield com/qq/taf/RequestPacket/sServantName Ljava/lang/String;
  bipush 6
  istore 5
  iconst_1
  istore 6
  aload_1
  astore_2
  aload_2
  iload 5
  iload 6
  invokevirtual com/qq/taf/jce/JceInputStream/readString(IZ)Ljava/lang/String;
  astore 10
  aload_0
  astore_2
  aload_2
  aload 10
  putfield com/qq/taf/RequestPacket/sFuncName Ljava/lang/String;
  getstatic com/qq/taf/RequestPacket/cache_sBuffer [B
  astore 11
  new java/lang/NoClassDefFoundError
  dup
  invokespecial java/lang/NoClassDefFoundError/<init>()V
  athrow
  iload 11
  ifne Label0
  iconst_1
  istore 5
  iload 5
  newarray byte
  astore 11
  iconst_0
  istore 5
  iconst_0
  istore 6
  aload 11
  iload 5
  iload 6
  bastore
  aload 11
  putstatic com/qq/taf/RequestPacket/cache_sBuffer [B
Label0:
  getstatic com/qq/taf/RequestPacket/cache_sBuffer [B
  astore 11
  bipush 7
  istore 5
  iconst_1
  istore 6
  aload_1
  astore_2
  aload_2
  aload 11
  iload 5
  iload 6
  invokevirtual com/qq/taf/jce/JceInputStream/read([BIZ)[B
  astore 11
  aload 11
  checkcast [B
  astore 11
  aload_0
  astore_2
  aload_2
  aload 11
  putfield com/qq/taf/RequestPacket/sBuffer [B
  aload_0
  astore_2
  aload_2
  getfield com/qq/taf/RequestPacket/iTimeout I
  istore 9
  bipush 8
  istore 5
  iconst_1
  istore 6
  aload_1
  astore_2
  aload_2
  iload 9
  iload 5
  iload 6
  invokevirtual com/qq/taf/jce/JceInputStream/read(IIZ)I
  istore 9
  aload_0
  astore_2
  aload_2
  iload 9
  putfield com/qq/taf/RequestPacket/iTimeout I
  getstatic com/qq/taf/RequestPacket/cache_context Ljava/util/Map;
  astore 12
  aload 12
  invokestatic app/DummyClass/invokeIfStmt(Ljava/lang/Object;)V
  aload 12
  ifnonnull Label1
  new java/util/HashMap
  astore 13
  aload 13
  invokespecial java/util/HashMap/<init>()V
  aload 13
  putstatic com/qq/taf/RequestPacket/cache_context Ljava/util/Map;
  getstatic com/qq/taf/RequestPacket/cache_context Ljava/util/Map;
  astore 12
  ldc ""
  astore 14
  ldc ""
  astore 15
  aload 12
  aload 14
  aload 15
  invokeinterface java/util/Map/put(Ljava/lang/Object;Ljava/lang/Object;)Ljava/lang/Object; 3
  pop
Label1:
  getstatic com/qq/taf/RequestPacket/cache_context Ljava/util/Map;
  astore 12
  bipush 9
  istore 5
  iconst_1
  istore 6
  aload_1
  astore_2
  aload_2
  aload 12
  iload 5
  iload 6
  invokevirtual com/qq/taf/jce/JceInputStream/read(Ljava/lang/Object;IZ)Ljava/lang/Object;
  astore 16
  aload 16
  astore 17
  aload 17
  checkcast java/util/Map
  astore 17
  aload 17
  astore 12
  aload_0
  astore_2
  aload_2
  aload 12
  putfield com/qq/taf/RequestPacket/context Ljava/util/Map;
  getstatic com/qq/taf/RequestPacket/cache_context Ljava/util/Map;
  astore 12
  aload 12
  invokestatic app/DummyClass/invokeIfStmt(Ljava/lang/Object;)V
  aload 12
  ifnonnull Label2
  new java/util/HashMap
  astore 13
  aload 13
  invokespecial java/util/HashMap/<init>()V
  aload 13
  putstatic com/qq/taf/RequestPacket/cache_context Ljava/util/Map;
  getstatic com/qq/taf/RequestPacket/cache_context Ljava/util/Map;
  astore 12
  ldc ""
  astore 14
  ldc ""
  astore 15
  aload 12
  aload 14
  aload 15
  invokeinterface java/util/Map/put(Ljava/lang/Object;Ljava/lang/Object;)Ljava/lang/Object; 3
  pop
Label2:
  getstatic com/qq/taf/RequestPacket/cache_context Ljava/util/Map;
  astore 12
  bipush 10
  istore 5
  iconst_1
  istore 6
  aload_1
  astore_2
  aload_2
  aload 12
  iload 5
  iload 6
  invokevirtual com/qq/taf/jce/JceInputStream/read(Ljava/lang/Object;IZ)Ljava/lang/Object;
  astore 16
  aload 16
  astore 18
  aload 18
  checkcast java/util/Map
  astore 18
  aload 18
  astore 12
  aload_0
  astore_2
  aload_2
  aload 12
  putfield com/qq/taf/RequestPacket/status Ljava/util/Map;
Label5:
  return
Label3:
  astore 19
  aload 19
  astore_2
  aload_2
  invokevirtual java/lang/Exception/printStackTrace()V
  getstatic java/lang/System/out Ljava/io/PrintStream;
  astore 20
  new java/lang/StringBuilder
  astore 21
  aload 21
  astore_2
  aload_2
  invokespecial java/lang/StringBuilder/<init>()V
  ldc "RequestPacket decode error "
  astore 14
  aload 21
  astore_2
  aload_2
  aload 14
  invokevirtual java/lang/StringBuilder/append(Ljava/lang/String;)Ljava/lang/StringBuilder;
  astore 21
  aload_0
  astore_2
  aload_2
  getfield com/qq/taf/RequestPacket/sBuffer [B
  astore 11
  aload 11
  invokestatic com/qq/jce/wup/WupHexUtil/bytes2HexStr([B)Ljava/lang/String;
  astore 22
  aload 21
  astore_2
  aload 22
  astore_3
  aload_2
  aload_3
  invokevirtual java/lang/StringBuilder/append(Ljava/lang/String;)Ljava/lang/StringBuilder;
  astore 21
  aload 21
  astore_2
  aload_2
  invokevirtual java/lang/StringBuilder/toString()Ljava/lang/String;
  astore 22
  aload 20
  astore_2
  aload 22
  astore_3
  aload_2
  aload_3
  invokevirtual java/io/PrintStream/println(Ljava/lang/String;)V
  new java/lang/RuntimeException
  astore 23
  aload 23
  astore_2
  aload 19
  astore_3
  aload_2
  aload_3
  invokespecial java/lang/RuntimeException/<init>(Ljava/lang/Throwable;)V
  aload 23
  athrow
  nop
.end <method>

.method public writeTo(Lcom/qq/taf/jce/JceOutputStream;)V
.limit locals 9
.limit stack 200
  nop
  aload_0
  getfield com/qq/taf/RequestPacket/iVersion S
  istore_2
  iconst_1
  istore_3
  aload_1
  iload_2
  iload_3
  invokevirtual com/qq/taf/jce/JceOutputStream/write(SI)V
  aload_0
  getfield com/qq/taf/RequestPacket/cPacketType B
  istore 4
  iconst_2
  istore_3
  aload_1
  iload 4
  iload_3
  invokevirtual com/qq/taf/jce/JceOutputStream/write(BI)V
  aload_0
  getfield com/qq/taf/RequestPacket/iMessageType I
  istore 5
  iconst_3
  istore_3
  aload_1
  iload 5
  iload_3
  invokevirtual com/qq/taf/jce/JceOutputStream/write(II)V
  aload_0
  getfield com/qq/taf/RequestPacket/iRequestId I
  istore 5
  iconst_4
  istore_3
  aload_1
  iload 5
  iload_3
  invokevirtual com/qq/taf/jce/JceOutputStream/write(II)V
  aload_0
  getfield com/qq/taf/RequestPacket/sServantName Ljava/lang/String;
  astore 6
  iconst_5
  istore_3
  aload_1
  aload 6
  iload_3
  invokevirtual com/qq/taf/jce/JceOutputStream/write(Ljava/lang/String;I)V
  aload_0
  getfield com/qq/taf/RequestPacket/sFuncName Ljava/lang/String;
  astore 6
  bipush 6
  istore_3
  aload_1
  aload 6
  iload_3
  invokevirtual com/qq/taf/jce/JceOutputStream/write(Ljava/lang/String;I)V
  aload_0
  getfield com/qq/taf/RequestPacket/sBuffer [B
  astore 7
  bipush 7
  istore_3
  aload_1
  aload 7
  iload_3
  invokevirtual com/qq/taf/jce/JceOutputStream/write([BI)V
  aload_0
  getfield com/qq/taf/RequestPacket/iTimeout I
  istore 5
  bipush 8
  istore_3
  aload_1
  iload 5
  iload_3
  invokevirtual com/qq/taf/jce/JceOutputStream/write(II)V
  aload_0
  getfield com/qq/taf/RequestPacket/context Ljava/util/Map;
  astore 8
  bipush 9
  istore_3
  aload_1
  aload 8
  iload_3
  invokevirtual com/qq/taf/jce/JceOutputStream/write(Ljava/util/Map;I)V
  aload_0
  getfield com/qq/taf/RequestPacket/status Ljava/util/Map;
  astore 8
  bipush 10
  istore_3
  aload_1
  aload 8
  iload_3
  invokevirtual com/qq/taf/jce/JceOutputStream/write(Ljava/util/Map;I)V
  return
  nop
.end <method>

