.source dalvik_source_VirusShare_32e70f448ebd75661a1cb12f9cd8e013.apk
.class public final enum  com/google/ads/util/AdUtil$a
.super java/lang/Enum
  .signature_attr "Ljava/lang/Enum<Lcom/google/ads/util/AdUtil$a;>;"
.field public static final enum "a" Lcom/google/ads/util/AdUtil$a;
.field public static final enum "b" Lcom/google/ads/util/AdUtil$a;
.field public static final enum "c" Lcom/google/ads/util/AdUtil$a;
.field public static final enum "d" Lcom/google/ads/util/AdUtil$a;
.field public static final enum "e" Lcom/google/ads/util/AdUtil$a;
.field public static final enum "f" Lcom/google/ads/util/AdUtil$a;
.field private static final "g" [Lcom/google/ads/util/AdUtil$a;

.method static <clinit>()V
.limit locals 4
.limit stack 200
  nop
  new com/google/ads/util/AdUtil$a
  astore_0
  ldc "INVALID"
  astore_1
  iconst_0
  istore_2
  aload_0
  aload_1
  iload_2
  invokespecial com/google/ads/util/AdUtil$a/<init>(Ljava/lang/String;I)V
  aload_0
  putstatic com/google/ads/util/AdUtil$a/a Lcom/google/ads/util/AdUtil$a;
  new com/google/ads/util/AdUtil$a
  astore_0
  ldc "SPEAKER"
  astore_1
  iconst_1
  istore_2
  aload_0
  aload_1
  iload_2
  invokespecial com/google/ads/util/AdUtil$a/<init>(Ljava/lang/String;I)V
  aload_0
  putstatic com/google/ads/util/AdUtil$a/b Lcom/google/ads/util/AdUtil$a;
  new com/google/ads/util/AdUtil$a
  astore_0
  ldc "HEADPHONES"
  astore_1
  iconst_2
  istore_2
  aload_0
  aload_1
  iload_2
  invokespecial com/google/ads/util/AdUtil$a/<init>(Ljava/lang/String;I)V
  aload_0
  putstatic com/google/ads/util/AdUtil$a/c Lcom/google/ads/util/AdUtil$a;
  new com/google/ads/util/AdUtil$a
  astore_0
  ldc "VIBRATE"
  astore_1
  iconst_3
  istore_2
  aload_0
  aload_1
  iload_2
  invokespecial com/google/ads/util/AdUtil$a/<init>(Ljava/lang/String;I)V
  aload_0
  putstatic com/google/ads/util/AdUtil$a/d Lcom/google/ads/util/AdUtil$a;
  new com/google/ads/util/AdUtil$a
  astore_0
  ldc "EMULATOR"
  astore_1
  iconst_4
  istore_2
  aload_0
  aload_1
  iload_2
  invokespecial com/google/ads/util/AdUtil$a/<init>(Ljava/lang/String;I)V
  aload_0
  putstatic com/google/ads/util/AdUtil$a/e Lcom/google/ads/util/AdUtil$a;
  new com/google/ads/util/AdUtil$a
  astore_0
  ldc "OTHER"
  astore_1
  iconst_5
  istore_2
  aload_0
  aload_1
  iload_2
  invokespecial com/google/ads/util/AdUtil$a/<init>(Ljava/lang/String;I)V
  aload_0
  putstatic com/google/ads/util/AdUtil$a/f Lcom/google/ads/util/AdUtil$a;
  bipush 6
  istore_2
  iload_2
  anewarray com/google/ads/util/AdUtil$a
  astore_3
  getstatic com/google/ads/util/AdUtil$a/a Lcom/google/ads/util/AdUtil$a;
  astore_0
  iconst_0
  istore_2
  aload_3
  iload_2
  aload_0
  aastore
  getstatic com/google/ads/util/AdUtil$a/b Lcom/google/ads/util/AdUtil$a;
  astore_0
  iconst_1
  istore_2
  aload_3
  iload_2
  aload_0
  aastore
  getstatic com/google/ads/util/AdUtil$a/c Lcom/google/ads/util/AdUtil$a;
  astore_0
  iconst_2
  istore_2
  aload_3
  iload_2
  aload_0
  aastore
  getstatic com/google/ads/util/AdUtil$a/d Lcom/google/ads/util/AdUtil$a;
  astore_0
  iconst_3
  istore_2
  aload_3
  iload_2
  aload_0
  aastore
  getstatic com/google/ads/util/AdUtil$a/e Lcom/google/ads/util/AdUtil$a;
  astore_0
  iconst_4
  istore_2
  aload_3
  iload_2
  aload_0
  aastore
  getstatic com/google/ads/util/AdUtil$a/f Lcom/google/ads/util/AdUtil$a;
  astore_0
  iconst_5
  istore_2
  aload_3
  iload_2
  aload_0
  aastore
  aload_3
  putstatic com/google/ads/util/AdUtil$a/g [Lcom/google/ads/util/AdUtil$a;
  return
  nop
.end <method>

.method private <init>(Ljava/lang/String;I)V
  .signature_attr "()V"
.limit locals 3
.limit stack 200
  nop
  aload_0
  aload_1
  iload_2
  invokespecial java/lang/Enum/<init>(Ljava/lang/String;I)V
  return
  nop
.end <method>

.method public static valueOf(Ljava/lang/String;)Lcom/google/ads/util/AdUtil$a;
.limit locals 5
.limit stack 200
  nop
  ldc com/google/ads/util/AdUtil$a
  astore_2
  aload_2
  aload_0
  invokestatic java/lang/Enum/valueOf(Ljava/lang/Class;Ljava/lang/String;)Ljava/lang/Enum;
  astore_1
  aload_1
  astore 4
  aload 4
  checkcast com/google/ads/util/AdUtil$a
  astore 4
  aload 4
  astore_3
  aload_3
  areturn
  nop
.end <method>

.method public static values()[Lcom/google/ads/util/AdUtil$a;
.limit locals 3
.limit stack 200
  nop
  getstatic com/google/ads/util/AdUtil$a/g [Lcom/google/ads/util/AdUtil$a;
  astore_0
  aload_0
  invokevirtual java/lang/Object/clone()Ljava/lang/Object;
  astore_1
  aload_1
  astore_2
  aload_2
  checkcast [Lcom/google/ads/util/AdUtil$a;
  astore_2
  aload_2
  astore_0
  aload_0
  areturn
  nop
.end <method>

