.source dalvik_source_VirusShare_32e70f448ebd75661a1cb12f9cd8e013.apk
.class  com/wiyun/ad/AdView$3$1
.super java/lang/Object
.implements  java/lang/Runnable
.field final "a" Lcom/wiyun/ad/AdView$3;

.method <init>(Lcom/wiyun/ad/AdView$3;)V
.limit locals 2
.limit stack 200
  nop
  aload_0
  aload_1
  putfield com/wiyun/ad/AdView$3$1/a Lcom/wiyun/ad/AdView$3;
  aload_0
  invokespecial java/lang/Object/<init>()V
  return
  nop
.end <method>

.method public run()V
.limit locals 4
.limit stack 200
  nop
  aload_0
  getfield com/wiyun/ad/AdView$3$1/a Lcom/wiyun/ad/AdView$3;
  astore_1
  aload_1
  invokestatic com/wiyun/ad/AdView$3/a(Lcom/wiyun/ad/AdView$3;)Lcom/wiyun/ad/AdView;
  astore_2
  new java/lang/NoClassDefFoundError
  dup
  invokespecial java/lang/NoClassDefFoundError/<init>()V
  athrow
  nop
  dload_3
  invokestatic app/DummyClass/invokeIfStmt(D)V
  iload_3
  ifeq Label0
  aload_0
  getfield com/wiyun/ad/AdView$3$1/a Lcom/wiyun/ad/AdView$3;
  astore_1
  aload_1
  invokestatic com/wiyun/ad/AdView$3/a(Lcom/wiyun/ad/AdView$3;)Lcom/wiyun/ad/AdView;
  astore_2
  aload_2
  invokevirtual com/wiyun/ad/AdView/requestAd()V
Label0:
  return
  nop
.end <method>

