.source dalvik_source_VirusShare_32e70f448ebd75661a1cb12f9cd8e013.apk
.class  com/wiyun/ad/x
.super java/lang/Object
.field private static "a" [C

.method static <clinit>()V
.limit locals 3
.limit stack 200
  nop
  bipush 16
  istore_1
  iload_1
  newarray char
  astore_0
  iconst_0
  istore_1
  bipush 48
  istore_2
  aload_0
  iload_1
  iload_2
  castore
  iconst_1
  istore_1
  bipush 49
  istore_2
  aload_0
  iload_1
  iload_2
  castore
  iconst_2
  istore_1
  bipush 50
  istore_2
  aload_0
  iload_1
  iload_2
  castore
  iconst_3
  istore_1
  bipush 51
  istore_2
  aload_0
  iload_1
  iload_2
  castore
  iconst_4
  istore_1
  bipush 52
  istore_2
  aload_0
  iload_1
  iload_2
  castore
  iconst_5
  istore_1
  bipush 53
  istore_2
  aload_0
  iload_1
  iload_2
  castore
  bipush 6
  istore_1
  bipush 54
  istore_2
  aload_0
  iload_1
  iload_2
  castore
  bipush 7
  istore_1
  bipush 55
  istore_2
  aload_0
  iload_1
  iload_2
  castore
  bipush 8
  istore_1
  bipush 56
  istore_2
  aload_0
  iload_1
  iload_2
  castore
  bipush 9
  istore_1
  bipush 57
  istore_2
  aload_0
  iload_1
  iload_2
  castore
  bipush 10
  istore_1
  bipush 97
  istore_2
  aload_0
  iload_1
  iload_2
  castore
  bipush 11
  istore_1
  bipush 98
  istore_2
  aload_0
  iload_1
  iload_2
  castore
  bipush 12
  istore_1
  bipush 99
  istore_2
  aload_0
  iload_1
  iload_2
  castore
  bipush 13
  istore_1
  bipush 100
  istore_2
  aload_0
  iload_1
  iload_2
  castore
  bipush 14
  istore_1
  bipush 101
  istore_2
  aload_0
  iload_1
  iload_2
  castore
  bipush 15
  istore_1
  bipush 102
  istore_2
  aload_0
  iload_1
  iload_2
  castore
  aload_0
  putstatic com/wiyun/ad/x/a [C
  return
  nop
.end <method>

.method <init>()V
.limit locals 1
.limit stack 200
  nop
  aload_0
  invokespecial java/lang/Object/<init>()V
  return
  nop
.end <method>

.method public static a(F)F
.limit locals 5
.limit stack 200
  nop
  invokestatic com/wiyun/ad/ab/m()Landroid/content/Context;
  astore_1
  new java/lang/NoClassDefFoundError
  dup
  invokespecial java/lang/NoClassDefFoundError/<init>()V
  athrow
  iload_1
  ifne Label0
  fload_0
  freturn
Label0:
  aload_1
  invokevirtual android/content/Context/getResources()Landroid/content/res/Resources;
  astore_2
  aload_2
  invokevirtual android/content/res/Resources/getDisplayMetrics()Landroid/util/DisplayMetrics;
  astore_3
  iconst_1
  istore 4
  iload 4
  fload_0
  aload_3
  invokestatic android/util/TypedValue/applyDimension(IFLandroid/util/DisplayMetrics;)F
  fstore_0
  fload_0
  freturn
  nop
.end <method>

.method public static a(ILjava/lang/String;)I
.limit locals 3
.limit stack 200
  nop
  iconst_0
  istore_2
  iload_0
  aload_1
  iload_2
  invokestatic com/wiyun/ad/x/a(ILjava/lang/String;I)I
  istore_0
  iload_0
  ireturn
  nop
.end <method>

.method public static a(ILjava/lang/String;I)I
.limit locals 6
.limit stack 200
  nop
  new java/lang/NoClassDefFoundError
  dup
  invokespecial java/lang/NoClassDefFoundError/<init>()V
  athrow
  iload_1
  ifne Label0
  iload_2
  ireturn
Label0:
  aload_1
  invokevirtual java/lang/String/trim()Ljava/lang/String;
  astore_1
  aload_1
  iload_0
  invokestatic java/lang/Long/parseLong(Ljava/lang/String;I)J
  lstore_3
Label2:
  lload_3
  l2i
  istore_2
  iload_2
  ireturn
Label1:
  astore 5
  iload_2
  ireturn
  nop
.end <method>

.method private static a(Ljava/lang/String;Ljava/lang/String;I)I
.limit locals 9
.limit stack 200
  nop
  aload_1
  invokevirtual java/lang/String/length()I
  istore_3
  iconst_0
  istore 4
  ldc 2147483647
  istore 5
Label3:
  new java/lang/NoClassDefFoundError
  dup
  invokespecial java/lang/NoClassDefFoundError/<init>()V
  athrow
  dload_3
  invokestatic app/DummyClass/invokeIfStmt(D)V
  iload 4
  iload_3
  if_icmplt Label0
  dload 5
  invokestatic app/DummyClass/invokeIfStmt(D)V
  ldc 2147483647
  istore 6
  iload 5
  iload 6
  if_icmpne Label1
  iconst_m1
  istore 5
Label1:
  iload 5
  ireturn
Label0:
  aload_1
  iload 4
  invokevirtual java/lang/String/charAt(I)C
  istore 7
  aload_0
  iload 7
  iload_2
  invokevirtual java/lang/String/indexOf(II)I
  istore 8
  dload 8
  invokestatic app/DummyClass/invokeIfStmt(D)V
  iconst_m1
  istore 6
  iload 8
  iload 6
  if_icmpeq Label2
  iload 5
  iload 8
  invokestatic java/lang/Math/min(II)I
  istore 5
Label2:
  iload 4
  iconst_1
  iadd
  istore 4
  goto Label3
  nop
.end <method>

.method public static a(Ljava/lang/String;Ljava/lang/String;)Ljava/lang/String;
.limit locals 14
.limit stack 200
  nop
  new java/lang/NoClassDefFoundError
  dup
  invokespecial java/lang/NoClassDefFoundError/<init>()V
  athrow
  iload_0
  ifne Label0
  aconst_null
  astore_2
  aload_2
  areturn
Label0:
  ldc "://"
  astore 4
  aload_0
  aload 4
  invokevirtual java/lang/String/indexOf(Ljava/lang/String;)I
  istore_3
  iload_3
  iconst_3
  iadd
  istore 5
  aload_0
  iload 5
  invokevirtual java/lang/String/substring(I)Ljava/lang/String;
  astore 6
  ldc "/"
  astore 4
  aload 6
  aload 4
  invokevirtual java/lang/String/split(Ljava/lang/String;)[Ljava/lang/String;
  astore 7
  new java/lang/StringBuilder
  astore 8
  iload_3
  iconst_3
  iadd
  istore_3
  iconst_0
  istore 9
  aload_0
  iload 9
  iload_3
  invokevirtual java/lang/String/substring(II)Ljava/lang/String;
  astore 6
  aload 8
  aload 6
  invokespecial java/lang/StringBuilder/<init>(Ljava/lang/String;)V
  iconst_0
  istore 9
  aload 7
  iload 9
  aaload
  astore 6
  aload 8
  aload 6
  invokevirtual java/lang/StringBuilder/append(Ljava/lang/String;)Ljava/lang/StringBuilder;
  pop
  bipush 47
  istore 9
  aload 8
  iload 9
  invokevirtual java/lang/StringBuilder/append(C)Ljava/lang/StringBuilder;
  pop
  iconst_1
  dstore_3
Label4:
  aload 7
  arraylength
  istore 5
  dload_3
  invokestatic app/DummyClass/invokeIfStmt(D)V
  dload 5
  invokestatic app/DummyClass/invokeIfStmt(D)V
  iload_3
  iload 5
  if_icmplt Label1
  aload 8
  invokevirtual java/lang/StringBuilder/toString()Ljava/lang/String;
  astore 6
  aload 6
  areturn
Label1:
  aload 7
  iload_3
  aaload
  astore 10
  bipush 37
  istore 9
  aload 10
  iload 9
  invokevirtual java/lang/String/indexOf(I)I
  istore 5
  dload 5
  invokestatic app/DummyClass/invokeIfStmt(D)V
  iconst_m1
  istore 9
  iload 5
  iload 9
  if_icmpne Label2
  aload 8
  aload 10
  aload_1
  invokestatic com/wiyun/ad/x/a(Ljava/lang/StringBuilder;Ljava/lang/String;Ljava/lang/String;)V
Label6:
  aload 7
  arraylength
  istore 5
  iload 5
  iconst_m1
  iadd
  istore 5
  dload_3
  invokestatic app/DummyClass/invokeIfStmt(D)V
  dload 5
  invokestatic app/DummyClass/invokeIfStmt(D)V
  iload_3
  iload 5
  if_icmpge Label3
  bipush 47
  istore 9
  aload 8
  iload 9
  invokevirtual java/lang/StringBuilder/append(C)Ljava/lang/StringBuilder;
  pop
Label3:
  iload_3
  iconst_1
  iadd
  istore_3
  goto Label4
Label2:
  iconst_0
  istore 11
Label8:
  dload 5
  invokestatic app/DummyClass/invokeIfStmt(D)V
  iconst_m1
  istore 9
  iload 5
  iload 9
  if_icmpne Label5
  aload 10
  iload 11
  invokevirtual java/lang/String/substring(I)Ljava/lang/String;
  astore 6
  aload 8
  aload 6
  aload_1
  invokestatic com/wiyun/ad/x/a(Ljava/lang/StringBuilder;Ljava/lang/String;Ljava/lang/String;)V
  goto Label6
Label19:
  astore 12
  aload_0
  areturn
Label5:
  aload 10
  iload 11
  iload 5
  invokevirtual java/lang/String/substring(II)Ljava/lang/String;
  astore 6
  aload 8
  aload 6
  aload_1
  invokestatic com/wiyun/ad/x/a(Ljava/lang/StringBuilder;Ljava/lang/String;Ljava/lang/String;)V
  aload 10
  invokevirtual java/lang/String/length()I
  istore 11
  iload 11
  iconst_m1
  iadd
  istore 11
  dload 5
  invokestatic app/DummyClass/invokeIfStmt(D)V
  dload 11
  invokestatic app/DummyClass/invokeIfStmt(D)V
  iload 5
  iload 11
  if_icmpne Label7
  ldc "%25"
  astore 4
  aload 8
  aload 4
  invokevirtual java/lang/StringBuilder/append(Ljava/lang/String;)Ljava/lang/StringBuilder;
  pop
  aload 10
  invokevirtual java/lang/String/length()I
  istore 11
  iconst_m1
  istore 5
  goto Label8
Label7:
  aload 10
  invokevirtual java/lang/String/length()I
  istore 11
  iload 11
  bipush -2
  iadd
  istore 11
  dload 5
  invokestatic app/DummyClass/invokeIfStmt(D)V
  dload 11
  invokestatic app/DummyClass/invokeIfStmt(D)V
  iload 5
  iload 11
  if_icmpge Label9
  iload 5
  iconst_1
  iadd
  istore 11
  aload 10
  iload 11
  invokevirtual java/lang/String/charAt(I)C
  istore 13
  dload 13
  invokestatic app/DummyClass/invokeIfStmt(D)V
  bipush 37
  istore 9
  iload 13
  iload 9
  if_icmpne Label10
  ldc "%25"
  astore 4
  aload 8
  aload 4
  invokevirtual java/lang/StringBuilder/append(Ljava/lang/String;)Ljava/lang/StringBuilder;
  pop
  iload 5
  iconst_2
  iadd
  istore 11
  bipush 37
  istore 9
  aload 10
  iload 9
  iload 11
  invokevirtual java/lang/String/indexOf(II)I
  istore 5
  goto Label8
Label10:
  dload 13
  invokestatic app/DummyClass/invokeIfStmt(D)V
  bipush 48
  istore 9
  iload 13
  iload 9
  if_icmplt Label11
  dload 13
  invokestatic app/DummyClass/invokeIfStmt(D)V
  bipush 57
  istore 9
  iload 13
  iload 9
  if_icmple Label12
Label11:
  dload 13
  invokestatic app/DummyClass/invokeIfStmt(D)V
  bipush 65
  istore 9
  iload 13
  iload 9
  if_icmplt Label13
  dload 13
  invokestatic app/DummyClass/invokeIfStmt(D)V
  bipush 90
  istore 9
  iload 13
  iload 9
  if_icmple Label12
Label13:
  dload 13
  invokestatic app/DummyClass/invokeIfStmt(D)V
  bipush 97
  istore 9
  iload 13
  iload 9
  if_icmplt Label14
  dload 13
  invokestatic app/DummyClass/invokeIfStmt(D)V
  bipush 122
  istore 9
  iload 13
  iload 9
  if_icmpgt Label14
Label12:
  iload 5
  iconst_2
  iadd
  istore 11
  aload 10
  iload 11
  invokevirtual java/lang/String/charAt(I)C
  istore 13
  dload 13
  invokestatic app/DummyClass/invokeIfStmt(D)V
  bipush 48
  istore 9
  iload 13
  iload 9
  if_icmplt Label15
  dload 13
  invokestatic app/DummyClass/invokeIfStmt(D)V
  bipush 57
  istore 9
  iload 13
  iload 9
  if_icmple Label16
Label15:
  dload 13
  invokestatic app/DummyClass/invokeIfStmt(D)V
  bipush 65
  istore 9
  iload 13
  iload 9
  if_icmplt Label17
  dload 13
  invokestatic app/DummyClass/invokeIfStmt(D)V
  bipush 90
  istore 9
  iload 13
  iload 9
  if_icmple Label16
Label17:
  dload 13
  invokestatic app/DummyClass/invokeIfStmt(D)V
  bipush 97
  istore 9
  iload 13
  iload 9
  if_icmplt Label18
  dload 13
  invokestatic app/DummyClass/invokeIfStmt(D)V
  bipush 122
  istore 9
  iload 13
  iload 9
  if_icmpgt Label18
Label16:
  iload 5
  iconst_3
  iadd
  istore 11
  aload 10
  iload 5
  iload 11
  invokevirtual java/lang/String/substring(II)Ljava/lang/String;
  astore 6
  aload 8
  aload 6
  invokevirtual java/lang/StringBuilder/append(Ljava/lang/String;)Ljava/lang/StringBuilder;
  pop
  iload 5
  iconst_3
  iadd
  istore 11
  bipush 37
  istore 9
  aload 10
  iload 9
  iload 11
  invokevirtual java/lang/String/indexOf(II)I
  istore 5
  goto Label8
Label18:
  ldc "%25"
  astore 4
  aload 8
  aload 4
  invokevirtual java/lang/StringBuilder/append(Ljava/lang/String;)Ljava/lang/StringBuilder;
  pop
  iload 5
  iconst_1
  iadd
  istore 11
  bipush 37
  istore 9
  aload 10
  iload 9
  iload 11
  invokevirtual java/lang/String/indexOf(II)I
  istore 5
  goto Label8
Label14:
  ldc "%25"
  astore 4
  aload 8
  aload 4
  invokevirtual java/lang/StringBuilder/append(Ljava/lang/String;)Ljava/lang/StringBuilder;
  pop
  iload 5
  iconst_1
  iadd
  istore 11
  bipush 37
  istore 9
  aload 10
  iload 9
  iload 11
  invokevirtual java/lang/String/indexOf(II)I
  istore 5
  goto Label8
Label9:
  ldc "%25"
  astore 4
  aload 8
  aload 4
  invokevirtual java/lang/StringBuilder/append(Ljava/lang/String;)Ljava/lang/StringBuilder;
  pop
  iload 5
  iconst_1
  iadd
  istore 11
  bipush 37
  istore 9
  aload 10
  iload 9
  iload 11
  invokevirtual java/lang/String/indexOf(II)I
  istore 5
Label20:
  goto Label8
  nop
.end <method>

.method public static a([B)Ljava/lang/String;
.limit locals 4
.limit stack 200
  nop
  aload_0
  arraylength
  istore_1
  iconst_0
  istore_3
  aload_0
  iload_3
  iload_1
  invokestatic com/wiyun/ad/x/a([BII)Ljava/lang/String;
  astore_2
  aload_2
  areturn
  nop
.end <method>

.method public static a([BII)Ljava/lang/String;
.limit locals 13
.limit stack 200
  nop
  new java/lang/NoClassDefFoundError
  dup
  invokespecial java/lang/NoClassDefFoundError/<init>()V
  athrow
  iload_0
  ifne Label0
  ldc "null"
  astore_3
  aload_3
  areturn
Label0:
  iload_1
  iload_2
  iadd
  istore 4
  aload_0
  arraylength
  istore_2
  dload 4
  invokestatic app/DummyClass/invokeIfStmt(D)V
  dload_2
  invokestatic app/DummyClass/invokeIfStmt(D)V
  iload 4
  iload_2
  if_icmple Label1
  aload_0
  arraylength
  istore 4
Label1:
  new java/lang/StringBuilder
  astore 5
  aload 5
  invokespecial java/lang/StringBuilder/<init>()V
Label3:
  dload_1
  invokestatic app/DummyClass/invokeIfStmt(D)V
  dload 4
  invokestatic app/DummyClass/invokeIfStmt(D)V
  iload_1
  iload 4
  if_icmplt Label2
  aload 5
  invokevirtual java/lang/StringBuilder/toString()Ljava/lang/String;
  astore 6
  aload 6
  areturn
Label2:
  getstatic com/wiyun/ad/x/a [C
  astore 7
  aload_0
  iload_1
  baload
  istore 8
  sipush 240
  istore 10
  iload 8
  iload 10
  iand
  istore 9
  iconst_4
  istore 10
  iload 9
  iload 10
  iushr
  istore 9
  aload 7
  iload 9
  caload
  istore 11
  aload 5
  iload 11
  invokevirtual java/lang/StringBuilder/append(C)Ljava/lang/StringBuilder;
  astore 12
  getstatic com/wiyun/ad/x/a [C
  astore 7
  aload_0
  iload_1
  baload
  istore 8
  bipush 15
  istore 10
  iload 8
  iload 10
  iand
  istore 8
  aload 7
  iload 8
  caload
  istore 11
  aload 12
  iload 11
  invokevirtual java/lang/StringBuilder/append(C)Ljava/lang/StringBuilder;
  pop
  iload_1
  iconst_1
  iadd
  istore_1
  goto Label3
  nop
.end <method>

.method private static a(Ljava/lang/StringBuilder;Ljava/lang/String;Ljava/lang/String;)V
.limit locals 9
.limit stack 200
  nop
  iconst_0
  istore_3
  ldc "?&=:,()+ "
  astore 5
  iconst_0
  istore 6
  aload_1
  aload 5
  iload 6
  invokestatic com/wiyun/ad/x/a(Ljava/lang/String;Ljava/lang/String;I)I
  istore 4
  new java/lang/NoClassDefFoundError
  dup
  invokespecial java/lang/NoClassDefFoundError/<init>()V
  athrow
  iconst_m1
  istore 6
  iload 4
  iload 6
  if_icmpne Label0
  aload_1
  aload_2
  invokestatic java/net/URLEncoder/encode(Ljava/lang/String;Ljava/lang/String;)Ljava/lang/String;
  astore 7
  aload_0
  aload 7
  invokevirtual java/lang/StringBuilder/append(Ljava/lang/String;)Ljava/lang/StringBuilder;
  pop
Label3:
  return
Label2:
  aload_1
  iload_3
  iload 4
  invokevirtual java/lang/String/substring(II)Ljava/lang/String;
  astore 7
  aload 7
  aload_2
  invokestatic java/net/URLEncoder/encode(Ljava/lang/String;Ljava/lang/String;)Ljava/lang/String;
  astore 7
  aload_0
  aload 7
  invokevirtual java/lang/StringBuilder/append(Ljava/lang/String;)Ljava/lang/StringBuilder;
  pop
  aload_1
  iload 4
  invokevirtual java/lang/String/charAt(I)C
  istore 8
  dload 8
  invokestatic app/DummyClass/invokeIfStmt(D)V
  bipush 32
  istore 6
  iload 8
  iload 6
  if_icmpne Label1
  ldc "%20"
  astore 5
  aload_0
  aload 5
  invokevirtual java/lang/StringBuilder/append(Ljava/lang/String;)Ljava/lang/StringBuilder;
  pop
Label4:
  iload 4
  iconst_1
  iadd
  istore_3
  ldc "?&=:,()+ "
  astore 5
  aload_1
  aload 5
  iload_3
  invokestatic com/wiyun/ad/x/a(Ljava/lang/String;Ljava/lang/String;I)I
  istore 4
Label0:
  dload 4
  invokestatic app/DummyClass/invokeIfStmt(D)V
  iconst_m1
  istore 6
  iload 4
  iload 6
  if_icmpne Label2
  aload_1
  iload_3
  invokevirtual java/lang/String/substring(I)Ljava/lang/String;
  astore 7
  aload 7
  aload_2
  invokestatic java/net/URLEncoder/encode(Ljava/lang/String;Ljava/lang/String;)Ljava/lang/String;
  astore 7
  aload_0
  aload 7
  invokevirtual java/lang/StringBuilder/append(Ljava/lang/String;)Ljava/lang/StringBuilder;
  pop
  goto Label3
Label1:
  aload_0
  iload 8
  invokevirtual java/lang/StringBuilder/append(C)Ljava/lang/StringBuilder;
  pop
  goto Label4
  nop
.end <method>

.method public static a()Z
.limit locals 3
.limit stack 200
  nop
  new java/lang/NoClassDefFoundError
  dup
  invokespecial java/lang/NoClassDefFoundError/<init>()V
  athrow
  nop
  ldc "mounted"
  astore_1
  aload_1
  aload_0
  invokevirtual java/lang/String/equals(Ljava/lang/Object;)Z
  istore_2
  iload_2
  ireturn
  nop
.end <method>

.method public static a(Ljava/io/File;)Z
.limit locals 7
.limit stack 200
  nop
  new java/lang/NoClassDefFoundError
  dup
  invokespecial java/lang/NoClassDefFoundError/<init>()V
  athrow
  iload_0
  ifne Label0
Label3:
  iconst_0
  istore_1
  iload_1
  ireturn
Label0:
  aload_0
  invokevirtual java/io/File/isDirectory()Z
  istore_2
  iload_2
  invokestatic app/DummyClass/invokeIfStmt(Z)V
  iload_2
  ifeq Label1
  aload_0
  invokevirtual java/io/File/listFiles()[Ljava/io/File;
  astore_3
  aload_3
  arraylength
  istore 4
  iconst_0
  dstore 5
Label4:
  dload 5
  invokestatic app/DummyClass/invokeIfStmt(D)V
  dload 4
  invokestatic app/DummyClass/invokeIfStmt(D)V
  iload 5
  iload 4
  if_icmplt Label2
  aload_0
  invokevirtual java/io/File/delete()Z
  istore_2
  iload_2
  ireturn
Label2:
  aload_3
  iload 5
  aaload
  astore 6
  aload 6
  invokestatic com/wiyun/ad/x/a(Ljava/io/File;)Z
  istore_2
  iload_2
  invokestatic app/DummyClass/invokeIfStmt(Z)V
  iload_2
  ifeq Label3
  iload 5
  iconst_1
  iadd
  istore 5
  goto Label4
Label1:
  aload_0
  invokevirtual java/io/File/delete()Z
  istore_2
  iload_2
  ireturn
  nop
.end <method>

.method public static a(Ljava/io/File;[B)Z
.limit locals 19
.limit stack 200
  nop
  aload_0
  astore_2
  aload_2
  invokevirtual java/io/File/getParentFile()Ljava/io/File;
  astore_3
  aload_3
  invokevirtual java/io/File/exists()Z
  istore 4
  new java/lang/NoClassDefFoundError
  dup
  invokespecial java/lang/NoClassDefFoundError/<init>()V
  athrow
  iload 4
  ifne Label0
  aload_0
  astore_2
  aload_2
  invokevirtual java/io/File/getParentFile()Ljava/io/File;
  astore_3
  aload_3
  invokevirtual java/io/File/mkdirs()Z
  pop
Label0:
  aconst_null
  astore 5
Label9:
  aload_0
  astore_2
  aload_2
  invokevirtual java/io/File/exists()Z
  istore 4
  iload 4
  invokestatic app/DummyClass/invokeIfStmt(Z)V
  iload 4
  ifne Label1
  aload_0
  astore_2
  aload_2
  invokevirtual java/io/File/createNewFile()Z
  pop
Label1:
  new java/io/FileOutputStream
  astore 6
  aload_0
  astore_2
  aload 6
  aload_2
  invokespecial java/io/FileOutputStream/<init>(Ljava/io/File;)V
Label10:
  aload_1
  astore_2
  aload 6
  aload_2
  invokevirtual java/io/FileOutputStream/write([B)V
  aload 6
  invokevirtual java/io/FileOutputStream/flush()V
Label13:
  aload 6
  invokestatic app/DummyClass/invokeIfStmt(Ljava/lang/Object;)V
  aload 6
  ifnull Label2
Label15:
  aload 6
  invokevirtual java/io/FileOutputStream/close()V
Label2:
  iconst_1
  istore 7
  iload 7
  ireturn
Label8:
  astore 8
Label6:
  new java/lang/StringBuilder
  astore 9
  ldc "Failed to save to file: "
  astore 10
  aload 9
  aload 10
  invokespecial java/lang/StringBuilder/<init>(Ljava/lang/String;)V
  aload_0
  astore_2
  aload_2
  invokevirtual java/io/File/getAbsolutePath()Ljava/lang/String;
  astore 11
  aload 9
  aload 11
  invokevirtual java/lang/StringBuilder/append(Ljava/lang/String;)Ljava/lang/StringBuilder;
  astore 9
  aload 9
  invokevirtual java/lang/StringBuilder/toString()Ljava/lang/String;
  astore 11
  ldc "WiYun"
  astore 10
  aload 10
  aload 11
  invokestatic android/util/Log/w(Ljava/lang/String;Ljava/lang/String;)I
  pop
Label17:
  aload 5
  invokestatic app/DummyClass/invokeIfStmt(Ljava/lang/Object;)V
  aload 5
  ifnull Label3
Label19:
  aload 5
  invokevirtual java/io/FileOutputStream/close()V
Label3:
  iconst_0
  istore 7
  iload 7
  ireturn
Label7:
  astore 12
  aconst_null
  astore 6
  aload 12
  astore 13
Label5:
  aload 6
  invokestatic app/DummyClass/invokeIfStmt(Ljava/lang/Object;)V
  aload 6
  ifnull Label4
Label21:
  aload 6
  invokevirtual java/io/FileOutputStream/close()V
Label4:
  aload 13
  athrow
Label14:
  astore 14
  goto Label2
Label18:
  astore 15
  goto Label3
Label20:
  astore 16
  goto Label4
Label11:
  astore 13
  goto Label5
Label16:
  astore 17
  aload 5
  astore 6
  aload 17
  astore 13
  goto Label5
Label12:
  astore 18
  aload 6
  astore 5
  goto Label6
  nop
.end <method>

.method public static a(Ljava/lang/String;)[B
.limit locals 11
.limit stack 200
  nop
  new java/lang/NoClassDefFoundError
  dup
  invokespecial java/lang/NoClassDefFoundError/<init>()V
  athrow
  iload_0
  ifne Label0
  iconst_0
  istore_2
  iload_2
  newarray byte
  astore_1
  aload_1
  areturn
Label0:
  ldc "UTF-8"
  astore 4
  aload_0
  aload 4
  invokevirtual java/lang/String/getBytes(Ljava/lang/String;)[B
  astore_3
Label2:
  aload_3
  areturn
Label1:
  astore 5
  new java/io/ByteArrayOutputStream
  astore 6
Label4:
  aload 6
  invokespecial java/io/ByteArrayOutputStream/<init>()V
  new java/io/DataOutputStream
  astore 7
  aload 7
  aload 6
  invokespecial java/io/DataOutputStream/<init>(Ljava/io/OutputStream;)V
  aload 7
  aload_0
  invokevirtual java/io/DataOutputStream/writeUTF(Ljava/lang/String;)V
  aload 6
  invokevirtual java/io/ByteArrayOutputStream/toByteArray()[B
  astore_3
  aload 6
  invokevirtual java/io/ByteArrayOutputStream/close()V
  aload 7
  invokevirtual java/io/DataOutputStream/close()V
  aload_3
  arraylength
  istore 8
  iload 8
  bipush -2
  iadd
  istore 8
  iload 8
  newarray byte
  astore_1
  aload_1
  arraylength
  istore 8
  iconst_2
  istore_2
  iconst_0
  istore 9
  aload_3
  iload_2
  aload_1
  iload 9
  iload 8
  invokestatic java/lang/System/arraycopy(Ljava/lang/Object;ILjava/lang/Object;II)V
Label5:
  aload_1
  areturn
Label3:
  astore 10
  iconst_0
  istore_2
  iload_2
  newarray byte
  astore_1
  aload_1
  areturn
  nop
.end <method>

.method public static b(Ljava/lang/String;Ljava/lang/String;)I
.limit locals 12
.limit stack 200
  nop
  new java/lang/NoClassDefFoundError
  dup
  invokespecial java/lang/NoClassDefFoundError/<init>()V
  athrow
  iload_0
  ifne Label0
  iconst_0
  istore_3
  iload_3
  anewarray java/lang/String
  astore_2
Label4:
  aload_1
  invokestatic app/DummyClass/invokeIfStmt(Ljava/lang/Object;)V
  iload_1
  ifne Label1
  iconst_0
  istore_3
  iload_3
  anewarray java/lang/String
  astore 4
Label5:
  aload_2
  arraylength
  istore 5
  aload 4
  arraylength
  istore 6
  iconst_0
  dstore 7
Label7:
  dload 7
  invokestatic app/DummyClass/invokeIfStmt(D)V
  dload 5
  invokestatic app/DummyClass/invokeIfStmt(D)V
  iload 7
  iload 5
  if_icmpge Label2
  dload 7
  invokestatic app/DummyClass/invokeIfStmt(D)V
  dload 6
  invokestatic app/DummyClass/invokeIfStmt(D)V
  iload 7
  iload 6
  if_icmplt Label3
Label2:
  iload 5
  iload 6
  isub
  istore 6
  iload 6
  ireturn
Label0:
  ldc "\\."
  astore 8
  aload_0
  aload 8
  invokevirtual java/lang/String/split(Ljava/lang/String;)[Ljava/lang/String;
  astore_2
  goto Label4
Label1:
  ldc "\\."
  astore 8
  aload_1
  aload 8
  invokevirtual java/lang/String/split(Ljava/lang/String;)[Ljava/lang/String;
  astore 4
  goto Label5
Label3:
  aload_2
  iload 7
  aaload
  astore 9
  aload 9
  invokestatic com/wiyun/ad/x/d(Ljava/lang/String;)I
  istore 10
  aload 4
  iload 7
  aaload
  astore_1
  aload_1
  invokestatic com/wiyun/ad/x/d(Ljava/lang/String;)I
  istore 11
  iload 10
  iload 11
  isub
  istore 11
  dload 11
  invokestatic app/DummyClass/invokeIfStmt(D)V
  iload 11
  ifeq Label6
  iload 11
  ireturn
Label6:
  iload 7
  iconst_1
  iadd
  istore 7
  goto Label7
  nop
.end <method>

.method public static b()Ljava/lang/String;
.limit locals 4
.limit stack 200
  nop
  new java/lang/StringBuilder
  astore_0
  aload_0
  invokespecial java/lang/StringBuilder/<init>()V
  new java/lang/NoClassDefFoundError
  dup
  invokespecial java/lang/NoClassDefFoundError/<init>()V
  athrow
  nop
  aload_0
  aload_1
  invokevirtual java/lang/StringBuilder/append(Ljava/lang/Object;)Ljava/lang/StringBuilder;
  astore_0
  ldc "/.wiyun/wiad/"
  astore_2
  aload_0
  aload_2
  invokevirtual java/lang/StringBuilder/append(Ljava/lang/String;)Ljava/lang/StringBuilder;
  astore_0
  aload_0
  invokevirtual java/lang/StringBuilder/toString()Ljava/lang/String;
  astore_3
  aload_3
  areturn
  nop
.end <method>

.method public static b(Ljava/lang/String;)Ljava/lang/String;
.limit locals 7
.limit stack 200
  nop
  aload_0
  invokevirtual java/lang/String/length()I
  istore_1
  new java/lang/NoClassDefFoundError
  dup
  invokespecial java/lang/NoClassDefFoundError/<init>()V
  athrow
  iconst_1
  istore_2
  iload_1
  iload_2
  if_icmplt Label0
  ldc "/"
  astore_3
  aload_3
  aload_0
  invokevirtual java/lang/String/equals(Ljava/lang/Object;)Z
  istore 4
  iload 4
  invokestatic app/DummyClass/invokeIfStmt(Z)V
  iload 4
  ifeq Label1
Label0:
  ldc ""
  astore_0
Label3:
  aload_0
  areturn
Label1:
  ldc "/"
  astore 5
  aload_0
  aload 5
  invokevirtual java/lang/String/endsWith(Ljava/lang/String;)Z
  istore 4
  iload 4
  invokestatic app/DummyClass/invokeIfStmt(Z)V
  iload 4
  ifeq Label2
  aload_0
  invokevirtual java/lang/String/length()I
  istore_1
  iload_1
  iconst_m1
  iadd
  istore_1
  iconst_0
  istore_2
  aload_0
  iload_2
  iload_1
  invokevirtual java/lang/String/substring(II)Ljava/lang/String;
  astore_0
Label2:
  getstatic java/io/File/separatorChar C
  istore 6
  aload_0
  iload 6
  invokevirtual java/lang/String/lastIndexOf(I)I
  istore_1
  dload_1
  invokestatic app/DummyClass/invokeIfStmt(D)V
  iconst_m1
  istore_2
  iload_1
  iload_2
  if_icmpeq Label3
  iload_1
  iconst_1
  iadd
  istore_1
  aload_0
  iload_1
  invokevirtual java/lang/String/substring(I)Ljava/lang/String;
  astore_3
  aload_3
  areturn
  nop
.end <method>

.method public static b([B)Ljava/lang/String;
.limit locals 5
.limit stack 200
  nop
  new java/lang/NoClassDefFoundError
  dup
  invokespecial java/lang/NoClassDefFoundError/<init>()V
  athrow
  iload_0
  ifne Label0
  ldc ""
  astore_1
  aload_1
  areturn
Label0:
  aload_0
  arraylength
  istore_2
  iconst_0
  istore 4
  aload_0
  iload 4
  iload_2
  invokestatic com/wiyun/ad/x/b([BII)Ljava/lang/String;
  astore_3
  aload_3
  areturn
  nop
.end <method>

.method public static b([BII)Ljava/lang/String;
.limit locals 6
.limit stack 200
  nop
  new java/lang/NoClassDefFoundError
  dup
  invokespecial java/lang/NoClassDefFoundError/<init>()V
  athrow
  iload_0
  ifne Label0
  ldc ""
  astore_3
  aload_3
  areturn
Label0:
  new java/lang/String
  astore 4
Label2:
  ldc "UTF-8"
  astore_3
  aload 4
  aload_0
  iload_1
  iload_2
  aload_3
  invokespecial java/lang/String/<init>([BIILjava/lang/String;)V
Label3:
  aload 4
  areturn
Label1:
  astore 5
  ldc ""
  astore_3
  aload_3
  areturn
  nop
.end <method>

.method public static b(Ljava/io/File;)[B
.limit locals 14
.limit stack 200
  .catch  java/lang/Throwable <from> Label5 <to> Label6 <using> Label4
  .catch  java/lang/Throwable <from> Label6 <to> Label8 <using> Label7
  .catch  java/lang/Throwable <from> Label0 <to> Label11 <using> Label7
  nop
  iconst_0
  istore_1
  aconst_null
  astore_3
  aload_3
  astore 4
  aload 4
  checkcast [B
  astore 4
  aload 4
  astore_2
Label5:
  new java/io/FileInputStream
  astore 5
  aload 5
  aload_0
  invokespecial java/io/FileInputStream/<init>(Ljava/io/File;)V
Label6:
  sipush 1024
  istore 7
  iload 7
  newarray byte
  astore 6
  new java/io/ByteArrayOutputStream
  astore 8
  aload 8
  invokespecial java/io/ByteArrayOutputStream/<init>()V
  iconst_0
  istore 9
Label2:
  new java/lang/NoClassDefFoundError
  dup
  invokespecial java/lang/NoClassDefFoundError/<init>()V
  athrow
  iconst_m1
  istore 7
  iload 9
  iload 7
  if_icmpne Label0
  aload 8
  invokevirtual java/io/ByteArrayOutputStream/toByteArray()[B
  astore 6
  aload 6
  astore_2
  aload 8
  invokevirtual java/io/ByteArrayOutputStream/flush()V
  aload 8
  invokevirtual java/io/ByteArrayOutputStream/close()V
Label8:
  aload 5
  invokestatic app/DummyClass/invokeIfStmt(Ljava/lang/Object;)V
  iload 5
  ifeq Label1
Label10:
  aload 5
  invokevirtual java/io/InputStream/close()V
Label1:
  aload_2
  areturn
Label0:
  iconst_0
  istore 7
  aload 8
  aload 6
  iload 7
  iload 9
  invokevirtual java/io/ByteArrayOutputStream/write([BII)V
  aload 5
  aload 6
  invokevirtual java/io/InputStream/read([B)I
  istore 9
Label11:
  goto Label2
Label4:
  astore 10
Label3:
  new java/lang/NoClassDefFoundError
  dup
  invokespecial java/lang/NoClassDefFoundError/<init>()V
  athrow
  iload_1
  ifeq Label1
Label13:
  aload_1
  invokevirtual java/io/InputStream/close()V
Label14:
  aload_2
  areturn
Label12:
  astore 11
  aload_2
  areturn
Label9:
  astore 12
  aload 6
  areturn
Label7:
  astore 13
  aload 5
  astore_1
  goto Label3
  nop
.end <method>

.method public static c(Ljava/lang/String;)Ljava/lang/String;
.limit locals 3
.limit stack 200
  nop
  ldc "gbk"
  astore_2
  aload_0
  aload_2
  invokestatic com/wiyun/ad/x/a(Ljava/lang/String;Ljava/lang/String;)Ljava/lang/String;
  astore_1
  aload_1
  areturn
  nop
.end <method>

.method public static d(Ljava/lang/String;)I
.limit locals 3
.limit stack 200
  nop
  bipush 10
  istore_2
  iload_2
  aload_0
  invokestatic com/wiyun/ad/x/a(ILjava/lang/String;)I
  istore_1
  iload_1
  ireturn
  nop
.end <method>

.method public static final e(Ljava/lang/String;)Ljava/lang/String;
.limit locals 7
.limit stack 200
  nop
  getstatic java/io/File/separatorChar C
  istore_1
  aload_0
  iload_1
  invokevirtual java/lang/String/lastIndexOf(I)I
  istore_2
  new java/lang/NoClassDefFoundError
  dup
  invokespecial java/lang/NoClassDefFoundError/<init>()V
  athrow
  iconst_m1
  istore_3
  iload_2
  iload_3
  if_icmpne Label0
  iconst_0
  istore_2
Label0:
  aload_0
  iload_2
  invokevirtual java/lang/String/substring(I)Ljava/lang/String;
  astore 4
  bipush 46
  istore_3
  aload 4
  iload_3
  invokevirtual java/lang/String/lastIndexOf(I)I
  istore 5
  dload 5
  invokestatic app/DummyClass/invokeIfStmt(D)V
  iconst_m1
  istore_3
  iload 5
  iload_3
  if_icmpeq Label1
  dload 5
  invokestatic app/DummyClass/invokeIfStmt(D)V
  iload 5
  ifeq Label1
  iload_2
  iload 5
  iadd
  istore 5
  iload 5
  iconst_1
  iadd
  istore 5
  aload_0
  iload 5
  invokevirtual java/lang/String/substring(I)Ljava/lang/String;
  astore 4
  aload 4
  areturn
Label1:
  ldc ""
  astore 6
  aload 6
  areturn
  nop
.end <method>

.method public static f(Ljava/lang/String;)J
.limit locals 6
.limit stack 200
  nop
  new java/lang/NoClassDefFoundError
  dup
  invokespecial java/lang/NoClassDefFoundError/<init>()V
  athrow
  iload_0
  ifne Label0
  ldc2_w 0
  lstore_1
  lload_1
  lreturn
Label0:
  aload_0
  invokevirtual java/lang/String/trim()Ljava/lang/String;
  astore_0
  aload_0
  invokestatic java/lang/Long/parseLong(Ljava/lang/String;)J
  lstore_3
Label2:
  lload_3
  lreturn
Label1:
  astore 5
  ldc2_w 0
  lstore_1
  lload_1
  lreturn
  nop
.end <method>

