.source SourceFile
.class final  com/mobisage/android/S
.super com/mobisage/android/aa

.method <init>(Landroid/os/Handler;)V
.limit locals 3
.limit stack 200
  nop
  aload_0
  aload_1
  invokespecial com/mobisage/android/aa/<init>(Landroid/os/Handler;)V
  sipush 2005
  istore_2
  aload_0
  iload_2
  putfield com/mobisage/android/O/c I
  return
  nop
.end <method>

.method protected final f(Lcom/mobisage/android/b;)V
.limit locals 26
.limit stack 200
  nop
  new java/lang/StringBuilder
  astore 4
  aload 4
  invokespecial java/lang/StringBuilder/<init>()V
  ldc "http://trc.adsage.com/trc/sdk/x.gif?"
  astore 5
  aload 4
  aload 5
  invokevirtual java/lang/StringBuilder/append(Ljava/lang/String;)Ljava/lang/StringBuilder;
  pop
  ldc "ver=M2_03"
  astore 5
  aload 4
  aload 5
  invokevirtual java/lang/StringBuilder/append(Ljava/lang/String;)Ljava/lang/StringBuilder;
  pop
  new java/lang/StringBuilder
  astore 6
  ldc "&event="
  astore 5
  aload 6
  aload 5
  invokespecial java/lang/StringBuilder/<init>(Ljava/lang/String;)V
  aload_1
  astore_2
  aload_2
  getfield com/mobisage/android/b/c Landroid/os/Bundle;
  astore 7
  ldc "EventType"
  astore 5
  new java/lang/NoClassDefFoundError
  dup
  invokespecial java/lang/NoClassDefFoundError/<init>()V
  athrow
  nop
  aload 6
  aload 8
  invokevirtual java/lang/StringBuilder/append(Ljava/lang/String;)Ljava/lang/StringBuilder;
  astore 6
  aload 6
  invokevirtual java/lang/StringBuilder/toString()Ljava/lang/String;
  astore 8
  aload 4
  aload 8
  invokevirtual java/lang/StringBuilder/append(Ljava/lang/String;)Ljava/lang/StringBuilder;
  pop
  new java/lang/StringBuilder
  astore 6
  ldc "&token="
  astore 5
  aload 6
  aload 5
  invokespecial java/lang/StringBuilder/<init>(Ljava/lang/String;)V
  aload_1
  astore_2
  aload_2
  getfield com/mobisage/android/b/c Landroid/os/Bundle;
  astore 7
  ldc "Token"
  astore 5
  aload 7
  aload 5
  invokevirtual android/os/Bundle/getString(Ljava/lang/String;)Ljava/lang/String;
  astore 8
  aload 6
  aload 8
  invokevirtual java/lang/StringBuilder/append(Ljava/lang/String;)Ljava/lang/StringBuilder;
  astore 6
  aload 6
  invokevirtual java/lang/StringBuilder/toString()Ljava/lang/String;
  astore 8
  aload 4
  aload 8
  invokevirtual java/lang/StringBuilder/append(Ljava/lang/String;)Ljava/lang/StringBuilder;
  pop
  new java/lang/StringBuilder
  astore 6
  ldc "&adgroupid="
  astore 5
  aload 6
  aload 5
  invokespecial java/lang/StringBuilder/<init>(Ljava/lang/String;)V
  aload_1
  astore_2
  aload_2
  getfield com/mobisage/android/b/c Landroid/os/Bundle;
  astore 7
  ldc "AdGroupID"
  astore 5
  aload 7
  aload 5
  invokevirtual android/os/Bundle/getString(Ljava/lang/String;)Ljava/lang/String;
  astore 8
  aload 6
  aload 8
  invokevirtual java/lang/StringBuilder/append(Ljava/lang/String;)Ljava/lang/StringBuilder;
  astore 6
  aload 6
  invokevirtual java/lang/StringBuilder/toString()Ljava/lang/String;
  astore 8
  aload 4
  aload 8
  invokevirtual java/lang/StringBuilder/append(Ljava/lang/String;)Ljava/lang/StringBuilder;
  pop
  new java/lang/StringBuilder
  astore 6
  ldc "&adid="
  astore 5
  aload 6
  aload 5
  invokespecial java/lang/StringBuilder/<init>(Ljava/lang/String;)V
  aload_1
  astore_2
  aload_2
  getfield com/mobisage/android/b/c Landroid/os/Bundle;
  astore 7
  ldc "AdID"
  astore 5
  aload 7
  aload 5
  invokevirtual android/os/Bundle/getString(Ljava/lang/String;)Ljava/lang/String;
  astore 8
  aload 6
  aload 8
  invokevirtual java/lang/StringBuilder/append(Ljava/lang/String;)Ljava/lang/StringBuilder;
  astore 6
  aload 6
  invokevirtual java/lang/StringBuilder/toString()Ljava/lang/String;
  astore 8
  aload 4
  aload 8
  invokevirtual java/lang/StringBuilder/append(Ljava/lang/String;)Ljava/lang/StringBuilder;
  pop
  new java/lang/StringBuilder
  astore 6
  ldc "&pid="
  astore 5
  aload 6
  aload 5
  invokespecial java/lang/StringBuilder/<init>(Ljava/lang/String;)V
  aload_1
  astore_2
  aload_2
  getfield com/mobisage/android/b/c Landroid/os/Bundle;
  astore 7
  ldc "PublisherID"
  astore 5
  aload 7
  aload 5
  invokevirtual android/os/Bundle/getString(Ljava/lang/String;)Ljava/lang/String;
  astore 8
  aload 6
  aload 8
  invokevirtual java/lang/StringBuilder/append(Ljava/lang/String;)Ljava/lang/StringBuilder;
  astore 6
  aload 6
  invokevirtual java/lang/StringBuilder/toString()Ljava/lang/String;
  astore 8
  aload 4
  aload 8
  invokevirtual java/lang/StringBuilder/append(Ljava/lang/String;)Ljava/lang/StringBuilder;
  pop
  new android/text/format/Time
  astore 9
  aload 9
  invokespecial android/text/format/Time/<init>()V
  ldc "GMT +0000"
  astore 5
  aload 9
  aload 5
  invokevirtual android/text/format/Time/switchTimezone(Ljava/lang/String;)V
  aload 9
  invokevirtual android/text/format/Time/setToNow()V
  new java/lang/StringBuilder
  astore 6
  ldc "&time="
  astore 5
  aload 6
  aload 5
  invokespecial java/lang/StringBuilder/<init>(Ljava/lang/String;)V
  ldc "%Y%m%d%H%M%S"
  astore 5
  aload 9
  aload 5
  invokevirtual android/text/format/Time/format(Ljava/lang/String;)Ljava/lang/String;
  astore 8
  aload 6
  aload 8
  invokevirtual java/lang/StringBuilder/append(Ljava/lang/String;)Ljava/lang/StringBuilder;
  astore 6
  aload 6
  invokevirtual java/lang/StringBuilder/toString()Ljava/lang/String;
  astore 8
  aload 4
  aload 8
  invokevirtual java/lang/StringBuilder/append(Ljava/lang/String;)Ljava/lang/StringBuilder;
  pop
  new java/lang/StringBuilder
  astore 6
  ldc "&uid="
  astore 5
  aload 6
  aload 5
  invokespecial java/lang/StringBuilder/<init>(Ljava/lang/String;)V
  getstatic com/mobisage/android/y/a Ljava/lang/String;
  astore 8
  aload 6
  aload 8
  invokevirtual java/lang/StringBuilder/append(Ljava/lang/String;)Ljava/lang/StringBuilder;
  astore 6
  aload 6
  invokevirtual java/lang/StringBuilder/toString()Ljava/lang/String;
  astore 8
  aload 4
  aload 8
  invokevirtual java/lang/StringBuilder/append(Ljava/lang/String;)Ljava/lang/StringBuilder;
  pop
  aload_1
  astore_2
  aload_2
  getfield com/mobisage/android/b/c Landroid/os/Bundle;
  astore 7
  ldc "Tag"
  astore 5
  aload 7
  aload 5
  invokevirtual android/os/Bundle/containsKey(Ljava/lang/String;)Z
  istore 10
  iload 10
  invokestatic app/DummyClass/invokeIfStmt(Z)V
  iload 10
  ifeq Label0
  new java/lang/StringBuilder
  astore 6
  ldc "&tag="
  astore 5
  aload 6
  aload 5
  invokespecial java/lang/StringBuilder/<init>(Ljava/lang/String;)V
  aload_1
  astore_2
  aload_2
  getfield com/mobisage/android/b/c Landroid/os/Bundle;
  astore 7
  ldc "Tag"
  astore 5
  aload 7
  aload 5
  invokevirtual android/os/Bundle/getString(Ljava/lang/String;)Ljava/lang/String;
  astore 8
  aload 8
  invokestatic java/net/URLEncoder/encode(Ljava/lang/String;)Ljava/lang/String;
  astore 8
  aload 6
  aload 8
  invokevirtual java/lang/StringBuilder/append(Ljava/lang/String;)Ljava/lang/StringBuilder;
  astore 6
  aload 6
  invokevirtual java/lang/StringBuilder/toString()Ljava/lang/String;
  astore 8
  aload 4
  aload 8
  invokevirtual java/lang/StringBuilder/append(Ljava/lang/String;)Ljava/lang/StringBuilder;
  pop
Label2:
  ldc "&sv=2.3.0"
  astore 5
  aload 4
  aload 5
  invokevirtual java/lang/StringBuilder/append(Ljava/lang/String;)Ljava/lang/StringBuilder;
  pop
  aload_1
  astore_2
  aload_2
  getfield com/mobisage/android/b/c Landroid/os/Bundle;
  astore 7
  ldc "CustomData"
  astore 5
  aload 7
  aload 5
  invokevirtual android/os/Bundle/containsKey(Ljava/lang/String;)Z
  istore 10
  iload 10
  invokestatic app/DummyClass/invokeIfStmt(Z)V
  iload 10
  ifeq Label1
  new java/lang/StringBuilder
  astore 6
  ldc "&cdata="
  astore 5
  aload 6
  aload 5
  invokespecial java/lang/StringBuilder/<init>(Ljava/lang/String;)V
  aload_1
  astore_2
  aload_2
  getfield com/mobisage/android/b/c Landroid/os/Bundle;
  astore 7
  ldc "CustomData"
  astore 5
  aload 7
  aload 5
  invokevirtual android/os/Bundle/getString(Ljava/lang/String;)Ljava/lang/String;
  astore 8
  aload 8
  invokestatic java/net/URLEncoder/encode(Ljava/lang/String;)Ljava/lang/String;
  astore 8
  aload 6
  aload 8
  invokevirtual java/lang/StringBuilder/append(Ljava/lang/String;)Ljava/lang/StringBuilder;
  astore 6
  aload 6
  invokevirtual java/lang/StringBuilder/toString()Ljava/lang/String;
  astore 8
  aload 4
  aload 8
  invokevirtual java/lang/StringBuilder/append(Ljava/lang/String;)Ljava/lang/StringBuilder;
  pop
Label3:
  new java/lang/StringBuilder
  astore 6
  ldc "&udid="
  astore 5
  aload 6
  aload 5
  invokespecial java/lang/StringBuilder/<init>(Ljava/lang/String;)V
  getstatic com/mobisage/android/y/g Ljava/lang/String;
  astore 8
  aload 6
  aload 8
  invokevirtual java/lang/StringBuilder/append(Ljava/lang/String;)Ljava/lang/StringBuilder;
  astore 6
  aload 6
  invokevirtual java/lang/StringBuilder/toString()Ljava/lang/String;
  astore 8
  aload 4
  aload 8
  invokevirtual java/lang/StringBuilder/append(Ljava/lang/String;)Ljava/lang/StringBuilder;
  pop
  new java/lang/StringBuilder
  astore 6
  ldc "&loc="
  astore 5
  aload 6
  aload 5
  invokespecial java/lang/StringBuilder/<init>(Ljava/lang/String;)V
  invokestatic com/mobisage/android/D/a()Lcom/mobisage/android/D;
  astore 11
  aload 11
  invokevirtual com/mobisage/android/D/b()Ljava/lang/String;
  astore 8
  aload 8
  invokestatic java/net/URLEncoder/encode(Ljava/lang/String;)Ljava/lang/String;
  astore 8
  aload 6
  aload 8
  invokevirtual java/lang/StringBuilder/append(Ljava/lang/String;)Ljava/lang/StringBuilder;
  astore 6
  aload 6
  invokevirtual java/lang/StringBuilder/toString()Ljava/lang/String;
  astore 8
  aload 4
  aload 8
  invokevirtual java/lang/StringBuilder/append(Ljava/lang/String;)Ljava/lang/StringBuilder;
  pop
  new java/lang/StringBuilder
  astore 6
  ldc "&oid="
  astore 5
  aload 6
  aload 5
  invokespecial java/lang/StringBuilder/<init>(Ljava/lang/String;)V
  iconst_2
  istore 12
  iload 12
  invokestatic java/lang/String/valueOf(I)Ljava/lang/String;
  astore 8
  aload 6
  aload 8
  invokevirtual java/lang/StringBuilder/append(Ljava/lang/String;)Ljava/lang/StringBuilder;
  astore 6
  aload 6
  invokevirtual java/lang/StringBuilder/toString()Ljava/lang/String;
  astore 8
  aload 4
  aload 8
  invokevirtual java/lang/StringBuilder/append(Ljava/lang/String;)Ljava/lang/StringBuilder;
  pop
  new java/lang/StringBuilder
  astore 6
  ldc "&ich="
  astore 5
  aload 6
  aload 5
  invokespecial java/lang/StringBuilder/<init>(Ljava/lang/String;)V
  getstatic com/mobisage/android/r/b Ljava/lang/String;
  astore 8
  aload 8
  invokestatic java/net/URLEncoder/encode(Ljava/lang/String;)Ljava/lang/String;
  astore 8
  aload 6
  aload 8
  invokevirtual java/lang/StringBuilder/append(Ljava/lang/String;)Ljava/lang/StringBuilder;
  astore 6
  aload 6
  invokevirtual java/lang/StringBuilder/toString()Ljava/lang/String;
  astore 8
  aload 4
  aload 8
  invokevirtual java/lang/StringBuilder/append(Ljava/lang/String;)Ljava/lang/StringBuilder;
  pop
  new java/lang/StringBuilder
  astore 6
  aload 6
  invokespecial java/lang/StringBuilder/<init>()V
  getstatic com/mobisage/android/r/f Ljava/lang/String;
  astore 8
  aload 6
  aload 8
  invokevirtual java/lang/StringBuilder/append(Ljava/lang/String;)Ljava/lang/StringBuilder;
  astore 6
  ldc "/Track"
  astore 5
  aload 6
  aload 5
  invokevirtual java/lang/StringBuilder/append(Ljava/lang/String;)Ljava/lang/StringBuilder;
  astore 6
  ldc "/"
  astore 5
  aload 6
  aload 5
  invokevirtual java/lang/StringBuilder/append(Ljava/lang/String;)Ljava/lang/StringBuilder;
  astore 6
  iconst_1
  istore 12
  aload 9
  iload 12
  invokevirtual android/text/format/Time/toMillis(Z)J
  lstore 13
  ldc2_w 1000
  lstore 15
  lload 13
  lload 15
  ldiv
  lstore 13
  lload 13
  invokestatic java/lang/String/valueOf(J)Ljava/lang/String;
  astore 8
  aload 6
  aload 8
  invokevirtual java/lang/StringBuilder/append(Ljava/lang/String;)Ljava/lang/StringBuilder;
  astore 6
  ldc "_"
  astore 5
  aload 6
  aload 5
  invokevirtual java/lang/StringBuilder/append(Ljava/lang/String;)Ljava/lang/StringBuilder;
  astore 6
  invokestatic java/util/UUID/randomUUID()Ljava/util/UUID;
  astore 17
  aload 17
  invokevirtual java/util/UUID/toString()Ljava/lang/String;
  astore 8
  aload 6
  aload 8
  invokevirtual java/lang/StringBuilder/append(Ljava/lang/String;)Ljava/lang/StringBuilder;
  astore 6
  ldc ".dat"
  astore 5
  aload 6
  aload 5
  invokevirtual java/lang/StringBuilder/append(Ljava/lang/String;)Ljava/lang/StringBuilder;
  astore 6
  aload 6
  invokevirtual java/lang/StringBuilder/toString()Ljava/lang/String;
  astore 8
  new java/io/File
  astore 18
  aload 18
  astore_2
  aload_2
  aload 8
  invokespecial java/io/File/<init>(Ljava/lang/String;)V
  aload 18
  astore_2
  aload_2
  invokevirtual java/io/File/mkdirs()Z
  pop
  aload 4
  invokevirtual java/lang/StringBuilder/toString()Ljava/lang/String;
  astore 19
  aload 18
  astore_2
  aload 19
  astore_3
  aload_2
  aload_3
  invokestatic com/mobisage/android/SNSSSLSocketFactory$a/a(Ljava/io/File;Ljava/lang/String;)V
  aload_0
  astore_2
  aload_2
  getfield com/mobisage/android/O/e Ljava/util/concurrent/ConcurrentHashMap;
  astore_2
  aload_2
  astore 20
  aload_1
  astore_2
  aload_2
  getfield com/mobisage/android/b/b Ljava/util/UUID;
  astore 17
  aload 20
  astore_2
  aload_1
  astore_3
  aload_2
  aload 17
  aload_3
  invokevirtual java/util/concurrent/ConcurrentHashMap/put(Ljava/lang/Object;Ljava/lang/Object;)Ljava/lang/Object;
  pop
  new com/mobisage/android/X
  astore 21
  aload 21
  astore_2
  aload_2
  invokespecial com/mobisage/android/X/<init>()V
  aload 21
  astore_2
  aload_2
  aload 8
  putfield com/mobisage/android/X/a Ljava/lang/String;
  aload_0
  astore_2
  aload_2
  getfield com/mobisage/android/aa/g Lcom/mobisage/android/aa$a;
  astore_2
  aload_2
  astore 22
  aload 22
  astore_2
  aload 21
  astore_3
  aload_3
  aload_2
  putfield com/mobisage/android/MobiSageMessage/callback Lcom/mobisage/android/IMobiSageMessageCallback;
  aload_1
  astore_2
  aload_2
  getfield com/mobisage/android/b/f Ljava/util/concurrent/LinkedBlockingQueue;
  astore_2
  aload_2
  astore 23
  aload 23
  astore_2
  aload 21
  astore_3
  aload_2
  aload_3
  invokevirtual java/util/concurrent/LinkedBlockingQueue/add(Ljava/lang/Object;)Z
  pop
  aload_0
  astore_2
  aload_2
  getfield com/mobisage/android/O/f Ljava/util/concurrent/ConcurrentHashMap;
  astore_2
  aload_2
  astore 20
  aload 21
  astore_2
  aload_2
  getfield com/mobisage/android/MobiSageMessage/c Ljava/util/UUID;
  astore 17
  aload_1
  astore_2
  aload_2
  getfield com/mobisage/android/b/b Ljava/util/UUID;
  astore_2
  aload_2
  astore 24
  aload 20
  astore_2
  aload 24
  astore_3
  aload_2
  aload 17
  aload_3
  invokevirtual java/util/concurrent/ConcurrentHashMap/put(Ljava/lang/Object;Ljava/lang/Object;)Ljava/lang/Object;
  pop
  invokestatic com/mobisage/android/H/a()Lcom/mobisage/android/H;
  astore 25
  aload 25
  astore_2
  aload 21
  astore_3
  aload_2
  aload_3
  invokevirtual com/mobisage/android/H/a(Lcom/mobisage/android/MobiSageMessage;)V
  return
Label0:
  ldc "&tag="
  astore 5
  aload 4
  aload 5
  invokevirtual java/lang/StringBuilder/append(Ljava/lang/String;)Ljava/lang/StringBuilder;
  pop
  goto Label2
Label1:
  ldc "&cdata="
  astore 5
  aload 4
  aload 5
  invokevirtual java/lang/StringBuilder/append(Ljava/lang/String;)Ljava/lang/StringBuilder;
  pop
  goto Label3
  nop
.end <method>

