.source dalvik_source_VirusShare_32e70f448ebd75661a1cb12f9cd8e013.apk
.class public  com/kuguo/ad/p
.super java/lang/Object
.field protected "A" I
.field protected "B" I
.field protected "C" I
.field protected "D" I
.field protected "E" Ljava/lang/String;
.field protected "F" Ljava/lang/String;
.field protected "a" Ljava/lang/String;
.field protected "b" Ljava/lang/String;
.field protected "c" J
.field protected "d" Ljava/lang/String;
.field protected "e" B
.field protected "f" I
.field protected "g" Ljava/lang/String;
.field protected "h" I
.field protected "i" Ljava/lang/String;
.field protected "j" Ljava/lang/Integer;
.field protected "k" Ljava/lang/String;
.field protected "l" Ljava/lang/String;
.field protected "m" I
.field protected "n" Ljava/lang/String;
.field protected "o" Ljava/lang/String;
.field protected "p" Ljava/lang/String;
.field protected "q" I
.field protected "r" I
.field protected "s" Ljava/lang/String;
.field protected "t" I
.field protected "u" I
.field protected "v" Ljava/lang/String;
.field protected "w" I
.field protected "x" I
.field protected "y" I
.field protected "z" I

.method public <init>()V
.limit locals 7
.limit stack 200
  nop
  aload_0
  invokespecial java/lang/Object/<init>()V
  ldc ""
  astore_1
  aload_0
  aload_1
  putfield com/kuguo/ad/p/a Ljava/lang/String;
  ldc ""
  astore_1
  aload_0
  aload_1
  putfield com/kuguo/ad/p/b Ljava/lang/String;
  ldc2_w 4294967295
  lstore_2
  aload_0
  lload_2
  putfield com/kuguo/ad/p/c J
  ldc ""
  astore_1
  aload_0
  aload_1
  putfield com/kuguo/ad/p/d Ljava/lang/String;
  iconst_0
  istore 4
  aload_0
  iload 4
  putfield com/kuguo/ad/p/e B
  iconst_m1
  istore 4
  aload_0
  iload 4
  putfield com/kuguo/ad/p/f I
  ldc ""
  astore_1
  aload_0
  aload_1
  putfield com/kuguo/ad/p/g Ljava/lang/String;
  iconst_m1
  istore 4
  aload_0
  iload 4
  putfield com/kuguo/ad/p/h I
  ldc ""
  astore_1
  aload_0
  aload_1
  putfield com/kuguo/ad/p/i Ljava/lang/String;
  iconst_m1
  istore 4
  iload 4
  invokestatic java/lang/Integer/valueOf(I)Ljava/lang/Integer;
  astore 5
  aload_0
  aload 5
  putfield com/kuguo/ad/p/j Ljava/lang/Integer;
  ldc "\u63a8\u8350"
  astore_1
  aload_0
  aload_1
  putfield com/kuguo/ad/p/k Ljava/lang/String;
  ldc "\u5e94\u7528\u8f6f\u4ef6"
  astore_1
  aload_0
  aload_1
  putfield com/kuguo/ad/p/l Ljava/lang/String;
  ldc 1048576
  istore 4
  aload_0
  iload 4
  putfield com/kuguo/ad/p/m I
  ldc "1.0"
  astore_1
  aload_0
  aload_1
  putfield com/kuguo/ad/p/n Ljava/lang/String;
  ldc ""
  astore_1
  aload_0
  aload_1
  putfield com/kuguo/ad/p/o Ljava/lang/String;
  ldc ""
  astore_1
  aload_0
  aload_1
  putfield com/kuguo/ad/p/p Ljava/lang/String;
  iconst_1
  istore 4
  aload_0
  iload 4
  putfield com/kuguo/ad/p/q I
  iconst_0
  istore 4
  aload_0
  iload 4
  putfield com/kuguo/ad/p/r I
  ldc ""
  astore_1
  aload_0
  aload_1
  putfield com/kuguo/ad/p/s Ljava/lang/String;
  iconst_1
  istore 4
  aload_0
  iload 4
  putfield com/kuguo/ad/p/t I
  iconst_0
  istore 4
  aload_0
  iload 4
  putfield com/kuguo/ad/p/u I
  ldc ""
  astore_1
  aload_0
  aload_1
  putfield com/kuguo/ad/p/v Ljava/lang/String;
  iconst_1
  istore 4
  aload_0
  iload 4
  putfield com/kuguo/ad/p/w I
  iconst_1
  istore 4
  aload_0
  iload 4
  putfield com/kuguo/ad/p/x I
  iconst_0
  istore 4
  aload_0
  iload 4
  putfield com/kuguo/ad/p/y I
  iconst_0
  istore 4
  aload_0
  iload 4
  putfield com/kuguo/ad/p/z I
  bipush 60
  istore 4
  aload_0
  iload 4
  putfield com/kuguo/ad/p/A I
  iconst_1
  istore 4
  aload_0
  iload 4
  putfield com/kuguo/ad/p/B I
  iconst_1
  istore 4
  aload_0
  iload 4
  putfield com/kuguo/ad/p/C I
  iconst_m1
  istore 4
  aload_0
  iload 4
  putfield com/kuguo/ad/p/D I
  ldc ""
  astore_1
  aload_0
  aload_1
  putfield com/kuguo/ad/p/E Ljava/lang/String;
  aconst_null
  astore 6
  aload_0
  aload 6
  putfield com/kuguo/ad/p/F Ljava/lang/String;
  return
  nop
.end <method>

.method public a()Ljava/lang/String;
.limit locals 9
.limit stack 200
  nop
  new java/lang/StringBuffer
  astore_1
  aload_1
  invokespecial java/lang/StringBuffer/<init>()V
  aload_0
  getfield com/kuguo/ad/p/a Ljava/lang/String;
  astore_2
  aload_1
  aload_2
  invokevirtual java/lang/StringBuffer/append(Ljava/lang/String;)Ljava/lang/StringBuffer;
  pop
  ldc "|#*"
  astore_3
  aload_1
  aload_3
  invokevirtual java/lang/StringBuffer/append(Ljava/lang/String;)Ljava/lang/StringBuffer;
  pop
  aload_0
  getfield com/kuguo/ad/p/b Ljava/lang/String;
  astore_2
  aload_1
  aload_2
  invokevirtual java/lang/StringBuffer/append(Ljava/lang/String;)Ljava/lang/StringBuffer;
  pop
  ldc "|#*"
  astore_3
  aload_1
  aload_3
  invokevirtual java/lang/StringBuffer/append(Ljava/lang/String;)Ljava/lang/StringBuffer;
  pop
  aload_0
  getfield com/kuguo/ad/p/d Ljava/lang/String;
  astore_2
  aload_1
  aload_2
  invokevirtual java/lang/StringBuffer/append(Ljava/lang/String;)Ljava/lang/StringBuffer;
  pop
  ldc "|#*"
  astore_3
  aload_1
  aload_3
  invokevirtual java/lang/StringBuffer/append(Ljava/lang/String;)Ljava/lang/StringBuffer;
  pop
  aload_0
  getfield com/kuguo/ad/p/c J
  lstore 4
  aload_1
  lload 4
  invokevirtual java/lang/StringBuffer/append(J)Ljava/lang/StringBuffer;
  pop
  ldc "|#*"
  astore_3
  aload_1
  aload_3
  invokevirtual java/lang/StringBuffer/append(Ljava/lang/String;)Ljava/lang/StringBuffer;
  pop
  aload_0
  getfield com/kuguo/ad/p/e B
  istore 6
  aload_1
  iload 6
  invokevirtual java/lang/StringBuffer/append(I)Ljava/lang/StringBuffer;
  pop
  ldc "|#*"
  astore_3
  aload_1
  aload_3
  invokevirtual java/lang/StringBuffer/append(Ljava/lang/String;)Ljava/lang/StringBuffer;
  pop
  aload_0
  getfield com/kuguo/ad/p/g Ljava/lang/String;
  astore_2
  aload_1
  aload_2
  invokevirtual java/lang/StringBuffer/append(Ljava/lang/String;)Ljava/lang/StringBuffer;
  pop
  ldc "|#*"
  astore_3
  aload_1
  aload_3
  invokevirtual java/lang/StringBuffer/append(Ljava/lang/String;)Ljava/lang/StringBuffer;
  pop
  aload_0
  getfield com/kuguo/ad/p/h I
  istore 7
  aload_1
  iload 7
  invokevirtual java/lang/StringBuffer/append(I)Ljava/lang/StringBuffer;
  pop
  ldc "|#*"
  astore_3
  aload_1
  aload_3
  invokevirtual java/lang/StringBuffer/append(Ljava/lang/String;)Ljava/lang/StringBuffer;
  pop
  aload_0
  getfield com/kuguo/ad/p/i Ljava/lang/String;
  astore_2
  aload_1
  aload_2
  invokevirtual java/lang/StringBuffer/append(Ljava/lang/String;)Ljava/lang/StringBuffer;
  pop
  ldc "|#*"
  astore_3
  aload_1
  aload_3
  invokevirtual java/lang/StringBuffer/append(Ljava/lang/String;)Ljava/lang/StringBuffer;
  pop
  aload_0
  getfield com/kuguo/ad/p/j Ljava/lang/Integer;
  astore 8
  aload_1
  aload 8
  invokevirtual java/lang/StringBuffer/append(Ljava/lang/Object;)Ljava/lang/StringBuffer;
  pop
  ldc "|#*"
  astore_3
  aload_1
  aload_3
  invokevirtual java/lang/StringBuffer/append(Ljava/lang/String;)Ljava/lang/StringBuffer;
  pop
  aload_0
  getfield com/kuguo/ad/p/k Ljava/lang/String;
  astore_2
  aload_1
  aload_2
  invokevirtual java/lang/StringBuffer/append(Ljava/lang/String;)Ljava/lang/StringBuffer;
  pop
  ldc "|#*"
  astore_3
  aload_1
  aload_3
  invokevirtual java/lang/StringBuffer/append(Ljava/lang/String;)Ljava/lang/StringBuffer;
  pop
  aload_0
  getfield com/kuguo/ad/p/l Ljava/lang/String;
  astore_2
  aload_1
  aload_2
  invokevirtual java/lang/StringBuffer/append(Ljava/lang/String;)Ljava/lang/StringBuffer;
  pop
  ldc "|#*"
  astore_3
  aload_1
  aload_3
  invokevirtual java/lang/StringBuffer/append(Ljava/lang/String;)Ljava/lang/StringBuffer;
  pop
  aload_0
  getfield com/kuguo/ad/p/m I
  istore 7
  aload_1
  iload 7
  invokevirtual java/lang/StringBuffer/append(I)Ljava/lang/StringBuffer;
  pop
  ldc "|#*"
  astore_3
  aload_1
  aload_3
  invokevirtual java/lang/StringBuffer/append(Ljava/lang/String;)Ljava/lang/StringBuffer;
  pop
  aload_0
  getfield com/kuguo/ad/p/n Ljava/lang/String;
  astore_2
  aload_1
  aload_2
  invokevirtual java/lang/StringBuffer/append(Ljava/lang/String;)Ljava/lang/StringBuffer;
  pop
  ldc "|#*"
  astore_3
  aload_1
  aload_3
  invokevirtual java/lang/StringBuffer/append(Ljava/lang/String;)Ljava/lang/StringBuffer;
  pop
  aload_0
  getfield com/kuguo/ad/p/o Ljava/lang/String;
  astore_2
  aload_1
  aload_2
  invokevirtual java/lang/StringBuffer/append(Ljava/lang/String;)Ljava/lang/StringBuffer;
  pop
  ldc "|#*"
  astore_3
  aload_1
  aload_3
  invokevirtual java/lang/StringBuffer/append(Ljava/lang/String;)Ljava/lang/StringBuffer;
  pop
  aload_0
  getfield com/kuguo/ad/p/p Ljava/lang/String;
  astore_2
  aload_1
  aload_2
  invokevirtual java/lang/StringBuffer/append(Ljava/lang/String;)Ljava/lang/StringBuffer;
  pop
  ldc "|#*"
  astore_3
  aload_1
  aload_3
  invokevirtual java/lang/StringBuffer/append(Ljava/lang/String;)Ljava/lang/StringBuffer;
  pop
  aload_0
  getfield com/kuguo/ad/p/q I
  istore 7
  aload_1
  iload 7
  invokevirtual java/lang/StringBuffer/append(I)Ljava/lang/StringBuffer;
  pop
  ldc "|#*"
  astore_3
  aload_1
  aload_3
  invokevirtual java/lang/StringBuffer/append(Ljava/lang/String;)Ljava/lang/StringBuffer;
  pop
  aload_0
  getfield com/kuguo/ad/p/r I
  istore 7
  aload_1
  iload 7
  invokevirtual java/lang/StringBuffer/append(I)Ljava/lang/StringBuffer;
  pop
  ldc "|#*"
  astore_3
  aload_1
  aload_3
  invokevirtual java/lang/StringBuffer/append(Ljava/lang/String;)Ljava/lang/StringBuffer;
  pop
  aload_0
  getfield com/kuguo/ad/p/v Ljava/lang/String;
  astore_2
  aload_1
  aload_2
  invokevirtual java/lang/StringBuffer/append(Ljava/lang/String;)Ljava/lang/StringBuffer;
  pop
  ldc "|#*"
  astore_3
  aload_1
  aload_3
  invokevirtual java/lang/StringBuffer/append(Ljava/lang/String;)Ljava/lang/StringBuffer;
  pop
  aload_0
  getfield com/kuguo/ad/p/s Ljava/lang/String;
  astore_2
  aload_1
  aload_2
  invokevirtual java/lang/StringBuffer/append(Ljava/lang/String;)Ljava/lang/StringBuffer;
  pop
  ldc "|#*"
  astore_3
  aload_1
  aload_3
  invokevirtual java/lang/StringBuffer/append(Ljava/lang/String;)Ljava/lang/StringBuffer;
  pop
  aload_0
  getfield com/kuguo/ad/p/E Ljava/lang/String;
  astore_2
  aload_1
  aload_2
  invokevirtual java/lang/StringBuffer/append(Ljava/lang/String;)Ljava/lang/StringBuffer;
  pop
  ldc "|#*"
  astore_3
  aload_1
  aload_3
  invokevirtual java/lang/StringBuffer/append(Ljava/lang/String;)Ljava/lang/StringBuffer;
  pop
  aload_0
  getfield com/kuguo/ad/p/u I
  istore 7
  aload_1
  iload 7
  invokevirtual java/lang/StringBuffer/append(I)Ljava/lang/StringBuffer;
  pop
  ldc "|#*"
  astore_3
  aload_1
  aload_3
  invokevirtual java/lang/StringBuffer/append(Ljava/lang/String;)Ljava/lang/StringBuffer;
  pop
  aload_0
  getfield com/kuguo/ad/p/x I
  istore 7
  aload_1
  iload 7
  invokevirtual java/lang/StringBuffer/append(I)Ljava/lang/StringBuffer;
  pop
  ldc "|#*"
  astore_3
  aload_1
  aload_3
  invokevirtual java/lang/StringBuffer/append(Ljava/lang/String;)Ljava/lang/StringBuffer;
  pop
  aload_0
  getfield com/kuguo/ad/p/y I
  istore 7
  aload_1
  iload 7
  invokevirtual java/lang/StringBuffer/append(I)Ljava/lang/StringBuffer;
  pop
  ldc "|#*"
  astore_3
  aload_1
  aload_3
  invokevirtual java/lang/StringBuffer/append(Ljava/lang/String;)Ljava/lang/StringBuffer;
  pop
  aload_0
  getfield com/kuguo/ad/p/z I
  istore 7
  aload_1
  iload 7
  invokevirtual java/lang/StringBuffer/append(I)Ljava/lang/StringBuffer;
  pop
  ldc "|#*"
  astore_3
  aload_1
  aload_3
  invokevirtual java/lang/StringBuffer/append(Ljava/lang/String;)Ljava/lang/StringBuffer;
  pop
  aload_0
  getfield com/kuguo/ad/p/B I
  istore 7
  aload_1
  iload 7
  invokevirtual java/lang/StringBuffer/append(I)Ljava/lang/StringBuffer;
  pop
  ldc "|#*"
  astore_3
  aload_1
  aload_3
  invokevirtual java/lang/StringBuffer/append(Ljava/lang/String;)Ljava/lang/StringBuffer;
  pop
  aload_0
  getfield com/kuguo/ad/p/C I
  istore 7
  aload_1
  iload 7
  invokevirtual java/lang/StringBuffer/append(I)Ljava/lang/StringBuffer;
  pop
  ldc "|#*"
  astore_3
  aload_1
  aload_3
  invokevirtual java/lang/StringBuffer/append(Ljava/lang/String;)Ljava/lang/StringBuffer;
  pop
  aload_0
  getfield com/kuguo/ad/p/D I
  istore 7
  aload_1
  iload 7
  invokevirtual java/lang/StringBuffer/append(I)Ljava/lang/StringBuffer;
  pop
  aload_1
  invokevirtual java/lang/StringBuffer/toString()Ljava/lang/String;
  astore_2
  aload_2
  areturn
  nop
.end <method>

.method public a(Ljava/lang/String;)Z
.limit locals 14
.limit stack 200
  nop
  ldc "|#*"
  astore_3
  aload_1
  aload_3
  invokestatic com/kuguo/ad/d/a(Ljava/lang/String;Ljava/lang/String;)[Ljava/lang/String;
  astore_2
  new java/lang/NoClassDefFoundError
  dup
  invokespecial java/lang/NoClassDefFoundError/<init>()V
  athrow
  iload_2
  ifne Label0
  iconst_0
  istore 4
  iload 4
  ireturn
Label0:
  iconst_0
  istore 4
  aload_2
  iload 4
  aaload
  astore 5
  aload_0
  aload 5
  putfield com/kuguo/ad/p/a Ljava/lang/String;
  iconst_1
  istore 4
  aload_2
  iload 4
  aaload
  astore 5
  aload_0
  aload 5
  putfield com/kuguo/ad/p/b Ljava/lang/String;
  iconst_2
  istore 4
  aload_2
  iload 4
  aaload
  astore 5
  aload_0
  aload 5
  putfield com/kuguo/ad/p/d Ljava/lang/String;
  iconst_3
  istore 4
  aload_2
  iload 4
  aaload
  astore 5
  aload 5
  invokestatic java/lang/Long/valueOf(Ljava/lang/String;)Ljava/lang/Long;
  astore 6
  aload 6
  invokevirtual java/lang/Long/longValue()J
  lstore 7
  aload_0
  lload 7
  putfield com/kuguo/ad/p/c J
  iconst_4
  istore 4
  aload_2
  iload 4
  aaload
  astore 5
  aload 5
  invokestatic java/lang/Byte/valueOf(Ljava/lang/String;)Ljava/lang/Byte;
  astore 9
  aload 9
  invokevirtual java/lang/Byte/byteValue()B
  istore 10
  aload_0
  iload 10
  putfield com/kuguo/ad/p/e B
  iconst_5
  istore 4
  aload_2
  iload 4
  aaload
  astore 5
  aload_0
  aload 5
  putfield com/kuguo/ad/p/g Ljava/lang/String;
  bipush 6
  istore 4
  aload_2
  iload 4
  aaload
  astore 5
  aload 5
  invokestatic java/lang/Integer/valueOf(Ljava/lang/String;)Ljava/lang/Integer;
  astore 11
  aload 11
  invokevirtual java/lang/Integer/intValue()I
  istore 12
  aload_0
  iload 12
  putfield com/kuguo/ad/p/h I
  bipush 7
  istore 4
  aload_2
  iload 4
  aaload
  astore 5
  aload_0
  aload 5
  putfield com/kuguo/ad/p/i Ljava/lang/String;
  bipush 8
  istore 4
  aload_2
  iload 4
  aaload
  astore 5
  aload 5
  invokestatic java/lang/Integer/valueOf(Ljava/lang/String;)Ljava/lang/Integer;
  astore 11
  aload_0
  aload 11
  putfield com/kuguo/ad/p/j Ljava/lang/Integer;
  bipush 9
  istore 4
  aload_2
  iload 4
  aaload
  astore 5
  aload_0
  aload 5
  putfield com/kuguo/ad/p/k Ljava/lang/String;
  bipush 10
  istore 4
  aload_2
  iload 4
  aaload
  astore 5
  aload_0
  aload 5
  putfield com/kuguo/ad/p/l Ljava/lang/String;
  bipush 11
  istore 4
  aload_2
  iload 4
  aaload
  astore 5
  aload 5
  invokestatic java/lang/Integer/valueOf(Ljava/lang/String;)Ljava/lang/Integer;
  astore 11
  aload 11
  invokevirtual java/lang/Integer/intValue()I
  istore 12
  aload_0
  iload 12
  putfield com/kuguo/ad/p/m I
  bipush 12
  istore 4
  aload_2
  iload 4
  aaload
  astore 5
  aload_0
  aload 5
  putfield com/kuguo/ad/p/n Ljava/lang/String;
  bipush 13
  istore 4
  aload_2
  iload 4
  aaload
  astore 5
  aload_0
  aload 5
  putfield com/kuguo/ad/p/o Ljava/lang/String;
  bipush 14
  istore 4
  aload_2
  iload 4
  aaload
  astore 5
  aload_0
  aload 5
  putfield com/kuguo/ad/p/p Ljava/lang/String;
  bipush 15
  istore 4
  aload_2
  iload 4
  aaload
  astore 5
  aload 5
  invokestatic java/lang/Integer/valueOf(Ljava/lang/String;)Ljava/lang/Integer;
  astore 11
  aload 11
  invokevirtual java/lang/Integer/intValue()I
  istore 12
  aload_0
  iload 12
  putfield com/kuguo/ad/p/q I
  bipush 16
  istore 4
  aload_2
  iload 4
  aaload
  astore 5
  aload 5
  invokestatic java/lang/Integer/valueOf(Ljava/lang/String;)Ljava/lang/Integer;
  astore 11
  aload 11
  invokevirtual java/lang/Integer/intValue()I
  istore 12
  aload_0
  iload 12
  putfield com/kuguo/ad/p/r I
  bipush 17
  istore 4
  aload_2
  iload 4
  aaload
  astore 5
  aload_0
  aload 5
  putfield com/kuguo/ad/p/v Ljava/lang/String;
  bipush 18
  istore 4
  aload_2
  iload 4
  aaload
  astore 5
  aload_0
  aload 5
  putfield com/kuguo/ad/p/s Ljava/lang/String;
  bipush 19
  istore 4
  aload_2
  iload 4
  aaload
  astore 5
  aload_0
  aload 5
  putfield com/kuguo/ad/p/E Ljava/lang/String;
  bipush 20
  istore 4
  aload_2
  iload 4
  aaload
  astore 5
  aload 5
  invokestatic java/lang/Integer/valueOf(Ljava/lang/String;)Ljava/lang/Integer;
  astore 11
  aload 11
  invokevirtual java/lang/Integer/intValue()I
  istore 12
  aload_0
  iload 12
  putfield com/kuguo/ad/p/u I
  bipush 21
  istore 4
  aload_2
  iload 4
  aaload
  astore 5
  aload 5
  invokestatic java/lang/Integer/valueOf(Ljava/lang/String;)Ljava/lang/Integer;
  astore 11
  aload 11
  invokevirtual java/lang/Integer/intValue()I
  istore 12
  aload_0
  iload 12
  putfield com/kuguo/ad/p/x I
  bipush 22
  istore 4
  aload_2
  iload 4
  aaload
  astore 5
  aload 5
  invokestatic java/lang/Integer/valueOf(Ljava/lang/String;)Ljava/lang/Integer;
  astore 11
  aload 11
  invokevirtual java/lang/Integer/intValue()I
  istore 12
  aload_0
  iload 12
  putfield com/kuguo/ad/p/y I
  bipush 23
  istore 4
  aload_2
  iload 4
  aaload
  astore 5
  aload 5
  invokestatic java/lang/Integer/valueOf(Ljava/lang/String;)Ljava/lang/Integer;
  astore 11
  aload 11
  invokevirtual java/lang/Integer/intValue()I
  istore 12
  aload_0
  iload 12
  putfield com/kuguo/ad/p/z I
  bipush 24
  istore 4
  aload_2
  iload 4
  aaload
  astore 5
  aload 5
  invokestatic java/lang/Integer/valueOf(Ljava/lang/String;)Ljava/lang/Integer;
  astore 11
  aload 11
  invokevirtual java/lang/Integer/intValue()I
  istore 12
  aload_0
  iload 12
  putfield com/kuguo/ad/p/B I
  bipush 25
  istore 4
  aload_2
  iload 4
  aaload
  astore 5
  aload 5
  invokestatic java/lang/Integer/valueOf(Ljava/lang/String;)Ljava/lang/Integer;
  astore 11
  aload 11
  invokevirtual java/lang/Integer/intValue()I
  istore 12
  aload_0
  iload 12
  putfield com/kuguo/ad/p/C I
  bipush 26
  istore 4
  aload_2
  iload 4
  aaload
  astore 5
  aload 5
  invokestatic java/lang/Integer/valueOf(Ljava/lang/String;)Ljava/lang/Integer;
  astore 11
  aload 11
  invokevirtual java/lang/Integer/intValue()I
  istore 12
  aload_0
  iload 12
  putfield com/kuguo/ad/p/D I
Label2:
  iconst_1
  istore 4
  iload 4
  ireturn
Label1:
  astore 13
  iconst_0
  istore 4
  iload 4
  ireturn
  nop
.end <method>

.method protected static a([B)[Lcom/kuguo/ad/p;
.limit locals 23
.limit stack 200
  nop
  iconst_0
  istore 4
  aload_0
  iload 4
  baload
  istore_3
  new java/lang/NoClassDefFoundError
  dup
  invokespecial java/lang/NoClassDefFoundError/<init>()V
  athrow
  iload_3
  ifge Label0
  new java/lang/StringBuilder
  astore 5
  aload 5
  invokespecial java/lang/StringBuilder/<init>()V
  ldc "the first byte  -- "
  astore 6
  aload 5
  aload 6
  invokevirtual java/lang/StringBuilder/append(Ljava/lang/String;)Ljava/lang/StringBuilder;
  astore 5
  aload 5
  iload_3
  invokevirtual java/lang/StringBuilder/append(I)Ljava/lang/StringBuilder;
  astore 5
  aload 5
  invokevirtual java/lang/StringBuilder/toString()Ljava/lang/String;
  astore 7
  ldc "android__log"
  astore 6
  aload 6
  aload 7
  invokestatic android/util/Log/d(Ljava/lang/String;Ljava/lang/String;)I
  pop
  aconst_null
  astore 8
  aload 8
  areturn
Label0:
  iconst_2
  istore 4
  iload 4
  newarray byte
  astore 9
  iconst_3
  istore 4
  iconst_0
  istore 10
  iconst_2
  istore 11
  aload_0
  astore_1
  aload_1
  iload 4
  aload 9
  iload 10
  iload 11
  invokestatic java/lang/System/arraycopy(Ljava/lang/Object;ILjava/lang/Object;II)V
  aload 9
  invokestatic com/kuguo/ad/e/c([B)I
  istore 12
  iconst_5
  istore 13
  iload 12
  anewarray com/kuguo/ad/p
  astore 14
  iconst_0
  dstore 15
Label36:
  dload 15
  invokestatic app/DummyClass/invokeIfStmt(D)V
  dload 12
  invokestatic app/DummyClass/invokeIfStmt(D)V
  iload 15
  iload 12
  if_icmpge Label1
  new com/kuguo/ad/p
  astore 16
  aload 16
  invokespecial com/kuguo/ad/p/<init>()V
Label35:
  iload 13
  iconst_1
  iadd
  istore 17
  aload_0
  iload 13
  baload
  istore 18
  iload 18
  istore_1
  dload_1
  invokestatic app/DummyClass/invokeIfStmt(D)V
  iconst_m1
  istore 4
  iload 18
  istore_1
  iload_1
  iload 4
  if_icmpeq Label2
  iload 18
  istore_1
  dload_1
  invokestatic app/DummyClass/invokeIfStmt(D)V
  iload 18
  lookupswitch
  2 : Label4
  3 : Label5
  4 : Label6
  5 : Label7
  6 : Label8
  7 : Label9
  8 : Label10
  9 : Label11
  10 : Label12
  11 : Label13
  12 : Label14
  13 : Label15
  14 : Label16
  15 : Label17
  16 : Label18
  17 : Label19
  18 : Label20
  19 : Label21
  20 : Label22
  21 : Label23
  22 : Label24
  23 : Label25
  24 : Label26
  25 : Label27
  26 : Label28
  27 : Label29
  28 : Label30
  29 : Label31
  30 : Label32
  31 : Label33
  default : Label3
Label3:
  goto Label34
Label34:
  iconst_2
  istore 4
  iload 4
  newarray byte
  astore 9
  iconst_0
  istore 4
  iconst_2
  istore 10
  aload_0
  astore_1
  iload 17
  istore_2
  aload_1
  iload_2
  aload 9
  iload 4
  iload 10
  invokestatic java/lang/System/arraycopy(Ljava/lang/Object;ILjava/lang/Object;II)V
  aload 9
  invokestatic com/kuguo/ad/e/c([B)I
  istore 13
  iload 17
  iconst_2
  iadd
  istore 17
  iload 17
  istore_1
  iload 13
  iload_1
  iadd
  istore 13
  goto Label35
Label4:
  iconst_2
  istore 4
  iload 4
  newarray byte
  astore 9
  iconst_0
  istore 4
  iconst_2
  istore 10
  aload_0
  astore_1
  iload 17
  istore_2
  aload_1
  iload_2
  aload 9
  iload 4
  iload 10
  invokestatic java/lang/System/arraycopy(Ljava/lang/Object;ILjava/lang/Object;II)V
  aload 9
  invokestatic com/kuguo/ad/e/c([B)I
  istore 13
  iload 17
  iconst_2
  iadd
  istore 17
  iload 13
  newarray byte
  astore 9
  iconst_0
  istore 4
  aload_0
  astore_1
  iload 17
  istore_2
  aload_1
  iload_2
  aload 9
  iload 4
  iload 13
  invokestatic java/lang/System/arraycopy(Ljava/lang/Object;ILjava/lang/Object;II)V
  new java/lang/String
  astore 19
  ldc "UTF-8"
  astore 6
  aload 19
  astore_1
  aload_1
  aload 9
  aload 6
  invokespecial java/lang/String/<init>([BLjava/lang/String;)V
  aload 19
  astore_1
  aload 16
  aload_1
  putfield com/kuguo/ad/p/a Ljava/lang/String;
  iload 17
  istore_1
  iload 13
  iload_1
  iadd
  istore 13
  goto Label35
Label5:
  iconst_2
  istore 4
  iload 4
  newarray byte
  astore 9
  iconst_0
  istore 4
  iconst_2
  istore 10
  aload_0
  astore_1
  iload 17
  istore_2
  aload_1
  iload_2
  aload 9
  iload 4
  iload 10
  invokestatic java/lang/System/arraycopy(Ljava/lang/Object;ILjava/lang/Object;II)V
  aload 9
  invokestatic com/kuguo/ad/e/c([B)I
  istore 13
  iload 17
  iconst_2
  iadd
  istore 17
  iload 13
  newarray byte
  astore 9
  iconst_0
  istore 4
  aload_0
  astore_1
  iload 17
  istore_2
  aload_1
  iload_2
  aload 9
  iload 4
  iload 13
  invokestatic java/lang/System/arraycopy(Ljava/lang/Object;ILjava/lang/Object;II)V
  new java/lang/String
  astore 7
  ldc "UTF-8"
  astore 6
  aload 7
  aload 9
  aload 6
  invokespecial java/lang/String/<init>([BLjava/lang/String;)V
  aload 16
  aload 7
  putfield com/kuguo/ad/p/b Ljava/lang/String;
  iload 17
  istore_1
  iload 13
  iload_1
  iadd
  istore 13
  goto Label35
Label6:
  iconst_2
  istore 4
  iload 4
  newarray byte
  astore 9
  iconst_0
  istore 4
  iconst_2
  istore 10
  aload_0
  astore_1
  iload 17
  istore_2
  aload_1
  iload_2
  aload 9
  iload 4
  iload 10
  invokestatic java/lang/System/arraycopy(Ljava/lang/Object;ILjava/lang/Object;II)V
  aload 9
  invokestatic com/kuguo/ad/e/c([B)I
  istore 13
  iload 17
  iconst_2
  iadd
  istore 17
  iload 13
  newarray byte
  astore 9
  iconst_0
  istore 4
  aload_0
  astore_1
  iload 17
  istore_2
  aload_1
  iload_2
  aload 9
  iload 4
  iload 13
  invokestatic java/lang/System/arraycopy(Ljava/lang/Object;ILjava/lang/Object;II)V
  aload 9
  invokestatic com/kuguo/ad/e/a([B)J
  lstore 20
  lload 20
  lstore_1
  aload 16
  lload_1
  putfield com/kuguo/ad/p/c J
  iload 17
  istore_1
  iload 13
  iload_1
  iadd
  istore 13
  goto Label35
Label8:
  iload 17
  iconst_2
  iadd
  istore 17
  iload 17
  iconst_1
  iadd
  istore 13
  aload_0
  iload 17
  baload
  istore 18
  iload 18
  istore_1
  aload 16
  iload_1
  putfield com/kuguo/ad/p/e B
  goto Label35
Label7:
  iconst_2
  istore 4
  iload 4
  newarray byte
  astore 9
  iconst_0
  istore 4
  iconst_2
  istore 10
  aload_0
  astore_1
  iload 17
  istore_2
  aload_1
  iload_2
  aload 9
  iload 4
  iload 10
  invokestatic java/lang/System/arraycopy(Ljava/lang/Object;ILjava/lang/Object;II)V
  aload 9
  invokestatic com/kuguo/ad/e/c([B)I
  istore 13
  iload 17
  iconst_2
  iadd
  istore 17
  iload 13
  newarray byte
  astore 9
  iconst_0
  istore 4
  aload_0
  astore_1
  iload 17
  istore_2
  aload_1
  iload_2
  aload 9
  iload 4
  iload 13
  invokestatic java/lang/System/arraycopy(Ljava/lang/Object;ILjava/lang/Object;II)V
  new java/lang/String
  astore 7
  aload 7
  aload 9
  invokespecial java/lang/String/<init>([B)V
  aload 16
  aload 7
  putfield com/kuguo/ad/p/d Ljava/lang/String;
  iload 17
  istore_1
  iload 13
  iload_1
  iadd
  istore 13
  goto Label35
Label9:
  iconst_2
  istore 4
  iload 4
  newarray byte
  astore 9
  iconst_0
  istore 4
  iconst_2
  istore 10
  aload_0
  astore_1
  iload 17
  istore_2
  aload_1
  iload_2
  aload 9
  iload 4
  iload 10
  invokestatic java/lang/System/arraycopy(Ljava/lang/Object;ILjava/lang/Object;II)V
  aload 9
  invokestatic com/kuguo/ad/e/c([B)I
  istore 13
  iload 17
  iconst_2
  iadd
  istore 17
  iload 13
  newarray byte
  astore 9
  iconst_0
  istore 4
  aload_0
  astore_1
  iload 17
  istore_2
  aload_1
  iload_2
  aload 9
  iload 4
  iload 13
  invokestatic java/lang/System/arraycopy(Ljava/lang/Object;ILjava/lang/Object;II)V
  new java/lang/String
  astore 7
  ldc "UTF-8"
  astore 6
  aload 7
  aload 9
  aload 6
  invokespecial java/lang/String/<init>([BLjava/lang/String;)V
  aload 16
  aload 7
  putfield com/kuguo/ad/p/g Ljava/lang/String;
  iload 17
  istore_1
  iload 13
  iload_1
  iadd
  istore 13
  goto Label35
Label10:
  iconst_2
  istore 4
  iload 4
  newarray byte
  astore 9
  iconst_0
  istore 4
  iconst_2
  istore 10
  aload_0
  astore_1
  iload 17
  istore_2
  aload_1
  iload_2
  aload 9
  iload 4
  iload 10
  invokestatic java/lang/System/arraycopy(Ljava/lang/Object;ILjava/lang/Object;II)V
  aload 9
  invokestatic com/kuguo/ad/e/c([B)I
  istore 13
  iload 17
  iconst_2
  iadd
  istore 17
  iload 13
  newarray byte
  astore 9
  iconst_0
  istore 4
  aload_0
  astore_1
  iload 17
  istore_2
  aload_1
  iload_2
  aload 9
  iload 4
  iload 13
  invokestatic java/lang/System/arraycopy(Ljava/lang/Object;ILjava/lang/Object;II)V
  aload 9
  invokestatic com/kuguo/ad/e/b([B)I
  istore 22
  iload 22
  istore_1
  aload 16
  iload_1
  putfield com/kuguo/ad/p/h I
  iload 17
  istore_1
  iload 13
  iload_1
  iadd
  istore 13
  goto Label35
Label11:
  iconst_2
  istore 4
  iload 4
  newarray byte
  astore 9
  iconst_0
  istore 4
  iconst_2
  istore 10
  aload_0
  astore_1
  iload 17
  istore_2
  aload_1
  iload_2
  aload 9
  iload 4
  iload 10
  invokestatic java/lang/System/arraycopy(Ljava/lang/Object;ILjava/lang/Object;II)V
  aload 9
  invokestatic com/kuguo/ad/e/c([B)I
  istore 22
  iload 17
  iconst_2
  iadd
  istore 13
  iload 22
  istore_1
  iload_1
  newarray byte
  astore 9
  iconst_0
  istore 4
  aload_0
  astore_1
  iload 22
  istore_2
  aload_1
  iload 13
  aload 9
  iload 4
  iload_2
  invokestatic java/lang/System/arraycopy(Ljava/lang/Object;ILjava/lang/Object;II)V
  new java/lang/String
  astore 7
  ldc "UTF-8"
  astore 6
  aload 7
  aload 9
  aload 6
  invokespecial java/lang/String/<init>([BLjava/lang/String;)V
  aload 16
  aload 7
  putfield com/kuguo/ad/p/i Ljava/lang/String;
  iload 22
  iload 13
  iadd
  istore 13
  goto Label35
Label12:
  iconst_2
  istore 4
  iload 4
  newarray byte
  astore 9
  iconst_0
  istore 4
  iconst_2
  istore 10
  aload_0
  astore_1
  iload 17
  istore_2
  aload_1
  iload_2
  aload 9
  iload 4
  iload 10
  invokestatic java/lang/System/arraycopy(Ljava/lang/Object;ILjava/lang/Object;II)V
  aload 9
  invokestatic com/kuguo/ad/e/c([B)I
  istore 22
  iload 17
  iconst_2
  iadd
  istore 13
  iload 22
  istore_1
  iload_1
  newarray byte
  astore 9
  iconst_0
  istore 4
  aload_0
  astore_1
  iload 22
  istore_2
  aload_1
  iload 13
  aload 9
  iload 4
  iload_2
  invokestatic java/lang/System/arraycopy(Ljava/lang/Object;ILjava/lang/Object;II)V
  new java/lang/String
  astore 7
  ldc "UTF-8"
  astore 6
  aload 7
  aload 9
  aload 6
  invokespecial java/lang/String/<init>([BLjava/lang/String;)V
  aload 16
  aload 7
  putfield com/kuguo/ad/p/k Ljava/lang/String;
  iload 22
  iload 13
  iadd
  istore 13
  goto Label35
Label13:
  iconst_2
  istore 4
  iload 4
  newarray byte
  astore 9
  iconst_0
  istore 4
  iconst_2
  istore 10
  aload_0
  astore_1
  iload 17
  istore_2
  aload_1
  iload_2
  aload 9
  iload 4
  iload 10
  invokestatic java/lang/System/arraycopy(Ljava/lang/Object;ILjava/lang/Object;II)V
  aload 9
  invokestatic com/kuguo/ad/e/c([B)I
  istore 22
  iload 17
  iconst_2
  iadd
  istore 13
  iload 22
  istore_1
  iload_1
  newarray byte
  astore 9
  iconst_0
  istore 4
  aload_0
  astore_1
  iload 22
  istore_2
  aload_1
  iload 13
  aload 9
  iload 4
  iload_2
  invokestatic java/lang/System/arraycopy(Ljava/lang/Object;ILjava/lang/Object;II)V
  new java/lang/String
  astore 7
  ldc "UTF-8"
  astore 6
  aload 7
  aload 9
  aload 6
  invokespecial java/lang/String/<init>([BLjava/lang/String;)V
  aload 16
  aload 7
  putfield com/kuguo/ad/p/l Ljava/lang/String;
  iload 22
  iload 13
  iadd
  istore 13
  goto Label35
Label14:
  iconst_2
  istore 4
  iload 4
  newarray byte
  astore 9
  iconst_0
  istore 4
  iconst_2
  istore 10
  aload_0
  astore_1
  iload 17
  istore_2
  aload_1
  iload_2
  aload 9
  iload 4
  iload 10
  invokestatic java/lang/System/arraycopy(Ljava/lang/Object;ILjava/lang/Object;II)V
  aload 9
  invokestatic com/kuguo/ad/e/c([B)I
  istore 22
  iload 17
  iconst_2
  iadd
  istore 13
  iload 22
  istore_1
  iload_1
  newarray byte
  astore 9
  iconst_0
  istore 4
  aload_0
  astore_1
  iload 22
  istore_2
  aload_1
  iload 13
  aload 9
  iload 4
  iload_2
  invokestatic java/lang/System/arraycopy(Ljava/lang/Object;ILjava/lang/Object;II)V
  aload 9
  invokestatic com/kuguo/ad/e/b([B)I
  istore 17
  iload 17
  istore_1
  aload 16
  iload_1
  putfield com/kuguo/ad/p/m I
  iload 22
  iload 13
  iadd
  istore 13
  goto Label35
Label15:
  iconst_2
  istore 4
  iload 4
  newarray byte
  astore 9
  iconst_0
  istore 4
  iconst_2
  istore 10
  aload_0
  astore_1
  iload 17
  istore_2
  aload_1
  iload_2
  aload 9
  iload 4
  iload 10
  invokestatic java/lang/System/arraycopy(Ljava/lang/Object;ILjava/lang/Object;II)V
  aload 9
  invokestatic com/kuguo/ad/e/c([B)I
  istore 22
  iload 17
  iconst_2
  iadd
  istore 13
  iload 22
  istore_1
  iload_1
  newarray byte
  astore 9
  iconst_0
  istore 4
  aload_0
  astore_1
  iload 22
  istore_2
  aload_1
  iload 13
  aload 9
  iload 4
  iload_2
  invokestatic java/lang/System/arraycopy(Ljava/lang/Object;ILjava/lang/Object;II)V
  new java/lang/String
  astore 7
  ldc "UTF-8"
  astore 6
  aload 7
  aload 9
  aload 6
  invokespecial java/lang/String/<init>([BLjava/lang/String;)V
  aload 16
  aload 7
  putfield com/kuguo/ad/p/n Ljava/lang/String;
  iload 22
  iload 13
  iadd
  istore 13
  goto Label35
Label16:
  iconst_2
  istore 4
  iload 4
  newarray byte
  astore 9
  iconst_0
  istore 4
  iconst_2
  istore 10
  aload_0
  astore_1
  iload 17
  istore_2
  aload_1
  iload_2
  aload 9
  iload 4
  iload 10
  invokestatic java/lang/System/arraycopy(Ljava/lang/Object;ILjava/lang/Object;II)V
  aload 9
  invokestatic com/kuguo/ad/e/c([B)I
  istore 22
  iload 17
  iconst_2
  iadd
  istore 13
  iload 22
  istore_1
  iload_1
  newarray byte
  astore 9
  iconst_0
  istore 4
  aload_0
  astore_1
  iload 22
  istore_2
  aload_1
  iload 13
  aload 9
  iload 4
  iload_2
  invokestatic java/lang/System/arraycopy(Ljava/lang/Object;ILjava/lang/Object;II)V
  new java/lang/String
  astore 7
  ldc "UTF-8"
  astore 6
  aload 7
  aload 9
  aload 6
  invokespecial java/lang/String/<init>([BLjava/lang/String;)V
  aload 16
  aload 7
  putfield com/kuguo/ad/p/o Ljava/lang/String;
  iload 22
  iload 13
  iadd
  istore 13
  goto Label35
Label20:
  iconst_2
  istore 4
  iload 4
  newarray byte
  astore 9
  iconst_0
  istore 4
  iconst_2
  istore 10
  aload_0
  astore_1
  iload 17
  istore_2
  aload_1
  iload_2
  aload 9
  iload 4
  iload 10
  invokestatic java/lang/System/arraycopy(Ljava/lang/Object;ILjava/lang/Object;II)V
  aload 9
  invokestatic com/kuguo/ad/e/c([B)I
  istore 22
  iload 17
  iconst_2
  iadd
  istore 13
  iload 22
  istore_1
  iload_1
  newarray byte
  astore 9
  iconst_0
  istore 4
  aload_0
  astore_1
  iload 22
  istore_2
  aload_1
  iload 13
  aload 9
  iload 4
  iload_2
  invokestatic java/lang/System/arraycopy(Ljava/lang/Object;ILjava/lang/Object;II)V
  new java/lang/String
  astore 7
  ldc "UTF-8"
  astore 6
  aload 7
  aload 9
  aload 6
  invokespecial java/lang/String/<init>([BLjava/lang/String;)V
  aload 16
  aload 7
  putfield com/kuguo/ad/p/s Ljava/lang/String;
  iload 22
  iload 13
  iadd
  istore 13
  goto Label35
Label18:
  iconst_2
  istore 4
  iload 4
  newarray byte
  astore 9
  iconst_0
  istore 4
  iconst_2
  istore 10
  aload_0
  astore_1
  iload 17
  istore_2
  aload_1
  iload_2
  aload 9
  iload 4
  iload 10
  invokestatic java/lang/System/arraycopy(Ljava/lang/Object;ILjava/lang/Object;II)V
  aload 9
  invokestatic com/kuguo/ad/e/c([B)I
  istore 22
  iload 17
  iconst_2
  iadd
  istore 13
  iload 22
  istore_1
  iload_1
  newarray byte
  astore 9
  iconst_0
  istore 4
  aload_0
  astore_1
  iload 22
  istore_2
  aload_1
  iload 13
  aload 9
  iload 4
  iload_2
  invokestatic java/lang/System/arraycopy(Ljava/lang/Object;ILjava/lang/Object;II)V
  aload 9
  invokestatic com/kuguo/ad/e/b([B)I
  istore 17
  iload 17
  istore_1
  aload 16
  iload_1
  putfield com/kuguo/ad/p/q I
  iload 22
  iload 13
  iadd
  istore 13
  goto Label35
Label19:
  iconst_2
  istore 4
  iload 4
  newarray byte
  astore 9
  iconst_0
  istore 4
  iconst_2
  istore 10
  aload_0
  astore_1
  iload 17
  istore_2
  aload_1
  iload_2
  aload 9
  iload 4
  iload 10
  invokestatic java/lang/System/arraycopy(Ljava/lang/Object;ILjava/lang/Object;II)V
  aload 9
  invokestatic com/kuguo/ad/e/c([B)I
  istore 22
  iload 17
  iconst_2
  iadd
  istore 13
  iload 22
  istore_1
  iload_1
  newarray byte
  astore 9
  iconst_0
  istore 4
  aload_0
  astore_1
  iload 22
  istore_2
  aload_1
  iload 13
  aload 9
  iload 4
  iload_2
  invokestatic java/lang/System/arraycopy(Ljava/lang/Object;ILjava/lang/Object;II)V
  aload 9
  invokestatic com/kuguo/ad/e/b([B)I
  istore 17
  iload 17
  istore_1
  aload 16
  iload_1
  putfield com/kuguo/ad/p/r I
  iload 22
  iload 13
  iadd
  istore 13
  goto Label35
Label17:
  iconst_2
  istore 4
  iload 4
  newarray byte
  astore 9
  iconst_0
  istore 4
  iconst_2
  istore 10
  aload_0
  astore_1
  iload 17
  istore_2
  aload_1
  iload_2
  aload 9
  iload 4
  iload 10
  invokestatic java/lang/System/arraycopy(Ljava/lang/Object;ILjava/lang/Object;II)V
  aload 9
  invokestatic com/kuguo/ad/e/c([B)I
  istore 22
  iload 17
  iconst_2
  iadd
  istore 13
  iload 22
  istore_1
  iload_1
  newarray byte
  astore 9
  iconst_0
  istore 4
  aload_0
  astore_1
  iload 22
  istore_2
  aload_1
  iload 13
  aload 9
  iload 4
  iload_2
  invokestatic java/lang/System/arraycopy(Ljava/lang/Object;ILjava/lang/Object;II)V
  new java/lang/String
  astore 7
  ldc "UTF-8"
  astore 6
  aload 7
  aload 9
  aload 6
  invokespecial java/lang/String/<init>([BLjava/lang/String;)V
  aload 16
  aload 7
  putfield com/kuguo/ad/p/p Ljava/lang/String;
  iload 22
  iload 13
  iadd
  istore 13
  goto Label35
Label21:
  iconst_2
  istore 4
  iload 4
  newarray byte
  astore 9
  iconst_0
  istore 4
  iconst_2
  istore 10
  aload_0
  astore_1
  iload 17
  istore_2
  aload_1
  iload_2
  aload 9
  iload 4
  iload 10
  invokestatic java/lang/System/arraycopy(Ljava/lang/Object;ILjava/lang/Object;II)V
  aload 9
  invokestatic com/kuguo/ad/e/c([B)I
  istore 22
  iload 17
  iconst_2
  iadd
  istore 13
  iload 22
  istore_1
  iload_1
  newarray byte
  astore 9
  iconst_0
  istore 4
  aload_0
  astore_1
  iload 22
  istore_2
  aload_1
  iload 13
  aload 9
  iload 4
  iload_2
  invokestatic java/lang/System/arraycopy(Ljava/lang/Object;ILjava/lang/Object;II)V
  aload 9
  invokestatic com/kuguo/ad/e/b([B)I
  istore 17
  iload 17
  istore_1
  aload 16
  iload_1
  putfield com/kuguo/ad/p/t I
  iload 22
  iload 13
  iadd
  istore 13
  goto Label35
Label22:
  iconst_2
  istore 4
  iload 4
  newarray byte
  astore 9
  iconst_0
  istore 4
  iconst_2
  istore 10
  aload_0
  astore_1
  iload 17
  istore_2
  aload_1
  iload_2
  aload 9
  iload 4
  iload 10
  invokestatic java/lang/System/arraycopy(Ljava/lang/Object;ILjava/lang/Object;II)V
  aload 9
  invokestatic com/kuguo/ad/e/c([B)I
  istore 22
  iload 17
  iconst_2
  iadd
  istore 13
  iload 22
  istore_1
  iload_1
  newarray byte
  astore 9
  iconst_0
  istore 4
  aload_0
  astore_1
  iload 22
  istore_2
  aload_1
  iload 13
  aload 9
  iload 4
  iload_2
  invokestatic java/lang/System/arraycopy(Ljava/lang/Object;ILjava/lang/Object;II)V
  aload 9
  invokestatic com/kuguo/ad/e/b([B)I
  istore 17
  iload 17
  istore_1
  aload 16
  iload_1
  putfield com/kuguo/ad/p/u I
  iload 22
  iload 13
  iadd
  istore 13
  goto Label35
Label23:
  iconst_2
  istore 4
  iload 4
  newarray byte
  astore 9
  iconst_0
  istore 4
  iconst_2
  istore 10
  aload_0
  astore_1
  iload 17
  istore_2
  aload_1
  iload_2
  aload 9
  iload 4
  iload 10
  invokestatic java/lang/System/arraycopy(Ljava/lang/Object;ILjava/lang/Object;II)V
  aload 9
  invokestatic com/kuguo/ad/e/c([B)I
  istore 22
  iload 17
  iconst_2
  iadd
  istore 13
  iload 22
  istore_1
  iload_1
  newarray byte
  astore 9
  iconst_0
  istore 4
  aload_0
  astore_1
  iload 22
  istore_2
  aload_1
  iload 13
  aload 9
  iload 4
  iload_2
  invokestatic java/lang/System/arraycopy(Ljava/lang/Object;ILjava/lang/Object;II)V
  new java/lang/String
  astore 7
  ldc "UTF-8"
  astore 6
  aload 7
  aload 9
  aload 6
  invokespecial java/lang/String/<init>([BLjava/lang/String;)V
  aload 16
  aload 7
  putfield com/kuguo/ad/p/v Ljava/lang/String;
  iload 22
  iload 13
  iadd
  istore 13
  goto Label35
Label24:
  iconst_2
  istore 4
  iload 4
  newarray byte
  astore 9
  iconst_0
  istore 4
  iconst_2
  istore 10
  aload_0
  astore_1
  iload 17
  istore_2
  aload_1
  iload_2
  aload 9
  iload 4
  iload 10
  invokestatic java/lang/System/arraycopy(Ljava/lang/Object;ILjava/lang/Object;II)V
  aload 9
  invokestatic com/kuguo/ad/e/c([B)I
  istore 22
  iload 17
  iconst_2
  iadd
  istore 13
  iload 22
  istore_1
  iload_1
  newarray byte
  astore 9
  iconst_0
  istore 4
  aload_0
  astore_1
  iload 22
  istore_2
  aload_1
  iload 13
  aload 9
  iload 4
  iload_2
  invokestatic java/lang/System/arraycopy(Ljava/lang/Object;ILjava/lang/Object;II)V
  aload 9
  invokestatic com/kuguo/ad/e/b([B)I
  istore 17
  iload 17
  istore_1
  aload 16
  iload_1
  putfield com/kuguo/ad/p/w I
  iload 22
  iload 13
  iadd
  istore 13
  goto Label35
Label25:
  iconst_2
  istore 4
  iload 4
  newarray byte
  astore 9
  iconst_0
  istore 4
  iconst_2
  istore 10
  aload_0
  astore_1
  iload 17
  istore_2
  aload_1
  iload_2
  aload 9
  iload 4
  iload 10
  invokestatic java/lang/System/arraycopy(Ljava/lang/Object;ILjava/lang/Object;II)V
  aload 9
  invokestatic com/kuguo/ad/e/c([B)I
  istore 22
  iload 17
  iconst_2
  iadd
  istore 13
  iload 22
  istore_1
  iload_1
  newarray byte
  astore 9
  iconst_0
  istore 4
  aload_0
  astore_1
  iload 22
  istore_2
  aload_1
  iload 13
  aload 9
  iload 4
  iload_2
  invokestatic java/lang/System/arraycopy(Ljava/lang/Object;ILjava/lang/Object;II)V
  aload 9
  invokestatic com/kuguo/ad/e/b([B)I
  istore 17
  iload 17
  istore_1
  aload 16
  iload_1
  putfield com/kuguo/ad/p/x I
  iload 22
  iload 13
  iadd
  istore 13
  goto Label35
Label26:
  iconst_2
  istore 4
  iload 4
  newarray byte
  astore 9
  iconst_0
  istore 4
  iconst_2
  istore 10
  aload_0
  astore_1
  iload 17
  istore_2
  aload_1
  iload_2
  aload 9
  iload 4
  iload 10
  invokestatic java/lang/System/arraycopy(Ljava/lang/Object;ILjava/lang/Object;II)V
  aload 9
  invokestatic com/kuguo/ad/e/c([B)I
  istore 22
  iload 17
  iconst_2
  iadd
  istore 13
  iload 22
  istore_1
  iload_1
  newarray byte
  astore 9
  iconst_0
  istore 4
  aload_0
  astore_1
  iload 22
  istore_2
  aload_1
  iload 13
  aload 9
  iload 4
  iload_2
  invokestatic java/lang/System/arraycopy(Ljava/lang/Object;ILjava/lang/Object;II)V
  aload 9
  invokestatic com/kuguo/ad/e/b([B)I
  istore 17
  iload 17
  istore_1
  aload 16
  iload_1
  putfield com/kuguo/ad/p/y I
  iload 22
  iload 13
  iadd
  istore 13
  goto Label35
Label27:
  iconst_2
  istore 4
  iload 4
  newarray byte
  astore 9
  iconst_0
  istore 4
  iconst_2
  istore 10
  aload_0
  astore_1
  iload 17
  istore_2
  aload_1
  iload_2
  aload 9
  iload 4
  iload 10
  invokestatic java/lang/System/arraycopy(Ljava/lang/Object;ILjava/lang/Object;II)V
  aload 9
  invokestatic com/kuguo/ad/e/c([B)I
  istore 22
  iload 17
  iconst_2
  iadd
  istore 13
  iload 22
  istore_1
  iload_1
  newarray byte
  astore 9
  iconst_0
  istore 4
  aload_0
  astore_1
  iload 22
  istore_2
  aload_1
  iload 13
  aload 9
  iload 4
  iload_2
  invokestatic java/lang/System/arraycopy(Ljava/lang/Object;ILjava/lang/Object;II)V
  aload 9
  invokestatic com/kuguo/ad/e/b([B)I
  istore 17
  iload 17
  istore_1
  aload 16
  iload_1
  putfield com/kuguo/ad/p/z I
  iload 22
  iload 13
  iadd
  istore 13
  goto Label35
Label28:
  iconst_2
  istore 4
  iload 4
  newarray byte
  astore 9
  iconst_0
  istore 4
  iconst_2
  istore 10
  aload_0
  astore_1
  iload 17
  istore_2
  aload_1
  iload_2
  aload 9
  iload 4
  iload 10
  invokestatic java/lang/System/arraycopy(Ljava/lang/Object;ILjava/lang/Object;II)V
  aload 9
  invokestatic com/kuguo/ad/e/c([B)I
  istore 22
  iload 17
  iconst_2
  iadd
  istore 13
  iload 22
  istore_1
  iload_1
  newarray byte
  astore 9
  iconst_0
  istore 4
  aload_0
  astore_1
  iload 22
  istore_2
  aload_1
  iload 13
  aload 9
  iload 4
  iload_2
  invokestatic java/lang/System/arraycopy(Ljava/lang/Object;ILjava/lang/Object;II)V
  aload 9
  invokestatic com/kuguo/ad/e/b([B)I
  istore 17
  iload 17
  istore_1
  aload 16
  iload_1
  putfield com/kuguo/ad/p/A I
  iload 22
  iload 13
  iadd
  istore 13
  goto Label35
Label29:
  iconst_2
  istore 4
  iload 4
  newarray byte
  astore 9
  iconst_0
  istore 4
  iconst_2
  istore 10
  aload_0
  astore_1
  iload 17
  istore_2
  aload_1
  iload_2
  aload 9
  iload 4
  iload 10
  invokestatic java/lang/System/arraycopy(Ljava/lang/Object;ILjava/lang/Object;II)V
  aload 9
  invokestatic com/kuguo/ad/e/c([B)I
  istore 22
  iload 17
  iconst_2
  iadd
  istore 13
  iload 22
  istore_1
  iload_1
  newarray byte
  astore 9
  iconst_0
  istore 4
  aload_0
  astore_1
  iload 22
  istore_2
  aload_1
  iload 13
  aload 9
  iload 4
  iload_2
  invokestatic java/lang/System/arraycopy(Ljava/lang/Object;ILjava/lang/Object;II)V
  aload 9
  invokestatic com/kuguo/ad/e/b([B)I
  istore 17
  iload 17
  istore_1
  aload 16
  iload_1
  putfield com/kuguo/ad/p/B I
  iload 22
  iload 13
  iadd
  istore 13
  goto Label35
Label30:
  iconst_2
  istore 4
  iload 4
  newarray byte
  astore 9
  iconst_0
  istore 4
  iconst_2
  istore 10
  aload_0
  astore_1
  iload 17
  istore_2
  aload_1
  iload_2
  aload 9
  iload 4
  iload 10
  invokestatic java/lang/System/arraycopy(Ljava/lang/Object;ILjava/lang/Object;II)V
  aload 9
  invokestatic com/kuguo/ad/e/c([B)I
  istore 22
  iload 17
  iconst_2
  iadd
  istore 13
  iload 22
  istore_1
  iload_1
  newarray byte
  astore 9
  iconst_0
  istore 4
  aload_0
  astore_1
  iload 22
  istore_2
  aload_1
  iload 13
  aload 9
  iload 4
  iload_2
  invokestatic java/lang/System/arraycopy(Ljava/lang/Object;ILjava/lang/Object;II)V
  aload 9
  invokestatic com/kuguo/ad/e/b([B)I
  istore 17
  iload 17
  istore_1
  aload 16
  iload_1
  putfield com/kuguo/ad/p/C I
  iload 22
  iload 13
  iadd
  istore 13
  goto Label35
Label31:
  iconst_2
  istore 4
  iload 4
  newarray byte
  astore 9
  iconst_0
  istore 4
  iconst_2
  istore 10
  aload_0
  astore_1
  iload 17
  istore_2
  aload_1
  iload_2
  aload 9
  iload 4
  iload 10
  invokestatic java/lang/System/arraycopy(Ljava/lang/Object;ILjava/lang/Object;II)V
  aload 9
  invokestatic com/kuguo/ad/e/c([B)I
  istore 22
  iload 17
  iconst_2
  iadd
  istore 13
  iload 22
  istore_1
  iload_1
  newarray byte
  astore 9
  iconst_0
  istore 4
  aload_0
  astore_1
  iload 22
  istore_2
  aload_1
  iload 13
  aload 9
  iload 4
  iload_2
  invokestatic java/lang/System/arraycopy(Ljava/lang/Object;ILjava/lang/Object;II)V
  aload 9
  invokestatic com/kuguo/ad/e/b([B)I
  istore 17
  iload 17
  istore_1
  aload 16
  iload_1
  putfield com/kuguo/ad/p/D I
  iload 22
  iload 13
  iadd
  istore 13
  goto Label35
Label32:
  iconst_2
  istore 4
  iload 4
  newarray byte
  astore 9
  iconst_0
  istore 4
  iconst_2
  istore 10
  aload_0
  astore_1
  iload 17
  istore_2
  aload_1
  iload_2
  aload 9
  iload 4
  iload 10
  invokestatic java/lang/System/arraycopy(Ljava/lang/Object;ILjava/lang/Object;II)V
  aload 9
  invokestatic com/kuguo/ad/e/c([B)I
  istore 22
  iload 17
  iconst_2
  iadd
  istore 13
  iload 22
  istore_1
  iload_1
  newarray byte
  astore 9
  iconst_0
  istore 4
  aload_0
  astore_1
  iload 22
  istore_2
  aload_1
  iload 13
  aload 9
  iload 4
  iload_2
  invokestatic java/lang/System/arraycopy(Ljava/lang/Object;ILjava/lang/Object;II)V
  new java/lang/String
  astore 7
  ldc "UTF-8"
  astore 6
  aload 7
  aload 9
  aload 6
  invokespecial java/lang/String/<init>([BLjava/lang/String;)V
  aload 16
  aload 7
  putfield com/kuguo/ad/p/E Ljava/lang/String;
  iload 22
  iload 13
  iadd
  istore 13
  goto Label35
Label33:
  iconst_2
  istore 4
  iload 4
  newarray byte
  astore 9
  iconst_0
  istore 4
  iconst_2
  istore 10
  aload_0
  astore_1
  iload 17
  istore_2
  aload_1
  iload_2
  aload 9
  iload 4
  iload 10
  invokestatic java/lang/System/arraycopy(Ljava/lang/Object;ILjava/lang/Object;II)V
  aload 9
  invokestatic com/kuguo/ad/e/c([B)I
  istore 22
  iload 17
  iconst_2
  iadd
  istore 13
  iload 22
  istore_1
  iload_1
  newarray byte
  astore 9
  iconst_0
  istore 4
  aload_0
  astore_1
  iload 22
  istore_2
  aload_1
  iload 13
  aload 9
  iload 4
  iload_2
  invokestatic java/lang/System/arraycopy(Ljava/lang/Object;ILjava/lang/Object;II)V
  new java/lang/String
  astore 7
  ldc "UTF-8"
  astore 6
  aload 7
  aload 9
  aload 6
  invokespecial java/lang/String/<init>([BLjava/lang/String;)V
  aload 16
  aload 7
  putfield com/kuguo/ad/p/F Ljava/lang/String;
  iload 22
  iload 13
  iadd
  istore 13
  goto Label35
Label2:
  aload 14
  iload 15
  aload 16
  aastore
  iload 15
  iconst_1
  iadd
  istore 15
  iload 17
  iconst_2
  iadd
  istore 13
  goto Label36
Label1:
  aload 14
  areturn
  nop
  nop
  nop
.end <method>

.method protected b()V
.limit locals 8
.limit stack 200
  nop
  ldc "--------------------AdsResponsePackage print------------------"
  astore_1
  aload_1
  invokestatic com/kuguo/ad/d/a(Ljava/lang/String;)V
  new java/lang/StringBuilder
  astore_2
  aload_2
  invokespecial java/lang/StringBuilder/<init>()V
  ldc "address: "
  astore_1
  aload_2
  aload_1
  invokevirtual java/lang/StringBuilder/append(Ljava/lang/String;)Ljava/lang/StringBuilder;
  astore_2
  aload_0
  getfield com/kuguo/ad/p/a Ljava/lang/String;
  astore_3
  aload_2
  aload_3
  invokevirtual java/lang/StringBuilder/append(Ljava/lang/String;)Ljava/lang/StringBuilder;
  astore_2
  aload_2
  invokevirtual java/lang/StringBuilder/toString()Ljava/lang/String;
  astore_3
  aload_3
  invokestatic com/kuguo/ad/d/a(Ljava/lang/String;)V
  new java/lang/StringBuilder
  astore_2
  aload_2
  invokespecial java/lang/StringBuilder/<init>()V
  ldc "body: "
  astore_1
  aload_2
  aload_1
  invokevirtual java/lang/StringBuilder/append(Ljava/lang/String;)Ljava/lang/StringBuilder;
  astore_2
  aload_0
  getfield com/kuguo/ad/p/b Ljava/lang/String;
  astore_3
  aload_2
  aload_3
  invokevirtual java/lang/StringBuilder/append(Ljava/lang/String;)Ljava/lang/StringBuilder;
  astore_2
  aload_2
  invokevirtual java/lang/StringBuilder/toString()Ljava/lang/String;
  astore_3
  aload_3
  invokestatic com/kuguo/ad/d/a(Ljava/lang/String;)V
  new java/lang/StringBuilder
  astore_2
  aload_2
  invokespecial java/lang/StringBuilder/<init>()V
  ldc "date: "
  astore_1
  aload_2
  aload_1
  invokevirtual java/lang/StringBuilder/append(Ljava/lang/String;)Ljava/lang/StringBuilder;
  astore_2
  aload_0
  getfield com/kuguo/ad/p/c J
  lstore 4
  aload_2
  lload 4
  invokevirtual java/lang/StringBuilder/append(J)Ljava/lang/StringBuilder;
  astore_2
  aload_2
  invokevirtual java/lang/StringBuilder/toString()Ljava/lang/String;
  astore_3
  aload_3
  invokestatic com/kuguo/ad/d/a(Ljava/lang/String;)V
  new java/lang/StringBuilder
  astore_2
  aload_2
  invokespecial java/lang/StringBuilder/<init>()V
  ldc "type: "
  astore_1
  aload_2
  aload_1
  invokevirtual java/lang/StringBuilder/append(Ljava/lang/String;)Ljava/lang/StringBuilder;
  astore_2
  aload_0
  getfield com/kuguo/ad/p/e B
  istore 6
  aload_2
  iload 6
  invokevirtual java/lang/StringBuilder/append(I)Ljava/lang/StringBuilder;
  astore_2
  aload_2
  invokevirtual java/lang/StringBuilder/toString()Ljava/lang/String;
  astore_3
  aload_3
  invokestatic com/kuguo/ad/d/a(Ljava/lang/String;)V
  new java/lang/StringBuilder
  astore_2
  aload_2
  invokespecial java/lang/StringBuilder/<init>()V
  ldc "url: "
  astore_1
  aload_2
  aload_1
  invokevirtual java/lang/StringBuilder/append(Ljava/lang/String;)Ljava/lang/StringBuilder;
  astore_2
  aload_0
  getfield com/kuguo/ad/p/d Ljava/lang/String;
  astore_3
  aload_2
  aload_3
  invokevirtual java/lang/StringBuilder/append(Ljava/lang/String;)Ljava/lang/StringBuilder;
  astore_2
  aload_2
  invokevirtual java/lang/StringBuilder/toString()Ljava/lang/String;
  astore_3
  aload_3
  invokestatic com/kuguo/ad/d/a(Ljava/lang/String;)V
  new java/lang/StringBuilder
  astore_2
  aload_2
  invokespecial java/lang/StringBuilder/<init>()V
  ldc "apkName: "
  astore_1
  aload_2
  aload_1
  invokevirtual java/lang/StringBuilder/append(Ljava/lang/String;)Ljava/lang/StringBuilder;
  astore_2
  aload_0
  getfield com/kuguo/ad/p/g Ljava/lang/String;
  astore_3
  aload_2
  aload_3
  invokevirtual java/lang/StringBuilder/append(Ljava/lang/String;)Ljava/lang/StringBuilder;
  astore_2
  aload_2
  invokevirtual java/lang/StringBuilder/toString()Ljava/lang/String;
  astore_3
  aload_3
  invokestatic com/kuguo/ad/d/a(Ljava/lang/String;)V
  new java/lang/StringBuilder
  astore_2
  aload_2
  invokespecial java/lang/StringBuilder/<init>()V
  ldc "advertId: "
  astore_1
  aload_2
  aload_1
  invokevirtual java/lang/StringBuilder/append(Ljava/lang/String;)Ljava/lang/StringBuilder;
  astore_2
  aload_0
  getfield com/kuguo/ad/p/h I
  istore 7
  aload_2
  iload 7
  invokevirtual java/lang/StringBuilder/append(I)Ljava/lang/StringBuilder;
  astore_2
  aload_2
  invokevirtual java/lang/StringBuilder/toString()Ljava/lang/String;
  astore_3
  aload_3
  invokestatic com/kuguo/ad/d/a(Ljava/lang/String;)V
  new java/lang/StringBuilder
  astore_2
  aload_2
  invokespecial java/lang/StringBuilder/<init>()V
  ldc "apkPackage: "
  astore_1
  aload_2
  aload_1
  invokevirtual java/lang/StringBuilder/append(Ljava/lang/String;)Ljava/lang/StringBuilder;
  astore_2
  aload_0
  getfield com/kuguo/ad/p/i Ljava/lang/String;
  astore_3
  aload_2
  aload_3
  invokevirtual java/lang/StringBuilder/append(Ljava/lang/String;)Ljava/lang/StringBuilder;
  astore_2
  aload_2
  invokevirtual java/lang/StringBuilder/toString()Ljava/lang/String;
  astore_3
  aload_3
  invokestatic com/kuguo/ad/d/a(Ljava/lang/String;)V
  new java/lang/StringBuilder
  astore_2
  aload_2
  invokespecial java/lang/StringBuilder/<init>()V
  ldc "title"
  astore_1
  aload_2
  aload_1
  invokevirtual java/lang/StringBuilder/append(Ljava/lang/String;)Ljava/lang/StringBuilder;
  astore_2
  aload_0
  getfield com/kuguo/ad/p/k Ljava/lang/String;
  astore_3
  aload_2
  aload_3
  invokevirtual java/lang/StringBuilder/append(Ljava/lang/String;)Ljava/lang/StringBuilder;
  astore_2
  aload_2
  invokevirtual java/lang/StringBuilder/toString()Ljava/lang/String;
  astore_3
  aload_3
  invokestatic com/kuguo/ad/d/a(Ljava/lang/String;)V
  new java/lang/StringBuilder
  astore_2
  aload_2
  invokespecial java/lang/StringBuilder/<init>()V
  ldc "appType: "
  astore_1
  aload_2
  aload_1
  invokevirtual java/lang/StringBuilder/append(Ljava/lang/String;)Ljava/lang/StringBuilder;
  astore_2
  aload_0
  getfield com/kuguo/ad/p/l Ljava/lang/String;
  astore_3
  aload_2
  aload_3
  invokevirtual java/lang/StringBuilder/append(Ljava/lang/String;)Ljava/lang/StringBuilder;
  astore_2
  aload_2
  invokevirtual java/lang/StringBuilder/toString()Ljava/lang/String;
  astore_3
  aload_3
  invokestatic com/kuguo/ad/d/a(Ljava/lang/String;)V
  new java/lang/StringBuilder
  astore_2
  aload_2
  invokespecial java/lang/StringBuilder/<init>()V
  ldc "appSize: "
  astore_1
  aload_2
  aload_1
  invokevirtual java/lang/StringBuilder/append(Ljava/lang/String;)Ljava/lang/StringBuilder;
  astore_2
  aload_0
  getfield com/kuguo/ad/p/m I
  istore 7
  aload_2
  iload 7
  invokevirtual java/lang/StringBuilder/append(I)Ljava/lang/StringBuilder;
  astore_2
  aload_2
  invokevirtual java/lang/StringBuilder/toString()Ljava/lang/String;
  astore_3
  aload_3
  invokestatic com/kuguo/ad/d/a(Ljava/lang/String;)V
  new java/lang/StringBuilder
  astore_2
  aload_2
  invokespecial java/lang/StringBuilder/<init>()V
  ldc "appVersion: "
  astore_1
  aload_2
  aload_1
  invokevirtual java/lang/StringBuilder/append(Ljava/lang/String;)Ljava/lang/StringBuilder;
  astore_2
  aload_0
  getfield com/kuguo/ad/p/n Ljava/lang/String;
  astore_3
  aload_2
  aload_3
  invokevirtual java/lang/StringBuilder/append(Ljava/lang/String;)Ljava/lang/StringBuilder;
  astore_2
  aload_2
  invokevirtual java/lang/StringBuilder/toString()Ljava/lang/String;
  astore_3
  aload_3
  invokestatic com/kuguo/ad/d/a(Ljava/lang/String;)V
  new java/lang/StringBuilder
  astore_2
  aload_2
  invokespecial java/lang/StringBuilder/<init>()V
  ldc "iconUrl: "
  astore_1
  aload_2
  aload_1
  invokevirtual java/lang/StringBuilder/append(Ljava/lang/String;)Ljava/lang/StringBuilder;
  astore_2
  aload_0
  getfield com/kuguo/ad/p/o Ljava/lang/String;
  astore_3
  aload_2
  aload_3
  invokevirtual java/lang/StringBuilder/append(Ljava/lang/String;)Ljava/lang/StringBuilder;
  astore_2
  aload_2
  invokevirtual java/lang/StringBuilder/toString()Ljava/lang/String;
  astore_3
  aload_3
  invokestatic com/kuguo/ad/d/a(Ljava/lang/String;)V
  new java/lang/StringBuilder
  astore_2
  aload_2
  invokespecial java/lang/StringBuilder/<init>()V
  ldc "captureUrls: "
  astore_1
  aload_2
  aload_1
  invokevirtual java/lang/StringBuilder/append(Ljava/lang/String;)Ljava/lang/StringBuilder;
  astore_2
  aload_0
  getfield com/kuguo/ad/p/p Ljava/lang/String;
  astore_3
  aload_2
  aload_3
  invokevirtual java/lang/StringBuilder/append(Ljava/lang/String;)Ljava/lang/StringBuilder;
  astore_2
  aload_2
  invokevirtual java/lang/StringBuilder/toString()Ljava/lang/String;
  astore_3
  aload_3
  invokestatic com/kuguo/ad/d/a(Ljava/lang/String;)V
  new java/lang/StringBuilder
  astore_2
  aload_2
  invokespecial java/lang/StringBuilder/<init>()V
  ldc "showDialog: "
  astore_1
  aload_2
  aload_1
  invokevirtual java/lang/StringBuilder/append(Ljava/lang/String;)Ljava/lang/StringBuilder;
  astore_2
  aload_0
  getfield com/kuguo/ad/p/q I
  istore 7
  aload_2
  iload 7
  invokevirtual java/lang/StringBuilder/append(I)Ljava/lang/StringBuilder;
  astore_2
  aload_2
  invokevirtual java/lang/StringBuilder/toString()Ljava/lang/String;
  astore_3
  aload_3
  invokestatic com/kuguo/ad/d/a(Ljava/lang/String;)V
  new java/lang/StringBuilder
  astore_2
  aload_2
  invokespecial java/lang/StringBuilder/<init>()V
  ldc "autoDownload: "
  astore_1
  aload_2
  aload_1
  invokevirtual java/lang/StringBuilder/append(Ljava/lang/String;)Ljava/lang/StringBuilder;
  astore_2
  aload_0
  getfield com/kuguo/ad/p/r I
  istore 7
  aload_2
  iload 7
  invokevirtual java/lang/StringBuilder/append(I)Ljava/lang/StringBuilder;
  astore_2
  aload_2
  invokevirtual java/lang/StringBuilder/toString()Ljava/lang/String;
  astore_3
  aload_3
  invokestatic com/kuguo/ad/d/a(Ljava/lang/String;)V
  new java/lang/StringBuilder
  astore_2
  aload_2
  invokespecial java/lang/StringBuilder/<init>()V
  ldc "forceClick: "
  astore_1
  aload_2
  aload_1
  invokevirtual java/lang/StringBuilder/append(Ljava/lang/String;)Ljava/lang/StringBuilder;
  astore_2
  aload_0
  getfield com/kuguo/ad/p/t I
  istore 7
  aload_2
  iload 7
  invokevirtual java/lang/StringBuilder/append(I)Ljava/lang/StringBuilder;
  astore_2
  aload_2
  invokevirtual java/lang/StringBuilder/toString()Ljava/lang/String;
  astore_3
  aload_3
  invokestatic com/kuguo/ad/d/a(Ljava/lang/String;)V
  new java/lang/StringBuilder
  astore_2
  aload_2
  invokespecial java/lang/StringBuilder/<init>()V
  ldc "autoInstall: "
  astore_1
  aload_2
  aload_1
  invokevirtual java/lang/StringBuilder/append(Ljava/lang/String;)Ljava/lang/StringBuilder;
  astore_2
  aload_0
  getfield com/kuguo/ad/p/u I
  istore 7
  aload_2
  iload 7
  invokevirtual java/lang/StringBuilder/append(I)Ljava/lang/StringBuilder;
  astore_2
  aload_2
  invokevirtual java/lang/StringBuilder/toString()Ljava/lang/String;
  astore_3
  aload_3
  invokestatic com/kuguo/ad/d/a(Ljava/lang/String;)V
  new java/lang/StringBuilder
  astore_2
  aload_2
  invokespecial java/lang/StringBuilder/<init>()V
  ldc "permissions: "
  astore_1
  aload_2
  aload_1
  invokevirtual java/lang/StringBuilder/append(Ljava/lang/String;)Ljava/lang/StringBuilder;
  astore_2
  aload_0
  getfield com/kuguo/ad/p/v Ljava/lang/String;
  astore_3
  aload_2
  aload_3
  invokevirtual java/lang/StringBuilder/append(Ljava/lang/String;)Ljava/lang/StringBuilder;
  astore_2
  aload_2
  invokevirtual java/lang/StringBuilder/toString()Ljava/lang/String;
  astore_3
  aload_3
  invokestatic com/kuguo/ad/d/a(Ljava/lang/String;)V
  new java/lang/StringBuilder
  astore_2
  aload_2
  invokespecial java/lang/StringBuilder/<init>()V
  ldc "marketPackage: "
  astore_1
  aload_2
  aload_1
  invokevirtual java/lang/StringBuilder/append(Ljava/lang/String;)Ljava/lang/StringBuilder;
  astore_2
  aload_0
  getfield com/kuguo/ad/p/s Ljava/lang/String;
  astore_3
  aload_2
  aload_3
  invokevirtual java/lang/StringBuilder/append(Ljava/lang/String;)Ljava/lang/StringBuilder;
  astore_2
  aload_2
  invokevirtual java/lang/StringBuilder/toString()Ljava/lang/String;
  astore_3
  aload_3
  invokestatic com/kuguo/ad/d/a(Ljava/lang/String;)V
  new java/lang/StringBuilder
  astore_2
  aload_2
  invokespecial java/lang/StringBuilder/<init>()V
  ldc "permissions: "
  astore_1
  aload_2
  aload_1
  invokevirtual java/lang/StringBuilder/append(Ljava/lang/String;)Ljava/lang/StringBuilder;
  astore_2
  aload_0
  getfield com/kuguo/ad/p/v Ljava/lang/String;
  astore_3
  aload_2
  aload_3
  invokevirtual java/lang/StringBuilder/append(Ljava/lang/String;)Ljava/lang/StringBuilder;
  astore_2
  aload_2
  invokevirtual java/lang/StringBuilder/toString()Ljava/lang/String;
  astore_3
  aload_3
  invokestatic com/kuguo/ad/d/a(Ljava/lang/String;)V
  new java/lang/StringBuilder
  astore_2
  aload_2
  invokespecial java/lang/StringBuilder/<init>()V
  ldc "nextRequest: "
  astore_1
  aload_2
  aload_1
  invokevirtual java/lang/StringBuilder/append(Ljava/lang/String;)Ljava/lang/StringBuilder;
  astore_2
  aload_0
  getfield com/kuguo/ad/p/w I
  istore 7
  aload_2
  iload 7
  invokevirtual java/lang/StringBuilder/append(I)Ljava/lang/StringBuilder;
  astore_2
  aload_2
  invokevirtual java/lang/StringBuilder/toString()Ljava/lang/String;
  astore_3
  aload_3
  invokestatic com/kuguo/ad/d/a(Ljava/lang/String;)V
  new java/lang/StringBuilder
  astore_2
  aload_2
  invokespecial java/lang/StringBuilder/<init>()V
  ldc "vibrate: "
  astore_1
  aload_2
  aload_1
  invokevirtual java/lang/StringBuilder/append(Ljava/lang/String;)Ljava/lang/StringBuilder;
  astore_2
  aload_0
  getfield com/kuguo/ad/p/x I
  istore 7
  aload_2
  iload 7
  invokevirtual java/lang/StringBuilder/append(I)Ljava/lang/StringBuilder;
  astore_2
  aload_2
  invokevirtual java/lang/StringBuilder/toString()Ljava/lang/String;
  astore_3
  aload_3
  invokestatic com/kuguo/ad/d/a(Ljava/lang/String;)V
  new java/lang/StringBuilder
  astore_2
  aload_2
  invokespecial java/lang/StringBuilder/<init>()V
  ldc "testAd: "
  astore_1
  aload_2
  aload_1
  invokevirtual java/lang/StringBuilder/append(Ljava/lang/String;)Ljava/lang/StringBuilder;
  astore_2
  aload_0
  getfield com/kuguo/ad/p/y I
  istore 7
  aload_2
  iload 7
  invokevirtual java/lang/StringBuilder/append(I)Ljava/lang/StringBuilder;
  astore_2
  aload_2
  invokevirtual java/lang/StringBuilder/toString()Ljava/lang/String;
  astore_3
  aload_3
  invokestatic com/kuguo/ad/d/a(Ljava/lang/String;)V
  new java/lang/StringBuilder
  astore_2
  aload_2
  invokespecial java/lang/StringBuilder/<init>()V
  ldc "spaceTime: "
  astore_1
  aload_2
  aload_1
  invokevirtual java/lang/StringBuilder/append(Ljava/lang/String;)Ljava/lang/StringBuilder;
  astore_2
  aload_0
  getfield com/kuguo/ad/p/A I
  istore 7
  aload_2
  iload 7
  invokevirtual java/lang/StringBuilder/append(I)Ljava/lang/StringBuilder;
  astore_2
  aload_2
  invokevirtual java/lang/StringBuilder/toString()Ljava/lang/String;
  astore_3
  aload_3
  invokestatic com/kuguo/ad/d/a(Ljava/lang/String;)V
  new java/lang/StringBuilder
  astore_2
  aload_2
  invokespecial java/lang/StringBuilder/<init>()V
  ldc "style: "
  astore_1
  aload_2
  aload_1
  invokevirtual java/lang/StringBuilder/append(Ljava/lang/String;)Ljava/lang/StringBuilder;
  astore_2
  aload_0
  getfield com/kuguo/ad/p/B I
  istore 7
  aload_2
  iload 7
  invokevirtual java/lang/StringBuilder/append(I)Ljava/lang/StringBuilder;
  astore_2
  aload_2
  invokevirtual java/lang/StringBuilder/toString()Ljava/lang/String;
  astore_3
  aload_3
  invokestatic com/kuguo/ad/d/a(Ljava/lang/String;)V
  new java/lang/StringBuilder
  astore_2
  aload_2
  invokespecial java/lang/StringBuilder/<init>()V
  ldc "downloadMode: "
  astore_1
  aload_2
  aload_1
  invokevirtual java/lang/StringBuilder/append(Ljava/lang/String;)Ljava/lang/StringBuilder;
  astore_2
  aload_0
  getfield com/kuguo/ad/p/C I
  istore 7
  aload_2
  iload 7
  invokevirtual java/lang/StringBuilder/append(I)Ljava/lang/StringBuilder;
  astore_2
  aload_2
  invokevirtual java/lang/StringBuilder/toString()Ljava/lang/String;
  astore_3
  aload_3
  invokestatic com/kuguo/ad/d/a(Ljava/lang/String;)V
  new java/lang/StringBuilder
  astore_2
  aload_2
  invokespecial java/lang/StringBuilder/<init>()V
  ldc "provider: "
  astore_1
  aload_2
  aload_1
  invokevirtual java/lang/StringBuilder/append(Ljava/lang/String;)Ljava/lang/StringBuilder;
  astore_2
  aload_0
  getfield com/kuguo/ad/p/E Ljava/lang/String;
  astore_3
  aload_2
  aload_3
  invokevirtual java/lang/StringBuilder/append(Ljava/lang/String;)Ljava/lang/StringBuilder;
  astore_2
  aload_2
  invokevirtual java/lang/StringBuilder/toString()Ljava/lang/String;
  astore_3
  aload_3
  invokestatic com/kuguo/ad/d/a(Ljava/lang/String;)V
  new java/lang/StringBuilder
  astore_2
  aload_2
  invokespecial java/lang/StringBuilder/<init>()V
  ldc "idAndPakcageNames: "
  astore_1
  aload_2
  aload_1
  invokevirtual java/lang/StringBuilder/append(Ljava/lang/String;)Ljava/lang/StringBuilder;
  astore_2
  aload_0
  getfield com/kuguo/ad/p/F Ljava/lang/String;
  astore_3
  aload_2
  aload_3
  invokevirtual java/lang/StringBuilder/append(Ljava/lang/String;)Ljava/lang/StringBuilder;
  astore_2
  aload_2
  invokevirtual java/lang/StringBuilder/toString()Ljava/lang/String;
  astore_3
  aload_3
  invokestatic com/kuguo/ad/d/a(Ljava/lang/String;)V
  ldc "----------------------------"
  astore_1
  aload_1
  invokestatic com/kuguo/ad/d/a(Ljava/lang/String;)V
  return
  nop
.end <method>

.method public toString()Ljava/lang/String;
.limit locals 2
.limit stack 200
  nop
  aload_0
  invokevirtual com/kuguo/ad/p/a()Ljava/lang/String;
  astore_1
  aload_1
  areturn
  nop
.end <method>

