.source WinsAPIAdapter.java
.class  com/admogo/adapters/WinsAPIAdapter$PingWinsADUrlRunnable
.super java/lang/Object
.implements  java/lang/Runnable
.field private "adMogoLayout" Lcom/admogo/AdMogoLayout;
.field private "key" Ljava/lang/String;

.method public <init>(Lcom/admogo/AdMogoLayout;Ljava/lang/String;)V
.limit locals 3
.limit stack 200
  nop
  aload_0
  invokespecial java/lang/Object/<init>()V
  aload_0
  aload_1
  putfield com/admogo/adapters/WinsAPIAdapter$PingWinsADUrlRunnable/adMogoLayout Lcom/admogo/AdMogoLayout;
  aload_0
  aload_2
  putfield com/admogo/adapters/WinsAPIAdapter$PingWinsADUrlRunnable/key Ljava/lang/String;
  return
  nop
.end <method>

.method public run()V
.limit locals 21
.limit stack 200
  .catch  java/lang/Exception <from> Label2 <to> Label0 <using> Label1
  nop
  new org/json/JSONObject
  astore_2
Label2:
  aload_2
  invokespecial org/json/JSONObject/<init>()V
  aload_0
  astore_1
  aload_1
  getfield com/admogo/adapters/WinsAPIAdapter$PingWinsADUrlRunnable/adMogoLayout Lcom/admogo/AdMogoLayout;
  astore_3
  new java/lang/NoClassDefFoundError
  dup
  invokespecial java/lang/NoClassDefFoundError/<init>()V
  athrow
  aload 4
  getfield com/admogo/AdMogoManager/deviceIDHash Ljava/lang/String;
  astore 5
  ldc "devid"
  astore 6
  aload_2
  aload 6
  aload 5
  invokevirtual org/json/JSONObject/put(Ljava/lang/String;Ljava/lang/Object;)Lorg/json/JSONObject;
  pop
  invokestatic com/admogo/adapters/WinsAPIAdapter/access$2()Lcom/admogo/obj/WinsAD;
  astore 7
  aload 7
  getfield com/admogo/obj/WinsAD/adid Ljava/lang/String;
  astore 8
  ldc "adid"
  astore 6
  aload_2
  aload 6
  aload 8
  invokevirtual org/json/JSONObject/put(Ljava/lang/String;Ljava/lang/Object;)Lorg/json/JSONObject;
  pop
  ldc "type"
  astore 6
  ldc "0"
  astore 9
  aload_2
  aload 6
  aload 9
  invokevirtual org/json/JSONObject/put(Ljava/lang/String;Ljava/lang/Object;)Lorg/json/JSONObject;
  pop
  ldc "PartnerID"
  astore 6
  ldc "mogo001"
  astore 9
  aload_2
  aload 6
  aload 9
  invokevirtual org/json/JSONObject/put(Ljava/lang/String;Ljava/lang/Object;)Lorg/json/JSONObject;
  pop
  new java/net/URL
  astore 10
  ldc "http://api.winsmedia.net/webviewAdClick"
  astore 6
  aload 10
  aload 6
  invokespecial java/net/URL/<init>(Ljava/lang/String;)V
  aload 10
  invokevirtual java/net/URL/openConnection()Ljava/net/URLConnection;
  astore 11
  aload 11
  astore 13
  aload 13
  checkcast java/net/HttpURLConnection
  astore 13
  aload 13
  astore 12
  iconst_1
  istore 14
  aload 12
  iload 14
  invokevirtual java/net/HttpURLConnection/setDoOutput(Z)V
  iconst_1
  istore 14
  aload 12
  iload 14
  invokevirtual java/net/HttpURLConnection/setDoInput(Z)V
  ldc "POST"
  astore 6
  aload 12
  aload 6
  invokevirtual java/net/HttpURLConnection/setRequestMethod(Ljava/lang/String;)V
  ldc "content-type"
  astore 6
  ldc "application/x-www-form-urlencoded"
  astore 9
  aload 12
  aload 6
  aload 9
  invokevirtual java/net/HttpURLConnection/setRequestProperty(Ljava/lang/String;Ljava/lang/String;)V
  aload_0
  astore_1
  aload_1
  getfield com/admogo/adapters/WinsAPIAdapter$PingWinsADUrlRunnable/key Ljava/lang/String;
  astore 8
  ldc "appkey"
  astore 6
  aload 12
  aload 6
  aload 8
  invokevirtual java/net/HttpURLConnection/addRequestProperty(Ljava/lang/String;Ljava/lang/String;)V
  sipush 10000
  istore 14
  aload 12
  iload 14
  invokevirtual java/net/HttpURLConnection/setConnectTimeout(I)V
  sipush 10000
  istore 14
  aload 12
  iload 14
  invokevirtual java/net/HttpURLConnection/setReadTimeout(I)V
  new java/io/BufferedWriter
  astore 15
  new java/io/OutputStreamWriter
  astore 16
  aload 12
  invokevirtual java/net/HttpURLConnection/getOutputStream()Ljava/io/OutputStream;
  astore 17
  aload 17
  astore_1
  aload 16
  aload_1
  invokespecial java/io/OutputStreamWriter/<init>(Ljava/io/OutputStream;)V
  aload 15
  aload 16
  invokespecial java/io/BufferedWriter/<init>(Ljava/io/Writer;)V
  aload_2
  invokevirtual org/json/JSONObject/toString()Ljava/lang/String;
  astore 5
  aload_0
  astore_1
  aload_1
  getfield com/admogo/adapters/WinsAPIAdapter$PingWinsADUrlRunnable/key Ljava/lang/String;
  astore 8
  aload 8
  invokestatic com/admogo/encryption/CryptUtils/getString(Ljava/lang/String;)Ljava/lang/String;
  astore 8
  iconst_0
  istore 14
  aload 5
  aload 8
  iload 14
  invokestatic com/admogo/encryption/CryptUtils/encrypt(Ljava/lang/String;Ljava/lang/String;Z)Ljava/lang/String;
  astore 8
  aload 15
  aload 8
  invokevirtual java/io/BufferedWriter/write(Ljava/lang/String;)V
  aload 15
  invokevirtual java/io/BufferedWriter/close()V
  aload 12
  invokevirtual java/net/HttpURLConnection/getInputStream()Ljava/io/InputStream;
  astore 18
  aload_0
  astore_1
  aload_1
  getfield com/admogo/adapters/WinsAPIAdapter$PingWinsADUrlRunnable/adMogoLayout Lcom/admogo/AdMogoLayout;
  astore_3
  aload_3
  getfield com/admogo/AdMogoLayout/adMogoManager Lcom/admogo/AdMogoManager;
  astore 4
  aload 18
  astore_1
  aload 4
  aload_1
  invokevirtual com/admogo/AdMogoManager/convertStreamToString(Ljava/io/InputStream;)Ljava/lang/String;
  astore 5
  aload_0
  astore_1
  aload_1
  getfield com/admogo/adapters/WinsAPIAdapter$PingWinsADUrlRunnable/key Ljava/lang/String;
  astore 8
  aload 8
  invokestatic com/admogo/encryption/CryptUtils/getString(Ljava/lang/String;)Ljava/lang/String;
  astore 8
  iconst_0
  istore 14
  aload 5
  aload 8
  iload 14
  invokestatic com/admogo/encryption/CryptUtils/decrypt(Ljava/lang/String;Ljava/lang/String;Z)Ljava/lang/String;
  astore 8
  aload_0
  astore_1
  aload_1
  getfield com/admogo/adapters/WinsAPIAdapter$PingWinsADUrlRunnable/key Ljava/lang/String;
  astore 5
  aload_0
  astore_1
  aload_1
  getfield com/admogo/adapters/WinsAPIAdapter$PingWinsADUrlRunnable/adMogoLayout Lcom/admogo/AdMogoLayout;
  astore_3
  aload 8
  aload 5
  aload_3
  invokestatic com/admogo/adapters/WinsAPIAdapter/access$3(Ljava/lang/String;Ljava/lang/String;Lcom/admogo/AdMogoLayout;)V
Label0:
  return
Label1:
  astore 19
  getstatic com/admogo/util/AdMogoUtil/ADMOGO Ljava/lang/String;
  astore 5
  ldc "PingWinsADUrlRunnable"
  astore 6
  aload 19
  astore_1
  new java/lang/NoClassDefFoundError
  dup
  invokespecial java/lang/NoClassDefFoundError/<init>()V
  athrow
  invokestatic com/admogo/adapters/WinsAPIAdapter/access$4()I
  istore 20
  iload 20
  istore_1
  dload_1
  invokestatic app/DummyClass/invokeIfStmt(D)V
  iconst_3
  istore 14
  iload 20
  istore_1
  iload_1
  iload 14
  if_icmpge Label0
  invokestatic com/admogo/adapters/WinsAPIAdapter/access$4()I
  istore 20
  iload 20
  iconst_1
  iadd
  istore 20
  iload 20
  istore_1
  iload_1
  invokestatic com/admogo/adapters/WinsAPIAdapter/access$5(I)V
  aload_0
  astore_1
  aload_1
  invokevirtual com/admogo/adapters/WinsAPIAdapter$PingWinsADUrlRunnable/run()V
  goto Label0
  nop
.end <method>

