.source dalvik_source_VirusShare_32e70f448ebd75661a1cb12f9cd8e013.apk
.class  com/wiyun/ad/AdView$2$1
.super java/lang/Thread
.field final "a" Lcom/wiyun/ad/AdView$2;
.field private final "b" Landroid/content/Context;

.method <init>(Lcom/wiyun/ad/AdView$2;Landroid/content/Context;)V
.limit locals 3
.limit stack 200
  nop
  aload_0
  aload_1
  putfield com/wiyun/ad/AdView$2$1/a Lcom/wiyun/ad/AdView$2;
  aload_0
  aload_2
  putfield com/wiyun/ad/AdView$2$1/b Landroid/content/Context;
  aload_0
  invokespecial java/lang/Thread/<init>()V
  return
  nop
.end <method>

.method public run()V
.limit locals 5
.limit stack 200
  nop
  aload_0
  getfield com/wiyun/ad/AdView$2$1/b Landroid/content/Context;
  astore_1
  aload_0
  getfield com/wiyun/ad/AdView$2$1/a Lcom/wiyun/ad/AdView$2;
  astore_2
  new java/lang/NoClassDefFoundError
  dup
  invokespecial java/lang/NoClassDefFoundError/<init>()V
  athrow
  nop
  aload_3
  invokestatic com/wiyun/ad/AdView/e(Lcom/wiyun/ad/AdView;)Lcom/wiyun/ad/j;
  astore 4
  aload_1
  aload 4
  invokestatic com/wiyun/ad/b/a(Landroid/content/Context;Lcom/wiyun/ad/j;)V
  return
  nop
.end <method>

