.source dalvik_source_VirusShare_32e70f448ebd75661a1cb12f9cd8e013.apk
.class public  com/tencent/mobwin/core/x
.super java/lang/Object
.field public static final "a" Ljava/lang/String; =  "/Tencent/MobWIN/"
.field public static final "b" Ljava/lang/String; =  "location.txt"
.field private static final "c" Ljava/lang/String; =  "OperateCard:"

.method private <init>()V
.limit locals 1
.limit stack 200
  nop
  aload_0
  invokespecial java/lang/Object/<init>()V
  return
  nop
.end <method>

.method public static a(Landroid/content/Context;Ljava/lang/String;)Ljava/lang/String;
.limit locals 15
.limit stack 200
  nop
  new java/lang/NoClassDefFoundError
  dup
  invokespecial java/lang/NoClassDefFoundError/<init>()V
  athrow
  nop
  ldc "mounted"
  astore_3
  aload_3
  aload_2
  invokevirtual java/lang/String/equals(Ljava/lang/Object;)Z
  istore 4
  iload 4
  invokestatic app/DummyClass/invokeIfStmt(Z)V
  iload 4
  ifeq Label0
  invokestatic android/os/Environment/getExternalStorageDirectory()Ljava/io/File;
  astore 5
  aload 5
  invokevirtual java/io/File/canWrite()Z
  istore 4
  iload 4
  invokestatic app/DummyClass/invokeIfStmt(Z)V
  iload 4
  ifeq Label0
  new java/io/File
  astore 6
  new java/lang/StringBuilder
  astore 7
  invokestatic android/os/Environment/getExternalStorageDirectory()Ljava/io/File;
  astore 5
  aload 5
  invokevirtual java/io/File/getPath()Ljava/lang/String;
  astore_3
  aload_3
  invokestatic java/lang/String/valueOf(Ljava/lang/Object;)Ljava/lang/String;
  astore_3
  aload 7
  aload_3
  invokespecial java/lang/StringBuilder/<init>(Ljava/lang/String;)V
  aload 7
  aload_1
  invokevirtual java/lang/StringBuilder/append(Ljava/lang/String;)Ljava/lang/StringBuilder;
  astore 7
  aload 7
  invokevirtual java/lang/StringBuilder/toString()Ljava/lang/String;
  astore_3
  aload 6
  aload_3
  invokespecial java/io/File/<init>(Ljava/lang/String;)V
  aload 6
  invokevirtual java/io/File/exists()Z
  istore 4
  iload 4
  invokestatic app/DummyClass/invokeIfStmt(Z)V
  iload 4
  ifne Label1
  aload 6
  invokevirtual java/io/File/mkdirs()Z
  pop
  aload 6
  invokevirtual java/io/File/lastModified()J
  lstore 8
  ldc "mobwin"
  astore 11
  iconst_0
  istore 12
  aload_0
  aload 11
  iload 12
  invokevirtual android/content/Context/getSharedPreferences(Ljava/lang/String;I)Landroid/content/SharedPreferences;
  astore 10
  aload 10
  invokeinterface android/content/SharedPreferences/edit()Landroid/content/SharedPreferences$Editor; 1
  astore 13
  ldc "MOBWIN_FILE_CREATE_TIME"
  astore 11
  aload 13
  aload 11
  lload 8
  invokeinterface android/content/SharedPreferences$Editor/putLong(Ljava/lang/String;J)Landroid/content/SharedPreferences$Editor; 4
  pop
  aload 13
  invokeinterface android/content/SharedPreferences$Editor/commit()Z 1
  pop
Label1:
  aload 6
  invokevirtual java/io/File/getAbsolutePath()Ljava/lang/String;
  astore_3
  ldc "/"
  astore 11
  aload_3
  aload 11
  invokevirtual java/lang/String/endsWith(Ljava/lang/String;)Z
  istore 4
  iload 4
  invokestatic app/DummyClass/invokeIfStmt(Z)V
  iload 4
  ifne Label2
  new java/lang/StringBuilder
  astore 7
  aload_3
  invokestatic java/lang/String/valueOf(Ljava/lang/Object;)Ljava/lang/String;
  astore_3
  aload 7
  aload_3
  invokespecial java/lang/StringBuilder/<init>(Ljava/lang/String;)V
  ldc "/"
  astore 11
  aload 7
  aload 11
  invokevirtual java/lang/StringBuilder/append(Ljava/lang/String;)Ljava/lang/StringBuilder;
  astore 7
  aload 7
  invokevirtual java/lang/StringBuilder/toString()Ljava/lang/String;
  astore_3
Label2:
  aload_3
  areturn
Label0:
  aload_0
  invokevirtual android/content/Context/getFilesDir()Ljava/io/File;
  astore 6
  aload 6
  invokevirtual java/io/File/getAbsolutePath()Ljava/lang/String;
  astore_3
  ldc "/"
  astore 11
  aload_3
  aload 11
  invokevirtual java/lang/String/endsWith(Ljava/lang/String;)Z
  istore 4
  iload 4
  invokestatic app/DummyClass/invokeIfStmt(Z)V
  iload 4
  ifeq Label3
  aload_3
  invokevirtual java/lang/String/length()I
  istore 14
  iload 14
  bipush -2
  iadd
  istore 14
  iconst_0
  istore 12
  aload_3
  iload 12
  iload 14
  invokevirtual java/lang/String/substring(II)Ljava/lang/String;
  astore_3
Label3:
  new java/lang/StringBuilder
  astore 7
  aload_3
  invokestatic java/lang/String/valueOf(Ljava/lang/Object;)Ljava/lang/String;
  astore_3
  aload 7
  aload_3
  invokespecial java/lang/StringBuilder/<init>(Ljava/lang/String;)V
  aload 7
  aload_1
  invokevirtual java/lang/StringBuilder/append(Ljava/lang/String;)Ljava/lang/StringBuilder;
  astore 7
  aload 7
  invokevirtual java/lang/StringBuilder/toString()Ljava/lang/String;
  astore_3
  aload_3
  areturn
  nop
.end <method>

.method public static a(JLandroid/content/Context;)V
.limit locals 15
.limit stack 200
  nop
  ldc "mobwin"
  astore 4
  iconst_0
  istore 5
  new java/lang/NoClassDefFoundError
  dup
  invokespecial java/lang/NoClassDefFoundError/<init>()V
  athrow
  nop
  ldc "MOBWIN_FILE_CREATE_TIME"
  astore 4
  ldc2_w 0
  lstore 8
  aload_3
  aload 4
  lload 8
  invokeinterface android/content/SharedPreferences/getLong(Ljava/lang/String;J)J 4
  lstore 6
  invokestatic java/lang/System/currentTimeMillis()J
  lstore 10
  ldc2_w 0
  lstore 8
  lload 6
  lload 8
  lcmp
  istore 12
  dload 12
  invokestatic app/DummyClass/invokeIfStmt(D)V
  iload 12
  ifeq Label0
  ldc2_w 0
  lstore 8
  lload 10
  lload 8
  lcmp
  istore 12
  dload 12
  invokestatic app/DummyClass/invokeIfStmt(D)V
  iload 12
  ifeq Label0
  ldc2_w 0
  lstore 8
  lload_0
  lload 8
  lcmp
  istore 12
  dload 12
  invokestatic app/DummyClass/invokeIfStmt(D)V
  iload 12
  ifeq Label0
  lload 10
  lload 6
  lsub
  lstore 10
  lload 10
  lload_0
  lcmp
  istore 12
  dload 12
  invokestatic app/DummyClass/invokeIfStmt(D)V
  iload 12
  ifle Label0
  ldc "/Tencent/MobWIN/"
  astore 4
  aload_2
  aload 4
  invokestatic com/tencent/mobwin/core/x/a(Landroid/content/Context;Ljava/lang/String;)Ljava/lang/String;
  astore 13
  aload 13
  invokestatic com/tencent/mobwin/core/x/a(Ljava/lang/String;)V
  aload_3
  invokeinterface android/content/SharedPreferences/edit()Landroid/content/SharedPreferences$Editor; 1
  astore 14
  ldc "MOBWIN_FILE_CREATE_TIME"
  astore 4
  ldc2_w 0
  lstore 8
  aload 14
  aload 4
  lload 8
  invokeinterface android/content/SharedPreferences$Editor/putLong(Ljava/lang/String;J)Landroid/content/SharedPreferences$Editor; 4
  pop
  aload 14
  invokeinterface android/content/SharedPreferences$Editor/commit()Z 1
  pop
Label1:
  return
Label0:
  ldc2_w 0
  lstore 8
  lload 6
  lload 8
  lcmp
  istore 12
  dload 12
  invokestatic app/DummyClass/invokeIfStmt(D)V
  iload 12
  ifne Label1
  ldc "/Tencent/MobWIN/"
  astore 4
  aload_2
  aload 4
  invokestatic com/tencent/mobwin/core/x/a(Landroid/content/Context;Ljava/lang/String;)Ljava/lang/String;
  astore 13
  aload 13
  invokestatic com/tencent/mobwin/core/x/a(Ljava/lang/String;)V
  goto Label1
  nop
.end <method>

.method public static a(Landroid/content/Context;[B)V
.limit locals 11
.limit stack 200
  .catch  java/lang/Exception <from> Label4 <to> Label5 <using> Label3
  .catch  java/lang/Exception <from> Label5 <to> Label2 <using> Label6
  .catch  java/lang/Exception <from> Label7 <to> Label8 <using> Label3
  nop
Label4:
  ldc "/Tencent/MobWIN/"
  astore_3
  aload_0
  aload_3
  invokestatic com/tencent/mobwin/core/x/a(Landroid/content/Context;Ljava/lang/String;)Ljava/lang/String;
  astore_2
  new java/lang/StringBuilder
  astore 4
  ldc "saveAdBitmap 1:save bitmap:"
  astore_3
  aload 4
  aload_3
  invokespecial java/lang/StringBuilder/<init>(Ljava/lang/String;)V
  aload 4
  aload_2
  invokevirtual java/lang/StringBuilder/append(Ljava/lang/String;)Ljava/lang/StringBuilder;
  astore 4
  ldc "location.txt"
  astore_3
  aload 4
  aload_3
  invokevirtual java/lang/StringBuilder/append(Ljava/lang/String;)Ljava/lang/StringBuilder;
  astore 4
  aload 4
  invokevirtual java/lang/StringBuilder/toString()Ljava/lang/String;
  astore 5
  ldc "OperateCard:"
  astore_3
  aload_3
  aload 5
  invokestatic com/tencent/mobwin/core/o/a(Ljava/lang/String;Ljava/lang/String;)V
  new java/io/File
  astore 6
  aload 6
  aload_2
  invokespecial java/io/File/<init>(Ljava/lang/String;)V
Label5:
  aload 6
  invokevirtual java/io/File/exists()Z
  istore 7
  new java/lang/NoClassDefFoundError
  dup
  invokespecial java/lang/NoClassDefFoundError/<init>()V
  athrow
  iload 7
  ifne Label0
  aload 6
  invokevirtual java/io/File/mkdirs()Z
  pop
Label0:
  new java/io/File
  astore 6
  ldc "location.txt"
  astore_3
  aload 6
  aload_2
  aload_3
  invokespecial java/io/File/<init>(Ljava/lang/String;Ljava/lang/String;)V
  aload 6
  invokevirtual java/io/File/exists()Z
  istore 7
  iload 7
  invokestatic app/DummyClass/invokeIfStmt(Z)V
  iload 7
  ifeq Label1
  aload 6
  invokevirtual java/io/File/delete()Z
  pop
Label1:
  aload 6
  invokevirtual java/io/File/createNewFile()Z
  pop
  new java/io/FileOutputStream
  astore 8
  aload 8
  aload 6
  invokespecial java/io/FileOutputStream/<init>(Ljava/io/File;)V
  aload 8
  aload_1
  invokevirtual java/io/FileOutputStream/write([B)V
  aload 8
  invokevirtual java/io/FileOutputStream/flush()V
  aload 8
  invokevirtual java/io/FileOutputStream/close()V
Label2:
  return
Label6:
  astore 9
Label7:
  aload 9
  invokevirtual java/lang/Exception/printStackTrace()V
Label8:
  goto Label2
Label3:
  astore 10
  aload 10
  invokevirtual java/lang/Exception/printStackTrace()V
  goto Label2
  nop
.end <method>

.method public static a(Ljava/lang/String;)V
.limit locals 3
.limit stack 200
  .catch  java/lang/Exception <from> Label2 <to> Label0 <using> Label1
  nop
Label2:
  aload_0
  invokestatic com/tencent/mobwin/core/x/b(Ljava/lang/String;)V
  aload_0
  invokevirtual java/lang/String/toString()Ljava/lang/String;
  astore_0
  new java/io/File
  astore_1
  aload_1
  aload_0
  invokespecial java/io/File/<init>(Ljava/lang/String;)V
  aload_1
  invokevirtual java/io/File/delete()Z
  pop
Label0:
  return
Label1:
  astore_2
  aload_2
  invokevirtual java/lang/Exception/printStackTrace()V
  goto Label0
  nop
.end <method>

.method public static a(Ljava/lang/String;Landroid/content/Context;)V
.limit locals 9
.limit stack 200
  .catch  java/lang/Exception <from> Label3 <to> Label1 <using> Label2
  nop
Label3:
  new java/lang/NoClassDefFoundError
  dup
  invokespecial java/lang/NoClassDefFoundError/<init>()V
  athrow
  nop
  ldc "mounted"
  astore 4
  aload_2
  aload 4
  invokevirtual java/lang/String/equals(Ljava/lang/Object;)Z
  istore_3
  iload_3
  invokestatic app/DummyClass/invokeIfStmt(Z)V
  iload_3
  ifeq Label0
  invokestatic android/os/Environment/getExternalStorageDirectory()Ljava/io/File;
  astore 5
  new java/lang/StringBuilder
  astore 6
  aload 6
  invokespecial java/lang/StringBuilder/<init>()V
  aload 6
  aload 5
  invokevirtual java/lang/StringBuilder/append(Ljava/lang/Object;)Ljava/lang/StringBuilder;
  astore 6
  ldc "/Tencent/MobWIN/"
  astore 4
  aload 6
  aload 4
  invokevirtual java/lang/StringBuilder/append(Ljava/lang/String;)Ljava/lang/StringBuilder;
  astore 6
  aload 6
  aload_0
  invokevirtual java/lang/StringBuilder/append(Ljava/lang/String;)Ljava/lang/StringBuilder;
  astore 6
  aload 6
  invokevirtual java/lang/StringBuilder/toString()Ljava/lang/String;
  astore 7
  new java/io/File
  astore 5
  aload 5
  aload 7
  invokespecial java/io/File/<init>(Ljava/lang/String;)V
  aload 5
  invokevirtual java/io/File/exists()Z
  istore_3
  iload_3
  invokestatic app/DummyClass/invokeIfStmt(Z)V
  iload_3
  ifeq Label0
  aload 5
  invokevirtual java/io/File/delete()Z
  pop
Label0:
  aload_1
  invokestatic app/DummyClass/invokeIfStmt(Ljava/lang/Object;)V
  iload_1
  ifeq Label1
  aload_1
  invokevirtual android/content/Context/getFilesDir()Ljava/io/File;
  astore 5
  aload 5
  invokevirtual java/io/File/getAbsolutePath()Ljava/lang/String;
  astore 7
  new java/lang/StringBuilder
  astore 6
  aload 7
  invokestatic java/lang/String/valueOf(Ljava/lang/Object;)Ljava/lang/String;
  astore 7
  aload 6
  aload 7
  invokespecial java/lang/StringBuilder/<init>(Ljava/lang/String;)V
  ldc "/Tencent/MobWIN/"
  astore 4
  aload 6
  aload 4
  invokevirtual java/lang/StringBuilder/append(Ljava/lang/String;)Ljava/lang/StringBuilder;
  astore 6
  aload 6
  aload_0
  invokevirtual java/lang/StringBuilder/append(Ljava/lang/String;)Ljava/lang/StringBuilder;
  astore 6
  aload 6
  invokevirtual java/lang/StringBuilder/toString()Ljava/lang/String;
  astore 7
  new java/io/File
  astore 5
  aload 5
  aload 7
  invokespecial java/io/File/<init>(Ljava/lang/String;)V
  aload 5
  invokevirtual java/io/File/exists()Z
  istore_3
  iload_3
  invokestatic app/DummyClass/invokeIfStmt(Z)V
  iload_3
  ifeq Label1
  aload 5
  invokevirtual java/io/File/delete()Z
  pop
Label1:
  return
Label2:
  astore 8
  aload 8
  invokevirtual java/lang/Exception/printStackTrace()V
  goto Label1
  nop
.end <method>

.method public static a(Ljava/lang/String;[BLandroid/content/Context;)V
.limit locals 18
.limit stack 200
  .catch  java/lang/Exception <from> Label4 <to> Label5 <using> Label3
  .catch  java/lang/Exception <from> Label5 <to> Label2 <using> Label6
  .catch  java/lang/Exception <from> Label7 <to> Label8 <using> Label3
  nop
Label4:
  ldc "/Tencent/MobWIN/"
  astore 5
  aload_2
  astore_3
  aload_3
  aload 5
  invokestatic com/tencent/mobwin/core/x/a(Landroid/content/Context;Ljava/lang/String;)Ljava/lang/String;
  astore 4
  new java/lang/StringBuilder
  astore 6
  ldc "saveAdBitmap 1:save bitmap:"
  astore 5
  aload 6
  aload 5
  invokespecial java/lang/StringBuilder/<init>(Ljava/lang/String;)V
  aload 6
  aload 4
  invokevirtual java/lang/StringBuilder/append(Ljava/lang/String;)Ljava/lang/StringBuilder;
  astore 6
  aload 6
  aload_0
  invokevirtual java/lang/StringBuilder/append(Ljava/lang/String;)Ljava/lang/StringBuilder;
  astore 6
  aload 6
  invokevirtual java/lang/StringBuilder/toString()Ljava/lang/String;
  astore 7
  ldc "OperateCard:"
  astore 5
  aload 5
  aload 7
  invokestatic com/tencent/mobwin/core/o/a(Ljava/lang/String;Ljava/lang/String;)V
  new java/io/File
  astore 8
  aload 8
  aload 4
  invokespecial java/io/File/<init>(Ljava/lang/String;)V
Label5:
  aload 8
  invokevirtual java/io/File/exists()Z
  istore 9
  new java/lang/NoClassDefFoundError
  dup
  invokespecial java/lang/NoClassDefFoundError/<init>()V
  athrow
  iload 9
  ifne Label0
  aload 8
  invokevirtual java/io/File/mkdirs()Z
  pop
  aload 8
  invokevirtual java/io/File/lastModified()J
  lstore 10
  ldc "mobwin"
  astore 5
  iconst_0
  istore 13
  aload_2
  astore_3
  aload_3
  aload 5
  iload 13
  invokevirtual android/content/Context/getSharedPreferences(Ljava/lang/String;I)Landroid/content/SharedPreferences;
  astore 12
  aload 12
  invokeinterface android/content/SharedPreferences/edit()Landroid/content/SharedPreferences$Editor; 1
  astore 14
  ldc "MOBWIN_FILE_CREATE_TIME"
  astore 5
  aload 14
  aload 5
  lload 10
  invokeinterface android/content/SharedPreferences$Editor/putLong(Ljava/lang/String;J)Landroid/content/SharedPreferences$Editor; 4
  pop
  aload 14
  invokeinterface android/content/SharedPreferences$Editor/commit()Z 1
  pop
Label0:
  new java/io/File
  astore 8
  aload 8
  aload 4
  aload_0
  invokespecial java/io/File/<init>(Ljava/lang/String;Ljava/lang/String;)V
  aload 8
  invokevirtual java/io/File/exists()Z
  istore 9
  iload 9
  invokestatic app/DummyClass/invokeIfStmt(Z)V
  iload 9
  ifeq Label1
  aload 8
  invokevirtual java/io/File/delete()Z
  pop
Label1:
  aload 8
  invokevirtual java/io/File/createNewFile()Z
  pop
  new java/io/FileOutputStream
  astore 15
  aload 15
  aload 8
  invokespecial java/io/FileOutputStream/<init>(Ljava/io/File;)V
  aload_1
  astore_3
  aload 15
  aload_3
  invokevirtual java/io/FileOutputStream/write([B)V
  aload 15
  invokevirtual java/io/FileOutputStream/flush()V
  aload 15
  invokevirtual java/io/FileOutputStream/close()V
Label2:
  return
Label6:
  astore 16
Label7:
  aload 16
  invokevirtual java/lang/Exception/printStackTrace()V
Label8:
  goto Label2
Label3:
  astore 17
  aload 17
  invokevirtual java/lang/Exception/printStackTrace()V
  goto Label2
  nop
.end <method>

.method public static a(Landroid/content/Context;)[B
.limit locals 16
.limit stack 200
  .catch  java/lang/Exception <from> Label2 <to> Label3 <using> Label1
  .catch  java/lang/Exception <from> Label6 <to> Label7 <using> Label1
  .catch  java/lang/Exception <from> Label8 <to> Label9 <using> Label1
  nop
  new java/lang/StringBuilder
  astore_1
Label2:
  ldc "/Tencent/MobWIN/"
  astore_3
  aload_0
  aload_3
  invokestatic com/tencent/mobwin/core/x/a(Landroid/content/Context;Ljava/lang/String;)Ljava/lang/String;
  astore_2
  aload_2
  invokestatic java/lang/String/valueOf(Ljava/lang/Object;)Ljava/lang/String;
  astore_2
  aload_1
  aload_2
  invokespecial java/lang/StringBuilder/<init>(Ljava/lang/String;)V
  ldc "location.txt"
  astore_3
  aload_1
  aload_3
  invokevirtual java/lang/StringBuilder/append(Ljava/lang/String;)Ljava/lang/StringBuilder;
  astore_1
  aload_1
  invokevirtual java/lang/StringBuilder/toString()Ljava/lang/String;
  astore 4
  new java/lang/StringBuilder
  astore_1
  ldc "readAdBitmap 1:read bitmap:"
  astore_3
  aload_1
  aload_3
  invokespecial java/lang/StringBuilder/<init>(Ljava/lang/String;)V
  aload_1
  aload 4
  invokevirtual java/lang/StringBuilder/append(Ljava/lang/String;)Ljava/lang/StringBuilder;
  astore_1
  aload_1
  invokevirtual java/lang/StringBuilder/toString()Ljava/lang/String;
  astore_2
  ldc "OperateCard:"
  astore_3
  aload_3
  aload_2
  invokestatic com/tencent/mobwin/core/o/a(Ljava/lang/String;Ljava/lang/String;)V
  new java/io/File
  astore 5
  aload 5
  aload 4
  invokespecial java/io/File/<init>(Ljava/lang/String;)V
  aload 5
  invokevirtual java/io/File/exists()Z
  istore 6
Label3:
  new java/lang/NoClassDefFoundError
  dup
  invokespecial java/lang/NoClassDefFoundError/<init>()V
  athrow
  iload 6
  ifne Label0
  aconst_null
  astore 7
  aload 7
  areturn
Label0:
  aconst_null
  astore 7
  aload 7
  astore 9
  aload 9
  checkcast [B
  astore 9
  aload 9
  astore 8
  new java/io/DataInputStream
  astore 10
  new java/io/FileInputStream
  astore 11
Label6:
  aload 11
  aload 5
  invokespecial java/io/FileInputStream/<init>(Ljava/io/File;)V
  aload 10
  aload 11
  invokespecial java/io/DataInputStream/<init>(Ljava/io/InputStream;)V
  aload 10
  invokevirtual java/io/DataInputStream/available()I
  istore 12
  iload 12
  newarray byte
  astore 8
  aload 10
  aload 8
  invokevirtual java/io/DataInputStream/read([B)I
  pop
  aload 10
  invokevirtual java/io/DataInputStream/close()V
Label7:
  aload 8
  areturn
Label5:
  astore 13
Label8:
  aload 13
  invokevirtual java/io/FileNotFoundException/printStackTrace()V
  aconst_null
  astore 7
  aload 7
  areturn
Label4:
  astore 14
  aload 14
  invokevirtual java/io/IOException/printStackTrace()V
Label9:
  aload 8
  areturn
Label1:
  astore 15
  aload 15
  invokevirtual java/lang/Exception/printStackTrace()V
  aconst_null
  astore 7
  aload 7
  areturn
  nop
.end <method>

.method public static b(Ljava/lang/String;)V
.limit locals 9
.limit stack 200
  nop
  new java/io/File
  astore_1
  aload_1
  aload_0
  invokespecial java/io/File/<init>(Ljava/lang/String;)V
  aload_1
  invokevirtual java/io/File/exists()Z
  istore_2
  new java/lang/NoClassDefFoundError
  dup
  invokespecial java/lang/NoClassDefFoundError/<init>()V
  athrow
  iload_2
  ifne Label0
Label1:
  return
Label0:
  aload_1
  invokevirtual java/io/File/isDirectory()Z
  istore_2
  iload_2
  invokestatic app/DummyClass/invokeIfStmt(Z)V
  iload_2
  ifeq Label1
  aload_1
  invokevirtual java/io/File/list()[Ljava/lang/String;
  astore_3
  iconst_0
  dstore 4
Label5:
  aload_3
  arraylength
  istore 5
  dload 4
  invokestatic app/DummyClass/invokeIfStmt(D)V
  dload 5
  invokestatic app/DummyClass/invokeIfStmt(D)V
  iload 4
  iload 5
  if_icmpge Label1
  getstatic java/io/File/separator Ljava/lang/String;
  astore 6
  aload_0
  aload 6
  invokevirtual java/lang/String/endsWith(Ljava/lang/String;)Z
  istore_2
  iload_2
  invokestatic app/DummyClass/invokeIfStmt(Z)V
  iload_2
  ifeq Label2
  new java/io/File
  astore_1
  new java/lang/StringBuilder
  astore 7
  aload_0
  invokestatic java/lang/String/valueOf(Ljava/lang/Object;)Ljava/lang/String;
  astore 6
  aload 7
  aload 6
  invokespecial java/lang/StringBuilder/<init>(Ljava/lang/String;)V
  aload_3
  iload 4
  aaload
  astore 6
  aload 7
  aload 6
  invokevirtual java/lang/StringBuilder/append(Ljava/lang/String;)Ljava/lang/StringBuilder;
  astore 7
  aload 7
  invokevirtual java/lang/StringBuilder/toString()Ljava/lang/String;
  astore 6
  aload_1
  aload 6
  invokespecial java/io/File/<init>(Ljava/lang/String;)V
Label6:
  aload_1
  invokevirtual java/io/File/isFile()Z
  istore_2
  iload_2
  invokestatic app/DummyClass/invokeIfStmt(Z)V
  iload_2
  ifeq Label3
  aload_1
  invokevirtual java/io/File/delete()Z
  pop
Label3:
  aload_1
  invokevirtual java/io/File/isDirectory()Z
  istore_2
  iload_2
  invokestatic app/DummyClass/invokeIfStmt(Z)V
  iload_2
  ifeq Label4
  new java/lang/StringBuilder
  astore 7
  aload_0
  invokestatic java/lang/String/valueOf(Ljava/lang/Object;)Ljava/lang/String;
  astore 6
  aload 7
  aload 6
  invokespecial java/lang/StringBuilder/<init>(Ljava/lang/String;)V
  ldc "/"
  astore 8
  aload 7
  aload 8
  invokevirtual java/lang/StringBuilder/append(Ljava/lang/String;)Ljava/lang/StringBuilder;
  astore 7
  aload_3
  iload 4
  aaload
  astore 6
  aload 7
  aload 6
  invokevirtual java/lang/StringBuilder/append(Ljava/lang/String;)Ljava/lang/StringBuilder;
  astore 7
  aload 7
  invokevirtual java/lang/StringBuilder/toString()Ljava/lang/String;
  astore 6
  aload 6
  invokestatic com/tencent/mobwin/core/x/b(Ljava/lang/String;)V
  new java/lang/StringBuilder
  astore 7
  aload_0
  invokestatic java/lang/String/valueOf(Ljava/lang/Object;)Ljava/lang/String;
  astore 6
  aload 7
  aload 6
  invokespecial java/lang/StringBuilder/<init>(Ljava/lang/String;)V
  ldc "/"
  astore 8
  aload 7
  aload 8
  invokevirtual java/lang/StringBuilder/append(Ljava/lang/String;)Ljava/lang/StringBuilder;
  astore 7
  aload_3
  iload 4
  aaload
  astore 6
  aload 7
  aload 6
  invokevirtual java/lang/StringBuilder/append(Ljava/lang/String;)Ljava/lang/StringBuilder;
  astore 7
  aload 7
  invokevirtual java/lang/StringBuilder/toString()Ljava/lang/String;
  astore 6
  aload 6
  invokestatic com/tencent/mobwin/core/x/a(Ljava/lang/String;)V
Label4:
  iload 4
  iconst_1
  iadd
  istore 4
  goto Label5
Label2:
  new java/io/File
  astore_1
  new java/lang/StringBuilder
  astore 7
  aload_0
  invokestatic java/lang/String/valueOf(Ljava/lang/Object;)Ljava/lang/String;
  astore 6
  aload 7
  aload 6
  invokespecial java/lang/StringBuilder/<init>(Ljava/lang/String;)V
  getstatic java/io/File/separator Ljava/lang/String;
  astore 6
  aload 7
  aload 6
  invokevirtual java/lang/StringBuilder/append(Ljava/lang/String;)Ljava/lang/StringBuilder;
  astore 7
  aload_3
  iload 4
  aaload
  astore 6
  aload 7
  aload 6
  invokevirtual java/lang/StringBuilder/append(Ljava/lang/String;)Ljava/lang/StringBuilder;
  astore 7
  aload 7
  invokevirtual java/lang/StringBuilder/toString()Ljava/lang/String;
  astore 6
  aload_1
  aload 6
  invokespecial java/io/File/<init>(Ljava/lang/String;)V
  goto Label6
  nop
.end <method>

.method public static b(Ljava/lang/String;Landroid/content/Context;)[B
.limit locals 16
.limit stack 200
  .catch  java/lang/Exception <from> Label2 <to> Label3 <using> Label1
  .catch  java/lang/Exception <from> Label6 <to> Label7 <using> Label1
  .catch  java/lang/Exception <from> Label8 <to> Label9 <using> Label1
  nop
  new java/lang/StringBuilder
  astore_2
Label2:
  ldc "/Tencent/MobWIN/"
  astore 4
  aload_1
  aload 4
  invokestatic com/tencent/mobwin/core/x/a(Landroid/content/Context;Ljava/lang/String;)Ljava/lang/String;
  astore_3
  aload_3
  invokestatic java/lang/String/valueOf(Ljava/lang/Object;)Ljava/lang/String;
  astore_3
  aload_2
  aload_3
  invokespecial java/lang/StringBuilder/<init>(Ljava/lang/String;)V
  aload_2
  aload_0
  invokevirtual java/lang/StringBuilder/append(Ljava/lang/String;)Ljava/lang/StringBuilder;
  astore_2
  aload_2
  invokevirtual java/lang/StringBuilder/toString()Ljava/lang/String;
  astore_0
  new java/lang/StringBuilder
  astore_2
  ldc "readAdBitmap 1:read bitmap:"
  astore 4
  aload_2
  aload 4
  invokespecial java/lang/StringBuilder/<init>(Ljava/lang/String;)V
  aload_2
  aload_0
  invokevirtual java/lang/StringBuilder/append(Ljava/lang/String;)Ljava/lang/StringBuilder;
  astore_2
  aload_2
  invokevirtual java/lang/StringBuilder/toString()Ljava/lang/String;
  astore_3
  ldc "OperateCard:"
  astore 4
  aload 4
  aload_3
  invokestatic com/tencent/mobwin/core/o/a(Ljava/lang/String;Ljava/lang/String;)V
  new java/io/File
  astore 5
  aload 5
  aload_0
  invokespecial java/io/File/<init>(Ljava/lang/String;)V
  aload 5
  invokevirtual java/io/File/exists()Z
  istore 6
Label3:
  new java/lang/NoClassDefFoundError
  dup
  invokespecial java/lang/NoClassDefFoundError/<init>()V
  athrow
  iload 6
  ifne Label0
  aconst_null
  astore 7
  aload 7
  areturn
Label0:
  aconst_null
  astore 7
  aload 7
  astore 9
  aload 9
  checkcast [B
  astore 9
  aload 9
  astore 8
  new java/io/DataInputStream
  astore 10
  new java/io/FileInputStream
  astore 11
Label6:
  aload 11
  aload 5
  invokespecial java/io/FileInputStream/<init>(Ljava/io/File;)V
  aload 10
  aload 11
  invokespecial java/io/DataInputStream/<init>(Ljava/io/InputStream;)V
  aload 10
  invokevirtual java/io/DataInputStream/available()I
  istore 12
  iload 12
  newarray byte
  astore 8
  aload 10
  aload 8
  invokevirtual java/io/DataInputStream/read([B)I
  pop
  aload 10
  invokevirtual java/io/DataInputStream/close()V
Label7:
  aload 8
  areturn
Label5:
  astore 13
Label8:
  aload 13
  invokevirtual java/io/FileNotFoundException/printStackTrace()V
  aconst_null
  astore 7
  aload 7
  areturn
Label4:
  astore 14
  aload 14
  invokevirtual java/io/IOException/printStackTrace()V
Label9:
  aload 8
  areturn
Label1:
  astore 15
  aload 15
  invokevirtual java/lang/Exception/printStackTrace()V
  aconst_null
  astore 7
  aload 7
  areturn
  nop
.end <method>

