.source AdAnimation.java
.class public  com/admogo/anim/AdAnimation
.super java/lang/Object
.field private "animation" Landroid/view/animation/Animation;

.method public <init>()V
.limit locals 1
.limit stack 200
  nop
  aload_0
  invokespecial java/lang/Object/<init>()V
  return
  nop
.end <method>

.method public setAnimation(ID)Landroid/view/animation/Animation;
.limit locals 15
.limit stack 200
  nop
  new java/lang/NoClassDefFoundError
  dup
  invokespecial java/lang/NoClassDefFoundError/<init>()V
  athrow
  iload_1
  lookupswitch
  3 : Label1
  4 : Label2
  5 : Label3
  6 : Label4
  7 : Label5
  default : Label0
Label0:
  goto Label6
Label6:
  new android/view/animation/AlphaAnimation
  astore 4
  ldc 0.100000
  fstore 5
  fconst_1
  fstore 6
  aload 4
  fload 5
  fload 6
  invokespecial android/view/animation/AlphaAnimation/<init>(FF)V
  aload_0
  aload 4
  putfield com/admogo/anim/AdAnimation/animation Landroid/view/animation/Animation;
  aload_0
  getfield com/admogo/anim/AdAnimation/animation Landroid/view/animation/Animation;
  astore 7
  ldc2_w 0
  lstore 8
  aload 7
  lload 8
  invokevirtual android/view/animation/Animation/setDuration(J)V
  aload_0
  getfield com/admogo/anim/AdAnimation/animation Landroid/view/animation/Animation;
  astore 7
  new android/view/animation/AccelerateDecelerateInterpolator
  astore 10
  aload 10
  invokespecial android/view/animation/AccelerateDecelerateInterpolator/<init>()V
  aload 7
  aload 10
  invokevirtual android/view/animation/Animation/setInterpolator(Landroid/view/animation/Interpolator;)V
Label7:
  aload_0
  getfield com/admogo/anim/AdAnimation/animation Landroid/view/animation/Animation;
  astore 7
  aload 7
  areturn
Label5:
  new android/view/animation/AlphaAnimation
  astore 4
  ldc 0.100000
  fstore 5
  fconst_1
  fstore 6
  aload 4
  fload 5
  fload 6
  invokespecial android/view/animation/AlphaAnimation/<init>(FF)V
  aload_0
  aload 4
  putfield com/admogo/anim/AdAnimation/animation Landroid/view/animation/Animation;
  aload_0
  getfield com/admogo/anim/AdAnimation/animation Landroid/view/animation/Animation;
  astore 7
  ldc2_w 400
  lstore 8
  aload 7
  lload 8
  invokevirtual android/view/animation/Animation/setDuration(J)V
  aload_0
  getfield com/admogo/anim/AdAnimation/animation Landroid/view/animation/Animation;
  astore 7
  new android/view/animation/AccelerateDecelerateInterpolator
  astore 10
  aload 10
  invokespecial android/view/animation/AccelerateDecelerateInterpolator/<init>()V
  aload 7
  aload 10
  invokevirtual android/view/animation/Animation/setInterpolator(Landroid/view/animation/Interpolator;)V
  goto Label7
Label4:
  new android/view/animation/TranslateAnimation
  astore 11
  sipush 320
  istore 12
  iload 12
  dload_2
  invokestatic com/admogo/util/AdMogoUtil/convertToScreenPixels(ID)I
  istore_1
  iload_1
  i2f
  fstore 13
  fconst_0
  fstore 5
  fconst_0
  fstore 6
  fconst_0
  fstore 14
  aload 11
  fload 13
  fload 5
  fload 6
  fload 14
  invokespecial android/view/animation/TranslateAnimation/<init>(FFFF)V
  aload_0
  aload 11
  putfield com/admogo/anim/AdAnimation/animation Landroid/view/animation/Animation;
  aload_0
  getfield com/admogo/anim/AdAnimation/animation Landroid/view/animation/Animation;
  astore 7
  ldc2_w 400
  lstore 8
  aload 7
  lload 8
  invokevirtual android/view/animation/Animation/setDuration(J)V
  aload_0
  getfield com/admogo/anim/AdAnimation/animation Landroid/view/animation/Animation;
  astore 7
  new android/view/animation/AccelerateDecelerateInterpolator
  astore 10
  aload 10
  invokespecial android/view/animation/AccelerateDecelerateInterpolator/<init>()V
  aload 7
  aload 10
  invokevirtual android/view/animation/Animation/setInterpolator(Landroid/view/animation/Interpolator;)V
  goto Label7
Label3:
  new android/view/animation/TranslateAnimation
  astore 11
  sipush 320
  istore 12
  iload 12
  dload_2
  invokestatic com/admogo/util/AdMogoUtil/convertToScreenPixels(ID)I
  istore_1
  iload_1
  ineg
  istore_1
  iload_1
  i2f
  fstore 13
  fconst_0
  fstore 5
  fconst_0
  fstore 6
  fconst_0
  fstore 14
  aload 11
  fload 13
  fload 5
  fload 6
  fload 14
  invokespecial android/view/animation/TranslateAnimation/<init>(FFFF)V
  aload_0
  aload 11
  putfield com/admogo/anim/AdAnimation/animation Landroid/view/animation/Animation;
  aload_0
  getfield com/admogo/anim/AdAnimation/animation Landroid/view/animation/Animation;
  astore 7
  ldc2_w 400
  lstore 8
  aload 7
  lload 8
  invokevirtual android/view/animation/Animation/setDuration(J)V
  aload_0
  getfield com/admogo/anim/AdAnimation/animation Landroid/view/animation/Animation;
  astore 7
  new android/view/animation/AccelerateDecelerateInterpolator
  astore 10
  aload 10
  invokespecial android/view/animation/AccelerateDecelerateInterpolator/<init>()V
  aload 7
  aload 10
  invokevirtual android/view/animation/Animation/setInterpolator(Landroid/view/animation/Interpolator;)V
  goto Label7
Label2:
  new android/view/animation/TranslateAnimation
  astore 11
  bipush 50
  istore 12
  iload 12
  dload_2
  invokestatic com/admogo/util/AdMogoUtil/convertToScreenPixels(ID)I
  istore_1
  iload_1
  i2f
  fstore 13
  fconst_0
  fstore 5
  fconst_0
  fstore 6
  fconst_0
  fstore 14
  aload 11
  fload 5
  fload 6
  fload 13
  fload 14
  invokespecial android/view/animation/TranslateAnimation/<init>(FFFF)V
  aload_0
  aload 11
  putfield com/admogo/anim/AdAnimation/animation Landroid/view/animation/Animation;
  aload_0
  getfield com/admogo/anim/AdAnimation/animation Landroid/view/animation/Animation;
  astore 7
  ldc2_w 400
  lstore 8
  aload 7
  lload 8
  invokevirtual android/view/animation/Animation/setDuration(J)V
  aload_0
  getfield com/admogo/anim/AdAnimation/animation Landroid/view/animation/Animation;
  astore 7
  new android/view/animation/AccelerateDecelerateInterpolator
  astore 10
  aload 10
  invokespecial android/view/animation/AccelerateDecelerateInterpolator/<init>()V
  aload 7
  aload 10
  invokevirtual android/view/animation/Animation/setInterpolator(Landroid/view/animation/Interpolator;)V
  goto Label7
Label1:
  new android/view/animation/TranslateAnimation
  astore 11
  bipush 50
  istore 12
  iload 12
  dload_2
  invokestatic com/admogo/util/AdMogoUtil/convertToScreenPixels(ID)I
  istore_1
  iload_1
  ineg
  istore_1
  iload_1
  i2f
  fstore 13
  fconst_0
  fstore 5
  fconst_0
  fstore 6
  fconst_0
  fstore 14
  aload 11
  fload 5
  fload 6
  fload 13
  fload 14
  invokespecial android/view/animation/TranslateAnimation/<init>(FFFF)V
  aload_0
  aload 11
  putfield com/admogo/anim/AdAnimation/animation Landroid/view/animation/Animation;
  aload_0
  getfield com/admogo/anim/AdAnimation/animation Landroid/view/animation/Animation;
  astore 7
  ldc2_w 400
  lstore 8
  aload 7
  lload 8
  invokevirtual android/view/animation/Animation/setDuration(J)V
  aload_0
  getfield com/admogo/anim/AdAnimation/animation Landroid/view/animation/Animation;
  astore 7
  new android/view/animation/AccelerateDecelerateInterpolator
  astore 10
  aload 10
  invokespecial android/view/animation/AccelerateDecelerateInterpolator/<init>()V
  aload 7
  aload 10
  invokevirtual android/view/animation/Animation/setInterpolator(Landroid/view/animation/Interpolator;)V
  goto Label7
  nop
  nop
  nop
.end <method>

