.source SourceFile
.class  com/mobisage/android/SNSSSLSocketFactory$a
.super java/lang/Object
.field final "a" Lcom/mobisage/android/l;

.method private <init>(Lcom/mobisage/android/l;)V
.limit locals 2
.limit stack 200
  nop
  aload_0
  aload_1
  putfield com/mobisage/android/SNSSSLSocketFactory$a/a Lcom/mobisage/android/l;
  aload_0
  invokespecial java/lang/Object/<init>()V
  return
  nop
.end <method>

.method <init>(Lcom/mobisage/android/l;B)V
  .synthetic
.limit locals 3
.limit stack 200
  nop
  aload_0
  aload_1
  invokespecial com/mobisage/android/SNSSSLSocketFactory$a/<init>(Lcom/mobisage/android/l;)V
  return
  nop
.end <method>

.method public static a(Ljava/io/File;)Ljava/lang/String;
.limit locals 9
.limit stack 200
  .catch  java/lang/Exception <from> Label3 <to> Label4 <using> Label2
  nop
  new java/io/FileReader
  astore_1
Label3:
  aload_1
  aload_0
  invokespecial java/io/FileReader/<init>(Ljava/io/File;)V
  new java/lang/StringBuffer
  astore_2
  aload_2
  invokespecial java/lang/StringBuffer/<init>()V
  sipush 1024
  istore 4
  iload 4
  newarray char
  astore_3
Label1:
  aload_1
  aload_3
  invokevirtual java/io/FileReader/read([C)I
  istore 5
  new java/lang/NoClassDefFoundError
  dup
  invokespecial java/lang/NoClassDefFoundError/<init>()V
  athrow
  iconst_m1
  istore 4
  iload 5
  iload 4
  if_icmpeq Label0
  iconst_0
  istore 4
  aload_2
  aload_3
  iload 4
  iload 5
  invokevirtual java/lang/StringBuffer/append([CII)Ljava/lang/StringBuffer;
  pop
  goto Label1
Label2:
  astore 6
  aconst_null
  astore 7
  aload 7
  areturn
Label0:
  aload_1
  invokevirtual java/io/FileReader/close()V
  aload_2
  invokevirtual java/lang/StringBuffer/toString()Ljava/lang/String;
  astore 8
Label4:
  aload 8
  areturn
  nop
.end <method>

.method public a()V
.limit locals 2
.limit stack 200
  nop
  aload_0
  getfield com/mobisage/android/SNSSSLSocketFactory$a/a Lcom/mobisage/android/l;
  astore_1
  new java/lang/NoClassDefFoundError
  dup
  invokespecial java/lang/NoClassDefFoundError/<init>()V
  athrow
  nop
  aload_1
  invokevirtual com/mobisage/android/l/onLoadAdFinish()V
  return
  nop
.end <method>

.method public static a(Ljava/io/File;Ljava/lang/String;)V
.limit locals 5
.limit stack 200
  .catch  java/lang/Exception <from> Label3 <to> Label1 <using> Label2
  nop
Label3:
  aload_0
  invokevirtual java/io/File/exists()Z
  istore_2
  new java/lang/NoClassDefFoundError
  dup
  invokespecial java/lang/NoClassDefFoundError/<init>()V
  athrow
  iload_2
  ifeq Label0
  aload_0
  invokevirtual java/io/File/delete()Z
  pop
Label0:
  aload_0
  invokevirtual java/io/File/createNewFile()Z
  pop
  new java/io/FileWriter
  astore_3
  aload_3
  aload_0
  invokespecial java/io/FileWriter/<init>(Ljava/io/File;)V
  aload_3
  aload_1
  invokevirtual java/io/FileWriter/write(Ljava/lang/String;)V
  aload_3
  invokevirtual java/io/FileWriter/close()V
Label1:
  return
Label2:
  astore 4
  goto Label1
  nop
.end <method>

.method public static a(Ljava/lang/String;Ljava/util/LinkedList;)Z
  .signature_attr "(Ljava/lang/String;Ljava/util/LinkedList<Ljava/lang/String;>;)Z"
.limit locals 10
.limit stack 200
  nop
  ldc "/*cache begin*/"
  astore_3
  aload_0
  aload_3
  invokevirtual java/lang/String/indexOf(Ljava/lang/String;)I
  istore_2
  ldc "/*cache end*/"
  astore_3
  aload_0
  aload_3
  invokevirtual java/lang/String/indexOf(Ljava/lang/String;)I
  istore 4
  new java/lang/NoClassDefFoundError
  dup
  invokespecial java/lang/NoClassDefFoundError/<init>()V
  athrow
  iconst_m1
  istore 5
  iload_2
  iload 5
  if_icmpeq Label0
  dload 4
  invokestatic app/DummyClass/invokeIfStmt(D)V
  iconst_m1
  istore 5
  iload 4
  iload 5
  if_icmpeq Label0
  iload_2
  bipush 15
  iadd
  istore 6
  dload 6
  invokestatic app/DummyClass/invokeIfStmt(D)V
  dload 4
  invokestatic app/DummyClass/invokeIfStmt(D)V
  iload 6
  iload 4
  if_icmple Label1
Label0:
  iconst_1
  istore 5
  iload 5
  ireturn
Label1:
  iload_2
  bipush 15
  iadd
  istore 6
  aload_0
  iload 6
  iload 4
  invokevirtual java/lang/String/substring(II)Ljava/lang/String;
  astore 7
  new org/json/JSONArray
  astore 8
Label4:
  aload 8
  aload 7
  invokespecial org/json/JSONArray/<init>(Ljava/lang/String;)V
  iconst_0
  dstore 5
  dload 5
  dstore 6
Label2:
  aload 8
  invokevirtual org/json/JSONArray/length()I
  istore 4
  dload 6
  invokestatic app/DummyClass/invokeIfStmt(D)V
  dload 4
  invokestatic app/DummyClass/invokeIfStmt(D)V
  iload 6
  iload 4
  if_icmpge Label0
  aload 8
  iload 6
  invokevirtual org/json/JSONArray/getString(I)Ljava/lang/String;
  astore 7
  aload_1
  aload 7
  invokevirtual java/util/LinkedList/add(Ljava/lang/Object;)Z
  pop
Label5:
  iload 6
  iconst_1
  iadd
  istore 6
  goto Label2
Label3:
  astore 9
  iconst_0
  istore 5
  iload 5
  ireturn
  nop
.end <method>

.method public static a(Ljava/security/MessageDigest;Ljava/lang/String;Ljava/lang/StringBuilder;Ljava/lang/StringBuilder;)Z
.limit locals 19
.limit stack 200
  .catch  java/security/NoSuchAlgorithmException <from> Label6 <to> Label7 <using> Label5
  nop
Label6:
  ldc "MD5"
  astore 5
  aload 5
  invokestatic java/security/MessageDigest/getInstance(Ljava/lang/String;)Ljava/security/MessageDigest;
  astore_0
  aload_0
  invokevirtual java/security/MessageDigest/reset()V
  ldc "UTF-8"
  astore 5
  aload_1
  astore 4
  new java/lang/NoClassDefFoundError
  dup
  invokespecial java/lang/NoClassDefFoundError/<init>()V
  athrow
  nop
  aload_0
  aload 6
  invokevirtual java/security/MessageDigest/digest([B)[B
  astore 6
  new java/lang/StringBuilder
  astore 7
  aload 6
  arraylength
  istore 8
  iload 8
  iconst_1
  ishl
  istore 8
  aload 7
  iload 8
  invokespecial java/lang/StringBuilder/<init>(I)V
  iconst_0
  dstore 9
Label1:
  aload 6
  arraylength
  istore 8
  dload 9
  invokestatic app/DummyClass/invokeIfStmt(D)V
  dload 8
  invokestatic app/DummyClass/invokeIfStmt(D)V
  iload 9
  iload 8
  if_icmpge Label0
  aload 6
  iload 9
  baload
  istore 10
  sipush 240
  istore 12
  iload 10
  iload 12
  iand
  istore 11
  iconst_4
  istore 12
  iload 11
  iload 12
  ishr
  istore 11
  bipush 16
  istore 12
  iload 11
  iload 12
  invokestatic java/lang/Character/forDigit(II)C
  istore 13
  aload 7
  iload 13
  invokevirtual java/lang/StringBuilder/append(C)Ljava/lang/StringBuilder;
  pop
  aload 6
  iload 9
  baload
  istore 10
  bipush 15
  istore 12
  iload 10
  iload 12
  iand
  istore 10
  bipush 16
  istore 12
  iload 10
  iload 12
  invokestatic java/lang/Character/forDigit(II)C
  istore 13
  aload 7
  iload 13
  invokevirtual java/lang/StringBuilder/append(C)Ljava/lang/StringBuilder;
  pop
  iload 9
  iconst_1
  iadd
  istore 9
  goto Label1
Label0:
  aload 7
  invokevirtual java/lang/StringBuilder/toString()Ljava/lang/String;
  astore 14
  invokestatic android/os/Environment/getExternalStorageState()Ljava/lang/String;
  astore_1
  ldc "unmounted"
  astore 15
  aload_1
  astore 4
  aload 15
  aload 4
  invokevirtual java/lang/String/equals(Ljava/lang/Object;)Z
  istore 16
  iload 16
  invokestatic app/DummyClass/invokeIfStmt(Z)V
  iload 16
  ifne Label2
  ldc "mounted_ro"
  astore 15
  aload_1
  astore 4
  aload 15
  aload 4
  invokevirtual java/lang/String/equals(Ljava/lang/Object;)Z
  istore 16
  iload 16
  invokestatic app/DummyClass/invokeIfStmt(Z)V
  iload 16
  ifne Label2
  ldc "unmountable"
  astore 15
  aload_1
  astore 4
  aload 15
  aload 4
  invokevirtual java/lang/String/equals(Ljava/lang/Object;)Z
  istore 16
  iload 16
  invokestatic app/DummyClass/invokeIfStmt(Z)V
  iload 16
  ifne Label2
  ldc "removed"
  astore 15
  aload_1
  astore 4
  aload 15
  aload 4
  invokevirtual java/lang/String/equals(Ljava/lang/Object;)Z
  istore 16
  iload 16
  invokestatic app/DummyClass/invokeIfStmt(Z)V
  iload 16
  ifne Label2
  ldc "bad_removal"
  astore 15
  aload_1
  astore 4
  aload 15
  aload 4
  invokevirtual java/lang/String/equals(Ljava/lang/Object;)Z
  istore 16
  iload 16
  invokestatic app/DummyClass/invokeIfStmt(Z)V
  iload 16
  ifne Label2
  ldc "nofs"
  astore 15
  aload_1
  astore 4
  aload 15
  aload 4
  invokevirtual java/lang/String/equals(Ljava/lang/Object;)Z
  istore 16
  iload 16
  invokestatic app/DummyClass/invokeIfStmt(Z)V
  iload 16
  ifne Label2
  ldc "shared"
  astore 15
  aload_1
  astore 4
  aload 15
  aload 4
  invokevirtual java/lang/String/equals(Ljava/lang/Object;)Z
  istore 16
  iload 16
  invokestatic app/DummyClass/invokeIfStmt(Z)V
  iload 16
  ifeq Label3
Label2:
  new java/lang/StringBuilder
  astore 7
  aload 7
  invokespecial java/lang/StringBuilder/<init>()V
  getstatic com/mobisage/android/r/e Ljava/lang/String;
  astore 15
  aload 7
  aload 15
  invokevirtual java/lang/StringBuilder/append(Ljava/lang/String;)Ljava/lang/StringBuilder;
  astore 7
  ldc "/MobiSage"
  astore 5
  aload 7
  aload 5
  invokevirtual java/lang/StringBuilder/append(Ljava/lang/String;)Ljava/lang/StringBuilder;
  astore 7
  ldc "/Cache"
  astore 5
  aload 7
  aload 5
  invokevirtual java/lang/StringBuilder/append(Ljava/lang/String;)Ljava/lang/StringBuilder;
  astore 7
  ldc "/"
  astore 5
  aload 7
  aload 5
  invokevirtual java/lang/StringBuilder/append(Ljava/lang/String;)Ljava/lang/StringBuilder;
  astore 7
  aload 7
  aload 14
  invokevirtual java/lang/StringBuilder/append(Ljava/lang/String;)Ljava/lang/StringBuilder;
  astore 7
  aload 7
  invokevirtual java/lang/StringBuilder/toString()Ljava/lang/String;
  astore 15
  aload_2
  astore 4
  aload 4
  aload 15
  invokevirtual java/lang/StringBuilder/append(Ljava/lang/String;)Ljava/lang/StringBuilder;
  pop
  new java/lang/StringBuilder
  astore 7
  aload 7
  invokespecial java/lang/StringBuilder/<init>()V
  getstatic com/mobisage/android/r/e Ljava/lang/String;
  astore 15
  aload 7
  aload 15
  invokevirtual java/lang/StringBuilder/append(Ljava/lang/String;)Ljava/lang/StringBuilder;
  astore 7
  ldc "/MobiSage"
  astore 5
  aload 7
  aload 5
  invokevirtual java/lang/StringBuilder/append(Ljava/lang/String;)Ljava/lang/StringBuilder;
  astore 7
  ldc "/Temp"
  astore 5
  aload 7
  aload 5
  invokevirtual java/lang/StringBuilder/append(Ljava/lang/String;)Ljava/lang/StringBuilder;
  astore 7
  ldc "/"
  astore 5
  aload 7
  aload 5
  invokevirtual java/lang/StringBuilder/append(Ljava/lang/String;)Ljava/lang/StringBuilder;
  astore 7
  aload 7
  aload 14
  invokevirtual java/lang/StringBuilder/append(Ljava/lang/String;)Ljava/lang/StringBuilder;
  astore 7
  aload 7
  invokevirtual java/lang/StringBuilder/toString()Ljava/lang/String;
  astore 15
  aload_3
  astore 4
  aload 4
  aload 15
  invokevirtual java/lang/StringBuilder/append(Ljava/lang/String;)Ljava/lang/StringBuilder;
  pop
Label4:
  new java/io/File
  astore 17
  aload_2
  astore 4
  aload 4
  invokevirtual java/lang/StringBuilder/toString()Ljava/lang/String;
  astore 15
  aload 17
  aload 15
  invokespecial java/io/File/<init>(Ljava/lang/String;)V
  aload 17
  invokevirtual java/io/File/getParentFile()Ljava/io/File;
  astore 17
  aload 17
  invokevirtual java/io/File/mkdirs()Z
  pop
  new java/io/File
  astore 17
  aload_3
  astore 4
  aload 4
  invokevirtual java/lang/StringBuilder/toString()Ljava/lang/String;
  astore 15
  aload 17
  aload 15
  invokespecial java/io/File/<init>(Ljava/lang/String;)V
  aload 17
  invokevirtual java/io/File/getParentFile()Ljava/io/File;
  astore 17
  aload 17
  invokevirtual java/io/File/mkdirs()Z
  pop
  iconst_1
  istore 12
  iload 12
  ireturn
Label3:
  invokestatic android/os/Environment/getExternalStorageDirectory()Ljava/io/File;
  astore 17
  new java/lang/StringBuilder
  astore 7
  aload 7
  invokespecial java/lang/StringBuilder/<init>()V
  aload 17
  invokevirtual java/io/File/getAbsolutePath()Ljava/lang/String;
  astore 15
  aload 7
  aload 15
  invokevirtual java/lang/StringBuilder/append(Ljava/lang/String;)Ljava/lang/StringBuilder;
  astore 7
  ldc "/MobiSage"
  astore 5
  aload 7
  aload 5
  invokevirtual java/lang/StringBuilder/append(Ljava/lang/String;)Ljava/lang/StringBuilder;
  astore 7
  ldc "/Cache"
  astore 5
  aload 7
  aload 5
  invokevirtual java/lang/StringBuilder/append(Ljava/lang/String;)Ljava/lang/StringBuilder;
  astore 7
  ldc "/"
  astore 5
  aload 7
  aload 5
  invokevirtual java/lang/StringBuilder/append(Ljava/lang/String;)Ljava/lang/StringBuilder;
  astore 7
  aload 7
  aload 14
  invokevirtual java/lang/StringBuilder/append(Ljava/lang/String;)Ljava/lang/StringBuilder;
  astore 7
  aload 7
  invokevirtual java/lang/StringBuilder/toString()Ljava/lang/String;
  astore 15
  aload_2
  astore 4
  aload 4
  aload 15
  invokevirtual java/lang/StringBuilder/append(Ljava/lang/String;)Ljava/lang/StringBuilder;
  pop
  new java/lang/StringBuilder
  astore 7
  aload 7
  invokespecial java/lang/StringBuilder/<init>()V
  aload 17
  invokevirtual java/io/File/getAbsolutePath()Ljava/lang/String;
  astore 15
  aload 7
  aload 15
  invokevirtual java/lang/StringBuilder/append(Ljava/lang/String;)Ljava/lang/StringBuilder;
  astore 7
  ldc "/MobiSage"
  astore 5
  aload 7
  aload 5
  invokevirtual java/lang/StringBuilder/append(Ljava/lang/String;)Ljava/lang/StringBuilder;
  astore 7
  ldc "/Temp"
  astore 5
  aload 7
  aload 5
  invokevirtual java/lang/StringBuilder/append(Ljava/lang/String;)Ljava/lang/StringBuilder;
  astore 7
  ldc "/"
  astore 5
  aload 7
  aload 5
  invokevirtual java/lang/StringBuilder/append(Ljava/lang/String;)Ljava/lang/StringBuilder;
  astore 7
  aload 7
  aload 14
  invokevirtual java/lang/StringBuilder/append(Ljava/lang/String;)Ljava/lang/StringBuilder;
  astore 7
  aload 7
  invokevirtual java/lang/StringBuilder/toString()Ljava/lang/String;
  astore 15
  aload_3
  astore 4
  aload 4
  aload 15
  invokevirtual java/lang/StringBuilder/append(Ljava/lang/String;)Ljava/lang/StringBuilder;
  pop
Label7:
  goto Label4
Label5:
  astore 18
  iconst_0
  istore 12
  iload 12
  ireturn
  nop
.end <method>

.method public static b(Ljava/lang/String;Ljava/util/LinkedList;)Z
  .signature_attr "(Ljava/lang/String;Ljava/util/LinkedList<Ljava/lang/String;>;)Z"
.limit locals 13
.limit stack 200
  nop
  ldc "/*ad_datas_begin*/"
  astore_3
  aload_0
  aload_3
  invokevirtual java/lang/String/indexOf(Ljava/lang/String;)I
  istore_2
  ldc "/*ad_datas_end*/"
  astore_3
  aload_0
  aload_3
  invokevirtual java/lang/String/indexOf(Ljava/lang/String;)I
  istore 4
  new java/lang/NoClassDefFoundError
  dup
  invokespecial java/lang/NoClassDefFoundError/<init>()V
  athrow
  iconst_m1
  istore 5
  iload_2
  iload 5
  if_icmpeq Label0
  dload 4
  invokestatic app/DummyClass/invokeIfStmt(D)V
  iconst_m1
  istore 5
  iload 4
  iload 5
  if_icmpeq Label0
  iload_2
  bipush 18
  iadd
  istore 6
  dload 6
  invokestatic app/DummyClass/invokeIfStmt(D)V
  dload 4
  invokestatic app/DummyClass/invokeIfStmt(D)V
  iload 6
  iload 4
  if_icmple Label1
Label0:
  iconst_1
  istore 5
  iload 5
  ireturn
Label1:
  iload_2
  bipush 18
  iadd
  istore 6
  aload_0
  iload 6
  iload 4
  invokevirtual java/lang/String/substring(II)Ljava/lang/String;
  astore 7
  new org/json/JSONArray
  astore 8
Label7:
  aload 8
  aload 7
  invokespecial org/json/JSONArray/<init>(Ljava/lang/String;)V
  iconst_0
  dstore 5
  dload 5
  dstore 6
Label5:
  aload 8
  invokevirtual org/json/JSONArray/length()I
  istore 4
  dload 6
  invokestatic app/DummyClass/invokeIfStmt(D)V
  dload 4
  invokestatic app/DummyClass/invokeIfStmt(D)V
  iload 6
  iload 4
  if_icmpge Label0
  aload 8
  iload 6
  invokevirtual org/json/JSONArray/getJSONObject(I)Lorg/json/JSONObject;
  astore 9
  ldc "cache_items"
  astore_3
  aload 9
  aload_3
  invokevirtual org/json/JSONObject/getJSONArray(Ljava/lang/String;)Lorg/json/JSONArray;
  astore 10
  aload 10
  invokestatic app/DummyClass/invokeIfStmt(Ljava/lang/Object;)V
  aload 10
  ifnull Label2
  iconst_0
  dstore 5
  dload 5
  dstore 4
Label4:
  aload 10
  invokevirtual org/json/JSONArray/length()I
  istore_2
  dload 4
  invokestatic app/DummyClass/invokeIfStmt(D)V
  dload_2
  invokestatic app/DummyClass/invokeIfStmt(D)V
  iload 4
  iload_2
  if_icmpge Label2
  aload 10
  iload 4
  invokevirtual org/json/JSONArray/getString(I)Ljava/lang/String;
  astore 7
  aload 9
  aload 7
  invokevirtual org/json/JSONObject/has(Ljava/lang/String;)Z
  istore 11
  iload 11
  invokestatic app/DummyClass/invokeIfStmt(Z)V
  iload 11
  ifeq Label3
  aload 9
  aload 7
  invokevirtual org/json/JSONObject/getString(Ljava/lang/String;)Ljava/lang/String;
  astore 7
  aload_1
  aload 7
  invokevirtual java/util/LinkedList/add(Ljava/lang/Object;)Z
  pop
Label3:
  iload 4
  iconst_1
  iadd
  istore 4
  goto Label4
Label2:
  iload 6
  iconst_1
  iadd
  istore 6
  goto Label5
Label6:
  astore 12
  iconst_0
  istore 5
  iload 5
  ireturn
  nop
.end <method>

