.source dalvik_source_VirusShare_32e70f448ebd75661a1cb12f9cd8e013.apk
.class public  com/google/ads/AdRequest
.super java/lang/Object
.field public static final "LOGTAG" Ljava/lang/String; =  "Ads"
.field public static final "TEST_EMULATOR" Ljava/lang/String;
.field public static final "VERSION" Ljava/lang/String; =  "4.1.1"
.field private "a" Lcom/google/ads/AdRequest$Gender;
.field private "b" Ljava/lang/String;
.field private "c" Ljava/util/Set;
.field private "d" Ljava/util/Map;
.field private "e" Landroid/location/Location;
.field private "f" Z
.field private "g" Z
.field private "h" Ljava/util/Set;

.method static <clinit>()V
.limit locals 2
.limit stack 200
  nop
  ldc "emulator"
  astore_1
  aload_1
  invokestatic com/google/ads/util/AdUtil/a(Ljava/lang/String;)Ljava/lang/String;
  astore_0
  aload_0
  putstatic com/google/ads/AdRequest/TEST_EMULATOR Ljava/lang/String;
  return
  nop
.end <method>

.method public <init>()V
.limit locals 3
.limit stack 200
  nop
  aload_0
  invokespecial java/lang/Object/<init>()V
  aconst_null
  astore_1
  aload_0
  aload_1
  putfield com/google/ads/AdRequest/a Lcom/google/ads/AdRequest$Gender;
  aconst_null
  astore_1
  aload_0
  aload_1
  putfield com/google/ads/AdRequest/b Ljava/lang/String;
  aconst_null
  astore_1
  aload_0
  aload_1
  putfield com/google/ads/AdRequest/c Ljava/util/Set;
  aconst_null
  astore_1
  aload_0
  aload_1
  putfield com/google/ads/AdRequest/d Ljava/util/Map;
  aconst_null
  astore_1
  aload_0
  aload_1
  putfield com/google/ads/AdRequest/e Landroid/location/Location;
  iconst_0
  istore_2
  aload_0
  iload_2
  putfield com/google/ads/AdRequest/f Z
  iconst_0
  istore_2
  aload_0
  iload_2
  putfield com/google/ads/AdRequest/g Z
  aconst_null
  astore_1
  aload_0
  aload_1
  putfield com/google/ads/AdRequest/h Ljava/util/Set;
  return
  nop
.end <method>

.method public addExtra(Ljava/lang/String;Ljava/lang/Object;)V
.limit locals 5
.limit stack 200
  nop
  aload_0
  getfield com/google/ads/AdRequest/d Ljava/util/Map;
  astore_3
  new java/lang/NoClassDefFoundError
  dup
  invokespecial java/lang/NoClassDefFoundError/<init>()V
  athrow
  iload_3
  ifne Label0
  new java/util/HashMap
  astore 4
  aload 4
  invokespecial java/util/HashMap/<init>()V
  aload_0
  aload 4
  putfield com/google/ads/AdRequest/d Ljava/util/Map;
Label0:
  aload_0
  getfield com/google/ads/AdRequest/d Ljava/util/Map;
  astore_3
  aload_3
  aload_1
  aload_2
  invokeinterface java/util/Map/put(Ljava/lang/Object;Ljava/lang/Object;)Ljava/lang/Object; 3
  pop
  return
  nop
.end <method>

.method public addKeyword(Ljava/lang/String;)V
.limit locals 4
.limit stack 200
  nop
  aload_0
  getfield com/google/ads/AdRequest/c Ljava/util/Set;
  astore_2
  new java/lang/NoClassDefFoundError
  dup
  invokespecial java/lang/NoClassDefFoundError/<init>()V
  athrow
  iload_2
  ifne Label0
  new java/util/HashSet
  astore_3
  aload_3
  invokespecial java/util/HashSet/<init>()V
  aload_0
  aload_3
  putfield com/google/ads/AdRequest/c Ljava/util/Set;
Label0:
  aload_0
  getfield com/google/ads/AdRequest/c Ljava/util/Set;
  astore_2
  aload_2
  aload_1
  invokeinterface java/util/Set/add(Ljava/lang/Object;)Z 2
  pop
  return
  nop
.end <method>

.method public addTestDevice(Ljava/lang/String;)V
.limit locals 4
.limit stack 200
  nop
  aload_0
  getfield com/google/ads/AdRequest/h Ljava/util/Set;
  astore_2
  new java/lang/NoClassDefFoundError
  dup
  invokespecial java/lang/NoClassDefFoundError/<init>()V
  athrow
  iload_2
  ifne Label0
  new java/util/HashSet
  astore_3
  aload_3
  invokespecial java/util/HashSet/<init>()V
  aload_0
  aload_3
  putfield com/google/ads/AdRequest/h Ljava/util/Set;
Label0:
  aload_0
  getfield com/google/ads/AdRequest/h Ljava/util/Set;
  astore_2
  aload_2
  aload_1
  invokeinterface java/util/Set/add(Ljava/lang/Object;)Z 2
  pop
  return
  nop
.end <method>

.method public getRequestMap(Landroid/content/Context;)Ljava/util/Map;
  .signature_attr "(Landroid/content/Context;)Ljava/util/Map<Ljava/lang/String;Ljava/lang/Object;>;"
.limit locals 16
.limit stack 200
  nop
  new java/util/HashMap
  astore_2
  aload_2
  invokespecial java/util/HashMap/<init>()V
  aload_0
  getfield com/google/ads/AdRequest/c Ljava/util/Set;
  astore_3
  new java/lang/NoClassDefFoundError
  dup
  invokespecial java/lang/NoClassDefFoundError/<init>()V
  athrow
  iload_3
  ifeq Label0
  aload_0
  getfield com/google/ads/AdRequest/c Ljava/util/Set;
  astore_3
  ldc "kw"
  astore 4
  aload_2
  aload 4
  aload_3
  invokeinterface java/util/Map/put(Ljava/lang/Object;Ljava/lang/Object;)Ljava/lang/Object; 3
  pop
Label0:
  aload_0
  getfield com/google/ads/AdRequest/a Lcom/google/ads/AdRequest$Gender;
  astore 5
  aload 5
  invokestatic app/DummyClass/invokeIfStmt(Ljava/lang/Object;)V
  aload 5
  ifnull Label1
  aload_0
  getfield com/google/ads/AdRequest/a Lcom/google/ads/AdRequest$Gender;
  astore 5
  aload 5
  invokevirtual com/google/ads/AdRequest$Gender/toString()Ljava/lang/String;
  astore 6
  ldc "cust_gender"
  astore 4
  aload_2
  aload 4
  aload 6
  invokeinterface java/util/Map/put(Ljava/lang/Object;Ljava/lang/Object;)Ljava/lang/Object; 3
  pop
Label1:
  aload_0
  getfield com/google/ads/AdRequest/b Ljava/lang/String;
  astore 7
  aload 7
  invokestatic app/DummyClass/invokeIfStmt(Ljava/lang/Object;)V
  aload 7
  ifnull Label2
  aload_0
  getfield com/google/ads/AdRequest/b Ljava/lang/String;
  astore 6
  ldc "cust_age"
  astore 4
  aload_2
  aload 4
  aload 6
  invokeinterface java/util/Map/put(Ljava/lang/Object;Ljava/lang/Object;)Ljava/lang/Object; 3
  pop
Label2:
  aload_0
  getfield com/google/ads/AdRequest/e Landroid/location/Location;
  astore 8
  aload 8
  invokestatic app/DummyClass/invokeIfStmt(Ljava/lang/Object;)V
  aload 8
  ifnull Label3
  aload_0
  getfield com/google/ads/AdRequest/e Landroid/location/Location;
  astore 8
  aload 8
  invokestatic com/google/ads/util/AdUtil/a(Landroid/location/Location;)Ljava/lang/String;
  astore 6
  ldc "uule"
  astore 4
  aload_2
  aload 4
  aload 6
  invokeinterface java/util/Map/put(Ljava/lang/Object;Ljava/lang/Object;)Ljava/lang/Object; 3
  pop
Label3:
  aload_0
  getfield com/google/ads/AdRequest/f Z
  istore 9
  iload 9
  invokestatic app/DummyClass/invokeIfStmt(Z)V
  iload 9
  ifeq Label4
  iconst_1
  istore 11
  iload 11
  istore 10
  iload 10
  invokestatic java/lang/Integer/valueOf(I)Ljava/lang/Integer;
  astore 12
  ldc "testing"
  astore 4
  aload_2
  aload 4
  aload 12
  invokeinterface java/util/Map/put(Ljava/lang/Object;Ljava/lang/Object;)Ljava/lang/Object; 3
  pop
Label4:
  aload_0
  aload_1
  invokevirtual com/google/ads/AdRequest/isTestDevice(Landroid/content/Context;)Z
  istore 9
  iload 9
  invokestatic app/DummyClass/invokeIfStmt(Z)V
  iload 9
  ifeq Label5
  ldc "adtest"
  astore 4
  ldc "on"
  astore 13
  aload_2
  aload 4
  aload 13
  invokeinterface java/util/Map/put(Ljava/lang/Object;Ljava/lang/Object;)Ljava/lang/Object; 3
  pop
Label7:
  aload_0
  getfield com/google/ads/AdRequest/d Ljava/util/Map;
  astore 14
  aload 14
  invokestatic app/DummyClass/invokeIfStmt(Ljava/lang/Object;)V
  aload 14
  ifnull Label6
  aload_0
  getfield com/google/ads/AdRequest/d Ljava/util/Map;
  astore 14
  ldc "extras"
  astore 4
  aload_2
  aload 4
  aload 14
  invokeinterface java/util/Map/put(Ljava/lang/Object;Ljava/lang/Object;)Ljava/lang/Object; 3
  pop
Label6:
  aload_2
  areturn
Label5:
  aload_0
  getfield com/google/ads/AdRequest/g Z
  istore 9
  iload 9
  invokestatic app/DummyClass/invokeIfStmt(Z)V
  iload 9
  ifne Label7
  invokestatic com/google/ads/util/AdUtil/c()Z
  istore 9
  iload 9
  invokestatic app/DummyClass/invokeIfStmt(Z)V
  iload 9
  ifeq Label8
  ldc "AdRequest.TEST_EMULATOR"
  astore 7
Label9:
  new java/lang/StringBuilder
  astore 15
  aload 15
  invokespecial java/lang/StringBuilder/<init>()V
  ldc "To get test ads on this device, call adRequest.addTestDevice("
  astore 4
  aload 15
  aload 4
  invokevirtual java/lang/StringBuilder/append(Ljava/lang/String;)Ljava/lang/StringBuilder;
  astore 15
  aload 15
  aload 7
  invokevirtual java/lang/StringBuilder/append(Ljava/lang/String;)Ljava/lang/StringBuilder;
  astore 15
  ldc ");"
  astore 4
  aload 15
  aload 4
  invokevirtual java/lang/StringBuilder/append(Ljava/lang/String;)Ljava/lang/StringBuilder;
  astore 15
  aload 15
  invokevirtual java/lang/StringBuilder/toString()Ljava/lang/String;
  astore 7
  aload 7
  invokestatic com/google/ads/util/a/c(Ljava/lang/String;)V
  iconst_1
  istore 11
  aload_0
  iload 11
  putfield com/google/ads/AdRequest/g Z
  goto Label7
Label8:
  new java/lang/StringBuilder
  astore 15
  aload 15
  invokespecial java/lang/StringBuilder/<init>()V
  ldc "\""
  astore 4
  aload 15
  aload 4
  invokevirtual java/lang/StringBuilder/append(Ljava/lang/String;)Ljava/lang/StringBuilder;
  astore 15
  aload_1
  invokestatic com/google/ads/util/AdUtil/a(Landroid/content/Context;)Ljava/lang/String;
  astore 7
  aload 15
  aload 7
  invokevirtual java/lang/StringBuilder/append(Ljava/lang/String;)Ljava/lang/StringBuilder;
  astore 15
  ldc "\""
  astore 4
  aload 15
  aload 4
  invokevirtual java/lang/StringBuilder/append(Ljava/lang/String;)Ljava/lang/StringBuilder;
  astore 15
  aload 15
  invokevirtual java/lang/StringBuilder/toString()Ljava/lang/String;
  astore 7
  goto Label9
  nop
.end <method>

.method public isTestDevice(Landroid/content/Context;)Z
.limit locals 6
.limit stack 200
  nop
  aload_0
  getfield com/google/ads/AdRequest/h Ljava/util/Set;
  astore_2
  new java/lang/NoClassDefFoundError
  dup
  invokespecial java/lang/NoClassDefFoundError/<init>()V
  athrow
  iload_2
  ifeq Label0
  aload_1
  invokestatic com/google/ads/util/AdUtil/a(Landroid/content/Context;)Ljava/lang/String;
  astore_3
  aload_3
  invokestatic app/DummyClass/invokeIfStmt(Ljava/lang/Object;)V
  aload_3
  ifnonnull Label1
Label0:
  iconst_0
  istore 4
  iload 4
  ireturn
Label1:
  aload_0
  getfield com/google/ads/AdRequest/h Ljava/util/Set;
  astore_2
  aload_2
  aload_3
  invokeinterface java/util/Set/contains(Ljava/lang/Object;)Z 2
  istore 5
  iload 5
  invokestatic app/DummyClass/invokeIfStmt(Z)V
  iload 5
  ifeq Label0
  iconst_1
  istore 4
  iload 4
  ireturn
  nop
.end <method>

.method public setBirthday(Ljava/lang/String;)V
.limit locals 2
.limit stack 200
  nop
  aload_0
  aload_1
  putfield com/google/ads/AdRequest/b Ljava/lang/String;
  return
  nop
.end <method>

.method public setExtras(Ljava/util/Map;)V
  .signature_attr "(Ljava/util/Map<Ljava/lang/String;Ljava/lang/Object;>;)V"
.limit locals 2
.limit stack 200
  nop
  aload_0
  aload_1
  putfield com/google/ads/AdRequest/d Ljava/util/Map;
  return
  nop
.end <method>

.method public setGender(Lcom/google/ads/AdRequest$Gender;)V
.limit locals 2
.limit stack 200
  nop
  aload_0
  aload_1
  putfield com/google/ads/AdRequest/a Lcom/google/ads/AdRequest$Gender;
  return
  nop
.end <method>

.method public setKeywords(Ljava/util/Set;)V
  .signature_attr "(Ljava/util/Set<Ljava/lang/String;>;)V"
.limit locals 2
.limit stack 200
  nop
  aload_0
  aload_1
  putfield com/google/ads/AdRequest/c Ljava/util/Set;
  return
  nop
.end <method>

.method public setLocation(Landroid/location/Location;)V
.limit locals 2
.limit stack 200
  nop
  aload_0
  aload_1
  putfield com/google/ads/AdRequest/e Landroid/location/Location;
  return
  nop
.end <method>

.method public setTestDevices(Ljava/util/Set;)V
  .signature_attr "(Ljava/util/Set<Ljava/lang/String;>;)V"
.limit locals 2
.limit stack 200
  nop
  aload_0
  aload_1
  putfield com/google/ads/AdRequest/h Ljava/util/Set;
  return
  nop
.end <method>

.method public setTesting(Z)V
.limit locals 2
.limit stack 200
  nop
  aload_0
  iload_1
  putfield com/google/ads/AdRequest/f Z
  return
  nop
.end <method>

