.source dalvik_source_VirusShare_32e70f448ebd75661a1cb12f9cd8e013.apk
.class public  com/wiyun/ad/ab
.super java/lang/Object
.field private static "a" Landroid/content/Context;
.field private static "b" Ljava/lang/ref/WeakReference;
.field private static "c" Ljava/lang/String;
.field private static "d" Ljava/lang/String;
.field private static "e" Landroid/location/Location;
.field private static "f" Ljava/lang/String;
.field private static "g" Ljava/lang/String;
.field private static "h" Ljava/lang/String;
.field private static "i" I =  0
.field private static "j" Ljava/lang/String;
.field private static "k" Ljava/lang/String;
.field private static "l" Ljava/lang/String;
.field private static "m" Ljava/lang/String;
.field private static "n" Ljava/lang/String;
.field private static "o" Ljava/lang/String;
.field private static "p" Ljava/lang/String;
.field private static "q" I =  0
.field private static "r" I =  0
.field private static "s" I =  0
.field private static "t" I =  0
.field private static "u" I =  0

.method static <clinit>()V
.limit locals 2
.limit stack 200
  nop
  iconst_m1
  istore_0
  iload_0
  putstatic com/wiyun/ad/ab/i I
  ldc ""
  astore_1
  aload_1
  putstatic com/wiyun/ad/ab/j Ljava/lang/String;
  ldc ""
  astore_1
  aload_1
  putstatic com/wiyun/ad/ab/k Ljava/lang/String;
  ldc ""
  astore_1
  aload_1
  putstatic com/wiyun/ad/ab/l Ljava/lang/String;
  return
  nop
.end <method>

.method public <init>()V
.limit locals 1
.limit stack 200
  nop
  aload_0
  invokespecial java/lang/Object/<init>()V
  return
  nop
.end <method>

.method private static A()V
.limit locals 9
.limit stack 200
  nop
  getstatic com/wiyun/ad/ab/g Ljava/lang/String;
  astore_0
  new java/lang/NoClassDefFoundError
  dup
  invokespecial java/lang/NoClassDefFoundError/<init>()V
  athrow
  nop
  iload_1
  invokestatic app/DummyClass/invokeIfStmt(Z)V
  iload_1
  ifeq Label0
  getstatic com/wiyun/ad/ab/a Landroid/content/Context;
  astore_2
  aload_2
  invokestatic app/DummyClass/invokeIfStmt(Ljava/lang/Object;)V
  aload_2
  ifnull Label0
  ldc "android.permission.READ_PHONE_STATE"
  astore 4
  aload_2
  aload 4
  invokevirtual android/content/Context/checkCallingOrSelfPermission(Ljava/lang/String;)I
  istore_3
  dload_3
  invokestatic app/DummyClass/invokeIfStmt(D)V
  iconst_m1
  istore 5
  iload_3
  iload 5
  if_icmpeq Label0
  ldc "phone"
  astore 4
  aload_2
  aload 4
  invokevirtual android/content/Context/getSystemService(Ljava/lang/String;)Ljava/lang/Object;
  astore 6
  aload 6
  astore 8
  aload 8
  checkcast android/telephony/TelephonyManager
  astore 8
  aload 8
  astore 7
  aload 7
  invokestatic app/DummyClass/invokeIfStmt(Ljava/lang/Object;)V
  aload 7
  ifnull Label0
  aload 7
  invokevirtual android/telephony/TelephonyManager/getDeviceId()Ljava/lang/String;
  astore_0
  aload_0
  putstatic com/wiyun/ad/ab/g Ljava/lang/String;
Label0:
  return
  nop
.end <method>

.method private static B()V
.limit locals 15
.limit stack 200
  nop
  getstatic com/wiyun/ad/ab/h Ljava/lang/String;
  astore_0
  new java/lang/NoClassDefFoundError
  dup
  invokespecial java/lang/NoClassDefFoundError/<init>()V
  athrow
  nop
  iload_1
  invokestatic app/DummyClass/invokeIfStmt(Z)V
  iload_1
  ifeq Label0
  getstatic com/wiyun/ad/ab/a Landroid/content/Context;
  astore_2
  new java/lang/StringBuilder
  astore_3
  aload_3
  invokespecial java/lang/StringBuilder/<init>()V
  getstatic com/wiyun/ad/ab/g Ljava/lang/String;
  astore_0
  aload_3
  aload_0
  invokevirtual java/lang/StringBuilder/append(Ljava/lang/String;)Ljava/lang/StringBuilder;
  pop
  aload_2
  invokevirtual android/content/Context/getContentResolver()Landroid/content/ContentResolver;
  astore 4
  ldc "android_id"
  astore 5
  aload 4
  aload 5
  invokestatic android/provider/Settings$Secure/getString(Landroid/content/ContentResolver;Ljava/lang/String;)Ljava/lang/String;
  astore_0
  aload_3
  aload_0
  invokevirtual java/lang/StringBuilder/append(Ljava/lang/String;)Ljava/lang/StringBuilder;
  pop
  aload_2
  invokevirtual android/content/Context/getResources()Landroid/content/res/Resources;
  astore 6
  aload 6
  invokevirtual android/content/res/Resources/getDisplayMetrics()Landroid/util/DisplayMetrics;
  astore 7
  aload 7
  getfield android/util/DisplayMetrics/density F
  fstore 8
  aload_3
  fload 8
  invokevirtual java/lang/StringBuilder/append(F)Ljava/lang/StringBuilder;
  pop
  ldc "android.permission.ACCESS_WIFI_STATE"
  astore 5
  aload_2
  aload 5
  invokevirtual android/content/Context/checkCallingOrSelfPermission(Ljava/lang/String;)I
  istore 9
  dload 9
  invokestatic app/DummyClass/invokeIfStmt(D)V
  iload 9
  ifne Label1
  ldc "wifi"
  astore 5
  aload_2
  aload 5
  invokevirtual android/content/Context/getSystemService(Ljava/lang/String;)Ljava/lang/Object;
  astore 10
  aload 10
  astore 12
  aload 12
  checkcast android/net/wifi/WifiManager
  astore 12
  aload 12
  astore 11
  aload 11
  invokestatic app/DummyClass/invokeIfStmt(Ljava/lang/Object;)V
  aload 11
  ifnull Label2
  aload 11
  invokevirtual android/net/wifi/WifiManager/getConnectionInfo()Landroid/net/wifi/WifiInfo;
  astore 13
  aload 13
  invokestatic app/DummyClass/invokeIfStmt(Ljava/lang/Object;)V
  aload 13
  ifnull Label2
  aload 13
  invokevirtual android/net/wifi/WifiInfo/getMacAddress()Ljava/lang/String;
  astore_0
  aload_3
  aload_0
  invokevirtual java/lang/StringBuilder/append(Ljava/lang/String;)Ljava/lang/StringBuilder;
  pop
Label2:
  aload_3
  invokevirtual java/lang/StringBuilder/toString()Ljava/lang/String;
  astore_0
  aload_0
  invokestatic com/wiyun/ad/ae/b(Ljava/lang/String;)[B
  astore 14
  aload 14
  invokestatic com/wiyun/ad/x/a([B)Ljava/lang/String;
  astore_0
  aload_0
  putstatic com/wiyun/ad/ab/h Ljava/lang/String;
Label0:
  return
Label1:
  ldc "00:00:00:00:00:00"
  astore 5
  aload_3
  aload 5
  invokevirtual java/lang/StringBuilder/append(Ljava/lang/String;)Ljava/lang/StringBuilder;
  pop
  goto Label2
  nop
.end <method>

.method private static C()Z
.limit locals 7
.limit stack 200
  nop
  getstatic com/wiyun/ad/ab/a Landroid/content/Context;
  astore_0
  new java/lang/NoClassDefFoundError
  dup
  invokespecial java/lang/NoClassDefFoundError/<init>()V
  athrow
  iload_0
  ifne Label0
  iconst_0
  istore_1
  iload_1
  ireturn
Label0:
  ldc "sensor"
  astore_3
  aload_0
  aload_3
  invokevirtual android/content/Context/getSystemService(Ljava/lang/String;)Ljava/lang/Object;
  astore_2
  aload_2
  astore 5
  aload 5
  checkcast android/hardware/SensorManager
  astore 5
  aload 5
  astore 4
  aload 4
  invokestatic app/DummyClass/invokeIfStmt(Ljava/lang/Object;)V
  aload 4
  ifnonnull Label1
  iconst_0
  istore_1
  iload_1
  ireturn
Label1:
  iconst_2
  istore_1
  aload 4
  iload_1
  invokevirtual android/hardware/SensorManager/getDefaultSensor(I)Landroid/hardware/Sensor;
  astore 6
  aload 6
  invokestatic app/DummyClass/invokeIfStmt(Ljava/lang/Object;)V
  aload 6
  ifnull Label2
  iconst_1
  istore_1
  iload_1
  ireturn
Label2:
  iconst_0
  istore_1
  iload_1
  ireturn
  nop
.end <method>

.method private static D()V
.limit locals 11
.limit stack 200
  nop
  iconst_0
  istore_0
  getstatic com/wiyun/ad/ab/i I
  istore_1
  new java/lang/NoClassDefFoundError
  dup
  invokespecial java/lang/NoClassDefFoundError/<init>()V
  athrow
  iconst_m1
  istore_2
  iload_1
  iload_2
  if_icmpne Label0
  getstatic com/wiyun/ad/ab/g Ljava/lang/String;
  astore_3
  getstatic android/os/Build/FINGERPRINT Ljava/lang/String;
  astore 4
  ldc "generic"
  astore 6
  aload 4
  aload 6
  invokevirtual java/lang/String/startsWith(Ljava/lang/String;)Z
  istore 5
  ldc "sdk"
  astore 4
  getstatic android/os/Build/MODEL Ljava/lang/String;
  astore 7
  aload 4
  aload 7
  invokevirtual java/lang/String/equalsIgnoreCase(Ljava/lang/String;)Z
  istore 8
  invokestatic com/wiyun/ad/ab/C()Z
  istore 9
  aload_3
  invokestatic android/text/TextUtils/isEmpty(Ljava/lang/CharSequence;)Z
  istore 10
  iload 10
  invokestatic app/DummyClass/invokeIfStmt(Z)V
  iload 10
  ifne Label1
  aload_3
  invokestatic com/wiyun/ad/ab/a(Ljava/lang/String;)Z
  istore 10
  iload 10
  invokestatic app/DummyClass/invokeIfStmt(Z)V
  iload 10
  ifeq Label1
  bipush 30
  istore_1
Label7:
  iload 5
  invokestatic app/DummyClass/invokeIfStmt(Z)V
  iload 5
  ifne Label2
  iload_1
  bipush 30
  iadd
  istore_1
Label2:
  iload 8
  invokestatic app/DummyClass/invokeIfStmt(Z)V
  iload 8
  ifne Label3
  iload_1
  bipush 20
  iadd
  istore_1
Label3:
  iload 9
  invokestatic app/DummyClass/invokeIfStmt(Z)V
  iload 9
  ifeq Label4
  iload_1
  bipush 50
  iadd
  istore_1
Label4:
  dload_1
  invokestatic app/DummyClass/invokeIfStmt(D)V
  bipush 50
  istore_2
  iload_1
  iload_2
  if_icmplt Label5
Label6:
  iload_0
  putstatic com/wiyun/ad/ab/i I
Label0:
  return
Label5:
  iconst_1
  istore_0
  goto Label6
Label1:
  iconst_0
  istore_1
  goto Label7
  nop
.end <method>

.method private static E()V
.limit locals 8
.limit stack 200
  nop
  getstatic com/wiyun/ad/ab/j Ljava/lang/String;
  astore_0
  new java/lang/NoClassDefFoundError
  dup
  invokespecial java/lang/NoClassDefFoundError/<init>()V
  athrow
  nop
  iload_1
  invokestatic app/DummyClass/invokeIfStmt(Z)V
  iload_1
  ifeq Label0
  getstatic com/wiyun/ad/ab/a Landroid/content/Context;
  astore_2
  aload_2
  invokestatic app/DummyClass/invokeIfStmt(Ljava/lang/Object;)V
  aload_2
  ifnonnull Label1
  ldc ""
  astore_3
  aload_3
  putstatic com/wiyun/ad/ab/j Ljava/lang/String;
Label0:
  return
Label1:
  getstatic com/wiyun/ad/ab/a Landroid/content/Context;
  astore_2
  aload_2
  invokevirtual android/content/Context/getResources()Landroid/content/res/Resources;
  astore 4
  aload 4
  invokevirtual android/content/res/Resources/getConfiguration()Landroid/content/res/Configuration;
  astore 5
  aload 5
  getfield android/content/res/Configuration/mcc I
  istore 6
  iload 6
  bipush 100
  imul
  istore 6
  aload 5
  getfield android/content/res/Configuration/mnc I
  istore 7
  iload 7
  iload 6
  iadd
  istore 7
  iload 7
  invokestatic java/lang/String/valueOf(I)Ljava/lang/String;
  astore_0
  aload_0
  putstatic com/wiyun/ad/ab/j Ljava/lang/String;
  goto Label0
  nop
.end <method>

.method private static F()Z
.limit locals 10
.limit stack 200
  nop
  getstatic com/wiyun/ad/ab/a Landroid/content/Context;
  astore_0
  ldc "android.permission.ACCESS_WIFI_STATE"
  astore_2
  new java/lang/NoClassDefFoundError
  dup
  invokespecial java/lang/NoClassDefFoundError/<init>()V
  athrow
  nop
  dload_1
  invokestatic app/DummyClass/invokeIfStmt(D)V
  iload_1
  ifne Label0
  getstatic com/wiyun/ad/ab/a Landroid/content/Context;
  astore_0
  ldc "wifi"
  astore_2
  aload_0
  aload_2
  invokevirtual android/content/Context/getSystemService(Ljava/lang/String;)Ljava/lang/Object;
  astore_3
  aload_3
  astore 5
  aload 5
  checkcast android/net/wifi/WifiManager
  astore 5
  aload 5
  astore 4
  aload 4
  invokestatic app/DummyClass/invokeIfStmt(Ljava/lang/Object;)V
  aload 4
  ifnull Label1
  aload 4
  invokevirtual android/net/wifi/WifiManager/getConnectionInfo()Landroid/net/wifi/WifiInfo;
  astore 6
  aload 6
  invokestatic app/DummyClass/invokeIfStmt(Ljava/lang/Object;)V
  aload 6
  ifnull Label2
  aload 6
  invokevirtual android/net/wifi/WifiInfo/getSupplicantState()Landroid/net/wifi/SupplicantState;
  astore 7
  getstatic android/net/wifi/SupplicantState/COMPLETED Landroid/net/wifi/SupplicantState;
  astore 8
  aload 7
  invokestatic app/DummyClass/invokeIfStmt(Ljava/lang/Object;)V
  aload 8
  invokestatic app/DummyClass/invokeIfStmt(Ljava/lang/Object;)V
  aload 7
  aload 8
  if_acmpne Label2
  iconst_1
  istore 9
  iload 9
  ireturn
Label2:
  iconst_0
  istore 9
  iload 9
  ireturn
Label1:
  iconst_0
  istore 9
  iload 9
  ireturn
Label0:
  iconst_0
  istore 9
  iload 9
  ireturn
  nop
.end <method>

.method public static a()I
.limit locals 1
.limit stack 200
  nop
  getstatic com/wiyun/ad/ab/s I
  istore_0
  iload_0
  ireturn
  nop
.end <method>

.method static a(Landroid/content/Context;)V
.limit locals 6
.limit stack 200
  nop
  getstatic com/wiyun/ad/ab/a Landroid/content/Context;
  astore_1
  new java/lang/NoClassDefFoundError
  dup
  invokespecial java/lang/NoClassDefFoundError/<init>()V
  athrow
  iload_1
  ifne Label0
  aload_0
  invokevirtual android/content/Context/getApplicationContext()Landroid/content/Context;
  astore_1
  aload_1
  putstatic com/wiyun/ad/ab/a Landroid/content/Context;
  aload_0
  instanceof android/app/Activity
  istore_2
  iload_2
  invokestatic app/DummyClass/invokeIfStmt(Z)V
  iload_2
  ifeq Label1
  new java/lang/ref/WeakReference
  astore_3
  aload_0
  astore 5
  aload 5
  checkcast android/app/Activity
  astore 5
  aload 5
  astore 4
  aload_3
  aload 4
  invokespecial java/lang/ref/WeakReference/<init>(Ljava/lang/Object;)V
  aload_3
  putstatic com/wiyun/ad/ab/b Ljava/lang/ref/WeakReference;
Label1:
  invokestatic com/wiyun/ad/ab/v()V
  invokestatic com/wiyun/ad/ab/x()V
  invokestatic com/wiyun/ad/ab/y()V
  invokestatic com/wiyun/ad/ab/E()V
  invokestatic com/wiyun/ad/ab/A()V
  invokestatic com/wiyun/ad/ab/D()V
  invokestatic com/wiyun/ad/ab/B()V
  invokestatic com/wiyun/ad/ab/z()V
  invokestatic com/wiyun/ad/ab/w()V
  invokestatic com/wiyun/ad/ab/r()V
  invokestatic com/wiyun/ad/ab/s()V
  invokestatic com/wiyun/ad/ab/u()V
  invokestatic com/wiyun/ad/ab/t()V
Label0:
  return
  nop
.end <method>

.method private static a(Ljava/lang/String;)Z
.limit locals 5
.limit stack 200
  nop
  new java/lang/NoClassDefFoundError
  dup
  invokespecial java/lang/NoClassDefFoundError/<init>()V
  athrow
  iload_0
  ifne Label0
Label1:
  iconst_0
  istore_1
  iload_1
  ireturn
Label0:
  aload_0
  invokevirtual java/lang/String/length()I
  istore_2
  iconst_0
  dstore_3
Label3:
  dload_3
  invokestatic app/DummyClass/invokeIfStmt(D)V
  dload_2
  invokestatic app/DummyClass/invokeIfStmt(D)V
  iload_3
  iload_2
  if_icmpge Label1
  aload_0
  iload_3
  invokevirtual java/lang/String/charAt(I)C
  istore 4
  dload 4
  invokestatic app/DummyClass/invokeIfStmt(D)V
  bipush 48
  istore_1
  iload 4
  iload_1
  if_icmpeq Label2
  iconst_1
  istore_1
  iload_1
  ireturn
Label2:
  iload_3
  iconst_1
  iadd
  istore_3
  goto Label3
  nop
.end <method>

.method public static b()I
.limit locals 1
.limit stack 200
  nop
  getstatic com/wiyun/ad/ab/t I
  istore_0
  iload_0
  ireturn
  nop
.end <method>

.method public static c()I
.limit locals 1
.limit stack 200
  nop
  getstatic com/wiyun/ad/ab/u I
  istore_0
  iload_0
  ireturn
  nop
.end <method>

.method public static d()Ljava/lang/String;
.limit locals 1
.limit stack 200
  nop
  getstatic com/wiyun/ad/ab/m Ljava/lang/String;
  astore_0
  aload_0
  areturn
  nop
.end <method>

.method public static e()Ljava/lang/String;
.limit locals 1
.limit stack 200
  nop
  getstatic com/wiyun/ad/ab/n Ljava/lang/String;
  astore_0
  aload_0
  areturn
  nop
.end <method>

.method public static f()I
.limit locals 1
.limit stack 200
  nop
  getstatic com/wiyun/ad/ab/q I
  istore_0
  iload_0
  ireturn
  nop
.end <method>

.method public static g()Ljava/lang/String;
.limit locals 1
.limit stack 200
  nop
  getstatic com/wiyun/ad/ab/d Ljava/lang/String;
  astore_0
  aload_0
  areturn
  nop
.end <method>

.method public static h()Ljava/lang/String;
.limit locals 1
.limit stack 200
  nop
  getstatic com/wiyun/ad/ab/f Ljava/lang/String;
  astore_0
  aload_0
  areturn
  nop
.end <method>

.method static i()Ljava/lang/String;
.limit locals 1
.limit stack 200
  nop
  getstatic com/wiyun/ad/ab/h Ljava/lang/String;
  astore_0
  aload_0
  areturn
  nop
.end <method>

.method public static j()I
.limit locals 1
.limit stack 200
  nop
  getstatic com/wiyun/ad/ab/r I
  istore_0
  iload_0
  ireturn
  nop
.end <method>

.method public static k()Ljava/lang/String;
.limit locals 1
.limit stack 200
  nop
  getstatic com/wiyun/ad/ab/o Ljava/lang/String;
  astore_0
  aload_0
  areturn
  nop
.end <method>

.method public static l()Ljava/lang/String;
.limit locals 1
.limit stack 200
  nop
  getstatic com/wiyun/ad/ab/p Ljava/lang/String;
  astore_0
  aload_0
  areturn
  nop
.end <method>

.method public static m()Landroid/content/Context;
.limit locals 1
.limit stack 200
  nop
  getstatic com/wiyun/ad/ab/a Landroid/content/Context;
  astore_0
  aload_0
  areturn
  nop
.end <method>

.method static n()Landroid/app/Activity;
.limit locals 5
.limit stack 200
  nop
  getstatic com/wiyun/ad/ab/b Ljava/lang/ref/WeakReference;
  astore_0
  new java/lang/NoClassDefFoundError
  dup
  invokespecial java/lang/NoClassDefFoundError/<init>()V
  athrow
  iload_0
  ifne Label0
  aconst_null
  astore_1
  aload_1
  areturn
Label0:
  getstatic com/wiyun/ad/ab/b Ljava/lang/ref/WeakReference;
  astore_0
  aload_0
  invokevirtual java/lang/ref/WeakReference/get()Ljava/lang/Object;
  astore_2
  aload_2
  astore 4
  aload 4
  checkcast android/app/Activity
  astore 4
  aload 4
  astore_3
  aload_3
  areturn
  nop
.end <method>

.method public static o()D
.limit locals 6
.limit stack 200
  nop
  getstatic com/wiyun/ad/ab/e Landroid/location/Location;
  astore_0
  new java/lang/NoClassDefFoundError
  dup
  invokespecial java/lang/NoClassDefFoundError/<init>()V
  athrow
  iload_0
  ifne Label0
Label1:
  ldc2_w 0.000000000000000
  dstore_1
  dload_1
  dreturn
Label0:
  getstatic com/wiyun/ad/ab/e Landroid/location/Location;
  astore_0
  aload_0
  invokevirtual android/location/Location/getLatitude()D
  dstore_3
  ldc2_w 0.000049999998737
  dstore_1
  dload_3
  dload_1
  dcmpg
  istore 5
  dload 5
  invokestatic app/DummyClass/invokeIfStmt(D)V
  iload 5
  iflt Label1
  getstatic com/wiyun/ad/ab/e Landroid/location/Location;
  astore_0
  aload_0
  invokevirtual android/location/Location/getLatitude()D
  dstore_3
  dload_3
  dreturn
  nop
.end <method>

.method public static p()D
.limit locals 6
.limit stack 200
  nop
  getstatic com/wiyun/ad/ab/e Landroid/location/Location;
  astore_0
  new java/lang/NoClassDefFoundError
  dup
  invokespecial java/lang/NoClassDefFoundError/<init>()V
  athrow
  iload_0
  ifne Label0
Label1:
  ldc2_w 0.000000000000000
  dstore_1
  dload_1
  dreturn
Label0:
  getstatic com/wiyun/ad/ab/e Landroid/location/Location;
  astore_0
  aload_0
  invokevirtual android/location/Location/getLongitude()D
  dstore_3
  ldc2_w 0.000049999998737
  dstore_1
  dload_3
  dload_1
  dcmpg
  istore 5
  dload 5
  invokestatic app/DummyClass/invokeIfStmt(D)V
  iload 5
  iflt Label1
  getstatic com/wiyun/ad/ab/e Landroid/location/Location;
  astore_0
  aload_0
  invokevirtual android/location/Location/getLongitude()D
  dstore_3
  dload_3
  dreturn
  nop
.end <method>

.method public static q()Ljava/lang/String;
.limit locals 1
.limit stack 200
  nop
  getstatic com/wiyun/ad/ab/c Ljava/lang/String;
  astore_0
  aload_0
  areturn
  nop
.end <method>

.method static r()V
.limit locals 13
.limit stack 200
  nop
  iconst_1
  istore_0
  getstatic com/wiyun/ad/ab/a Landroid/content/Context;
  astore_1
  new java/lang/NoClassDefFoundError
  dup
  invokespecial java/lang/NoClassDefFoundError/<init>()V
  athrow
  iload_1
  ifeq Label0
  aload_1
  invokevirtual android/content/Context/getPackageManager()Landroid/content/pm/PackageManager;
  astore_2
Label9:
  ldc "com.lenovo.appstore"
  astore 4
  aload_2
  aload 4
  invokevirtual android/content/pm/PackageManager/getPackageGids(Ljava/lang/String;)[I
  astore_3
Label10:
  aload_3
  invokestatic app/DummyClass/invokeIfStmt(Ljava/lang/Object;)V
  aload_3
  ifnull Label1
  iconst_1
  istore 5
Label6:
  iload 5
  invokestatic app/DummyClass/invokeIfStmt(Z)V
  iload 5
  ifne Label2
Label12:
  ldc "com.lenovo.leos.appstore"
  astore 4
  aload_2
  aload 4
  invokevirtual android/content/pm/PackageManager/getPackageGids(Ljava/lang/String;)[I
  astore_3
Label13:
  aload_3
  invokestatic app/DummyClass/invokeIfStmt(Ljava/lang/Object;)V
  aload_3
  ifnull Label3
Label7:
  iload_0
  invokestatic app/DummyClass/invokeIfStmt(Z)V
  iload_0
  ifeq Label4
  ldc "lenovo"
  astore 4
  aload 4
  putstatic com/wiyun/ad/ab/m Ljava/lang/String;
  aload_1
  invokevirtual android/content/Context/getResources()Landroid/content/res/Resources;
  astore 6
  aload 6
  invokevirtual android/content/res/Resources/getDisplayMetrics()Landroid/util/DisplayMetrics;
  astore 7
  aload 7
  getfield android/util/DisplayMetrics/heightPixels I
  istore 8
  dload 8
  invokestatic app/DummyClass/invokeIfStmt(D)V
  sipush 800
  istore 9
  iload 8
  iload 9
  if_icmple Label5
  ldc "lepad"
  astore 4
  aload 4
  putstatic com/wiyun/ad/ab/n Ljava/lang/String;
Label0:
  return
Label1:
  iconst_0
  istore 5
  goto Label6
Label8:
  astore 10
  iconst_0
  istore 5
  goto Label6
Label3:
  iconst_0
  istore_0
  goto Label7
Label11:
  astore 11
  iload 5
  istore_0
  goto Label7
Label5:
  ldc "lephone"
  astore 4
  aload 4
  putstatic com/wiyun/ad/ab/n Ljava/lang/String;
  goto Label0
Label4:
  getstatic android/os/Build/BRAND Ljava/lang/String;
  astore 12
  aload 12
  putstatic com/wiyun/ad/ab/m Ljava/lang/String;
  getstatic android/os/Build/MODEL Ljava/lang/String;
  astore 12
  aload 12
  putstatic com/wiyun/ad/ab/n Ljava/lang/String;
  goto Label0
Label2:
  iload 5
  istore_0
  goto Label7
  nop
.end <method>

.method static s()V
.limit locals 9
.limit stack 200
  nop
  invokestatic com/wiyun/ad/ab/F()Z
  istore_0
  new java/lang/NoClassDefFoundError
  dup
  invokespecial java/lang/NoClassDefFoundError/<init>()V
  athrow
  iload_0
  ifeq Label0
  iconst_4
  istore_1
Label2:
  iload_1
  putstatic com/wiyun/ad/ab/q I
  return
Label0:
  getstatic com/wiyun/ad/ab/a Landroid/content/Context;
  astore_2
  ldc "phone"
  astore 4
  aload_2
  aload 4
  invokevirtual android/content/Context/getSystemService(Ljava/lang/String;)Ljava/lang/Object;
  astore_3
  aload_3
  astore 6
  aload 6
  checkcast android/telephony/TelephonyManager
  astore 6
  aload 6
  astore 5
  aload 5
  invokestatic app/DummyClass/invokeIfStmt(Ljava/lang/Object;)V
  aload 5
  ifnonnull Label1
  iconst_0
  istore_1
  goto Label2
Label1:
  aload 5
  invokevirtual android/telephony/TelephonyManager/getNetworkType()I
  istore 7
  dload 7
  invokestatic app/DummyClass/invokeIfStmt(D)V
  iconst_1
  istore 8
  iload 7
  iload 8
  if_icmpeq Label3
  dload 7
  invokestatic app/DummyClass/invokeIfStmt(D)V
  iconst_2
  istore 8
  iload 7
  iload 8
  if_icmpeq Label3
  dload 7
  invokestatic app/DummyClass/invokeIfStmt(D)V
  iload 7
  ifne Label4
Label3:
  iconst_2
  istore_1
  goto Label2
Label4:
  iconst_3
  istore_1
  goto Label2
  nop
.end <method>

.method private static t()V
.limit locals 5
.limit stack 200
  nop
  getstatic com/wiyun/ad/ab/a Landroid/content/Context;
  astore_0
  new java/lang/NoClassDefFoundError
  dup
  invokespecial java/lang/NoClassDefFoundError/<init>()V
  athrow
  iload_0
  ifne Label0
Label1:
  return
Label0:
  getstatic com/wiyun/ad/ab/a Landroid/content/Context;
  astore_0
  aload_0
  invokevirtual android/content/Context/getResources()Landroid/content/res/Resources;
  astore_1
  aload_1
  invokevirtual android/content/res/Resources/getDisplayMetrics()Landroid/util/DisplayMetrics;
  astore_2
  aload_2
  getfield android/util/DisplayMetrics/widthPixels I
  istore_3
  iload_3
  putstatic com/wiyun/ad/ab/s I
  aload_2
  getfield android/util/DisplayMetrics/heightPixels I
  istore_3
  iload_3
  putstatic com/wiyun/ad/ab/t I
  aload_2
  getfield android/util/DisplayMetrics/densityDpi I
  istore_3
  iload_3
  putstatic com/wiyun/ad/ab/u I
  getstatic com/wiyun/ad/ab/s I
  istore_3
  getstatic com/wiyun/ad/ab/t I
  istore 4
  dload_3
  invokestatic app/DummyClass/invokeIfStmt(D)V
  dload 4
  invokestatic app/DummyClass/invokeIfStmt(D)V
  iload_3
  iload 4
  if_icmple Label1
  getstatic com/wiyun/ad/ab/t I
  istore 4
  getstatic com/wiyun/ad/ab/s I
  istore_3
  iload_3
  putstatic com/wiyun/ad/ab/t I
  iload 4
  putstatic com/wiyun/ad/ab/s I
  goto Label1
  nop
.end <method>

.method private static u()V
.limit locals 2
.limit stack 200
  nop
  invokestatic java/util/Locale/getDefault()Ljava/util/Locale;
  astore_0
  aload_0
  invokevirtual java/util/Locale/getLanguage()Ljava/lang/String;
  astore_1
  aload_1
  putstatic com/wiyun/ad/ab/o Ljava/lang/String;
  aload_0
  invokevirtual java/util/Locale/getCountry()Ljava/lang/String;
  astore_1
  aload_1
  putstatic com/wiyun/ad/ab/p Ljava/lang/String;
  return
  nop
.end <method>

.method private static v()V
.limit locals 7
.limit stack 200
  nop
  new java/lang/NoClassDefFoundError
  dup
  invokespecial java/lang/NoClassDefFoundError/<init>()V
  athrow
Label2:
  ldc "SDK_INT"
  astore_2
  aload_0
  aload_2
  invokevirtual java/lang/Class/getField(Ljava/lang/String;)Ljava/lang/reflect/Field;
  astore_1
  aconst_null
  astore 4
  aload_1
  aload 4
  invokevirtual java/lang/reflect/Field/getInt(Ljava/lang/Object;)I
  istore_3
Label3:
  iload_3
  putstatic com/wiyun/ad/ab/r I
Label0:
  return
Label1:
  astore 5
  iconst_3
  istore 6
  iload 6
  putstatic com/wiyun/ad/ab/r I
  goto Label0
  nop
.end <method>

.method private static w()V
.limit locals 2
.limit stack 200
  nop
  getstatic com/wiyun/ad/ab/a Landroid/content/Context;
  astore_0
  new java/lang/NoClassDefFoundError
  dup
  invokespecial java/lang/NoClassDefFoundError/<init>()V
  athrow
  iload_0
  ifeq Label0
  getstatic com/wiyun/ad/ab/a Landroid/content/Context;
  astore_0
  aload_0
  invokevirtual android/content/Context/getPackageName()Ljava/lang/String;
  astore_1
  aload_1
  putstatic com/wiyun/ad/ab/c Ljava/lang/String;
Label0:
  return
  nop
.end <method>

.method private static x()V
.limit locals 13
.limit stack 200
  nop
  getstatic com/wiyun/ad/ab/l Ljava/lang/String;
  astore_0
  new java/lang/NoClassDefFoundError
  dup
  invokespecial java/lang/NoClassDefFoundError/<init>()V
  athrow
  nop
  iload_1
  invokestatic app/DummyClass/invokeIfStmt(Z)V
  iload_1
  ifeq Label0
  getstatic com/wiyun/ad/ab/a Landroid/content/Context;
  astore_2
  aload_2
  invokestatic app/DummyClass/invokeIfStmt(Ljava/lang/Object;)V
  aload_2
  ifnull Label0
  ldc "android.permission.READ_PHONE_STATE"
  astore 4
  aload_2
  aload 4
  invokevirtual android/content/Context/checkCallingOrSelfPermission(Ljava/lang/String;)I
  istore_3
  dload_3
  invokestatic app/DummyClass/invokeIfStmt(D)V
  iconst_m1
  istore 5
  iload_3
  iload 5
  if_icmpeq Label0
  ldc "phone"
  astore 4
  aload_2
  aload 4
  invokevirtual android/content/Context/getSystemService(Ljava/lang/String;)Ljava/lang/Object;
  astore 6
  aload 6
  astore 8
  aload 8
  checkcast android/telephony/TelephonyManager
  astore 8
  aload 8
  astore 7
  aload 7
  invokestatic app/DummyClass/invokeIfStmt(Ljava/lang/Object;)V
  aload 7
  ifnonnull Label1
  aconst_null
  astore_0
Label3:
  aload_0
  invokestatic android/text/TextUtils/isEmpty(Ljava/lang/CharSequence;)Z
  istore_1
  iload_1
  invokestatic app/DummyClass/invokeIfStmt(Z)V
  iload_1
  ifne Label0
  aload_0
  invokestatic com/wiyun/ad/x/a(Ljava/lang/String;)[B
  astore 9
  iconst_0
  dstore_3
Label4:
  aload 9
  arraylength
  istore 10
  dload_3
  invokestatic app/DummyClass/invokeIfStmt(D)V
  dload 10
  invokestatic app/DummyClass/invokeIfStmt(D)V
  iload_3
  iload 10
  if_icmplt Label2
  aload 9
  invokestatic com/wiyun/ad/w/a([B)Ljava/lang/String;
  astore_0
  aload_0
  putstatic com/wiyun/ad/ab/l Ljava/lang/String;
Label0:
  return
Label1:
  aload 7
  invokevirtual android/telephony/TelephonyManager/getLine1Number()Ljava/lang/String;
  astore_0
  goto Label3
Label2:
  aload 9
  iload_3
  baload
  istore 11
  iconst_4
  istore 5
  iload 11
  iload 5
  ishr
  istore 11
  bipush 15
  istore 5
  iload 11
  iload 5
  iand
  istore 12
  aload 9
  iload_3
  baload
  istore 11
  bipush 15
  istore 5
  iload 11
  iload 5
  iand
  istore 11
  iload 11
  iconst_4
  ishl
  istore 10
  iload 12
  iload 10
  ior
  istore 10
  iload 10
  sipush 255
  ixor
  istore 10
  iload 10
  sipush 255
  iadd
  istore 10
  iload 10
  i2b
  istore 12
  aload 9
  iload_3
  iload 12
  bastore
  iload_3
  iconst_1
  iadd
  istore_3
  goto Label4
  nop
.end <method>

.method private static y()V
.limit locals 8
.limit stack 200
  nop
  getstatic com/wiyun/ad/ab/a Landroid/content/Context;
  astore_0
  getstatic com/wiyun/ad/ab/k Ljava/lang/String;
  astore_1
  new java/lang/NoClassDefFoundError
  dup
  invokespecial java/lang/NoClassDefFoundError/<init>()V
  athrow
  nop
  iload_2
  invokestatic app/DummyClass/invokeIfStmt(Z)V
  iload_2
  ifeq Label0
  aload_0
  invokestatic app/DummyClass/invokeIfStmt(Ljava/lang/Object;)V
  iload_0
  ifeq Label0
  ldc "android.permission.READ_PHONE_STATE"
  astore 4
  aload_0
  aload 4
  invokevirtual android/content/Context/checkCallingOrSelfPermission(Ljava/lang/String;)I
  istore_3
  dload_3
  invokestatic app/DummyClass/invokeIfStmt(D)V
  iload_3
  ifne Label0
  ldc "phone"
  astore 4
  aload_0
  aload 4
  invokevirtual android/content/Context/getSystemService(Ljava/lang/String;)Ljava/lang/Object;
  astore 5
  aload 5
  astore 7
  aload 7
  checkcast android/telephony/TelephonyManager
  astore 7
  aload 7
  astore 6
  aload 6
  invokestatic app/DummyClass/invokeIfStmt(Ljava/lang/Object;)V
  aload 6
  ifnull Label0
  aload 6
  invokevirtual android/telephony/TelephonyManager/getNetworkOperatorName()Ljava/lang/String;
  astore_1
  aload_1
  putstatic com/wiyun/ad/ab/k Ljava/lang/String;
Label0:
  return
  nop
.end <method>

.method private static z()V
.limit locals 9
.limit stack 200
  nop
  getstatic com/wiyun/ad/ab/f Ljava/lang/String;
  astore_0
  new java/lang/NoClassDefFoundError
  dup
  invokespecial java/lang/NoClassDefFoundError/<init>()V
  athrow
  iload_0
  ifne Label0
  getstatic com/wiyun/ad/ab/i I
  istore_1
  dload_1
  invokestatic app/DummyClass/invokeIfStmt(D)V
  iconst_1
  istore_2
  iload_1
  iload_2
  if_icmpne Label1
  ldc "000000000000000"
  astore_3
  aload_3
  putstatic com/wiyun/ad/ab/f Ljava/lang/String;
Label0:
  return
Label1:
  getstatic com/wiyun/ad/ab/a Landroid/content/Context;
  astore 4
  aload 4
  invokestatic app/DummyClass/invokeIfStmt(Ljava/lang/Object;)V
  aload 4
  ifnull Label0
  ldc "android.permission.READ_PHONE_STATE"
  astore_3
  aload 4
  aload_3
  invokevirtual android/content/Context/checkCallingOrSelfPermission(Ljava/lang/String;)I
  istore_1
  dload_1
  invokestatic app/DummyClass/invokeIfStmt(D)V
  iconst_m1
  istore_2
  iload_1
  iload_2
  if_icmpeq Label0
  ldc "phone"
  astore_3
  aload 4
  aload_3
  invokevirtual android/content/Context/getSystemService(Ljava/lang/String;)Ljava/lang/Object;
  astore 5
  aload 5
  astore 7
  aload 7
  checkcast android/telephony/TelephonyManager
  astore 7
  aload 7
  astore 6
  aload 6
  invokestatic app/DummyClass/invokeIfStmt(Ljava/lang/Object;)V
  aload 6
  ifnull Label2
  aload 6
  invokevirtual android/telephony/TelephonyManager/getDeviceId()Ljava/lang/String;
  astore_0
  aload_0
  putstatic com/wiyun/ad/ab/f Ljava/lang/String;
  getstatic com/wiyun/ad/ab/f Ljava/lang/String;
  astore_0
  aload_0
  invokestatic com/wiyun/ad/ab/a(Ljava/lang/String;)Z
  istore 8
  iload 8
  invokestatic app/DummyClass/invokeIfStmt(Z)V
  iload 8
  ifne Label0
  invokestatic com/wiyun/ad/ab/i()Ljava/lang/String;
  astore_0
  aload_0
  putstatic com/wiyun/ad/ab/f Ljava/lang/String;
  goto Label0
Label2:
  invokestatic com/wiyun/ad/ab/i()Ljava/lang/String;
  astore_0
  aload_0
  putstatic com/wiyun/ad/ab/f Ljava/lang/String;
  goto Label0
  nop
.end <method>

