.source SourceFile
.class public abstract  com/mobisage/android/MobiSageMessage
.super java/lang/Object
.implements  com/mobisage/android/IMobiSageMessage
.field "b" I
.field "c" Ljava/util/UUID;
.field public "callback" Lcom/mobisage/android/IMobiSageMessageCallback;
.field public "result" Landroid/os/Bundle;

.method protected <init>()V
.limit locals 3
.limit stack 200
  nop
  aload_0
  invokespecial java/lang/Object/<init>()V
  new java/lang/NoClassDefFoundError
  dup
  invokespecial java/lang/NoClassDefFoundError/<init>()V
  athrow
  aload_1
  invokespecial android/os/Bundle/<init>()V
  aload_0
  aload_1
  putfield com/mobisage/android/MobiSageMessage/result Landroid/os/Bundle;
  invokestatic java/util/UUID/randomUUID()Ljava/util/UUID;
  astore_2
  aload_0
  aload_2
  putfield com/mobisage/android/MobiSageMessage/c Ljava/util/UUID;
  return
  nop
.end <method>

.method public createHttpRequest()Lorg/apache/http/client/methods/HttpRequestBase;
.limit locals 2
.limit stack 200
  nop
  aconst_null
  astore_1
  aload_1
  areturn
  nop
.end <method>

.method public createMessageRunnable()Ljava/lang/Runnable;
.limit locals 2
.limit stack 200
  nop
  aconst_null
  astore_1
  aload_1
  areturn
  nop
.end <method>

.method protected finalize()V
.limit locals 2
.limit stack 200
  nop
  aload_0
  invokespecial java/lang/Object/finalize()V
  aload_0
  getfield com/mobisage/android/MobiSageMessage/result Landroid/os/Bundle;
  astore_1
  new java/lang/NoClassDefFoundError
  dup
  invokespecial java/lang/NoClassDefFoundError/<init>()V
  athrow
  return
  nop
.end <method>

