.source SourceFile
.class final  com/mobisage/android/O$a
.super java/lang/Object
.implements  com/mobisage/android/a
.field private "a" Lcom/mobisage/android/O;

.method private <init>(Lcom/mobisage/android/O;)V
.limit locals 2
.limit stack 200
  nop
  aload_0
  aload_1
  putfield com/mobisage/android/O$a/a Lcom/mobisage/android/O;
  aload_0
  invokespecial java/lang/Object/<init>()V
  return
  nop
.end <method>

.method <init>(Lcom/mobisage/android/O;B)V
  .synthetic
.limit locals 3
.limit stack 200
  nop
  aload_0
  aload_1
  invokespecial com/mobisage/android/O$a/<init>(Lcom/mobisage/android/O;)V
  return
  nop
.end <method>

.method public final a(Lcom/mobisage/android/b;)V
.limit locals 3
.limit stack 200
  nop
  aload_0
  getfield com/mobisage/android/O$a/a Lcom/mobisage/android/O;
  astore_2
  aload_2
  aload_1
  invokevirtual com/mobisage/android/O/a(Lcom/mobisage/android/b;)V
  return
  nop
.end <method>

.method public final b(Lcom/mobisage/android/b;)V
.limit locals 3
.limit stack 200
  nop
  aload_0
  getfield com/mobisage/android/O$a/a Lcom/mobisage/android/O;
  astore_2
  aload_2
  aload_1
  invokevirtual com/mobisage/android/O/c(Lcom/mobisage/android/b;)V
  return
  nop
.end <method>

