.source SourceFile
.class final  com/mobisage/android/q
.super com/mobisage/android/N
.field private "c" Ljava/io/InputStream;
.field private "d" Ljava/io/BufferedInputStream;
.field private "e" Ljava/io/FileOutputStream;

.method public <init>(Lcom/mobisage/android/MobiSageResMessage;)V
.limit locals 2
.limit stack 200
  nop
  aload_0
  aload_1
  invokespecial com/mobisage/android/N/<init>(Lcom/mobisage/android/MobiSageMessage;)V
  return
  nop
.end <method>

.method public final a()V
.limit locals 6
.limit stack 200
  nop
  aload_0
  invokespecial com/mobisage/android/N/a()V
  aload_0
  getfield com/mobisage/android/q/d Ljava/io/BufferedInputStream;
  astore_1
  new java/lang/NoClassDefFoundError
  dup
  invokespecial java/lang/NoClassDefFoundError/<init>()V
  athrow
  iload_1
  ifeq Label0
  aload_0
  getfield com/mobisage/android/q/d Ljava/io/BufferedInputStream;
  astore_1
Label5:
  aload_1
  invokevirtual java/io/BufferedInputStream/close()V
Label0:
  aconst_null
  astore_2
  aload_0
  aload_2
  putfield com/mobisage/android/q/d Ljava/io/BufferedInputStream;
  aload_0
  getfield com/mobisage/android/q/c Ljava/io/InputStream;
  astore_3
  aload_3
  invokestatic app/DummyClass/invokeIfStmt(Ljava/lang/Object;)V
  aload_3
  ifnull Label1
  aload_0
  getfield com/mobisage/android/q/c Ljava/io/InputStream;
  astore_3
  aload_3
  invokevirtual java/io/InputStream/close()V
Label1:
  aconst_null
  astore_2
  aload_0
  aload_2
  putfield com/mobisage/android/q/c Ljava/io/InputStream;
  aload_0
  getfield com/mobisage/android/q/e Ljava/io/FileOutputStream;
  astore 4
  aload 4
  invokestatic app/DummyClass/invokeIfStmt(Ljava/lang/Object;)V
  aload 4
  ifnull Label2
  aload_0
  getfield com/mobisage/android/q/e Ljava/io/FileOutputStream;
  astore 4
  aload 4
  invokevirtual java/io/FileOutputStream/close()V
Label2:
  aconst_null
  astore_2
  aload_0
  aload_2
  putfield com/mobisage/android/q/e Ljava/io/FileOutputStream;
Label3:
  return
Label4:
  astore 5
  goto Label3
  nop
.end <method>

.method private a(II)V
.limit locals 26
.limit stack 200
  nop
  getstatic com/mobisage/android/r/h Landroid/content/Context;
  astore 6
  aload_0
  astore_3
  aload_3
  getfield com/mobisage/android/N/a Lcom/mobisage/android/MobiSageMessage;
  astore 7
  aload 7
  astore 9
  aload 9
  checkcast com/mobisage/android/o
  astore 9
  aload 9
  astore 8
  ldc "notification"
  astore 11
  new java/lang/NoClassDefFoundError
  dup
  invokespecial java/lang/NoClassDefFoundError/<init>()V
  athrow
  nop
  aload 10
  astore 13
  aload 13
  checkcast android/app/NotificationManager
  astore 13
  aload 13
  astore 12
  new android/content/Intent
  astore 14
  ldc com/mobisage/android/MobiSageApkService
  astore 15
  aload 14
  aload 6
  aload 15
  invokespecial android/content/Intent/<init>(Landroid/content/Context;Ljava/lang/Class;)V
  new android/os/Bundle
  astore 16
  aload 16
  invokespecial android/os/Bundle/<init>()V
  aload 8
  getfield com/mobisage/android/MobiSageMessage/c Ljava/util/UUID;
  astore 17
  aload 17
  invokevirtual java/util/UUID/toString()Ljava/lang/String;
  astore 18
  ldc "did"
  astore 11
  aload 16
  aload 11
  aload 18
  invokevirtual android/os/Bundle/putString(Ljava/lang/String;Ljava/lang/String;)V
  ldc "action"
  astore 11
  iconst_1
  istore 19
  iload 19
  istore_3
  aload 16
  aload 11
  iload_3
  invokevirtual android/os/Bundle/putInt(Ljava/lang/String;I)V
  ldc "ExtraData"
  astore 11
  aload 14
  aload 11
  aload 16
  invokevirtual android/content/Intent/putExtra(Ljava/lang/String;Landroid/os/Bundle;)Landroid/content/Intent;
  pop
  iconst_0
  istore 19
  ldc 134217728
  istore 21
  iload 19
  istore_3
  iload 21
  istore 4
  aload 6
  iload_3
  aload 14
  iload 4
  invokestatic android/app/PendingIntent/getService(Landroid/content/Context;ILandroid/content/Intent;I)Landroid/app/PendingIntent;
  astore 20
  new android/app/Notification
  astore 22
  aload 22
  astore_3
  aload_3
  invokespecial android/app/Notification/<init>()V
  aload 8
  getfield com/mobisage/android/o/a Ljava/lang/String;
  astore 18
  aload 22
  astore_3
  aload_3
  aload 18
  putfield android/app/Notification/tickerText Ljava/lang/CharSequence;
  ldc 17301633
  istore 19
  iload 19
  istore_3
  aload 22
  astore 4
  aload 4
  iload_3
  putfield android/app/Notification/icon I
  bipush 16
  istore 19
  iload 19
  istore_3
  aload 22
  astore 4
  aload 4
  iload_3
  putfield android/app/Notification/flags I
  aload 8
  getfield com/mobisage/android/o/a Ljava/lang/String;
  astore 18
  new java/lang/StringBuilder
  astore 23
  ldc "\u4e0b\u8f7d\u4e2d"
  astore 11
  aload 23
  astore_3
  aload_3
  aload 11
  invokespecial java/lang/StringBuilder/<init>(Ljava/lang/String;)V
  iload_1
  bipush 100
  imul
  istore 24
  iload 24
  istore_3
  iload_2
  istore 4
  iload_3
  iload 4
  idiv
  istore_3
  iload_3
  istore 24
  aload 23
  astore_3
  iload 24
  istore 4
  aload_3
  iload 4
  invokevirtual java/lang/StringBuilder/append(I)Ljava/lang/StringBuilder;
  astore 23
  ldc "%\uff0c\u70b9\u51fb\u53d6\u6d88\u4e0b\u8f7d"
  astore 11
  aload 23
  astore_3
  aload_3
  aload 11
  invokevirtual java/lang/StringBuilder/append(Ljava/lang/String;)Ljava/lang/StringBuilder;
  astore 23
  aload 23
  astore_3
  aload_3
  invokevirtual java/lang/StringBuilder/toString()Ljava/lang/String;
  astore 25
  aload 22
  astore_3
  aload 25
  astore 4
  aload 20
  astore 5
  aload_3
  aload 6
  aload 18
  aload 4
  aload 5
  invokevirtual android/app/Notification/setLatestEventInfo(Landroid/content/Context;Ljava/lang/CharSequence;Ljava/lang/CharSequence;Landroid/app/PendingIntent;)V
  aload 8
  getfield com/mobisage/android/MobiSageMessage/c Ljava/util/UUID;
  astore 17
  aload 17
  invokevirtual java/util/UUID/hashCode()I
  istore 24
  iload 24
  istore_3
  aload 22
  astore 4
  aload 12
  iload_3
  aload 4
  invokevirtual android/app/NotificationManager/notify(ILandroid/app/Notification;)V
  return
  nop
.end <method>

.method public final run()V
.limit locals 62
.limit stack 200
  nop
  aload_0
  astore_1
  aload_1
  getfield com/mobisage/android/N/a Lcom/mobisage/android/MobiSageMessage;
  astore 5
  aload 5
  astore 7
  aload 7
  checkcast com/mobisage/android/MobiSageResMessage
  astore 7
  aload 7
  astore 6
  new java/lang/NoClassDefFoundError
  dup
  invokespecial java/lang/NoClassDefFoundError/<init>()V
  athrow
Label9:
  aload 8
  invokespecial org/apache/http/conn/scheme/SchemeRegistry/<init>()V
  new org/apache/http/conn/scheme/Scheme
  astore 9
  invokestatic org/apache/http/conn/scheme/PlainSocketFactory/getSocketFactory()Lorg/apache/http/conn/scheme/PlainSocketFactory;
  astore 10
  ldc "http"
  astore 11
  bipush 80
  istore 12
  aload 9
  aload 11
  aload 10
  iload 12
  invokespecial org/apache/http/conn/scheme/Scheme/<init>(Ljava/lang/String;Lorg/apache/http/conn/scheme/SocketFactory;I)V
  aload 8
  aload 9
  invokevirtual org/apache/http/conn/scheme/SchemeRegistry/register(Lorg/apache/http/conn/scheme/Scheme;)Lorg/apache/http/conn/scheme/Scheme;
  pop
  new org/apache/http/conn/scheme/Scheme
  astore 9
  new com/mobisage/android/SNSSSLSocketFactory
  astore 13
  aload 13
  invokespecial com/mobisage/android/SNSSSLSocketFactory/<init>()V
  aload 13
  astore 15
  aload 15
  checkcast org/apache/http/conn/scheme/SocketFactory
  astore 15
  aload 15
  astore 14
  ldc "https"
  astore 11
  sipush 443
  istore 12
  aload 9
  aload 11
  aload 14
  iload 12
  invokespecial org/apache/http/conn/scheme/Scheme/<init>(Ljava/lang/String;Lorg/apache/http/conn/scheme/SocketFactory;I)V
  aload 8
  aload 9
  invokevirtual org/apache/http/conn/scheme/SchemeRegistry/register(Lorg/apache/http/conn/scheme/Scheme;)Lorg/apache/http/conn/scheme/Scheme;
  pop
  new org/apache/http/params/BasicHttpParams
  astore 16
  aload 16
  invokespecial org/apache/http/params/BasicHttpParams/<init>()V
  sipush 5000
  istore 12
  iload 12
  invokestatic java/lang/Integer/valueOf(I)Ljava/lang/Integer;
  astore 17
  ldc "http.connection.timeout"
  astore 11
  aload 17
  astore_1
  aload 16
  aload 11
  aload_1
  invokeinterface org/apache/http/params/HttpParams/setParameter(Ljava/lang/String;Ljava/lang/Object;)Lorg/apache/http/params/HttpParams; 3
  pop
  sipush 5000
  istore 12
  iload 12
  invokestatic java/lang/Integer/valueOf(I)Ljava/lang/Integer;
  astore 17
  ldc "http.socket.timeout"
  astore 11
  aload 17
  astore_1
  aload 16
  aload 11
  aload_1
  invokeinterface org/apache/http/params/HttpParams/setParameter(Ljava/lang/String;Ljava/lang/Object;)Lorg/apache/http/params/HttpParams; 3
  pop
  getstatic org/apache/http/HttpVersion/HTTP_1_1 Lorg/apache/http/HttpVersion;
  astore 18
  aload 18
  astore_1
  aload 16
  aload_1
  invokestatic org/apache/http/params/HttpProtocolParams/setVersion(Lorg/apache/http/params/HttpParams;Lorg/apache/http/ProtocolVersion;)V
  ldc "UTF-8"
  astore 11
  aload 16
  aload 11
  invokestatic org/apache/http/params/HttpProtocolParams/setContentCharset(Lorg/apache/http/params/HttpParams;Ljava/lang/String;)V
  new org/apache/http/impl/conn/SingleClientConnManager
  astore 19
  aload 19
  astore_1
  aload_1
  aload 16
  aload 8
  invokespecial org/apache/http/impl/conn/SingleClientConnManager/<init>(Lorg/apache/http/params/HttpParams;Lorg/apache/http/conn/scheme/SchemeRegistry;)V
  new org/apache/http/impl/client/DefaultHttpClient
  astore 20
  aload 20
  astore_1
  aload 19
  astore_2
  aload_1
  aload_2
  aload 16
  invokespecial org/apache/http/impl/client/DefaultHttpClient/<init>(Lorg/apache/http/conn/ClientConnectionManager;Lorg/apache/http/params/HttpParams;)V
  aload 20
  astore_1
  aload_0
  astore_2
  aload_2
  aload_1
  putfield com/mobisage/android/N/b Lorg/apache/http/client/HttpClient;
  aload_0
  astore_1
  aload_1
  getfield com/mobisage/android/N/b Lorg/apache/http/client/HttpClient;
  astore_1
  aload_1
  astore 21
  aload 6
  invokevirtual com/mobisage/android/MobiSageResMessage/createHttpRequest()Lorg/apache/http/client/methods/HttpRequestBase;
  astore 22
  aload 21
  astore_1
  aload 22
  astore_2
  aload_1
  aload_2
  invokeinterface org/apache/http/client/HttpClient/execute(Lorg/apache/http/client/methods/HttpUriRequest;)Lorg/apache/http/HttpResponse; 2
  astore 23
  aload 23
  astore_1
  aload_1
  invokeinterface org/apache/http/HttpResponse/getStatusLine()Lorg/apache/http/StatusLine; 1
  astore 24
  aload 24
  astore_1
  aload_1
  invokeinterface org/apache/http/StatusLine/getStatusCode()I 1
  istore 25
  aload 6
  getfield com/mobisage/android/MobiSageMessage/result Landroid/os/Bundle;
  astore_1
  aload_1
  astore 26
  ldc "StatusCode"
  astore 11
  aload 26
  astore_1
  iload 25
  istore_2
  aload_1
  aload 11
  iload_2
  invokevirtual android/os/Bundle/putInt(Ljava/lang/String;I)V
  iload 25
  istore_1
  dload_1
  invokestatic app/DummyClass/invokeIfStmt(D)V
  sipush 400
  istore 12
  iload 25
  istore_1
  iload_1
  iload 12
  if_icmpge Label0
  ldc "Content-Length"
  astore 11
  aload 23
  astore_1
  aload_1
  aload 11
  invokeinterface org/apache/http/HttpResponse/getHeaders(Ljava/lang/String;)[Lorg/apache/http/Header; 2
  astore 27
  iconst_0
  istore 12
  aload 27
  iload 12
  aaload
  astore 28
  aload 28
  astore_1
  aload_1
  invokeinterface org/apache/http/Header/getValue()Ljava/lang/String; 1
  astore 29
  aload 29
  astore_1
  aload_1
  invokestatic java/lang/Integer/parseInt(Ljava/lang/String;)I
  istore 30
  new java/io/File
  astore 31
  aload 31
  astore 32
  aload 6
  getfield com/mobisage/android/MobiSageResMessage/tempURL Ljava/lang/String;
  astore_1
  aload_1
  astore 29
  aload 31
  astore_1
  aload 29
  astore_2
  aload_1
  aload_2
  invokespecial java/io/File/<init>(Ljava/lang/String;)V
  aload 31
  astore_1
  aload_1
  invokevirtual java/io/File/exists()Z
  istore 33
  iload 33
  istore_1
  iload_1
  invokestatic app/DummyClass/invokeIfStmt(Z)V
  iload 33
  ifne Label1
  aload 31
  astore_1
  aload_1
  invokevirtual java/io/File/createNewFile()Z
  pop
Label1:
  aload 6
  getfield com/mobisage/android/MobiSageResMessage/d Ljava/lang/Boolean;
  astore_1
  aload_1
  astore 34
  aload 34
  astore_1
  aload_1
  invokevirtual java/lang/Boolean/booleanValue()Z
  istore 33
  iload 33
  istore_1
  iload_1
  invokestatic app/DummyClass/invokeIfStmt(Z)V
  iload 33
  ifeq Label2
  iload 25
  istore_1
  dload_1
  invokestatic app/DummyClass/invokeIfStmt(D)V
  sipush 206
  istore 12
  iload 25
  istore_1
  iload_1
  iload 12
  if_icmpeq Label2
  aload 32
  astore_1
  aload_1
  invokevirtual java/io/File/delete()Z
  pop
  aload 32
  astore_1
  aload_1
  invokevirtual java/io/File/createNewFile()Z
  pop
Label2:
  invokestatic java/lang/System/currentTimeMillis()J
  lstore 35
  aload 32
  astore_1
  aload_1
  invokevirtual java/io/File/length()J
  lstore 37
  lload 37
  lstore_1
  lload_1
  l2i
  istore_1
  iload_1
  istore 25
  aload_0
  astore_1
  iload 25
  istore_2
  iload 30
  istore_3
  aload_1
  iload_2
  iload_3
  invokespecial com/mobisage/android/q/a(II)V
  aload 23
  astore_1
  aload_1
  invokeinterface org/apache/http/HttpResponse/getEntity()Lorg/apache/http/HttpEntity; 1
  astore 39
  aload 39
  astore_1
  aload_1
  invokeinterface org/apache/http/HttpEntity/getContent()Ljava/io/InputStream; 1
  astore 40
  aload 40
  astore_1
  aload_0
  astore_2
  aload_2
  aload_1
  putfield com/mobisage/android/q/c Ljava/io/InputStream;
  new java/io/BufferedInputStream
  astore 41
  aload_0
  astore_1
  aload_1
  getfield com/mobisage/android/q/c Ljava/io/InputStream;
  astore_1
  aload_1
  astore 40
  aload 41
  astore_1
  aload 40
  astore_2
  aload_1
  aload_2
  invokespecial java/io/BufferedInputStream/<init>(Ljava/io/InputStream;)V
  aload 41
  astore_1
  aload_0
  astore_2
  aload_2
  aload_1
  putfield com/mobisage/android/q/d Ljava/io/BufferedInputStream;
  new java/io/FileOutputStream
  astore 42
  iconst_1
  istore 12
  aload 42
  astore_1
  aload 32
  astore_2
  aload_1
  aload_2
  iload 12
  invokespecial java/io/FileOutputStream/<init>(Ljava/io/File;Z)V
  aload 42
  astore_1
  aload_0
  astore_2
  aload_2
  aload_1
  putfield com/mobisage/android/q/e Ljava/io/FileOutputStream;
  ldc 65535
  istore 12
  iload 12
  newarray byte
  astore_1
  aload_1
  astore 43
Label4:
  aload_0
  astore_1
  aload_1
  getfield com/mobisage/android/q/d Ljava/io/BufferedInputStream;
  astore_1
  aload_1
  astore 44
  aload 44
  astore_1
  aload 43
  astore_2
  aload_1
  aload_2
  invokevirtual java/io/BufferedInputStream/read([B)I
  istore 25
  iload 25
  istore_1
  dload_1
  invokestatic app/DummyClass/invokeIfStmt(D)V
  iconst_m1
  istore 12
  iload 25
  istore_1
  iload_1
  iload 12
  if_icmpeq Label3
  aload_0
  astore_1
  aload_1
  getfield com/mobisage/android/q/e Ljava/io/FileOutputStream;
  astore_1
  aload_1
  astore 45
  iconst_0
  istore 12
  aload 45
  astore_1
  aload 43
  astore_2
  iload 25
  istore_3
  aload_1
  aload_2
  iload 12
  iload_3
  invokevirtual java/io/FileOutputStream/write([BII)V
  invokestatic java/lang/System/currentTimeMillis()J
  lstore 46
  lload 46
  lload 35
  lsub
  lstore 48
  ldc2_w 2000
  lstore 51
  lload 48
  lload 51
  lcmp
  istore 50
  iload 50
  istore_1
  dload_1
  invokestatic app/DummyClass/invokeIfStmt(D)V
  iload 50
  ifle Label4
  aload 32
  astore_1
  aload_1
  invokevirtual java/io/File/length()J
  lstore 48
  lload 48
  lstore_1
  lload_1
  l2i
  istore_1
  iload_1
  istore 25
  iload 30
  istore_1
  iload_1
  i2l
  lstore_1
  lload_1
  lstore 48
  aload 6
  getfield com/mobisage/android/MobiSageResMessage/e J
  lstore_1
  lload_1
  lstore 35
  lload 48
  lstore_1
  lload 35
  lstore_3
  lload_1
  lload_3
  ladd
  lstore_1
  lload_1
  lstore 48
  lload 48
  lstore_1
  lload_1
  l2i
  istore_1
  iload_1
  istore 53
  aload_0
  astore_1
  iload 25
  istore_2
  iload 53
  istore_3
  aload_1
  iload_2
  iload_3
  invokespecial com/mobisage/android/q/a(II)V
  lload 46
  lstore 35
  goto Label4
Label3:
  aload_0
  astore_1
  aload_1
  getfield com/mobisage/android/q/d Ljava/io/BufferedInputStream;
  astore_1
  aload_1
  astore 44
  aload 44
  astore_1
  aload_1
  invokevirtual java/io/BufferedInputStream/close()V
  aload_0
  astore_1
  aload_1
  getfield com/mobisage/android/q/c Ljava/io/InputStream;
  astore_1
  aload_1
  astore 40
  aload 40
  astore_1
  aload_1
  invokevirtual java/io/InputStream/close()V
  aload_0
  astore_1
  aload_1
  getfield com/mobisage/android/q/e Ljava/io/FileOutputStream;
  astore_1
  aload_1
  astore 45
  aload 45
  astore_1
  aload_1
  invokevirtual java/io/FileOutputStream/close()V
  aload 32
  astore_1
  aload_1
  invokevirtual java/io/File/length()J
  lstore 48
  iload 30
  istore_1
  iload_1
  i2l
  lstore_1
  lload_1
  lstore 46
  aload 6
  getfield com/mobisage/android/MobiSageResMessage/e J
  lstore_1
  lload_1
  lstore 35
  lload 46
  lstore_1
  lload 35
  lstore_3
  lload_1
  lload_3
  ladd
  lstore_1
  lload_1
  lstore 46
  lload 48
  lload 46
  lcmp
  istore 50
  iload 50
  istore_1
  dload_1
  invokestatic app/DummyClass/invokeIfStmt(D)V
  iload 50
  ifeq Label5
  aload 32
  astore_1
  aload_1
  invokevirtual java/io/File/delete()Z
  pop
  aload 6
  getfield com/mobisage/android/MobiSageMessage/result Landroid/os/Bundle;
  astore_1
  aload_1
  astore 26
  ldc "StatusCode"
  astore 11
  sipush 400
  istore 12
  aload 26
  astore_1
  aload_1
  aload 11
  iload 12
  invokevirtual android/os/Bundle/putInt(Ljava/lang/String;I)V
Label0:
  getstatic com/mobisage/android/r/h Landroid/content/Context;
  astore 54
  new android/content/Intent
  astore 55
  ldc com/mobisage/android/MobiSageApkService
  astore 56
  aload 55
  astore_1
  aload 54
  astore_2
  aload 56
  astore_3
  aload_1
  aload_2
  aload_3
  invokespecial android/content/Intent/<init>(Landroid/content/Context;Ljava/lang/Class;)V
  aload 6
  getfield com/mobisage/android/MobiSageMessage/result Landroid/os/Bundle;
  astore_1
  aload_1
  astore 26
  ldc "action"
  astore 11
  iconst_3
  istore 12
  aload 26
  astore_1
  aload_1
  aload 11
  iload 12
  invokevirtual android/os/Bundle/putInt(Ljava/lang/String;I)V
  aload 6
  getfield com/mobisage/android/MobiSageMessage/result Landroid/os/Bundle;
  astore_1
  aload_1
  astore 26
  aload 6
  getfield com/mobisage/android/MobiSageMessage/c Ljava/util/UUID;
  astore_1
  aload_1
  astore 57
  aload 57
  astore_1
  aload_1
  invokevirtual java/util/UUID/toString()Ljava/lang/String;
  astore 58
  ldc "did"
  astore 11
  aload 26
  astore_1
  aload 58
  astore_2
  aload_1
  aload 11
  aload_2
  invokevirtual android/os/Bundle/putString(Ljava/lang/String;Ljava/lang/String;)V
  aload 6
  getfield com/mobisage/android/MobiSageMessage/result Landroid/os/Bundle;
  astore_1
  aload_1
  astore 26
  ldc "ExtraData"
  astore 11
  aload 55
  astore_1
  aload 26
  astore_2
  aload_1
  aload 11
  aload_2
  invokevirtual android/content/Intent/putExtra(Ljava/lang/String;Landroid/os/Bundle;)Landroid/content/Intent;
  pop
  aload 54
  astore_1
  aload 55
  astore_2
  aload_1
  aload_2
  invokevirtual android/content/Context/startService(Landroid/content/Intent;)Landroid/content/ComponentName;
  pop
Label6:
  return
Label5:
  new java/io/File
  astore 59
  aload 6
  getfield com/mobisage/android/MobiSageResMessage/targetURL Ljava/lang/String;
  astore_1
  aload_1
  astore 58
Label10:
  aload 59
  astore_1
  aload 58
  astore_2
  aload_1
  aload_2
  invokespecial java/io/File/<init>(Ljava/lang/String;)V
  aload 32
  astore_1
  aload 59
  astore_2
  aload_1
  aload_2
  invokevirtual java/io/File/renameTo(Ljava/io/File;)Z
  pop
Label11:
  goto Label0
Label8:
  astore 60
Label12:
  aload 6
  getfield com/mobisage/android/MobiSageMessage/result Landroid/os/Bundle;
  astore_1
  aload_1
  astore 26
  ldc "StatusCode"
  astore 11
  sipush 400
  istore 12
  aload 26
  astore_1
  aload_1
  aload 11
  iload 12
  invokevirtual android/os/Bundle/putInt(Ljava/lang/String;I)V
  aload 6
  getfield com/mobisage/android/MobiSageMessage/result Landroid/os/Bundle;
  astore_1
  aload_1
  astore 26
  aload 60
  astore_1
  aload_1
  invokevirtual java/io/IOException/getLocalizedMessage()Ljava/lang/String;
  astore 29
  ldc "ErrorText"
  astore 11
  aload 26
  astore_1
  aload 29
  astore_2
  aload_1
  aload 11
  aload_2
  invokevirtual android/os/Bundle/putString(Ljava/lang/String;Ljava/lang/String;)V
Label13:
  getstatic com/mobisage/android/r/h Landroid/content/Context;
  astore 54
  new android/content/Intent
  astore 55
  ldc com/mobisage/android/MobiSageApkService
  astore 56
  aload 55
  astore_1
  aload 54
  astore_2
  aload 56
  astore_3
  aload_1
  aload_2
  aload_3
  invokespecial android/content/Intent/<init>(Landroid/content/Context;Ljava/lang/Class;)V
  aload 6
  getfield com/mobisage/android/MobiSageMessage/result Landroid/os/Bundle;
  astore_1
  aload_1
  astore 26
  ldc "action"
  astore 11
  iconst_3
  istore 12
  aload 26
  astore_1
  aload_1
  aload 11
  iload 12
  invokevirtual android/os/Bundle/putInt(Ljava/lang/String;I)V
  aload 6
  getfield com/mobisage/android/MobiSageMessage/result Landroid/os/Bundle;
  astore_1
  aload_1
  astore 26
  aload 6
  getfield com/mobisage/android/MobiSageMessage/c Ljava/util/UUID;
  astore_1
  aload_1
  astore 57
  aload 57
  astore_1
  aload_1
  invokevirtual java/util/UUID/toString()Ljava/lang/String;
  astore 29
  ldc "did"
  astore 11
  aload 26
  astore_1
  aload 29
  astore_2
  aload_1
  aload 11
  aload_2
  invokevirtual android/os/Bundle/putString(Ljava/lang/String;Ljava/lang/String;)V
  aload 6
  getfield com/mobisage/android/MobiSageMessage/result Landroid/os/Bundle;
  astore_1
  aload_1
  astore 26
  ldc "ExtraData"
  astore 11
  aload 55
  astore_1
  aload 26
  astore_2
  aload_1
  aload 11
  aload_2
  invokevirtual android/content/Intent/putExtra(Ljava/lang/String;Landroid/os/Bundle;)Landroid/content/Intent;
  pop
  aload 54
  astore_1
  aload 55
  astore_2
  aload_1
  aload_2
  invokevirtual android/content/Context/startService(Landroid/content/Intent;)Landroid/content/ComponentName;
  pop
  goto Label6
Label7:
  astore 61
  getstatic com/mobisage/android/r/h Landroid/content/Context;
  astore 54
  new android/content/Intent
  astore 55
  ldc com/mobisage/android/MobiSageApkService
  astore 56
  aload 55
  astore_1
  aload 54
  astore_2
  aload 56
  astore_3
  aload_1
  aload_2
  aload_3
  invokespecial android/content/Intent/<init>(Landroid/content/Context;Ljava/lang/Class;)V
  aload 6
  getfield com/mobisage/android/MobiSageMessage/result Landroid/os/Bundle;
  astore_1
  aload_1
  astore 26
  ldc "action"
  astore 11
  iconst_3
  istore 12
  aload 26
  astore_1
  aload_1
  aload 11
  iload 12
  invokevirtual android/os/Bundle/putInt(Ljava/lang/String;I)V
  aload 6
  getfield com/mobisage/android/MobiSageMessage/result Landroid/os/Bundle;
  astore_1
  aload_1
  astore 26
  aload 6
  getfield com/mobisage/android/MobiSageMessage/c Ljava/util/UUID;
  astore_1
  aload_1
  astore 57
  aload 57
  astore_1
  aload_1
  invokevirtual java/util/UUID/toString()Ljava/lang/String;
  astore 29
  ldc "did"
  astore 11
  aload 26
  astore_1
  aload 29
  astore_2
  aload_1
  aload 11
  aload_2
  invokevirtual android/os/Bundle/putString(Ljava/lang/String;Ljava/lang/String;)V
  aload 6
  getfield com/mobisage/android/MobiSageMessage/result Landroid/os/Bundle;
  astore_1
  aload_1
  astore 26
  ldc "ExtraData"
  astore 11
  aload 55
  astore_1
  aload 26
  astore_2
  aload_1
  aload 11
  aload_2
  invokevirtual android/content/Intent/putExtra(Ljava/lang/String;Landroid/os/Bundle;)Landroid/content/Intent;
  pop
  aload 54
  astore_1
  aload 55
  astore_2
  aload_1
  aload_2
  invokevirtual android/content/Context/startService(Landroid/content/Intent;)Landroid/content/ComponentName;
  pop
  aload 61
  athrow
  nop
.end <method>

