.source dalvik_source_VirusShare_32e70f448ebd75661a1cb12f9cd8e013.apk
.class public  com/kuguo/ad/t
.super java/lang/Object
.field private static "b" Lcom/kuguo/ad/t;
.field private "a" Landroid/content/Context;
.field private "c" Landroid/os/Handler;

.method private <init>(Landroid/content/Context;)V
.limit locals 3
.limit stack 200
  nop
  aload_0
  invokespecial java/lang/Object/<init>()V
  new java/lang/NoClassDefFoundError
  dup
  invokespecial java/lang/NoClassDefFoundError/<init>()V
  athrow
  aload_2
  aload_0
  invokespecial com/kuguo/ad/a/<init>(Lcom/kuguo/ad/t;)V
  aload_0
  aload_2
  putfield com/kuguo/ad/t/c Landroid/os/Handler;
  aload_0
  aload_1
  putfield com/kuguo/ad/t/a Landroid/content/Context;
  return
  nop
.end <method>

.method protected static a(I)I
.limit locals 2
.limit stack 200
  nop
  new java/lang/NoClassDefFoundError
  dup
  invokespecial java/lang/NoClassDefFoundError/<init>()V
  athrow
  iload_0
  lookupswitch
  0 : Label1
  1 : Label2
  2 : Label3
  3 : Label4
  4 : Label5
  default : Label0
Label0:
  goto Label1
Label1:
  ldc 17301586
  istore_1
  iload_1
  ireturn
Label2:
  ldc 17301646
  istore_1
  iload_1
  ireturn
Label3:
  ldc 17301647
  istore_1
  iload_1
  ireturn
Label4:
  ldc 17301547
  istore_1
  iload_1
  ireturn
Label5:
  ldc 17301651
  istore_1
  iload_1
  ireturn
  nop
  nop
  nop
.end <method>

.method static a(Lcom/kuguo/ad/t;)Landroid/content/Context;
  .synthetic
.limit locals 2
.limit stack 200
  nop
  aload_0
  getfield com/kuguo/ad/t/a Landroid/content/Context;
  astore_1
  aload_1
  areturn
  nop
.end <method>

.method public static a(Landroid/content/Context;)Lcom/kuguo/ad/t;
.limit locals 2
.limit stack 200
  nop
  getstatic com/kuguo/ad/t/b Lcom/kuguo/ad/t;
  astore_1
  new java/lang/NoClassDefFoundError
  dup
  invokespecial java/lang/NoClassDefFoundError/<init>()V
  athrow
  iload_1
  ifne Label0
  new com/kuguo/ad/t
  astore_1
  aload_1
  aload_0
  invokespecial com/kuguo/ad/t/<init>(Landroid/content/Context;)V
  aload_1
  putstatic com/kuguo/ad/t/b Lcom/kuguo/ad/t;
Label0:
  getstatic com/kuguo/ad/t/b Lcom/kuguo/ad/t;
  astore_1
  aload_1
  areturn
  nop
.end <method>

.method protected a()V
.limit locals 3
.limit stack 200
  nop
  aload_0
  getfield com/kuguo/ad/t/a Landroid/content/Context;
  astore_1
  aload_1
  invokestatic com/kuguo/ad/d/d(Landroid/content/Context;)[Lcom/kuguo/ad/p;
  astore_2
  aload_0
  aload_2
  invokevirtual com/kuguo/ad/t/a([Lcom/kuguo/ad/p;)V
  return
  nop
.end <method>

.method protected static a(Landroid/content/Context;Lcom/kuguo/ad/p;)V
.limit locals 16
.limit stack 200
  nop
  aload_1
  getfield com/kuguo/ad/p/e B
  istore 9
  new java/lang/NoClassDefFoundError
  dup
  invokespecial java/lang/NoClassDefFoundError/<init>()V
  athrow
  iload 9
  lookupswitch
  1 : Label1
  2 : Label1
  3 : Label2
  4 : Label2
  5 : Label1
  6 : Label2
  7 : Label1
  8 : Label1
  default : Label0
Label0:
  goto Label3
Label3:
  return
Label1:
  aload_0
  aload_1
  invokestatic com/kuguo/ad/t/b(Landroid/content/Context;Lcom/kuguo/ad/p;)Landroid/content/Intent;
  astore 10
  aload_1
  getfield com/kuguo/ad/p/D I
  istore 11
  iload 11
  invokestatic com/kuguo/ad/t/a(I)I
  istore 12
  aload_1
  getfield com/kuguo/ad/p/t I
  istore 11
  iconst_1
  istore 14
  iload 14
  istore 13
  dload 11
  invokestatic app/DummyClass/invokeIfStmt(D)V
  dload 13
  invokestatic app/DummyClass/invokeIfStmt(D)V
  iload 11
  iload 13
  if_icmpne Label4
  bipush 32
  istore 11
Label5:
  iconst_1
  istore 14
  iconst_0
  istore 15
  aload_0
  astore_2
  aload 10
  astore_3
  iload 12
  istore 4
  aload_1
  astore 5
  iload 11
  istore 6
  iload 14
  istore 7
  iload 15
  istore 8
  aload_2
  aload_3
  iload 4
  aload 5
  iload 6
  iload 7
  iload 8
  invokestatic com/kuguo/ad/d/a(Landroid/content/Context;Landroid/content/Intent;ILcom/kuguo/ad/p;IZZ)V
  goto Label3
Label4:
  getstatic com/kuguo/ad/d/a I
  istore 11
  goto Label5
Label2:
  aload_0
  aload_1
  invokestatic com/kuguo/ad/MainActivity/a(Landroid/content/Context;Lcom/kuguo/ad/p;)V
  goto Label3
  nop
  nop
.end <method>

.method protected a(Lcom/kuguo/ad/p;)V
.limit locals 4
.limit stack 200
  nop
  new java/lang/NoClassDefFoundError
  dup
  invokespecial java/lang/NoClassDefFoundError/<init>()V
  athrow
  aload_2
  invokespecial android/os/Message/<init>()V
  aload_2
  aload_1
  putfield android/os/Message/obj Ljava/lang/Object;
  aload_0
  getfield com/kuguo/ad/t/c Landroid/os/Handler;
  astore_3
  aload_3
  aload_2
  invokevirtual android/os/Handler/sendMessage(Landroid/os/Message;)Z
  pop
  return
  nop
.end <method>

.method protected a(Ljava/io/InputStream;)V
.limit locals 32
.limit stack 200
  .catch  java/lang/Throwable <from> Label18 <to> Label19 <using> Label16
  .catch  java/io/IOException <from> Label18 <to> Label19 <using> Label17
  .catch  java/lang/Throwable <from> Label22 <to> Label23 <using> Label20
  .catch  java/io/IOException <from> Label22 <to> Label23 <using> Label21
  .catch  java/lang/Throwable <from> Label1 <to> Label26 <using> Label24
  .catch  java/io/IOException <from> Label1 <to> Label26 <using> Label25
  .catch  java/lang/Throwable <from> Label15 <to> Label27 <using> Label27
  .catch  java/lang/Throwable <from> Label0 <to> Label28 <using> Label24
  .catch  java/lang/Throwable <from> Label28 <to> Label29 <using> Label24
  .catch  java/io/IOException <from> Label28 <to> Label29 <using> Label25
  .catch  java/lang/Throwable <from> Label29 <to> Label30 <using> Label24
  .catch  java/lang/Throwable <from> Label5 <to> Label31 <using> Label24
  .catch  java/io/IOException <from> Label5 <to> Label31 <using> Label25
  .catch  java/lang/Throwable <from> Label32 <to> Label33 <using> Label24
  .catch  java/io/IOException <from> Label32 <to> Label33 <using> Label25
  nop
  aconst_null
  astore 5
  iconst_0
  istore 6
  new java/io/ByteArrayOutputStream
  astore 7
  aload 7
  astore 8
Label18:
  aload 7
  invokespecial java/io/ByteArrayOutputStream/<init>()V
Label19:
  new java/io/DataInputStream
  astore 9
  aload 9
  astore 10
Label22:
  aload_1
  astore_2
  aload 9
  aload_2
  invokespecial java/io/DataInputStream/<init>(Ljava/io/InputStream;)V
Label23:
  sipush 512
  istore 12
  iload 12
  newarray byte
  astore 11
Label1:
  aload 9
  aload 11
  invokevirtual java/io/DataInputStream/read([B)I
  istore 13
  new java/lang/NoClassDefFoundError
  dup
  invokespecial java/lang/NoClassDefFoundError/<init>()V
  athrow
  iconst_m1
  istore 12
  iload 13
  iload 12
  if_icmpeq Label0
  aload 8
  astore 14
  aload 14
  checkcast java/io/ByteArrayOutputStream
  astore 14
  aload 14
  astore 7
  iconst_0
  istore 12
  aload 7
  aload 11
  iload 12
  iload 13
  invokevirtual java/io/ByteArrayOutputStream/write([BII)V
  aload 8
  astore 15
  aload 15
  checkcast java/io/ByteArrayOutputStream
  astore 15
  aload 15
  astore 7
  aload 7
  invokevirtual java/io/ByteArrayOutputStream/flush()V
Label26:
  goto Label1
Label25:
  astore 16
  aload 9
  astore 5
Label15:
  new java/lang/Exception
  astore 17
  aload 17
  aload 16
  invokespecial java/lang/Exception/<init>(Ljava/lang/Throwable;)V
  aload 17
  athrow
Label27:
  astore 18
  aload 5
  astore 10
Label14:
  new java/lang/NoClassDefFoundError
  dup
  invokespecial java/lang/NoClassDefFoundError/<init>()V
  athrow
  iload 8
  ifeq Label2
  aload 8
  astore 19
  aload 19
  checkcast java/io/ByteArrayOutputStream
  astore 19
  aload 19
  astore 7
  aload 7
  invokevirtual java/io/ByteArrayOutputStream/close()V
Label2:
  aload 10
  invokestatic app/DummyClass/invokeIfStmt(Ljava/lang/Object;)V
  iload 10
  ifeq Label3
  aload 10
  invokevirtual java/io/DataInputStream/close()V
Label3:
  aload 18
  athrow
Label0:
  aload 8
  astore 20
  aload 20
  checkcast java/io/ByteArrayOutputStream
  astore 20
  aload 20
  astore 7
Label28:
  aload 7
  invokevirtual java/io/ByteArrayOutputStream/toByteArray()[B
  astore 11
Label29:
  aload 11
  invokestatic app/DummyClass/invokeIfStmt(Ljava/lang/Object;)V
  aload 11
  ifnull Label4
  aload 11
  arraylength
  istore_2
  iload_2
  istore 21
Label30:
  dload_2
  invokestatic app/DummyClass/invokeIfStmt(D)V
  iload 21
  ifne Label5
Label4:
  aload 8
  invokestatic app/DummyClass/invokeIfStmt(Ljava/lang/Object;)V
  iload 8
  ifeq Label6
  aload 8
  astore 22
  aload 22
  checkcast java/io/ByteArrayOutputStream
  astore 22
  aload 22
  astore 7
  aload 7
  invokevirtual java/io/ByteArrayOutputStream/close()V
Label6:
  aload 9
  invokestatic app/DummyClass/invokeIfStmt(Ljava/lang/Object;)V
  iload 9
  ifeq Label7
  aload 9
  invokevirtual java/io/DataInputStream/close()V
Label7:
  return
Label5:
  aload 11
  invokestatic com/kuguo/ad/p/a([B)[Lcom/kuguo/ad/p;
  astore 23
Label31:
  aload 23
  astore_2
  aload_2
  invokestatic app/DummyClass/invokeIfStmt(Ljava/lang/Object;)V
  aload 23
  ifnonnull Label8
  aload 8
  invokestatic app/DummyClass/invokeIfStmt(Ljava/lang/Object;)V
  iload 8
  ifeq Label9
  aload 8
  astore 24
  aload 24
  checkcast java/io/ByteArrayOutputStream
  astore 24
  aload 24
  astore 7
  aload 7
  invokevirtual java/io/ByteArrayOutputStream/close()V
Label9:
  aload 9
  invokestatic app/DummyClass/invokeIfStmt(Ljava/lang/Object;)V
  iload 9
  ifeq Label7
  aload 9
  invokevirtual java/io/DataInputStream/close()V
  goto Label7
Label8:
  aload 23
  astore_2
  aload_2
  arraylength
  istore_2
  iload_2
  istore 21
Label12:
  dload 6
  invokestatic app/DummyClass/invokeIfStmt(D)V
  iload 21
  istore_2
  dload_2
  invokestatic app/DummyClass/invokeIfStmt(D)V
  iload 21
  istore_2
  iload 6
  iload_2
  if_icmpge Label10
  aload 23
  iload 6
  aaload
  astore 25
  aload_0
  astore_2
  aload_2
  getfield com/kuguo/ad/t/a Landroid/content/Context;
  astore_2
  aload_2
  astore 26
Label32:
  aload 26
  astore_2
  aload 25
  astore_3
  aload_2
  aload_3
  invokestatic com/kuguo/ad/d/a(Landroid/content/Context;Lcom/kuguo/ad/p;)Z
  pop
  aload 25
  astore_2
  aload_2
  getfield com/kuguo/ad/p/y I
  istore_2
  iload_2
  istore 27
  dload_2
  invokestatic app/DummyClass/invokeIfStmt(D)V
  iconst_1
  istore 12
  iload 27
  istore_2
  iload_2
  iload 12
  if_icmpeq Label11
  aload 25
  astore_2
  aload_2
  getfield com/kuguo/ad/p/F Ljava/lang/String;
  astore_2
  aload_2
  astore 28
  aload 28
  astore_2
  aload_2
  invokestatic com/kuguo/ad/d/c(Ljava/lang/String;)Z
  pop
  aload 25
  astore_2
  aload_2
  getfield com/kuguo/ad/p/A I
  istore_2
  iload_2
  istore 27
  iload_2
  i2l
  lstore_2
  lload_2
  lstore 29
  lload 29
  lstore_2
  lload_2
  invokestatic com/kuguo/ad/d/a(J)V
Label11:
  iload 6
  iconst_1
  iadd
  istore 6
  goto Label12
Label10:
  aload_0
  astore_2
  aload 23
  astore_3
  aload_2
  aload_3
  invokevirtual com/kuguo/ad/t/a([Lcom/kuguo/ad/p;)V
Label33:
  aload 8
  invokestatic app/DummyClass/invokeIfStmt(Ljava/lang/Object;)V
  iload 8
  ifeq Label13
  aload 8
  astore 31
  aload 31
  checkcast java/io/ByteArrayOutputStream
  astore 31
  aload 31
  astore 7
  aload 7
  invokevirtual java/io/ByteArrayOutputStream/close()V
Label13:
  aload 9
  invokestatic app/DummyClass/invokeIfStmt(Ljava/lang/Object;)V
  iload 9
  ifeq Label7
  aload 9
  invokevirtual java/io/DataInputStream/close()V
  goto Label7
Label16:
  astore 18
  iconst_0
  istore 8
  iconst_0
  istore 10
  goto Label14
Label20:
  astore 18
  iconst_0
  istore 10
  goto Label14
Label24:
  astore 18
  goto Label14
Label17:
  astore 16
  iconst_0
  istore 8
  goto Label15
Label21:
  astore 16
  goto Label15
  nop
.end <method>

.method protected a([Lcom/kuguo/ad/p;)V
.limit locals 12
.limit stack 200
  nop
  new java/lang/NoClassDefFoundError
  dup
  invokespecial java/lang/NoClassDefFoundError/<init>()V
  athrow
  iload_1
  ifne Label0
Label1:
  return
Label0:
  aload_0
  getfield com/kuguo/ad/t/a Landroid/content/Context;
  astore_2
  aload_2
  invokestatic com/kuguo/a/e/a(Landroid/content/Context;)Lcom/kuguo/a/e;
  pop
  aload_1
  arraylength
  istore_3
  iconst_0
  dstore 4
Label3:
  dload 4
  invokestatic app/DummyClass/invokeIfStmt(D)V
  dload_3
  invokestatic app/DummyClass/invokeIfStmt(D)V
  iload 4
  iload_3
  if_icmpge Label1
  aload_1
  iload 4
  aaload
  astore 5
  aload 5
  getfield com/kuguo/ad/p/h I
  istore 6
  dload 6
  invokestatic app/DummyClass/invokeIfStmt(D)V
  iconst_m1
  istore 7
  iload 6
  iload 7
  if_icmpne Label2
Label5:
  iload 4
  iconst_1
  iadd
  istore 4
  goto Label3
Label2:
  aload 5
  invokevirtual com/kuguo/ad/p/b()V
  aload_0
  getfield com/kuguo/ad/t/a Landroid/content/Context;
  astore_2
  aload 5
  getfield com/kuguo/ad/p/i Ljava/lang/String;
  astore 8
  aload_2
  aload 8
  invokestatic com/kuguo/ad/d/c(Landroid/content/Context;Ljava/lang/String;)Z
  istore 9
  iload 9
  invokestatic app/DummyClass/invokeIfStmt(Z)V
  iload 9
  ifeq Label4
  aload 5
  getfield com/kuguo/ad/p/y I
  istore 6
  dload 6
  invokestatic app/DummyClass/invokeIfStmt(D)V
  iconst_1
  istore 7
  iload 6
  iload 7
  if_icmpne Label5
Label4:
  aload 5
  getfield com/kuguo/ad/p/j Ljava/lang/Integer;
  astore 10
  aload 10
  invokevirtual java/lang/Integer/intValue()I
  istore 11
  dload 11
  invokestatic app/DummyClass/invokeIfStmt(D)V
  iconst_m1
  istore 7
  iload 11
  iload 7
  if_icmpne Label5
  aload_0
  aload 5
  invokespecial com/kuguo/ad/t/b(Lcom/kuguo/ad/p;)V
  goto Label5
  nop
.end <method>

.method protected static b(Landroid/content/Context;Lcom/kuguo/ad/p;)Landroid/content/Intent;
.limit locals 8
.limit stack 200
  nop
  new java/lang/NoClassDefFoundError
  dup
  invokespecial java/lang/NoClassDefFoundError/<init>()V
  athrow
  ldc com/kuguo/ad/MainActivity
  astore_3
  aload_2
  aload_0
  aload_3
  invokespecial android/content/Intent/<init>(Landroid/content/Context;Ljava/lang/Class;)V
  ldc 268435456
  istore 4
  aload_2
  iload 4
  invokevirtual android/content/Intent/setFlags(I)Landroid/content/Intent;
  pop
  aload_1
  invokevirtual com/kuguo/ad/p/a()Ljava/lang/String;
  astore 5
  ldc "message"
  astore 6
  aload_2
  aload 6
  aload 5
  invokevirtual android/content/Intent/putExtra(Ljava/lang/String;Ljava/lang/String;)Landroid/content/Intent;
  pop
  aload_1
  getfield com/kuguo/ad/p/f I
  istore 7
  ldc "sharedid"
  astore 6
  aload_2
  aload 6
  iload 7
  invokevirtual android/content/Intent/putExtra(Ljava/lang/String;I)Landroid/content/Intent;
  pop
  ldc "shortcut"
  astore 6
  iconst_0
  istore 4
  aload_2
  aload 6
  iload 4
  invokevirtual android/content/Intent/putExtra(Ljava/lang/String;Z)Landroid/content/Intent;
  pop
  aload_2
  areturn
  nop
.end <method>

.method private b(Lcom/kuguo/ad/p;)V
.limit locals 21
.limit stack 200
  nop
  new java/lang/NoClassDefFoundError
  dup
  invokespecial java/lang/NoClassDefFoundError/<init>()V
  athrow
  aload_0
  astore_2
  aload_2
  getfield com/kuguo/ad/t/a Landroid/content/Context;
  astore 4
  ldc com/kuguo/ad/MainReceiver
  astore 5
  aload_3
  aload 4
  aload 5
  invokespecial android/content/Intent/<init>(Landroid/content/Context;Ljava/lang/Class;)V
  aload_1
  astore_2
  aload_2
  invokevirtual java/lang/Object/getClass()Ljava/lang/Class;
  astore 6
  aload 6
  invokevirtual java/lang/Class/getClassLoader()Ljava/lang/ClassLoader;
  astore 7
  aload_3
  aload 7
  invokevirtual android/content/Intent/setExtrasClassLoader(Ljava/lang/ClassLoader;)V
  ldc "type"
  astore 8
  ldc "AdAlarm"
  astore 9
  aload_3
  aload 8
  aload 9
  invokevirtual android/content/Intent/putExtra(Ljava/lang/String;Ljava/lang/String;)Landroid/content/Intent;
  pop
  aload_1
  astore_2
  aload_2
  getfield com/kuguo/ad/p/f I
  istore 10
  ldc "sharedid"
  astore 8
  aload_3
  aload 8
  iload 10
  invokevirtual android/content/Intent/putExtra(Ljava/lang/String;I)Landroid/content/Intent;
  pop
  aload_1
  astore_2
  aload_2
  invokevirtual com/kuguo/ad/p/a()Ljava/lang/String;
  astore 11
  ldc "message"
  astore 8
  aload_3
  aload 8
  aload 11
  invokevirtual android/content/Intent/putExtra(Ljava/lang/String;Ljava/lang/String;)Landroid/content/Intent;
  pop
  aload_0
  astore_2
  aload_2
  getfield com/kuguo/ad/t/a Landroid/content/Context;
  astore 4
  aload_1
  astore_2
  aload_2
  getfield com/kuguo/ad/p/h I
  istore 12
  ldc 134217728
  istore 14
  aload 4
  iload 12
  aload_3
  iload 14
  invokestatic android/app/PendingIntent/getBroadcast(Landroid/content/Context;ILandroid/content/Intent;I)Landroid/app/PendingIntent;
  astore 13
  invokestatic java/util/Calendar/getInstance()Ljava/util/Calendar;
  astore 15
  invokestatic java/lang/System/currentTimeMillis()J
  lstore 16
  aload 15
  lload 16
  invokevirtual java/util/Calendar/setTimeInMillis(J)V
  aload_0
  astore_2
  aload_2
  getfield com/kuguo/ad/t/a Landroid/content/Context;
  astore 4
  ldc "alarm"
  astore 8
  aload 4
  aload 8
  invokevirtual android/content/Context/getSystemService(Ljava/lang/String;)Ljava/lang/Object;
  astore 18
  aload 18
  astore 20
  aload 20
  checkcast android/app/AlarmManager
  astore 20
  aload 20
  astore 19
  aload 15
  invokevirtual java/util/Calendar/getTimeInMillis()J
  lstore 16
  iconst_0
  istore 14
  aload 19
  astore_2
  aload_2
  iload 14
  lload 16
  aload 13
  invokevirtual android/app/AlarmManager/set(IJLandroid/app/PendingIntent;)V
  ldc "have set the alarm!"
  astore 8
  aload 8
  invokestatic com/kuguo/ad/d/a(Ljava/lang/String;)V
  return
  nop
.end <method>

