.source SourceFile
.class final  com/mobisage/android/F
.super java/lang/Object
.field "a" Ljava/lang/String;
.field "b" Ljava/lang/String;
.field "c" Ljava/lang/String;
.field "d" Ljava/lang/String;
.field "e" Ljava/lang/String;
.field private "f" Landroid/content/Context;

.method <init>(Landroid/content/Context;)V
.limit locals 2
.limit stack 200
  nop
  aload_0
  invokespecial java/lang/Object/<init>()V
  aload_0
  aload_1
  putfield com/mobisage/android/F/f Landroid/content/Context;
  return
  nop
.end <method>

.method static a(Lcom/mobisage/android/F;)Landroid/content/Context;
  .synthetic
.limit locals 2
.limit stack 200
  nop
  aload_0
  getfield com/mobisage/android/F/f Landroid/content/Context;
  astore_1
  aload_1
  areturn
  nop
.end <method>

.method private a(Ljava/util/HashMap;)V
  .signature_attr "(Ljava/util/HashMap<Ljava/lang/String;Ljava/lang/String;>;)V"
.limit locals 21
.limit stack 200
  nop
  new com/mobisage/android/b
  astore_3
  aload_3
  invokespecial com/mobisage/android/b/<init>()V
  aload_3
  getfield com/mobisage/android/b/c Landroid/os/Bundle;
  astore 4
  ldc "eventtype"
  astore 6
  aload_1
  astore_2
  aload_2
  aload 6
  invokevirtual java/util/HashMap/get(Ljava/lang/Object;)Ljava/lang/Object;
  astore 5
  aload 5
  astore 8
  aload 8
  checkcast java/lang/String
  astore 8
  aload 8
  astore 7
  ldc "EventType"
  astore 6
  new java/lang/NoClassDefFoundError
  dup
  invokespecial java/lang/NoClassDefFoundError/<init>()V
  athrow
  ldc "token"
  astore 6
  aload_1
  astore_2
  aload_2
  aload 6
  invokevirtual java/util/HashMap/containsKey(Ljava/lang/Object;)Z
  istore 9
  iload 9
  invokestatic app/DummyClass/invokeIfStmt(Z)V
  iload 9
  ifeq Label0
  aload_3
  getfield com/mobisage/android/b/c Landroid/os/Bundle;
  astore 4
  ldc "token"
  astore 6
  aload_1
  astore_2
  aload_2
  aload 6
  invokevirtual java/util/HashMap/get(Ljava/lang/Object;)Ljava/lang/Object;
  astore 5
  aload 5
  astore 10
  aload 10
  checkcast java/lang/String
  astore 10
  aload 10
  astore 7
  ldc "Token"
  astore 6
  aload 4
  aload 6
  aload 7
  invokevirtual android/os/Bundle/putString(Ljava/lang/String;Ljava/lang/String;)V
Label5:
  ldc "adid"
  astore 6
  aload_1
  astore_2
  aload_2
  aload 6
  invokevirtual java/util/HashMap/containsKey(Ljava/lang/Object;)Z
  istore 9
  iload 9
  invokestatic app/DummyClass/invokeIfStmt(Z)V
  iload 9
  ifeq Label1
  aload_3
  getfield com/mobisage/android/b/c Landroid/os/Bundle;
  astore 4
  ldc "adid"
  astore 6
  aload_1
  astore_2
  aload_2
  aload 6
  invokevirtual java/util/HashMap/get(Ljava/lang/Object;)Ljava/lang/Object;
  astore 5
  aload 5
  astore 11
  aload 11
  checkcast java/lang/String
  astore 11
  aload 11
  astore 7
  ldc "AdID"
  astore 6
  aload 4
  aload 6
  aload 7
  invokevirtual android/os/Bundle/putString(Ljava/lang/String;Ljava/lang/String;)V
Label6:
  ldc "adgroupid"
  astore 6
  aload_1
  astore_2
  aload_2
  aload 6
  invokevirtual java/util/HashMap/containsKey(Ljava/lang/Object;)Z
  istore 9
  iload 9
  invokestatic app/DummyClass/invokeIfStmt(Z)V
  iload 9
  ifeq Label2
  aload_3
  getfield com/mobisage/android/b/c Landroid/os/Bundle;
  astore 4
  ldc "adgroupid"
  astore 6
  aload_1
  astore_2
  aload_2
  aload 6
  invokevirtual java/util/HashMap/get(Ljava/lang/Object;)Ljava/lang/Object;
  astore 5
  aload 5
  astore 12
  aload 12
  checkcast java/lang/String
  astore 12
  aload 12
  astore 7
  ldc "AdGroupID"
  astore 6
  aload 4
  aload 6
  aload 7
  invokevirtual android/os/Bundle/putString(Ljava/lang/String;Ljava/lang/String;)V
Label7:
  ldc "tag"
  astore 6
  aload_1
  astore_2
  aload_2
  aload 6
  invokevirtual java/util/HashMap/containsKey(Ljava/lang/Object;)Z
  istore 9
  iload 9
  invokestatic app/DummyClass/invokeIfStmt(Z)V
  iload 9
  ifeq Label3
  aload_3
  getfield com/mobisage/android/b/c Landroid/os/Bundle;
  astore 4
  ldc "tag"
  astore 6
  aload_1
  astore_2
  aload_2
  aload 6
  invokevirtual java/util/HashMap/get(Ljava/lang/Object;)Ljava/lang/Object;
  astore 5
  aload 5
  astore 13
  aload 13
  checkcast java/lang/String
  astore 13
  aload 13
  astore 7
  ldc "Tag"
  astore 6
  aload 4
  aload 6
  aload 7
  invokevirtual android/os/Bundle/putString(Ljava/lang/String;Ljava/lang/String;)V
Label3:
  aload_0
  astore_2
  aload_2
  getfield com/mobisage/android/F/b Ljava/lang/String;
  astore 14
  aload 14
  invokestatic app/DummyClass/invokeIfStmt(Ljava/lang/Object;)V
  aload 14
  ifnull Label4
  aload_3
  getfield com/mobisage/android/b/c Landroid/os/Bundle;
  astore 4
  aload_0
  astore_2
  aload_2
  getfield com/mobisage/android/F/b Ljava/lang/String;
  astore 7
  ldc "CustomData"
  astore 6
  aload 4
  aload 6
  aload 7
  invokevirtual android/os/Bundle/putString(Ljava/lang/String;Ljava/lang/String;)V
Label4:
  aload_3
  getfield com/mobisage/android/b/c Landroid/os/Bundle;
  astore 4
  aload_0
  astore_2
  aload_2
  getfield com/mobisage/android/F/c Ljava/lang/String;
  astore 7
  ldc "PublisherID"
  astore 6
  aload 4
  aload 6
  aload 7
  invokevirtual android/os/Bundle/putString(Ljava/lang/String;Ljava/lang/String;)V
  invokestatic com/mobisage/android/Y/a()Lcom/mobisage/android/Y;
  astore 15
  sipush 2005
  istore 16
  aload 15
  iload 16
  aload_3
  invokevirtual com/mobisage/android/Y/a(ILcom/mobisage/android/b;)V
  new android/content/Intent
  astore 17
  ldc "lpg"
  astore 6
  aload_1
  astore_2
  aload_2
  aload 6
  invokevirtual java/util/HashMap/get(Ljava/lang/Object;)Ljava/lang/Object;
  astore 5
  aload 5
  astore 18
  aload 18
  checkcast java/lang/String
  astore 18
  aload 18
  astore 7
  aload 7
  invokestatic android/net/Uri/parse(Ljava/lang/String;)Landroid/net/Uri;
  astore 19
  ldc "android.intent.action.VIEW"
  astore 6
  aload 19
  astore_2
  aload 17
  aload 6
  aload_2
  invokespecial android/content/Intent/<init>(Ljava/lang/String;Landroid/net/Uri;)V
  aload_0
  astore_2
  aload_2
  getfield com/mobisage/android/F/f Landroid/content/Context;
  astore_2
  aload_2
  astore 20
  aload 20
  astore_2
  aload_2
  aload 17
  invokevirtual android/content/Context/startActivity(Landroid/content/Intent;)V
  return
Label0:
  aload_3
  getfield com/mobisage/android/b/c Landroid/os/Bundle;
  astore 4
  aload_0
  astore_2
  aload_2
  getfield com/mobisage/android/F/a Ljava/lang/String;
  astore 7
  ldc "Token"
  astore 6
  aload 4
  aload 6
  aload 7
  invokevirtual android/os/Bundle/putString(Ljava/lang/String;Ljava/lang/String;)V
  goto Label5
Label1:
  aload_3
  getfield com/mobisage/android/b/c Landroid/os/Bundle;
  astore 4
  aload_0
  astore_2
  aload_2
  getfield com/mobisage/android/F/d Ljava/lang/String;
  astore 7
  ldc "AdID"
  astore 6
  aload 4
  aload 6
  aload 7
  invokevirtual android/os/Bundle/putString(Ljava/lang/String;Ljava/lang/String;)V
  goto Label6
Label2:
  aload_3
  getfield com/mobisage/android/b/c Landroid/os/Bundle;
  astore 4
  aload_0
  astore_2
  aload_2
  getfield com/mobisage/android/F/e Ljava/lang/String;
  astore 7
  ldc "AdGroupID"
  astore 6
  aload 4
  aload 6
  aload 7
  invokevirtual android/os/Bundle/putString(Ljava/lang/String;Ljava/lang/String;)V
  goto Label7
  nop
.end <method>

.method private b(Ljava/util/HashMap;)V
  .signature_attr "(Ljava/util/HashMap<Ljava/lang/String;Ljava/lang/String;>;)V"
.limit locals 27
.limit stack 200
  nop
  new com/mobisage/android/b
  astore 5
  aload 5
  invokespecial com/mobisage/android/b/<init>()V
  aload 5
  getfield com/mobisage/android/b/c Landroid/os/Bundle;
  astore 6
  ldc "eventtype"
  astore 8
  aload_1
  astore_2
  aload_2
  aload 8
  invokevirtual java/util/HashMap/get(Ljava/lang/Object;)Ljava/lang/Object;
  astore 7
  aload 7
  astore 10
  aload 10
  checkcast java/lang/String
  astore 10
  aload 10
  astore 9
  ldc "EventType"
  astore 8
  new java/lang/NoClassDefFoundError
  dup
  invokespecial java/lang/NoClassDefFoundError/<init>()V
  athrow
  ldc "token"
  astore 8
  aload_1
  astore_2
  aload_2
  aload 8
  invokevirtual java/util/HashMap/containsKey(Ljava/lang/Object;)Z
  istore 11
  iload 11
  invokestatic app/DummyClass/invokeIfStmt(Z)V
  iload 11
  ifeq Label0
  aload 5
  getfield com/mobisage/android/b/c Landroid/os/Bundle;
  astore 6
  ldc "token"
  astore 8
  aload_1
  astore_2
  aload_2
  aload 8
  invokevirtual java/util/HashMap/get(Ljava/lang/Object;)Ljava/lang/Object;
  astore 7
  aload 7
  astore 12
  aload 12
  checkcast java/lang/String
  astore 12
  aload 12
  astore 9
  ldc "Token"
  astore 8
  aload 6
  aload 8
  aload 9
  invokevirtual android/os/Bundle/putString(Ljava/lang/String;Ljava/lang/String;)V
Label7:
  ldc "adid"
  astore 8
  aload_1
  astore_2
  aload_2
  aload 8
  invokevirtual java/util/HashMap/containsKey(Ljava/lang/Object;)Z
  istore 11
  iload 11
  invokestatic app/DummyClass/invokeIfStmt(Z)V
  iload 11
  ifeq Label1
  aload 5
  getfield com/mobisage/android/b/c Landroid/os/Bundle;
  astore 6
  ldc "adid"
  astore 8
  aload_1
  astore_2
  aload_2
  aload 8
  invokevirtual java/util/HashMap/get(Ljava/lang/Object;)Ljava/lang/Object;
  astore 7
  aload 7
  astore 13
  aload 13
  checkcast java/lang/String
  astore 13
  aload 13
  astore 9
  ldc "AdID"
  astore 8
  aload 6
  aload 8
  aload 9
  invokevirtual android/os/Bundle/putString(Ljava/lang/String;Ljava/lang/String;)V
Label8:
  ldc "adgroupid"
  astore 8
  aload_1
  astore_2
  aload_2
  aload 8
  invokevirtual java/util/HashMap/containsKey(Ljava/lang/Object;)Z
  istore 11
  iload 11
  invokestatic app/DummyClass/invokeIfStmt(Z)V
  iload 11
  ifeq Label2
  aload 5
  getfield com/mobisage/android/b/c Landroid/os/Bundle;
  astore 6
  ldc "adgroupid"
  astore 8
  aload_1
  astore_2
  aload_2
  aload 8
  invokevirtual java/util/HashMap/get(Ljava/lang/Object;)Ljava/lang/Object;
  astore 7
  aload 7
  astore 14
  aload 14
  checkcast java/lang/String
  astore 14
  aload 14
  astore 9
  ldc "AdGroupID"
  astore 8
  aload 6
  aload 8
  aload 9
  invokevirtual android/os/Bundle/putString(Ljava/lang/String;Ljava/lang/String;)V
Label9:
  ldc "tag"
  astore 8
  aload_1
  astore_2
  aload_2
  aload 8
  invokevirtual java/util/HashMap/containsKey(Ljava/lang/Object;)Z
  istore 11
  iload 11
  invokestatic app/DummyClass/invokeIfStmt(Z)V
  iload 11
  ifeq Label3
  aload 5
  getfield com/mobisage/android/b/c Landroid/os/Bundle;
  astore 6
  ldc "tag"
  astore 8
  aload_1
  astore_2
  aload_2
  aload 8
  invokevirtual java/util/HashMap/get(Ljava/lang/Object;)Ljava/lang/Object;
  astore 7
  aload 7
  astore 15
  aload 15
  checkcast java/lang/String
  astore 15
  aload 15
  astore 9
  ldc "Tag"
  astore 8
  aload 6
  aload 8
  aload 9
  invokevirtual android/os/Bundle/putString(Ljava/lang/String;Ljava/lang/String;)V
Label3:
  aload_0
  astore_2
  aload_2
  getfield com/mobisage/android/F/b Ljava/lang/String;
  astore 16
  aload 16
  invokestatic app/DummyClass/invokeIfStmt(Ljava/lang/Object;)V
  aload 16
  ifnull Label4
  aload 5
  getfield com/mobisage/android/b/c Landroid/os/Bundle;
  astore 6
  aload_0
  astore_2
  aload_2
  getfield com/mobisage/android/F/b Ljava/lang/String;
  astore 9
  ldc "CustomData"
  astore 8
  aload 6
  aload 8
  aload 9
  invokevirtual android/os/Bundle/putString(Ljava/lang/String;Ljava/lang/String;)V
Label4:
  aload 5
  getfield com/mobisage/android/b/c Landroid/os/Bundle;
  astore 6
  aload_0
  astore_2
  aload_2
  getfield com/mobisage/android/F/c Ljava/lang/String;
  astore 9
  ldc "PublisherID"
  astore 8
  aload 6
  aload 8
  aload 9
  invokevirtual android/os/Bundle/putString(Ljava/lang/String;Ljava/lang/String;)V
  invokestatic com/mobisage/android/Y/a()Lcom/mobisage/android/Y;
  astore 17
  sipush 2005
  istore 18
  iload 18
  istore_2
  aload 17
  iload_2
  aload 5
  invokevirtual com/mobisage/android/Y/a(ILcom/mobisage/android/b;)V
  invokestatic android/os/Environment/getExternalStorageDirectory()Ljava/io/File;
  astore 19
  aload 19
  astore_2
  aload_2
  invokevirtual java/io/File/exists()Z
  istore 11
  iload 11
  invokestatic app/DummyClass/invokeIfStmt(Z)V
  iload 11
  ifeq Label5
  aload 19
  astore_2
  aload_2
  invokevirtual java/io/File/canWrite()Z
  istore 11
  iload 11
  invokestatic app/DummyClass/invokeIfStmt(Z)V
  iload 11
  ifne Label6
Label5:
  aload_0
  astore_2
  aload_2
  getfield com/mobisage/android/F/f Landroid/content/Context;
  astore_2
  aload_2
  astore 20
  ldc "Can\'t find sdcard!"
  astore 8
  iconst_5
  istore 18
  aload 20
  astore_2
  iload 18
  istore_3
  aload_2
  aload 8
  iload_3
  invokestatic android/widget/Toast/makeText(Landroid/content/Context;Ljava/lang/CharSequence;I)Landroid/widget/Toast;
  astore 21
  aload 21
  astore_2
  aload_2
  invokevirtual android/widget/Toast/show()V
Label11:
  return
Label0:
  aload 5
  getfield com/mobisage/android/b/c Landroid/os/Bundle;
  astore 6
  aload_0
  astore_2
  aload_2
  getfield com/mobisage/android/F/a Ljava/lang/String;
  astore 9
  ldc "Token"
  astore 8
  aload 6
  aload 8
  aload 9
  invokevirtual android/os/Bundle/putString(Ljava/lang/String;Ljava/lang/String;)V
  goto Label7
Label1:
  aload 5
  getfield com/mobisage/android/b/c Landroid/os/Bundle;
  astore 6
  aload_0
  astore_2
  aload_2
  getfield com/mobisage/android/F/d Ljava/lang/String;
  astore 9
  ldc "AdID"
  astore 8
  aload 6
  aload 8
  aload 9
  invokevirtual android/os/Bundle/putString(Ljava/lang/String;Ljava/lang/String;)V
  goto Label8
Label2:
  aload 5
  getfield com/mobisage/android/b/c Landroid/os/Bundle;
  astore 6
  aload_0
  astore_2
  aload_2
  getfield com/mobisage/android/F/e Ljava/lang/String;
  astore 9
  ldc "AdGroupID"
  astore 8
  aload 6
  aload 8
  aload 9
  invokevirtual android/os/Bundle/putString(Ljava/lang/String;Ljava/lang/String;)V
  goto Label9
Label6:
  new android/content/Intent
  astore 22
  aload_0
  astore_2
  aload_2
  getfield com/mobisage/android/F/f Landroid/content/Context;
  astore_2
  aload_2
  astore 20
  ldc com/mobisage/android/MobiSageApkService
  astore 23
  aload 22
  astore_2
  aload 20
  astore_3
  aload 23
  astore 4
  aload_2
  aload_3
  aload 4
  invokespecial android/content/Intent/<init>(Landroid/content/Context;Ljava/lang/Class;)V
  new android/os/Bundle
  astore 6
  aload 6
  invokespecial android/os/Bundle/<init>()V
  ldc "action"
  astore 8
  iconst_0
  istore 18
  iload 18
  istore_2
  aload 6
  aload 8
  iload_2
  invokevirtual android/os/Bundle/putInt(Ljava/lang/String;I)V
  ldc "lpg"
  astore 8
  aload_1
  astore_2
  aload_2
  aload 8
  invokevirtual java/util/HashMap/get(Ljava/lang/Object;)Ljava/lang/Object;
  astore 7
  aload 7
  astore 24
  aload 24
  checkcast java/lang/String
  astore 24
  aload 24
  astore 9
  ldc "lpg"
  astore 8
  aload 6
  aload 8
  aload 9
  invokevirtual android/os/Bundle/putString(Ljava/lang/String;Ljava/lang/String;)V
  ldc "name"
  astore 8
  aload_1
  astore_2
  aload_2
  aload 8
  invokevirtual java/util/HashMap/containsKey(Ljava/lang/Object;)Z
  istore 11
  iload 11
  invokestatic app/DummyClass/invokeIfStmt(Z)V
  iload 11
  ifeq Label10
  ldc "name"
  astore 8
  aload_1
  astore_2
  aload_2
  aload 8
  invokevirtual java/util/HashMap/get(Ljava/lang/Object;)Ljava/lang/Object;
  astore 7
  aload 7
  astore 25
  aload 25
  checkcast java/lang/String
  astore 25
  aload 25
  astore 9
  ldc "name"
  astore 8
  aload 6
  aload 8
  aload 9
  invokevirtual android/os/Bundle/putString(Ljava/lang/String;Ljava/lang/String;)V
Label12:
  ldc "ExtraData"
  astore 8
  aload 22
  astore_2
  aload_2
  aload 8
  aload 6
  invokevirtual android/content/Intent/putExtra(Ljava/lang/String;Landroid/os/Bundle;)Landroid/content/Intent;
  pop
  aload_0
  astore_2
  aload_2
  getfield com/mobisage/android/F/f Landroid/content/Context;
  astore_2
  aload_2
  astore 20
  aload 20
  astore_2
  aload 22
  astore_3
  aload_2
  aload_3
  invokevirtual android/content/Context/startService(Landroid/content/Intent;)Landroid/content/ComponentName;
  pop
  goto Label11
Label10:
  new java/io/File
  astore 19
  ldc "lpg"
  astore 8
  aload_1
  astore_2
  aload_2
  aload 8
  invokevirtual java/util/HashMap/get(Ljava/lang/Object;)Ljava/lang/Object;
  astore 7
  aload 7
  astore 26
  aload 26
  checkcast java/lang/String
  astore 26
  aload 26
  astore 16
  aload 19
  astore_2
  aload_2
  aload 16
  invokespecial java/io/File/<init>(Ljava/lang/String;)V
  aload 19
  astore_2
  aload_2
  invokevirtual java/io/File/getName()Ljava/lang/String;
  astore 9
  ldc "name"
  astore 8
  aload 6
  aload 8
  aload 9
  invokevirtual android/os/Bundle/putString(Ljava/lang/String;Ljava/lang/String;)V
  goto Label12
  nop
.end <method>

.method private c(Ljava/util/HashMap;)V
  .signature_attr "(Ljava/util/HashMap<Ljava/lang/String;Ljava/lang/String;>;)V"
.limit locals 27
.limit stack 200
  nop
  new com/mobisage/android/b
  astore 5
  aload 5
  invokespecial com/mobisage/android/b/<init>()V
  aload 5
  getfield com/mobisage/android/b/c Landroid/os/Bundle;
  astore 6
  ldc "eventtype"
  astore 8
  aload_1
  astore_2
  aload_2
  aload 8
  invokevirtual java/util/HashMap/get(Ljava/lang/Object;)Ljava/lang/Object;
  astore 7
  aload 7
  astore 10
  aload 10
  checkcast java/lang/String
  astore 10
  aload 10
  astore 9
  ldc "EventType"
  astore 8
  new java/lang/NoClassDefFoundError
  dup
  invokespecial java/lang/NoClassDefFoundError/<init>()V
  athrow
  ldc "token"
  astore 8
  aload_1
  astore_2
  aload_2
  aload 8
  invokevirtual java/util/HashMap/containsKey(Ljava/lang/Object;)Z
  istore 11
  iload 11
  invokestatic app/DummyClass/invokeIfStmt(Z)V
  iload 11
  ifeq Label0
  aload 5
  getfield com/mobisage/android/b/c Landroid/os/Bundle;
  astore 6
  ldc "token"
  astore 8
  aload_1
  astore_2
  aload_2
  aload 8
  invokevirtual java/util/HashMap/get(Ljava/lang/Object;)Ljava/lang/Object;
  astore 7
  aload 7
  astore 12
  aload 12
  checkcast java/lang/String
  astore 12
  aload 12
  astore 9
  ldc "Token"
  astore 8
  aload 6
  aload 8
  aload 9
  invokevirtual android/os/Bundle/putString(Ljava/lang/String;Ljava/lang/String;)V
Label6:
  ldc "adid"
  astore 8
  aload_1
  astore_2
  aload_2
  aload 8
  invokevirtual java/util/HashMap/containsKey(Ljava/lang/Object;)Z
  istore 11
  iload 11
  invokestatic app/DummyClass/invokeIfStmt(Z)V
  iload 11
  ifeq Label1
  aload 5
  getfield com/mobisage/android/b/c Landroid/os/Bundle;
  astore 6
  ldc "adid"
  astore 8
  aload_1
  astore_2
  aload_2
  aload 8
  invokevirtual java/util/HashMap/get(Ljava/lang/Object;)Ljava/lang/Object;
  astore 7
  aload 7
  astore 13
  aload 13
  checkcast java/lang/String
  astore 13
  aload 13
  astore 9
  ldc "AdID"
  astore 8
  aload 6
  aload 8
  aload 9
  invokevirtual android/os/Bundle/putString(Ljava/lang/String;Ljava/lang/String;)V
Label7:
  ldc "adgroupid"
  astore 8
  aload_1
  astore_2
  aload_2
  aload 8
  invokevirtual java/util/HashMap/containsKey(Ljava/lang/Object;)Z
  istore 11
  iload 11
  invokestatic app/DummyClass/invokeIfStmt(Z)V
  iload 11
  ifeq Label2
  aload 5
  getfield com/mobisage/android/b/c Landroid/os/Bundle;
  astore 6
  ldc "adgroupid"
  astore 8
  aload_1
  astore_2
  aload_2
  aload 8
  invokevirtual java/util/HashMap/get(Ljava/lang/Object;)Ljava/lang/Object;
  astore 7
  aload 7
  astore 14
  aload 14
  checkcast java/lang/String
  astore 14
  aload 14
  astore 9
  ldc "AdGroupID"
  astore 8
  aload 6
  aload 8
  aload 9
  invokevirtual android/os/Bundle/putString(Ljava/lang/String;Ljava/lang/String;)V
Label8:
  ldc "tag"
  astore 8
  aload_1
  astore_2
  aload_2
  aload 8
  invokevirtual java/util/HashMap/containsKey(Ljava/lang/Object;)Z
  istore 11
  iload 11
  invokestatic app/DummyClass/invokeIfStmt(Z)V
  iload 11
  ifeq Label3
  aload 5
  getfield com/mobisage/android/b/c Landroid/os/Bundle;
  astore 6
  ldc "tag"
  astore 8
  aload_1
  astore_2
  aload_2
  aload 8
  invokevirtual java/util/HashMap/get(Ljava/lang/Object;)Ljava/lang/Object;
  astore 7
  aload 7
  astore 15
  aload 15
  checkcast java/lang/String
  astore 15
  aload 15
  astore 9
  ldc "Tag"
  astore 8
  aload 6
  aload 8
  aload 9
  invokevirtual android/os/Bundle/putString(Ljava/lang/String;Ljava/lang/String;)V
Label3:
  aload_0
  astore_2
  aload_2
  getfield com/mobisage/android/F/b Ljava/lang/String;
  astore 16
  aload 16
  invokestatic app/DummyClass/invokeIfStmt(Ljava/lang/Object;)V
  aload 16
  ifnull Label4
  aload 5
  getfield com/mobisage/android/b/c Landroid/os/Bundle;
  astore 6
  aload_0
  astore_2
  aload_2
  getfield com/mobisage/android/F/b Ljava/lang/String;
  astore 9
  ldc "CustomData"
  astore 8
  aload 6
  aload 8
  aload 9
  invokevirtual android/os/Bundle/putString(Ljava/lang/String;Ljava/lang/String;)V
Label4:
  aload 5
  getfield com/mobisage/android/b/c Landroid/os/Bundle;
  astore 6
  aload_0
  astore_2
  aload_2
  getfield com/mobisage/android/F/c Ljava/lang/String;
  astore 9
  ldc "PublisherID"
  astore 8
  aload 6
  aload 8
  aload 9
  invokevirtual android/os/Bundle/putString(Ljava/lang/String;Ljava/lang/String;)V
  invokestatic com/mobisage/android/Y/a()Lcom/mobisage/android/Y;
  astore 17
  sipush 2005
  istore 18
  iload 18
  istore_2
  aload 17
  iload_2
  aload 5
  invokevirtual com/mobisage/android/Y/a(ILcom/mobisage/android/b;)V
  new android/content/Intent
  astore 19
  aload_0
  astore_2
  aload_2
  getfield com/mobisage/android/F/f Landroid/content/Context;
  astore_2
  aload_2
  astore 20
  ldc com/mobisage/android/MobiSageActivity
  astore 21
  aload 19
  astore_2
  aload 20
  astore_3
  aload 21
  astore 4
  aload_2
  aload_3
  aload 4
  invokespecial android/content/Intent/<init>(Landroid/content/Context;Ljava/lang/Class;)V
  ldc "type"
  astore 8
  ldc "ad"
  astore 22
  aload 19
  astore_2
  aload 22
  astore_3
  aload_2
  aload 8
  aload_3
  invokevirtual android/content/Intent/putExtra(Ljava/lang/String;Ljava/lang/String;)Landroid/content/Intent;
  pop
  ldc "lpg"
  astore 8
  aload_1
  astore_2
  aload_2
  aload 8
  invokevirtual java/util/HashMap/get(Ljava/lang/Object;)Ljava/lang/Object;
  astore 7
  aload 7
  astore 23
  aload 23
  checkcast java/lang/String
  astore 23
  aload 23
  astore 9
  ldc "lpg"
  astore 8
  aload 19
  astore_2
  aload_2
  aload 8
  aload 9
  invokevirtual android/content/Intent/putExtra(Ljava/lang/String;Ljava/lang/String;)Landroid/content/Intent;
  pop
  ldc "adid"
  astore 8
  aload_1
  astore_2
  aload_2
  aload 8
  invokevirtual java/util/HashMap/get(Ljava/lang/Object;)Ljava/lang/Object;
  astore 7
  aload 7
  astore 24
  aload 24
  checkcast java/lang/String
  astore 24
  aload 24
  astore 9
  ldc "adid"
  astore 8
  aload 19
  astore_2
  aload_2
  aload 8
  aload 9
  invokevirtual android/content/Intent/putExtra(Ljava/lang/String;Ljava/lang/String;)Landroid/content/Intent;
  pop
  ldc "adgroupid"
  astore 8
  aload_1
  astore_2
  aload_2
  aload 8
  invokevirtual java/util/HashMap/get(Ljava/lang/Object;)Ljava/lang/Object;
  astore 7
  aload 7
  astore 25
  aload 25
  checkcast java/lang/String
  astore 25
  aload 25
  astore 9
  ldc "adgroupid"
  astore 8
  aload 19
  astore_2
  aload_2
  aload 8
  aload 9
  invokevirtual android/content/Intent/putExtra(Ljava/lang/String;Ljava/lang/String;)Landroid/content/Intent;
  pop
  ldc "token"
  astore 8
  aload_1
  astore_2
  aload_2
  aload 8
  invokevirtual java/util/HashMap/get(Ljava/lang/Object;)Ljava/lang/Object;
  astore 7
  aload 7
  astore 26
  aload 26
  checkcast java/lang/String
  astore 26
  aload 26
  astore 9
  ldc "token"
  astore 8
  aload 19
  astore_2
  aload_2
  aload 8
  aload 9
  invokevirtual android/content/Intent/putExtra(Ljava/lang/String;Ljava/lang/String;)Landroid/content/Intent;
  pop
  aload_0
  astore_2
  aload_2
  getfield com/mobisage/android/F/c Ljava/lang/String;
  astore 9
  ldc "pid"
  astore 8
  aload 19
  astore_2
  aload_2
  aload 8
  aload 9
  invokevirtual android/content/Intent/putExtra(Ljava/lang/String;Ljava/lang/String;)Landroid/content/Intent;
  pop
  aload_0
  astore_2
  aload_2
  getfield com/mobisage/android/F/b Ljava/lang/String;
  astore 16
  aload 16
  invokestatic app/DummyClass/invokeIfStmt(Ljava/lang/Object;)V
  aload 16
  ifnull Label5
  aload_0
  astore_2
  aload_2
  getfield com/mobisage/android/F/b Ljava/lang/String;
  astore 9
  ldc "customdata"
  astore 8
  aload 19
  astore_2
  aload_2
  aload 8
  aload 9
  invokevirtual android/content/Intent/putExtra(Ljava/lang/String;Ljava/lang/String;)Landroid/content/Intent;
  pop
Label5:
  aload_0
  astore_2
  aload_2
  getfield com/mobisage/android/F/f Landroid/content/Context;
  astore_2
  aload_2
  astore 20
  aload 20
  astore_2
  aload 19
  astore_3
  aload_2
  aload_3
  invokevirtual android/content/Context/startActivity(Landroid/content/Intent;)V
  return
Label0:
  aload 5
  getfield com/mobisage/android/b/c Landroid/os/Bundle;
  astore 6
  aload_0
  astore_2
  aload_2
  getfield com/mobisage/android/F/a Ljava/lang/String;
  astore 9
  ldc "Token"
  astore 8
  aload 6
  aload 8
  aload 9
  invokevirtual android/os/Bundle/putString(Ljava/lang/String;Ljava/lang/String;)V
  goto Label6
Label1:
  aload 5
  getfield com/mobisage/android/b/c Landroid/os/Bundle;
  astore 6
  aload_0
  astore_2
  aload_2
  getfield com/mobisage/android/F/d Ljava/lang/String;
  astore 9
  ldc "AdID"
  astore 8
  aload 6
  aload 8
  aload 9
  invokevirtual android/os/Bundle/putString(Ljava/lang/String;Ljava/lang/String;)V
  goto Label7
Label2:
  aload 5
  getfield com/mobisage/android/b/c Landroid/os/Bundle;
  astore 6
  aload_0
  astore_2
  aload_2
  getfield com/mobisage/android/F/e Ljava/lang/String;
  astore 9
  ldc "AdGroupID"
  astore 8
  aload 6
  aload 8
  aload 9
  invokevirtual android/os/Bundle/putString(Ljava/lang/String;Ljava/lang/String;)V
  goto Label8
  nop
.end <method>

.method public final clickAd(Ljava/lang/String;)V
.limit locals 29
.limit stack 200
  nop
  aload_1
  astore_2
  aload_2
  invokestatic com/mobisage/android/MobiSageURIUtility/parserURIQuery(Ljava/lang/String;)Ljava/util/HashMap;
  astore 5
  iconst_2
  istore 7
  iload 7
  invokestatic java/lang/String/valueOf(I)Ljava/lang/String;
  astore 6
  ldc "eventtype"
  astore 8
  aload 5
  aload 8
  aload 6
  invokevirtual java/util/HashMap/put(Ljava/lang/Object;Ljava/lang/Object;)Ljava/lang/Object;
  pop
  ldc "action"
  astore 8
  aload 5
  aload 8
  invokevirtual java/util/HashMap/get(Ljava/lang/Object;)Ljava/lang/Object;
  astore 9
  aload 9
  astore 10
  aload 10
  checkcast java/lang/String
  astore 10
  aload 10
  astore 6
  aload 6
  invokestatic java/lang/Integer/valueOf(Ljava/lang/String;)Ljava/lang/Integer;
  astore 11
  aload 11
  invokevirtual java/lang/Integer/intValue()I
  istore 12
  new java/lang/NoClassDefFoundError
  dup
  invokespecial java/lang/NoClassDefFoundError/<init>()V
  athrow
  iload 12
  lookupswitch
  1 : Label1
  2 : Label2
  3 : Label3
  4 : Label4
  default : Label0
Label0:
  goto Label5
Label5:
  return
Label4:
  aload_0
  astore_2
  aload_2
  aload 5
  invokespecial com/mobisage/android/F/a(Ljava/util/HashMap;)V
  goto Label5
Label2:
  aload_0
  astore_2
  aload_2
  aload 5
  invokespecial com/mobisage/android/F/b(Ljava/util/HashMap;)V
  goto Label5
Label3:
  new com/mobisage/android/b
  astore 13
  aload 13
  invokespecial com/mobisage/android/b/<init>()V
  aload 13
  getfield com/mobisage/android/b/c Landroid/os/Bundle;
  astore 14
  ldc "eventtype"
  astore 8
  aload 5
  aload 8
  invokevirtual java/util/HashMap/get(Ljava/lang/Object;)Ljava/lang/Object;
  astore 9
  aload 9
  astore 15
  aload 15
  checkcast java/lang/String
  astore 15
  aload 15
  astore 6
  ldc "EventType"
  astore 8
  aload 14
  aload 8
  aload 6
  invokevirtual android/os/Bundle/putString(Ljava/lang/String;Ljava/lang/String;)V
  ldc "token"
  astore 8
  aload 5
  aload 8
  invokevirtual java/util/HashMap/containsKey(Ljava/lang/Object;)Z
  istore 16
  iload 16
  invokestatic app/DummyClass/invokeIfStmt(Z)V
  iload 16
  ifeq Label6
  aload 13
  getfield com/mobisage/android/b/c Landroid/os/Bundle;
  astore 14
  ldc "token"
  astore 8
  aload 5
  aload 8
  invokevirtual java/util/HashMap/get(Ljava/lang/Object;)Ljava/lang/Object;
  astore 9
  aload 9
  astore 17
  aload 17
  checkcast java/lang/String
  astore 17
  aload 17
  astore_1
  ldc "Token"
  astore 8
  aload_1
  astore_2
  aload 14
  aload 8
  aload_2
  invokevirtual android/os/Bundle/putString(Ljava/lang/String;Ljava/lang/String;)V
Label11:
  ldc "adid"
  astore 8
  aload 5
  aload 8
  invokevirtual java/util/HashMap/containsKey(Ljava/lang/Object;)Z
  istore 16
  iload 16
  invokestatic app/DummyClass/invokeIfStmt(Z)V
  iload 16
  ifeq Label7
  aload 13
  getfield com/mobisage/android/b/c Landroid/os/Bundle;
  astore 14
  ldc "adid"
  astore 8
  aload 5
  aload 8
  invokevirtual java/util/HashMap/get(Ljava/lang/Object;)Ljava/lang/Object;
  astore 9
  aload 9
  astore 18
  aload 18
  checkcast java/lang/String
  astore 18
  aload 18
  astore_1
  ldc "AdID"
  astore 8
  aload_1
  astore_2
  aload 14
  aload 8
  aload_2
  invokevirtual android/os/Bundle/putString(Ljava/lang/String;Ljava/lang/String;)V
Label12:
  ldc "adgroupid"
  astore 8
  aload 5
  aload 8
  invokevirtual java/util/HashMap/containsKey(Ljava/lang/Object;)Z
  istore 16
  iload 16
  invokestatic app/DummyClass/invokeIfStmt(Z)V
  iload 16
  ifeq Label8
  aload 13
  getfield com/mobisage/android/b/c Landroid/os/Bundle;
  astore 14
  ldc "adgroupid"
  astore 8
  aload 5
  aload 8
  invokevirtual java/util/HashMap/get(Ljava/lang/Object;)Ljava/lang/Object;
  astore 9
  aload 9
  astore 19
  aload 19
  checkcast java/lang/String
  astore 19
  aload 19
  astore_1
  ldc "AdGroupID"
  astore 8
  aload_1
  astore_2
  aload 14
  aload 8
  aload_2
  invokevirtual android/os/Bundle/putString(Ljava/lang/String;Ljava/lang/String;)V
Label13:
  ldc "tag"
  astore 8
  aload 5
  aload 8
  invokevirtual java/util/HashMap/containsKey(Ljava/lang/Object;)Z
  istore 16
  iload 16
  invokestatic app/DummyClass/invokeIfStmt(Z)V
  iload 16
  ifeq Label9
  aload 13
  getfield com/mobisage/android/b/c Landroid/os/Bundle;
  astore 14
  ldc "tag"
  astore 8
  aload 5
  aload 8
  invokevirtual java/util/HashMap/get(Ljava/lang/Object;)Ljava/lang/Object;
  astore 9
  aload 9
  astore 20
  aload 20
  checkcast java/lang/String
  astore 20
  aload 20
  astore_1
  ldc "Tag"
  astore 8
  aload_1
  astore_2
  aload 14
  aload 8
  aload_2
  invokevirtual android/os/Bundle/putString(Ljava/lang/String;Ljava/lang/String;)V
Label9:
  aload_0
  astore_2
  aload_2
  getfield com/mobisage/android/F/b Ljava/lang/String;
  astore 6
  aload 6
  invokestatic app/DummyClass/invokeIfStmt(Ljava/lang/Object;)V
  aload 6
  ifnull Label10
  aload 13
  getfield com/mobisage/android/b/c Landroid/os/Bundle;
  astore 14
  aload_0
  astore_2
  aload_2
  getfield com/mobisage/android/F/b Ljava/lang/String;
  astore_2
  aload_2
  astore_1
  ldc "CustomData"
  astore 8
  aload_1
  astore_2
  aload 14
  aload 8
  aload_2
  invokevirtual android/os/Bundle/putString(Ljava/lang/String;Ljava/lang/String;)V
Label10:
  aload 13
  getfield com/mobisage/android/b/c Landroid/os/Bundle;
  astore 14
  aload_0
  astore_2
  aload_2
  getfield com/mobisage/android/F/c Ljava/lang/String;
  astore_2
  aload_2
  astore_1
  ldc "PublisherID"
  astore 8
  aload_1
  astore_2
  aload 14
  aload 8
  aload_2
  invokevirtual android/os/Bundle/putString(Ljava/lang/String;Ljava/lang/String;)V
  invokestatic com/mobisage/android/Y/a()Lcom/mobisage/android/Y;
  astore 21
  sipush 2005
  istore 7
  aload 21
  astore_2
  aload_2
  iload 7
  aload 13
  invokevirtual com/mobisage/android/Y/a(ILcom/mobisage/android/b;)V
  new android/app/AlertDialog$Builder
  astore 22
  aload_0
  astore_2
  aload_2
  getfield com/mobisage/android/F/f Landroid/content/Context;
  astore_2
  aload_2
  astore 23
  aload 22
  astore_2
  aload 23
  astore_3
  aload_2
  aload_3
  invokespecial android/app/AlertDialog$Builder/<init>(Landroid/content/Context;)V
  aload 22
  astore_2
  aload_2
  invokevirtual android/app/AlertDialog$Builder/create()Landroid/app/AlertDialog;
  astore 24
  ldc "tip"
  astore 8
  aload 5
  aload 8
  invokevirtual java/util/HashMap/get(Ljava/lang/Object;)Ljava/lang/Object;
  astore 9
  aload 9
  astore 26
  aload 26
  checkcast java/lang/CharSequence
  astore 26
  aload 26
  astore 25
  aload 24
  astore_2
  aload 25
  astore_3
  aload_2
  aload_3
  invokevirtual android/app/AlertDialog/setMessage(Ljava/lang/CharSequence;)V
  iconst_1
  istore 7
  aload 24
  astore_2
  aload_2
  iload 7
  invokevirtual android/app/AlertDialog/setCancelable(Z)V
  new com/mobisage/android/F$1
  astore 27
  aload 27
  astore_2
  aload_0
  astore_3
  aload_2
  aload_3
  aload 5
  invokespecial com/mobisage/android/F$1/<init>(Lcom/mobisage/android/F;Ljava/util/HashMap;)V
  iconst_m1
  istore 7
  ldc "OK"
  astore 8
  aload 24
  astore_2
  aload 27
  astore_3
  aload_2
  iload 7
  aload 8
  aload_3
  invokevirtual android/app/AlertDialog/setButton(ILjava/lang/CharSequence;Landroid/content/DialogInterface$OnClickListener;)V
  new com/mobisage/android/F$2
  astore 28
  aload 28
  astore_2
  aload_0
  astore_3
  aload 24
  astore 4
  aload_2
  aload_3
  aload 4
  invokespecial com/mobisage/android/F$2/<init>(Lcom/mobisage/android/F;Landroid/app/AlertDialog;)V
  bipush -2
  istore 7
  ldc "Cancel"
  astore 8
  aload 24
  astore_2
  aload 28
  astore_3
  aload_2
  iload 7
  aload 8
  aload_3
  invokevirtual android/app/AlertDialog/setButton(ILjava/lang/CharSequence;Landroid/content/DialogInterface$OnClickListener;)V
  aload 24
  astore_2
  aload_2
  invokevirtual android/app/AlertDialog/show()V
  goto Label5
Label6:
  aload 13
  getfield com/mobisage/android/b/c Landroid/os/Bundle;
  astore 14
  aload_0
  astore_2
  aload_2
  getfield com/mobisage/android/F/a Ljava/lang/String;
  astore_2
  aload_2
  astore_1
  ldc "Token"
  astore 8
  aload_1
  astore_2
  aload 14
  aload 8
  aload_2
  invokevirtual android/os/Bundle/putString(Ljava/lang/String;Ljava/lang/String;)V
  goto Label11
Label7:
  aload 13
  getfield com/mobisage/android/b/c Landroid/os/Bundle;
  astore 14
  aload_0
  astore_2
  aload_2
  getfield com/mobisage/android/F/d Ljava/lang/String;
  astore_2
  aload_2
  astore_1
  ldc "AdID"
  astore 8
  aload_1
  astore_2
  aload 14
  aload 8
  aload_2
  invokevirtual android/os/Bundle/putString(Ljava/lang/String;Ljava/lang/String;)V
  goto Label12
Label8:
  aload 13
  getfield com/mobisage/android/b/c Landroid/os/Bundle;
  astore 14
  aload_0
  astore_2
  aload_2
  getfield com/mobisage/android/F/e Ljava/lang/String;
  astore_2
  aload_2
  astore_1
  ldc "AdGroupID"
  astore 8
  aload_1
  astore_2
  aload 14
  aload 8
  aload_2
  invokevirtual android/os/Bundle/putString(Ljava/lang/String;Ljava/lang/String;)V
  goto Label13
Label1:
  aload_0
  astore_2
  aload_2
  aload 5
  invokespecial com/mobisage/android/F/c(Ljava/util/HashMap;)V
  goto Label5
  nop
  nop
.end <method>

.method public final destoryJavascriptAgent()V
.limit locals 2
.limit stack 200
  nop
  aconst_null
  astore_1
  aload_0
  aload_1
  putfield com/mobisage/android/F/f Landroid/content/Context;
  return
  nop
.end <method>

.method public final impressiontrack(Ljava/lang/String;)V
.limit locals 14
.limit stack 200
  .catch  org/json/JSONException <from> Label6 <to> Label7 <using> Label5
  nop
  new org/json/JSONArray
  astore_2
Label6:
  aload_1
  invokestatic java/net/URLDecoder/decode(Ljava/lang/String;)Ljava/lang/String;
  astore_1
  aload_2
  aload_1
  invokespecial org/json/JSONArray/<init>(Ljava/lang/String;)V
  iconst_0
  istore_3
Label3:
  aload_2
  invokevirtual org/json/JSONArray/length()I
  istore 4
  new java/lang/NoClassDefFoundError
  dup
  invokespecial java/lang/NoClassDefFoundError/<init>()V
  athrow
  dload 4
  invokestatic app/DummyClass/invokeIfStmt(D)V
  iload_3
  iload 4
  if_icmpge Label0
  aload_2
  iload_3
  invokevirtual org/json/JSONArray/getJSONObject(I)Lorg/json/JSONObject;
  astore 5
  new com/mobisage/android/b
  astore 6
  aload 6
  invokespecial com/mobisage/android/b/<init>()V
  aload 6
  getfield com/mobisage/android/b/c Landroid/os/Bundle;
  astore 7
  ldc "adgroupid"
  astore 9
  aload 5
  aload 9
  invokevirtual org/json/JSONObject/getString(Ljava/lang/String;)Ljava/lang/String;
  astore 8
  ldc "AdGroupID"
  astore 9
  aload 7
  aload 9
  aload 8
  invokevirtual android/os/Bundle/putString(Ljava/lang/String;Ljava/lang/String;)V
  aload 6
  getfield com/mobisage/android/b/c Landroid/os/Bundle;
  astore 7
  ldc "adid"
  astore 9
  aload 5
  aload 9
  invokevirtual org/json/JSONObject/getString(Ljava/lang/String;)Ljava/lang/String;
  astore_1
  ldc "AdID"
  astore 9
  aload 7
  aload 9
  aload_1
  invokevirtual android/os/Bundle/putString(Ljava/lang/String;Ljava/lang/String;)V
  ldc "token"
  astore 9
  aload 5
  aload 9
  invokevirtual org/json/JSONObject/has(Ljava/lang/String;)Z
  istore 10
  iload 10
  invokestatic app/DummyClass/invokeIfStmt(Z)V
  iload 10
  ifeq Label1
  aload 6
  getfield com/mobisage/android/b/c Landroid/os/Bundle;
  astore 7
  ldc "token"
  astore 9
  aload 5
  aload 9
  invokevirtual org/json/JSONObject/getString(Ljava/lang/String;)Ljava/lang/String;
  astore_1
  ldc "Token"
  astore 9
  aload 7
  aload 9
  aload_1
  invokevirtual android/os/Bundle/putString(Ljava/lang/String;Ljava/lang/String;)V
Label4:
  aload_0
  getfield com/mobisage/android/F/b Ljava/lang/String;
  astore 8
  aload 8
  invokestatic app/DummyClass/invokeIfStmt(Ljava/lang/Object;)V
  aload 8
  ifnull Label2
  aload 6
  getfield com/mobisage/android/b/c Landroid/os/Bundle;
  astore 7
  aload_0
  getfield com/mobisage/android/F/b Ljava/lang/String;
  astore_1
  ldc "CustomData"
  astore 9
  aload 7
  aload 9
  aload_1
  invokevirtual android/os/Bundle/putString(Ljava/lang/String;Ljava/lang/String;)V
Label2:
  aload 6
  getfield com/mobisage/android/b/c Landroid/os/Bundle;
  astore 7
  aload_0
  getfield com/mobisage/android/F/c Ljava/lang/String;
  astore_1
  ldc "PublisherID"
  astore 9
  aload 7
  aload 9
  aload_1
  invokevirtual android/os/Bundle/putString(Ljava/lang/String;Ljava/lang/String;)V
  invokestatic com/mobisage/android/Y/a()Lcom/mobisage/android/Y;
  astore 11
  sipush 2004
  istore 12
  aload 11
  iload 12
  aload 6
  invokevirtual com/mobisage/android/Y/a(ILcom/mobisage/android/b;)V
  iload_3
  iconst_1
  iadd
  istore_3
  goto Label3
Label1:
  aload 6
  getfield com/mobisage/android/b/c Landroid/os/Bundle;
  astore 7
  aload_0
  getfield com/mobisage/android/F/a Ljava/lang/String;
  astore_1
  ldc "Token"
  astore 9
  aload 7
  aload 9
  aload_1
  invokevirtual android/os/Bundle/putString(Ljava/lang/String;Ljava/lang/String;)V
Label7:
  goto Label4
Label5:
  astore 13
Label0:
  return
  nop
.end <method>

.method public final onWebClickAd(Ljava/lang/String;)V
.limit locals 32
.limit stack 200
  nop
  aload_1
  astore_2
  aload_2
  invokestatic com/mobisage/android/MobiSageURIUtility/parserURIQuery(Ljava/lang/String;)Ljava/util/HashMap;
  astore 4
  bipush 8
  istore 6
  iload 6
  invokestatic java/lang/String/valueOf(I)Ljava/lang/String;
  astore 5
  ldc "eventtype"
  astore 7
  aload 4
  aload 7
  aload 5
  invokevirtual java/util/HashMap/put(Ljava/lang/Object;Ljava/lang/Object;)Ljava/lang/Object;
  pop
  ldc "action"
  astore 7
  aload 4
  aload 7
  invokevirtual java/util/HashMap/get(Ljava/lang/Object;)Ljava/lang/Object;
  astore 8
  aload 8
  astore 9
  aload 9
  checkcast java/lang/String
  astore 9
  aload 9
  astore 5
  aload 5
  invokestatic java/lang/Integer/valueOf(Ljava/lang/String;)Ljava/lang/Integer;
  astore 10
  aload 10
  invokevirtual java/lang/Integer/intValue()I
  istore 11
  new java/lang/NoClassDefFoundError
  dup
  invokespecial java/lang/NoClassDefFoundError/<init>()V
  athrow
  iload 11
  lookupswitch
  1 : Label1
  2 : Label2
  3 : Label3
  4 : Label4
  default : Label0
Label0:
  goto Label5
Label5:
  return
Label4:
  aload_0
  astore_2
  aload_2
  aload 4
  invokespecial com/mobisage/android/F/a(Ljava/util/HashMap;)V
  goto Label5
Label2:
  aload_0
  astore_2
  aload_2
  aload 4
  invokespecial com/mobisage/android/F/b(Ljava/util/HashMap;)V
  goto Label5
Label3:
  new com/mobisage/android/b
  astore 12
  aload 12
  invokespecial com/mobisage/android/b/<init>()V
  aload 12
  getfield com/mobisage/android/b/c Landroid/os/Bundle;
  astore 13
  ldc "eventtype"
  astore 7
  aload 4
  aload 7
  invokevirtual java/util/HashMap/get(Ljava/lang/Object;)Ljava/lang/Object;
  astore 8
  aload 8
  astore 14
  aload 14
  checkcast java/lang/String
  astore 14
  aload 14
  astore 5
  ldc "EventType"
  astore 7
  aload 13
  aload 7
  aload 5
  invokevirtual android/os/Bundle/putString(Ljava/lang/String;Ljava/lang/String;)V
  ldc "token"
  astore 7
  aload 4
  aload 7
  invokevirtual java/util/HashMap/containsKey(Ljava/lang/Object;)Z
  istore 15
  iload 15
  invokestatic app/DummyClass/invokeIfStmt(Z)V
  iload 15
  ifeq Label6
  aload 12
  getfield com/mobisage/android/b/c Landroid/os/Bundle;
  astore 13
  ldc "token"
  astore 7
  aload 4
  aload 7
  invokevirtual java/util/HashMap/get(Ljava/lang/Object;)Ljava/lang/Object;
  astore 8
  aload 8
  astore 16
  aload 16
  checkcast java/lang/String
  astore 16
  aload 16
  astore_1
  ldc "Token"
  astore 7
  aload_1
  astore_2
  aload 13
  aload 7
  aload_2
  invokevirtual android/os/Bundle/putString(Ljava/lang/String;Ljava/lang/String;)V
Label16:
  ldc "adid"
  astore 7
  aload 4
  aload 7
  invokevirtual java/util/HashMap/containsKey(Ljava/lang/Object;)Z
  istore 15
  iload 15
  invokestatic app/DummyClass/invokeIfStmt(Z)V
  iload 15
  ifeq Label7
  aload 12
  getfield com/mobisage/android/b/c Landroid/os/Bundle;
  astore 13
  ldc "adid"
  astore 7
  aload 4
  aload 7
  invokevirtual java/util/HashMap/get(Ljava/lang/Object;)Ljava/lang/Object;
  astore 8
  aload 8
  astore 17
  aload 17
  checkcast java/lang/String
  astore 17
  aload 17
  astore_1
  ldc "AdID"
  astore 7
  aload_1
  astore_2
  aload 13
  aload 7
  aload_2
  invokevirtual android/os/Bundle/putString(Ljava/lang/String;Ljava/lang/String;)V
Label17:
  ldc "adgroupid"
  astore 7
  aload 4
  aload 7
  invokevirtual java/util/HashMap/containsKey(Ljava/lang/Object;)Z
  istore 15
  iload 15
  invokestatic app/DummyClass/invokeIfStmt(Z)V
  iload 15
  ifeq Label8
  aload 12
  getfield com/mobisage/android/b/c Landroid/os/Bundle;
  astore 13
  ldc "adgroupid"
  astore 7
  aload 4
  aload 7
  invokevirtual java/util/HashMap/get(Ljava/lang/Object;)Ljava/lang/Object;
  astore 8
  aload 8
  astore 18
  aload 18
  checkcast java/lang/String
  astore 18
  aload 18
  astore_1
  ldc "AdGroupID"
  astore 7
  aload_1
  astore_2
  aload 13
  aload 7
  aload_2
  invokevirtual android/os/Bundle/putString(Ljava/lang/String;Ljava/lang/String;)V
Label18:
  ldc "tag"
  astore 7
  aload 4
  aload 7
  invokevirtual java/util/HashMap/containsKey(Ljava/lang/Object;)Z
  istore 15
  iload 15
  invokestatic app/DummyClass/invokeIfStmt(Z)V
  iload 15
  ifeq Label9
  aload 12
  getfield com/mobisage/android/b/c Landroid/os/Bundle;
  astore 13
  ldc "tag"
  astore 7
  aload 4
  aload 7
  invokevirtual java/util/HashMap/get(Ljava/lang/Object;)Ljava/lang/Object;
  astore 8
  aload 8
  astore 19
  aload 19
  checkcast java/lang/String
  astore 19
  aload 19
  astore_1
  ldc "Tag"
  astore 7
  aload_1
  astore_2
  aload 13
  aload 7
  aload_2
  invokevirtual android/os/Bundle/putString(Ljava/lang/String;Ljava/lang/String;)V
Label9:
  aload_0
  astore_2
  aload_2
  getfield com/mobisage/android/F/b Ljava/lang/String;
  astore 5
  aload 5
  invokestatic app/DummyClass/invokeIfStmt(Ljava/lang/Object;)V
  aload 5
  ifnull Label10
  aload 12
  getfield com/mobisage/android/b/c Landroid/os/Bundle;
  astore 13
  aload_0
  astore_2
  aload_2
  getfield com/mobisage/android/F/b Ljava/lang/String;
  astore_2
  aload_2
  astore_1
  ldc "CustomData"
  astore 7
  aload_1
  astore_2
  aload 13
  aload 7
  aload_2
  invokevirtual android/os/Bundle/putString(Ljava/lang/String;Ljava/lang/String;)V
Label10:
  aload 12
  getfield com/mobisage/android/b/c Landroid/os/Bundle;
  astore 13
  aload_0
  astore_2
  aload_2
  getfield com/mobisage/android/F/c Ljava/lang/String;
  astore_2
  aload_2
  astore_1
  ldc "PublisherID"
  astore 7
  aload_1
  astore_2
  aload 13
  aload 7
  aload_2
  invokevirtual android/os/Bundle/putString(Ljava/lang/String;Ljava/lang/String;)V
  invokestatic com/mobisage/android/Y/a()Lcom/mobisage/android/Y;
  astore 20
  sipush 2005
  istore 6
  aload 20
  astore_2
  aload_2
  iload 6
  aload 12
  invokevirtual com/mobisage/android/Y/a(ILcom/mobisage/android/b;)V
  new com/mobisage/android/b
  astore 12
  aload 12
  invokespecial com/mobisage/android/b/<init>()V
  aload 12
  getfield com/mobisage/android/b/c Landroid/os/Bundle;
  astore 13
  iconst_5
  istore 6
  iload 6
  invokestatic java/lang/String/valueOf(I)Ljava/lang/String;
  astore_1
  ldc "EventType"
  astore 7
  aload_1
  astore_2
  aload 13
  aload 7
  aload_2
  invokevirtual android/os/Bundle/putString(Ljava/lang/String;Ljava/lang/String;)V
  ldc "token"
  astore 7
  aload 4
  aload 7
  invokevirtual java/util/HashMap/containsKey(Ljava/lang/Object;)Z
  istore 15
  iload 15
  invokestatic app/DummyClass/invokeIfStmt(Z)V
  iload 15
  ifeq Label11
  aload 12
  getfield com/mobisage/android/b/c Landroid/os/Bundle;
  astore 13
  ldc "token"
  astore 7
  aload 4
  aload 7
  invokevirtual java/util/HashMap/get(Ljava/lang/Object;)Ljava/lang/Object;
  astore 8
  aload 8
  astore 21
  aload 21
  checkcast java/lang/String
  astore 21
  aload 21
  astore_1
  ldc "Token"
  astore 7
  aload_1
  astore_2
  aload 13
  aload 7
  aload_2
  invokevirtual android/os/Bundle/putString(Ljava/lang/String;Ljava/lang/String;)V
Label19:
  ldc "adid"
  astore 7
  aload 4
  aload 7
  invokevirtual java/util/HashMap/containsKey(Ljava/lang/Object;)Z
  istore 15
  iload 15
  invokestatic app/DummyClass/invokeIfStmt(Z)V
  iload 15
  ifeq Label12
  aload 12
  getfield com/mobisage/android/b/c Landroid/os/Bundle;
  astore 13
  ldc "adid"
  astore 7
  aload 4
  aload 7
  invokevirtual java/util/HashMap/get(Ljava/lang/Object;)Ljava/lang/Object;
  astore 8
  aload 8
  astore 22
  aload 22
  checkcast java/lang/String
  astore 22
  aload 22
  astore_1
  ldc "AdID"
  astore 7
  aload_1
  astore_2
  aload 13
  aload 7
  aload_2
  invokevirtual android/os/Bundle/putString(Ljava/lang/String;Ljava/lang/String;)V
Label20:
  ldc "adgroupid"
  astore 7
  aload 4
  aload 7
  invokevirtual java/util/HashMap/containsKey(Ljava/lang/Object;)Z
  istore 15
  iload 15
  invokestatic app/DummyClass/invokeIfStmt(Z)V
  iload 15
  ifeq Label13
  aload 12
  getfield com/mobisage/android/b/c Landroid/os/Bundle;
  astore 13
  ldc "adgroupid"
  astore 7
  aload 4
  aload 7
  invokevirtual java/util/HashMap/get(Ljava/lang/Object;)Ljava/lang/Object;
  astore 8
  aload 8
  astore 23
  aload 23
  checkcast java/lang/String
  astore 23
  aload 23
  astore_1
  ldc "AdGroupID"
  astore 7
  aload_1
  astore_2
  aload 13
  aload 7
  aload_2
  invokevirtual android/os/Bundle/putString(Ljava/lang/String;Ljava/lang/String;)V
Label21:
  ldc "tag"
  astore 7
  aload 4
  aload 7
  invokevirtual java/util/HashMap/containsKey(Ljava/lang/Object;)Z
  istore 15
  iload 15
  invokestatic app/DummyClass/invokeIfStmt(Z)V
  iload 15
  ifeq Label14
  aload 12
  getfield com/mobisage/android/b/c Landroid/os/Bundle;
  astore 13
  ldc "tag"
  astore 7
  aload 4
  aload 7
  invokevirtual java/util/HashMap/get(Ljava/lang/Object;)Ljava/lang/Object;
  astore 8
  aload 8
  astore 24
  aload 24
  checkcast java/lang/String
  astore 24
  aload 24
  astore_1
  ldc "Tag"
  astore 7
  aload_1
  astore_2
  aload 13
  aload 7
  aload_2
  invokevirtual android/os/Bundle/putString(Ljava/lang/String;Ljava/lang/String;)V
Label14:
  aload_0
  astore_2
  aload_2
  getfield com/mobisage/android/F/b Ljava/lang/String;
  astore 5
  aload 5
  invokestatic app/DummyClass/invokeIfStmt(Ljava/lang/Object;)V
  aload 5
  ifnull Label15
  aload 12
  getfield com/mobisage/android/b/c Landroid/os/Bundle;
  astore 13
  aload_0
  astore_2
  aload_2
  getfield com/mobisage/android/F/b Ljava/lang/String;
  astore_2
  aload_2
  astore_1
  ldc "CustomData"
  astore 7
  aload_1
  astore_2
  aload 13
  aload 7
  aload_2
  invokevirtual android/os/Bundle/putString(Ljava/lang/String;Ljava/lang/String;)V
Label15:
  aload 12
  getfield com/mobisage/android/b/c Landroid/os/Bundle;
  astore 13
  aload_0
  astore_2
  aload_2
  getfield com/mobisage/android/F/c Ljava/lang/String;
  astore_2
  aload_2
  astore_1
  ldc "PublisherID"
  astore 7
  aload_1
  astore_2
  aload 13
  aload 7
  aload_2
  invokevirtual android/os/Bundle/putString(Ljava/lang/String;Ljava/lang/String;)V
  invokestatic com/mobisage/android/Y/a()Lcom/mobisage/android/Y;
  astore 20
  sipush 2005
  istore 6
  aload 20
  astore_2
  aload_2
  iload 6
  aload 12
  invokevirtual com/mobisage/android/Y/a(ILcom/mobisage/android/b;)V
  new android/content/Intent
  astore 25
  ldc "lpg"
  astore 7
  aload 4
  aload 7
  invokevirtual java/util/HashMap/get(Ljava/lang/Object;)Ljava/lang/Object;
  astore 8
  aload 8
  astore 26
  aload 26
  checkcast java/lang/String
  astore 26
  aload 26
  astore_1
  ldc "tel://"
  astore 7
  ldc "tel:"
  astore 28
  aload_1
  astore_2
  aload 28
  astore_3
  aload_2
  aload 7
  aload_3
  invokevirtual java/lang/String/replace(Ljava/lang/CharSequence;Ljava/lang/CharSequence;)Ljava/lang/String;
  astore 27
  aload 27
  astore_2
  aload_2
  invokestatic android/net/Uri/parse(Ljava/lang/String;)Landroid/net/Uri;
  astore 29
  ldc "android.intent.action.DIAL"
  astore 7
  aload 25
  astore_2
  aload 29
  astore_3
  aload_2
  aload 7
  aload_3
  invokespecial android/content/Intent/<init>(Ljava/lang/String;Landroid/net/Uri;)V
  aload_0
  astore_2
  aload_2
  getfield com/mobisage/android/F/f Landroid/content/Context;
  astore_2
  aload_2
  astore 30
  aload 30
  astore_2
  aload 25
  astore_3
  aload_2
  aload_3
  invokevirtual android/content/Context/startActivity(Landroid/content/Intent;)V
  goto Label5
Label6:
  aload 12
  getfield com/mobisage/android/b/c Landroid/os/Bundle;
  astore 13
  aload_0
  astore_2
  aload_2
  getfield com/mobisage/android/F/a Ljava/lang/String;
  astore_2
  aload_2
  astore 31
  ldc "Token"
  astore 7
  aload 31
  astore_2
  aload 13
  aload 7
  aload_2
  invokevirtual android/os/Bundle/putString(Ljava/lang/String;Ljava/lang/String;)V
  goto Label16
Label7:
  aload 12
  getfield com/mobisage/android/b/c Landroid/os/Bundle;
  astore 13
  aload_0
  astore_2
  aload_2
  getfield com/mobisage/android/F/d Ljava/lang/String;
  astore_2
  aload_2
  astore 31
  ldc "AdID"
  astore 7
  aload 31
  astore_2
  aload 13
  aload 7
  aload_2
  invokevirtual android/os/Bundle/putString(Ljava/lang/String;Ljava/lang/String;)V
  goto Label17
Label8:
  aload 12
  getfield com/mobisage/android/b/c Landroid/os/Bundle;
  astore 13
  aload_0
  astore_2
  aload_2
  getfield com/mobisage/android/F/e Ljava/lang/String;
  astore_2
  aload_2
  astore 31
  ldc "AdGroupID"
  astore 7
  aload 31
  astore_2
  aload 13
  aload 7
  aload_2
  invokevirtual android/os/Bundle/putString(Ljava/lang/String;Ljava/lang/String;)V
  goto Label18
Label11:
  aload 12
  getfield com/mobisage/android/b/c Landroid/os/Bundle;
  astore 13
  aload_0
  astore_2
  aload_2
  getfield com/mobisage/android/F/a Ljava/lang/String;
  astore_2
  aload_2
  astore 31
  ldc "Token"
  astore 7
  aload 31
  astore_2
  aload 13
  aload 7
  aload_2
  invokevirtual android/os/Bundle/putString(Ljava/lang/String;Ljava/lang/String;)V
  goto Label19
Label12:
  aload 12
  getfield com/mobisage/android/b/c Landroid/os/Bundle;
  astore 13
  aload_0
  astore_2
  aload_2
  getfield com/mobisage/android/F/d Ljava/lang/String;
  astore_2
  aload_2
  astore 31
  ldc "AdID"
  astore 7
  aload 31
  astore_2
  aload 13
  aload 7
  aload_2
  invokevirtual android/os/Bundle/putString(Ljava/lang/String;Ljava/lang/String;)V
  goto Label20
Label13:
  aload 12
  getfield com/mobisage/android/b/c Landroid/os/Bundle;
  astore 13
  aload_0
  astore_2
  aload_2
  getfield com/mobisage/android/F/e Ljava/lang/String;
  astore_2
  aload_2
  astore 31
  ldc "AdGroupID"
  astore 7
  aload 31
  astore_2
  aload 13
  aload 7
  aload_2
  invokevirtual android/os/Bundle/putString(Ljava/lang/String;Ljava/lang/String;)V
  goto Label21
Label1:
  aload_0
  astore_2
  aload_2
  aload 4
  invokespecial com/mobisage/android/F/c(Ljava/util/HashMap;)V
  goto Label5
  nop
  nop
  nop
.end <method>

