.source SourceFile
.class public  com/mobisage/sns/common/MSOAToken
.super java/lang/Object
.field public "key" Ljava/lang/String;
.field public "pin" Ljava/lang/String;
.field public "secret" Ljava/lang/String;

.method public <init>()V
.limit locals 1
.limit stack 200
  nop
  aload_0
  invokespecial java/lang/Object/<init>()V
  return
  nop
.end <method>

.method public <init>(Ljava/lang/String;)V
.limit locals 9
.limit stack 200
  nop
  aload_0
  invokespecial java/lang/Object/<init>()V
  aload_1
  invokestatic com/mobisage/android/MobiSageURIUtility/parserURIQuery(Ljava/lang/String;)Ljava/util/HashMap;
  astore_2
  ldc "oauth_token"
  astore 4
  aload_2
  aload 4
  invokevirtual java/util/HashMap/containsKey(Ljava/lang/Object;)Z
  istore_3
  new java/lang/NoClassDefFoundError
  dup
  invokespecial java/lang/NoClassDefFoundError/<init>()V
  athrow
  iload_3
  ifeq Label0
  ldc "oauth_token"
  astore 4
  aload_2
  aload 4
  invokevirtual java/util/HashMap/get(Ljava/lang/Object;)Ljava/lang/Object;
  astore 5
  aload 5
  astore 6
  aload 6
  checkcast java/lang/String
  astore 6
  aload 6
  astore_1
  aload_0
  aload_1
  putfield com/mobisage/sns/common/MSOAToken/key Ljava/lang/String;
Label0:
  ldc "oauth_token_secret"
  astore 4
  aload_2
  aload 4
  invokevirtual java/util/HashMap/containsKey(Ljava/lang/Object;)Z
  istore_3
  iload_3
  invokestatic app/DummyClass/invokeIfStmt(Z)V
  iload_3
  ifeq Label1
  ldc "oauth_token_secret"
  astore 4
  aload_2
  aload 4
  invokevirtual java/util/HashMap/get(Ljava/lang/Object;)Ljava/lang/Object;
  astore 5
  aload 5
  astore 7
  aload 7
  checkcast java/lang/String
  astore 7
  aload 7
  astore_1
  aload_0
  aload_1
  putfield com/mobisage/sns/common/MSOAToken/secret Ljava/lang/String;
Label1:
  ldc "oauth_verifier"
  astore 4
  aload_2
  aload 4
  invokevirtual java/util/HashMap/containsKey(Ljava/lang/Object;)Z
  istore_3
  iload_3
  invokestatic app/DummyClass/invokeIfStmt(Z)V
  iload_3
  ifeq Label2
  ldc "oauth_verifier"
  astore 4
  aload_2
  aload 4
  invokevirtual java/util/HashMap/get(Ljava/lang/Object;)Ljava/lang/Object;
  astore 5
  aload 5
  astore 8
  aload 8
  checkcast java/lang/String
  astore 8
  aload 8
  astore_1
  aload_0
  aload_1
  putfield com/mobisage/sns/common/MSOAToken/pin Ljava/lang/String;
Label2:
  return
  nop
.end <method>

