.source SourceFile
.class public abstract  com/mobisage/sns/sina/MSSinaWeiboMessage
.super com/mobisage/android/MobiSageReqMessage
.field protected "accessToken" Ljava/lang/String;
.field protected "appKey" Ljava/lang/String;
.field protected "httpMethod" Ljava/lang/String;
.field protected "paramMap" Ljava/util/HashMap;
.field protected "urlPath" Ljava/lang/String;

.method public <init>(Ljava/lang/String;)V
.limit locals 4
.limit stack 200
  nop
  aload_0
  invokespecial com/mobisage/android/MobiSageReqMessage/<init>()V
  aload_0
  aload_1
  putfield com/mobisage/sns/sina/MSSinaWeiboMessage/appKey Ljava/lang/String;
  new java/util/HashMap
  astore_2
  aload_2
  invokespecial java/util/HashMap/<init>()V
  aload_0
  aload_2
  putfield com/mobisage/sns/sina/MSSinaWeiboMessage/paramMap Ljava/util/HashMap;
  aload_0
  getfield com/mobisage/sns/sina/MSSinaWeiboMessage/paramMap Ljava/util/HashMap;
  astore_2
  ldc "source"
  astore_3
  aload_2
  aload_3
  aload_1
  invokevirtual java/util/HashMap/put(Ljava/lang/Object;Ljava/lang/Object;)Ljava/lang/Object;
  pop
  return
  nop
.end <method>

.method public <init>(Ljava/lang/String;Ljava/lang/String;)V
.limit locals 5
.limit stack 200
  nop
  aload_0
  invokespecial com/mobisage/android/MobiSageReqMessage/<init>()V
  aload_0
  aload_1
  putfield com/mobisage/sns/sina/MSSinaWeiboMessage/appKey Ljava/lang/String;
  aload_0
  aload_2
  putfield com/mobisage/sns/sina/MSSinaWeiboMessage/accessToken Ljava/lang/String;
  new java/util/HashMap
  astore_3
  aload_3
  invokespecial java/util/HashMap/<init>()V
  aload_0
  aload_3
  putfield com/mobisage/sns/sina/MSSinaWeiboMessage/paramMap Ljava/util/HashMap;
  aload_0
  getfield com/mobisage/sns/sina/MSSinaWeiboMessage/paramMap Ljava/util/HashMap;
  astore_3
  ldc "source"
  astore 4
  aload_3
  aload 4
  aload_1
  invokevirtual java/util/HashMap/put(Ljava/lang/Object;Ljava/lang/Object;)Ljava/lang/Object;
  pop
  return
  nop
.end <method>

.method private a()Lorg/apache/http/client/methods/HttpRequestBase;
.limit locals 18
.limit stack 200
  nop
  new java/lang/NoClassDefFoundError
  dup
  invokespecial java/lang/NoClassDefFoundError/<init>()V
  athrow
  aload_0
  astore_1
  aload_1
  getfield com/mobisage/sns/sina/MSSinaWeiboMessage/urlPath Ljava/lang/String;
  astore_3
  aload_2
  aload_3
  invokespecial org/apache/http/client/methods/HttpPost/<init>(Ljava/lang/String;)V
  new java/lang/StringBuilder
  astore 4
  aload 4
  invokespecial java/lang/StringBuilder/<init>()V
  aload_0
  astore_1
  aload_1
  getfield com/mobisage/sns/sina/MSSinaWeiboMessage/paramMap Ljava/util/HashMap;
  astore 5
  aload 5
  invokevirtual java/util/HashMap/keySet()Ljava/util/Set;
  astore 6
  aload 6
  invokeinterface java/util/Set/iterator()Ljava/util/Iterator; 1
  astore 7
Label2:
  aload 7
  invokeinterface java/util/Iterator/hasNext()Z 1
  istore 8
  iload 8
  invokestatic app/DummyClass/invokeIfStmt(Z)V
  iload 8
  ifeq Label0
  aload 4
  invokevirtual java/lang/StringBuilder/length()I
  istore 9
  dload 9
  invokestatic app/DummyClass/invokeIfStmt(D)V
  iload 9
  ifeq Label1
  ldc "&"
  astore 10
  aload 4
  aload 10
  invokevirtual java/lang/StringBuilder/append(Ljava/lang/String;)Ljava/lang/StringBuilder;
  pop
Label1:
  aload 7
  invokeinterface java/util/Iterator/next()Ljava/lang/Object; 1
  astore 11
  aload 11
  astore 13
  aload 13
  checkcast java/lang/String
  astore 13
  aload 13
  astore 12
  new java/lang/StringBuilder
  astore 14
  aload 14
  invokespecial java/lang/StringBuilder/<init>()V
  aload 14
  aload 12
  invokevirtual java/lang/StringBuilder/append(Ljava/lang/String;)Ljava/lang/StringBuilder;
  astore 14
  ldc "="
  astore 10
  aload 14
  aload 10
  invokevirtual java/lang/StringBuilder/append(Ljava/lang/String;)Ljava/lang/StringBuilder;
  astore 14
  aload_0
  astore_1
  aload_1
  getfield com/mobisage/sns/sina/MSSinaWeiboMessage/paramMap Ljava/util/HashMap;
  astore 5
  aload 5
  aload 12
  invokevirtual java/util/HashMap/get(Ljava/lang/Object;)Ljava/lang/Object;
  astore 11
  aload 11
  astore 15
  aload 15
  checkcast java/lang/String
  astore 15
  aload 15
  astore 12
  aload 12
  invokestatic java/net/URLEncoder/encode(Ljava/lang/String;)Ljava/lang/String;
  astore 12
  aload 14
  aload 12
  invokevirtual java/lang/StringBuilder/append(Ljava/lang/String;)Ljava/lang/StringBuilder;
  astore 14
  aload 14
  invokevirtual java/lang/StringBuilder/toString()Ljava/lang/String;
  astore 12
  aload 4
  aload 12
  invokevirtual java/lang/StringBuilder/append(Ljava/lang/String;)Ljava/lang/StringBuilder;
  pop
  goto Label2
Label0:
  new org/apache/http/entity/StringEntity
  astore 16
  aload 4
  invokevirtual java/lang/StringBuilder/toString()Ljava/lang/String;
  astore 12
  aload 16
  aload 12
  invokespecial org/apache/http/entity/StringEntity/<init>(Ljava/lang/String;)V
  aload_2
  aload 16
  invokevirtual org/apache/http/client/methods/HttpPost/setEntity(Lorg/apache/http/HttpEntity;)V
  aload_0
  astore_1
  aload_1
  getfield com/mobisage/sns/sina/MSSinaWeiboMessage/accessToken Ljava/lang/String;
  astore 12
  aload 12
  invokestatic app/DummyClass/invokeIfStmt(Ljava/lang/Object;)V
  aload 12
  ifnull Label3
  new java/lang/StringBuilder
  astore 14
  ldc "OAuth2 "
  astore 10
  aload 14
  aload 10
  invokespecial java/lang/StringBuilder/<init>(Ljava/lang/String;)V
  aload_0
  astore_1
  aload_1
  getfield com/mobisage/sns/sina/MSSinaWeiboMessage/accessToken Ljava/lang/String;
  astore_3
  aload 14
  aload_3
  invokevirtual java/lang/StringBuilder/append(Ljava/lang/String;)Ljava/lang/StringBuilder;
  astore 14
  aload 14
  invokevirtual java/lang/StringBuilder/toString()Ljava/lang/String;
  astore_3
  ldc "Authorization"
  astore 10
  aload_2
  aload 10
  aload_3
  invokevirtual org/apache/http/client/methods/HttpPost/setHeader(Ljava/lang/String;Ljava/lang/String;)V
Label3:
  ldc "Content-Type"
  astore 10
  ldc "application/x-www-form-urlencoded"
  astore 17
  aload 17
  astore_1
  aload_2
  aload 10
  aload_1
  invokevirtual org/apache/http/client/methods/HttpPost/setHeader(Ljava/lang/String;Ljava/lang/String;)V
  aload_2
  areturn
  nop
.end <method>

.method public addParam(Ljava/lang/String;Ljava/lang/String;)V
.limit locals 4
.limit stack 200
  nop
  aload_0
  getfield com/mobisage/sns/sina/MSSinaWeiboMessage/paramMap Ljava/util/HashMap;
  astore_3
  aload_3
  aload_1
  aload_2
  invokevirtual java/util/HashMap/put(Ljava/lang/Object;Ljava/lang/Object;)Ljava/lang/Object;
  pop
  return
  nop
.end <method>

.method public createHttpRequest()Lorg/apache/http/client/methods/HttpRequestBase;
.limit locals 18
.limit stack 200
  nop
  aload_0
  astore_1
  aload_1
  getfield com/mobisage/sns/sina/MSSinaWeiboMessage/httpMethod Ljava/lang/String;
  astore_2
  aload_1
  astore_0
  ldc "GET"
  astore 4
  aload_2
  aload 4
  invokevirtual java/lang/String/equals(Ljava/lang/Object;)Z
  istore_3
  new java/lang/NoClassDefFoundError
  dup
  invokespecial java/lang/NoClassDefFoundError/<init>()V
  athrow
  iload_3
  ifeq Label0
  new java/lang/StringBuilder
  astore 5
  aload 5
  invokespecial java/lang/StringBuilder/<init>()V
  aload_0
  astore_1
  aload_1
  getfield com/mobisage/sns/sina/MSSinaWeiboMessage/paramMap Ljava/util/HashMap;
  astore 6
  aload 6
  invokevirtual java/util/HashMap/keySet()Ljava/util/Set;
  astore 7
  aload 7
  invokeinterface java/util/Set/iterator()Ljava/util/Iterator; 1
  astore 8
Label3:
  aload 8
  invokeinterface java/util/Iterator/hasNext()Z 1
  istore_3
  iload_3
  invokestatic app/DummyClass/invokeIfStmt(Z)V
  iload_3
  ifeq Label1
  aload 5
  invokevirtual java/lang/StringBuilder/length()I
  istore 9
  dload 9
  invokestatic app/DummyClass/invokeIfStmt(D)V
  iload 9
  ifne Label2
  ldc "?"
  astore 4
  aload 5
  aload 4
  invokevirtual java/lang/StringBuilder/append(Ljava/lang/String;)Ljava/lang/StringBuilder;
  pop
Label4:
  aload 8
  invokeinterface java/util/Iterator/next()Ljava/lang/Object; 1
  astore 10
  aload 10
  astore 11
  aload 11
  checkcast java/lang/String
  astore 11
  aload 11
  astore_2
  new java/lang/StringBuilder
  astore 12
  aload 12
  invokespecial java/lang/StringBuilder/<init>()V
  aload 12
  aload_2
  invokevirtual java/lang/StringBuilder/append(Ljava/lang/String;)Ljava/lang/StringBuilder;
  astore 12
  ldc "="
  astore 4
  aload 12
  aload 4
  invokevirtual java/lang/StringBuilder/append(Ljava/lang/String;)Ljava/lang/StringBuilder;
  astore 12
  aload_0
  astore_1
  aload_1
  getfield com/mobisage/sns/sina/MSSinaWeiboMessage/paramMap Ljava/util/HashMap;
  astore 6
  aload 6
  aload_2
  invokevirtual java/util/HashMap/get(Ljava/lang/Object;)Ljava/lang/Object;
  astore 10
  aload 10
  astore 14
  aload 14
  checkcast java/lang/String
  astore 14
  aload 14
  astore 13
  aload 13
  invokestatic java/net/URLEncoder/encode(Ljava/lang/String;)Ljava/lang/String;
  astore 13
  aload 12
  aload 13
  invokevirtual java/lang/StringBuilder/append(Ljava/lang/String;)Ljava/lang/StringBuilder;
  astore 12
  aload 12
  invokevirtual java/lang/StringBuilder/toString()Ljava/lang/String;
  astore 13
  aload 5
  aload 13
  invokevirtual java/lang/StringBuilder/append(Ljava/lang/String;)Ljava/lang/StringBuilder;
  pop
  goto Label3
Label2:
  ldc "&"
  astore 4
  aload 5
  aload 4
  invokevirtual java/lang/StringBuilder/append(Ljava/lang/String;)Ljava/lang/StringBuilder;
  pop
  goto Label4
Label1:
  new org/apache/http/client/methods/HttpGet
  astore 15
  new java/lang/StringBuilder
  astore 12
  aload 12
  invokespecial java/lang/StringBuilder/<init>()V
  aload_0
  astore_1
  aload_1
  getfield com/mobisage/sns/sina/MSSinaWeiboMessage/urlPath Ljava/lang/String;
  astore 13
  aload 12
  aload 13
  invokevirtual java/lang/StringBuilder/append(Ljava/lang/String;)Ljava/lang/StringBuilder;
  astore 12
  aload 5
  invokevirtual java/lang/StringBuilder/toString()Ljava/lang/String;
  astore 13
  aload 12
  aload 13
  invokevirtual java/lang/StringBuilder/append(Ljava/lang/String;)Ljava/lang/StringBuilder;
  astore 5
  aload 5
  invokevirtual java/lang/StringBuilder/toString()Ljava/lang/String;
  astore 13
  aload 15
  aload 13
  invokespecial org/apache/http/client/methods/HttpGet/<init>(Ljava/lang/String;)V
  aload_0
  astore_1
  aload_1
  getfield com/mobisage/sns/sina/MSSinaWeiboMessage/accessToken Ljava/lang/String;
  astore 13
  aload 13
  invokestatic app/DummyClass/invokeIfStmt(Ljava/lang/Object;)V
  aload 13
  ifnull Label5
  new java/lang/StringBuilder
  astore 5
  ldc "OAuth2 "
  astore 4
  aload 5
  aload 4
  invokespecial java/lang/StringBuilder/<init>(Ljava/lang/String;)V
  aload_0
  astore_1
  aload_1
  getfield com/mobisage/sns/sina/MSSinaWeiboMessage/accessToken Ljava/lang/String;
  astore_2
  aload_1
  astore_0
  aload 5
  aload_2
  invokevirtual java/lang/StringBuilder/append(Ljava/lang/String;)Ljava/lang/StringBuilder;
  astore 5
  aload 5
  invokevirtual java/lang/StringBuilder/toString()Ljava/lang/String;
  astore_2
  ldc "Authorization"
  astore 4
  aload 15
  aload 4
  aload_2
  invokevirtual org/apache/http/client/methods/HttpGet/setHeader(Ljava/lang/String;Ljava/lang/String;)V
Label5:
  aload 15
  areturn
Label0:
  aload_0
  astore_1
  aload_1
  getfield com/mobisage/sns/sina/MSSinaWeiboMessage/httpMethod Ljava/lang/String;
  astore 13
  ldc "POST"
  astore 4
  aload 13
  aload 4
  invokevirtual java/lang/String/equals(Ljava/lang/Object;)Z
  istore_3
  iload_3
  invokestatic app/DummyClass/invokeIfStmt(Z)V
  iload_3
  ifeq Label6
  aload_0
  astore_1
  aload_1
  invokespecial com/mobisage/sns/sina/MSSinaWeiboMessage/a()Lorg/apache/http/client/methods/HttpRequestBase;
  astore 16
  aload 16
  areturn
Label6:
  aconst_null
  astore 17
  aload 17
  areturn
  nop
.end <method>

