.source SourceFile
.class abstract  com/mobisage/android/aa
.super com/mobisage/android/O
.field protected "g" Lcom/mobisage/android/aa$a;
.field private "h" Lcom/mobisage/android/aa;

.method protected <init>(Landroid/os/Handler;)V
.limit locals 4
.limit stack 200
  nop
  aload_0
  aload_1
  invokespecial com/mobisage/android/O/<init>(Landroid/os/Handler;)V
  aload_0
  aload_0
  putfield com/mobisage/android/aa/h Lcom/mobisage/android/aa;
  new com/mobisage/android/aa$a
  astore_2
  iconst_0
  istore_3
  aload_2
  aload_0
  iload_3
  invokespecial com/mobisage/android/aa$a/<init>(Lcom/mobisage/android/aa;B)V
  aload_0
  aload_2
  putfield com/mobisage/android/aa/g Lcom/mobisage/android/aa$a;
  return
  nop
.end <method>

.method static a(Lcom/mobisage/android/aa;)Lcom/mobisage/android/aa;
  .synthetic
.limit locals 1
.limit stack 200
  nop
  aload_0
  getfield com/mobisage/android/aa/h Lcom/mobisage/android/aa;
  astore_0
  aload_0
  areturn
  nop
.end <method>

.method public final a(Landroid/os/Message;)V
.limit locals 23
.limit stack 200
  nop
  aload_1
  astore_2
  new java/lang/NoClassDefFoundError
  dup
  invokespecial java/lang/NoClassDefFoundError/<init>()V
  athrow
  aload_2
  astore_1
  aload_3
  instanceof com/mobisage/android/b
  istore 4
  iload 4
  invokestatic app/DummyClass/invokeIfStmt(Z)V
  iload 4
  ifeq Label0
  aload_1
  astore_2
  aload_2
  getfield android/os/Message/obj Ljava/lang/Object;
  astore_3
  aload_2
  astore_1
  aload_3
  astore 6
  aload 6
  checkcast com/mobisage/android/b
  astore 6
  aload 6
  astore 5
  aload_0
  astore_2
  aload_2
  aload 5
  invokevirtual com/mobisage/android/aa/f(Lcom/mobisage/android/b;)V
Label1:
  return
Label0:
  aload_1
  astore_2
  aload_2
  getfield android/os/Message/obj Ljava/lang/Object;
  astore_3
  aload_2
  astore_1
  aload_3
  instanceof com/mobisage/android/X
  istore 4
  iload 4
  invokestatic app/DummyClass/invokeIfStmt(Z)V
  iload 4
  ifeq Label1
  aload_1
  astore_2
  aload_2
  getfield android/os/Message/obj Ljava/lang/Object;
  astore_3
  aload_2
  astore_1
  aload_3
  astore 8
  aload 8
  checkcast com/mobisage/android/X
  astore 8
  aload 8
  astore 7
  aload 7
  getfield com/mobisage/android/MobiSageMessage/result Landroid/os/Bundle;
  astore 9
  ldc "StatusCode"
  astore 11
  aload 9
  aload 11
  invokevirtual android/os/Bundle/getInt(Ljava/lang/String;)I
  istore 10
  dload 10
  invokestatic app/DummyClass/invokeIfStmt(D)V
  sipush 200
  istore 12
  iload 10
  iload 12
  if_icmpeq Label2
  dload 10
  invokestatic app/DummyClass/invokeIfStmt(D)V
  sipush 302
  istore 12
  iload 10
  iload 12
  if_icmpne Label3
Label2:
  new java/io/File
  astore 13
  aload 7
  getfield com/mobisage/android/X/a Ljava/lang/String;
  astore 14
  aload 13
  aload 14
  invokespecial java/io/File/<init>(Ljava/lang/String;)V
  aload 13
  invokevirtual java/io/File/delete()Z
  pop
  aload_0
  astore_2
  aload_2
  getfield com/mobisage/android/O/f Ljava/util/concurrent/ConcurrentHashMap;
  astore 15
  aload 7
  getfield com/mobisage/android/MobiSageMessage/c Ljava/util/UUID;
  astore 16
  aload 15
  aload 16
  invokevirtual java/util/concurrent/ConcurrentHashMap/get(Ljava/lang/Object;)Ljava/lang/Object;
  astore_3
  aload_3
  astore 18
  aload 18
  checkcast java/util/UUID
  astore 18
  aload 18
  astore 17
  aload_0
  astore_2
  aload_2
  getfield com/mobisage/android/O/f Ljava/util/concurrent/ConcurrentHashMap;
  astore 15
  aload 7
  getfield com/mobisage/android/MobiSageMessage/c Ljava/util/UUID;
  astore 16
  aload 15
  aload 16
  invokevirtual java/util/concurrent/ConcurrentHashMap/remove(Ljava/lang/Object;)Ljava/lang/Object;
  pop
  aload_0
  astore_2
  aload_2
  getfield com/mobisage/android/O/e Ljava/util/concurrent/ConcurrentHashMap;
  astore 15
  aload 15
  aload 17
  invokevirtual java/util/concurrent/ConcurrentHashMap/get(Ljava/lang/Object;)Ljava/lang/Object;
  astore_3
  aload_3
  astore 19
  aload 19
  checkcast com/mobisage/android/b
  astore 19
  aload 19
  astore 5
  aload 5
  getfield com/mobisage/android/b/f Ljava/util/concurrent/LinkedBlockingQueue;
  astore_2
  aload_2
  astore 20
  aload 20
  astore_2
  aload_2
  aload 7
  invokevirtual java/util/concurrent/LinkedBlockingQueue/remove(Ljava/lang/Object;)Z
  pop
  aload 5
  getfield com/mobisage/android/b/f Ljava/util/concurrent/LinkedBlockingQueue;
  astore_2
  aload_2
  astore 20
  aload 20
  astore_2
  aload_2
  invokevirtual java/util/concurrent/LinkedBlockingQueue/size()I
  istore 10
  dload 10
  invokestatic app/DummyClass/invokeIfStmt(D)V
  iload 10
  ifne Label1
  aload_0
  astore_2
  aload_2
  getfield com/mobisage/android/O/e Ljava/util/concurrent/ConcurrentHashMap;
  astore 15
  aload 5
  getfield com/mobisage/android/b/b Ljava/util/UUID;
  astore 17
  aload 15
  aload 17
  invokevirtual java/util/concurrent/ConcurrentHashMap/remove(Ljava/lang/Object;)Ljava/lang/Object;
  pop
  aload 5
  getfield com/mobisage/android/b/g Lcom/mobisage/android/a;
  astore_2
  aload_2
  astore 21
  aload 21
  astore_2
  aload_2
  invokestatic app/DummyClass/invokeIfStmt(Ljava/lang/Object;)V
  aload 21
  ifnull Label1
  aload 5
  getfield com/mobisage/android/b/g Lcom/mobisage/android/a;
  astore_2
  aload_2
  astore 21
  aload 21
  astore_2
  aload_2
  aload 5
  invokeinterface com/mobisage/android/a/a(Lcom/mobisage/android/b;)V 2
  goto Label1
Label3:
  new android/os/Bundle
  astore 9
  aload 9
  invokespecial android/os/Bundle/<init>()V
  aload 7
  aload 9
  putfield com/mobisage/android/MobiSageMessage/result Landroid/os/Bundle;
  invokestatic com/mobisage/android/H/a()Lcom/mobisage/android/H;
  astore 22
  aload 22
  astore_2
  aload_2
  aload 7
  invokevirtual com/mobisage/android/H/a(Lcom/mobisage/android/MobiSageMessage;)V
  goto Label1
  nop
.end <method>

.method protected abstract f(Lcom/mobisage/android/b;)V
.end <method>

