.source MobiSageAdapter.java
.class public  com/admogo/adapters/MobiSageAdapter
.super com/admogo/adapters/AdMogoAdapter
.implements  com/mobisage/android/IMobiSageAdViewListener
.field private "activity" Landroid/app/Activity;
.field private "adView" Lcom/mobisage/android/MobiSageAdBanner;
.field "handler" Landroid/os/Handler;
.field private "task" Ljava/util/TimerTask;
.field private final "timer" Ljava/util/Timer;

.method public <init>(Lcom/admogo/AdMogoLayout;Lcom/admogo/obj/Ration;)V
.limit locals 9
.limit stack 200
  nop
  aload_0
  aload_1
  aload_2
  invokespecial com/admogo/adapters/AdMogoAdapter/<init>(Lcom/admogo/AdMogoLayout;Lcom/admogo/obj/Ration;)V
  new java/util/Timer
  astore_3
  aload_3
  invokespecial java/util/Timer/<init>()V
  aload_0
  aload_3
  putfield com/admogo/adapters/MobiSageAdapter/timer Ljava/util/Timer;
  new java/lang/NoClassDefFoundError
  dup
  invokespecial java/lang/NoClassDefFoundError/<init>()V
  athrow
  aload 4
  aload_0
  invokespecial com/admogo/adapters/MobiSageAdapter$1/<init>(Lcom/admogo/adapters/MobiSageAdapter;)V
  aload_0
  aload 4
  putfield com/admogo/adapters/MobiSageAdapter/handler Landroid/os/Handler;
  new com/admogo/adapters/MobiSageAdapter$2
  astore 5
  aload 5
  aload_0
  invokespecial com/admogo/adapters/MobiSageAdapter$2/<init>(Lcom/admogo/adapters/MobiSageAdapter;)V
  aload_0
  aload 5
  putfield com/admogo/adapters/MobiSageAdapter/task Ljava/util/TimerTask;
  aload_0
  getfield com/admogo/adapters/MobiSageAdapter/timer Ljava/util/Timer;
  astore_3
  aload_0
  getfield com/admogo/adapters/MobiSageAdapter/task Ljava/util/TimerTask;
  astore 6
  ldc2_w 15000
  lstore 7
  aload_3
  aload 6
  lload 7
  invokevirtual java/util/Timer/schedule(Ljava/util/TimerTask;J)V
  return
  nop
.end <method>

.method static access$0(Lcom/admogo/adapters/MobiSageAdapter;)Landroid/app/Activity;
  .synthetic
.limit locals 2
.limit stack 200
  nop
  aload_0
  getfield com/admogo/adapters/MobiSageAdapter/activity Landroid/app/Activity;
  astore_1
  aload_1
  areturn
  nop
.end <method>

.method public click()V
.limit locals 5
.limit stack 200
  nop
  aload_0
  getfield com/admogo/adapters/AdMogoAdapter/adMogoLayoutReference Ljava/lang/ref/WeakReference;
  astore_1
  aload_1
  invokevirtual java/lang/ref/WeakReference/get()Ljava/lang/Object;
  astore_2
  aload_2
  astore 4
  new java/lang/NoClassDefFoundError
  dup
  invokespecial java/lang/NoClassDefFoundError/<init>()V
  athrow
  aload 4
  astore_3
  aload_3
  invokevirtual com/admogo/AdMogoLayout/countClick()V
  return
  nop
.end <method>

.method public finish()V
.limit locals 1
.limit stack 200
  nop
  return
  nop
.end <method>

.method public handle()V
.limit locals 16
.limit stack 200
  nop
  aload_0
  getfield com/admogo/adapters/AdMogoAdapter/adMogoLayoutReference Ljava/lang/ref/WeakReference;
  astore_1
  aload_1
  invokevirtual java/lang/ref/WeakReference/get()Ljava/lang/Object;
  astore_2
  aload_2
  astore 4
  new java/lang/NoClassDefFoundError
  dup
  invokespecial java/lang/NoClassDefFoundError/<init>()V
  athrow
  aload 4
  astore_3
  aload_3
  invokestatic app/DummyClass/invokeIfStmt(Ljava/lang/Object;)V
  iload_3
  ifne Label0
Label1:
  return
Label0:
  aload_3
  getfield com/admogo/AdMogoLayout/activityReference Ljava/lang/ref/WeakReference;
  astore_1
  aload_1
  invokevirtual java/lang/ref/WeakReference/get()Ljava/lang/Object;
  astore_2
  aload_2
  astore 6
  aload 6
  checkcast android/app/Activity
  astore 6
  aload 6
  astore 5
  aload_0
  aload 5
  putfield com/admogo/adapters/MobiSageAdapter/activity Landroid/app/Activity;
  aload_0
  getfield com/admogo/adapters/MobiSageAdapter/activity Landroid/app/Activity;
  astore 5
  aload 5
  invokestatic app/DummyClass/invokeIfStmt(Ljava/lang/Object;)V
  aload 5
  ifnull Label1
Label3:
  aload_3
  invokevirtual com/admogo/AdMogoLayout/getAdType()I
  istore 7
  dload 7
  invokestatic app/DummyClass/invokeIfStmt(D)V
  bipush 6
  istore 8
  iload 7
  iload 8
  if_icmpeq Label1
  aload_3
  invokevirtual com/admogo/AdMogoLayout/getAdType()I
  istore 7
  dload 7
  invokestatic app/DummyClass/invokeIfStmt(D)V
  bipush 7
  istore 8
  iload 7
  iload 8
  if_icmpeq Label1
  new com/mobisage/android/MobiSageAdBanner
  astore 9
  aload_0
  getfield com/admogo/adapters/MobiSageAdapter/activity Landroid/app/Activity;
  astore 5
  aload_0
  getfield com/admogo/adapters/AdMogoAdapter/ration Lcom/admogo/obj/Ration;
  astore 10
  aload 10
  getfield com/admogo/obj/Ration/key Ljava/lang/String;
  astore 11
  aconst_null
  astore 12
  aconst_null
  astore 13
  aload 9
  aload 5
  aload 11
  aload 12
  aload 13
  invokespecial com/mobisage/android/MobiSageAdBanner/<init>(Landroid/content/Context;Ljava/lang/String;Ljava/lang/String;Ljava/lang/String;)V
  aload_0
  aload 9
  putfield com/admogo/adapters/MobiSageAdapter/adView Lcom/mobisage/android/MobiSageAdBanner;
  aload_0
  getfield com/admogo/adapters/MobiSageAdapter/adView Lcom/mobisage/android/MobiSageAdBanner;
  astore 9
  iconst_0
  istore 8
  iload 8
  invokestatic java/lang/Integer/valueOf(I)Ljava/lang/Integer;
  astore 14
  aload 9
  aload 14
  invokevirtual com/mobisage/android/MobiSageAdBanner/setAdRefreshInterval(Ljava/lang/Integer;)V
  aload_0
  getfield com/admogo/adapters/MobiSageAdapter/adView Lcom/mobisage/android/MobiSageAdBanner;
  astore 9
  aload_3
  aload 9
  invokevirtual com/admogo/AdMogoLayout/addView(Landroid/view/View;)V
  aload_0
  getfield com/admogo/adapters/MobiSageAdapter/adView Lcom/mobisage/android/MobiSageAdBanner;
  astore 9
  aload 9
  aload_0
  invokevirtual com/mobisage/android/MobiSageAdBanner/setMobiSageAdViewListener(Lcom/mobisage/android/IMobiSageAdViewListener;)V
Label4:
  goto Label1
Label2:
  astore 15
  aload_3
  invokevirtual com/admogo/AdMogoLayout/rollover()V
  goto Label1
  nop
.end <method>

.method public onMobiSageAdViewHide(Ljava/lang/Object;)V
.limit locals 2
.limit stack 200
  nop
  return
  nop
.end <method>

.method public onMobiSageAdViewShow(Ljava/lang/Object;)V
.limit locals 16
.limit stack 200
  nop
  aload_0
  getfield com/admogo/adapters/MobiSageAdapter/timer Ljava/util/Timer;
  astore_2
  aload_2
  invokevirtual java/util/Timer/cancel()V
  getstatic com/admogo/util/AdMogoUtil/ADMOGO Ljava/lang/String;
  astore_3
  ldc "MobiSage AdViewShow"
  astore 4
  new java/lang/NoClassDefFoundError
  dup
  invokespecial java/lang/NoClassDefFoundError/<init>()V
  athrow
  aload_0
  getfield com/admogo/adapters/MobiSageAdapter/adView Lcom/mobisage/android/MobiSageAdBanner;
  astore 5
  aconst_null
  astore 6
  aload 5
  aload 6
  invokevirtual com/mobisage/android/MobiSageAdBanner/setMobiSageAdViewListener(Lcom/mobisage/android/IMobiSageAdViewListener;)V
  aload_0
  getfield com/admogo/adapters/MobiSageAdapter/activity Landroid/app/Activity;
  astore 7
  aload 7
  invokevirtual android/app/Activity/isFinishing()Z
  istore 8
  iload 8
  invokestatic app/DummyClass/invokeIfStmt(Z)V
  iload 8
  ifne Label0
  aload_0
  getfield com/admogo/adapters/AdMogoAdapter/adMogoLayoutReference Ljava/lang/ref/WeakReference;
  astore 9
  aload 9
  invokevirtual java/lang/ref/WeakReference/get()Ljava/lang/Object;
  astore_1
  aload_1
  astore 11
  aload 11
  checkcast com/admogo/AdMogoLayout
  astore 11
  aload 11
  astore 10
  aload 10
  invokestatic app/DummyClass/invokeIfStmt(Ljava/lang/Object;)V
  aload 10
  ifnonnull Label1
Label0:
  return
Label1:
  aload 10
  getfield com/admogo/AdMogoLayout/adMogoManager Lcom/admogo/AdMogoManager;
  astore 12
  aload 12
  invokevirtual com/admogo/AdMogoManager/resetRollover()V
  aload 10
  getfield com/admogo/AdMogoLayout/handler Landroid/os/Handler;
  astore 13
  new com/admogo/AdMogoLayout$ViewAdRunnable
  astore 14
  aload_0
  getfield com/admogo/adapters/MobiSageAdapter/adView Lcom/mobisage/android/MobiSageAdBanner;
  astore 5
  bipush 31
  istore 15
  aload 14
  aload 10
  aload 5
  iload 15
  invokespecial com/admogo/AdMogoLayout$ViewAdRunnable/<init>(Lcom/admogo/AdMogoLayout;Landroid/view/ViewGroup;I)V
  aload 13
  aload 14
  invokevirtual android/os/Handler/post(Ljava/lang/Runnable;)Z
  pop
  aload 10
  invokevirtual com/admogo/AdMogoLayout/rotateThreadedDelayed()V
  goto Label0
  nop
.end <method>

.method public onMobiSageAdViewUpdate(Ljava/lang/Object;)V
.limit locals 3
.limit stack 200
  nop
  aload_0
  getfield com/admogo/adapters/MobiSageAdapter/timer Ljava/util/Timer;
  astore_2
  aload_2
  invokevirtual java/util/Timer/cancel()V
  return
  nop
.end <method>

