.source dalvik_source_VirusShare_32e70f448ebd75661a1cb12f9cd8e013.apk
.class public  com/tencent/mobwin/core/a/b
.super java/lang/Object
.field public "a" I
.field public "b" J
.field public "c" J
.field public "d" J
.field public "e" I
.field public "f" I
.field public "g" Ljava/lang/String;
.field public "h" Ljava/lang/String;
.field public "i" Ljava/lang/String;

.method public <init>()V
.limit locals 5
.limit stack 200
  nop
  aload_0
  invokespecial java/lang/Object/<init>()V
  iconst_0
  istore_1
  aload_0
  iload_1
  putfield com/tencent/mobwin/core/a/b/a I
  ldc2_w 0
  lstore_2
  aload_0
  lload_2
  putfield com/tencent/mobwin/core/a/b/b J
  ldc2_w 0
  lstore_2
  aload_0
  lload_2
  putfield com/tencent/mobwin/core/a/b/c J
  ldc2_w 0
  lstore_2
  aload_0
  lload_2
  putfield com/tencent/mobwin/core/a/b/d J
  iconst_0
  istore_1
  aload_0
  iload_1
  putfield com/tencent/mobwin/core/a/b/e I
  iconst_0
  istore_1
  aload_0
  iload_1
  putfield com/tencent/mobwin/core/a/b/f I
  ldc ""
  astore 4
  aload_0
  aload 4
  putfield com/tencent/mobwin/core/a/b/g Ljava/lang/String;
  ldc ""
  astore 4
  aload_0
  aload 4
  putfield com/tencent/mobwin/core/a/b/h Ljava/lang/String;
  ldc ""
  astore 4
  aload_0
  aload 4
  putfield com/tencent/mobwin/core/a/b/i Ljava/lang/String;
  return
  nop
.end <method>

.method public static a(Landroid/content/Context;)Lcom/tencent/mobwin/core/a/b;
.limit locals 12
.limit stack 200
  nop
  new com/tencent/mobwin/core/a/b
  astore_1
  aload_1
  invokespecial com/tencent/mobwin/core/a/b/<init>()V
  new java/lang/NoClassDefFoundError
  dup
  invokespecial java/lang/NoClassDefFoundError/<init>()V
  athrow
  iload_0
  ifeq Label0
  ldc "mobwin"
  astore_3
  iconst_0
  istore 4
  aload_0
  aload_3
  iload 4
  invokevirtual android/content/Context/getSharedPreferences(Ljava/lang/String;I)Landroid/content/SharedPreferences;
  astore_2
  ldc "ADID"
  astore_3
  iconst_0
  istore 4
  aload_2
  aload_3
  iload 4
  invokeinterface android/content/SharedPreferences/getInt(Ljava/lang/String;I)I 3
  istore 5
  aload_1
  iload 5
  putfield com/tencent/mobwin/core/a/b/a I
  ldc "ADSTART"
  astore_3
  ldc2_w 0
  lstore 8
  aload_2
  aload_3
  lload 8
  invokeinterface android/content/SharedPreferences/getLong(Ljava/lang/String;J)J 4
  lstore 6
  aload_1
  lload 6
  putfield com/tencent/mobwin/core/a/b/b J
  ldc "ADEND"
  astore_3
  ldc2_w 0
  lstore 8
  aload_2
  aload_3
  lload 8
  invokeinterface android/content/SharedPreferences/getLong(Ljava/lang/String;J)J 4
  lstore 6
  aload_1
  lload 6
  putfield com/tencent/mobwin/core/a/b/c J
  ldc "ADLAST"
  astore_3
  ldc2_w 0
  lstore 8
  aload_2
  aload_3
  lload 8
  invokeinterface android/content/SharedPreferences/getLong(Ljava/lang/String;J)J 4
  lstore 6
  aload_1
  lload 6
  putfield com/tencent/mobwin/core/a/b/d J
  ldc "ADRESULTCODE"
  astore_3
  iconst_0
  istore 4
  aload_2
  aload_3
  iload 4
  invokeinterface android/content/SharedPreferences/getInt(Ljava/lang/String;I)I 3
  istore 5
  aload_1
  iload 5
  putfield com/tencent/mobwin/core/a/b/f I
  ldc "ADGETMILLSECONDS"
  astore_3
  iconst_0
  istore 4
  aload_2
  aload_3
  iload 4
  invokeinterface android/content/SharedPreferences/getInt(Ljava/lang/String;I)I 3
  istore 5
  aload_1
  iload 5
  putfield com/tencent/mobwin/core/a/b/e I
  ldc "SDKTIMESTAMP"
  astore_3
  ldc ""
  astore 11
  aload_2
  aload_3
  aload 11
  invokeinterface android/content/SharedPreferences/getString(Ljava/lang/String;Ljava/lang/String;)Ljava/lang/String; 3
  astore 10
  aload_1
  aload 10
  putfield com/tencent/mobwin/core/a/b/g Ljava/lang/String;
  ldc "CURRENTSID"
  astore_3
  ldc ""
  astore 11
  aload_2
  aload_3
  aload 11
  invokeinterface android/content/SharedPreferences/getString(Ljava/lang/String;Ljava/lang/String;)Ljava/lang/String; 3
  astore 10
  aload_1
  aload 10
  putfield com/tencent/mobwin/core/a/b/h Ljava/lang/String;
  ldc "PRESID"
  astore_3
  ldc ""
  astore 11
  aload_2
  aload_3
  aload 11
  invokeinterface android/content/SharedPreferences/getString(Ljava/lang/String;Ljava/lang/String;)Ljava/lang/String; 3
  astore 10
  aload_1
  aload 10
  putfield com/tencent/mobwin/core/a/b/i Ljava/lang/String;
Label0:
  aload_1
  areturn
  nop
.end <method>

.method public static a(Landroid/content/Context;Lcom/tencent/mobwin/core/a/b;)V
.limit locals 11
.limit stack 200
  nop
  new java/lang/NoClassDefFoundError
  dup
  invokespecial java/lang/NoClassDefFoundError/<init>()V
  athrow
  iload_0
  ifeq Label0
  aload_1
  getfield com/tencent/mobwin/core/a/b/a I
  istore_2
  dload_2
  invokestatic app/DummyClass/invokeIfStmt(D)V
  iload_2
  ifeq Label0
  ldc "mobwin"
  astore 4
  iconst_0
  istore 5
  aload_0
  aload 4
  iload 5
  invokevirtual android/content/Context/getSharedPreferences(Ljava/lang/String;I)Landroid/content/SharedPreferences;
  astore_3
  aload_3
  invokeinterface android/content/SharedPreferences/edit()Landroid/content/SharedPreferences$Editor; 1
  astore 6
  aload_1
  getfield com/tencent/mobwin/core/a/b/a I
  istore_2
  ldc "ADID"
  astore 4
  aload 6
  aload 4
  iload_2
  invokeinterface android/content/SharedPreferences$Editor/putInt(Ljava/lang/String;I)Landroid/content/SharedPreferences$Editor; 3
  pop
  aload_1
  getfield com/tencent/mobwin/core/a/b/b J
  lstore 7
  ldc "ADSTART"
  astore 4
  aload 6
  aload 4
  lload 7
  invokeinterface android/content/SharedPreferences$Editor/putLong(Ljava/lang/String;J)Landroid/content/SharedPreferences$Editor; 4
  pop
  aload_1
  getfield com/tencent/mobwin/core/a/b/c J
  lstore 7
  ldc "ADEND"
  astore 4
  aload 6
  aload 4
  lload 7
  invokeinterface android/content/SharedPreferences$Editor/putLong(Ljava/lang/String;J)Landroid/content/SharedPreferences$Editor; 4
  pop
  aload_1
  getfield com/tencent/mobwin/core/a/b/d J
  lstore 7
  ldc "ADLAST"
  astore 4
  aload 6
  aload 4
  lload 7
  invokeinterface android/content/SharedPreferences$Editor/putLong(Ljava/lang/String;J)Landroid/content/SharedPreferences$Editor; 4
  pop
  aload_1
  getfield com/tencent/mobwin/core/a/b/f I
  istore_2
  ldc "ADRESULTCODE"
  astore 4
  aload 6
  aload 4
  iload_2
  invokeinterface android/content/SharedPreferences$Editor/putInt(Ljava/lang/String;I)Landroid/content/SharedPreferences$Editor; 3
  pop
  aload_1
  getfield com/tencent/mobwin/core/a/b/e I
  istore_2
  ldc "ADGETMILLSECONDS"
  astore 4
  aload 6
  aload 4
  iload_2
  invokeinterface android/content/SharedPreferences$Editor/putInt(Ljava/lang/String;I)Landroid/content/SharedPreferences$Editor; 3
  pop
  aload_1
  getfield com/tencent/mobwin/core/a/b/g Ljava/lang/String;
  astore 9
  ldc "SDKTIMESTAMP"
  astore 4
  aload 6
  aload 4
  aload 9
  invokeinterface android/content/SharedPreferences$Editor/putString(Ljava/lang/String;Ljava/lang/String;)Landroid/content/SharedPreferences$Editor; 3
  pop
  aload_1
  getfield com/tencent/mobwin/core/a/b/h Ljava/lang/String;
  astore 10
  ldc "CURRENTSID"
  astore 4
  aload 6
  aload 4
  aload 10
  invokeinterface android/content/SharedPreferences$Editor/putString(Ljava/lang/String;Ljava/lang/String;)Landroid/content/SharedPreferences$Editor; 3
  pop
  aload_1
  getfield com/tencent/mobwin/core/a/b/i Ljava/lang/String;
  astore 10
  ldc "PRESID"
  astore 4
  aload 6
  aload 4
  aload 10
  invokeinterface android/content/SharedPreferences$Editor/putString(Ljava/lang/String;Ljava/lang/String;)Landroid/content/SharedPreferences$Editor; 3
  pop
  aload 6
  invokeinterface android/content/SharedPreferences$Editor/commit()Z 1
  pop
Label0:
  return
  nop
.end <method>

