.source SourceFile
.class final  com/mobisage/android/ac
.super com/mobisage/android/aa

.method <init>(Landroid/os/Handler;)V
.limit locals 3
.limit stack 200
  nop
  aload_0
  aload_1
  invokespecial com/mobisage/android/aa/<init>(Landroid/os/Handler;)V
  sipush 2001
  istore_2
  aload_0
  iload_2
  putfield com/mobisage/android/O/c I
  return
  nop
.end <method>

.method protected final f(Lcom/mobisage/android/b;)V
.limit locals 31
.limit stack 200
  nop
  new java/lang/StringBuilder
  astore 5
  aload 5
  invokespecial java/lang/StringBuilder/<init>()V
  ldc "http://trc.adsage.com/trc/sdk/x.gif?"
  astore 6
  aload 5
  aload 6
  invokevirtual java/lang/StringBuilder/append(Ljava/lang/String;)Ljava/lang/StringBuilder;
  pop
  ldc "ver=M3_02"
  astore 6
  aload 5
  aload 6
  invokevirtual java/lang/StringBuilder/append(Ljava/lang/String;)Ljava/lang/StringBuilder;
  pop
  new java/lang/StringBuilder
  astore 7
  ldc "&md="
  astore 6
  aload 7
  aload 6
  invokespecial java/lang/StringBuilder/<init>(Ljava/lang/String;)V
  new java/lang/NoClassDefFoundError
  dup
  invokespecial java/lang/NoClassDefFoundError/<init>()V
  athrow
  aload 8
  invokestatic java/net/URLEncoder/encode(Ljava/lang/String;)Ljava/lang/String;
  astore 8
  aload 7
  aload 8
  invokevirtual java/lang/StringBuilder/append(Ljava/lang/String;)Ljava/lang/StringBuilder;
  astore 7
  aload 7
  invokevirtual java/lang/StringBuilder/toString()Ljava/lang/String;
  astore 8
  aload 5
  aload 8
  invokevirtual java/lang/StringBuilder/append(Ljava/lang/String;)Ljava/lang/StringBuilder;
  pop
  new java/lang/StringBuilder
  astore 7
  ldc "&pid="
  astore 6
  aload 7
  aload 6
  invokespecial java/lang/StringBuilder/<init>(Ljava/lang/String;)V
  getstatic com/mobisage/android/r/a Ljava/lang/String;
  astore 8
  aload 7
  aload 8
  invokevirtual java/lang/StringBuilder/append(Ljava/lang/String;)Ljava/lang/StringBuilder;
  astore 7
  aload 7
  invokevirtual java/lang/StringBuilder/toString()Ljava/lang/String;
  astore 8
  aload 5
  aload 8
  invokevirtual java/lang/StringBuilder/append(Ljava/lang/String;)Ljava/lang/StringBuilder;
  pop
  new java/lang/StringBuilder
  astore 7
  ldc "&muid="
  astore 6
  aload 7
  aload 6
  invokespecial java/lang/StringBuilder/<init>(Ljava/lang/String;)V
  getstatic com/mobisage/android/y/a Ljava/lang/String;
  astore 8
  aload 7
  aload 8
  invokevirtual java/lang/StringBuilder/append(Ljava/lang/String;)Ljava/lang/StringBuilder;
  astore 7
  aload 7
  invokevirtual java/lang/StringBuilder/toString()Ljava/lang/String;
  astore 8
  aload 5
  aload 8
  invokevirtual java/lang/StringBuilder/append(Ljava/lang/String;)Ljava/lang/StringBuilder;
  pop
  new java/lang/StringBuilder
  astore 7
  ldc "&ns="
  astore 6
  aload 7
  aload 6
  invokespecial java/lang/StringBuilder/<init>(Ljava/lang/String;)V
  aload_1
  astore_2
  aload_2
  getfield com/mobisage/android/b/c Landroid/os/Bundle;
  astore 9
  ldc "Network"
  astore 6
  aload 9
  aload 6
  invokevirtual android/os/Bundle/getString(Ljava/lang/String;)Ljava/lang/String;
  astore 8
  aload 7
  aload 8
  invokevirtual java/lang/StringBuilder/append(Ljava/lang/String;)Ljava/lang/StringBuilder;
  astore 7
  aload 7
  invokevirtual java/lang/StringBuilder/toString()Ljava/lang/String;
  astore 8
  aload 5
  aload 8
  invokevirtual java/lang/StringBuilder/append(Ljava/lang/String;)Ljava/lang/StringBuilder;
  pop
  new java/lang/StringBuilder
  astore 7
  ldc "&nsr="
  astore 6
  aload 7
  aload 6
  invokespecial java/lang/StringBuilder/<init>(Ljava/lang/String;)V
  aload_1
  astore_2
  aload_2
  getfield com/mobisage/android/b/c Landroid/os/Bundle;
  astore 9
  ldc "Carrier"
  astore 6
  aload 9
  aload 6
  invokevirtual android/os/Bundle/getString(Ljava/lang/String;)Ljava/lang/String;
  astore 8
  aload 7
  aload 8
  invokevirtual java/lang/StringBuilder/append(Ljava/lang/String;)Ljava/lang/StringBuilder;
  astore 7
  aload 7
  invokevirtual java/lang/StringBuilder/toString()Ljava/lang/String;
  astore 8
  aload 5
  aload 8
  invokevirtual java/lang/StringBuilder/append(Ljava/lang/String;)Ljava/lang/StringBuilder;
  pop
  ldc "&av=2.3.0"
  astore 6
  aload 5
  aload 6
  invokevirtual java/lang/StringBuilder/append(Ljava/lang/String;)Ljava/lang/StringBuilder;
  pop
  new java/lang/StringBuilder
  astore 7
  ldc "&eid="
  astore 6
  aload 7
  aload 6
  invokespecial java/lang/StringBuilder/<init>(Ljava/lang/String;)V
  aload_1
  astore_2
  aload_2
  getfield com/mobisage/android/b/c Landroid/os/Bundle;
  astore 9
  ldc "EventID"
  astore 6
  aload 9
  aload 6
  invokevirtual android/os/Bundle/getString(Ljava/lang/String;)Ljava/lang/String;
  astore 8
  aload 7
  aload 8
  invokevirtual java/lang/StringBuilder/append(Ljava/lang/String;)Ljava/lang/StringBuilder;
  astore 7
  aload 7
  invokevirtual java/lang/StringBuilder/toString()Ljava/lang/String;
  astore 8
  aload 5
  aload 8
  invokevirtual java/lang/StringBuilder/append(Ljava/lang/String;)Ljava/lang/StringBuilder;
  pop
  new java/lang/StringBuilder
  astore 7
  ldc "&eb="
  astore 6
  aload 7
  aload 6
  invokespecial java/lang/StringBuilder/<init>(Ljava/lang/String;)V
  aload_1
  astore_2
  aload_2
  getfield com/mobisage/android/b/c Landroid/os/Bundle;
  astore 9
  ldc "EventObject"
  astore 6
  aload 9
  aload 6
  invokevirtual android/os/Bundle/getString(Ljava/lang/String;)Ljava/lang/String;
  astore 8
  aload 8
  invokestatic java/net/URLEncoder/encode(Ljava/lang/String;)Ljava/lang/String;
  astore 8
  aload 7
  aload 8
  invokevirtual java/lang/StringBuilder/append(Ljava/lang/String;)Ljava/lang/StringBuilder;
  astore 7
  aload 7
  invokevirtual java/lang/StringBuilder/toString()Ljava/lang/String;
  astore 8
  aload 5
  aload 8
  invokevirtual java/lang/StringBuilder/append(Ljava/lang/String;)Ljava/lang/StringBuilder;
  pop
  new java/lang/StringBuilder
  astore 7
  ldc "&se="
  astore 6
  aload 7
  aload 6
  invokespecial java/lang/StringBuilder/<init>(Ljava/lang/String;)V
  aload_1
  astore_2
  aload_2
  getfield com/mobisage/android/b/c Landroid/os/Bundle;
  astore 9
  ldc "SystemEvent"
  astore 6
  aload 9
  aload 6
  invokevirtual android/os/Bundle/getString(Ljava/lang/String;)Ljava/lang/String;
  astore 8
  aload 7
  aload 8
  invokevirtual java/lang/StringBuilder/append(Ljava/lang/String;)Ljava/lang/StringBuilder;
  astore 7
  aload 7
  invokevirtual java/lang/StringBuilder/toString()Ljava/lang/String;
  astore 8
  aload 5
  aload 8
  invokevirtual java/lang/StringBuilder/append(Ljava/lang/String;)Ljava/lang/StringBuilder;
  pop
  new android/text/format/Time
  astore 10
  aload 10
  invokespecial android/text/format/Time/<init>()V
  aload 10
  invokevirtual android/text/format/Time/setToNow()V
  getstatic com/mobisage/android/r/g J
  lstore 11
  ldc2_w 0
  lstore 14
  lload 11
  lload 14
  lcmp
  istore 13
  dload 13
  invokestatic app/DummyClass/invokeIfStmt(D)V
  iload 13
  ifne Label0
  ldc "&st=0"
  astore 6
  aload 5
  aload 6
  invokevirtual java/lang/StringBuilder/append(Ljava/lang/String;)Ljava/lang/StringBuilder;
  pop
  iconst_1
  istore 16
  aload 10
  iload 16
  invokevirtual android/text/format/Time/toMillis(Z)J
  lstore 11
  lload 11
  putstatic com/mobisage/android/r/g J
Label1:
  new java/lang/StringBuilder
  astore 7
  ldc "&et="
  astore 6
  aload 7
  aload 6
  invokespecial java/lang/StringBuilder/<init>(Ljava/lang/String;)V
  ldc "%Y-%m-%d"
  astore 6
  aload 10
  aload 6
  invokevirtual android/text/format/Time/format(Ljava/lang/String;)Ljava/lang/String;
  astore 8
  aload 7
  aload 8
  invokevirtual java/lang/StringBuilder/append(Ljava/lang/String;)Ljava/lang/StringBuilder;
  astore 7
  aload 7
  invokevirtual java/lang/StringBuilder/toString()Ljava/lang/String;
  astore 8
  aload 5
  aload 8
  invokevirtual java/lang/StringBuilder/append(Ljava/lang/String;)Ljava/lang/StringBuilder;
  pop
  new java/lang/StringBuilder
  astore 7
  ldc "&scr="
  astore 6
  aload 7
  aload 6
  invokespecial java/lang/StringBuilder/<init>(Ljava/lang/String;)V
  getstatic com/mobisage/android/y/d Ljava/lang/String;
  astore 8
  aload 7
  aload 8
  invokevirtual java/lang/StringBuilder/append(Ljava/lang/String;)Ljava/lang/StringBuilder;
  astore 7
  aload 7
  invokevirtual java/lang/StringBuilder/toString()Ljava/lang/String;
  astore 8
  aload 5
  aload 8
  invokevirtual java/lang/StringBuilder/append(Ljava/lang/String;)Ljava/lang/StringBuilder;
  pop
  ldc "&ol=1"
  astore 6
  aload 5
  aload 6
  invokevirtual java/lang/StringBuilder/append(Ljava/lang/String;)Ljava/lang/StringBuilder;
  pop
  new java/lang/StringBuilder
  astore 7
  ldc "&sv="
  astore 6
  aload 7
  aload 6
  invokespecial java/lang/StringBuilder/<init>(Ljava/lang/String;)V
  getstatic android/os/Build$VERSION/RELEASE Ljava/lang/String;
  astore 8
  aload 7
  aload 8
  invokevirtual java/lang/StringBuilder/append(Ljava/lang/String;)Ljava/lang/StringBuilder;
  astore 7
  aload 7
  invokevirtual java/lang/StringBuilder/toString()Ljava/lang/String;
  astore 8
  aload 5
  aload 8
  invokevirtual java/lang/StringBuilder/append(Ljava/lang/String;)Ljava/lang/StringBuilder;
  pop
  new java/lang/StringBuilder
  astore 7
  ldc "&sl="
  astore 6
  aload 7
  aload 6
  invokespecial java/lang/StringBuilder/<init>(Ljava/lang/String;)V
  invokestatic java/util/Locale/getDefault()Ljava/util/Locale;
  astore 17
  aload 17
  invokevirtual java/util/Locale/getLanguage()Ljava/lang/String;
  astore 8
  aload 7
  aload 8
  invokevirtual java/lang/StringBuilder/append(Ljava/lang/String;)Ljava/lang/StringBuilder;
  astore 7
  aload 7
  invokevirtual java/lang/StringBuilder/toString()Ljava/lang/String;
  astore 8
  aload 5
  aload 8
  invokevirtual java/lang/StringBuilder/append(Ljava/lang/String;)Ljava/lang/StringBuilder;
  pop
  new java/lang/StringBuilder
  astore 7
  ldc "&cv="
  astore 6
  aload 7
  aload 6
  invokespecial java/lang/StringBuilder/<init>(Ljava/lang/String;)V
  aload_1
  astore_2
  aload_2
  getfield com/mobisage/android/b/c Landroid/os/Bundle;
  astore 9
  ldc "AppVersion"
  astore 6
  aload 9
  aload 6
  invokevirtual android/os/Bundle/getString(Ljava/lang/String;)Ljava/lang/String;
  astore 8
  aload 7
  aload 8
  invokevirtual java/lang/StringBuilder/append(Ljava/lang/String;)Ljava/lang/StringBuilder;
  astore 7
  aload 7
  invokevirtual java/lang/StringBuilder/toString()Ljava/lang/String;
  astore 8
  aload 5
  aload 8
  invokevirtual java/lang/StringBuilder/append(Ljava/lang/String;)Ljava/lang/StringBuilder;
  pop
  ldc "&ib=1"
  astore 6
  aload 5
  aload 6
  invokevirtual java/lang/StringBuilder/append(Ljava/lang/String;)Ljava/lang/StringBuilder;
  pop
  new java/lang/StringBuilder
  astore 7
  ldc "&tm="
  astore 6
  aload 7
  aload 6
  invokespecial java/lang/StringBuilder/<init>(Ljava/lang/String;)V
  ldc "%H:%M:%S"
  astore 6
  aload 10
  aload 6
  invokevirtual android/text/format/Time/format(Ljava/lang/String;)Ljava/lang/String;
  astore 8
  aload 7
  aload 8
  invokevirtual java/lang/StringBuilder/append(Ljava/lang/String;)Ljava/lang/StringBuilder;
  astore 7
  aload 7
  invokevirtual java/lang/StringBuilder/toString()Ljava/lang/String;
  astore 8
  aload 5
  aload 8
  invokevirtual java/lang/StringBuilder/append(Ljava/lang/String;)Ljava/lang/StringBuilder;
  pop
  new java/lang/StringBuilder
  astore 7
  ldc "&tz="
  astore 6
  aload 7
  aload 6
  invokespecial java/lang/StringBuilder/<init>(Ljava/lang/String;)V
  invokestatic android/text/format/Time/getCurrentTimezone()Ljava/lang/String;
  astore 8
  aload 7
  aload 8
  invokevirtual java/lang/StringBuilder/append(Ljava/lang/String;)Ljava/lang/StringBuilder;
  astore 7
  aload 7
  invokevirtual java/lang/StringBuilder/toString()Ljava/lang/String;
  astore 8
  aload 5
  aload 8
  invokevirtual java/lang/StringBuilder/append(Ljava/lang/String;)Ljava/lang/StringBuilder;
  pop
  new java/lang/StringBuilder
  astore 7
  ldc "&sid="
  astore 6
  aload 7
  aload 6
  invokespecial java/lang/StringBuilder/<init>(Ljava/lang/String;)V
  getstatic com/mobisage/android/r/g J
  lstore 11
  ldc2_w 1000
  lstore 14
  lload 11
  lload 14
  ldiv
  lstore 11
  lload 11
  invokestatic java/lang/String/valueOf(J)Ljava/lang/String;
  astore 8
  aload 7
  aload 8
  invokevirtual java/lang/StringBuilder/append(Ljava/lang/String;)Ljava/lang/StringBuilder;
  astore 7
  aload 7
  invokevirtual java/lang/StringBuilder/toString()Ljava/lang/String;
  astore 8
  aload 5
  aload 8
  invokevirtual java/lang/StringBuilder/append(Ljava/lang/String;)Ljava/lang/StringBuilder;
  pop
  new java/lang/StringBuilder
  astore 7
  ldc "&ich="
  astore 6
  aload 7
  aload 6
  invokespecial java/lang/StringBuilder/<init>(Ljava/lang/String;)V
  getstatic com/mobisage/android/r/b Ljava/lang/String;
  astore 8
  aload 8
  invokestatic java/net/URLEncoder/encode(Ljava/lang/String;)Ljava/lang/String;
  astore 8
  aload 7
  aload 8
  invokevirtual java/lang/StringBuilder/append(Ljava/lang/String;)Ljava/lang/StringBuilder;
  astore 7
  aload 7
  invokevirtual java/lang/StringBuilder/toString()Ljava/lang/String;
  astore 8
  aload 5
  aload 8
  invokevirtual java/lang/StringBuilder/append(Ljava/lang/String;)Ljava/lang/StringBuilder;
  pop
  new java/lang/StringBuilder
  astore 7
  ldc "&mac="
  astore 6
  aload 7
  aload 6
  invokespecial java/lang/StringBuilder/<init>(Ljava/lang/String;)V
  getstatic com/mobisage/android/r/h Landroid/content/Context;
  astore 18
  aload 18
  astore_2
  aload_2
  invokestatic com/mobisage/android/y/b(Landroid/content/Context;)Ljava/lang/String;
  astore 8
  aload 7
  aload 8
  invokevirtual java/lang/StringBuilder/append(Ljava/lang/String;)Ljava/lang/StringBuilder;
  astore 7
  aload 7
  invokevirtual java/lang/StringBuilder/toString()Ljava/lang/String;
  astore 8
  aload 5
  aload 8
  invokevirtual java/lang/StringBuilder/append(Ljava/lang/String;)Ljava/lang/StringBuilder;
  pop
  new java/lang/StringBuilder
  astore 7
  ldc "&udid="
  astore 6
  aload 7
  aload 6
  invokespecial java/lang/StringBuilder/<init>(Ljava/lang/String;)V
  getstatic com/mobisage/android/y/g Ljava/lang/String;
  astore 8
  aload 7
  aload 8
  invokevirtual java/lang/StringBuilder/append(Ljava/lang/String;)Ljava/lang/StringBuilder;
  astore 7
  aload 7
  invokevirtual java/lang/StringBuilder/toString()Ljava/lang/String;
  astore 8
  aload 5
  aload 8
  invokevirtual java/lang/StringBuilder/append(Ljava/lang/String;)Ljava/lang/StringBuilder;
  pop
  new java/lang/StringBuilder
  astore 7
  ldc "&loc="
  astore 6
  aload 7
  aload 6
  invokespecial java/lang/StringBuilder/<init>(Ljava/lang/String;)V
  invokestatic com/mobisage/android/D/a()Lcom/mobisage/android/D;
  astore 19
  aload 19
  astore_2
  aload_2
  invokevirtual com/mobisage/android/D/b()Ljava/lang/String;
  astore 8
  aload 8
  invokestatic java/net/URLEncoder/encode(Ljava/lang/String;)Ljava/lang/String;
  astore 8
  aload 7
  aload 8
  invokevirtual java/lang/StringBuilder/append(Ljava/lang/String;)Ljava/lang/StringBuilder;
  astore 7
  aload 7
  invokevirtual java/lang/StringBuilder/toString()Ljava/lang/String;
  astore 8
  aload 5
  aload 8
  invokevirtual java/lang/StringBuilder/append(Ljava/lang/String;)Ljava/lang/StringBuilder;
  pop
  new java/lang/StringBuilder
  astore 7
  ldc "&oid="
  astore 6
  aload 7
  aload 6
  invokespecial java/lang/StringBuilder/<init>(Ljava/lang/String;)V
  iconst_2
  istore 16
  iload 16
  invokestatic java/lang/String/valueOf(I)Ljava/lang/String;
  astore 8
  aload 7
  aload 8
  invokevirtual java/lang/StringBuilder/append(Ljava/lang/String;)Ljava/lang/StringBuilder;
  astore 7
  aload 7
  invokevirtual java/lang/StringBuilder/toString()Ljava/lang/String;
  astore 8
  aload 5
  aload 8
  invokevirtual java/lang/StringBuilder/append(Ljava/lang/String;)Ljava/lang/StringBuilder;
  pop
  new java/lang/StringBuilder
  astore 7
  aload 7
  invokespecial java/lang/StringBuilder/<init>()V
  getstatic com/mobisage/android/r/f Ljava/lang/String;
  astore 8
  aload 7
  aload 8
  invokevirtual java/lang/StringBuilder/append(Ljava/lang/String;)Ljava/lang/StringBuilder;
  astore 7
  ldc "/Track"
  astore 6
  aload 7
  aload 6
  invokevirtual java/lang/StringBuilder/append(Ljava/lang/String;)Ljava/lang/StringBuilder;
  astore 7
  ldc "/"
  astore 6
  aload 7
  aload 6
  invokevirtual java/lang/StringBuilder/append(Ljava/lang/String;)Ljava/lang/StringBuilder;
  astore 7
  iconst_1
  istore 16
  aload 10
  iload 16
  invokevirtual android/text/format/Time/toMillis(Z)J
  lstore 11
  ldc2_w 1000
  lstore 14
  lload 11
  lload 14
  ldiv
  lstore 11
  lload 11
  invokestatic java/lang/String/valueOf(J)Ljava/lang/String;
  astore 8
  aload 7
  aload 8
  invokevirtual java/lang/StringBuilder/append(Ljava/lang/String;)Ljava/lang/StringBuilder;
  astore 7
  ldc "_"
  astore 6
  aload 7
  aload 6
  invokevirtual java/lang/StringBuilder/append(Ljava/lang/String;)Ljava/lang/StringBuilder;
  astore 7
  invokestatic java/util/UUID/randomUUID()Ljava/util/UUID;
  astore 20
  aload 20
  astore_2
  aload_2
  invokevirtual java/util/UUID/toString()Ljava/lang/String;
  astore 8
  aload 7
  aload 8
  invokevirtual java/lang/StringBuilder/append(Ljava/lang/String;)Ljava/lang/StringBuilder;
  astore 7
  ldc ".dat"
  astore 6
  aload 7
  aload 6
  invokevirtual java/lang/StringBuilder/append(Ljava/lang/String;)Ljava/lang/StringBuilder;
  astore 7
  aload 7
  invokevirtual java/lang/StringBuilder/toString()Ljava/lang/String;
  astore 8
  new java/io/File
  astore 21
  aload 21
  astore_2
  aload_2
  aload 8
  invokespecial java/io/File/<init>(Ljava/lang/String;)V
  aload 21
  astore_2
  aload_2
  invokevirtual java/io/File/mkdirs()Z
  pop
  aload 5
  invokevirtual java/lang/StringBuilder/toString()Ljava/lang/String;
  astore 22
  aload 21
  astore_2
  aload 22
  astore_3
  aload_2
  aload_3
  invokestatic com/mobisage/android/SNSSSLSocketFactory$a/a(Ljava/io/File;Ljava/lang/String;)V
  aload_0
  astore_2
  aload_2
  getfield com/mobisage/android/O/e Ljava/util/concurrent/ConcurrentHashMap;
  astore_2
  aload_2
  astore 23
  aload_1
  astore_2
  aload_2
  getfield com/mobisage/android/b/b Ljava/util/UUID;
  astore_2
  aload_2
  astore 20
  aload 23
  astore_2
  aload 20
  astore_3
  aload_1
  astore 4
  aload_2
  aload_3
  aload 4
  invokevirtual java/util/concurrent/ConcurrentHashMap/put(Ljava/lang/Object;Ljava/lang/Object;)Ljava/lang/Object;
  pop
  new com/mobisage/android/X
  astore 24
  aload 24
  astore_2
  aload_2
  invokespecial com/mobisage/android/X/<init>()V
  aload 24
  astore_2
  aload_2
  aload 8
  putfield com/mobisage/android/X/a Ljava/lang/String;
  aload_0
  astore_2
  aload_2
  getfield com/mobisage/android/aa/g Lcom/mobisage/android/aa$a;
  astore_2
  aload_2
  astore 25
  aload 25
  astore_2
  aload 24
  astore_3
  aload_3
  aload_2
  putfield com/mobisage/android/MobiSageMessage/callback Lcom/mobisage/android/IMobiSageMessageCallback;
  aload_1
  astore_2
  aload_2
  getfield com/mobisage/android/b/f Ljava/util/concurrent/LinkedBlockingQueue;
  astore_2
  aload_2
  astore 26
  aload 26
  astore_2
  aload 24
  astore_3
  aload_2
  aload_3
  invokevirtual java/util/concurrent/LinkedBlockingQueue/add(Ljava/lang/Object;)Z
  pop
  aload_0
  astore_2
  aload_2
  getfield com/mobisage/android/O/f Ljava/util/concurrent/ConcurrentHashMap;
  astore_2
  aload_2
  astore 23
  aload 24
  astore_2
  aload_2
  getfield com/mobisage/android/MobiSageMessage/c Ljava/util/UUID;
  astore_2
  aload_2
  astore 20
  aload_1
  astore_2
  aload_2
  getfield com/mobisage/android/b/b Ljava/util/UUID;
  astore_2
  aload_2
  astore 27
  aload 23
  astore_2
  aload 20
  astore_3
  aload 27
  astore 4
  aload_2
  aload_3
  aload 4
  invokevirtual java/util/concurrent/ConcurrentHashMap/put(Ljava/lang/Object;Ljava/lang/Object;)Ljava/lang/Object;
  pop
  invokestatic com/mobisage/android/H/a()Lcom/mobisage/android/H;
  astore 28
  aload 28
  astore_2
  aload 24
  astore_3
  aload_2
  aload_3
  invokevirtual com/mobisage/android/H/a(Lcom/mobisage/android/MobiSageMessage;)V
  return
Label0:
  iconst_1
  istore 16
  aload 10
  iload 16
  invokevirtual android/text/format/Time/toMillis(Z)J
  lstore 11
  new java/lang/StringBuilder
  astore 7
  ldc "&st="
  astore 6
  aload 7
  aload 6
  invokespecial java/lang/StringBuilder/<init>(Ljava/lang/String;)V
  getstatic com/mobisage/android/r/g J
  lstore 29
  lload 11
  lload 29
  lsub
  lstore 29
  ldc2_w 1000
  lstore 14
  lload 29
  lstore_2
  lload_2
  lload 14
  ldiv
  lstore_2
  lload_2
  lstore 29
  lload 29
  lstore_2
  lload_2
  invokestatic java/lang/String/valueOf(J)Ljava/lang/String;
  astore 22
  aload 22
  astore_2
  aload 7
  aload_2
  invokevirtual java/lang/StringBuilder/append(Ljava/lang/String;)Ljava/lang/StringBuilder;
  astore 7
  aload 7
  invokevirtual java/lang/StringBuilder/toString()Ljava/lang/String;
  astore 22
  aload 22
  astore_2
  aload 5
  aload_2
  invokevirtual java/lang/StringBuilder/append(Ljava/lang/String;)Ljava/lang/StringBuilder;
  pop
  ldc2_w 0
  lstore 14
  lload 14
  putstatic com/mobisage/android/r/g J
  goto Label1
  nop
.end <method>

