.source dalvik_source_VirusShare_32e70f448ebd75661a1cb12f9cd8e013.apk
.class  com/kuguo/ad/r
.super java/lang/Object
.field "a" Landroid/graphics/drawable/GradientDrawable;
.field "b" Landroid/graphics/drawable/GradientDrawable;
.field "c" Landroid/graphics/drawable/GradientDrawable;
.field "d" Landroid/graphics/drawable/GradientDrawable;
.field final "e" Lcom/kuguo/ad/l;

.method public <init>(Lcom/kuguo/ad/l;I)V
.limit locals 11
.limit stack 200
  nop
  aload_0
  aload_1
  putfield com/kuguo/ad/r/e Lcom/kuguo/ad/l;
  aload_0
  invokespecial java/lang/Object/<init>()V
  new java/lang/NoClassDefFoundError
  dup
  invokespecial java/lang/NoClassDefFoundError/<init>()V
  athrow
  iload_2
  lookupswitch
  0 : Label1
  1 : Label2
  2 : Label3
  3 : Label4
  default : Label0
Label0:
  goto Label5
Label5:
  new android/graphics/drawable/GradientDrawable
  astore_3
  getstatic android/graphics/drawable/GradientDrawable$Orientation/TOP_BOTTOM Landroid/graphics/drawable/GradientDrawable$Orientation;
  astore 4
  iconst_3
  istore 6
  iload 6
  newarray int
  astore 5
  iconst_0
  istore 6
  ldc -16744193
  istore 7
  aload 5
  iload 6
  iload 7
  iastore
  iconst_1
  istore 6
  ldc -8076801
  istore 7
  aload 5
  iload 6
  iload 7
  iastore
  iconst_2
  istore 6
  ldc -16744193
  istore 7
  aload 5
  iload 6
  iload 7
  iastore
  aload_3
  aload 4
  aload 5
  invokespecial android/graphics/drawable/GradientDrawable/<init>(Landroid/graphics/drawable/GradientDrawable$Orientation;[I)V
  aload_0
  aload_3
  putfield com/kuguo/ad/r/a Landroid/graphics/drawable/GradientDrawable;
  new android/graphics/drawable/GradientDrawable
  astore_3
  getstatic android/graphics/drawable/GradientDrawable$Orientation/BOTTOM_TOP Landroid/graphics/drawable/GradientDrawable$Orientation;
  astore 4
  iconst_3
  istore 6
  iload 6
  newarray int
  astore 5
  iconst_0
  istore 6
  ldc -16744193
  istore 7
  aload 5
  iload 6
  iload 7
  iastore
  iconst_1
  istore 6
  ldc -8076801
  istore 7
  aload 5
  iload 6
  iload 7
  iastore
  iconst_2
  istore 6
  ldc -16744193
  istore 7
  aload 5
  iload 6
  iload 7
  iastore
  aload_3
  aload 4
  aload 5
  invokespecial android/graphics/drawable/GradientDrawable/<init>(Landroid/graphics/drawable/GradientDrawable$Orientation;[I)V
  aload_0
  aload_3
  putfield com/kuguo/ad/r/b Landroid/graphics/drawable/GradientDrawable;
  new android/graphics/drawable/GradientDrawable
  astore_3
  aload_3
  invokespecial android/graphics/drawable/GradientDrawable/<init>()V
  aload_0
  aload_3
  putfield com/kuguo/ad/r/c Landroid/graphics/drawable/GradientDrawable;
  aload_0
  getfield com/kuguo/ad/r/c Landroid/graphics/drawable/GradientDrawable;
  astore_3
  aload_1
  invokestatic com/kuguo/ad/l/a(Lcom/kuguo/ad/l;)Landroid/content/Context;
  astore 8
  iconst_5
  istore 6
  aload 8
  iload 6
  invokestatic com/kuguo/ad/d/a(Landroid/content/Context;I)I
  istore_2
  iload_2
  i2f
  fstore 9
  aload_3
  fload 9
  invokevirtual android/graphics/drawable/GradientDrawable/setCornerRadius(F)V
  aload_0
  getfield com/kuguo/ad/r/c Landroid/graphics/drawable/GradientDrawable;
  astore_3
  iconst_0
  istore 6
  aload_3
  iload 6
  invokevirtual android/graphics/drawable/GradientDrawable/setColor(I)V
  new android/graphics/drawable/GradientDrawable
  astore_3
  aload_3
  invokespecial android/graphics/drawable/GradientDrawable/<init>()V
  aload_0
  aload_3
  putfield com/kuguo/ad/r/d Landroid/graphics/drawable/GradientDrawable;
  aload_0
  getfield com/kuguo/ad/r/d Landroid/graphics/drawable/GradientDrawable;
  astore_3
  ldc 1998133616
  istore 6
  aload_3
  iload 6
  invokevirtual android/graphics/drawable/GradientDrawable/setColor(I)V
  aload_0
  getfield com/kuguo/ad/r/d Landroid/graphics/drawable/GradientDrawable;
  astore_3
  aload_1
  invokestatic com/kuguo/ad/l/a(Lcom/kuguo/ad/l;)Landroid/content/Context;
  astore 8
  iconst_5
  istore 6
  aload 8
  iload 6
  invokestatic com/kuguo/ad/d/a(Landroid/content/Context;I)I
  istore 10
  iload 10
  i2f
  fstore 9
  aload_3
  fload 9
  invokevirtual android/graphics/drawable/GradientDrawable/setCornerRadius(F)V
Label6:
  return
Label1:
  new android/graphics/drawable/GradientDrawable
  astore_3
  getstatic android/graphics/drawable/GradientDrawable$Orientation/TOP_BOTTOM Landroid/graphics/drawable/GradientDrawable$Orientation;
  astore 4
  iconst_3
  istore 6
  iload 6
  newarray int
  astore 5
  iconst_0
  istore 6
  ldc -11364418
  istore 7
  aload 5
  iload 6
  iload 7
  iastore
  iconst_1
  istore 6
  ldc -11364418
  istore 7
  aload 5
  iload 6
  iload 7
  iastore
  iconst_2
  istore 6
  ldc -11364418
  istore 7
  aload 5
  iload 6
  iload 7
  iastore
  aload_3
  aload 4
  aload 5
  invokespecial android/graphics/drawable/GradientDrawable/<init>(Landroid/graphics/drawable/GradientDrawable$Orientation;[I)V
  aload_0
  aload_3
  putfield com/kuguo/ad/r/a Landroid/graphics/drawable/GradientDrawable;
  new android/graphics/drawable/GradientDrawable
  astore_3
  getstatic android/graphics/drawable/GradientDrawable$Orientation/BOTTOM_TOP Landroid/graphics/drawable/GradientDrawable$Orientation;
  astore 4
  iconst_3
  istore 6
  iload 6
  newarray int
  astore 5
  iconst_0
  istore 6
  ldc -11364418
  istore 7
  aload 5
  iload 6
  iload 7
  iastore
  iconst_1
  istore 6
  ldc -11364418
  istore 7
  aload 5
  iload 6
  iload 7
  iastore
  iconst_2
  istore 6
  ldc -11364418
  istore 7
  aload 5
  iload 6
  iload 7
  iastore
  aload_3
  aload 4
  aload 5
  invokespecial android/graphics/drawable/GradientDrawable/<init>(Landroid/graphics/drawable/GradientDrawable$Orientation;[I)V
  aload_0
  aload_3
  putfield com/kuguo/ad/r/b Landroid/graphics/drawable/GradientDrawable;
  new android/graphics/drawable/GradientDrawable
  astore_3
  aload_3
  invokespecial android/graphics/drawable/GradientDrawable/<init>()V
  aload_0
  aload_3
  putfield com/kuguo/ad/r/c Landroid/graphics/drawable/GradientDrawable;
  aload_0
  getfield com/kuguo/ad/r/c Landroid/graphics/drawable/GradientDrawable;
  astore_3
  aload_1
  invokestatic com/kuguo/ad/l/a(Lcom/kuguo/ad/l;)Landroid/content/Context;
  astore 8
  iconst_5
  istore 6
  aload 8
  iload 6
  invokestatic com/kuguo/ad/d/a(Landroid/content/Context;I)I
  istore_2
  iload_2
  i2f
  fstore 9
  aload_3
  fload 9
  invokevirtual android/graphics/drawable/GradientDrawable/setCornerRadius(F)V
  aload_0
  getfield com/kuguo/ad/r/c Landroid/graphics/drawable/GradientDrawable;
  astore_3
  iconst_0
  istore 6
  aload_3
  iload 6
  invokevirtual android/graphics/drawable/GradientDrawable/setColor(I)V
  new android/graphics/drawable/GradientDrawable
  astore_3
  aload_3
  invokespecial android/graphics/drawable/GradientDrawable/<init>()V
  aload_0
  aload_3
  putfield com/kuguo/ad/r/d Landroid/graphics/drawable/GradientDrawable;
  aload_0
  getfield com/kuguo/ad/r/d Landroid/graphics/drawable/GradientDrawable;
  astore_3
  ldc 1998133616
  istore 6
  aload_3
  iload 6
  invokevirtual android/graphics/drawable/GradientDrawable/setColor(I)V
  aload_0
  getfield com/kuguo/ad/r/d Landroid/graphics/drawable/GradientDrawable;
  astore_3
  aload_1
  invokestatic com/kuguo/ad/l/a(Lcom/kuguo/ad/l;)Landroid/content/Context;
  astore 8
  iconst_5
  istore 6
  aload 8
  iload 6
  invokestatic com/kuguo/ad/d/a(Landroid/content/Context;I)I
  istore 10
  iload 10
  i2f
  fstore 9
  aload_3
  fload 9
  invokevirtual android/graphics/drawable/GradientDrawable/setCornerRadius(F)V
  goto Label6
Label2:
  new android/graphics/drawable/GradientDrawable
  astore_3
  getstatic android/graphics/drawable/GradientDrawable$Orientation/TOP_BOTTOM Landroid/graphics/drawable/GradientDrawable$Orientation;
  astore 4
  iconst_3
  istore 6
  iload 6
  newarray int
  astore 5
  iconst_0
  istore 6
  ldc -8537861
  istore 7
  aload 5
  iload 6
  iload 7
  iastore
  iconst_1
  istore 6
  ldc -16500879
  istore 7
  aload 5
  iload 6
  iload 7
  iastore
  iconst_2
  istore 6
  ldc -8537861
  istore 7
  aload 5
  iload 6
  iload 7
  iastore
  aload_3
  aload 4
  aload 5
  invokespecial android/graphics/drawable/GradientDrawable/<init>(Landroid/graphics/drawable/GradientDrawable$Orientation;[I)V
  aload_0
  aload_3
  putfield com/kuguo/ad/r/a Landroid/graphics/drawable/GradientDrawable;
  new android/graphics/drawable/GradientDrawable
  astore_3
  getstatic android/graphics/drawable/GradientDrawable$Orientation/BOTTOM_TOP Landroid/graphics/drawable/GradientDrawable$Orientation;
  astore 4
  iconst_3
  istore 6
  iload 6
  newarray int
  astore 5
  iconst_0
  istore 6
  ldc -8537861
  istore 7
  aload 5
  iload 6
  iload 7
  iastore
  iconst_1
  istore 6
  ldc -16500879
  istore 7
  aload 5
  iload 6
  iload 7
  iastore
  iconst_2
  istore 6
  ldc -8537861
  istore 7
  aload 5
  iload 6
  iload 7
  iastore
  aload_3
  aload 4
  aload 5
  invokespecial android/graphics/drawable/GradientDrawable/<init>(Landroid/graphics/drawable/GradientDrawable$Orientation;[I)V
  aload_0
  aload_3
  putfield com/kuguo/ad/r/b Landroid/graphics/drawable/GradientDrawable;
  new android/graphics/drawable/GradientDrawable
  astore_3
  aload_3
  invokespecial android/graphics/drawable/GradientDrawable/<init>()V
  aload_0
  aload_3
  putfield com/kuguo/ad/r/c Landroid/graphics/drawable/GradientDrawable;
  aload_0
  getfield com/kuguo/ad/r/c Landroid/graphics/drawable/GradientDrawable;
  astore_3
  aload_1
  invokestatic com/kuguo/ad/l/a(Lcom/kuguo/ad/l;)Landroid/content/Context;
  astore 8
  iconst_5
  istore 6
  aload 8
  iload 6
  invokestatic com/kuguo/ad/d/a(Landroid/content/Context;I)I
  istore_2
  iload_2
  i2f
  fstore 9
  aload_3
  fload 9
  invokevirtual android/graphics/drawable/GradientDrawable/setCornerRadius(F)V
  aload_0
  getfield com/kuguo/ad/r/c Landroid/graphics/drawable/GradientDrawable;
  astore_3
  iconst_0
  istore 6
  aload_3
  iload 6
  invokevirtual android/graphics/drawable/GradientDrawable/setColor(I)V
  new android/graphics/drawable/GradientDrawable
  astore_3
  aload_3
  invokespecial android/graphics/drawable/GradientDrawable/<init>()V
  aload_0
  aload_3
  putfield com/kuguo/ad/r/d Landroid/graphics/drawable/GradientDrawable;
  aload_0
  getfield com/kuguo/ad/r/d Landroid/graphics/drawable/GradientDrawable;
  astore_3
  ldc 1998133616
  istore 6
  aload_3
  iload 6
  invokevirtual android/graphics/drawable/GradientDrawable/setColor(I)V
  aload_0
  getfield com/kuguo/ad/r/d Landroid/graphics/drawable/GradientDrawable;
  astore_3
  aload_1
  invokestatic com/kuguo/ad/l/a(Lcom/kuguo/ad/l;)Landroid/content/Context;
  astore 8
  iconst_5
  istore 6
  aload 8
  iload 6
  invokestatic com/kuguo/ad/d/a(Landroid/content/Context;I)I
  istore 10
  iload 10
  i2f
  fstore 9
  aload_3
  fload 9
  invokevirtual android/graphics/drawable/GradientDrawable/setCornerRadius(F)V
  goto Label6
Label3:
  new android/graphics/drawable/GradientDrawable
  astore_3
  getstatic android/graphics/drawable/GradientDrawable$Orientation/TOP_BOTTOM Landroid/graphics/drawable/GradientDrawable$Orientation;
  astore 4
  iconst_3
  istore 6
  iload 6
  newarray int
  astore 5
  iconst_0
  istore 6
  ldc -14305670
  istore 7
  aload 5
  iload 6
  iload 7
  iastore
  iconst_1
  istore 6
  ldc -16100221
  istore 7
  aload 5
  iload 6
  iload 7
  iastore
  iconst_2
  istore 6
  ldc -6165568
  istore 7
  aload 5
  iload 6
  iload 7
  iastore
  aload_3
  aload 4
  aload 5
  invokespecial android/graphics/drawable/GradientDrawable/<init>(Landroid/graphics/drawable/GradientDrawable$Orientation;[I)V
  aload_0
  aload_3
  putfield com/kuguo/ad/r/a Landroid/graphics/drawable/GradientDrawable;
  new android/graphics/drawable/GradientDrawable
  astore_3
  getstatic android/graphics/drawable/GradientDrawable$Orientation/BOTTOM_TOP Landroid/graphics/drawable/GradientDrawable$Orientation;
  astore 4
  iconst_3
  istore 6
  iload 6
  newarray int
  astore 5
  iconst_0
  istore 6
  ldc -14305670
  istore 7
  aload 5
  iload 6
  iload 7
  iastore
  iconst_1
  istore 6
  ldc -16100221
  istore 7
  aload 5
  iload 6
  iload 7
  iastore
  iconst_2
  istore 6
  ldc -6165568
  istore 7
  aload 5
  iload 6
  iload 7
  iastore
  aload_3
  aload 4
  aload 5
  invokespecial android/graphics/drawable/GradientDrawable/<init>(Landroid/graphics/drawable/GradientDrawable$Orientation;[I)V
  aload_0
  aload_3
  putfield com/kuguo/ad/r/b Landroid/graphics/drawable/GradientDrawable;
  new android/graphics/drawable/GradientDrawable
  astore_3
  aload_3
  invokespecial android/graphics/drawable/GradientDrawable/<init>()V
  aload_0
  aload_3
  putfield com/kuguo/ad/r/c Landroid/graphics/drawable/GradientDrawable;
  aload_0
  getfield com/kuguo/ad/r/c Landroid/graphics/drawable/GradientDrawable;
  astore_3
  aload_1
  invokestatic com/kuguo/ad/l/a(Lcom/kuguo/ad/l;)Landroid/content/Context;
  astore 8
  iconst_5
  istore 6
  aload 8
  iload 6
  invokestatic com/kuguo/ad/d/a(Landroid/content/Context;I)I
  istore_2
  iload_2
  i2f
  fstore 9
  aload_3
  fload 9
  invokevirtual android/graphics/drawable/GradientDrawable/setCornerRadius(F)V
  aload_0
  getfield com/kuguo/ad/r/c Landroid/graphics/drawable/GradientDrawable;
  astore_3
  iconst_0
  istore 6
  aload_3
  iload 6
  invokevirtual android/graphics/drawable/GradientDrawable/setColor(I)V
  new android/graphics/drawable/GradientDrawable
  astore_3
  aload_3
  invokespecial android/graphics/drawable/GradientDrawable/<init>()V
  aload_0
  aload_3
  putfield com/kuguo/ad/r/d Landroid/graphics/drawable/GradientDrawable;
  aload_0
  getfield com/kuguo/ad/r/d Landroid/graphics/drawable/GradientDrawable;
  astore_3
  ldc 1998133616
  istore 6
  aload_3
  iload 6
  invokevirtual android/graphics/drawable/GradientDrawable/setColor(I)V
  aload_0
  getfield com/kuguo/ad/r/d Landroid/graphics/drawable/GradientDrawable;
  astore_3
  aload_1
  invokestatic com/kuguo/ad/l/a(Lcom/kuguo/ad/l;)Landroid/content/Context;
  astore 8
  iconst_5
  istore 6
  aload 8
  iload 6
  invokestatic com/kuguo/ad/d/a(Landroid/content/Context;I)I
  istore 10
  iload 10
  i2f
  fstore 9
  aload_3
  fload 9
  invokevirtual android/graphics/drawable/GradientDrawable/setCornerRadius(F)V
  goto Label6
Label4:
  new android/graphics/drawable/GradientDrawable
  astore_3
  getstatic android/graphics/drawable/GradientDrawable$Orientation/TOP_BOTTOM Landroid/graphics/drawable/GradientDrawable$Orientation;
  astore 4
  iconst_3
  istore 6
  iload 6
  newarray int
  astore 5
  iconst_0
  istore 6
  ldc -10373696
  istore 7
  aload 5
  iload 6
  iload 7
  iastore
  iconst_1
  istore 6
  ldc -7543346
  istore 7
  aload 5
  iload 6
  iload 7
  iastore
  iconst_2
  istore 6
  ldc -6296606
  istore 7
  aload 5
  iload 6
  iload 7
  iastore
  aload_3
  aload 4
  aload 5
  invokespecial android/graphics/drawable/GradientDrawable/<init>(Landroid/graphics/drawable/GradientDrawable$Orientation;[I)V
  aload_0
  aload_3
  putfield com/kuguo/ad/r/a Landroid/graphics/drawable/GradientDrawable;
  new android/graphics/drawable/GradientDrawable
  astore_3
  getstatic android/graphics/drawable/GradientDrawable$Orientation/BOTTOM_TOP Landroid/graphics/drawable/GradientDrawable$Orientation;
  astore 4
  iconst_3
  istore 6
  iload 6
  newarray int
  astore 5
  iconst_0
  istore 6
  ldc -10373696
  istore 7
  aload 5
  iload 6
  iload 7
  iastore
  iconst_1
  istore 6
  ldc -7543346
  istore 7
  aload 5
  iload 6
  iload 7
  iastore
  iconst_2
  istore 6
  ldc -6296606
  istore 7
  aload 5
  iload 6
  iload 7
  iastore
  aload_3
  aload 4
  aload 5
  invokespecial android/graphics/drawable/GradientDrawable/<init>(Landroid/graphics/drawable/GradientDrawable$Orientation;[I)V
  aload_0
  aload_3
  putfield com/kuguo/ad/r/b Landroid/graphics/drawable/GradientDrawable;
  new android/graphics/drawable/GradientDrawable
  astore_3
  aload_3
  invokespecial android/graphics/drawable/GradientDrawable/<init>()V
  aload_0
  aload_3
  putfield com/kuguo/ad/r/c Landroid/graphics/drawable/GradientDrawable;
  aload_0
  getfield com/kuguo/ad/r/c Landroid/graphics/drawable/GradientDrawable;
  astore_3
  aload_1
  invokestatic com/kuguo/ad/l/a(Lcom/kuguo/ad/l;)Landroid/content/Context;
  astore 8
  iconst_5
  istore 6
  aload 8
  iload 6
  invokestatic com/kuguo/ad/d/a(Landroid/content/Context;I)I
  istore_2
  iload_2
  i2f
  fstore 9
  aload_3
  fload 9
  invokevirtual android/graphics/drawable/GradientDrawable/setCornerRadius(F)V
  aload_0
  getfield com/kuguo/ad/r/c Landroid/graphics/drawable/GradientDrawable;
  astore_3
  iconst_0
  istore 6
  aload_3
  iload 6
  invokevirtual android/graphics/drawable/GradientDrawable/setColor(I)V
  new android/graphics/drawable/GradientDrawable
  astore_3
  aload_3
  invokespecial android/graphics/drawable/GradientDrawable/<init>()V
  aload_0
  aload_3
  putfield com/kuguo/ad/r/d Landroid/graphics/drawable/GradientDrawable;
  aload_0
  getfield com/kuguo/ad/r/d Landroid/graphics/drawable/GradientDrawable;
  astore_3
  ldc 1998133616
  istore 6
  aload_3
  iload 6
  invokevirtual android/graphics/drawable/GradientDrawable/setColor(I)V
  aload_0
  getfield com/kuguo/ad/r/d Landroid/graphics/drawable/GradientDrawable;
  astore_3
  aload_1
  invokestatic com/kuguo/ad/l/a(Lcom/kuguo/ad/l;)Landroid/content/Context;
  astore 8
  iconst_5
  istore 6
  aload 8
  iload 6
  invokestatic com/kuguo/ad/d/a(Landroid/content/Context;I)I
  istore 10
  iload 10
  i2f
  fstore 9
  aload_3
  fload 9
  invokevirtual android/graphics/drawable/GradientDrawable/setCornerRadius(F)V
  goto Label6
  nop
  nop
.end <method>

