.source AdsMOGOAction.java
.class  com/admogo/AdsMOGOAction$1
.super java/lang/Object
.implements  java/lang/Runnable

.method <init>()V
.limit locals 1
.limit stack 200
  nop
  aload_0
  invokespecial java/lang/Object/<init>()V
  return
  nop
.end <method>

.method public run()V
.limit locals 23
.limit stack 200
  nop
Label3:
  invokestatic com/admogo/AdsMOGOAction/access$0()Z
  istore 4
  new java/lang/NoClassDefFoundError
  dup
  invokespecial java/lang/NoClassDefFoundError/<init>()V
  athrow
  iload 4
  ifeq Label0
  return
Label0:
  new org/apache/http/params/BasicHttpParams
  astore 5
Label5:
  aload 5
  invokespecial org/apache/http/params/BasicHttpParams/<init>()V
  sipush 30000
  istore 6
  aload 5
  iload 6
  invokestatic org/apache/http/params/HttpConnectionParams/setConnectionTimeout(Lorg/apache/http/params/HttpParams;I)V
  sipush 30000
  istore 6
  aload 5
  iload 6
  invokestatic org/apache/http/params/HttpConnectionParams/setSoTimeout(Lorg/apache/http/params/HttpParams;I)V
  new org/apache/http/impl/client/DefaultHttpClient
  astore 7
  aload 7
  aload 5
  invokespecial org/apache/http/impl/client/DefaultHttpClient/<init>(Lorg/apache/http/params/HttpParams;)V
  invokestatic com/admogo/AdsMOGOAction/access$1()[Ljava/lang/String;
  astore 8
  invokestatic com/admogo/AdsMOGOAction/access$2()I
  istore 9
  aload 8
  iload 9
  aaload
  astore 10
  iconst_2
  istore 6
  iload 6
  anewarray java/lang/Object
  astore 11
  invokestatic com/admogo/AdsMOGOAction/access$3()Ljava/lang/String;
  astore 12
  iconst_0
  istore 6
  aload 11
  iload 6
  aload 12
  aastore
  invokestatic com/admogo/AdsMOGOAction/access$4()Ljava/lang/String;
  astore 12
  iconst_1
  istore 6
  aload 11
  iload 6
  aload 12
  aastore
  aload 10
  aload 11
  invokestatic java/lang/String/format(Ljava/lang/String;[Ljava/lang/Object;)Ljava/lang/String;
  astore 12
  new org/apache/http/client/methods/HttpGet
  astore 13
  aload 13
  aload 12
  invokespecial org/apache/http/client/methods/HttpGet/<init>(Ljava/lang/String;)V
  aload 7
  aload 13
  invokeinterface org/apache/http/client/HttpClient/execute(Lorg/apache/http/client/methods/HttpUriRequest;)Lorg/apache/http/HttpResponse; 2
  astore 14
  aload 14
  invokeinterface org/apache/http/HttpResponse/getEntity()Lorg/apache/http/HttpEntity; 1
  astore 15
  aload 15
  invokestatic app/DummyClass/invokeIfStmt(Ljava/lang/Object;)V
  aload 15
  ifnull Label1
  aload 14
  invokeinterface org/apache/http/HttpResponse/getStatusLine()Lorg/apache/http/StatusLine; 1
  astore 16
  aload 16
  invokeinterface org/apache/http/StatusLine/getStatusCode()I 1
  istore 9
  dload 9
  invokestatic app/DummyClass/invokeIfStmt(D)V
  sipush 200
  istore 6
  iload 9
  iload 6
  if_icmpne Label2
  iconst_1
  istore 6
  iload 6
  invokestatic com/admogo/AdsMOGOAction/access$5(Z)V
  invokestatic com/admogo/AdsMOGOAction/access$6()Landroid/content/Context;
  astore 17
  ldc "AdsMogo Action SDK"
  astore 19
  iconst_0
  istore 6
  aload 17
  astore_1
  aload 19
  astore_2
  aload_1
  aload_2
  iload 6
  invokevirtual android/content/Context/getSharedPreferences(Ljava/lang/String;I)Landroid/content/SharedPreferences;
  astore 18
  aload 18
  astore_1
  aload_1
  invokeinterface android/content/SharedPreferences/edit()Landroid/content/SharedPreferences$Editor; 1
  astore 20
  ldc "is_aciton"
  astore 19
  iconst_0
  istore 6
  aload 20
  astore_1
  aload 19
  astore_2
  aload_1
  aload_2
  iload 6
  invokeinterface android/content/SharedPreferences$Editor/putBoolean(Ljava/lang/String;Z)Landroid/content/SharedPreferences$Editor; 3
  pop
  aload 20
  astore_1
  aload_1
  invokeinterface android/content/SharedPreferences$Editor/commit()Z 1
  pop
Label1:
  invokestatic com/admogo/AdsMOGOAction/access$0()Z
  istore 4
  iload 4
  invokestatic app/DummyClass/invokeIfStmt(Z)V
  iload 4
  ifne Label3
  invokestatic com/admogo/AdsMOGOAction/access$2()I
  istore 9
  iload 9
  iconst_1
  iadd
  istore 9
  iload 9
  iconst_4
  irem
  istore 9
  iload 9
  invokestatic com/admogo/AdsMOGOAction/access$7(I)V
  invokestatic com/admogo/AdsMOGOAction/access$8()I
  istore 9
  iload 9
  iconst_1
  iadd
  istore 9
  iload 9
  invokestatic com/admogo/AdsMOGOAction/access$9(I)V
  invokestatic com/admogo/AdsMOGOAction/access$8()I
  istore 9
  dload 9
  invokestatic app/DummyClass/invokeIfStmt(D)V
  iconst_3
  istore 6
  iload 9
  iload 6
  if_icmple Label3
  iconst_1
  istore 6
  iload 6
  invokestatic com/admogo/AdsMOGOAction/access$5(Z)V
  goto Label3
Label2:
  iconst_0
  istore 6
  iload 6
  invokestatic com/admogo/AdsMOGOAction/access$5(Z)V
Label6:
  goto Label1
Label4:
  astore 21
  iconst_0
  istore 6
  iload 6
  invokestatic com/admogo/AdsMOGOAction/access$5(Z)V
  ldc "AdsMogo Action SDK"
  astore 19
  ldc "Caught ClientProtocolException in actionRunnable()"
  astore 22
  aload 19
  astore_1
  aload 22
  astore_2
  aload 21
  astore_3
  aload_1
  aload_2
  aload_3
  invokestatic android/util/Log/i(Ljava/lang/String;Ljava/lang/String;Ljava/lang/Throwable;)I
  pop
  goto Label1
  nop
.end <method>

