.source SourceFile
.class public  com/mobisage/sns/tencent/MSTencentAuthorize
.super com/mobisage/sns/tencent/MSTencentWeiboMessage

.method public <init>(Lcom/mobisage/sns/common/MSOAToken;Lcom/mobisage/sns/common/MSOAConsumer;)V
.limit locals 6
.limit stack 200
  nop
  aload_0
  aload_1
  aload_2
  invokespecial com/mobisage/sns/tencent/MSTencentWeiboMessage/<init>(Lcom/mobisage/sns/common/MSOAToken;Lcom/mobisage/sns/common/MSOAConsumer;)V
  ldc "https://open.t.qq.com/cgi-bin/authorize"
  astore_3
  aload_0
  aload_3
  putfield com/mobisage/sns/tencent/MSTencentWeiboMessage/urlPath Ljava/lang/String;
  ldc "GET"
  astore_3
  aload_0
  aload_3
  putfield com/mobisage/sns/tencent/MSTencentWeiboMessage/httpMethod Ljava/lang/String;
  aload_0
  getfield com/mobisage/sns/tencent/MSTencentWeiboMessage/paramMap Ljava/util/HashMap;
  astore 4
  ldc "oauth_token"
  astore_3
  ldc ""
  astore 5
  aload 4
  aload_3
  aload 5
  invokevirtual java/util/HashMap/put(Ljava/lang/Object;Ljava/lang/Object;)Ljava/lang/Object;
  pop
  return
  nop
.end <method>

.method public generateAuthorizeURL()Ljava/lang/String;
.limit locals 13
.limit stack 200
  nop
  new java/lang/StringBuilder
  astore_1
  aload_1
  invokespecial java/lang/StringBuilder/<init>()V
  aload_0
  getfield com/mobisage/sns/tencent/MSTencentWeiboMessage/paramMap Ljava/util/HashMap;
  astore_2
  aload_2
  invokevirtual java/util/HashMap/keySet()Ljava/util/Set;
  astore_3
  aload_3
  invokeinterface java/util/Set/iterator()Ljava/util/Iterator; 1
  astore 4
Label2:
  aload 4
  invokeinterface java/util/Iterator/hasNext()Z 1
  istore 5
  new java/lang/NoClassDefFoundError
  dup
  invokespecial java/lang/NoClassDefFoundError/<init>()V
  athrow
  iload 5
  ifeq Label0
  aload_1
  invokevirtual java/lang/StringBuilder/length()I
  istore 6
  dload 6
  invokestatic app/DummyClass/invokeIfStmt(D)V
  iload 6
  ifne Label1
  ldc "?"
  astore 7
  aload_1
  aload 7
  invokevirtual java/lang/StringBuilder/append(Ljava/lang/String;)Ljava/lang/StringBuilder;
  pop
Label1:
  aload 4
  invokeinterface java/util/Iterator/next()Ljava/lang/Object; 1
  astore 8
  aload 8
  astore 10
  aload 10
  checkcast java/lang/String
  astore 10
  aload 10
  astore 9
  ldc "oauth_token"
  astore 7
  aload 9
  aload 7
  invokevirtual java/lang/String/equals(Ljava/lang/Object;)Z
  istore 5
  iload 5
  invokestatic app/DummyClass/invokeIfStmt(Z)V
  iload 5
  ifeq Label2
  new java/lang/StringBuilder
  astore 11
  aload 11
  invokespecial java/lang/StringBuilder/<init>()V
  aload 11
  aload 9
  invokevirtual java/lang/StringBuilder/append(Ljava/lang/String;)Ljava/lang/StringBuilder;
  astore 11
  ldc "="
  astore 7
  aload 11
  aload 7
  invokevirtual java/lang/StringBuilder/append(Ljava/lang/String;)Ljava/lang/StringBuilder;
  astore 11
  aload_0
  getfield com/mobisage/sns/tencent/MSTencentWeiboMessage/paramMap Ljava/util/HashMap;
  astore_2
  aload_2
  aload 9
  invokevirtual java/util/HashMap/get(Ljava/lang/Object;)Ljava/lang/Object;
  astore 8
  aload 8
  astore 12
  aload 12
  checkcast java/lang/String
  astore 12
  aload 12
  astore 9
  aload 9
  invokestatic java/net/URLEncoder/encode(Ljava/lang/String;)Ljava/lang/String;
  astore 9
  aload 11
  aload 9
  invokevirtual java/lang/StringBuilder/append(Ljava/lang/String;)Ljava/lang/StringBuilder;
  astore 11
  aload 11
  invokevirtual java/lang/StringBuilder/toString()Ljava/lang/String;
  astore 9
  aload_1
  aload 9
  invokevirtual java/lang/StringBuilder/append(Ljava/lang/String;)Ljava/lang/StringBuilder;
  pop
  goto Label2
Label0:
  new java/lang/StringBuilder
  astore 11
  aload 11
  invokespecial java/lang/StringBuilder/<init>()V
  aload_0
  getfield com/mobisage/sns/tencent/MSTencentWeiboMessage/urlPath Ljava/lang/String;
  astore 9
  aload 11
  aload 9
  invokevirtual java/lang/StringBuilder/append(Ljava/lang/String;)Ljava/lang/StringBuilder;
  astore 11
  aload_1
  invokevirtual java/lang/StringBuilder/toString()Ljava/lang/String;
  astore 9
  aload 11
  aload 9
  invokevirtual java/lang/StringBuilder/append(Ljava/lang/String;)Ljava/lang/StringBuilder;
  astore 11
  aload 11
  invokevirtual java/lang/StringBuilder/toString()Ljava/lang/String;
  astore 9
  aload 9
  areturn
  nop
.end <method>

