.source InMobiSourceAdapter.java
.class public  com/admogo/adapters/InMobiSourceAdapter
.super com/admogo/adapters/AdMogoAdapter
.field private static final "AD_TYPE_BANNER" I =  1
.field private static final "AD_TYPE_TEXT" I =  2
.field private static "inmobiAD" Lcom/admogo/obj/InmobiAD;
.field private static "webView" Landroid/webkit/WebView;

.method public <init>(Lcom/admogo/AdMogoLayout;Lcom/admogo/obj/Ration;)V
.limit locals 8
.limit stack 200
  nop
  aload_0
  aload_1
  aload_2
  invokespecial com/admogo/adapters/AdMogoAdapter/<init>(Lcom/admogo/AdMogoLayout;Lcom/admogo/obj/Ration;)V
  new java/lang/NoClassDefFoundError
  dup
  invokespecial java/lang/NoClassDefFoundError/<init>()V
  athrow
  aload_1
  getfield com/admogo/AdMogoLayout/activityReference Ljava/lang/ref/WeakReference;
  astore 4
  aload 4
  invokevirtual java/lang/ref/WeakReference/get()Ljava/lang/Object;
  astore 5
  aload 5
  astore 7
  aload 7
  checkcast android/content/Context
  astore 7
  aload 7
  astore 6
  aload_3
  aload 6
  invokespecial android/webkit/WebView/<init>(Landroid/content/Context;)V
  aload_3
  putstatic com/admogo/adapters/InMobiSourceAdapter/webView Landroid/webkit/WebView;
  return
  nop
.end <method>

.method static access$0(Lcom/admogo/AdMogoLayout;Ljava/lang/String;)Lcom/admogo/obj/InmobiAD;
  .synthetic
.limit locals 3
.limit stack 200
  nop
  aload_0
  aload_1
  invokestatic com/admogo/adapters/InMobiSourceAdapter/getInmobiAD(Lcom/admogo/AdMogoLayout;Ljava/lang/String;)Lcom/admogo/obj/InmobiAD;
  astore_2
  aload_2
  areturn
  nop
.end <method>

.method static access$1(Lcom/admogo/obj/InmobiAD;)V
  .synthetic
.limit locals 1
.limit stack 200
  nop
  aload_0
  putstatic com/admogo/adapters/InMobiSourceAdapter/inmobiAD Lcom/admogo/obj/InmobiAD;
  return
  nop
.end <method>

.method static access$2()Lcom/admogo/obj/InmobiAD;
  .synthetic
.limit locals 1
.limit stack 200
  nop
  getstatic com/admogo/adapters/InMobiSourceAdapter/inmobiAD Lcom/admogo/obj/InmobiAD;
  astore_0
  aload_0
  areturn
  nop
.end <method>

.method public click()V
.limit locals 14
.limit stack 200
  nop
  aload_0
  getfield com/admogo/adapters/AdMogoAdapter/adMogoLayoutReference Ljava/lang/ref/WeakReference;
  astore_1
  aload_1
  invokevirtual java/lang/ref/WeakReference/get()Ljava/lang/Object;
  astore_2
  aload_2
  astore 4
  new java/lang/NoClassDefFoundError
  dup
  invokespecial java/lang/NoClassDefFoundError/<init>()V
  athrow
  aload 4
  astore_3
  aload_3
  invokestatic app/DummyClass/invokeIfStmt(Ljava/lang/Object;)V
  iload_3
  ifeq Label0
  getstatic com/admogo/adapters/InMobiSourceAdapter/inmobiAD Lcom/admogo/obj/InmobiAD;
  astore 5
  aload 5
  invokestatic app/DummyClass/invokeIfStmt(Ljava/lang/Object;)V
  aload 5
  ifnull Label0
  getstatic com/admogo/adapters/InMobiSourceAdapter/inmobiAD Lcom/admogo/obj/InmobiAD;
  astore 5
  aload 5
  invokevirtual com/admogo/obj/InmobiAD/getAdUrl()Ljava/lang/String;
  astore 6
  aload 6
  invokestatic app/DummyClass/invokeIfStmt(Ljava/lang/Object;)V
  aload 6
  ifnonnull Label1
Label0:
  getstatic com/admogo/util/AdMogoUtil/ADMOGO Ljava/lang/String;
  astore 7
  ldc "inmobi click error adMogoLayout or inmobiAD or AdUrl is null"
  astore 8
  aload 7
  aload 8
  invokestatic android/util/Log/d(Ljava/lang/String;Ljava/lang/String;)I
  pop
Label2:
  return
Label1:
  aload_3
  getfield com/admogo/AdMogoLayout/activityReference Ljava/lang/ref/WeakReference;
  astore_1
  aload_1
  invokevirtual java/lang/ref/WeakReference/get()Ljava/lang/Object;
  astore_2
  aload_2
  astore 10
  aload 10
  checkcast android/content/Context
  astore 10
  aload 10
  astore 9
  aload_3
  invokevirtual com/admogo/AdMogoLayout/countClick()V
  new android/content/Intent
  astore 11
  ldc com/admogo/AdMogoWebView
  astore 12
  aload 11
  aload 9
  aload 12
  invokespecial android/content/Intent/<init>(Landroid/content/Context;Ljava/lang/Class;)V
  new android/os/Bundle
  astore 13
  aload 13
  invokespecial android/os/Bundle/<init>()V
  getstatic com/admogo/adapters/InMobiSourceAdapter/inmobiAD Lcom/admogo/obj/InmobiAD;
  astore 5
  aload 5
  invokevirtual com/admogo/obj/InmobiAD/getAdUrl()Ljava/lang/String;
  astore 6
  ldc "link"
  astore 8
  aload 13
  aload 8
  aload 6
  invokevirtual android/os/Bundle/putString(Ljava/lang/String;Ljava/lang/String;)V
  aload 11
  aload 13
  invokevirtual android/content/Intent/putExtras(Landroid/os/Bundle;)Landroid/content/Intent;
  pop
  aload 9
  aload 11
  invokevirtual android/content/Context/startActivity(Landroid/content/Intent;)V
  goto Label2
  nop
.end <method>

.method public displayInmobiAD()V
.limit locals 50
.limit stack 200
  nop
  aload_0
  astore_1
  aload_1
  getfield com/admogo/adapters/AdMogoAdapter/adMogoLayoutReference Ljava/lang/ref/WeakReference;
  astore 5
  aload 5
  invokevirtual java/lang/ref/WeakReference/get()Ljava/lang/Object;
  astore 6
  aload 6
  astore 8
  new java/lang/NoClassDefFoundError
  dup
  invokespecial java/lang/NoClassDefFoundError/<init>()V
  athrow
  aload 8
  astore 7
  aload 7
  invokestatic app/DummyClass/invokeIfStmt(Ljava/lang/Object;)V
  iload 7
  ifne Label0
Label1:
  return
Label0:
  aload 7
  getfield com/admogo/AdMogoLayout/activityReference Ljava/lang/ref/WeakReference;
  astore 5
  aload 5
  invokevirtual java/lang/ref/WeakReference/get()Ljava/lang/Object;
  astore 6
  aload 6
  astore 10
  aload 10
  checkcast android/app/Activity
  astore 10
  aload 10
  astore 9
  aload 9
  invokestatic app/DummyClass/invokeIfStmt(Ljava/lang/Object;)V
  aload 9
  ifnull Label1
  aload 9
  invokestatic com/admogo/util/AdMogoUtil/getDensity(Landroid/app/Activity;)D
  dstore 11
  bipush 50
  istore 14
  iload 14
  dload 11
  invokestatic com/admogo/util/AdMogoUtil/convertToScreenPixels(ID)I
  istore 13
  iload 13
  i2d
  dstore 15
  bipush 42
  istore 14
  iload 14
  dload 11
  invokestatic com/admogo/util/AdMogoUtil/convertToScreenPixels(ID)I
  istore 13
  iload 13
  i2d
  dstore_1
  dload_1
  dstore 17
  bipush 20
  istore 14
  iload 14
  dload 11
  invokestatic com/admogo/util/AdMogoUtil/convertToScreenPixels(ID)I
  istore 13
  iload 13
  i2d
  dstore_1
  dload_1
  dstore 19
  iconst_4
  istore 14
  iload 14
  dload 11
  invokestatic com/admogo/util/AdMogoUtil/convertToScreenPixels(ID)I
  istore 13
  iload 13
  i2d
  dstore 11
  getstatic com/admogo/adapters/InMobiSourceAdapter/inmobiAD Lcom/admogo/obj/InmobiAD;
  astore 21
  aload 21
  astore_1
  aload_1
  invokevirtual com/admogo/obj/InmobiAD/getAdsType()I
  istore 13
  dload 13
  invokestatic app/DummyClass/invokeIfStmt(D)V
  iload 13
  lookupswitch
  1 : Label3
  2 : Label4
  default : Label2
Label2:
  goto Label5
Label5:
  aload 7
  getfield com/admogo/AdMogoLayout/adMogoManager Lcom/admogo/AdMogoManager;
  astore_1
  aload_1
  astore 22
  aload 22
  astore_1
  aload_1
  invokevirtual com/admogo/AdMogoManager/resetRollover()V
  aload 7
  invokevirtual com/admogo/AdMogoLayout/rotateThreadedDelayed()V
  goto Label1
Label3:
  getstatic com/admogo/util/AdMogoUtil/ADMOGO Ljava/lang/String;
  astore 23
  ldc "InmobiAD type: banner"
  astore 24
  aload 23
  astore_1
  aload 24
  astore_2
  aload_1
  aload_2
  invokestatic android/util/Log/d(Ljava/lang/String;Ljava/lang/String;)I
  pop
  getstatic com/admogo/adapters/InMobiSourceAdapter/inmobiAD Lcom/admogo/obj/InmobiAD;
  astore 21
  aload 21
  astore_1
  aload_1
  invokevirtual com/admogo/obj/InmobiAD/getAdImg()Landroid/graphics/drawable/Drawable;
  astore 25
  aload 25
  astore_1
  aload_1
  invokestatic app/DummyClass/invokeIfStmt(Ljava/lang/Object;)V
  aload 25
  ifnonnull Label6
  aload 7
  invokevirtual com/admogo/AdMogoLayout/rollover()V
  goto Label1
Label6:
  new android/widget/ImageView
  astore 26
  aload 26
  astore_1
  aload_1
  aload 9
  invokespecial android/widget/ImageView/<init>(Landroid/content/Context;)V
  getstatic com/admogo/adapters/InMobiSourceAdapter/inmobiAD Lcom/admogo/obj/InmobiAD;
  astore 21
  aload 21
  astore_1
  aload_1
  invokevirtual com/admogo/obj/InmobiAD/getAdImg()Landroid/graphics/drawable/Drawable;
  astore 25
  aload 26
  astore_1
  aload 25
  astore_2
  aload_1
  aload_2
  invokevirtual android/widget/ImageView/setImageDrawable(Landroid/graphics/drawable/Drawable;)V
  getstatic android/widget/ImageView$ScaleType/CENTER_CROP Landroid/widget/ImageView$ScaleType;
  astore 27
  aload 26
  astore_1
  aload 27
  astore_2
  aload_1
  aload_2
  invokevirtual android/widget/ImageView/setScaleType(Landroid/widget/ImageView$ScaleType;)V
  new android/widget/RelativeLayout$LayoutParams
  astore 28
  dload 15
  d2i
  istore 13
  iconst_m1
  istore 14
  aload 28
  astore_1
  aload_1
  iload 14
  iload 13
  invokespecial android/widget/RelativeLayout$LayoutParams/<init>(II)V
  bipush 13
  istore 14
  aload 28
  astore_1
  aload_1
  iload 14
  invokevirtual android/widget/RelativeLayout$LayoutParams/addRule(I)V
  new android/widget/RelativeLayout
  astore 29
  aload 29
  astore_1
  aload_1
  aload 9
  invokespecial android/widget/RelativeLayout/<init>(Landroid/content/Context;)V
  aload 29
  astore_1
  aload 26
  astore_2
  aload 28
  astore_3
  aload_1
  aload_2
  aload_3
  invokevirtual android/widget/RelativeLayout/addView(Landroid/view/View;Landroid/view/ViewGroup$LayoutParams;)V
  aload_0
  astore_1
  aload_1
  getfield com/admogo/adapters/AdMogoAdapter/ration Lcom/admogo/obj/Ration;
  astore_1
  aload_1
  astore 30
  aload 30
  astore_1
  aload_1
  getfield com/admogo/obj/Ration/type I
  istore 13
  aload 29
  astore_1
  aload 7
  aload_1
  iload 13
  invokevirtual com/admogo/AdMogoLayout/pushSubView(Landroid/view/ViewGroup;I)V
  goto Label5
Label4:
  getstatic com/admogo/util/AdMogoUtil/ADMOGO Ljava/lang/String;
  astore 23
  ldc "InmobiAD type: text"
  astore 24
  aload 23
  astore_1
  aload 24
  astore_2
  aload_1
  aload_2
  invokestatic android/util/Log/d(Ljava/lang/String;Ljava/lang/String;)I
  pop
  new android/widget/RelativeLayout
  astore 29
  aload 29
  astore_1
  aload_1
  aload 9
  invokespecial android/widget/RelativeLayout/<init>(Landroid/content/Context;)V
  getstatic com/admogo/adapters/InMobiSourceAdapter/inmobiAD Lcom/admogo/obj/InmobiAD;
  astore 21
  aload 21
  astore_1
  aload_1
  invokevirtual com/admogo/obj/InmobiAD/getLinkText()Ljava/lang/String;
  astore 23
  aload 23
  astore_1
  aload_1
  invokestatic app/DummyClass/invokeIfStmt(Ljava/lang/Object;)V
  aload 23
  ifnonnull Label7
  aload 7
  invokevirtual com/admogo/AdMogoLayout/rollover()V
  goto Label1
Label7:
  new android/widget/FrameLayout$LayoutParams
  astore 31
  dload 15
  d2i
  istore 13
  iconst_m1
  istore 14
  aload 31
  astore_1
  aload_1
  iload 14
  iload 13
  invokespecial android/widget/FrameLayout$LayoutParams/<init>(II)V
  aload 29
  astore_1
  aload 31
  astore_2
  aload_1
  aload_2
  invokevirtual android/widget/RelativeLayout/setLayoutParams(Landroid/view/ViewGroup$LayoutParams;)V
  new android/widget/ImageView
  astore 26
  aload 26
  astore_1
  aload_1
  aload 9
  invokespecial android/widget/ImageView/<init>(Landroid/content/Context;)V
  aload 7
  getfield com/admogo/AdMogoLayout/extra Lcom/admogo/obj/Extra;
  astore_1
  aload_1
  astore 32
  aload 32
  astore_1
  aload_1
  getfield com/admogo/obj/Extra/bgRed I
  istore 13
  aload 7
  getfield com/admogo/AdMogoLayout/extra Lcom/admogo/obj/Extra;
  astore_1
  aload_1
  astore 32
  aload 32
  astore_1
  aload_1
  getfield com/admogo/obj/Extra/bgGreen I
  istore_1
  iload_1
  istore 33
  aload 7
  getfield com/admogo/AdMogoLayout/extra Lcom/admogo/obj/Extra;
  astore_1
  aload_1
  astore 32
  aload 32
  astore_1
  aload_1
  getfield com/admogo/obj/Extra/bgBlue I
  istore_1
  iload_1
  istore 34
  iload 33
  istore_1
  iload 34
  istore_2
  iload 13
  iload_1
  iload_2
  invokestatic android/graphics/Color/rgb(III)I
  istore 13
  new android/graphics/drawable/GradientDrawable
  astore 35
  getstatic android/graphics/drawable/GradientDrawable$Orientation/TOP_BOTTOM Landroid/graphics/drawable/GradientDrawable$Orientation;
  astore 36
  iconst_2
  istore 14
  iload 14
  newarray int
  astore_1
  aload_1
  astore 37
  bipush 100
  istore 14
  sipush 255
  istore 38
  sipush 255
  istore 39
  sipush 255
  istore 40
  iload 38
  istore_1
  iload 39
  istore_2
  iload 40
  istore_3
  iload 14
  iload_1
  iload_2
  iload_3
  invokestatic android/graphics/Color/argb(IIII)I
  istore 34
  iconst_0
  istore 14
  aload 37
  iload 14
  iload 34
  iastore
  iconst_0
  istore 14
  sipush 255
  istore 38
  sipush 255
  istore 39
  sipush 255
  istore 40
  iload 38
  istore_1
  iload 39
  istore_2
  iload 40
  istore_3
  iload 14
  iload_1
  iload_2
  iload_3
  invokestatic android/graphics/Color/argb(IIII)I
  istore 34
  iconst_1
  istore 14
  aload 37
  iload 14
  iload 34
  iastore
  aload 35
  astore_1
  aload 36
  astore_2
  aload 37
  astore_3
  aload_1
  aload_2
  aload_3
  invokespecial android/graphics/drawable/GradientDrawable/<init>(Landroid/graphics/drawable/GradientDrawable$Orientation;[I)V
  aload 26
  astore_1
  aload 35
  astore_2
  aload_1
  aload_2
  invokevirtual android/widget/ImageView/setBackgroundDrawable(Landroid/graphics/drawable/Drawable;)V
  new android/widget/RelativeLayout$LayoutParams
  astore 28
  dload 19
  dstore_1
  dload_1
  d2i
  istore_1
  iload_1
  istore 34
  iconst_m1
  istore 14
  aload 28
  astore_1
  iload 34
  istore_2
  aload_1
  iload 14
  iload_2
  invokespecial android/widget/RelativeLayout$LayoutParams/<init>(II)V
  aload 26
  astore_1
  aload 35
  astore_2
  aload_1
  aload_2
  invokevirtual android/widget/ImageView/setBackgroundDrawable(Landroid/graphics/drawable/Drawable;)V
  aload 29
  astore_1
  aload 26
  astore_2
  aload 28
  astore_3
  aload_1
  aload_2
  aload_3
  invokevirtual android/widget/RelativeLayout/addView(Landroid/view/View;Landroid/view/ViewGroup$LayoutParams;)V
  aload 29
  astore_1
  aload_1
  iload 13
  invokevirtual android/widget/RelativeLayout/setBackgroundColor(I)V
  new android/widget/ImageView
  astore 26
  aload 26
  astore_1
  aload_1
  aload 9
  invokespecial android/widget/ImageView/<init>(Landroid/content/Context;)V
  new android/graphics/drawable/BitmapDrawable
  astore 41
  aload_0
  astore_1
  aload_1
  invokevirtual java/lang/Object/getClass()Ljava/lang/Class;
  astore 42
  ldc "/com/admogo/assets/webview_bar_back.png"
  astore 24
  aload 42
  astore_1
  aload 24
  astore_2
  aload_1
  aload_2
  invokevirtual java/lang/Class/getResourceAsStream(Ljava/lang/String;)Ljava/io/InputStream;
  astore 43
  aload 41
  astore_1
  aload 43
  astore_2
  aload_1
  aload_2
  invokespecial android/graphics/drawable/BitmapDrawable/<init>(Ljava/io/InputStream;)V
  aload 26
  astore_1
  aload 41
  astore_2
  aload_1
  aload_2
  invokevirtual android/widget/ImageView/setImageDrawable(Landroid/graphics/drawable/Drawable;)V
  bipush 10
  istore 14
  aload 26
  astore_1
  aload_1
  iload 14
  invokevirtual android/widget/ImageView/setId(I)V
  new android/widget/RelativeLayout$LayoutParams
  astore 28
  dload 17
  dstore_1
  dload_1
  d2i
  istore_1
  iload_1
  istore 34
  dload 17
  dstore_1
  dload_1
  d2i
  istore_1
  iload_1
  istore 33
  aload 28
  astore_1
  iload 34
  istore_2
  iload 33
  istore_3
  aload_1
  iload_2
  iload_3
  invokespecial android/widget/RelativeLayout$LayoutParams/<init>(II)V
  dload 11
  d2i
  istore_1
  iload_1
  istore 34
  dload 11
  d2i
  istore_1
  iload_1
  istore 44
  dload 11
  d2i
  istore_1
  iload_1
  istore 33
  dload 11
  d2i
  istore 13
  aload 28
  astore_1
  iload 34
  istore_2
  iload 44
  istore_3
  iload 33
  istore 4
  aload_1
  iload_2
  iload_3
  iload 4
  iload 13
  invokevirtual android/widget/RelativeLayout$LayoutParams/setMargins(IIII)V
  aload 29
  astore_1
  aload 26
  astore_2
  aload 28
  astore_3
  aload_1
  aload_2
  aload_3
  invokevirtual android/widget/RelativeLayout/addView(Landroid/view/View;Landroid/view/ViewGroup$LayoutParams;)V
  new android/widget/TextView
  astore 45
  aload 45
  astore_1
  aload_1
  aload 9
  invokespecial android/widget/TextView/<init>(Landroid/content/Context;)V
  getstatic com/admogo/adapters/InMobiSourceAdapter/inmobiAD Lcom/admogo/obj/InmobiAD;
  astore 21
Label10:
  aload 21
  astore_1
  aload_1
  invokevirtual com/admogo/obj/InmobiAD/getLinkText()Ljava/lang/String;
  astore 23
  aload 23
  astore_1
  aload_1
  invokestatic app/DummyClass/invokeIfStmt(Ljava/lang/Object;)V
  aload 23
  ifnonnull Label8
  aload 7
  invokevirtual com/admogo/AdMogoLayout/rotateThreadedNow()V
Label8:
  getstatic com/admogo/adapters/InMobiSourceAdapter/inmobiAD Lcom/admogo/obj/InmobiAD;
  astore 21
  aload 21
  astore_1
  aload_1
  invokevirtual com/admogo/obj/InmobiAD/getLinkText()Ljava/lang/String;
  astore 23
  aload 45
  astore_1
  aload 23
  astore_2
  aload_1
  aload_2
  invokevirtual android/widget/TextView/setText(Ljava/lang/CharSequence;)V
  getstatic android/graphics/Typeface/DEFAULT_BOLD Landroid/graphics/Typeface;
  astore 46
  iconst_1
  istore 14
  aload 45
  astore_1
  aload 46
  astore_2
  aload_1
  aload_2
  iload 14
  invokevirtual android/widget/TextView/setTypeface(Landroid/graphics/Typeface;I)V
  aload 7
  getfield com/admogo/AdMogoLayout/extra Lcom/admogo/obj/Extra;
  astore_1
  aload_1
  astore 32
  aload 32
  astore_1
  aload_1
  getfield com/admogo/obj/Extra/fgRed I
  istore_1
  iload_1
  istore 44
  aload 7
  getfield com/admogo/AdMogoLayout/extra Lcom/admogo/obj/Extra;
  astore_1
  aload_1
  astore 32
  aload 32
  astore_1
  aload_1
  getfield com/admogo/obj/Extra/fgGreen I
  istore_1
  iload_1
  istore 47
  aload 7
  getfield com/admogo/AdMogoLayout/extra Lcom/admogo/obj/Extra;
  astore_1
  aload_1
  astore 32
  aload 32
  astore_1
  aload_1
  getfield com/admogo/obj/Extra/fgBlue I
  istore_1
  iload_1
  istore 34
  iload 44
  istore_1
  iload 47
  istore_2
  iload 34
  istore_3
  iload_1
  iload_2
  iload_3
  invokestatic android/graphics/Color/rgb(III)I
  istore 44
  aload 45
  astore_1
  iload 44
  istore_2
  aload_1
  iload_2
  invokevirtual android/widget/TextView/setTextColor(I)V
  iconst_2
  istore 14
  aload 45
  astore_1
  aload_1
  iload 14
  invokevirtual android/widget/TextView/setMaxLines(I)V
  ldc 16.000000
  fstore 48
  aload 45
  astore_1
  fload 48
  fstore_2
  aload_1
  fload_2
  invokevirtual android/widget/TextView/setTextSize(F)V
  new android/widget/RelativeLayout$LayoutParams
  astore 28
  dload 15
  d2i
  istore_1
  iload_1
  istore 44
  iconst_m1
  istore 14
  aload 28
  astore_1
  iload 44
  istore_2
  aload_1
  iload 14
  iload_2
  invokespecial android/widget/RelativeLayout$LayoutParams/<init>(II)V
  aload 26
  astore_1
  aload_1
  invokevirtual android/widget/ImageView/getId()I
  istore 44
  iconst_1
  istore 14
  aload 28
  astore_1
  iload 44
  istore_2
  aload_1
  iload 14
  iload_2
  invokevirtual android/widget/RelativeLayout$LayoutParams/addRule(II)V
  bipush 10
  istore 14
  aload 28
  astore_1
  aload_1
  iload 14
  invokevirtual android/widget/RelativeLayout$LayoutParams/addRule(I)V
  bipush 15
  istore 14
  aload 28
  astore_1
  aload_1
  iload 14
  invokevirtual android/widget/RelativeLayout$LayoutParams/addRule(I)V
  bipush 13
  istore 14
  aload 28
  astore_1
  aload_1
  iload 14
  invokevirtual android/widget/RelativeLayout$LayoutParams/addRule(I)V
  bipush 16
  istore 14
  aload 45
  astore_1
  aload_1
  iload 14
  invokevirtual android/widget/TextView/setGravity(I)V
  aload 29
  astore_1
  aload 45
  astore_2
  aload 28
  astore_3
  aload_1
  aload_2
  aload_3
  invokevirtual android/widget/RelativeLayout/addView(Landroid/view/View;Landroid/view/ViewGroup$LayoutParams;)V
  aload_0
  astore_1
  aload_1
  getfield com/admogo/adapters/AdMogoAdapter/ration Lcom/admogo/obj/Ration;
  astore_1
  aload_1
  astore 30
  aload 30
  astore_1
  aload_1
  getfield com/admogo/obj/Ration/type I
  istore_1
  iload_1
  istore 44
  aload 29
  astore_1
  iload 44
  istore_2
  aload 7
  aload_1
  iload_2
  invokevirtual com/admogo/AdMogoLayout/pushSubView(Landroid/view/ViewGroup;I)V
  goto Label5
Label9:
  astore 49
  getstatic com/admogo/adapters/InMobiSourceAdapter/inmobiAD Lcom/admogo/obj/InmobiAD;
  astore 21
  ldc "Haven\'t description!"
  astore 24
  aload 21
  astore_1
  aload 24
  astore_2
  aload_1
  aload_2
  invokevirtual com/admogo/obj/InmobiAD/setLinkText(Ljava/lang/String;)V
  goto Label8
  nop
  nop
  nop
.end <method>

.method private static encodeInfo(Ljava/lang/String;)Ljava/lang/String;
.limit locals 4
.limit stack 200
  .catch  java/io/UnsupportedEncodingException <from> Label1 <to> Label2 <using> Label0
  nop
Label1:
  ldc "utf-8"
  astore_2
  aload_0
  aload_2
  invokestatic java/net/URLEncoder/encode(Ljava/lang/String;Ljava/lang/String;)Ljava/lang/String;
  astore_1
Label2:
  aload_1
  areturn
Label0:
  astore_3
  aload_0
  areturn
  nop
.end <method>

.method private static fetchImage(Ljava/lang/String;)Landroid/graphics/drawable/Drawable;
.limit locals 10
.limit stack 200
  .catch  java/lang/Exception <from> Label1 <to> Label2 <using> Label0
  nop
  new java/net/URL
  astore_1
Label1:
  aload_1
  aload_0
  invokespecial java/net/URL/<init>(Ljava/lang/String;)V
  aload_1
  invokevirtual java/net/URL/getContent()Ljava/lang/Object;
  astore_2
  aload_2
  astore 4
  aload 4
  checkcast java/io/InputStream
  astore 4
  aload 4
  astore_3
  ldc "src"
  astore 6
  new java/lang/NoClassDefFoundError
  dup
  invokespecial java/lang/NoClassDefFoundError/<init>()V
  athrow
  nop
  aload_3
  invokevirtual java/io/InputStream/close()V
Label2:
  aload 5
  areturn
Label0:
  astore 7
  getstatic com/admogo/util/AdMogoUtil/ADMOGO Ljava/lang/String;
  astore 8
  ldc "Unable to fetchImage(): "
  astore 6
  new java/lang/NoClassDefFoundError
  dup
  invokespecial java/lang/NoClassDefFoundError/<init>()V
  athrow
  aconst_null
  astore 9
  aload 9
  areturn
  nop
.end <method>

.method public finish()V
.limit locals 1
.limit stack 200
  nop
  return
  nop
.end <method>

.method private static getInmobiAD(Lcom/admogo/AdMogoLayout;Ljava/lang/String;)Lcom/admogo/obj/InmobiAD;
.limit locals 35
.limit stack 200
  nop
  iconst_0
  istore 4
  aload_1
  astore 5
  aload_0
  astore_2
  new java/lang/NoClassDefFoundError
  dup
  invokespecial java/lang/NoClassDefFoundError/<init>()V
  athrow
  aload 6
  invokevirtual com/admogo/AdMogoManager/getIpAddress()Ljava/lang/String;
  astore 7
  aload 7
  invokestatic com/admogo/adapters/InMobiSourceAdapter/encodeInfo(Ljava/lang/String;)Ljava/lang/String;
  astore 8
  aload_0
  astore_2
  aload_2
  getfield com/admogo/AdMogoLayout/activityReference Ljava/lang/ref/WeakReference;
  astore 9
  aload 9
  invokevirtual java/lang/ref/WeakReference/get()Ljava/lang/Object;
  astore 10
  aload 10
  astore 12
  aload 12
  checkcast android/content/Context
  astore 12
  aload 12
  astore 11
  aload 11
  invokestatic com/admogo/adapters/InMobiSourceAdapter/getUA(Landroid/content/Context;)Ljava/lang/String;
  astore 13
  aload_0
  astore_2
  aload_2
  getfield com/admogo/AdMogoLayout/adMogoManager Lcom/admogo/AdMogoManager;
  astore 6
  aload 6
  getfield com/admogo/AdMogoManager/deviceIDHash Ljava/lang/String;
  astore 7
  aload 7
  invokestatic com/admogo/adapters/InMobiSourceAdapter/encodeInfo(Ljava/lang/String;)Ljava/lang/String;
  astore 7
  aload_0
  astore_2
  aload_2
  invokevirtual com/admogo/AdMogoLayout/getCountryCode()Ljava/lang/String;
  astore 14
  ldc "cn"
  astore 16
  aload 14
  aload 16
  invokevirtual java/lang/String/equals(Ljava/lang/Object;)Z
  istore 15
  iload 15
  invokestatic app/DummyClass/invokeIfStmt(Z)V
  iload 15
  ifeq Label0
  ldc "zh_CN"
  astore_1
Label3:
  aload_0
  astore_2
  aload_2
  getfield com/admogo/AdMogoLayout/activityReference Ljava/lang/ref/WeakReference;
  astore 9
  aload 9
  invokevirtual java/lang/ref/WeakReference/get()Ljava/lang/Object;
  astore 10
  aload 10
  astore 17
  aload 17
  checkcast android/content/Context
  astore 17
  aload 17
  astore 11
  aload 11
  invokestatic com/admogo/GetUserInfo/getNetworkType(Landroid/content/Context;)Ljava/lang/String;
  astore 18
  ldc "2"
  astore 16
  aload 18
  astore_2
  aload_2
  aload 16
  invokevirtual java/lang/String/equals(Ljava/lang/Object;)Z
  istore 15
  iload 15
  invokestatic app/DummyClass/invokeIfStmt(Z)V
  iload 15
  ifeq Label1
  ldc "wifi"
  astore 18
Label4:
  aload 18
  astore_2
  aload_2
  invokestatic com/admogo/adapters/InMobiSourceAdapter/encodeInfo(Ljava/lang/String;)Ljava/lang/String;
  astore 19
  bipush 9
  istore 21
  iload 21
  istore_2
  iload_2
  anewarray java/lang/Object
  astore_2
  aload_2
  astore 20
  iconst_0
  istore 21
  aload 20
  iload 21
  aload 5
  aastore
  iconst_1
  istore 21
  aload 20
  iload 21
  aload 8
  aastore
  iconst_2
  istore 21
  aload 20
  iload 21
  aload 13
  aastore
  iconst_3
  istore 21
  aload 20
  iload 21
  aload 7
  aastore
  iconst_4
  istore 21
  aload 20
  iload 21
  aload_1
  aastore
  iconst_5
  istore 21
  aload 20
  iload 21
  aload 19
  aastore
  bipush 6
  istore 21
  ldc "pr-SPEC-ATATA-20090521"
  astore 16
  aload 20
  iload 21
  aload 16
  aastore
  bipush 7
  istore 21
  ldc "adsmogo"
  astore 16
  aload 20
  iload 21
  aload 16
  aastore
  bipush 8
  istore 21
  ldc "xml"
  astore 16
  aload 20
  iload 21
  aload 16
  aastore
  ldc "mk-siteid=%s&mk-carrier=%s&h-user-agent=%s&u-id=%s&d-localization=%s&d-netType=%s&mk-version=%s&ref-tag=%s&format=%s"
  astore 16
  aload 20
  astore_2
  aload 16
  aload_2
  invokestatic java/lang/String/format(Ljava/lang/String;[Ljava/lang/Object;)Ljava/lang/String;
  astore 14
  getstatic com/admogo/util/AdMogoUtil/ADMOGO Ljava/lang/String;
  astore 22
  new java/lang/StringBuilder
  astore 23
  ldc "INMOBI params:"
  astore 16
  aload 23
  astore_2
  aload_2
  aload 16
  invokespecial java/lang/StringBuilder/<init>(Ljava/lang/String;)V
  aload 23
  astore_2
  aload_2
  aload 14
  invokevirtual java/lang/StringBuilder/append(Ljava/lang/String;)Ljava/lang/StringBuilder;
  astore 23
  aload 23
  astore_2
  aload_2
  invokevirtual java/lang/StringBuilder/toString()Ljava/lang/String;
  astore 7
  aload 22
  astore_2
  aload_2
  aload 7
  invokestatic android/util/Log/i(Ljava/lang/String;Ljava/lang/String;)I
  pop
  new org/apache/http/impl/client/DefaultHttpClient
  astore 24
Label7:
  aload 24
  astore_2
  aload_2
  invokespecial org/apache/http/impl/client/DefaultHttpClient/<init>()V
  new org/apache/http/client/methods/HttpPost
  astore 25
  ldc "http://w.inmobi.com/showad.asm"
  astore 16
  aload 25
  astore_2
  aload_2
  aload 16
  invokespecial org/apache/http/client/methods/HttpPost/<init>(Ljava/lang/String;)V
  ldc "X-Mkhoj-SiteID"
  astore 16
  ldc "4028cba631d63df10131e1d3818b00cc"
  astore 26
  aload 25
  astore_2
  aload 26
  astore_3
  aload_2
  aload 16
  aload_3
  invokevirtual org/apache/http/client/methods/HttpPost/addHeader(Ljava/lang/String;Ljava/lang/String;)V
  ldc "Content-Type"
  astore 16
  ldc "application/x-www-form-urlencoded "
  astore 26
  aload 25
  astore_2
  aload 26
  astore_3
  aload_2
  aload 16
  aload_3
  invokevirtual org/apache/http/client/methods/HttpPost/addHeader(Ljava/lang/String;Ljava/lang/String;)V
  new org/apache/http/entity/StringEntity
  astore 27
  aload 27
  astore_2
  aload_2
  aload 14
  invokespecial org/apache/http/entity/StringEntity/<init>(Ljava/lang/String;)V
  aload 25
  astore_2
  aload 27
  astore_3
  aload_2
  aload_3
  invokevirtual org/apache/http/client/methods/HttpPost/setEntity(Lorg/apache/http/HttpEntity;)V
  aload 24
  astore_2
  aload 25
  astore_3
  aload_2
  aload_3
  invokeinterface org/apache/http/client/HttpClient/execute(Lorg/apache/http/client/methods/HttpUriRequest;)Lorg/apache/http/HttpResponse; 2
  astore 28
  aload 28
  astore_2
  aload_2
  invokeinterface org/apache/http/HttpResponse/getStatusLine()Lorg/apache/http/StatusLine; 1
  astore 29
  aload 29
  astore_2
  aload_2
  invokeinterface org/apache/http/StatusLine/getStatusCode()I 1
  istore 30
  iload 30
  istore_2
  dload_2
  invokestatic app/DummyClass/invokeIfStmt(D)V
  sipush 200
  istore 21
  iload 30
  istore_2
  iload 21
  istore_3
  iload_2
  iload_3
  if_icmpne Label2
  aload 28
  astore_2
  aload_2
  invokeinterface org/apache/http/HttpResponse/getEntity()Lorg/apache/http/HttpEntity; 1
  astore 31
  aload 31
  astore_2
  aload_2
  invokestatic org/apache/http/util/EntityUtils/toString(Lorg/apache/http/HttpEntity;)Ljava/lang/String;
  astore 22
  aload 22
  astore_2
  aload_2
  invokestatic com/admogo/adapters/InMobiSourceAdapter/getInmobiADByXML(Ljava/lang/String;)Lcom/admogo/obj/InmobiAD;
  astore 32
Label8:
  aload 32
  astore 4
Label5:
  aload 4
  areturn
Label0:
  ldc "en_US"
  astore_1
  goto Label3
Label1:
  ldc "mobile"
  astore 18
  goto Label4
Label2:
  aconst_null
  astore 33
  aload 33
  areturn
Label6:
  astore 34
  getstatic com/admogo/util/AdMogoUtil/ADMOGO Ljava/lang/String;
  astore 22
  ldc "Caught IOException in InmobiSoure"
  astore 16
  aload 22
  astore_2
  aload 34
  astore_3
  aload_2
  aload 16
  aload_3
  invokestatic android/util/Log/e(Ljava/lang/String;Ljava/lang/String;Ljava/lang/Throwable;)I
  pop
  goto Label5
  nop
.end <method>

.method private static getInmobiADByXML(Ljava/lang/String;)Lcom/admogo/obj/InmobiAD;
.limit locals 27
.limit stack 200
  .catch  java/lang/Exception <from> Label18 <to> Label19 <using> Label17
  nop
  aconst_null
  astore_3
  invokestatic javax/xml/parsers/DocumentBuilderFactory/newInstance()Ljavax/xml/parsers/DocumentBuilderFactory;
  astore 4
Label18:
  aload 4
  invokevirtual javax/xml/parsers/DocumentBuilderFactory/newDocumentBuilder()Ljavax/xml/parsers/DocumentBuilder;
  astore 5
  new org/xml/sax/InputSource
  astore 6
  new java/io/StringReader
  astore 7
  aload_0
  astore_1
  aload 7
  aload_1
  invokespecial java/io/StringReader/<init>(Ljava/lang/String;)V
  aload 6
  aload 7
  invokespecial org/xml/sax/InputSource/<init>(Ljava/io/Reader;)V
  aload 5
  aload 6
  invokevirtual javax/xml/parsers/DocumentBuilder/parse(Lorg/xml/sax/InputSource;)Lorg/w3c/dom/Document;
  astore 8
  new java/lang/NoClassDefFoundError
  dup
  invokespecial java/lang/NoClassDefFoundError/<init>()V
  athrow
  iload 8
  ifne Label0
  getstatic com/admogo/util/AdMogoUtil/ADMOGO Ljava/lang/String;
  astore 9
  ldc "inmobi xml is null"
  astore 10
  aload 9
  aload 10
  invokestatic android/util/Log/w(Ljava/lang/String;Ljava/lang/String;)I
  pop
  aconst_null
  astore 11
  aload 11
  areturn
Label0:
  aload 8
  invokeinterface org/w3c/dom/Document/getDocumentElement()Lorg/w3c/dom/Element; 1
  astore 12
  aload 12
  invokestatic app/DummyClass/invokeIfStmt(Ljava/lang/Object;)V
  aload 12
  ifnonnull Label1
  getstatic com/admogo/util/AdMogoUtil/ADMOGO Ljava/lang/String;
  astore 13
  new java/lang/StringBuilder
  astore 14
  ldc "inmobi xml not have ad root info-->"
  astore 10
  aload 14
  aload 10
  invokespecial java/lang/StringBuilder/<init>(Ljava/lang/String;)V
  aload_0
  astore_1
  aload 14
  aload_1
  invokevirtual java/lang/StringBuilder/append(Ljava/lang/String;)Ljava/lang/StringBuilder;
  astore 14
  aload 14
  invokevirtual java/lang/StringBuilder/toString()Ljava/lang/String;
  astore 9
  aload 13
  aload 9
  invokestatic android/util/Log/w(Ljava/lang/String;Ljava/lang/String;)I
  pop
  aconst_null
  astore 11
  aload 11
  areturn
Label1:
  ldc "Ad"
  astore 10
  aload 12
  aload 10
  invokeinterface org/w3c/dom/Element/getElementsByTagName(Ljava/lang/String;)Lorg/w3c/dom/NodeList; 2
  astore 15
  aload 15
  invokestatic app/DummyClass/invokeIfStmt(Ljava/lang/Object;)V
  aload 15
  ifnull Label2
  aload 15
  invokeinterface org/w3c/dom/NodeList/getLength()I 1
  istore 16
  dload 16
  invokestatic app/DummyClass/invokeIfStmt(D)V
  iconst_1
  istore 17
  iload 17
  istore_1
  iload 16
  iload_1
  if_icmpge Label3
Label2:
  getstatic com/admogo/util/AdMogoUtil/ADMOGO Ljava/lang/String;
  astore 13
  new java/lang/StringBuilder
  astore 14
  ldc "inmobi xml content exception info-->"
  astore 10
  aload 14
  aload 10
  invokespecial java/lang/StringBuilder/<init>(Ljava/lang/String;)V
  aload_0
  astore_1
  aload 14
  aload_1
  invokevirtual java/lang/StringBuilder/append(Ljava/lang/String;)Ljava/lang/StringBuilder;
  astore 14
  aload 14
  invokevirtual java/lang/StringBuilder/toString()Ljava/lang/String;
  astore 9
  aload 13
  aload 9
  invokestatic android/util/Log/w(Ljava/lang/String;Ljava/lang/String;)I
  pop
  aconst_null
  astore 11
  aload 11
  areturn
Label3:
  aload 15
  invokeinterface org/w3c/dom/NodeList/getLength()I 1
  istore 16
  dload 16
  invokestatic app/DummyClass/invokeIfStmt(D)V
  iload 16
  ifle Label4
  new com/admogo/obj/InmobiAD
  astore 18
  aload 18
  astore_1
  aload_1
  invokespecial com/admogo/obj/InmobiAD/<init>()V
Label19:
  iconst_0
  istore 17
  iload 17
  istore_1
  aload 15
  iload_1
  invokeinterface org/w3c/dom/NodeList/item(I)Lorg/w3c/dom/Node; 2
  astore 19
  aload 19
  astore 20
  aload 20
  checkcast org/w3c/dom/Element
  astore 20
  aload 20
  astore 12
  aload 12
  invokeinterface org/w3c/dom/Element/getChildNodes()Lorg/w3c/dom/NodeList; 1
  astore 15
  ldc "type"
  astore 10
  aload 12
  aload 10
  invokeinterface org/w3c/dom/Element/getAttribute(Ljava/lang/String;)Ljava/lang/String; 2
  astore 13
  ldc "banner"
  astore 10
  aload 13
  aload 10
  invokevirtual java/lang/String/equals(Ljava/lang/Object;)Z
  istore 21
  iload 21
  istore_1
  iload_1
  invokestatic app/DummyClass/invokeIfStmt(Z)V
  iload 21
  ifeq Label5
  iconst_1
  istore 17
  aload 18
  astore_1
  iload 17
  istore_2
  aload_1
  iload_2
  invokevirtual com/admogo/obj/InmobiAD/setAdsType(I)V
  iconst_0
  dstore 16
Label8:
  aload 15
  invokeinterface org/w3c/dom/NodeList/getLength()I 1
  istore 22
  dload 16
  invokestatic app/DummyClass/invokeIfStmt(D)V
  iload 22
  istore_1
  dload_1
  invokestatic app/DummyClass/invokeIfStmt(D)V
  iload 22
  istore_1
  iload 16
  iload_1
  if_icmplt Label6
  aload 18
  astore_1
  aload_1
  invokevirtual com/admogo/obj/InmobiAD/getImgUrl()Ljava/lang/String;
  astore 13
  aload 13
  invokestatic com/admogo/adapters/InMobiSourceAdapter/fetchImage(Ljava/lang/String;)Landroid/graphics/drawable/Drawable;
  astore 23
  aload 18
  astore_1
  aload 23
  astore_2
  aload_1
  aload_2
  invokevirtual com/admogo/obj/InmobiAD/setAdImg(Landroid/graphics/drawable/Drawable;)V
  aload 18
  astore_3
Label4:
  aload_3
  areturn
Label6:
  aload 15
  iload 16
  invokeinterface org/w3c/dom/NodeList/item(I)Lorg/w3c/dom/Node; 2
  astore 19
  aload 19
  astore 24
  aload 24
  checkcast org/w3c/dom/Element
  astore 24
  aload 24
  astore 12
  aload 12
  invokeinterface org/w3c/dom/Element/getNodeName()Ljava/lang/String; 1
  astore 13
  ldc "ImageURL"
  astore 10
  aload 13
  aload 10
  invokevirtual java/lang/String/equals(Ljava/lang/Object;)Z
  istore 21
  iload 21
  istore_1
  iload_1
  invokestatic app/DummyClass/invokeIfStmt(Z)V
  iload 21
  ifeq Label7
  aload 12
  invokeinterface org/w3c/dom/Element/getFirstChild()Lorg/w3c/dom/Node; 1
  astore 19
  aload 19
  astore_1
  aload_1
  invokeinterface org/w3c/dom/Node/getNodeValue()Ljava/lang/String; 1
  astore 13
  aload 18
  astore_1
  aload_1
  aload 13
  invokevirtual com/admogo/obj/InmobiAD/setImgUrl(Ljava/lang/String;)V
Label10:
  iload 16
  iconst_1
  iadd
  istore 16
  goto Label8
Label7:
  aload 12
  invokeinterface org/w3c/dom/Element/getNodeName()Ljava/lang/String; 1
  astore 13
  ldc "Placement"
  astore 10
  aload 13
  aload 10
  invokevirtual java/lang/String/equals(Ljava/lang/Object;)Z
  istore 21
  iload 21
  istore_1
  iload_1
  invokestatic app/DummyClass/invokeIfStmt(Z)V
  iload 21
  ifeq Label9
  aload 12
  invokeinterface org/w3c/dom/Element/getFirstChild()Lorg/w3c/dom/Node; 1
  astore 19
  aload 19
  astore_1
  aload_1
  invokeinterface org/w3c/dom/Node/getNodeValue()Ljava/lang/String; 1
  astore 13
  aload 18
  astore_1
  aload_1
  aload 13
  invokevirtual com/admogo/obj/InmobiAD/setPlacement(Ljava/lang/String;)V
Label21:
  goto Label10
Label20:
  astore 25
  aload 18
  astore_3
Label16:
  aload 25
  astore_1
  aload_1
  invokevirtual java/lang/Exception/printStackTrace()V
  goto Label4
Label9:
  aload 12
  invokeinterface org/w3c/dom/Element/getNodeName()Ljava/lang/String; 1
  astore 13
  ldc "AdURL"
  astore 10
  aload 13
  aload 10
  invokevirtual java/lang/String/equals(Ljava/lang/Object;)Z
  istore 21
  iload 21
  istore_1
  iload_1
  invokestatic app/DummyClass/invokeIfStmt(Z)V
  iload 21
  ifeq Label10
  aload 12
  invokeinterface org/w3c/dom/Element/getFirstChild()Lorg/w3c/dom/Node; 1
  astore 19
  aload 19
  astore_1
  aload_1
  invokeinterface org/w3c/dom/Node/getNodeValue()Ljava/lang/String; 1
  astore 13
  aload 18
  astore_1
  aload_1
  aload 13
  invokevirtual com/admogo/obj/InmobiAD/setAdUrl(Ljava/lang/String;)V
  goto Label10
Label5:
  iconst_2
  istore 17
  aload 18
  astore_1
  iload 17
  istore_2
  aload_1
  iload_2
  invokevirtual com/admogo/obj/InmobiAD/setAdsType(I)V
  iconst_0
  istore 22
Label13:
  aload 15
  invokeinterface org/w3c/dom/NodeList/getLength()I 1
  istore 16
  iload 22
  istore_1
  dload_1
  invokestatic app/DummyClass/invokeIfStmt(D)V
  dload 16
  invokestatic app/DummyClass/invokeIfStmt(D)V
  iload 22
  istore_1
  iload_1
  iload 16
  if_icmplt Label11
  aload 18
  astore_3
  goto Label4
Label11:
  iload 22
  istore_1
  aload 15
  iload_1
  invokeinterface org/w3c/dom/NodeList/item(I)Lorg/w3c/dom/Node; 2
  astore 19
  aload 19
  astore 26
  aload 26
  checkcast org/w3c/dom/Element
  astore 26
  aload 26
  astore 12
  aload 12
  invokeinterface org/w3c/dom/Element/getNodeName()Ljava/lang/String; 1
  astore 13
  ldc "LinkText"
  astore 10
  aload 13
  aload 10
  invokevirtual java/lang/String/equals(Ljava/lang/Object;)Z
  istore 21
  iload 21
  istore_1
  iload_1
  invokestatic app/DummyClass/invokeIfStmt(Z)V
  iload 21
  ifeq Label12
  aload 12
  invokeinterface org/w3c/dom/Element/getFirstChild()Lorg/w3c/dom/Node; 1
  astore 19
  aload 19
  astore_1
  aload_1
  invokeinterface org/w3c/dom/Node/getNodeValue()Ljava/lang/String; 1
  astore 13
  aload 18
  astore_1
  aload_1
  aload 13
  invokevirtual com/admogo/obj/InmobiAD/setLinkText(Ljava/lang/String;)V
Label15:
  iload 22
  iconst_1
  iadd
  istore 22
  goto Label13
Label12:
  aload 12
  invokeinterface org/w3c/dom/Element/getNodeName()Ljava/lang/String; 1
  astore 13
  ldc "Placement"
  astore 10
  aload 13
  aload 10
  invokevirtual java/lang/String/equals(Ljava/lang/Object;)Z
  istore 21
  iload 21
  istore_1
  iload_1
  invokestatic app/DummyClass/invokeIfStmt(Z)V
  iload 21
  ifeq Label14
  aload 12
  invokeinterface org/w3c/dom/Element/getFirstChild()Lorg/w3c/dom/Node; 1
  astore 19
  aload 19
  astore_1
  aload_1
  invokeinterface org/w3c/dom/Node/getNodeValue()Ljava/lang/String; 1
  astore 13
  aload 18
  astore_1
  aload_1
  aload 13
  invokevirtual com/admogo/obj/InmobiAD/setPlacement(Ljava/lang/String;)V
  goto Label15
Label14:
  aload 12
  invokeinterface org/w3c/dom/Element/getNodeName()Ljava/lang/String; 1
  astore 13
  ldc "AdURL"
  astore 10
  aload 13
  aload 10
  invokevirtual java/lang/String/equals(Ljava/lang/Object;)Z
  istore 21
  iload 21
  istore_1
  iload_1
  invokestatic app/DummyClass/invokeIfStmt(Z)V
  iload 21
  ifeq Label15
  aload 12
  invokeinterface org/w3c/dom/Element/getFirstChild()Lorg/w3c/dom/Node; 1
  astore 19
  aload 19
  astore_1
  aload_1
  invokeinterface org/w3c/dom/Node/getNodeValue()Ljava/lang/String; 1
  astore 13
  aload 18
  astore_1
  aload_1
  aload 13
  invokevirtual com/admogo/obj/InmobiAD/setAdUrl(Ljava/lang/String;)V
Label22:
  goto Label15
Label17:
  astore 25
  goto Label16
  nop
.end <method>

.method private static getUA(Landroid/content/Context;)Ljava/lang/String;
.limit locals 5
.limit stack 200
  nop
  new java/lang/NoClassDefFoundError
  dup
  invokespecial java/lang/NoClassDefFoundError/<init>()V
  athrow
  iload_0
  ifne Label0
  ldc ""
  astore_1
  aload_1
  areturn
Label0:
  getstatic com/admogo/adapters/InMobiSourceAdapter/webView Landroid/webkit/WebView;
  astore_2
  aload_2
  invokevirtual android/webkit/WebView/getSettings()Landroid/webkit/WebSettings;
  astore_3
  aload_3
  invokevirtual android/webkit/WebSettings/getUserAgentString()Ljava/lang/String;
  astore 4
  aload 4
  invokestatic com/admogo/adapters/InMobiSourceAdapter/encodeInfo(Ljava/lang/String;)Ljava/lang/String;
  astore 4
  aload 4
  areturn
  nop
.end <method>

.method public handle()V
.limit locals 11
.limit stack 200
  nop
  aload_0
  getfield com/admogo/adapters/AdMogoAdapter/adMogoLayoutReference Ljava/lang/ref/WeakReference;
  astore_1
  aload_1
  invokevirtual java/lang/ref/WeakReference/get()Ljava/lang/Object;
  astore_2
  aload_2
  astore 4
  new java/lang/NoClassDefFoundError
  dup
  invokespecial java/lang/NoClassDefFoundError/<init>()V
  athrow
  aload 4
  astore_3
  aload_3
  invokestatic app/DummyClass/invokeIfStmt(Ljava/lang/Object;)V
  iload_3
  ifne Label0
Label1:
  return
Label0:
  aload_3
  getfield com/admogo/AdMogoLayout/scheduler Ljava/util/concurrent/ScheduledExecutorService;
  astore 5
  new com/admogo/adapters/InMobiSourceAdapter$FetchInmobiADRunnable
  astore 6
  aload_0
  getfield com/admogo/adapters/AdMogoAdapter/ration Lcom/admogo/obj/Ration;
  astore 7
  aload 6
  aload 7
  aload_0
  invokespecial com/admogo/adapters/InMobiSourceAdapter$FetchInmobiADRunnable/<init>(Lcom/admogo/obj/Ration;Lcom/admogo/adapters/InMobiSourceAdapter;)V
  getstatic java/util/concurrent/TimeUnit/SECONDS Ljava/util/concurrent/TimeUnit;
  astore 8
  ldc2_w 0
  lstore 9
  aload 5
  aload 6
  lload 9
  aload 8
  invokeinterface java/util/concurrent/ScheduledExecutorService/schedule(Ljava/lang/Runnable;JLjava/util/concurrent/TimeUnit;)Ljava/util/concurrent/ScheduledFuture; 5
  pop
  goto Label1
  nop
.end <method>

