.source dalvik_source_VirusShare_32e70f448ebd75661a1cb12f9cd8e013.apk
.class final  com/wiyun/ad/e$a
.super java/lang/Thread
.field final "a" Lcom/wiyun/ad/e;
.field private "b" Ljava/lang/String;
.field private "c" Ljava/lang/String;
.field private "d" Landroid/os/Handler;
.field private "e" I
.field private "f" I
.field private "g" I

.method <init>(Lcom/wiyun/ad/e;Ljava/lang/String;Landroid/os/Handler;)V
.limit locals 5
.limit stack 200
  nop
  aload_0
  aload_1
  putfield com/wiyun/ad/e$a/a Lcom/wiyun/ad/e;
  aload_0
  invokespecial java/lang/Thread/<init>()V
  iconst_0
  istore 4
  aload_0
  iload 4
  putfield com/wiyun/ad/e$a/g I
  aload_0
  aload_2
  putfield com/wiyun/ad/e$a/b Ljava/lang/String;
  aload_0
  getfield com/wiyun/ad/e$a/b Ljava/lang/String;
  astore_2
  aload_2
  invokestatic com/wiyun/ad/x/b(Ljava/lang/String;)Ljava/lang/String;
  astore_2
  aload_0
  aload_2
  putfield com/wiyun/ad/e$a/c Ljava/lang/String;
  aload_0
  aload_3
  putfield com/wiyun/ad/e$a/d Landroid/os/Handler;
  iconst_1
  istore 4
  aload_0
  iload 4
  invokevirtual com/wiyun/ad/e$a/setDaemon(Z)V
  return
  nop
.end <method>

.method static a(Lcom/wiyun/ad/e$a;)Lcom/wiyun/ad/e;
  .synthetic
.limit locals 2
.limit stack 200
  nop
  aload_0
  getfield com/wiyun/ad/e$a/a Lcom/wiyun/ad/e;
  astore_1
  aload_1
  areturn
  nop
.end <method>

.method private a()Lorg/apache/http/impl/client/DefaultHttpClient;
.limit locals 9
.limit stack 200
  nop
  new java/lang/NoClassDefFoundError
  dup
  invokespecial java/lang/NoClassDefFoundError/<init>()V
  athrow
  aload_1
  invokespecial org/apache/http/params/BasicHttpParams/<init>()V
  getstatic org/apache/http/HttpVersion/HTTP_1_0 Lorg/apache/http/HttpVersion;
  astore_2
  aload_1
  aload_2
  invokestatic org/apache/http/params/HttpProtocolParams/setVersion(Lorg/apache/http/params/HttpParams;Lorg/apache/http/ProtocolVersion;)V
  ldc "UTF-8"
  astore_3
  aload_1
  aload_3
  invokestatic org/apache/http/params/HttpProtocolParams/setContentCharset(Lorg/apache/http/params/HttpParams;Ljava/lang/String;)V
  iconst_0
  istore 4
  aload_1
  iload 4
  invokestatic org/apache/http/params/HttpProtocolParams/setUseExpectContinue(Lorg/apache/http/params/HttpParams;Z)V
  sipush 10000
  istore 4
  aload_1
  iload 4
  invokestatic org/apache/http/params/HttpConnectionParams/setConnectionTimeout(Lorg/apache/http/params/HttpParams;I)V
  sipush 10000
  istore 4
  aload_1
  iload 4
  invokestatic org/apache/http/params/HttpConnectionParams/setSoTimeout(Lorg/apache/http/params/HttpParams;I)V
  new org/apache/http/impl/client/DefaultHttpClient
  astore 5
  aload 5
  aload_1
  invokespecial org/apache/http/impl/client/DefaultHttpClient/<init>(Lorg/apache/http/params/HttpParams;)V
  invokestatic com/wiyun/ad/l/b()Z
  istore 6
  iload 6
  invokestatic app/DummyClass/invokeIfStmt(Z)V
  iload 6
  ifne Label0
  invokestatic com/wiyun/ad/l/c()Z
  istore 6
  iload 6
  invokestatic app/DummyClass/invokeIfStmt(Z)V
  iload 6
  ifeq Label0
  invokestatic com/wiyun/ad/l/d()Lorg/apache/http/HttpHost;
  astore 7
  aload 7
  invokestatic app/DummyClass/invokeIfStmt(Ljava/lang/Object;)V
  aload 7
  ifnull Label0
  aload 5
  invokevirtual org/apache/http/impl/client/DefaultHttpClient/getParams()Lorg/apache/http/params/HttpParams;
  astore 8
  ldc "http.route.default-proxy"
  astore_3
  aload 8
  aload_3
  aload 7
  invokeinterface org/apache/http/params/HttpParams/setParameter(Ljava/lang/String;Ljava/lang/Object;)Lorg/apache/http/params/HttpParams; 3
  pop
Label0:
  aload 5
  areturn
  nop
.end <method>

.method private a(Lorg/apache/http/HttpResponse;Ljava/io/File;)Z
.limit locals 22
.limit stack 200
  nop
  sipush 4096
  istore 5
  iload 5
  newarray byte
  astore 4
  aload_1
  astore_3
  new java/lang/NoSuchMethodError
  dup
  invokespecial java/lang/NoSuchMethodError/<init>()V
  athrow
  nop
  aload 6
  invokeinterface org/apache/http/HttpEntity/getContent()Ljava/io/InputStream; 1
  astore 7
  aload 7
  invokestatic app/DummyClass/invokeIfStmt(Ljava/lang/Object;)V
  aload 7
  ifnonnull Label0
Label2:
  iconst_0
  istore 5
  iload 5
  ireturn
Label0:
  aload_2
  astore_3
  aload_3
  invokevirtual java/io/File/exists()Z
  istore 8
  iload 8
  invokestatic app/DummyClass/invokeIfStmt(Z)V
  iload 8
  ifeq Label1
  aload_2
  astore_3
  aload_3
  invokevirtual java/io/File/delete()Z
  istore 8
  iload 8
  invokestatic app/DummyClass/invokeIfStmt(Z)V
  iload 8
  ifeq Label2
Label1:
  aload_2
  astore_3
  aload_3
  invokevirtual java/io/File/getParentFile()Ljava/io/File;
  astore 9
  aload 9
  invokevirtual java/io/File/exists()Z
  istore 8
  iload 8
  invokestatic app/DummyClass/invokeIfStmt(Z)V
  iload 8
  ifne Label3
  aload 9
  invokevirtual java/io/File/mkdirs()Z
  istore 8
  iload 8
  invokestatic app/DummyClass/invokeIfStmt(Z)V
  iload 8
  ifeq Label2
Label3:
  new java/io/FileOutputStream
  astore 10
Label15:
  aload_2
  astore_3
  aload 10
  aload_3
  invokespecial java/io/FileOutputStream/<init>(Ljava/io/File;)V
Label16:
  iconst_0
  istore 11
Label9:
  dload 11
  invokestatic app/DummyClass/invokeIfStmt(D)V
  iconst_m1
  istore 5
  iload 11
  iload 5
  if_icmpne Label4
  aload 10
  invokestatic app/DummyClass/invokeIfStmt(Ljava/lang/Object;)V
  aload 10
  ifnull Label5
Label18:
  aload 10
  invokevirtual java/io/FileOutputStream/flush()V
  aload 10
  invokevirtual java/io/FileOutputStream/close()V
Label5:
  iconst_1
  istore 5
  iload 5
  ireturn
Label4:
  iconst_0
  istore 5
  aload 10
  aload 4
  iload 5
  iload 11
  invokevirtual java/io/FileOutputStream/write([BII)V
  aload_0
  astore_3
  aload_3
  getfield com/wiyun/ad/e$a/a Lcom/wiyun/ad/e;
  astore 12
  aload 12
  invokevirtual com/wiyun/ad/e/getParent()Landroid/view/ViewParent;
  astore 13
  aload 13
  invokestatic app/DummyClass/invokeIfStmt(Ljava/lang/Object;)V
  aload 13
  ifnull Label6
  aload_0
  astore_3
  aload_3
  getfield com/wiyun/ad/e$a/a Lcom/wiyun/ad/e;
  astore 12
  aload 12
  invokevirtual com/wiyun/ad/e/getParent()Landroid/view/ViewParent;
  astore 13
  aload 13
  invokeinterface android/view/ViewParent/getParent()Landroid/view/ViewParent; 1
  astore 13
Label21:
  aload 13
  invokestatic app/DummyClass/invokeIfStmt(Ljava/lang/Object;)V
  aload 13
  ifnonnull Label7
Label6:
  aload 10
  invokestatic app/DummyClass/invokeIfStmt(Ljava/lang/Object;)V
  aload 10
  ifnull Label2
Label23:
  aload 10
  invokevirtual java/io/FileOutputStream/flush()V
  aload 10
  invokevirtual java/io/FileOutputStream/close()V
Label24:
  iconst_0
  istore 5
  iload 5
  ireturn
Label22:
  astore 14
  iconst_0
  istore 5
  iload 5
  ireturn
Label7:
  aload_0
  astore_3
  aload_3
  getfield com/wiyun/ad/e$a/f I
  istore 15
  iload 11
  iload 15
  iadd
  istore 15
  aload_0
  astore_3
  aload_3
  iload 15
  putfield com/wiyun/ad/e$a/f I
  aload_0
  astore_3
  aload_3
  getfield com/wiyun/ad/e$a/f I
  istore 15
  aload_0
  astore_3
  aload_3
  getfield com/wiyun/ad/e$a/g I
  istore 11
  iload 15
  iload 11
  isub
  istore 15
  dload 15
  invokestatic app/DummyClass/invokeIfStmt(D)V
  ldc 100000
  istore 5
  iload 15
  iload 5
  if_icmple Label8
  aload_0
  astore_3
  aload_3
  invokespecial com/wiyun/ad/e$a/b()V
  aload_0
  astore_3
  aload_3
  getfield com/wiyun/ad/e$a/f I
  istore 15
  aload_0
  astore_3
  aload_3
  iload 15
  putfield com/wiyun/ad/e$a/g I
Label8:
  aload 7
  aload 4
  invokevirtual java/io/InputStream/read([B)I
  istore 15
Label25:
  iload 15
  istore 11
  goto Label9
Label14:
  astore 16
  aconst_null
  astore 10
Label12:
  aload 10
  invokestatic app/DummyClass/invokeIfStmt(Ljava/lang/Object;)V
  aload 10
  ifnull Label2
Label27:
  aload 10
  invokevirtual java/io/FileOutputStream/flush()V
  aload 10
  invokevirtual java/io/FileOutputStream/close()V
Label28:
  iconst_0
  istore 5
  iload 5
  ireturn
Label26:
  astore 17
  iconst_0
  istore 5
  iload 5
  ireturn
Label13:
  astore 18
  aconst_null
  astore 10
Label11:
  aload 10
  invokestatic app/DummyClass/invokeIfStmt(Ljava/lang/Object;)V
  aload 10
  ifnull Label10
Label30:
  aload 10
  invokevirtual java/io/FileOutputStream/flush()V
  aload 10
  invokevirtual java/io/FileOutputStream/close()V
Label10:
  aload 18
  athrow
Label17:
  astore 19
  goto Label5
Label29:
  astore 20
  goto Label10
Label19:
  astore 18
  goto Label11
Label20:
  astore 21
  goto Label12
  nop
.end <method>

.method private b()V
.limit locals 34
.limit stack 200
  nop
  iconst_0
  istore 6
  new java/lang/StringBuilder
  astore 7
  aload 7
  invokespecial java/lang/StringBuilder/<init>()V
  ldc "downloading"
  astore 9
  aload 9
  invokestatic com/wiyun/ad/q/a(Ljava/lang/String;)Ljava/lang/String;
  astore 8
  aload 7
  aload 8
  invokevirtual java/lang/StringBuilder/append(Ljava/lang/String;)Ljava/lang/StringBuilder;
  pop
  new java/lang/StringBuilder
  astore 10
  aload 7
  invokevirtual java/lang/StringBuilder/toString()Ljava/lang/String;
  astore 8
  aload 8
  invokestatic java/lang/String/valueOf(Ljava/lang/Object;)Ljava/lang/String;
  astore 8
  aload 10
  aload 8
  invokespecial java/lang/StringBuilder/<init>(Ljava/lang/String;)V
  aload_0
  astore_1
  aload_1
  getfield com/wiyun/ad/e$a/c Ljava/lang/String;
  astore 8
  aload 10
  aload 8
  invokevirtual java/lang/StringBuilder/append(Ljava/lang/String;)Ljava/lang/StringBuilder;
  astore 10
  aload 10
  invokevirtual java/lang/StringBuilder/toString()Ljava/lang/String;
  astore 11
  new java/lang/NoClassDefFoundError
  dup
  invokespecial java/lang/NoClassDefFoundError/<init>()V
  athrow
  aload 12
  invokespecial android/content/Intent/<init>()V
  ldc 268435456
  istore 13
  aload 12
  iload 13
  invokevirtual android/content/Intent/addFlags(I)Landroid/content/Intent;
  pop
  aload_0
  astore_1
  aload_1
  getfield com/wiyun/ad/e$a/a Lcom/wiyun/ad/e;
  astore 14
  aload 14
  invokevirtual com/wiyun/ad/e/getContext()Landroid/content/Context;
  astore 15
  aload 15
  invokevirtual android/content/Context/getResources()Landroid/content/res/Resources;
  astore 16
  aload_0
  astore_1
  aload_1
  getfield com/wiyun/ad/e$a/a Lcom/wiyun/ad/e;
  astore 14
  aload 14
  invokevirtual com/wiyun/ad/e/getContext()Landroid/content/Context;
  astore 15
  aload 15
  invokevirtual android/content/Context/getPackageName()Ljava/lang/String;
  astore 17
  new android/app/Notification
  astore 18
  aload 18
  astore_1
  aload_1
  invokespecial android/app/Notification/<init>()V
  aload 18
  astore_1
  aload_1
  getfield android/app/Notification/flags I
  istore_1
  iload_1
  istore 19
  iload 19
  iconst_2
  ior
  istore 19
  iload 19
  istore_1
  aload 18
  astore_2
  aload_2
  iload_1
  putfield android/app/Notification/flags I
  ldc "icon"
  astore 9
  ldc "drawable"
  astore 20
  aload 20
  astore_1
  aload 17
  astore_2
  aload 16
  aload 9
  aload_1
  aload_2
  invokevirtual android/content/res/Resources/getIdentifier(Ljava/lang/String;Ljava/lang/String;Ljava/lang/String;)I
  istore 19
  iload 19
  istore_1
  aload 18
  astore_2
  aload_2
  iload_1
  putfield android/app/Notification/icon I
  new java/lang/StringBuilder
  astore 10
  ldc "downloading"
  astore 9
  aload 9
  invokestatic com/wiyun/ad/q/a(Ljava/lang/String;)Ljava/lang/String;
  astore 21
  aload 21
  astore_1
  aload_1
  invokestatic java/lang/String/valueOf(Ljava/lang/Object;)Ljava/lang/String;
  astore 21
  aload 21
  astore_1
  aload 10
  aload_1
  invokespecial java/lang/StringBuilder/<init>(Ljava/lang/String;)V
  aload_0
  astore_1
  aload_1
  getfield com/wiyun/ad/e$a/c Ljava/lang/String;
  astore_1
  aload_1
  astore 21
  aload 21
  astore_1
  aload 10
  aload_1
  invokevirtual java/lang/StringBuilder/append(Ljava/lang/String;)Ljava/lang/StringBuilder;
  astore 10
  aload 10
  invokevirtual java/lang/StringBuilder/toString()Ljava/lang/String;
  astore 21
  aload 21
  astore_1
  aload 18
  astore_2
  aload_2
  aload_1
  putfield android/app/Notification/tickerText Ljava/lang/CharSequence;
  aload_0
  astore_1
  aload_1
  getfield com/wiyun/ad/e$a/a Lcom/wiyun/ad/e;
  astore 14
  aload 14
  invokevirtual com/wiyun/ad/e/getContext()Landroid/content/Context;
  astore 15
  iconst_0
  istore 13
  iconst_0
  istore 23
  iload 23
  istore_1
  aload 15
  iload 13
  aload 12
  iload_1
  invokestatic android/app/PendingIntent/getActivity(Landroid/content/Context;ILandroid/content/Intent;I)Landroid/app/PendingIntent;
  astore 22
  aload 22
  astore_1
  aload 18
  astore_2
  aload_2
  aload_1
  putfield android/app/Notification/contentIntent Landroid/app/PendingIntent;
  ldc "wy_ad_notification"
  astore 9
  aload 9
  invokestatic com/wiyun/ad/v/c(Ljava/lang/String;)I
  istore 19
  new android/widget/RemoteViews
  astore 24
  aload 24
  astore_1
  aload 17
  astore_2
  iload 19
  istore_3
  aload_1
  aload_2
  iload_3
  invokespecial android/widget/RemoteViews/<init>(Ljava/lang/String;I)V
  ldc "panel_image"
  astore 9
  aload 9
  invokestatic com/wiyun/ad/v/b(Ljava/lang/String;)I
  istore 19
  bipush 8
  istore 13
  aload 24
  astore_1
  iload 19
  istore_2
  aload_1
  iload_2
  iload 13
  invokevirtual android/widget/RemoteViews/setViewVisibility(II)V
  ldc "panel_event"
  astore 9
  aload 9
  invokestatic com/wiyun/ad/v/b(Ljava/lang/String;)I
  istore 19
  bipush 8
  istore 13
  aload 24
  astore_1
  iload 19
  istore_2
  aload_1
  iload_2
  iload 13
  invokevirtual android/widget/RemoteViews/setViewVisibility(II)V
  ldc "down_progress_bar"
  astore 9
  aload 9
  invokestatic com/wiyun/ad/v/b(Ljava/lang/String;)I
  istore 25
  aload_0
  astore_1
  aload_1
  getfield com/wiyun/ad/e$a/e I
  istore_1
  iload_1
  istore 19
  aload_0
  astore_1
  aload_1
  getfield com/wiyun/ad/e$a/f I
  istore_1
  iload_1
  istore 26
  iconst_0
  istore 13
  iload 13
  istore 27
  aload 24
  astore_1
  iload 25
  istore_2
  iload 19
  istore_3
  iload 26
  istore 4
  iload 27
  istore 5
  aload_1
  iload_2
  iload_3
  iload 4
  iload 5
  invokevirtual android/widget/RemoteViews/setProgressBar(IIIZ)V
  ldc "down_title"
  astore 9
  aload 9
  invokestatic com/wiyun/ad/v/b(Ljava/lang/String;)I
  istore 26
  aload 24
  astore_1
  iload 26
  istore_2
  aload_1
  iload_2
  aload 11
  invokevirtual android/widget/RemoteViews/setTextViewText(ILjava/lang/CharSequence;)V
  ldc "down_progress_info"
  astore 9
  aload 9
  invokestatic com/wiyun/ad/v/b(Ljava/lang/String;)I
  istore 26
  iconst_3
  istore 13
  iload 13
  anewarray java/lang/Object
  astore_1
  aload_1
  astore 28
  aload_0
  astore_1
  aload_1
  getfield com/wiyun/ad/e$a/f I
  istore_1
  iload_1
  istore 25
  iload_1
  invokestatic java/lang/Integer/valueOf(I)Ljava/lang/Integer;
  astore 29
  iconst_0
  istore 13
  aload 28
  iload 13
  aload 29
  aastore
  aload_0
  astore_1
  aload_1
  getfield com/wiyun/ad/e$a/e I
  istore_1
  iload_1
  istore 19
  iload_1
  invokestatic java/lang/Integer/valueOf(I)Ljava/lang/Integer;
  astore 29
  iconst_1
  istore 13
  aload 28
  iload 13
  aload 29
  aastore
  aload_0
  astore_1
  aload_1
  getfield com/wiyun/ad/e$a/e I
  istore_1
  iload_1
  istore 19
  dload_1
  invokestatic app/DummyClass/invokeIfStmt(D)V
  iload 19
  ifne Label0
Label1:
  iload 6
  invokestatic java/lang/Integer/valueOf(I)Ljava/lang/Integer;
  astore 29
  iconst_2
  istore 13
  aload 28
  iload 13
  aload 29
  aastore
  ldc "%d/%d (%d%%)"
  astore 9
  aload 28
  astore_1
  aload 9
  aload_1
  invokestatic java/lang/String/format(Ljava/lang/String;[Ljava/lang/Object;)Ljava/lang/String;
  astore 21
  aload 24
  astore_1
  iload 26
  istore_2
  aload 21
  astore_3
  aload_1
  iload_2
  aload_3
  invokevirtual android/widget/RemoteViews/setTextViewText(ILjava/lang/CharSequence;)V
  ldc "image"
  astore 9
  aload 9
  invokestatic com/wiyun/ad/v/b(Ljava/lang/String;)I
  istore 26
  ldc "icon"
  astore 9
  aload 9
  invokestatic com/wiyun/ad/v/a(Ljava/lang/String;)I
  istore 25
  aload 24
  astore_1
  iload 26
  istore_2
  iload 25
  istore_3
  aload_1
  iload_2
  iload_3
  invokevirtual android/widget/RemoteViews/setImageViewResource(II)V
  aload 24
  astore_1
  aload 18
  astore_2
  aload_2
  aload_1
  putfield android/app/Notification/contentView Landroid/widget/RemoteViews;
  aload_0
  astore_1
  aload_1
  getfield com/wiyun/ad/e$a/a Lcom/wiyun/ad/e;
  astore 14
  aload 14
  invokevirtual com/wiyun/ad/e/getContext()Landroid/content/Context;
  astore 15
  ldc "notification"
  astore 9
  aload 15
  aload 9
  invokevirtual android/content/Context/getSystemService(Ljava/lang/String;)Ljava/lang/Object;
  astore 30
  aload 30
  astore 32
  aload 32
  checkcast android/app/NotificationManager
  astore 32
  aload 32
  astore 31
  aload_0
  astore_1
  aload_1
  getfield com/wiyun/ad/e$a/a Lcom/wiyun/ad/e;
  astore 14
  aload 14
  invokestatic com/wiyun/ad/e/c(Lcom/wiyun/ad/e;)Lcom/wiyun/ad/AdView;
  astore 33
  aload 33
  astore_1
  aload_1
  invokevirtual java/lang/Object/hashCode()I
  istore 26
  aload 31
  astore_1
  iload 26
  istore_2
  aload 18
  astore_3
  aload_1
  iload_2
  aload_3
  invokevirtual android/app/NotificationManager/notify(ILandroid/app/Notification;)V
  return
Label0:
  aload_0
  astore_1
  aload_1
  getfield com/wiyun/ad/e$a/f I
  istore_1
  iload_1
  istore 19
  iload 19
  bipush 100
  imul
  istore 19
  aload_0
  astore_1
  aload_1
  getfield com/wiyun/ad/e$a/e I
  istore 6
  iload 19
  iload 6
  idiv
  istore 6
  goto Label1
  nop
.end <method>

.method private c()V
.limit locals 9
.limit stack 200
  nop
  aload_0
  getfield com/wiyun/ad/e$a/a Lcom/wiyun/ad/e;
  astore_1
  new java/lang/NoClassDefFoundError
  dup
  invokespecial java/lang/NoClassDefFoundError/<init>()V
  athrow
  nop
  ldc "notification"
  astore 4
  aload_2
  aload 4
  invokevirtual android/content/Context/getSystemService(Ljava/lang/String;)Ljava/lang/Object;
  astore_3
  aload_3
  astore 6
  aload 6
  checkcast android/app/NotificationManager
  astore 6
  aload 6
  astore 5
  aload_0
  getfield com/wiyun/ad/e$a/a Lcom/wiyun/ad/e;
  astore_1
  aload_1
  invokestatic com/wiyun/ad/e/c(Lcom/wiyun/ad/e;)Lcom/wiyun/ad/AdView;
  astore 7
  aload 7
  invokevirtual java/lang/Object/hashCode()I
  istore 8
  aload 5
  iload 8
  invokevirtual android/app/NotificationManager/cancel(I)V
  return
  nop
.end <method>

.method public run()V
.limit locals 33
.limit stack 200
  nop
  aload_0
  astore_1
  aload_1
  invokespecial com/wiyun/ad/e$a/a()Lorg/apache/http/impl/client/DefaultHttpClient;
  astore_3
  new java/lang/NoClassDefFoundError
  dup
  invokespecial java/lang/NoClassDefFoundError/<init>()V
  athrow
Label11:
  aload_0
  astore_1
  aload_1
  getfield com/wiyun/ad/e$a/b Ljava/lang/String;
  astore 5
  aload 5
  invokestatic com/wiyun/ad/x/c(Ljava/lang/String;)Ljava/lang/String;
  astore 5
  aload 4
  aload 5
  invokespecial org/apache/http/client/methods/HttpGet/<init>(Ljava/lang/String;)V
  aload_3
  aload 4
  invokevirtual org/apache/http/impl/client/DefaultHttpClient/execute(Lorg/apache/http/client/methods/HttpUriRequest;)Lorg/apache/http/HttpResponse;
  astore 6
  aload 6
  invokeinterface org/apache/http/HttpResponse/getStatusLine()Lorg/apache/http/StatusLine; 1
  astore 7
  aload 7
  invokeinterface org/apache/http/StatusLine/getStatusCode()I 1
  istore 8
  dload 8
  invokestatic app/DummyClass/invokeIfStmt(D)V
  sipush 300
  istore 9
  iload 8
  iload 9
  if_icmpge Label0
  ldc "Content-Length"
  astore 11
  aload 6
  aload 11
  invokeinterface org/apache/http/HttpResponse/getFirstHeader(Ljava/lang/String;)Lorg/apache/http/Header; 2
  astore 10
  aload 10
  invokestatic app/DummyClass/invokeIfStmt(Ljava/lang/Object;)V
  aload 10
  ifnull Label1
  aload 10
  invokeinterface org/apache/http/Header/getValue()Ljava/lang/String; 1
  astore 5
  aload 5
  invokestatic com/wiyun/ad/x/d(Ljava/lang/String;)I
  istore 8
  aload_0
  astore_1
  aload_1
  iload 8
  putfield com/wiyun/ad/e$a/e I
  aload_0
  astore_1
  aload_1
  getfield com/wiyun/ad/e$a/a Lcom/wiyun/ad/e;
  astore 12
  aload 12
  invokevirtual com/wiyun/ad/e/getContext()Landroid/content/Context;
  astore 13
  aload 13
  astore 15
  aload 15
  checkcast android/app/Activity
  astore 15
  aload 15
  astore 14
  aload_0
  astore_1
  aload_1
  getfield com/wiyun/ad/e$a/a Lcom/wiyun/ad/e;
  astore 12
  aload_0
  astore_1
  aload_1
  getfield com/wiyun/ad/e$a/c Ljava/lang/String;
  astore 5
  aload 12
  aload 5
  invokestatic com/wiyun/ad/e/a(Lcom/wiyun/ad/e;Ljava/lang/String;)Ljava/io/File;
  astore 16
  aload 16
  invokestatic app/DummyClass/invokeIfStmt(Ljava/lang/Object;)V
  aload 16
  ifnonnull Label2
  new com/wiyun/ad/e$a$5
  astore 17
  aload 17
  astore_1
  aload_0
  astore_2
  aload_1
  aload_2
  invokespecial com/wiyun/ad/e$a$5/<init>(Lcom/wiyun/ad/e$a;)V
  aload 17
  astore_1
  aload 14
  aload_1
  invokevirtual android/app/Activity/runOnUiThread(Ljava/lang/Runnable;)V
Label12:
  aload_3
  invokestatic app/DummyClass/invokeIfStmt(Ljava/lang/Object;)V
  iload_3
  ifeq Label3
  aload_3
  invokevirtual org/apache/http/impl/client/DefaultHttpClient/getConnectionManager()Lorg/apache/http/conn/ClientConnectionManager;
  astore 18
  aload 18
  astore_1
  aload_1
  invokeinterface org/apache/http/conn/ClientConnectionManager/shutdown()V 1
Label3:
  aload_0
  astore_1
  aload_1
  invokespecial com/wiyun/ad/e$a/c()V
Label6:
  return
Label2:
  aload_0
  astore_1
  aload_1
  invokespecial com/wiyun/ad/e$a/b()V
  aload_0
  astore_1
  aload_1
  aload 6
  aload 16
  invokespecial com/wiyun/ad/e$a/a(Lorg/apache/http/HttpResponse;Ljava/io/File;)Z
  istore 19
  iload 19
  istore_1
  iload_1
  invokestatic app/DummyClass/invokeIfStmt(Z)V
  iload 19
  ifeq Label4
  new com/wiyun/ad/e$a$1
  astore 20
  aload 20
  astore_1
  aload_0
  astore_2
  aload_1
  aload_2
  invokespecial com/wiyun/ad/e$a$1/<init>(Lcom/wiyun/ad/e$a;)V
  aload 20
  astore_1
  aload 14
  aload_1
  invokevirtual android/app/Activity/runOnUiThread(Ljava/lang/Runnable;)V
  aload_0
  astore_1
  aload_1
  invokespecial com/wiyun/ad/e$a/c()V
  new android/os/Message
  astore 21
  aload 21
  astore_1
  aload_1
  invokespecial android/os/Message/<init>()V
  iconst_3
  istore 9
  aload 21
  astore_1
  aload_1
  iload 9
  putfield android/os/Message/what I
  aload_0
  astore_1
  aload_1
  getfield com/wiyun/ad/e$a/d Landroid/os/Handler;
  astore_1
  aload_1
  astore 22
  aload 22
  astore_1
  aload 21
  astore_2
  aload_1
  aload_2
  invokevirtual android/os/Handler/sendMessage(Landroid/os/Message;)Z
  pop
  new android/content/Intent
  astore 23
  ldc "android.intent.action.VIEW"
  astore 11
  aload 23
  astore_1
  aload_1
  aload 11
  invokespecial android/content/Intent/<init>(Ljava/lang/String;)V
  aload 16
  invokestatic android/net/Uri/fromFile(Ljava/io/File;)Landroid/net/Uri;
  astore 24
  ldc "application/vnd.android.package-archive"
  astore 11
  aload 23
  astore_1
  aload 24
  astore_2
  aload_1
  aload_2
  aload 11
  invokevirtual android/content/Intent/setDataAndType(Landroid/net/Uri;Ljava/lang/String;)Landroid/content/Intent;
  pop
  aload_0
  astore_1
  aload_1
  getfield com/wiyun/ad/e$a/a Lcom/wiyun/ad/e;
  astore 12
  aload 12
  invokevirtual com/wiyun/ad/e/getContext()Landroid/content/Context;
  astore 13
  aload 23
  astore_1
  aload 13
  aload_1
  invokevirtual android/content/Context/startActivity(Landroid/content/Intent;)V
  new com/wiyun/ad/e$a$2
  astore 25
  aload 25
  astore_1
  aload_0
  astore_2
  aload_1
  aload_2
  invokespecial com/wiyun/ad/e$a$2/<init>(Lcom/wiyun/ad/e$a;)V
  aload 25
  astore_1
  aload_1
  invokevirtual com/wiyun/ad/e$a$2/start()V
Label1:
  aload_3
  invokestatic app/DummyClass/invokeIfStmt(Ljava/lang/Object;)V
  iload_3
  ifeq Label5
  aload_3
  invokevirtual org/apache/http/impl/client/DefaultHttpClient/getConnectionManager()Lorg/apache/http/conn/ClientConnectionManager;
  astore 18
  aload 18
  astore_1
  aload_1
  invokeinterface org/apache/http/conn/ClientConnectionManager/shutdown()V 1
Label5:
  aload_0
  astore_1
  aload_1
  invokespecial com/wiyun/ad/e$a/c()V
  goto Label6
Label4:
  new com/wiyun/ad/e$a$3
  astore 26
Label13:
  aload 26
  astore_1
  aload_0
  astore_2
  aload_1
  aload_2
  invokespecial com/wiyun/ad/e$a$3/<init>(Lcom/wiyun/ad/e$a;)V
  aload 26
  astore_1
  aload 14
  aload_1
  invokevirtual android/app/Activity/runOnUiThread(Ljava/lang/Runnable;)V
Label14:
  goto Label1
Label10:
  astore 27
Label15:
  new java/lang/StringBuilder
  astore 28
  ldc "failed to download apk: "
  astore 11
  aload 28
  astore_1
  aload_1
  aload 11
  invokespecial java/lang/StringBuilder/<init>(Ljava/lang/String;)V
  aload_0
  astore_1
  aload_1
  getfield com/wiyun/ad/e$a/c Ljava/lang/String;
  astore_1
  aload_1
  astore 29
  aload 28
  astore_1
  aload 29
  astore_2
  aload_1
  aload_2
  invokevirtual java/lang/StringBuilder/append(Ljava/lang/String;)Ljava/lang/StringBuilder;
  astore 28
  aload 28
  astore_1
  aload_1
  invokevirtual java/lang/StringBuilder/toString()Ljava/lang/String;
  astore 29
  ldc "WiYun"
  astore 11
  aload 29
  astore_1
  aload 11
  aload_1
  invokestatic com/wiyun/ad/s/c(Ljava/lang/String;Ljava/lang/String;)V
  aload_0
  astore_1
  aload_1
  getfield com/wiyun/ad/e$a/a Lcom/wiyun/ad/e;
  astore 12
  aload 12
  invokevirtual com/wiyun/ad/e/getContext()Landroid/content/Context;
  astore 13
  aload 13
  astore 30
  aload 30
  checkcast android/app/Activity
  astore 30
  aload 30
  astore 14
  new com/wiyun/ad/e$a$4
  astore 31
  aload 31
  astore_1
  aload_0
  astore_2
  aload_1
  aload_2
  invokespecial com/wiyun/ad/e$a$4/<init>(Lcom/wiyun/ad/e$a;)V
  aload 31
  astore_1
  aload 14
  aload_1
  invokevirtual android/app/Activity/runOnUiThread(Ljava/lang/Runnable;)V
Label16:
  aload_3
  invokestatic app/DummyClass/invokeIfStmt(Ljava/lang/Object;)V
  iload_3
  ifeq Label7
  aload_3
  invokevirtual org/apache/http/impl/client/DefaultHttpClient/getConnectionManager()Lorg/apache/http/conn/ClientConnectionManager;
  astore 18
  aload 18
  astore_1
  aload_1
  invokeinterface org/apache/http/conn/ClientConnectionManager/shutdown()V 1
Label7:
  aload_0
  astore_1
  aload_1
  invokespecial com/wiyun/ad/e$a/c()V
  goto Label6
Label0:
  new java/lang/StringBuilder
  astore 28
Label17:
  ldc "failed to download, statuscode is "
  astore 11
  aload 28
  astore_1
  aload_1
  aload 11
  invokespecial java/lang/StringBuilder/<init>(Ljava/lang/String;)V
  aload 28
  astore_1
  aload_1
  iload 8
  invokevirtual java/lang/StringBuilder/append(I)Ljava/lang/StringBuilder;
  astore 28
  aload 28
  astore_1
  aload_1
  invokevirtual java/lang/StringBuilder/toString()Ljava/lang/String;
  astore 5
  ldc "WiYun"
  astore 11
  aload 11
  aload 5
  invokestatic com/wiyun/ad/s/c(Ljava/lang/String;Ljava/lang/String;)V
Label18:
  goto Label1
Label9:
  astore 32
  aload_3
  invokestatic app/DummyClass/invokeIfStmt(Ljava/lang/Object;)V
  iload_3
  ifeq Label8
  aload_3
  invokevirtual org/apache/http/impl/client/DefaultHttpClient/getConnectionManager()Lorg/apache/http/conn/ClientConnectionManager;
  astore 18
  aload 18
  astore_1
  aload_1
  invokeinterface org/apache/http/conn/ClientConnectionManager/shutdown()V 1
Label8:
  aload_0
  astore_1
  aload_1
  invokespecial com/wiyun/ad/e$a/c()V
  aload 32
  athrow
  nop
.end <method>

