.source SourceFile
.class final  com/adwo/adsdk/O
.super java/lang/Object
.implements  java/lang/Runnable
.field private "a" Lcom/adwo/adsdk/N;
.field private final "b" Lcom/adwo/adsdk/k;
.field private final "c" Lcom/adwo/adsdk/b;
.field private final "d" I
.field private final "e" Z
.field private final "f" Landroid/content/Context;

.method <init>(Lcom/adwo/adsdk/N;Lcom/adwo/adsdk/k;Lcom/adwo/adsdk/b;IZLandroid/content/Context;)V
.limit locals 7
.limit stack 200
  nop
  aload_0
  aload_1
  putfield com/adwo/adsdk/O/a Lcom/adwo/adsdk/N;
  aload_0
  aload_2
  putfield com/adwo/adsdk/O/b Lcom/adwo/adsdk/k;
  aload_0
  aload_3
  putfield com/adwo/adsdk/O/c Lcom/adwo/adsdk/b;
  aload_0
  iload 4
  putfield com/adwo/adsdk/O/d I
  aload_0
  iload 5
  putfield com/adwo/adsdk/O/e Z
  aload_0
  aload 6
  putfield com/adwo/adsdk/O/f Landroid/content/Context;
  aload_0
  invokespecial java/lang/Object/<init>()V
  return
  nop
.end <method>

.method public final run()V
.limit locals 29
.limit stack 200
  .catch  java/lang/Throwable <from> Label16 <to> Label11 <using> Label14
  .catch  java/lang/Exception <from> Label16 <to> Label11 <using> Label15
  .catch  java/lang/Throwable <from> Label2 <to> Label17 <using> Label14
  .catch  java/lang/Exception <from> Label2 <to> Label17 <using> Label15
  .catch  java/lang/Throwable <from> Label18 <to> Label19 <using> Label14
  .catch  java/lang/Throwable <from> Label0 <to> Label20 <using> Label14
  .catch  java/lang/Exception <from> Label0 <to> Label20 <using> Label15
  .catch  java/lang/Throwable <from> Label10 <to> Label21 <using> Label14
  .catch  java/lang/Exception <from> Label10 <to> Label21 <using> Label15
  nop
  iconst_0
  istore_3
Label16:
  aload_0
  astore_1
  aload_1
  getfield com/adwo/adsdk/O/b Lcom/adwo/adsdk/k;
  astore 4
  aload 4
  invokevirtual com/adwo/adsdk/k/c()Ljava/lang/String;
  astore 5
  new java/lang/NoClassDefFoundError
  dup
  invokespecial java/lang/NoClassDefFoundError/<init>()V
  athrow
  iload 5
  ifeq Label0
  aload_0
  astore_1
  aload_1
  getfield com/adwo/adsdk/O/b Lcom/adwo/adsdk/k;
  astore 4
  aload 4
  invokevirtual com/adwo/adsdk/k/a()Ljava/lang/String;
  astore 5
  aload 5
  invokestatic app/DummyClass/invokeIfStmt(Ljava/lang/Object;)V
  aload 5
  ifnull Label0
  aload_0
  astore_1
  aload_1
  getfield com/adwo/adsdk/O/a Lcom/adwo/adsdk/N;
  astore 6
  aload 6
  invokestatic com/adwo/adsdk/N/a(Lcom/adwo/adsdk/N;)Lcom/adwo/adsdk/AdwoAdView;
  astore 7
  aload_0
  astore_1
  aload_1
  getfield com/adwo/adsdk/O/c Lcom/adwo/adsdk/b;
  astore 8
  aload 7
  aload 8
  invokevirtual com/adwo/adsdk/AdwoAdView/addView(Landroid/view/View;)V
  aload_0
  astore_1
  aload_1
  getfield com/adwo/adsdk/O/a Lcom/adwo/adsdk/N;
  astore 6
  aload 6
  invokestatic com/adwo/adsdk/N/a(Lcom/adwo/adsdk/N;)Lcom/adwo/adsdk/AdwoAdView;
  astore 7
  iconst_4
  istore 9
  aload 7
  iload 9
  invokevirtual com/adwo/adsdk/AdwoAdView/setVisibility(I)V
  new com/adwo/adsdk/ab
  astore 10
  aload_0
  astore_1
  aload_1
  getfield com/adwo/adsdk/O/c Lcom/adwo/adsdk/b;
  astore 8
  aload_0
  astore_1
  aload_1
  getfield com/adwo/adsdk/O/a Lcom/adwo/adsdk/N;
  astore 6
  aload 6
  invokestatic com/adwo/adsdk/N/a(Lcom/adwo/adsdk/N;)Lcom/adwo/adsdk/AdwoAdView;
  astore 7
  aload 10
  aload 8
  aload 7
  invokespecial com/adwo/adsdk/ab/<init>(Landroid/view/View;Lcom/adwo/adsdk/AdwoAdView;)V
  aload_0
  astore_1
  aload_1
  getfield com/adwo/adsdk/O/b Lcom/adwo/adsdk/k;
  astore 4
  aload 4
  invokevirtual com/adwo/adsdk/k/a()Ljava/lang/String;
  astore 5
  aload 10
  getfield com/adwo/adsdk/ab/e Landroid/webkit/WebView;
  astore 11
  aload 11
  invokestatic app/DummyClass/invokeIfStmt(Ljava/lang/Object;)V
  aload 11
  ifnull Label1
  aload 10
  getfield com/adwo/adsdk/ab/e Landroid/webkit/WebView;
  astore 11
  aload 11
  aload 5
  invokevirtual android/webkit/WebView/loadUrl(Ljava/lang/String;)V
Label1:
  iconst_2
  istore 9
  iload 9
  newarray int
  astore 12
  aload_0
  astore_1
  aload_1
  getfield com/adwo/adsdk/O/a Lcom/adwo/adsdk/N;
  astore 6
  aload 6
  invokestatic com/adwo/adsdk/N/a(Lcom/adwo/adsdk/N;)Lcom/adwo/adsdk/AdwoAdView;
  astore 7
  aload 7
  aload 12
  invokevirtual com/adwo/adsdk/AdwoAdView/getLocationOnScreen([I)V
  iconst_1
  istore 9
  aload 12
  iload 9
  iaload
  istore 13
  iload 13
  i2f
  fstore 14
  aload_0
  astore_1
  aload_1
  getfield com/adwo/adsdk/O/a Lcom/adwo/adsdk/N;
  astore 6
  aload 6
  invokestatic com/adwo/adsdk/N/a(Lcom/adwo/adsdk/N;)Lcom/adwo/adsdk/AdwoAdView;
  astore 7
  aload 7
  invokestatic com/adwo/adsdk/AdwoAdView/e(Lcom/adwo/adsdk/AdwoAdView;)F
  fstore 15
  fconst_2
  fstore 16
  fload 15
  fload 16
  fdiv
  fstore 15
  fload 14
  fload 15
  fcmpg
  istore 17
  iload 17
  istore_1
  dload_1
  invokestatic app/DummyClass/invokeIfStmt(D)V
  iload 17
  ifgt Label2
  iconst_1
  istore 9
  aload 10
  iload 9
  invokevirtual com/adwo/adsdk/ab/a(Z)V
Label7:
  aload_0
  astore_1
  aload_1
  getfield com/adwo/adsdk/O/a Lcom/adwo/adsdk/N;
  astore 6
  aload 6
  invokestatic com/adwo/adsdk/N/a(Lcom/adwo/adsdk/N;)Lcom/adwo/adsdk/AdwoAdView;
  astore 7
  aload 10
  aload 7
  putfield com/adwo/adsdk/ab/f Lcom/adwo/adsdk/a;
Label11:
  aload_0
  astore_1
  aload_1
  getfield com/adwo/adsdk/O/a Lcom/adwo/adsdk/N;
  astore 6
  aload 6
  invokestatic com/adwo/adsdk/N/a(Lcom/adwo/adsdk/N;)Lcom/adwo/adsdk/AdwoAdView;
  astore 7
  iconst_0
  istore 9
  iload 9
  istore 18
  iload 18
  istore_1
  aload 7
  iload_1
  putfield com/adwo/adsdk/AdwoAdView/a Z
Label8:
  aload_0
  astore_1
  aload_1
  getfield com/adwo/adsdk/O/b Lcom/adwo/adsdk/k;
  astore 4
  aload 4
  getfield com/adwo/adsdk/k/j Ljava/util/List;
  astore_1
  aload_1
  astore 19
  aload 19
  astore_1
  aload_1
  invokestatic app/DummyClass/invokeIfStmt(Ljava/lang/Object;)V
  aload 19
  ifnull Label3
  aload_0
  astore_1
  aload_1
  getfield com/adwo/adsdk/O/b Lcom/adwo/adsdk/k;
  astore 4
  aload 4
  getfield com/adwo/adsdk/k/j Ljava/util/List;
  astore_1
  aload_1
  astore 19
  aload 19
  astore_1
  aload_1
  invokeinterface java/util/List/size()I 1
  istore 13
  dload 13
  invokestatic app/DummyClass/invokeIfStmt(D)V
  iload 13
  ifeq Label3
Label12:
  dload_3
  invokestatic app/DummyClass/invokeIfStmt(D)V
  dload 13
  invokestatic app/DummyClass/invokeIfStmt(D)V
  iload_3
  iload 13
  if_icmplt Label4
Label3:
  aload_0
  astore_1
  aload_1
  getfield com/adwo/adsdk/O/b Lcom/adwo/adsdk/k;
  astore 4
  aload 4
  getfield com/adwo/adsdk/k/k Ljava/util/List;
  astore_1
  aload_1
  astore 19
  aload 19
  astore_1
  aload_1
  invokestatic app/DummyClass/invokeIfStmt(Ljava/lang/Object;)V
  aload 19
  ifnull Label5
  aload_0
  astore_1
  aload_1
  getfield com/adwo/adsdk/O/b Lcom/adwo/adsdk/k;
  astore 4
  aload 4
  getfield com/adwo/adsdk/k/k Ljava/util/List;
  astore_1
  aload_1
  astore 19
  aload 19
  astore_1
  aload_1
  invokeinterface java/util/List/size()I 1
  istore 13
  dload 13
  invokestatic app/DummyClass/invokeIfStmt(D)V
  iload 13
  ifle Label5
  aload_0
  astore_1
  aload_1
  getfield com/adwo/adsdk/O/b Lcom/adwo/adsdk/k;
  astore 4
  aload 4
  getfield com/adwo/adsdk/k/k Ljava/util/List;
  astore_1
  aload_1
  astore 19
  aload 19
  astore_1
  aload_1
  invokeinterface java/util/List/iterator()Ljava/util/Iterator; 1
  astore 20
Label13:
  aload 20
  astore_1
  aload_1
  invokeinterface java/util/Iterator/hasNext()Z 1
  istore 18
  iload 18
  istore_1
  iload_1
  invokestatic app/DummyClass/invokeIfStmt(Z)V
  iload 18
  ifne Label6
Label5:
  return
Label2:
  iconst_0
  istore 9
  aload 10
  iload 9
  invokevirtual com/adwo/adsdk/ab/a(Z)V
Label17:
  goto Label7
Label15:
  astore 21
Label18:
  aload 21
  astore_1
  aload_1
  invokevirtual java/lang/Exception/toString()Ljava/lang/String;
  astore 22
  ldc "Adwo SDK"
  astore 23
  aload 23
  astore_1
  aload 22
  astore_2
  new java/lang/NoClassDefFoundError
  dup
  invokespecial java/lang/NoClassDefFoundError/<init>()V
  athrow
  aload 21
  astore_1
  aload_1
  invokevirtual java/lang/Exception/printStackTrace()V
Label19:
  aload_0
  astore_1
  aload_1
  getfield com/adwo/adsdk/O/a Lcom/adwo/adsdk/N;
  astore 6
  aload 6
  invokestatic com/adwo/adsdk/N/a(Lcom/adwo/adsdk/N;)Lcom/adwo/adsdk/AdwoAdView;
  astore 7
  iconst_0
  istore 9
  iload 9
  istore 18
  iload 18
  istore_1
  aload 7
  iload_1
  putfield com/adwo/adsdk/AdwoAdView/a Z
  goto Label8
Label0:
  aload_0
  astore_1
  aload_1
  getfield com/adwo/adsdk/O/a Lcom/adwo/adsdk/N;
  astore 6
  aload 6
  invokestatic com/adwo/adsdk/N/a(Lcom/adwo/adsdk/N;)Lcom/adwo/adsdk/AdwoAdView;
  astore 7
  aload_0
  astore_1
  aload_1
  getfield com/adwo/adsdk/O/c Lcom/adwo/adsdk/b;
  astore 8
  aload 7
  aload 8
  invokevirtual com/adwo/adsdk/AdwoAdView/addView(Landroid/view/View;)V
  aload_0
  astore_1
  aload_1
  getfield com/adwo/adsdk/O/d I
  istore 13
  dload 13
  invokestatic app/DummyClass/invokeIfStmt(D)V
  iload 13
  ifne Label9
  aload_0
  astore_1
  aload_1
  getfield com/adwo/adsdk/O/e Z
  istore_1
  iload_1
  istore 18
  iload_1
  invokestatic app/DummyClass/invokeIfStmt(Z)V
  iload 18
  ifeq Label10
  aload_0
  astore_1
  aload_1
  getfield com/adwo/adsdk/O/a Lcom/adwo/adsdk/N;
  astore 6
  aload 6
  invokestatic com/adwo/adsdk/N/a(Lcom/adwo/adsdk/N;)Lcom/adwo/adsdk/AdwoAdView;
  astore 7
  aload_0
  astore_1
  aload_1
  getfield com/adwo/adsdk/O/c Lcom/adwo/adsdk/b;
  astore 8
  aload 7
  aload 8
  invokestatic com/adwo/adsdk/AdwoAdView/b(Lcom/adwo/adsdk/AdwoAdView;Lcom/adwo/adsdk/b;)V
Label20:
  goto Label11
Label14:
  astore 24
  aload_0
  astore_1
  aload_1
  getfield com/adwo/adsdk/O/a Lcom/adwo/adsdk/N;
  astore 6
  new java/lang/NoClassDefFoundError
  dup
  invokespecial java/lang/NoClassDefFoundError/<init>()V
  athrow
  nop
  iconst_0
  istore 9
  iload 9
  istore 18
  iload 18
  istore_1
  aload 7
  iload_1
  putfield com/adwo/adsdk/AdwoAdView/a Z
  aload 24
  athrow
Label10:
  aload_0
  astore_1
  aload_1
  getfield com/adwo/adsdk/O/a Lcom/adwo/adsdk/N;
  astore 6
  aload 6
  invokestatic com/adwo/adsdk/N/a(Lcom/adwo/adsdk/N;)Lcom/adwo/adsdk/AdwoAdView;
  astore 7
  aload_0
  astore_1
  aload_1
  getfield com/adwo/adsdk/O/c Lcom/adwo/adsdk/b;
  astore 8
  aload 7
  aload 8
  invokestatic com/adwo/adsdk/AdwoAdView/c(Lcom/adwo/adsdk/AdwoAdView;Lcom/adwo/adsdk/b;)V
  goto Label11
Label9:
  aload_0
  astore_1
  aload_1
  getfield com/adwo/adsdk/O/a Lcom/adwo/adsdk/N;
  astore 6
  aload 6
  invokestatic com/adwo/adsdk/N/a(Lcom/adwo/adsdk/N;)Lcom/adwo/adsdk/AdwoAdView;
  astore 7
  aload_0
  astore_1
  aload_1
  getfield com/adwo/adsdk/O/c Lcom/adwo/adsdk/b;
  astore 8
  aload 7
  aload 8
  invokestatic com/adwo/adsdk/AdwoAdView/a(Lcom/adwo/adsdk/AdwoAdView;Lcom/adwo/adsdk/b;)V
Label21:
  goto Label11
Label4:
  aload_0
  astore_1
  aload_1
  getfield com/adwo/adsdk/O/b Lcom/adwo/adsdk/k;
  astore 4
  aload 4
  getfield com/adwo/adsdk/k/j Ljava/util/List;
  astore_1
  aload_1
  astore 19
  aload 19
  astore_1
  aload_1
  iload_3
  invokeinterface java/util/List/get(I)Ljava/lang/Object; 2
  astore 25
  aload 25
  astore 26
  aload 26
  checkcast java/lang/String
  astore 26
  aload 26
  astore 22
  aload 22
  astore_1
  aload_1
  invokestatic com/adwo/adsdk/p/c(Ljava/lang/String;)V
  iload_3
  iconst_1
  iadd
  istore_3
  goto Label12
Label6:
  aload 20
  astore_1
  aload_1
  invokeinterface java/util/Iterator/next()Ljava/lang/Object; 1
  astore 25
  aload 25
  astore 27
  aload 27
  checkcast java/lang/String
  astore 27
  aload 27
  astore 22
  aload_0
  astore_1
  aload_1
  getfield com/adwo/adsdk/O/a Lcom/adwo/adsdk/N;
  astore 6
  aload 6
  invokestatic com/adwo/adsdk/N/a(Lcom/adwo/adsdk/N;)Lcom/adwo/adsdk/AdwoAdView;
  pop
  aload_0
  astore_1
  aload_1
  getfield com/adwo/adsdk/O/f Landroid/content/Context;
  astore_1
  aload_1
  astore 28
  aload 28
  astore_1
  aload 22
  astore_2
  aload_1
  aload_2
  invokestatic com/adwo/adsdk/AdwoAdView/a(Landroid/content/Context;Ljava/lang/String;)Z
  istore 18
  iload 18
  istore_1
  iload_1
  invokestatic app/DummyClass/invokeIfStmt(Z)V
  iload 18
  ifeq Label13
  aload_0
  astore_1
  aload_1
  getfield com/adwo/adsdk/O/b Lcom/adwo/adsdk/k;
  astore 4
  aload 4
  getfield com/adwo/adsdk/k/b I
  istore 13
  iload 13
  putstatic com/adwo/adsdk/Y/d I
  goto Label13
  nop
.end <method>

