.source SourceFile
.class final  com/mobisage/android/R
.super java/lang/Object
.field private static "a" Lcom/mobisage/android/R;
.field private "b" Ljava/util/concurrent/ScheduledThreadPoolExecutor;
.field private "c" Ljava/util/concurrent/ConcurrentHashMap;

.method static <clinit>()V
.limit locals 1
.limit stack 200
  nop
  new com/mobisage/android/R
  astore_0
  aload_0
  invokespecial com/mobisage/android/R/<init>()V
  aload_0
  putstatic com/mobisage/android/R/a Lcom/mobisage/android/R;
  return
  nop
.end <method>

.method private <init>()V
.limit locals 4
.limit stack 200
  nop
  aload_0
  invokespecial java/lang/Object/<init>()V
  new java/util/concurrent/ScheduledThreadPoolExecutor
  astore_1
  iconst_4
  istore_2
  aload_1
  iload_2
  invokespecial java/util/concurrent/ScheduledThreadPoolExecutor/<init>(I)V
  aload_0
  aload_1
  putfield com/mobisage/android/R/b Ljava/util/concurrent/ScheduledThreadPoolExecutor;
  new java/util/concurrent/ConcurrentHashMap
  astore_3
  aload_3
  invokespecial java/util/concurrent/ConcurrentHashMap/<init>()V
  aload_0
  aload_3
  putfield com/mobisage/android/R/c Ljava/util/concurrent/ConcurrentHashMap;
  return
  nop
.end <method>

.method public static a()Lcom/mobisage/android/R;
.limit locals 1
.limit stack 200
  nop
  getstatic com/mobisage/android/R/a Lcom/mobisage/android/R;
  astore_0
  aload_0
  areturn
  nop
.end <method>

.method public final a(Lcom/mobisage/android/Q;)V
.limit locals 20
.limit stack 200
  nop
  aload_1
  astore_2
  aload_2
  getfield com/mobisage/android/Q/d Z
  istore 9
  new java/lang/NoClassDefFoundError
  dup
  invokespecial java/lang/NoClassDefFoundError/<init>()V
  athrow
  iconst_1
  istore 10
  iload 10
  iload 9
  if_icmpne Label0
  aload_0
  astore_2
  aload_2
  getfield com/mobisage/android/R/b Ljava/util/concurrent/ScheduledThreadPoolExecutor;
  astore 11
  aload_1
  astore_2
  aload_2
  getfield com/mobisage/android/Q/c J
  lstore 12
  aload_1
  astore_2
  aload_2
  getfield com/mobisage/android/Q/e J
  lstore 14
  getstatic java/util/concurrent/TimeUnit/SECONDS Ljava/util/concurrent/TimeUnit;
  astore 16
  aload 11
  astore_2
  aload_1
  astore_3
  lload 12
  lstore 4
  lload 14
  lstore 6
  aload 16
  astore 8
  aload_2
  aload_3
  lload 4
  lload 6
  aload 8
  invokevirtual java/util/concurrent/ScheduledThreadPoolExecutor/scheduleAtFixedRate(Ljava/lang/Runnable;JJLjava/util/concurrent/TimeUnit;)Ljava/util/concurrent/ScheduledFuture;
  astore 17
  aload_0
  astore_2
  aload_2
  getfield com/mobisage/android/R/c Ljava/util/concurrent/ConcurrentHashMap;
  astore_2
  aload_2
  astore 18
  aload_1
  astore_2
  aload_2
  getfield com/mobisage/android/Q/b Ljava/util/UUID;
  astore_2
  aload_2
  astore 19
  aload 18
  astore_2
  aload 19
  astore_3
  aload_2
  aload_3
  aload 17
  invokevirtual java/util/concurrent/ConcurrentHashMap/put(Ljava/lang/Object;Ljava/lang/Object;)Ljava/lang/Object;
  pop
Label1:
  return
Label0:
  aload_0
  astore_2
  aload_2
  getfield com/mobisage/android/R/b Ljava/util/concurrent/ScheduledThreadPoolExecutor;
  astore 11
  aload_1
  astore_2
  aload_2
  getfield com/mobisage/android/Q/c J
  lstore 14
  getstatic java/util/concurrent/TimeUnit/SECONDS Ljava/util/concurrent/TimeUnit;
  astore 16
  aload_1
  astore_2
  aload 11
  aload_2
  lload 14
  aload 16
  invokevirtual java/util/concurrent/ScheduledThreadPoolExecutor/schedule(Ljava/lang/Runnable;JLjava/util/concurrent/TimeUnit;)Ljava/util/concurrent/ScheduledFuture;
  astore 17
  aload_0
  astore_2
  aload_2
  getfield com/mobisage/android/R/c Ljava/util/concurrent/ConcurrentHashMap;
  astore_2
  aload_2
  astore 18
  aload_1
  astore_2
  aload_2
  getfield com/mobisage/android/Q/b Ljava/util/UUID;
  astore_2
  aload_2
  astore 19
  aload 18
  astore_2
  aload 19
  astore_3
  aload_2
  aload_3
  aload 17
  invokevirtual java/util/concurrent/ConcurrentHashMap/put(Ljava/lang/Object;Ljava/lang/Object;)Ljava/lang/Object;
  pop
  goto Label1
  nop
.end <method>

.method public final b(Lcom/mobisage/android/Q;)V
.limit locals 9
.limit stack 200
  nop
  aload_0
  getfield com/mobisage/android/R/c Ljava/util/concurrent/ConcurrentHashMap;
  astore_2
  aload_1
  getfield com/mobisage/android/Q/b Ljava/util/UUID;
  astore_3
  aload_2
  aload_3
  invokevirtual java/util/concurrent/ConcurrentHashMap/containsKey(Ljava/lang/Object;)Z
  istore 4
  new java/lang/NoClassDefFoundError
  dup
  invokespecial java/lang/NoClassDefFoundError/<init>()V
  athrow
  iload 4
  ifne Label0
Label1:
  return
Label0:
  aload_0
  getfield com/mobisage/android/R/c Ljava/util/concurrent/ConcurrentHashMap;
  astore_2
  aload_1
  getfield com/mobisage/android/Q/b Ljava/util/UUID;
  astore_3
  aload_2
  aload_3
  invokevirtual java/util/concurrent/ConcurrentHashMap/get(Ljava/lang/Object;)Ljava/lang/Object;
  astore 5
  aload 5
  astore 7
  aload 7
  checkcast java/util/concurrent/ScheduledFuture
  astore 7
  aload 7
  astore 6
  iconst_1
  istore 8
  aload 6
  iload 8
  invokeinterface java/util/concurrent/ScheduledFuture/cancel(Z)Z 2
  pop
  aload_0
  getfield com/mobisage/android/R/c Ljava/util/concurrent/ConcurrentHashMap;
  astore_2
  aload_1
  getfield com/mobisage/android/Q/b Ljava/util/UUID;
  astore_3
  aload_2
  aload_3
  invokevirtual java/util/concurrent/ConcurrentHashMap/remove(Ljava/lang/Object;)Ljava/lang/Object;
  pop
  goto Label1
  nop
.end <method>

