.source InMobiSourceAdapter.java
.class  com/admogo/adapters/InMobiSourceAdapter$FetchInmobiADRunnable
.super java/lang/Object
.implements  java/lang/Runnable
.field private "inmobiSourceAdapter" Lcom/admogo/adapters/InMobiSourceAdapter;
.field private "ration" Lcom/admogo/obj/Ration;

.method public <init>(Lcom/admogo/obj/Ration;Lcom/admogo/adapters/InMobiSourceAdapter;)V
.limit locals 3
.limit stack 200
  nop
  aload_0
  invokespecial java/lang/Object/<init>()V
  aload_0
  aload_1
  putfield com/admogo/adapters/InMobiSourceAdapter$FetchInmobiADRunnable/ration Lcom/admogo/obj/Ration;
  aload_0
  aload_2
  putfield com/admogo/adapters/InMobiSourceAdapter$FetchInmobiADRunnable/inmobiSourceAdapter Lcom/admogo/adapters/InMobiSourceAdapter;
  return
  nop
.end <method>

.method public run()V
.limit locals 13
.limit stack 200
  nop
  aload_0
  getfield com/admogo/adapters/InMobiSourceAdapter$FetchInmobiADRunnable/inmobiSourceAdapter Lcom/admogo/adapters/InMobiSourceAdapter;
  astore_1
  aload_1
  getfield com/admogo/adapters/AdMogoAdapter/adMogoLayoutReference Ljava/lang/ref/WeakReference;
  astore_2
  aload_2
  invokevirtual java/lang/ref/WeakReference/get()Ljava/lang/Object;
  astore_3
  aload_3
  astore 5
  new java/lang/NoClassDefFoundError
  dup
  invokespecial java/lang/NoClassDefFoundError/<init>()V
  athrow
  aload 5
  astore 4
  aload 4
  invokestatic app/DummyClass/invokeIfStmt(Ljava/lang/Object;)V
  iload 4
  ifne Label0
Label2:
  return
Label0:
  aload_0
  getfield com/admogo/adapters/InMobiSourceAdapter$FetchInmobiADRunnable/ration Lcom/admogo/obj/Ration;
  astore 6
  aload 6
  getfield com/admogo/obj/Ration/key Ljava/lang/String;
  astore 7
  aload 4
  aload 7
  invokestatic com/admogo/adapters/InMobiSourceAdapter/access$0(Lcom/admogo/AdMogoLayout;Ljava/lang/String;)Lcom/admogo/obj/InmobiAD;
  astore 8
  aload 8
  invokestatic com/admogo/adapters/InMobiSourceAdapter/access$1(Lcom/admogo/obj/InmobiAD;)V
  invokestatic com/admogo/adapters/InMobiSourceAdapter/access$2()Lcom/admogo/obj/InmobiAD;
  astore 8
  aload 8
  invokestatic app/DummyClass/invokeIfStmt(Ljava/lang/Object;)V
  aload 8
  ifnonnull Label1
  getstatic com/admogo/util/AdMogoUtil/ADMOGO Ljava/lang/String;
  astore 9
  ldc "get INMOBIAD fail InmobiAd is null"
  astore 10
  aload 9
  aload 10
  invokestatic android/util/Log/w(Ljava/lang/String;Ljava/lang/String;)I
  pop
  aload 4
  invokevirtual com/admogo/AdMogoLayout/rollover()V
  goto Label2
Label1:
  aload 4
  getfield com/admogo/AdMogoLayout/handler Landroid/os/Handler;
  astore 11
  new com/admogo/adapters/InMobiSourceAdapter$DisplayInmobiADRunnable
  astore 12
  aload_0
  getfield com/admogo/adapters/InMobiSourceAdapter$FetchInmobiADRunnable/inmobiSourceAdapter Lcom/admogo/adapters/InMobiSourceAdapter;
  astore_1
  aload 12
  aload_1
  invokespecial com/admogo/adapters/InMobiSourceAdapter$DisplayInmobiADRunnable/<init>(Lcom/admogo/adapters/InMobiSourceAdapter;)V
  aload 11
  aload 12
  invokevirtual android/os/Handler/post(Ljava/lang/Runnable;)Z
  pop
  goto Label2
  nop
.end <method>

