.source SourceFile
.class final  com/mobisage/android/u$a
.super java/lang/Object
.implements  com/mobisage/android/IMobiSageMessageCallback
.field private "a" Lcom/mobisage/android/u;

.method private <init>(Lcom/mobisage/android/u;)V
.limit locals 2
.limit stack 200
  nop
  aload_0
  aload_1
  putfield com/mobisage/android/u$a/a Lcom/mobisage/android/u;
  aload_0
  invokespecial java/lang/Object/<init>()V
  return
  nop
.end <method>

.method <init>(Lcom/mobisage/android/u;B)V
  .synthetic
.limit locals 3
.limit stack 200
  nop
  aload_0
  aload_1
  invokespecial com/mobisage/android/u$a/<init>(Lcom/mobisage/android/u;)V
  return
  nop
.end <method>

.method public final onMobiSageMessageFinish(Lcom/mobisage/android/MobiSageMessage;)V
.limit locals 6
.limit stack 200
  nop
  aload_0
  getfield com/mobisage/android/u$a/a Lcom/mobisage/android/u;
  astore_2
  aload_2
  getfield com/mobisage/android/O/a Landroid/os/Handler;
  astore_3
  aload_0
  getfield com/mobisage/android/u$a/a Lcom/mobisage/android/u;
  astore_2
  aload_2
  getfield com/mobisage/android/O/c I
  istore 4
  new java/lang/NoClassDefFoundError
  dup
  invokespecial java/lang/NoClassDefFoundError/<init>()V
  athrow
  nop
  aload 5
  aload_1
  putfield android/os/Message/obj Ljava/lang/Object;
  aload 5
  invokevirtual android/os/Message/sendToTarget()V
  return
  nop
.end <method>

