.source SourceFile
.class public abstract  com/mobisage/android/MobiSageURIUtility
.super java/lang/Object

.method public <init>()V
.limit locals 1
.limit stack 200
  nop
  aload_0
  invokespecial java/lang/Object/<init>()V
  return
  nop
.end <method>

.method public static parserURIQuery(Ljava/lang/String;)Ljava/util/HashMap;
  .signature_attr "(Ljava/lang/String;)Ljava/util/HashMap<Ljava/lang/String;Ljava/lang/String;>;"
.limit locals 9
.limit stack 200
  nop
  new java/util/HashMap
  astore_1
  aload_1
  invokespecial java/util/HashMap/<init>()V
  new java/lang/StringBuilder
  astore_2
  aload_2
  invokespecial java/lang/StringBuilder/<init>()V
  iconst_0
  istore_3
  iconst_0
  istore 4
Label5:
  aload_0
  invokevirtual java/lang/String/length()I
  istore 5
  new java/lang/NoClassDefFoundError
  dup
  invokespecial java/lang/NoClassDefFoundError/<init>()V
  athrow
  dload 5
  invokestatic app/DummyClass/invokeIfStmt(D)V
  iload_3
  iload 5
  if_icmpge Label0
  aload_0
  iload_3
  invokevirtual java/lang/String/charAt(I)C
  istore 6
  dload 6
  invokestatic app/DummyClass/invokeIfStmt(D)V
  iload 6
  lookupswitch
  38 : Label2
  61 : Label3
  default : Label1
Label1:
  goto Label4
Label4:
  aload_2
  iload 6
  invokevirtual java/lang/StringBuilder/append(C)Ljava/lang/StringBuilder;
  pop
Label6:
  iload_3
  iconst_1
  iadd
  istore_3
  goto Label5
Label3:
  aload_2
  invokevirtual java/lang/StringBuilder/toString()Ljava/lang/String;
  astore 4
  aload_2
  invokevirtual java/lang/StringBuilder/length()I
  istore 5
  iconst_0
  istore 7
  aload_2
  iload 7
  iload 5
  invokevirtual java/lang/StringBuilder/delete(II)Ljava/lang/StringBuilder;
  pop
  goto Label6
Label2:
  aload_2
  invokevirtual java/lang/StringBuilder/toString()Ljava/lang/String;
  astore 8
  aload 8
  invokestatic java/net/URLDecoder/decode(Ljava/lang/String;)Ljava/lang/String;
  astore 8
  aload_1
  aload 4
  aload 8
  invokevirtual java/util/HashMap/put(Ljava/lang/Object;Ljava/lang/Object;)Ljava/lang/Object;
  pop
  aload_2
  invokevirtual java/lang/StringBuilder/length()I
  istore 5
  iconst_0
  istore 7
  aload_2
  iload 7
  iload 5
  invokevirtual java/lang/StringBuilder/delete(II)Ljava/lang/StringBuilder;
  pop
  iconst_0
  istore 4
  goto Label6
Label0:
  aload_2
  invokevirtual java/lang/StringBuilder/length()I
  istore 5
  dload 5
  invokestatic app/DummyClass/invokeIfStmt(D)V
  iload 5
  ifeq Label7
  aload 4
  invokestatic app/DummyClass/invokeIfStmt(Ljava/lang/Object;)V
  iload 4
  ifeq Label7
  aload_2
  invokevirtual java/lang/StringBuilder/toString()Ljava/lang/String;
  astore 8
  aload 8
  invokestatic java/net/URLDecoder/decode(Ljava/lang/String;)Ljava/lang/String;
  astore 8
  aload_1
  aload 4
  aload 8
  invokevirtual java/util/HashMap/put(Ljava/lang/Object;Ljava/lang/Object;)Ljava/lang/Object;
  pop
Label7:
  aload_1
  areturn
  nop
  nop
  nop
.end <method>

