.source SourceFile
.class final  com/adwo/adsdk/e
.super java/lang/Thread
.field private "a" Lcom/adwo/adsdk/d;

.method <init>(Lcom/adwo/adsdk/d;)V
.limit locals 2
.limit stack 200
  nop
  aload_0
  aload_1
  putfield com/adwo/adsdk/e/a Lcom/adwo/adsdk/d;
  aload_0
  invokespecial java/lang/Thread/<init>()V
  return
  nop
.end <method>

.method public final run()V
.limit locals 5
.limit stack 200
  nop
  aload_0
  getfield com/adwo/adsdk/e/a Lcom/adwo/adsdk/d;
  astore_1
  new java/lang/NoClassDefFoundError
  dup
  invokespecial java/lang/NoClassDefFoundError/<init>()V
  athrow
  nop
  aload_2
  getfield com/adwo/adsdk/b/a Lcom/adwo/adsdk/k;
  astore_3
  aload_3
  invokevirtual com/adwo/adsdk/k/b()V
  aload_0
  getfield com/adwo/adsdk/e/a Lcom/adwo/adsdk/d;
  astore_1
  aload_1
  invokestatic com/adwo/adsdk/d/a(Lcom/adwo/adsdk/d;)Lcom/adwo/adsdk/b;
  astore_2
  iconst_0
  istore 4
  aload_2
  iload 4
  invokestatic com/adwo/adsdk/b/a(Lcom/adwo/adsdk/b;Z)V
  return
  nop
.end <method>

