.source AdMogoManager.java
.class public  com/admogo/AdMogoManager
.super java/lang/Object
.field private static final "GETINFO_TIMEOUT_TIME" I =  10000
.field private static final "PREFS_STRING_CONFIG" Ljava/lang/String; =  "config"
.field private static "PREFS_STRING_COUNTRY" Ljava/lang/String;
.field private static final "PREFS_STRING_GETINFOTIME" Ljava/lang/String; =  "getInfoTime"
.field private static final "PREFS_STRING_TEMPCONFIG" Ljava/lang/String; =  "tempConfig"
.field private static final "PREFS_STRING_TIMESTAMP" Ljava/lang/String; =  "timestamp"
.field private static final "SENDDATA_TIMEOUT_TIME" I =  20000
.field private static "URL_INDEX" I =  0
.field private static "URL_INDEXARRAY" [I
.field private static "cityName" Ljava/lang/String;
.field private static "configExpireTimeout" J =  0
.field private static "ipAddress" Ljava/lang/String;
.field public static "isSendData" Z =  0
.field public static "isSendLocation" Z =  0
.field public static "lastRation" Lcom/admogo/obj/Ration;
.field public static "pngSize" I =  0
.field public static "tempConfig" Ljava/util/Hashtable;
.field public static "testMode" I =  0
.field private "GetInfoRunnable" Ljava/lang/Runnable;
.field private "SendDataRunnable" Ljava/lang/Runnable;
.field private "adFirstRation" Lcom/admogo/obj/Ration;
.field private "adType" I
.field private "contextReference" Ljava/lang/ref/WeakReference;
.field private "cpuInfo" Ljava/lang/String;
.field public "deviceIDHash" Ljava/lang/String;
.field public "deviceName" Ljava/lang/String;
.field private "expressMode" Z
.field private "extra" Lcom/admogo/obj/Extra;
.field private "fillRListEmpty" Z
.field public "fillRationsList" Ljava/util/List;
.field private "getCountryCode" Ljava/lang/String;
.field public "height" I
.field public "ifGetInfo" Z
.field private "isFillRationList" Z
.field public "isGetInfo" Z
.field public "keyAdMogo" Ljava/lang/String;
.field private "latitude" D
.field private "longitude" D
.field private "memoryInfo" Ljava/lang/String;
.field private "networkType" Ljava/lang/String;
.field private "operInfo" Ljava/lang/String;
.field public "os" Ljava/lang/String;
.field private "packageName" Ljava/lang/String;
.field private "randomRation" Lcom/admogo/obj/Ration;
.field public "rationsList" Ljava/util/List;
.field "rollovers" Ljava/util/Iterator;
.field public final "scheduler" Ljava/util/concurrent/ScheduledExecutorService;
.field private "screenSize" Ljava/lang/String;
.field private "searchURL" Ljava/lang/Runnable;
.field private "tempRationsList" Ljava/util/List;
.field private "totalWeight" D
.field private "versionCode" I
.field private "versionName" Ljava/lang/String;
.field public "width" I

.method static <clinit>()V
.limit locals 7
.limit stack 200
  nop
  new java/util/Hashtable
  astore_0
  aload_0
  invokespecial java/util/Hashtable/<init>()V
  aload_0
  putstatic com/admogo/AdMogoManager/tempConfig Ljava/util/Hashtable;
  ldc2_w 1800000
  lstore_1
  lload_1
  putstatic com/admogo/AdMogoManager/configExpireTimeout J
  iconst_0
  istore_3
  iload_3
  putstatic com/admogo/AdMogoManager/isSendLocation Z
  iconst_0
  istore_3
  iload_3
  putstatic com/admogo/AdMogoManager/isSendData Z
  iconst_0
  istore_3
  iload_3
  istore 4
  iload 4
  putstatic com/admogo/AdMogoManager/URL_INDEX I
  iconst_4
  istore_3
  iload_3
  newarray int
  astore 5
  aload 5
  putstatic com/admogo/AdMogoManager/URL_INDEXARRAY [I
  iconst_0
  istore_3
  iload_3
  istore 4
  iload 4
  putstatic com/admogo/AdMogoManager/pngSize I
  ldc ""
  astore 6
  aload 6
  putstatic com/admogo/AdMogoManager/cityName Ljava/lang/String;
  ldc "cn"
  astore 6
  aload 6
  putstatic com/admogo/AdMogoManager/PREFS_STRING_COUNTRY Ljava/lang/String;
  iconst_0
  istore_3
  iload_3
  istore 4
  iload 4
  putstatic com/admogo/AdMogoManager/testMode I
  return
  nop
.end <method>

.method public <init>(Ljava/lang/ref/WeakReference;Ljava/lang/String;IZ)V
  .signature_attr "(Ljava/lang/ref/WeakReference<Landroid/content/Context;>;Ljava/lang/String;IZ)V"
.limit locals 64
.limit stack 200
  nop
  aload_0
  astore 5
  aload 5
  invokespecial java/lang/Object/<init>()V
  iconst_0
  istore 11
  aload_0
  astore 5
  aload 5
  iload 11
  putfield com/admogo/AdMogoManager/isFillRationList Z
  iconst_0
  istore 11
  aload_0
  astore 5
  aload 5
  iload 11
  putfield com/admogo/AdMogoManager/fillRListEmpty Z
  new java/util/ArrayList
  astore 12
  aload 12
  invokespecial java/util/ArrayList/<init>()V
  aload_0
  astore 5
  aload 5
  aload 12
  putfield com/admogo/AdMogoManager/tempRationsList Ljava/util/List;
  ldc2_w 0.000000000000000
  dstore 13
  aload_0
  astore 5
  aload 5
  dload 13
  putfield com/admogo/AdMogoManager/totalWeight D
  iconst_0
  istore 11
  aload_0
  astore 5
  aload 5
  iload 11
  putfield com/admogo/AdMogoManager/isGetInfo Z
  iconst_0
  istore 11
  aload_0
  astore 5
  aload 5
  iload 11
  putfield com/admogo/AdMogoManager/ifGetInfo Z
  iconst_1
  istore 11
  iload 11
  invokestatic java/util/concurrent/Executors/newScheduledThreadPool(I)Ljava/util/concurrent/ScheduledExecutorService;
  astore 15
  aload_0
  astore 5
  aload 5
  aload 15
  putfield com/admogo/AdMogoManager/scheduler Ljava/util/concurrent/ScheduledExecutorService;
  new com/admogo/AdMogoManager$1
  astore 16
  aload_0
  astore 5
  aload 16
  aload 5
  invokespecial com/admogo/AdMogoManager$1/<init>(Lcom/admogo/AdMogoManager;)V
  aload_0
  astore 5
  aload 5
  aload 16
  putfield com/admogo/AdMogoManager/GetInfoRunnable Ljava/lang/Runnable;
  new com/admogo/AdMogoManager$2
  astore 17
  aload_0
  astore 5
  aload 17
  aload 5
  invokespecial com/admogo/AdMogoManager$2/<init>(Lcom/admogo/AdMogoManager;)V
  aload_0
  astore 5
  aload 5
  aload 17
  putfield com/admogo/AdMogoManager/SendDataRunnable Ljava/lang/Runnable;
  new com/admogo/AdMogoManager$3
  astore 18
  aload_0
  astore 5
  aload 18
  aload 5
  invokespecial com/admogo/AdMogoManager$3/<init>(Lcom/admogo/AdMogoManager;)V
  aload_0
  astore 5
  aload 5
  aload 18
  putfield com/admogo/AdMogoManager/searchURL Ljava/lang/Runnable;
  getstatic com/admogo/util/AdMogoUtil/ADMOGO Ljava/lang/String;
  astore 19
  ldc "Creating adMogoManager..."
  astore 20
  new java/lang/NoClassDefFoundError
  dup
  invokespecial java/lang/NoClassDefFoundError/<init>()V
  athrow
  aload_1
  astore 5
  aload_0
  astore 6
  aload 6
  aload 5
  putfield com/admogo/AdMogoManager/contextReference Ljava/lang/ref/WeakReference;
  aload_2
  astore 5
  aload_0
  astore 6
  aload 6
  aload 5
  putfield com/admogo/AdMogoManager/keyAdMogo Ljava/lang/String;
  iload_3
  istore 5
  aload_0
  astore 6
  aload 6
  iload 5
  putfield com/admogo/AdMogoManager/adType I
  iload 4
  istore 5
  aload_0
  astore 6
  aload 6
  iload 5
  putfield com/admogo/AdMogoManager/expressMode Z
  aload_1
  astore 5
  aload 5
  invokevirtual java/lang/ref/WeakReference/get()Ljava/lang/Object;
  astore 21
  aload 21
  astore 23
  aload 23
  checkcast android/content/Context
  astore 23
  aload 23
  astore 22
  ldc "window"
  astore 20
  aload 22
  astore 5
  aload 5
  aload 20
  invokevirtual android/content/Context/getSystemService(Ljava/lang/String;)Ljava/lang/Object;
  astore 21
  aload 21
  astore 25
  aload 25
  checkcast android/view/WindowManager
  astore 25
  aload 25
  astore 24
  aload 24
  astore 5
  aload 5
  invokeinterface android/view/WindowManager/getDefaultDisplay()Landroid/view/Display; 1
  astore 26
  aload 26
  astore 5
  aload 5
  invokevirtual android/view/Display/getWidth()I
  istore 27
  iload 27
  istore 5
  aload_0
  astore 6
  aload 6
  iload 5
  putfield com/admogo/AdMogoManager/width I
  aload 24
  astore 5
  aload 5
  invokeinterface android/view/WindowManager/getDefaultDisplay()Landroid/view/Display; 1
  astore 26
  aload 26
  astore 5
  aload 5
  invokevirtual android/view/Display/getHeight()I
  istore 27
  iload 27
  istore 5
  aload_0
  astore 6
  aload 6
  iload 5
  putfield com/admogo/AdMogoManager/height I
  new java/util/Random
  astore 28
  aload 28
  astore 5
  aload 5
  invokespecial java/util/Random/<init>()V
  aload 28
  astore 5
  aload 5
  invokevirtual java/util/Random/nextDouble()D
  dstore 29
  ldc2_w 3.000000000000000
  dstore 13
  dload 29
  dstore 5
  dload 5
  dload 13
  dmul
  dstore 5
  dload 5
  dstore 29
  dload 29
  dstore 5
  dload 5
  d2i
  istore 5
  iload 5
  istore 27
  getstatic com/admogo/AdMogoManager/URL_INDEXARRAY [I
  astore 31
  iconst_0
  istore 11
  aload 31
  iload 11
  iload 27
  iastore
  iconst_1
  istore_3
Label8:
  iload_3
  istore 5
  dload 5
  invokestatic app/DummyClass/invokeIfStmt(D)V
  iconst_4
  istore 11
  iload_3
  istore 5
  iload 5
  iload 11
  if_icmplt Label0
  getstatic com/admogo/AdMogoManager/testMode I
  istore 27
  getstatic com/admogo/AdMogoManager/URL_INDEXARRAY [I
  astore 31
  iconst_0
  istore 11
  aload 31
  iload 11
  iaload
  istore_3
  iload 27
  istore 5
  iload_3
  istore 6
  iload 5
  iload 6
  invokestatic com/admogo/util/AdMogoUtil/changeURL(II)V
  aload_0
  astore 5
  aload 5
  getfield com/admogo/AdMogoManager/width I
  istore 5
  iload 5
  istore 27
  aload_0
  astore 5
  aload 5
  getfield com/admogo/AdMogoManager/height I
  istore 5
  iload 5
  istore_3
  iload 27
  istore 5
  dload 5
  invokestatic app/DummyClass/invokeIfStmt(D)V
  iload_3
  istore 5
  dload 5
  invokestatic app/DummyClass/invokeIfStmt(D)V
  iload 27
  istore 5
  iload_3
  istore 6
  iload 5
  iload 6
  if_icmple Label1
  new java/lang/StringBuilder
  astore 32
  aload_0
  astore 5
  aload 5
  getfield com/admogo/AdMogoManager/height I
  istore 5
  iload 5
  istore 27
  iload 5
  invokestatic java/lang/String/valueOf(I)Ljava/lang/String;
  astore 33
  aload 32
  astore 5
  aload 33
  astore 6
  aload 5
  aload 6
  invokespecial java/lang/StringBuilder/<init>(Ljava/lang/String;)V
  ldc "*"
  astore 20
  aload 32
  astore 5
  aload 5
  aload 20
  invokevirtual java/lang/StringBuilder/append(Ljava/lang/String;)Ljava/lang/StringBuilder;
  astore 32
  aload_0
  astore 5
  aload 5
  getfield com/admogo/AdMogoManager/width I
  istore 5
  iload 5
  istore 27
  aload 32
  astore 5
  iload 27
  istore 6
  aload 5
  iload 6
  invokevirtual java/lang/StringBuilder/append(I)Ljava/lang/StringBuilder;
  astore 32
  aload 32
  astore 5
  aload 5
  invokevirtual java/lang/StringBuilder/toString()Ljava/lang/String;
  astore 33
  aload 33
  astore 5
  aload_0
  astore 6
  aload 6
  aload 5
  putfield com/admogo/AdMogoManager/screenSize Ljava/lang/String;
  aload_0
  astore 5
  aload 5
  getfield com/admogo/AdMogoManager/height I
  istore 5
  iload 5
  istore 27
  dload 5
  invokestatic app/DummyClass/invokeIfStmt(D)V
  iload 27
  lookupswitch
  240 : Label3
  320 : Label4
  480 : Label5
  default : Label2
Label2:
  goto Label6
Label6:
  iconst_0
  istore 11
  iload 11
  putstatic com/admogo/AdMogoManager/pngSize I
Label9:
  aload_1
  astore 5
  aload 5
  invokevirtual java/lang/ref/WeakReference/get()Ljava/lang/Object;
  astore 21
  aload 21
  astore 34
  aload 34
  checkcast android/content/Context
  astore 34
  aload 34
  astore 22
  ldc "wifi"
  astore 20
  aload 22
  astore 5
  aload 5
  aload 20
  invokevirtual android/content/Context/getSystemService(Ljava/lang/String;)Ljava/lang/Object;
  astore 21
  aload 21
  astore 36
  aload 36
  checkcast android/net/wifi/WifiManager
  astore 36
  aload 36
  astore 35
  new org/apache/http/impl/client/DefaultHttpClient
  astore 37
  aload 37
  astore 5
  aload 5
  invokespecial org/apache/http/impl/client/DefaultHttpClient/<init>()V
Label19:
  aload 35
  astore 5
  aload 5
  invokevirtual android/net/wifi/WifiManager/isWifiEnabled()Z
  istore 38
  iload 38
  istore 5
  iload 5
  invokestatic app/DummyClass/invokeIfStmt(Z)V
  iload 38
  ifne Label7
  ldc "content://telephony/carriers/preferapn"
  astore 20
  aload 20
  invokestatic android/net/Uri/parse(Ljava/lang/String;)Landroid/net/Uri;
  astore 39
  aload_1
  astore 5
  aload 5
  invokevirtual java/lang/ref/WeakReference/get()Ljava/lang/Object;
  astore 21
  aload 21
  astore 40
  aload 40
  checkcast android/content/Context
  astore 40
  aload 40
  astore 22
  aload 22
  astore 5
  aload 5
  invokevirtual android/content/Context/getContentResolver()Landroid/content/ContentResolver;
  astore 41
  aconst_null
  astore 43
  aconst_null
  astore 44
  aconst_null
  astore 45
  aconst_null
  astore 46
  aload 41
  astore 5
  aload 39
  astore 6
  aload 43
  astore 7
  aload 44
  astore 8
  aload 45
  astore 9
  aload 46
  astore 10
  aload 5
  aload 6
  aload 7
  aload 8
  aload 9
  aload 10
  invokevirtual android/content/ContentResolver/query(Landroid/net/Uri;[Ljava/lang/String;Ljava/lang/String;[Ljava/lang/String;Ljava/lang/String;)Landroid/database/Cursor;
  astore 42
  aload 42
  astore 5
  aload 5
  invokestatic app/DummyClass/invokeIfStmt(Ljava/lang/Object;)V
  aload 42
  ifnull Label7
  aload 42
  astore 5
  aload 5
  invokeinterface android/database/Cursor/moveToNext()Z 1
  pop
  ldc "proxy"
  astore 20
  aload 42
  astore 5
  aload 5
  aload 20
  invokeinterface android/database/Cursor/getColumnIndex(Ljava/lang/String;)I 2
  istore 27
  aload 42
  astore 5
  iload 27
  istore 6
  aload 5
  iload 6
  invokeinterface android/database/Cursor/getString(I)Ljava/lang/String; 2
  astore_2
  aload_2
  astore 5
  aload 5
  invokestatic app/DummyClass/invokeIfStmt(Ljava/lang/Object;)V
  aload_2
  ifnull Label7
  aload_2
  astore 5
  aload 5
  invokevirtual java/lang/String/trim()Ljava/lang/String;
  astore 33
  aload 33
  astore 5
  aload 5
  invokevirtual java/lang/String/length()I
  istore 27
  iload 27
  istore 5
  dload 5
  invokestatic app/DummyClass/invokeIfStmt(D)V
  iload 27
  ifle Label7
  new org/apache/http/HttpHost
  astore 47
  bipush 80
  istore 11
  aload 47
  astore 5
  aload_2
  astore 6
  aload 5
  aload 6
  iload 11
  invokespecial org/apache/http/HttpHost/<init>(Ljava/lang/String;I)V
  aload 37
  astore 5
  aload 5
  invokeinterface org/apache/http/client/HttpClient/getParams()Lorg/apache/http/params/HttpParams; 1
  astore 48
  ldc "http.route.default-proxy"
  astore 20
  aload 48
  astore 5
  aload 47
  astore 6
  aload 5
  aload 20
  aload 6
  invokeinterface org/apache/http/params/HttpParams/setParameter(Ljava/lang/String;Ljava/lang/Object;)Lorg/apache/http/params/HttpParams; 3
  pop
Label7:
  aload_1
  astore 5
  aload 5
  invokevirtual java/lang/ref/WeakReference/get()Ljava/lang/Object;
  astore 21
  aload 21
  astore 49
  aload 49
  checkcast android/content/Context
  astore 49
  aload 49
  astore 22
  aload 22
  astore 5
  aload 5
  invokevirtual android/content/Context/getPackageName()Ljava/lang/String;
  astore 33
  aload 33
  astore 5
  aload_0
  astore 6
  aload 6
  aload 5
  putfield com/admogo/AdMogoManager/packageName Ljava/lang/String;
Label21:
  aload_1
  astore 5
  aload 5
  invokevirtual java/lang/ref/WeakReference/get()Ljava/lang/Object;
  astore 21
  aload 21
  astore 50
  aload 50
  checkcast android/content/Context
  astore 50
  aload 50
  astore 22
  aload 22
  astore 5
  aload 5
  invokevirtual android/content/Context/getPackageManager()Landroid/content/pm/PackageManager;
  astore 51
  aload_0
  astore 5
  aload 5
  getfield com/admogo/AdMogoManager/packageName Ljava/lang/String;
  astore 5
  aload 5
  astore 33
  iconst_0
  istore 11
  aload 51
  astore 5
  aload 33
  astore 6
  aload 5
  aload 6
  iload 11
  invokevirtual android/content/pm/PackageManager/getPackageInfo(Ljava/lang/String;I)Landroid/content/pm/PackageInfo;
  astore 52
  aload 52
  astore 5
  aload 5
  getfield android/content/pm/PackageInfo/versionName Ljava/lang/String;
  astore 5
  aload 5
  astore 33
  ldc " "
  astore 20
  ldc "%20"
  astore 53
  aload 33
  astore 5
  aload 53
  astore 6
  aload 5
  aload 20
  aload 6
  invokevirtual java/lang/String/replace(Ljava/lang/CharSequence;Ljava/lang/CharSequence;)Ljava/lang/String;
  astore 33
Label22:
  aload 33
  astore 5
  aload_0
  astore 6
  aload 6
  aload 5
  putfield com/admogo/AdMogoManager/versionName Ljava/lang/String;
Label15:
  aload_1
  astore 5
  aload 5
  invokevirtual java/lang/ref/WeakReference/get()Ljava/lang/Object;
  astore 21
  aload 21
  astore 54
  aload 54
  checkcast android/content/Context
  astore 54
  aload 54
  astore 22
  aload 22
  astore 5
  aload 5
  invokevirtual android/content/Context/getPackageManager()Landroid/content/pm/PackageManager;
  astore 51
  aload_0
  astore 5
  aload 5
  getfield com/admogo/AdMogoManager/packageName Ljava/lang/String;
  astore 5
  aload 5
  astore 33
  iconst_0
  istore 11
  aload 51
  astore 5
  aload 33
  astore 6
  aload 5
  aload 6
  iload 11
  invokevirtual android/content/pm/PackageManager/getPackageInfo(Ljava/lang/String;I)Landroid/content/pm/PackageInfo;
  astore 52
Label24:
  aload 52
  astore 5
  aload 5
  getfield android/content/pm/PackageInfo/versionCode I
  istore 5
  iload 5
  istore 27
  aload_0
  astore 6
  aload 6
  iload 5
  putfield com/admogo/AdMogoManager/versionCode I
Label16:
  aload_1
  astore 5
  aload 5
  invokevirtual java/lang/ref/WeakReference/get()Ljava/lang/Object;
  astore 21
  aload 21
  astore 55
  aload 55
  checkcast android/content/Context
  astore 55
  aload 55
  astore 22
  aload 22
  astore 5
  aload 5
  invokestatic com/admogo/GetUserInfo/getNetworkType(Landroid/content/Context;)Ljava/lang/String;
  astore 33
  aload 33
  astore 5
  aload_0
  astore 6
  aload 6
  aload 5
  putfield com/admogo/AdMogoManager/networkType Ljava/lang/String;
  aload_1
  astore 5
  aload 5
  invokevirtual java/lang/ref/WeakReference/get()Ljava/lang/Object;
  astore 21
  aload 21
  astore 56
  aload 56
  checkcast android/content/Context
  astore 56
  aload 56
  astore 22
  aload 22
  astore 5
  aload 5
  invokestatic com/admogo/GetUserInfo/getOperators(Landroid/content/Context;)Ljava/lang/String;
  astore 33
  aload 33
  astore 5
  aload_0
  astore 6
  aload 6
  aload 5
  putfield com/admogo/AdMogoManager/operInfo Ljava/lang/String;
  invokestatic com/admogo/GetUserInfo/GetCPUInfo()Ljava/lang/String;
  astore 33
  aload 33
  astore 5
  aload_0
  astore 6
  aload 6
  aload 5
  putfield com/admogo/AdMogoManager/cpuInfo Ljava/lang/String;
  aload_1
  astore 5
  aload 5
  invokevirtual java/lang/ref/WeakReference/get()Ljava/lang/Object;
  astore 21
  aload 21
  astore 57
  aload 57
  checkcast android/content/Context
  astore 57
  aload 57
  astore 22
  aload 22
  astore 5
  aload 5
  invokestatic com/admogo/GetUserInfo/getMemoryInfo(Landroid/content/Context;)Ljava/lang/String;
  astore 33
  aload 33
  astore 5
  aload_0
  astore 6
  aload 6
  aload 5
  putfield com/admogo/AdMogoManager/memoryInfo Ljava/lang/String;
Label17:
  aload_1
  astore 5
  aload 5
  invokevirtual java/lang/ref/WeakReference/get()Ljava/lang/Object;
  astore 21
  aload 21
  astore 58
  aload 58
  checkcast android/content/Context
  astore 58
  aload 58
  astore 22
  aload 22
  astore 5
  aload 5
  invokestatic com/admogo/GetUserInfo/getDeviceID(Landroid/content/Context;)Ljava/lang/String;
  astore 33
  aload 33
  astore 5
  aload_0
  astore 6
  aload 6
  aload 5
  putfield com/admogo/AdMogoManager/deviceIDHash Ljava/lang/String;
  aload_0
  astore 5
  aload 5
  getfield com/admogo/AdMogoManager/deviceIDHash Ljava/lang/String;
  astore 5
  aload 5
  astore 33
  aload 33
  astore 5
  aload 5
  invokestatic com/admogo/util/AdMogoUtil/convertToHex(Ljava/lang/String;)Ljava/lang/String;
  astore 33
  aload 33
  astore 5
  aload_0
  astore 6
  aload 6
  aload 5
  putfield com/admogo/AdMogoManager/deviceIDHash Ljava/lang/String;
  getstatic android/os/Build$VERSION/RELEASE Ljava/lang/String;
  astore 33
  aload 33
  astore 5
  aload 5
  invokestatic java/net/URLEncoder/encode(Ljava/lang/String;)Ljava/lang/String;
  astore 33
  aload 33
  astore 5
  aload_0
  astore 6
  aload 6
  aload 5
  putfield com/admogo/AdMogoManager/os Ljava/lang/String;
  getstatic android/os/Build/MODEL Ljava/lang/String;
  astore 33
  aload 33
  astore 5
  aload 5
  invokestatic java/net/URLEncoder/encode(Ljava/lang/String;)Ljava/lang/String;
  astore 33
  aload 33
  astore 5
  aload_0
  astore 6
  aload 6
  aload 5
  putfield com/admogo/AdMogoManager/deviceName Ljava/lang/String;
  getstatic com/admogo/util/AdMogoUtil/ADMOGO Ljava/lang/String;
  astore 33
  new java/lang/StringBuilder
  astore 32
  ldc "Hashed device ID is: "
  astore 20
  aload 32
  astore 5
  aload 5
  aload 20
  invokespecial java/lang/StringBuilder/<init>(Ljava/lang/String;)V
  aload_0
  astore 5
  aload 5
  getfield com/admogo/AdMogoManager/deviceIDHash Ljava/lang/String;
  astore 19
  aload 32
  astore 5
  aload 5
  aload 19
  invokevirtual java/lang/StringBuilder/append(Ljava/lang/String;)Ljava/lang/StringBuilder;
  astore 32
  aload 32
  astore 5
  aload 5
  invokevirtual java/lang/StringBuilder/toString()Ljava/lang/String;
  astore 19
  aload 33
  astore 5
  aload 5
  aload 19
  invokestatic android/util/Log/d(Ljava/lang/String;Ljava/lang/String;)I
  pop
  getstatic com/admogo/util/AdMogoUtil/ADMOGO Ljava/lang/String;
  astore 33
  ldc "AdsMOGO SDK Version : 1.1.6"
  astore 20
  aload 33
  astore 5
  aload 5
  aload 20
  invokestatic android/util/Log/d(Ljava/lang/String;Ljava/lang/String;)I
  pop
  getstatic com/admogo/util/AdMogoUtil/ADMOGO Ljava/lang/String;
  astore 33
  ldc "Finished creating adMogoManager"
  astore 20
  aload 33
  astore 5
  aload 5
  aload 20
  invokestatic android/util/Log/i(Ljava/lang/String;Ljava/lang/String;)I
  pop
  return
Label0:
  iload 27
  iconst_1
  iadd
  istore 27
  getstatic com/admogo/AdMogoManager/URL_INDEXARRAY [I
  astore 31
  iload 27
  iconst_4
  irem
  istore 59
  aload 31
  iload_3
  iload 59
  iastore
  iload_3
  iconst_1
  iadd
  istore_3
  goto Label8
Label3:
  iconst_1
  istore 11
  iload 11
  putstatic com/admogo/AdMogoManager/pngSize I
  goto Label9
Label4:
  iconst_2
  istore 11
  iload 11
  putstatic com/admogo/AdMogoManager/pngSize I
  goto Label9
Label5:
  iconst_3
  istore 11
  iload 11
  putstatic com/admogo/AdMogoManager/pngSize I
  goto Label9
Label1:
  new java/lang/StringBuilder
  astore 32
  aload_0
  astore 5
  aload 5
  getfield com/admogo/AdMogoManager/width I
  istore 5
  iload 5
  istore 59
  iload 5
  invokestatic java/lang/String/valueOf(I)Ljava/lang/String;
  astore 33
  aload 32
  astore 5
  aload 33
  astore 6
  aload 5
  aload 6
  invokespecial java/lang/StringBuilder/<init>(Ljava/lang/String;)V
  ldc "*"
  astore 20
  aload 32
  astore 5
  aload 5
  aload 20
  invokevirtual java/lang/StringBuilder/append(Ljava/lang/String;)Ljava/lang/StringBuilder;
  astore 32
  aload_0
  astore 5
  aload 5
  getfield com/admogo/AdMogoManager/height I
  istore 5
  iload 5
  istore 59
  aload 32
  astore 5
  iload 59
  istore 6
  aload 5
  iload 6
  invokevirtual java/lang/StringBuilder/append(I)Ljava/lang/StringBuilder;
  astore 32
  aload 32
  astore 5
  aload 5
  invokevirtual java/lang/StringBuilder/toString()Ljava/lang/String;
  astore 33
  aload 33
  astore 5
  aload_0
  astore 6
  aload 6
  aload 5
  putfield com/admogo/AdMogoManager/screenSize Ljava/lang/String;
  aload_0
  astore 5
  aload 5
  getfield com/admogo/AdMogoManager/width I
  istore 5
  iload 5
  istore 59
  dload 5
  invokestatic app/DummyClass/invokeIfStmt(D)V
  iload 59
  lookupswitch
  240 : Label11
  320 : Label12
  480 : Label13
  default : Label10
Label10:
  goto Label14
Label14:
  iconst_0
  istore 11
  iload 11
  putstatic com/admogo/AdMogoManager/pngSize I
  goto Label9
Label11:
  iconst_1
  istore 11
  iload 11
  putstatic com/admogo/AdMogoManager/pngSize I
  goto Label9
Label12:
  iconst_2
  istore 11
  iload 11
  putstatic com/admogo/AdMogoManager/pngSize I
  goto Label9
Label13:
  iconst_3
  istore 11
  iload 11
  putstatic com/admogo/AdMogoManager/pngSize I
  goto Label9
Label18:
  astore 60
  getstatic com/admogo/util/AdMogoUtil/ADMOGO Ljava/lang/String;
  astore 33
  ldc "Not android.permission.ACCESS_WIFI_STATE."
  astore 20
  aload 33
  astore 5
  aload 5
  aload 20
  invokestatic android/util/Log/i(Ljava/lang/String;Ljava/lang/String;)I
  pop
  goto Label7
Label20:
  astore 61
  ldc "1.0"
  astore 20
  aload_0
  astore 5
  aload 5
  aload 20
  putfield com/admogo/AdMogoManager/versionName Ljava/lang/String;
  goto Label15
Label23:
  astore 62
  iconst_1
  istore 11
  aload_0
  astore 5
  aload 5
  iload 11
  putfield com/admogo/AdMogoManager/versionCode I
  goto Label16
Label25:
  astore 63
  aload 63
  astore 5
  aload 5
  invokevirtual java/lang/Exception/toString()Ljava/lang/String;
  astore 19
  ldc "getPhoneInfo"
  astore 20
  aload 20
  aload 19
  invokestatic android/util/Log/w(Ljava/lang/String;Ljava/lang/String;)I
  pop
  goto Label17
  nop
  nop
  nop
.end <method>

.method static access$0(Lcom/admogo/AdMogoManager;)Ljava/lang/ref/WeakReference;
  .synthetic
.limit locals 2
.limit stack 200
  nop
  aload_0
  getfield com/admogo/AdMogoManager/contextReference Ljava/lang/ref/WeakReference;
  astore_1
  aload_1
  areturn
  nop
.end <method>

.method static access$1()I
  .synthetic
.limit locals 1
.limit stack 200
  nop
  getstatic com/admogo/AdMogoManager/URL_INDEX I
  istore_0
  iload_0
  ireturn
  nop
.end <method>

.method static access$10(Lcom/admogo/AdMogoManager;)Ljava/lang/String;
  .synthetic
.limit locals 2
.limit stack 200
  nop
  aload_0
  getfield com/admogo/AdMogoManager/networkType Ljava/lang/String;
  astore_1
  aload_1
  areturn
  nop
.end <method>

.method static access$11(Lcom/admogo/AdMogoManager;)Ljava/lang/String;
  .synthetic
.limit locals 2
.limit stack 200
  nop
  aload_0
  getfield com/admogo/AdMogoManager/operInfo Ljava/lang/String;
  astore_1
  aload_1
  areturn
  nop
.end <method>

.method static access$12(Lcom/admogo/AdMogoManager;)Ljava/lang/String;
  .synthetic
.limit locals 2
.limit stack 200
  nop
  aload_0
  getfield com/admogo/AdMogoManager/screenSize Ljava/lang/String;
  astore_1
  aload_1
  areturn
  nop
.end <method>

.method static access$13(Lcom/admogo/AdMogoManager;)Ljava/lang/String;
  .synthetic
.limit locals 2
.limit stack 200
  nop
  aload_0
  getfield com/admogo/AdMogoManager/cpuInfo Ljava/lang/String;
  astore_1
  aload_1
  areturn
  nop
.end <method>

.method static access$14(Lcom/admogo/AdMogoManager;)Ljava/lang/String;
  .synthetic
.limit locals 2
.limit stack 200
  nop
  aload_0
  getfield com/admogo/AdMogoManager/memoryInfo Ljava/lang/String;
  astore_1
  aload_1
  areturn
  nop
.end <method>

.method static access$15(Lcom/admogo/AdMogoManager;)Ljava/lang/String;
  .synthetic
.limit locals 2
.limit stack 200
  nop
  aload_0
  getfield com/admogo/AdMogoManager/getCountryCode Ljava/lang/String;
  astore_1
  aload_1
  areturn
  nop
.end <method>

.method static access$16(Lcom/admogo/AdMogoManager;D)V
  .synthetic
.limit locals 3
.limit stack 200
  nop
  aload_0
  dload_1
  putfield com/admogo/AdMogoManager/latitude D
  return
  nop
.end <method>

.method static access$17(Lcom/admogo/AdMogoManager;D)V
  .synthetic
.limit locals 3
.limit stack 200
  nop
  aload_0
  dload_1
  putfield com/admogo/AdMogoManager/longitude D
  return
  nop
.end <method>

.method static access$18(Lcom/admogo/AdMogoManager;Ljava/lang/String;)Ljava/lang/String;
  .synthetic
.limit locals 2
.limit stack 200
  nop
  aload_0
  aload_1
  invokespecial com/admogo/AdMogoManager/parseCityJsonString(Ljava/lang/String;)Ljava/lang/String;
  astore_1
  aload_1
  areturn
  nop
.end <method>

.method static access$19(Ljava/lang/String;)V
  .synthetic
.limit locals 1
.limit stack 200
  nop
  aload_0
  putstatic com/admogo/AdMogoManager/cityName Ljava/lang/String;
  return
  nop
.end <method>

.method static access$2(I)V
  .synthetic
.limit locals 1
.limit stack 200
  nop
  iload_0
  putstatic com/admogo/AdMogoManager/URL_INDEX I
  return
  nop
.end <method>

.method static access$3()[I
  .synthetic
.limit locals 1
.limit stack 200
  nop
  getstatic com/admogo/AdMogoManager/URL_INDEXARRAY [I
  astore_0
  aload_0
  areturn
  nop
.end <method>

.method static access$4()Ljava/lang/String;
  .synthetic
.limit locals 1
.limit stack 200
  nop
  getstatic com/admogo/AdMogoManager/cityName Ljava/lang/String;
  astore_0
  aload_0
  areturn
  nop
.end <method>

.method static access$5(Lcom/admogo/AdMogoManager;)D
  .synthetic
.limit locals 3
.limit stack 200
  nop
  aload_0
  getfield com/admogo/AdMogoManager/latitude D
  dstore_1
  dload_1
  dreturn
  nop
.end <method>

.method static access$6(Lcom/admogo/AdMogoManager;)D
  .synthetic
.limit locals 3
.limit stack 200
  nop
  aload_0
  getfield com/admogo/AdMogoManager/longitude D
  dstore_1
  dload_1
  dreturn
  nop
.end <method>

.method static access$7(Lcom/admogo/AdMogoManager;)Ljava/lang/String;
  .synthetic
.limit locals 2
.limit stack 200
  nop
  aload_0
  getfield com/admogo/AdMogoManager/packageName Ljava/lang/String;
  astore_1
  aload_1
  areturn
  nop
.end <method>

.method static access$8(Lcom/admogo/AdMogoManager;)Ljava/lang/String;
  .synthetic
.limit locals 2
.limit stack 200
  nop
  aload_0
  getfield com/admogo/AdMogoManager/versionName Ljava/lang/String;
  astore_1
  aload_1
  areturn
  nop
.end <method>

.method static access$9(Lcom/admogo/AdMogoManager;)I
  .synthetic
.limit locals 2
.limit stack 200
  nop
  aload_0
  getfield com/admogo/AdMogoManager/versionCode I
  istore_1
  iload_1
  ireturn
  nop
.end <method>

.method public static clear()V
.limit locals 4
.limit stack 200
  nop
  getstatic com/admogo/util/AdMogoUtil/ADMOGO Ljava/lang/String;
  astore_0
  ldc "Is Cleaning"
  astore_1
  new java/lang/NoClassDefFoundError
  dup
  invokespecial java/lang/NoClassDefFoundError/<init>()V
  athrow
  ldc ""
  astore_1
  aload_1
  putstatic com/admogo/AdMogoTargeting/countryCode Ljava/lang/String;
  iconst_0
  istore_2
  iload_2
  putstatic com/admogo/AdMogoManager/isSendLocation Z
  getstatic com/admogo/AdMogoManager/tempConfig Ljava/util/Hashtable;
  astore_3
  aload_3
  invokevirtual java/util/Hashtable/clear()V
  return
  nop
.end <method>

.method public convertStreamToString(Ljava/io/InputStream;)Ljava/lang/String;
.limit locals 16
.limit stack 200
  .catch  java/lang/Throwable <from> Label1 <to> Label4 <using> Label2
  .catch  java/io/IOException <from> Label1 <to> Label4 <using> Label3
  .catch  java/lang/Throwable <from> Label8 <to> Label9 <using> Label2
  .catch  java/io/IOException <from> Label8 <to> Label9 <using> Label3
  .catch  java/lang/Throwable <from> Label10 <to> Label11 <using> Label2
  .catch  java/io/IOException <from> Label15 <to> Label16 <using> Label14
  nop
  new java/io/BufferedReader
  astore_2
  new java/io/InputStreamReader
  astore_3
  aload_3
  aload_1
  invokespecial java/io/InputStreamReader/<init>(Ljava/io/InputStream;)V
  sipush 8192
  istore 4
  aload_2
  aload_3
  iload 4
  invokespecial java/io/BufferedReader/<init>(Ljava/io/Reader;I)V
  new java/lang/StringBuilder
  astore 5
  aload 5
  invokespecial java/lang/StringBuilder/<init>()V
Label1:
  aload_2
  invokevirtual java/io/BufferedReader/readLine()Ljava/lang/String;
  astore 6
Label4:
  new java/lang/NoClassDefFoundError
  dup
  invokespecial java/lang/NoClassDefFoundError/<init>()V
  athrow
  iload 6
  ifne Label0
Label6:
  aload_1
  invokevirtual java/io/InputStream/close()V
Label7:
  aload 5
  invokevirtual java/lang/StringBuilder/toString()Ljava/lang/String;
  astore 6
  aload 6
  areturn
Label0:
  new java/lang/StringBuilder
  astore 7
Label8:
  aload 6
  invokestatic java/lang/String/valueOf(Ljava/lang/Object;)Ljava/lang/String;
  astore 6
  aload 7
  aload 6
  invokespecial java/lang/StringBuilder/<init>(Ljava/lang/String;)V
  ldc "\n"
  astore 8
  aload 7
  aload 8
  invokevirtual java/lang/StringBuilder/append(Ljava/lang/String;)Ljava/lang/StringBuilder;
  astore 7
  aload 7
  invokevirtual java/lang/StringBuilder/toString()Ljava/lang/String;
  astore 6
  aload 5
  aload 6
  invokevirtual java/lang/StringBuilder/append(Ljava/lang/String;)Ljava/lang/StringBuilder;
  pop
Label9:
  goto Label1
Label3:
  astore 9
Label10:
  getstatic com/admogo/util/AdMogoUtil/ADMOGO Ljava/lang/String;
  astore 6
  ldc "Caught IOException in convertStreamToString()"
  astore 8
  new java/lang/NoClassDefFoundError
  dup
  invokespecial java/lang/NoClassDefFoundError/<init>()V
  athrow
Label11:
  aload_1
  invokevirtual java/io/InputStream/close()V
Label13:
  aconst_null
  astore 10
  aload 10
  areturn
Label12:
  astore 11
  getstatic com/admogo/util/AdMogoUtil/ADMOGO Ljava/lang/String;
  astore 12
  ldc "Caught IOException in convertStreamToString()"
  astore 8
  aload 12
  aload 8
  aload 11
  invokestatic android/util/Log/e(Ljava/lang/String;Ljava/lang/String;Ljava/lang/Throwable;)I
  pop
  aconst_null
  astore 10
  aload 10
  areturn
Label2:
  astore 13
Label15:
  aload_1
  invokevirtual java/io/InputStream/close()V
Label16:
  aload 13
  athrow
Label14:
  astore 14
  getstatic com/admogo/util/AdMogoUtil/ADMOGO Ljava/lang/String;
  astore 12
  ldc "Caught IOException in convertStreamToString()"
  astore 8
  new java/lang/NoClassDefFoundError
  dup
  invokespecial java/lang/NoClassDefFoundError/<init>()V
  athrow
  aconst_null
  astore 10
  aload 10
  areturn
Label5:
  astore 15
  getstatic com/admogo/util/AdMogoUtil/ADMOGO Ljava/lang/String;
  astore 12
  ldc "Caught IOException in convertStreamToString()"
  astore 8
  aload 12
  aload 8
  aload 15
  invokestatic android/util/Log/e(Ljava/lang/String;Ljava/lang/String;Ljava/lang/Throwable;)I
  pop
  aconst_null
  astore 10
  aload 10
  areturn
  nop
.end <method>

.method public fetchConfig()V
.limit locals 46
.limit stack 200
  nop
  aload_0
  astore_1
  aload_1
  getfield com/admogo/AdMogoManager/contextReference Ljava/lang/ref/WeakReference;
  astore 7
  aload 7
  invokevirtual java/lang/ref/WeakReference/get()Ljava/lang/Object;
  astore 8
  aload 8
  astore 10
  new java/lang/NoClassDefFoundError
  dup
  invokespecial java/lang/NoClassDefFoundError/<init>()V
  athrow
  aload 10
  astore 9
  aload 9
  invokestatic app/DummyClass/invokeIfStmt(Ljava/lang/Object;)V
  iload 9
  ifne Label0
Label7:
  return
Label0:
  getstatic com/admogo/AdMogoManager/testMode I
  istore 11
  getstatic com/admogo/AdMogoManager/URL_INDEXARRAY [I
  astore 12
  getstatic com/admogo/AdMogoManager/URL_INDEX I
  istore 13
  aload 12
  iload 13
  iaload
  istore 13
  iload 11
  iload 13
  invokestatic com/admogo/util/AdMogoUtil/changeURL(II)V
  aload_0
  astore_1
  aload_1
  getfield com/admogo/AdMogoManager/keyAdMogo Ljava/lang/String;
  astore 14
  iconst_0
  istore 16
  aload 9
  aload 14
  iload 16
  invokevirtual android/content/Context/getSharedPreferences(Ljava/lang/String;I)Landroid/content/SharedPreferences;
  astore 15
  iconst_1
  istore 17
  ldc ""
  astore 14
  aload_0
  astore_1
  aload_1
  getfield com/admogo/AdMogoManager/expressMode Z
  istore_1
  iload_1
  istore 18
  iload_1
  invokestatic app/DummyClass/invokeIfStmt(Z)V
  iload 18
  ifne Label1
  getstatic com/admogo/AdMogoManager/URL_INDEX I
  istore 11
  dload 11
  invokestatic app/DummyClass/invokeIfStmt(D)V
  iload 11
  ifne Label1
  new java/lang/StringBuilder
  astore 19
  aload_0
  astore_1
  aload_1
  getfield com/admogo/AdMogoManager/keyAdMogo Ljava/lang/String;
  astore 14
  aload 14
  invokestatic java/lang/String/valueOf(Ljava/lang/Object;)Ljava/lang/String;
  astore 14
  aload 19
  astore_1
  aload_1
  aload 14
  invokespecial java/lang/StringBuilder/<init>(Ljava/lang/String;)V
  aload_0
  astore_1
  aload_1
  getfield com/admogo/AdMogoManager/adType I
  istore 11
  aload 19
  astore_1
  aload_1
  iload 11
  invokevirtual java/lang/StringBuilder/append(I)Ljava/lang/StringBuilder;
  astore 19
  getstatic com/admogo/AdMogoManager/PREFS_STRING_COUNTRY Ljava/lang/String;
  astore 14
  aload 19
  astore_1
  aload_1
  aload 14
  invokevirtual java/lang/StringBuilder/append(Ljava/lang/String;)Ljava/lang/StringBuilder;
  astore 19
  ldc "config"
  astore 20
  aload 19
  astore_1
  aload 20
  astore_2
  aload_1
  aload_2
  invokevirtual java/lang/StringBuilder/append(Ljava/lang/String;)Ljava/lang/StringBuilder;
  astore 19
  aload 19
  astore_1
  aload_1
  invokevirtual java/lang/StringBuilder/toString()Ljava/lang/String;
  astore 14
  ldc ""
  astore 20
  aload 20
  astore_1
  aload 15
  aload 14
  aload_1
  invokeinterface android/content/SharedPreferences/getString(Ljava/lang/String;Ljava/lang/String;)Ljava/lang/String; 3
  astore 14
Label1:
  new java/lang/StringBuilder
  astore 19
  aload_0
  astore_1
  aload_1
  getfield com/admogo/AdMogoManager/keyAdMogo Ljava/lang/String;
  astore_1
  aload_1
  astore 21
  aload 21
  astore_1
  aload_1
  invokestatic java/lang/String/valueOf(Ljava/lang/Object;)Ljava/lang/String;
  astore 21
  aload 19
  astore_1
  aload 21
  astore_2
  aload_1
  aload_2
  invokespecial java/lang/StringBuilder/<init>(Ljava/lang/String;)V
  aload_0
  astore_1
  aload_1
  getfield com/admogo/AdMogoManager/adType I
  istore 11
  aload 19
  astore_1
  aload_1
  iload 11
  invokevirtual java/lang/StringBuilder/append(I)Ljava/lang/StringBuilder;
  astore 19
  getstatic com/admogo/AdMogoManager/PREFS_STRING_COUNTRY Ljava/lang/String;
  astore 21
  aload 19
  astore_1
  aload 21
  astore_2
  aload_1
  aload_2
  invokevirtual java/lang/StringBuilder/append(Ljava/lang/String;)Ljava/lang/StringBuilder;
  astore 19
  ldc "getInfoTime"
  astore 20
  aload 19
  astore_1
  aload 20
  astore_2
  aload_1
  aload_2
  invokevirtual java/lang/StringBuilder/append(Ljava/lang/String;)Ljava/lang/StringBuilder;
  astore 19
  aload 19
  astore_1
  aload_1
  invokevirtual java/lang/StringBuilder/toString()Ljava/lang/String;
  astore 21
  aconst_null
  astore 23
  aload 21
  astore_1
  aload 23
  astore_2
  aload 15
  aload_1
  aload_2
  invokeinterface android/content/SharedPreferences/getString(Ljava/lang/String;Ljava/lang/String;)Ljava/lang/String; 3
  astore 22
  getstatic com/admogo/util/AdMogoUtil/ADMOGO Ljava/lang/String;
  astore 21
  ldc "Stored config info not present or expired, fetching fresh data"
  astore 20
  aload 21
  astore_1
  aload 20
  astore_2
  aload_1
  aload_2
  invokestatic android/util/Log/i(Ljava/lang/String;Ljava/lang/String;)I
  pop
  iconst_2
  istore 13
  aload_0
  astore_1
  aload_1
  getfield com/admogo/AdMogoManager/adType I
  istore 11
  dload 11
  invokestatic app/DummyClass/invokeIfStmt(D)V
  iconst_1
  istore 16
  iload 11
  iload 16
  if_icmpne Label2
  iconst_2
  istore 13
Label12:
  getstatic com/admogo/util/AdMogoUtil/urlConfig Ljava/lang/String;
  astore 24
  iconst_4
  istore 16
  iload 16
  anewarray java/lang/Object
  astore_1
  aload_1
  astore 25
  aload_0
  astore_1
  aload_1
  getfield com/admogo/AdMogoManager/keyAdMogo Ljava/lang/String;
  astore_1
  aload_1
  astore 21
  iconst_0
  istore 16
  aload 25
  iload 16
  aload 21
  aastore
  sipush 289
  istore 16
  iload 16
  invokestatic java/lang/Integer/valueOf(I)Ljava/lang/Integer;
  astore 26
  iconst_1
  istore 16
  aload 25
  iload 16
  aload 26
  aastore
  iload 13
  invokestatic java/lang/Integer/valueOf(I)Ljava/lang/Integer;
  astore 26
  iconst_2
  istore 16
  aload 25
  iload 16
  aload 26
  aastore
  aload_0
  astore_1
  aload_1
  getfield com/admogo/AdMogoManager/getCountryCode Ljava/lang/String;
  astore_1
  aload_1
  astore 21
  iconst_3
  istore 16
  aload 25
  iload 16
  aload 21
  aastore
  aload 24
  astore_1
  aload 25
  astore_2
  aload_1
  aload_2
  invokestatic java/lang/String/format(Ljava/lang/String;[Ljava/lang/Object;)Ljava/lang/String;
  astore 21
  aload 22
  astore_1
  aload_1
  invokestatic android/text/TextUtils/isEmpty(Ljava/lang/CharSequence;)Z
  istore 18
  iload 18
  istore_1
  iload_1
  invokestatic app/DummyClass/invokeIfStmt(Z)V
  iload 18
  ifne Label3
  new java/lang/StringBuilder
  astore 19
  aload 21
  astore_1
  aload_1
  invokestatic java/lang/String/valueOf(Ljava/lang/Object;)Ljava/lang/String;
  astore 24
  aload 19
  astore_1
  aload 24
  astore_2
  aload_1
  aload_2
  invokespecial java/lang/StringBuilder/<init>(Ljava/lang/String;)V
  ldc "&timestamp="
  astore 20
  aload 19
  astore_1
  aload 20
  astore_2
  aload_1
  aload_2
  invokevirtual java/lang/StringBuilder/append(Ljava/lang/String;)Ljava/lang/StringBuilder;
  astore 19
  ldc " "
  astore 20
  ldc "%20"
  astore 27
  aload 22
  astore_1
  aload 20
  astore_2
  aload 27
  astore_3
  aload_1
  aload_2
  aload_3
  invokevirtual java/lang/String/replace(Ljava/lang/CharSequence;Ljava/lang/CharSequence;)Ljava/lang/String;
  astore 24
  aload 19
  astore_1
  aload 24
  astore_2
  aload_1
  aload_2
  invokevirtual java/lang/StringBuilder/append(Ljava/lang/String;)Ljava/lang/StringBuilder;
  astore 19
  aload 19
  astore_1
  aload_1
  invokevirtual java/lang/StringBuilder/toString()Ljava/lang/String;
  astore 21
Label3:
  new org/apache/http/client/methods/HttpGet
  astore 28
  aload 28
  astore_1
  aload 21
  astore_2
  aload_1
  aload_2
  invokespecial org/apache/http/client/methods/HttpGet/<init>(Ljava/lang/String;)V
  new org/apache/http/params/BasicHttpParams
  astore 29
  aload 29
  astore_1
  aload_1
  invokespecial org/apache/http/params/BasicHttpParams/<init>()V
  sipush 10000
  istore 16
  aload 29
  astore_1
  aload_1
  iload 16
  invokestatic org/apache/http/params/HttpConnectionParams/setConnectionTimeout(Lorg/apache/http/params/HttpParams;I)V
  sipush 10000
  istore 16
  aload 29
  astore_1
  aload_1
  iload 16
  invokestatic org/apache/http/params/HttpConnectionParams/setSoTimeout(Lorg/apache/http/params/HttpParams;I)V
  new org/apache/http/impl/client/DefaultHttpClient
  astore 30
  aload 30
  astore_1
  aload 29
  astore_2
  aload_1
  aload_2
  invokespecial org/apache/http/impl/client/DefaultHttpClient/<init>(Lorg/apache/http/params/HttpParams;)V
Label16:
  aload 30
  astore_1
  aload 28
  astore_2
  aload_1
  aload_2
  invokevirtual org/apache/http/impl/client/DefaultHttpClient/execute(Lorg/apache/http/client/methods/HttpUriRequest;)Lorg/apache/http/HttpResponse;
  astore 31
  iconst_2
  istore 16
  iload 16
  anewarray java/lang/Object
  astore_1
  aload_1
  astore 25
  aload_0
  astore_1
  aload_1
  getfield com/admogo/AdMogoManager/keyAdMogo Ljava/lang/String;
  astore_1
  aload_1
  astore 21
  iconst_0
  istore 16
  aload 25
  iload 16
  aload 21
  aastore
  aload_0
  astore_1
  aload_1
  getfield com/admogo/AdMogoManager/getCountryCode Ljava/lang/String;
  astore_1
  aload_1
  astore 21
  iconst_1
  istore 16
  aload 25
  iload 16
  aload 21
  aastore
  ldc "Showing Config:\n Mogo_ID: %s\n CountryCode: %s"
  astore 20
  aload 20
  astore_1
  aload 25
  astore_2
  aload_1
  aload_2
  invokestatic java/lang/String/format(Ljava/lang/String;[Ljava/lang/Object;)Ljava/lang/String;
  astore 22
  getstatic com/admogo/util/AdMogoUtil/ADMOGO Ljava/lang/String;
  astore 24
  aload 24
  astore_1
  aload 22
  astore_2
  aload_1
  aload_2
  invokestatic android/util/Log/d(Ljava/lang/String;Ljava/lang/String;)I
  pop
  getstatic com/admogo/util/AdMogoUtil/ADMOGO Ljava/lang/String;
  astore 24
  aload 31
  astore_1
  aload_1
  invokeinterface org/apache/http/HttpResponse/getStatusLine()Lorg/apache/http/StatusLine; 1
  astore 32
  aload 32
  astore_1
  aload_1
  invokevirtual java/lang/Object/toString()Ljava/lang/String;
  astore 21
  aload 24
  astore_1
  aload 21
  astore_2
  aload_1
  aload_2
  invokestatic android/util/Log/d(Ljava/lang/String;Ljava/lang/String;)I
  pop
  aload 31
  astore_1
  aload_1
  invokeinterface org/apache/http/HttpResponse/getEntity()Lorg/apache/http/HttpEntity; 1
  astore 33
  aload 33
  astore_1
  aload_1
  invokestatic app/DummyClass/invokeIfStmt(Ljava/lang/Object;)V
  aload 33
  ifnull Label4
  aload 31
  astore_1
  aload_1
  invokeinterface org/apache/http/HttpResponse/getStatusLine()Lorg/apache/http/StatusLine; 1
  astore 32
  aload 32
  astore_1
  aload_1
  invokeinterface org/apache/http/StatusLine/getStatusCode()I 1
  istore 34
  iload 34
  istore_1
  dload_1
  invokestatic app/DummyClass/invokeIfStmt(D)V
  sipush 200
  istore 16
  iload 34
  istore_1
  iload_1
  iload 16
  if_icmpne Label5
  iconst_1
  istore 16
  aload_0
  astore_1
  aload_1
  iload 16
  putfield com/admogo/AdMogoManager/ifGetInfo Z
  aload_0
  astore_1
  aload_1
  getfield com/admogo/AdMogoManager/scheduler Ljava/util/concurrent/ScheduledExecutorService;
  astore_1
  aload_1
  astore 35
  aload_0
  astore_1
  aload_1
  getfield com/admogo/AdMogoManager/SendDataRunnable Ljava/lang/Runnable;
  astore_1
  aload_1
  astore 36
  getstatic java/util/concurrent/TimeUnit/SECONDS Ljava/util/concurrent/TimeUnit;
  astore 37
  ldc2_w 0
  lstore 38
  aload 35
  astore_1
  aload 36
  astore_2
  lload 38
  lstore_3
  aload 37
  astore 5
  aload_1
  aload_2
  lload_3
  aload 5
  invokeinterface java/util/concurrent/ScheduledExecutorService/schedule(Ljava/lang/Runnable;JLjava/util/concurrent/TimeUnit;)Ljava/util/concurrent/ScheduledFuture; 5
  pop
  aload 33
  astore_1
  aload_1
  invokeinterface org/apache/http/HttpEntity/getContent()Ljava/io/InputStream; 1
  astore 40
  aload_0
  astore_1
  aload 40
  astore_2
  aload_1
  aload_2
  invokevirtual com/admogo/AdMogoManager/convertStreamToString(Ljava/io/InputStream;)Ljava/lang/String;
  astore 21
  ldc "\n"
  astore 20
  ldc ""
  astore 27
  aload 21
  astore_1
  aload 20
  astore_2
  aload 27
  astore_3
  aload_1
  aload_2
  aload_3
  invokevirtual java/lang/String/replace(Ljava/lang/CharSequence;Ljava/lang/CharSequence;)Ljava/lang/String;
  astore 41
  ldc "[\"empty\"]"
  astore 20
  aload 41
  astore_1
  aload 20
  astore_2
  aload_1
  aload_2
  invokevirtual java/lang/String/equals(Ljava/lang/Object;)Z
  istore 18
  iload 18
  istore_1
  iload_1
  invokestatic app/DummyClass/invokeIfStmt(Z)V
  iload 18
  ifne Label6
  aload 21
  astore 14
  getstatic com/admogo/util/AdMogoUtil/ADMOGO Ljava/lang/String;
  astore 41
  new java/lang/StringBuilder
  astore 19
  ldc "Prefs{"
  astore 20
  aload 19
  astore_1
  aload 20
  astore_2
  aload_1
  aload_2
  invokespecial java/lang/StringBuilder/<init>(Ljava/lang/String;)V
  aload_0
  astore_1
  aload_1
  getfield com/admogo/AdMogoManager/keyAdMogo Ljava/lang/String;
  astore_1
  aload_1
  astore 24
  aload 19
  astore_1
  aload 24
  astore_2
  aload_1
  aload_2
  invokevirtual java/lang/StringBuilder/append(Ljava/lang/String;)Ljava/lang/StringBuilder;
  astore 19
  ldc "}: {\""
  astore 20
  aload 19
  astore_1
  aload 20
  astore_2
  aload_1
  aload_2
  invokevirtual java/lang/StringBuilder/append(Ljava/lang/String;)Ljava/lang/StringBuilder;
  astore 19
  ldc "config"
  astore 20
  aload 19
  astore_1
  aload 20
  astore_2
  aload_1
  aload_2
  invokevirtual java/lang/StringBuilder/append(Ljava/lang/String;)Ljava/lang/StringBuilder;
  astore 19
  ldc "\": \""
  astore 20
  aload 19
  astore_1
  aload 20
  astore_2
  aload_1
  aload_2
  invokevirtual java/lang/StringBuilder/append(Ljava/lang/String;)Ljava/lang/StringBuilder;
  astore 19
  aload 19
  astore_1
  aload 21
  astore_2
  aload_1
  aload_2
  invokevirtual java/lang/StringBuilder/append(Ljava/lang/String;)Ljava/lang/StringBuilder;
  astore 19
  ldc "\""
  astore 20
  aload 19
  astore_1
  aload 20
  astore_2
  aload_1
  aload_2
  invokevirtual java/lang/StringBuilder/append(Ljava/lang/String;)Ljava/lang/StringBuilder;
  astore 19
  ldc "}"
  astore 20
  aload 19
  astore_1
  aload 20
  astore_2
  aload_1
  aload_2
  invokevirtual java/lang/StringBuilder/append(Ljava/lang/String;)Ljava/lang/StringBuilder;
  astore 19
  aload 19
  astore_1
  aload_1
  invokevirtual java/lang/StringBuilder/toString()Ljava/lang/String;
  astore 24
  aload 41
  astore_1
  aload 24
  astore_2
  aload_1
  aload_2
  invokestatic android/util/Log/d(Ljava/lang/String;Ljava/lang/String;)I
  pop
  aload 15
  invokeinterface android/content/SharedPreferences/edit()Landroid/content/SharedPreferences$Editor; 1
  astore 42
  new java/lang/StringBuilder
  astore 19
  aload_0
  astore_1
  aload_1
  getfield com/admogo/AdMogoManager/keyAdMogo Ljava/lang/String;
  astore_1
  aload_1
  astore 41
  aload 41
  astore_1
  aload_1
  invokestatic java/lang/String/valueOf(Ljava/lang/Object;)Ljava/lang/String;
  astore 41
  aload 19
  astore_1
  aload 41
  astore_2
  aload_1
  aload_2
  invokespecial java/lang/StringBuilder/<init>(Ljava/lang/String;)V
  aload_0
  astore_1
  aload_1
  getfield com/admogo/AdMogoManager/adType I
  istore_1
  iload_1
  istore 34
  aload 19
  astore_1
  iload 34
  istore_2
  aload_1
  iload_2
  invokevirtual java/lang/StringBuilder/append(I)Ljava/lang/StringBuilder;
  astore 19
  getstatic com/admogo/AdMogoManager/PREFS_STRING_COUNTRY Ljava/lang/String;
  astore 41
  aload 19
  astore_1
  aload 41
  astore_2
  aload_1
  aload_2
  invokevirtual java/lang/StringBuilder/append(Ljava/lang/String;)Ljava/lang/StringBuilder;
  astore 19
  ldc "config"
  astore 20
  aload 19
  astore_1
  aload 20
  astore_2
  aload_1
  aload_2
  invokevirtual java/lang/StringBuilder/append(Ljava/lang/String;)Ljava/lang/StringBuilder;
  astore 19
  aload 19
  astore_1
  aload_1
  invokevirtual java/lang/StringBuilder/toString()Ljava/lang/String;
  astore 41
  aload 42
  astore_1
  aload 41
  astore_2
  aload 21
  astore_3
  aload_1
  aload_2
  aload_3
  invokeinterface android/content/SharedPreferences$Editor/putString(Ljava/lang/String;Ljava/lang/String;)Landroid/content/SharedPreferences$Editor; 3
  pop
  new java/lang/StringBuilder
  astore 19
  aload_0
  astore_1
  aload_1
  getfield com/admogo/AdMogoManager/keyAdMogo Ljava/lang/String;
  astore_1
  aload_1
  astore 41
  aload 41
  astore_1
  aload_1
  invokestatic java/lang/String/valueOf(Ljava/lang/Object;)Ljava/lang/String;
  astore 41
  aload 19
  astore_1
  aload 41
  astore_2
  aload_1
  aload_2
  invokespecial java/lang/StringBuilder/<init>(Ljava/lang/String;)V
  aload_0
  astore_1
  aload_1
  getfield com/admogo/AdMogoManager/adType I
  istore_1
  iload_1
  istore 34
  aload 19
  astore_1
  iload 34
  istore_2
  aload_1
  iload_2
  invokevirtual java/lang/StringBuilder/append(I)Ljava/lang/StringBuilder;
  astore 19
  getstatic com/admogo/AdMogoManager/PREFS_STRING_COUNTRY Ljava/lang/String;
  astore 41
  aload 19
  astore_1
  aload 41
  astore_2
  aload_1
  aload_2
  invokevirtual java/lang/StringBuilder/append(Ljava/lang/String;)Ljava/lang/StringBuilder;
  astore 19
  ldc "timestamp"
  astore 20
  aload 19
  astore_1
  aload 20
  astore_2
  aload_1
  aload_2
  invokevirtual java/lang/StringBuilder/append(Ljava/lang/String;)Ljava/lang/StringBuilder;
  astore 19
  aload 19
  astore_1
  aload_1
  invokevirtual java/lang/StringBuilder/toString()Ljava/lang/String;
  astore 41
  invokestatic java/lang/System/currentTimeMillis()J
  lstore 43
  aload 42
  astore_1
  aload 41
  astore_2
  lload 43
  lstore_3
  aload_1
  aload_2
  lload_3
  invokeinterface android/content/SharedPreferences$Editor/putLong(Ljava/lang/String;J)Landroid/content/SharedPreferences$Editor; 4
  pop
  aload 42
  astore_1
  aload_1
  invokeinterface android/content/SharedPreferences$Editor/commit()Z 1
  pop
  aload_0
  astore_1
  aload 21
  astore_2
  aload_1
  aload_2
  invokespecial com/admogo/AdMogoManager/parseConfigurationString(Ljava/lang/String;)V
  iconst_1
  istore 16
  aload_0
  astore_1
  aload_1
  iload 16
  putfield com/admogo/AdMogoManager/isGetInfo Z
Label4:
  iload 17
  istore_1
  iload_1
  invokestatic app/DummyClass/invokeIfStmt(Z)V
  iload 17
  ifne Label7
  aload 14
  invokestatic android/text/TextUtils/isEmpty(Ljava/lang/CharSequence;)Z
  istore 18
  iload 18
  istore_1
  iload_1
  invokestatic app/DummyClass/invokeIfStmt(Z)V
  iload 18
  ifeq Label8
  aload_0
  astore_1
  aload_1
  getfield com/admogo/AdMogoManager/expressMode Z
  istore_1
  iload_1
  istore 18
  iload_1
  invokestatic app/DummyClass/invokeIfStmt(Z)V
  iload 18
  ifne Label9
  getstatic com/admogo/AdMogoManager/URL_INDEX I
  istore 34
  iload 34
  istore_1
  dload_1
  invokestatic app/DummyClass/invokeIfStmt(D)V
  iload 34
  ifne Label9
  aload_0
  astore_1
  aload_1
  invokespecial com/admogo/AdMogoManager/readOfflineFile()Z
  pop
Label9:
  aload_0
  astore_1
  aload_1
  invokespecial com/admogo/AdMogoManager/searchURL()V
  goto Label7
Label2:
  aload_0
  astore_1
  aload_1
  getfield com/admogo/AdMogoManager/adType I
  istore_1
  iload_1
  istore 34
  dload_1
  invokestatic app/DummyClass/invokeIfStmt(D)V
  iconst_2
  istore 16
  iload 34
  istore_1
  iload_1
  iload 16
  if_icmpeq Label10
  aload_0
  astore_1
  aload_1
  getfield com/admogo/AdMogoManager/adType I
  istore_1
  iload_1
  istore 34
  dload_1
  invokestatic app/DummyClass/invokeIfStmt(D)V
  iconst_3
  istore 16
  iload 34
  istore_1
  iload_1
  iload 16
  if_icmpeq Label10
  aload_0
  astore_1
  aload_1
  getfield com/admogo/AdMogoManager/adType I
  istore_1
  iload_1
  istore 34
  dload_1
  invokestatic app/DummyClass/invokeIfStmt(D)V
  iconst_4
  istore 16
  iload 34
  istore_1
  iload_1
  iload 16
  if_icmpeq Label10
  aload_0
  astore_1
  aload_1
  getfield com/admogo/AdMogoManager/adType I
  istore_1
  iload_1
  istore 34
  dload_1
  invokestatic app/DummyClass/invokeIfStmt(D)V
  iconst_5
  istore 16
  iload 34
  istore_1
  iload_1
  iload 16
  if_icmpne Label11
Label10:
  bipush 8
  istore 13
  goto Label12
Label11:
  aload_0
  astore_1
  aload_1
  getfield com/admogo/AdMogoManager/adType I
  istore_1
  iload_1
  istore 34
  dload_1
  invokestatic app/DummyClass/invokeIfStmt(D)V
  bipush 7
  istore 16
  iload 34
  istore_1
  iload_1
  iload 16
  if_icmpne Label13
  bipush 32
  istore 13
  goto Label12
Label13:
  aload_0
  astore_1
  aload_1
  getfield com/admogo/AdMogoManager/adType I
  istore_1
  iload_1
  istore 34
  dload_1
  invokestatic app/DummyClass/invokeIfStmt(D)V
  bipush 6
  istore 16
  iload 34
  istore_1
  iload_1
  iload 16
  if_icmpne Label12
  sipush 128
  istore 13
  goto Label12
Label6:
  aload_0
  astore_1
  aload_1
  getfield com/admogo/AdMogoManager/expressMode Z
  istore_1
  iload_1
  istore 18
  iload_1
  invokestatic app/DummyClass/invokeIfStmt(Z)V
  iload 18
  ifne Label4
  getstatic com/admogo/AdMogoManager/URL_INDEX I
  istore 34
  iload 34
  istore_1
  dload_1
  invokestatic app/DummyClass/invokeIfStmt(D)V
  iload 34
  ifne Label4
  aload_0
  astore_1
  aload_1
  aload 14
  invokespecial com/admogo/AdMogoManager/parseConfigurationString(Ljava/lang/String;)V
Label17:
  goto Label4
Label15:
  astore 45
  getstatic com/admogo/util/AdMogoUtil/ADMOGO Ljava/lang/String;
  astore 41
  ldc "Caught Exception in fetchConfig()"
  astore 20
  aload 41
  astore_1
  aload 20
  astore_2
  aload_1
  aload_2
  invokestatic android/util/Log/w(Ljava/lang/String;Ljava/lang/String;)I
  pop
  iconst_0
  istore 17
  goto Label4
Label5:
  iconst_0
  istore 17
  goto Label4
Label8:
  aload_0
  astore_1
  aload_1
  getfield com/admogo/AdMogoManager/expressMode Z
  istore_1
  iload_1
  istore 18
  iload_1
  invokestatic app/DummyClass/invokeIfStmt(Z)V
  iload 18
  ifne Label14
  getstatic com/admogo/AdMogoManager/URL_INDEX I
  istore 34
  iload 34
  istore_1
  dload_1
  invokestatic app/DummyClass/invokeIfStmt(D)V
  iload 34
  ifne Label14
  aload_0
  astore_1
  aload_1
  aload 14
  invokespecial com/admogo/AdMogoManager/parseConfigurationString(Ljava/lang/String;)V
Label14:
  aload_0
  astore_1
  aload_1
  getfield com/admogo/AdMogoManager/scheduler Ljava/util/concurrent/ScheduledExecutorService;
  astore_1
  aload_1
  astore 35
  aload_0
  astore_1
  aload_1
  getfield com/admogo/AdMogoManager/searchURL Ljava/lang/Runnable;
  astore_1
  aload_1
  astore 36
  getstatic java/util/concurrent/TimeUnit/SECONDS Ljava/util/concurrent/TimeUnit;
  astore 37
  ldc2_w 0
  lstore 38
  aload 35
  astore_1
  aload 36
  astore_2
  lload 38
  lstore_3
  aload 37
  astore 5
  aload_1
  aload_2
  lload_3
  aload 5
  invokeinterface java/util/concurrent/ScheduledExecutorService/schedule(Ljava/lang/Runnable;JLjava/util/concurrent/TimeUnit;)Ljava/util/concurrent/ScheduledFuture; 5
  pop
  goto Label7
  nop
.end <method>

.method public fetchImage(Ljava/lang/String;)Landroid/graphics/drawable/Drawable;
.limit locals 13
.limit stack 200
  .catch  java/lang/Exception <from> Label1 <to> Label2 <using> Label0
  nop
  new java/net/URL
  astore_2
Label1:
  aload_2
  aload_1
  invokespecial java/net/URL/<init>(Ljava/lang/String;)V
  aload_2
  invokevirtual java/net/URL/getContent()Ljava/lang/Object;
  astore_3
  aload_3
  astore 5
  aload 5
  checkcast java/io/InputStream
  astore 5
  aload 5
  astore 4
  ldc "src"
  astore 7
  new java/lang/NoClassDefFoundError
  dup
  invokespecial java/lang/NoClassDefFoundError/<init>()V
  athrow
  nop
  aload 4
  invokevirtual java/io/InputStream/close()V
Label2:
  aload 6
  areturn
Label0:
  astore 8
  getstatic com/admogo/util/AdMogoUtil/ADMOGO Ljava/lang/String;
  astore 9
  new java/lang/StringBuilder
  astore 10
  ldc "Unable to fetchImage() and imgUrl-->"
  astore 7
  aload 10
  aload 7
  invokespecial java/lang/StringBuilder/<init>(Ljava/lang/String;)V
  aload 10
  aload_1
  invokevirtual java/lang/StringBuilder/append(Ljava/lang/String;)Ljava/lang/StringBuilder;
  astore 10
  aload 10
  invokevirtual java/lang/StringBuilder/toString()Ljava/lang/String;
  astore 11
  new java/lang/NoClassDefFoundError
  dup
  invokespecial java/lang/NoClassDefFoundError/<init>()V
  athrow
  aconst_null
  astore 12
  aload 12
  areturn
  nop
.end <method>

.method public fillRListEmpty()Z
.limit locals 2
.limit stack 200
  nop
  aload_0
  getfield com/admogo/AdMogoManager/fillRListEmpty Z
  istore_1
  iload_1
  ireturn
  nop
.end <method>

.method public getCityName(DD)V
.limit locals 16
.limit stack 200
  nop
  aload_0
  getfield com/admogo/AdMogoManager/scheduler Ljava/util/concurrent/ScheduledExecutorService;
  astore 11
  new com/admogo/AdMogoManager$getCityNameRunnable
  astore 12
  aload 12
  astore 5
  aload_0
  astore 6
  dload_1
  dstore 7
  dload_3
  dstore 9
  aload 5
  aload 6
  dload 7
  dload 9
  invokespecial com/admogo/AdMogoManager$getCityNameRunnable/<init>(Lcom/admogo/AdMogoManager;DD)V
  getstatic java/util/concurrent/TimeUnit/SECONDS Ljava/util/concurrent/TimeUnit;
  astore 13
  ldc2_w 0
  lstore 14
  aload 11
  aload 12
  lload 14
  aload 13
  invokeinterface java/util/concurrent/ScheduledExecutorService/schedule(Ljava/lang/Runnable;JLjava/util/concurrent/TimeUnit;)Ljava/util/concurrent/ScheduledFuture; 5
  pop
  return
  nop
.end <method>

.method public getConfigurationPriority()V
.limit locals 28
.limit stack 200
  nop
  aload_0
  astore_1
  aload_1
  getfield com/admogo/AdMogoManager/contextReference Ljava/lang/ref/WeakReference;
  astore 5
  aload 5
  invokevirtual java/lang/ref/WeakReference/get()Ljava/lang/Object;
  astore 6
  aload 6
  astore 8
  new java/lang/NoClassDefFoundError
  dup
  invokespecial java/lang/NoClassDefFoundError/<init>()V
  athrow
  aload 8
  astore 7
  aload 7
  invokestatic app/DummyClass/invokeIfStmt(Ljava/lang/Object;)V
  iload 7
  ifne Label0
Label2:
  return
Label0:
  getstatic com/admogo/AdMogoManager/tempConfig Ljava/util/Hashtable;
  astore 9
  new java/lang/StringBuilder
  astore 10
  aload_0
  astore_1
  aload_1
  getfield com/admogo/AdMogoManager/keyAdMogo Ljava/lang/String;
  astore 11
  aload 11
  invokestatic java/lang/String/valueOf(Ljava/lang/Object;)Ljava/lang/String;
  astore 11
  aload 10
  aload 11
  invokespecial java/lang/StringBuilder/<init>(Ljava/lang/String;)V
  aload_0
  astore_1
  aload_1
  getfield com/admogo/AdMogoManager/adType I
  istore 12
  aload 10
  iload 12
  invokevirtual java/lang/StringBuilder/append(I)Ljava/lang/StringBuilder;
  astore 10
  getstatic com/admogo/AdMogoManager/PREFS_STRING_COUNTRY Ljava/lang/String;
  astore 11
  aload 10
  aload 11
  invokevirtual java/lang/StringBuilder/append(Ljava/lang/String;)Ljava/lang/StringBuilder;
  astore 10
  ldc "tempConfig"
  astore 13
  aload 10
  aload 13
  invokevirtual java/lang/StringBuilder/append(Ljava/lang/String;)Ljava/lang/StringBuilder;
  astore 10
  aload 10
  invokevirtual java/lang/StringBuilder/toString()Ljava/lang/String;
  astore 11
  aload 9
  aload 11
  invokevirtual java/util/Hashtable/get(Ljava/lang/Object;)Ljava/lang/Object;
  astore 6
  aload 6
  astore 14
  aload 14
  checkcast java/lang/String
  astore 14
  aload 14
  astore 11
  aload_0
  astore_1
  aload_1
  getfield com/admogo/AdMogoManager/keyAdMogo Ljava/lang/String;
  astore 15
  iconst_0
  istore 17
  iload 17
  istore_1
  aload 7
  aload 15
  iload_1
  invokevirtual android/content/Context/getSharedPreferences(Ljava/lang/String;I)Landroid/content/SharedPreferences;
  astore 16
  new java/lang/StringBuilder
  astore 10
  aload_0
  astore_1
  aload_1
  getfield com/admogo/AdMogoManager/keyAdMogo Ljava/lang/String;
  astore 15
  aload 15
  invokestatic java/lang/String/valueOf(Ljava/lang/Object;)Ljava/lang/String;
  astore 15
  aload 10
  aload 15
  invokespecial java/lang/StringBuilder/<init>(Ljava/lang/String;)V
  aload_0
  astore_1
  aload_1
  getfield com/admogo/AdMogoManager/adType I
  istore 12
  aload 10
  iload 12
  invokevirtual java/lang/StringBuilder/append(I)Ljava/lang/StringBuilder;
  astore 10
  getstatic com/admogo/AdMogoManager/PREFS_STRING_COUNTRY Ljava/lang/String;
  astore 15
  aload 10
  aload 15
  invokevirtual java/lang/StringBuilder/append(Ljava/lang/String;)Ljava/lang/StringBuilder;
  astore 10
  ldc "timestamp"
  astore 13
  aload 10
  aload 13
  invokevirtual java/lang/StringBuilder/append(Ljava/lang/String;)Ljava/lang/StringBuilder;
  astore 10
  aload 10
  invokevirtual java/lang/StringBuilder/toString()Ljava/lang/String;
  astore 15
  ldc2_w 4294967295
  lstore 20
  lload 20
  lstore_1
  aload 16
  aload 15
  lload_1
  invokeinterface android/content/SharedPreferences/getLong(Ljava/lang/String;J)J 4
  lstore 18
  aload 11
  invokestatic android/text/TextUtils/isEmpty(Ljava/lang/CharSequence;)Z
  istore 22
  iload 22
  istore_1
  iload_1
  invokestatic app/DummyClass/invokeIfStmt(Z)V
  iload 22
  ifeq Label1
  aload_0
  astore_1
  aload_1
  invokevirtual com/admogo/AdMogoManager/fetchConfig()V
  goto Label2
Label1:
  invokestatic java/lang/System/currentTimeMillis()J
  lstore 23
  getstatic com/admogo/AdMogoManager/configExpireTimeout J
  lstore 25
  lload 25
  lstore_1
  lload 18
  lstore_3
  lload_1
  lload_3
  ladd
  lstore_1
  lload_1
  lstore 25
  lload 23
  lload 25
  lcmp
  istore 27
  iload 27
  istore_1
  dload_1
  invokestatic app/DummyClass/invokeIfStmt(D)V
  iload 27
  iflt Label3
  aload_0
  astore_1
  aload_1
  invokevirtual com/admogo/AdMogoManager/fetchConfig()V
  goto Label2
Label3:
  aload_0
  astore_1
  aload_1
  aload 11
  invokespecial com/admogo/AdMogoManager/parseConfigurationString(Ljava/lang/String;)V
  goto Label2
  nop
.end <method>

.method public getExtra()Lcom/admogo/obj/Extra;
.limit locals 2
.limit stack 200
  nop
  aload_0
  getfield com/admogo/AdMogoManager/extra Lcom/admogo/obj/Extra;
  astore_1
  aload_1
  areturn
  nop
.end <method>

.method public getIpAddress()Ljava/lang/String;
.limit locals 14
.limit stack 200
  nop
  getstatic com/admogo/AdMogoManager/ipAddress Ljava/lang/String;
  astore_1
  new java/lang/NoClassDefFoundError
  dup
  invokespecial java/lang/NoClassDefFoundError/<init>()V
  athrow
  iload_1
  ifeq Label0
  getstatic com/admogo/AdMogoManager/ipAddress Ljava/lang/String;
  astore_2
  ldc ""
  astore 4
  aload_2
  aload 4
  invokevirtual java/lang/String/equals(Ljava/lang/Object;)Z
  istore_3
  iload_3
  invokestatic app/DummyClass/invokeIfStmt(Z)V
  iload_3
  ifne Label0
  getstatic com/admogo/AdMogoManager/ipAddress Ljava/lang/String;
  astore_2
  ldc "\\d+\\.\\d+\\.\\d+\\.\\d+"
  astore 4
  aload_0
  aload 4
  aload_2
  invokespecial com/admogo/AdMogoManager/mathStr(Ljava/lang/String;Ljava/lang/String;)Z
  istore_3
  iload_3
  invokestatic app/DummyClass/invokeIfStmt(Z)V
  iload_3
  ifeq Label0
  getstatic com/admogo/AdMogoManager/ipAddress Ljava/lang/String;
  astore_2
  aload_2
  areturn
Label0:
  ldc ""
  astore 4
  aload 4
  putstatic com/admogo/AdMogoManager/ipAddress Ljava/lang/String;
  invokestatic com/admogo/AdMogoManager/getLocalIPAddress()Ljava/lang/String;
  astore_2
  aload_2
  putstatic com/admogo/AdMogoManager/ipAddress Ljava/lang/String;
  getstatic com/admogo/AdMogoManager/ipAddress Ljava/lang/String;
  astore_1
  ldc "(127[.]0[.]0[.]1)|(localhost)|(10[.]\\d{1,3}[.]\\d{1,3}[.]\\d{1,3})|(172[.]((1[6-9])|(2\\d)|(3[01]))[.]\\d{1,3}[.]\\d{1,3})|(192[.]168[.]\\d{1,3}[.]\\d{1,3})"
  astore 4
  aload_0
  aload 4
  aload_1
  invokespecial com/admogo/AdMogoManager/mathStr(Ljava/lang/String;Ljava/lang/String;)Z
  istore_3
  iload_3
  invokestatic app/DummyClass/invokeIfStmt(Z)V
  iload_3
  ifne Label1
  getstatic com/admogo/AdMogoManager/ipAddress Ljava/lang/String;
  astore_2
  aload_2
  areturn
Label1:
  new org/apache/http/client/methods/HttpGet
  astore 5
  getstatic com/admogo/util/AdMogoUtil/urlGetIp Ljava/lang/String;
  astore_2
Label4:
  aload 5
  aload_2
  invokespecial org/apache/http/client/methods/HttpGet/<init>(Ljava/lang/String;)V
  new org/apache/http/impl/client/DefaultHttpClient
  astore 6
  aload 6
  invokespecial org/apache/http/impl/client/DefaultHttpClient/<init>()V
  aload 6
  aload 5
  invokevirtual org/apache/http/impl/client/DefaultHttpClient/execute(Lorg/apache/http/client/methods/HttpUriRequest;)Lorg/apache/http/HttpResponse;
  astore 7
  aload 7
  invokeinterface org/apache/http/HttpResponse/getStatusLine()Lorg/apache/http/StatusLine; 1
  astore 8
  aload 8
  invokeinterface org/apache/http/StatusLine/getStatusCode()I 1
  istore 9
  dload 9
  invokestatic app/DummyClass/invokeIfStmt(D)V
  sipush 200
  istore 10
  iload 9
  iload 10
  if_icmpne Label2
  new java/lang/StringBuilder
  astore 11
  aload 7
  invokeinterface org/apache/http/HttpResponse/getEntity()Lorg/apache/http/HttpEntity; 1
  astore 12
  ldc "utf-8"
  astore 4
  aload 12
  aload 4
  invokestatic org/apache/http/util/EntityUtils/toString(Lorg/apache/http/HttpEntity;Ljava/lang/String;)Ljava/lang/String;
  astore_2
  aload_2
  invokestatic java/lang/String/valueOf(Ljava/lang/Object;)Ljava/lang/String;
  astore_2
  aload 11
  aload_2
  invokespecial java/lang/StringBuilder/<init>(Ljava/lang/String;)V
  aload 11
  invokevirtual java/lang/StringBuilder/toString()Ljava/lang/String;
  astore_2
Label5:
  aload_2
  putstatic com/admogo/AdMogoManager/ipAddress Ljava/lang/String;
Label2:
  getstatic com/admogo/AdMogoManager/ipAddress Ljava/lang/String;
  astore_2
  aload_2
  areturn
Label3:
  astore 13
  getstatic com/admogo/util/AdMogoUtil/ADMOGO Ljava/lang/String;
  astore_2
  ldc "INMOBI get IP Exception"
  astore 4
  aload_2
  aload 4
  aload 13
  invokestatic android/util/Log/e(Ljava/lang/String;Ljava/lang/String;Ljava/lang/Throwable;)I
  pop
  goto Label2
  nop
.end <method>

.method private static getLocalIPAddress()Ljava/lang/String;
.limit locals 11
.limit stack 200
  .catch  java/net/SocketException <from> Label5 <to> Label6 <using> Label4
  .catch  java/net/SocketException <from> Label0 <to> Label7 <using> Label4
  nop
Label5:
  invokestatic java/net/NetworkInterface/getNetworkInterfaces()Ljava/util/Enumeration;
  astore_0
Label1:
  aload_0
  invokeinterface java/util/Enumeration/hasMoreElements()Z 1
  istore_1
Label6:
  new java/lang/NoClassDefFoundError
  dup
  invokespecial java/lang/NoClassDefFoundError/<init>()V
  athrow
  iload_1
  ifne Label0
Label3:
  ldc ""
  astore_2
  aload_2
  areturn
Label0:
  aload_0
  invokeinterface java/util/Enumeration/nextElement()Ljava/lang/Object; 1
  astore_3
  aload_3
  astore 5
  aload 5
  checkcast java/net/NetworkInterface
  astore 5
  aload 5
  astore 4
  aload 4
  invokevirtual java/net/NetworkInterface/getInetAddresses()Ljava/util/Enumeration;
  astore 6
Label2:
  aload 6
  invokeinterface java/util/Enumeration/hasMoreElements()Z 1
  istore_1
  iload_1
  invokestatic app/DummyClass/invokeIfStmt(Z)V
  iload_1
  ifeq Label1
  aload 6
  invokeinterface java/util/Enumeration/nextElement()Ljava/lang/Object; 1
  astore_3
  aload_3
  astore 8
  aload 8
  checkcast java/net/InetAddress
  astore 8
  aload 8
  astore 7
  aload 7
  invokevirtual java/net/InetAddress/isLoopbackAddress()Z
  istore_1
  iload_1
  invokestatic app/DummyClass/invokeIfStmt(Z)V
  iload_1
  ifne Label2
  aload 7
  invokevirtual java/net/InetAddress/getHostAddress()Ljava/lang/String;
  astore 9
  aload 9
  invokevirtual java/lang/String/toString()Ljava/lang/String;
  astore 9
Label7:
  aload 9
  areturn
Label4:
  astore 10
  aload 10
  invokevirtual java/net/SocketException/toString()Ljava/lang/String;
  astore 9
  ldc "Error"
  astore_2
  new java/lang/NoClassDefFoundError
  dup
  invokespecial java/lang/NoClassDefFoundError/<init>()V
  athrow
  goto Label3
  nop
.end <method>

.method public getPublicCustom(Ljava/lang/String;II)Lcom/admogo/obj/PublicCustom;
.limit locals 25
.limit stack 200
  nop
  new java/lang/NoClassDefFoundError
  dup
  invokespecial java/lang/NoClassDefFoundError/<init>()V
  athrow
  aload 6
  invokespecial org/apache/http/impl/client/DefaultHttpClient/<init>()V
  ldc ""
  astore 7
  dload_2
  dstore 4
  dload 4
  invokestatic app/DummyClass/invokeIfStmt(D)V
  bipush 45
  istore 8
  iload_2
  istore 4
  iload 4
  iload 8
  if_icmpne Label0
  getstatic com/admogo/util/AdMogoUtil/urlExchange Ljava/lang/String;
  astore_1
  iconst_5
  istore 8
  iload 8
  anewarray java/lang/Object
  astore 9
  aload_0
  astore 4
  aload 4
  getfield com/admogo/AdMogoManager/keyAdMogo Ljava/lang/String;
  astore 10
  iconst_0
  istore 8
  aload 9
  iload 8
  aload 10
  aastore
  aload_0
  astore 4
  aload 4
  getfield com/admogo/AdMogoManager/adType I
  istore 4
  iload 4
  istore_3
  iload 4
  invokestatic java/lang/Integer/valueOf(I)Ljava/lang/Integer;
  astore 11
  iconst_1
  istore 8
  aload 9
  iload 8
  aload 11
  aastore
  aload_0
  astore 4
  aload 4
  getfield com/admogo/AdMogoManager/getCountryCode Ljava/lang/String;
  astore 10
  iconst_2
  istore 8
  aload 9
  iload 8
  aload 10
  aastore
  aload_0
  astore 4
  aload 4
  getfield com/admogo/AdMogoManager/deviceIDHash Ljava/lang/String;
  astore 10
  iconst_3
  istore 8
  aload 9
  iload 8
  aload 10
  aastore
  aload_0
  astore 4
  aload 4
  getfield com/admogo/AdMogoManager/networkType Ljava/lang/String;
  astore 10
  iconst_4
  istore 8
  aload 9
  iload 8
  aload 10
  aastore
  aload_1
  astore 4
  aload 4
  aload 9
  invokestatic java/lang/String/format(Ljava/lang/String;[Ljava/lang/Object;)Ljava/lang/String;
  astore 10
Label5:
  getstatic com/admogo/AdMogoManager/cityName Ljava/lang/String;
  astore_1
  aload_1
  astore 4
  aload 4
  invokestatic android/text/TextUtils/isEmpty(Ljava/lang/CharSequence;)Z
  istore 12
  iload 12
  invokestatic app/DummyClass/invokeIfStmt(Z)V
  iload 12
  ifne Label1
  new java/lang/StringBuilder
  astore 13
  aload 10
  invokestatic java/lang/String/valueOf(Ljava/lang/Object;)Ljava/lang/String;
  astore 10
  aload 13
  aload 10
  invokespecial java/lang/StringBuilder/<init>(Ljava/lang/String;)V
  ldc "&area="
  astore 14
  aload 13
  aload 14
  invokevirtual java/lang/StringBuilder/append(Ljava/lang/String;)Ljava/lang/StringBuilder;
  astore 13
  getstatic com/admogo/AdMogoManager/cityName Ljava/lang/String;
  astore 10
  aload 10
  invokestatic java/net/URLEncoder/encode(Ljava/lang/String;)Ljava/lang/String;
  astore 10
  aload 13
  aload 10
  invokevirtual java/lang/StringBuilder/append(Ljava/lang/String;)Ljava/lang/StringBuilder;
  astore 13
  aload 13
  invokevirtual java/lang/StringBuilder/toString()Ljava/lang/String;
  astore 10
Label1:
  new org/apache/http/client/methods/HttpGet
  astore 15
  aload 15
  aload 10
  invokespecial org/apache/http/client/methods/HttpGet/<init>(Ljava/lang/String;)V
  dload_2
  dstore 4
  dload 4
  invokestatic app/DummyClass/invokeIfStmt(D)V
  bipush 27
  istore 8
  iload_2
  istore 4
  iload 4
  iload 8
  if_icmpne Label2
  ldc "c"
  astore 14
  aload 15
  aload 14
  aload 7
  invokevirtual org/apache/http/client/methods/HttpGet/setHeader(Ljava/lang/String;Ljava/lang/String;)V
Label2:
  aload 6
  aload 15
  invokeinterface org/apache/http/client/HttpClient/execute(Lorg/apache/http/client/methods/HttpUriRequest;)Lorg/apache/http/HttpResponse; 2
  astore 16
  getstatic com/admogo/util/AdMogoUtil/ADMOGO Ljava/lang/String;
  astore 10
  aload 16
  invokeinterface org/apache/http/HttpResponse/getStatusLine()Lorg/apache/http/StatusLine; 1
  astore 17
  aload 17
  invokevirtual java/lang/Object/toString()Ljava/lang/String;
  astore 7
  aload 10
  aload 7
  invokestatic android/util/Log/d(Ljava/lang/String;Ljava/lang/String;)I
  pop
  aload 16
  invokeinterface org/apache/http/HttpResponse/getEntity()Lorg/apache/http/HttpEntity; 1
  astore 18
  aload 18
  invokestatic app/DummyClass/invokeIfStmt(Ljava/lang/Object;)V
  aload 18
  ifnull Label3
  aload 18
  invokeinterface org/apache/http/HttpEntity/getContent()Ljava/io/InputStream; 1
  astore 19
  aload_0
  astore 4
  aload 4
  aload 19
  invokevirtual com/admogo/AdMogoManager/convertStreamToString(Ljava/io/InputStream;)Ljava/lang/String;
  astore 7
  aload_0
  astore 4
  aload 4
  aload 7
  invokespecial com/admogo/AdMogoManager/parsePublicCustomJsonString(Ljava/lang/String;)Lcom/admogo/obj/PublicCustom;
  astore 20
Label9:
  aload 20
  areturn
Label0:
  dload_2
  dstore 4
  dload 4
  invokestatic app/DummyClass/invokeIfStmt(D)V
  bipush 27
  istore 8
  iload_2
  istore 4
  iload 4
  iload 8
  if_icmpne Label4
  getstatic com/admogo/util/AdMogoUtil/urlMogo Ljava/lang/String;
  astore 10
  bipush 7
  istore 8
  iload 8
  anewarray java/lang/Object
  astore 9
  aload_0
  astore 4
  aload 4
  getfield com/admogo/AdMogoManager/keyAdMogo Ljava/lang/String;
  astore 7
  iconst_0
  istore 8
  aload 9
  iload 8
  aload 7
  aastore
  iconst_1
  istore 8
  aload 9
  iload 8
  aload_1
  aastore
  aload_0
  astore 4
  aload 4
  getfield com/admogo/AdMogoManager/adType I
  istore 4
  iload 4
  istore 21
  iload 4
  invokestatic java/lang/Integer/valueOf(I)Ljava/lang/Integer;
  astore 11
  iconst_2
  istore 8
  aload 9
  iload 8
  aload 11
  aastore
  aload_0
  astore 4
  aload 4
  getfield com/admogo/AdMogoManager/getCountryCode Ljava/lang/String;
  astore 7
  iconst_3
  istore 8
  aload 9
  iload 8
  aload 7
  aastore
  aload_0
  astore 4
  aload 4
  getfield com/admogo/AdMogoManager/deviceIDHash Ljava/lang/String;
  astore 7
  iconst_4
  istore 8
  aload 9
  iload 8
  aload 7
  aastore
  aload_0
  astore 4
  aload 4
  getfield com/admogo/AdMogoManager/networkType Ljava/lang/String;
  astore 7
  iconst_5
  istore 8
  aload 9
  iload 8
  aload 7
  aastore
  iload_3
  istore 4
  iload 4
  invokestatic java/lang/Integer/valueOf(I)Ljava/lang/Integer;
  astore 11
  bipush 6
  istore 8
  aload 9
  iload 8
  aload 11
  aastore
  aload 10
  aload 9
  invokestatic java/lang/String/format(Ljava/lang/String;[Ljava/lang/Object;)Ljava/lang/String;
  astore 10
  new java/lang/StringBuilder
  astore 13
  aload_0
  astore 4
  aload 4
  getfield com/admogo/AdMogoManager/keyAdMogo Ljava/lang/String;
  astore 7
  aload 7
  invokestatic java/lang/String/valueOf(Ljava/lang/Object;)Ljava/lang/String;
  astore 7
  aload 13
  aload 7
  invokespecial java/lang/StringBuilder/<init>(Ljava/lang/String;)V
  aload_0
  astore 4
  aload 4
  getfield com/admogo/AdMogoManager/adType I
  istore 4
  iload 4
  istore 21
  aload 13
  iload 4
  invokevirtual java/lang/StringBuilder/append(I)Ljava/lang/StringBuilder;
  astore 13
  aload_0
  astore 4
  aload 4
  getfield com/admogo/AdMogoManager/getCountryCode Ljava/lang/String;
  astore 7
  aload 13
  aload 7
  invokevirtual java/lang/StringBuilder/append(Ljava/lang/String;)Ljava/lang/StringBuilder;
  astore 13
  ldc "2"
  astore 14
  aload 13
  aload 14
  invokevirtual java/lang/StringBuilder/append(Ljava/lang/String;)Ljava/lang/StringBuilder;
  astore 13
  aload_0
  astore 4
  aload 4
  getfield com/admogo/AdMogoManager/networkType Ljava/lang/String;
  astore 7
  aload 13
  aload 7
  invokevirtual java/lang/StringBuilder/append(Ljava/lang/String;)Ljava/lang/StringBuilder;
  astore 13
  aload_0
  astore 4
  aload 4
  getfield com/admogo/AdMogoManager/deviceIDHash Ljava/lang/String;
  astore 7
  aload 13
  aload 7
  invokevirtual java/lang/StringBuilder/append(Ljava/lang/String;)Ljava/lang/StringBuilder;
  astore 13
  aload_1
  astore 4
  aload 13
  aload 4
  invokevirtual java/lang/StringBuilder/append(Ljava/lang/String;)Ljava/lang/StringBuilder;
  astore 13
  ldc "Q8tFVImbNuvsmBwWwdqsPE6jsRQsSPkQ"
  astore 14
  aload 13
  aload 14
  invokevirtual java/lang/StringBuilder/append(Ljava/lang/String;)Ljava/lang/StringBuilder;
  astore 13
  aload 13
  invokevirtual java/lang/StringBuilder/toString()Ljava/lang/String;
  astore 7
  aload 7
  invokestatic com/admogo/util/AdMogoUtil/convertToHex(Ljava/lang/String;)Ljava/lang/String;
  astore 7
  goto Label5
Label4:
  dload_2
  dstore 4
  dload 4
  invokestatic app/DummyClass/invokeIfStmt(D)V
  bipush 48
  istore 8
  iload_2
  istore 4
  iload 4
  iload 8
  if_icmpne Label6
  getstatic com/admogo/util/AdMogoUtil/urlPremium Ljava/lang/String;
  astore 10
  bipush 6
  istore 8
  iload 8
  anewarray java/lang/Object
  astore 9
  aload_0
  astore 4
  aload 4
  getfield com/admogo/AdMogoManager/keyAdMogo Ljava/lang/String;
  astore 4
  aload 4
  astore 22
  iconst_0
  istore 8
  aload 9
  iload 8
  aload 22
  aastore
  iconst_1
  istore 8
  aload 9
  iload 8
  aload_1
  aastore
  aload_0
  astore 4
  aload 4
  getfield com/admogo/AdMogoManager/deviceIDHash Ljava/lang/String;
  astore 4
  aload 4
  astore 22
  iconst_2
  istore 8
  aload 9
  iload 8
  aload 22
  aastore
  aload_0
  astore 4
  aload 4
  getfield com/admogo/AdMogoManager/adType I
  istore 4
  iload 4
  istore 21
  iload 4
  invokestatic java/lang/Integer/valueOf(I)Ljava/lang/Integer;
  astore 11
  iconst_3
  istore 8
  aload 9
  iload 8
  aload 11
  aastore
  aload_0
  astore 4
  aload 4
  getfield com/admogo/AdMogoManager/getCountryCode Ljava/lang/String;
  astore 4
  aload 4
  astore 22
  iconst_4
  istore 8
  aload 9
  iload 8
  aload 22
  aastore
  aload_0
  astore 4
  aload 4
  getfield com/admogo/AdMogoManager/networkType Ljava/lang/String;
  astore 4
  aload 4
  astore 22
  iconst_5
  istore 8
  aload 9
  iload 8
  aload 22
  aastore
  aload 10
  aload 9
  invokestatic java/lang/String/format(Ljava/lang/String;[Ljava/lang/Object;)Ljava/lang/String;
  astore 10
  goto Label5
Label6:
  dload_2
  dstore 4
  dload 4
  invokestatic app/DummyClass/invokeIfStmt(D)V
  bipush 54
  istore 8
  iload_2
  istore 4
  iload 4
  iload 8
  if_icmpne Label7
  getstatic com/admogo/util/AdMogoUtil/urlRecommend Ljava/lang/String;
  astore 22
  bipush 6
  istore 8
  iload 8
  anewarray java/lang/Object
  astore 9
  aload_0
  astore 4
  aload 4
  getfield com/admogo/AdMogoManager/keyAdMogo Ljava/lang/String;
  astore 10
  iconst_0
  istore 8
  aload 9
  iload 8
  aload 10
  aastore
  iconst_1
  istore 8
  aload 9
  iload 8
  aload_1
  aastore
  aload_0
  astore 4
  aload 4
  getfield com/admogo/AdMogoManager/deviceIDHash Ljava/lang/String;
  astore 10
  iconst_2
  istore 8
  aload 9
  iload 8
  aload 10
  aastore
  aload_0
  astore 4
  aload 4
  getfield com/admogo/AdMogoManager/adType I
  istore 4
  iload 4
  istore 21
  iload 4
  invokestatic java/lang/Integer/valueOf(I)Ljava/lang/Integer;
  astore 11
  iconst_3
  istore 8
  aload 9
  iload 8
  aload 11
  aastore
  aload_0
  astore 4
  aload 4
  getfield com/admogo/AdMogoManager/getCountryCode Ljava/lang/String;
  astore 10
  iconst_4
  istore 8
  aload 9
  iload 8
  aload 10
  aastore
  aload_0
  astore 4
  aload 4
  getfield com/admogo/AdMogoManager/networkType Ljava/lang/String;
  astore 10
  iconst_5
  istore 8
  aload 9
  iload 8
  aload 10
  aastore
  aload 22
  astore 4
  aload 4
  aload 9
  invokestatic java/lang/String/format(Ljava/lang/String;[Ljava/lang/Object;)Ljava/lang/String;
  astore 10
  goto Label5
Label7:
  getstatic com/admogo/util/AdMogoUtil/urlCustom Ljava/lang/String;
  astore 22
  iconst_5
  istore 8
  iload 8
  anewarray java/lang/Object
  astore 9
  aload_0
  astore 4
  aload 4
  getfield com/admogo/AdMogoManager/keyAdMogo Ljava/lang/String;
  astore 10
  iconst_0
  istore 8
  aload 9
  iload 8
  aload 10
  aastore
  iconst_1
  istore 8
  aload 9
  iload 8
  aload_1
  aastore
  aload_0
  astore 4
  aload 4
  getfield com/admogo/AdMogoManager/deviceIDHash Ljava/lang/String;
  astore 10
  iconst_2
  istore 8
  aload 9
  iload 8
  aload 10
  aastore
  aload_0
  astore 4
  aload 4
  getfield com/admogo/AdMogoManager/getCountryCode Ljava/lang/String;
  astore 10
  iconst_3
  istore 8
  aload 9
  iload 8
  aload 10
  aastore
  aload_0
  astore 4
  aload 4
  getfield com/admogo/AdMogoManager/adType I
  istore 4
  iload 4
  istore 21
  iload 4
  invokestatic java/lang/Integer/valueOf(I)Ljava/lang/Integer;
  astore 11
  iconst_4
  istore 8
  aload 9
  iload 8
  aload 11
  aastore
  aload 22
  astore 4
  aload 4
  aload 9
  invokestatic java/lang/String/format(Ljava/lang/String;[Ljava/lang/Object;)Ljava/lang/String;
  astore 10
  goto Label5
Label3:
  aconst_null
  astore 23
  aload 23
  areturn
Label8:
  astore 24
  getstatic com/admogo/util/AdMogoUtil/ADMOGO Ljava/lang/String;
  astore 22
  ldc "Caught IOException in getAd()"
  astore 14
  aload 22
  astore 4
  aload 24
  astore 5
  aload 4
  aload 14
  aload 5
  invokestatic android/util/Log/e(Ljava/lang/String;Ljava/lang/String;Ljava/lang/Throwable;)I
  pop
  goto Label3
  nop
.end <method>

.method private getRandomRation(Lcom/admogo/obj/Ration;)Lcom/admogo/obj/Ration;
.limit locals 33
.limit stack 200
  nop
  new java/util/Random
  astore 5
  aload 5
  invokespecial java/util/Random/<init>()V
  ldc2_w 100.000000000000000
  dstore 6
  aload_0
  astore_2
  aload_2
  dload 6
  putfield com/admogo/AdMogoManager/totalWeight D
  aload_1
  astore_2
  new java/lang/NoClassDefFoundError
  dup
  invokespecial java/lang/NoClassDefFoundError/<init>()V
  athrow
  iload_1
  ifeq Label0
  aload_0
  astore_2
  aload_2
  getfield com/admogo/AdMogoManager/extra Lcom/admogo/obj/Extra;
  astore 8
  aload 8
  getfield com/admogo/obj/Extra/improveClick I
  istore 9
  dload 9
  invokestatic app/DummyClass/invokeIfStmt(D)V
  iload 9
  ifeq Label0
  aload_0
  astore_2
  aload_2
  getfield com/admogo/AdMogoManager/isFillRationList Z
  istore 10
  iload 10
  invokestatic app/DummyClass/invokeIfStmt(Z)V
  iload 10
  ifeq Label1
Label0:
  aload 5
  invokevirtual java/util/Random/nextDouble()D
  dstore 11
  aload_0
  astore_2
  aload_2
  getfield com/admogo/AdMogoManager/totalWeight D
  dstore 13
  dload 11
  dload 13
  dmul
  dstore 11
  ldc2_w 0.000000000000000
  dstore 13
  getstatic com/admogo/util/AdMogoUtil/ADMOGO Ljava/lang/String;
  astore 15
  new java/lang/StringBuilder
  astore 16
  ldc "Dart is <"
  astore 17
  aload 16
  aload 17
  invokespecial java/lang/StringBuilder/<init>(Ljava/lang/String;)V
  aload 16
  dload 11
  invokevirtual java/lang/StringBuilder/append(D)Ljava/lang/StringBuilder;
  astore 16
  ldc "> of <"
  astore 17
  aload 16
  aload 17
  invokevirtual java/lang/StringBuilder/append(Ljava/lang/String;)Ljava/lang/StringBuilder;
  astore 16
  aload_0
  astore_2
  aload_2
  getfield com/admogo/AdMogoManager/totalWeight D
  dstore_2
  dload_2
  dstore 18
  dload 18
  dstore_2
  aload 16
  dload_2
  invokevirtual java/lang/StringBuilder/append(D)Ljava/lang/StringBuilder;
  astore 16
  ldc ">"
  astore 17
  aload 16
  aload 17
  invokevirtual java/lang/StringBuilder/append(Ljava/lang/String;)Ljava/lang/StringBuilder;
  astore 16
  aload 16
  invokevirtual java/lang/StringBuilder/toString()Ljava/lang/String;
  astore 20
  aload 20
  astore_2
  aload 15
  aload_2
  invokestatic android/util/Log/d(Ljava/lang/String;Ljava/lang/String;)I
  pop
  aload_0
  astore_2
  aload_2
  invokevirtual com/admogo/AdMogoManager/isFillRaitonList()Z
  istore 10
  iload 10
  invokestatic app/DummyClass/invokeIfStmt(Z)V
  iload 10
  ifeq Label2
  aload_0
  astore_2
  aload_2
  getfield com/admogo/AdMogoManager/fillRationsList Ljava/util/List;
  astore_2
  aload_2
  astore 21
  aload 21
  astore_2
  aload_2
  invokeinterface java/util/List/iterator()Ljava/util/Iterator; 1
  astore 22
Label4:
  aconst_null
  astore_1
Label5:
  aload 22
  astore_2
  aload_2
  invokeinterface java/util/Iterator/hasNext()Z 1
  istore 10
  iload 10
  invokestatic app/DummyClass/invokeIfStmt(Z)V
  iload 10
  ifne Label3
Label6:
  aload_1
  astore_2
  aload_0
  astore_3
  aload_3
  aload_2
  putfield com/admogo/AdMogoManager/randomRation Lcom/admogo/obj/Ration;
  aload_1
  areturn
Label2:
  aload_0
  astore_2
  aload_2
  getfield com/admogo/AdMogoManager/rationsList Ljava/util/List;
  astore_2
  aload_2
  astore 21
  aload 21
  astore_2
  aload_2
  invokeinterface java/util/List/iterator()Ljava/util/Iterator; 1
  astore 22
  goto Label4
Label3:
  aload 22
  astore_2
  aload_2
  invokeinterface java/util/Iterator/next()Ljava/lang/Object; 1
  astore 23
  aload 23
  astore 24
  aload 24
  checkcast com/admogo/obj/Ration
  astore 24
  aload 24
  astore_1
  aload_1
  astore_2
  aload_2
  getfield com/admogo/obj/Ration/weight D
  dstore_2
  dload_2
  dstore 18
  dload 18
  dstore_2
  dload 13
  dload_2
  dadd
  dstore 13
  dload 13
  dload 11
  dcmpl
  istore 25
  iload 25
  istore_2
  dload_2
  invokestatic app/DummyClass/invokeIfStmt(D)V
  iload 25
  iflt Label5
  goto Label6
Label1:
  ldc2_w 0.000000000000000
  dstore 13
  aload_0
  astore_2
  aload_2
  getfield com/admogo/AdMogoManager/tempRationsList Ljava/util/List;
  astore_2
  aload_2
  astore 21
  aload 21
  astore_2
  aload_2
  invokeinterface java/util/List/clear()V 1
  iconst_0
  dstore 9
Label11:
  aload_0
  astore_2
  aload_2
  getfield com/admogo/AdMogoManager/rationsList Ljava/util/List;
  astore_2
  aload_2
  astore 21
  aload 21
  astore_2
  aload_2
  invokeinterface java/util/List/size()I 1
  istore 26
  dload 9
  invokestatic app/DummyClass/invokeIfStmt(D)V
  iload 26
  istore_2
  dload_2
  invokestatic app/DummyClass/invokeIfStmt(D)V
  iload 26
  istore_2
  iload 9
  iload_2
  if_icmplt Label7
  aload_1
  astore_2
  aload_2
  getfield com/admogo/obj/Ration/bf I
  istore_2
  iload_2
  istore 26
  dload_2
  invokestatic app/DummyClass/invokeIfStmt(D)V
  iconst_1
  istore 27
  iload 26
  istore_2
  iload 27
  istore_3
  iload_2
  iload_3
  if_icmpeq Label8
  aload_1
  astore_2
  aload_2
  getfield com/admogo/obj/Ration/weight D
  dstore 13
  aload_0
  astore_2
  aload_2
  getfield com/admogo/AdMogoManager/tempRationsList Ljava/util/List;
  astore_2
  aload_2
  astore 21
  aload 21
  astore_2
  aload_1
  astore_3
  aload_2
  aload_3
  invokeinterface java/util/List/add(Ljava/lang/Object;)Z 2
  pop
Label8:
  aload 5
  invokevirtual java/util/Random/nextDouble()D
  dstore 18
  aload_0
  astore_2
  aload_2
  getfield com/admogo/AdMogoManager/totalWeight D
  dstore 11
  dload 11
  dload 13
  dsub
  dstore 13
  dload 18
  dstore_2
  dload_2
  dload 13
  dmul
  dstore_2
  dload_2
  dstore 18
  ldc2_w 0.000000000000000
  dstore 13
  aload_0
  astore_2
  aload_2
  getfield com/admogo/AdMogoManager/tempRationsList Ljava/util/List;
  astore_2
  aload_2
  astore 21
  aload 21
  astore_2
  aload_2
  invokeinterface java/util/List/iterator()Ljava/util/Iterator; 1
  astore 22
  aload 22
  astore_2
  aload_0
  astore_3
  aload_3
  aload_2
  putfield com/admogo/AdMogoManager/rollovers Ljava/util/Iterator;
  getstatic com/admogo/util/AdMogoUtil/ADMOGO Ljava/lang/String;
  astore 20
  new java/lang/StringBuilder
  astore 16
  ldc "Dart is <"
  astore 17
  aload 16
  aload 17
  invokespecial java/lang/StringBuilder/<init>(Ljava/lang/String;)V
  dload 18
  dstore_2
  aload 16
  dload_2
  invokevirtual java/lang/StringBuilder/append(D)Ljava/lang/StringBuilder;
  astore 16
  ldc "> of <"
  astore 17
  aload 16
  aload 17
  invokevirtual java/lang/StringBuilder/append(Ljava/lang/String;)Ljava/lang/StringBuilder;
  astore 16
  aload_0
  astore_2
  aload_2
  getfield com/admogo/AdMogoManager/totalWeight D
  dstore 11
  aload 16
  dload 11
  invokevirtual java/lang/StringBuilder/append(D)Ljava/lang/StringBuilder;
  astore 16
  ldc ">"
  astore 17
  aload 16
  aload 17
  invokevirtual java/lang/StringBuilder/append(Ljava/lang/String;)Ljava/lang/StringBuilder;
  astore 16
  aload 16
  invokevirtual java/lang/StringBuilder/toString()Ljava/lang/String;
  astore 15
  aload 20
  astore_2
  aload_2
  aload 15
  invokestatic android/util/Log/d(Ljava/lang/String;Ljava/lang/String;)I
  pop
  aload_0
  astore_2
  aload_2
  getfield com/admogo/AdMogoManager/tempRationsList Ljava/util/List;
  astore_2
  aload_2
  astore 21
  aload 21
  astore_2
  aload_2
  invokeinterface java/util/List/iterator()Ljava/util/Iterator; 1
  astore 22
  aconst_null
  astore_1
Label12:
  aload 22
  astore_2
  aload_2
  invokeinterface java/util/Iterator/hasNext()Z 1
  istore 10
  iload 10
  invokestatic app/DummyClass/invokeIfStmt(Z)V
  iload 10
  ifne Label9
Label13:
  aload_1
  astore_2
  aload_0
  astore_3
  aload_3
  aload_2
  putfield com/admogo/AdMogoManager/randomRation Lcom/admogo/obj/Ration;
  aload_1
  areturn
Label7:
  aload_0
  astore_2
  aload_2
  getfield com/admogo/AdMogoManager/rationsList Ljava/util/List;
  astore_2
  aload_2
  astore 21
  aload 21
  astore_2
  aload_2
  iload 9
  invokeinterface java/util/List/get(I)Ljava/lang/Object; 2
  astore 23
  aload 23
  astore 29
  aload 29
  checkcast com/admogo/obj/Ration
  astore 29
  aload 29
  astore 28
  aload 28
  astore_2
  aload_2
  getfield com/admogo/obj/Ration/nid Ljava/lang/String;
  astore_2
  aload_2
  astore 20
  aload_1
  astore_2
  aload_2
  getfield com/admogo/obj/Ration/nid Ljava/lang/String;
  astore 15
  aload 20
  astore_2
  aload_2
  aload 15
  invokevirtual java/lang/String/equals(Ljava/lang/Object;)Z
  istore 10
  iload 10
  invokestatic app/DummyClass/invokeIfStmt(Z)V
  iload 10
  ifne Label10
  aload_0
  astore_2
  aload_2
  getfield com/admogo/AdMogoManager/tempRationsList Ljava/util/List;
  astore_2
  aload_2
  astore 21
  aload_0
  astore_2
  aload_2
  getfield com/admogo/AdMogoManager/rationsList Ljava/util/List;
  astore_2
  aload_2
  astore 30
  aload 30
  astore_2
  aload_2
  iload 9
  invokeinterface java/util/List/get(I)Ljava/lang/Object; 2
  astore 23
  aload 23
  astore 31
  aload 31
  checkcast com/admogo/obj/Ration
  astore 31
  aload 31
  astore 28
  aload 21
  astore_2
  aload 28
  astore_3
  aload_2
  aload_3
  invokeinterface java/util/List/add(Ljava/lang/Object;)Z 2
  pop
Label10:
  iload 9
  iconst_1
  iadd
  istore 9
  goto Label11
Label9:
  aload 22
  astore_2
  aload_2
  invokeinterface java/util/Iterator/next()Ljava/lang/Object; 1
  astore 23
  aload 23
  astore 32
  aload 32
  checkcast com/admogo/obj/Ration
  astore 32
  aload 32
  astore_1
  aload_1
  astore_2
  aload_2
  getfield com/admogo/obj/Ration/weight D
  dstore 11
  dload 13
  dload 11
  dadd
  dstore 13
  dload 13
  dload 18
  dcmpl
  istore 25
  iload 25
  istore_2
  dload_2
  invokestatic app/DummyClass/invokeIfStmt(D)V
  iload 25
  iflt Label12
  goto Label13
  nop
.end <method>

.method public getRation(Lcom/admogo/obj/Ration;)Lcom/admogo/obj/Ration;
.limit locals 5
.limit stack 200
  nop
  aload_0
  getfield com/admogo/AdMogoManager/extra Lcom/admogo/obj/Extra;
  astore_2
  aload_2
  getfield com/admogo/obj/Extra/adFirst I
  istore_3
  new java/lang/NoClassDefFoundError
  dup
  invokespecial java/lang/NoClassDefFoundError/<init>()V
  athrow
  iload_3
  ifeq Label0
  aload_0
  getfield com/admogo/AdMogoManager/adFirstRation Lcom/admogo/obj/Ration;
  astore 4
  aload 4
  invokestatic app/DummyClass/invokeIfStmt(Ljava/lang/Object;)V
  aload 4
  ifnull Label0
  aload_0
  getfield com/admogo/AdMogoManager/adFirstRation Lcom/admogo/obj/Ration;
  astore 4
  aload 4
  areturn
Label0:
  aload_0
  aload_1
  invokespecial com/admogo/AdMogoManager/getRandomRation(Lcom/admogo/obj/Ration;)Lcom/admogo/obj/Ration;
  astore_1
  aload_1
  areturn
  nop
.end <method>

.method public getRollover()Lcom/admogo/obj/Ration;
.limit locals 12
.limit stack 200
  nop
  aload_0
  getfield com/admogo/AdMogoManager/rollovers Ljava/util/Iterator;
  astore_1
  new java/lang/NoClassDefFoundError
  dup
  invokespecial java/lang/NoClassDefFoundError/<init>()V
  athrow
  iload_1
  ifne Label0
  aconst_null
  astore_2
Label1:
  aload_2
  areturn
Label0:
  aconst_null
  astore_2
  aload_0
  getfield com/admogo/AdMogoManager/rollovers Ljava/util/Iterator;
  astore_1
  aload_1
  invokeinterface java/util/Iterator/hasNext()Z 1
  istore_3
  iload_3
  invokestatic app/DummyClass/invokeIfStmt(Z)V
  iload_3
  ifeq Label1
  aload_0
  getfield com/admogo/AdMogoManager/rollovers Ljava/util/Iterator;
  astore_1
  aload_1
  invokeinterface java/util/Iterator/next()Ljava/lang/Object; 1
  astore 4
  aload 4
  astore 5
  aload 5
  checkcast com/admogo/obj/Ration
  astore 5
  aload 5
  astore_2
  aload_2
  putstatic com/admogo/AdMogoManager/lastRation Lcom/admogo/obj/Ration;
  aload_0
  getfield com/admogo/AdMogoManager/randomRation Lcom/admogo/obj/Ration;
  astore 6
  aload 6
  invokestatic app/DummyClass/invokeIfStmt(Ljava/lang/Object;)V
  aload 6
  ifnull Label1
  aload_0
  getfield com/admogo/AdMogoManager/randomRation Lcom/admogo/obj/Ration;
  astore 6
  aload 6
  getfield com/admogo/obj/Ration/type I
  istore 7
  aload_2
  getfield com/admogo/obj/Ration/type I
  istore 8
  dload 7
  invokestatic app/DummyClass/invokeIfStmt(D)V
  dload 8
  invokestatic app/DummyClass/invokeIfStmt(D)V
  iload 7
  iload 8
  if_icmpne Label1
  aload_0
  getfield com/admogo/AdMogoManager/rollovers Ljava/util/Iterator;
  astore_1
  aload_1
  invokeinterface java/util/Iterator/hasNext()Z 1
  istore_3
  iload_3
  invokestatic app/DummyClass/invokeIfStmt(Z)V
  iload_3
  ifeq Label2
  aload_0
  getfield com/admogo/AdMogoManager/rollovers Ljava/util/Iterator;
  astore_1
  aload_1
  invokeinterface java/util/Iterator/next()Ljava/lang/Object; 1
  astore 4
  aload 4
  astore 9
  aload 9
  checkcast com/admogo/obj/Ration
  astore 9
  aload 9
  astore_2
  aload_2
  areturn
Label2:
  aload_0
  getfield com/admogo/AdMogoManager/isFillRationList Z
  istore_3
  iload_3
  invokestatic app/DummyClass/invokeIfStmt(Z)V
  iload_3
  ifeq Label3
  iconst_1
  istore 10
  aload_0
  iload 10
  putfield com/admogo/AdMogoManager/fillRListEmpty Z
Label3:
  aconst_null
  astore 11
  aload 11
  areturn
  nop
.end <method>

.method public isFillRaitonList()Z
.limit locals 2
.limit stack 200
  nop
  aload_0
  getfield com/admogo/AdMogoManager/isFillRationList Z
  istore_1
  iload_1
  ireturn
  nop
.end <method>

.method private mathStr(Ljava/lang/String;Ljava/lang/String;)Z
.limit locals 6
.limit stack 200
  nop
  aload_1
  invokestatic java/util/regex/Pattern/compile(Ljava/lang/String;)Ljava/util/regex/Pattern;
  astore_3
  aload_3
  aload_2
  invokevirtual java/util/regex/Pattern/matcher(Ljava/lang/CharSequence;)Ljava/util/regex/Matcher;
  astore 4
  aload 4
  invokevirtual java/util/regex/Matcher/matches()Z
  istore 5
  iload 5
  ireturn
  nop
.end <method>

.method public offlineConfigurationPriority()V
.limit locals 33
.limit stack 200
  nop
  aload_0
  astore_1
  aload_1
  getfield com/admogo/AdMogoManager/contextReference Ljava/lang/ref/WeakReference;
  astore 7
  aload 7
  invokevirtual java/lang/ref/WeakReference/get()Ljava/lang/Object;
  astore 8
  aload 8
  astore 10
  new java/lang/NoClassDefFoundError
  dup
  invokespecial java/lang/NoClassDefFoundError/<init>()V
  athrow
  aload 10
  astore 9
  aload 9
  invokestatic app/DummyClass/invokeIfStmt(Ljava/lang/Object;)V
  iload 9
  ifne Label0
Label4:
  return
Label0:
  getstatic com/admogo/util/AdMogoUtil/ADMOGO Ljava/lang/String;
  astore 11
  ldc "Using stored config data"
  astore 12
  aload 11
  aload 12
  invokestatic android/util/Log/i(Ljava/lang/String;Ljava/lang/String;)I
  pop
  getstatic com/admogo/AdMogoManager/tempConfig Ljava/util/Hashtable;
  astore 13
  new java/lang/StringBuilder
  astore 14
  aload_0
  astore_1
  aload_1
  getfield com/admogo/AdMogoManager/keyAdMogo Ljava/lang/String;
  astore 15
  aload 15
  invokestatic java/lang/String/valueOf(Ljava/lang/Object;)Ljava/lang/String;
  astore 11
  aload 14
  aload 11
  invokespecial java/lang/StringBuilder/<init>(Ljava/lang/String;)V
  aload_0
  astore_1
  aload_1
  getfield com/admogo/AdMogoManager/adType I
  istore 16
  aload 14
  iload 16
  invokevirtual java/lang/StringBuilder/append(I)Ljava/lang/StringBuilder;
  astore 14
  getstatic com/admogo/AdMogoManager/PREFS_STRING_COUNTRY Ljava/lang/String;
  astore 11
  aload 14
  aload 11
  invokevirtual java/lang/StringBuilder/append(Ljava/lang/String;)Ljava/lang/StringBuilder;
  astore 14
  ldc "tempConfig"
  astore 12
  aload 14
  aload 12
  invokevirtual java/lang/StringBuilder/append(Ljava/lang/String;)Ljava/lang/StringBuilder;
  astore 14
  aload 14
  invokevirtual java/lang/StringBuilder/toString()Ljava/lang/String;
  astore 11
  aload 13
  aload 11
  invokevirtual java/util/Hashtable/get(Ljava/lang/Object;)Ljava/lang/Object;
  astore 8
  aload 8
  astore 17
  aload 17
  checkcast java/lang/String
  astore 17
  aload 17
  astore 11
  aload_0
  astore_1
  aload_1
  getfield com/admogo/AdMogoManager/keyAdMogo Ljava/lang/String;
  astore 15
  iconst_0
  istore 19
  iload 19
  istore_1
  aload 9
  aload 15
  iload_1
  invokevirtual android/content/Context/getSharedPreferences(Ljava/lang/String;I)Landroid/content/SharedPreferences;
  astore 18
  new java/lang/StringBuilder
  astore 14
  aload_0
  astore_1
  aload_1
  getfield com/admogo/AdMogoManager/keyAdMogo Ljava/lang/String;
  astore 15
  aload 15
  invokestatic java/lang/String/valueOf(Ljava/lang/Object;)Ljava/lang/String;
  astore 15
  aload 14
  aload 15
  invokespecial java/lang/StringBuilder/<init>(Ljava/lang/String;)V
  aload_0
  astore_1
  aload_1
  getfield com/admogo/AdMogoManager/adType I
  istore 16
  aload 14
  iload 16
  invokevirtual java/lang/StringBuilder/append(I)Ljava/lang/StringBuilder;
  astore 14
  getstatic com/admogo/AdMogoManager/PREFS_STRING_COUNTRY Ljava/lang/String;
  astore 15
  aload 14
  aload 15
  invokevirtual java/lang/StringBuilder/append(Ljava/lang/String;)Ljava/lang/StringBuilder;
  astore 14
  ldc "timestamp"
  astore 12
  aload 14
  aload 12
  invokevirtual java/lang/StringBuilder/append(Ljava/lang/String;)Ljava/lang/StringBuilder;
  astore 14
  aload 14
  invokevirtual java/lang/StringBuilder/toString()Ljava/lang/String;
  astore 15
  ldc2_w 4294967295
  lstore 22
  aload 18
  astore_1
  lload 22
  lstore_2
  aload_1
  aload 15
  lload_2
  invokeinterface android/content/SharedPreferences/getLong(Ljava/lang/String;J)J 4
  lstore 20
  aload 11
  invokestatic android/text/TextUtils/isEmpty(Ljava/lang/CharSequence;)Z
  istore 24
  iload 24
  istore_1
  iload_1
  invokestatic app/DummyClass/invokeIfStmt(Z)V
  iload 24
  ifeq Label1
  new java/lang/StringBuilder
  astore 14
  aload_0
  astore_1
  aload_1
  getfield com/admogo/AdMogoManager/keyAdMogo Ljava/lang/String;
  astore 11
  aload 11
  invokestatic java/lang/String/valueOf(Ljava/lang/Object;)Ljava/lang/String;
  astore 11
  aload 14
  aload 11
  invokespecial java/lang/StringBuilder/<init>(Ljava/lang/String;)V
  aload_0
  astore_1
  aload_1
  getfield com/admogo/AdMogoManager/adType I
  istore 16
  aload 14
  iload 16
  invokevirtual java/lang/StringBuilder/append(I)Ljava/lang/StringBuilder;
  astore 14
  getstatic com/admogo/AdMogoManager/PREFS_STRING_COUNTRY Ljava/lang/String;
  astore 11
  aload 14
  aload 11
  invokevirtual java/lang/StringBuilder/append(Ljava/lang/String;)Ljava/lang/StringBuilder;
  astore 14
  ldc "config"
  astore 12
  aload 14
  aload 12
  invokevirtual java/lang/StringBuilder/append(Ljava/lang/String;)Ljava/lang/StringBuilder;
  astore 14
  aload 14
  invokevirtual java/lang/StringBuilder/toString()Ljava/lang/String;
  astore 11
  ldc ""
  astore 12
  aload 18
  astore_1
  aload_1
  aload 11
  aload 12
  invokeinterface android/content/SharedPreferences/getString(Ljava/lang/String;Ljava/lang/String;)Ljava/lang/String; 3
  astore 11
  aload 11
  invokestatic android/text/TextUtils/isEmpty(Ljava/lang/CharSequence;)Z
  istore 24
  iload 24
  istore_1
  iload_1
  invokestatic app/DummyClass/invokeIfStmt(Z)V
  iload 24
  ifeq Label2
  aload_0
  astore_1
  aload_1
  invokespecial com/admogo/AdMogoManager/readOfflineFile()Z
  istore 24
  iload 24
  istore_1
  iload_1
  invokestatic app/DummyClass/invokeIfStmt(Z)V
  iload 24
  ifne Label3
  aload_0
  astore_1
  aload_1
  invokevirtual com/admogo/AdMogoManager/fetchConfig()V
  goto Label4
Label2:
  aload_0
  astore_1
  aload_1
  aload 11
  invokespecial com/admogo/AdMogoManager/parseConfigurationString(Ljava/lang/String;)V
Label3:
  aload_0
  astore_1
  aload_1
  getfield com/admogo/AdMogoManager/scheduler Ljava/util/concurrent/ScheduledExecutorService;
  astore_1
  aload_1
  astore 25
  aload_0
  astore_1
  aload_1
  getfield com/admogo/AdMogoManager/GetInfoRunnable Ljava/lang/Runnable;
  astore_1
  aload_1
  astore 26
  getstatic java/util/concurrent/TimeUnit/SECONDS Ljava/util/concurrent/TimeUnit;
  astore 27
  ldc2_w 0
  lstore 22
  aload 25
  astore_1
  aload 26
  astore_2
  lload 22
  lstore_3
  aload 27
  astore 5
  aload_1
  aload_2
  lload_3
  aload 5
  invokeinterface java/util/concurrent/ScheduledExecutorService/schedule(Ljava/lang/Runnable;JLjava/util/concurrent/TimeUnit;)Ljava/util/concurrent/ScheduledFuture; 5
  pop
  goto Label4
Label1:
  aload_0
  astore_1
  aload_1
  aload 11
  invokespecial com/admogo/AdMogoManager/parseConfigurationString(Ljava/lang/String;)V
  invokestatic java/lang/System/currentTimeMillis()J
  lstore 28
  getstatic com/admogo/AdMogoManager/configExpireTimeout J
  lstore 30
  lload 30
  lstore_1
  lload 20
  lstore_3
  lload_1
  lload_3
  ladd
  lstore_1
  lload_1
  lstore 30
  lload 28
  lload 30
  lcmp
  istore 32
  iload 32
  istore_1
  dload_1
  invokestatic app/DummyClass/invokeIfStmt(D)V
  iload 32
  iflt Label4
  aload_0
  astore_1
  aload_1
  invokevirtual com/admogo/AdMogoManager/fetchConfig()V
  goto Label4
  nop
.end <method>

.method private parseCityJsonString(Ljava/lang/String;)Ljava/lang/String;
.limit locals 15
.limit stack 200
  .catch  org/json/JSONException <from> Label7 <to> Label8 <using> Label6
  .catch  org/json/JSONException <from> Label0 <to> Label9 <using> Label6
  nop
  ldc ""
  astore_2
  ldc ""
  astore_3
  new org/json/JSONObject
  astore 4
Label7:
  aload 4
  aload_1
  invokespecial org/json/JSONObject/<init>(Ljava/lang/String;)V
  ldc "results"
  astore 6
  aload 4
  aload 6
  invokevirtual org/json/JSONObject/getJSONArray(Ljava/lang/String;)Lorg/json/JSONArray;
  astore 5
  iconst_0
  istore 7
  aload 5
  iload 7
  invokevirtual org/json/JSONArray/getJSONObject(I)Lorg/json/JSONObject;
  astore 4
  ldc "address_components"
  astore 6
  aload 4
  aload 6
  invokevirtual org/json/JSONObject/getJSONArray(Ljava/lang/String;)Lorg/json/JSONArray;
  astore 5
  iconst_0
  istore 8
Label4:
  aload 5
  invokevirtual org/json/JSONArray/length()I
  istore 9
Label8:
  new java/lang/NoClassDefFoundError
  dup
  invokespecial java/lang/NoClassDefFoundError/<init>()V
  athrow
  dload 9
  invokestatic app/DummyClass/invokeIfStmt(D)V
  iload 8
  iload 9
  if_icmplt Label0
  aload_2
  invokestatic android/text/TextUtils/isEmpty(Ljava/lang/CharSequence;)Z
  istore 10
  iload 10
  invokestatic app/DummyClass/invokeIfStmt(Z)V
  iload 10
  ifne Label1
  aload_3
  invokestatic android/text/TextUtils/isEmpty(Ljava/lang/CharSequence;)Z
  istore 10
  iload 10
  invokestatic app/DummyClass/invokeIfStmt(Z)V
  iload 10
  ifeq Label2
Label1:
  ldc ""
  astore 6
  aload 6
  areturn
Label0:
  aload 5
  iload 8
  invokevirtual org/json/JSONArray/getJSONObject(I)Lorg/json/JSONObject;
  astore 4
  ldc "types"
  astore 6
  aload 4
  aload 6
  invokevirtual org/json/JSONObject/getJSONArray(Ljava/lang/String;)Lorg/json/JSONArray;
  astore 11
  iconst_0
  istore 7
  aload 11
  iload 7
  invokevirtual org/json/JSONArray/getString(I)Ljava/lang/String;
  astore_1
  ldc "locality"
  astore 6
  aload_1
  aload 6
  invokevirtual java/lang/String/equals(Ljava/lang/Object;)Z
  istore 10
  iload 10
  invokestatic app/DummyClass/invokeIfStmt(Z)V
  iload 10
  ifeq Label3
  ldc "long_name"
  astore 6
  aload 4
  aload 6
  invokevirtual org/json/JSONObject/getString(Ljava/lang/String;)Ljava/lang/String;
  astore_2
Label5:
  iload 8
  iconst_1
  iadd
  istore 8
  goto Label4
Label3:
  ldc "administrative_area_level_1"
  astore 6
  aload_1
  aload 6
  invokevirtual java/lang/String/equals(Ljava/lang/Object;)Z
  istore 10
  iload 10
  invokestatic app/DummyClass/invokeIfStmt(Z)V
  iload 10
  ifeq Label5
  ldc "long_name"
  astore 6
  aload 4
  aload 6
  invokevirtual org/json/JSONObject/getString(Ljava/lang/String;)Ljava/lang/String;
  astore 12
Label9:
  aload 12
  astore_3
  goto Label5
Label6:
  astore 13
  getstatic com/admogo/util/AdMogoUtil/ADMOGO Ljava/lang/String;
  astore 12
  ldc "Caught JSONException in parseCityJsonString()"
  astore 6
  new java/lang/NoClassDefFoundError
  dup
  invokespecial java/lang/NoClassDefFoundError/<init>()V
  athrow
  ldc ""
  astore 6
  aload 6
  areturn
Label2:
  new java/lang/StringBuilder
  astore 14
  aload_3
  invokestatic java/lang/String/valueOf(Ljava/lang/Object;)Ljava/lang/String;
  astore 12
  aload 14
  aload 12
  invokespecial java/lang/StringBuilder/<init>(Ljava/lang/String;)V
  ldc ","
  astore 6
  aload 14
  aload 6
  invokevirtual java/lang/StringBuilder/append(Ljava/lang/String;)Ljava/lang/StringBuilder;
  astore 14
  aload 14
  aload_2
  invokevirtual java/lang/StringBuilder/append(Ljava/lang/String;)Ljava/lang/StringBuilder;
  astore 14
  aload 14
  invokevirtual java/lang/StringBuilder/toString()Ljava/lang/String;
  astore 12
  aload 12
  areturn
  nop
.end <method>

.method private parseConfigurationString(Ljava/lang/String;)V
.limit locals 12
.limit stack 200
  .catch  java/lang/NullPointerException <from> Label3 <to> Label4 <using> Label1
  .catch  org/json/JSONException <from> Label3 <to> Label4 <using> Label2
  .catch  java/lang/Exception <from> Label4 <to> Label0 <using> Label5
  .catch  java/lang/NullPointerException <from> Label6 <to> Label7 <using> Label1
  .catch  org/json/JSONException <from> Label6 <to> Label7 <using> Label2
  .catch  java/lang/NullPointerException <from> Label7 <to> Label8 <using> Label1
  nop
  aload_0
  aload_1
  invokespecial com/admogo/AdMogoManager/saveTempConfig(Ljava/lang/String;)V
  new org/json/JSONObject
  astore_2
Label3:
  aload_2
  aload_1
  invokespecial org/json/JSONObject/<init>(Ljava/lang/String;)V
  ldc "extra"
  astore 4
  aload_2
  aload 4
  invokevirtual org/json/JSONObject/getJSONObject(Ljava/lang/String;)Lorg/json/JSONObject;
  astore_3
  aload_0
  aload_3
  invokespecial com/admogo/AdMogoManager/parseExtraJson(Lorg/json/JSONObject;)V
  ldc "rations"
  astore 4
  aload_2
  aload 4
  invokevirtual org/json/JSONObject/getJSONArray(Ljava/lang/String;)Lorg/json/JSONArray;
  astore 5
  aload_0
  aload 5
  invokespecial com/admogo/AdMogoManager/parseRationsJson(Lorg/json/JSONArray;)V
Label4:
  ldc "bf"
  astore 4
  aload_2
  aload 4
  invokevirtual org/json/JSONObject/getJSONArray(Ljava/lang/String;)Lorg/json/JSONArray;
  astore 5
  aload_0
  aload 5
  invokespecial com/admogo/AdMogoManager/parseFillRationsJson(Lorg/json/JSONArray;)V
Label0:
  return
Label5:
  astore 6
  new java/util/ArrayList
  astore 7
Label6:
  aload 7
  invokespecial java/util/ArrayList/<init>()V
Label7:
  aload_0
  aload 7
  putfield com/admogo/AdMogoManager/fillRationsList Ljava/util/List;
Label8:
  goto Label0
Label2:
  astore 8
  getstatic com/admogo/util/AdMogoUtil/ADMOGO Ljava/lang/String;
  astore 9
  ldc "Unable to parse response from JSON. This may or may not be fatal."
  astore 4
  new java/lang/NoClassDefFoundError
  dup
  invokespecial java/lang/NoClassDefFoundError/<init>()V
  athrow
  new com/admogo/obj/Extra
  astore 10
  aload 10
  invokespecial com/admogo/obj/Extra/<init>()V
  aload_0
  aload 10
  putfield com/admogo/AdMogoManager/extra Lcom/admogo/obj/Extra;
  goto Label0
Label1:
  astore 11
  getstatic com/admogo/util/AdMogoUtil/ADMOGO Ljava/lang/String;
  astore 9
  ldc "Unable to parse response from JSON. This may or may not be fatal."
  astore 4
  new java/lang/NoClassDefFoundError
  dup
  invokespecial java/lang/NoClassDefFoundError/<init>()V
  athrow
  new com/admogo/obj/Extra
  astore 10
  aload 10
  invokespecial com/admogo/obj/Extra/<init>()V
  aload_0
  aload 10
  putfield com/admogo/AdMogoManager/extra Lcom/admogo/obj/Extra;
  goto Label0
  nop
.end <method>

.method private parseExtraJson(Lorg/json/JSONObject;)V
.limit locals 31
.limit stack 200
  .catch  org/json/JSONException <from> Label11 <to> Label12 <using> Label10
  .catch  java/lang/Exception <from> Label14 <to> Label3 <using> Label13
  .catch  org/json/JSONException <from> Label15 <to> Label0 <using> Label10
  .catch  org/json/JSONException <from> Label21 <to> Label22 <using> Label10
  nop
  new com/admogo/obj/Extra
  astore 6
  aload 6
  invokespecial com/admogo/obj/Extra/<init>()V
Label11:
  ldc "cycle_time"
  astore 8
  aload_1
  astore_2
  aload_2
  aload 8
  invokevirtual org/json/JSONObject/getInt(Ljava/lang/String;)I
  istore 7
  aload 6
  iload 7
  putfield com/admogo/obj/Extra/cycleTime I
  ldc "location_on"
  astore 8
  aload_1
  astore_2
  aload_2
  aload 8
  invokevirtual org/json/JSONObject/getInt(Ljava/lang/String;)I
  istore 7
  aload 6
  iload 7
  putfield com/admogo/obj/Extra/locationOn I
  ldc "transition"
  astore 8
  aload_1
  astore_2
  aload_2
  aload 8
  invokevirtual org/json/JSONObject/getInt(Ljava/lang/String;)I
  istore 7
  aload 6
  iload 7
  putfield com/admogo/obj/Extra/transition I
  ldc "improve_click"
  astore 8
  aload_1
  astore_2
  aload_2
  aload 8
  invokevirtual org/json/JSONObject/getInt(Ljava/lang/String;)I
  istore 7
Label12:
  aload 6
  iload 7
  putfield com/admogo/obj/Extra/improveClick I
Label14:
  ldc "closead_on"
  astore 8
  aload_1
  astore_2
  aload_2
  aload 8
  invokevirtual org/json/JSONObject/getInt(Ljava/lang/String;)I
  istore 7
  aload 6
  iload 7
  putfield com/admogo/obj/Extra/closeAdOn I
Label3:
  aload_0
  astore_2
  aload_2
  getfield com/admogo/AdMogoManager/ifGetInfo Z
  istore 9
  new java/lang/NoClassDefFoundError
  dup
  invokespecial java/lang/NoClassDefFoundError/<init>()V
  athrow
  iload 9
  ifeq Label0
  aload 6
  getfield com/admogo/obj/Extra/locationOn I
  istore 7
  dload 7
  invokestatic app/DummyClass/invokeIfStmt(D)V
  iload 7
  ifne Label0
Label15:
  iconst_0
  istore 10
  aload_0
  astore_2
  aload_2
  iload 10
  invokevirtual com/admogo/AdMogoManager/sendLocationData(Z)V
Label0:
  ldc "adf"
  astore 8
  aload_1
  astore_2
  aload_2
  aload 8
  invokevirtual org/json/JSONObject/getInt(Ljava/lang/String;)I
  istore 7
  aload 6
  iload 7
  putfield com/admogo/obj/Extra/adFirst I
Label5:
  ldc "timestamp"
  astore 8
  aload_1
  astore_2
  aload_2
  aload 8
  invokevirtual org/json/JSONObject/getString(Ljava/lang/String;)Ljava/lang/String;
  astore 11
  aload 6
  aload 11
  putfield com/admogo/obj/Extra/timestamp Ljava/lang/String;
Label6:
  ldc "version"
  astore 8
  aload_1
  astore_2
  aload_2
  aload 8
  invokevirtual org/json/JSONObject/getString(Ljava/lang/String;)Ljava/lang/String;
  astore 11
  aload 11
  invokestatic android/text/TextUtils/isEmpty(Ljava/lang/CharSequence;)Z
  istore 9
  iload 9
  invokestatic app/DummyClass/invokeIfStmt(Z)V
  iload 9
  ifeq Label1
  iconst_m1
  istore 10
  aload 6
  iload 10
  putfield com/admogo/obj/Extra/version I
Label7:
  ldc "sdkver"
  astore 8
  aload_1
  astore_2
  aload_2
  aload 8
  invokevirtual org/json/JSONObject/getString(Ljava/lang/String;)Ljava/lang/String;
  astore 11
  aload 11
  invokestatic android/text/TextUtils/isEmpty(Ljava/lang/CharSequence;)Z
  istore 9
  iload 9
  invokestatic app/DummyClass/invokeIfStmt(Z)V
  iload 9
  ifeq Label2
  iconst_0
  istore 10
  aload 6
  iload 10
  putfield com/admogo/obj/Extra/SDKversion I
Label8:
  ldc "package"
  astore 8
  aload_1
  astore_2
  aload_2
  aload 8
  invokevirtual org/json/JSONObject/getString(Ljava/lang/String;)Ljava/lang/String;
  astore 11
  aload 6
  aload 11
  putfield com/admogo/obj/Extra/packageName Ljava/lang/String;
Label9:
  aload_0
  astore_2
  aload_2
  getfield com/admogo/AdMogoManager/contextReference Ljava/lang/ref/WeakReference;
  astore 12
Label21:
  aload 12
  invokevirtual java/lang/ref/WeakReference/get()Ljava/lang/Object;
  astore 13
  aload 13
  astore 15
  aload 15
  checkcast android/content/Context
  astore 15
  aload 15
  astore 14
  aload_0
  astore_2
  aload_2
  getfield com/admogo/AdMogoManager/keyAdMogo Ljava/lang/String;
  astore 11
  iconst_0
  istore 10
  aload 14
  aload 11
  iload 10
  invokevirtual android/content/Context/getSharedPreferences(Ljava/lang/String;I)Landroid/content/SharedPreferences;
  astore 16
  aload 16
  invokeinterface android/content/SharedPreferences/edit()Landroid/content/SharedPreferences$Editor; 1
  astore 17
  new java/lang/StringBuilder
  astore 18
  aload_0
  astore_2
  aload_2
  getfield com/admogo/AdMogoManager/keyAdMogo Ljava/lang/String;
  astore 11
  aload 11
  invokestatic java/lang/String/valueOf(Ljava/lang/Object;)Ljava/lang/String;
  astore 11
  aload 18
  astore_2
  aload_2
  aload 11
  invokespecial java/lang/StringBuilder/<init>(Ljava/lang/String;)V
  aload_0
  astore_2
  aload_2
  getfield com/admogo/AdMogoManager/adType I
  istore 7
  aload 18
  astore_2
  aload_2
  iload 7
  invokevirtual java/lang/StringBuilder/append(I)Ljava/lang/StringBuilder;
  astore 18
  getstatic com/admogo/AdMogoManager/PREFS_STRING_COUNTRY Ljava/lang/String;
  astore 11
  aload 18
  astore_2
  aload_2
  aload 11
  invokevirtual java/lang/StringBuilder/append(Ljava/lang/String;)Ljava/lang/StringBuilder;
  astore 18
  ldc "getInfoTime"
  astore 8
  aload 18
  astore_2
  aload_2
  aload 8
  invokevirtual java/lang/StringBuilder/append(Ljava/lang/String;)Ljava/lang/StringBuilder;
  astore 18
  aload 18
  astore_2
  aload_2
  invokevirtual java/lang/StringBuilder/toString()Ljava/lang/String;
  astore 11
  aload 6
  getfield com/admogo/obj/Extra/timestamp Ljava/lang/String;
  astore_2
  aload_2
  astore 19
  aload 19
  astore_2
  aload 17
  aload 11
  aload_2
  invokeinterface android/content/SharedPreferences$Editor/putString(Ljava/lang/String;Ljava/lang/String;)Landroid/content/SharedPreferences$Editor; 3
  pop
  new java/lang/StringBuilder
  astore 18
  aload_0
  astore_2
  aload_2
  getfield com/admogo/AdMogoManager/keyAdMogo Ljava/lang/String;
  astore_2
  aload_2
  astore 19
  aload 19
  astore_2
  aload_2
  invokestatic java/lang/String/valueOf(Ljava/lang/Object;)Ljava/lang/String;
  astore 19
  aload 18
  astore_2
  aload 19
  astore_3
  aload_2
  aload_3
  invokespecial java/lang/StringBuilder/<init>(Ljava/lang/String;)V
  aload_0
  astore_2
  aload_2
  getfield com/admogo/AdMogoManager/adType I
  istore 7
  aload 18
  astore_2
  aload_2
  iload 7
  invokevirtual java/lang/StringBuilder/append(I)Ljava/lang/StringBuilder;
  astore 18
  getstatic com/admogo/AdMogoManager/PREFS_STRING_COUNTRY Ljava/lang/String;
  astore 19
  aload 18
  astore_2
  aload 19
  astore_3
  aload_2
  aload_3
  invokevirtual java/lang/StringBuilder/append(Ljava/lang/String;)Ljava/lang/StringBuilder;
  astore 18
  ldc "timestamp"
  astore 8
  aload 18
  astore_2
  aload_2
  aload 8
  invokevirtual java/lang/StringBuilder/append(Ljava/lang/String;)Ljava/lang/StringBuilder;
  astore 18
  aload 18
  astore_2
  aload_2
  invokevirtual java/lang/StringBuilder/toString()Ljava/lang/String;
  astore 19
  invokestatic java/lang/System/currentTimeMillis()J
  lstore 20
  aload 19
  astore_2
  lload 20
  lstore_3
  aload 17
  aload_2
  lload_3
  invokeinterface android/content/SharedPreferences$Editor/putLong(Ljava/lang/String;J)Landroid/content/SharedPreferences$Editor; 4
  pop
  aload 17
  invokeinterface android/content/SharedPreferences$Editor/commit()Z 1
  pop
  ldc "background_color_rgb"
  astore 8
  aload_1
  astore_2
  aload_2
  aload 8
  invokevirtual org/json/JSONObject/getJSONObject(Ljava/lang/String;)Lorg/json/JSONObject;
  astore 22
  ldc "red"
  astore 8
  aload 22
  astore_2
  aload_2
  aload 8
  invokevirtual org/json/JSONObject/getInt(Ljava/lang/String;)I
  istore 7
  aload 6
  iload 7
  putfield com/admogo/obj/Extra/bgRed I
  ldc "green"
  astore 8
  aload 22
  astore_2
  aload_2
  aload 8
  invokevirtual org/json/JSONObject/getInt(Ljava/lang/String;)I
  istore 7
  aload 6
  iload 7
  putfield com/admogo/obj/Extra/bgGreen I
  ldc "blue"
  astore 8
  aload 22
  astore_2
  aload_2
  aload 8
  invokevirtual org/json/JSONObject/getInt(Ljava/lang/String;)I
  istore 7
  aload 6
  iload 7
  putfield com/admogo/obj/Extra/bgBlue I
  ldc "alpha"
  astore 8
  aload 22
  astore_2
  aload_2
  aload 8
  invokevirtual org/json/JSONObject/getInt(Ljava/lang/String;)I
  istore 7
  iload 7
  sipush 255
  imul
  istore 7
  aload 6
  iload 7
  putfield com/admogo/obj/Extra/bgAlpha I
  ldc "text_color_rgb"
  astore 8
  aload_1
  astore_2
  aload_2
  aload 8
  invokevirtual org/json/JSONObject/getJSONObject(Ljava/lang/String;)Lorg/json/JSONObject;
  astore 22
  ldc "red"
  astore 8
  aload 22
  astore_2
  aload_2
  aload 8
  invokevirtual org/json/JSONObject/getInt(Ljava/lang/String;)I
  istore 7
  aload 6
  iload 7
  putfield com/admogo/obj/Extra/fgRed I
  ldc "green"
  astore 8
  aload 22
  astore_2
  aload_2
  aload 8
  invokevirtual org/json/JSONObject/getInt(Ljava/lang/String;)I
  istore 7
  aload 6
  iload 7
  putfield com/admogo/obj/Extra/fgGreen I
  ldc "blue"
  astore 8
  aload 22
  astore_2
  aload_2
  aload 8
  invokevirtual org/json/JSONObject/getInt(Ljava/lang/String;)I
  istore 7
  aload 6
  iload 7
  putfield com/admogo/obj/Extra/fgBlue I
  ldc "alpha"
  astore 8
  aload 22
  astore_2
  aload_2
  aload 8
  invokevirtual org/json/JSONObject/getInt(Ljava/lang/String;)I
  istore 7
Label22:
  iload 7
  sipush 255
  imul
  istore 7
  aload 6
  iload 7
  putfield com/admogo/obj/Extra/fgAlpha I
Label4:
  aload_0
  astore_2
  aload_2
  aload 6
  putfield com/admogo/AdMogoManager/extra Lcom/admogo/obj/Extra;
  return
Label13:
  astore 23
  iconst_0
  istore 10
  aload 6
  iload 10
  putfield com/admogo/obj/Extra/closeAdOn I
  goto Label3
Label10:
  astore 24
  getstatic com/admogo/util/AdMogoUtil/ADMOGO Ljava/lang/String;
  astore 19
  ldc "Exception in parsing config.extra JSON. This may or may not be fatal."
  astore 8
  aload 19
  astore_2
  aload 24
  astore_3
  new java/lang/NoClassDefFoundError
  dup
  invokespecial java/lang/NoClassDefFoundError/<init>()V
  athrow
  goto Label4
Label16:
  astore 25
  iconst_0
  istore 10
  aload 6
  iload 10
  putfield com/admogo/obj/Extra/adFirst I
  goto Label5
Label17:
  astore 26
  ldc ""
  astore 8
  aload 6
  aload 8
  putfield com/admogo/obj/Extra/timestamp Ljava/lang/String;
  goto Label6
Label1:
  ldc "version"
  astore 8
  aload_1
  astore_2
  aload_2
  aload 8
  invokevirtual org/json/JSONObject/getString(Ljava/lang/String;)Ljava/lang/String;
  astore 19
  aload 19
  astore_2
  aload_2
  invokestatic java/lang/Integer/valueOf(Ljava/lang/String;)Ljava/lang/Integer;
  astore 27
  aload 27
  astore_2
  aload_2
  invokevirtual java/lang/Integer/intValue()I
  istore 7
  aload 6
  iload 7
  putfield com/admogo/obj/Extra/version I
Label23:
  goto Label7
Label18:
  astore 28
  iconst_m1
  istore 10
  aload 6
  iload 10
  putfield com/admogo/obj/Extra/version I
  goto Label7
Label2:
  ldc "sdkver"
  astore 8
  aload_1
  astore_2
  aload_2
  aload 8
  invokevirtual org/json/JSONObject/getString(Ljava/lang/String;)Ljava/lang/String;
  astore 19
  aload 19
  astore_2
  aload_2
  invokestatic java/lang/Integer/valueOf(Ljava/lang/String;)Ljava/lang/Integer;
  astore 27
  aload 27
  astore_2
  aload_2
  invokevirtual java/lang/Integer/intValue()I
  istore 7
  aload 6
  iload 7
  putfield com/admogo/obj/Extra/SDKversion I
Label24:
  goto Label8
Label19:
  astore 29
  iconst_0
  istore 10
  aload 6
  iload 10
  putfield com/admogo/obj/Extra/SDKversion I
  goto Label8
Label20:
  astore 30
  ldc ""
  astore 8
  aload 6
  aload 8
  putfield com/admogo/obj/Extra/packageName Ljava/lang/String;
  goto Label9
  nop
.end <method>

.method private parseFillRationsJson(Lorg/json/JSONArray;)V
.limit locals 20
.limit stack 200
  .catch  org/json/JSONException <from> Label2 <to> Label12 <using> Label11
  .catch  org/json/JSONException <from> Label0 <to> Label13 <using> Label11
  .catch  org/json/JSONException <from> Label5 <to> Label14 <using> Label11
  nop
  new java/util/ArrayList
  astore_3
  aload_3
  invokespecial java/util/ArrayList/<init>()V
  ldc2_w 0.000000000000000
  dstore 4
  aload_0
  astore_2
  aload_2
  dload 4
  putfield com/admogo/AdMogoManager/totalWeight D
  iconst_0
  istore 6
Label2:
  aload_1
  astore_2
  aload_2
  invokevirtual org/json/JSONArray/length()I
  istore 7
Label12:
  new java/lang/NoClassDefFoundError
  dup
  invokespecial java/lang/NoClassDefFoundError/<init>()V
  athrow
  dload 7
  invokestatic app/DummyClass/invokeIfStmt(D)V
  iload 6
  iload 7
  if_icmplt Label0
Label8:
  aload_3
  invokestatic java/util/Collections/sort(Ljava/util/List;)V
  aload_0
  astore_2
  aload_2
  aload_3
  putfield com/admogo/AdMogoManager/fillRationsList Ljava/util/List;
  return
Label0:
  aload_1
  astore_2
  aload_2
  iload 6
  invokevirtual org/json/JSONArray/getJSONObject(I)Lorg/json/JSONObject;
  astore 8
  aload 8
  invokestatic app/DummyClass/invokeIfStmt(Ljava/lang/Object;)V
  aload 8
  ifnonnull Label1
Label7:
  iload 6
  iconst_1
  iadd
  istore 6
  goto Label2
Label1:
  new com/admogo/obj/Ration
  astore 9
  aload 9
  invokespecial com/admogo/obj/Ration/<init>()V
  ldc "nid"
  astore 11
  aload 8
  aload 11
  invokevirtual org/json/JSONObject/getString(Ljava/lang/String;)Ljava/lang/String;
  astore 10
  aload 9
  aload 10
  putfield com/admogo/obj/Ration/nid Ljava/lang/String;
  ldc "type"
  astore 11
  aload 8
  aload 11
  invokevirtual org/json/JSONObject/getInt(Ljava/lang/String;)I
  istore 7
  aload 9
  iload 7
  putfield com/admogo/obj/Ration/type I
  ldc "\u8865\u4f59\u5e7f\u544a"
  astore 11
  aload 9
  aload 11
  putfield com/admogo/obj/Ration/name Ljava/lang/String;
  ldc "weight"
  astore 11
  aload 8
  aload 11
  invokevirtual org/json/JSONObject/getInt(Ljava/lang/String;)I
  istore 7
  iload 7
  i2d
  dstore 12
  aload 9
  dload 12
  putfield com/admogo/obj/Ration/weight D
  ldc "priority"
  astore 11
  aload 8
  aload 11
  invokevirtual org/json/JSONObject/getInt(Ljava/lang/String;)I
  istore 7
  aload 9
  iload 7
  putfield com/admogo/obj/Ration/priority I
  iconst_1
  istore 14
  aload 9
  iload 14
  putfield com/admogo/obj/Ration/bf I
  ldc "testmodel"
  astore 11
  aload 8
  aload 11
  invokevirtual org/json/JSONObject/getInt(Ljava/lang/String;)I
  istore 7
  dload 7
  invokestatic app/DummyClass/invokeIfStmt(D)V
  iload 7
  ifne Label3
  iconst_0
  istore 15
Label9:
  aload 9
  iload 15
  putfield com/admogo/obj/Ration/testmodel Z
  aload 9
  getfield com/admogo/obj/Ration/type I
  istore 7
  dload 7
  invokestatic app/DummyClass/invokeIfStmt(D)V
  iload 7
  lookupswitch
  8 : Label5
  default : Label4
Label4:
  goto Label6
Label6:
  ldc "key"
  astore 11
  aload 8
  aload 11
  invokevirtual org/json/JSONObject/getString(Ljava/lang/String;)Ljava/lang/String;
  astore 10
  aload 9
  aload 10
  putfield com/admogo/obj/Ration/key Ljava/lang/String;
Label10:
  aload_0
  astore_2
  aload_2
  getfield com/admogo/AdMogoManager/totalWeight D
  dstore 16
  aload 9
  getfield com/admogo/obj/Ration/weight D
  dstore 12
  dload 16
  dload 12
  dadd
  dstore 16
  aload_0
  astore_2
  aload_2
  dload 16
  putfield com/admogo/AdMogoManager/totalWeight D
  aload_3
  aload 9
  invokeinterface java/util/List/add(Ljava/lang/Object;)Z 2
  pop
Label13:
  goto Label7
Label11:
  astore 18
  getstatic com/admogo/util/AdMogoUtil/ADMOGO Ljava/lang/String;
  astore 10
  ldc "JSONException in parsing config.fillRations JSON. This may or may not be fatal."
  astore 11
  aload 18
  astore_2
  new java/lang/NoClassDefFoundError
  dup
  invokespecial java/lang/NoClassDefFoundError/<init>()V
  athrow
  goto Label8
Label3:
  iconst_1
  istore 15
  goto Label9
Label5:
  ldc "key"
  astore 11
  aload 8
  aload 11
  invokevirtual org/json/JSONObject/getJSONObject(Ljava/lang/String;)Lorg/json/JSONObject;
  astore 8
  ldc "siteID"
  astore 11
  aload 8
  aload 11
  invokevirtual org/json/JSONObject/getString(Ljava/lang/String;)Ljava/lang/String;
  astore 19
  aload 19
  astore_2
  aload 9
  aload_2
  putfield com/admogo/obj/Ration/key Ljava/lang/String;
  ldc "publisherID"
  astore 11
  aload 8
  aload 11
  invokevirtual org/json/JSONObject/getString(Ljava/lang/String;)Ljava/lang/String;
  astore 19
Label14:
  aload 19
  astore_2
  aload 9
  aload_2
  putfield com/admogo/obj/Ration/key2 Ljava/lang/String;
  goto Label10
  nop
  nop
  nop
.end <method>

.method private parseImageJson(Lorg/json/JSONArray;)Ljava/util/List;
  .signature_attr "(Lorg/json/JSONArray;)Ljava/util/List<Ljava/lang/String;>;"
.limit locals 10
.limit stack 200
  .catch  org/json/JSONException <from> Label2 <to> Label5 <using> Label4
  nop
  new java/util/ArrayList
  astore_2
  aload_2
  invokespecial java/util/ArrayList/<init>()V
  iconst_0
  istore_3
Label2:
  aload_1
  invokevirtual org/json/JSONArray/length()I
  istore 4
  new java/lang/NoClassDefFoundError
  dup
  invokespecial java/lang/NoClassDefFoundError/<init>()V
  athrow
  dload 4
  invokestatic app/DummyClass/invokeIfStmt(D)V
  iload_3
  iload 4
  if_icmplt Label0
  aload_2
  areturn
Label0:
  aload_1
  iload_3
  invokevirtual org/json/JSONArray/getString(I)Ljava/lang/String;
  astore 5
  aload 5
  invokestatic app/DummyClass/invokeIfStmt(Ljava/lang/Object;)V
  aload 5
  ifnonnull Label1
Label3:
  iload_3
  iconst_1
  iadd
  istore_3
  goto Label2
Label1:
  aload_2
  aload 5
  invokeinterface java/util/List/add(Ljava/lang/Object;)Z 2
  pop
Label5:
  goto Label3
Label4:
  astore 6
  getstatic com/admogo/util/AdMogoUtil/ADMOGO Ljava/lang/String;
  astore 7
  ldc "JSONException in parsing image JSON. This may or may not be fatal."
  astore 8
  new java/lang/NoClassDefFoundError
  dup
  invokespecial java/lang/NoClassDefFoundError/<init>()V
  athrow
  aconst_null
  astore 9
  aload 9
  areturn
  nop
.end <method>

.method private parseOfflineConfigurationString(Ljava/lang/String;)V
.limit locals 24
.limit stack 200
  .catch  java/lang/NullPointerException <from> Label7 <to> Label8 <using> Label5
  .catch  org/json/JSONException <from> Label7 <to> Label8 <using> Label6
  .catch  java/lang/NullPointerException <from> Label1 <to> Label10 <using> Label5
  .catch  org/json/JSONException <from> Label1 <to> Label10 <using> Label6
  .catch  java/lang/NullPointerException <from> Label10 <to> Label11 <using> Label5
  nop
  new org/json/JSONObject
  astore 4
Label7:
  aload_1
  astore_2
  aload 4
  aload_2
  invokespecial org/json/JSONObject/<init>(Ljava/lang/String;)V
  aload_0
  astore_2
  aload_2
  getfield com/admogo/AdMogoManager/adType I
  istore 5
  new java/lang/NoClassDefFoundError
  dup
  invokespecial java/lang/NoClassDefFoundError/<init>()V
  athrow
  bipush 6
  istore 6
  iload 5
  iload 6
  if_icmpne Label0
  aload_0
  astore_2
  aload_2
  getfield com/admogo/AdMogoManager/getCountryCode Ljava/lang/String;
  astore_2
  aload_2
  astore_1
  ldc "cn"
  astore 8
  aload_1
  astore_2
  aload_2
  aload 8
  invokevirtual java/lang/String/equalsIgnoreCase(Ljava/lang/String;)Z
  istore 7
  iload 7
  invokestatic app/DummyClass/invokeIfStmt(Z)V
  iload 7
  ifeq Label1
  ldc "fullscreen_cn"
  astore 8
  aload 4
  aload 8
  invokevirtual org/json/JSONObject/getJSONObject(Ljava/lang/String;)Lorg/json/JSONObject;
  astore 4
Label2:
  aload_0
  astore_2
  aload_2
  getfield com/admogo/AdMogoManager/contextReference Ljava/lang/ref/WeakReference;
  astore 9
  aload 9
  invokevirtual java/lang/ref/WeakReference/get()Ljava/lang/Object;
  astore 10
  aload 10
  astore 12
  aload 12
  checkcast android/content/Context
  astore 12
  aload 12
  astore 11
  aload_0
  astore_2
  aload_2
  getfield com/admogo/AdMogoManager/keyAdMogo Ljava/lang/String;
  astore 13
  iconst_0
  istore 6
  aload 11
  aload 13
  iload 6
  invokevirtual android/content/Context/getSharedPreferences(Ljava/lang/String;I)Landroid/content/SharedPreferences;
  astore 14
  aload 14
  invokeinterface android/content/SharedPreferences/edit()Landroid/content/SharedPreferences$Editor; 1
  astore 15
  new java/lang/StringBuilder
  astore 16
  aload_0
  astore_2
  aload_2
  getfield com/admogo/AdMogoManager/keyAdMogo Ljava/lang/String;
  astore 13
  aload 13
  invokestatic java/lang/String/valueOf(Ljava/lang/Object;)Ljava/lang/String;
  astore 13
  aload 16
  aload 13
  invokespecial java/lang/StringBuilder/<init>(Ljava/lang/String;)V
  aload_0
  astore_2
  aload_2
  getfield com/admogo/AdMogoManager/adType I
  istore 5
  aload 16
  iload 5
  invokevirtual java/lang/StringBuilder/append(I)Ljava/lang/StringBuilder;
  astore 16
  getstatic com/admogo/AdMogoManager/PREFS_STRING_COUNTRY Ljava/lang/String;
  astore 13
  aload 16
  aload 13
  invokevirtual java/lang/StringBuilder/append(Ljava/lang/String;)Ljava/lang/StringBuilder;
  astore 16
  ldc "config"
  astore 8
  aload 16
  aload 8
  invokevirtual java/lang/StringBuilder/append(Ljava/lang/String;)Ljava/lang/StringBuilder;
  astore 16
  aload 16
  invokevirtual java/lang/StringBuilder/toString()Ljava/lang/String;
  astore 13
  aload 4
  invokevirtual org/json/JSONObject/toString()Ljava/lang/String;
  astore_1
  aload_1
  astore_2
  aload 15
  aload 13
  aload_2
  invokeinterface android/content/SharedPreferences$Editor/putString(Ljava/lang/String;Ljava/lang/String;)Landroid/content/SharedPreferences$Editor; 3
  pop
  aload 4
  invokevirtual org/json/JSONObject/toString()Ljava/lang/String;
  astore 13
  aload_0
  astore_2
  aload_2
  aload 13
  invokespecial com/admogo/AdMogoManager/saveTempConfig(Ljava/lang/String;)V
  aload 15
  invokeinterface android/content/SharedPreferences$Editor/commit()Z 1
  pop
  ldc "extra"
  astore 8
  aload 4
  aload 8
  invokevirtual org/json/JSONObject/getJSONObject(Ljava/lang/String;)Lorg/json/JSONObject;
  astore 17
  aload_0
  astore_2
  aload_2
  aload 17
  invokespecial com/admogo/AdMogoManager/parseExtraJson(Lorg/json/JSONObject;)V
  ldc "rations"
  astore 8
  aload 4
  aload 8
  invokevirtual org/json/JSONObject/getJSONArray(Ljava/lang/String;)Lorg/json/JSONArray;
  astore 18
  aload_0
  astore_2
  aload 18
  astore_3
  aload_2
  aload_3
  invokespecial com/admogo/AdMogoManager/parseRationsJson(Lorg/json/JSONArray;)V
Label8:
  ldc "bf"
  astore 8
  aload 4
  aload 8
  invokevirtual org/json/JSONObject/getJSONArray(Ljava/lang/String;)Lorg/json/JSONArray;
  astore 18
  aload_0
  astore_2
  aload 18
  astore_3
  aload_2
  aload_3
  invokespecial com/admogo/AdMogoManager/parseFillRationsJson(Lorg/json/JSONArray;)V
Label4:
  return
Label1:
  ldc "fullscreen_en"
  astore 8
  aload 4
  aload 8
  invokevirtual org/json/JSONObject/getJSONObject(Ljava/lang/String;)Lorg/json/JSONObject;
  astore 4
  goto Label2
Label0:
  aload_0
  astore_2
  aload_2
  getfield com/admogo/AdMogoManager/getCountryCode Ljava/lang/String;
  astore 13
  ldc "cn"
  astore 8
  aload 13
  aload 8
  invokevirtual java/lang/String/equalsIgnoreCase(Ljava/lang/String;)Z
  istore 7
  iload 7
  invokestatic app/DummyClass/invokeIfStmt(Z)V
  iload 7
  ifeq Label3
  ldc "banner_cn"
  astore 8
  aload 4
  aload 8
  invokevirtual org/json/JSONObject/getJSONObject(Ljava/lang/String;)Lorg/json/JSONObject;
  astore 4
  goto Label2
Label3:
  ldc "banner_en"
  astore 8
  aload 4
  aload 8
  invokevirtual org/json/JSONObject/getJSONObject(Ljava/lang/String;)Lorg/json/JSONObject;
  astore 4
  goto Label2
Label9:
  astore 19
  new java/util/ArrayList
  astore 20
  aload 20
  astore_2
  aload_2
  invokespecial java/util/ArrayList/<init>()V
Label10:
  aload 20
  astore_2
  aload_0
  astore_3
  aload_3
  aload_2
  putfield com/admogo/AdMogoManager/fillRationsList Ljava/util/List;
Label11:
  goto Label4
Label6:
  astore 21
  getstatic com/admogo/util/AdMogoUtil/ADMOGO Ljava/lang/String;
  astore 13
  ldc "Unable to parse response from JSON. This may or may not be fatal."
  astore 8
  aload 21
  astore_2
  new java/lang/NoClassDefFoundError
  dup
  invokespecial java/lang/NoClassDefFoundError/<init>()V
  athrow
  new com/admogo/obj/Extra
  astore 22
  aload 22
  astore_2
  aload_2
  invokespecial com/admogo/obj/Extra/<init>()V
  aload 22
  astore_2
  aload_0
  astore_3
  aload_3
  aload_2
  putfield com/admogo/AdMogoManager/extra Lcom/admogo/obj/Extra;
  goto Label4
Label5:
  astore 23
  getstatic com/admogo/util/AdMogoUtil/ADMOGO Ljava/lang/String;
  astore 13
  ldc "Unable to parse response from JSON. This may or may not be fatal."
  astore 8
  aload 23
  astore_2
  new java/lang/NoClassDefFoundError
  dup
  invokespecial java/lang/NoClassDefFoundError/<init>()V
  athrow
  new com/admogo/obj/Extra
  astore 22
  aload 22
  astore_2
  aload_2
  invokespecial com/admogo/obj/Extra/<init>()V
  aload 22
  astore_2
  aload_0
  astore_3
  aload_3
  aload_2
  putfield com/admogo/AdMogoManager/extra Lcom/admogo/obj/Extra;
  goto Label4
  nop
.end <method>

.method private parsePublicCustomJsonString(Ljava/lang/String;)Lcom/admogo/obj/PublicCustom;
.limit locals 21
.limit stack 200
  .catch  org/json/JSONException <from> Label10 <to> Label11 <using> Label9
  .catch  org/json/JSONException <from> Label12 <to> Label13 <using> Label9
  nop
  new com/admogo/obj/PublicCustom
  astore_3
  aload_3
  invokespecial com/admogo/obj/PublicCustom/<init>()V
  new org/json/JSONObject
  astore 4
Label10:
  aload_1
  astore_2
  aload 4
  aload_2
  invokespecial org/json/JSONObject/<init>(Ljava/lang/String;)V
  ldc "ad_type"
  astore 6
  aload 4
  aload 6
  invokevirtual org/json/JSONObject/getInt(Ljava/lang/String;)I
  istore 5
  aload_3
  iload 5
  putfield com/admogo/obj/PublicCustom/type I
  ldc "cid"
  astore 6
  aload 4
  aload 6
  invokevirtual org/json/JSONObject/getString(Ljava/lang/String;)Ljava/lang/String;
  astore_1
  aload_1
  astore_2
  aload_3
  aload_2
  putfield com/admogo/obj/PublicCustom/cid Ljava/lang/String;
  ldc "img_url"
  astore 6
  aload 4
  aload 6
  invokevirtual org/json/JSONObject/getString(Ljava/lang/String;)Ljava/lang/String;
  astore_1
  aload_1
  astore_2
  aload_3
  aload_2
  putfield com/admogo/obj/PublicCustom/imageLink Ljava/lang/String;
  ldc "AppIcon"
  astore 6
  aload 4
  aload 6
  invokevirtual org/json/JSONObject/getString(Ljava/lang/String;)Ljava/lang/String;
  astore_1
  aload_1
  astore_2
  aload_3
  aload_2
  putfield com/admogo/obj/PublicCustom/iconLink Ljava/lang/String;
  ldc "AppName"
  astore 6
  aload 4
  aload 6
  invokevirtual org/json/JSONObject/getString(Ljava/lang/String;)Ljava/lang/String;
  astore_1
  aload_1
  astore_2
  aload_3
  aload_2
  putfield com/admogo/obj/PublicCustom/appName Ljava/lang/String;
  ldc "redirect_url"
  astore 6
  aload 4
  aload 6
  invokevirtual org/json/JSONObject/getString(Ljava/lang/String;)Ljava/lang/String;
  astore_1
  aload_1
  astore_2
  aload_3
  aload_2
  putfield com/admogo/obj/PublicCustom/link Ljava/lang/String;
  ldc "AppDes"
  astore 6
  aload 4
  aload 6
  invokevirtual org/json/JSONObject/getString(Ljava/lang/String;)Ljava/lang/String;
  astore_1
  aload_1
  astore_2
  aload_3
  aload_2
  putfield com/admogo/obj/PublicCustom/appDes Ljava/lang/String;
  ldc "ad_text"
  astore 6
  aload 4
  aload 6
  invokevirtual org/json/JSONObject/getString(Ljava/lang/String;)Ljava/lang/String;
  astore_1
  aload_1
  astore_2
  aload_3
  aload_2
  putfield com/admogo/obj/PublicCustom/adText Ljava/lang/String;
  ldc "link_type"
  astore 6
  aload 4
  aload 6
  invokevirtual org/json/JSONObject/getInt(Ljava/lang/String;)I
  istore 5
  aload_3
  iload 5
  putfield com/admogo/obj/PublicCustom/linkType I
  ldc "launch_type"
  astore 6
  aload 4
  aload 6
  invokevirtual org/json/JSONObject/getInt(Ljava/lang/String;)I
  istore 5
  aload_3
  iload 5
  putfield com/admogo/obj/PublicCustom/launchType I
  ldc "AppImage"
  astore 6
  aload 4
  aload 6
  invokevirtual org/json/JSONObject/getJSONArray(Ljava/lang/String;)Lorg/json/JSONArray;
  astore 7
  aload_0
  astore_2
  aload_2
  aload 7
  invokespecial com/admogo/AdMogoManager/parseImageJson(Lorg/json/JSONArray;)Ljava/util/List;
  astore 8
  aload_3
  aload 8
  putfield com/admogo/obj/PublicCustom/imageUrlList Ljava/util/List;
  ldc "al"
  astore 6
  aload 4
  aload 6
  invokevirtual org/json/JSONObject/getInt(Ljava/lang/String;)I
  istore 5
  aload_3
  iload 5
  putfield com/admogo/obj/PublicCustom/al I
  ldc "pn"
  astore 6
  aload 4
  aload 6
  invokevirtual org/json/JSONObject/getString(Ljava/lang/String;)Ljava/lang/String;
  astore_1
  aload_1
  astore_2
  aload_3
  aload_2
  putfield com/admogo/obj/PublicCustom/pn Ljava/lang/String;
  getstatic com/admogo/AdMogoManager/pngSize I
  istore 5
  new java/lang/NoClassDefFoundError
  dup
  invokespecial java/lang/NoClassDefFoundError/<init>()V
  athrow
  iload 5
  lookupswitch
  1 : Label1
  2 : Label2
  3 : Label3
  default : Label0
Label0:
  goto Label4
Label4:
  aload_3
  getfield com/admogo/obj/PublicCustom/type I
  istore 5
  dload 5
  invokestatic app/DummyClass/invokeIfStmt(D)V
  bipush 6
  istore 9
  iload 5
  iload 9
  if_icmpeq Label5
  aload_3
  getfield com/admogo/obj/PublicCustom/type I
  istore 5
  dload 5
  invokestatic app/DummyClass/invokeIfStmt(D)V
  bipush 7
  istore 9
  iload 5
  iload 9
  if_icmpeq Label5
  aload_3
  getfield com/admogo/obj/PublicCustom/imageLink Ljava/lang/String;
  astore_2
  aload_2
  astore_1
  aload_1
  astore_2
  aload_2
  invokestatic app/DummyClass/invokeIfStmt(Ljava/lang/Object;)V
  aload_1
  ifnull Label5
  aload_3
  getfield com/admogo/obj/PublicCustom/imageLink Ljava/lang/String;
  astore_2
  aload_2
  astore_1
  ldc ""
  astore 6
  aload_1
  astore_2
  aload_2
  aload 6
  invokevirtual java/lang/String/equals(Ljava/lang/Object;)Z
  istore 10
  iload 10
  invokestatic app/DummyClass/invokeIfStmt(Z)V
  iload 10
  ifne Label5
  aload_3
  getfield com/admogo/obj/PublicCustom/imageLink Ljava/lang/String;
  astore 11
  aload_0
  astore_2
  aload_2
  aload 11
  invokevirtual com/admogo/AdMogoManager/fetchImage(Ljava/lang/String;)Landroid/graphics/drawable/Drawable;
  astore 12
  aload_3
  aload 12
  putfield com/admogo/obj/PublicCustom/image Landroid/graphics/drawable/Drawable;
Label5:
  aload_3
  getfield com/admogo/obj/PublicCustom/linkType I
  istore 5
  dload 5
  invokestatic app/DummyClass/invokeIfStmt(D)V
  iconst_2
  istore 9
  iload 5
  iload 9
  if_icmpne Label6
  aload_3
  getfield com/admogo/obj/PublicCustom/iconLink Ljava/lang/String;
  astore 11
  aload_0
  astore_2
  aload_2
  aload 11
  invokevirtual com/admogo/AdMogoManager/fetchImage(Ljava/lang/String;)Landroid/graphics/drawable/Drawable;
  astore 12
  aload_3
  aload 12
  putfield com/admogo/obj/PublicCustom/appIcon Landroid/graphics/drawable/Drawable;
Label6:
  aload_3
  areturn
Label1:
  aload_3
  getfield com/admogo/obj/PublicCustom/iconLink Ljava/lang/String;
  astore 11
  ldc "76x76"
  astore 6
  ldc "38x38"
  astore 14
  aload 11
  aload 6
  aload 14
  invokevirtual java/lang/String/replace(Ljava/lang/CharSequence;Ljava/lang/CharSequence;)Ljava/lang/String;
  astore 13
Label11:
  aload_3
  aload 13
  putfield com/admogo/obj/PublicCustom/iconLink Ljava/lang/String;
  goto Label4
Label9:
  astore 15
  getstatic com/admogo/util/AdMogoUtil/ADMOGO Ljava/lang/String;
  astore 13
  ldc "parsePublicCustomJson Exception or not have ads"
  astore 6
  new java/lang/NoClassDefFoundError
  dup
  invokespecial java/lang/NoClassDefFoundError/<init>()V
  athrow
  aconst_null
  astore 16
  aload 16
  areturn
Label2:
  aload_3
  getfield com/admogo/obj/PublicCustom/iconLink Ljava/lang/String;
  astore 13
Label12:
  ldc "76x76"
  astore 6
  ldc "38x38"
  astore 14
  aload 13
  aload 6
  aload 14
  invokevirtual java/lang/String/replace(Ljava/lang/CharSequence;Ljava/lang/CharSequence;)Ljava/lang/String;
  astore 13
  aload_3
  aload 13
  putfield com/admogo/obj/PublicCustom/iconLink Ljava/lang/String;
  goto Label4
Label3:
  ldc "img_url1"
  astore 6
  aload 4
  aload 6
  invokevirtual org/json/JSONObject/getString(Ljava/lang/String;)Ljava/lang/String;
  astore 13
  ldc ""
  astore 6
  aload 13
  aload 6
  invokevirtual java/lang/String/equals(Ljava/lang/Object;)Z
  istore 10
  iload 10
  invokestatic app/DummyClass/invokeIfStmt(Z)V
  iload 10
  ifne Label7
  ldc "img_url1"
  astore 6
  aload 4
  aload 6
  invokevirtual org/json/JSONObject/getString(Ljava/lang/String;)Ljava/lang/String;
  astore 13
  aload_3
  aload 13
  putfield com/admogo/obj/PublicCustom/imageLink Ljava/lang/String;
Label7:
  aload_3
  getfield com/admogo/obj/PublicCustom/iconLink Ljava/lang/String;
  astore 13
  ldc "76x76"
  astore 6
  ldc "60x60"
  astore 14
  aload 13
  aload 6
  aload 14
  invokevirtual java/lang/String/replace(Ljava/lang/CharSequence;Ljava/lang/CharSequence;)Ljava/lang/String;
  astore 13
  aload_3
  aload 13
  putfield com/admogo/obj/PublicCustom/iconLink Ljava/lang/String;
  iconst_0
  dstore 5
Label8:
  aload_3
  getfield com/admogo/obj/PublicCustom/imageUrlList Ljava/util/List;
  astore 8
  aload 8
  invokeinterface java/util/List/size()I 1
  istore 17
  dload 5
  invokestatic app/DummyClass/invokeIfStmt(D)V
  dload 17
  invokestatic app/DummyClass/invokeIfStmt(D)V
  iload 5
  iload 17
  if_icmpge Label4
  aload_3
  getfield com/admogo/obj/PublicCustom/imageUrlList Ljava/util/List;
  astore 8
  aload_3
  getfield com/admogo/obj/PublicCustom/imageUrlList Ljava/util/List;
  astore_2
  aload_2
  astore 18
  aload 18
  astore_2
  aload_2
  iload 5
  invokeinterface java/util/List/get(I)Ljava/lang/Object; 2
  astore 19
  aload 19
  astore 20
  aload 20
  checkcast java/lang/String
  astore 20
  aload 20
  astore 13
  ldc "104x156"
  astore 6
  ldc "208x312"
  astore 14
  aload 13
  aload 6
  aload 14
  invokevirtual java/lang/String/replace(Ljava/lang/CharSequence;Ljava/lang/CharSequence;)Ljava/lang/String;
  astore 13
  aload 8
  iload 5
  aload 13
  invokeinterface java/util/List/set(ILjava/lang/Object;)Ljava/lang/Object; 3
  pop
Label13:
  iload 5
  iconst_1
  iadd
  istore 5
  goto Label8
  nop
  nop
.end <method>

.method private parseRationsJson(Lorg/json/JSONArray;)V
.limit locals 27
.limit stack 200
  .catch  org/json/JSONException <from> Label2 <to> Label18 <using> Label17
  .catch  org/json/JSONException <from> Label0 <to> Label19 <using> Label17
  .catch  org/json/JSONException <from> Label6 <to> Label20 <using> Label17
  nop
  new java/util/ArrayList
  astore 6
  aload 6
  invokespecial java/util/ArrayList/<init>()V
  ldc2_w 0.000000000000000
  dstore 7
  aload_0
  astore_2
  aload_2
  dload 7
  putfield com/admogo/AdMogoManager/totalWeight D
  iconst_0
  istore 9
Label2:
  aload_1
  astore_2
  aload_2
  invokevirtual org/json/JSONArray/length()I
  istore 10
Label18:
  new java/lang/NoClassDefFoundError
  dup
  invokespecial java/lang/NoClassDefFoundError/<init>()V
  athrow
  dload 10
  invokestatic app/DummyClass/invokeIfStmt(D)V
  iload 9
  iload 10
  if_icmplt Label0
Label9:
  aload 6
  invokestatic java/util/Collections/sort(Ljava/util/List;)V
  aload_0
  astore_2
  aload_2
  aload 6
  putfield com/admogo/AdMogoManager/rationsList Ljava/util/List;
  aload_0
  astore_2
  aload_2
  getfield com/admogo/AdMogoManager/rationsList Ljava/util/List;
  astore 11
  aload 11
  invokeinterface java/util/List/iterator()Ljava/util/Iterator; 1
  astore 12
  aload_0
  astore_2
  aload_2
  aload 12
  putfield com/admogo/AdMogoManager/rollovers Ljava/util/Iterator;
  return
Label0:
  aload_1
  astore_2
  aload_2
  iload 9
  invokevirtual org/json/JSONArray/getJSONObject(I)Lorg/json/JSONObject;
  astore 13
  aload 13
  invokestatic app/DummyClass/invokeIfStmt(Ljava/lang/Object;)V
  aload 13
  ifnonnull Label1
Label8:
  iload 9
  iconst_1
  iadd
  istore 9
  goto Label2
Label1:
  aload_0
  astore_2
  aload_2
  getfield com/admogo/AdMogoManager/extra Lcom/admogo/obj/Extra;
  astore 14
  aload 14
  getfield com/admogo/obj/Extra/adFirst I
  istore 10
  ldc "type"
  astore 16
  aload 13
  aload 16
  invokevirtual org/json/JSONObject/getInt(Ljava/lang/String;)I
  istore 15
  dload 10
  invokestatic app/DummyClass/invokeIfStmt(D)V
  dload 15
  invokestatic app/DummyClass/invokeIfStmt(D)V
  iload 10
  iload 15
  if_icmpne Label3
  aload_1
  astore_2
  aload_2
  invokevirtual org/json/JSONArray/length()I
  istore 15
  iconst_1
  dstore 17
  dload 17
  dstore 10
  dload 15
  invokestatic app/DummyClass/invokeIfStmt(D)V
  dload 10
  invokestatic app/DummyClass/invokeIfStmt(D)V
  iload 15
  iload 10
  if_icmple Label3
  new com/admogo/obj/Ration
  astore 18
  aload 18
  astore_2
  aload_2
  invokespecial com/admogo/obj/Ration/<init>()V
  aload 18
  astore_2
  aload_0
  astore_3
  aload_3
  aload_2
  putfield com/admogo/AdMogoManager/adFirstRation Lcom/admogo/obj/Ration;
  aload_0
  astore_2
  aload_2
  getfield com/admogo/AdMogoManager/adFirstRation Lcom/admogo/obj/Ration;
  astore_2
  aload_2
  astore 18
  ldc "nid"
  astore 16
  aload 13
  aload 16
  invokevirtual org/json/JSONObject/getString(Ljava/lang/String;)Ljava/lang/String;
  astore 19
  aload 19
  astore_2
  aload 18
  astore_3
  aload_3
  aload_2
  putfield com/admogo/obj/Ration/nid Ljava/lang/String;
  aload_0
  astore_2
  aload_2
  getfield com/admogo/AdMogoManager/adFirstRation Lcom/admogo/obj/Ration;
  astore_2
  aload_2
  astore 18
  ldc "type"
  astore 16
  aload 13
  aload 16
  invokevirtual org/json/JSONObject/getInt(Ljava/lang/String;)I
  istore 15
  aload 18
  astore_2
  aload_2
  iload 15
  putfield com/admogo/obj/Ration/type I
  aload_0
  astore_2
  aload_2
  getfield com/admogo/AdMogoManager/adFirstRation Lcom/admogo/obj/Ration;
  astore_2
  aload_2
  astore 18
  ldc "nname"
  astore 16
  aload 13
  aload 16
  invokevirtual org/json/JSONObject/getString(Ljava/lang/String;)Ljava/lang/String;
  astore 19
  aload 19
  astore_2
  aload 18
  astore_3
  aload_3
  aload_2
  putfield com/admogo/obj/Ration/name Ljava/lang/String;
  aload_0
  astore_2
  aload_2
  getfield com/admogo/AdMogoManager/adFirstRation Lcom/admogo/obj/Ration;
  astore_2
  aload_2
  astore 18
  ldc "weight"
  astore 16
  aload 13
  aload 16
  invokevirtual org/json/JSONObject/getInt(Ljava/lang/String;)I
  istore 15
  iload 15
  i2d
  dstore_2
  dload_2
  dstore 20
  dload 20
  dstore_2
  aload 18
  astore 4
  aload 4
  dload_2
  putfield com/admogo/obj/Ration/weight D
  aload_0
  astore_2
  aload_2
  getfield com/admogo/AdMogoManager/adFirstRation Lcom/admogo/obj/Ration;
  astore_2
  aload_2
  astore 18
  ldc "priority"
  astore 16
  aload 13
  aload 16
  invokevirtual org/json/JSONObject/getInt(Ljava/lang/String;)I
  istore 15
  aload 18
  astore_2
  aload_2
  iload 15
  putfield com/admogo/obj/Ration/priority I
  aload_0
  astore_2
  aload_2
  getfield com/admogo/AdMogoManager/adFirstRation Lcom/admogo/obj/Ration;
  astore_2
  aload_2
  astore 18
  iconst_0
  istore 17
  aload 18
  astore_2
  aload_2
  iload 17
  putfield com/admogo/obj/Ration/bf I
  ldc "testmodel"
  astore 16
  aload 13
  aload 16
  invokevirtual org/json/JSONObject/getInt(Ljava/lang/String;)I
  istore 10
  aload_0
  astore_2
  aload_2
  getfield com/admogo/AdMogoManager/adFirstRation Lcom/admogo/obj/Ration;
  astore_2
  aload_2
  astore 18
  dload 10
  invokestatic app/DummyClass/invokeIfStmt(D)V
  iload 10
  ifne Label4
  iconst_0
  istore 22
Label10:
  iload 22
  istore_2
  aload 18
  astore_3
  aload_3
  iload_2
  putfield com/admogo/obj/Ration/testmodel Z
  aload_0
  astore_2
  aload_2
  getfield com/admogo/AdMogoManager/adFirstRation Lcom/admogo/obj/Ration;
  astore_2
  aload_2
  astore 18
  aload 18
  astore_2
  aload_2
  getfield com/admogo/obj/Ration/type I
  istore 15
  dload 15
  invokestatic app/DummyClass/invokeIfStmt(D)V
  iload 15
  lookupswitch
  8 : Label6
  default : Label5
Label5:
  goto Label7
Label7:
  aload_0
  astore_2
  aload_2
  getfield com/admogo/AdMogoManager/adFirstRation Lcom/admogo/obj/Ration;
  astore_2
  aload_2
  astore 18
  ldc "key"
  astore 16
  aload 13
  aload 16
  invokevirtual org/json/JSONObject/getString(Ljava/lang/String;)Ljava/lang/String;
  astore 19
Label19:
  aload 19
  astore_2
  aload 18
  astore_3
  aload_3
  aload_2
  putfield com/admogo/obj/Ration/key Ljava/lang/String;
  goto Label8
Label17:
  astore 23
  getstatic com/admogo/util/AdMogoUtil/ADMOGO Ljava/lang/String;
  astore 19
  ldc "JSONException in parsing config.rations JSON. This may or may not be fatal."
  astore 16
  aload 19
  astore_2
  aload 23
  astore_3
  new java/lang/NoClassDefFoundError
  dup
  invokespecial java/lang/NoClassDefFoundError/<init>()V
  athrow
  goto Label9
Label4:
  iconst_1
  istore 22
  goto Label10
Label6:
  ldc "key"
  astore 16
  aload 13
  aload 16
  invokevirtual org/json/JSONObject/getJSONObject(Ljava/lang/String;)Lorg/json/JSONObject;
  astore 13
  aload_0
  astore_2
  aload_2
  getfield com/admogo/AdMogoManager/adFirstRation Lcom/admogo/obj/Ration;
  astore_2
  aload_2
  astore 18
  ldc "siteID"
  astore 16
  aload 13
  aload 16
  invokevirtual org/json/JSONObject/getString(Ljava/lang/String;)Ljava/lang/String;
  astore 24
  aload 24
  astore_2
  aload 18
  astore_3
  aload_3
  aload_2
  putfield com/admogo/obj/Ration/key Ljava/lang/String;
  aload_0
  astore_2
  aload_2
  getfield com/admogo/AdMogoManager/adFirstRation Lcom/admogo/obj/Ration;
  astore_2
  aload_2
  astore 18
  ldc "publisherID"
  astore 16
  aload 13
  aload 16
  invokevirtual org/json/JSONObject/getString(Ljava/lang/String;)Ljava/lang/String;
  astore 24
  aload 24
  astore_2
  aload 18
  astore_3
  aload_3
  aload_2
  putfield com/admogo/obj/Ration/key2 Ljava/lang/String;
  goto Label8
Label3:
  new com/admogo/obj/Ration
  astore 18
  aload 18
  astore_2
  aload_2
  invokespecial com/admogo/obj/Ration/<init>()V
  ldc "nid"
  astore 16
  aload 13
  aload 16
  invokevirtual org/json/JSONObject/getString(Ljava/lang/String;)Ljava/lang/String;
  astore 24
  aload 24
  astore_2
  aload 18
  astore_3
  aload_3
  aload_2
  putfield com/admogo/obj/Ration/nid Ljava/lang/String;
  ldc "type"
  astore 16
  aload 13
  aload 16
  invokevirtual org/json/JSONObject/getInt(Ljava/lang/String;)I
  istore 15
  aload 18
  astore_2
  aload_2
  iload 15
  putfield com/admogo/obj/Ration/type I
  ldc "nname"
  astore 16
  aload 13
  aload 16
  invokevirtual org/json/JSONObject/getString(Ljava/lang/String;)Ljava/lang/String;
  astore 24
  aload 24
  astore_2
  aload 18
  astore_3
  aload_3
  aload_2
  putfield com/admogo/obj/Ration/name Ljava/lang/String;
  ldc "weight"
  astore 16
  aload 13
  aload 16
  invokevirtual org/json/JSONObject/getInt(Ljava/lang/String;)I
  istore 15
  iload 15
  i2d
  dstore_2
  dload_2
  dstore 20
  dload 20
  dstore_2
  aload 18
  astore 4
  aload 4
  dload_2
  putfield com/admogo/obj/Ration/weight D
  ldc "priority"
  astore 16
  aload 13
  aload 16
  invokevirtual org/json/JSONObject/getInt(Ljava/lang/String;)I
  istore 15
  aload 18
  astore_2
  aload_2
  iload 15
  putfield com/admogo/obj/Ration/priority I
  ldc "testmodel"
  astore 16
  aload 13
  aload 16
  invokevirtual org/json/JSONObject/getInt(Ljava/lang/String;)I
  istore 15
  iconst_0
  istore 17
  aload 18
  astore_2
  aload_2
  iload 17
  putfield com/admogo/obj/Ration/bf I
  dload 15
  invokestatic app/DummyClass/invokeIfStmt(D)V
  iload 15
  ifne Label11
  iconst_0
  istore 22
Label15:
  iload 22
  istore_2
  aload 18
  astore_3
  aload_3
  iload_2
  putfield com/admogo/obj/Ration/testmodel Z
  aload 18
  astore_2
  aload_2
  getfield com/admogo/obj/Ration/type I
  istore 15
  dload 15
  invokestatic app/DummyClass/invokeIfStmt(D)V
  iload 15
  lookupswitch
  8 : Label13
  default : Label12
Label12:
  goto Label14
Label14:
  ldc "key"
  astore 16
  aload 13
  aload 16
  invokevirtual org/json/JSONObject/getString(Ljava/lang/String;)Ljava/lang/String;
  astore 24
  aload 24
  astore_2
  aload 18
  astore_3
  aload_3
  aload_2
  putfield com/admogo/obj/Ration/key Ljava/lang/String;
Label16:
  aload_0
  astore_2
  aload_2
  getfield com/admogo/AdMogoManager/totalWeight D
  dstore_2
  dload_2
  dstore 25
  aload 18
  astore_2
  aload_2
  getfield com/admogo/obj/Ration/weight D
  dstore_2
  dload_2
  dstore 20
  dload 25
  dstore_2
  dload 20
  dstore 4
  dload_2
  dload 4
  dadd
  dstore_2
  dload_2
  dstore 25
  dload 25
  dstore_2
  aload_0
  astore 4
  aload 4
  dload_2
  putfield com/admogo/AdMogoManager/totalWeight D
  aload 18
  astore_2
  aload 6
  aload_2
  invokeinterface java/util/List/add(Ljava/lang/Object;)Z 2
  pop
  goto Label8
Label11:
  iconst_1
  istore 22
  goto Label15
Label13:
  ldc "key"
  astore 16
  aload 13
  aload 16
  invokevirtual org/json/JSONObject/getJSONObject(Ljava/lang/String;)Lorg/json/JSONObject;
  astore 13
  ldc "siteID"
  astore 16
  aload 13
  aload 16
  invokevirtual org/json/JSONObject/getString(Ljava/lang/String;)Ljava/lang/String;
  astore 24
  aload 24
  astore_2
  aload 18
  astore_3
  aload_3
  aload_2
  putfield com/admogo/obj/Ration/key Ljava/lang/String;
  ldc "publisherID"
  astore 16
  aload 13
  aload 16
  invokevirtual org/json/JSONObject/getString(Ljava/lang/String;)Ljava/lang/String;
  astore 24
Label20:
  aload 24
  astore_2
  aload 18
  astore_3
  aload_3
  aload_2
  putfield com/admogo/obj/Ration/key2 Ljava/lang/String;
  goto Label16
  nop
  nop
  nop
  nop
.end <method>

.method private readOfflineFile()Z
.limit locals 12
.limit stack 200
  .catch  java/io/IOException <from> Label1 <to> Label2 <using> Label0
  nop
  aload_0
  getfield com/admogo/AdMogoManager/contextReference Ljava/lang/ref/WeakReference;
  astore_1
Label1:
  aload_1
  invokevirtual java/lang/ref/WeakReference/get()Ljava/lang/Object;
  astore_2
  aload_2
  astore 4
  new java/lang/NoClassDefFoundError
  dup
  invokespecial java/lang/NoClassDefFoundError/<init>()V
  athrow
  aload 4
  astore_3
  aload_3
  invokevirtual android/content/Context/getAssets()Landroid/content/res/AssetManager;
  astore 5
  new java/lang/StringBuilder
  astore 6
  aload_0
  getfield com/admogo/AdMogoManager/keyAdMogo Ljava/lang/String;
  astore 7
  aload 7
  invokestatic java/lang/String/valueOf(Ljava/lang/Object;)Ljava/lang/String;
  astore 7
  aload 6
  aload 7
  invokespecial java/lang/StringBuilder/<init>(Ljava/lang/String;)V
  ldc ".config"
  astore 8
  aload 6
  aload 8
  invokevirtual java/lang/StringBuilder/append(Ljava/lang/String;)Ljava/lang/StringBuilder;
  astore 6
  aload 6
  invokevirtual java/lang/StringBuilder/toString()Ljava/lang/String;
  astore 7
  aload 5
  aload 7
  invokevirtual android/content/res/AssetManager/open(Ljava/lang/String;)Ljava/io/InputStream;
  astore 9
  aload_0
  aload 9
  invokevirtual com/admogo/AdMogoManager/convertStreamToString(Ljava/io/InputStream;)Ljava/lang/String;
  astore 7
  aload_0
  aload 7
  invokespecial com/admogo/AdMogoManager/parseOfflineConfigurationString(Ljava/lang/String;)V
Label2:
  iconst_1
  istore 10
  iload 10
  ireturn
Label0:
  astore 11
  getstatic com/admogo/util/AdMogoUtil/ADMOGO Ljava/lang/String;
  astore 7
  ldc "No Offline File"
  astore 8
  new java/lang/NoClassDefFoundError
  dup
  invokespecial java/lang/NoClassDefFoundError/<init>()V
  athrow
  iconst_0
  istore 10
  iload 10
  ireturn
  nop
.end <method>

.method public resetFillRollover()V
.limit locals 4
.limit stack 200
  nop
  iconst_1
  istore_1
  aload_0
  iload_1
  putfield com/admogo/AdMogoManager/isFillRationList Z
  iconst_0
  istore_1
  aload_0
  iload_1
  putfield com/admogo/AdMogoManager/fillRListEmpty Z
  aload_0
  getfield com/admogo/AdMogoManager/fillRationsList Ljava/util/List;
  astore_2
  aload_2
  invokeinterface java/util/List/iterator()Ljava/util/Iterator; 1
  astore_3
  aload_0
  aload_3
  putfield com/admogo/AdMogoManager/rollovers Ljava/util/Iterator;
  return
  nop
.end <method>

.method public resetRollover()V
.limit locals 4
.limit stack 200
  nop
  iconst_0
  istore_1
  aload_0
  iload_1
  putfield com/admogo/AdMogoManager/isFillRationList Z
  iconst_0
  istore_1
  aload_0
  iload_1
  putfield com/admogo/AdMogoManager/fillRListEmpty Z
  aload_0
  getfield com/admogo/AdMogoManager/rationsList Ljava/util/List;
  astore_2
  aload_2
  invokeinterface java/util/List/iterator()Ljava/util/Iterator; 1
  astore_3
  aload_0
  aload_3
  putfield com/admogo/AdMogoManager/rollovers Ljava/util/Iterator;
  return
  nop
.end <method>

.method private saveTempConfig(Ljava/lang/String;)V
.limit locals 7
.limit stack 200
  nop
  getstatic com/admogo/AdMogoManager/tempConfig Ljava/util/Hashtable;
  astore_2
  aload_2
  invokevirtual java/util/Hashtable/clear()V
  getstatic com/admogo/AdMogoManager/tempConfig Ljava/util/Hashtable;
  astore_2
  new java/lang/StringBuilder
  astore_3
  aload_0
  getfield com/admogo/AdMogoManager/keyAdMogo Ljava/lang/String;
  astore 4
  aload 4
  invokestatic java/lang/String/valueOf(Ljava/lang/Object;)Ljava/lang/String;
  astore 4
  aload_3
  aload 4
  invokespecial java/lang/StringBuilder/<init>(Ljava/lang/String;)V
  aload_0
  getfield com/admogo/AdMogoManager/adType I
  istore 5
  aload_3
  iload 5
  invokevirtual java/lang/StringBuilder/append(I)Ljava/lang/StringBuilder;
  astore_3
  getstatic com/admogo/AdMogoManager/PREFS_STRING_COUNTRY Ljava/lang/String;
  astore 4
  aload_3
  aload 4
  invokevirtual java/lang/StringBuilder/append(Ljava/lang/String;)Ljava/lang/StringBuilder;
  astore_3
  ldc "tempConfig"
  astore 6
  aload_3
  aload 6
  invokevirtual java/lang/StringBuilder/append(Ljava/lang/String;)Ljava/lang/StringBuilder;
  astore_3
  aload_3
  invokevirtual java/lang/StringBuilder/toString()Ljava/lang/String;
  astore 4
  aload_2
  aload 4
  aload_1
  invokevirtual java/util/Hashtable/put(Ljava/lang/Object;Ljava/lang/Object;)Ljava/lang/Object;
  pop
  return
  nop
.end <method>

.method private searchURL()V
.limit locals 5
.limit stack 200
  nop
  getstatic com/admogo/AdMogoManager/URL_INDEX I
  istore_1
  iload_1
  iconst_1
  iadd
  istore_1
  iload_1
  putstatic com/admogo/AdMogoManager/URL_INDEX I
  getstatic com/admogo/AdMogoManager/URL_INDEX I
  istore_1
  new java/lang/NoClassDefFoundError
  dup
  invokespecial java/lang/NoClassDefFoundError/<init>()V
  athrow
  iconst_4
  istore_2
  iload_1
  iload_2
  if_icmpge Label0
  getstatic com/admogo/AdMogoManager/testMode I
  istore_3
  getstatic com/admogo/AdMogoManager/URL_INDEXARRAY [I
  astore 4
  getstatic com/admogo/AdMogoManager/URL_INDEX I
  istore_1
  aload 4
  iload_1
  iaload
  istore_1
  iload_3
  iload_1
  invokestatic com/admogo/util/AdMogoUtil/changeURL(II)V
  aload_0
  invokevirtual com/admogo/AdMogoManager/fetchConfig()V
Label1:
  return
Label0:
  iconst_1
  istore_2
  aload_0
  iload_2
  putfield com/admogo/AdMogoManager/isGetInfo Z
  goto Label1
  nop
.end <method>

.method public sendLocationData(Z)V
.limit locals 9
.limit stack 200
  nop
  getstatic com/admogo/AdMogoManager/isSendLocation Z
  istore_2
  new java/lang/NoClassDefFoundError
  dup
  invokespecial java/lang/NoClassDefFoundError/<init>()V
  athrow
  iload_2
  ifne Label0
  aload_0
  getfield com/admogo/AdMogoManager/scheduler Ljava/util/concurrent/ScheduledExecutorService;
  astore_3
  new com/admogo/AdMogoManager$sendLocationRunnable
  astore 4
  aload 4
  aload_0
  iload_1
  invokespecial com/admogo/AdMogoManager$sendLocationRunnable/<init>(Lcom/admogo/AdMogoManager;Z)V
  getstatic java/util/concurrent/TimeUnit/SECONDS Ljava/util/concurrent/TimeUnit;
  astore 5
  ldc2_w 0
  lstore 6
  aload_3
  aload 4
  lload 6
  aload 5
  invokeinterface java/util/concurrent/ScheduledExecutorService/schedule(Ljava/lang/Runnable;JLjava/util/concurrent/TimeUnit;)Ljava/util/concurrent/ScheduledFuture; 5
  pop
  iconst_1
  istore 8
  iload 8
  putstatic com/admogo/AdMogoManager/isSendLocation Z
Label0:
  return
  nop
.end <method>

.method public static setConfigExpireTimeout(J)V
.limit locals 2
.limit stack 200
  nop
  lload_0
  putstatic com/admogo/AdMogoManager/configExpireTimeout J
  return
  nop
.end <method>

.method public setLocation(Ljava/lang/String;)V
.limit locals 4
.limit stack 200
  nop
  aload_0
  aload_1
  putfield com/admogo/AdMogoManager/getCountryCode Ljava/lang/String;
  aload_0
  getfield com/admogo/AdMogoManager/getCountryCode Ljava/lang/String;
  astore_1
  ldc "cn"
  astore_3
  aload_1
  aload_3
  invokevirtual java/lang/String/equalsIgnoreCase(Ljava/lang/String;)Z
  istore_2
  new java/lang/NoClassDefFoundError
  dup
  invokespecial java/lang/NoClassDefFoundError/<init>()V
  athrow
  iload_2
  ifne Label0
  ldc "en"
  astore_3
  aload_3
  putstatic com/admogo/AdMogoManager/PREFS_STRING_COUNTRY Ljava/lang/String;
Label0:
  return
  nop
.end <method>

