.source dalvik_source_VirusShare_32e70f448ebd75661a1cb12f9cd8e013.apk
.class public  com/kuguo/ad/d
.super java/lang/Object
.field protected static "a" I =  0

.method static <clinit>()V
.limit locals 1
.limit stack 200
  nop
  bipush -99
  istore_0
  iload_0
  putstatic com/kuguo/ad/d/a I
  return
  nop
.end <method>

.method public <init>()V
.limit locals 1
.limit stack 200
  nop
  aload_0
  invokespecial java/lang/Object/<init>()V
  return
  nop
.end <method>

.method protected static a()I
.limit locals 14
.limit stack 200
  nop
  iconst_0
  istore_0
  new java/lang/NoClassDefFoundError
  dup
  invokespecial java/lang/NoClassDefFoundError/<init>()V
  athrow
  nop
  ldc "mounted"
  astore_2
  aload_2
  aload_1
  invokevirtual java/lang/String/equals(Ljava/lang/Object;)Z
  istore_3
  iload_3
  invokestatic app/DummyClass/invokeIfStmt(Z)V
  iload_3
  ifne Label0
Label1:
  iload_0
  ireturn
Label0:
  new java/io/File
  astore 4
  invokestatic android/os/Environment/getExternalStorageDirectory()Ljava/io/File;
  astore 5
  ldc "download/ads/"
  astore 6
  aload 4
  aload 5
  aload 6
  invokespecial java/io/File/<init>(Ljava/io/File;Ljava/lang/String;)V
  aload 4
  invokevirtual java/io/File/exists()Z
  istore_3
  iload_3
  invokestatic app/DummyClass/invokeIfStmt(Z)V
  iload_3
  ifeq Label1
  aload 4
  invokevirtual java/io/File/list()[Ljava/lang/String;
  astore 7
  aload 7
  invokestatic app/DummyClass/invokeIfStmt(Ljava/lang/Object;)V
  aload 7
  ifnull Label1
  aload 7
  arraylength
  istore 8
  iconst_0
  dstore 9
Label3:
  dload 9
  invokestatic app/DummyClass/invokeIfStmt(D)V
  dload 8
  invokestatic app/DummyClass/invokeIfStmt(D)V
  iload 9
  iload 8
  if_icmpge Label1
  aload 7
  iload 9
  aaload
  astore_2
Label5:
  aload_2
  invokestatic java/lang/Integer/valueOf(Ljava/lang/String;)Ljava/lang/Integer;
  astore 10
  aload 10
  invokevirtual java/lang/Integer/intValue()I
  istore 11
Label6:
  dload 11
  invokestatic app/DummyClass/invokeIfStmt(D)V
  bipush 121
  istore 12
  iload 11
  iload 12
  if_icmpeq Label2
  iload_0
  iconst_1
  iadd
  istore_0
Label2:
  iload 9
  iconst_1
  iadd
  istore 9
  goto Label3
Label4:
  astore 13
  goto Label2
  nop
.end <method>

.method protected static a(Landroid/content/Context;I)I
.limit locals 7
.limit stack 200
  nop
  new java/lang/NoClassDefFoundError
  dup
  invokespecial java/lang/NoClassDefFoundError/<init>()V
  athrow
  nop
  aload_2
  invokevirtual android/content/res/Resources/getDisplayMetrics()Landroid/util/DisplayMetrics;
  astore_3
  aload_3
  getfield android/util/DisplayMetrics/density F
  fstore 4
  iload_1
  i2f
  fstore 5
  fload 4
  fload 5
  fmul
  fstore 4
  ldc 0.500000
  fstore 6
  fload 4
  fload 6
  fadd
  fstore 4
  fload 4
  f2i
  istore_1
  iload_1
  ireturn
  nop
.end <method>

.method protected static a(Landroid/content/Context;Ljava/lang/String;I)I
.limit locals 22
.limit stack 200
  .catch  java/lang/Throwable <from> Label6 <to> Label7 <using> Label4
  .catch  java/lang/Exception <from> Label6 <to> Label7 <using> Label5
  .catch  java/lang/Throwable <from> Label7 <to> Label10 <using> Label8
  .catch  java/lang/Throwable <from> Label3 <to> Label13 <using> Label8
  nop
  iconst_0
  istore 4
Label6:
  aload_0
  astore_3
  new java/lang/NoClassDefFoundError
  dup
  invokespecial java/lang/NoClassDefFoundError/<init>()V
  athrow
  nop
  new java/io/BufferedReader
  astore 6
  new java/io/InputStreamReader
  astore 7
  iconst_3
  istore 9
  aload_1
  astore_3
  aload 5
  aload_3
  iload 9
  invokevirtual android/content/res/AssetManager/open(Ljava/lang/String;I)Ljava/io/InputStream;
  astore 8
  aload 7
  aload 8
  invokespecial java/io/InputStreamReader/<init>(Ljava/io/InputStream;)V
  aload 6
  aload 7
  invokespecial java/io/BufferedReader/<init>(Ljava/io/Reader;)V
Label7:
  aload 6
  invokevirtual java/io/BufferedReader/readLine()Ljava/lang/String;
  astore 10
  aload 10
  invokestatic java/lang/Integer/valueOf(Ljava/lang/String;)Ljava/lang/Integer;
  astore 11
  aload 11
  invokevirtual java/lang/Integer/intValue()I
  istore 12
Label10:
  iload 12
  istore_2
  aload 6
  invokestatic app/DummyClass/invokeIfStmt(Ljava/lang/Object;)V
  aload 6
  ifnull Label0
Label12:
  aload 6
  invokevirtual java/io/BufferedReader/close()V
Label0:
  iload_2
  ireturn
Label5:
  astore 13
  aconst_null
  astore 6
Label3:
  new java/lang/StringBuilder
  astore 14
  aload 14
  invokespecial java/lang/StringBuilder/<init>()V
  aload_1
  astore_3
  aload 14
  aload_3
  invokevirtual java/lang/StringBuilder/append(Ljava/lang/String;)Ljava/lang/StringBuilder;
  astore 14
  ldc " is not exist!"
  astore 15
  aload 14
  aload 15
  invokevirtual java/lang/StringBuilder/append(Ljava/lang/String;)Ljava/lang/StringBuilder;
  astore 14
  aload 14
  invokevirtual java/lang/StringBuilder/toString()Ljava/lang/String;
  astore 10
  aload 10
  invokestatic com/kuguo/ad/d/a(Ljava/lang/String;)V
Label13:
  new java/lang/NoClassDefFoundError
  dup
  invokespecial java/lang/NoClassDefFoundError/<init>()V
  athrow
  iload 6
  ifeq Label0
Label15:
  aload 6
  invokevirtual java/io/BufferedReader/close()V
Label16:
  iload_2
  ireturn
Label14:
  astore 16
  iload_2
  ireturn
Label4:
  astore 17
Label2:
  new java/lang/NoClassDefFoundError
  dup
  invokespecial java/lang/NoClassDefFoundError/<init>()V
  athrow
  iload 4
  ifeq Label1
Label18:
  aload 4
  invokevirtual java/io/BufferedReader/close()V
Label1:
  aload 17
  athrow
Label11:
  astore 18
  iload 12
  ireturn
Label17:
  astore 19
  goto Label1
Label8:
  astore 20
  aload 6
  astore 4
  aload 20
  astore 17
  goto Label2
Label9:
  astore 21
  goto Label3
  nop
.end <method>

.method protected static final a(Landroid/content/Context;Ljava/lang/String;Ljava/lang/String;)I
.limit locals 20
.limit stack 200
  .catch  java/lang/NoSuchFieldException <from> Label8 <to> Label9 <using> Label3
  .catch  java/lang/SecurityException <from> Label8 <to> Label9 <using> Label4
  .catch  java/lang/InstantiationException <from> Label8 <to> Label9 <using> Label5
  .catch  java/lang/IllegalAccessException <from> Label8 <to> Label9 <using> Label6
  .catch  java/lang/ClassNotFoundException <from> Label8 <to> Label9 <using> Label7
  nop
  new java/lang/StringBuilder
  astore 4
Label8:
  aload 4
  invokespecial java/lang/StringBuilder/<init>()V
  aload_0
  astore_3
  new java/lang/NoClassDefFoundError
  dup
  invokespecial java/lang/NoClassDefFoundError/<init>()V
  athrow
  nop
  aload 4
  aload 5
  invokevirtual java/lang/StringBuilder/append(Ljava/lang/String;)Ljava/lang/StringBuilder;
  astore 4
  ldc ".R"
  astore 6
  aload 4
  aload 6
  invokevirtual java/lang/StringBuilder/append(Ljava/lang/String;)Ljava/lang/StringBuilder;
  astore 4
  aload 4
  invokevirtual java/lang/StringBuilder/toString()Ljava/lang/String;
  astore 5
  aload 5
  invokestatic java/lang/Class/forName(Ljava/lang/String;)Ljava/lang/Class;
  astore 7
  aload 7
  invokevirtual java/lang/Class/getDeclaredClasses()[Ljava/lang/Class;
  astore 8
  aload 8
  arraylength
  istore 9
  iconst_0
  dstore 10
Label2:
  dload 10
  invokestatic app/DummyClass/invokeIfStmt(D)V
  dload 9
  invokestatic app/DummyClass/invokeIfStmt(D)V
  iload 10
  iload 9
  if_icmpge Label0
  aload 8
  iload 10
  aaload
  astore 7
  aload 7
  invokevirtual java/lang/Class/getSimpleName()Ljava/lang/String;
  astore 5
  aload_1
  astore_3
  aload_3
  aload 5
  invokevirtual java/lang/String/equals(Ljava/lang/Object;)Z
  istore 11
  iload 11
  invokestatic app/DummyClass/invokeIfStmt(Z)V
  iload 11
  ifeq Label1
  aload_2
  astore_3
  aload 7
  aload_3
  invokevirtual java/lang/Class/getDeclaredField(Ljava/lang/String;)Ljava/lang/reflect/Field;
  astore 12
  aload 7
  invokevirtual java/lang/Class/newInstance()Ljava/lang/Object;
  astore 13
  aload 12
  aload 13
  invokevirtual java/lang/reflect/Field/getInt(Ljava/lang/Object;)I
  istore 10
Label9:
  iload 10
  ireturn
Label1:
  iload 10
  iconst_1
  iadd
  istore 10
  goto Label2
Label3:
  astore 14
Label0:
  iconst_m1
  istore 15
  iload 15
  ireturn
Label4:
  astore 16
  goto Label0
Label5:
  astore 17
  goto Label0
Label6:
  astore 18
  goto Label0
Label7:
  astore 19
  goto Label0
  nop
.end <method>

.method protected static a(Landroid/content/Context;Ljava/io/File;I)Landroid/content/Intent;
.limit locals 7
.limit stack 200
  nop
  new java/lang/NoClassDefFoundError
  dup
  invokespecial java/lang/NoClassDefFoundError/<init>()V
  athrow
  ldc "android.intent.action.VIEW"
  astore 4
  aload_3
  aload 4
  invokespecial android/content/Intent/<init>(Ljava/lang/String;)V
  aload_1
  invokestatic android/net/Uri/fromFile(Ljava/io/File;)Landroid/net/Uri;
  astore 5
  ldc "application/vnd.android.package-archive"
  astore 4
  aload_3
  aload 5
  aload 4
  invokevirtual android/content/Intent/setDataAndType(Landroid/net/Uri;Ljava/lang/String;)Landroid/content/Intent;
  pop
  ldc 268435456
  istore 6
  aload_3
  iload 6
  invokevirtual android/content/Intent/addFlags(I)Landroid/content/Intent;
  pop
  aload_3
  areturn
  nop
.end <method>

.method protected static a(Landroid/content/Context;Ljava/lang/String;Z)Landroid/graphics/Bitmap;
.limit locals 11
.limit stack 200
  nop
  new java/lang/NoClassDefFoundError
  dup
  invokespecial java/lang/NoClassDefFoundError/<init>()V
  athrow
  iload_2
  ifeq Label0
  aload_0
  invokevirtual android/content/Context/getAssets()Landroid/content/res/AssetManager;
  astore_3
Label2:
  aload_3
  aload_1
  invokevirtual android/content/res/AssetManager/open(Ljava/lang/String;)Ljava/io/InputStream;
  astore 4
  aload 4
  invokestatic android/graphics/BitmapFactory/decodeStream(Ljava/io/InputStream;)Landroid/graphics/Bitmap;
  astore 5
Label3:
  aload 5
  areturn
Label1:
  astore 6
  aload 6
  invokevirtual java/lang/Exception/printStackTrace()V
  aconst_null
  astore 7
  aload 7
  areturn
Label0:
  new java/io/FileInputStream
  astore 8
Label6:
  aload 8
  aload_1
  invokespecial java/io/FileInputStream/<init>(Ljava/lang/String;)V
  aload 8
  invokestatic android/graphics/BitmapFactory/decodeStream(Ljava/io/InputStream;)Landroid/graphics/Bitmap;
  astore 5
Label7:
  aload 5
  areturn
Label5:
  astore 9
  aload 9
  invokevirtual java/io/FileNotFoundException/printStackTrace()V
  aconst_null
  astore 7
  aload 7
  areturn
Label4:
  astore 10
  aload 10
  invokevirtual java/lang/Exception/printStackTrace()V
  aconst_null
  astore 7
  aload 7
  areturn
  nop
.end <method>

.method protected static a(Landroid/view/View;)Landroid/widget/ImageView;
.limit locals 12
.limit stack 200
  nop
  new java/lang/NoClassDefFoundError
  dup
  invokespecial java/lang/NoClassDefFoundError/<init>()V
  athrow
  iload_1
  invokestatic app/DummyClass/invokeIfStmt(Z)V
  iload_1
  ifeq Label0
  aload_0
  astore_3
  aload_3
  checkcast android/widget/ImageView
  astore_3
  aload_3
  astore_2
  aload_2
  areturn
Label0:
  aload_0
  instanceof android/view/ViewGroup
  istore_1
  iload_1
  invokestatic app/DummyClass/invokeIfStmt(Z)V
  iload_1
  ifeq Label1
  iconst_0
  dstore 4
Label4:
  aload_0
  astore 6
  aload 6
  checkcast android/view/ViewGroup
  astore 6
  aload 6
  astore 5
  aload 5
  invokevirtual android/view/ViewGroup/getChildCount()I
  istore 7
  dload 4
  invokestatic app/DummyClass/invokeIfStmt(D)V
  dload 7
  invokestatic app/DummyClass/invokeIfStmt(D)V
  iload 4
  iload 7
  if_icmpge Label1
  aload_0
  astore 8
  aload 8
  checkcast android/view/ViewGroup
  astore 8
  aload 8
  astore 5
  aload 5
  iload 4
  invokevirtual android/view/ViewGroup/getChildAt(I)Landroid/view/View;
  astore 9
  aload 9
  instanceof android/widget/ImageView
  istore_1
  iload_1
  invokestatic app/DummyClass/invokeIfStmt(Z)V
  iload_1
  ifeq Label2
  aload 9
  astore 10
  aload 10
  checkcast android/widget/ImageView
  astore 10
  aload 10
  astore_2
  aload_2
  areturn
Label2:
  aload 9
  instanceof android/view/ViewGroup
  istore_1
  iload_1
  invokestatic app/DummyClass/invokeIfStmt(Z)V
  iload_1
  ifeq Label3
  aload 9
  invokestatic com/kuguo/ad/d/a(Landroid/view/View;)Landroid/widget/ImageView;
  astore_2
  aload_2
  areturn
Label3:
  iload 4
  iconst_1
  iadd
  istore 4
  goto Label4
Label1:
  aconst_null
  astore 11
  aload 11
  areturn
  nop
.end <method>

.method protected static a(Landroid/content/Context;Ljava/lang/String;)Lcom/kuguo/ad/p;
.limit locals 11
.limit stack 200
  nop
  new java/lang/NoClassDefFoundError
  dup
  invokespecial java/lang/NoClassDefFoundError/<init>()V
  athrow
  iload_1
  ifeq Label0
  aload_1
  invokevirtual java/lang/String/trim()Ljava/lang/String;
  astore_2
  ldc ""
  astore 4
  aload_2
  aload 4
  invokevirtual java/lang/String/equals(Ljava/lang/Object;)Z
  istore_3
  iload_3
  invokestatic app/DummyClass/invokeIfStmt(Z)V
  iload_3
  ifeq Label1
Label0:
  aconst_null
  astore 5
Label5:
  aload 5
  areturn
Label1:
  aload_0
  invokestatic com/kuguo/ad/d/d(Landroid/content/Context;)[Lcom/kuguo/ad/p;
  astore 6
  aload 6
  invokestatic app/DummyClass/invokeIfStmt(Ljava/lang/Object;)V
  aload 6
  ifnull Label2
  aload 6
  arraylength
  istore 7
  dload 7
  invokestatic app/DummyClass/invokeIfStmt(D)V
  iload 7
  ifgt Label3
Label2:
  aconst_null
  astore 8
  aload 8
  areturn
Label3:
  aload 6
  arraylength
  istore 7
  iconst_0
  dstore 9
Label6:
  dload 9
  invokestatic app/DummyClass/invokeIfStmt(D)V
  dload 7
  invokestatic app/DummyClass/invokeIfStmt(D)V
  iload 9
  iload 7
  if_icmpge Label4
  aload 6
  iload 9
  aaload
  astore 5
  aload 5
  getfield com/kuguo/ad/p/i Ljava/lang/String;
  astore 10
  aload_1
  aload 10
  invokevirtual java/lang/String/equals(Ljava/lang/Object;)Z
  istore_3
  iload_3
  invokestatic app/DummyClass/invokeIfStmt(Z)V
  iload_3
  ifne Label5
  iload 9
  iconst_1
  iadd
  istore 9
  goto Label6
Label4:
  aconst_null
  astore 8
  aload 8
  areturn
  nop
.end <method>

.method public static a(Landroid/content/Context;)Ljava/lang/String;
.limit locals 8
.limit stack 200
  nop
  ldc "phone"
  astore_2
  new java/lang/NoClassDefFoundError
  dup
  invokespecial java/lang/NoClassDefFoundError/<init>()V
  athrow
  nop
  aload_1
  astore 4
  aload 4
  checkcast android/telephony/TelephonyManager
  astore 4
  aload 4
  astore_3
  aload_3
  invokevirtual android/telephony/TelephonyManager/getSubscriberId()Ljava/lang/String;
  astore 5
  new java/lang/StringBuilder
  astore 6
  aload 6
  invokespecial java/lang/StringBuilder/<init>()V
  ldc "imsi == "
  astore_2
  aload 6
  aload_2
  invokevirtual java/lang/StringBuilder/append(Ljava/lang/String;)Ljava/lang/StringBuilder;
  astore 6
  aload 6
  aload 5
  invokevirtual java/lang/StringBuilder/append(Ljava/lang/String;)Ljava/lang/StringBuilder;
  astore 6
  aload 6
  invokevirtual java/lang/StringBuilder/toString()Ljava/lang/String;
  astore 7
  aload 7
  invokestatic com/kuguo/ad/d/a(Ljava/lang/String;)V
  aload 5
  areturn
  nop
.end <method>

.method protected static a(Ljava/lang/String;I)Ljava/lang/String;
.limit locals 10
.limit stack 200
  nop
  new java/lang/NoClassDefFoundError
  dup
  invokespecial java/lang/NoClassDefFoundError/<init>()V
  athrow
  nop
  ldc "mounted"
  astore_3
  aload_3
  aload_2
  invokevirtual java/lang/String/equals(Ljava/lang/Object;)Z
  istore 4
  iload 4
  invokestatic app/DummyClass/invokeIfStmt(Z)V
  iload 4
  ifne Label0
Label1:
  aconst_null
  astore 5
  aload 5
  areturn
Label0:
  new java/lang/StringBuilder
  astore 6
  aload 6
  invokespecial java/lang/StringBuilder/<init>()V
  ldc "download/ads/"
  astore 7
  aload 6
  aload 7
  invokevirtual java/lang/StringBuilder/append(Ljava/lang/String;)Ljava/lang/StringBuilder;
  astore 6
  aload 6
  iload_1
  invokevirtual java/lang/StringBuilder/append(I)Ljava/lang/StringBuilder;
  astore 6
  ldc "/"
  astore 7
  aload 6
  aload 7
  invokevirtual java/lang/StringBuilder/append(Ljava/lang/String;)Ljava/lang/StringBuilder;
  astore 6
  aload 6
  aload_0
  invokevirtual java/lang/StringBuilder/append(Ljava/lang/String;)Ljava/lang/StringBuilder;
  astore 6
  aload 6
  invokevirtual java/lang/StringBuilder/toString()Ljava/lang/String;
  astore_3
  new java/io/File
  astore 8
  invokestatic android/os/Environment/getExternalStorageDirectory()Ljava/io/File;
  astore 9
  aload 8
  aload 9
  aload_3
  invokespecial java/io/File/<init>(Ljava/io/File;Ljava/lang/String;)V
  aload 8
  invokevirtual java/io/File/exists()Z
  istore 4
  iload 4
  invokestatic app/DummyClass/invokeIfStmt(Z)V
  iload 4
  ifeq Label1
  aload 8
  invokevirtual java/io/File/getPath()Ljava/lang/String;
  astore_3
  aload_3
  areturn
  nop
.end <method>

.method protected static a(J)V
.limit locals 5
.limit stack 200
  nop
  new java/lang/StringBuilder
  astore_2
  aload_2
  invokespecial java/lang/StringBuilder/<init>()V
  ldc "spaceTime ------------------------- "
  astore_3
  aload_2
  aload_3
  invokevirtual java/lang/StringBuilder/append(Ljava/lang/String;)Ljava/lang/StringBuilder;
  astore_2
  aload_2
  lload_0
  invokevirtual java/lang/StringBuilder/append(J)Ljava/lang/StringBuilder;
  astore_2
  aload_2
  invokevirtual java/lang/StringBuilder/toString()Ljava/lang/String;
  astore 4
  aload 4
  invokestatic com/kuguo/ad/d/a(Ljava/lang/String;)V
  lload_0
  invokestatic java/lang/String/valueOf(J)Ljava/lang/String;
  astore 4
  ldc "download/ads/st.dat"
  astore_3
  aload_3
  aload 4
  invokestatic com/kuguo/ad/d/b(Ljava/lang/String;Ljava/lang/String;)Z
  pop
  return
  nop
.end <method>

.method protected static a(Landroid/content/Context;Landroid/content/Intent;ILcom/kuguo/ad/p;IZZ)V
.limit locals 39
.limit stack 200
  nop
  aload_3
  astore 7
  aload 7
  getfield com/kuguo/ad/p/h I
  istore 10
  iload 10
  sipush 10000
  iadd
  istore 10
  ldc "notification"
  astore 12
  aload_0
  astore 7
  new java/lang/NoClassDefFoundError
  dup
  invokespecial java/lang/NoClassDefFoundError/<init>()V
  athrow
  nop
  aload 11
  astore 14
  aload 14
  checkcast android/app/NotificationManager
  astore 14
  aload 14
  astore 13
  iload 6
  istore 7
  iload 7
  invokestatic app/DummyClass/invokeIfStmt(Z)V
  iload 6
  ifeq Label0
  aload 13
  iload 10
  invokevirtual android/app/NotificationManager/cancel(I)V
Label4:
  return
Label0:
  new android/app/Notification
  astore 15
  aload_3
  astore 7
  aload 7
  getfield com/kuguo/ad/p/k Ljava/lang/String;
  astore 16
  invokestatic java/lang/System/currentTimeMillis()J
  lstore 17
  iload_2
  istore 7
  aload 15
  iload 7
  aload 16
  lload 17
  invokespecial android/app/Notification/<init>(ILjava/lang/CharSequence;J)V
  ldc 134217728
  istore 20
  aload_0
  astore 7
  aload_1
  astore 8
  aload 7
  iload 10
  aload 8
  iload 20
  invokestatic android/app/PendingIntent/getActivity(Landroid/content/Context;ILandroid/content/Intent;I)Landroid/app/PendingIntent;
  astore 19
  ldc "layout"
  astore 12
  ldc "kuguo_notify"
  astore 22
  aload_0
  astore 7
  aload 7
  aload 12
  aload 22
  invokestatic com/kuguo/ad/d/a(Landroid/content/Context;Ljava/lang/String;Ljava/lang/String;)I
  istore 21
  ldc "id"
  astore 12
  ldc "icon"
  astore 22
  aload_0
  astore 7
  aload 7
  aload 12
  aload 22
  invokestatic com/kuguo/ad/d/a(Landroid/content/Context;Ljava/lang/String;Ljava/lang/String;)I
  istore 23
  ldc "id"
  astore 12
  ldc "title"
  astore 22
  aload_0
  astore 7
  aload 7
  aload 12
  aload 22
  invokestatic com/kuguo/ad/d/a(Landroid/content/Context;Ljava/lang/String;Ljava/lang/String;)I
  istore 24
  ldc "id"
  astore 12
  ldc "body"
  astore 22
  aload_0
  astore 7
  aload 7
  aload 12
  aload 22
  invokestatic com/kuguo/ad/d/a(Landroid/content/Context;Ljava/lang/String;Ljava/lang/String;)I
  istore 25
  ldc "id"
  astore 12
  ldc "time"
  astore 22
  aload_0
  astore 7
  aload 7
  aload 12
  aload 22
  invokestatic com/kuguo/ad/d/a(Landroid/content/Context;Ljava/lang/String;Ljava/lang/String;)I
  istore 26
  aload_3
  astore 7
  aload 7
  getfield com/kuguo/ad/p/h I
  istore 7
  iload 7
  istore_2
  ldc "icon.png"
  astore 12
  iload_2
  istore 7
  aload 12
  iload 7
  invokestatic com/kuguo/ad/d/a(Ljava/lang/String;I)Ljava/lang/String;
  astore 27
  iconst_0
  istore 20
  aload_0
  astore 7
  aload 27
  astore 8
  aload 7
  aload 8
  iload 20
  invokestatic com/kuguo/ad/d/a(Landroid/content/Context;Ljava/lang/String;Z)Landroid/graphics/Bitmap;
  astore 28
  dload 21
  invokestatic app/DummyClass/invokeIfStmt(D)V
  iconst_m1
  istore 20
  iload 21
  iload 20
  if_icmpeq Label1
  iload 25
  istore 7
  dload 7
  invokestatic app/DummyClass/invokeIfStmt(D)V
  iconst_m1
  istore 20
  iload 25
  istore 7
  iload 7
  iload 20
  if_icmpeq Label1
  iload 23
  istore 7
  dload 7
  invokestatic app/DummyClass/invokeIfStmt(D)V
  iconst_m1
  istore 20
  iload 23
  istore 7
  iload 7
  iload 20
  if_icmpeq Label1
  iload 24
  istore 7
  dload 7
  invokestatic app/DummyClass/invokeIfStmt(D)V
  iconst_m1
  istore 20
  iload 24
  istore 7
  iload 7
  iload 20
  if_icmpeq Label1
  iload 26
  istore 7
  dload 7
  invokestatic app/DummyClass/invokeIfStmt(D)V
  iconst_m1
  istore 20
  iload 26
  istore 7
  iload 7
  iload 20
  if_icmpeq Label1
  aload 28
  astore 7
  aload 7
  invokestatic app/DummyClass/invokeIfStmt(Ljava/lang/Object;)V
  aload 28
  ifnull Label1
  aload 15
  aload 19
  putfield android/app/Notification/contentIntent Landroid/app/PendingIntent;
  new android/widget/RemoteViews
  astore 29
  aload_0
  astore 7
  aload 7
  invokevirtual android/content/Context/getPackageName()Ljava/lang/String;
  astore 27
  aload 29
  astore 7
  aload 27
  astore 8
  aload 7
  aload 8
  iload 21
  invokespecial android/widget/RemoteViews/<init>(Ljava/lang/String;I)V
  aload 29
  astore 7
  aload 15
  aload 7
  putfield android/app/Notification/contentView Landroid/widget/RemoteViews;
  aload 29
  astore 7
  iload 23
  istore 8
  aload 28
  astore 9
  aload 7
  iload 8
  aload 9
  invokevirtual android/widget/RemoteViews/setImageViewBitmap(ILandroid/graphics/Bitmap;)V
  new java/lang/StringBuilder
  astore 30
  aload 30
  astore 7
  aload 7
  invokespecial java/lang/StringBuilder/<init>()V
  ldc "<big>"
  astore 12
  aload 30
  astore 7
  aload 7
  aload 12
  invokevirtual java/lang/StringBuilder/append(Ljava/lang/String;)Ljava/lang/StringBuilder;
  astore 30
  aload_3
  astore 7
  aload 7
  getfield com/kuguo/ad/p/k Ljava/lang/String;
  astore 7
  aload 7
  astore 27
  aload 30
  astore 7
  aload 27
  astore 8
  aload 7
  aload 8
  invokevirtual java/lang/StringBuilder/append(Ljava/lang/String;)Ljava/lang/StringBuilder;
  astore 30
  ldc "</big>"
  astore 12
  aload 30
  astore 7
  aload 7
  aload 12
  invokevirtual java/lang/StringBuilder/append(Ljava/lang/String;)Ljava/lang/StringBuilder;
  astore 30
  aload 30
  astore 7
  aload 7
  invokevirtual java/lang/StringBuilder/toString()Ljava/lang/String;
  astore 27
  aload 27
  astore 7
  aload 7
  invokestatic android/text/Html/fromHtml(Ljava/lang/String;)Landroid/text/Spanned;
  astore 31
  aload 29
  astore 7
  iload 24
  istore 8
  aload 31
  astore 9
  aload 7
  iload 8
  aload 9
  invokevirtual android/widget/RemoteViews/setTextViewText(ILjava/lang/CharSequence;)V
  aload_3
  astore 7
  aload 7
  getfield com/kuguo/ad/p/b Ljava/lang/String;
  astore 7
  aload 7
  astore 27
  aload 29
  astore 7
  iload 25
  istore 8
  aload 27
  astore 9
  aload 7
  iload 8
  aload 9
  invokevirtual android/widget/RemoteViews/setTextViewText(ILjava/lang/CharSequence;)V
  new java/text/SimpleDateFormat
  astore 32
  ldc "H:mm"
  astore 12
  aload 32
  astore 7
  aload 7
  aload 12
  invokespecial java/text/SimpleDateFormat/<init>(Ljava/lang/String;)V
  new java/util/Date
  astore 33
  aload 33
  astore 7
  aload 7
  invokespecial java/util/Date/<init>()V
  aload 32
  astore 7
  aload 33
  astore 8
  aload 7
  aload 8
  invokevirtual java/text/SimpleDateFormat/format(Ljava/util/Date;)Ljava/lang/String;
  astore 27
  aload 29
  astore 7
  iload 26
  istore 8
  aload 27
  astore 9
  aload 7
  iload 8
  aload 9
  invokevirtual android/widget/RemoteViews/setTextViewText(ILjava/lang/CharSequence;)V
Label5:
  getstatic com/kuguo/ad/d/a I
  istore 26
  dload 4
  dstore 7
  dload 7
  invokestatic app/DummyClass/invokeIfStmt(D)V
  iload 26
  istore 7
  dload 7
  invokestatic app/DummyClass/invokeIfStmt(D)V
  iload 4
  istore 7
  iload 26
  istore 8
  iload 7
  iload 8
  if_icmpeq Label2
  iload 4
  istore 7
  aload 15
  iload 7
  putfield android/app/Notification/flags I
Label2:
  iload 5
  istore 7
  iload 7
  invokestatic app/DummyClass/invokeIfStmt(Z)V
  iload 5
  ifeq Label3
  aload 15
  getfield android/app/Notification/defaults I
  istore 7
  iload 7
  istore 26
  iload 26
  iconst_4
  ior
  istore 26
  iload 26
  istore 7
  aload 15
  iload 7
  putfield android/app/Notification/defaults I
  aload 15
  getfield android/app/Notification/flags I
  istore 7
  iload 7
  istore 26
  iload 26
  iconst_1
  ior
  istore 26
  iload 26
  istore 7
  aload 15
  iload 7
  putfield android/app/Notification/flags I
  ldc -16711936
  istore 20
  aload 15
  iload 20
  putfield android/app/Notification/ledARGB I
  sipush 500
  istore 20
  aload 15
  iload 20
  putfield android/app/Notification/ledOnMS I
  sipush 2000
  istore 20
  aload 15
  iload 20
  putfield android/app/Notification/ledOffMS I
Label3:
  aload 13
  iload 10
  aload 15
  invokevirtual android/app/NotificationManager/notify(ILandroid/app/Notification;)V
  goto Label4
Label1:
  aload_3
  astore 7
  aload 7
  getfield com/kuguo/ad/p/k Ljava/lang/String;
  astore 7
  aload 7
  astore 27
  aload_3
  astore 7
  aload 7
  getfield com/kuguo/ad/p/b Ljava/lang/String;
  astore 16
  aload_0
  astore 7
  aload 27
  astore 8
  aload 15
  aload 7
  aload 8
  aload 16
  aload 19
  invokevirtual android/app/Notification/setLatestEventInfo(Landroid/content/Context;Ljava/lang/CharSequence;Ljava/lang/CharSequence;Landroid/app/PendingIntent;)V
Label7:
  aload_0
  astore 7
  aload 7
  invokestatic android/view/LayoutInflater/from(Landroid/content/Context;)Landroid/view/LayoutInflater;
  astore 34
  aload 15
  getfield android/app/Notification/contentView Landroid/widget/RemoteViews;
  astore 7
  aload 7
  astore 29
  aload 29
  astore 7
  aload 7
  invokevirtual android/widget/RemoteViews/getLayoutId()I
  istore 26
  aconst_null
  astore 36
  aload 34
  astore 7
  iload 26
  istore 8
  aload 36
  astore 9
  aload 7
  iload 8
  aload 9
  invokevirtual android/view/LayoutInflater/inflate(ILandroid/view/ViewGroup;)Landroid/view/View;
  astore 35
  aload 35
  astore 7
  aload 7
  invokestatic app/DummyClass/invokeIfStmt(Ljava/lang/Object;)V
  aload 35
  ifnull Label5
  aload 35
  astore 7
  aload 7
  invokestatic com/kuguo/ad/d/a(Landroid/view/View;)Landroid/widget/ImageView;
  astore 37
  aload 37
  astore 7
  aload 7
  invokestatic app/DummyClass/invokeIfStmt(Ljava/lang/Object;)V
  aload 37
  ifnull Label5
  aload 28
  astore 7
  aload 7
  invokestatic app/DummyClass/invokeIfStmt(Ljava/lang/Object;)V
  aload 28
  ifnull Label5
  aload 15
  getfield android/app/Notification/contentView Landroid/widget/RemoteViews;
  astore 7
  aload 7
  astore 29
  aload 37
  astore 7
  aload 7
  invokevirtual android/widget/ImageView/getId()I
  istore 26
  aload 29
  astore 7
  iload 26
  istore 8
  aload 28
  astore 9
  aload 7
  iload 8
  aload 9
  invokevirtual android/widget/RemoteViews/setImageViewBitmap(ILandroid/graphics/Bitmap;)V
Label8:
  goto Label5
Label6:
  astore 38
  goto Label5
  nop
.end <method>

.method public static a(Landroid/content/Context;Ljava/lang/String;Ljava/lang/String;I)V
.limit locals 8
.limit stack 200
  nop
  new java/lang/NoClassDefFoundError
  dup
  invokespecial java/lang/NoClassDefFoundError/<init>()V
  athrow
  iload_1
  ifeq Label0
  ldc ""
  astore 4
  aload 4
  aload_1
  invokevirtual java/lang/String/equals(Ljava/lang/Object;)Z
  istore 5
  iload 5
  invokestatic app/DummyClass/invokeIfStmt(Z)V
  iload 5
  ifne Label0
  aload_2
  invokestatic app/DummyClass/invokeIfStmt(Ljava/lang/Object;)V
  iload_2
  ifeq Label0
  ldc ""
  astore 4
  aload 4
  aload_2
  invokevirtual java/lang/String/equals(Ljava/lang/Object;)Z
  istore 5
  iload 5
  invokestatic app/DummyClass/invokeIfStmt(Z)V
  iload 5
  ifeq Label1
Label0:
  return
Label1:
  new java/io/File
  astore 6
  aload 6
  aload_1
  invokespecial java/io/File/<init>(Ljava/lang/String;)V
  aload_0
  aload 6
  iload_3
  invokestatic com/kuguo/ad/d/a(Landroid/content/Context;Ljava/io/File;I)Landroid/content/Intent;
  astore 7
  aload_0
  aload 7
  invokevirtual android/content/Context/startActivity(Landroid/content/Intent;)V
  goto Label0
  nop
.end <method>

.method protected static a(Ljava/lang/String;)V
.limit locals 1
.limit stack 200
  nop
  return
  nop
.end <method>

.method private static a(Landroid/content/Context;II)Z
.limit locals 25
.limit stack 200
  nop
  iload_2
  istore_3
  new java/lang/NoClassDefFoundError
  dup
  invokespecial java/lang/NoClassDefFoundError/<init>()V
  athrow
  iconst_m1
  istore 4
  iload_2
  istore_3
  iload_3
  iload 4
  if_icmpne Label0
  iconst_0
  istore 4
  iload 4
  ireturn
Label0:
  ldc "request_prefs"
  astore 6
  iconst_0
  istore 4
  aload_0
  astore_3
  aload_3
  aload 6
  iload 4
  invokevirtual android/content/Context/getSharedPreferences(Ljava/lang/String;I)Landroid/content/SharedPreferences;
  astore 5
  ldc "adsState"
  astore 6
  ldc ""
  astore 8
  aload 5
  aload 6
  aload 8
  invokeinterface android/content/SharedPreferences/getString(Ljava/lang/String;Ljava/lang/String;)Ljava/lang/String; 3
  astore 7
  aload 5
  invokeinterface android/content/SharedPreferences/edit()Landroid/content/SharedPreferences$Editor; 1
  astore 9
  ldc ""
  astore 10
  aload 10
  aload 7
  invokevirtual java/lang/String/equals(Ljava/lang/Object;)Z
  istore 11
  iload 11
  invokestatic app/DummyClass/invokeIfStmt(Z)V
  iload 11
  ifeq Label1
  new java/lang/StringBuilder
  astore 12
  aload 12
  invokespecial java/lang/StringBuilder/<init>()V
  ldc ""
  astore 6
  aload 12
  aload 6
  invokevirtual java/lang/StringBuilder/append(Ljava/lang/String;)Ljava/lang/StringBuilder;
  astore 12
  iload_1
  istore_3
  aload 12
  iload_3
  invokevirtual java/lang/StringBuilder/append(I)Ljava/lang/StringBuilder;
  astore 12
  ldc ","
  astore 6
  aload 12
  aload 6
  invokevirtual java/lang/StringBuilder/append(Ljava/lang/String;)Ljava/lang/StringBuilder;
  astore 12
  iload_2
  istore_3
  aload 12
  iload_3
  invokevirtual java/lang/StringBuilder/append(I)Ljava/lang/StringBuilder;
  astore 12
  aload 12
  invokevirtual java/lang/StringBuilder/toString()Ljava/lang/String;
  astore 7
  ldc "adsState"
  astore 6
  aload 9
  aload 6
  aload 7
  invokeinterface android/content/SharedPreferences$Editor/putString(Ljava/lang/String;Ljava/lang/String;)Landroid/content/SharedPreferences$Editor; 3
  pop
Label9:
  aload 9
  invokeinterface android/content/SharedPreferences$Editor/commit()Z 1
  istore 11
  iload 11
  ireturn
Label1:
  new java/util/HashMap
  astore 13
  aload 13
  invokespecial java/util/HashMap/<init>()V
  ldc ";"
  astore 6
  aload 7
  aload 6
  invokestatic com/kuguo/ad/d/a(Ljava/lang/String;Ljava/lang/String;)[Ljava/lang/String;
  astore 14
  aload 14
  invokestatic app/DummyClass/invokeIfStmt(Ljava/lang/Object;)V
  aload 14
  ifnull Label2
  aload 14
  arraylength
  istore 15
  iconst_0
  dstore 16
Label4:
  dload 16
  invokestatic app/DummyClass/invokeIfStmt(D)V
  dload 15
  invokestatic app/DummyClass/invokeIfStmt(D)V
  iload 16
  iload 15
  if_icmpge Label2
  aload 14
  iload 16
  aaload
  astore 10
  ldc ","
  astore 6
  aload 10
  aload 6
  invokestatic com/kuguo/ad/d/a(Ljava/lang/String;Ljava/lang/String;)[Ljava/lang/String;
  astore 17
  aload 17
  invokestatic app/DummyClass/invokeIfStmt(Ljava/lang/Object;)V
  aload 17
  ifnull Label3
  aload 17
  arraylength
  istore 18
  dload 18
  invokestatic app/DummyClass/invokeIfStmt(D)V
  iconst_2
  istore 4
  iload 18
  iload 4
  if_icmpne Label3
  iconst_0
  istore 4
  aload 17
  iload 4
  aaload
  astore 7
  iconst_1
  istore 4
  aload 17
  iload 4
  aaload
  astore 10
  aload 13
  aload 7
  aload 10
  invokevirtual java/util/HashMap/put(Ljava/lang/Object;Ljava/lang/Object;)Ljava/lang/Object;
  pop
Label3:
  iload 16
  iconst_1
  iadd
  istore 16
  goto Label4
Label2:
  iload_1
  istore_3
  iload_3
  invokestatic java/lang/String/valueOf(I)Ljava/lang/String;
  astore 7
  iload_2
  istore_3
  iload_3
  invokestatic java/lang/String/valueOf(I)Ljava/lang/String;
  astore 10
  aload 13
  aload 7
  aload 10
  invokevirtual java/util/HashMap/put(Ljava/lang/Object;Ljava/lang/Object;)Ljava/lang/Object;
  pop
  aload 13
  invokevirtual java/util/HashMap/keySet()Ljava/util/Set;
  astore 19
  aload 19
  astore_3
  aload_3
  invokeinterface java/util/Set/iterator()Ljava/util/Iterator; 1
  astore 20
  aconst_null
  astore 21
Label7:
  aload 20
  astore_3
  aload_3
  invokeinterface java/util/Iterator/hasNext()Z 1
  istore 11
  iload 11
  invokestatic app/DummyClass/invokeIfStmt(Z)V
  iload 11
  ifeq Label5
  aload 21
  astore_3
  aload_3
  invokestatic app/DummyClass/invokeIfStmt(Ljava/lang/Object;)V
  aload 21
  ifnonnull Label6
  new java/lang/StringBuffer
  astore 21
  aload 21
  astore_3
  aload_3
  invokespecial java/lang/StringBuffer/<init>()V
Label8:
  aload 20
  astore_3
  aload_3
  invokeinterface java/util/Iterator/next()Ljava/lang/Object; 1
  astore 22
  aload 22
  astore 23
  aload 23
  checkcast java/lang/String
  astore 23
  aload 23
  astore 7
  aload 13
  aload 7
  invokevirtual java/util/HashMap/get(Ljava/lang/Object;)Ljava/lang/Object;
  astore 22
  aload 22
  astore 24
  aload 24
  checkcast java/lang/String
  astore 24
  aload 24
  astore 10
  aload 21
  astore_3
  aload_3
  aload 7
  invokevirtual java/lang/StringBuffer/append(Ljava/lang/String;)Ljava/lang/StringBuffer;
  pop
  ldc ","
  astore 6
  aload 21
  astore_3
  aload_3
  aload 6
  invokevirtual java/lang/StringBuffer/append(Ljava/lang/String;)Ljava/lang/StringBuffer;
  pop
  aload 21
  astore_3
  aload_3
  aload 10
  invokevirtual java/lang/StringBuffer/append(Ljava/lang/String;)Ljava/lang/StringBuffer;
  pop
  goto Label7
Label6:
  ldc ";"
  astore 6
  aload 21
  astore_3
  aload_3
  aload 6
  invokevirtual java/lang/StringBuffer/append(Ljava/lang/String;)Ljava/lang/StringBuffer;
  pop
  goto Label8
Label5:
  aload 21
  astore_3
  aload_3
  invokestatic app/DummyClass/invokeIfStmt(Ljava/lang/Object;)V
  aload 21
  ifnull Label9
  aload 21
  astore_3
  aload_3
  invokevirtual java/lang/StringBuffer/toString()Ljava/lang/String;
  astore 7
  ldc "adsState"
  astore 6
  aload 9
  aload 6
  aload 7
  invokeinterface android/content/SharedPreferences$Editor/putString(Ljava/lang/String;Ljava/lang/String;)Landroid/content/SharedPreferences$Editor; 3
  pop
  goto Label9
  nop
.end <method>

.method protected static a(Landroid/content/Context;Lcom/kuguo/ad/p;)Z
.limit locals 12
.limit stack 200
  nop
  iconst_0
  istore_2
  ldc "message_prefs"
  astore 4
  iconst_0
  istore 5
  new java/lang/NoClassDefFoundError
  dup
  invokespecial java/lang/NoClassDefFoundError/<init>()V
  athrow
  nop
  aload_1
  getfield com/kuguo/ad/p/w I
  istore 6
  aload_0
  iload 6
  invokestatic com/kuguo/ad/d/b(Landroid/content/Context;I)Z
  pop
  aload_1
  getfield com/kuguo/ad/p/h I
  istore 6
  dload 6
  invokestatic app/DummyClass/invokeIfStmt(D)V
  iconst_m1
  istore 5
  iload 6
  iload 5
  if_icmpne Label0
  iconst_0
  istore 5
  iload 5
  ireturn
Label0:
  new java/lang/StringBuilder
  astore 7
  aload 7
  invokespecial java/lang/StringBuilder/<init>()V
  ldc ""
  astore 4
  aload 7
  aload 4
  invokevirtual java/lang/StringBuilder/append(Ljava/lang/String;)Ljava/lang/StringBuilder;
  astore 7
  aload 7
  iload_2
  invokevirtual java/lang/StringBuilder/append(I)Ljava/lang/StringBuilder;
  astore 7
  aload 7
  invokevirtual java/lang/StringBuilder/toString()Ljava/lang/String;
  astore 8
  aload_3
  aload 8
  invokeinterface android/content/SharedPreferences/contains(Ljava/lang/String;)Z 2
  istore 9
  iload 9
  invokestatic app/DummyClass/invokeIfStmt(Z)V
  iload 9
  ifeq Label1
  iload_2
  iconst_1
  iadd
  istore_2
  goto Label0
Label1:
  aload_1
  iload_2
  putfield com/kuguo/ad/p/f I
  aload_3
  invokeinterface android/content/SharedPreferences/edit()Landroid/content/SharedPreferences$Editor; 1
  astore 10
  new java/lang/StringBuilder
  astore 7
  aload 7
  invokespecial java/lang/StringBuilder/<init>()V
  ldc ""
  astore 4
  aload 7
  aload 4
  invokevirtual java/lang/StringBuilder/append(Ljava/lang/String;)Ljava/lang/StringBuilder;
  astore 7
  aload 7
  iload_2
  invokevirtual java/lang/StringBuilder/append(I)Ljava/lang/StringBuilder;
  astore 7
  aload 7
  invokevirtual java/lang/StringBuilder/toString()Ljava/lang/String;
  astore 8
  aload_1
  invokevirtual com/kuguo/ad/p/a()Ljava/lang/String;
  astore 11
  aload 10
  aload 8
  aload 11
  invokeinterface android/content/SharedPreferences$Editor/putString(Ljava/lang/String;Ljava/lang/String;)Landroid/content/SharedPreferences$Editor; 3
  pop
  aload 10
  invokeinterface android/content/SharedPreferences$Editor/commit()Z 1
  istore 9
  iload 9
  ireturn
  nop
.end <method>

.method protected static a(Ljava/lang/String;Ljava/lang/String;)[Ljava/lang/String;
.limit locals 15
.limit stack 200
  nop
  iconst_0
  istore_2
  new java/lang/NoClassDefFoundError
  dup
  invokespecial java/lang/NoClassDefFoundError/<init>()V
  athrow
  iload_0
  ifeq Label0
  ldc ""
  astore 4
  aload_0
  aload 4
  invokevirtual java/lang/String/equals(Ljava/lang/Object;)Z
  istore_3
  iload_3
  invokestatic app/DummyClass/invokeIfStmt(Z)V
  iload_3
  ifne Label0
  aload_1
  invokestatic app/DummyClass/invokeIfStmt(Ljava/lang/Object;)V
  iload_1
  ifeq Label0
  ldc ""
  astore 4
  aload_1
  aload 4
  invokevirtual java/lang/String/equals(Ljava/lang/Object;)Z
  istore_3
  iload_3
  invokestatic app/DummyClass/invokeIfStmt(Z)V
  iload_3
  ifeq Label1
Label0:
  aconst_null
  astore 5
  aload 5
  areturn
Label1:
  new java/util/ArrayList
  astore 6
  aload 6
  invokespecial java/util/ArrayList/<init>()V
  iconst_0
  istore 7
Label6:
  aload_0
  aload_1
  iload 7
  invokevirtual java/lang/String/indexOf(Ljava/lang/String;I)I
  istore 8
  dload 8
  invokestatic app/DummyClass/invokeIfStmt(D)V
  iconst_m1
  istore 9
  iload 8
  iload 9
  if_icmpne Label2
  aload_0
  invokevirtual java/lang/String/length()I
  istore 8
  dload 8
  invokestatic app/DummyClass/invokeIfStmt(D)V
  dload 7
  invokestatic app/DummyClass/invokeIfStmt(D)V
  iload 8
  iload 7
  if_icmple Label3
  aload_0
  iload 7
  invokevirtual java/lang/String/substring(I)Ljava/lang/String;
  astore 10
  aload 6
  aload 10
  invokeinterface java/util/List/add(Ljava/lang/Object;)Z 2
  pop
Label3:
  aload 6
  invokeinterface java/util/List/size()I 1
  istore 7
  iload 7
  anewarray java/lang/String
  astore 11
  aload 6
  invokeinterface java/util/List/listIterator()Ljava/util/ListIterator; 1
  astore 12
Label5:
  aload 12
  invokeinterface java/util/Iterator/hasNext()Z 1
  istore_3
  iload_3
  invokestatic app/DummyClass/invokeIfStmt(Z)V
  iload_3
  ifeq Label4
  aload 12
  invokeinterface java/util/Iterator/next()Ljava/lang/Object; 1
  astore 13
  aload 13
  astore 14
  aload 14
  checkcast java/lang/String
  astore 14
  aload 14
  astore 10
  aload 11
  iload_2
  aload 10
  aastore
  iload_2
  iconst_1
  iadd
  istore_2
  goto Label5
Label2:
  aload_0
  iload 7
  iload 8
  invokevirtual java/lang/String/substring(II)Ljava/lang/String;
  astore 10
  aload 6
  aload 10
  invokeinterface java/util/List/add(Ljava/lang/Object;)Z 2
  pop
  aload_1
  invokevirtual java/lang/String/length()I
  istore 7
  iload 7
  iload 8
  iadd
  istore 7
  goto Label6
Label4:
  aload 11
  areturn
  nop
.end <method>

.method protected static b(Landroid/content/Context;)I
.limit locals 6
.limit stack 200
  nop
  ldc "ads/p.txt"
  astore_2
  ldc 100061
  istore_3
  aload_0
  aload_2
  iload_3
  invokestatic com/kuguo/ad/d/a(Landroid/content/Context;Ljava/lang/String;I)I
  istore_1
  new java/lang/StringBuilder
  astore 4
  aload 4
  invokespecial java/lang/StringBuilder/<init>()V
  ldc "projectId == "
  astore_2
  aload 4
  aload_2
  invokevirtual java/lang/StringBuilder/append(Ljava/lang/String;)Ljava/lang/StringBuilder;
  astore 4
  aload 4
  iload_1
  invokevirtual java/lang/StringBuilder/append(I)Ljava/lang/StringBuilder;
  astore 4
  aload 4
  invokevirtual java/lang/StringBuilder/toString()Ljava/lang/String;
  astore 5
  aload 5
  invokestatic com/kuguo/ad/d/a(Ljava/lang/String;)V
  iload_1
  ireturn
  nop
.end <method>

.method protected static b()J
.limit locals 10
.limit stack 200
  .catch  java/lang/Exception <from> Label3 <to> Label1 <using> Label2
  nop
Label3:
  ldc "download/ads/st.dat"
  astore_1
  aload_1
  invokestatic com/kuguo/ad/d/b(Ljava/lang/String;)Ljava/lang/String;
  astore_0
  aload_0
  invokestatic java/lang/Long/valueOf(Ljava/lang/String;)Ljava/lang/Long;
  astore_2
  aload_2
  invokevirtual java/lang/Long/longValue()J
  lstore_3
Label1:
  ldc2_w 4294967295
  lstore 6
  lload_3
  lload 6
  lcmp
  istore 5
  new java/lang/NoClassDefFoundError
  dup
  invokespecial java/lang/NoClassDefFoundError/<init>()V
  athrow
  iload 5
  ifne Label0
  ldc2_w 60
  lstore_3
Label0:
  new java/lang/StringBuilder
  astore 8
  aload 8
  invokespecial java/lang/StringBuilder/<init>()V
  ldc "spaceTime ----------getSpaceTime-------------- "
  astore_1
  aload 8
  aload_1
  invokevirtual java/lang/StringBuilder/append(Ljava/lang/String;)Ljava/lang/StringBuilder;
  astore 8
  aload 8
  lload_3
  invokevirtual java/lang/StringBuilder/append(J)Ljava/lang/StringBuilder;
  astore 8
  aload 8
  invokevirtual java/lang/StringBuilder/toString()Ljava/lang/String;
  astore_0
  aload_0
  invokestatic com/kuguo/ad/d/a(Ljava/lang/String;)V
  lload_3
  lreturn
Label2:
  astore 9
  ldc2_w 4294967295
  lstore_3
  goto Label1
  nop
.end <method>

.method protected static b(Landroid/content/Context;Ljava/lang/String;)Lcom/kuguo/ad/p;
.limit locals 11
.limit stack 200
  nop
  new java/lang/NoClassDefFoundError
  dup
  invokespecial java/lang/NoClassDefFoundError/<init>()V
  athrow
  iload_1
  ifeq Label0
  aload_1
  invokevirtual java/lang/String/trim()Ljava/lang/String;
  astore_2
  ldc ""
  astore 4
  aload_2
  aload 4
  invokevirtual java/lang/String/equals(Ljava/lang/Object;)Z
  istore_3
  iload_3
  invokestatic app/DummyClass/invokeIfStmt(Z)V
  iload_3
  ifeq Label1
Label0:
  aconst_null
  astore 5
Label5:
  aload 5
  areturn
Label1:
  aload_0
  invokestatic com/kuguo/ad/d/d(Landroid/content/Context;)[Lcom/kuguo/ad/p;
  astore 6
  aload 6
  invokestatic app/DummyClass/invokeIfStmt(Ljava/lang/Object;)V
  aload 6
  ifnull Label2
  aload 6
  arraylength
  istore 7
  dload 7
  invokestatic app/DummyClass/invokeIfStmt(D)V
  iload 7
  ifgt Label3
Label2:
  aconst_null
  astore 8
  aload 8
  areturn
Label3:
  aload 6
  arraylength
  istore 7
  iconst_0
  dstore 9
Label6:
  dload 9
  invokestatic app/DummyClass/invokeIfStmt(D)V
  dload 7
  invokestatic app/DummyClass/invokeIfStmt(D)V
  iload 9
  iload 7
  if_icmpge Label4
  aload 6
  iload 9
  aaload
  astore 5
  aload 5
  getfield com/kuguo/ad/p/d Ljava/lang/String;
  astore 10
  aload_1
  aload 10
  invokevirtual java/lang/String/equals(Ljava/lang/Object;)Z
  istore_3
  iload_3
  invokestatic app/DummyClass/invokeIfStmt(Z)V
  iload_3
  ifne Label5
  iload 9
  iconst_1
  iadd
  istore 9
  goto Label6
Label4:
  aconst_null
  astore 8
  aload 8
  areturn
  nop
.end <method>

.method protected static b(Landroid/content/Context;Ljava/lang/String;I)Ljava/io/File;
.limit locals 11
.limit stack 200
  nop
  new java/lang/NoClassDefFoundError
  dup
  invokespecial java/lang/NoClassDefFoundError/<init>()V
  athrow
  nop
  ldc "mounted"
  astore 4
  aload 4
  aload_3
  invokevirtual java/lang/String/equals(Ljava/lang/Object;)Z
  istore 5
  iload 5
  invokestatic app/DummyClass/invokeIfStmt(Z)V
  iload 5
  ifne Label0
  aconst_null
  astore 6
  aload 6
  areturn
Label0:
  new java/lang/StringBuilder
  astore 7
  aload 7
  invokespecial java/lang/StringBuilder/<init>()V
  ldc "download/ads/"
  astore 8
  aload 7
  aload 8
  invokevirtual java/lang/StringBuilder/append(Ljava/lang/String;)Ljava/lang/StringBuilder;
  astore 7
  aload 7
  iload_2
  invokevirtual java/lang/StringBuilder/append(I)Ljava/lang/StringBuilder;
  astore 7
  aload 7
  invokevirtual java/lang/StringBuilder/toString()Ljava/lang/String;
  astore 4
  new java/io/File
  astore 9
  invokestatic android/os/Environment/getExternalStorageDirectory()Ljava/io/File;
  astore 10
  aload 9
  aload 10
  aload 4
  invokespecial java/io/File/<init>(Ljava/io/File;Ljava/lang/String;)V
  aload 9
  invokevirtual java/io/File/exists()Z
  istore 5
  iload 5
  invokestatic app/DummyClass/invokeIfStmt(Z)V
  iload 5
  ifne Label1
  aload 9
  invokevirtual java/io/File/mkdirs()Z
  pop
Label1:
  new java/io/File
  astore 10
  invokestatic android/os/Environment/getExternalStorageDirectory()Ljava/io/File;
  astore 9
  new java/lang/StringBuilder
  astore 7
  aload 7
  invokespecial java/lang/StringBuilder/<init>()V
  aload 7
  aload 4
  invokevirtual java/lang/StringBuilder/append(Ljava/lang/String;)Ljava/lang/StringBuilder;
  astore 7
  ldc "/"
  astore 8
  aload 7
  aload 8
  invokevirtual java/lang/StringBuilder/append(Ljava/lang/String;)Ljava/lang/StringBuilder;
  astore 7
  aload 7
  aload_1
  invokevirtual java/lang/StringBuilder/append(Ljava/lang/String;)Ljava/lang/StringBuilder;
  astore 7
  aload 7
  invokevirtual java/lang/StringBuilder/toString()Ljava/lang/String;
  astore 4
  aload 10
  aload 9
  aload 4
  invokespecial java/io/File/<init>(Ljava/io/File;Ljava/lang/String;)V
  aload 10
  areturn
  nop
.end <method>

.method protected static b(Ljava/lang/String;)Ljava/lang/String;
.limit locals 31
.limit stack 200
  nop
  iconst_0
  istore_2
  new java/lang/NoClassDefFoundError
  dup
  invokespecial java/lang/NoClassDefFoundError/<init>()V
  athrow
  nop
  ldc "mounted"
  astore 4
  aload 4
  aload_3
  invokevirtual java/lang/String/equals(Ljava/lang/Object;)Z
  istore 5
  iload 5
  invokestatic app/DummyClass/invokeIfStmt(Z)V
  iload 5
  ifne Label0
Label1:
  aload_2
  areturn
Label0:
  new java/io/File
  astore 6
  invokestatic android/os/Environment/getExternalStorageDirectory()Ljava/io/File;
  astore 7
  aload_0
  astore_1
  aload 6
  aload 7
  aload_1
  invokespecial java/io/File/<init>(Ljava/io/File;Ljava/lang/String;)V
  aload 6
  invokevirtual java/io/File/exists()Z
  istore 5
  iload 5
  invokestatic app/DummyClass/invokeIfStmt(Z)V
  iload 5
  ifeq Label1
  new java/io/FileInputStream
  astore 8
  aload 8
  astore 9
Label10:
  aload 8
  aload 6
  invokespecial java/io/FileInputStream/<init>(Ljava/io/File;)V
Label11:
  new java/io/DataInputStream
  astore 10
  aload 10
  astore 11
  aload 8
  astore 13
  aload 13
  checkcast java/io/InputStream
  astore 13
  aload 13
  astore 12
Label14:
  aload 10
  aload 12
  invokespecial java/io/DataInputStream/<init>(Ljava/io/InputStream;)V
Label15:
  aload 10
  checkcast java/io/DataInputStream
  astore 10
Label18:
  aload 10
  invokevirtual java/io/DataInputStream/readUTF()Ljava/lang/String;
  astore 4
Label19:
  aload 4
  astore_2
  aload 11
  invokestatic app/DummyClass/invokeIfStmt(Ljava/lang/Object;)V
  aload 11
  ifnull Label2
  aload 11
  astore 14
  aload 14
  checkcast java/io/DataInputStream
  astore 14
  aload 14
  astore 10
Label21:
  aload 10
  invokevirtual java/io/DataInputStream/close()V
Label2:
  aload 9
  invokestatic app/DummyClass/invokeIfStmt(Ljava/lang/Object;)V
  aload 9
  ifnull Label1
  aload 9
  astore 15
  aload 15
  checkcast java/io/FileInputStream
  astore 15
  aload 15
  astore 8
Label23:
  aload 8
  invokevirtual java/io/FileInputStream/close()V
Label24:
  aload 4
  areturn
Label22:
  astore 16
  aload 16
  invokevirtual java/io/IOException/printStackTrace()V
  aload 4
  areturn
Label20:
  astore 17
  aload 17
  astore_1
  aload_1
  invokevirtual java/io/IOException/printStackTrace()V
  goto Label2
Label9:
  astore 18
  aconst_null
  astore 11
  aconst_null
  astore 9
Label7:
  aload 18
  astore_1
  aload_1
  invokevirtual java/io/IOException/printStackTrace()V
Label25:
  aload 11
  invokestatic app/DummyClass/invokeIfStmt(Ljava/lang/Object;)V
  aload 11
  ifnull Label3
  aload 11
  astore 19
  aload 19
  checkcast java/io/DataInputStream
  astore 19
  aload 19
  astore 10
Label27:
  aload 10
  invokevirtual java/io/DataInputStream/close()V
Label3:
  aload 9
  invokestatic app/DummyClass/invokeIfStmt(Ljava/lang/Object;)V
  aload 9
  ifnull Label1
  aload 9
  astore 20
  aload 20
  checkcast java/io/FileInputStream
  astore 20
  aload 20
  astore 8
Label29:
  aload 8
  invokevirtual java/io/FileInputStream/close()V
Label30:
  aconst_null
  astore 21
  aload 21
  areturn
Label28:
  astore 22
  aload 22
  astore_1
  aload_1
  invokevirtual java/io/IOException/printStackTrace()V
  aconst_null
  astore 21
  aload 21
  areturn
Label26:
  astore 23
  aload 23
  astore_1
  aload_1
  invokevirtual java/io/IOException/printStackTrace()V
  goto Label3
Label8:
  astore 24
  aconst_null
  astore 11
  aconst_null
  astore 9
  aload 24
  astore 25
Label6:
  aload 11
  invokestatic app/DummyClass/invokeIfStmt(Ljava/lang/Object;)V
  aload 11
  ifnull Label4
  aload 11
  astore 26
  aload 26
  checkcast java/io/DataInputStream
  astore 26
  aload 26
  astore 10
Label32:
  aload 10
  invokevirtual java/io/DataInputStream/close()V
Label4:
  aload 9
  invokestatic app/DummyClass/invokeIfStmt(Ljava/lang/Object;)V
  aload 9
  ifnull Label5
  aload 9
  astore 27
  aload 27
  checkcast java/io/FileInputStream
  astore 27
  aload 27
  astore 8
Label34:
  aload 8
  invokevirtual java/io/FileInputStream/close()V
Label5:
  aload 25
  athrow
Label31:
  astore 28
  aload 28
  astore_1
  aload_1
  invokevirtual java/io/IOException/printStackTrace()V
  goto Label4
Label33:
  astore 29
  aload 29
  astore_1
  aload_1
  invokevirtual java/io/IOException/printStackTrace()V
  goto Label5
Label12:
  astore 30
  aconst_null
  astore 11
  aload 30
  astore 25
  goto Label6
Label16:
  astore 25
  goto Label6
Label13:
  astore 18
  aconst_null
  astore 11
  goto Label7
Label17:
  astore 18
  goto Label7
  nop
.end <method>

.method protected static b(J)V
.limit locals 5
.limit stack 200
  nop
  lload_0
  invokestatic java/lang/String/valueOf(J)Ljava/lang/String;
  astore_2
  ldc "download/ads/rt.dat"
  astore_3
  aload_3
  aload_2
  invokestatic com/kuguo/ad/d/b(Ljava/lang/String;Ljava/lang/String;)Z
  pop
  new java/lang/StringBuilder
  astore 4
  aload 4
  invokespecial java/lang/StringBuilder/<init>()V
  ldc "spaceTime ------------------------- "
  astore_3
  aload 4
  aload_3
  invokevirtual java/lang/StringBuilder/append(Ljava/lang/String;)Ljava/lang/StringBuilder;
  astore 4
  aload 4
  lload_0
  invokevirtual java/lang/StringBuilder/append(J)Ljava/lang/StringBuilder;
  astore 4
  aload 4
  invokevirtual java/lang/StringBuilder/toString()Ljava/lang/String;
  astore_2
  aload_2
  invokestatic com/kuguo/ad/d/a(Ljava/lang/String;)V
  return
  nop
.end <method>

.method private static b(Landroid/content/Context;I)Z
.limit locals 14
.limit stack 200
  nop
  ldc "request_prefs"
  astore_3
  iconst_0
  istore 4
  new java/lang/NoClassDefFoundError
  dup
  invokespecial java/lang/NoClassDefFoundError/<init>()V
  athrow
  nop
  aload_2
  invokeinterface android/content/SharedPreferences/edit()Landroid/content/SharedPreferences$Editor; 1
  astore 5
  ldc "nextRequest"
  astore_3
  aload 5
  aload_3
  iload_1
  invokeinterface android/content/SharedPreferences$Editor/putInt(Ljava/lang/String;I)Landroid/content/SharedPreferences$Editor; 3
  pop
  invokestatic java/util/Calendar/getInstance()Ljava/util/Calendar;
  astore 6
  invokestatic java/lang/System/currentTimeMillis()J
  lstore 7
  aload 6
  lload 7
  invokevirtual java/util/Calendar/setTimeInMillis(J)V
  iconst_1
  istore 4
  aload 6
  iload 4
  invokevirtual java/util/Calendar/get(I)I
  istore_1
  iconst_2
  istore 4
  aload 6
  iload 4
  invokevirtual java/util/Calendar/get(I)I
  istore 9
  iconst_5
  istore 4
  aload 6
  iload 4
  invokevirtual java/util/Calendar/get(I)I
  istore 10
  new java/lang/StringBuilder
  astore 11
  aload 11
  invokespecial java/lang/StringBuilder/<init>()V
  aload 11
  iload_1
  invokevirtual java/lang/StringBuilder/append(I)Ljava/lang/StringBuilder;
  astore 11
  ldc "-"
  astore_3
  aload 11
  aload_3
  invokevirtual java/lang/StringBuilder/append(Ljava/lang/String;)Ljava/lang/StringBuilder;
  astore 11
  aload 11
  iload 9
  invokevirtual java/lang/StringBuilder/append(I)Ljava/lang/StringBuilder;
  astore 11
  ldc "-"
  astore_3
  aload 11
  aload_3
  invokevirtual java/lang/StringBuilder/append(Ljava/lang/String;)Ljava/lang/StringBuilder;
  astore 11
  aload 11
  iload 10
  invokevirtual java/lang/StringBuilder/append(I)Ljava/lang/StringBuilder;
  astore 11
  aload 11
  invokevirtual java/lang/StringBuilder/toString()Ljava/lang/String;
  astore 12
  ldc "date"
  astore_3
  aload 5
  aload_3
  aload 12
  invokeinterface android/content/SharedPreferences$Editor/putString(Ljava/lang/String;Ljava/lang/String;)Landroid/content/SharedPreferences$Editor; 3
  pop
  aload 5
  invokeinterface android/content/SharedPreferences$Editor/commit()Z 1
  istore 13
  iload 13
  ireturn
  nop
.end <method>

.method protected static b(Landroid/content/Context;Lcom/kuguo/ad/p;)Z
.limit locals 18
.limit stack 200
  nop
  aload_1
  astore_2
  new java/lang/NoClassDefFoundError
  dup
  invokespecial java/lang/NoClassDefFoundError/<init>()V
  athrow
  iload_1
  ifne Label0
Label1:
  iconst_0
  istore_3
  iload_3
  ireturn
Label0:
  ldc "message_prefs"
  astore 5
  iconst_0
  istore_3
  aload_0
  astore_2
  aload_2
  aload 5
  iload_3
  invokevirtual android/content/Context/getSharedPreferences(Ljava/lang/String;I)Landroid/content/SharedPreferences;
  astore 4
  new java/lang/StringBuilder
  astore 6
  aload 6
  invokespecial java/lang/StringBuilder/<init>()V
  ldc ""
  astore 5
  aload 6
  aload 5
  invokevirtual java/lang/StringBuilder/append(Ljava/lang/String;)Ljava/lang/StringBuilder;
  astore 6
  aload_1
  astore_2
  aload_2
  getfield com/kuguo/ad/p/f I
  istore 7
  aload 6
  iload 7
  invokevirtual java/lang/StringBuilder/append(I)Ljava/lang/StringBuilder;
  astore 6
  aload 6
  invokevirtual java/lang/StringBuilder/toString()Ljava/lang/String;
  astore 8
  aload 4
  aload 8
  invokeinterface android/content/SharedPreferences/contains(Ljava/lang/String;)Z 2
  istore 9
  iload 9
  invokestatic app/DummyClass/invokeIfStmt(Z)V
  iload 9
  ifeq Label1
  aload_0
  astore_2
  aload_2
  invokestatic com/kuguo/ad/d/d(Landroid/content/Context;)[Lcom/kuguo/ad/p;
  astore 10
  aload 10
  invokestatic app/DummyClass/invokeIfStmt(Ljava/lang/Object;)V
  aload 10
  ifnull Label1
  aload 10
  arraylength
  istore 11
  iconst_0
  dstore 12
Label4:
  dload 12
  invokestatic app/DummyClass/invokeIfStmt(D)V
  dload 11
  invokestatic app/DummyClass/invokeIfStmt(D)V
  iload 12
  iload 11
  if_icmpge Label1
  aload 10
  iload 12
  aaload
  astore 13
  aload 13
  getfield com/kuguo/ad/p/f I
  istore 14
  aload_1
  astore_2
  aload_2
  getfield com/kuguo/ad/p/f I
  istore 7
  dload 14
  invokestatic app/DummyClass/invokeIfStmt(D)V
  dload 7
  invokestatic app/DummyClass/invokeIfStmt(D)V
  iload 14
  iload 7
  if_icmpne Label2
  aload 13
  getfield com/kuguo/ad/p/j Ljava/lang/Integer;
  astore 15
  aload 15
  invokevirtual java/lang/Integer/intValue()I
  istore 12
  dload 12
  invokestatic app/DummyClass/invokeIfStmt(D)V
  iconst_3
  istore_3
  iload 12
  iload_3
  if_icmpeq Label1
  aload 13
  getfield com/kuguo/ad/p/j Ljava/lang/Integer;
  astore 15
  aload 15
  invokevirtual java/lang/Integer/intValue()I
  istore 12
  aload_1
  astore_2
  aload_2
  getfield com/kuguo/ad/p/j Ljava/lang/Integer;
  astore 15
  aload 15
  invokevirtual java/lang/Integer/intValue()I
  istore 7
  dload 12
  invokestatic app/DummyClass/invokeIfStmt(D)V
  dload 7
  invokestatic app/DummyClass/invokeIfStmt(D)V
  iload 12
  iload 7
  if_icmplt Label3
  aload_1
  astore_2
  aload_2
  getfield com/kuguo/ad/p/j Ljava/lang/Integer;
  astore 15
  aload 15
  invokevirtual java/lang/Integer/intValue()I
  istore 12
  dload 12
  invokestatic app/DummyClass/invokeIfStmt(D)V
  iconst_3
  istore_3
  iload 12
  iload_3
  if_icmpne Label1
Label3:
  aload 4
  invokeinterface android/content/SharedPreferences/edit()Landroid/content/SharedPreferences$Editor; 1
  astore 16
  aload 16
  aload 8
  invokeinterface android/content/SharedPreferences$Editor/remove(Ljava/lang/String;)Landroid/content/SharedPreferences$Editor; 2
  pop
  aload_1
  astore_2
  aload_2
  invokevirtual com/kuguo/ad/p/a()Ljava/lang/String;
  astore 17
  aload 16
  aload 8
  aload 17
  invokeinterface android/content/SharedPreferences$Editor/putString(Ljava/lang/String;Ljava/lang/String;)Landroid/content/SharedPreferences$Editor; 3
  pop
  aload_1
  astore_2
  aload_2
  getfield com/kuguo/ad/p/h I
  istore 12
  aload_1
  astore_2
  aload_2
  getfield com/kuguo/ad/p/j Ljava/lang/Integer;
  astore 15
  aload 15
  invokevirtual java/lang/Integer/intValue()I
  istore 7
  aload_0
  astore_2
  aload_2
  iload 12
  iload 7
  invokestatic com/kuguo/ad/d/a(Landroid/content/Context;II)Z
  pop
  aload 16
  invokeinterface android/content/SharedPreferences$Editor/commit()Z 1
  istore 9
  iload 9
  ireturn
Label2:
  iload 12
  iconst_1
  iadd
  istore 12
  goto Label4
  nop
.end <method>

.method private static b(Ljava/lang/String;Ljava/lang/String;)Z
.limit locals 31
.limit stack 200
  nop
  iconst_0
  istore_3
  iconst_0
  istore 4
  new java/lang/NoClassDefFoundError
  dup
  invokespecial java/lang/NoClassDefFoundError/<init>()V
  athrow
  nop
  ldc "mounted"
  astore 6
  aload 6
  aload 5
  invokevirtual java/lang/String/equals(Ljava/lang/Object;)Z
  istore 7
  iload 7
  invokestatic app/DummyClass/invokeIfStmt(Z)V
  iload 7
  ifne Label0
Label4:
  iload 4
  ireturn
Label0:
  new java/io/File
  astore 8
  aload 8
  astore 9
  invokestatic android/os/Environment/getExternalStorageDirectory()Ljava/io/File;
  astore 10
  aload_0
  astore_2
  aload 8
  aload 10
  aload_2
  invokespecial java/io/File/<init>(Ljava/io/File;Ljava/lang/String;)V
  new java/io/File
  astore 8
  aload 9
  invokevirtual java/io/File/getParent()Ljava/lang/String;
  astore 6
  aload 8
  aload 6
  invokespecial java/io/File/<init>(Ljava/lang/String;)V
  aload 8
  invokevirtual java/io/File/exists()Z
  istore 7
  iload 7
  invokestatic app/DummyClass/invokeIfStmt(Z)V
  iload 7
  ifne Label1
  aload 8
  invokevirtual java/io/File/mkdirs()Z
  pop
Label5:
  aload 9
  invokevirtual java/io/File/createNewFile()Z
  istore 7
  iload 7
  invokestatic app/DummyClass/invokeIfStmt(Z)V
  iload 7
  ifeq Label2
  new java/io/FileOutputStream
  astore 11
  aload 11
  astore 12
  aload 11
  aload 9
  invokespecial java/io/FileOutputStream/<init>(Ljava/io/File;)V
Label14:
  new java/io/DataOutputStream
  astore 13
  aload 13
  astore 14
Label17:
  aload 13
  aload 11
  invokespecial java/io/DataOutputStream/<init>(Ljava/io/OutputStream;)V
Label18:
  aload 13
  checkcast java/io/DataOutputStream
  astore 13
Label21:
  aload_1
  astore_2
  aload 13
  aload_2
  invokevirtual java/io/DataOutputStream/writeUTF(Ljava/lang/String;)V
  aload 14
  astore 15
  aload 15
  checkcast java/io/DataOutputStream
  astore 15
  aload 15
  astore 13
  aload 13
  invokevirtual java/io/DataOutputStream/flush()V
Label22:
  iconst_1
  istore 4
  aload 14
  invokestatic app/DummyClass/invokeIfStmt(Ljava/lang/Object;)V
  aload 14
  ifnull Label3
  aload 14
  astore 16
  aload 16
  checkcast java/io/DataOutputStream
  astore 16
  aload 16
  astore 13
Label24:
  aload 13
  invokevirtual java/io/DataOutputStream/close()V
Label3:
  aload 12
  invokestatic app/DummyClass/invokeIfStmt(Ljava/lang/Object;)V
  aload 12
  ifnull Label4
  aload 12
  astore 17
  aload 17
  checkcast java/io/FileOutputStream
  astore 17
  aload 17
  astore 11
Label26:
  aload 11
  invokevirtual java/io/FileOutputStream/close()V
Label27:
  iconst_1
  istore 18
  iload 18
  ireturn
Label25:
  astore 19
  aload 19
  astore_2
  aload_2
  invokevirtual java/io/IOException/printStackTrace()V
  iconst_1
  istore 18
  iload 18
  ireturn
Label1:
  aload 9
  invokevirtual java/io/File/exists()Z
  istore 7
  iload 7
  invokestatic app/DummyClass/invokeIfStmt(Z)V
  iload 7
  ifeq Label5
  aload 9
  invokevirtual java/io/File/delete()Z
  pop
  goto Label5
Label23:
  astore 20
  aload 20
  astore_2
  aload_2
  invokevirtual java/io/IOException/printStackTrace()V
  goto Label3
Label2:
  goto Label6
Label6:
  goto Label4
Label13:
  astore 21
  aconst_null
  astore 14
Label11:
  aload 21
  astore_2
  aload_2
  invokevirtual java/io/IOException/printStackTrace()V
Label29:
  aload 14
  invokestatic app/DummyClass/invokeIfStmt(Ljava/lang/Object;)V
  aload 14
  ifnull Label7
  aload 14
  astore 22
  aload 22
  checkcast java/io/DataOutputStream
  astore 22
  aload 22
  astore 13
Label31:
  aload 13
  invokevirtual java/io/DataOutputStream/close()V
Label7:
  aload_3
  invokestatic app/DummyClass/invokeIfStmt(Ljava/lang/Object;)V
  aload_3
  ifnull Label4
  aload_3
  astore 23
  aload 23
  checkcast java/io/FileOutputStream
  astore 23
  aload 23
  astore 11
Label33:
  aload 11
  invokevirtual java/io/FileOutputStream/close()V
Label34:
  iconst_0
  istore 18
  iload 18
  ireturn
Label32:
  astore 24
  aload 24
  astore_2
  aload_2
  invokevirtual java/io/IOException/printStackTrace()V
  iconst_0
  istore 18
  iload 18
  ireturn
Label30:
  astore 25
  aload 25
  astore_2
  aload_2
  invokevirtual java/io/IOException/printStackTrace()V
  goto Label7
Label12:
  astore 26
  aconst_null
  astore 12
Label10:
  aload_3
  invokestatic app/DummyClass/invokeIfStmt(Ljava/lang/Object;)V
  aload_3
  ifnull Label8
  aload_3
  astore 27
  aload 27
  checkcast java/io/DataOutputStream
  astore 27
  aload 27
  astore 13
Label36:
  aload 13
  invokevirtual java/io/DataOutputStream/close()V
Label8:
  aload 12
  invokestatic app/DummyClass/invokeIfStmt(Ljava/lang/Object;)V
  aload 12
  ifnull Label9
  aload 12
  astore 28
  aload 28
  checkcast java/io/FileOutputStream
  astore 28
  aload 28
  astore 11
Label38:
  aload 11
  invokevirtual java/io/FileOutputStream/close()V
Label9:
  aload 26
  athrow
Label35:
  astore 29
  aload 29
  astore_2
  aload_2
  invokevirtual java/io/IOException/printStackTrace()V
  goto Label8
Label37:
  astore 30
  aload 30
  astore_2
  aload_2
  invokevirtual java/io/IOException/printStackTrace()V
  goto Label9
Label15:
  astore 26
  goto Label10
Label19:
  astore 26
  aload 14
  astore_3
  goto Label10
Label28:
  astore 26
  aload_3
  astore 12
  aload 14
  astore_3
  goto Label10
Label16:
  astore 21
  aconst_null
  astore 14
  aload 12
  astore_3
  goto Label11
Label20:
  astore 21
  aload 12
  astore_3
  goto Label11
  nop
.end <method>

.method protected static c(Landroid/content/Context;)I
.limit locals 6
.limit stack 200
  nop
  ldc "ads/m.txt"
  astore_2
  iconst_1
  istore_3
  aload_0
  aload_2
  iload_3
  invokestatic com/kuguo/ad/d/a(Landroid/content/Context;Ljava/lang/String;I)I
  istore_1
  new java/lang/StringBuilder
  astore 4
  aload 4
  invokespecial java/lang/StringBuilder/<init>()V
  ldc "-------startMode == "
  astore_2
  aload 4
  aload_2
  invokevirtual java/lang/StringBuilder/append(Ljava/lang/String;)Ljava/lang/StringBuilder;
  astore 4
  aload 4
  iload_1
  invokevirtual java/lang/StringBuilder/append(I)Ljava/lang/StringBuilder;
  astore 4
  aload 4
  invokevirtual java/lang/StringBuilder/toString()Ljava/lang/String;
  astore 5
  ldc "android__log"
  astore_2
  new java/lang/NoClassDefFoundError
  dup
  invokespecial java/lang/NoClassDefFoundError/<init>()V
  athrow
  iload_1
  ireturn
  nop
.end <method>

.method protected static c()J
.limit locals 10
.limit stack 200
  .catch  java/lang/Exception <from> Label3 <to> Label1 <using> Label2
  nop
Label3:
  ldc "download/ads/rt.dat"
  astore_1
  aload_1
  invokestatic com/kuguo/ad/d/b(Ljava/lang/String;)Ljava/lang/String;
  astore_0
  aload_0
  invokestatic java/lang/Long/valueOf(Ljava/lang/String;)Ljava/lang/Long;
  astore_2
  aload_2
  invokevirtual java/lang/Long/longValue()J
  lstore_3
Label1:
  ldc2_w 4294967295
  lstore 6
  lload_3
  lload 6
  lcmp
  istore 5
  new java/lang/NoClassDefFoundError
  dup
  invokespecial java/lang/NoClassDefFoundError/<init>()V
  athrow
  iload 5
  ifne Label0
  ldc2_w 0
  lstore_3
Label0:
  new java/lang/StringBuilder
  astore 8
  aload 8
  invokespecial java/lang/StringBuilder/<init>()V
  ldc "requestTime ----------getRequestTime-------------- "
  astore_1
  aload 8
  aload_1
  invokevirtual java/lang/StringBuilder/append(Ljava/lang/String;)Ljava/lang/StringBuilder;
  astore 8
  aload 8
  lload_3
  invokevirtual java/lang/StringBuilder/append(J)Ljava/lang/StringBuilder;
  astore 8
  aload 8
  invokevirtual java/lang/StringBuilder/toString()Ljava/lang/String;
  astore_0
  aload_0
  invokestatic com/kuguo/ad/d/a(Ljava/lang/String;)V
  lload_3
  lreturn
Label2:
  astore 9
  ldc2_w 4294967295
  lstore_3
  goto Label1
  nop
.end <method>

.method protected static c(Landroid/content/Context;Lcom/kuguo/ad/p;)Z
.limit locals 14
.limit stack 200
  nop
  aload_1
  getfield com/kuguo/ad/p/s Ljava/lang/String;
  astore_2
  new java/lang/NoClassDefFoundError
  dup
  invokespecial java/lang/NoClassDefFoundError/<init>()V
  athrow
  iload_2
  ifne Label0
Label1:
  iconst_0
  istore_3
  iload_3
  ireturn
Label0:
  aload_1
  getfield com/kuguo/ad/p/s Ljava/lang/String;
  astore 4
  ldc ";"
  astore 6
  aload 4
  aload 6
  invokestatic com/kuguo/ad/d/a(Ljava/lang/String;Ljava/lang/String;)[Ljava/lang/String;
  astore 5
  aload 5
  invokestatic app/DummyClass/invokeIfStmt(Ljava/lang/Object;)V
  aload 5
  ifnull Label1
  aload 5
  arraylength
  istore 7
  iconst_0
  dstore 8
Label3:
  dload 8
  invokestatic app/DummyClass/invokeIfStmt(D)V
  dload 7
  invokestatic app/DummyClass/invokeIfStmt(D)V
  iload 8
  iload 7
  if_icmpge Label1
  aload 5
  iload 8
  aaload
  astore_2
  aload_0
  aload_2
  invokestatic com/kuguo/ad/d/c(Landroid/content/Context;Ljava/lang/String;)Z
  istore 9
  iload 9
  invokestatic app/DummyClass/invokeIfStmt(Z)V
  iload 9
  ifeq Label2
  new android/content/Intent
  astore 10
  ldc "android.intent.action.VIEW"
  astore 6
  aload 10
  aload 6
  invokespecial android/content/Intent/<init>(Ljava/lang/String;)V
  new java/lang/StringBuilder
  astore 11
  aload 11
  invokespecial java/lang/StringBuilder/<init>()V
  ldc "market://details?id="
  astore 6
  aload 11
  aload 6
  invokevirtual java/lang/StringBuilder/append(Ljava/lang/String;)Ljava/lang/StringBuilder;
  astore 11
  aload_1
  getfield com/kuguo/ad/p/i Ljava/lang/String;
  astore 4
  aload 4
  invokevirtual java/lang/String/trim()Ljava/lang/String;
  astore 4
  aload 11
  aload 4
  invokevirtual java/lang/StringBuilder/append(Ljava/lang/String;)Ljava/lang/StringBuilder;
  astore 11
  aload 11
  invokevirtual java/lang/StringBuilder/toString()Ljava/lang/String;
  astore 4
  aload 4
  invokestatic android/net/Uri/parse(Ljava/lang/String;)Landroid/net/Uri;
  astore 12
  aload 10
  aload 12
  invokevirtual android/content/Intent/setData(Landroid/net/Uri;)Landroid/content/Intent;
  pop
  aload 10
  aload_2
  invokevirtual android/content/Intent/setPackage(Ljava/lang/String;)Landroid/content/Intent;
  pop
  ldc 268435456
  istore_3
  aload 10
  iload_3
  invokevirtual android/content/Intent/setFlags(I)Landroid/content/Intent;
  pop
Label5:
  aload_0
  aload 10
  invokevirtual android/content/Context/startActivity(Landroid/content/Intent;)V
Label6:
  iconst_1
  istore_3
  iload_3
  ireturn
Label4:
  astore 13
Label2:
  iload 8
  iconst_1
  iadd
  istore 8
  goto Label3
  nop
.end <method>

.method protected static c(Landroid/content/Context;Ljava/lang/String;)Z
.limit locals 5
.limit stack 200
  nop
  new java/lang/NoClassDefFoundError
  dup
  invokespecial java/lang/NoClassDefFoundError/<init>()V
  athrow
  nop
Label1:
  aload_1
  invokevirtual java/lang/String/trim()Ljava/lang/String;
  astore_1
  sipush 256
  istore_3
  aload_2
  aload_1
  iload_3
  invokevirtual android/content/pm/PackageManager/getPackageInfo(Ljava/lang/String;I)Landroid/content/pm/PackageInfo;
  pop
Label2:
  iconst_1
  istore_3
  iload_3
  ireturn
Label0:
  astore 4
  iconst_0
  istore_3
  iload_3
  ireturn
  nop
.end <method>

.method protected static c(Ljava/lang/String;)Z
.limit locals 6
.limit stack 200
  nop
  new java/lang/NoClassDefFoundError
  dup
  invokespecial java/lang/NoClassDefFoundError/<init>()V
  athrow
  iload_0
  ifeq Label0
  ldc ""
  astore_1
  aload_1
  aload_0
  invokevirtual java/lang/String/equals(Ljava/lang/Object;)Z
  istore_2
  iload_2
  invokestatic app/DummyClass/invokeIfStmt(Z)V
  iload_2
  ifeq Label1
Label0:
  iconst_0
  istore_3
  iload_3
  ireturn
Label1:
  new java/lang/StringBuilder
  astore 4
  aload 4
  invokespecial java/lang/StringBuilder/<init>()V
  ldc "ids--- "
  astore 5
  aload 4
  aload 5
  invokevirtual java/lang/StringBuilder/append(Ljava/lang/String;)Ljava/lang/StringBuilder;
  astore 4
  aload 4
  aload_0
  invokevirtual java/lang/StringBuilder/append(Ljava/lang/String;)Ljava/lang/StringBuilder;
  astore 4
  aload 4
  invokevirtual java/lang/StringBuilder/toString()Ljava/lang/String;
  astore_1
  aload_1
  invokestatic com/kuguo/ad/d/a(Ljava/lang/String;)V
  ldc "download/ads/verify.dat"
  astore 5
  aload 5
  aload_0
  invokestatic com/kuguo/ad/d/b(Ljava/lang/String;Ljava/lang/String;)Z
  istore_2
  iload_2
  ireturn
  nop
.end <method>

.method protected static d(Landroid/content/Context;Ljava/lang/String;)Z
.limit locals 4
.limit stack 200
  nop
  aload_0
  aload_1
  invokestatic com/kuguo/ad/d/e(Landroid/content/Context;Ljava/lang/String;)Landroid/content/Intent;
  astore_2
  new java/lang/NoClassDefFoundError
  dup
  invokespecial java/lang/NoClassDefFoundError/<init>()V
  athrow
  iload_2
  ifeq Label0
  aload_0
  aload_2
  invokevirtual android/content/Context/startActivity(Landroid/content/Intent;)V
  iconst_1
  istore_3
  iload_3
  ireturn
Label0:
  iconst_0
  istore_3
  iload_3
  ireturn
  nop
.end <method>

.method protected static d(Landroid/content/Context;)[Lcom/kuguo/ad/p;
.limit locals 20
.limit stack 200
  nop
  ldc "message_prefs"
  astore_3
  iconst_0
  istore 4
  aload_0
  astore_1
  new java/lang/NoClassDefFoundError
  dup
  invokespecial java/lang/NoClassDefFoundError/<init>()V
  athrow
  nop
  aload_2
  invokeinterface android/content/SharedPreferences/getAll()Ljava/util/Map; 1
  astore 5
  aload 5
  invokestatic app/DummyClass/invokeIfStmt(Ljava/lang/Object;)V
  aload 5
  ifnull Label0
  aload 5
  invokeinterface java/util/Map/size()I 1
  istore 6
  dload 6
  invokestatic app/DummyClass/invokeIfStmt(D)V
  iload 6
  ifgt Label1
Label0:
  aconst_null
  astore 7
  aload 7
  areturn
Label1:
  aload 5
  invokeinterface java/util/Map/keySet()Ljava/util/Set; 1
  astore 8
  aload 8
  invokeinterface java/util/Set/iterator()Ljava/util/Iterator; 1
  astore 9
  aload 5
  invokeinterface java/util/Map/size()I 1
  istore 6
  iload 6
  anewarray com/kuguo/ad/p
  astore 10
  iconst_0
  istore 6
Label4:
  aload 9
  invokeinterface java/util/Iterator/hasNext()Z 1
  istore 11
  iload 11
  invokestatic app/DummyClass/invokeIfStmt(Z)V
  iload 11
  ifeq Label2
  aload 9
  invokeinterface java/util/Iterator/next()Ljava/lang/Object; 1
  astore 12
  aload 12
  astore 14
  aload 14
  checkcast java/lang/String
  astore 14
  aload 14
  astore 13
  aconst_null
  astore 7
  aload_2
  aload 13
  aload 7
  invokeinterface android/content/SharedPreferences/getString(Ljava/lang/String;Ljava/lang/String;)Ljava/lang/String; 3
  astore 15
  new com/kuguo/ad/p
  astore 16
  aload 16
  invokespecial com/kuguo/ad/p/<init>()V
  aload 16
  aload 15
  invokevirtual com/kuguo/ad/p/a(Ljava/lang/String;)Z
  istore 11
  iload 11
  invokestatic app/DummyClass/invokeIfStmt(Z)V
  iload 11
  ifeq Label3
  aload 13
  invokestatic java/lang/Integer/valueOf(Ljava/lang/String;)Ljava/lang/Integer;
  astore 17
  aload 17
  astore_1
  aload_1
  invokevirtual java/lang/Integer/intValue()I
  istore 18
  iload 18
  istore_1
  aload 16
  iload_1
  putfield com/kuguo/ad/p/f I
  aload 10
  iload 6
  aload 16
  aastore
  iload 6
  iconst_1
  iadd
  istore 6
  goto Label4
Label3:
  aload_2
  invokeinterface android/content/SharedPreferences/edit()Landroid/content/SharedPreferences$Editor; 1
  astore 19
  aload 19
  astore_1
  aload_1
  invokeinterface android/content/SharedPreferences$Editor/clear()Landroid/content/SharedPreferences$Editor; 1
  astore 19
  aload 19
  astore_1
  aload_1
  invokeinterface android/content/SharedPreferences$Editor/commit()Z 1
  pop
  aconst_null
  astore 7
  aload 7
  areturn
Label2:
  aload 10
  areturn
  nop
.end <method>

.method protected static e(Landroid/content/Context;)I
.limit locals 15
.limit stack 200
  nop
  ldc "request_prefs"
  astore_2
  iconst_0
  istore_3
  new java/lang/NoClassDefFoundError
  dup
  invokespecial java/lang/NoClassDefFoundError/<init>()V
  athrow
  nop
  ldc "nextRequest"
  astore_2
  iconst_1
  istore_3
  aload_1
  aload_2
  iload_3
  invokeinterface android/content/SharedPreferences/getInt(Ljava/lang/String;I)I 3
  istore 4
  dload 4
  invokestatic app/DummyClass/invokeIfStmt(D)V
  iconst_1
  istore_3
  iload 4
  iload_3
  if_icmpne Label0
  iconst_0
  istore_3
  iload_3
  ireturn
Label0:
  invokestatic java/util/Calendar/getInstance()Ljava/util/Calendar;
  astore 5
  invokestatic java/lang/System/currentTimeMillis()J
  lstore 6
  aload 5
  lload 6
  invokevirtual java/util/Calendar/setTimeInMillis(J)V
  iconst_1
  istore_3
  aload 5
  iload_3
  invokevirtual java/util/Calendar/get(I)I
  istore 8
  iconst_2
  istore_3
  aload 5
  iload_3
  invokevirtual java/util/Calendar/get(I)I
  istore 4
  iconst_5
  istore_3
  aload 5
  iload_3
  invokevirtual java/util/Calendar/get(I)I
  istore 9
  new java/lang/StringBuilder
  astore 10
  aload 10
  invokespecial java/lang/StringBuilder/<init>()V
  aload 10
  iload 8
  invokevirtual java/lang/StringBuilder/append(I)Ljava/lang/StringBuilder;
  astore 10
  ldc "-"
  astore_2
  aload 10
  aload_2
  invokevirtual java/lang/StringBuilder/append(Ljava/lang/String;)Ljava/lang/StringBuilder;
  astore 10
  aload 10
  iload 4
  invokevirtual java/lang/StringBuilder/append(I)Ljava/lang/StringBuilder;
  astore 10
  ldc "-"
  astore_2
  aload 10
  aload_2
  invokevirtual java/lang/StringBuilder/append(Ljava/lang/String;)Ljava/lang/StringBuilder;
  astore 10
  aload 10
  iload 9
  invokevirtual java/lang/StringBuilder/append(I)Ljava/lang/StringBuilder;
  astore 10
  aload 10
  invokevirtual java/lang/StringBuilder/toString()Ljava/lang/String;
  astore 11
  ldc "date"
  astore_2
  aload_1
  aload_2
  aload 11
  invokeinterface android/content/SharedPreferences/getString(Ljava/lang/String;Ljava/lang/String;)Ljava/lang/String; 3
  astore 12
  aload 11
  aload 12
  invokevirtual java/lang/String/equals(Ljava/lang/Object;)Z
  istore 13
  iload 13
  invokestatic app/DummyClass/invokeIfStmt(Z)V
  iload 13
  ifne Label1
  iconst_1
  istore_3
  iload_3
  ireturn
Label1:
  ldc "adsState"
  astore_2
  aconst_null
  astore 14
  aload_1
  aload_2
  aload 14
  invokeinterface android/content/SharedPreferences/getString(Ljava/lang/String;Ljava/lang/String;)Ljava/lang/String; 3
  astore 12
  aload 12
  invokestatic app/DummyClass/invokeIfStmt(Ljava/lang/Object;)V
  aload 12
  ifnull Label2
  iconst_2
  istore_3
  iload_3
  ireturn
Label2:
  iconst_m1
  istore_3
  iload_3
  ireturn
  nop
.end <method>

.method public static e(Landroid/content/Context;Ljava/lang/String;)Landroid/content/Intent;
.limit locals 21
.limit stack 200
  nop
  aload_1
  astore_2
  new java/lang/NoClassDefFoundError
  dup
  invokespecial java/lang/NoClassDefFoundError/<init>()V
  athrow
  iload_1
  ifeq Label0
  aload_1
  astore_2
  aload_2
  invokevirtual java/lang/String/trim()Ljava/lang/String;
  astore 5
  ldc ""
  astore 7
  aload 5
  aload 7
  invokevirtual java/lang/String/equals(Ljava/lang/Object;)Z
  istore 6
  iload 6
  invokestatic app/DummyClass/invokeIfStmt(Z)V
  iload 6
  ifeq Label1
Label0:
  aconst_null
  astore 8
  aload 8
  areturn
Label1:
  aload_0
  astore_2
  aload_2
  invokevirtual android/content/Context/getPackageManager()Landroid/content/pm/PackageManager;
  astore 9
  new android/content/Intent
  astore 10
  ldc "android.intent.action.MAIN"
  astore 7
  aconst_null
  astore 8
  aload 10
  aload 7
  aload 8
  invokespecial android/content/Intent/<init>(Ljava/lang/String;Landroid/net/Uri;)V
  ldc "android.intent.category.LAUNCHER"
  astore 7
  aload 10
  aload 7
  invokevirtual android/content/Intent/addCategory(Ljava/lang/String;)Landroid/content/Intent;
  pop
  iconst_0
  istore 12
  aload 9
  aload 10
  iload 12
  invokevirtual android/content/pm/PackageManager/queryIntentActivities(Landroid/content/Intent;I)Ljava/util/List;
  astore 11
  aload 11
  invokestatic app/DummyClass/invokeIfStmt(Ljava/lang/Object;)V
  aload 11
  ifnull Label2
  aload 11
  invokeinterface java/util/List/size()I 1
  istore 13
  iconst_0
  dstore 14
Label5:
  dload 14
  invokestatic app/DummyClass/invokeIfStmt(D)V
  dload 13
  invokestatic app/DummyClass/invokeIfStmt(D)V
  iload 14
  iload 13
  if_icmpge Label2
  aload 11
  iload 14
  invokeinterface java/util/List/get(I)Ljava/lang/Object; 2
  astore 15
  aload 15
  astore 17
  aload 17
  checkcast android/content/pm/ResolveInfo
  astore 17
  aload 17
  astore 16
  aload 16
  getfield android/content/pm/ResolveInfo/activityInfo Landroid/content/pm/ActivityInfo;
  astore_2
  aload_2
  astore 18
  aload 18
  astore_2
  aload_2
  getfield android/content/pm/PackageItemInfo/packageName Ljava/lang/String;
  astore_2
  aload_2
  astore 19
  aload_1
  astore_2
  aload 19
  astore_3
  aload_2
  aload_3
  invokevirtual java/lang/String/equals(Ljava/lang/Object;)Z
  istore 6
  iload 6
  invokestatic app/DummyClass/invokeIfStmt(Z)V
  iload 6
  ifeq Label3
Label6:
  aload 16
  invokestatic app/DummyClass/invokeIfStmt(Ljava/lang/Object;)V
  aload 16
  ifnonnull Label4
  aconst_null
  astore 8
  aload 8
  areturn
Label3:
  iload 14
  iconst_1
  iadd
  istore 14
  goto Label5
Label4:
  new android/content/ComponentName
  astore 20
  aload 16
  getfield android/content/pm/ResolveInfo/activityInfo Landroid/content/pm/ActivityInfo;
  astore_2
  aload_2
  astore 18
  aload 18
  astore_2
  aload_2
  getfield android/content/pm/PackageItemInfo/name Ljava/lang/String;
  astore_2
  aload_2
  astore 19
  aload 20
  astore_2
  aload_1
  astore_3
  aload 19
  astore 4
  aload_2
  aload_3
  aload 4
  invokespecial android/content/ComponentName/<init>(Ljava/lang/String;Ljava/lang/String;)V
  new android/content/Intent
  astore 10
  aload 10
  invokespecial android/content/Intent/<init>()V
  aload 20
  astore_2
  aload 10
  aload_2
  invokevirtual android/content/Intent/setComponent(Landroid/content/ComponentName;)Landroid/content/Intent;
  pop
  ldc 268435456
  istore 12
  aload 10
  iload 12
  invokevirtual android/content/Intent/setFlags(I)Landroid/content/Intent;
  pop
  aload 10
  areturn
Label2:
  aconst_null
  astore 16
  goto Label6
  nop
.end <method>

.method protected static f(Landroid/content/Context;)Z
.limit locals 6
.limit stack 200
  nop
  ldc "request_prefs"
  astore_2
  iconst_0
  istore_3
  new java/lang/NoClassDefFoundError
  dup
  invokespecial java/lang/NoClassDefFoundError/<init>()V
  athrow
  nop
  aload_1
  invokeinterface android/content/SharedPreferences/edit()Landroid/content/SharedPreferences$Editor; 1
  astore 4
  ldc "adsState"
  astore_2
  aload 4
  aload_2
  invokeinterface android/content/SharedPreferences$Editor/remove(Ljava/lang/String;)Landroid/content/SharedPreferences$Editor; 2
  pop
  aload 4
  invokeinterface android/content/SharedPreferences$Editor/commit()Z 1
  istore 5
  iload 5
  ireturn
  nop
.end <method>

.method protected static f(Landroid/content/Context;Ljava/lang/String;)Z
.limit locals 7
.limit stack 200
  nop
  ldc "coo_id"
  astore_3
  iconst_0
  istore 4
  new java/lang/NoClassDefFoundError
  dup
  invokespecial java/lang/NoClassDefFoundError/<init>()V
  athrow
  nop
  aload_2
  invokeinterface android/content/SharedPreferences/edit()Landroid/content/SharedPreferences$Editor; 1
  astore 5
  ldc "cooId"
  astore_3
  aload 5
  aload_3
  aload_1
  invokeinterface android/content/SharedPreferences$Editor/putString(Ljava/lang/String;Ljava/lang/String;)Landroid/content/SharedPreferences$Editor; 3
  pop
  aload 5
  invokeinterface android/content/SharedPreferences$Editor/commit()Z 1
  istore 6
  iload 6
  ireturn
  nop
.end <method>

.method protected static g(Landroid/content/Context;)V
.limit locals 22
.limit stack 200
  nop
  iconst_0
  istore_2
  aload_0
  astore_1
  aload_1
  invokestatic com/kuguo/ad/d/d(Landroid/content/Context;)[Lcom/kuguo/ad/p;
  astore_3
  new java/lang/NoClassDefFoundError
  dup
  invokespecial java/lang/NoClassDefFoundError/<init>()V
  athrow
  iload_3
  ifne Label0
Label10:
  return
Label0:
  ldc "message_prefs"
  astore 5
  iconst_0
  istore 6
  aload_0
  astore_1
  aload_1
  aload 5
  iload 6
  invokevirtual android/content/Context/getSharedPreferences(Ljava/lang/String;I)Landroid/content/SharedPreferences;
  astore 4
  aload 4
  invokeinterface android/content/SharedPreferences/edit()Landroid/content/SharedPreferences$Editor; 1
  astore 7
  aload_3
  arraylength
  istore 8
Label3:
  dload_2
  invokestatic app/DummyClass/invokeIfStmt(D)V
  dload 8
  invokestatic app/DummyClass/invokeIfStmt(D)V
  iload_2
  iload 8
  if_icmpge Label1
  aload_3
  iload_2
  aaload
  astore 9
  new java/lang/StringBuilder
  astore 10
  aload 10
  invokespecial java/lang/StringBuilder/<init>()V
  ldc ""
  astore 5
  aload 10
  aload 5
  invokevirtual java/lang/StringBuilder/append(Ljava/lang/String;)Ljava/lang/StringBuilder;
  astore 10
  aload 9
  getfield com/kuguo/ad/p/f I
  istore 11
  aload 10
  iload 11
  invokevirtual java/lang/StringBuilder/append(I)Ljava/lang/StringBuilder;
  astore 10
  aload 10
  invokevirtual java/lang/StringBuilder/toString()Ljava/lang/String;
  astore 12
  aload 9
  getfield com/kuguo/ad/p/c J
  lstore 13
  ldc2_w 864000000
  lstore 15
  lload 13
  lload 15
  ladd
  lstore 13
  invokestatic java/lang/System/currentTimeMillis()J
  lstore 17
  lload 13
  lload 17
  lcmp
  istore 19
  iload 19
  istore_1
  dload_1
  invokestatic app/DummyClass/invokeIfStmt(D)V
  iload 19
  ifge Label2
  aload 7
  aload 12
  invokeinterface android/content/SharedPreferences$Editor/remove(Ljava/lang/String;)Landroid/content/SharedPreferences$Editor; 2
  pop
Label9:
  iload_2
  iconst_1
  iadd
  istore_2
  goto Label3
Label2:
  aload 9
  getfield com/kuguo/ad/p/e B
  istore_1
  iload_1
  istore 19
  dload_1
  invokestatic app/DummyClass/invokeIfStmt(D)V
  iload 19
  lookupswitch
  0 : Label5
  1 : Label6
  2 : Label7
  3 : Label6
  4 : Label7
  5 : Label8
  6 : Label7
  7 : Label8
  8 : Label7
  default : Label4
Label4:
  goto Label8
Label8:
  goto Label9
Label5:
  aload 9
  getfield com/kuguo/ad/p/j Ljava/lang/Integer;
  astore_1
  aload_1
  astore 20
  aload 20
  astore_1
  aload_1
  invokevirtual java/lang/Integer/intValue()I
  istore 11
  dload 11
  invokestatic app/DummyClass/invokeIfStmt(D)V
  iconst_1
  istore 6
  iload 11
  iload 6
  if_icmpne Label9
  aload 7
  aload 12
  invokeinterface android/content/SharedPreferences$Editor/remove(Ljava/lang/String;)Landroid/content/SharedPreferences$Editor; 2
  pop
  goto Label9
Label7:
  aload 9
  getfield com/kuguo/ad/p/j Ljava/lang/Integer;
  astore_1
  aload_1
  astore 20
  aload 20
  astore_1
  aload_1
  invokevirtual java/lang/Integer/intValue()I
  istore 21
  iload 21
  istore_1
  dload_1
  invokestatic app/DummyClass/invokeIfStmt(D)V
  iconst_2
  istore 6
  iload 21
  istore_1
  iload_1
  iload 6
  if_icmpne Label9
  aload 7
  aload 12
  invokeinterface android/content/SharedPreferences$Editor/remove(Ljava/lang/String;)Landroid/content/SharedPreferences$Editor; 2
  pop
  goto Label9
Label6:
  aload 9
  getfield com/kuguo/ad/p/j Ljava/lang/Integer;
  astore_1
  aload_1
  astore 20
  aload 20
  astore_1
  aload_1
  invokevirtual java/lang/Integer/intValue()I
  istore 21
  iload 21
  istore_1
  dload_1
  invokestatic app/DummyClass/invokeIfStmt(D)V
  iconst_3
  istore 6
  iload 21
  istore_1
  iload_1
  iload 6
  if_icmpne Label9
  aload 7
  aload 12
  invokeinterface android/content/SharedPreferences$Editor/remove(Ljava/lang/String;)Landroid/content/SharedPreferences$Editor; 2
  pop
  goto Label9
Label1:
  aload 7
  invokeinterface android/content/SharedPreferences$Editor/commit()Z 1
  pop
  goto Label10
  nop
  nop
.end <method>

.method protected static h(Landroid/content/Context;)Ljava/lang/String;
.limit locals 8
.limit stack 200
  nop
  ldc "request_prefs"
  astore_2
  iconst_0
  istore_3
  new java/lang/NoClassDefFoundError
  dup
  invokespecial java/lang/NoClassDefFoundError/<init>()V
  athrow
  nop
  ldc "adsState"
  astore_2
  aconst_null
  astore 5
  aload_1
  aload_2
  aload 5
  invokeinterface android/content/SharedPreferences/getString(Ljava/lang/String;Ljava/lang/String;)Ljava/lang/String; 3
  astore 4
  new java/lang/StringBuilder
  astore 6
  aload 6
  invokespecial java/lang/StringBuilder/<init>()V
  ldc "adsState == "
  astore_2
  aload 6
  aload_2
  invokevirtual java/lang/StringBuilder/append(Ljava/lang/String;)Ljava/lang/StringBuilder;
  astore 6
  aload 6
  aload 4
  invokevirtual java/lang/StringBuilder/append(Ljava/lang/String;)Ljava/lang/StringBuilder;
  astore 6
  aload 6
  invokevirtual java/lang/StringBuilder/toString()Ljava/lang/String;
  astore 7
  aload 7
  invokestatic com/kuguo/ad/d/a(Ljava/lang/String;)V
  aload 4
  areturn
  nop
.end <method>

.method public static i(Landroid/content/Context;)Z
.limit locals 4
.limit stack 200
  nop
  new java/lang/NoClassDefFoundError
  dup
  invokespecial java/lang/NoClassDefFoundError/<init>()V
  athrow
  nop
  aload_1
  getfield android/content/pm/ApplicationInfo/flags I
  istore_2
  iload_2
  iconst_1
  iand
  istore_2
  dload_2
  invokestatic app/DummyClass/invokeIfStmt(D)V
  iload_2
  ifle Label0
  iconst_1
  istore_3
  iload_3
  ireturn
Label0:
  iconst_0
  istore_3
  iload_3
  ireturn
  nop
.end <method>

.method protected static j(Landroid/content/Context;)Ljava/lang/String;
.limit locals 14
.limit stack 200
  nop
  iconst_0
  istore_1
  ldc "download/ads/verify.dat"
  astore_3
  aload_3
  invokestatic com/kuguo/ad/d/b(Ljava/lang/String;)Ljava/lang/String;
  astore_2
  new java/lang/NoClassDefFoundError
  dup
  invokespecial java/lang/NoClassDefFoundError/<init>()V
  athrow
  iload_2
  ifeq Label0
  ldc ""
  astore 4
  aload 4
  aload_2
  invokevirtual java/lang/String/equals(Ljava/lang/Object;)Z
  istore 5
  iload 5
  invokestatic app/DummyClass/invokeIfStmt(Z)V
  iload 5
  ifeq Label1
Label0:
  aconst_null
  astore 6
  aload 6
  areturn
Label1:
  new java/lang/StringBuilder
  astore 7
  aload 7
  invokespecial java/lang/StringBuilder/<init>()V
  ldc "ids--- "
  astore_3
  aload 7
  aload_3
  invokevirtual java/lang/StringBuilder/append(Ljava/lang/String;)Ljava/lang/StringBuilder;
  astore 7
  aload 7
  aload_2
  invokevirtual java/lang/StringBuilder/append(Ljava/lang/String;)Ljava/lang/StringBuilder;
  astore 7
  aload 7
  invokevirtual java/lang/StringBuilder/toString()Ljava/lang/String;
  astore 4
  aload 4
  invokestatic com/kuguo/ad/d/a(Ljava/lang/String;)V
  ldc ";"
  astore_3
  aload_2
  aload_3
  invokestatic com/kuguo/ad/d/a(Ljava/lang/String;Ljava/lang/String;)[Ljava/lang/String;
  astore 8
  aload 8
  invokestatic app/DummyClass/invokeIfStmt(Ljava/lang/Object;)V
  aload 8
  ifnull Label0
  aload 8
  arraylength
  istore 9
  iconst_0
  dstore 10
Label5:
  dload 10
  invokestatic app/DummyClass/invokeIfStmt(D)V
  dload 9
  invokestatic app/DummyClass/invokeIfStmt(D)V
  iload 10
  iload 9
  if_icmpge Label2
  aload 8
  iload 10
  aaload
  astore 4
  ldc ","
  astore_3
  aload 4
  aload_3
  invokestatic com/kuguo/ad/d/a(Ljava/lang/String;Ljava/lang/String;)[Ljava/lang/String;
  astore 11
  aload 11
  invokestatic app/DummyClass/invokeIfStmt(Ljava/lang/Object;)V
  aload 11
  ifnull Label3
  aload 11
  arraylength
  istore 12
  dload 12
  invokestatic app/DummyClass/invokeIfStmt(D)V
  iconst_2
  istore 13
  iload 12
  iload 13
  if_icmpne Label3
  iconst_1
  istore 13
  aload 11
  iload 13
  aaload
  astore_2
  aload_0
  aload_2
  invokestatic com/kuguo/ad/d/c(Landroid/content/Context;Ljava/lang/String;)Z
  istore 5
  iload 5
  invokestatic app/DummyClass/invokeIfStmt(Z)V
  iload 5
  ifeq Label3
  aload_1
  invokestatic app/DummyClass/invokeIfStmt(Ljava/lang/Object;)V
  aload_1
  ifnonnull Label4
  new java/lang/StringBuffer
  astore_1
  iconst_0
  istore 13
  aload 11
  iload 13
  aaload
  astore_2
  aload_1
  aload_2
  invokespecial java/lang/StringBuffer/<init>(Ljava/lang/String;)V
Label3:
  iload 10
  iconst_1
  iadd
  istore 10
  goto Label5
Label4:
  ldc ","
  astore_3
  aload_1
  aload_3
  invokevirtual java/lang/StringBuffer/append(Ljava/lang/String;)Ljava/lang/StringBuffer;
  pop
  iconst_0
  istore 13
  aload 11
  iload 13
  aaload
  astore_2
  aload_1
  aload_2
  invokevirtual java/lang/StringBuffer/append(Ljava/lang/String;)Ljava/lang/StringBuffer;
  pop
  goto Label3
Label2:
  aload_1
  invokestatic app/DummyClass/invokeIfStmt(Ljava/lang/Object;)V
  aload_1
  ifnull Label6
  aload_1
  invokevirtual java/lang/StringBuffer/toString()Ljava/lang/String;
  astore_2
  aload_2
  areturn
Label6:
  ldc ""
  astore_3
  aload_3
  areturn
  nop
.end <method>

.method protected static k(Landroid/content/Context;)Ljava/lang/String;
.limit locals 6
.limit stack 200
  nop
  ldc "coo_id"
  astore_2
  iconst_0
  istore_3
  new java/lang/NoClassDefFoundError
  dup
  invokespecial java/lang/NoClassDefFoundError/<init>()V
  athrow
  nop
  ldc "cooId"
  astore_2
  aconst_null
  astore 5
  aload_1
  aload_2
  aload 5
  invokeinterface android/content/SharedPreferences/getString(Ljava/lang/String;Ljava/lang/String;)Ljava/lang/String; 3
  astore 4
  aload 4
  areturn
  nop
.end <method>

