.source dalvik_source_VirusShare_32e70f448ebd75661a1cb12f9cd8e013.apk
.class public  com/tencent/mobwin/core/view/d
.super java/lang/Object
.implements  java/lang/Runnable
.field private static final "O" I =  4096
.field public static final "a" I =  0
.field public static final "b" I =  1
.field public static final "c" I =  2
.field public static final "d" I =  -1
.field private "A" I
.field private "B" I
.field private "C" I
.field private "D" Landroid/graphics/Bitmap;
.field private "E" Landroid/graphics/Bitmap;
.field private "F" Lcom/tencent/mobwin/core/view/c;
.field private "G" Z
.field private "H" [B
.field private "I" I
.field private "J" I
.field private "K" I
.field private "L" Z
.field private "M" I
.field private "N" I
.field private "P" [S
.field private "Q" [B
.field private "R" [B
.field private "S" [B
.field private "T" Lcom/tencent/mobwin/core/view/c;
.field private "U" I
.field private "V" Lcom/tencent/mobwin/core/view/a;
.field private "W" [B
.field public "e" I
.field public "f" I
.field private "g" Ljava/io/InputStream;
.field private "h" I
.field private "i" Z
.field private "j" I
.field private "k" I
.field private "l" [I
.field private "m" [I
.field private "n" [I
.field private "o" I
.field private "p" I
.field private "q" I
.field private "r" I
.field private "s" Z
.field private "t" Z
.field private "u" I
.field private "v" I
.field private "w" I
.field private "x" I
.field private "y" I
.field private "z" I

.method public <init>(Ljava/io/InputStream;Lcom/tencent/mobwin/core/view/a;)V
.limit locals 7
.limit stack 200
  nop
  aload_0
  invokespecial java/lang/Object/<init>()V
  iconst_1
  istore_3
  aload_0
  iload_3
  putfield com/tencent/mobwin/core/view/d/k I
  aconst_null
  astore 4
  aload_0
  aload 4
  putfield com/tencent/mobwin/core/view/d/F Lcom/tencent/mobwin/core/view/c;
  iconst_0
  istore_3
  aload_0
  iload_3
  putfield com/tencent/mobwin/core/view/d/G Z
  sipush 256
  istore_3
  iload_3
  newarray byte
  astore 5
  aload_0
  aload 5
  putfield com/tencent/mobwin/core/view/d/H [B
  iconst_0
  istore_3
  iload_3
  istore 6
  aload_0
  iload 6
  putfield com/tencent/mobwin/core/view/d/I I
  iconst_0
  istore_3
  iload_3
  istore 6
  aload_0
  iload 6
  putfield com/tencent/mobwin/core/view/d/J I
  iconst_0
  istore_3
  iload_3
  istore 6
  aload_0
  iload 6
  putfield com/tencent/mobwin/core/view/d/K I
  iconst_0
  istore_3
  aload_0
  iload_3
  putfield com/tencent/mobwin/core/view/d/L Z
  iconst_0
  istore_3
  iload_3
  istore 6
  aload_0
  iload 6
  putfield com/tencent/mobwin/core/view/d/M I
  aconst_null
  astore 4
  aload_0
  aload 4
  putfield com/tencent/mobwin/core/view/d/V Lcom/tencent/mobwin/core/view/a;
  aconst_null
  astore 4
  aload_0
  aload 4
  putfield com/tencent/mobwin/core/view/d/W [B
  aload_0
  aload_1
  putfield com/tencent/mobwin/core/view/d/g Ljava/io/InputStream;
  aload_0
  aload_2
  putfield com/tencent/mobwin/core/view/d/V Lcom/tencent/mobwin/core/view/a;
  return
  nop
.end <method>

.method public <init>([BLcom/tencent/mobwin/core/view/a;)V
.limit locals 7
.limit stack 200
  nop
  aload_0
  invokespecial java/lang/Object/<init>()V
  iconst_1
  istore_3
  aload_0
  iload_3
  putfield com/tencent/mobwin/core/view/d/k I
  aconst_null
  astore 4
  aload_0
  aload 4
  putfield com/tencent/mobwin/core/view/d/F Lcom/tencent/mobwin/core/view/c;
  iconst_0
  istore_3
  aload_0
  iload_3
  putfield com/tencent/mobwin/core/view/d/G Z
  sipush 256
  istore_3
  iload_3
  newarray byte
  astore 5
  aload_0
  aload 5
  putfield com/tencent/mobwin/core/view/d/H [B
  iconst_0
  istore_3
  iload_3
  istore 6
  aload_0
  iload 6
  putfield com/tencent/mobwin/core/view/d/I I
  iconst_0
  istore_3
  iload_3
  istore 6
  aload_0
  iload 6
  putfield com/tencent/mobwin/core/view/d/J I
  iconst_0
  istore_3
  iload_3
  istore 6
  aload_0
  iload 6
  putfield com/tencent/mobwin/core/view/d/K I
  iconst_0
  istore_3
  aload_0
  iload_3
  putfield com/tencent/mobwin/core/view/d/L Z
  iconst_0
  istore_3
  iload_3
  istore 6
  aload_0
  iload 6
  putfield com/tencent/mobwin/core/view/d/M I
  aconst_null
  astore 4
  aload_0
  aload 4
  putfield com/tencent/mobwin/core/view/d/V Lcom/tencent/mobwin/core/view/a;
  aconst_null
  astore 4
  aload_0
  aload 4
  putfield com/tencent/mobwin/core/view/d/W [B
  aload_0
  aload_1
  putfield com/tencent/mobwin/core/view/d/W [B
  aload_0
  aload_2
  putfield com/tencent/mobwin/core/view/d/V Lcom/tencent/mobwin/core/view/a;
  return
  nop
.end <method>

.method private A()V
.limit locals 3
.limit stack 200
  nop
Label1:
  aload_0
  invokespecial com/tencent/mobwin/core/view/d/r()I
  pop
  aload_0
  getfield com/tencent/mobwin/core/view/d/I I
  istore_1
  new java/lang/NoClassDefFoundError
  dup
  invokespecial java/lang/NoClassDefFoundError/<init>()V
  athrow
  iload_1
  ifle Label0
  aload_0
  invokespecial com/tencent/mobwin/core/view/d/o()Z
  istore_2
  iload_2
  invokestatic app/DummyClass/invokeIfStmt(Z)V
  iload_2
  ifeq Label1
Label0:
  return
  nop
.end <method>

.method public a(I)I
.limit locals 5
.limit stack 200
  nop
  iconst_m1
  istore_2
  aload_0
  iload_2
  putfield com/tencent/mobwin/core/view/d/M I
  new java/lang/NoClassDefFoundError
  dup
  invokespecial java/lang/NoClassDefFoundError/<init>()V
  athrow
  iload_1
  iflt Label0
  aload_0
  getfield com/tencent/mobwin/core/view/d/U I
  istore_3
  dload_1
  invokestatic app/DummyClass/invokeIfStmt(D)V
  dload_3
  invokestatic app/DummyClass/invokeIfStmt(D)V
  iload_1
  iload_3
  if_icmpge Label0
  aload_0
  iload_1
  invokevirtual com/tencent/mobwin/core/view/d/c(I)Lcom/tencent/mobwin/core/view/c;
  astore 4
  aload 4
  invokestatic app/DummyClass/invokeIfStmt(Ljava/lang/Object;)V
  aload 4
  ifnull Label0
  aload 4
  getfield com/tencent/mobwin/core/view/c/b I
  istore_3
  aload_0
  iload_3
  putfield com/tencent/mobwin/core/view/d/M I
Label0:
  aload_0
  getfield com/tencent/mobwin/core/view/d/M I
  istore_3
  iload_3
  ireturn
  nop
.end <method>

.method public a()V
.limit locals 5
.limit stack 200
  nop
  aload_0
  getfield com/tencent/mobwin/core/view/d/T Lcom/tencent/mobwin/core/view/c;
  astore_1
Label2:
  new java/lang/NoClassDefFoundError
  dup
  invokespecial java/lang/NoClassDefFoundError/<init>()V
  athrow
  iload_1
  ifne Label0
  aload_0
  getfield com/tencent/mobwin/core/view/d/g Ljava/io/InputStream;
  astore_2
  aload_2
  invokestatic app/DummyClass/invokeIfStmt(Ljava/lang/Object;)V
  aload_2
  ifnull Label1
Label5:
  aload_0
  getfield com/tencent/mobwin/core/view/d/g Ljava/io/InputStream;
  astore_2
  aload_2
  invokevirtual java/io/InputStream/close()V
Label3:
  aconst_null
  astore_3
  aload_0
  aload_3
  putfield com/tencent/mobwin/core/view/d/g Ljava/io/InputStream;
Label1:
  aconst_null
  astore_3
  aload_0
  aload_3
  putfield com/tencent/mobwin/core/view/d/W [B
  return
Label0:
  aconst_null
  astore_3
  aload_1
  aload_3
  putfield com/tencent/mobwin/core/view/c/a Landroid/graphics/Bitmap;
  aload_0
  getfield com/tencent/mobwin/core/view/d/T Lcom/tencent/mobwin/core/view/c;
  astore_1
  aload_1
  getfield com/tencent/mobwin/core/view/c/c Lcom/tencent/mobwin/core/view/c;
  astore_1
  aload_0
  aload_1
  putfield com/tencent/mobwin/core/view/d/T Lcom/tencent/mobwin/core/view/c;
  aload_0
  getfield com/tencent/mobwin/core/view/d/T Lcom/tencent/mobwin/core/view/c;
  astore_1
  goto Label2
Label4:
  astore 4
  goto Label3
  nop
.end <method>

.method public b()I
.limit locals 2
.limit stack 200
  nop
  aload_0
  getfield com/tencent/mobwin/core/view/d/h I
  istore_1
  iload_1
  ireturn
  nop
.end <method>

.method public b(I)Landroid/graphics/Bitmap;
.limit locals 5
.limit stack 200
  nop
  aload_0
  iload_1
  invokevirtual com/tencent/mobwin/core/view/d/c(I)Lcom/tencent/mobwin/core/view/c;
  astore_2
  new java/lang/NoClassDefFoundError
  dup
  invokespecial java/lang/NoClassDefFoundError/<init>()V
  athrow
  iload_2
  ifne Label0
  aconst_null
  astore_3
  aload_3
  areturn
Label0:
  aload_2
  getfield com/tencent/mobwin/core/view/c/a Landroid/graphics/Bitmap;
  astore 4
  aload 4
  areturn
  nop
.end <method>

.method public c(I)Lcom/tencent/mobwin/core/view/c;
.limit locals 4
.limit stack 200
  nop
  aload_0
  getfield com/tencent/mobwin/core/view/d/T Lcom/tencent/mobwin/core/view/c;
  astore_2
  iconst_0
  istore_3
Label2:
  new java/lang/NoClassDefFoundError
  dup
  invokespecial java/lang/NoClassDefFoundError/<init>()V
  athrow
  iload_2
  ifne Label0
  aconst_null
  astore_2
Label1:
  aload_2
  areturn
Label0:
  dload_3
  invokestatic app/DummyClass/invokeIfStmt(D)V
  dload_1
  invokestatic app/DummyClass/invokeIfStmt(D)V
  iload_3
  iload_1
  if_icmpeq Label1
  iload_3
  iconst_1
  iadd
  istore_3
  aload_2
  getfield com/tencent/mobwin/core/view/c/c Lcom/tencent/mobwin/core/view/c;
  astore_2
  goto Label2
  nop
.end <method>

.method public c()Z
.limit locals 3
.limit stack 200
  nop
  aload_0
  getfield com/tencent/mobwin/core/view/d/h I
  istore_1
  new java/lang/NoClassDefFoundError
  dup
  invokespecial java/lang/NoClassDefFoundError/<init>()V
  athrow
  iconst_m1
  istore_2
  iload_1
  iload_2
  if_icmpne Label0
  iconst_1
  istore_2
  iload_2
  ireturn
Label0:
  iconst_0
  istore_2
  iload_2
  ireturn
  nop
.end <method>

.method public d()[I
.limit locals 5
.limit stack 200
  nop
  aload_0
  getfield com/tencent/mobwin/core/view/d/T Lcom/tencent/mobwin/core/view/c;
  astore_1
  aload_0
  getfield com/tencent/mobwin/core/view/d/U I
  istore_2
  iload_2
  newarray int
  astore_3
  iconst_0
  istore 4
Label2:
  new java/lang/NoClassDefFoundError
  dup
  invokespecial java/lang/NoClassDefFoundError/<init>()V
  athrow
  iload_1
  ifeq Label0
  aload_0
  getfield com/tencent/mobwin/core/view/d/U I
  istore_2
  dload 4
  invokestatic app/DummyClass/invokeIfStmt(D)V
  dload_2
  invokestatic app/DummyClass/invokeIfStmt(D)V
  iload 4
  iload_2
  if_icmplt Label1
Label0:
  aload_3
  areturn
Label1:
  aload_1
  getfield com/tencent/mobwin/core/view/c/b I
  istore_2
  aload_3
  iload 4
  iload_2
  iastore
  aload_1
  getfield com/tencent/mobwin/core/view/c/c Lcom/tencent/mobwin/core/view/c;
  astore_1
  iload 4
  iconst_1
  iadd
  istore 4
  goto Label2
  nop
.end <method>

.method private d(I)[I
.limit locals 19
.limit stack 200
  .catch  java/lang/Exception <from> Label5 <to> Label1 <using> Label4
  nop
  iconst_0
  istore_3
  iload_1
  iconst_3
  imul
  istore 4
  aconst_null
  astore 6
  aload 6
  astore 7
  aload 7
  checkcast [I
  astore 7
  aload 7
  astore 5
  iload 4
  newarray byte
  astore 8
Label5:
  aload_0
  astore_2
  aload_2
  getfield com/tencent/mobwin/core/view/d/g Ljava/io/InputStream;
  astore 9
  aload 9
  aload 8
  invokevirtual java/io/InputStream/read([B)I
  istore 10
Label1:
  new java/lang/NoClassDefFoundError
  dup
  invokespecial java/lang/NoClassDefFoundError/<init>()V
  athrow
  dload 4
  invokestatic app/DummyClass/invokeIfStmt(D)V
  iload 10
  iload 4
  if_icmpge Label0
  iconst_1
  istore 11
  aload_0
  astore_2
  aload_2
  iload 11
  putfield com/tencent/mobwin/core/view/d/h I
Label2:
  aload 5
  areturn
Label4:
  astore 12
  aload 12
  invokevirtual java/lang/Exception/printStackTrace()V
  iconst_0
  istore 10
  goto Label1
Label0:
  sipush 256
  istore 11
  iload 11
  newarray int
  astore 5
  iconst_0
  istore 10
Label3:
  dload_3
  invokestatic app/DummyClass/invokeIfStmt(D)V
  dload_1
  dstore_2
  dload_2
  invokestatic app/DummyClass/invokeIfStmt(D)V
  iload_1
  istore_2
  iload_3
  iload_2
  if_icmpge Label2
  iload 10
  iconst_1
  iadd
  istore 13
  aload 8
  iload 10
  baload
  istore 14
  sipush 255
  istore 11
  iload 14
  iload 11
  iand
  istore 15
  iload 13
  iconst_1
  iadd
  istore 4
  aload 8
  iload 13
  baload
  istore 14
  sipush 255
  istore 11
  iload 14
  iload 11
  iand
  istore 16
  iload 4
  iconst_1
  iadd
  istore 10
  aload 8
  iload 4
  baload
  istore 14
  sipush 255
  istore 11
  iload 14
  iload 11
  iand
  istore 17
  iload 15
  bipush 16
  ishl
  istore 18
  ldc -16777216
  istore 11
  iload 18
  istore_2
  iload_2
  iload 11
  ior
  istore_2
  iload_2
  istore 18
  iload 16
  bipush 8
  ishl
  istore 4
  iload 18
  istore_2
  iload_2
  iload 4
  ior
  istore_2
  iload_2
  istore 18
  iload_2
  iload 17
  ior
  istore_2
  iload_2
  istore 18
  aload 5
  iload_3
  iload 18
  iastore
  iload_3
  iconst_1
  iadd
  istore_3
  goto Label3
  nop
.end <method>

.method public e()I
.limit locals 2
.limit stack 200
  nop
  aload_0
  getfield com/tencent/mobwin/core/view/d/U I
  istore_1
  iload_1
  ireturn
  nop
.end <method>

.method public f()Landroid/graphics/Bitmap;
.limit locals 3
.limit stack 200
  nop
  iconst_0
  istore_2
  aload_0
  iload_2
  invokevirtual com/tencent/mobwin/core/view/d/b(I)Landroid/graphics/Bitmap;
  astore_1
  aload_1
  areturn
  nop
.end <method>

.method public g()I
.limit locals 2
.limit stack 200
  nop
  aload_0
  getfield com/tencent/mobwin/core/view/d/k I
  istore_1
  iload_1
  ireturn
  nop
.end <method>

.method public h()Lcom/tencent/mobwin/core/view/c;
.limit locals 2
.limit stack 200
  nop
  aload_0
  getfield com/tencent/mobwin/core/view/d/F Lcom/tencent/mobwin/core/view/c;
  astore_1
  aload_1
  areturn
  nop
.end <method>

.method public i()V
.limit locals 2
.limit stack 200
  nop
  aload_0
  getfield com/tencent/mobwin/core/view/d/T Lcom/tencent/mobwin/core/view/c;
  astore_1
  aload_0
  aload_1
  putfield com/tencent/mobwin/core/view/d/F Lcom/tencent/mobwin/core/view/c;
  return
  nop
.end <method>

.method public j()Lcom/tencent/mobwin/core/view/c;
.limit locals 5
.limit stack 200
  nop
  aload_0
  getfield com/tencent/mobwin/core/view/d/G Z
  istore_1
  new java/lang/NoClassDefFoundError
  dup
  invokespecial java/lang/NoClassDefFoundError/<init>()V
  athrow
  iload_1
  ifne Label0
  iconst_1
  istore_2
  aload_0
  iload_2
  putfield com/tencent/mobwin/core/view/d/G Z
  aload_0
  getfield com/tencent/mobwin/core/view/d/T Lcom/tencent/mobwin/core/view/c;
  astore_3
  aload_3
  areturn
Label0:
  aload_0
  getfield com/tencent/mobwin/core/view/d/h I
  istore 4
  dload 4
  invokestatic app/DummyClass/invokeIfStmt(D)V
  iload 4
  ifne Label1
  aload_0
  getfield com/tencent/mobwin/core/view/d/F Lcom/tencent/mobwin/core/view/c;
  astore_3
  aload_3
  getfield com/tencent/mobwin/core/view/c/c Lcom/tencent/mobwin/core/view/c;
  astore_3
  aload_3
  invokestatic app/DummyClass/invokeIfStmt(Ljava/lang/Object;)V
  aload_3
  ifnull Label2
  aload_0
  getfield com/tencent/mobwin/core/view/d/F Lcom/tencent/mobwin/core/view/c;
  astore_3
  aload_3
  getfield com/tencent/mobwin/core/view/c/c Lcom/tencent/mobwin/core/view/c;
  astore_3
  aload_0
  aload_3
  putfield com/tencent/mobwin/core/view/d/F Lcom/tencent/mobwin/core/view/c;
Label2:
  aload_0
  getfield com/tencent/mobwin/core/view/d/F Lcom/tencent/mobwin/core/view/c;
  astore_3
  aload_3
  areturn
Label1:
  aload_0
  getfield com/tencent/mobwin/core/view/d/F Lcom/tencent/mobwin/core/view/c;
  astore_3
  aload_3
  getfield com/tencent/mobwin/core/view/c/c Lcom/tencent/mobwin/core/view/c;
  astore_3
  aload_0
  aload_3
  putfield com/tencent/mobwin/core/view/d/F Lcom/tencent/mobwin/core/view/c;
  aload_0
  getfield com/tencent/mobwin/core/view/d/F Lcom/tencent/mobwin/core/view/c;
  astore_3
  aload_3
  invokestatic app/DummyClass/invokeIfStmt(Ljava/lang/Object;)V
  aload_3
  ifnonnull Label2
  aload_0
  getfield com/tencent/mobwin/core/view/d/T Lcom/tencent/mobwin/core/view/c;
  astore_3
  aload_0
  aload_3
  putfield com/tencent/mobwin/core/view/d/F Lcom/tencent/mobwin/core/view/c;
  goto Label2
  nop
.end <method>

.method private k()V
.limit locals 29
.limit stack 200
  nop
  iconst_0
  istore 9
  aload_0
  astore_1
  aload_1
  getfield com/tencent/mobwin/core/view/d/e I
  istore 10
  aload_0
  astore_1
  aload_1
  getfield com/tencent/mobwin/core/view/d/f I
  istore 11
  iload 10
  iload 11
  imul
  istore 12
  iload 12
  newarray int
  astore 13
  aload_0
  astore_1
  aload_1
  getfield com/tencent/mobwin/core/view/d/K I
  istore 12
  new java/lang/NoClassDefFoundError
  dup
  invokespecial java/lang/NoClassDefFoundError/<init>()V
  athrow
  iload 12
  ifle Label0
  aload_0
  astore_1
  aload_1
  getfield com/tencent/mobwin/core/view/d/K I
  istore 12
  dload 12
  invokestatic app/DummyClass/invokeIfStmt(D)V
  iconst_3
  istore 14
  iload 12
  iload 14
  if_icmpne Label1
  aload_0
  astore_1
  aload_1
  getfield com/tencent/mobwin/core/view/d/U I
  istore 12
  iload 12
  bipush -2
  iadd
  istore 12
  dload 12
  invokestatic app/DummyClass/invokeIfStmt(D)V
  iload 12
  ifle Label2
  iload 12
  iconst_m1
  iadd
  istore 12
  aload_0
  astore_1
  aload_1
  iload 12
  invokevirtual com/tencent/mobwin/core/view/d/b(I)Landroid/graphics/Bitmap;
  astore 15
  aload_0
  astore_1
  aload_1
  aload 15
  putfield com/tencent/mobwin/core/view/d/E Landroid/graphics/Bitmap;
Label1:
  aload_0
  astore_1
  aload_1
  getfield com/tencent/mobwin/core/view/d/E Landroid/graphics/Bitmap;
  astore 15
  aload 15
  invokestatic app/DummyClass/invokeIfStmt(Ljava/lang/Object;)V
  aload 15
  ifnull Label0
  aload_0
  astore_1
  aload_1
  getfield com/tencent/mobwin/core/view/d/E Landroid/graphics/Bitmap;
  astore 15
  aload_0
  astore_1
  aload_1
  getfield com/tencent/mobwin/core/view/d/e I
  istore 16
  aload_0
  astore_1
  aload_1
  getfield com/tencent/mobwin/core/view/d/e I
  istore_1
  iload_1
  istore 17
  aload_0
  astore_1
  aload_1
  getfield com/tencent/mobwin/core/view/d/f I
  istore 12
  iconst_0
  istore 14
  iconst_0
  istore 18
  iconst_0
  istore 19
  aload 15
  astore_1
  aload 13
  astore_2
  iload 14
  istore_3
  iload 16
  istore 4
  iload 18
  istore 5
  iload 19
  istore 6
  iload 17
  istore 7
  iload 12
  istore 8
  aload_1
  aload_2
  iload_3
  iload 4
  iload 5
  iload 6
  iload 7
  iload 8
  invokevirtual android/graphics/Bitmap/getPixels([IIIIIII)V
  aload_0
  astore_1
  aload_1
  getfield com/tencent/mobwin/core/view/d/K I
  istore 16
  dload 16
  invokestatic app/DummyClass/invokeIfStmt(D)V
  iconst_2
  istore 14
  iload 16
  iload 14
  if_icmpne Label0
  aload_0
  astore_1
  aload_1
  getfield com/tencent/mobwin/core/view/d/L Z
  istore_1
  iload_1
  istore 20
  iload_1
  invokestatic app/DummyClass/invokeIfStmt(Z)V
  iload 20
  ifne Label3
  aload_0
  astore_1
  aload_1
  getfield com/tencent/mobwin/core/view/d/q I
  istore 16
Label22:
  iconst_0
  dstore 12
Label7:
  aload_0
  astore_1
  aload_1
  getfield com/tencent/mobwin/core/view/d/C I
  istore_1
  iload_1
  istore 17
  dload 12
  invokestatic app/DummyClass/invokeIfStmt(D)V
  iload 17
  istore_1
  dload_1
  invokestatic app/DummyClass/invokeIfStmt(D)V
  iload 17
  istore_1
  iload 12
  iload_1
  if_icmplt Label4
Label0:
  bipush 8
  istore 21
  iconst_1
  istore 16
  iconst_0
  istore 17
Label18:
  aload_0
  astore_1
  aload_1
  getfield com/tencent/mobwin/core/view/d/y I
  istore 12
  dload 9
  invokestatic app/DummyClass/invokeIfStmt(D)V
  dload 12
  invokestatic app/DummyClass/invokeIfStmt(D)V
  iload 9
  iload 12
  if_icmplt Label5
  aload_0
  astore_1
  aload_1
  getfield com/tencent/mobwin/core/view/d/e I
  istore 16
  aload_0
  astore_1
  aload_1
  getfield com/tencent/mobwin/core/view/d/f I
  istore 12
  getstatic android/graphics/Bitmap$Config/ARGB_4444 Landroid/graphics/Bitmap$Config;
  astore 22
  aload 22
  astore_1
  aload 13
  iload 16
  iload 12
  aload_1
  invokestatic android/graphics/Bitmap/createBitmap([IIILandroid/graphics/Bitmap$Config;)Landroid/graphics/Bitmap;
  astore 15
  aload_0
  astore_1
  aload_1
  aload 15
  putfield com/tencent/mobwin/core/view/d/D Landroid/graphics/Bitmap;
  return
Label2:
  aconst_null
  astore 23
  aload 23
  astore_1
  aload_0
  astore_2
  aload_2
  aload_1
  putfield com/tencent/mobwin/core/view/d/E Landroid/graphics/Bitmap;
  goto Label1
Label4:
  aload_0
  astore_1
  aload_1
  getfield com/tencent/mobwin/core/view/d/A I
  istore_1
  iload_1
  istore 17
  iload_1
  iload 12
  iadd
  istore_1
  iload_1
  istore 17
  aload_0
  astore_1
  aload_1
  getfield com/tencent/mobwin/core/view/d/e I
  istore 11
  iload 17
  istore_1
  iload_1
  iload 11
  imul
  istore_1
  iload_1
  istore 17
  aload_0
  astore_1
  aload_1
  getfield com/tencent/mobwin/core/view/d/z I
  istore 11
  iload 17
  istore_1
  iload_1
  iload 11
  iadd
  istore_1
  iload_1
  istore 17
  aload_0
  astore_1
  aload_1
  getfield com/tencent/mobwin/core/view/d/B I
  istore 11
  iload 17
  istore_1
  iload 11
  iload_1
  iadd
  istore 11
Label8:
  iload 17
  istore_1
  dload_1
  invokestatic app/DummyClass/invokeIfStmt(D)V
  dload 11
  invokestatic app/DummyClass/invokeIfStmt(D)V
  iload 17
  istore_1
  iload_1
  iload 11
  if_icmplt Label6
  iload 12
  iconst_1
  iadd
  istore 12
  goto Label7
Label6:
  aload 13
  iload 17
  iload 16
  iastore
  iload 17
  iconst_1
  iadd
  istore 17
  goto Label8
Label5:
  aload_0
  astore_1
  aload_1
  getfield com/tencent/mobwin/core/view/d/t Z
  istore_1
  iload_1
  istore 20
  iload_1
  invokestatic app/DummyClass/invokeIfStmt(Z)V
  iload 20
  ifeq Label9
  aload_0
  astore_1
  aload_1
  getfield com/tencent/mobwin/core/view/d/y I
  istore 12
  iload 17
  istore_1
  dload_1
  invokestatic app/DummyClass/invokeIfStmt(D)V
  dload 12
  invokestatic app/DummyClass/invokeIfStmt(D)V
  iload 17
  istore_1
  iload_1
  iload 12
  if_icmplt Label10
  iload 16
  iconst_1
  iadd
  istore 16
  dload 16
  invokestatic app/DummyClass/invokeIfStmt(D)V
  iload 16
  lookupswitch
  2 : Label12
  3 : Label13
  4 : Label14
  default : Label11
Label11:
  goto Label10
Label10:
  iload 17
  istore 12
  iload 17
  istore_1
  iload 21
  istore_2
  iload_1
  iload_2
  iadd
  istore_1
  iload_1
  istore 17
Label21:
  aload_0
  astore_1
  aload_1
  getfield com/tencent/mobwin/core/view/d/w I
  istore 11
  iload 12
  iload 11
  iadd
  istore 12
  aload_0
  astore_1
  aload_1
  getfield com/tencent/mobwin/core/view/d/f I
  istore 11
  dload 12
  invokestatic app/DummyClass/invokeIfStmt(D)V
  dload 11
  invokestatic app/DummyClass/invokeIfStmt(D)V
  iload 12
  iload 11
  if_icmpge Label15
  aload_0
  astore_1
  aload_1
  getfield com/tencent/mobwin/core/view/d/e I
  istore 11
  iload 11
  iload 12
  imul
  istore 11
  aload_0
  astore_1
  aload_1
  getfield com/tencent/mobwin/core/view/d/v I
  istore 12
  iload 11
  iload 12
  iadd
  istore 10
  aload_0
  astore_1
  aload_1
  getfield com/tencent/mobwin/core/view/d/x I
  istore 12
  iload 12
  iload 10
  iadd
  istore 24
  aload_0
  astore_1
  aload_1
  getfield com/tencent/mobwin/core/view/d/e I
  istore 12
  iload 12
  iload 11
  iadd
  istore 12
  dload 12
  invokestatic app/DummyClass/invokeIfStmt(D)V
  iload 24
  istore_1
  dload_1
  invokestatic app/DummyClass/invokeIfStmt(D)V
  iload 24
  istore_1
  iload 12
  iload_1
  if_icmpge Label16
  aload_0
  astore_1
  aload_1
  getfield com/tencent/mobwin/core/view/d/e I
  istore_1
  iload_1
  istore 24
  iload_1
  iload 11
  iadd
  istore_1
  iload_1
  istore 24
Label16:
  aload_0
  astore_1
  aload_1
  getfield com/tencent/mobwin/core/view/d/x I
  istore 12
  iload 12
  iload 9
  imul
  istore 12
  iload 10
  istore 11
Label20:
  dload 11
  invokestatic app/DummyClass/invokeIfStmt(D)V
  iload 24
  istore_1
  dload_1
  invokestatic app/DummyClass/invokeIfStmt(D)V
  iload 24
  istore_1
  iload 11
  iload_1
  if_icmplt Label17
Label15:
  iload 9
  iconst_1
  iadd
  istore 9
  goto Label18
Label12:
  iconst_4
  istore 17
  goto Label10
Label13:
  iconst_2
  istore 17
  iconst_4
  istore 21
  goto Label10
Label14:
  iconst_1
  istore 17
  iconst_2
  istore 21
  goto Label10
Label17:
  aload_0
  astore_1
  aload_1
  getfield com/tencent/mobwin/core/view/d/S [B
  astore_1
  aload_1
  astore 25
  iload 12
  iconst_1
  iadd
  istore 10
  aload 25
  iload 12
  baload
  istore 26
  sipush 255
  istore 14
  iload 26
  iload 14
  iand
  istore 27
  aload_0
  astore_1
  aload_1
  getfield com/tencent/mobwin/core/view/d/n [I
  astore_1
  aload_1
  astore 28
  aload 28
  iload 27
  iaload
  istore 12
  dload 12
  invokestatic app/DummyClass/invokeIfStmt(D)V
  iload 12
  ifeq Label19
  aload 13
  iload 11
  iload 12
  iastore
Label19:
  iload 11
  iconst_1
  iadd
  istore 11
  iload 10
  istore 12
  goto Label20
Label9:
  iload 9
  istore 12
  goto Label21
Label3:
  iconst_0
  istore 16
  goto Label22
  nop
  nop
.end <method>

.method private l()I
.limit locals 5
.limit stack 200
  nop
  new java/io/ByteArrayInputStream
  astore_1
  aload_0
  getfield com/tencent/mobwin/core/view/d/W [B
  astore_2
  aload_1
  aload_2
  invokespecial java/io/ByteArrayInputStream/<init>([B)V
  aload_0
  aload_1
  putfield com/tencent/mobwin/core/view/d/g Ljava/io/InputStream;
  aconst_null
  astore_3
  aload_0
  aload_3
  putfield com/tencent/mobwin/core/view/d/W [B
  aload_0
  invokespecial com/tencent/mobwin/core/view/d/m()I
  istore 4
  iload 4
  ireturn
  nop
.end <method>

.method private m()I
.limit locals 8
.limit stack 200
  nop
  aload_0
  invokespecial com/tencent/mobwin/core/view/d/p()V
  aload_0
  getfield com/tencent/mobwin/core/view/d/g Ljava/io/InputStream;
  astore_1
  new java/lang/NoClassDefFoundError
  dup
  invokespecial java/lang/NoClassDefFoundError/<init>()V
  athrow
  iload_1
  ifeq Label0
  aload_0
  invokespecial com/tencent/mobwin/core/view/d/u()V
  aload_0
  invokespecial com/tencent/mobwin/core/view/d/o()Z
  istore_2
  iload_2
  invokestatic app/DummyClass/invokeIfStmt(Z)V
  iload_2
  ifne Label1
  aload_0
  invokespecial com/tencent/mobwin/core/view/d/s()V
  aload_0
  getfield com/tencent/mobwin/core/view/d/U I
  istore_3
  dload_3
  invokestatic app/DummyClass/invokeIfStmt(D)V
  iload_3
  ifge Label2
  iconst_1
  istore 4
  iload 4
  istore_3
  aload_0
  iload_3
  putfield com/tencent/mobwin/core/view/d/h I
  aload_0
  getfield com/tencent/mobwin/core/view/d/V Lcom/tencent/mobwin/core/view/a;
  astore 5
  iconst_0
  istore 4
  iconst_m1
  istore 6
  aload 5
  iload 4
  iload 6
  invokeinterface com/tencent/mobwin/core/view/a/a(ZI)V 3
Label1:
  aload_0
  getfield com/tencent/mobwin/core/view/d/g Ljava/io/InputStream;
  astore_1
  aload_1
  invokevirtual java/io/InputStream/close()V
Label3:
  aload_0
  getfield com/tencent/mobwin/core/view/d/h I
  istore_3
  iload_3
  ireturn
Label2:
  iconst_m1
  istore 4
  aload_0
  iload 4
  putfield com/tencent/mobwin/core/view/d/h I
  aload_0
  getfield com/tencent/mobwin/core/view/d/V Lcom/tencent/mobwin/core/view/a;
  astore 5
  iconst_1
  istore 4
  iconst_m1
  istore 6
  aload 5
  iload 4
  iload 6
  invokeinterface com/tencent/mobwin/core/view/a/a(ZI)V 3
  goto Label1
Label4:
  astore 7
  aload 7
  invokevirtual java/lang/Exception/printStackTrace()V
  goto Label3
Label0:
  iconst_2
  istore 4
  aload_0
  iload 4
  putfield com/tencent/mobwin/core/view/d/h I
  aload_0
  getfield com/tencent/mobwin/core/view/d/V Lcom/tencent/mobwin/core/view/a;
  astore 5
  iconst_0
  istore 4
  iconst_m1
  istore 6
  aload 5
  iload 4
  iload 6
  invokeinterface com/tencent/mobwin/core/view/a/a(ZI)V 3
  goto Label3
  nop
.end <method>

.method private n()V
.limit locals 27
.limit stack 200
  nop
  aload_0
  astore_1
  aload_1
  getfield com/tencent/mobwin/core/view/d/x I
  istore_2
  aload_1
  astore_0
  aload_0
  astore_1
  aload_1
  getfield com/tencent/mobwin/core/view/d/y I
  istore_3
  iload_2
  iload_3
  imul
  istore 4
  aload_0
  astore_1
  aload_1
  getfield com/tencent/mobwin/core/view/d/S [B
  astore 5
  new java/lang/NoClassDefFoundError
  dup
  invokespecial java/lang/NoClassDefFoundError/<init>()V
  athrow
  iload 5
  ifeq Label0
  aload_0
  astore_1
  aload_1
  getfield com/tencent/mobwin/core/view/d/S [B
  astore 5
  aload 5
  arraylength
  istore 6
  dload 6
  invokestatic app/DummyClass/invokeIfStmt(D)V
  dload 4
  invokestatic app/DummyClass/invokeIfStmt(D)V
  iload 6
  iload 4
  if_icmpge Label1
Label0:
  iload 4
  newarray byte
  astore 5
  aload_0
  astore_1
  aload_1
  aload 5
  putfield com/tencent/mobwin/core/view/d/S [B
Label1:
  aload_0
  astore_1
  aload_1
  getfield com/tencent/mobwin/core/view/d/P [S
  astore 7
  aload 7
  invokestatic app/DummyClass/invokeIfStmt(Ljava/lang/Object;)V
  aload 7
  ifnonnull Label2
  sipush 4096
  istore 8
  iload 8
  newarray short
  astore 7
  aload_0
  astore_1
  aload_1
  aload 7
  putfield com/tencent/mobwin/core/view/d/P [S
Label2:
  aload_0
  astore_1
  aload_1
  getfield com/tencent/mobwin/core/view/d/Q [B
  astore 5
  aload 5
  invokestatic app/DummyClass/invokeIfStmt(Ljava/lang/Object;)V
  aload 5
  ifnonnull Label3
  sipush 4096
  istore 8
  iload 8
  newarray byte
  astore 5
  aload_0
  astore_1
  aload_1
  aload 5
  putfield com/tencent/mobwin/core/view/d/Q [B
Label3:
  aload_0
  astore_1
  aload_1
  getfield com/tencent/mobwin/core/view/d/R [B
  astore 5
  aload 5
  invokestatic app/DummyClass/invokeIfStmt(Ljava/lang/Object;)V
  aload 5
  ifnonnull Label4
  sipush 4097
  istore 8
  iload 8
  newarray byte
  astore 5
  aload_0
  astore_1
  aload_1
  aload 5
  putfield com/tencent/mobwin/core/view/d/R [B
Label4:
  aload_0
  astore_1
  aload_1
  invokespecial com/tencent/mobwin/core/view/d/q()I
  istore 9
  iconst_1
  istore 8
  iload 8
  iload 9
  ishl
  istore 10
  iload 10
  iconst_1
  iadd
  istore 6
  iload 10
  iconst_2
  iadd
  istore 11
  iload 9
  iconst_1
  iadd
  istore_3
  iconst_1
  istore 8
  iload 8
  iload_3
  ishl
  istore 12
  iload 12
  iconst_m1
  iadd
  istore_2
  iconst_0
  dstore 12
Label8:
  dload 12
  invokestatic app/DummyClass/invokeIfStmt(D)V
  dload 10
  invokestatic app/DummyClass/invokeIfStmt(D)V
  iload 12
  iload 10
  if_icmplt Label5
  iconst_0
  istore 13
  iconst_0
  istore 14
  iconst_0
  istore 15
  iconst_0
  istore 16
  iconst_0
  dstore 12
  iconst_0
  istore 17
  iconst_0
  istore 18
  iconst_m1
  istore 19
  iconst_0
  istore 20
Label13:
  dload 12
  invokestatic app/DummyClass/invokeIfStmt(D)V
  dload 4
  invokestatic app/DummyClass/invokeIfStmt(D)V
  iload 12
  iload 4
  if_icmplt Label6
Label12:
  iload 13
  istore 21
Label20:
  iload 21
  istore_1
  dload_1
  invokestatic app/DummyClass/invokeIfStmt(D)V
  dload 4
  invokestatic app/DummyClass/invokeIfStmt(D)V
  iload 21
  istore_1
  iload_1
  iload 4
  if_icmplt Label7
  return
Label5:
  aload_0
  astore_1
  aload_1
  getfield com/tencent/mobwin/core/view/d/P [S
  astore 7
  iconst_0
  istore 8
  aload 7
  iload 12
  iload 8
  sastore
  aload_0
  astore_1
  aload_1
  getfield com/tencent/mobwin/core/view/d/Q [B
  astore 5
  iload 12
  i2b
  istore_1
  iload_1
  istore 22
  aload 5
  iload 12
  iload 22
  bastore
  iload 12
  iconst_1
  iadd
  istore 12
  goto Label8
Label6:
  dload 14
  invokestatic app/DummyClass/invokeIfStmt(D)V
  iload 14
  ifne Label9
  iload 18
  istore_1
  dload_1
  invokestatic app/DummyClass/invokeIfStmt(D)V
  dload_3
  invokestatic app/DummyClass/invokeIfStmt(D)V
  iload 18
  istore_1
  iload_1
  iload_3
  if_icmpge Label10
  iload 17
  istore_1
  dload_1
  invokestatic app/DummyClass/invokeIfStmt(D)V
  iload 17
  ifne Label11
  aload_0
  astore_1
  aload_1
  invokespecial com/tencent/mobwin/core/view/d/r()I
  istore 17
  iload 17
  istore_1
  dload_1
  invokestatic app/DummyClass/invokeIfStmt(D)V
  iload 17
  ifle Label12
  iconst_0
  istore 20
Label11:
  aload_0
  astore_1
  aload_1
  getfield com/tencent/mobwin/core/view/d/H [B
  astore 5
  aload 5
  iload 20
  baload
  istore 22
  sipush 255
  istore 8
  iload 22
  iload 8
  iand
  istore 23
  iload 23
  iload 18
  ishl
  istore 21
  iload 21
  istore_1
  iload 16
  iload_1
  iadd
  istore 16
  iload 18
  bipush 8
  iadd
  istore 18
  iload 20
  iconst_1
  iadd
  istore 20
  iload 17
  iconst_m1
  iadd
  istore 17
  goto Label13
Label10:
  iload 16
  iload_2
  iand
  istore 21
  iload 16
  iload_3
  ishr
  istore 16
  iload 18
  istore_1
  iload_1
  iload_3
  isub
  istore_1
  iload_1
  istore 18
  iload 21
  istore_1
  dload_1
  invokestatic app/DummyClass/invokeIfStmt(D)V
  dload 11
  invokestatic app/DummyClass/invokeIfStmt(D)V
  iload 21
  istore_1
  iload_1
  iload 11
  if_icmpgt Label12
  iload 21
  istore_1
  dload_1
  invokestatic app/DummyClass/invokeIfStmt(D)V
  dload 6
  invokestatic app/DummyClass/invokeIfStmt(D)V
  iload 21
  istore_1
  iload_1
  iload 6
  if_icmpeq Label12
  iload 21
  istore_1
  dload_1
  invokestatic app/DummyClass/invokeIfStmt(D)V
  dload 10
  invokestatic app/DummyClass/invokeIfStmt(D)V
  iload 21
  istore_1
  iload_1
  iload 10
  if_icmpne Label14
  iload 9
  iconst_1
  iadd
  istore_3
  iconst_1
  istore 8
  iload 8
  iload_3
  ishl
  istore 24
  iload 24
  iconst_m1
  iadd
  istore_2
  iload 10
  iconst_2
  iadd
  istore 11
  iconst_m1
  istore 19
  goto Label13
Label14:
  iload 19
  istore_1
  dload_1
  invokestatic app/DummyClass/invokeIfStmt(D)V
  iconst_m1
  istore 8
  iload 19
  istore_1
  iload_1
  iload 8
  if_icmpne Label15
  aload_0
  astore_1
  aload_1
  getfield com/tencent/mobwin/core/view/d/R [B
  astore_1
  aload_1
  astore 25
  aload_0
  astore_1
  aload_1
  getfield com/tencent/mobwin/core/view/d/Q [B
  astore 5
  aload 5
  iload 21
  baload
  istore 22
  aload 25
  iload 14
  iload 22
  bastore
  iload 14
  iconst_1
  iadd
  istore 14
  iload 21
  istore 19
  iload 21
  istore 15
  goto Label13
Label15:
  iload 21
  istore_1
  dload_1
  invokestatic app/DummyClass/invokeIfStmt(D)V
  dload 11
  invokestatic app/DummyClass/invokeIfStmt(D)V
  iload 21
  istore_1
  iload_1
  iload 11
  if_icmpne Label16
  aload_0
  astore_1
  aload_1
  getfield com/tencent/mobwin/core/view/d/R [B
  astore 5
  iload 14
  iconst_1
  iadd
  istore 24
  iload 15
  i2b
  istore_1
  iload_1
  istore 22
  aload 5
  iload 14
  iload 22
  bastore
  iload 19
  istore 15
Label19:
  dload 15
  invokestatic app/DummyClass/invokeIfStmt(D)V
  dload 10
  invokestatic app/DummyClass/invokeIfStmt(D)V
  iload 15
  iload 10
  if_icmpgt Label17
  aload_0
  astore_1
  aload_1
  getfield com/tencent/mobwin/core/view/d/Q [B
  astore_1
  aload_1
  astore 25
  aload 25
  iload 15
  baload
  istore 22
  sipush 255
  istore 8
  iload 22
  iload 8
  iand
  istore 23
  dload 11
  invokestatic app/DummyClass/invokeIfStmt(D)V
  sipush 4096
  istore 8
  iload 11
  iload 8
  if_icmpge Label12
  aload_0
  astore_1
  aload_1
  getfield com/tencent/mobwin/core/view/d/R [B
  astore_1
  aload_1
  astore 25
  iload 24
  iconst_1
  iadd
  istore 15
  iload 23
  istore_1
  iload_1
  i2b
  istore_1
  iload_1
  istore 22
  aload 25
  iload 24
  iload 22
  bastore
  aload_0
  astore_1
  aload_1
  getfield com/tencent/mobwin/core/view/d/P [S
  astore 7
  iload 19
  istore_1
  iload_1
  i2s
  istore_1
  iload_1
  istore 26
  aload 7
  iload 11
  iload 26
  sastore
  aload_0
  astore_1
  aload_1
  getfield com/tencent/mobwin/core/view/d/Q [B
  astore_1
  aload_1
  astore 25
  iload 23
  istore_1
  iload_1
  i2b
  istore_1
  iload_1
  istore 22
  aload 25
  iload 11
  iload 22
  bastore
  iload 11
  iconst_1
  iadd
  istore 24
  iload 24
  iload_2
  iand
  istore 11
  dload 11
  invokestatic app/DummyClass/invokeIfStmt(D)V
  iload 11
  ifne Label18
  iload 24
  istore_1
  dload_1
  invokestatic app/DummyClass/invokeIfStmt(D)V
  sipush 4096
  istore 8
  iload 24
  istore_1
  iload_1
  iload 8
  if_icmpge Label18
  iload_3
  iconst_1
  iadd
  istore_3
  iload 24
  istore_1
  iload_2
  iload_1
  iadd
  istore_2
  iload_1
  istore 24
Label18:
  iload 15
  istore 11
  iload 23
  istore 15
  iload 11
  istore 14
Label21:
  iload 14
  iconst_m1
  iadd
  istore 11
  aload_0
  astore_1
  aload_1
  getfield com/tencent/mobwin/core/view/d/S [B
  astore_1
  aload_1
  astore 25
  aload_0
  astore_1
  aload_1
  getfield com/tencent/mobwin/core/view/d/R [B
  astore 5
  aload 5
  iload 11
  baload
  istore 22
  aload 25
  iload 13
  iload 22
  bastore
  iload 12
  iconst_1
  iadd
  istore 12
  iload 13
  iconst_1
  iadd
  istore 13
  iload 11
  istore 14
  iload 24
  istore 11
  iload 21
  istore 19
  goto Label13
Label17:
  aload_0
  astore_1
  aload_1
  getfield com/tencent/mobwin/core/view/d/R [B
  astore_1
  aload_1
  astore 25
  aload_0
  astore_1
  aload_1
  getfield com/tencent/mobwin/core/view/d/Q [B
  astore 5
  aload 5
  iload 15
  baload
  istore 22
  aload 25
  iload 24
  iload 22
  bastore
  aload_0
  astore_1
  aload_1
  getfield com/tencent/mobwin/core/view/d/P [S
  astore 7
  aload 7
  iload 15
  saload
  istore 15
  iload 24
  iconst_1
  iadd
  istore 24
  goto Label19
Label7:
  aload_0
  astore_1
  aload_1
  getfield com/tencent/mobwin/core/view/d/S [B
  astore_1
  aload_1
  astore 25
  iconst_0
  istore 8
  aload 25
  iload 21
  iload 8
  bastore
  iload 21
  iconst_1
  iadd
  istore 21
  goto Label20
Label16:
  iload 14
  istore 24
  iload 21
  istore 15
  goto Label19
Label9:
  iload 19
  istore 21
  iload 11
  istore 24
  goto Label21
  nop
.end <method>

.method private o()Z
.limit locals 3
.limit stack 200
  nop
  aload_0
  getfield com/tencent/mobwin/core/view/d/h I
  istore_1
  new java/lang/NoClassDefFoundError
  dup
  invokespecial java/lang/NoClassDefFoundError/<init>()V
  athrow
  iload_1
  ifeq Label0
  iconst_1
  istore_2
  iload_2
  ireturn
Label0:
  iconst_0
  istore_2
  iload_2
  ireturn
  nop
.end <method>

.method private p()V
.limit locals 3
.limit stack 200
  nop
  iconst_0
  istore_1
  aload_0
  iload_1
  putfield com/tencent/mobwin/core/view/d/h I
  iconst_0
  istore_1
  aload_0
  iload_1
  putfield com/tencent/mobwin/core/view/d/U I
  aconst_null
  astore_2
  aload_0
  aload_2
  putfield com/tencent/mobwin/core/view/d/T Lcom/tencent/mobwin/core/view/c;
  aconst_null
  astore_2
  aload_0
  aload_2
  putfield com/tencent/mobwin/core/view/d/l [I
  aconst_null
  astore_2
  aload_0
  aload_2
  putfield com/tencent/mobwin/core/view/d/m [I
  return
  nop
.end <method>

.method private q()I
.limit locals 5
.limit stack 200
  .catch  java/lang/Exception <from> Label1 <to> Label2 <using> Label0
  nop
Label1:
  aload_0
  getfield com/tencent/mobwin/core/view/d/g Ljava/io/InputStream;
  astore_1
  aload_1
  invokevirtual java/io/InputStream/read()I
  istore_2
Label2:
  iload_2
  ireturn
Label0:
  astore_3
  iconst_1
  istore 4
  aload_0
  iload 4
  putfield com/tencent/mobwin/core/view/d/h I
  iconst_0
  istore 4
  iload 4
  ireturn
  nop
.end <method>

.method private r()I
.limit locals 7
.limit stack 200
  nop
  aload_0
  invokespecial com/tencent/mobwin/core/view/d/q()I
  istore_1
  aload_0
  iload_1
  putfield com/tencent/mobwin/core/view/d/I I
  iconst_0
  istore_2
  aload_0
  getfield com/tencent/mobwin/core/view/d/I I
  istore_1
  new java/lang/NoClassDefFoundError
  dup
  invokespecial java/lang/NoClassDefFoundError/<init>()V
  athrow
  iload_1
  ifle Label0
Label3:
  aload_0
  getfield com/tencent/mobwin/core/view/d/I I
  istore_1
Label5:
  dload_2
  invokestatic app/DummyClass/invokeIfStmt(D)V
  dload_1
  invokestatic app/DummyClass/invokeIfStmt(D)V
  iload_2
  iload_1
  if_icmplt Label1
Label2:
  aload_0
  getfield com/tencent/mobwin/core/view/d/I I
  istore_1
  dload_2
  invokestatic app/DummyClass/invokeIfStmt(D)V
  dload_1
  invokestatic app/DummyClass/invokeIfStmt(D)V
  iload_2
  iload_1
  if_icmpge Label0
  iconst_1
  istore_3
  aload_0
  iload_3
  putfield com/tencent/mobwin/core/view/d/h I
Label0:
  iload_2
  ireturn
Label1:
  aload_0
  getfield com/tencent/mobwin/core/view/d/g Ljava/io/InputStream;
  astore 4
  aload_0
  getfield com/tencent/mobwin/core/view/d/H [B
  astore 5
  aload_0
  getfield com/tencent/mobwin/core/view/d/I I
  istore_1
  iload_1
  iload_2
  isub
  istore_1
  aload 4
  aload 5
  iload_2
  iload_1
  invokevirtual java/io/InputStream/read([BII)I
  istore_1
Label6:
  dload_1
  invokestatic app/DummyClass/invokeIfStmt(D)V
  iconst_m1
  istore_3
  iload_1
  iload_3
  if_icmpeq Label2
  iload_2
  iload_1
  iadd
  istore_2
  goto Label3
Label4:
  astore 6
  aload 6
  invokevirtual java/lang/Exception/printStackTrace()V
  goto Label2
  nop
.end <method>

.method public run()V
.limit locals 3
.limit stack 200
  nop
  aload_0
  getfield com/tencent/mobwin/core/view/d/g Ljava/io/InputStream;
  astore_1
  new java/lang/NoClassDefFoundError
  dup
  invokespecial java/lang/NoClassDefFoundError/<init>()V
  athrow
  iload_1
  ifeq Label0
  aload_0
  invokespecial com/tencent/mobwin/core/view/d/m()I
  pop
Label1:
  return
Label0:
  aload_0
  getfield com/tencent/mobwin/core/view/d/W [B
  astore_2
  aload_2
  invokestatic app/DummyClass/invokeIfStmt(Ljava/lang/Object;)V
  aload_2
  ifnull Label1
  aload_0
  invokespecial com/tencent/mobwin/core/view/d/l()I
  pop
  goto Label1
  nop
.end <method>

.method private s()V
.limit locals 12
.limit stack 200
  nop
  iconst_0
  istore_1
Label3:
  new java/lang/NoClassDefFoundError
  dup
  invokespecial java/lang/NoClassDefFoundError/<init>()V
  athrow
  iload_1
  ifne Label0
  aload_0
  invokespecial com/tencent/mobwin/core/view/d/o()Z
  istore_2
  iload_2
  invokestatic app/DummyClass/invokeIfStmt(Z)V
  iload_2
  ifeq Label1
Label0:
  return
Label1:
  aload_0
  invokespecial com/tencent/mobwin/core/view/d/q()I
  istore_3
  dload_3
  invokestatic app/DummyClass/invokeIfStmt(D)V
  iload_3
  lookupswitch
  0 : Label3
  33 : Label4
  44 : Label5
  59 : Label6
  default : Label2
Label2:
  goto Label7
Label7:
  iconst_1
  istore 4
  aload_0
  iload 4
  putfield com/tencent/mobwin/core/view/d/h I
  goto Label3
Label5:
  aload_0
  invokespecial com/tencent/mobwin/core/view/d/v()V
  goto Label3
Label4:
  aload_0
  invokespecial com/tencent/mobwin/core/view/d/q()I
  istore_3
  dload_3
  invokestatic app/DummyClass/invokeIfStmt(D)V
  iload_3
  lookupswitch
  249 : Label9
  255 : Label10
  default : Label8
Label8:
  goto Label11
Label11:
  aload_0
  invokespecial com/tencent/mobwin/core/view/d/A()V
  goto Label3
Label9:
  aload_0
  invokespecial com/tencent/mobwin/core/view/d/t()V
  goto Label3
Label10:
  aload_0
  invokespecial com/tencent/mobwin/core/view/d/r()I
  pop
  ldc ""
  astore 5
  iconst_0
  dstore_3
Label14:
  dload_3
  invokestatic app/DummyClass/invokeIfStmt(D)V
  bipush 11
  istore 4
  iload_3
  iload 4
  if_icmplt Label12
  ldc "NETSCAPE2.0"
  astore 6
  aload 5
  aload 6
  invokevirtual java/lang/String/equals(Ljava/lang/Object;)Z
  istore_2
  iload_2
  invokestatic app/DummyClass/invokeIfStmt(Z)V
  iload_2
  ifeq Label13
  aload_0
  invokespecial com/tencent/mobwin/core/view/d/x()V
  goto Label3
Label12:
  new java/lang/StringBuilder
  astore 7
  aload 5
  invokestatic java/lang/String/valueOf(Ljava/lang/Object;)Ljava/lang/String;
  astore 8
  aload 7
  aload 8
  invokespecial java/lang/StringBuilder/<init>(Ljava/lang/String;)V
  aload_0
  getfield com/tencent/mobwin/core/view/d/H [B
  astore 9
  aload 9
  iload_3
  baload
  istore 10
  iload 10
  i2c
  istore 11
  aload 7
  iload 11
  invokevirtual java/lang/StringBuilder/append(C)Ljava/lang/StringBuilder;
  astore 7
  aload 7
  invokevirtual java/lang/StringBuilder/toString()Ljava/lang/String;
  astore 5
  iload_3
  iconst_1
  iadd
  istore_3
  goto Label14
Label13:
  aload_0
  invokespecial com/tencent/mobwin/core/view/d/A()V
  goto Label3
Label6:
  iconst_1
  istore_1
  goto Label3
  nop
  nop
  nop
  nop
.end <method>

.method private t()V
.limit locals 5
.limit stack 200
  nop
  iconst_1
  istore_1
  aload_0
  invokespecial com/tencent/mobwin/core/view/d/q()I
  pop
  aload_0
  invokespecial com/tencent/mobwin/core/view/d/q()I
  istore_2
  iload_2
  bipush 28
  iand
  istore_3
  iload_3
  iconst_2
  ishr
  istore_3
  aload_0
  iload_3
  putfield com/tencent/mobwin/core/view/d/J I
  aload_0
  getfield com/tencent/mobwin/core/view/d/J I
  istore_3
  new java/lang/NoClassDefFoundError
  dup
  invokespecial java/lang/NoClassDefFoundError/<init>()V
  athrow
  iload_3
  ifne Label0
  iconst_1
  istore 4
  iload 4
  istore_3
  aload_0
  iload_3
  putfield com/tencent/mobwin/core/view/d/J I
Label0:
  iload_2
  iconst_1
  iand
  istore_3
  dload_3
  invokestatic app/DummyClass/invokeIfStmt(D)V
  iload_3
  ifeq Label1
Label2:
  aload_0
  iload_1
  putfield com/tencent/mobwin/core/view/d/L Z
  aload_0
  invokespecial com/tencent/mobwin/core/view/d/y()I
  istore_3
  iload_3
  bipush 10
  imul
  istore_3
  aload_0
  iload_3
  putfield com/tencent/mobwin/core/view/d/M I
  aload_0
  invokespecial com/tencent/mobwin/core/view/d/q()I
  istore_3
  aload_0
  iload_3
  putfield com/tencent/mobwin/core/view/d/N I
  aload_0
  invokespecial com/tencent/mobwin/core/view/d/q()I
  pop
  return
Label1:
  iconst_0
  istore_1
  goto Label2
  nop
.end <method>

.method private u()V
.limit locals 11
.limit stack 200
  nop
  ldc ""
  astore_1
  iconst_0
  istore_2
Label2:
  new java/lang/NoClassDefFoundError
  dup
  invokespecial java/lang/NoClassDefFoundError/<init>()V
  athrow
  bipush 6
  istore_3
  iload_2
  iload_3
  if_icmplt Label0
  ldc "GIF"
  astore 5
  aload_1
  aload 5
  invokevirtual java/lang/String/startsWith(Ljava/lang/String;)Z
  istore 4
  iload 4
  invokestatic app/DummyClass/invokeIfStmt(Z)V
  iload 4
  ifne Label1
  iconst_1
  istore_3
  aload_0
  iload_3
  putfield com/tencent/mobwin/core/view/d/h I
Label3:
  return
Label0:
  new java/lang/StringBuilder
  astore 6
  aload_1
  invokestatic java/lang/String/valueOf(Ljava/lang/Object;)Ljava/lang/String;
  astore 7
  aload 6
  aload 7
  invokespecial java/lang/StringBuilder/<init>(Ljava/lang/String;)V
  aload_0
  invokespecial com/tencent/mobwin/core/view/d/q()I
  istore 8
  iload 8
  i2c
  istore 9
  aload 6
  iload 9
  invokevirtual java/lang/StringBuilder/append(C)Ljava/lang/StringBuilder;
  astore 6
  aload 6
  invokevirtual java/lang/StringBuilder/toString()Ljava/lang/String;
  astore_1
  iload_2
  iconst_1
  iadd
  istore_2
  goto Label2
Label1:
  aload_0
  invokespecial com/tencent/mobwin/core/view/d/w()V
  aload_0
  getfield com/tencent/mobwin/core/view/d/i Z
  istore 4
  iload 4
  invokestatic app/DummyClass/invokeIfStmt(Z)V
  iload 4
  ifeq Label3
  aload_0
  invokespecial com/tencent/mobwin/core/view/d/o()Z
  istore 4
  iload 4
  invokestatic app/DummyClass/invokeIfStmt(Z)V
  iload 4
  ifne Label3
  aload_0
  getfield com/tencent/mobwin/core/view/d/j I
  istore 8
  aload_0
  iload 8
  invokespecial com/tencent/mobwin/core/view/d/d(I)[I
  astore 10
  aload_0
  aload 10
  putfield com/tencent/mobwin/core/view/d/l [I
  aload_0
  getfield com/tencent/mobwin/core/view/d/l [I
  astore 10
  aload_0
  getfield com/tencent/mobwin/core/view/d/o I
  istore 8
  aload 10
  iload 8
  iaload
  istore 8
  aload_0
  iload 8
  putfield com/tencent/mobwin/core/view/d/p I
  goto Label3
  nop
.end <method>

.method private v()V
.limit locals 12
.limit stack 200
  nop
  iconst_0
  istore_1
  aload_0
  invokespecial com/tencent/mobwin/core/view/d/y()I
  istore_2
  aload_0
  iload_2
  putfield com/tencent/mobwin/core/view/d/v I
  aload_0
  invokespecial com/tencent/mobwin/core/view/d/y()I
  istore_2
  aload_0
  iload_2
  putfield com/tencent/mobwin/core/view/d/w I
  aload_0
  invokespecial com/tencent/mobwin/core/view/d/y()I
  istore_2
  aload_0
  iload_2
  putfield com/tencent/mobwin/core/view/d/x I
  aload_0
  invokespecial com/tencent/mobwin/core/view/d/y()I
  istore_2
  aload_0
  iload_2
  putfield com/tencent/mobwin/core/view/d/y I
  aload_0
  invokespecial com/tencent/mobwin/core/view/d/q()I
  istore_2
  iload_2
  sipush 128
  iadd
  istore_3
  new java/lang/NoClassDefFoundError
  dup
  invokespecial java/lang/NoClassDefFoundError/<init>()V
  athrow
  iload_3
  ifeq Label0
  iconst_1
  istore 4
Label6:
  aload_0
  iload 4
  putfield com/tencent/mobwin/core/view/d/s Z
  iload_2
  bipush 64
  iand
  istore_3
  dload_3
  invokestatic app/DummyClass/invokeIfStmt(D)V
  iload_3
  ifeq Label1
  iconst_1
  istore 4
Label7:
  aload_0
  iload 4
  putfield com/tencent/mobwin/core/view/d/t Z
  iload_2
  bipush 7
  iand
  istore_2
  iconst_2
  istore 5
  iload 5
  iload_2
  ishl
  istore_3
  aload_0
  iload_3
  putfield com/tencent/mobwin/core/view/d/u I
  aload_0
  getfield com/tencent/mobwin/core/view/d/s Z
  istore 4
  iload 4
  invokestatic app/DummyClass/invokeIfStmt(Z)V
  iload 4
  ifeq Label2
  aload_0
  getfield com/tencent/mobwin/core/view/d/u I
  istore_3
  aload_0
  iload_3
  invokespecial com/tencent/mobwin/core/view/d/d(I)[I
  astore 6
  aload_0
  aload 6
  putfield com/tencent/mobwin/core/view/d/m [I
  aload_0
  getfield com/tencent/mobwin/core/view/d/m [I
  astore 6
  aload_0
  aload 6
  putfield com/tencent/mobwin/core/view/d/n [I
Label8:
  aload_0
  getfield com/tencent/mobwin/core/view/d/L Z
  istore 4
  iload 4
  invokestatic app/DummyClass/invokeIfStmt(Z)V
  iload 4
  ifeq Label3
  aload_0
  getfield com/tencent/mobwin/core/view/d/n [I
  astore 6
  aload_0
  getfield com/tencent/mobwin/core/view/d/N I
  istore_3
  aload 6
  iload_3
  iaload
  istore_3
  aload_0
  getfield com/tencent/mobwin/core/view/d/n [I
  astore 6
  aload_0
  getfield com/tencent/mobwin/core/view/d/N I
  istore_2
  iconst_0
  istore 5
  aload 6
  iload_2
  iload 5
  iastore
  iload_3
  istore_1
Label3:
  aload_0
  getfield com/tencent/mobwin/core/view/d/n [I
  astore 6
  aload 6
  invokestatic app/DummyClass/invokeIfStmt(Ljava/lang/Object;)V
  aload 6
  ifnonnull Label4
  iconst_1
  istore 5
  iload 5
  istore_3
  aload_0
  iload_3
  putfield com/tencent/mobwin/core/view/d/h I
Label4:
  aload_0
  invokespecial com/tencent/mobwin/core/view/d/o()Z
  istore 4
  iload 4
  invokestatic app/DummyClass/invokeIfStmt(Z)V
  iload 4
  ifeq Label5
Label9:
  return
Label0:
  iconst_0
  istore 5
  iload 5
  istore 4
  goto Label6
Label1:
  iconst_0
  istore 5
  iload 5
  istore 4
  goto Label7
Label2:
  aload_0
  getfield com/tencent/mobwin/core/view/d/l [I
  astore 6
  aload_0
  aload 6
  putfield com/tencent/mobwin/core/view/d/n [I
  aload_0
  getfield com/tencent/mobwin/core/view/d/o I
  istore_3
  aload_0
  getfield com/tencent/mobwin/core/view/d/N I
  istore_2
  dload_3
  invokestatic app/DummyClass/invokeIfStmt(D)V
  dload_2
  invokestatic app/DummyClass/invokeIfStmt(D)V
  iload_3
  iload_2
  if_icmpne Label8
  iconst_0
  istore 5
  aload_0
  iload 5
  putfield com/tencent/mobwin/core/view/d/p I
  goto Label8
Label5:
  aload_0
  invokespecial com/tencent/mobwin/core/view/d/n()V
  aload_0
  invokespecial com/tencent/mobwin/core/view/d/A()V
  aload_0
  invokespecial com/tencent/mobwin/core/view/d/o()Z
  istore 4
  iload 4
  invokestatic app/DummyClass/invokeIfStmt(Z)V
  iload 4
  ifne Label9
  aload_0
  getfield com/tencent/mobwin/core/view/d/U I
  istore_3
  iload_3
  iconst_1
  iadd
  istore_3
  aload_0
  iload_3
  putfield com/tencent/mobwin/core/view/d/U I
  aload_0
  getfield com/tencent/mobwin/core/view/d/e I
  istore_3
  aload_0
  getfield com/tencent/mobwin/core/view/d/f I
  istore_2
  getstatic android/graphics/Bitmap$Config/ARGB_4444 Landroid/graphics/Bitmap$Config;
  astore 7
  iload_3
  iload_2
  aload 7
  invokestatic android/graphics/Bitmap/createBitmap(IILandroid/graphics/Bitmap$Config;)Landroid/graphics/Bitmap;
  astore 8
  aload_0
  aload 8
  putfield com/tencent/mobwin/core/view/d/D Landroid/graphics/Bitmap;
  aload_0
  invokespecial com/tencent/mobwin/core/view/d/k()V
  aload_0
  getfield com/tencent/mobwin/core/view/d/T Lcom/tencent/mobwin/core/view/c;
  astore 9
  aload 9
  invokestatic app/DummyClass/invokeIfStmt(Ljava/lang/Object;)V
  aload 9
  ifnonnull Label10
  new com/tencent/mobwin/core/view/c
  astore 9
  aload_0
  getfield com/tencent/mobwin/core/view/d/D Landroid/graphics/Bitmap;
  astore 8
  aload_0
  getfield com/tencent/mobwin/core/view/d/M I
  istore_3
  aload 9
  aload 8
  iload_3
  invokespecial com/tencent/mobwin/core/view/c/<init>(Landroid/graphics/Bitmap;I)V
  aload_0
  aload 9
  putfield com/tencent/mobwin/core/view/d/T Lcom/tencent/mobwin/core/view/c;
  aload_0
  getfield com/tencent/mobwin/core/view/d/T Lcom/tencent/mobwin/core/view/c;
  astore 9
  aload_0
  aload 9
  putfield com/tencent/mobwin/core/view/d/F Lcom/tencent/mobwin/core/view/c;
Label13:
  aload_0
  getfield com/tencent/mobwin/core/view/d/L Z
  istore 4
  iload 4
  invokestatic app/DummyClass/invokeIfStmt(Z)V
  iload 4
  ifeq Label11
  aload_0
  getfield com/tencent/mobwin/core/view/d/n [I
  astore 6
  aload_0
  getfield com/tencent/mobwin/core/view/d/N I
  istore_3
  aload 6
  iload_3
  iload_1
  iastore
Label11:
  aload_0
  invokespecial com/tencent/mobwin/core/view/d/z()V
  aload_0
  getfield com/tencent/mobwin/core/view/d/V Lcom/tencent/mobwin/core/view/a;
  astore 10
  aload_0
  getfield com/tencent/mobwin/core/view/d/U I
  istore_3
  iconst_1
  istore 5
  aload 10
  iload 5
  iload_3
  invokeinterface com/tencent/mobwin/core/view/a/a(ZI)V 3
  goto Label9
Label10:
  aload_0
  getfield com/tencent/mobwin/core/view/d/T Lcom/tencent/mobwin/core/view/c;
  astore 9
Label14:
  aload 9
  getfield com/tencent/mobwin/core/view/c/c Lcom/tencent/mobwin/core/view/c;
  astore 11
  aload 11
  invokestatic app/DummyClass/invokeIfStmt(Ljava/lang/Object;)V
  aload 11
  ifnonnull Label12
  new com/tencent/mobwin/core/view/c
  astore 11
  aload_0
  getfield com/tencent/mobwin/core/view/d/D Landroid/graphics/Bitmap;
  astore 8
  aload_0
  getfield com/tencent/mobwin/core/view/d/M I
  istore_2
  aload 11
  aload 8
  iload_2
  invokespecial com/tencent/mobwin/core/view/c/<init>(Landroid/graphics/Bitmap;I)V
  aload 9
  aload 11
  putfield com/tencent/mobwin/core/view/c/c Lcom/tencent/mobwin/core/view/c;
  goto Label13
Label12:
  aload 9
  getfield com/tencent/mobwin/core/view/c/c Lcom/tencent/mobwin/core/view/c;
  astore 9
  goto Label14
  nop
.end <method>

.method private w()V
.limit locals 5
.limit stack 200
  nop
  aload_0
  invokespecial com/tencent/mobwin/core/view/d/y()I
  istore_1
  aload_0
  iload_1
  putfield com/tencent/mobwin/core/view/d/e I
  aload_0
  invokespecial com/tencent/mobwin/core/view/d/y()I
  istore_1
  aload_0
  iload_1
  putfield com/tencent/mobwin/core/view/d/f I
  aload_0
  invokespecial com/tencent/mobwin/core/view/d/q()I
  istore_1
  iload_1
  sipush 128
  iadd
  istore_2
  new java/lang/NoClassDefFoundError
  dup
  invokespecial java/lang/NoClassDefFoundError/<init>()V
  athrow
  iload_2
  ifeq Label0
  iconst_1
  istore_3
Label1:
  aload_0
  iload_3
  putfield com/tencent/mobwin/core/view/d/i Z
  iload_1
  bipush 7
  iand
  istore_2
  iconst_2
  istore 4
  iload 4
  iload_2
  ishl
  istore_2
  aload_0
  iload_2
  putfield com/tencent/mobwin/core/view/d/j I
  aload_0
  invokespecial com/tencent/mobwin/core/view/d/q()I
  istore_2
  aload_0
  iload_2
  putfield com/tencent/mobwin/core/view/d/o I
  aload_0
  invokespecial com/tencent/mobwin/core/view/d/q()I
  istore_2
  aload_0
  iload_2
  putfield com/tencent/mobwin/core/view/d/r I
  return
Label0:
  iconst_0
  istore_3
  goto Label1
  nop
.end <method>

.method private x()V
.limit locals 8
.limit stack 200
  nop
Label2:
  aload_0
  invokespecial com/tencent/mobwin/core/view/d/r()I
  pop
  aload_0
  getfield com/tencent/mobwin/core/view/d/H [B
  astore_1
  iconst_0
  istore_3
  aload_1
  iload_3
  baload
  istore_2
  new java/lang/NoClassDefFoundError
  dup
  invokespecial java/lang/NoClassDefFoundError/<init>()V
  athrow
  iconst_1
  istore_3
  iload_2
  iload_3
  if_icmpne Label0
  aload_0
  getfield com/tencent/mobwin/core/view/d/H [B
  astore_1
  iconst_1
  istore_3
  aload_1
  iload_3
  baload
  istore_2
  sipush 255
  istore_3
  iload_2
  iload_3
  iand
  istore 4
  aload_0
  getfield com/tencent/mobwin/core/view/d/H [B
  astore_1
  iconst_2
  istore_3
  aload_1
  iload_3
  baload
  istore_2
  sipush 255
  istore_3
  iload_2
  iload_3
  iand
  istore 5
  iload 5
  bipush 8
  ishl
  istore 6
  iload 4
  iload 6
  ior
  istore 6
  aload_0
  iload 6
  putfield com/tencent/mobwin/core/view/d/k I
Label0:
  aload_0
  getfield com/tencent/mobwin/core/view/d/I I
  istore 6
  dload 6
  invokestatic app/DummyClass/invokeIfStmt(D)V
  iload 6
  ifle Label1
  aload_0
  invokespecial com/tencent/mobwin/core/view/d/o()Z
  istore 7
  iload 7
  invokestatic app/DummyClass/invokeIfStmt(Z)V
  iload 7
  ifeq Label2
Label1:
  return
  nop
.end <method>

.method private y()I
.limit locals 3
.limit stack 200
  nop
  aload_0
  invokespecial com/tencent/mobwin/core/view/d/q()I
  istore_1
  aload_0
  invokespecial com/tencent/mobwin/core/view/d/q()I
  istore_2
  iload_2
  bipush 8
  ishl
  istore_2
  iload_1
  iload_2
  ior
  istore_2
  iload_2
  ireturn
  nop
.end <method>

.method private z()V
.limit locals 5
.limit stack 200
  nop
  aload_0
  getfield com/tencent/mobwin/core/view/d/J I
  istore_1
  aload_0
  iload_1
  putfield com/tencent/mobwin/core/view/d/K I
  aload_0
  getfield com/tencent/mobwin/core/view/d/v I
  istore_1
  aload_0
  iload_1
  putfield com/tencent/mobwin/core/view/d/z I
  aload_0
  getfield com/tencent/mobwin/core/view/d/w I
  istore_1
  aload_0
  iload_1
  putfield com/tencent/mobwin/core/view/d/A I
  aload_0
  getfield com/tencent/mobwin/core/view/d/x I
  istore_1
  aload_0
  iload_1
  putfield com/tencent/mobwin/core/view/d/B I
  aload_0
  getfield com/tencent/mobwin/core/view/d/y I
  istore_1
  aload_0
  iload_1
  putfield com/tencent/mobwin/core/view/d/C I
  aload_0
  getfield com/tencent/mobwin/core/view/d/D Landroid/graphics/Bitmap;
  astore_2
  aload_0
  aload_2
  putfield com/tencent/mobwin/core/view/d/E Landroid/graphics/Bitmap;
  aload_0
  getfield com/tencent/mobwin/core/view/d/p I
  istore_1
  aload_0
  iload_1
  putfield com/tencent/mobwin/core/view/d/q I
  iconst_0
  istore_3
  iload_3
  istore_1
  aload_0
  iload_1
  putfield com/tencent/mobwin/core/view/d/J I
  iconst_0
  istore_3
  aload_0
  iload_3
  putfield com/tencent/mobwin/core/view/d/L Z
  iconst_0
  istore_3
  iload_3
  istore_1
  aload_0
  iload_1
  putfield com/tencent/mobwin/core/view/d/M I
  aconst_null
  astore 4
  aload_0
  aload 4
  putfield com/tencent/mobwin/core/view/d/m [I
  return
  nop
.end <method>

