.source SourceFile
.class final  com/mobisage/android/W
.super com/mobisage/android/aa

.method <init>(Landroid/os/Handler;)V
.limit locals 3
.limit stack 200
  nop
  aload_0
  aload_1
  invokespecial com/mobisage/android/aa/<init>(Landroid/os/Handler;)V
  sipush 2000
  istore_2
  aload_0
  iload_2
  putfield com/mobisage/android/O/c I
  return
  nop
.end <method>

.method protected final f(Lcom/mobisage/android/b;)V
.limit locals 20
.limit stack 200
  nop
  aload_0
  astore_2
  aload_2
  getfield com/mobisage/android/O/e Ljava/util/concurrent/ConcurrentHashMap;
  astore 4
  aload_1
  astore_2
  aload_2
  getfield com/mobisage/android/b/b Ljava/util/UUID;
  astore 5
  aload_1
  astore_2
  aload 4
  aload 5
  aload_2
  invokevirtual java/util/concurrent/ConcurrentHashMap/put(Ljava/lang/Object;Ljava/lang/Object;)Ljava/lang/Object;
  pop
  new java/io/File
  astore 6
  new java/lang/StringBuilder
  astore 7
  aload 7
  invokespecial java/lang/StringBuilder/<init>()V
  getstatic com/mobisage/android/r/f Ljava/lang/String;
  astore 8
  aload 7
  aload 8
  invokevirtual java/lang/StringBuilder/append(Ljava/lang/String;)Ljava/lang/StringBuilder;
  astore 7
  ldc "/Track"
  astore 9
  aload 7
  aload 9
  invokevirtual java/lang/StringBuilder/append(Ljava/lang/String;)Ljava/lang/StringBuilder;
  astore 7
  ldc "/"
  astore 9
  aload 7
  aload 9
  invokevirtual java/lang/StringBuilder/append(Ljava/lang/String;)Ljava/lang/StringBuilder;
  astore 7
  aload 7
  invokevirtual java/lang/StringBuilder/toString()Ljava/lang/String;
  astore 8
  aload 6
  aload 8
  invokespecial java/io/File/<init>(Ljava/lang/String;)V
  aload 6
  invokevirtual java/io/File/exists()Z
  istore 10
  new java/lang/NoClassDefFoundError
  dup
  invokespecial java/lang/NoClassDefFoundError/<init>()V
  athrow
  iload 10
  ifne Label0
  aload 6
  invokevirtual java/io/File/mkdirs()Z
  pop
Label0:
  aload 6
  invokevirtual java/io/File/listFiles()[Ljava/io/File;
  astore 11
  aload 11
  invokestatic app/DummyClass/invokeIfStmt(Ljava/lang/Object;)V
  aload 11
  ifnull Label1
  iconst_0
  dstore 12
Label2:
  aload 11
  arraylength
  istore 13
  dload 12
  invokestatic app/DummyClass/invokeIfStmt(D)V
  dload 13
  invokestatic app/DummyClass/invokeIfStmt(D)V
  iload 12
  iload 13
  if_icmpge Label1
  new com/mobisage/android/X
  astore 14
  aload 14
  invokespecial com/mobisage/android/X/<init>()V
  aload 11
  iload 12
  aaload
  astore 6
  aload 6
  invokevirtual java/io/File/getPath()Ljava/lang/String;
  astore 8
  aload 14
  aload 8
  putfield com/mobisage/android/X/a Ljava/lang/String;
  aload_0
  astore_2
  aload_2
  getfield com/mobisage/android/aa/g Lcom/mobisage/android/aa$a;
  astore 15
  aload 14
  aload 15
  putfield com/mobisage/android/MobiSageMessage/callback Lcom/mobisage/android/IMobiSageMessageCallback;
  aload_1
  astore_2
  aload_2
  getfield com/mobisage/android/b/f Ljava/util/concurrent/LinkedBlockingQueue;
  astore 16
  aload 16
  aload 14
  invokevirtual java/util/concurrent/LinkedBlockingQueue/add(Ljava/lang/Object;)Z
  pop
  aload_0
  astore_2
  aload_2
  getfield com/mobisage/android/O/f Ljava/util/concurrent/ConcurrentHashMap;
  astore 4
  aload 14
  getfield com/mobisage/android/MobiSageMessage/c Ljava/util/UUID;
  astore 5
  aload_1
  astore_2
  aload_2
  getfield com/mobisage/android/b/b Ljava/util/UUID;
  astore 17
  aload 4
  aload 5
  aload 17
  invokevirtual java/util/concurrent/ConcurrentHashMap/put(Ljava/lang/Object;Ljava/lang/Object;)Ljava/lang/Object;
  pop
  invokestatic com/mobisage/android/H/a()Lcom/mobisage/android/H;
  astore 18
  aload 18
  astore_2
  aload_2
  aload 14
  invokevirtual com/mobisage/android/H/a(Lcom/mobisage/android/MobiSageMessage;)V
  iload 12
  iconst_1
  iadd
  istore 12
  goto Label2
Label1:
  aload_1
  astore_2
  aload_2
  invokevirtual com/mobisage/android/b/a()Z
  istore 10
  iload 10
  invokestatic app/DummyClass/invokeIfStmt(Z)V
  iload 10
  ifeq Label3
  aload_0
  astore_2
  aload_2
  getfield com/mobisage/android/O/e Ljava/util/concurrent/ConcurrentHashMap;
  astore 4
  aload_1
  astore_2
  aload_2
  getfield com/mobisage/android/b/b Ljava/util/UUID;
  astore 17
  aload 4
  aload 17
  invokevirtual java/util/concurrent/ConcurrentHashMap/remove(Ljava/lang/Object;)Ljava/lang/Object;
  pop
  aload_1
  astore_2
  aload_2
  getfield com/mobisage/android/b/g Lcom/mobisage/android/a;
  astore_2
  aload_2
  astore 19
  aload 19
  astore_2
  aload_2
  invokestatic app/DummyClass/invokeIfStmt(Ljava/lang/Object;)V
  aload 19
  ifnull Label3
  aload_1
  astore_2
  aload_2
  getfield com/mobisage/android/b/g Lcom/mobisage/android/a;
  astore_2
  aload_2
  astore 19
  aload 19
  astore_2
  aload_1
  astore_3
  aload_2
  aload_3
  invokeinterface com/mobisage/android/a/a(Lcom/mobisage/android/b;)V 2
Label3:
  return
  nop
.end <method>

