.source dalvik_source_VirusShare_32e70f448ebd75661a1cb12f9cd8e013.apk
.class public  com/kuguo/a/f
.super java/lang/Object
.implements  com/kuguo/b/h
.field private "a" Lcom/kuguo/b/d;
.field private "b" Ljava/io/File;
.field private "c" I
.field private "d" I
.field private "e" I
.field private "f" Lcom/kuguo/a/d;
.field private "g" I
.field private "h" Lcom/kuguo/a/e;
.field private "i" Ljava/io/BufferedInputStream;
.field private "j" I
.field private "k" I
.field private "l" Ljava/lang/Exception;
.field private "m" Ljava/lang/String;
.field private "n" Ljava/lang/Object;
.field private "o" Ljava/lang/String;
.field private "p" Ljava/lang/String;

.method <init>(Landroid/content/Context;Lcom/kuguo/a/c;)V
.limit locals 12
.limit stack 200
  nop
  aload_0
  invokespecial java/lang/Object/<init>()V
  iconst_3
  istore_3
  aload_0
  iload_3
  putfield com/kuguo/a/f/k I
  new com/kuguo/b/g
  astore 4
  aload_2
  getfield com/kuguo/a/c/a Ljava/lang/String;
  astore 5
  aload 4
  aload 5
  invokespecial com/kuguo/b/g/<init>(Ljava/lang/String;)V
  new com/kuguo/b/a
  astore 6
  aload 6
  aload_1
  aload 4
  invokespecial com/kuguo/b/a/<init>(Landroid/content/Context;Lcom/kuguo/b/g;)V
  aload_0
  aload 6
  putfield com/kuguo/a/f/a Lcom/kuguo/b/d;
  invokestatic com/kuguo/a/e/a()Lcom/kuguo/a/e;
  astore 7
  aload_0
  aload 7
  putfield com/kuguo/a/f/h Lcom/kuguo/a/e;
  aload_2
  getfield com/kuguo/a/c/a Ljava/lang/String;
  astore 5
  aload_0
  aload 5
  putfield com/kuguo/a/f/m Ljava/lang/String;
  new java/io/File
  astore 8
  aload_2
  getfield com/kuguo/a/c/b Ljava/lang/String;
  astore 5
  aload 8
  aload 5
  invokespecial java/io/File/<init>(Ljava/lang/String;)V
  aload_0
  aload 8
  putfield com/kuguo/a/f/b Ljava/io/File;
  aload_2
  getfield com/kuguo/a/c/c I
  istore 9
  aload_0
  iload 9
  putfield com/kuguo/a/f/d I
  aload_2
  getfield com/kuguo/a/c/d I
  istore 9
  aload_0
  iload 9
  putfield com/kuguo/a/f/e I
  aload_2
  getfield com/kuguo/a/c/e I
  istore 9
  aload_0
  iload 9
  putfield com/kuguo/a/f/c I
  aload_2
  getfield com/kuguo/a/c/f Ljava/lang/String;
  astore 5
  aload_0
  aload 5
  putfield com/kuguo/a/f/p Ljava/lang/String;
  aload_2
  getfield com/kuguo/a/c/g Ljava/lang/String;
  astore 5
  aload_0
  aload 5
  putfield com/kuguo/a/f/o Ljava/lang/String;
  aload_2
  getfield com/kuguo/a/c/h I
  istore 9
  aload_0
  iload 9
  putfield com/kuguo/a/f/g I
  aload_0
  getfield com/kuguo/a/f/m Ljava/lang/String;
  astore 5
  ldc ".apk"
  astore 11
  aload 5
  aload 11
  invokevirtual java/lang/String/endsWith(Ljava/lang/String;)Z
  istore 10
  new java/lang/NoClassDefFoundError
  dup
  invokespecial java/lang/NoClassDefFoundError/<init>()V
  athrow
  iload 10
  ifeq Label0
  iconst_0
  istore_3
  aload_0
  iload_3
  putfield com/kuguo/a/f/g I
Label0:
  return
  nop
.end <method>

.method public <init>(Ljava/lang/String;Ljava/io/File;I)V
.limit locals 14
.limit stack 200
  nop
  aload_0
  invokespecial java/lang/Object/<init>()V
  iconst_3
  istore 4
  aload_0
  iload 4
  putfield com/kuguo/a/f/k I
  aload_0
  aload_2
  putfield com/kuguo/a/f/b Ljava/io/File;
  aload_0
  aload_1
  putfield com/kuguo/a/f/m Ljava/lang/String;
  iconst_0
  istore 4
  aload_0
  iload 4
  putfield com/kuguo/a/f/d I
  new java/lang/NoClassDefFoundError
  dup
  invokespecial java/lang/NoClassDefFoundError/<init>()V
  athrow
  iconst_1
  istore 4
  iload_3
  iload 4
  if_icmpne Label0
  aload_0
  invokevirtual com/kuguo/a/f/n()J
  lstore 5
  new java/lang/StringBuilder
  astore 7
  aload 7
  invokespecial java/lang/StringBuilder/<init>()V
  aload 7
  aload_1
  invokevirtual java/lang/StringBuilder/append(Ljava/lang/String;)Ljava/lang/StringBuilder;
  astore 7
  ldc "&pointer="
  astore 8
  aload 7
  aload 8
  invokevirtual java/lang/StringBuilder/append(Ljava/lang/String;)Ljava/lang/StringBuilder;
  astore 7
  aload 7
  lload 5
  invokevirtual java/lang/StringBuilder/append(J)Ljava/lang/StringBuilder;
  astore 7
  aload 7
  invokevirtual java/lang/StringBuilder/toString()Ljava/lang/String;
  astore_1
  lload 5
  l2i
  istore 9
  aload_0
  iload 9
  putfield com/kuguo/a/f/d I
Label0:
  new com/kuguo/b/a
  astore 10
  invokestatic com/kuguo/a/e/a()Lcom/kuguo/a/e;
  astore 11
  aload 11
  getfield com/kuguo/a/e/a Landroid/content/Context;
  astore 12
  new com/kuguo/b/g
  astore 13
  aload 13
  aload_1
  invokespecial com/kuguo/b/g/<init>(Ljava/lang/String;)V
  aload 10
  aload 12
  aload 13
  invokespecial com/kuguo/b/a/<init>(Landroid/content/Context;Lcom/kuguo/b/g;)V
  aload_0
  aload 10
  putfield com/kuguo/a/f/a Lcom/kuguo/b/d;
  iconst_m1
  istore 4
  aload_0
  iload 4
  putfield com/kuguo/a/f/e I
  iconst_0
  istore 4
  aload_0
  iload 4
  putfield com/kuguo/a/f/c I
  aload_0
  iload_3
  putfield com/kuguo/a/f/g I
  aload_0
  invokespecial com/kuguo/a/f/p()V
  return
  nop
.end <method>

.method public a()Lcom/kuguo/b/d;
.limit locals 2
.limit stack 200
  nop
  aload_0
  getfield com/kuguo/a/f/a Lcom/kuguo/b/d;
  astore_1
  aload_1
  areturn
  nop
.end <method>

.method public a(I)V
.limit locals 2
.limit stack 200
  nop
  aload_0
  iload_1
  putfield com/kuguo/a/f/g I
  return
  nop
.end <method>

.method public a(Lcom/kuguo/a/d;)V
.limit locals 2
.limit stack 200
  nop
  aload_0
  aload_1
  putfield com/kuguo/a/f/f Lcom/kuguo/a/d;
  return
  nop
.end <method>

.method public a(Lcom/kuguo/b/d;I)V
.limit locals 8
.limit stack 200
  nop
  aload_0
  getfield com/kuguo/a/f/c I
  istore_3
  new java/lang/NoClassDefFoundError
  dup
  invokespecial java/lang/NoClassDefFoundError/<init>()V
  athrow
  iload_3
  lookupswitch
  1 : Label1
  2 : Label1
  default : Label0
Label0:
  goto Label2
Label2:
  return
Label1:
  dload_2
  invokestatic app/DummyClass/invokeIfStmt(D)V
  iload_2
  lookupswitch
  -4 : Label4
  -3 : Label4
  -2 : Label2
  200 : Label5
  default : Label3
Label3:
  goto Label6
Label6:
  aload_1
  invokevirtual com/kuguo/b/d/b()V
  goto Label2
Label5:
  iconst_2
  istore 4
  aload_0
  iload 4
  invokevirtual com/kuguo/a/f/b(I)V
  aload_1
  invokevirtual com/kuguo/b/d/f()Ljava/io/InputStream;
  astore 5
  new java/io/BufferedInputStream
  astore 6
  sipush 4096
  istore 4
  aload 6
  aload 5
  iload 4
  invokespecial java/io/BufferedInputStream/<init>(Ljava/io/InputStream;I)V
  aload_0
  aload 6
  putfield com/kuguo/a/f/i Ljava/io/BufferedInputStream;
  iconst_m1
  istore 4
  aload_0
  iload 4
  putfield com/kuguo/a/f/e I
  aload_0
  getfield com/kuguo/a/f/d I
  istore_3
  aload_0
  invokevirtual com/kuguo/a/f/g()I
  istore_2
  iload_3
  iload_2
  iadd
  istore_3
  aload_0
  iload_3
  putfield com/kuguo/a/f/e I
  aload_0
  getfield com/kuguo/a/f/i Ljava/io/BufferedInputStream;
  astore 6
  aload_0
  aload 6
  invokespecial com/kuguo/a/f/a(Ljava/io/InputStream;)V
  goto Label2
Label4:
  aload_1
  invokevirtual com/kuguo/b/d/i()Ljava/lang/Exception;
  astore 7
  aload_0
  aload 7
  invokespecial com/kuguo/a/f/a(Ljava/lang/Exception;)V
  goto Label2
  nop
  nop
  nop
.end <method>

.method private a(Ljava/io/InputStream;)V
.limit locals 32
.limit stack 200
  .catch  java/lang/Throwable <from> Label15 <to> Label16 <using> Label13
  .catch  java/lang/Exception <from> Label15 <to> Label16 <using> Label14
  .catch  java/lang/Throwable <from> Label16 <to> Label19 <using> Label17
  .catch  java/lang/Exception <from> Label16 <to> Label19 <using> Label18
  .catch  java/lang/Throwable <from> Label11 <to> Label20 <using> Label17
  .catch  java/io/IOException <from> Label20 <to> Label8 <using> Label21
  .catch  java/lang/Throwable <from> Label1 <to> Label22 <using> Label17
  .catch  java/lang/Exception <from> Label1 <to> Label22 <using> Label18
  .catch  java/io/IOException <from> Label10 <to> Label9 <using> Label23
  .catch  java/lang/Throwable <from> Label2 <to> Label5 <using> Label17
  .catch  java/lang/Exception <from> Label2 <to> Label5 <using> Label18
  nop
  new java/io/File
  astore 7
  new java/lang/StringBuilder
  astore 8
Label15:
  aload 8
  invokespecial java/lang/StringBuilder/<init>()V
  aload_0
  astore_2
  aload_2
  getfield com/kuguo/a/f/b Ljava/io/File;
  astore 9
  aload 9
  invokevirtual java/io/File/getAbsolutePath()Ljava/lang/String;
  astore 10
  aload 8
  aload 10
  invokevirtual java/lang/StringBuilder/append(Ljava/lang/String;)Ljava/lang/StringBuilder;
  astore 8
  ldc ".tmp"
  astore 11
  aload 8
  aload 11
  invokevirtual java/lang/StringBuilder/append(Ljava/lang/String;)Ljava/lang/StringBuilder;
  astore 8
  aload 8
  invokevirtual java/lang/StringBuilder/toString()Ljava/lang/String;
  astore 10
  aload 7
  aload 10
  invokespecial java/io/File/<init>(Ljava/lang/String;)V
  new java/io/RandomAccessFile
  astore 12
  ldc "rw"
  astore 11
  aload 12
  aload 7
  aload 11
  invokespecial java/io/RandomAccessFile/<init>(Ljava/io/File;Ljava/lang/String;)V
Label16:
  aload_0
  astore_2
  aload_2
  getfield com/kuguo/a/f/a Lcom/kuguo/b/d;
  astore 13
  aload 13
  invokevirtual com/kuguo/b/d/g()Ljava/util/Map;
  astore 14
  new java/lang/NoClassDefFoundError
  dup
  invokespecial java/lang/NoClassDefFoundError/<init>()V
  athrow
  iload 14
  ifeq Label0
  ldc "fileflag"
  astore 11
  aload 14
  aload 11
  invokeinterface java/util/Map/get(Ljava/lang/Object;)Ljava/lang/Object; 2
  astore 15
  aload 15
  astore 16
  aload 16
  checkcast java/lang/String
  astore 16
  aload 16
  astore 10
Label12:
  aload_0
  astore_2
  aload_2
  getfield com/kuguo/a/f/g I
  istore 17
  dload 17
  invokestatic app/DummyClass/invokeIfStmt(D)V
  iconst_1
  istore 18
  iload 18
  istore_2
  iload 17
  iload_2
  if_icmpne Label1
  aload 10
  invokestatic app/DummyClass/invokeIfStmt(Ljava/lang/Object;)V
  aload 10
  ifnull Label1
  ldc "true"
  astore 19
  aload 19
  astore_2
  aload_2
  aload 10
  invokevirtual java/lang/String/equals(Ljava/lang/Object;)Z
  istore 20
  iload 20
  istore_2
  iload_2
  invokestatic app/DummyClass/invokeIfStmt(Z)V
  iload 20
  ifeq Label1
  aload 12
  invokevirtual java/io/RandomAccessFile/length()J
  lstore 21
  lload 21
  lstore_2
  aload 12
  lload_2
  invokevirtual java/io/RandomAccessFile/seek(J)V
Label4:
  new java/lang/StringBuilder
  astore 8
  aload 8
  invokespecial java/lang/StringBuilder/<init>()V
  ldc "-----------------downloadsize == "
  astore 11
  aload 8
  aload 11
  invokevirtual java/lang/StringBuilder/append(Ljava/lang/String;)Ljava/lang/StringBuilder;
  astore 8
  aload_0
  astore_2
  aload_2
  invokevirtual com/kuguo/a/f/h()I
  istore 17
  aload 8
  iload 17
  invokevirtual java/lang/StringBuilder/append(I)Ljava/lang/StringBuilder;
  astore 8
  aload 8
  invokevirtual java/lang/StringBuilder/toString()Ljava/lang/String;
  astore 10
  ldc "android__log"
  astore 11
  aload 11
  aload 10
  invokestatic com/kuguo/c/a/a(Ljava/lang/String;Ljava/lang/Object;)V
  new java/lang/StringBuilder
  astore 8
  aload 8
  invokespecial java/lang/StringBuilder/<init>()V
  ldc "-----------------totalsize == "
  astore 11
  aload 8
  aload 11
  invokevirtual java/lang/StringBuilder/append(Ljava/lang/String;)Ljava/lang/StringBuilder;
  astore 8
  aload_0
  astore_2
  aload_2
  invokevirtual com/kuguo/a/f/g()I
  istore 17
  aload 8
  iload 17
  invokevirtual java/lang/StringBuilder/append(I)Ljava/lang/StringBuilder;
  astore 8
  aload 8
  invokevirtual java/lang/StringBuilder/toString()Ljava/lang/String;
  astore 10
  ldc "android__log"
  astore 11
  aload 11
  aload 10
  invokestatic com/kuguo/c/a/a(Ljava/lang/String;Ljava/lang/Object;)V
  new java/lang/StringBuilder
  astore 8
  aload 8
  invokespecial java/lang/StringBuilder/<init>()V
  ldc "url------------ "
  astore 11
  aload 8
  aload 11
  invokevirtual java/lang/StringBuilder/append(Ljava/lang/String;)Ljava/lang/StringBuilder;
  astore 8
  aload_0
  astore_2
  aload_2
  getfield com/kuguo/a/f/a Lcom/kuguo/b/d;
  astore 13
  aload 13
  invokevirtual com/kuguo/b/d/d()Lcom/kuguo/b/g;
  astore 23
  aload 23
  astore_2
  aload_2
  invokevirtual com/kuguo/b/g/c()Ljava/lang/String;
  astore 10
  aload 8
  aload 10
  invokevirtual java/lang/StringBuilder/append(Ljava/lang/String;)Ljava/lang/StringBuilder;
  astore 8
  aload 8
  invokevirtual java/lang/StringBuilder/toString()Ljava/lang/String;
  astore 10
  ldc "android__log"
  astore 11
  aload 11
  aload 10
  invokestatic com/kuguo/c/a/a(Ljava/lang/String;Ljava/lang/Object;)V
  new java/lang/StringBuilder
  astore 8
  aload 8
  invokespecial java/lang/StringBuilder/<init>()V
  ldc "----------------mode == "
  astore 11
  aload 8
  aload 11
  invokevirtual java/lang/StringBuilder/append(Ljava/lang/String;)Ljava/lang/StringBuilder;
  astore 8
  aload_0
  astore_2
  aload_2
  getfield com/kuguo/a/f/g I
  istore 17
  aload 8
  iload 17
  invokevirtual java/lang/StringBuilder/append(I)Ljava/lang/StringBuilder;
  astore 8
  aload 8
  invokevirtual java/lang/StringBuilder/toString()Ljava/lang/String;
  astore 10
  ldc "android__log"
  astore 11
  aload 11
  aload 10
  invokestatic com/kuguo/c/a/a(Ljava/lang/String;Ljava/lang/Object;)V
  sipush 4096
  istore 18
  iload 18
  istore_2
  iload_2
  newarray byte
  astore_2
  aload_2
  astore 24
  iconst_0
  istore 17
Label3:
  aload_0
  astore_2
  aload_2
  getfield com/kuguo/a/f/c I
  istore_2
  iload_2
  istore 25
  dload_2
  invokestatic app/DummyClass/invokeIfStmt(D)V
  iconst_2
  istore 18
  iload 25
  istore_2
  iload 18
  istore_3
  iload_2
  iload_3
  if_icmpne Label2
  aload_1
  astore_2
  aload 24
  astore_3
  aload_2
  aload_3
  invokevirtual java/io/InputStream/read([B)I
  istore 17
  dload 17
  invokestatic app/DummyClass/invokeIfStmt(D)V
  iconst_m1
  istore 18
  iload 18
  istore_2
  iload 17
  iload_2
  if_icmpeq Label2
  iconst_0
  istore 18
  aload 24
  astore_2
  iload 18
  istore_3
  aload 12
  aload_2
  iload_3
  iload 17
  invokevirtual java/io/RandomAccessFile/write([BII)V
  aload_0
  astore_2
  aload_2
  getfield com/kuguo/a/f/d I
  istore_2
  iload_2
  istore 25
  iload_2
  iload 17
  iadd
  istore_2
  iload_2
  istore 25
  aload_0
  astore_3
  aload_3
  iload_2
  putfield com/kuguo/a/f/d I
  aload_0
  astore_2
  aload_2
  getfield com/kuguo/a/f/f Lcom/kuguo/a/d;
  astore_2
  aload_2
  astore 26
  aload 26
  astore_2
  aload_2
  invokestatic app/DummyClass/invokeIfStmt(Ljava/lang/Object;)V
  aload 26
  ifnull Label3
  aload_0
  astore_2
  aload_2
  getfield com/kuguo/a/f/f Lcom/kuguo/a/d;
  astore_2
  aload_2
  astore 26
  iload 17
  i2l
  lstore_2
  lload_2
  lstore 21
  aload 26
  astore_2
  aload_0
  astore_3
  lload 21
  lstore 4
  aload_2
  aload_3
  lload 4
  invokeinterface com/kuguo/a/d/a(Lcom/kuguo/a/f;J)V 4
Label19:
  goto Label3
Label18:
  astore 27
Label11:
  aload 27
  astore_2
  aload_2
  invokevirtual java/lang/Exception/printStackTrace()V
  aload_0
  astore_2
  aload 27
  astore_3
  aload_2
  aload_3
  invokespecial com/kuguo/a/f/a(Ljava/lang/Exception;)V
Label20:
  aload 12
  invokevirtual java/io/RandomAccessFile/close()V
Label8:
  aload_0
  astore_2
  aload_2
  getfield com/kuguo/a/f/a Lcom/kuguo/b/d;
  astore 13
  aload 13
  invokevirtual com/kuguo/b/d/b()V
Label6:
  return
Label1:
  aload_0
  astore_2
  aload_2
  invokevirtual com/kuguo/a/f/g()I
  istore 17
  aload_0
  astore_2
  aload_2
  iload 17
  putfield com/kuguo/a/f/e I
  iconst_0
  istore 18
  iload 18
  istore_2
  aload_0
  astore_3
  aload_3
  iload_2
  putfield com/kuguo/a/f/d I
Label22:
  goto Label4
Label17:
  astore 28
Label10:
  aload 12
  invokevirtual java/io/RandomAccessFile/close()V
Label9:
  aload_0
  astore_2
  aload_2
  getfield com/kuguo/a/f/a Lcom/kuguo/b/d;
  astore 13
  aload 13
  invokevirtual com/kuguo/b/d/b()V
  aload 28
  athrow
Label2:
  aload_0
  astore_2
  aload_2
  getfield com/kuguo/a/f/b Ljava/io/File;
  astore 9
  aload 7
  aload 9
  invokevirtual java/io/File/renameTo(Ljava/io/File;)Z
  pop
  dload 17
  invokestatic app/DummyClass/invokeIfStmt(D)V
  iconst_m1
  istore 18
  iload 18
  istore_2
  iload 17
  iload_2
  if_icmpne Label5
  iconst_4
  istore 18
  aload_0
  astore_2
  iload 18
  istore_3
  aload_2
  iload_3
  invokevirtual com/kuguo/a/f/b(I)V
Label5:
  aload 12
  invokevirtual java/io/RandomAccessFile/close()V
Label7:
  aload_0
  astore_2
  aload_2
  getfield com/kuguo/a/f/a Lcom/kuguo/b/d;
  astore 13
  aload 13
  invokevirtual com/kuguo/b/d/b()V
  goto Label6
Label24:
  astore 29
  aload 29
  astore_2
  aload_2
  invokevirtual java/io/IOException/printStackTrace()V
  goto Label7
Label21:
  astore 30
  aload 30
  astore_2
  aload_2
  invokevirtual java/io/IOException/printStackTrace()V
  goto Label8
Label23:
  astore 31
  aload 31
  astore_2
  aload_2
  invokevirtual java/io/IOException/printStackTrace()V
  goto Label9
Label13:
  astore 28
  aconst_null
  astore 12
  goto Label10
Label14:
  astore 27
  aconst_null
  astore 12
  goto Label11
Label0:
  aconst_null
  astore 10
  goto Label12
  nop
.end <method>

.method private a(Ljava/lang/Exception;)V
.limit locals 7
.limit stack 200
  nop
  ldc "android__log"
  astore_2
  ldc "trytorecoverdownload"
  astore_3
  aload_2
  aload_3
  invokestatic com/kuguo/c/a/a(Ljava/lang/String;Ljava/lang/Object;)V
  aload_0
  getfield com/kuguo/a/f/j I
  istore 4
  iload 4
  iconst_1
  iadd
  istore 5
  aload_0
  iload 5
  putfield com/kuguo/a/f/j I
  aload_0
  getfield com/kuguo/a/f/k I
  istore 5
  new java/lang/NoClassDefFoundError
  dup
  invokespecial java/lang/NoClassDefFoundError/<init>()V
  athrow
  dload 5
  invokestatic app/DummyClass/invokeIfStmt(D)V
  iload 4
  iload 5
  if_icmpge Label0
  aload_0
  invokespecial com/kuguo/a/f/q()V
Label1:
  return
Label0:
  iconst_0
  istore 6
  aload_0
  iload 6
  putfield com/kuguo/a/f/j I
  aload_0
  aload_1
  putfield com/kuguo/a/f/l Ljava/lang/Exception;
  iconst_5
  istore 6
  aload_0
  iload 6
  invokevirtual com/kuguo/a/f/b(I)V
  goto Label1
  nop
.end <method>

.method public a(Ljava/lang/Object;)V
.limit locals 2
.limit stack 200
  nop
  aload_0
  aload_1
  putfield com/kuguo/a/f/n Ljava/lang/Object;
  return
  nop
.end <method>

.method public a(Ljava/lang/String;)V
.limit locals 2
.limit stack 200
  nop
  aload_0
  aload_1
  putfield com/kuguo/a/f/o Ljava/lang/String;
  return
  nop
.end <method>

.method public b()Ljava/io/File;
.limit locals 2
.limit stack 200
  nop
  aload_0
  getfield com/kuguo/a/f/b Ljava/io/File;
  astore_1
  aload_1
  areturn
  nop
.end <method>

.method b(I)V
.limit locals 10
.limit stack 200
  nop
  new java/lang/StringBuilder
  astore_2
  aload_2
  invokespecial java/lang/StringBuilder/<init>()V
  ldc "DownloadTask.java setState() "
  astore_3
  aload_2
  aload_3
  invokevirtual java/lang/StringBuilder/append(Ljava/lang/String;)Ljava/lang/StringBuilder;
  astore_2
  aload_2
  iload_1
  invokevirtual java/lang/StringBuilder/append(I)Ljava/lang/StringBuilder;
  astore_2
  aload_2
  invokevirtual java/lang/StringBuilder/toString()Ljava/lang/String;
  astore 4
  ldc "android__log"
  astore_3
  aload_3
  aload 4
  invokestatic com/kuguo/c/a/a(Ljava/lang/String;Ljava/lang/Object;)V
  aload_0
  getfield com/kuguo/a/f/c I
  istore 5
  new java/lang/NoClassDefFoundError
  dup
  invokespecial java/lang/NoClassDefFoundError/<init>()V
  athrow
  dload 5
  invokestatic app/DummyClass/invokeIfStmt(D)V
  iload_1
  iload 5
  if_icmpeq Label0
  aload_0
  iload_1
  putfield com/kuguo/a/f/c I
  dload_1
  invokestatic app/DummyClass/invokeIfStmt(D)V
  iconst_4
  istore 6
  iload_1
  iload 6
  if_icmpne Label1
  aload_0
  getfield com/kuguo/a/f/h Lcom/kuguo/a/e;
  astore 7
  aload 7
  invokevirtual com/kuguo/a/e/b()Z
  istore 8
  iload 8
  invokestatic app/DummyClass/invokeIfStmt(Z)V
  iload 8
  ifne Label2
Label1:
  dload_1
  invokestatic app/DummyClass/invokeIfStmt(D)V
  iconst_5
  istore 6
  iload_1
  iload 6
  if_icmpne Label3
  aload_0
  getfield com/kuguo/a/f/h Lcom/kuguo/a/e;
  astore 7
  aload 7
  invokevirtual com/kuguo/a/e/c()Z
  istore 8
  iload 8
  invokestatic app/DummyClass/invokeIfStmt(Z)V
  iload 8
  ifeq Label3
Label2:
  aload_0
  invokevirtual com/kuguo/a/f/e()V
Label4:
  aload_0
  getfield com/kuguo/a/f/f Lcom/kuguo/a/d;
  astore 9
  aload 9
  invokestatic app/DummyClass/invokeIfStmt(Ljava/lang/Object;)V
  aload 9
  ifnull Label0
  aload_0
  getfield com/kuguo/a/f/f Lcom/kuguo/a/d;
  astore 9
  aload 9
  aload_0
  iload_1
  invokeinterface com/kuguo/a/d/a(Lcom/kuguo/a/f;I)V 3
Label0:
  return
Label3:
  aload_0
  getfield com/kuguo/a/f/h Lcom/kuguo/a/e;
  astore 7
  aload 7
  aload_0
  invokevirtual com/kuguo/a/e/f(Lcom/kuguo/a/f;)V
  goto Label4
  nop
.end <method>

.method public c()V
.limit locals 7
.limit stack 200
  nop
  aload_0
  invokevirtual com/kuguo/a/f/o()Z
  istore_1
  new java/lang/NoClassDefFoundError
  dup
  invokespecial java/lang/NoClassDefFoundError/<init>()V
  athrow
  iload_1
  ifeq Label0
  iconst_4
  istore_2
  aload_0
  iload_2
  invokevirtual com/kuguo/a/f/b(I)V
Label4:
  return
Label0:
  aload_0
  getfield com/kuguo/a/f/c I
  istore_3
  dload_3
  invokestatic app/DummyClass/invokeIfStmt(D)V
  iload_3
  lookupswitch
  0 : Label2
  default : Label1
Label1:
  goto Label3
Label3:
  goto Label4
Label2:
  aload_0
  getfield com/kuguo/a/f/h Lcom/kuguo/a/e;
  astore 4
  aload 4
  aload_0
  invokevirtual com/kuguo/a/e/b(Lcom/kuguo/a/f;)Lcom/kuguo/a/f;
  astore 5
  aload_0
  getfield com/kuguo/a/f/h Lcom/kuguo/a/e;
  astore 4
  aload 4
  aload_0
  invokevirtual com/kuguo/a/e/a(Lcom/kuguo/a/f;)Z
  istore_1
  iload_1
  invokestatic app/DummyClass/invokeIfStmt(Z)V
  iload_1
  ifeq Label5
  aload 5
  getfield com/kuguo/a/f/c I
  istore_3
  dload_3
  invokestatic app/DummyClass/invokeIfStmt(D)V
  iconst_4
  istore_2
  iload_3
  iload_2
  if_icmpeq Label5
  aload 5
  getfield com/kuguo/a/f/c I
  istore_3
  dload_3
  invokestatic app/DummyClass/invokeIfStmt(D)V
  iconst_5
  istore_2
  iload_3
  iload_2
  if_icmpne Label4
Label5:
  aload_0
  getfield com/kuguo/a/f/b Ljava/io/File;
  astore 6
  aload 6
  invokestatic app/DummyClass/invokeIfStmt(Ljava/lang/Object;)V
  aload 6
  ifnull Label4
  iconst_0
  istore_2
  aload_0
  iload_2
  putfield com/kuguo/a/f/d I
  iconst_1
  istore_2
  aload_0
  iload_2
  invokevirtual com/kuguo/a/f/b(I)V
  aload_0
  getfield com/kuguo/a/f/h Lcom/kuguo/a/e;
  astore 4
  aload 4
  aload_0
  invokevirtual com/kuguo/a/e/c(Lcom/kuguo/a/f;)V
  goto Label4
  nop
  nop
  nop
.end <method>

.method public d()V
.limit locals 5
.limit stack 200
  nop
  new java/lang/StringBuilder
  astore_1
  aload_1
  invokespecial java/lang/StringBuilder/<init>()V
  ldc "-------------task resume ++++++++"
  astore_2
  aload_1
  aload_2
  invokevirtual java/lang/StringBuilder/append(Ljava/lang/String;)Ljava/lang/StringBuilder;
  astore_1
  aload_0
  getfield com/kuguo/a/f/c I
  istore_3
  aload_1
  iload_3
  invokevirtual java/lang/StringBuilder/append(I)Ljava/lang/StringBuilder;
  astore_1
  aload_1
  invokevirtual java/lang/StringBuilder/toString()Ljava/lang/String;
  astore 4
  ldc "android__log"
  astore_2
  aload_2
  aload 4
  invokestatic com/kuguo/c/a/a(Ljava/lang/String;Ljava/lang/Object;)V
  aload_0
  getfield com/kuguo/a/f/c I
  istore_3
  new java/lang/NoClassDefFoundError
  dup
  invokespecial java/lang/NoClassDefFoundError/<init>()V
  athrow
  iload_3
  lookupswitch
  3 : Label1
  4 : Label2
  5 : Label1
  default : Label0
Label0:
  goto Label2
Label2:
  return
Label1:
  aload_0
  invokespecial com/kuguo/a/f/q()V
  goto Label2
  nop
  nop
.end <method>

.method public e()V
.limit locals 3
.limit stack 200
  nop
  iconst_0
  istore_1
  aload_0
  iload_1
  invokevirtual com/kuguo/a/f/b(I)V
  aload_0
  getfield com/kuguo/a/f/h Lcom/kuguo/a/e;
  astore_2
  aload_2
  aload_0
  invokevirtual com/kuguo/a/e/d(Lcom/kuguo/a/f;)V
  return
  nop
.end <method>

.method public equals(Ljava/lang/Object;)Z
.limit locals 10
.limit stack 200
  nop
  aload_1
  instanceof com/kuguo/a/f
  istore_2
  new java/lang/NoClassDefFoundError
  dup
  invokespecial java/lang/NoClassDefFoundError/<init>()V
  athrow
  iload_2
  ifeq Label0
  aload_1
  astore 4
  aload 4
  checkcast com/kuguo/a/f
  astore 4
  aload 4
  astore_3
  aload_0
  invokevirtual com/kuguo/a/f/l()Ljava/lang/String;
  astore 5
  aload 5
  invokestatic app/DummyClass/invokeIfStmt(Ljava/lang/Object;)V
  aload 5
  ifnull Label0
  aload_0
  getfield com/kuguo/a/f/b Ljava/io/File;
  astore 6
  aload 6
  invokestatic app/DummyClass/invokeIfStmt(Ljava/lang/Object;)V
  aload 6
  ifnonnull Label1
Label0:
  iconst_0
  istore 7
  iload 7
  ireturn
Label1:
  aload_3
  invokevirtual com/kuguo/a/f/l()Ljava/lang/String;
  astore 8
  aload 5
  aload 8
  invokevirtual java/lang/String/equals(Ljava/lang/Object;)Z
  istore_2
  iload_2
  invokestatic app/DummyClass/invokeIfStmt(Z)V
  iload_2
  ifeq Label0
  aload_0
  getfield com/kuguo/a/f/b Ljava/io/File;
  astore 6
  aload_3
  invokevirtual com/kuguo/a/f/b()Ljava/io/File;
  astore 9
  aload 6
  aload 9
  invokevirtual java/io/File/equals(Ljava/lang/Object;)Z
  istore_2
  iload_2
  invokestatic app/DummyClass/invokeIfStmt(Z)V
  iload_2
  ifeq Label0
  iconst_1
  istore 7
  iload 7
  ireturn
  nop
.end <method>

.method public f()I
.limit locals 2
.limit stack 200
  nop
  aload_0
  getfield com/kuguo/a/f/c I
  istore_1
  iload_1
  ireturn
  nop
.end <method>

.method public g()I
.limit locals 10
.limit stack 200
  nop
  aload_0
  getfield com/kuguo/a/f/e I
  istore_1
  new java/lang/NoClassDefFoundError
  dup
  invokespecial java/lang/NoClassDefFoundError/<init>()V
  athrow
  iconst_m1
  istore_2
  iload_1
  iload_2
  if_icmpne Label0
  aload_0
  getfield com/kuguo/a/f/a Lcom/kuguo/b/d;
  astore_3
  aload_3
  invokevirtual com/kuguo/b/d/h()I
  istore_1
  dload_1
  invokestatic app/DummyClass/invokeIfStmt(D)V
  sipush 200
  istore_2
  iload_1
  iload_2
  if_icmpne Label0
  aload_0
  getfield com/kuguo/a/f/a Lcom/kuguo/b/d;
  astore_3
  aload_3
  invokevirtual com/kuguo/b/d/g()Ljava/util/Map;
  astore 4
  aload 4
  invokestatic app/DummyClass/invokeIfStmt(Ljava/lang/Object;)V
  aload 4
  ifnull Label0
  ldc "Content-Length"
  astore 6
  aload 4
  aload 6
  invokeinterface java/util/Map/get(Ljava/lang/Object;)Ljava/lang/Object; 2
  astore 5
  aload 5
  astore 8
  aload 8
  checkcast java/lang/String
  astore 8
  aload 8
  astore 7
  aload 7
  invokestatic app/DummyClass/invokeIfStmt(Ljava/lang/Object;)V
  aload 7
  ifnull Label0
Label2:
  aload 7
  invokestatic java/lang/Integer/parseInt(Ljava/lang/String;)I
  istore_1
  aload_0
  iload_1
  putfield com/kuguo/a/f/e I
Label0:
  aload_0
  getfield com/kuguo/a/f/e I
  istore_1
  iload_1
  ireturn
Label1:
  astore 9
  aload 9
  invokevirtual java/lang/Exception/printStackTrace()V
  goto Label0
  nop
.end <method>

.method public h()I
.limit locals 2
.limit stack 200
  nop
  aload_0
  getfield com/kuguo/a/f/d I
  istore_1
  iload_1
  ireturn
  nop
.end <method>

.method public i()Ljava/lang/String;
.limit locals 9
.limit stack 200
  nop
  aload_0
  getfield com/kuguo/a/f/p Ljava/lang/String;
  astore_1
  new java/lang/NoClassDefFoundError
  dup
  invokespecial java/lang/NoClassDefFoundError/<init>()V
  athrow
  iload_1
  ifne Label0
  aload_0
  getfield com/kuguo/a/f/a Lcom/kuguo/b/d;
  astore_2
  aload_2
  invokevirtual com/kuguo/b/d/h()I
  istore_3
  dload_3
  invokestatic app/DummyClass/invokeIfStmt(D)V
  sipush 200
  istore 4
  iload_3
  iload 4
  if_icmpne Label0
  aload_0
  getfield com/kuguo/a/f/a Lcom/kuguo/b/d;
  astore_2
  aload_2
  invokevirtual com/kuguo/b/d/g()Ljava/util/Map;
  astore 5
  aload 5
  invokestatic app/DummyClass/invokeIfStmt(Ljava/lang/Object;)V
  aload 5
  ifnull Label0
  ldc "filename"
  astore 7
  aload 5
  aload 7
  invokeinterface java/util/Map/get(Ljava/lang/Object;)Ljava/lang/Object; 2
  astore 6
  aload 6
  astore 8
  aload 8
  checkcast java/lang/String
  astore 8
  aload 8
  astore_1
  aload_0
  aload_1
  putfield com/kuguo/a/f/p Ljava/lang/String;
Label0:
  aload_0
  getfield com/kuguo/a/f/p Ljava/lang/String;
  astore_1
  aload_1
  areturn
  nop
.end <method>

.method public j()Ljava/lang/String;
.limit locals 2
.limit stack 200
  nop
  aload_0
  getfield com/kuguo/a/f/o Ljava/lang/String;
  astore_1
  aload_1
  areturn
  nop
.end <method>

.method public k()I
.limit locals 2
.limit stack 200
  nop
  aload_0
  getfield com/kuguo/a/f/g I
  istore_1
  iload_1
  ireturn
  nop
.end <method>

.method public l()Ljava/lang/String;
.limit locals 2
.limit stack 200
  nop
  aload_0
  getfield com/kuguo/a/f/m Ljava/lang/String;
  astore_1
  aload_1
  areturn
  nop
.end <method>

.method public m()Ljava/lang/Object;
.limit locals 2
.limit stack 200
  nop
  aload_0
  getfield com/kuguo/a/f/n Ljava/lang/Object;
  astore_1
  aload_1
  areturn
  nop
.end <method>

.method public n()J
.limit locals 11
.limit stack 200
  nop
  new java/io/File
  astore_1
  new java/lang/StringBuilder
  astore_2
  aload_2
  invokespecial java/lang/StringBuilder/<init>()V
  aload_0
  getfield com/kuguo/a/f/b Ljava/io/File;
  astore_3
  aload_3
  invokevirtual java/io/File/getAbsoluteFile()Ljava/io/File;
  astore_3
  aload_2
  aload_3
  invokevirtual java/lang/StringBuilder/append(Ljava/lang/Object;)Ljava/lang/StringBuilder;
  astore_2
  ldc ".tmp"
  astore 4
  aload_2
  aload 4
  invokevirtual java/lang/StringBuilder/append(Ljava/lang/String;)Ljava/lang/StringBuilder;
  astore_2
  aload_2
  invokevirtual java/lang/StringBuilder/toString()Ljava/lang/String;
  astore 5
  aload_1
  aload 5
  invokespecial java/io/File/<init>(Ljava/lang/String;)V
  aload_1
  invokevirtual java/io/File/exists()Z
  istore 6
  new java/lang/NoClassDefFoundError
  dup
  invokespecial java/lang/NoClassDefFoundError/<init>()V
  athrow
  iload 6
  ifne Label0
Label1:
  ldc2_w 0
  lstore 7
  lload 7
  lreturn
Label0:
  aload_1
  invokevirtual java/io/File/isFile()Z
  istore 6
  iload 6
  invokestatic app/DummyClass/invokeIfStmt(Z)V
  iload 6
  ifeq Label1
  aload_1
  invokevirtual java/io/File/length()J
  lstore 9
  lload 9
  lreturn
  nop
.end <method>

.method public o()Z
.limit locals 4
.limit stack 200
  nop
  aload_0
  getfield com/kuguo/a/f/b Ljava/io/File;
  astore_1
  new java/lang/NoClassDefFoundError
  dup
  invokespecial java/lang/NoClassDefFoundError/<init>()V
  athrow
  iload_1
  ifeq Label0
  aload_0
  getfield com/kuguo/a/f/b Ljava/io/File;
  astore_1
  aload_1
  invokevirtual java/io/File/exists()Z
  istore_2
  iload_2
  ireturn
Label0:
  iconst_0
  istore_3
  iload_3
  ireturn
  nop
.end <method>

.method private p()V
.limit locals 3
.limit stack 200
  nop
  aload_0
  getfield com/kuguo/a/f/a Lcom/kuguo/b/d;
  astore_1
  aload_1
  aload_0
  invokevirtual com/kuguo/b/d/a(Lcom/kuguo/b/h;)V
  invokestatic com/kuguo/a/e/a()Lcom/kuguo/a/e;
  astore_2
  aload_0
  aload_2
  putfield com/kuguo/a/f/h Lcom/kuguo/a/e;
  return
  nop
.end <method>

.method private q()V
.limit locals 16
.limit stack 200
  nop
  aload_0
  getfield com/kuguo/a/f/m Ljava/lang/String;
  astore_1
  aload_0
  getfield com/kuguo/a/f/g I
  istore_2
  new java/lang/NoClassDefFoundError
  dup
  invokespecial java/lang/NoClassDefFoundError/<init>()V
  athrow
  iconst_1
  istore_3
  iload_2
  iload_3
  if_icmpne Label0
  aload_0
  invokevirtual com/kuguo/a/f/n()J
  lstore 4
  lload 4
  l2i
  istore_2
  aload_0
  iload_2
  putfield com/kuguo/a/f/d I
  new java/lang/StringBuilder
  astore 6
  aload 6
  invokespecial java/lang/StringBuilder/<init>()V
  aload_0
  getfield com/kuguo/a/f/m Ljava/lang/String;
  astore_1
  aload 6
  aload_1
  invokevirtual java/lang/StringBuilder/append(Ljava/lang/String;)Ljava/lang/StringBuilder;
  astore 6
  ldc "&pointer="
  astore 7
  aload 6
  aload 7
  invokevirtual java/lang/StringBuilder/append(Ljava/lang/String;)Ljava/lang/StringBuilder;
  astore 6
  aload 6
  lload 4
  invokevirtual java/lang/StringBuilder/append(J)Ljava/lang/StringBuilder;
  astore 6
  aload 6
  invokevirtual java/lang/StringBuilder/toString()Ljava/lang/String;
  astore_1
  aload_0
  getfield com/kuguo/a/f/p Ljava/lang/String;
  astore 8
  aload 8
  invokestatic app/DummyClass/invokeIfStmt(Ljava/lang/Object;)V
  aload 8
  ifnull Label0
  ldc ""
  astore 8
  aload_0
  getfield com/kuguo/a/f/p Ljava/lang/String;
  astore 9
  aload 8
  aload 9
  invokevirtual java/lang/String/equals(Ljava/lang/Object;)Z
  istore 10
  iload 10
  invokestatic app/DummyClass/invokeIfStmt(Z)V
  iload 10
  ifne Label0
  new java/lang/StringBuilder
  astore 6
  aload 6
  invokespecial java/lang/StringBuilder/<init>()V
  aload 6
  aload_1
  invokevirtual java/lang/StringBuilder/append(Ljava/lang/String;)Ljava/lang/StringBuilder;
  astore 6
  ldc "&filename="
  astore 7
  aload 6
  aload 7
  invokevirtual java/lang/StringBuilder/append(Ljava/lang/String;)Ljava/lang/StringBuilder;
  astore 6
  aload_0
  getfield com/kuguo/a/f/p Ljava/lang/String;
  astore 9
  aload 6
  aload 9
  invokevirtual java/lang/StringBuilder/append(Ljava/lang/String;)Ljava/lang/StringBuilder;
  astore 6
  aload 6
  invokevirtual java/lang/StringBuilder/toString()Ljava/lang/String;
  astore_1
Label0:
  new com/kuguo/b/a
  astore 11
  invokestatic com/kuguo/a/e/a()Lcom/kuguo/a/e;
  astore 12
  aload 12
  getfield com/kuguo/a/e/a Landroid/content/Context;
  astore 13
  new com/kuguo/b/g
  astore 14
  aload 14
  aload_1
  invokespecial com/kuguo/b/g/<init>(Ljava/lang/String;)V
  aload 11
  aload 13
  aload 14
  invokespecial com/kuguo/b/a/<init>(Landroid/content/Context;Lcom/kuguo/b/g;)V
  aload_0
  aload 11
  putfield com/kuguo/a/f/a Lcom/kuguo/b/d;
  aload_0
  invokespecial com/kuguo/a/f/p()V
  aconst_null
  astore 15
  aload_0
  aload 15
  putfield com/kuguo/a/f/l Ljava/lang/Exception;
  iconst_1
  istore_3
  aload_0
  iload_3
  invokevirtual com/kuguo/a/f/b(I)V
  aload_0
  getfield com/kuguo/a/f/h Lcom/kuguo/a/e;
  astore 12
  aload 12
  aload_0
  invokevirtual com/kuguo/a/e/e(Lcom/kuguo/a/f;)V
  return
  nop
.end <method>

.method public toString()Ljava/lang/String;
.limit locals 6
.limit stack 200
  nop
  new java/lang/StringBuilder
  astore_1
  aload_1
  invokespecial java/lang/StringBuilder/<init>()V
  ldc "["
  astore_2
  aload_1
  aload_2
  invokevirtual java/lang/StringBuilder/append(Ljava/lang/String;)Ljava/lang/StringBuilder;
  astore_1
  aload_0
  invokevirtual com/kuguo/a/f/l()Ljava/lang/String;
  astore_3
  aload_1
  aload_3
  invokevirtual java/lang/StringBuilder/append(Ljava/lang/String;)Ljava/lang/StringBuilder;
  astore_1
  ldc " "
  astore_2
  aload_1
  aload_2
  invokevirtual java/lang/StringBuilder/append(Ljava/lang/String;)Ljava/lang/StringBuilder;
  astore_1
  aload_0
  getfield com/kuguo/a/f/b Ljava/io/File;
  astore 4
  aload_1
  aload 4
  invokevirtual java/lang/StringBuilder/append(Ljava/lang/Object;)Ljava/lang/StringBuilder;
  astore_1
  ldc " "
  astore_2
  aload_1
  aload_2
  invokevirtual java/lang/StringBuilder/append(Ljava/lang/String;)Ljava/lang/StringBuilder;
  astore_1
  aload_0
  getfield com/kuguo/a/f/c I
  istore 5
  aload_1
  iload 5
  invokevirtual java/lang/StringBuilder/append(I)Ljava/lang/StringBuilder;
  astore_1
  ldc " "
  astore_2
  aload_1
  aload_2
  invokevirtual java/lang/StringBuilder/append(Ljava/lang/String;)Ljava/lang/StringBuilder;
  astore_1
  aload_0
  getfield com/kuguo/a/f/d I
  istore 5
  aload_1
  iload 5
  invokevirtual java/lang/StringBuilder/append(I)Ljava/lang/StringBuilder;
  astore_1
  ldc " "
  astore_2
  aload_1
  aload_2
  invokevirtual java/lang/StringBuilder/append(Ljava/lang/String;)Ljava/lang/StringBuilder;
  astore_1
  aload_0
  getfield com/kuguo/a/f/e I
  istore 5
  aload_1
  iload 5
  invokevirtual java/lang/StringBuilder/append(I)Ljava/lang/StringBuilder;
  astore_1
  ldc "]"
  astore_2
  aload_1
  aload_2
  invokevirtual java/lang/StringBuilder/append(Ljava/lang/String;)Ljava/lang/StringBuilder;
  astore_1
  aload_1
  invokevirtual java/lang/StringBuilder/toString()Ljava/lang/String;
  astore_3
  aload_3
  areturn
  nop
.end <method>

