.source SourceFile
.class public final  com/adwo/adsdk/FSAdUtil
.super java/lang/Object
.field private static "B" Z =  0
.field private static final "C" Lcom/adwo/adsdk/FSAdUtil;
.field private static "D" [B
.field private static "F" I =  0
.field private static "a" Landroid/telephony/TelephonyManager;
.field private static "b" Z =  0
.field private static "c" [B
.field private static "d" [B
.field private static "e" Ljava/lang/String;
.field private static "g" I =  0
.field private static "h" I =  0
.field private static "i" I =  0
.field private static "j" I =  0
.field private static volatile "k" I =  0
.field private static "n" B =  0
.field private static "o" B =  0
.field private static "p" [B
.field private static "q" [B
.field private static "r" B =  0
.field private static "s" S =  0
.field private static "t" [B
.field private static "u" B =  0
.field private static "v" B =  0
.field private static "w" B =  0
.field private static "y" Ljava/util/Set;
.field private "A" B
.field private "E" Ljava/lang/String;
.field private "f" Ljava/lang/String;
.field private "l" Ljava/lang/String;
.field private "m" Landroid/content/Context;
.field private "x" Ljava/lang/String;
.field private "z" Lcom/adwo/adsdk/SplashAdListener;

.method static <clinit>()V
.limit locals 7
.limit stack 200
  nop
  iconst_0
  istore_0
  iload_0
  putstatic com/adwo/adsdk/FSAdUtil/b Z
  aconst_null
  astore_1
  aload_1
  putstatic com/adwo/adsdk/FSAdUtil/c [B
  aconst_null
  astore_1
  aload_1
  putstatic com/adwo/adsdk/FSAdUtil/d [B
  aconst_null
  astore_1
  aload_1
  putstatic com/adwo/adsdk/FSAdUtil/e Ljava/lang/String;
  iconst_1
  istore_0
  iload_0
  istore_2
  iload_2
  putstatic com/adwo/adsdk/FSAdUtil/g I
  iconst_2
  istore_0
  iload_0
  putstatic com/adwo/adsdk/FSAdUtil/h I
  iconst_3
  istore_0
  iload_0
  putstatic com/adwo/adsdk/FSAdUtil/i I
  iconst_4
  istore_0
  iload_0
  putstatic com/adwo/adsdk/FSAdUtil/j I
  iconst_1
  istore_0
  iload_0
  istore_2
  iload_2
  putstatic com/adwo/adsdk/FSAdUtil/k I
  iconst_0
  istore_0
  iload_0
  i2b
  istore_3
  iload_3
  putstatic com/adwo/adsdk/FSAdUtil/n B
  iconst_0
  istore_0
  iload_0
  i2b
  istore_3
  iload_3
  putstatic com/adwo/adsdk/FSAdUtil/o B
  aconst_null
  astore_1
  aload_1
  putstatic com/adwo/adsdk/FSAdUtil/p [B
  aconst_null
  astore_1
  aload_1
  putstatic com/adwo/adsdk/FSAdUtil/q [B
  iconst_0
  istore_0
  iload_0
  i2b
  istore_3
  iload_3
  putstatic com/adwo/adsdk/FSAdUtil/r B
  iconst_0
  istore_0
  iload_0
  i2s
  istore 4
  iload 4
  putstatic com/adwo/adsdk/FSAdUtil/s S
  aconst_null
  astore_1
  aload_1
  putstatic com/adwo/adsdk/FSAdUtil/t [B
  iconst_2
  istore_0
  iload_0
  putstatic com/adwo/adsdk/FSAdUtil/u B
  iconst_5
  istore_0
  iload_0
  putstatic com/adwo/adsdk/FSAdUtil/v B
  bipush 50
  istore_0
  iload_0
  putstatic com/adwo/adsdk/FSAdUtil/w B
  new java/util/HashSet
  astore 5
  aload 5
  invokespecial java/util/HashSet/<init>()V
  aload 5
  putstatic com/adwo/adsdk/FSAdUtil/y Ljava/util/Set;
  iconst_1
  istore_0
  iload_0
  putstatic com/adwo/adsdk/FSAdUtil/B Z
  new com/adwo/adsdk/FSAdUtil
  astore 6
  aload 6
  invokespecial com/adwo/adsdk/FSAdUtil/<init>()V
  aload 6
  putstatic com/adwo/adsdk/FSAdUtil/C Lcom/adwo/adsdk/FSAdUtil;
  aconst_null
  astore_1
  aload_1
  putstatic com/adwo/adsdk/FSAdUtil/D [B
  iconst_0
  istore_0
  iload_0
  istore_2
  iload_2
  putstatic com/adwo/adsdk/FSAdUtil/F I
  return
  nop
.end <method>

.method public <init>()V
.limit locals 3
.limit stack 200
  nop
  aload_0
  invokespecial java/lang/Object/<init>()V
  aconst_null
  astore_1
  aload_0
  aload_1
  putfield com/adwo/adsdk/FSAdUtil/l Ljava/lang/String;
  aconst_null
  astore_1
  aload_0
  aload_1
  putfield com/adwo/adsdk/FSAdUtil/m Landroid/content/Context;
  ldc ""
  astore_2
  aload_0
  aload_2
  putfield com/adwo/adsdk/FSAdUtil/x Ljava/lang/String;
  aconst_null
  astore_1
  aload_0
  aload_1
  putfield com/adwo/adsdk/FSAdUtil/E Ljava/lang/String;
  return
  nop
.end <method>

.method protected static a(Landroid/content/Context;BB)Lcom/adwo/adsdk/FSAd;
.limit locals 101
.limit stack 200
  .catch  java/lang/Throwable <from> Label25 <to> Label26 <using> Label24
  .catch  java/lang/Throwable <from> Label36 <to> Label4 <using> Label24
  .catch  java/lang/Throwable <from> Label1 <to> Label37 <using> Label24
  .catch  java/lang/Throwable <from> Label57 <to> Label58 <using> Label24
  .catch  java/lang/Throwable <from> Label63 <to> Label64 <using> Label24
  .catch  java/lang/Throwable <from> Label67 <to> Label21 <using> Label24
  .catch  java/lang/Throwable <from> Label21 <to> Label24 <using> Label24
  nop
  ldc com/adwo/adsdk/FSAdUtil
  astore 31
  aload 31
  monitorenter
Label25:
  ldc "android.permission.INTERNET"
  astore 33
  aload_0
  astore_3
  aload 33
  astore 4
  new java/lang/NoClassDefFoundError
  dup
  invokespecial java/lang/NoClassDefFoundError/<init>()V
  athrow
  nop
  dload 32
  dstore_3
  dload_3
  invokestatic app/DummyClass/invokeIfStmt(D)V
  iconst_m1
  istore 34
  iload 32
  istore_3
  iload 34
  istore 4
  iload_3
  iload 4
  if_icmpne Label0
  ldc "Adwo SDK"
  astore 33
  ldc "Cannot request an ad without INTERNET permissions!  Open manifest.xml and just before the final </manifest> tag add:  <uses-permission android:name=\"android.permission.INTERNET\" />"
  astore 35
  aload 33
  astore_3
  aload 35
  astore 4
  aload_3
  aload 4
  invokestatic android/util/Log/e(Ljava/lang/String;Ljava/lang/String;)I
  pop
Label0:
  getstatic com/adwo/adsdk/FSAdUtil/y Ljava/util/Set;
  astore 36
  aload 36
  astore_3
  aload_3
  invokeinterface java/util/Set/size()I 1
  istore 32
  iload 32
  istore_3
  iload_3
  i2s
  istore_3
  iload_3
  istore 37
  iload_3
  anewarray java/lang/Integer
  astore_3
  aload_3
  astore 38
  getstatic com/adwo/adsdk/FSAdUtil/y Ljava/util/Set;
  astore 36
  aload 36
  astore_3
  aload_3
  invokeinterface java/util/Set/iterator()Ljava/util/Iterator; 1
  astore 39
  iconst_0
  istore 32
Label5:
  aload 39
  astore_3
  aload_3
  invokeinterface java/util/Iterator/hasNext()Z 1
  istore 40
  iload 40
  istore_3
  iload_3
  invokestatic app/DummyClass/invokeIfStmt(Z)V
  iload 40
  ifne Label1
  getstatic com/adwo/adsdk/FSAdUtil/v B
  istore 41
  getstatic com/adwo/adsdk/FSAdUtil/w B
  istore 42
  getstatic com/adwo/adsdk/FSAdUtil/r B
  istore 43
  getstatic com/adwo/adsdk/FSAdUtil/u B
  istore 44
  getstatic com/adwo/adsdk/FSAdUtil/c [B
  astore 45
  getstatic com/adwo/adsdk/FSAdUtil/d [B
  astore 46
  getstatic com/adwo/adsdk/FSAdUtil/p [B
  astore 47
  getstatic com/adwo/adsdk/FSAdUtil/q [B
  astore 48
  getstatic com/adwo/adsdk/FSAdUtil/F I
  istore 32
  iload 32
  istore_3
  iload_3
  i2s
  istore_3
  iload_3
  istore 49
  getstatic com/adwo/adsdk/FSAdUtil/n B
  istore 50
  getstatic com/adwo/adsdk/FSAdUtil/o B
  istore 51
  getstatic com/adwo/adsdk/FSAdUtil/D [B
  astore 52
  getstatic com/adwo/adsdk/FSAdUtil/t [B
  astore 53
  getstatic com/adwo/adsdk/FSAdUtil/s S
  istore 54
  iconst_0
  istore 34
  iconst_0
  istore 55
  iconst_0
  istore 56
  iconst_0
  istore 57
  iconst_0
  istore 58
  ldc2_w 0.000000000000000
  dstore 59
  ldc2_w 0.000000000000000
  dstore 61
  iconst_0
  istore 63
  iload 41
  istore_3
  iload 42
  istore 4
  iload 43
  istore 5
  iload_1
  istore 6
  iload 44
  istore 7
  iload 34
  istore 8
  aload 45
  astore 9
  iload_2
  istore 10
  iload 55
  istore 11
  aload 46
  astore 12
  aload 47
  astore 13
  aload 48
  astore 14
  iload 56
  istore 15
  iload 57
  istore 16
  iload 49
  istore 17
  iload 50
  istore 18
  iload 51
  istore 19
  aload 52
  astore 20
  aload 53
  astore 21
  iload 58
  istore 22
  dload 59
  dstore 23
  dload 61
  dstore 25
  iload 63
  istore 27
  iload 37
  istore 28
  aload 38
  astore 29
  iload 54
  istore 30
  iload_3
  iload 4
  iload 5
  iload 6
  iload 7
  iload 8
  aload 9
  iload 10
  iload 11
  aload 12
  aload 13
  aload 14
  iload 15
  iload 16
  iload 17
  iload 18
  iload 19
  aload 20
  aload 21
  iload 22
  dload 23
  dload 25
  iload 27
  iload 28
  aload 29
  iload 30
  invokestatic com/adwo/adsdk/X/a(BBBBBZ[BBS[B[B[BSSSBB[B[BZDDBS[Ljava/lang/Integer;S)[B
  astore 53
  aconst_null
  astore 64
  aconst_null
  astore 65
  aconst_null
  astore 66
  getstatic com/adwo/adsdk/FSAdUtil/g I
  istore 32
  iload 32
  putstatic com/adwo/adsdk/FSAdUtil/k I
Label26:
  getstatic com/adwo/adsdk/FSAdUtil/k I
  istore 32
  getstatic com/adwo/adsdk/FSAdUtil/g I
  istore 67
  iload 32
  istore_3
  dload_3
  invokestatic app/DummyClass/invokeIfStmt(D)V
  iload 67
  istore_3
  dload_3
  invokestatic app/DummyClass/invokeIfStmt(D)V
  iload 32
  istore_3
  iload 67
  istore 4
  iload_3
  iload 4
  if_icmpne Label2
  new java/net/URL
  astore 68
  new java/lang/String
  astore 69
  getstatic com/adwo/adsdk/Y/e [B
  astore 52
Label29:
  ldc "UTF-8"
  astore 33
  aload 69
  astore_3
  aload 52
  astore 4
  aload 33
  astore 5
  aload_3
  aload 4
  aload 5
  invokespecial java/lang/String/<init>([BLjava/lang/String;)V
  aload 68
  astore_3
  aload 69
  astore 4
  aload_3
  aload 4
  invokespecial java/net/URL/<init>(Ljava/lang/String;)V
  aload 68
  astore_3
  aload_3
  invokevirtual java/net/URL/openConnection()Ljava/net/URLConnection;
  astore 70
  aload 70
  astore 72
  aload 72
  checkcast java/net/HttpURLConnection
  astore 72
  aload 72
  astore 71
Label30:
  getstatic com/adwo/adsdk/Y/a I
  istore 67
Label33:
  aload 71
  astore_3
  iload 67
  istore 4
  aload_3
  iload 4
  invokevirtual java/net/HttpURLConnection/setConnectTimeout(I)V
  getstatic com/adwo/adsdk/Y/a I
  istore 67
  aload 71
  astore_3
  iload 67
  istore 4
  aload_3
  iload 4
  invokevirtual java/net/HttpURLConnection/setReadTimeout(I)V
Label34:
  aload 71
  astore 66
Label8:
  aload 66
  astore_3
  aload_3
  invokestatic app/DummyClass/invokeIfStmt(Ljava/lang/Object;)V
  aload 66
  ifnonnull Label3
  aload 66
  astore_3
  aload_3
  invokestatic app/DummyClass/invokeIfStmt(Ljava/lang/Object;)V
  aload 66
  ifnull Label4
Label36:
  aload 66
  astore_3
  aload_3
  invokevirtual java/net/HttpURLConnection/disconnect()V
Label4:
  aconst_null
  astore 73
Label14:
  ldc com/adwo/adsdk/FSAdUtil
  astore 31
  aload 31
  monitorexit
  aload 73
  areturn
Label1:
  aload 39
  astore_3
  aload_3
  invokeinterface java/util/Iterator/next()Ljava/lang/Object; 1
  astore 74
  aload 74
  astore 76
  aload 76
  checkcast java/lang/Integer
  astore 76
  aload 76
  astore 75
  aload 75
  astore_3
  aload_3
  invokevirtual java/lang/Integer/intValue()I
  istore 67
  iload 67
  istore_3
  iload_3
  invokestatic java/lang/Integer/valueOf(I)Ljava/lang/Integer;
  astore 75
  aload 38
  iload 32
  aload 75
  aastore
Label37:
  iload 32
  iconst_1
  iadd
  istore 32
  goto Label5
Label2:
  getstatic com/adwo/adsdk/FSAdUtil/k I
  istore 67
  getstatic com/adwo/adsdk/FSAdUtil/h I
  istore 32
  iload 67
  istore_3
  dload_3
  invokestatic app/DummyClass/invokeIfStmt(D)V
  iload 32
  istore_3
  dload_3
  invokestatic app/DummyClass/invokeIfStmt(D)V
  iload 67
  istore_3
  iload 32
  istore 4
  iload_3
  iload 4
  if_icmpeq Label6
  getstatic com/adwo/adsdk/FSAdUtil/k I
  istore 67
  getstatic com/adwo/adsdk/FSAdUtil/i I
  istore 32
  iload 67
  istore_3
  dload_3
  invokestatic app/DummyClass/invokeIfStmt(D)V
  iload 32
  istore_3
  dload_3
  invokestatic app/DummyClass/invokeIfStmt(D)V
  iload 67
  istore_3
  iload 32
  istore 4
  iload_3
  iload 4
  if_icmpne Label7
Label6:
  new java/net/URL
  astore 68
  new java/lang/String
  astore 69
  getstatic com/adwo/adsdk/Y/i [B
  astore 52
Label38:
  ldc "utf-8"
  astore 33
  aload 69
  astore_3
  aload 52
  astore 4
  aload 33
  astore 5
  aload_3
  aload 4
  aload 5
  invokespecial java/lang/String/<init>([BLjava/lang/String;)V
  aload 68
  astore_3
  aload 69
  astore 4
  aload_3
  aload 4
  invokespecial java/net/URL/<init>(Ljava/lang/String;)V
  aload 68
  astore_3
  aload_3
  invokevirtual java/net/URL/openConnection()Ljava/net/URLConnection;
  astore 70
  aload 70
  astore 77
  aload 77
  checkcast java/net/HttpURLConnection
  astore 77
  aload 77
  astore 71
Label39:
  new java/lang/String
  astore 78
  getstatic com/adwo/adsdk/Y/g [B
  astore 52
Label40:
  ldc "utf-8"
  astore 33
  aload 78
  astore_3
  aload 52
  astore 4
  aload 33
  astore 5
  aload_3
  aload 4
  aload 5
  invokespecial java/lang/String/<init>([BLjava/lang/String;)V
  ldc "X-Online-Host"
  astore 33
  aload 71
  astore_3
  aload 33
  astore 4
  aload 78
  astore 5
  aload_3
  aload 4
  aload 5
  invokevirtual java/net/HttpURLConnection/setRequestProperty(Ljava/lang/String;Ljava/lang/String;)V
  getstatic com/adwo/adsdk/Y/a I
  istore 67
  iload 67
  iconst_2
  imul
  istore 67
  aload 71
  astore_3
  iload 67
  istore 4
  aload_3
  iload 4
  invokevirtual java/net/HttpURLConnection/setConnectTimeout(I)V
  getstatic com/adwo/adsdk/Y/a I
  istore 67
  iload 67
  iconst_2
  imul
  istore 67
  aload 71
  astore_3
  iload 67
  istore 4
  aload_3
  iload 4
  invokevirtual java/net/HttpURLConnection/setReadTimeout(I)V
Label41:
  aload 71
  astore 66
  goto Label8
Label7:
  getstatic com/adwo/adsdk/FSAdUtil/k I
  istore 67
  getstatic com/adwo/adsdk/FSAdUtil/j I
  istore 32
  iload 67
  istore_3
  dload_3
  invokestatic app/DummyClass/invokeIfStmt(D)V
  iload 32
  istore_3
  dload_3
  invokestatic app/DummyClass/invokeIfStmt(D)V
  iload 67
  istore_3
  iload 32
  istore 4
  iload_3
  iload 4
  if_icmpne Label8
  new java/net/URL
  astore 68
  new java/lang/String
  astore 79
  getstatic com/adwo/adsdk/Y/e [B
  astore 52
Label42:
  ldc "UTF-8"
  astore 33
  aload 79
  astore_3
  aload 52
  astore 4
  aload 33
  astore 5
  aload_3
  aload 4
  aload 5
  invokespecial java/lang/String/<init>([BLjava/lang/String;)V
  aload 68
  astore_3
  aload 79
  astore 4
  aload_3
  aload 4
  invokespecial java/net/URL/<init>(Ljava/lang/String;)V
  new java/net/Proxy
  astore 80
  getstatic java/net/Proxy$Type/HTTP Ljava/net/Proxy$Type;
  astore 81
  new java/net/InetSocketAddress
  astore 82
  new java/lang/String
  astore 79
  getstatic com/adwo/adsdk/Y/j [B
  astore 52
  ldc "utf-8"
  astore 33
  aload 79
  astore_3
  aload 52
  astore 4
  aload 33
  astore 5
  aload_3
  aload 4
  aload 5
  invokespecial java/lang/String/<init>([BLjava/lang/String;)V
  bipush 80
  istore 34
  aload 82
  astore_3
  aload 79
  astore 4
  iload 34
  istore 5
  aload_3
  aload 4
  iload 5
  invokespecial java/net/InetSocketAddress/<init>(Ljava/lang/String;I)V
  aload 80
  astore_3
  aload 81
  astore 4
  aload 82
  astore 5
  aload_3
  aload 4
  aload 5
  invokespecial java/net/Proxy/<init>(Ljava/net/Proxy$Type;Ljava/net/SocketAddress;)V
  aload 68
  astore_3
  aload 80
  astore 4
  aload_3
  aload 4
  invokevirtual java/net/URL/openConnection(Ljava/net/Proxy;)Ljava/net/URLConnection;
  astore 70
  aload 70
  astore 83
  aload 83
  checkcast java/net/HttpURLConnection
  astore 83
  aload 83
  astore 71
Label43:
  getstatic com/adwo/adsdk/Y/a I
  istore 67
  iload 67
  iconst_2
  imul
  istore 67
Label44:
  aload 71
  astore_3
  iload 67
  istore 4
  aload_3
  iload 4
  invokevirtual java/net/HttpURLConnection/setConnectTimeout(I)V
  getstatic com/adwo/adsdk/Y/a I
  istore 67
  iload 67
  iconst_2
  imul
  istore 67
  aload 71
  astore_3
  iload 67
  istore 4
  aload_3
  iload 4
  invokevirtual java/net/HttpURLConnection/setReadTimeout(I)V
Label45:
  aload 71
  astore 66
  goto Label8
Label3:
  ldc "POST"
  astore 33
  aload 66
  astore_3
  aload 33
  astore 4
  aload_3
  aload 4
  invokevirtual java/net/HttpURLConnection/setRequestMethod(Ljava/lang/String;)V
  iconst_1
  istore 34
  aload 66
  astore_3
  iload 34
  istore 4
  aload_3
  iload 4
  invokevirtual java/net/HttpURLConnection/setDoOutput(Z)V
  ldc "Content-Type"
  astore 33
  ldc "application/x-www-form-urlencoded"
  astore 35
  aload 66
  astore_3
  aload 33
  astore 4
  aload 35
  astore 5
  aload_3
  aload 4
  aload 5
  invokevirtual java/net/HttpURLConnection/setRequestProperty(Ljava/lang/String;Ljava/lang/String;)V
  aload 53
  astore_3
  aload_3
  arraylength
  istore_3
  iload_3
  istore 67
  iload_3
  invokestatic java/lang/Integer/toString(I)Ljava/lang/String;
  astore 69
  ldc "Content-Length"
  astore 33
  aload 66
  astore_3
  aload 33
  astore 4
  aload 69
  astore 5
  aload_3
  aload 4
  aload 5
  invokevirtual java/net/HttpURLConnection/setRequestProperty(Ljava/lang/String;Ljava/lang/String;)V
  aload 66
  astore_3
  aload_3
  invokevirtual java/net/HttpURLConnection/getOutputStream()Ljava/io/OutputStream;
  astore 84
Label47:
  aload 84
  astore 64
Label49:
  aload 84
  astore_3
  aload 53
  astore 4
  aload_3
  aload 4
  invokevirtual java/io/OutputStream/write([B)V
  aload 66
  astore_3
  aload_3
  invokevirtual java/net/HttpURLConnection/getInputStream()Ljava/io/InputStream;
  astore 85
Label50:
  aload 85
  astore 65
  new java/io/ByteArrayOutputStream
  astore 86
Label52:
  aload 86
  astore_3
  aload_3
  invokespecial java/io/ByteArrayOutputStream/<init>()V
Label15:
  aload 65
  astore_3
  aload_3
  invokevirtual java/io/InputStream/read()I
  istore 67
  iload 67
  istore_3
  dload_3
  invokestatic app/DummyClass/invokeIfStmt(D)V
  iconst_m1
  istore 34
  iload 67
  istore_3
  iload 34
  istore 4
  iload_3
  iload 4
  if_icmpne Label9
  aload 86
  astore_3
  aload_3
  invokevirtual java/io/ByteArrayOutputStream/toByteArray()[B
  astore 53
  aload 53
  astore_3
  aload_3
  arraylength
  istore_3
  iload_3
  istore 67
  dload_3
  invokestatic app/DummyClass/invokeIfStmt(D)V
  iload 67
  ifle Label10
  aload 53
  astore_3
  aload_3
  invokestatic com/adwo/adsdk/FSAd/a([B)Lcom/adwo/adsdk/FSAd;
  astore 73
Label53:
  aload 73
  astore_3
  aload_3
  invokevirtual com/adwo/adsdk/FSAd/getError()Lcom/adwo/adsdk/ErrorCode;
  astore 87
Label55:
  aload 87
  astore_3
  aload_3
  invokestatic app/DummyClass/invokeIfStmt(Ljava/lang/Object;)V
  aload 87
  ifnonnull Label11
  getstatic com/adwo/adsdk/FSAdUtil/s S
  istore 54
  iload 54
  iconst_1
  iadd
  istore 67
  iload 67
  istore_3
  iload_3
  i2s
  istore_3
  iload_3
  istore 54
  iload 54
  putstatic com/adwo/adsdk/FSAdUtil/s S
Label18:
  aload 64
  astore_3
  aload_3
  invokestatic app/DummyClass/invokeIfStmt(Ljava/lang/Object;)V
  aload 64
  ifnull Label12
Label57:
  aload 64
  astore_3
  aload_3
  invokevirtual java/io/OutputStream/close()V
Label12:
  aload 65
  astore_3
  aload_3
  invokestatic app/DummyClass/invokeIfStmt(Ljava/lang/Object;)V
  aload 65
  ifnull Label13
  aload 65
  astore_3
  aload_3
  invokevirtual java/io/InputStream/close()V
Label13:
  aload 66
  astore_3
  aload_3
  invokestatic app/DummyClass/invokeIfStmt(Ljava/lang/Object;)V
  aload 66
  ifnull Label14
  aload 66
  astore_3
  aload_3
  invokevirtual java/net/HttpURLConnection/disconnect()V
Label58:
  goto Label14
Label56:
  astore 88
  goto Label14
Label9:
  aload 86
  astore_3
  iload 67
  istore 4
  aload_3
  iload 4
  invokevirtual java/io/ByteArrayOutputStream/write(I)V
Label59:
  goto Label15
Label51:
  astore 89
  aload 64
  astore 84
  aload 65
  astore 85
  aload 66
  astore 71
  aload 89
  astore 90
  aconst_null
  astore 73
Label23:
  aload 90
  astore_3
  aload_3
  invokevirtual java/lang/Exception/printStackTrace()V
  ldc "Adwo SDK"
  astore 33
  ldc "Could not get ad from Adwo servers,Network Error!"
  astore 35
  aload 33
  astore_3
  aload 35
  astore 4
  aload_3
  aload 4
  invokestatic android/util/Log/w(Ljava/lang/String;Ljava/lang/String;)I
  pop
Label61:
  aload 84
  astore_3
  aload_3
  invokestatic app/DummyClass/invokeIfStmt(Ljava/lang/Object;)V
  aload 84
  ifnull Label16
Label63:
  aload 84
  astore_3
  aload_3
  invokevirtual java/io/OutputStream/close()V
Label16:
  aload 85
  astore_3
  aload_3
  invokestatic app/DummyClass/invokeIfStmt(Ljava/lang/Object;)V
  aload 85
  ifnull Label17
  aload 85
  astore_3
  aload_3
  invokevirtual java/io/InputStream/close()V
Label17:
  aload 71
  astore_3
  aload_3
  invokestatic app/DummyClass/invokeIfStmt(Ljava/lang/Object;)V
  aload 71
  ifnull Label14
  aload 71
  astore_3
  aload_3
  invokevirtual java/net/HttpURLConnection/disconnect()V
Label64:
  goto Label14
Label62:
  astore 91
  goto Label14
Label10:
  ldc "Adwo SDK"
  astore 33
  ldc "Could not get ad from Adwo servers."
  astore 35
  aload 33
  astore_3
  aload 35
  astore 4
  aload_3
  aload 4
  invokestatic android/util/Log/w(Ljava/lang/String;Ljava/lang/String;)I
  pop
Label65:
  aconst_null
  astore 73
  goto Label18
Label27:
  astore 92
Label22:
  aload 64
  astore_3
  aload_3
  invokestatic app/DummyClass/invokeIfStmt(Ljava/lang/Object;)V
  aload 64
  ifnull Label19
Label67:
  aload 64
  astore_3
  aload_3
  invokevirtual java/io/OutputStream/close()V
Label19:
  aload 65
  astore_3
  aload_3
  invokestatic app/DummyClass/invokeIfStmt(Ljava/lang/Object;)V
  aload 65
  ifnull Label20
  aload 65
  astore_3
  aload_3
  invokevirtual java/io/InputStream/close()V
Label20:
  aload 66
  astore_3
  aload_3
  invokestatic app/DummyClass/invokeIfStmt(Ljava/lang/Object;)V
  aload 66
  ifnull Label21
  aload 66
  astore_3
  aload_3
  invokevirtual java/net/HttpURLConnection/disconnect()V
Label21:
  aload 92
  athrow
Label24:
  astore 93
  ldc com/adwo/adsdk/FSAdUtil
  astore 31
  aload 31
  monitorexit
  aload 93
  athrow
Label35:
  astore 94
  goto Label4
Label66:
  astore 95
  goto Label21
Label31:
  astore 96
  aload 71
  astore 66
  aload 96
  astore 92
  goto Label22
Label60:
  astore 92
  aload 71
  astore 66
  aload 85
  astore 65
  aload 84
  astore 64
  goto Label22
Label28:
  astore 97
  aconst_null
  astore 84
  aconst_null
  astore 85
  aconst_null
  astore 71
  aload 97
  astore 90
  aconst_null
  astore 73
  goto Label23
Label32:
  astore 90
  aconst_null
  astore 84
  aconst_null
  astore 85
  aconst_null
  astore 73
  goto Label23
Label46:
  astore 98
  aconst_null
  astore 84
  aconst_null
  astore 85
  aload 66
  astore 71
  aload 98
  astore 90
  aconst_null
  astore 73
  goto Label23
Label48:
  astore 99
  aload 64
  astore 84
  aconst_null
  astore 85
  aload 66
  astore 71
  aload 99
  astore 90
  aconst_null
  astore 73
  goto Label23
Label54:
  astore 100
  aload 64
  astore 84
  aload 65
  astore 85
  aload 66
  astore 71
  aload 100
  astore 90
  goto Label23
Label11:
  goto Label18
  nop
.end <method>

.method static a(Lcom/adwo/adsdk/FSAdUtil;)Lcom/adwo/adsdk/SplashAdListener;
  .synthetic
.limit locals 2
.limit stack 200
  nop
  aload_0
  getfield com/adwo/adsdk/FSAdUtil/z Lcom/adwo/adsdk/SplashAdListener;
  astore_1
  aload_1
  areturn
  nop
.end <method>

.method protected static a()Z
.limit locals 1
.limit stack 200
  nop
  getstatic com/adwo/adsdk/FSAdUtil/B Z
  istore_0
  iload_0
  ireturn
  nop
.end <method>

.method private static a(Landroid/content/Context;)[B
.limit locals 16
.limit stack 200
  nop
  ldc "android.permission.READ_PHONE_STATE"
  astore_2
  new java/lang/NoClassDefFoundError
  dup
  invokespecial java/lang/NoClassDefFoundError/<init>()V
  athrow
  nop
  dload_1
  invokestatic app/DummyClass/invokeIfStmt(D)V
  iconst_m1
  istore_3
  iload_1
  iload_3
  if_icmpne Label0
  ldc "Adwo SDK"
  astore_2
  ldc "Cannot request an ad without READ_PHONE_STATE permissions!  Open manifest.xml and just before the final </manifest> tag add:  <uses-permission android:name=\"android.permission.READ_PHONE_STATE\" />"
  astore 4
  aload_2
  aload 4
  invokestatic android/util/Log/e(Ljava/lang/String;Ljava/lang/String;)I
  pop
Label0:
  aconst_null
  astore 5
  getstatic com/adwo/adsdk/FSAdUtil/e Ljava/lang/String;
  astore 6
  aload 6
  invokestatic app/DummyClass/invokeIfStmt(Ljava/lang/Object;)V
  aload 6
  ifnonnull Label1
  getstatic com/adwo/adsdk/FSAdUtil/a Landroid/telephony/TelephonyManager;
  astore 7
  aload 7
  invokestatic app/DummyClass/invokeIfStmt(Ljava/lang/Object;)V
  aload 7
  ifnull Label1
  getstatic com/adwo/adsdk/FSAdUtil/a Landroid/telephony/TelephonyManager;
  astore 7
  aload 7
  invokevirtual android/telephony/TelephonyManager/getDeviceId()Ljava/lang/String;
  astore 5
Label1:
  aload_0
  invokevirtual android/content/Context/getContentResolver()Landroid/content/ContentResolver;
  astore 8
  ldc "android_id"
  astore_2
  aload 8
  aload_2
  invokestatic android/provider/Settings$System/getString(Landroid/content/ContentResolver;Ljava/lang/String;)Ljava/lang/String;
  astore 6
  aload 5
  invokestatic app/DummyClass/invokeIfStmt(Ljava/lang/Object;)V
  aload 5
  ifnull Label2
  new java/lang/StringBuilder
  astore 9
  aload 5
  invokestatic java/lang/String/valueOf(Ljava/lang/Object;)Ljava/lang/String;
  astore 5
  aload 9
  aload 5
  invokespecial java/lang/StringBuilder/<init>(Ljava/lang/String;)V
  ldc "|"
  astore_2
  aload 9
  aload_2
  invokevirtual java/lang/StringBuilder/append(Ljava/lang/String;)Ljava/lang/StringBuilder;
  astore 9
  aload 9
  aload 6
  invokevirtual java/lang/StringBuilder/append(Ljava/lang/String;)Ljava/lang/StringBuilder;
  astore 9
  aload 9
  invokevirtual java/lang/StringBuilder/toString()Ljava/lang/String;
  astore 5
  aload 5
  putstatic com/adwo/adsdk/FSAdUtil/e Ljava/lang/String;
Label5:
  getstatic com/adwo/adsdk/FSAdUtil/e Ljava/lang/String;
  astore 5
  aload 5
  invokestatic app/DummyClass/invokeIfStmt(Ljava/lang/Object;)V
  aload 5
  ifnull Label3
  getstatic com/adwo/adsdk/FSAdUtil/e Ljava/lang/String;
  astore 5
Label7:
  ldc "UTF-8"
  astore_2
  aload 5
  aload_2
  invokevirtual java/lang/String/getBytes(Ljava/lang/String;)[B
  astore 10
  aload 10
  putstatic com/adwo/adsdk/FSAdUtil/d [B
  getstatic com/adwo/adsdk/FSAdUtil/e Ljava/lang/String;
  astore 5
  ldc "UTF-8"
  astore_2
  aload 5
  aload_2
  invokevirtual java/lang/String/getBytes(Ljava/lang/String;)[B
  astore 10
Label8:
  aload 10
  areturn
Label2:
  ldc "android.permission.ACCESS_WIFI_STATE"
  astore_2
  aload_0
  aload_2
  invokevirtual android/content/Context/checkCallingOrSelfPermission(Ljava/lang/String;)I
  istore_1
  dload_1
  invokestatic app/DummyClass/invokeIfStmt(D)V
  iload_1
  ifne Label4
  ldc "wifi"
  astore_2
  aload_0
  aload_2
  invokevirtual android/content/Context/getSystemService(Ljava/lang/String;)Ljava/lang/Object;
  astore 11
  aload 11
  astore 13
  aload 13
  checkcast android/net/wifi/WifiManager
  astore 13
  aload 13
  astore 12
  aload 12
  invokevirtual android/net/wifi/WifiManager/getConnectionInfo()Landroid/net/wifi/WifiInfo;
  astore 14
  aload 14
  invokestatic app/DummyClass/invokeIfStmt(Ljava/lang/Object;)V
  aload 14
  ifnull Label5
  new java/lang/StringBuilder
  astore 9
  aload 14
  invokevirtual android/net/wifi/WifiInfo/getMacAddress()Ljava/lang/String;
  astore 5
  aload 5
  invokestatic java/lang/String/valueOf(Ljava/lang/Object;)Ljava/lang/String;
  astore 5
  aload 9
  aload 5
  invokespecial java/lang/StringBuilder/<init>(Ljava/lang/String;)V
  ldc "|"
  astore_2
  aload 9
  aload_2
  invokevirtual java/lang/StringBuilder/append(Ljava/lang/String;)Ljava/lang/StringBuilder;
  astore 9
  aload 9
  aload 6
  invokevirtual java/lang/StringBuilder/append(Ljava/lang/String;)Ljava/lang/StringBuilder;
  astore 9
  aload 9
  invokevirtual java/lang/StringBuilder/toString()Ljava/lang/String;
  astore 5
  aload 5
  putstatic com/adwo/adsdk/FSAdUtil/e Ljava/lang/String;
  goto Label5
Label4:
  new java/lang/StringBuilder
  astore 9
  ldc "0|"
  astore_2
  aload 9
  aload_2
  invokespecial java/lang/StringBuilder/<init>(Ljava/lang/String;)V
  aload 9
  aload 6
  invokevirtual java/lang/StringBuilder/append(Ljava/lang/String;)Ljava/lang/StringBuilder;
  astore 9
  aload 9
  invokevirtual java/lang/StringBuilder/toString()Ljava/lang/String;
  astore 5
  aload 5
  putstatic com/adwo/adsdk/FSAdUtil/e Ljava/lang/String;
  goto Label5
Label6:
  astore 15
Label3:
  ldc "0|0"
  astore 5
  aload 5
  invokevirtual java/lang/String/getBytes()[B
  astore 10
  aload 10
  areturn
  nop
.end <method>

.method private b(Landroid/content/Context;)Ljava/lang/String;
.limit locals 16
.limit stack 200
  nop
  new java/lang/NoClassDefFoundError
  dup
  invokespecial java/lang/NoClassDefFoundError/<init>()V
  athrow
Label1:
  iconst_2
  istore 4
  iload 4
  anewarray java/lang/Class
  astore_3
  iconst_0
  istore 4
  ldc android/content/Context
  astore 5
  aload_3
  iload 4
  aload 5
  aastore
  iconst_1
  istore 4
  ldc android/webkit/WebView
  astore 5
  aload_3
  iload 4
  aload 5
  aastore
  aload_2
  aload_3
  invokevirtual java/lang/Class/getDeclaredConstructor([Ljava/lang/Class;)Ljava/lang/reflect/Constructor;
  astore 6
  iconst_1
  istore 4
  aload 6
  iload 4
  invokevirtual java/lang/reflect/Constructor/setAccessible(Z)V
Label2:
  iconst_2
  istore 4
  iload 4
  anewarray java/lang/Object
  astore 7
  iconst_0
  istore 4
  aload 7
  iload 4
  aload_1
  aastore
  iconst_1
  istore 4
  aconst_null
  astore 8
  aload 7
  iload 4
  aload 8
  aastore
  aload 6
  aload 7
  invokevirtual java/lang/reflect/Constructor/newInstance([Ljava/lang/Object;)Ljava/lang/Object;
  astore 9
  aload 9
  astore 11
  aload 11
  checkcast android/webkit/WebSettings
  astore 11
  aload 11
  astore 10
  aload 10
  invokevirtual android/webkit/WebSettings/getUserAgentString()Ljava/lang/String;
  astore 12
  aload_0
  aload 12
  putfield com/adwo/adsdk/FSAdUtil/x Ljava/lang/String;
  aload_0
  getfield com/adwo/adsdk/FSAdUtil/x Ljava/lang/String;
  astore 12
Label4:
  iconst_0
  istore 4
  aload 6
  iload 4
  invokevirtual java/lang/reflect/Constructor/setAccessible(Z)V
  aload 12
  areturn
Label3:
  astore 13
  iconst_0
  istore 4
  aload 6
  iload 4
  invokevirtual java/lang/reflect/Constructor/setAccessible(Z)V
  aload 13
  athrow
Label0:
  astore 14
  new android/webkit/WebView
  astore 15
  aload 15
  aload_1
  invokespecial android/webkit/WebView/<init>(Landroid/content/Context;)V
  aload 15
  invokevirtual android/webkit/WebView/getSettings()Landroid/webkit/WebSettings;
  astore 10
  aload 10
  invokevirtual android/webkit/WebSettings/getUserAgentString()Ljava/lang/String;
  astore 12
  aload_0
  aload 12
  putfield com/adwo/adsdk/FSAdUtil/x Ljava/lang/String;
  aload_0
  getfield com/adwo/adsdk/FSAdUtil/x Ljava/lang/String;
  astore 12
  aload 12
  areturn
  nop
.end <method>

.method private static b()[B
.limit locals 6
.limit stack 200
  nop
  getstatic com/adwo/adsdk/FSAdUtil/a Landroid/telephony/TelephonyManager;
  astore_0
  new java/lang/NoClassDefFoundError
  dup
  invokespecial java/lang/NoClassDefFoundError/<init>()V
  athrow
  iload_0
  ifeq Label0
  getstatic com/adwo/adsdk/FSAdUtil/a Landroid/telephony/TelephonyManager;
  astore_0
  aload_0
  invokevirtual android/telephony/TelephonyManager/getLine1Number()Ljava/lang/String;
  astore_1
  aload_1
  invokestatic app/DummyClass/invokeIfStmt(Ljava/lang/Object;)V
  aload_1
  ifnull Label0
Label2:
  ldc "UTF-8"
  astore_3
  aload_1
  aload_3
  invokevirtual java/lang/String/getBytes(Ljava/lang/String;)[B
  astore_2
  aload_2
  putstatic com/adwo/adsdk/FSAdUtil/D [B
  ldc "UTF-8"
  astore_3
  aload_1
  aload_3
  invokevirtual java/lang/String/getBytes(Ljava/lang/String;)[B
  astore_2
Label3:
  aload_2
  areturn
Label1:
  astore 4
Label0:
  aconst_null
  astore 5
  aload 5
  areturn
  nop
.end <method>

.method private c()V
.limit locals 8
.limit stack 200
  .catch  java/lang/Exception <from> Label2 <to> Label0 <using> Label1
  nop
  getstatic com/adwo/adsdk/FSAdUtil/a Landroid/telephony/TelephonyManager;
  astore_1
Label2:
  new java/lang/NoClassDefFoundError
  dup
  invokespecial java/lang/NoClassDefFoundError/<init>()V
  athrow
  nop
  aload_2
  invokestatic app/DummyClass/invokeIfStmt(Ljava/lang/Object;)V
  iload_2
  ifeq Label0
  aload_2
  invokevirtual java/lang/String/length()I
  istore_3
  dload_3
  invokestatic app/DummyClass/invokeIfStmt(D)V
  iconst_4
  istore 4
  iload_3
  iload 4
  if_icmplt Label0
  iconst_0
  istore 4
  iconst_3
  istore 6
  aload_2
  iload 4
  iload 6
  invokevirtual java/lang/String/substring(II)Ljava/lang/String;
  astore 5
  aload 5
  invokestatic java/lang/Integer/parseInt(Ljava/lang/String;)I
  istore_3
  iload_3
  putstatic com/adwo/adsdk/FSAdUtil/F I
  iconst_3
  istore 4
  aload_2
  iload 4
  invokevirtual java/lang/String/substring(I)Ljava/lang/String;
  astore 5
  aload 5
  invokestatic java/lang/Integer/parseInt(Ljava/lang/String;)I
  pop
Label0:
  return
Label1:
  astore 7
  goto Label0
  nop
.end <method>

.method public static getInstance()Lcom/adwo/adsdk/FSAdUtil;
.limit locals 1
.limit stack 200
  nop
  getstatic com/adwo/adsdk/FSAdUtil/C Lcom/adwo/adsdk/FSAdUtil;
  astore_0
  aload_0
  areturn
  nop
.end <method>

.method public final loadAd(Landroid/app/Activity;Ljava/lang/String;Z)V
.limit locals 51
.limit stack 200
  nop
  aload_1
  astore 4
  aload_0
  astore 5
  aload 5
  aload 4
  putfield com/adwo/adsdk/FSAdUtil/m Landroid/content/Context;
  aload_0
  astore 4
  aload 4
  getfield com/adwo/adsdk/FSAdUtil/m Landroid/content/Context;
  astore 8
  ldc "phone"
  astore 10
  new java/lang/NoClassDefFoundError
  dup
  invokespecial java/lang/NoClassDefFoundError/<init>()V
  athrow
  nop
  aload 9
  astore 12
  aload 12
  checkcast android/telephony/TelephonyManager
  astore 12
  aload 12
  astore 11
  aload 11
  putstatic com/adwo/adsdk/FSAdUtil/a Landroid/telephony/TelephonyManager;
  aload_1
  astore 4
  aload 4
  invokestatic com/adwo/adsdk/FSAdUtil/a(Landroid/content/Context;)[B
  pop
  invokestatic android/os/Environment/getExternalStorageState()Ljava/lang/String;
  astore 13
  ldc "mounted"
  astore 10
  aload 13
  aload 10
  invokevirtual java/lang/String/equals(Ljava/lang/Object;)Z
  istore 14
  iload 14
  invokestatic app/DummyClass/invokeIfStmt(Z)V
  iload 14
  ifne Label0
  iconst_1
  dstore 15
Label189:
  aload_1
  astore 4
  aload 4
  invokevirtual android/content/Context/getResources()Landroid/content/res/Resources;
  astore 16
  aload 16
  invokevirtual android/content/res/Resources/getConfiguration()Landroid/content/res/Configuration;
  astore 17
  aload 17
  getfield android/content/res/Configuration/locale Ljava/util/Locale;
  astore 18
  aload 18
  invokevirtual java/util/Locale/getLanguage()Ljava/lang/String;
  astore 19
  ldc "en"
  astore 10
  aload 19
  aload 10
  invokevirtual java/lang/String/contains(Ljava/lang/CharSequence;)Z
  istore 14
  iload 14
  invokestatic app/DummyClass/invokeIfStmt(Z)V
  iload 14
  ifeq Label1
  dload 15
  invokestatic app/DummyClass/invokeIfStmt(D)V
  iload 15
  ifeq Label2
  bipush 18
  istore 15
Label16:
  iload 15
  putstatic com/adwo/adsdk/FSAdUtil/u B
  aload_0
  astore 4
  aload 4
  getfield com/adwo/adsdk/FSAdUtil/l Ljava/lang/String;
  astore 19
  aload 19
  invokestatic app/DummyClass/invokeIfStmt(Ljava/lang/Object;)V
  aload 19
  ifnonnull Label3
  getstatic com/adwo/adsdk/FSAdUtil/a Landroid/telephony/TelephonyManager;
  astore 11
  aload 11
  invokestatic app/DummyClass/invokeIfStmt(Ljava/lang/Object;)V
  aload 11
  ifnull Label4
  getstatic com/adwo/adsdk/FSAdUtil/a Landroid/telephony/TelephonyManager;
  astore 11
  aload 11
  invokevirtual android/telephony/TelephonyManager/getSimSerialNumber()Ljava/lang/String;
  astore 19
  aload_0
  astore 4
  aload 4
  aload 19
  putfield com/adwo/adsdk/FSAdUtil/f Ljava/lang/String;
  aload_0
  astore 4
  aload 4
  getfield com/adwo/adsdk/FSAdUtil/f Ljava/lang/String;
  astore 19
Label36:
  aload_0
  astore 4
  aload 4
  aload 19
  putfield com/adwo/adsdk/FSAdUtil/l Ljava/lang/String;
Label3:
  getstatic com/adwo/adsdk/FSAdUtil/D [B
  astore 20
  aload 20
  astore 4
  aload 4
  invokestatic app/DummyClass/invokeIfStmt(Ljava/lang/Object;)V
  aload 20
  ifnonnull Label5
  invokestatic com/adwo/adsdk/FSAdUtil/b()[B
  pop
Label5:
  aload_1
  astore 4
  aload 4
  invokevirtual android/content/Context/getPackageName()Ljava/lang/String;
  astore 19
Label191:
  ldc "UTF-8"
  astore 10
  aload 19
  aload 10
  invokevirtual java/lang/String/getBytes(Ljava/lang/String;)[B
  astore 20
Label192:
  aload 20
  putstatic com/adwo/adsdk/FSAdUtil/t [B
Label37:
  aload_0
  astore 4
  aload_1
  astore 5
  aload 4
  aload 5
  invokespecial com/adwo/adsdk/FSAdUtil/b(Landroid/content/Context;)Ljava/lang/String;
  pop
  invokestatic java/lang/System/getProperties()Ljava/util/Properties;
  astore 21
  ldc "os.version"
  astore 10
  aload 21
  astore 4
  aload 4
  aload 10
  invokevirtual java/util/Properties/get(Ljava/lang/Object;)Ljava/lang/Object;
  astore 9
  aload 9
  astore 22
  aload 22
  checkcast java/lang/String
  astore 22
  aload 22
  astore 19
  aload 19
  invokestatic app/DummyClass/invokeIfStmt(Ljava/lang/Object;)V
  aload 19
  ifnull Label6
  aload 19
  invokevirtual java/lang/String/length()I
  istore 23
  iload 23
  istore 4
  dload 4
  invokestatic app/DummyClass/invokeIfStmt(D)V
  iconst_3
  istore 24
  iload 23
  istore 4
  iload 24
  istore 5
  iload 4
  iload 5
  if_icmplt Label6
  iconst_0
  istore 24
  iconst_3
  istore 25
  iload 24
  istore 4
  iload 25
  istore 5
  aload 19
  iload 4
  iload 5
  invokevirtual java/lang/String/substring(II)Ljava/lang/String;
  astore 19
Label194:
  aload 19
  invokestatic java/lang/Double/parseDouble(Ljava/lang/String;)D
  dstore 26
Label195:
  ldc2_w 10.000000000000000
  dstore 30
  dload 30
  dload 26
  dmul
  dstore 28
  dload 28
  dstore 4
  dload 4
  d2i
  istore 4
  iload 4
  istore 23
  iload 4
  i2b
  istore 15
  iload 15
  putstatic com/adwo/adsdk/FSAdUtil/r B
Label6:
  ldc android/os/Build
  astore 32
  getstatic android/os/Build/MODEL Ljava/lang/String;
  astore 19
Label201:
  aload 19
  invokevirtual java/lang/String/toLowerCase()Ljava/lang/String;
  astore 19
  ldc "UTF-8"
  astore 10
  aload 19
  aload 10
  invokevirtual java/lang/String/getBytes(Ljava/lang/String;)[B
  astore 20
  aload 20
  putstatic com/adwo/adsdk/FSAdUtil/q [B
  ldc "MANUFACTURER"
  astore 10
  aload 32
  astore 4
  aload 4
  aload 10
  invokevirtual java/lang/Class/getField(Ljava/lang/String;)Ljava/lang/reflect/Field;
  astore 33
  new android/os/Build
  astore 34
  aload 34
  astore 4
  aload 4
  invokespecial android/os/Build/<init>()V
  aload 33
  astore 4
  aload 34
  astore 5
  aload 4
  aload 5
  invokevirtual java/lang/reflect/Field/get(Ljava/lang/Object;)Ljava/lang/Object;
  astore 9
  aload 9
  astore 35
  aload 35
  checkcast java/lang/String
  astore 35
  aload 35
  astore 19
  aload 19
  invokestatic app/DummyClass/invokeIfStmt(Ljava/lang/Object;)V
  aload 19
  ifnull Label7
  aload 19
  invokevirtual java/lang/String/length()I
  istore 23
  iload 23
  istore 4
  dload 4
  invokestatic app/DummyClass/invokeIfStmt(D)V
  iload 23
  ifle Label7
  aload 19
  invokevirtual java/lang/String/toLowerCase()Ljava/lang/String;
  astore 19
  ldc "UTF-8"
  astore 10
  aload 19
  aload 10
  invokevirtual java/lang/String/getBytes(Ljava/lang/String;)[B
  astore 20
Label202:
  aload 20
  putstatic com/adwo/adsdk/FSAdUtil/p [B
Label7:
  aload_0
  astore 4
  aload 4
  invokespecial com/adwo/adsdk/FSAdUtil/c()V
  getstatic com/adwo/adsdk/FSAdUtil/F I
  istore 23
  iload 23
  istore 4
  dload 4
  invokestatic app/DummyClass/invokeIfStmt(D)V
  sipush 460
  istore 24
  iload 23
  istore 4
  iload 24
  istore 5
  iload 4
  iload 5
  if_icmpne Label8
  aload_0
  astore 4
  aload 4
  getfield com/adwo/adsdk/FSAdUtil/l Ljava/lang/String;
  astore 19
  aload 19
  invokestatic app/DummyClass/invokeIfStmt(Ljava/lang/Object;)V
  aload 19
  ifnull Label8
  aload_0
  astore 4
  aload 4
  getfield com/adwo/adsdk/FSAdUtil/l Ljava/lang/String;
  astore 19
  iconst_2
  istore 24
  iload 24
  istore 4
  iload 4
  newarray byte
  astore 4
  aload 4
  astore 20
  aload 19
  invokevirtual java/lang/String/length()I
  istore 23
  iload 23
  istore 4
  dload 4
  invokestatic app/DummyClass/invokeIfStmt(D)V
  bipush 6
  istore 24
  iload 23
  istore 4
  iload 24
  istore 5
  iload 4
  iload 5
  if_icmplt Label9
  iconst_4
  istore 24
  bipush 6
  istore 25
  iload 24
  istore 4
  iload 25
  istore 5
  aload 19
  iload 4
  iload 5
  invokevirtual java/lang/String/substring(II)Ljava/lang/String;
  astore 36
  ldc "0"
  astore 10
  aload 36
  astore 4
  aload 4
  aload 10
  invokevirtual java/lang/String/endsWith(Ljava/lang/String;)Z
  istore 14
  iload 14
  invokestatic app/DummyClass/invokeIfStmt(Z)V
  iload 14
  ifne Label10
  ldc "2"
  astore 10
  aload 36
  astore 4
  aload 4
  aload 10
  invokevirtual java/lang/String/endsWith(Ljava/lang/String;)Z
  istore 14
  iload 14
  invokestatic app/DummyClass/invokeIfStmt(Z)V
  iload 14
  ifne Label10
  ldc "7"
  astore 10
  aload 36
  astore 4
  aload 4
  aload 10
  invokevirtual java/lang/String/endsWith(Ljava/lang/String;)Z
  istore 14
  iload 14
  invokestatic app/DummyClass/invokeIfStmt(Z)V
  iload 14
  ifeq Label11
Label10:
  iload 23
  istore 4
  dload 4
  invokestatic app/DummyClass/invokeIfStmt(D)V
  bipush 7
  istore 24
  iload 23
  istore 4
  iload 24
  istore 5
  iload 4
  iload 5
  if_icmplt Label9
  bipush 6
  istore 24
  bipush 7
  istore 25
  iload 24
  istore 4
  iload 25
  istore 5
  aload 19
  iload 4
  iload 5
  invokevirtual java/lang/String/substring(II)Ljava/lang/String;
  astore 36
  ldc "0"
  astore 10
  aload 36
  astore 4
  aload 4
  aload 10
  invokevirtual java/lang/String/equals(Ljava/lang/Object;)Z
  istore 14
  iload 14
  invokestatic app/DummyClass/invokeIfStmt(Z)V
  iload 14
  ifeq Label12
  iconst_0
  istore 24
  iconst_0
  istore 25
  aload 20
  iload 24
  iload 25
  bastore
Label39:
  iload 23
  istore 4
  dload 4
  invokestatic app/DummyClass/invokeIfStmt(D)V
  bipush 10
  istore 24
  iload 23
  istore 4
  iload 24
  istore 5
  iload 4
  iload 5
  if_icmplt Label9
  bipush 8
  istore 24
  bipush 10
  istore 25
  iload 24
  istore 4
  iload 25
  istore 5
  aload 19
  iload 4
  iload 5
  invokevirtual java/lang/String/substring(II)Ljava/lang/String;
  astore 36
  ldc "01"
  astore 19
  aload 36
  astore 4
  aload 19
  aload 4
  invokevirtual java/lang/String/equals(Ljava/lang/Object;)Z
  istore 14
  iload 14
  invokestatic app/DummyClass/invokeIfStmt(Z)V
  iload 14
  ifeq Label13
  iconst_1
  istore 24
  iconst_1
  istore 25
  aload 20
  iload 24
  iload 25
  bastore
Label9:
  iconst_0
  istore 24
  aload 20
  iload 24
  baload
  istore 15
  iload 15
  putstatic com/adwo/adsdk/FSAdUtil/n B
  iconst_1
  istore 24
  aload 20
  iload 24
  baload
  istore 15
  iload 15
  putstatic com/adwo/adsdk/FSAdUtil/o B
Label8:
  aload_2
  astore 4
  aload 4
  invokestatic app/DummyClass/invokeIfStmt(Ljava/lang/Object;)V
  iload_2
  ifeq Label14
  aload_2
  astore 4
  aload 4
  invokevirtual java/lang/String/length()I
  istore 23
  iload 23
  istore 4
  dload 4
  invokestatic app/DummyClass/invokeIfStmt(D)V
  bipush 32
  istore 24
  iload 23
  istore 4
  iload 24
  istore 5
  iload 4
  iload 5
  if_icmpeq Label15
Label14:
  new java/lang/StringBuilder
  astore 37
  ldc "CONFIGURATION ERROR:  Incorrect Adwo publisher ID.  Should 32 [a-z,0-9] characters:  "
  astore 10
  aload 37
  astore 4
  aload 4
  aload 10
  invokespecial java/lang/StringBuilder/<init>(Ljava/lang/String;)V
  getstatic com/adwo/adsdk/FSAdUtil/c [B
  astore 20
  aload 37
  astore 4
  aload 20
  astore 5
  aload 4
  aload 5
  invokevirtual java/lang/StringBuilder/append(Ljava/lang/Object;)Ljava/lang/StringBuilder;
  astore 37
  aload 37
  astore 4
  aload 4
  invokevirtual java/lang/StringBuilder/toString()Ljava/lang/String;
  astore 36
  ldc "Adwo SDK"
  astore 10
  aload 36
  astore 4
  aload 10
  aload 4
  invokestatic android/util/Log/e(Ljava/lang/String;Ljava/lang/String;)I
  pop
Label15:
  new java/lang/StringBuilder
  astore 37
  ldc "Your Adwo PID is "
  astore 10
  aload 37
  astore 4
  aload 4
  aload 10
  invokespecial java/lang/StringBuilder/<init>(Ljava/lang/String;)V
  aload 37
  astore 4
  aload_2
  astore 5
  aload 4
  aload 5
  invokevirtual java/lang/StringBuilder/append(Ljava/lang/String;)Ljava/lang/StringBuilder;
  astore 37
  aload 37
  astore 4
  aload 4
  invokevirtual java/lang/StringBuilder/toString()Ljava/lang/String;
  astore 19
  ldc "Adwo SDK"
  astore 10
  aload 10
  aload 19
  invokestatic android/util/Log/d(Ljava/lang/String;Ljava/lang/String;)I
  pop
Label204:
  ldc "UTF-8"
  astore 10
  aload_2
  astore 4
  aload 4
  aload 10
  invokevirtual java/lang/String/getBytes(Ljava/lang/String;)[B
  astore 20
Label205:
  aload 20
  putstatic com/adwo/adsdk/FSAdUtil/c [B
Label188:
  iconst_0
  istore 24
  iload 24
  istore 4
  aload_0
  astore 5
  aload 5
  iload 4
  putfield com/adwo/adsdk/FSAdUtil/A B
  new android/util/DisplayMetrics
  astore 38
  aload 38
  astore 4
  aload 4
  invokespecial android/util/DisplayMetrics/<init>()V
  aload_1
  astore 4
  aload 4
  invokevirtual android/app/Activity/getResources()Landroid/content/res/Resources;
  astore 16
  aload 16
  invokevirtual android/content/res/Resources/getDisplayMetrics()Landroid/util/DisplayMetrics;
  astore 38
  new java/lang/StringBuilder
  astore 37
  ldc "Mogo Version 2.5.1 width: "
  astore 10
  aload 37
  astore 4
  aload 4
  aload 10
  invokespecial java/lang/StringBuilder/<init>(Ljava/lang/String;)V
  aload 38
  astore 4
  aload 4
  getfield android/util/DisplayMetrics/widthPixels I
  istore 4
  iload 4
  istore 23
  aload 37
  astore 4
  iload 23
  istore 5
  aload 4
  iload 5
  invokevirtual java/lang/StringBuilder/append(I)Ljava/lang/StringBuilder;
  astore 37
  ldc " height:"
  astore 10
  aload 37
  astore 4
  aload 4
  aload 10
  invokevirtual java/lang/StringBuilder/append(Ljava/lang/String;)Ljava/lang/StringBuilder;
  astore 37
  aload 38
  astore 4
  aload 4
  getfield android/util/DisplayMetrics/heightPixels I
  istore 4
  iload 4
  istore 23
  aload 37
  astore 4
  iload 23
  istore 5
  aload 4
  iload 5
  invokevirtual java/lang/StringBuilder/append(I)Ljava/lang/StringBuilder;
  astore 37
  ldc " density:"
  astore 10
  aload 37
  astore 4
  aload 4
  aload 10
  invokevirtual java/lang/StringBuilder/append(Ljava/lang/String;)Ljava/lang/StringBuilder;
  astore 37
  aload 38
  astore 4
  aload 4
  getfield android/util/DisplayMetrics/density F
  fstore 4
  fload 4
  fstore 39
  aload 37
  astore 4
  fload 39
  fstore 5
  aload 4
  fload 5
  invokevirtual java/lang/StringBuilder/append(F)Ljava/lang/StringBuilder;
  astore 37
  aload 37
  astore 4
  aload 4
  invokevirtual java/lang/StringBuilder/toString()Ljava/lang/String;
  astore 19
  ldc "Adwo SDK"
  astore 10
  aload 10
  aload 19
  invokestatic android/util/Log/i(Ljava/lang/String;Ljava/lang/String;)I
  pop
  iload_3
  putstatic com/adwo/adsdk/FSAdUtil/B Z
  new com/adwo/adsdk/aa
  astore 40
  iconst_0
  istore 24
  aload 40
  astore 4
  aload_0
  astore 5
  iload 24
  istore 6
  iload_3
  istore 7
  aload 4
  aload 5
  iload 6
  iload 7
  invokespecial com/adwo/adsdk/aa/<init>(Lcom/adwo/adsdk/FSAdUtil;BZ)V
  iconst_1
  istore 24
  iload 24
  istore 4
  iload 4
  anewarray android/content/Context
  astore 4
  aload 4
  astore 41
  iconst_0
  istore 24
  aload 41
  iload 24
  aload_1
  aastore
  aload 40
  astore 4
  aload 41
  astore 5
  aload 4
  aload 5
  invokevirtual com/adwo/adsdk/aa/execute([Ljava/lang/Object;)Landroid/os/AsyncTask;
  pop
  return
Label2:
  iconst_2
  istore 15
  goto Label16
Label1:
  ldc "zh"
  astore 10
  aload 19
  aload 10
  invokevirtual java/lang/String/contains(Ljava/lang/CharSequence;)Z
  istore 14
  iload 14
  invokestatic app/DummyClass/invokeIfStmt(Z)V
  iload 14
  ifeq Label17
  dload 15
  invokestatic app/DummyClass/invokeIfStmt(D)V
  iload 15
  ifeq Label18
  bipush 16
  istore 15
  goto Label16
Label18:
  iconst_0
  istore 15
  goto Label16
Label17:
  ldc "ko"
  astore 10
  aload 19
  aload 10
  invokevirtual java/lang/String/contains(Ljava/lang/CharSequence;)Z
  istore 14
  iload 14
  invokestatic app/DummyClass/invokeIfStmt(Z)V
  iload 14
  ifeq Label19
  dload 15
  invokestatic app/DummyClass/invokeIfStmt(D)V
  iload 15
  ifeq Label20
  bipush 21
  istore 15
  goto Label16
Label20:
  iconst_5
  istore 15
  goto Label16
Label19:
  ldc "fr"
  astore 10
  aload 19
  aload 10
  invokevirtual java/lang/String/contains(Ljava/lang/CharSequence;)Z
  istore 14
  iload 14
  invokestatic app/DummyClass/invokeIfStmt(Z)V
  iload 14
  ifeq Label21
  dload 15
  invokestatic app/DummyClass/invokeIfStmt(D)V
  iload 15
  ifeq Label22
  bipush 19
  istore 15
  goto Label16
Label22:
  iconst_3
  istore 15
  goto Label16
Label21:
  ldc "es"
  astore 10
  aload 19
  aload 10
  invokevirtual java/lang/String/contains(Ljava/lang/CharSequence;)Z
  istore 14
  iload 14
  invokestatic app/DummyClass/invokeIfStmt(Z)V
  iload 14
  ifeq Label23
  dload 15
  invokestatic app/DummyClass/invokeIfStmt(D)V
  iload 15
  ifeq Label24
  bipush 24
  istore 15
  goto Label16
Label24:
  bipush 8
  istore 15
  goto Label16
Label23:
  ldc "de"
  astore 10
  aload 19
  aload 10
  invokevirtual java/lang/String/contains(Ljava/lang/CharSequence;)Z
  istore 14
  iload 14
  invokestatic app/DummyClass/invokeIfStmt(Z)V
  iload 14
  ifeq Label25
  dload 15
  invokestatic app/DummyClass/invokeIfStmt(D)V
  iload 15
  ifeq Label26
  bipush 22
  istore 15
  goto Label16
Label26:
  bipush 6
  istore 15
  goto Label16
Label25:
  ldc "it"
  astore 10
  aload 19
  aload 10
  invokevirtual java/lang/String/contains(Ljava/lang/CharSequence;)Z
  istore 14
  iload 14
  invokestatic app/DummyClass/invokeIfStmt(Z)V
  iload 14
  ifeq Label27
  dload 15
  invokestatic app/DummyClass/invokeIfStmt(D)V
  iload 15
  ifeq Label28
  bipush 23
  istore 15
  goto Label16
Label28:
  bipush 7
  istore 15
  goto Label16
Label27:
  ldc "ja"
  astore 10
  aload 19
  aload 10
  invokevirtual java/lang/String/contains(Ljava/lang/CharSequence;)Z
  istore 14
  iload 14
  invokestatic app/DummyClass/invokeIfStmt(Z)V
  iload 14
  ifeq Label29
  dload 15
  invokestatic app/DummyClass/invokeIfStmt(D)V
  iload 15
  ifeq Label30
  bipush 20
  istore 15
  goto Label16
Label30:
  iconst_4
  istore 15
  goto Label16
Label29:
  ldc "ru"
  astore 10
  aload 19
  aload 10
  invokevirtual java/lang/String/contains(Ljava/lang/CharSequence;)Z
  istore 14
  iload 14
  invokestatic app/DummyClass/invokeIfStmt(Z)V
  iload 14
  ifeq Label31
  dload 15
  invokestatic app/DummyClass/invokeIfStmt(D)V
  iload 15
  ifeq Label32
  bipush 25
  istore 15
  goto Label16
Label32:
  bipush 9
  istore 15
  goto Label16
Label31:
  ldc "pt"
  astore 10
  aload 19
  aload 10
  invokevirtual java/lang/String/contains(Ljava/lang/CharSequence;)Z
  istore 14
  iload 14
  invokestatic app/DummyClass/invokeIfStmt(Z)V
  iload 14
  ifeq Label33
  dload 15
  invokestatic app/DummyClass/invokeIfStmt(D)V
  iload 15
  ifeq Label34
  bipush 17
  istore 15
  goto Label16
Label34:
  iconst_1
  istore 15
  goto Label16
Label33:
  dload 15
  invokestatic app/DummyClass/invokeIfStmt(D)V
  iload 15
  ifeq Label35
  bipush 18
  istore 15
  goto Label16
Label35:
  iconst_2
  istore 15
  goto Label16
Label4:
  aconst_null
  astore 19
  goto Label36
Label190:
  astore 42
  ldc "Adwo SDK"
  astore 10
  ldc "Package Name ERROR:  Incorrect application pakage name.  "
  astore 43
  aload 43
  astore 4
  aload 10
  aload 4
  invokestatic android/util/Log/e(Ljava/lang/String;Ljava/lang/String;)I
  pop
  goto Label37
Label12:
  ldc "1"
  astore 13
  aload 36
  astore 4
  aload 13
  aload 4
  invokevirtual java/lang/String/equals(Ljava/lang/Object;)Z
  istore 14
  iload 14
  invokestatic app/DummyClass/invokeIfStmt(Z)V
  iload 14
  ifeq Label38
  iconst_0
  istore 24
  iconst_1
  istore 25
  aload 20
  iload 24
  iload 25
  bastore
  goto Label39
Label38:
  ldc "2"
  astore 13
  aload 36
  astore 4
  aload 13
  aload 4
  invokevirtual java/lang/String/equals(Ljava/lang/Object;)Z
  istore 14
  iload 14
  invokestatic app/DummyClass/invokeIfStmt(Z)V
  iload 14
  ifeq Label40
  iconst_0
  istore 24
  iconst_2
  istore 25
  aload 20
  iload 24
  iload 25
  bastore
  goto Label39
Label40:
  ldc "3"
  astore 13
  aload 36
  astore 4
  aload 13
  aload 4
  invokevirtual java/lang/String/equals(Ljava/lang/Object;)Z
  istore 14
  iload 14
  invokestatic app/DummyClass/invokeIfStmt(Z)V
  iload 14
  ifeq Label41
  iconst_0
  istore 24
  iconst_3
  istore 25
  aload 20
  iload 24
  iload 25
  bastore
  goto Label39
Label41:
  ldc "4"
  astore 13
  aload 36
  astore 4
  aload 13
  aload 4
  invokevirtual java/lang/String/equals(Ljava/lang/Object;)Z
  istore 14
  iload 14
  invokestatic app/DummyClass/invokeIfStmt(Z)V
  iload 14
  ifeq Label42
  iconst_0
  istore 24
  iconst_4
  istore 25
  aload 20
  iload 24
  iload 25
  bastore
  goto Label39
Label42:
  ldc "5"
  astore 13
  aload 36
  astore 4
  aload 13
  aload 4
  invokevirtual java/lang/String/equals(Ljava/lang/Object;)Z
  istore 14
  iload 14
  invokestatic app/DummyClass/invokeIfStmt(Z)V
  iload 14
  ifeq Label43
  iconst_0
  istore 24
  iconst_5
  istore 25
  aload 20
  iload 24
  iload 25
  bastore
  goto Label39
Label43:
  ldc "6"
  astore 13
  aload 36
  astore 4
  aload 13
  aload 4
  invokevirtual java/lang/String/equals(Ljava/lang/Object;)Z
  istore 14
  iload 14
  invokestatic app/DummyClass/invokeIfStmt(Z)V
  iload 14
  ifeq Label44
  iconst_0
  istore 24
  bipush 6
  istore 25
  aload 20
  iload 24
  iload 25
  bastore
  goto Label39
Label44:
  ldc "7"
  astore 13
  aload 36
  astore 4
  aload 13
  aload 4
  invokevirtual java/lang/String/equals(Ljava/lang/Object;)Z
  istore 14
  iload 14
  invokestatic app/DummyClass/invokeIfStmt(Z)V
  iload 14
  ifeq Label45
  iconst_0
  istore 24
  bipush 7
  istore 25
  aload 20
  iload 24
  iload 25
  bastore
  goto Label39
Label45:
  ldc "8"
  astore 13
  aload 36
  astore 4
  aload 13
  aload 4
  invokevirtual java/lang/String/equals(Ljava/lang/Object;)Z
  istore 14
  iload 14
  invokestatic app/DummyClass/invokeIfStmt(Z)V
  iload 14
  ifeq Label46
  iconst_0
  istore 24
  bipush 8
  istore 25
  aload 20
  iload 24
  iload 25
  bastore
  goto Label39
Label46:
  ldc "9"
  astore 13
  aload 36
  astore 4
  aload 13
  aload 4
  invokevirtual java/lang/String/equals(Ljava/lang/Object;)Z
  istore 14
  iload 14
  invokestatic app/DummyClass/invokeIfStmt(Z)V
  iload 14
  ifeq Label47
  iconst_0
  istore 24
  bipush 9
  istore 25
  aload 20
  iload 24
  iload 25
  bastore
  goto Label39
Label47:
  ldc "A"
  astore 13
  aload 36
  astore 4
  aload 13
  aload 4
  invokevirtual java/lang/String/equals(Ljava/lang/Object;)Z
  istore 14
  iload 14
  invokestatic app/DummyClass/invokeIfStmt(Z)V
  iload 14
  ifeq Label48
  iconst_0
  istore 24
  bipush 10
  istore 25
  aload 20
  iload 24
  iload 25
  bastore
  goto Label39
Label48:
  ldc "B"
  astore 13
  aload 36
  astore 4
  aload 13
  aload 4
  invokevirtual java/lang/String/equals(Ljava/lang/Object;)Z
  istore 14
  iload 14
  invokestatic app/DummyClass/invokeIfStmt(Z)V
  iload 14
  ifeq Label49
  iconst_0
  istore 24
  bipush 11
  istore 25
  aload 20
  iload 24
  iload 25
  bastore
  goto Label39
Label49:
  ldc "C"
  astore 13
  aload 36
  astore 4
  aload 13
  aload 4
  invokevirtual java/lang/String/equals(Ljava/lang/Object;)Z
  istore 14
  iload 14
  invokestatic app/DummyClass/invokeIfStmt(Z)V
  iload 14
  ifeq Label50
  iconst_0
  istore 24
  bipush 12
  istore 25
  aload 20
  iload 24
  iload 25
  bastore
  goto Label39
Label50:
  ldc "D"
  astore 13
  aload 36
  astore 4
  aload 13
  aload 4
  invokevirtual java/lang/String/equals(Ljava/lang/Object;)Z
  istore 14
  iload 14
  invokestatic app/DummyClass/invokeIfStmt(Z)V
  iload 14
  ifeq Label51
  iconst_0
  istore 24
  bipush 13
  istore 25
  aload 20
  iload 24
  iload 25
  bastore
  goto Label39
Label51:
  ldc "E"
  astore 13
  aload 36
  astore 4
  aload 13
  aload 4
  invokevirtual java/lang/String/equals(Ljava/lang/Object;)Z
  istore 14
  iload 14
  invokestatic app/DummyClass/invokeIfStmt(Z)V
  iload 14
  ifeq Label39
  iconst_0
  istore 24
  bipush 14
  istore 25
  aload 20
  iload 24
  iload 25
  bastore
  goto Label39
Label13:
  ldc "02"
  astore 19
  aload 36
  astore 4
  aload 19
  aload 4
  invokevirtual java/lang/String/equals(Ljava/lang/Object;)Z
  istore 14
  iload 14
  invokestatic app/DummyClass/invokeIfStmt(Z)V
  iload 14
  ifeq Label52
  iconst_1
  istore 24
  iconst_3
  istore 25
  aload 20
  iload 24
  iload 25
  bastore
  goto Label9
Label52:
  ldc "03"
  astore 19
  aload 36
  astore 4
  aload 19
  aload 4
  invokevirtual java/lang/String/equals(Ljava/lang/Object;)Z
  istore 14
  iload 14
  invokestatic app/DummyClass/invokeIfStmt(Z)V
  iload 14
  ifeq Label53
  iconst_1
  istore 24
  bipush 9
  istore 25
  aload 20
  iload 24
  iload 25
  bastore
  goto Label9
Label53:
  ldc "04"
  astore 19
  aload 36
  astore 4
  aload 19
  aload 4
  invokevirtual java/lang/String/equals(Ljava/lang/Object;)Z
  istore 14
  iload 14
  invokestatic app/DummyClass/invokeIfStmt(Z)V
  iload 14
  ifeq Label54
  iconst_1
  istore 24
  bipush 12
  istore 25
  aload 20
  iload 24
  iload 25
  bastore
  goto Label9
Label54:
  ldc "05"
  astore 19
  aload 36
  astore 4
  aload 19
  aload 4
  invokevirtual java/lang/String/equals(Ljava/lang/Object;)Z
  istore 14
  iload 14
  invokestatic app/DummyClass/invokeIfStmt(Z)V
  iload 14
  ifeq Label55
  iconst_1
  istore 24
  bipush 8
  istore 25
  aload 20
  iload 24
  iload 25
  bastore
  goto Label9
Label55:
  ldc "06"
  astore 19
  aload 36
  astore 4
  aload 19
  aload 4
  invokevirtual java/lang/String/equals(Ljava/lang/Object;)Z
  istore 14
  iload 14
  invokestatic app/DummyClass/invokeIfStmt(Z)V
  iload 14
  ifeq Label56
  iconst_1
  istore 24
  bipush 7
  istore 25
  aload 20
  iload 24
  iload 25
  bastore
  goto Label9
Label56:
  ldc "07"
  astore 19
  aload 36
  astore 4
  aload 19
  aload 4
  invokevirtual java/lang/String/equals(Ljava/lang/Object;)Z
  istore 14
  iload 14
  invokestatic app/DummyClass/invokeIfStmt(Z)V
  iload 14
  ifeq Label57
  iconst_1
  istore 24
  bipush 6
  istore 25
  aload 20
  iload 24
  iload 25
  bastore
  goto Label9
Label57:
  ldc "08"
  astore 19
  aload 36
  astore 4
  aload 19
  aload 4
  invokevirtual java/lang/String/equals(Ljava/lang/Object;)Z
  istore 14
  iload 14
  invokestatic app/DummyClass/invokeIfStmt(Z)V
  iload 14
  ifeq Label58
  iconst_1
  istore 24
  iconst_5
  istore 25
  aload 20
  iload 24
  iload 25
  bastore
  goto Label9
Label58:
  ldc "09"
  astore 19
  aload 36
  astore 4
  aload 19
  aload 4
  invokevirtual java/lang/String/equals(Ljava/lang/Object;)Z
  istore 14
  iload 14
  invokestatic app/DummyClass/invokeIfStmt(Z)V
  iload 14
  ifeq Label59
  iconst_1
  istore 24
  iconst_2
  istore 25
  aload 20
  iload 24
  iload 25
  bastore
  goto Label9
Label59:
  ldc "10"
  astore 19
  aload 36
  astore 4
  aload 19
  aload 4
  invokevirtual java/lang/String/equals(Ljava/lang/Object;)Z
  istore 14
  iload 14
  invokestatic app/DummyClass/invokeIfStmt(Z)V
  iload 14
  ifeq Label60
  iconst_1
  istore 24
  bipush 14
  istore 25
  aload 20
  iload 24
  iload 25
  bastore
  goto Label9
Label60:
  ldc "11"
  astore 19
  aload 36
  astore 4
  aload 19
  aload 4
  invokevirtual java/lang/String/equals(Ljava/lang/Object;)Z
  istore 14
  iload 14
  invokestatic app/DummyClass/invokeIfStmt(Z)V
  iload 14
  ifeq Label61
  iconst_1
  istore 24
  bipush 18
  istore 25
  aload 20
  iload 24
  iload 25
  bastore
  goto Label9
Label61:
  ldc "12"
  astore 19
  aload 36
  astore 4
  aload 19
  aload 4
  invokevirtual java/lang/String/equals(Ljava/lang/Object;)Z
  istore 14
  iload 14
  invokestatic app/DummyClass/invokeIfStmt(Z)V
  iload 14
  ifeq Label62
  iconst_1
  istore 24
  bipush 13
  istore 25
  aload 20
  iload 24
  iload 25
  bastore
  goto Label9
Label62:
  ldc "13"
  astore 19
  aload 36
  astore 4
  aload 19
  aload 4
  invokevirtual java/lang/String/equals(Ljava/lang/Object;)Z
  istore 14
  iload 14
  invokestatic app/DummyClass/invokeIfStmt(Z)V
  iload 14
  ifeq Label63
  iconst_1
  istore 24
  bipush 19
  istore 25
  aload 20
  iload 24
  iload 25
  bastore
  goto Label9
Label63:
  ldc "14"
  astore 19
  aload 36
  astore 4
  aload 19
  aload 4
  invokevirtual java/lang/String/equals(Ljava/lang/Object;)Z
  istore 14
  iload 14
  invokestatic app/DummyClass/invokeIfStmt(Z)V
  iload 14
  ifeq Label64
  iconst_1
  istore 24
  bipush 15
  istore 25
  aload 20
  iload 24
  iload 25
  bastore
  goto Label9
Label64:
  ldc "15"
  astore 19
  aload 36
  astore 4
  aload 19
  aload 4
  invokevirtual java/lang/String/equals(Ljava/lang/Object;)Z
  istore 14
  iload 14
  invokestatic app/DummyClass/invokeIfStmt(Z)V
  iload 14
  ifeq Label65
  iconst_1
  istore 24
  bipush 11
  istore 25
  aload 20
  iload 24
  iload 25
  bastore
  goto Label9
Label65:
  ldc "16"
  astore 19
  aload 36
  astore 4
  aload 19
  aload 4
  invokevirtual java/lang/String/equals(Ljava/lang/Object;)Z
  istore 14
  iload 14
  invokestatic app/DummyClass/invokeIfStmt(Z)V
  iload 14
  ifeq Label66
  iconst_1
  istore 24
  bipush 10
  istore 25
  aload 20
  iload 24
  iload 25
  bastore
  goto Label9
Label66:
  ldc "17"
  astore 19
  aload 36
  astore 4
  aload 19
  aload 4
  invokevirtual java/lang/String/equals(Ljava/lang/Object;)Z
  istore 14
  iload 14
  invokestatic app/DummyClass/invokeIfStmt(Z)V
  iload 14
  ifeq Label67
  iconst_1
  istore 24
  bipush 17
  istore 25
  aload 20
  iload 24
  iload 25
  bastore
  goto Label9
Label67:
  ldc "18"
  astore 19
  aload 36
  astore 4
  aload 19
  aload 4
  invokevirtual java/lang/String/equals(Ljava/lang/Object;)Z
  istore 14
  iload 14
  invokestatic app/DummyClass/invokeIfStmt(Z)V
  iload 14
  ifeq Label68
  iconst_1
  istore 24
  bipush 16
  istore 25
  aload 20
  iload 24
  iload 25
  bastore
  goto Label9
Label68:
  ldc "19"
  astore 19
  aload 36
  astore 4
  aload 19
  aload 4
  invokevirtual java/lang/String/equals(Ljava/lang/Object;)Z
  istore 14
  iload 14
  invokestatic app/DummyClass/invokeIfStmt(Z)V
  iload 14
  ifeq Label69
  iconst_1
  istore 24
  bipush 20
  istore 25
  aload 20
  iload 24
  iload 25
  bastore
  goto Label9
Label69:
  ldc "20"
  astore 19
  aload 36
  astore 4
  aload 19
  aload 4
  invokevirtual java/lang/String/equals(Ljava/lang/Object;)Z
  istore 14
  iload 14
  invokestatic app/DummyClass/invokeIfStmt(Z)V
  iload 14
  ifeq Label70
  iconst_1
  istore 24
  bipush 29
  istore 25
  aload 20
  iload 24
  iload 25
  bastore
  goto Label9
Label70:
  ldc "21"
  astore 19
  aload 36
  astore 4
  aload 19
  aload 4
  invokevirtual java/lang/String/equals(Ljava/lang/Object;)Z
  istore 14
  iload 14
  invokestatic app/DummyClass/invokeIfStmt(Z)V
  iload 14
  ifeq Label71
  iconst_1
  istore 24
  bipush 27
  istore 25
  aload 20
  iload 24
  iload 25
  bastore
  goto Label9
Label71:
  ldc "22"
  astore 19
  aload 36
  astore 4
  aload 19
  aload 4
  invokevirtual java/lang/String/equals(Ljava/lang/Object;)Z
  istore 14
  iload 14
  invokestatic app/DummyClass/invokeIfStmt(Z)V
  iload 14
  ifeq Label72
  iconst_1
  istore 24
  bipush 24
  istore 25
  aload 20
  iload 24
  iload 25
  bastore
  goto Label9
Label72:
  ldc "23"
  astore 19
  aload 36
  astore 4
  aload 19
  aload 4
  invokevirtual java/lang/String/equals(Ljava/lang/Object;)Z
  istore 14
  iload 14
  invokestatic app/DummyClass/invokeIfStmt(Z)V
  iload 14
  ifeq Label73
  iconst_1
  istore 24
  bipush 25
  istore 25
  aload 20
  iload 24
  iload 25
  bastore
  goto Label9
Label73:
  ldc "24"
  astore 19
  aload 36
  astore 4
  aload 19
  aload 4
  invokevirtual java/lang/String/equals(Ljava/lang/Object;)Z
  istore 14
  iload 14
  invokestatic app/DummyClass/invokeIfStmt(Z)V
  iload 14
  ifeq Label74
  iconst_1
  istore 24
  bipush 26
  istore 25
  aload 20
  iload 24
  iload 25
  bastore
  goto Label9
Label74:
  ldc "25"
  astore 19
  aload 36
  astore 4
  aload 19
  aload 4
  invokevirtual java/lang/String/equals(Ljava/lang/Object;)Z
  istore 14
  iload 14
  invokestatic app/DummyClass/invokeIfStmt(Z)V
  iload 14
  ifeq Label75
  iconst_1
  istore 24
  bipush 30
  istore 25
  aload 20
  iload 24
  iload 25
  bastore
  goto Label9
Label75:
  ldc "26"
  astore 19
  aload 36
  astore 4
  aload 19
  aload 4
  invokevirtual java/lang/String/equals(Ljava/lang/Object;)Z
  istore 14
  iload 14
  invokestatic app/DummyClass/invokeIfStmt(Z)V
  iload 14
  ifeq Label76
  iconst_1
  istore 24
  bipush 21
  istore 25
  aload 20
  iload 24
  iload 25
  bastore
  goto Label9
Label76:
  ldc "27"
  astore 19
  aload 36
  astore 4
  aload 19
  aload 4
  invokevirtual java/lang/String/equals(Ljava/lang/Object;)Z
  istore 14
  iload 14
  invokestatic app/DummyClass/invokeIfStmt(Z)V
  iload 14
  ifeq Label77
  iconst_1
  istore 24
  bipush 22
  istore 25
  aload 20
  iload 24
  iload 25
  bastore
  goto Label9
Label77:
  ldc "28"
  astore 19
  aload 36
  astore 4
  aload 19
  aload 4
  invokevirtual java/lang/String/equals(Ljava/lang/Object;)Z
  istore 14
  iload 14
  invokestatic app/DummyClass/invokeIfStmt(Z)V
  iload 14
  ifeq Label78
  iconst_1
  istore 24
  bipush 23
  istore 25
  aload 20
  iload 24
  iload 25
  bastore
  goto Label9
Label78:
  ldc "29"
  astore 19
  aload 36
  astore 4
  aload 19
  aload 4
  invokevirtual java/lang/String/equals(Ljava/lang/Object;)Z
  istore 14
  iload 14
  invokestatic app/DummyClass/invokeIfStmt(Z)V
  iload 14
  ifeq Label79
  iconst_1
  istore 24
  bipush 28
  istore 25
  aload 20
  iload 24
  iload 25
  bastore
  goto Label9
Label79:
  ldc "30"
  astore 19
  aload 36
  astore 4
  aload 19
  aload 4
  invokevirtual java/lang/String/equals(Ljava/lang/Object;)Z
  istore 14
  iload 14
  invokestatic app/DummyClass/invokeIfStmt(Z)V
  iload 14
  ifeq Label80
  iconst_1
  istore 24
  bipush 31
  istore 25
  aload 20
  iload 24
  iload 25
  bastore
  goto Label9
Label80:
  ldc "31"
  astore 19
  aload 36
  astore 4
  aload 19
  aload 4
  invokevirtual java/lang/String/equals(Ljava/lang/Object;)Z
  istore 14
  iload 14
  invokestatic app/DummyClass/invokeIfStmt(Z)V
  iload 14
  ifeq Label9
  iconst_1
  istore 24
  iconst_4
  istore 25
  aload 20
  iload 24
  iload 25
  bastore
  goto Label9
Label11:
  ldc "1"
  astore 10
  aload 36
  astore 4
  aload 4
  aload 10
  invokevirtual java/lang/String/endsWith(Ljava/lang/String;)Z
  istore 14
  iload 14
  invokestatic app/DummyClass/invokeIfStmt(Z)V
  iload 14
  ifeq Label81
  iload 23
  istore 4
  dload 4
  invokestatic app/DummyClass/invokeIfStmt(D)V
  bipush 9
  istore 24
  iload 23
  istore 4
  iload 24
  istore 5
  iload 4
  iload 5
  if_icmplt Label9
  bipush 8
  istore 24
  bipush 9
  istore 25
  iload 24
  istore 4
  iload 25
  istore 5
  aload 19
  iload 4
  iload 5
  invokevirtual java/lang/String/substring(II)Ljava/lang/String;
  astore 36
  ldc "0"
  astore 13
  aload 36
  astore 4
  aload 13
  aload 4
  invokevirtual java/lang/String/equals(Ljava/lang/Object;)Z
  istore 14
  iload 14
  invokestatic app/DummyClass/invokeIfStmt(Z)V
  iload 14
  ifeq Label82
  iconst_0
  istore 24
  bipush 24
  istore 25
  aload 20
  iload 24
  iload 25
  bastore
Label85:
  iload 23
  istore 4
  dload 4
  invokestatic app/DummyClass/invokeIfStmt(D)V
  bipush 13
  istore 24
  iload 23
  istore 4
  iload 24
  istore 5
  iload 4
  iload 5
  if_icmplt Label9
  bipush 10
  istore 24
  bipush 13
  istore 25
  iload 24
  istore 4
  iload 25
  istore 5
  aload 19
  iload 4
  iload 5
  invokevirtual java/lang/String/substring(II)Ljava/lang/String;
  astore 36
  ldc "010"
  astore 10
  aload 36
  astore 4
  aload 4
  aload 10
  invokevirtual java/lang/String/equals(Ljava/lang/Object;)Z
  istore 14
  iload 14
  invokestatic app/DummyClass/invokeIfStmt(Z)V
  iload 14
  ifeq Label83
  iconst_1
  istore 24
  iconst_1
  istore 25
  aload 20
  iload 24
  iload 25
  bastore
  goto Label9
Label82:
  ldc "1"
  astore 13
  aload 36
  astore 4
  aload 13
  aload 4
  invokevirtual java/lang/String/equals(Ljava/lang/Object;)Z
  istore 14
  iload 14
  invokestatic app/DummyClass/invokeIfStmt(Z)V
  iload 14
  ifeq Label84
  iconst_0
  istore 24
  bipush 15
  istore 25
  aload 20
  iload 24
  iload 25
  bastore
  goto Label85
Label84:
  ldc "2"
  astore 13
  aload 36
  astore 4
  aload 13
  aload 4
  invokevirtual java/lang/String/equals(Ljava/lang/Object;)Z
  istore 14
  iload 14
  invokestatic app/DummyClass/invokeIfStmt(Z)V
  iload 14
  ifeq Label86
  iconst_0
  istore 24
  bipush 16
  istore 25
  aload 20
  iload 24
  iload 25
  bastore
  goto Label85
Label86:
  ldc "5"
  astore 13
  aload 36
  astore 4
  aload 13
  aload 4
  invokevirtual java/lang/String/equals(Ljava/lang/Object;)Z
  istore 14
  iload 14
  invokestatic app/DummyClass/invokeIfStmt(Z)V
  iload 14
  ifeq Label87
  iconst_0
  istore 24
  bipush 19
  istore 25
  aload 20
  iload 24
  iload 25
  bastore
  goto Label85
Label87:
  ldc "6"
  astore 13
  aload 36
  astore 4
  aload 13
  aload 4
  invokevirtual java/lang/String/equals(Ljava/lang/Object;)Z
  istore 14
  iload 14
  invokestatic app/DummyClass/invokeIfStmt(Z)V
  iload 14
  ifeq Label85
  iconst_0
  istore 24
  bipush 20
  istore 25
  aload 20
  iload 24
  iload 25
  bastore
  goto Label85
Label83:
  ldc "022"
  astore 10
  aload 36
  astore 4
  aload 4
  aload 10
  invokevirtual java/lang/String/equals(Ljava/lang/Object;)Z
  istore 14
  iload 14
  invokestatic app/DummyClass/invokeIfStmt(Z)V
  iload 14
  ifeq Label88
  iconst_1
  istore 24
  iconst_3
  istore 25
  aload 20
  iload 24
  iload 25
  bastore
  goto Label9
Label88:
  ldc "31"
  astore 10
  aload 36
  astore 4
  aload 4
  aload 10
  invokevirtual java/lang/String/startsWith(Ljava/lang/String;)Z
  istore 14
  iload 14
  invokestatic app/DummyClass/invokeIfStmt(Z)V
  iload 14
  ifne Label89
  ldc "33"
  astore 10
  aload 36
  astore 4
  aload 4
  aload 10
  invokevirtual java/lang/String/startsWith(Ljava/lang/String;)Z
  istore 14
  iload 14
  invokestatic app/DummyClass/invokeIfStmt(Z)V
  iload 14
  ifeq Label90
Label89:
  iconst_1
  istore 24
  bipush 9
  istore 25
  aload 20
  iload 24
  iload 25
  bastore
  goto Label9
Label90:
  ldc "35"
  astore 10
  aload 36
  astore 4
  aload 4
  aload 10
  invokevirtual java/lang/String/startsWith(Ljava/lang/String;)Z
  istore 14
  iload 14
  invokestatic app/DummyClass/invokeIfStmt(Z)V
  iload 14
  ifne Label91
  ldc "34"
  astore 10
  aload 36
  astore 4
  aload 4
  aload 10
  invokevirtual java/lang/String/startsWith(Ljava/lang/String;)Z
  istore 14
  iload 14
  invokestatic app/DummyClass/invokeIfStmt(Z)V
  iload 14
  ifeq Label92
Label91:
  iconst_1
  istore 24
  bipush 12
  istore 25
  aload 20
  iload 24
  iload 25
  bastore
  goto Label9
Label92:
  ldc "47"
  astore 10
  aload 36
  astore 4
  aload 4
  aload 10
  invokevirtual java/lang/String/startsWith(Ljava/lang/String;)Z
  istore 14
  iload 14
  invokestatic app/DummyClass/invokeIfStmt(Z)V
  iload 14
  ifne Label93
  ldc "48"
  astore 10
  aload 36
  astore 4
  aload 4
  aload 10
  invokevirtual java/lang/String/startsWith(Ljava/lang/String;)Z
  istore 14
  iload 14
  invokestatic app/DummyClass/invokeIfStmt(Z)V
  iload 14
  ifeq Label94
Label93:
  iconst_1
  istore 24
  bipush 8
  istore 25
  aload 20
  iload 24
  iload 25
  bastore
  goto Label9
Label94:
  ldc "024"
  astore 10
  aload 36
  astore 4
  aload 4
  aload 10
  invokevirtual java/lang/String/equals(Ljava/lang/Object;)Z
  istore 14
  iload 14
  invokestatic app/DummyClass/invokeIfStmt(Z)V
  iload 14
  ifne Label95
  ldc "41"
  astore 10
  aload 36
  astore 4
  aload 4
  aload 10
  invokevirtual java/lang/String/startsWith(Ljava/lang/String;)Z
  istore 14
  iload 14
  invokestatic app/DummyClass/invokeIfStmt(Z)V
  iload 14
  ifne Label95
  ldc "42"
  astore 10
  aload 36
  astore 4
  aload 4
  aload 10
  invokevirtual java/lang/String/startsWith(Ljava/lang/String;)Z
  istore 14
  iload 14
  invokestatic app/DummyClass/invokeIfStmt(Z)V
  iload 14
  ifeq Label96
Label95:
  iconst_1
  istore 24
  bipush 7
  istore 25
  aload 20
  iload 24
  iload 25
  bastore
  goto Label9
Label96:
  ldc "43"
  astore 10
  aload 36
  astore 4
  aload 4
  aload 10
  invokevirtual java/lang/String/startsWith(Ljava/lang/String;)Z
  istore 14
  iload 14
  invokestatic app/DummyClass/invokeIfStmt(Z)V
  iload 14
  ifeq Label97
  iconst_1
  istore 24
  bipush 6
  istore 25
  aload 20
  iload 24
  iload 25
  bastore
  goto Label9
Label97:
  ldc "45"
  astore 10
  aload 36
  astore 4
  aload 4
  aload 10
  invokevirtual java/lang/String/startsWith(Ljava/lang/String;)Z
  istore 14
  iload 14
  invokestatic app/DummyClass/invokeIfStmt(Z)V
  iload 14
  ifne Label98
  ldc "46"
  astore 10
  aload 36
  astore 4
  aload 4
  aload 10
  invokevirtual java/lang/String/startsWith(Ljava/lang/String;)Z
  istore 14
  iload 14
  invokestatic app/DummyClass/invokeIfStmt(Z)V
  iload 14
  ifeq Label99
Label98:
  iconst_1
  istore 24
  iconst_5
  istore 25
  aload 20
  iload 24
  iload 25
  bastore
  goto Label9
Label99:
  ldc "021"
  astore 10
  aload 36
  astore 4
  aload 4
  aload 10
  invokevirtual java/lang/String/equals(Ljava/lang/Object;)Z
  istore 14
  iload 14
  invokestatic app/DummyClass/invokeIfStmt(Z)V
  iload 14
  ifeq Label100
  iconst_1
  istore 24
  iconst_2
  istore 25
  aload 20
  iload 24
  iload 25
  bastore
  goto Label9
Label100:
  ldc "025"
  astore 10
  aload 36
  astore 4
  aload 4
  aload 10
  invokevirtual java/lang/String/equals(Ljava/lang/Object;)Z
  istore 14
  iload 14
  invokestatic app/DummyClass/invokeIfStmt(Z)V
  iload 14
  ifne Label101
  ldc "51"
  astore 10
  aload 36
  astore 4
  aload 4
  aload 10
  invokevirtual java/lang/String/startsWith(Ljava/lang/String;)Z
  istore 14
  iload 14
  invokestatic app/DummyClass/invokeIfStmt(Z)V
  iload 14
  ifne Label101
  ldc "52"
  astore 10
  aload 36
  astore 4
  aload 4
  aload 10
  invokevirtual java/lang/String/startsWith(Ljava/lang/String;)Z
  istore 14
  iload 14
  invokestatic app/DummyClass/invokeIfStmt(Z)V
  iload 14
  ifeq Label102
Label101:
  iconst_1
  istore 24
  bipush 14
  istore 25
  aload 20
  iload 24
  iload 25
  bastore
  goto Label9
Label102:
  ldc "57"
  astore 10
  aload 36
  astore 4
  aload 4
  aload 10
  invokevirtual java/lang/String/startsWith(Ljava/lang/String;)Z
  istore 14
  iload 14
  invokestatic app/DummyClass/invokeIfStmt(Z)V
  iload 14
  ifeq Label103
  iconst_1
  istore 24
  bipush 18
  istore 25
  aload 20
  iload 24
  iload 25
  bastore
  goto Label9
Label103:
  ldc "55"
  astore 10
  aload 36
  astore 4
  aload 4
  aload 10
  invokevirtual java/lang/String/startsWith(Ljava/lang/String;)Z
  istore 14
  iload 14
  invokestatic app/DummyClass/invokeIfStmt(Z)V
  iload 14
  ifne Label104
  ldc "56"
  astore 10
  aload 36
  astore 4
  aload 4
  aload 10
  invokevirtual java/lang/String/startsWith(Ljava/lang/String;)Z
  istore 14
  iload 14
  invokestatic app/DummyClass/invokeIfStmt(Z)V
  iload 14
  ifeq Label105
Label104:
  iconst_1
  istore 24
  bipush 13
  istore 25
  aload 20
  iload 24
  iload 25
  bastore
  goto Label9
Label105:
  ldc "59"
  astore 10
  aload 36
  astore 4
  aload 4
  aload 10
  invokevirtual java/lang/String/startsWith(Ljava/lang/String;)Z
  istore 14
  iload 14
  invokestatic app/DummyClass/invokeIfStmt(Z)V
  iload 14
  ifeq Label106
  iconst_1
  istore 24
  bipush 19
  istore 25
  aload 20
  iload 24
  iload 25
  bastore
  goto Label9
Label106:
  ldc "79"
  astore 10
  aload 36
  astore 4
  aload 4
  aload 10
  invokevirtual java/lang/String/startsWith(Ljava/lang/String;)Z
  istore 14
  iload 14
  invokestatic app/DummyClass/invokeIfStmt(Z)V
  iload 14
  ifne Label107
  ldc "70"
  astore 10
  aload 36
  astore 4
  aload 4
  aload 10
  invokevirtual java/lang/String/startsWith(Ljava/lang/String;)Z
  istore 14
  iload 14
  invokestatic app/DummyClass/invokeIfStmt(Z)V
  iload 14
  ifeq Label108
Label107:
  iconst_1
  istore 24
  bipush 15
  istore 25
  aload 20
  iload 24
  iload 25
  bastore
  goto Label9
Label108:
  ldc "53"
  astore 10
  aload 36
  astore 4
  aload 4
  aload 10
  invokevirtual java/lang/String/startsWith(Ljava/lang/String;)Z
  istore 14
  iload 14
  invokestatic app/DummyClass/invokeIfStmt(Z)V
  iload 14
  ifne Label109
  ldc "54"
  astore 10
  aload 36
  astore 4
  aload 4
  aload 10
  invokevirtual java/lang/String/startsWith(Ljava/lang/String;)Z
  istore 14
  iload 14
  invokestatic app/DummyClass/invokeIfStmt(Z)V
  iload 14
  ifne Label109
  ldc "63"
  astore 10
  aload 36
  astore 4
  aload 4
  aload 10
  invokevirtual java/lang/String/startsWith(Ljava/lang/String;)Z
  istore 14
  iload 14
  invokestatic app/DummyClass/invokeIfStmt(Z)V
  iload 14
  ifeq Label110
Label109:
  iconst_1
  istore 24
  bipush 11
  istore 25
  aload 20
  iload 24
  iload 25
  bastore
  goto Label9
Label110:
  ldc "37"
  astore 10
  aload 36
  astore 4
  aload 4
  aload 10
  invokevirtual java/lang/String/startsWith(Ljava/lang/String;)Z
  istore 14
  iload 14
  invokestatic app/DummyClass/invokeIfStmt(Z)V
  iload 14
  ifne Label111
  ldc "39"
  astore 10
  aload 36
  astore 4
  aload 4
  aload 10
  invokevirtual java/lang/String/startsWith(Ljava/lang/String;)Z
  istore 14
  iload 14
  invokestatic app/DummyClass/invokeIfStmt(Z)V
  iload 14
  ifeq Label112
Label111:
  iconst_1
  istore 24
  bipush 10
  istore 25
  aload 20
  iload 24
  iload 25
  bastore
  goto Label9
Label112:
  ldc "027"
  astore 10
  aload 36
  astore 4
  aload 4
  aload 10
  invokevirtual java/lang/String/equals(Ljava/lang/Object;)Z
  istore 14
  iload 14
  invokestatic app/DummyClass/invokeIfStmt(Z)V
  iload 14
  ifne Label113
  ldc "71"
  astore 10
  aload 36
  astore 4
  aload 4
  aload 10
  invokevirtual java/lang/String/startsWith(Ljava/lang/String;)Z
  istore 14
  iload 14
  invokestatic app/DummyClass/invokeIfStmt(Z)V
  iload 14
  ifne Label113
  ldc "72"
  astore 10
  aload 36
  astore 4
  aload 4
  aload 10
  invokevirtual java/lang/String/startsWith(Ljava/lang/String;)Z
  istore 14
  iload 14
  invokestatic app/DummyClass/invokeIfStmt(Z)V
  iload 14
  ifeq Label114
Label113:
  iconst_1
  istore 24
  bipush 17
  istore 25
  aload 20
  iload 24
  iload 25
  bastore
  goto Label9
Label114:
  ldc "73"
  astore 10
  aload 36
  astore 4
  aload 4
  aload 10
  invokevirtual java/lang/String/startsWith(Ljava/lang/String;)Z
  istore 14
  iload 14
  invokestatic app/DummyClass/invokeIfStmt(Z)V
  iload 14
  ifne Label115
  ldc "74"
  astore 10
  aload 36
  astore 4
  aload 4
  aload 10
  invokevirtual java/lang/String/startsWith(Ljava/lang/String;)Z
  istore 14
  iload 14
  invokestatic app/DummyClass/invokeIfStmt(Z)V
  iload 14
  ifeq Label116
Label115:
  iconst_1
  istore 24
  bipush 16
  istore 25
  aload 20
  iload 24
  iload 25
  bastore
  goto Label9
Label116:
  ldc "020"
  astore 10
  aload 36
  astore 4
  aload 4
  aload 10
  invokevirtual java/lang/String/equals(Ljava/lang/Object;)Z
  istore 14
  iload 14
  invokestatic app/DummyClass/invokeIfStmt(Z)V
  iload 14
  ifne Label117
  ldc "75"
  astore 10
  aload 36
  astore 4
  aload 4
  aload 10
  invokevirtual java/lang/String/startsWith(Ljava/lang/String;)Z
  istore 14
  iload 14
  invokestatic app/DummyClass/invokeIfStmt(Z)V
  iload 14
  ifne Label117
  ldc "76"
  astore 10
  aload 36
  astore 4
  aload 4
  aload 10
  invokevirtual java/lang/String/startsWith(Ljava/lang/String;)Z
  istore 14
  iload 14
  invokestatic app/DummyClass/invokeIfStmt(Z)V
  iload 14
  ifne Label117
  ldc "66"
  astore 10
  aload 36
  astore 4
  aload 4
  aload 10
  invokevirtual java/lang/String/startsWith(Ljava/lang/String;)Z
  istore 14
  iload 14
  invokestatic app/DummyClass/invokeIfStmt(Z)V
  iload 14
  ifeq Label118
Label117:
  iconst_1
  istore 24
  bipush 20
  istore 25
  aload 20
  iload 24
  iload 25
  bastore
  goto Label9
Label118:
  ldc "77"
  astore 10
  aload 36
  astore 4
  aload 4
  aload 10
  invokevirtual java/lang/String/startsWith(Ljava/lang/String;)Z
  istore 14
  iload 14
  invokestatic app/DummyClass/invokeIfStmt(Z)V
  iload 14
  ifeq Label119
  iconst_1
  istore 24
  bipush 29
  istore 25
  aload 20
  iload 24
  iload 25
  bastore
  goto Label9
Label119:
  ldc "898"
  astore 10
  aload 36
  astore 4
  aload 4
  aload 10
  invokevirtual java/lang/String/equals(Ljava/lang/Object;)Z
  istore 14
  iload 14
  invokestatic app/DummyClass/invokeIfStmt(Z)V
  iload 14
  ifeq Label120
  iconst_1
  istore 24
  bipush 27
  istore 25
  aload 20
  iload 24
  iload 25
  bastore
  goto Label9
Label120:
  ldc "028"
  astore 10
  aload 36
  astore 4
  aload 4
  aload 10
  invokevirtual java/lang/String/equals(Ljava/lang/Object;)Z
  istore 14
  iload 14
  invokestatic app/DummyClass/invokeIfStmt(Z)V
  iload 14
  ifne Label121
  ldc "81"
  astore 10
  aload 36
  astore 4
  aload 4
  aload 10
  invokevirtual java/lang/String/startsWith(Ljava/lang/String;)Z
  istore 14
  iload 14
  invokestatic app/DummyClass/invokeIfStmt(Z)V
  iload 14
  ifne Label121
  ldc "82"
  astore 10
  aload 36
  astore 4
  aload 4
  aload 10
  invokevirtual java/lang/String/startsWith(Ljava/lang/String;)Z
  istore 14
  iload 14
  invokestatic app/DummyClass/invokeIfStmt(Z)V
  iload 14
  ifne Label121
  ldc "83"
  astore 10
  aload 36
  astore 4
  aload 4
  aload 10
  invokevirtual java/lang/String/startsWith(Ljava/lang/String;)Z
  istore 14
  iload 14
  invokestatic app/DummyClass/invokeIfStmt(Z)V
  iload 14
  ifeq Label122
Label121:
  iconst_1
  istore 24
  bipush 24
  istore 25
  aload 20
  iload 24
  iload 25
  bastore
  goto Label9
Label122:
  ldc "85"
  astore 10
  aload 36
  astore 4
  aload 4
  aload 10
  invokevirtual java/lang/String/startsWith(Ljava/lang/String;)Z
  istore 14
  iload 14
  invokestatic app/DummyClass/invokeIfStmt(Z)V
  iload 14
  ifne Label9
  ldc "87"
  astore 10
  aload 36
  astore 4
  aload 4
  aload 10
  invokevirtual java/lang/String/startsWith(Ljava/lang/String;)Z
  istore 14
  iload 14
  invokestatic app/DummyClass/invokeIfStmt(Z)V
  iload 14
  ifne Label123
  ldc "88"
  astore 10
  aload 36
  astore 4
  aload 4
  aload 10
  invokevirtual java/lang/String/startsWith(Ljava/lang/String;)Z
  istore 14
  iload 14
  invokestatic app/DummyClass/invokeIfStmt(Z)V
  iload 14
  ifne Label123
  ldc "69"
  astore 10
  aload 36
  astore 4
  aload 4
  aload 10
  invokevirtual java/lang/String/startsWith(Ljava/lang/String;)Z
  istore 14
  iload 14
  invokestatic app/DummyClass/invokeIfStmt(Z)V
  iload 14
  ifeq Label124
Label123:
  iconst_1
  istore 24
  bipush 26
  istore 25
  aload 20
  iload 24
  iload 25
  bastore
  goto Label9
Label124:
  ldc "89"
  astore 10
  aload 36
  astore 4
  aload 4
  aload 10
  invokevirtual java/lang/String/startsWith(Ljava/lang/String;)Z
  istore 14
  iload 14
  invokestatic app/DummyClass/invokeIfStmt(Z)V
  iload 14
  ifeq Label125
  iconst_1
  istore 24
  bipush 30
  istore 25
  aload 20
  iload 24
  iload 25
  bastore
  goto Label9
Label125:
  ldc "029"
  astore 10
  aload 36
  astore 4
  aload 4
  aload 10
  invokevirtual java/lang/String/equals(Ljava/lang/Object;)Z
  istore 14
  iload 14
  invokestatic app/DummyClass/invokeIfStmt(Z)V
  iload 14
  ifne Label126
  ldc "91"
  astore 10
  aload 36
  astore 4
  aload 4
  aload 10
  invokevirtual java/lang/String/startsWith(Ljava/lang/String;)Z
  istore 14
  iload 14
  invokestatic app/DummyClass/invokeIfStmt(Z)V
  iload 14
  ifeq Label127
Label126:
  iconst_1
  istore 24
  bipush 21
  istore 25
  aload 20
  iload 24
  iload 25
  bastore
  goto Label9
Label127:
  ldc "93"
  astore 10
  aload 36
  astore 4
  aload 4
  aload 10
  invokevirtual java/lang/String/startsWith(Ljava/lang/String;)Z
  istore 14
  iload 14
  invokestatic app/DummyClass/invokeIfStmt(Z)V
  iload 14
  ifne Label128
  ldc "94"
  astore 10
  aload 36
  astore 4
  aload 4
  aload 10
  invokevirtual java/lang/String/startsWith(Ljava/lang/String;)Z
  istore 14
  iload 14
  invokestatic app/DummyClass/invokeIfStmt(Z)V
  iload 14
  ifeq Label129
Label128:
  iconst_1
  istore 24
  bipush 22
  istore 25
  aload 20
  iload 24
  iload 25
  bastore
  goto Label9
Label129:
  ldc "97"
  astore 10
  aload 36
  astore 4
  aload 4
  aload 10
  invokevirtual java/lang/String/startsWith(Ljava/lang/String;)Z
  istore 14
  iload 14
  invokestatic app/DummyClass/invokeIfStmt(Z)V
  iload 14
  ifeq Label130
  iconst_1
  istore 24
  bipush 23
  istore 25
  aload 20
  iload 24
  iload 25
  bastore
  goto Label9
Label130:
  ldc "95"
  astore 10
  aload 36
  astore 4
  aload 4
  aload 10
  invokevirtual java/lang/String/startsWith(Ljava/lang/String;)Z
  istore 14
  iload 14
  invokestatic app/DummyClass/invokeIfStmt(Z)V
  iload 14
  ifeq Label131
  iconst_1
  istore 24
  bipush 28
  istore 25
  aload 20
  iload 24
  iload 25
  bastore
  goto Label9
Label131:
  ldc "90"
  astore 10
  aload 36
  astore 4
  aload 4
  aload 10
  invokevirtual java/lang/String/startsWith(Ljava/lang/String;)Z
  istore 14
  iload 14
  invokestatic app/DummyClass/invokeIfStmt(Z)V
  iload 14
  ifne Label132
  ldc "99"
  astore 10
  aload 36
  astore 4
  aload 4
  aload 10
  invokevirtual java/lang/String/startsWith(Ljava/lang/String;)Z
  istore 14
  iload 14
  invokestatic app/DummyClass/invokeIfStmt(Z)V
  iload 14
  ifeq Label133
Label132:
  iconst_1
  istore 24
  bipush 31
  istore 25
  aload 20
  iload 24
  iload 25
  bastore
  goto Label9
Label133:
  ldc "023"
  astore 10
  aload 36
  astore 4
  aload 4
  aload 10
  invokevirtual java/lang/String/equals(Ljava/lang/Object;)Z
  istore 14
  iload 14
  invokestatic app/DummyClass/invokeIfStmt(Z)V
  iload 14
  ifeq Label9
  iconst_1
  istore 24
  iconst_4
  istore 25
  aload 20
  iload 24
  iload 25
  bastore
  goto Label9
Label81:
  ldc "3"
  astore 10
  aload 36
  astore 4
  aload 4
  aload 10
  invokevirtual java/lang/String/endsWith(Ljava/lang/String;)Z
  istore 14
  iload 14
  invokestatic app/DummyClass/invokeIfStmt(Z)V
  iload 14
  ifeq Label9
  iload 23
  istore 4
  dload 4
  invokestatic app/DummyClass/invokeIfStmt(D)V
  bipush 9
  istore 24
  iload 23
  istore 4
  iload 24
  istore 5
  iload 4
  iload 5
  if_icmplt Label9
  bipush 8
  istore 24
  bipush 9
  istore 25
  iload 24
  istore 4
  iload 25
  istore 5
  aload 19
  iload 4
  iload 5
  invokevirtual java/lang/String/substring(II)Ljava/lang/String;
  astore 36
  ldc "3"
  astore 13
  aload 36
  astore 4
  aload 13
  aload 4
  invokevirtual java/lang/String/equals(Ljava/lang/Object;)Z
  istore 14
  iload 14
  invokestatic app/DummyClass/invokeIfStmt(Z)V
  iload 14
  ifeq Label134
  iconst_0
  istore 24
  bipush 17
  istore 25
  aload 20
  iload 24
  iload 25
  bastore
Label137:
  iload 23
  istore 4
  dload 4
  invokestatic app/DummyClass/invokeIfStmt(D)V
  bipush 13
  istore 24
  iload 23
  istore 4
  iload 24
  istore 5
  iload 4
  iload 5
  if_icmplt Label9
  bipush 10
  istore 24
  bipush 13
  istore 25
  iload 24
  istore 4
  iload 25
  istore 5
  aload 19
  iload 4
  iload 5
  invokevirtual java/lang/String/substring(II)Ljava/lang/String;
  astore 36
  ldc "010"
  astore 19
  aload 36
  astore 4
  aload 19
  aload 4
  invokevirtual java/lang/String/equals(Ljava/lang/Object;)Z
  istore 14
  iload 14
  invokestatic app/DummyClass/invokeIfStmt(Z)V
  iload 14
  ifeq Label135
  iconst_1
  istore 24
  iconst_1
  istore 25
  aload 20
  iload 24
  iload 25
  bastore
  goto Label9
Label134:
  ldc "4"
  astore 13
  aload 36
  astore 4
  aload 13
  aload 4
  invokevirtual java/lang/String/equals(Ljava/lang/Object;)Z
  istore 14
  iload 14
  invokestatic app/DummyClass/invokeIfStmt(Z)V
  iload 14
  ifeq Label136
  iconst_0
  istore 24
  bipush 18
  istore 25
  aload 20
  iload 24
  iload 25
  bastore
  goto Label137
Label136:
  ldc "7"
  astore 13
  aload 36
  astore 4
  aload 13
  aload 4
  invokevirtual java/lang/String/equals(Ljava/lang/Object;)Z
  istore 14
  iload 14
  invokestatic app/DummyClass/invokeIfStmt(Z)V
  iload 14
  ifeq Label138
  iconst_0
  istore 24
  bipush 21
  istore 25
  aload 20
  iload 24
  iload 25
  bastore
  goto Label137
Label138:
  ldc "8"
  astore 13
  aload 36
  astore 4
  aload 13
  aload 4
  invokevirtual java/lang/String/equals(Ljava/lang/Object;)Z
  istore 14
  iload 14
  invokestatic app/DummyClass/invokeIfStmt(Z)V
  iload 14
  ifeq Label139
  iconst_0
  istore 24
  bipush 22
  istore 25
  aload 20
  iload 24
  iload 25
  bastore
  goto Label137
Label139:
  ldc "9"
  astore 13
  aload 36
  astore 4
  aload 13
  aload 4
  invokevirtual java/lang/String/equals(Ljava/lang/Object;)Z
  istore 14
  iload 14
  invokestatic app/DummyClass/invokeIfStmt(Z)V
  iload 14
  ifeq Label137
  iconst_0
  istore 24
  bipush 23
  istore 25
  aload 20
  iload 24
  iload 25
  bastore
  goto Label137
Label135:
  ldc "022"
  astore 19
  aload 36
  astore 4
  aload 19
  aload 4
  invokevirtual java/lang/String/equals(Ljava/lang/Object;)Z
  istore 14
  iload 14
  invokestatic app/DummyClass/invokeIfStmt(Z)V
  iload 14
  ifeq Label140
  iconst_1
  istore 24
  iconst_3
  istore 25
  aload 20
  iload 24
  iload 25
  bastore
  goto Label9
Label140:
  ldc "31"
  astore 10
  aload 36
  astore 4
  aload 4
  aload 10
  invokevirtual java/lang/String/startsWith(Ljava/lang/String;)Z
  istore 14
  iload 14
  invokestatic app/DummyClass/invokeIfStmt(Z)V
  iload 14
  ifne Label141
  ldc "33"
  astore 10
  aload 36
  astore 4
  aload 4
  aload 10
  invokevirtual java/lang/String/startsWith(Ljava/lang/String;)Z
  istore 14
  iload 14
  invokestatic app/DummyClass/invokeIfStmt(Z)V
  iload 14
  ifeq Label142
Label141:
  iconst_1
  istore 24
  bipush 9
  istore 25
  aload 20
  iload 24
  iload 25
  bastore
  goto Label9
Label142:
  ldc "35"
  astore 10
  aload 36
  astore 4
  aload 4
  aload 10
  invokevirtual java/lang/String/startsWith(Ljava/lang/String;)Z
  istore 14
  iload 14
  invokestatic app/DummyClass/invokeIfStmt(Z)V
  iload 14
  ifne Label143
  ldc "34"
  astore 10
  aload 36
  astore 4
  aload 4
  aload 10
  invokevirtual java/lang/String/startsWith(Ljava/lang/String;)Z
  istore 14
  iload 14
  invokestatic app/DummyClass/invokeIfStmt(Z)V
  iload 14
  ifeq Label144
Label143:
  iconst_1
  istore 24
  bipush 12
  istore 25
  aload 20
  iload 24
  iload 25
  bastore
  goto Label9
Label144:
  ldc "47"
  astore 10
  aload 36
  astore 4
  aload 4
  aload 10
  invokevirtual java/lang/String/startsWith(Ljava/lang/String;)Z
  istore 14
  iload 14
  invokestatic app/DummyClass/invokeIfStmt(Z)V
  iload 14
  ifne Label145
  ldc "48"
  astore 10
  aload 36
  astore 4
  aload 4
  aload 10
  invokevirtual java/lang/String/startsWith(Ljava/lang/String;)Z
  istore 14
  iload 14
  invokestatic app/DummyClass/invokeIfStmt(Z)V
  iload 14
  ifeq Label146
Label145:
  iconst_1
  istore 24
  bipush 8
  istore 25
  aload 20
  iload 24
  iload 25
  bastore
  goto Label9
Label146:
  ldc "024"
  astore 19
  aload 36
  astore 4
  aload 19
  aload 4
  invokevirtual java/lang/String/equals(Ljava/lang/Object;)Z
  istore 14
  iload 14
  invokestatic app/DummyClass/invokeIfStmt(Z)V
  iload 14
  ifne Label147
  ldc "41"
  astore 10
  aload 36
  astore 4
  aload 4
  aload 10
  invokevirtual java/lang/String/startsWith(Ljava/lang/String;)Z
  istore 14
  iload 14
  invokestatic app/DummyClass/invokeIfStmt(Z)V
  iload 14
  ifne Label147
  ldc "42"
  astore 10
  aload 36
  astore 4
  aload 4
  aload 10
  invokevirtual java/lang/String/startsWith(Ljava/lang/String;)Z
  istore 14
  iload 14
  invokestatic app/DummyClass/invokeIfStmt(Z)V
  iload 14
  ifeq Label148
Label147:
  iconst_1
  istore 24
  bipush 7
  istore 25
  aload 20
  iload 24
  iload 25
  bastore
  goto Label9
Label148:
  ldc "43"
  astore 10
  aload 36
  astore 4
  aload 4
  aload 10
  invokevirtual java/lang/String/startsWith(Ljava/lang/String;)Z
  istore 14
  iload 14
  invokestatic app/DummyClass/invokeIfStmt(Z)V
  iload 14
  ifeq Label149
  iconst_1
  istore 24
  bipush 6
  istore 25
  aload 20
  iload 24
  iload 25
  bastore
  goto Label9
Label149:
  ldc "45"
  astore 10
  aload 36
  astore 4
  aload 4
  aload 10
  invokevirtual java/lang/String/startsWith(Ljava/lang/String;)Z
  istore 14
  iload 14
  invokestatic app/DummyClass/invokeIfStmt(Z)V
  iload 14
  ifne Label150
  ldc "46"
  astore 10
  aload 36
  astore 4
  aload 4
  aload 10
  invokevirtual java/lang/String/startsWith(Ljava/lang/String;)Z
  istore 14
  iload 14
  invokestatic app/DummyClass/invokeIfStmt(Z)V
  iload 14
  ifeq Label151
Label150:
  iconst_1
  istore 24
  iconst_5
  istore 25
  aload 20
  iload 24
  iload 25
  bastore
  goto Label9
Label151:
  ldc "021"
  astore 19
  aload 36
  astore 4
  aload 19
  aload 4
  invokevirtual java/lang/String/equals(Ljava/lang/Object;)Z
  istore 14
  iload 14
  invokestatic app/DummyClass/invokeIfStmt(Z)V
  iload 14
  ifeq Label152
  iconst_1
  istore 24
  iconst_2
  istore 25
  aload 20
  iload 24
  iload 25
  bastore
  goto Label9
Label152:
  ldc "025"
  astore 10
  aload 36
  astore 4
  aload 4
  aload 10
  invokevirtual java/lang/String/equals(Ljava/lang/Object;)Z
  istore 14
  iload 14
  invokestatic app/DummyClass/invokeIfStmt(Z)V
  iload 14
  ifne Label153
  ldc "51"
  astore 10
  aload 36
  astore 4
  aload 4
  aload 10
  invokevirtual java/lang/String/startsWith(Ljava/lang/String;)Z
  istore 14
  iload 14
  invokestatic app/DummyClass/invokeIfStmt(Z)V
  iload 14
  ifne Label153
  ldc "52"
  astore 10
  aload 36
  astore 4
  aload 4
  aload 10
  invokevirtual java/lang/String/startsWith(Ljava/lang/String;)Z
  istore 14
  iload 14
  invokestatic app/DummyClass/invokeIfStmt(Z)V
  iload 14
  ifeq Label154
Label153:
  iconst_1
  istore 24
  bipush 14
  istore 25
  aload 20
  iload 24
  iload 25
  bastore
  goto Label9
Label154:
  ldc "57"
  astore 10
  aload 36
  astore 4
  aload 4
  aload 10
  invokevirtual java/lang/String/startsWith(Ljava/lang/String;)Z
  istore 14
  iload 14
  invokestatic app/DummyClass/invokeIfStmt(Z)V
  iload 14
  ifne Label155
  ldc "58"
  astore 10
  aload 36
  astore 4
  aload 4
  aload 10
  invokevirtual java/lang/String/startsWith(Ljava/lang/String;)Z
  istore 14
  iload 14
  invokestatic app/DummyClass/invokeIfStmt(Z)V
  iload 14
  ifeq Label156
Label155:
  iconst_1
  istore 24
  bipush 18
  istore 25
  aload 20
  iload 24
  iload 25
  bastore
  goto Label9
Label156:
  ldc "55"
  astore 10
  aload 36
  astore 4
  aload 4
  aload 10
  invokevirtual java/lang/String/startsWith(Ljava/lang/String;)Z
  istore 14
  iload 14
  invokestatic app/DummyClass/invokeIfStmt(Z)V
  iload 14
  ifne Label157
  ldc "56"
  astore 10
  aload 36
  astore 4
  aload 4
  aload 10
  invokevirtual java/lang/String/startsWith(Ljava/lang/String;)Z
  istore 14
  iload 14
  invokestatic app/DummyClass/invokeIfStmt(Z)V
  iload 14
  ifeq Label158
Label157:
  iconst_1
  istore 24
  bipush 13
  istore 25
  aload 20
  iload 24
  iload 25
  bastore
  goto Label9
Label158:
  ldc "59"
  astore 10
  aload 36
  astore 4
  aload 4
  aload 10
  invokevirtual java/lang/String/startsWith(Ljava/lang/String;)Z
  istore 14
  iload 14
  invokestatic app/DummyClass/invokeIfStmt(Z)V
  iload 14
  ifeq Label159
  iconst_1
  istore 24
  bipush 19
  istore 25
  aload 20
  iload 24
  iload 25
  bastore
  goto Label9
Label159:
  ldc "79"
  astore 10
  aload 36
  astore 4
  aload 4
  aload 10
  invokevirtual java/lang/String/startsWith(Ljava/lang/String;)Z
  istore 14
  iload 14
  invokestatic app/DummyClass/invokeIfStmt(Z)V
  iload 14
  ifne Label160
  ldc "70"
  astore 10
  aload 36
  astore 4
  aload 4
  aload 10
  invokevirtual java/lang/String/startsWith(Ljava/lang/String;)Z
  istore 14
  iload 14
  invokestatic app/DummyClass/invokeIfStmt(Z)V
  iload 14
  ifeq Label161
Label160:
  iconst_1
  istore 24
  bipush 15
  istore 25
  aload 20
  iload 24
  iload 25
  bastore
  goto Label9
Label161:
  ldc "53"
  astore 10
  aload 36
  astore 4
  aload 4
  aload 10
  invokevirtual java/lang/String/startsWith(Ljava/lang/String;)Z
  istore 14
  iload 14
  invokestatic app/DummyClass/invokeIfStmt(Z)V
  iload 14
  ifne Label162
  ldc "54"
  astore 10
  aload 36
  astore 4
  aload 4
  aload 10
  invokevirtual java/lang/String/startsWith(Ljava/lang/String;)Z
  istore 14
  iload 14
  invokestatic app/DummyClass/invokeIfStmt(Z)V
  iload 14
  ifne Label162
  ldc "63"
  astore 10
  aload 36
  astore 4
  aload 4
  aload 10
  invokevirtual java/lang/String/startsWith(Ljava/lang/String;)Z
  istore 14
  iload 14
  invokestatic app/DummyClass/invokeIfStmt(Z)V
  iload 14
  ifeq Label163
Label162:
  iconst_1
  istore 24
  bipush 11
  istore 25
  aload 20
  iload 24
  iload 25
  bastore
  goto Label9
Label163:
  ldc "37"
  astore 10
  aload 36
  astore 4
  aload 4
  aload 10
  invokevirtual java/lang/String/startsWith(Ljava/lang/String;)Z
  istore 14
  iload 14
  invokestatic app/DummyClass/invokeIfStmt(Z)V
  iload 14
  ifne Label164
  ldc "39"
  astore 10
  aload 36
  astore 4
  aload 4
  aload 10
  invokevirtual java/lang/String/startsWith(Ljava/lang/String;)Z
  istore 14
  iload 14
  invokestatic app/DummyClass/invokeIfStmt(Z)V
  iload 14
  ifeq Label165
Label164:
  iconst_1
  istore 24
  bipush 10
  istore 25
  aload 20
  iload 24
  iload 25
  bastore
  goto Label9
Label165:
  ldc "027"
  astore 19
  aload 36
  astore 4
  aload 19
  aload 4
  invokevirtual java/lang/String/equals(Ljava/lang/Object;)Z
  istore 14
  iload 14
  invokestatic app/DummyClass/invokeIfStmt(Z)V
  iload 14
  ifne Label166
  ldc "71"
  astore 10
  aload 36
  astore 4
  aload 4
  aload 10
  invokevirtual java/lang/String/startsWith(Ljava/lang/String;)Z
  istore 14
  iload 14
  invokestatic app/DummyClass/invokeIfStmt(Z)V
  iload 14
  ifne Label166
  ldc "72"
  astore 10
  aload 36
  astore 4
  aload 4
  aload 10
  invokevirtual java/lang/String/startsWith(Ljava/lang/String;)Z
  istore 14
  iload 14
  invokestatic app/DummyClass/invokeIfStmt(Z)V
  iload 14
  ifeq Label167
Label166:
  iconst_1
  istore 24
  bipush 17
  istore 25
  aload 20
  iload 24
  iload 25
  bastore
  goto Label9
Label167:
  ldc "73"
  astore 10
  aload 36
  astore 4
  aload 4
  aload 10
  invokevirtual java/lang/String/startsWith(Ljava/lang/String;)Z
  istore 14
  iload 14
  invokestatic app/DummyClass/invokeIfStmt(Z)V
  iload 14
  ifne Label168
  ldc "74"
  astore 10
  aload 36
  astore 4
  aload 4
  aload 10
  invokevirtual java/lang/String/startsWith(Ljava/lang/String;)Z
  istore 14
  iload 14
  invokestatic app/DummyClass/invokeIfStmt(Z)V
  iload 14
  ifeq Label169
Label168:
  iconst_1
  istore 24
  bipush 16
  istore 25
  aload 20
  iload 24
  iload 25
  bastore
  goto Label9
Label169:
  ldc "020"
  astore 19
  aload 36
  astore 4
  aload 19
  aload 4
  invokevirtual java/lang/String/equals(Ljava/lang/Object;)Z
  istore 14
  iload 14
  invokestatic app/DummyClass/invokeIfStmt(Z)V
  iload 14
  ifne Label170
  ldc "75"
  astore 10
  aload 36
  astore 4
  aload 4
  aload 10
  invokevirtual java/lang/String/startsWith(Ljava/lang/String;)Z
  istore 14
  iload 14
  invokestatic app/DummyClass/invokeIfStmt(Z)V
  iload 14
  ifne Label170
  ldc "76"
  astore 10
  aload 36
  astore 4
  aload 4
  aload 10
  invokevirtual java/lang/String/startsWith(Ljava/lang/String;)Z
  istore 14
  iload 14
  invokestatic app/DummyClass/invokeIfStmt(Z)V
  iload 14
  ifne Label170
  ldc "66"
  astore 10
  aload 36
  astore 4
  aload 4
  aload 10
  invokevirtual java/lang/String/startsWith(Ljava/lang/String;)Z
  istore 14
  iload 14
  invokestatic app/DummyClass/invokeIfStmt(Z)V
  iload 14
  ifeq Label171
Label170:
  iconst_1
  istore 24
  bipush 20
  istore 25
  aload 20
  iload 24
  iload 25
  bastore
  goto Label9
Label171:
  ldc "77"
  astore 10
  aload 36
  astore 4
  aload 4
  aload 10
  invokevirtual java/lang/String/startsWith(Ljava/lang/String;)Z
  istore 14
  iload 14
  invokestatic app/DummyClass/invokeIfStmt(Z)V
  iload 14
  ifeq Label172
  iconst_1
  istore 24
  bipush 29
  istore 25
  aload 20
  iload 24
  iload 25
  bastore
  goto Label9
Label172:
  ldc "898"
  astore 19
  aload 36
  astore 4
  aload 19
  aload 4
  invokevirtual java/lang/String/equals(Ljava/lang/Object;)Z
  istore 14
  iload 14
  invokestatic app/DummyClass/invokeIfStmt(Z)V
  iload 14
  ifeq Label173
  iconst_1
  istore 24
  bipush 27
  istore 25
  aload 20
  iload 24
  iload 25
  bastore
  goto Label9
Label173:
  ldc "028"
  astore 19
  aload 36
  astore 4
  aload 19
  aload 4
  invokevirtual java/lang/String/equals(Ljava/lang/Object;)Z
  istore 14
  iload 14
  invokestatic app/DummyClass/invokeIfStmt(Z)V
  iload 14
  ifne Label174
  ldc "81"
  astore 10
  aload 36
  astore 4
  aload 4
  aload 10
  invokevirtual java/lang/String/startsWith(Ljava/lang/String;)Z
  istore 14
  iload 14
  invokestatic app/DummyClass/invokeIfStmt(Z)V
  iload 14
  ifne Label174
  ldc "82"
  astore 10
  aload 36
  astore 4
  aload 4
  aload 10
  invokevirtual java/lang/String/startsWith(Ljava/lang/String;)Z
  istore 14
  iload 14
  invokestatic app/DummyClass/invokeIfStmt(Z)V
  iload 14
  ifne Label174
  ldc "83"
  astore 10
  aload 36
  astore 4
  aload 4
  aload 10
  invokevirtual java/lang/String/startsWith(Ljava/lang/String;)Z
  istore 14
  iload 14
  invokestatic app/DummyClass/invokeIfStmt(Z)V
  iload 14
  ifeq Label175
Label174:
  iconst_1
  istore 24
  bipush 24
  istore 25
  aload 20
  iload 24
  iload 25
  bastore
  goto Label9
Label175:
  ldc "85"
  astore 10
  aload 36
  astore 4
  aload 4
  aload 10
  invokevirtual java/lang/String/startsWith(Ljava/lang/String;)Z
  istore 14
  iload 14
  invokestatic app/DummyClass/invokeIfStmt(Z)V
  iload 14
  ifeq Label176
  iconst_1
  istore 24
  bipush 25
  istore 25
  aload 20
  iload 24
  iload 25
  bastore
  goto Label9
Label176:
  ldc "87"
  astore 10
  aload 36
  astore 4
  aload 4
  aload 10
  invokevirtual java/lang/String/startsWith(Ljava/lang/String;)Z
  istore 14
  iload 14
  invokestatic app/DummyClass/invokeIfStmt(Z)V
  iload 14
  ifne Label177
  ldc "88"
  astore 10
  aload 36
  astore 4
  aload 4
  aload 10
  invokevirtual java/lang/String/startsWith(Ljava/lang/String;)Z
  istore 14
  iload 14
  invokestatic app/DummyClass/invokeIfStmt(Z)V
  iload 14
  ifne Label177
  ldc "69"
  astore 10
  aload 36
  astore 4
  aload 4
  aload 10
  invokevirtual java/lang/String/startsWith(Ljava/lang/String;)Z
  istore 14
  iload 14
  invokestatic app/DummyClass/invokeIfStmt(Z)V
  iload 14
  ifeq Label178
Label177:
  iconst_1
  istore 24
  bipush 26
  istore 25
  aload 20
  iload 24
  iload 25
  bastore
  goto Label9
Label178:
  ldc "89"
  astore 10
  aload 36
  astore 4
  aload 4
  aload 10
  invokevirtual java/lang/String/startsWith(Ljava/lang/String;)Z
  istore 14
  iload 14
  invokestatic app/DummyClass/invokeIfStmt(Z)V
  iload 14
  ifeq Label179
  iconst_1
  istore 24
  bipush 30
  istore 25
  aload 20
  iload 24
  iload 25
  bastore
  goto Label9
Label179:
  ldc "029"
  astore 19
  aload 36
  astore 4
  aload 19
  aload 4
  invokevirtual java/lang/String/equals(Ljava/lang/Object;)Z
  istore 14
  iload 14
  invokestatic app/DummyClass/invokeIfStmt(Z)V
  iload 14
  ifne Label180
  ldc "91"
  astore 10
  aload 36
  astore 4
  aload 4
  aload 10
  invokevirtual java/lang/String/startsWith(Ljava/lang/String;)Z
  istore 14
  iload 14
  invokestatic app/DummyClass/invokeIfStmt(Z)V
  iload 14
  ifeq Label181
Label180:
  iconst_1
  istore 24
  bipush 21
  istore 25
  aload 20
  iload 24
  iload 25
  bastore
  goto Label9
Label181:
  ldc "93"
  astore 10
  aload 36
  astore 4
  aload 4
  aload 10
  invokevirtual java/lang/String/startsWith(Ljava/lang/String;)Z
  istore 14
  iload 14
  invokestatic app/DummyClass/invokeIfStmt(Z)V
  iload 14
  ifne Label182
  ldc "94"
  astore 10
  aload 36
  astore 4
  aload 4
  aload 10
  invokevirtual java/lang/String/startsWith(Ljava/lang/String;)Z
  istore 14
  iload 14
  invokestatic app/DummyClass/invokeIfStmt(Z)V
  iload 14
  ifeq Label183
Label182:
  iconst_1
  istore 24
  bipush 22
  istore 25
  aload 20
  iload 24
  iload 25
  bastore
  goto Label9
Label183:
  ldc "97"
  astore 10
  aload 36
  astore 4
  aload 4
  aload 10
  invokevirtual java/lang/String/startsWith(Ljava/lang/String;)Z
  istore 14
  iload 14
  invokestatic app/DummyClass/invokeIfStmt(Z)V
  iload 14
  ifeq Label184
  iconst_1
  istore 24
  bipush 23
  istore 25
  aload 20
  iload 24
  iload 25
  bastore
  goto Label9
Label184:
  ldc "95"
  astore 10
  aload 36
  astore 4
  aload 4
  aload 10
  invokevirtual java/lang/String/startsWith(Ljava/lang/String;)Z
  istore 14
  iload 14
  invokestatic app/DummyClass/invokeIfStmt(Z)V
  iload 14
  ifeq Label185
  iconst_1
  istore 24
  bipush 28
  istore 25
  aload 20
  iload 24
  iload 25
  bastore
  goto Label9
Label185:
  ldc "90"
  astore 10
  aload 36
  astore 4
  aload 4
  aload 10
  invokevirtual java/lang/String/startsWith(Ljava/lang/String;)Z
  istore 14
  iload 14
  invokestatic app/DummyClass/invokeIfStmt(Z)V
  iload 14
  ifne Label186
  ldc "99"
  astore 10
  aload 36
  astore 4
  aload 4
  aload 10
  invokevirtual java/lang/String/startsWith(Ljava/lang/String;)Z
  istore 14
  iload 14
  invokestatic app/DummyClass/invokeIfStmt(Z)V
  iload 14
  ifeq Label187
Label186:
  iconst_1
  istore 24
  bipush 31
  istore 25
  aload 20
  iload 24
  iload 25
  bastore
  goto Label9
Label187:
  ldc "023"
  astore 19
  aload 36
  astore 4
  aload 19
  aload 4
  invokevirtual java/lang/String/equals(Ljava/lang/Object;)Z
  istore 14
  iload 14
  invokestatic app/DummyClass/invokeIfStmt(Z)V
  iload 14
  ifeq Label9
  iconst_1
  istore 24
  iconst_4
  istore 25
  aload 20
  iload 24
  iload 25
  bastore
  goto Label9
Label203:
  astore 44
  new java/lang/StringBuilder
  astore 37
  ldc "CONFIGURATION ERROR:  Incorrect Adwo PID.  Should 32 [a-z,0-9] characters:  "
  astore 10
  aload 37
  astore 4
  aload 4
  aload 10
  invokespecial java/lang/StringBuilder/<init>(Ljava/lang/String;)V
  getstatic com/adwo/adsdk/FSAdUtil/c [B
  astore 20
  aload 37
  astore 4
  aload 20
  astore 5
  aload 4
  aload 5
  invokevirtual java/lang/StringBuilder/append(Ljava/lang/Object;)Ljava/lang/StringBuilder;
  astore 37
  aload 37
  astore 4
  aload 4
  invokevirtual java/lang/StringBuilder/toString()Ljava/lang/String;
  astore 36
  ldc "Adwo SDK"
  astore 10
  aload 36
  astore 4
  aload 10
  aload 4
  invokestatic android/util/Log/e(Ljava/lang/String;Ljava/lang/String;)I
  pop
  goto Label188
Label196:
  astore 45
  goto Label7
Label197:
  astore 46
  goto Label7
Label198:
  astore 47
  goto Label7
Label199:
  astore 48
  goto Label7
Label200:
  astore 49
  goto Label7
Label193:
  astore 50
  goto Label6
Label0:
  iconst_0
  dstore 15
  goto Label189
  nop
.end <method>

.method public final setSplashAdListener(Lcom/adwo/adsdk/SplashAdListener;)V
.limit locals 2
.limit stack 200
  nop
  aload_0
  aload_1
  putfield com/adwo/adsdk/FSAdUtil/z Lcom/adwo/adsdk/SplashAdListener;
  return
  nop
.end <method>

