.source CaseeSourceAdapter.java
.class public  com/admogo/adapters/CaseeSourceAdapter
.super com/admogo/adapters/AdMogoAdapter
.field private static "caseeAD" Lcom/admogo/obj/CaseeAD;

.method public <init>(Lcom/admogo/AdMogoLayout;Lcom/admogo/obj/Ration;)V
.limit locals 3
.limit stack 200
  nop
  aload_0
  aload_1
  aload_2
  invokespecial com/admogo/adapters/AdMogoAdapter/<init>(Lcom/admogo/AdMogoLayout;Lcom/admogo/obj/Ration;)V
  return
  nop
.end <method>

.method static access$0(Lcom/admogo/AdMogoLayout;Ljava/lang/String;)Lcom/admogo/obj/CaseeAD;
  .synthetic
.limit locals 3
.limit stack 200
  nop
  aload_0
  aload_1
  invokestatic com/admogo/adapters/CaseeSourceAdapter/getCaseeAD(Lcom/admogo/AdMogoLayout;Ljava/lang/String;)Lcom/admogo/obj/CaseeAD;
  astore_2
  aload_2
  areturn
  nop
.end <method>

.method static access$1(Lcom/admogo/obj/CaseeAD;)V
  .synthetic
.limit locals 1
.limit stack 200
  nop
  aload_0
  putstatic com/admogo/adapters/CaseeSourceAdapter/caseeAD Lcom/admogo/obj/CaseeAD;
  return
  nop
.end <method>

.method static access$2()Lcom/admogo/obj/CaseeAD;
  .synthetic
.limit locals 1
.limit stack 200
  nop
  getstatic com/admogo/adapters/CaseeSourceAdapter/caseeAD Lcom/admogo/obj/CaseeAD;
  astore_0
  aload_0
  areturn
  nop
.end <method>

.method static access$3(Lcom/admogo/adapters/CaseeSourceAdapter;)V
  .synthetic
.limit locals 1
.limit stack 200
  nop
  aload_0
  invokespecial com/admogo/adapters/CaseeSourceAdapter/displayCaseeAD()V
  return
  nop
.end <method>

.method public click()V
.limit locals 14
.limit stack 200
  nop
  aload_0
  getfield com/admogo/adapters/AdMogoAdapter/adMogoLayoutReference Ljava/lang/ref/WeakReference;
  astore_1
  aload_1
  invokevirtual java/lang/ref/WeakReference/get()Ljava/lang/Object;
  astore_2
  aload_2
  astore 4
  new java/lang/NoClassDefFoundError
  dup
  invokespecial java/lang/NoClassDefFoundError/<init>()V
  athrow
  aload 4
  astore_3
  aload_3
  invokestatic app/DummyClass/invokeIfStmt(Ljava/lang/Object;)V
  iload_3
  ifeq Label0
  getstatic com/admogo/adapters/CaseeSourceAdapter/caseeAD Lcom/admogo/obj/CaseeAD;
  astore 5
  aload 5
  invokestatic app/DummyClass/invokeIfStmt(Ljava/lang/Object;)V
  aload 5
  ifnull Label0
  getstatic com/admogo/adapters/CaseeSourceAdapter/caseeAD Lcom/admogo/obj/CaseeAD;
  astore 5
  aload 5
  invokevirtual com/admogo/obj/CaseeAD/getUrl()Ljava/lang/String;
  astore 6
  aload 6
  invokestatic app/DummyClass/invokeIfStmt(Ljava/lang/Object;)V
  aload 6
  ifnonnull Label1
Label0:
  getstatic com/admogo/util/AdMogoUtil/ADMOGO Ljava/lang/String;
  astore 7
  ldc "adMogoLayout or caseeAD or caseeAD lost"
  astore 8
  aload 7
  aload 8
  invokestatic android/util/Log/d(Ljava/lang/String;Ljava/lang/String;)I
  pop
Label2:
  return
Label1:
  aload_3
  getfield com/admogo/AdMogoLayout/activityReference Ljava/lang/ref/WeakReference;
  astore_1
  aload_1
  invokevirtual java/lang/ref/WeakReference/get()Ljava/lang/Object;
  astore_2
  aload_2
  astore 10
  aload 10
  checkcast android/content/Context
  astore 10
  aload 10
  astore 9
  aload_3
  invokevirtual com/admogo/AdMogoLayout/countClick()V
  new android/content/Intent
  astore 11
  ldc com/admogo/AdMogoWebView
  astore 12
  aload 11
  aload 9
  aload 12
  invokespecial android/content/Intent/<init>(Landroid/content/Context;Ljava/lang/Class;)V
  new android/os/Bundle
  astore 13
  aload 13
  invokespecial android/os/Bundle/<init>()V
  getstatic com/admogo/adapters/CaseeSourceAdapter/caseeAD Lcom/admogo/obj/CaseeAD;
  astore 5
  aload 5
  invokevirtual com/admogo/obj/CaseeAD/getUrl()Ljava/lang/String;
  astore 6
  ldc "link"
  astore 8
  aload 13
  aload 8
  aload 6
  invokevirtual android/os/Bundle/putString(Ljava/lang/String;Ljava/lang/String;)V
  aload 11
  aload 13
  invokevirtual android/content/Intent/putExtras(Landroid/os/Bundle;)Landroid/content/Intent;
  pop
  aload 9
  aload 11
  invokevirtual android/content/Context/startActivity(Landroid/content/Intent;)V
  goto Label2
  nop
.end <method>

.method private displayCaseeAD()V
.limit locals 25
.limit stack 200
  nop
  getstatic com/admogo/util/AdMogoUtil/ADMOGO Ljava/lang/String;
  astore 4
  ldc "will display CaseeAD"
  astore 5
  new java/lang/NoClassDefFoundError
  dup
  invokespecial java/lang/NoClassDefFoundError/<init>()V
  athrow
  aload_0
  astore_1
  aload_1
  getfield com/admogo/adapters/AdMogoAdapter/adMogoLayoutReference Ljava/lang/ref/WeakReference;
  astore 6
  aload 6
  invokevirtual java/lang/ref/WeakReference/get()Ljava/lang/Object;
  astore 7
  aload 7
  astore 9
  aload 9
  checkcast com/admogo/AdMogoLayout
  astore 9
  aload 9
  astore 8
  aload 8
  invokestatic app/DummyClass/invokeIfStmt(Ljava/lang/Object;)V
  aload 8
  ifnonnull Label0
Label1:
  return
Label0:
  aload 8
  getfield com/admogo/AdMogoLayout/activityReference Ljava/lang/ref/WeakReference;
  astore 6
  aload 6
  invokevirtual java/lang/ref/WeakReference/get()Ljava/lang/Object;
  astore 7
  aload 7
  astore 11
  aload 11
  checkcast android/app/Activity
  astore 11
  aload 11
  astore 10
  aload 10
  invokestatic app/DummyClass/invokeIfStmt(Ljava/lang/Object;)V
  aload 10
  ifnull Label1
  aload 10
  invokestatic com/admogo/util/AdMogoUtil/getDensity(Landroid/app/Activity;)D
  dstore 12
  bipush 50
  istore 15
  iload 15
  dload 12
  invokestatic com/admogo/util/AdMogoUtil/convertToScreenPixels(ID)I
  istore 14
  iload 14
  i2d
  dstore 12
  getstatic com/admogo/util/AdMogoUtil/ADMOGO Ljava/lang/String;
  astore 16
  ldc "CaseeAD type: banner"
  astore 5
  aload 16
  aload 5
  invokestatic android/util/Log/d(Ljava/lang/String;Ljava/lang/String;)I
  pop
  getstatic com/admogo/adapters/CaseeSourceAdapter/caseeAD Lcom/admogo/obj/CaseeAD;
  astore 17
  aload 17
  astore_1
  aload_1
  invokestatic app/DummyClass/invokeIfStmt(Ljava/lang/Object;)V
  aload 17
  ifnull Label2
  getstatic com/admogo/adapters/CaseeSourceAdapter/caseeAD Lcom/admogo/obj/CaseeAD;
  astore 17
  aload 17
  astore_1
  aload_1
  invokevirtual com/admogo/obj/CaseeAD/getuLogoDrawable()Landroid/graphics/drawable/Drawable;
  astore 18
  aload 18
  astore_1
  aload_1
  invokestatic app/DummyClass/invokeIfStmt(Ljava/lang/Object;)V
  aload 18
  ifnonnull Label3
Label2:
  aload 8
  invokevirtual com/admogo/AdMogoLayout/rollover()V
  goto Label1
Label3:
  new android/widget/ImageView
  astore 19
  aload 19
  astore_1
  aload_1
  aload 10
  invokespecial android/widget/ImageView/<init>(Landroid/content/Context;)V
  getstatic com/admogo/adapters/CaseeSourceAdapter/caseeAD Lcom/admogo/obj/CaseeAD;
  astore 17
  aload 17
  astore_1
  aload_1
  invokevirtual com/admogo/obj/CaseeAD/getuLogoDrawable()Landroid/graphics/drawable/Drawable;
  astore 18
  aload 19
  astore_1
  aload 18
  astore_2
  aload_1
  aload_2
  invokevirtual android/widget/ImageView/setImageDrawable(Landroid/graphics/drawable/Drawable;)V
  getstatic android/widget/ImageView$ScaleType/CENTER_CROP Landroid/widget/ImageView$ScaleType;
  astore 20
  aload 19
  astore_1
  aload 20
  astore_2
  aload_1
  aload_2
  invokevirtual android/widget/ImageView/setScaleType(Landroid/widget/ImageView$ScaleType;)V
  new android/widget/RelativeLayout$LayoutParams
  astore 21
  dload 12
  d2i
  istore 14
  iconst_m1
  istore 15
  aload 21
  astore_1
  aload_1
  iload 15
  iload 14
  invokespecial android/widget/RelativeLayout$LayoutParams/<init>(II)V
  bipush 13
  istore 15
  aload 21
  astore_1
  aload_1
  iload 15
  invokevirtual android/widget/RelativeLayout$LayoutParams/addRule(I)V
  new android/widget/RelativeLayout
  astore 22
  aload 22
  astore_1
  aload_1
  aload 10
  invokespecial android/widget/RelativeLayout/<init>(Landroid/content/Context;)V
  aload 22
  astore_1
  aload 19
  astore_2
  aload 21
  astore_3
  aload_1
  aload_2
  aload_3
  invokevirtual android/widget/RelativeLayout/addView(Landroid/view/View;Landroid/view/ViewGroup$LayoutParams;)V
  aload_0
  astore_1
  aload_1
  getfield com/admogo/adapters/AdMogoAdapter/ration Lcom/admogo/obj/Ration;
  astore_1
  aload_1
  astore 23
  aload 23
  astore_1
  aload_1
  getfield com/admogo/obj/Ration/type I
  istore 14
  aload 22
  astore_1
  aload 8
  aload_1
  iload 14
  invokevirtual com/admogo/AdMogoLayout/pushSubView(Landroid/view/ViewGroup;I)V
  aload 8
  getfield com/admogo/AdMogoLayout/adMogoManager Lcom/admogo/AdMogoManager;
  astore_1
  aload_1
  astore 24
  aload 24
  astore_1
  aload_1
  invokevirtual com/admogo/AdMogoManager/resetRollover()V
  aload 8
  invokevirtual com/admogo/AdMogoLayout/rotateThreadedDelayed()V
  goto Label1
  nop
.end <method>

.method private static fetchImage(Ljava/lang/String;)Landroid/graphics/drawable/Drawable;
.limit locals 10
.limit stack 200
  .catch  java/lang/Exception <from> Label1 <to> Label2 <using> Label0
  nop
  new java/net/URL
  astore_1
Label1:
  aload_1
  aload_0
  invokespecial java/net/URL/<init>(Ljava/lang/String;)V
  aload_1
  invokevirtual java/net/URL/getContent()Ljava/lang/Object;
  astore_2
  aload_2
  astore 4
  aload 4
  checkcast java/io/InputStream
  astore 4
  aload 4
  astore_3
  ldc "src"
  astore 6
  new java/lang/NoClassDefFoundError
  dup
  invokespecial java/lang/NoClassDefFoundError/<init>()V
  athrow
  nop
  aload_3
  invokevirtual java/io/InputStream/close()V
Label2:
  aload 5
  areturn
Label0:
  astore 7
  getstatic com/admogo/util/AdMogoUtil/ADMOGO Ljava/lang/String;
  astore 8
  ldc "Unable to fetchImage(): "
  astore 6
  new java/lang/NoClassDefFoundError
  dup
  invokespecial java/lang/NoClassDefFoundError/<init>()V
  athrow
  aconst_null
  astore 9
  aload 9
  areturn
  nop
.end <method>

.method public finish()V
.limit locals 1
.limit stack 200
  nop
  return
  nop
.end <method>

.method private static getCaseeAD(Lcom/admogo/AdMogoLayout;Ljava/lang/String;)Lcom/admogo/obj/CaseeAD;
.limit locals 26
.limit stack 200
  nop
  aload_0
  astore_2
  new java/lang/NoClassDefFoundError
  dup
  invokespecial java/lang/NoClassDefFoundError/<init>()V
  athrow
  aload 4
  invokevirtual java/lang/ref/WeakReference/get()Ljava/lang/Object;
  astore 5
  aload 5
  astore 7
  aload 7
  checkcast android/content/Context
  astore 7
  aload 7
  astore 6
  aload 6
  invokestatic com/admogo/adapters/CaseeSourceAdapter/getImei(Landroid/content/Context;)Ljava/lang/String;
  astore 8
  aconst_null
  astore 9
  iconst_4
  istore 11
  iload 11
  anewarray java/lang/Object
  astore 10
  iconst_0
  istore 11
  ldc "http://wap.casee.cn/mo/Mogo.ad"
  astore 12
  aload 10
  iload 11
  aload 12
  aastore
  iconst_1
  istore 11
  ldc "getAd"
  astore 12
  aload 10
  iload 11
  aload 12
  aastore
  iconst_2
  istore 11
  aload 10
  iload 11
  aload_1
  aastore
  iconst_3
  istore 11
  aload 10
  iload 11
  aload 8
  aastore
  ldc "%s?_m=%s&appid=%s&imei=%s"
  astore 12
  aload 12
  aload 10
  invokestatic java/lang/String/format(Ljava/lang/String;[Ljava/lang/Object;)Ljava/lang/String;
  astore 13
  new org/apache/http/client/methods/HttpGet
  astore 14
Label6:
  aload 14
  aload 13
  invokespecial org/apache/http/client/methods/HttpGet/<init>(Ljava/lang/String;)V
  new org/apache/http/impl/client/DefaultHttpClient
  astore 15
  aload 15
  invokespecial org/apache/http/impl/client/DefaultHttpClient/<init>()V
  aload 15
  aload 14
  invokevirtual org/apache/http/impl/client/DefaultHttpClient/execute(Lorg/apache/http/client/methods/HttpUriRequest;)Lorg/apache/http/HttpResponse;
  astore 16
  aload 16
  invokeinterface org/apache/http/HttpResponse/getStatusLine()Lorg/apache/http/StatusLine; 1
  astore 17
  aload 17
  invokeinterface org/apache/http/StatusLine/getStatusCode()I 1
  istore 18
  iload 18
  istore_2
  dload_2
  invokestatic app/DummyClass/invokeIfStmt(D)V
  sipush 200
  istore 11
  iload 18
  istore_2
  iload_2
  iload 11
  if_icmpne Label0
  aload 16
  invokeinterface org/apache/http/HttpResponse/getEntity()Lorg/apache/http/HttpEntity; 1
  astore 19
  aload 19
  astore_2
  aload_2
  invokestatic org/apache/http/util/EntityUtils/toString(Lorg/apache/http/HttpEntity;)Ljava/lang/String;
  astore 8
  aload 8
  invokestatic app/DummyClass/invokeIfStmt(Ljava/lang/Object;)V
  aload 8
  ifnull Label1
  ldc ""
  astore 12
  aload 8
  aload 12
  invokevirtual java/lang/String/equals(Ljava/lang/Object;)Z
  istore 20
  iload 20
  istore_2
  iload_2
  invokestatic app/DummyClass/invokeIfStmt(Z)V
  iload 20
  ifne Label1
  ldc "{}"
  astore 12
  aload 8
  aload 12
  invokevirtual java/lang/String/equals(Ljava/lang/Object;)Z
  istore 20
  iload 20
  istore_2
  iload_2
  invokestatic app/DummyClass/invokeIfStmt(Z)V
  iload 20
  ifeq Label2
Label1:
  getstatic com/admogo/util/AdMogoUtil/ADMOGO Ljava/lang/String;
  astore 21
  ldc "CaseeAD json is null"
  astore 12
  aload 21
  astore_2
  aload_2
  aload 12
  invokestatic android/util/Log/w(Ljava/lang/String;Ljava/lang/String;)I
  pop
  aconst_null
  astore 22
  aload 22
  areturn
Label2:
  aload 8
  invokestatic com/admogo/adapters/CaseeSourceAdapter/getCaseeADByJson(Ljava/lang/String;)Lcom/admogo/obj/CaseeAD;
  astore 23
Label7:
  aload 23
  astore 9
Label3:
  aload 9
  areturn
Label0:
  aconst_null
  astore 22
  aload 22
  areturn
Label5:
  astore 24
  getstatic com/admogo/util/AdMogoUtil/ADMOGO Ljava/lang/String;
  astore 21
  ldc "getCaseeAD SocketException"
  astore 12
  aload 21
  astore_2
  aload 24
  astore_3
  aload_2
  aload 12
  aload_3
  invokestatic android/util/Log/e(Ljava/lang/String;Ljava/lang/String;Ljava/lang/Throwable;)I
  pop
  goto Label3
Label4:
  astore 25
  getstatic com/admogo/util/AdMogoUtil/ADMOGO Ljava/lang/String;
  astore 21
  ldc "getCaseeAD"
  astore 12
  aload 21
  astore_2
  aload 25
  astore_3
  aload_2
  aload 12
  aload_3
  invokestatic android/util/Log/e(Ljava/lang/String;Ljava/lang/String;Ljava/lang/Throwable;)I
  pop
  goto Label3
  nop
.end <method>

.method private static getCaseeADByJson(Ljava/lang/String;)Lcom/admogo/obj/CaseeAD;
.limit locals 17
.limit stack 200
  .catch  org/json/JSONException <from> Label4 <to> Label5 <using> Label3
  .catch  org/json/JSONException <from> Label5 <to> Label1 <using> Label6
  nop
  new org/json/JSONObject
  astore 7
Label4:
  aload_0
  astore_1
  aload 7
  aload_1
  invokespecial org/json/JSONObject/<init>(Ljava/lang/String;)V
  new com/admogo/obj/CaseeAD
  astore 8
  ldc "adid"
  astore 10
  aload 7
  aload 10
  invokevirtual org/json/JSONObject/getString(Ljava/lang/String;)Ljava/lang/String;
  astore 9
  ldc "adurl"
  astore 10
  aload 7
  aload 10
  invokevirtual org/json/JSONObject/getString(Ljava/lang/String;)Ljava/lang/String;
  astore 11
  ldc "adname"
  astore 10
  aload 7
  aload 10
  invokevirtual org/json/JSONObject/getString(Ljava/lang/String;)Ljava/lang/String;
  astore 12
  ldc "url"
  astore 10
  aload 7
  aload 10
  invokevirtual org/json/JSONObject/getString(Ljava/lang/String;)Ljava/lang/String;
  astore 13
  ldc "ulogo"
  astore 10
  aload 7
  aload 10
  invokevirtual org/json/JSONObject/getString(Ljava/lang/String;)Ljava/lang/String;
  astore_0
  aload 8
  astore_1
  aload 9
  astore_2
  aload 11
  astore_3
  aload 12
  astore 4
  aload 13
  astore 5
  aload_0
  astore 6
  aload_1
  aload_2
  aload_3
  aload 4
  aload 5
  aload 6
  invokespecial com/admogo/obj/CaseeAD/<init>(Ljava/lang/String;Ljava/lang/String;Ljava/lang/String;Ljava/lang/String;Ljava/lang/String;)V
Label5:
  aload 8
  invokevirtual com/admogo/obj/CaseeAD/getuLogo()Ljava/lang/String;
  astore 13
  new java/lang/NoClassDefFoundError
  dup
  invokespecial java/lang/NoClassDefFoundError/<init>()V
  athrow
  iload 13
  ifne Label0
  aconst_null
  astore 14
  aload 14
  areturn
Label0:
  aload 8
  invokevirtual com/admogo/obj/CaseeAD/getuLogo()Ljava/lang/String;
  astore 13
  aload 13
  invokestatic com/admogo/adapters/CaseeSourceAdapter/fetchImage(Ljava/lang/String;)Landroid/graphics/drawable/Drawable;
  astore 15
  aload 8
  aload 15
  invokevirtual com/admogo/obj/CaseeAD/setuLogoDrawable(Landroid/graphics/drawable/Drawable;)V
Label1:
  aload 8
  areturn
Label3:
  astore 16
  iconst_0
  istore 8
Label2:
  getstatic com/admogo/util/AdMogoUtil/ADMOGO Ljava/lang/String;
  astore 13
  ldc "Get CaseeAD By Json Fail"
  astore 10
  new java/lang/NoClassDefFoundError
  dup
  invokespecial java/lang/NoClassDefFoundError/<init>()V
  athrow
  goto Label1
Label6:
  astore 16
  goto Label2
  nop
.end <method>

.method private static getImei(Landroid/content/Context;)Ljava/lang/String;
.limit locals 6
.limit stack 200
  nop
  ldc "phone"
  astore_2
  new java/lang/NoClassDefFoundError
  dup
  invokespecial java/lang/NoClassDefFoundError/<init>()V
  athrow
  nop
  aload_1
  astore 4
  aload 4
  checkcast android/telephony/TelephonyManager
  astore 4
  aload 4
  astore_3
  aload_3
  invokevirtual android/telephony/TelephonyManager/getDeviceId()Ljava/lang/String;
  astore 5
  aload 5
  areturn
  nop
.end <method>

.method public handle()V
.limit locals 11
.limit stack 200
  nop
  aload_0
  getfield com/admogo/adapters/AdMogoAdapter/adMogoLayoutReference Ljava/lang/ref/WeakReference;
  astore_1
  aload_1
  invokevirtual java/lang/ref/WeakReference/get()Ljava/lang/Object;
  astore_2
  aload_2
  astore 4
  new java/lang/NoClassDefFoundError
  dup
  invokespecial java/lang/NoClassDefFoundError/<init>()V
  athrow
  aload 4
  astore_3
  aload_3
  invokestatic app/DummyClass/invokeIfStmt(Ljava/lang/Object;)V
  iload_3
  ifne Label0
Label1:
  return
Label0:
  aload_3
  getfield com/admogo/AdMogoLayout/scheduler Ljava/util/concurrent/ScheduledExecutorService;
  astore 5
  new com/admogo/adapters/CaseeSourceAdapter$FetchCaseeRunnable
  astore 6
  aload_0
  getfield com/admogo/adapters/AdMogoAdapter/ration Lcom/admogo/obj/Ration;
  astore 7
  aload 6
  aload 7
  aload_0
  invokespecial com/admogo/adapters/CaseeSourceAdapter$FetchCaseeRunnable/<init>(Lcom/admogo/obj/Ration;Lcom/admogo/adapters/CaseeSourceAdapter;)V
  getstatic java/util/concurrent/TimeUnit/SECONDS Ljava/util/concurrent/TimeUnit;
  astore 8
  ldc2_w 0
  lstore 9
  aload 5
  aload 6
  lload 9
  aload 8
  invokeinterface java/util/concurrent/ScheduledExecutorService/schedule(Ljava/lang/Runnable;JLjava/util/concurrent/TimeUnit;)Ljava/util/concurrent/ScheduledFuture; 5
  pop
  goto Label1
  nop
.end <method>

