.source SourceFile
.class final  com/mobisage/android/L
.super com/mobisage/android/N
.field private "c" Ljava/io/InputStream;
.field private "d" Ljava/io/BufferedInputStream;
.field private "e" Ljava/io/FileOutputStream;

.method public <init>(Lcom/mobisage/android/MobiSageResMessage;)V
.limit locals 2
.limit stack 200
  nop
  aload_0
  aload_1
  invokespecial com/mobisage/android/N/<init>(Lcom/mobisage/android/MobiSageMessage;)V
  return
  nop
.end <method>

.method public final a()V
.limit locals 5
.limit stack 200
  nop
  aload_0
  invokespecial com/mobisage/android/N/a()V
  aload_0
  getfield com/mobisage/android/L/d Ljava/io/BufferedInputStream;
  astore_1
  new java/lang/NoClassDefFoundError
  dup
  invokespecial java/lang/NoClassDefFoundError/<init>()V
  athrow
  iload_1
  ifeq Label0
  aload_0
  getfield com/mobisage/android/L/d Ljava/io/BufferedInputStream;
  astore_1
Label4:
  aload_1
  invokevirtual java/io/BufferedInputStream/close()V
Label0:
  aload_0
  getfield com/mobisage/android/L/c Ljava/io/InputStream;
  astore_2
  aload_2
  invokestatic app/DummyClass/invokeIfStmt(Ljava/lang/Object;)V
  aload_2
  ifnull Label1
  aload_0
  getfield com/mobisage/android/L/c Ljava/io/InputStream;
  astore_2
  aload_2
  invokevirtual java/io/InputStream/close()V
Label1:
  aload_0
  getfield com/mobisage/android/L/e Ljava/io/FileOutputStream;
  astore_3
  aload_3
  invokestatic app/DummyClass/invokeIfStmt(Ljava/lang/Object;)V
  aload_3
  ifnull Label2
  aload_0
  getfield com/mobisage/android/L/e Ljava/io/FileOutputStream;
  astore_3
  aload_3
  invokevirtual java/io/FileOutputStream/close()V
Label2:
  return
Label3:
  astore 4
  goto Label2
  nop
.end <method>

.method public final run()V
.limit locals 52
.limit stack 200
  nop
  aload_0
  astore_1
  aload_1
  getfield com/mobisage/android/N/a Lcom/mobisage/android/MobiSageMessage;
  astore 4
  aload 4
  astore 6
  aload 6
  checkcast com/mobisage/android/MobiSageResMessage
  astore 6
  aload 6
  astore 5
  new java/lang/NoClassDefFoundError
  dup
  invokespecial java/lang/NoClassDefFoundError/<init>()V
  athrow
Label10:
  aload 7
  invokespecial org/apache/http/conn/scheme/SchemeRegistry/<init>()V
  new org/apache/http/conn/scheme/Scheme
  astore 8
  invokestatic org/apache/http/conn/scheme/PlainSocketFactory/getSocketFactory()Lorg/apache/http/conn/scheme/PlainSocketFactory;
  astore 9
  ldc "http"
  astore 10
  bipush 80
  istore 11
  aload 8
  aload 10
  aload 9
  iload 11
  invokespecial org/apache/http/conn/scheme/Scheme/<init>(Ljava/lang/String;Lorg/apache/http/conn/scheme/SocketFactory;I)V
  aload 7
  aload 8
  invokevirtual org/apache/http/conn/scheme/SchemeRegistry/register(Lorg/apache/http/conn/scheme/Scheme;)Lorg/apache/http/conn/scheme/Scheme;
  pop
  new org/apache/http/conn/scheme/Scheme
  astore 8
  new com/mobisage/android/SNSSSLSocketFactory
  astore 12
  aload 12
  invokespecial com/mobisage/android/SNSSSLSocketFactory/<init>()V
  aload 12
  astore 14
  aload 14
  checkcast org/apache/http/conn/scheme/SocketFactory
  astore 14
  aload 14
  astore 13
  ldc "https"
  astore 10
  sipush 443
  istore 11
  aload 8
  aload 10
  aload 13
  iload 11
  invokespecial org/apache/http/conn/scheme/Scheme/<init>(Ljava/lang/String;Lorg/apache/http/conn/scheme/SocketFactory;I)V
  aload 7
  aload 8
  invokevirtual org/apache/http/conn/scheme/SchemeRegistry/register(Lorg/apache/http/conn/scheme/Scheme;)Lorg/apache/http/conn/scheme/Scheme;
  pop
  new org/apache/http/params/BasicHttpParams
  astore 15
  aload 15
  invokespecial org/apache/http/params/BasicHttpParams/<init>()V
  sipush 5000
  istore 11
  iload 11
  invokestatic java/lang/Integer/valueOf(I)Ljava/lang/Integer;
  astore 16
  ldc "http.connection.timeout"
  astore 10
  aload 15
  aload 10
  aload 16
  invokeinterface org/apache/http/params/HttpParams/setParameter(Ljava/lang/String;Ljava/lang/Object;)Lorg/apache/http/params/HttpParams; 3
  pop
  sipush 5000
  istore 11
  iload 11
  invokestatic java/lang/Integer/valueOf(I)Ljava/lang/Integer;
  astore 16
  ldc "http.socket.timeout"
  astore 10
  aload 15
  aload 10
  aload 16
  invokeinterface org/apache/http/params/HttpParams/setParameter(Ljava/lang/String;Ljava/lang/Object;)Lorg/apache/http/params/HttpParams; 3
  pop
  getstatic org/apache/http/HttpVersion/HTTP_1_1 Lorg/apache/http/HttpVersion;
  astore 17
  aload 17
  astore_1
  aload 15
  aload_1
  invokestatic org/apache/http/params/HttpProtocolParams/setVersion(Lorg/apache/http/params/HttpParams;Lorg/apache/http/ProtocolVersion;)V
  ldc "UTF-8"
  astore 10
  aload 15
  aload 10
  invokestatic org/apache/http/params/HttpProtocolParams/setContentCharset(Lorg/apache/http/params/HttpParams;Ljava/lang/String;)V
  new org/apache/http/impl/conn/SingleClientConnManager
  astore 18
  aload 18
  astore_1
  aload_1
  aload 15
  aload 7
  invokespecial org/apache/http/impl/conn/SingleClientConnManager/<init>(Lorg/apache/http/params/HttpParams;Lorg/apache/http/conn/scheme/SchemeRegistry;)V
  new org/apache/http/impl/client/DefaultHttpClient
  astore 19
  aload 19
  astore_1
  aload 18
  astore_2
  aload_1
  aload_2
  aload 15
  invokespecial org/apache/http/impl/client/DefaultHttpClient/<init>(Lorg/apache/http/conn/ClientConnectionManager;Lorg/apache/http/params/HttpParams;)V
  aload 19
  astore_1
  aload_0
  astore_2
  aload_2
  aload_1
  putfield com/mobisage/android/N/b Lorg/apache/http/client/HttpClient;
  aload_0
  astore_1
  aload_1
  getfield com/mobisage/android/N/b Lorg/apache/http/client/HttpClient;
  astore_1
  aload_1
  astore 20
  aload 5
  invokevirtual com/mobisage/android/MobiSageResMessage/createHttpRequest()Lorg/apache/http/client/methods/HttpRequestBase;
  astore 21
  aload 20
  astore_1
  aload 21
  astore_2
  aload_1
  aload_2
  invokeinterface org/apache/http/client/HttpClient/execute(Lorg/apache/http/client/methods/HttpUriRequest;)Lorg/apache/http/HttpResponse; 2
  astore 22
  aload 22
  astore_1
  aload_1
  invokeinterface org/apache/http/HttpResponse/getStatusLine()Lorg/apache/http/StatusLine; 1
  astore 23
  aload 23
  astore_1
  aload_1
  invokeinterface org/apache/http/StatusLine/getStatusCode()I 1
  istore 24
  aload 5
  getfield com/mobisage/android/MobiSageMessage/result Landroid/os/Bundle;
  astore_1
  aload_1
  astore 25
  ldc "StatusCode"
  astore 10
  aload 25
  astore_1
  iload 24
  istore_2
  aload_1
  aload 10
  iload_2
  invokevirtual android/os/Bundle/putInt(Ljava/lang/String;I)V
  iload 24
  istore_1
  dload_1
  invokestatic app/DummyClass/invokeIfStmt(D)V
  sipush 400
  istore 11
  iload 24
  istore_1
  iload_1
  iload 11
  if_icmpge Label0
  new java/io/File
  astore 26
  aload 26
  astore 27
  aload 5
  getfield com/mobisage/android/MobiSageResMessage/tempURL Ljava/lang/String;
  astore_1
  aload_1
  astore 28
  aload 26
  astore_1
  aload 28
  astore_2
  aload_1
  aload_2
  invokespecial java/io/File/<init>(Ljava/lang/String;)V
  aload 26
  astore_1
  aload_1
  invokevirtual java/io/File/exists()Z
  istore 29
  iload 29
  istore_1
  iload_1
  invokestatic app/DummyClass/invokeIfStmt(Z)V
  iload 29
  ifne Label1
  aload 26
  astore_1
  aload_1
  invokevirtual java/io/File/createNewFile()Z
  pop
Label1:
  aload 5
  getfield com/mobisage/android/MobiSageResMessage/d Ljava/lang/Boolean;
  astore_1
  aload_1
  astore 30
  aload 30
  astore_1
  aload_1
  invokevirtual java/lang/Boolean/booleanValue()Z
  istore 29
  iload 29
  istore_1
  iload_1
  invokestatic app/DummyClass/invokeIfStmt(Z)V
  iload 29
  ifeq Label2
  iload 24
  istore_1
  dload_1
  invokestatic app/DummyClass/invokeIfStmt(D)V
  sipush 206
  istore 11
  iload 24
  istore_1
  iload_1
  iload 11
  if_icmpeq Label2
  aload 27
  astore_1
  aload_1
  invokevirtual java/io/File/delete()Z
  pop
  aload 27
  astore_1
  aload_1
  invokevirtual java/io/File/createNewFile()Z
  pop
Label2:
  aload 22
  astore_1
  aload_1
  invokeinterface org/apache/http/HttpResponse/getEntity()Lorg/apache/http/HttpEntity; 1
  astore 31
  aload 31
  astore_1
  aload_1
  invokeinterface org/apache/http/HttpEntity/getContent()Ljava/io/InputStream; 1
  astore 32
  aload 32
  astore_1
  aload_0
  astore_2
  aload_2
  aload_1
  putfield com/mobisage/android/L/c Ljava/io/InputStream;
  new java/io/BufferedInputStream
  astore 33
  aload_0
  astore_1
  aload_1
  getfield com/mobisage/android/L/c Ljava/io/InputStream;
  astore_1
  aload_1
  astore 32
  aload 33
  astore_1
  aload 32
  astore_2
  aload_1
  aload_2
  invokespecial java/io/BufferedInputStream/<init>(Ljava/io/InputStream;)V
  aload 33
  astore_1
  aload_0
  astore_2
  aload_2
  aload_1
  putfield com/mobisage/android/L/d Ljava/io/BufferedInputStream;
  new java/io/FileOutputStream
  astore 34
  iconst_1
  istore 11
  aload 34
  astore_1
  aload 27
  astore_2
  aload_1
  aload_2
  iload 11
  invokespecial java/io/FileOutputStream/<init>(Ljava/io/File;Z)V
  aload 34
  astore_1
  aload_0
  astore_2
  aload_2
  aload_1
  putfield com/mobisage/android/L/e Ljava/io/FileOutputStream;
  ldc 65536
  istore 11
  iload 11
  newarray byte
  astore_1
  aload_1
  astore 35
Label4:
  aload_0
  astore_1
  aload_1
  getfield com/mobisage/android/L/d Ljava/io/BufferedInputStream;
  astore_1
  aload_1
  astore 36
  aload 36
  astore_1
  aload 35
  astore_2
  aload_1
  aload_2
  invokevirtual java/io/BufferedInputStream/read([B)I
  istore 24
  iload 24
  istore_1
  dload_1
  invokestatic app/DummyClass/invokeIfStmt(D)V
  iconst_m1
  istore 11
  iload 24
  istore_1
  iload_1
  iload 11
  if_icmpeq Label3
  aload_0
  astore_1
  aload_1
  getfield com/mobisage/android/L/e Ljava/io/FileOutputStream;
  astore_1
  aload_1
  astore 37
  iconst_0
  istore 11
  aload 37
  astore_1
  aload 35
  astore_2
  iload 24
  istore_3
  aload_1
  aload_2
  iload 11
  iload_3
  invokevirtual java/io/FileOutputStream/write([BII)V
Label11:
  goto Label4
Label9:
  astore 38
Label12:
  aload 5
  getfield com/mobisage/android/MobiSageMessage/result Landroid/os/Bundle;
  astore_1
  aload_1
  astore 25
  aload 38
  astore_1
  aload_1
  invokevirtual java/lang/Exception/getLocalizedMessage()Ljava/lang/String;
  astore 39
  ldc "ErrorText"
  astore 10
  aload 25
  astore_1
  aload 39
  astore_2
  aload_1
  aload 10
  aload_2
  invokevirtual android/os/Bundle/putString(Ljava/lang/String;Ljava/lang/String;)V
Label13:
  aload 5
  getfield com/mobisage/android/MobiSageMessage/callback Lcom/mobisage/android/IMobiSageMessageCallback;
  astore_1
  aload_1
  astore 40
  aload 40
  astore_1
  aload_1
  invokestatic app/DummyClass/invokeIfStmt(Ljava/lang/Object;)V
  aload 40
  ifnull Label5
  aload 5
  getfield com/mobisage/android/MobiSageMessage/callback Lcom/mobisage/android/IMobiSageMessageCallback;
  astore_1
  aload_1
  astore 40
  aload 40
  astore_1
  aload_1
  aload 5
  invokeinterface com/mobisage/android/IMobiSageMessageCallback/onMobiSageMessageFinish(Lcom/mobisage/android/MobiSageMessage;)V 2
Label5:
  aload_0
  astore_1
  aload_1
  invokespecial com/mobisage/android/N/run()V
  return
Label3:
  aload_0
  astore_1
  aload_1
  getfield com/mobisage/android/L/d Ljava/io/BufferedInputStream;
  astore_1
  aload_1
  astore 36
  aload 36
  astore_1
  aload_1
  invokevirtual java/io/BufferedInputStream/close()V
  aload_0
  astore_1
  aload_1
  getfield com/mobisage/android/L/c Ljava/io/InputStream;
  astore_1
  aload_1
  astore 32
  aload 32
  astore_1
  aload_1
  invokevirtual java/io/InputStream/close()V
  aload_0
  astore_1
  aload_1
  getfield com/mobisage/android/L/e Ljava/io/FileOutputStream;
  astore_1
  aload_1
  astore 37
  aload 37
  astore_1
  aload_1
  invokevirtual java/io/FileOutputStream/close()V
  ldc "Content-Length"
  astore 10
  aload 22
  astore_1
  aload_1
  aload 10
  invokeinterface org/apache/http/HttpResponse/getHeaders(Ljava/lang/String;)[Lorg/apache/http/Header; 2
  astore 41
  iconst_0
  istore 11
  aload 41
  iload 11
  aaload
  astore 42
  aload 42
  astore_1
  aload_1
  invokeinterface org/apache/http/Header/getValue()Ljava/lang/String; 1
  astore 39
  aload 39
  astore_1
  aload_1
  invokestatic java/lang/Integer/parseInt(Ljava/lang/String;)I
  istore 24
  aload 27
  astore_1
  aload_1
  invokevirtual java/io/File/length()J
  lstore 43
  iload 24
  istore_1
  iload_1
  i2l
  lstore_1
  lload_1
  lstore 45
  aload 5
  getfield com/mobisage/android/MobiSageResMessage/e J
  lstore_1
  lload_1
  lstore 47
  lload 45
  lload 47
  ladd
  lstore 47
  lload 43
  lload 47
  lcmp
  istore 49
  iload 49
  istore_1
  dload_1
  invokestatic app/DummyClass/invokeIfStmt(D)V
  iload 49
  ifeq Label6
  aload 27
  astore_1
  aload_1
  invokevirtual java/io/File/delete()Z
  pop
  aload 5
  getfield com/mobisage/android/MobiSageMessage/result Landroid/os/Bundle;
  astore_1
  aload_1
  astore 25
  ldc "StatusCode"
  astore 10
  sipush 400
  istore 11
  aload 25
  astore_1
  aload_1
  aload 10
  iload 11
  invokevirtual android/os/Bundle/putInt(Ljava/lang/String;I)V
Label0:
  aload 5
  getfield com/mobisage/android/MobiSageMessage/callback Lcom/mobisage/android/IMobiSageMessageCallback;
  astore_1
  aload_1
  astore 40
  aload 40
  astore_1
  aload_1
  invokestatic app/DummyClass/invokeIfStmt(Ljava/lang/Object;)V
  aload 40
  ifnull Label5
  aload 5
  getfield com/mobisage/android/MobiSageMessage/callback Lcom/mobisage/android/IMobiSageMessageCallback;
  astore_1
  aload_1
  astore 40
  aload 40
  astore_1
  aload_1
  aload 5
  invokeinterface com/mobisage/android/IMobiSageMessageCallback/onMobiSageMessageFinish(Lcom/mobisage/android/MobiSageMessage;)V 2
  goto Label5
Label6:
  new java/io/File
  astore 50
Label14:
  aload 5
  getfield com/mobisage/android/MobiSageResMessage/targetURL Ljava/lang/String;
  astore_1
  aload_1
  astore 39
  aload 50
  astore_1
  aload 39
  astore_2
  aload_1
  aload_2
  invokespecial java/io/File/<init>(Ljava/lang/String;)V
  aload 27
  astore_1
  aload 50
  astore_2
  aload_1
  aload_2
  invokevirtual java/io/File/renameTo(Ljava/io/File;)Z
  pop
Label15:
  goto Label0
Label8:
  astore 51
  aload 5
  getfield com/mobisage/android/MobiSageMessage/callback Lcom/mobisage/android/IMobiSageMessageCallback;
  astore_1
  aload_1
  astore 40
  aload 40
  astore_1
  aload_1
  invokestatic app/DummyClass/invokeIfStmt(Ljava/lang/Object;)V
  aload 40
  ifnull Label7
  aload 5
  getfield com/mobisage/android/MobiSageMessage/callback Lcom/mobisage/android/IMobiSageMessageCallback;
  astore_1
  aload_1
  astore 40
  aload 40
  astore_1
  aload_1
  aload 5
  invokeinterface com/mobisage/android/IMobiSageMessageCallback/onMobiSageMessageFinish(Lcom/mobisage/android/MobiSageMessage;)V 2
Label7:
  aload 51
  athrow
  nop
.end <method>

