.source dalvik_source_VirusShare_32e70f448ebd75661a1cb12f9cd8e013.apk
.class  com/wiyun/ad/e$a$5
.super java/lang/Object
.implements  java/lang/Runnable
.field final "a" Lcom/wiyun/ad/e$a;

.method <init>(Lcom/wiyun/ad/e$a;)V
.limit locals 2
.limit stack 200
  nop
  aload_0
  aload_1
  putfield com/wiyun/ad/e$a$5/a Lcom/wiyun/ad/e$a;
  aload_0
  invokespecial java/lang/Object/<init>()V
  return
  nop
.end <method>

.method public run()V
.limit locals 9
.limit stack 200
  nop
  aload_0
  getfield com/wiyun/ad/e$a$5/a Lcom/wiyun/ad/e$a;
  astore_1
  aload_1
  invokestatic com/wiyun/ad/e$a/a(Lcom/wiyun/ad/e$a;)Lcom/wiyun/ad/e;
  astore_2
  new java/lang/NoClassDefFoundError
  dup
  invokespecial java/lang/NoClassDefFoundError/<init>()V
  athrow
  nop
  aload_3
  invokestatic app/DummyClass/invokeIfStmt(Ljava/lang/Object;)V
  iload_3
  ifeq Label0
  aload_0
  getfield com/wiyun/ad/e$a$5/a Lcom/wiyun/ad/e$a;
  astore_1
  aload_1
  invokestatic com/wiyun/ad/e$a/a(Lcom/wiyun/ad/e$a;)Lcom/wiyun/ad/e;
  astore_2
  aload_2
  invokevirtual com/wiyun/ad/e/getContext()Landroid/content/Context;
  astore_3
  ldc "no_sd_card"
  astore 5
  aload 5
  invokestatic com/wiyun/ad/q/a(Ljava/lang/String;)Ljava/lang/String;
  astore 4
  iconst_0
  istore 7
  aload_3
  aload 4
  iload 7
  invokestatic android/widget/Toast/makeText(Landroid/content/Context;Ljava/lang/CharSequence;I)Landroid/widget/Toast;
  astore 6
  aload 6
  invokevirtual android/widget/Toast/show()V
Label0:
  aload_0
  getfield com/wiyun/ad/e$a$5/a Lcom/wiyun/ad/e$a;
  astore_1
  aload_1
  invokestatic com/wiyun/ad/e$a/a(Lcom/wiyun/ad/e$a;)Lcom/wiyun/ad/e;
  astore_2
  aload_2
  invokestatic com/wiyun/ad/e/e(Lcom/wiyun/ad/e;)Lcom/wiyun/ad/AdView$AdListener;
  astore 8
  aload 8
  invokestatic app/DummyClass/invokeIfStmt(Ljava/lang/Object;)V
  aload 8
  ifnull Label1
  aload_0
  getfield com/wiyun/ad/e$a$5/a Lcom/wiyun/ad/e$a;
  astore_1
  aload_1
  invokestatic com/wiyun/ad/e$a/a(Lcom/wiyun/ad/e$a;)Lcom/wiyun/ad/e;
  astore_2
  aload_2
  invokestatic com/wiyun/ad/e/e(Lcom/wiyun/ad/e;)Lcom/wiyun/ad/AdView$AdListener;
  astore 8
  aload 8
  invokeinterface com/wiyun/ad/AdView$AdListener/onAppDownloadFailed()V 1
Label1:
  return
  nop
.end <method>

