.source AdMogoLayout.java
.class  com/admogo/AdMogoLayout$HandleAdRunnable
.super java/lang/Object
.implements  java/lang/Runnable
.field private "adMogoLayoutReference" Ljava/lang/ref/WeakReference;

.method public <init>(Lcom/admogo/AdMogoLayout;)V
.limit locals 3
.limit stack 200
  nop
  aload_0
  invokespecial java/lang/Object/<init>()V
  new java/lang/ref/WeakReference
  astore_2
  aload_2
  aload_1
  invokespecial java/lang/ref/WeakReference/<init>(Ljava/lang/Object;)V
  aload_0
  aload_2
  putfield com/admogo/AdMogoLayout$HandleAdRunnable/adMogoLayoutReference Ljava/lang/ref/WeakReference;
  return
  nop
.end <method>

.method public run()V
.limit locals 5
.limit stack 200
  nop
  aload_0
  getfield com/admogo/AdMogoLayout$HandleAdRunnable/adMogoLayoutReference Ljava/lang/ref/WeakReference;
  astore_1
  aload_1
  invokevirtual java/lang/ref/WeakReference/get()Ljava/lang/Object;
  astore_2
  aload_2
  astore 4
  new java/lang/NoClassDefFoundError
  dup
  invokespecial java/lang/NoClassDefFoundError/<init>()V
  athrow
  aload 4
  astore_3
  aload_3
  invokestatic app/DummyClass/invokeIfStmt(Ljava/lang/Object;)V
  iload_3
  ifeq Label0
  aload_3
  invokestatic com/admogo/AdMogoLayout/access$17(Lcom/admogo/AdMogoLayout;)V
Label0:
  return
  nop
.end <method>

