.source SourceFile
.class final  com/mobisage/android/d
.super com/mobisage/android/O
.field private "g" Lcom/mobisage/android/d$a;

.method <init>(Landroid/os/Handler;)V
.limit locals 4
.limit stack 200
  nop
  aload_0
  aload_1
  invokespecial com/mobisage/android/O/<init>(Landroid/os/Handler;)V
  sipush 1014
  istore_2
  aload_0
  iload_2
  putfield com/mobisage/android/O/c I
  new com/mobisage/android/d$a
  astore_3
  iconst_0
  istore_2
  aload_3
  aload_0
  iload_2
  invokespecial com/mobisage/android/d$a/<init>(Lcom/mobisage/android/d;B)V
  aload_0
  aload_3
  putfield com/mobisage/android/d/g Lcom/mobisage/android/d$a;
  return
  nop
.end <method>

.method public final a(Landroid/os/Message;)V
.limit locals 29
.limit stack 200
  nop
  aload_1
  astore_2
  new java/lang/NoClassDefFoundError
  dup
  invokespecial java/lang/NoClassDefFoundError/<init>()V
  athrow
  aload 4
  instanceof com/mobisage/android/b
  istore 5
  iload 5
  invokestatic app/DummyClass/invokeIfStmt(Z)V
  iload 5
  ifeq Label0
  aload_1
  astore_2
  aload_2
  getfield android/os/Message/obj Ljava/lang/Object;
  astore 4
  aload 4
  astore 7
  aload 7
  checkcast com/mobisage/android/b
  astore 7
  aload 7
  astore 6
  aload_0
  astore_2
  aload_2
  getfield com/mobisage/android/O/e Ljava/util/concurrent/ConcurrentHashMap;
  astore 8
  aload 6
  getfield com/mobisage/android/b/b Ljava/util/UUID;
  astore 9
  aload 8
  aload 9
  aload 6
  invokevirtual java/util/concurrent/ConcurrentHashMap/put(Ljava/lang/Object;Ljava/lang/Object;)Ljava/lang/Object;
  pop
  new com/mobisage/android/MobiSageResMessage
  astore 10
  aload 10
  invokespecial com/mobisage/android/MobiSageResMessage/<init>()V
  aload_0
  astore_2
  aload_2
  getfield com/mobisage/android/d/g Lcom/mobisage/android/d$a;
  astore 11
  aload 10
  aload 11
  putfield com/mobisage/android/MobiSageMessage/callback Lcom/mobisage/android/IMobiSageMessageCallback;
  aload 6
  getfield com/mobisage/android/b/c Landroid/os/Bundle;
  astore 12
  ldc "SourceURL"
  astore 14
  aload 12
  aload 14
  invokevirtual android/os/Bundle/getString(Ljava/lang/String;)Ljava/lang/String;
  astore 13
  aload 10
  aload 13
  putfield com/mobisage/android/MobiSageResMessage/sourceURL Ljava/lang/String;
  aload 6
  getfield com/mobisage/android/b/c Landroid/os/Bundle;
  astore 12
  ldc "TragetURL"
  astore 14
  aload 12
  aload 14
  invokevirtual android/os/Bundle/getString(Ljava/lang/String;)Ljava/lang/String;
  astore 13
  aload 10
  aload 13
  putfield com/mobisage/android/MobiSageResMessage/targetURL Ljava/lang/String;
  aload 6
  getfield com/mobisage/android/b/c Landroid/os/Bundle;
  astore 12
  ldc "TempURL"
  astore 14
  aload 12
  aload 14
  invokevirtual android/os/Bundle/getString(Ljava/lang/String;)Ljava/lang/String;
  astore 13
  aload 10
  aload 13
  putfield com/mobisage/android/MobiSageResMessage/tempURL Ljava/lang/String;
  aload 6
  getfield com/mobisage/android/b/f Ljava/util/concurrent/LinkedBlockingQueue;
  astore 15
  aload 15
  aload 10
  invokevirtual java/util/concurrent/LinkedBlockingQueue/add(Ljava/lang/Object;)Z
  pop
  aload_0
  astore_2
  aload_2
  getfield com/mobisage/android/O/f Ljava/util/concurrent/ConcurrentHashMap;
  astore 8
  aload 10
  getfield com/mobisage/android/MobiSageMessage/c Ljava/util/UUID;
  astore 9
  aload 6
  getfield com/mobisage/android/b/b Ljava/util/UUID;
  astore 16
  aload 8
  aload 9
  aload 16
  invokevirtual java/util/concurrent/ConcurrentHashMap/put(Ljava/lang/Object;Ljava/lang/Object;)Ljava/lang/Object;
  pop
  invokestatic com/mobisage/android/H/a()Lcom/mobisage/android/H;
  astore 17
  aload 17
  aload 10
  invokevirtual com/mobisage/android/H/a(Lcom/mobisage/android/MobiSageMessage;)V
Label1:
  return
Label0:
  aload_1
  astore_2
  aload_2
  getfield android/os/Message/obj Ljava/lang/Object;
  astore 4
  aload 4
  instanceof com/mobisage/android/MobiSageResMessage
  istore 5
  iload 5
  invokestatic app/DummyClass/invokeIfStmt(Z)V
  iload 5
  ifeq Label1
  aload_1
  astore_2
  aload_2
  getfield android/os/Message/obj Ljava/lang/Object;
  astore 4
  aload 4
  astore 18
  aload 18
  checkcast com/mobisage/android/MobiSageResMessage
  astore 18
  aload 18
  astore 10
  aload_0
  astore_2
  aload_2
  getfield com/mobisage/android/O/f Ljava/util/concurrent/ConcurrentHashMap;
  astore 8
  aload 10
  getfield com/mobisage/android/MobiSageMessage/c Ljava/util/UUID;
  astore 16
  aload 8
  aload 16
  invokevirtual java/util/concurrent/ConcurrentHashMap/get(Ljava/lang/Object;)Ljava/lang/Object;
  astore 4
  aload 4
  astore 19
  aload 19
  checkcast java/util/UUID
  astore 19
  aload 19
  astore 16
  aload_0
  astore_2
  aload_2
  getfield com/mobisage/android/O/e Ljava/util/concurrent/ConcurrentHashMap;
  astore 8
  aload 8
  aload 16
  invokevirtual java/util/concurrent/ConcurrentHashMap/get(Ljava/lang/Object;)Ljava/lang/Object;
  astore 4
  aload 4
  astore 20
  aload 20
  checkcast com/mobisage/android/b
  astore 20
  aload 20
  astore 6
  aload_0
  astore_2
  aload_2
  getfield com/mobisage/android/O/f Ljava/util/concurrent/ConcurrentHashMap;
  astore 8
  aload 10
  getfield com/mobisage/android/MobiSageMessage/c Ljava/util/UUID;
  astore 16
  aload 8
  aload 16
  invokevirtual java/util/concurrent/ConcurrentHashMap/remove(Ljava/lang/Object;)Ljava/lang/Object;
  pop
  aload 6
  getfield com/mobisage/android/b/f Ljava/util/concurrent/LinkedBlockingQueue;
  astore 15
  aload 15
  aload 10
  invokevirtual java/util/concurrent/LinkedBlockingQueue/remove(Ljava/lang/Object;)Z
  pop
  aload 10
  getfield com/mobisage/android/MobiSageMessage/result Landroid/os/Bundle;
  astore 12
  ldc "StatusCode"
  astore 14
  aload 12
  aload 14
  invokevirtual android/os/Bundle/getInt(Ljava/lang/String;)I
  istore 21
  iload 21
  istore_2
  dload_2
  invokestatic app/DummyClass/invokeIfStmt(D)V
  sipush 400
  istore 22
  iload 21
  istore_2
  iload 22
  istore_3
  iload_2
  iload_3
  if_icmplt Label2
  aload_0
  astore_2
  aload_2
  aload 6
  invokevirtual com/mobisage/android/d/c(Lcom/mobisage/android/b;)V
  goto Label1
Label2:
  new java/util/ArrayList
  astore 23
  aload 23
  astore_2
  aload_2
  invokespecial java/util/ArrayList/<init>()V
  aload 10
  getfield com/mobisage/android/MobiSageResMessage/targetURL Ljava/lang/String;
  astore 13
  aload 23
  astore_2
  aload_2
  aload 13
  invokevirtual java/util/ArrayList/add(Ljava/lang/Object;)Z
  pop
  new com/mobisage/android/b
  astore 24
  aload 24
  astore_2
  aload_2
  invokespecial com/mobisage/android/b/<init>()V
  aload 24
  astore_2
  aload_2
  getfield com/mobisage/android/b/c Landroid/os/Bundle;
  astore_2
  aload_2
  astore 25
  aload 6
  getfield com/mobisage/android/b/c Landroid/os/Bundle;
  astore 12
  ldc "TragetURL"
  astore 14
  aload 12
  aload 14
  invokevirtual android/os/Bundle/getString(Ljava/lang/String;)Ljava/lang/String;
  astore 13
  ldc "OwnerURL"
  astore 14
  aload 25
  astore_2
  aload_2
  aload 14
  aload 13
  invokevirtual android/os/Bundle/putString(Ljava/lang/String;Ljava/lang/String;)V
  aload 24
  astore_2
  aload_2
  getfield com/mobisage/android/b/c Landroid/os/Bundle;
  astore_2
  aload_2
  astore 25
  ldc "LpgCache"
  astore 14
  aload 25
  astore_2
  aload 23
  astore_3
  aload_2
  aload 14
  aload_3
  invokevirtual android/os/Bundle/putStringArrayList(Ljava/lang/String;Ljava/util/ArrayList;)V
  aload 6
  getfield com/mobisage/android/b/b Ljava/util/UUID;
  astore 16
  aload 24
  astore_2
  aload_2
  aload 16
  putfield com/mobisage/android/b/a Ljava/util/UUID;
  aload_0
  astore_2
  aload_2
  getfield com/mobisage/android/O/b Lcom/mobisage/android/O$a;
  astore_2
  aload_2
  astore 26
  aload 26
  astore_2
  aload 24
  astore_3
  aload_3
  aload_2
  putfield com/mobisage/android/b/g Lcom/mobisage/android/a;
  aload 6
  getfield com/mobisage/android/b/e Ljava/util/concurrent/LinkedBlockingQueue;
  astore 15
  aload 24
  astore_2
  aload 15
  aload_2
  invokevirtual java/util/concurrent/LinkedBlockingQueue/add(Ljava/lang/Object;)Z
  pop
  aload_0
  astore_2
  aload_2
  getfield com/mobisage/android/O/a Landroid/os/Handler;
  astore_2
  aload_2
  astore 27
  sipush 1006
  istore 22
  aload 27
  astore_2
  iload 22
  istore_3
  aload_2
  iload_3
  invokevirtual android/os/Handler/obtainMessage(I)Landroid/os/Message;
  astore_1
  aload 24
  astore_2
  aload_1
  astore_3
  aload_3
  aload_2
  putfield android/os/Message/obj Ljava/lang/Object;
  aload_1
  astore_2
  aload_2
  invokevirtual android/os/Message/sendToTarget()V
  aload 6
  invokevirtual com/mobisage/android/b/a()Z
  istore 5
  iload 5
  invokestatic app/DummyClass/invokeIfStmt(Z)V
  iload 5
  ifeq Label1
  aload_0
  astore_2
  aload_2
  getfield com/mobisage/android/O/e Ljava/util/concurrent/ConcurrentHashMap;
  astore 8
  aload 6
  getfield com/mobisage/android/b/b Ljava/util/UUID;
  astore 16
  aload 8
  aload 16
  invokevirtual java/util/concurrent/ConcurrentHashMap/remove(Ljava/lang/Object;)Ljava/lang/Object;
  pop
  aload 6
  getfield com/mobisage/android/b/g Lcom/mobisage/android/a;
  astore_2
  aload_2
  astore 28
  aload 28
  astore_2
  aload_2
  invokestatic app/DummyClass/invokeIfStmt(Ljava/lang/Object;)V
  aload 28
  ifnull Label1
  aload 6
  getfield com/mobisage/android/b/g Lcom/mobisage/android/a;
  astore_2
  aload_2
  astore 28
  aload 28
  astore_2
  aload_2
  aload 6
  invokeinterface com/mobisage/android/a/a(Lcom/mobisage/android/b;)V 2
  goto Label1
  nop
.end <method>

.method protected final a(Lcom/mobisage/android/b;)V
.limit locals 19
.limit stack 200
  nop
  aload_0
  astore_2
  aload_2
  getfield com/mobisage/android/O/e Ljava/util/concurrent/ConcurrentHashMap;
  astore_3
  aload_2
  astore_0
  aload_1
  astore_2
  aload_2
  getfield com/mobisage/android/b/a Ljava/util/UUID;
  astore 4
  aload_3
  aload 4
  invokevirtual java/util/concurrent/ConcurrentHashMap/containsKey(Ljava/lang/Object;)Z
  istore 5
  new java/lang/NoClassDefFoundError
  dup
  invokespecial java/lang/NoClassDefFoundError/<init>()V
  athrow
  iload 5
  ifne Label0
Label2:
  return
Label0:
  aload_0
  astore_2
  aload_2
  getfield com/mobisage/android/O/e Ljava/util/concurrent/ConcurrentHashMap;
  astore_3
  aload_2
  astore_0
  aload_1
  astore_2
  aload_2
  getfield com/mobisage/android/b/a Ljava/util/UUID;
  astore 4
  aload_3
  aload 4
  invokevirtual java/util/concurrent/ConcurrentHashMap/get(Ljava/lang/Object;)Ljava/lang/Object;
  astore 6
  aload 6
  astore 8
  aload 8
  checkcast com/mobisage/android/b
  astore 8
  aload 8
  astore 7
  aload 7
  getfield com/mobisage/android/b/e Ljava/util/concurrent/LinkedBlockingQueue;
  astore 9
  aload_1
  astore_2
  aload 9
  aload_2
  invokevirtual java/util/concurrent/LinkedBlockingQueue/remove(Ljava/lang/Object;)Z
  pop
  aload_1
  astore_2
  aload_2
  getfield com/mobisage/android/b/c Landroid/os/Bundle;
  astore 10
  ldc "OwnerURL"
  astore 11
  aload 10
  aload 11
  invokevirtual android/os/Bundle/containsKey(Ljava/lang/String;)Z
  istore 5
  iload 5
  invokestatic app/DummyClass/invokeIfStmt(Z)V
  iload 5
  ifeq Label1
  aload_1
  astore_2
  aload_2
  getfield com/mobisage/android/b/c Landroid/os/Bundle;
  astore 10
  ldc "OwnerURL"
  astore 11
  aload 10
  aload 11
  invokevirtual android/os/Bundle/getString(Ljava/lang/String;)Ljava/lang/String;
  astore 12
  new java/io/File
  astore 13
  aload 13
  aload 12
  invokespecial java/io/File/<init>(Ljava/lang/String;)V
  aload 13
  invokestatic com/mobisage/android/SNSSSLSocketFactory$a/a(Ljava/io/File;)Ljava/lang/String;
  astore 14
  aload_1
  astore_2
  aload_2
  getfield com/mobisage/android/b/c Landroid/os/Bundle;
  astore 10
  ldc "SourceURL"
  astore 11
  aload 10
  aload 11
  invokevirtual android/os/Bundle/getString(Ljava/lang/String;)Ljava/lang/String;
  astore 15
  new java/lang/StringBuilder
  astore 16
  ldc "file://"
  astore 11
  aload 16
  aload 11
  invokespecial java/lang/StringBuilder/<init>(Ljava/lang/String;)V
  aload_1
  astore_2
  aload_2
  getfield com/mobisage/android/b/c Landroid/os/Bundle;
  astore 10
  ldc "TargetURL"
  astore 11
  aload 10
  aload 11
  invokevirtual android/os/Bundle/getString(Ljava/lang/String;)Ljava/lang/String;
  astore 17
  aload 16
  aload 17
  invokevirtual java/lang/StringBuilder/append(Ljava/lang/String;)Ljava/lang/StringBuilder;
  astore 16
  aload 16
  invokevirtual java/lang/StringBuilder/toString()Ljava/lang/String;
  astore 17
  aload 14
  aload 15
  aload 17
  invokevirtual java/lang/String/replace(Ljava/lang/CharSequence;Ljava/lang/CharSequence;)Ljava/lang/String;
  astore 15
  new java/io/File
  astore 13
  aload 13
  aload 12
  invokespecial java/io/File/<init>(Ljava/lang/String;)V
  aload 13
  aload 15
  invokestatic com/mobisage/android/SNSSSLSocketFactory$a/a(Ljava/io/File;Ljava/lang/String;)V
Label1:
  aload 7
  invokevirtual com/mobisage/android/b/a()Z
  istore 5
  iload 5
  invokestatic app/DummyClass/invokeIfStmt(Z)V
  iload 5
  ifeq Label2
  aload_0
  astore_2
  aload_2
  getfield com/mobisage/android/O/e Ljava/util/concurrent/ConcurrentHashMap;
  astore_3
  aload_2
  astore_0
  aload 7
  getfield com/mobisage/android/b/b Ljava/util/UUID;
  astore 4
  aload_3
  aload 4
  invokevirtual java/util/concurrent/ConcurrentHashMap/remove(Ljava/lang/Object;)Ljava/lang/Object;
  pop
  aload 7
  getfield com/mobisage/android/b/g Lcom/mobisage/android/a;
  astore_2
  aload_2
  astore 18
  aload 18
  astore_2
  aload_2
  invokestatic app/DummyClass/invokeIfStmt(Ljava/lang/Object;)V
  aload 18
  ifnull Label2
  aload 7
  getfield com/mobisage/android/b/g Lcom/mobisage/android/a;
  astore_2
  aload_2
  astore 18
  aload 18
  astore_2
  aload_2
  aload 7
  invokeinterface com/mobisage/android/a/a(Lcom/mobisage/android/b;)V 2
  goto Label2
  nop
.end <method>

