.source SourceFile
.class final  com/mobisage/android/w$b
.super com/mobisage/android/Q
.field private "a" Lcom/mobisage/android/w;

.method private <init>(Lcom/mobisage/android/w;)V
.limit locals 5
.limit stack 200
  nop
  aload_0
  aload_1
  putfield com/mobisage/android/w$b/a Lcom/mobisage/android/w;
  aload_0
  invokespecial com/mobisage/android/Q/<init>()V
  ldc2_w 5
  lstore_2
  aload_0
  lload_2
  putfield com/mobisage/android/Q/c J
  iconst_1
  istore 4
  aload_0
  iload 4
  putfield com/mobisage/android/Q/d Z
  ldc2_w 600
  lstore_2
  aload_0
  lload_2
  putfield com/mobisage/android/Q/e J
  return
  nop
.end <method>

.method <init>(Lcom/mobisage/android/w;B)V
  .synthetic
.limit locals 3
.limit stack 200
  nop
  aload_0
  aload_1
  invokespecial com/mobisage/android/w$b/<init>(Lcom/mobisage/android/w;)V
  return
  nop
.end <method>

.method public final run()V
.limit locals 5
.limit stack 200
  nop
  new com/mobisage/android/b
  astore_1
  aload_1
  invokespecial com/mobisage/android/b/<init>()V
  aload_0
  getfield com/mobisage/android/w$b/a Lcom/mobisage/android/w;
  astore_2
  new java/lang/NoClassDefFoundError
  dup
  invokespecial java/lang/NoClassDefFoundError/<init>()V
  athrow
  nop
  aload_1
  aload_3
  putfield com/mobisage/android/b/g Lcom/mobisage/android/a;
  invokestatic com/mobisage/android/w/a()Lcom/mobisage/android/w;
  astore_2
  sipush 3000
  istore 4
  aload_2
  iload 4
  aload_1
  invokevirtual com/mobisage/android/w/a(ILcom/mobisage/android/b;)V
  return
  nop
.end <method>

