.source SuizongAPIAdapter.java
.class public  com/admogo/adapters/SuizongAPIAdapter
.super com/admogo/adapters/AdMogoAdapter
.field static final "API" Ljava/lang/String; =  "http://api.suizong.com/mobile/"
.field public static final "CONTENT_BUF_SIZE" I =  4096
.field public static "ip" Ljava/lang/String;
.field private static "url" Ljava/lang/String;
.field private "adMogoLayout" Lcom/admogo/AdMogoLayout;
.field private "density" D
.field private "px50" D
.field private "serial_key" Ljava/lang/String;
.field private "suizongAD" Lcom/admogo/obj/SuizongAD;

.method static <clinit>()V
.limit locals 1
.limit stack 200
  nop
  ldc ""
  astore_0
  aload_0
  putstatic com/admogo/adapters/SuizongAPIAdapter/url Ljava/lang/String;
  return
  nop
.end <method>

.method public <init>(Lcom/admogo/AdMogoLayout;Lcom/admogo/obj/Ration;)V
.limit locals 4
.limit stack 200
  nop
  aload_0
  aload_1
  aload_2
  invokespecial com/admogo/adapters/AdMogoAdapter/<init>(Lcom/admogo/AdMogoLayout;Lcom/admogo/obj/Ration;)V
  ldc "67590f398bf0447931eb20fa2b63bb34"
  astore_3
  aload_0
  aload_3
  putfield com/admogo/adapters/SuizongAPIAdapter/serial_key Ljava/lang/String;
  return
  nop
.end <method>

.method static access$0(Lcom/admogo/adapters/SuizongAPIAdapter;Lcom/admogo/AdMogoLayout;Ljava/lang/String;)V
  .synthetic
.limit locals 3
.limit stack 200
  nop
  aload_0
  aload_1
  aload_2
  invokespecial com/admogo/adapters/SuizongAPIAdapter/requestSuizongAD(Lcom/admogo/AdMogoLayout;Ljava/lang/String;)V
  return
  nop
.end <method>

.method static access$1(Lcom/admogo/adapters/SuizongAPIAdapter;)Lcom/admogo/obj/SuizongAD;
  .synthetic
.limit locals 2
.limit stack 200
  nop
  aload_0
  getfield com/admogo/adapters/SuizongAPIAdapter/suizongAD Lcom/admogo/obj/SuizongAD;
  astore_1
  aload_1
  areturn
  nop
.end <method>

.method static access$2(Lcom/admogo/adapters/SuizongAPIAdapter;)Ljava/util/HashMap;
  .synthetic
.limit locals 2
.limit stack 200
  nop
  aload_0
  invokespecial com/admogo/adapters/SuizongAPIAdapter/putInfoToRequestCount()Ljava/util/HashMap;
  astore_1
  aload_1
  areturn
  nop
.end <method>

.method static access$3(Lcom/admogo/adapters/SuizongAPIAdapter;Ljava/util/HashMap;Ljava/lang/String;)V
  .synthetic
.limit locals 3
.limit stack 200
  nop
  aload_0
  aload_1
  aload_2
  invokespecial com/admogo/adapters/SuizongAPIAdapter/httpRequest(Ljava/util/HashMap;Ljava/lang/String;)V
  return
  nop
.end <method>

.method public click()V
.limit locals 6
.limit stack 200
  nop
  new java/lang/StringBuilder
  astore_1
  ldc "http://api.suizong.com/mobile/"
  astore_3
  aload_3
  invokestatic java/lang/String/valueOf(Ljava/lang/Object;)Ljava/lang/String;
  astore_2
  aload_1
  aload_2
  invokespecial java/lang/StringBuilder/<init>(Ljava/lang/String;)V
  ldc "ADServerClickAPI"
  astore_3
  aload_1
  aload_3
  invokevirtual java/lang/StringBuilder/append(Ljava/lang/String;)Ljava/lang/StringBuilder;
  astore_1
  aload_1
  invokevirtual java/lang/StringBuilder/toString()Ljava/lang/String;
  astore_2
  aload_2
  putstatic com/admogo/adapters/SuizongAPIAdapter/url Ljava/lang/String;
  new com/admogo/adapters/SuizongAPIAdapter$2
  astore 4
  aload 4
  aload_0
  invokespecial com/admogo/adapters/SuizongAPIAdapter$2/<init>(Lcom/admogo/adapters/SuizongAPIAdapter;)V
  aload 4
  invokevirtual com/admogo/adapters/SuizongAPIAdapter$2/start()V
  aload_0
  getfield com/admogo/adapters/SuizongAPIAdapter/adMogoLayout Lcom/admogo/AdMogoLayout;
  astore 5
  new java/lang/NoClassDefFoundError
  dup
  invokespecial java/lang/NoClassDefFoundError/<init>()V
  athrow
  return
  nop
.end <method>

.method public static createConnection(Ljava/util/HashMap;Ljava/lang/String;Ljava/lang/String;ZZZZII)Ljava/net/HttpURLConnection;
  .signature_attr "(Ljava/util/HashMap<Ljava/lang/String;Ljava/lang/String;>;Ljava/lang/String;Ljava/lang/String;ZZZZII)Ljava/net/HttpURLConnection;"
.limit locals 22
.limit stack 200
  nop
  new java/net/URL
  astore 10
  getstatic com/admogo/adapters/SuizongAPIAdapter/url Ljava/lang/String;
  astore 11
  aload 10
  aload 11
  invokespecial java/net/URL/<init>(Ljava/lang/String;)V
  aload 10
  invokevirtual java/net/URL/openConnection()Ljava/net/URLConnection;
  astore 12
  aload 12
  astore 14
  aload 14
  checkcast java/net/HttpURLConnection
  astore 14
  aload 14
  astore 13
  iload_3
  istore 9
  aload 13
  iload 9
  invokevirtual java/net/HttpURLConnection/setDoInput(Z)V
  iload 4
  istore 9
  aload 13
  iload 9
  invokevirtual java/net/HttpURLConnection/setDoOutput(Z)V
  aload 13
  aload_2
  invokevirtual java/net/HttpURLConnection/setRequestMethod(Ljava/lang/String;)V
  iload 5
  istore 9
  aload 13
  iload 9
  invokevirtual java/net/HttpURLConnection/setUseCaches(Z)V
  iload 6
  istore 9
  aload 13
  iload 9
  invokevirtual java/net/HttpURLConnection/setInstanceFollowRedirects(Z)V
  iload 7
  istore 9
  aload 13
  iload 9
  invokevirtual java/net/HttpURLConnection/setConnectTimeout(I)V
  iload 8
  istore 9
  aload 13
  iload 9
  invokevirtual java/net/HttpURLConnection/setReadTimeout(I)V
  new java/lang/NoClassDefFoundError
  dup
  invokespecial java/lang/NoClassDefFoundError/<init>()V
  athrow
  iload_0
  ifeq Label0
  aload_0
  invokevirtual java/util/HashMap/isEmpty()Z
  istore 6
  iload 6
  istore 9
  iload 9
  invokestatic app/DummyClass/invokeIfStmt(Z)V
  iload 6
  ifne Label0
  aload_0
  invokevirtual java/util/HashMap/keySet()Ljava/util/Set;
  astore 15
  aload 15
  invokeinterface java/util/Set/iterator()Ljava/util/Iterator; 1
  astore 16
Label2:
  aload 16
  invokeinterface java/util/Iterator/hasNext()Z 1
  istore 6
  iload 6
  istore 9
  iload 9
  invokestatic app/DummyClass/invokeIfStmt(Z)V
  iload 6
  ifne Label1
Label0:
  aload 13
  invokevirtual java/net/HttpURLConnection/connect()V
  aload 13
  invokevirtual java/net/HttpURLConnection/getOutputStream()Ljava/io/OutputStream;
  astore 17
  aload_1
  invokevirtual java/lang/String/getBytes()[B
  astore 18
  aload 17
  aload 18
  invokevirtual java/io/OutputStream/write([B)V
  aload 17
  invokevirtual java/io/OutputStream/flush()V
  aload 17
  invokevirtual java/io/OutputStream/close()V
  aload 13
  areturn
Label1:
  aload 16
  invokeinterface java/util/Iterator/next()Ljava/lang/Object; 1
  astore 19
  aload 19
  astore 20
  aload 20
  checkcast java/lang/String
  astore 20
  aload 20
  astore 11
  aload_0
  aload 11
  invokevirtual java/util/HashMap/get(Ljava/lang/Object;)Ljava/lang/Object;
  astore 19
  aload 19
  astore 21
  aload 21
  checkcast java/lang/String
  astore 21
  aload 21
  astore_2
  aload 13
  aload 11
  aload_2
  invokevirtual java/net/HttpURLConnection/addRequestProperty(Ljava/lang/String;Ljava/lang/String;)V
  goto Label2
  nop
.end <method>

.method public displaySuizongAD()V
.limit locals 29
.limit stack 200
  nop
  aload_0
  astore_1
  aload_1
  getfield com/admogo/adapters/AdMogoAdapter/adMogoLayoutReference Ljava/lang/ref/WeakReference;
  astore 7
  aload 7
  invokevirtual java/lang/ref/WeakReference/get()Ljava/lang/Object;
  astore 8
  aload 8
  astore 10
  new java/lang/NoClassDefFoundError
  dup
  invokespecial java/lang/NoClassDefFoundError/<init>()V
  athrow
  aload 10
  astore 9
  aload 9
  invokestatic app/DummyClass/invokeIfStmt(Ljava/lang/Object;)V
  iload 9
  ifne Label0
Label1:
  return
Label0:
  aload 9
  getfield com/admogo/AdMogoLayout/activityReference Ljava/lang/ref/WeakReference;
  astore 7
  aload 7
  invokevirtual java/lang/ref/WeakReference/get()Ljava/lang/Object;
  astore 8
  aload 8
  astore 12
  aload 12
  checkcast android/app/Activity
  astore 12
  aload 12
  astore 11
  aload 11
  invokestatic app/DummyClass/invokeIfStmt(Ljava/lang/Object;)V
  aload 11
  ifnull Label1
  getstatic com/admogo/util/AdMogoUtil/ADMOGO Ljava/lang/String;
  astore 13
  ldc "Serving SuizongAD type: banner"
  astore 14
  aload 13
  aload 14
  invokestatic android/util/Log/d(Ljava/lang/String;Ljava/lang/String;)I
  pop
  new android/webkit/WebView
  astore 15
  aload 15
  aload 11
  invokespecial android/webkit/WebView/<init>(Landroid/content/Context;)V
  new android/widget/RelativeLayout$LayoutParams
  astore 16
  aload_0
  astore_1
  aload_1
  getfield com/admogo/adapters/SuizongAPIAdapter/px50 D
  dstore_1
  dload_1
  dstore 17
  dload 17
  dstore_1
  dload_1
  d2i
  istore_1
  iload_1
  istore 19
  iconst_m1
  istore 20
  iload 20
  istore_1
  iload 19
  istore_2
  aload 16
  iload_1
  iload_2
  invokespecial android/widget/RelativeLayout$LayoutParams/<init>(II)V
  aload 9
  aload 15
  aload 16
  invokevirtual com/admogo/AdMogoLayout/addView(Landroid/view/View;Landroid/view/ViewGroup$LayoutParams;)V
  aload 15
  invokevirtual android/webkit/WebView/getSettings()Landroid/webkit/WebSettings;
  astore 21
  iconst_1
  istore 20
  aload 21
  astore_1
  iload 20
  istore_2
  aload_1
  iload_2
  invokevirtual android/webkit/WebSettings/setJavaScriptEnabled(Z)V
  aload_0
  astore_1
  aload_1
  getfield com/admogo/adapters/SuizongAPIAdapter/suizongAD Lcom/admogo/obj/SuizongAD;
  astore_1
  aload_1
  astore 22
  aload 22
  astore_1
  aload_1
  getfield com/admogo/obj/SuizongAD/data Ljava/lang/String;
  astore_1
  aload_1
  astore 23
  ldc "http://api.suizong.com/mobile"
  astore 14
  ldc "text/html"
  astore 24
  ldc "UTF-8"
  astore 25
  aconst_null
  astore 26
  aload 15
  astore_1
  aload 14
  astore_2
  aload 23
  astore_3
  aload 24
  astore 4
  aload 25
  astore 5
  aload 26
  astore 6
  aload_1
  aload_2
  aload_3
  aload 4
  aload 5
  aload 6
  invokevirtual android/webkit/WebView/loadDataWithBaseURL(Ljava/lang/String;Ljava/lang/String;Ljava/lang/String;Ljava/lang/String;Ljava/lang/String;)V
  ldc 33554432
  istore 20
  iload 20
  istore_1
  aload 15
  iload_1
  invokevirtual android/webkit/WebView/setScrollBarStyle(I)V
  new com/admogo/adapters/SuizongAPIAdapter$webViewClient
  astore 27
  aconst_null
  astore 26
  aload 27
  astore_1
  aload_0
  astore_2
  aload 26
  astore_3
  aload_1
  aload_2
  aload_3
  invokespecial com/admogo/adapters/SuizongAPIAdapter$webViewClient/<init>(Lcom/admogo/adapters/SuizongAPIAdapter;Lcom/admogo/adapters/SuizongAPIAdapter$webViewClient;)V
  aload 27
  astore_1
  aload 15
  aload_1
  invokevirtual android/webkit/WebView/setWebViewClient(Landroid/webkit/WebViewClient;)V
  bipush 51
  istore 20
  iload 20
  istore_1
  aload 9
  aload 15
  iload_1
  invokevirtual com/admogo/AdMogoLayout/pushSubView(Landroid/view/ViewGroup;I)V
  aload 9
  getfield com/admogo/AdMogoLayout/adMogoManager Lcom/admogo/AdMogoManager;
  astore_1
  aload_1
  astore 28
  aload 28
  astore_1
  aload_1
  invokevirtual com/admogo/AdMogoManager/resetRollover()V
  aload 9
  invokevirtual com/admogo/AdMogoLayout/rotateThreadedDelayed()V
  goto Label1
  nop
.end <method>

.method public finish()V
.limit locals 3
.limit stack 200
  nop
  getstatic com/admogo/util/AdMogoUtil/ADMOGO Ljava/lang/String;
  astore_1
  ldc "SuizongAD Finished"
  astore_2
  new java/lang/NoClassDefFoundError
  dup
  invokespecial java/lang/NoClassDefFoundError/<init>()V
  athrow
  return
  nop
.end <method>

.method private getLocalIPAddress()Ljava/lang/String;
.limit locals 12
.limit stack 200
  .catch  java/net/SocketException <from> Label5 <to> Label6 <using> Label4
  .catch  java/net/SocketException <from> Label0 <to> Label7 <using> Label4
  nop
Label5:
  invokestatic java/net/NetworkInterface/getNetworkInterfaces()Ljava/util/Enumeration;
  astore_1
Label1:
  aload_1
  invokeinterface java/util/Enumeration/hasMoreElements()Z 1
  istore_2
Label6:
  new java/lang/NoClassDefFoundError
  dup
  invokespecial java/lang/NoClassDefFoundError/<init>()V
  athrow
  iload_2
  ifne Label0
Label3:
  ldc ""
  astore_3
  aload_3
  areturn
Label0:
  aload_1
  invokeinterface java/util/Enumeration/nextElement()Ljava/lang/Object; 1
  astore 4
  aload 4
  astore 6
  aload 6
  checkcast java/net/NetworkInterface
  astore 6
  aload 6
  astore 5
  aload 5
  invokevirtual java/net/NetworkInterface/getInetAddresses()Ljava/util/Enumeration;
  astore 7
Label2:
  aload 7
  invokeinterface java/util/Enumeration/hasMoreElements()Z 1
  istore_2
  iload_2
  invokestatic app/DummyClass/invokeIfStmt(Z)V
  iload_2
  ifeq Label1
  aload 7
  invokeinterface java/util/Enumeration/nextElement()Ljava/lang/Object; 1
  astore 4
  aload 4
  astore 9
  aload 9
  checkcast java/net/InetAddress
  astore 9
  aload 9
  astore 8
  aload 8
  invokevirtual java/net/InetAddress/isLoopbackAddress()Z
  istore_2
  iload_2
  invokestatic app/DummyClass/invokeIfStmt(Z)V
  iload_2
  ifne Label2
  aload 8
  invokevirtual java/net/InetAddress/getHostAddress()Ljava/lang/String;
  astore 10
  aload 10
  invokevirtual java/lang/String/toString()Ljava/lang/String;
  astore 10
Label7:
  aload 10
  areturn
Label4:
  astore 11
  aload 11
  invokevirtual java/net/SocketException/toString()Ljava/lang/String;
  astore 10
  ldc "Error"
  astore_3
  new java/lang/NoClassDefFoundError
  dup
  invokespecial java/lang/NoClassDefFoundError/<init>()V
  athrow
  goto Label3
  nop
.end <method>

.method public handle()V
.limit locals 16
.limit stack 200
  nop
  aload_0
  getfield com/admogo/adapters/AdMogoAdapter/adMogoLayoutReference Ljava/lang/ref/WeakReference;
  astore_1
  aload_1
  invokevirtual java/lang/ref/WeakReference/get()Ljava/lang/Object;
  astore_2
  aload_2
  astore 4
  new java/lang/NoClassDefFoundError
  dup
  invokespecial java/lang/NoClassDefFoundError/<init>()V
  athrow
  aload 4
  astore_3
  aload_0
  aload_3
  putfield com/admogo/adapters/SuizongAPIAdapter/adMogoLayout Lcom/admogo/AdMogoLayout;
  aload_0
  getfield com/admogo/adapters/SuizongAPIAdapter/adMogoLayout Lcom/admogo/AdMogoLayout;
  astore_3
  aload_3
  invokestatic app/DummyClass/invokeIfStmt(Ljava/lang/Object;)V
  aload_3
  ifnonnull Label0
Label1:
  return
Label0:
  new com/admogo/obj/SuizongAD
  astore 5
  aload 5
  invokespecial com/admogo/obj/SuizongAD/<init>()V
  aload_0
  aload 5
  putfield com/admogo/adapters/SuizongAPIAdapter/suizongAD Lcom/admogo/obj/SuizongAD;
  getstatic com/admogo/util/AdMogoUtil/density D
  dstore 6
  aload_0
  dload 6
  putfield com/admogo/adapters/SuizongAPIAdapter/density D
  aload_0
  getfield com/admogo/adapters/SuizongAPIAdapter/density D
  dstore 6
  bipush 50
  istore 9
  iload 9
  dload 6
  invokestatic com/admogo/util/AdMogoUtil/convertToScreenPixels(ID)I
  istore 8
  iload 8
  i2d
  dstore 6
  aload_0
  dload 6
  putfield com/admogo/adapters/SuizongAPIAdapter/px50 D
  aload_0
  getfield com/admogo/adapters/SuizongAPIAdapter/adMogoLayout Lcom/admogo/AdMogoLayout;
  astore_3
  aload_3
  getfield com/admogo/AdMogoLayout/scheduler Ljava/util/concurrent/ScheduledExecutorService;
  astore 10
  new com/admogo/adapters/SuizongAPIAdapter$FetchSuizongADRunnable
  astore 11
  aload_0
  getfield com/admogo/adapters/AdMogoAdapter/ration Lcom/admogo/obj/Ration;
  astore 12
  aload 11
  aload_0
  aload_0
  aload 12
  invokespecial com/admogo/adapters/SuizongAPIAdapter$FetchSuizongADRunnable/<init>(Lcom/admogo/adapters/SuizongAPIAdapter;Lcom/admogo/adapters/SuizongAPIAdapter;Lcom/admogo/obj/Ration;)V
  getstatic java/util/concurrent/TimeUnit/SECONDS Ljava/util/concurrent/TimeUnit;
  astore 13
  ldc2_w 0
  lstore 14
  aload 10
  aload 11
  lload 14
  aload 13
  invokeinterface java/util/concurrent/ScheduledExecutorService/schedule(Ljava/lang/Runnable;JLjava/util/concurrent/TimeUnit;)Ljava/util/concurrent/ScheduledFuture; 5
  pop
  goto Label1
  nop
.end <method>

.method private httpRequest(Ljava/util/HashMap;Ljava/lang/String;)V
  .signature_attr "(Ljava/util/HashMap<Ljava/lang/String;Ljava/lang/String;>;Ljava/lang/String;)V"
.limit locals 39
.limit stack 200
  .catch  java/lang/Throwable <from> Label23 <to> Label7 <using> Label21
  .catch  java/lang/Exception <from> Label23 <to> Label7 <using> Label22
  .catch  java/lang/Throwable <from> Label2 <to> Label28 <using> Label21
  .catch  java/lang/Exception <from> Label2 <to> Label28 <using> Label22
  .catch  java/lang/Throwable <from> Label14 <to> Label29 <using> Label21
  .catch  java/lang/Throwable <from> Label1 <to> Label13 <using> Label21
  .catch  java/lang/Exception <from> Label1 <to> Label13 <using> Label22
  .catch  java/lang/Throwable <from> Label11 <to> Label37 <using> Label21
  .catch  java/lang/Exception <from> Label11 <to> Label37 <using> Label22
  .catch  java/lang/Throwable <from> Label15 <to> Label42 <using> Label21
  .catch  java/lang/Exception <from> Label15 <to> Label42 <using> Label22
  nop
  iconst_0
  istore 12
  iconst_0
  istore 13
  iconst_0
  istore 14
Label23:
  ldc "POST"
  astore 15
  iconst_1
  istore 16
  iconst_1
  istore 17
  iconst_0
  istore 18
  iconst_0
  istore 19
  sipush 30000
  istore 20
  sipush 30000
  istore 21
  aload_1
  astore_3
  aload_2
  astore 4
  aload 15
  astore 5
  iload 16
  istore 6
  iload 17
  istore 7
  iload 18
  istore 8
  iload 19
  istore 9
  iload 20
  istore 10
  iload 21
  istore 11
  aload_3
  aload 4
  aload 5
  iload 6
  iload 7
  iload 8
  iload 9
  iload 10
  iload 11
  invokestatic com/admogo/adapters/SuizongAPIAdapter/createConnection(Ljava/util/HashMap;Ljava/lang/String;Ljava/lang/String;ZZZZII)Ljava/net/HttpURLConnection;
  astore 12
  aload 12
  invokevirtual java/net/HttpURLConnection/getResponseCode()I
  istore 22
  iload 22
  istore_3
  new java/lang/NoClassDefFoundError
  dup
  invokespecial java/lang/NoClassDefFoundError/<init>()V
  athrow
  sipush 200
  istore 16
  iload 22
  istore_3
  iload 16
  iload_3
  if_icmpne Label0
  ldc "request"
  astore 15
  aload_2
  astore_3
  aload_3
  aload 15
  invokevirtual java/lang/String/equals(Ljava/lang/Object;)Z
  istore 23
  iload 23
  istore_3
  iload_3
  invokestatic app/DummyClass/invokeIfStmt(Z)V
  iload 23
  ifeq Label1
  aload_0
  astore_3
  aload_3
  getfield com/admogo/adapters/SuizongAPIAdapter/suizongAD Lcom/admogo/obj/SuizongAD;
  astore_3
  aload_3
  astore 24
  ldc "status"
  astore 15
  aload 12
  aload 15
  invokevirtual java/net/HttpURLConnection/getHeaderField(Ljava/lang/String;)Ljava/lang/String;
  astore 25
  aload 25
  astore_3
  aload 24
  astore 4
  aload 4
  aload_3
  putfield com/admogo/obj/SuizongAD/status Ljava/lang/String;
  aload_0
  astore_3
  aload_3
  getfield com/admogo/adapters/SuizongAPIAdapter/suizongAD Lcom/admogo/obj/SuizongAD;
  astore_3
  aload_3
  astore 24
  aload 24
  astore_3
  aload_3
  getfield com/admogo/obj/SuizongAD/status Ljava/lang/String;
  astore_3
  aload_3
  astore 25
  ldc "1"
  astore 15
  aload 25
  astore_3
  aload_3
  aload 15
  invokevirtual java/lang/String/equals(Ljava/lang/Object;)Z
  istore 23
  iload 23
  istore_3
  iload_3
  invokestatic app/DummyClass/invokeIfStmt(Z)V
  iload 23
  ifeq Label2
  aload_0
  astore_3
  aload_3
  getfield com/admogo/adapters/SuizongAPIAdapter/suizongAD Lcom/admogo/obj/SuizongAD;
  astore_3
  aload_3
  astore 24
  ldc "adid"
  astore 15
  aload 12
  aload 15
  invokevirtual java/net/HttpURLConnection/getHeaderField(Ljava/lang/String;)Ljava/lang/String;
  astore 25
  aload 25
  astore_3
  aload 24
  astore 4
  aload 4
  aload_3
  putfield com/admogo/obj/SuizongAD/adid Ljava/lang/String;
  aload_0
  astore_3
  aload_3
  getfield com/admogo/adapters/SuizongAPIAdapter/suizongAD Lcom/admogo/obj/SuizongAD;
  astore_3
  aload_3
  astore 24
  ldc "updatetime"
  astore 15
  aload 12
  aload 15
  invokevirtual java/net/HttpURLConnection/getHeaderField(Ljava/lang/String;)Ljava/lang/String;
  astore 25
  aload 25
  astore_3
  aload 24
  astore 4
  aload 4
  aload_3
  putfield com/admogo/obj/SuizongAD/updateTime Ljava/lang/String;
  aload_0
  astore_3
  aload_3
  getfield com/admogo/adapters/SuizongAPIAdapter/suizongAD Lcom/admogo/obj/SuizongAD;
  astore_3
  aload_3
  astore 24
  ldc "width"
  astore 15
  aload 12
  aload 15
  invokevirtual java/net/HttpURLConnection/getHeaderField(Ljava/lang/String;)Ljava/lang/String;
  astore 25
  aload 25
  astore_3
  aload 24
  astore 4
  aload 4
  aload_3
  putfield com/admogo/obj/SuizongAD/awidth Ljava/lang/String;
  aload_0
  astore_3
  aload_3
  getfield com/admogo/adapters/SuizongAPIAdapter/suizongAD Lcom/admogo/obj/SuizongAD;
  astore_3
  aload_3
  astore 24
  ldc "height"
  astore 15
  aload 12
  aload 15
  invokevirtual java/net/HttpURLConnection/getHeaderField(Ljava/lang/String;)Ljava/lang/String;
  astore 25
  aload 25
  astore_3
  aload 24
  astore 4
  aload 4
  aload_3
  putfield com/admogo/obj/SuizongAD/aheight Ljava/lang/String;
  aload_0
  astore_3
  aload_3
  getfield com/admogo/adapters/SuizongAPIAdapter/suizongAD Lcom/admogo/obj/SuizongAD;
  astore_3
  aload_3
  astore 24
  ldc "width"
  astore 15
  aload 12
  aload 15
  invokevirtual java/net/HttpURLConnection/getHeaderField(Ljava/lang/String;)Ljava/lang/String;
  astore 25
  aload 25
  astore_3
  aload 24
  astore 4
  aload 4
  aload_3
  putfield com/admogo/obj/SuizongAD/awidth Ljava/lang/String;
  aload_0
  astore_3
  aload_3
  getfield com/admogo/adapters/SuizongAPIAdapter/suizongAD Lcom/admogo/obj/SuizongAD;
  astore_3
  aload_3
  astore 24
  ldc "refresh"
  astore 15
  aload 12
  aload 15
  invokevirtual java/net/HttpURLConnection/getHeaderField(Ljava/lang/String;)Ljava/lang/String;
  astore 25
  aload 25
  astore_3
  aload 24
  astore 4
  aload 4
  aload_3
  putfield com/admogo/obj/SuizongAD/refreshTime Ljava/lang/String;
  aload_0
  astore_3
  aload_3
  getfield com/admogo/adapters/SuizongAPIAdapter/suizongAD Lcom/admogo/obj/SuizongAD;
  astore_3
  aload_3
  astore 24
  ldc "imps_url"
  astore 15
  aload 12
  aload 15
  invokevirtual java/net/HttpURLConnection/getHeaderField(Ljava/lang/String;)Ljava/lang/String;
  astore 25
  aload 25
  astore_3
  aload 24
  astore 4
  aload 4
  aload_3
  putfield com/admogo/obj/SuizongAD/impURL Ljava/lang/String;
  aload_0
  astore_3
  aload_3
  getfield com/admogo/adapters/SuizongAPIAdapter/suizongAD Lcom/admogo/obj/SuizongAD;
  astore_3
  aload_3
  astore 24
  ldc "click_url"
  astore 15
  aload 12
  aload 15
  invokevirtual java/net/HttpURLConnection/getHeaderField(Ljava/lang/String;)Ljava/lang/String;
  astore 25
  aload 25
  astore_3
  aload 24
  astore 4
  aload 4
  aload_3
  putfield com/admogo/obj/SuizongAD/clickURL Ljava/lang/String;
  aload_0
  astore_3
  aload_3
  getfield com/admogo/adapters/SuizongAPIAdapter/suizongAD Lcom/admogo/obj/SuizongAD;
  astore_3
  aload_3
  astore 24
  ldc "price_type"
  astore 15
  aload 12
  aload 15
  invokevirtual java/net/HttpURLConnection/getHeaderField(Ljava/lang/String;)Ljava/lang/String;
  astore 25
  aload 25
  astore_3
  aload 24
  astore 4
  aload 4
  aload_3
  putfield com/admogo/obj/SuizongAD/priceType Ljava/lang/String;
  aload_0
  astore_3
  aload_3
  getfield com/admogo/adapters/SuizongAPIAdapter/suizongAD Lcom/admogo/obj/SuizongAD;
  astore_3
  aload_3
  astore 24
  ldc "price"
  astore 15
  aload 12
  aload 15
  invokevirtual java/net/HttpURLConnection/getHeaderField(Ljava/lang/String;)Ljava/lang/String;
  astore 25
  aload 25
  astore_3
  aload 24
  astore 4
  aload 4
  aload_3
  putfield com/admogo/obj/SuizongAD/price Ljava/lang/String;
Label7:
  aload 14
  invokestatic app/DummyClass/invokeIfStmt(Ljava/lang/Object;)V
  aload 14
  ifnull Label3
Label25:
  aload 14
  invokevirtual java/io/BufferedReader/close()V
Label3:
  aload 13
  invokestatic app/DummyClass/invokeIfStmt(Ljava/lang/Object;)V
  aload 13
  ifnull Label4
Label27:
  aload 13
  invokevirtual java/io/InputStream/close()V
Label4:
  goto Label5
Label5:
  aload 12
  invokestatic app/DummyClass/invokeIfStmt(Ljava/lang/Object;)V
  iload 12
  ifeq Label6
  aload 12
  invokevirtual java/net/HttpURLConnection/disconnect()V
Label6:
  return
Label2:
  aload_0
  astore_3
  aload_3
  getfield com/admogo/adapters/SuizongAPIAdapter/suizongAD Lcom/admogo/obj/SuizongAD;
  astore_3
  aload_3
  astore 24
  ldc "msg"
  astore 15
  aload 12
  aload 15
  invokevirtual java/net/HttpURLConnection/getHeaderField(Ljava/lang/String;)Ljava/lang/String;
  astore 25
  aload 25
  astore_3
  aload 24
  astore 4
  aload 4
  aload_3
  putfield com/admogo/obj/SuizongAD/msg Ljava/lang/String;
  getstatic com/admogo/util/AdMogoUtil/ADMOGO Ljava/lang/String;
  astore 25
  new java/lang/StringBuilder
  astore 26
  ldc "suizong status != 1 msg->"
  astore 15
  aload 26
  astore_3
  aload_3
  aload 15
  invokespecial java/lang/StringBuilder/<init>(Ljava/lang/String;)V
  aload_0
  astore_3
  aload_3
  getfield com/admogo/adapters/SuizongAPIAdapter/suizongAD Lcom/admogo/obj/SuizongAD;
  astore_3
  aload_3
  astore 24
  aload 24
  astore_3
  aload_3
  getfield com/admogo/obj/SuizongAD/msg Ljava/lang/String;
  astore_3
  aload_3
  astore 27
  aload 26
  astore_3
  aload 27
  astore 4
  aload_3
  aload 4
  invokevirtual java/lang/StringBuilder/append(Ljava/lang/String;)Ljava/lang/StringBuilder;
  astore 26
  aload 26
  astore_3
  aload_3
  invokevirtual java/lang/StringBuilder/toString()Ljava/lang/String;
  astore 27
  aload 25
  astore_3
  aload 27
  astore 4
  aload_3
  aload 4
  invokestatic android/util/Log/w(Ljava/lang/String;Ljava/lang/String;)I
  pop
Label28:
  goto Label7
Label22:
  astore 28
Label14:
  aload_0
  astore_3
  aload_3
  getfield com/admogo/adapters/SuizongAPIAdapter/suizongAD Lcom/admogo/obj/SuizongAD;
  astore_3
  aload_3
  astore 24
  ldc "2"
  astore 15
  aload 24
  astore_3
  aload_3
  aload 15
  putfield com/admogo/obj/SuizongAD/status Ljava/lang/String;
  ldc "httpRequest"
  astore 15
  ldc "httpRequest"
  astore 29
  aload 29
  astore_3
  aload 28
  astore 4
  new java/lang/NoClassDefFoundError
  dup
  invokespecial java/lang/NoClassDefFoundError/<init>()V
  athrow
Label29:
  aload 14
  invokestatic app/DummyClass/invokeIfStmt(Ljava/lang/Object;)V
  iload 14
  ifeq Label8
Label31:
  aload 14
  invokevirtual java/io/BufferedReader/close()V
Label8:
  aload 13
  invokestatic app/DummyClass/invokeIfStmt(Ljava/lang/Object;)V
  iload 13
  ifeq Label9
Label33:
  aload 13
  invokevirtual java/io/InputStream/close()V
Label9:
  goto Label10
Label10:
  aload 12
  invokestatic app/DummyClass/invokeIfStmt(Ljava/lang/Object;)V
  iload 12
  ifeq Label6
  aload 12
  invokevirtual java/net/HttpURLConnection/disconnect()V
  goto Label6
Label1:
  ldc "getbody"
  astore 15
  aload_2
  astore_3
  aload_3
  aload 15
  invokevirtual java/lang/String/equals(Ljava/lang/Object;)Z
  istore 23
  iload 23
  istore_3
  iload_3
  invokestatic app/DummyClass/invokeIfStmt(Z)V
  iload 23
  ifeq Label11
  aload 12
  invokevirtual java/net/HttpURLConnection/getInputStream()Ljava/io/InputStream;
  astore 13
  new java/io/BufferedReader
  astore 30
  new java/io/InputStreamReader
  astore 31
  aload 31
  astore_3
  aload_3
  aload 13
  invokespecial java/io/InputStreamReader/<init>(Ljava/io/InputStream;)V
  sipush 4096
  istore 16
  aload 30
  astore_3
  aload 31
  astore 4
  aload_3
  aload 4
  iload 16
  invokespecial java/io/BufferedReader/<init>(Ljava/io/Reader;I)V
Label13:
  aload 30
  astore_3
  aload_3
  invokevirtual java/io/BufferedReader/readLine()Ljava/lang/String;
  astore 25
  aload 25
  astore_3
  aload_3
  invokestatic app/DummyClass/invokeIfStmt(Ljava/lang/Object;)V
  aload 25
  ifnonnull Label12
  aload 30
  astore 14
  goto Label7
Label12:
  aload_0
  astore_3
  aload_3
  getfield com/admogo/adapters/SuizongAPIAdapter/suizongAD Lcom/admogo/obj/SuizongAD;
  astore_3
  aload_3
  astore 24
  aload 24
  astore_3
  aload_3
  getfield com/admogo/obj/SuizongAD/data Ljava/lang/String;
  astore_3
  aload_3
  astore 27
  new java/lang/StringBuilder
  astore 26
  aload 27
  astore_3
  aload_3
  invokestatic java/lang/String/valueOf(Ljava/lang/Object;)Ljava/lang/String;
  astore 27
  aload 26
  astore_3
  aload 27
  astore 4
  aload_3
  aload 4
  invokespecial java/lang/StringBuilder/<init>(Ljava/lang/String;)V
  ldc "%20"
  astore 15
  ldc " "
  astore 29
  aload 25
  astore_3
  aload 29
  astore 4
  aload_3
  aload 15
  aload 4
  invokevirtual java/lang/String/replace(Ljava/lang/CharSequence;Ljava/lang/CharSequence;)Ljava/lang/String;
  astore 25
  aload 26
  astore_3
  aload 25
  astore 4
  aload_3
  aload 4
  invokevirtual java/lang/StringBuilder/append(Ljava/lang/String;)Ljava/lang/StringBuilder;
  astore 26
  aload 26
  astore_3
  aload_3
  invokevirtual java/lang/StringBuilder/toString()Ljava/lang/String;
  astore 25
  aload 25
  astore_3
  aload 24
  astore 4
  aload 4
  aload_3
  putfield com/admogo/obj/SuizongAD/data Ljava/lang/String;
Label36:
  goto Label13
Label35:
  astore 28
  aload 30
  astore 14
  goto Label14
Label11:
  ldc "imps"
  astore 15
  aload_2
  astore_3
  aload_3
  aload 15
  invokevirtual java/lang/String/equals(Ljava/lang/Object;)Z
  istore 23
  iload 23
  istore_3
  iload_3
  invokestatic app/DummyClass/invokeIfStmt(Z)V
  iload 23
  ifeq Label15
  ldc "result"
  astore 15
  aload 12
  aload 15
  invokevirtual java/net/HttpURLConnection/getHeaderField(Ljava/lang/String;)Ljava/lang/String;
  astore 25
  aload 25
  astore_3
  aload_3
  invokestatic app/DummyClass/invokeIfStmt(Ljava/lang/Object;)V
  aload 25
  ifnull Label7
  ldc "result"
  astore 15
  aload 12
  aload 15
  invokevirtual java/net/HttpURLConnection/getHeaderField(Ljava/lang/String;)Ljava/lang/String;
  astore 25
  ldc "1"
  astore 15
  aload 25
  astore_3
  aload_3
  aload 15
  invokevirtual java/lang/String/equals(Ljava/lang/Object;)Z
  pop
Label37:
  goto Label7
Label21:
  astore 32
Label20:
  new java/lang/NoClassDefFoundError
  dup
  invokespecial java/lang/NoClassDefFoundError/<init>()V
  athrow
  iload 14
  ifeq Label16
Label39:
  aload 14
  invokevirtual java/io/BufferedReader/close()V
Label16:
  aload 13
  invokestatic app/DummyClass/invokeIfStmt(Ljava/lang/Object;)V
  iload 13
  ifeq Label17
Label41:
  aload 13
  invokevirtual java/io/InputStream/close()V
Label17:
  goto Label18
Label18:
  aload 12
  invokestatic app/DummyClass/invokeIfStmt(Ljava/lang/Object;)V
  iload 12
  ifeq Label19
  aload 12
  invokevirtual java/net/HttpURLConnection/disconnect()V
Label19:
  aload 32
  athrow
Label15:
  ldc "click"
  astore 15
  aload_2
  astore_3
  aload_3
  aload 15
  invokevirtual java/lang/String/equals(Ljava/lang/Object;)Z
  istore 23
  iload 23
  istore_3
  iload_3
  invokestatic app/DummyClass/invokeIfStmt(Z)V
  iload 23
  ifeq Label7
  ldc "result"
  astore 15
  aload 12
  aload 15
  invokevirtual java/net/HttpURLConnection/getHeaderField(Ljava/lang/String;)Ljava/lang/String;
  astore 25
  aload 25
  astore_3
  aload_3
  invokestatic app/DummyClass/invokeIfStmt(Ljava/lang/Object;)V
  aload 25
  ifnull Label7
  ldc "result"
  astore 15
  aload 12
  aload 15
  invokevirtual java/net/HttpURLConnection/getHeaderField(Ljava/lang/String;)Ljava/lang/String;
  astore 25
  ldc "1"
  astore 15
  aload 25
  astore_3
  aload_3
  aload 15
  invokevirtual java/lang/String/equals(Ljava/lang/Object;)Z
  pop
  goto Label7
Label0:
  aload_0
  astore_3
  aload_3
  getfield com/admogo/adapters/SuizongAPIAdapter/suizongAD Lcom/admogo/obj/SuizongAD;
  astore_3
  aload_3
  astore 24
  ldc "2"
  astore 15
  aload 24
  astore_3
  aload_3
  aload 15
  putfield com/admogo/obj/SuizongAD/status Ljava/lang/String;
Label42:
  goto Label7
Label30:
  astore 33
  aload 33
  astore_3
  aload_3
  invokevirtual java/io/IOException/printStackTrace()V
  goto Label8
Label32:
  astore 34
  aload 34
  astore_3
  aload_3
  invokevirtual java/io/IOException/printStackTrace()V
  goto Label9
Label38:
  astore 35
  aload 35
  astore_3
  aload_3
  invokevirtual java/io/IOException/printStackTrace()V
  goto Label16
Label40:
  astore 36
  aload 36
  astore_3
  aload_3
  invokevirtual java/io/IOException/printStackTrace()V
  goto Label17
Label24:
  astore 37
  aload 37
  astore_3
  aload_3
  invokevirtual java/io/IOException/printStackTrace()V
  goto Label3
Label26:
  astore 38
  aload 38
  astore_3
  aload_3
  invokevirtual java/io/IOException/printStackTrace()V
  goto Label4
Label34:
  astore 32
  aload 30
  astore 14
  goto Label20
  nop
.end <method>

.method private makePcheck(Ljava/util/HashMap;)Ljava/lang/String;
  .signature_attr "(Ljava/util/HashMap<Ljava/lang/String;Ljava/lang/String;>;)Ljava/lang/String;"
.limit locals 27
.limit stack 200
  .catch  java/lang/Exception <from> Label1 <to> Label2 <using> Label0
  nop
  ldc "appkey"
  astore 5
  aload_1
  astore_2
  aload_2
  aload 5
  invokevirtual java/util/HashMap/get(Ljava/lang/Object;)Ljava/lang/Object;
  astore 4
  aload 4
  astore 7
  aload 7
  checkcast java/lang/String
  astore 7
  aload 7
  astore 6
  ldc "uuid"
  astore 5
  aload_1
  astore_2
  aload_2
  aload 5
  invokevirtual java/util/HashMap/get(Ljava/lang/Object;)Ljava/lang/Object;
  astore 4
  aload 4
  astore 9
  aload 9
  checkcast java/lang/String
  astore 9
  aload 9
  astore 8
  ldc "client"
  astore 5
  aload_1
  astore_2
  aload_2
  aload 5
  invokevirtual java/util/HashMap/get(Ljava/lang/Object;)Ljava/lang/Object;
  astore 4
  aload 4
  astore 11
  aload 11
  checkcast java/lang/String
  astore 11
  aload 11
  astore 10
  ldc "ip"
  astore 5
  aload_1
  astore_2
  aload_2
  aload 5
  invokevirtual java/util/HashMap/get(Ljava/lang/Object;)Ljava/lang/Object;
  astore 4
  aload 4
  astore 13
  aload 13
  checkcast java/lang/String
  astore 13
  aload 13
  astore 12
  ldc "density"
  astore 5
  aload_1
  astore_2
  aload_2
  aload 5
  invokevirtual java/util/HashMap/get(Ljava/lang/Object;)Ljava/lang/Object;
  astore 4
  aload 4
  astore 15
  aload 15
  checkcast java/lang/String
  astore 15
  aload 15
  astore 14
  ldc "aw"
  astore 5
  aload_1
  astore_2
  aload_2
  aload 5
  invokevirtual java/util/HashMap/get(Ljava/lang/Object;)Ljava/lang/Object;
  astore 4
  aload 4
  astore 17
  aload 17
  checkcast java/lang/String
  astore 17
  aload 17
  astore 16
  ldc "ah"
  astore 5
  aload_1
  astore_2
  aload_2
  aload 5
  invokevirtual java/util/HashMap/get(Ljava/lang/Object;)Ljava/lang/Object;
  astore 4
  aload 4
  astore 19
  aload 19
  checkcast java/lang/String
  astore 19
  aload 19
  astore 18
  ldc "pw"
  astore 5
  aload_1
  astore_2
  aload_2
  aload 5
  invokevirtual java/util/HashMap/get(Ljava/lang/Object;)Ljava/lang/Object;
  astore 4
  aload 4
  astore 21
  aload 21
  checkcast java/lang/String
  astore 21
  aload 21
  astore 20
  ldc "ph"
  astore 5
  aload_1
  astore_2
  aload_2
  aload 5
  invokevirtual java/util/HashMap/get(Ljava/lang/Object;)Ljava/lang/Object;
  astore 4
  aload 4
  astore 23
  aload 23
  checkcast java/lang/String
  astore 23
  aload 23
  astore 22
  new java/lang/StringBuffer
  astore 24
Label1:
  aload 24
  astore_2
  aload_2
  invokespecial java/lang/StringBuffer/<init>()V
  aload 24
  astore_2
  aload_2
  aload 6
  invokevirtual java/lang/StringBuffer/append(Ljava/lang/String;)Ljava/lang/StringBuffer;
  pop
  aload 24
  astore_2
  aload_2
  aload 8
  invokevirtual java/lang/StringBuffer/append(Ljava/lang/String;)Ljava/lang/StringBuffer;
  pop
  aload 24
  astore_2
  aload_2
  aload 10
  invokevirtual java/lang/StringBuffer/append(Ljava/lang/String;)Ljava/lang/StringBuffer;
  pop
  aload 24
  astore_2
  aload_2
  aload 12
  invokevirtual java/lang/StringBuffer/append(Ljava/lang/String;)Ljava/lang/StringBuffer;
  pop
  aload 24
  astore_2
  aload_2
  aload 14
  invokevirtual java/lang/StringBuffer/append(Ljava/lang/String;)Ljava/lang/StringBuffer;
  pop
  aload 24
  astore_2
  aload_2
  aload 16
  invokevirtual java/lang/StringBuffer/append(Ljava/lang/String;)Ljava/lang/StringBuffer;
  pop
  aload 24
  astore_2
  aload 18
  astore_3
  aload_2
  aload_3
  invokevirtual java/lang/StringBuffer/append(Ljava/lang/String;)Ljava/lang/StringBuffer;
  pop
  aload 24
  astore_2
  aload 20
  astore_3
  aload_2
  aload_3
  invokevirtual java/lang/StringBuffer/append(Ljava/lang/String;)Ljava/lang/StringBuffer;
  pop
  aload 24
  astore_2
  aload 22
  astore_3
  aload_2
  aload_3
  invokevirtual java/lang/StringBuffer/append(Ljava/lang/String;)Ljava/lang/StringBuffer;
  pop
  aload 24
  astore_2
  aload_2
  invokevirtual java/lang/StringBuffer/toString()Ljava/lang/String;
  astore 22
  aload 22
  astore_2
  aload_2
  invokestatic com/admogo/encryption/SHA1/SHA(Ljava/lang/String;)Ljava/lang/String;
  astore 22
Label2:
  aload 22
  areturn
Label0:
  astore 25
  aconst_null
  astore 26
  aload 26
  areturn
  nop
.end <method>

.method private makePcheck4GetBody(Ljava/util/HashMap;)Ljava/lang/String;
  .signature_attr "(Ljava/util/HashMap<Ljava/lang/String;Ljava/lang/String;>;)Ljava/lang/String;"
.limit locals 11
.limit stack 200
  nop
  ldc "adid"
  astore_3
  aload_1
  aload_3
  invokevirtual java/util/HashMap/get(Ljava/lang/Object;)Ljava/lang/Object;
  astore_2
  new java/lang/NoClassDefFoundError
  dup
  invokespecial java/lang/NoClassDefFoundError/<init>()V
  athrow
  iload_2
  ifne Label0
  ldc ""
  astore 4
Label2:
  ldc "updatetime"
  astore_3
  aload_1
  aload_3
  invokevirtual java/util/HashMap/get(Ljava/lang/Object;)Ljava/lang/Object;
  astore_2
  aload_2
  invokestatic app/DummyClass/invokeIfStmt(Ljava/lang/Object;)V
  aload_2
  ifnonnull Label1
  ldc ""
  astore 5
Label3:
  new java/lang/StringBuffer
  astore 6
Label5:
  aload 6
  invokespecial java/lang/StringBuffer/<init>()V
  aload 6
  aload 4
  invokevirtual java/lang/StringBuffer/append(Ljava/lang/String;)Ljava/lang/StringBuffer;
  pop
  aload 6
  aload 5
  invokevirtual java/lang/StringBuffer/append(Ljava/lang/String;)Ljava/lang/StringBuffer;
  pop
  aload 6
  invokevirtual java/lang/StringBuffer/toString()Ljava/lang/String;
  astore 5
  aload 5
  invokestatic com/admogo/encryption/SHA1/SHA(Ljava/lang/String;)Ljava/lang/String;
  astore 5
Label6:
  aload 5
  areturn
Label0:
  ldc "adid"
  astore_3
  aload_1
  aload_3
  invokevirtual java/util/HashMap/get(Ljava/lang/Object;)Ljava/lang/Object;
  astore_2
  aload_2
  astore 7
  aload 7
  checkcast java/lang/String
  astore 7
  aload 7
  astore 4
  goto Label2
Label1:
  ldc "updatetime"
  astore_3
  aload_1
  aload_3
  invokevirtual java/util/HashMap/get(Ljava/lang/Object;)Ljava/lang/Object;
  astore_2
  aload_2
  astore 8
  aload 8
  checkcast java/lang/String
  astore 8
  aload 8
  astore 5
  goto Label3
Label4:
  astore 9
  aload 9
  invokevirtual java/lang/Exception/printStackTrace()V
  aconst_null
  astore 10
  aload 10
  areturn
  nop
.end <method>

.method private makePcheck4Show(Ljava/util/HashMap;)Ljava/lang/String;
  .signature_attr "(Ljava/util/HashMap<Ljava/lang/String;Ljava/lang/String;>;)Ljava/lang/String;"
.limit locals 25
.limit stack 200
  .catch  java/lang/Exception <from> Label1 <to> Label2 <using> Label0
  nop
  ldc "appkey"
  astore 5
  aload_1
  astore_2
  aload_2
  aload 5
  invokevirtual java/util/HashMap/get(Ljava/lang/Object;)Ljava/lang/Object;
  astore 4
  aload 4
  astore 7
  aload 7
  checkcast java/lang/String
  astore 7
  aload 7
  astore 6
  ldc "uuid"
  astore 5
  aload_1
  astore_2
  aload_2
  aload 5
  invokevirtual java/util/HashMap/get(Ljava/lang/Object;)Ljava/lang/Object;
  astore 4
  aload 4
  astore 9
  aload 9
  checkcast java/lang/String
  astore 9
  aload 9
  astore 8
  ldc "adid"
  astore 5
  aload_1
  astore_2
  aload_2
  aload 5
  invokevirtual java/util/HashMap/get(Ljava/lang/Object;)Ljava/lang/Object;
  astore 4
  aload 4
  astore 11
  aload 11
  checkcast java/lang/String
  astore 11
  aload 11
  astore 10
  ldc "updatetime"
  astore 5
  aload_1
  astore_2
  aload_2
  aload 5
  invokevirtual java/util/HashMap/get(Ljava/lang/Object;)Ljava/lang/Object;
  astore 4
  aload 4
  astore 13
  aload 13
  checkcast java/lang/String
  astore 13
  aload 13
  astore 12
  ldc "client"
  astore 5
  aload_1
  astore_2
  aload_2
  aload 5
  invokevirtual java/util/HashMap/get(Ljava/lang/Object;)Ljava/lang/Object;
  astore 4
  aload 4
  astore 15
  aload 15
  checkcast java/lang/String
  astore 15
  aload 15
  astore 14
  ldc "ip"
  astore 5
  aload_1
  astore_2
  aload_2
  aload 5
  invokevirtual java/util/HashMap/get(Ljava/lang/Object;)Ljava/lang/Object;
  astore 4
  aload 4
  astore 17
  aload 17
  checkcast java/lang/String
  astore 17
  aload 17
  astore 16
  ldc "pw"
  astore 5
  aload_1
  astore_2
  aload_2
  aload 5
  invokevirtual java/util/HashMap/get(Ljava/lang/Object;)Ljava/lang/Object;
  astore 4
  aload 4
  astore 19
  aload 19
  checkcast java/lang/String
  astore 19
  aload 19
  astore 18
  ldc "ph"
  astore 5
  aload_1
  astore_2
  aload_2
  aload 5
  invokevirtual java/util/HashMap/get(Ljava/lang/Object;)Ljava/lang/Object;
  astore 4
  aload 4
  astore 21
  aload 21
  checkcast java/lang/String
  astore 21
  aload 21
  astore 20
  new java/lang/StringBuffer
  astore 22
Label1:
  aload 22
  astore_2
  aload_2
  invokespecial java/lang/StringBuffer/<init>()V
  aload 22
  astore_2
  aload_2
  aload 6
  invokevirtual java/lang/StringBuffer/append(Ljava/lang/String;)Ljava/lang/StringBuffer;
  pop
  aload 22
  astore_2
  aload_2
  aload 8
  invokevirtual java/lang/StringBuffer/append(Ljava/lang/String;)Ljava/lang/StringBuffer;
  pop
  aload 22
  astore_2
  aload_2
  aload 14
  invokevirtual java/lang/StringBuffer/append(Ljava/lang/String;)Ljava/lang/StringBuffer;
  pop
  aload 22
  astore_2
  aload_2
  aload 16
  invokevirtual java/lang/StringBuffer/append(Ljava/lang/String;)Ljava/lang/StringBuffer;
  pop
  aload 22
  astore_2
  aload_2
  aload 10
  invokevirtual java/lang/StringBuffer/append(Ljava/lang/String;)Ljava/lang/StringBuffer;
  pop
  aload 22
  astore_2
  aload_2
  aload 12
  invokevirtual java/lang/StringBuffer/append(Ljava/lang/String;)Ljava/lang/StringBuffer;
  pop
  aload 22
  astore_2
  aload 18
  astore_3
  aload_2
  aload_3
  invokevirtual java/lang/StringBuffer/append(Ljava/lang/String;)Ljava/lang/StringBuffer;
  pop
  aload 22
  astore_2
  aload 20
  astore_3
  aload_2
  aload_3
  invokevirtual java/lang/StringBuffer/append(Ljava/lang/String;)Ljava/lang/StringBuffer;
  pop
  aload 22
  astore_2
  aload_2
  invokevirtual java/lang/StringBuffer/toString()Ljava/lang/String;
  astore 20
  aload 20
  astore_2
  aload_2
  invokestatic com/admogo/encryption/SHA1/SHA(Ljava/lang/String;)Ljava/lang/String;
  astore 20
Label2:
  aload 20
  areturn
Label0:
  astore 23
  aconst_null
  astore 24
  aload 24
  areturn
  nop
.end <method>

.method private putInfoToRequestCount()Ljava/util/HashMap;
  .signature_attr "()Ljava/util/HashMap<Ljava/lang/String;Ljava/lang/String;>;"
.limit locals 19
.limit stack 200
  nop
  aload_0
  astore_1
  aload_1
  getfield com/admogo/adapters/AdMogoAdapter/adMogoLayoutReference Ljava/lang/ref/WeakReference;
  astore_2
  aload_1
  astore_0
  aload_2
  invokevirtual java/lang/ref/WeakReference/get()Ljava/lang/Object;
  astore_3
  aload_3
  astore 5
  new java/lang/NoClassDefFoundError
  dup
  invokespecial java/lang/NoClassDefFoundError/<init>()V
  athrow
  aload 5
  astore 4
  aload 4
  invokestatic app/DummyClass/invokeIfStmt(Ljava/lang/Object;)V
  iload 4
  ifne Label0
  getstatic com/admogo/util/AdMogoUtil/ADMOGO Ljava/lang/String;
  astore 6
  ldc "suizong putInfoToRequestClick adMogoLayout is null"
  astore 7
  aload 6
  aload 7
  invokestatic android/util/Log/e(Ljava/lang/String;Ljava/lang/String;)I
  pop
  aconst_null
  astore 8
  aload 8
  areturn
Label0:
  aload 4
  getfield com/admogo/AdMogoLayout/activityReference Ljava/lang/ref/WeakReference;
  astore_2
  aload_2
  invokevirtual java/lang/ref/WeakReference/get()Ljava/lang/Object;
  astore_3
  aload_3
  astore 10
  aload 10
  checkcast android/content/Context
  astore 10
  aload 10
  astore 9
  aload 9
  invokestatic app/DummyClass/invokeIfStmt(Ljava/lang/Object;)V
  aload 9
  ifnonnull Label1
  getstatic com/admogo/util/AdMogoUtil/ADMOGO Ljava/lang/String;
  astore 6
  ldc "suizong putInfoToRequestClick context is null"
  astore 7
  aload 6
  aload 7
  invokestatic android/util/Log/e(Ljava/lang/String;Ljava/lang/String;)I
  pop
  aconst_null
  astore 8
  aload 8
  areturn
Label1:
  new java/util/HashMap
  astore 11
  aload 11
  invokespecial java/util/HashMap/<init>()V
  aload_0
  astore_1
  aload_1
  getfield com/admogo/adapters/AdMogoAdapter/ration Lcom/admogo/obj/Ration;
  astore 12
  aload 12
  getfield com/admogo/obj/Ration/key Ljava/lang/String;
  astore 13
  ldc "appkey"
  astore 7
  aload 11
  aload 7
  aload 13
  invokevirtual java/util/HashMap/put(Ljava/lang/Object;Ljava/lang/Object;)Ljava/lang/Object;
  pop
  aload 4
  getfield com/admogo/AdMogoLayout/adMogoManager Lcom/admogo/AdMogoManager;
  astore 14
  aload 14
  getfield com/admogo/AdMogoManager/deviceIDHash Ljava/lang/String;
  astore 13
  ldc "uuid"
  astore 7
  aload 11
  aload 7
  aload 13
  invokevirtual java/util/HashMap/put(Ljava/lang/Object;Ljava/lang/Object;)Ljava/lang/Object;
  pop
  aload_0
  astore_1
  aload_1
  getfield com/admogo/adapters/SuizongAPIAdapter/suizongAD Lcom/admogo/obj/SuizongAD;
  astore 15
  aload 15
  getfield com/admogo/obj/SuizongAD/adid Ljava/lang/String;
  astore 13
  ldc "adid"
  astore 7
  aload 11
  aload 7
  aload 13
  invokevirtual java/util/HashMap/put(Ljava/lang/Object;Ljava/lang/Object;)Ljava/lang/Object;
  pop
  aload_0
  astore_1
  aload_1
  getfield com/admogo/adapters/SuizongAPIAdapter/suizongAD Lcom/admogo/obj/SuizongAD;
  astore 15
  aload 15
  getfield com/admogo/obj/SuizongAD/updateTime Ljava/lang/String;
  astore 13
  ldc "updatetime"
  astore 7
  aload 11
  aload 7
  aload 13
  invokevirtual java/util/HashMap/put(Ljava/lang/Object;Ljava/lang/Object;)Ljava/lang/Object;
  pop
  ldc "client"
  astore 7
  ldc "2"
  astore 16
  aload 11
  aload 7
  aload 16
  invokevirtual java/util/HashMap/put(Ljava/lang/Object;Ljava/lang/Object;)Ljava/lang/Object;
  pop
  aload_0
  astore_1
  aload_1
  invokespecial com/admogo/adapters/SuizongAPIAdapter/getLocalIPAddress()Ljava/lang/String;
  astore 13
  ldc "ip"
  astore 7
  aload 11
  aload 7
  aload 13
  invokevirtual java/util/HashMap/put(Ljava/lang/Object;Ljava/lang/Object;)Ljava/lang/Object;
  pop
  new java/lang/StringBuilder
  astore 17
  aload 4
  getfield com/admogo/AdMogoLayout/adMogoManager Lcom/admogo/AdMogoManager;
  astore 14
  aload 14
  getfield com/admogo/AdMogoManager/width I
  istore_1
  iload_1
  istore 18
  iload_1
  invokestatic java/lang/String/valueOf(I)Ljava/lang/String;
  astore 13
  aload 17
  astore_1
  aload_1
  aload 13
  invokespecial java/lang/StringBuilder/<init>(Ljava/lang/String;)V
  aload 17
  astore_1
  aload_1
  invokevirtual java/lang/StringBuilder/toString()Ljava/lang/String;
  astore 13
  ldc "pw"
  astore 7
  aload 11
  aload 7
  aload 13
  invokevirtual java/util/HashMap/put(Ljava/lang/Object;Ljava/lang/Object;)Ljava/lang/Object;
  pop
  new java/lang/StringBuilder
  astore 17
  aload 4
  getfield com/admogo/AdMogoLayout/adMogoManager Lcom/admogo/AdMogoManager;
  astore 14
  aload 14
  getfield com/admogo/AdMogoManager/height I
  istore_1
  iload_1
  istore 18
  iload_1
  invokestatic java/lang/String/valueOf(I)Ljava/lang/String;
  astore 13
  aload 17
  astore_1
  aload_1
  aload 13
  invokespecial java/lang/StringBuilder/<init>(Ljava/lang/String;)V
  aload 17
  astore_1
  aload_1
  invokevirtual java/lang/StringBuilder/toString()Ljava/lang/String;
  astore 13
  ldc "ph"
  astore 7
  aload 11
  aload 7
  aload 13
  invokevirtual java/util/HashMap/put(Ljava/lang/Object;Ljava/lang/Object;)Ljava/lang/Object;
  pop
  aload_0
  astore_1
  aload_1
  aload 11
  invokespecial com/admogo/adapters/SuizongAPIAdapter/makePcheck4Show(Ljava/util/HashMap;)Ljava/lang/String;
  astore 13
  ldc "pcheck"
  astore 7
  aload 11
  aload 7
  aload 13
  invokevirtual java/util/HashMap/put(Ljava/lang/Object;Ljava/lang/Object;)Ljava/lang/Object;
  pop
  new java/lang/StringBuilder
  astore 17
  aload 13
  invokestatic java/lang/String/valueOf(Ljava/lang/Object;)Ljava/lang/String;
  astore 13
  aload 17
  astore_1
  aload_1
  aload 13
  invokespecial java/lang/StringBuilder/<init>(Ljava/lang/String;)V
  aload_0
  astore_1
  aload_1
  getfield com/admogo/adapters/SuizongAPIAdapter/serial_key Ljava/lang/String;
  astore 13
  aload 17
  astore_1
  aload_1
  aload 13
  invokevirtual java/lang/StringBuilder/append(Ljava/lang/String;)Ljava/lang/StringBuilder;
  astore 17
  aload 17
  astore_1
  aload_1
  invokevirtual java/lang/StringBuilder/toString()Ljava/lang/String;
  astore 13
  aload 13
  invokestatic com/admogo/encryption/MD5/MD5Encode(Ljava/lang/String;)Ljava/lang/String;
  astore 13
  ldc "icheck"
  astore 7
  aload 11
  aload 7
  aload 13
  invokevirtual java/util/HashMap/put(Ljava/lang/Object;Ljava/lang/Object;)Ljava/lang/Object;
  pop
  aload 11
  areturn
  nop
.end <method>

.method private requestSuizongAD(Lcom/admogo/AdMogoLayout;Ljava/lang/String;)V
.limit locals 16
.limit stack 200
  .catch  java/lang/Exception <from> Label4 <to> Label5 <using> Label3
  nop
  getstatic com/admogo/adapters/SuizongAPIAdapter/ip Ljava/lang/String;
  astore_3
Label4:
  new java/lang/NoClassDefFoundError
  dup
  invokespecial java/lang/NoClassDefFoundError/<init>()V
  athrow
  nop
  iload 4
  invokestatic app/DummyClass/invokeIfStmt(Z)V
  iload 4
  ifeq Label0
  aload_0
  invokespecial com/admogo/adapters/SuizongAPIAdapter/getLocalIPAddress()Ljava/lang/String;
  astore_3
  aload_3
  putstatic com/admogo/adapters/SuizongAPIAdapter/ip Ljava/lang/String;
Label0:
  new java/util/HashMap
  astore 5
  aload 5
  invokespecial java/util/HashMap/<init>()V
  ldc "appkey"
  astore 6
  aload 5
  aload 6
  aload_2
  invokevirtual java/util/HashMap/put(Ljava/lang/Object;Ljava/lang/Object;)Ljava/lang/Object;
  pop
  aload_1
  getfield com/admogo/AdMogoLayout/adMogoManager Lcom/admogo/AdMogoManager;
  astore 7
  aload 7
  getfield com/admogo/AdMogoManager/deviceIDHash Ljava/lang/String;
  astore_2
  ldc "uuid"
  astore 6
  aload 5
  aload 6
  aload_2
  invokevirtual java/util/HashMap/put(Ljava/lang/Object;Ljava/lang/Object;)Ljava/lang/Object;
  pop
  ldc "client"
  astore 6
  ldc "2"
  astore 8
  aload 5
  aload 6
  aload 8
  invokevirtual java/util/HashMap/put(Ljava/lang/Object;Ljava/lang/Object;)Ljava/lang/Object;
  pop
  getstatic com/admogo/adapters/SuizongAPIAdapter/ip Ljava/lang/String;
  astore_2
  ldc "ip"
  astore 6
  aload 5
  aload 6
  aload_2
  invokevirtual java/util/HashMap/put(Ljava/lang/Object;Ljava/lang/Object;)Ljava/lang/Object;
  pop
  new java/lang/StringBuilder
  astore 9
  aload 9
  invokespecial java/lang/StringBuilder/<init>()V
  aload_0
  getfield com/admogo/adapters/SuizongAPIAdapter/density D
  dstore 10
  aload 9
  dload 10
  invokevirtual java/lang/StringBuilder/append(D)Ljava/lang/StringBuilder;
  astore 9
  aload 9
  invokevirtual java/lang/StringBuilder/toString()Ljava/lang/String;
  astore_2
  ldc "density"
  astore 6
  aload 5
  aload 6
  aload_2
  invokevirtual java/util/HashMap/put(Ljava/lang/Object;Ljava/lang/Object;)Ljava/lang/Object;
  pop
  new java/lang/StringBuilder
  astore 9
  aload 9
  invokespecial java/lang/StringBuilder/<init>()V
  aload_1
  getfield com/admogo/AdMogoLayout/adMogoManager Lcom/admogo/AdMogoManager;
  astore 7
  aload 7
  getfield com/admogo/AdMogoManager/width I
  istore 12
  aload 9
  iload 12
  invokevirtual java/lang/StringBuilder/append(I)Ljava/lang/StringBuilder;
  astore 9
  aload 9
  invokevirtual java/lang/StringBuilder/toString()Ljava/lang/String;
  astore_2
  ldc "pw"
  astore 6
  aload 5
  aload 6
  aload_2
  invokevirtual java/util/HashMap/put(Ljava/lang/Object;Ljava/lang/Object;)Ljava/lang/Object;
  pop
  new java/lang/StringBuilder
  astore 9
  aload 9
  invokespecial java/lang/StringBuilder/<init>()V
  aload_1
  getfield com/admogo/AdMogoLayout/adMogoManager Lcom/admogo/AdMogoManager;
  astore 7
  aload 7
  getfield com/admogo/AdMogoManager/height I
  istore 12
  aload 9
  iload 12
  invokevirtual java/lang/StringBuilder/append(I)Ljava/lang/StringBuilder;
  astore 9
  aload 9
  invokevirtual java/lang/StringBuilder/toString()Ljava/lang/String;
  astore_2
  ldc "ph"
  astore 6
  aload 5
  aload 6
  aload_2
  invokevirtual java/util/HashMap/put(Ljava/lang/Object;Ljava/lang/Object;)Ljava/lang/Object;
  pop
  ldc "aw"
  astore 6
  ldc "320"
  astore 8
  aload 5
  aload 6
  aload 8
  invokevirtual java/util/HashMap/put(Ljava/lang/Object;Ljava/lang/Object;)Ljava/lang/Object;
  pop
  ldc "ah"
  astore 6
  ldc "50"
  astore 8
  aload 5
  aload 6
  aload 8
  invokevirtual java/util/HashMap/put(Ljava/lang/Object;Ljava/lang/Object;)Ljava/lang/Object;
  pop
  aload_0
  aload 5
  invokespecial com/admogo/adapters/SuizongAPIAdapter/makePcheck(Ljava/util/HashMap;)Ljava/lang/String;
  astore_2
  ldc "pcheck"
  astore 6
  aload 5
  aload 6
  aload_2
  invokevirtual java/util/HashMap/put(Ljava/lang/Object;Ljava/lang/Object;)Ljava/lang/Object;
  pop
  new java/lang/StringBuilder
  astore 9
  aload_0
  aload 5
  invokespecial com/admogo/adapters/SuizongAPIAdapter/makePcheck(Ljava/util/HashMap;)Ljava/lang/String;
  astore_2
  aload_2
  invokestatic java/lang/String/valueOf(Ljava/lang/Object;)Ljava/lang/String;
  astore_2
  aload 9
  aload_2
  invokespecial java/lang/StringBuilder/<init>(Ljava/lang/String;)V
  aload_0
  getfield com/admogo/adapters/SuizongAPIAdapter/serial_key Ljava/lang/String;
  astore_2
  aload 9
  aload_2
  invokevirtual java/lang/StringBuilder/append(Ljava/lang/String;)Ljava/lang/StringBuilder;
  astore 9
  aload 9
  invokevirtual java/lang/StringBuilder/toString()Ljava/lang/String;
  astore_2
  aload_2
  invokestatic com/admogo/encryption/MD5/MD5Encode(Ljava/lang/String;)Ljava/lang/String;
  astore_2
  ldc "icheck"
  astore 6
  aload 5
  aload 6
  aload_2
  invokevirtual java/util/HashMap/put(Ljava/lang/Object;Ljava/lang/Object;)Ljava/lang/Object;
  pop
  new java/lang/StringBuilder
  astore 9
  ldc "http://api.suizong.com/mobile/"
  astore 6
  aload 6
  invokestatic java/lang/String/valueOf(Ljava/lang/Object;)Ljava/lang/String;
  astore_3
  aload 9
  aload_3
  invokespecial java/lang/StringBuilder/<init>(Ljava/lang/String;)V
  ldc "ADServerGetAPI"
  astore 6
  aload 9
  aload 6
  invokevirtual java/lang/StringBuilder/append(Ljava/lang/String;)Ljava/lang/StringBuilder;
  astore 9
  aload 9
  invokevirtual java/lang/StringBuilder/toString()Ljava/lang/String;
  astore_3
  aload_3
  putstatic com/admogo/adapters/SuizongAPIAdapter/url Ljava/lang/String;
  ldc "request"
  astore 6
  aload_0
  aload 5
  aload 6
  invokespecial com/admogo/adapters/SuizongAPIAdapter/httpRequest(Ljava/util/HashMap;Ljava/lang/String;)V
  aload_0
  getfield com/admogo/adapters/SuizongAPIAdapter/suizongAD Lcom/admogo/obj/SuizongAD;
  astore 13
  aload 13
  getfield com/admogo/obj/SuizongAD/status Ljava/lang/String;
  astore_3
  ldc "1"
  astore 6
  aload_3
  aload 6
  invokevirtual java/lang/String/equals(Ljava/lang/Object;)Z
  istore 4
  iload 4
  invokestatic app/DummyClass/invokeIfStmt(Z)V
  iload 4
  ifne Label1
  aload_1
  invokevirtual com/admogo/AdMogoLayout/rollover()V
Label2:
  return
Label1:
  new java/util/HashMap
  astore 5
  aload 5
  invokespecial java/util/HashMap/<init>()V
  aload_0
  getfield com/admogo/adapters/SuizongAPIAdapter/suizongAD Lcom/admogo/obj/SuizongAD;
  astore 13
  aload 13
  getfield com/admogo/obj/SuizongAD/adid Ljava/lang/String;
  astore_2
  ldc "adid"
  astore 6
  aload 5
  aload 6
  aload_2
  invokevirtual java/util/HashMap/put(Ljava/lang/Object;Ljava/lang/Object;)Ljava/lang/Object;
  pop
  aload_0
  getfield com/admogo/adapters/SuizongAPIAdapter/suizongAD Lcom/admogo/obj/SuizongAD;
  astore 13
  aload 13
  getfield com/admogo/obj/SuizongAD/updateTime Ljava/lang/String;
  astore_2
  ldc "updatetime"
  astore 6
  aload 5
  aload 6
  aload_2
  invokevirtual java/util/HashMap/put(Ljava/lang/Object;Ljava/lang/Object;)Ljava/lang/Object;
  pop
  aload_0
  aload 5
  invokespecial com/admogo/adapters/SuizongAPIAdapter/makePcheck4GetBody(Ljava/util/HashMap;)Ljava/lang/String;
  astore_2
  ldc "pcheck"
  astore 6
  aload 5
  aload 6
  aload_2
  invokevirtual java/util/HashMap/put(Ljava/lang/Object;Ljava/lang/Object;)Ljava/lang/Object;
  pop
  new java/lang/StringBuilder
  astore 9
  aload_2
  invokestatic java/lang/String/valueOf(Ljava/lang/Object;)Ljava/lang/String;
  astore_2
  aload 9
  aload_2
  invokespecial java/lang/StringBuilder/<init>(Ljava/lang/String;)V
  aload_0
  getfield com/admogo/adapters/SuizongAPIAdapter/serial_key Ljava/lang/String;
  astore_2
  aload 9
  aload_2
  invokevirtual java/lang/StringBuilder/append(Ljava/lang/String;)Ljava/lang/StringBuilder;
  astore 9
  aload 9
  invokevirtual java/lang/StringBuilder/toString()Ljava/lang/String;
  astore_2
  aload_2
  invokestatic com/admogo/encryption/MD5/MD5Encode(Ljava/lang/String;)Ljava/lang/String;
  astore_2
  ldc "icheck"
  astore 6
  aload 5
  aload 6
  aload_2
  invokevirtual java/util/HashMap/put(Ljava/lang/Object;Ljava/lang/Object;)Ljava/lang/Object;
  pop
  new java/lang/StringBuilder
  astore 9
  ldc "http://api.suizong.com/mobile/"
  astore 6
  aload 6
  invokestatic java/lang/String/valueOf(Ljava/lang/Object;)Ljava/lang/String;
  astore_3
  aload 9
  aload_3
  invokespecial java/lang/StringBuilder/<init>(Ljava/lang/String;)V
  ldc "ADServerGetBodyAPI"
  astore 6
  aload 9
  aload 6
  invokevirtual java/lang/StringBuilder/append(Ljava/lang/String;)Ljava/lang/StringBuilder;
  astore 9
  aload 9
  invokevirtual java/lang/StringBuilder/toString()Ljava/lang/String;
  astore_3
  aload_3
  putstatic com/admogo/adapters/SuizongAPIAdapter/url Ljava/lang/String;
  ldc "getbody"
  astore 6
  aload_0
  aload 5
  aload 6
  invokespecial com/admogo/adapters/SuizongAPIAdapter/httpRequest(Ljava/util/HashMap;Ljava/lang/String;)V
  new java/lang/StringBuilder
  astore 9
  ldc "http://api.suizong.com/mobile/"
  astore 6
  aload 6
  invokestatic java/lang/String/valueOf(Ljava/lang/Object;)Ljava/lang/String;
  astore_3
  aload 9
  aload_3
  invokespecial java/lang/StringBuilder/<init>(Ljava/lang/String;)V
  ldc "ADServerShowAPI"
  astore 6
  aload 9
  aload 6
  invokevirtual java/lang/StringBuilder/append(Ljava/lang/String;)Ljava/lang/StringBuilder;
  astore 9
  aload 9
  invokevirtual java/lang/StringBuilder/toString()Ljava/lang/String;
  astore_3
  aload_3
  putstatic com/admogo/adapters/SuizongAPIAdapter/url Ljava/lang/String;
  new com/admogo/adapters/SuizongAPIAdapter$1
  astore 14
  aload 14
  aload_0
  invokespecial com/admogo/adapters/SuizongAPIAdapter$1/<init>(Lcom/admogo/adapters/SuizongAPIAdapter;)V
  aload 14
  invokevirtual com/admogo/adapters/SuizongAPIAdapter$1/start()V
Label5:
  goto Label2
Label3:
  astore 15
  goto Label2
  nop
.end <method>

