.source dalvik_source_VirusShare_32e70f448ebd75661a1cb12f9cd8e013.apk
.class public  com/tencent/mobwin/core/a/c
.super java/lang/Object
.field private "a" Ljava/util/Map;
.field private "b" Ljava/util/Map;
.field private "c" LMobWin/UserInfo;
.field private "d" LMobWin/AppInfo;

.method public <init>(Landroid/content/Context;)V
.limit locals 3
.limit stack 200
  nop
  aload_0
  invokespecial java/lang/Object/<init>()V
  aload_1
  invokestatic com/tencent/mobwin/core/a/f/a(Landroid/content/Context;)Ljava/util/Map;
  astore_2
  aload_0
  aload_2
  putfield com/tencent/mobwin/core/a/c/a Ljava/util/Map;
  invokestatic com/tencent/mobwin/core/a/f/b()Ljava/util/Map;
  astore_2
  aload_0
  aload_2
  putfield com/tencent/mobwin/core/a/c/b Ljava/util/Map;
  return
  nop
.end <method>

.method public a(Landroid/content/Context;)LMobWin/UserInfo;
.limit locals 51
.limit stack 200
  nop
  aload_0
  astore_2
  aload_2
  getfield com/tencent/mobwin/core/a/c/a Ljava/util/Map;
  astore 6
  ldc "imei"
  astore 8
  aload 6
  aload 8
  invokeinterface java/util/Map/get(Ljava/lang/Object;)Ljava/lang/Object; 2
  astore 7
  aload 7
  astore 10
  aload 10
  checkcast java/lang/String
  astore 10
  aload 10
  astore 9
  aload_0
  astore_2
  aload_2
  getfield com/tencent/mobwin/core/a/c/a Ljava/util/Map;
  astore 6
  ldc "meid"
  astore 8
  aload 6
  aload 8
  invokeinterface java/util/Map/get(Ljava/lang/Object;)Ljava/lang/Object; 2
  astore 7
  aload 7
  astore 12
  aload 12
  checkcast java/lang/String
  astore 12
  aload 12
  astore 11
  aload_0
  astore_2
  aload_2
  getfield com/tencent/mobwin/core/a/c/a Ljava/util/Map;
  astore 6
  ldc "imsi"
  astore 8
  aload 6
  aload 8
  invokeinterface java/util/Map/get(Ljava/lang/Object;)Ljava/lang/Object; 2
  astore 7
  aload 7
  astore 14
  aload 14
  checkcast java/lang/String
  astore 14
  aload 14
  astore 13
  aload_0
  astore_2
  aload_2
  getfield com/tencent/mobwin/core/a/c/a Ljava/util/Map;
  astore 6
  ldc "tel_support"
  astore 8
  aload 6
  aload 8
  invokeinterface java/util/Map/get(Ljava/lang/Object;)Ljava/lang/Object; 2
  astore 7
  aload 7
  astore 16
  aload 16
  checkcast java/lang/String
  astore 16
  aload 16
  astore 15
  aload_0
  astore_2
  aload_2
  getfield com/tencent/mobwin/core/a/c/a Ljava/util/Map;
  astore 6
  ldc "wifi_support"
  astore 8
  aload 6
  aload 8
  invokeinterface java/util/Map/get(Ljava/lang/Object;)Ljava/lang/Object; 2
  astore 7
  aload 7
  astore 18
  aload 18
  checkcast java/lang/String
  astore 18
  aload 18
  astore 17
  aload_0
  astore_2
  aload_2
  getfield com/tencent/mobwin/core/a/c/a Ljava/util/Map;
  astore 6
  ldc "lwp_support"
  astore 8
  aload 6
  aload 8
  invokeinterface java/util/Map/get(Ljava/lang/Object;)Ljava/lang/Object; 2
  astore 7
  aload 7
  astore 20
  aload 20
  checkcast java/lang/String
  astore 20
  aload 20
  astore 19
  new java/lang/StringBuilder
  astore 21
  ldc "\u5b89\u5168\u7b49\u7ea7:"
  astore 8
  aload 21
  astore_2
  aload_2
  aload 8
  invokespecial java/lang/StringBuilder/<init>(Ljava/lang/String;)V
  invokestatic com/tencent/mobwin/core/a/d/a()I
  istore 22
  aload 21
  astore_2
  iload 22
  istore_3
  aload_2
  iload_3
  invokevirtual java/lang/StringBuilder/append(I)Ljava/lang/StringBuilder;
  astore 21
  aload 21
  astore_2
  aload_2
  invokevirtual java/lang/StringBuilder/toString()Ljava/lang/String;
  astore 23
  ldc "IORY"
  astore 8
  aload 23
  astore_2
  aload 8
  aload_2
  invokestatic com/tencent/mobwin/core/o/b(Ljava/lang/String;Ljava/lang/String;)V
  new java/lang/StringBuilder
  astore 21
  ldc "IMEI:"
  astore 8
  aload 21
  astore_2
  aload_2
  aload 8
  invokespecial java/lang/StringBuilder/<init>(Ljava/lang/String;)V
  aload 21
  astore_2
  aload_2
  aload 9
  invokevirtual java/lang/StringBuilder/append(Ljava/lang/String;)Ljava/lang/StringBuilder;
  astore 21
  aload 21
  astore_2
  aload_2
  invokevirtual java/lang/StringBuilder/toString()Ljava/lang/String;
  astore 23
  ldc "IORY"
  astore 8
  aload 23
  astore_2
  aload 8
  aload_2
  invokestatic com/tencent/mobwin/core/o/b(Ljava/lang/String;Ljava/lang/String;)V
  new java/lang/StringBuilder
  astore 21
  ldc "meid:"
  astore 8
  aload 21
  astore_2
  aload_2
  aload 8
  invokespecial java/lang/StringBuilder/<init>(Ljava/lang/String;)V
  aload 21
  astore_2
  aload_2
  aload 11
  invokevirtual java/lang/StringBuilder/append(Ljava/lang/String;)Ljava/lang/StringBuilder;
  astore 21
  aload 21
  astore_2
  aload_2
  invokevirtual java/lang/StringBuilder/toString()Ljava/lang/String;
  astore 23
  ldc "IORY"
  astore 8
  aload 23
  astore_2
  aload 8
  aload_2
  invokestatic com/tencent/mobwin/core/o/b(Ljava/lang/String;Ljava/lang/String;)V
  invokestatic com/tencent/mobwin/core/a/d/a()I
  istore 22
  iload 22
  istore_2
  new java/lang/NoClassDefFoundError
  dup
  invokespecial java/lang/NoClassDefFoundError/<init>()V
  athrow
  iload 22
  lookupswitch
  0 : Label1
  1 : Label2
  2 : Label3
  3 : Label4
  default : Label0
Label0:
  goto Label5
Label5:
  new java/lang/StringBuilder
  astore 21
  aload 21
  astore_2
  aload_2
  invokespecial java/lang/StringBuilder/<init>()V
  aload_0
  astore_2
  aload_2
  getfield com/tencent/mobwin/core/a/c/c LMobWin/UserInfo;
  astore_2
  aload_2
  astore 24
  aload 21
  astore_2
  aload 24
  astore_3
  aload_2
  aload_3
  invokevirtual java/lang/StringBuilder/append(Ljava/lang/Object;)Ljava/lang/StringBuilder;
  astore 21
  aload 21
  astore_2
  aload_2
  invokevirtual java/lang/StringBuilder/toString()Ljava/lang/String;
  astore 19
  ldc "SDK"
  astore 8
  aload 19
  astore_2
  aload 8
  aload_2
  invokestatic com/tencent/mobwin/core/o/a(Ljava/lang/String;Ljava/lang/String;)V
  aload_0
  astore_2
  aload_2
  getfield com/tencent/mobwin/core/a/c/c LMobWin/UserInfo;
  astore_2
  aload_2
  astore 24
  aload 24
  areturn
Label1:
  new MobWin/UserInfo
  astore 24
  aload 24
  astore_2
  aload_2
  invokespecial MobWin/UserInfo/<init>()V
  aload 24
  astore_2
  aload_0
  astore_3
  aload_3
  aload_2
  putfield com/tencent/mobwin/core/a/c/c LMobWin/UserInfo;
  aload_0
  astore_2
  aload_2
  getfield com/tencent/mobwin/core/a/c/c LMobWin/UserInfo;
  astore_2
  aload_2
  astore 24
  aload_0
  astore_2
  aload_2
  getfield com/tencent/mobwin/core/a/c/b Ljava/util/Map;
  astore 6
  ldc "brand"
  astore 8
  aload 6
  aload 8
  invokeinterface java/util/Map/get(Ljava/lang/Object;)Ljava/lang/Object; 2
  astore 7
  aload 7
  astore 26
  aload 26
  checkcast java/lang/String
  astore 26
  aload 26
  astore 25
  aload 24
  astore_2
  aload 25
  astore_3
  aload_2
  aload_3
  invokevirtual MobWin/UserInfo/setBrand(Ljava/lang/String;)V
  aload_0
  astore_2
  aload_2
  getfield com/tencent/mobwin/core/a/c/c LMobWin/UserInfo;
  astore_2
  aload_2
  astore 24
  aload_0
  astore_2
  aload_2
  getfield com/tencent/mobwin/core/a/c/b Ljava/util/Map;
  astore 6
  ldc "manufacturer"
  astore 8
  aload 6
  aload 8
  invokeinterface java/util/Map/get(Ljava/lang/Object;)Ljava/lang/Object; 2
  astore 7
  aload 7
  astore 27
  aload 27
  checkcast java/lang/String
  astore 27
  aload 27
  astore 25
  aload 24
  astore_2
  aload 25
  astore_3
  aload_2
  aload_3
  invokevirtual MobWin/UserInfo/setManufacturer(Ljava/lang/String;)V
  aload_0
  astore_2
  aload_2
  getfield com/tencent/mobwin/core/a/c/c LMobWin/UserInfo;
  astore_2
  aload_2
  astore 24
  aload_0
  astore_2
  aload_2
  getfield com/tencent/mobwin/core/a/c/b Ljava/util/Map;
  astore 6
  ldc "model"
  astore 8
  aload 6
  aload 8
  invokeinterface java/util/Map/get(Ljava/lang/Object;)Ljava/lang/Object; 2
  astore 7
  aload 7
  astore 28
  aload 28
  checkcast java/lang/String
  astore 28
  aload 28
  astore 25
  aload 24
  astore_2
  aload 25
  astore_3
  aload_2
  aload_3
  invokevirtual MobWin/UserInfo/setModel(Ljava/lang/String;)V
  aload_0
  astore_2
  aload_2
  getfield com/tencent/mobwin/core/a/c/c LMobWin/UserInfo;
  astore_2
  aload_2
  astore 24
  new java/lang/StringBuilder
  astore 21
  ldc "Android "
  astore 8
  aload 21
  astore_2
  aload_2
  aload 8
  invokespecial java/lang/StringBuilder/<init>(Ljava/lang/String;)V
  aload_0
  astore_2
  aload_2
  getfield com/tencent/mobwin/core/a/c/b Ljava/util/Map;
  astore 6
  ldc "release"
  astore 8
  aload 6
  aload 8
  invokeinterface java/util/Map/get(Ljava/lang/Object;)Ljava/lang/Object; 2
  astore 7
  aload 7
  astore 29
  aload 29
  checkcast java/lang/String
  astore 29
  aload 29
  astore 25
  aload 21
  astore_2
  aload 25
  astore_3
  aload_2
  aload_3
  invokevirtual java/lang/StringBuilder/append(Ljava/lang/String;)Ljava/lang/StringBuilder;
  astore 21
  aload 21
  astore_2
  aload_2
  invokevirtual java/lang/StringBuilder/toString()Ljava/lang/String;
  astore 25
  aload 24
  astore_2
  aload 25
  astore_3
  aload_2
  aload_3
  invokevirtual MobWin/UserInfo/setOs(Ljava/lang/String;)V
  aload_0
  astore_2
  aload_2
  getfield com/tencent/mobwin/core/a/c/c LMobWin/UserInfo;
  astore_2
  aload_2
  astore 24
  aload 9
  invokestatic app/DummyClass/invokeIfStmt(Ljava/lang/Object;)V
  iload 9
  ifne Label6
  ldc "-"
  astore 9
Label6:
  aload 24
  astore_2
  aload_2
  aload 9
  invokevirtual MobWin/UserInfo/setImei(Ljava/lang/String;)V
  aload_0
  astore_2
  aload_2
  getfield com/tencent/mobwin/core/a/c/c LMobWin/UserInfo;
  astore_2
  aload_2
  astore 24
  aload 11
  invokestatic app/DummyClass/invokeIfStmt(Ljava/lang/Object;)V
  iload 11
  ifne Label7
  ldc "-"
  astore 11
Label7:
  aload 24
  astore_2
  aload_2
  aload 11
  invokevirtual MobWin/UserInfo/setMeid(Ljava/lang/String;)V
  aload_0
  astore_2
  aload_2
  getfield com/tencent/mobwin/core/a/c/c LMobWin/UserInfo;
  astore_2
  aload_2
  astore 24
  aload 13
  invokestatic app/DummyClass/invokeIfStmt(Ljava/lang/Object;)V
  iload 13
  ifne Label8
  ldc "-"
  astore 13
Label8:
  aload 24
  astore_2
  aload_2
  aload 13
  invokevirtual MobWin/UserInfo/setImsi(Ljava/lang/String;)V
  aload_0
  astore_2
  aload_2
  getfield com/tencent/mobwin/core/a/c/c LMobWin/UserInfo;
  astore_2
  aload_2
  astore 24
  aload_0
  astore_2
  aload_2
  getfield com/tencent/mobwin/core/a/c/a Ljava/util/Map;
  astore 6
  ldc "mac"
  astore 8
  aload 6
  aload 8
  invokeinterface java/util/Map/get(Ljava/lang/Object;)Ljava/lang/Object; 2
  astore 7
  aload 7
  astore 30
  aload 30
  checkcast java/lang/String
  astore 30
  aload 30
  astore 25
  aload 24
  astore_2
  aload 25
  astore_3
  aload_2
  aload_3
  invokevirtual MobWin/UserInfo/setMac(Ljava/lang/String;)V
  aload_0
  astore_2
  aload_2
  getfield com/tencent/mobwin/core/a/c/c LMobWin/UserInfo;
  astore_2
  aload_2
  astore 24
  aload_0
  astore_2
  aload_2
  getfield com/tencent/mobwin/core/a/c/a Ljava/util/Map;
  astore 6
  ldc "lang"
  astore 8
  aload 6
  aload 8
  invokeinterface java/util/Map/get(Ljava/lang/Object;)Ljava/lang/Object; 2
  astore 7
  aload 7
  astore 31
  aload 31
  checkcast java/lang/String
  astore 31
  aload 31
  astore 25
  aload 24
  astore_2
  aload 25
  astore_3
  aload_2
  aload_3
  invokevirtual MobWin/UserInfo/setLanguage(Ljava/lang/String;)V
  aload_0
  astore_2
  aload_2
  getfield com/tencent/mobwin/core/a/c/a Ljava/util/Map;
  astore 6
  ldc "tel"
  astore 8
  aload 6
  aload 8
  invokeinterface java/util/Map/get(Ljava/lang/Object;)Ljava/lang/Object; 2
  astore 7
  aload 7
  astore 32
  aload 32
  checkcast java/lang/String
  astore 32
  aload 32
  astore 25
  aload_0
  astore_2
  aload_2
  getfield com/tencent/mobwin/core/a/c/c LMobWin/UserInfo;
  astore_2
  aload_2
  astore 24
  ldc2_w 4294967295
  lstore 35
  aload 25
  astore_2
  lload 35
  lstore_3
  aload_2
  lload_3
  invokestatic com/tencent/mobwin/utils/b/a(Ljava/lang/String;J)J
  lstore 33
  aload 24
  astore_2
  lload 33
  lstore_3
  aload_2
  lload_3
  invokevirtual MobWin/UserInfo/setPhone_number(J)V
  aload_0
  astore_2
  aload_2
  getfield com/tencent/mobwin/core/a/c/c LMobWin/UserInfo;
  astore_2
  aload_2
  astore 24
  aload_1
  astore_2
  aload_2
  invokestatic com/tencent/mobwin/utils/b/a(Landroid/content/Context;)I
  istore 22
  iload 22
  istore_2
  iload_2
  i2s
  istore_2
  iload_2
  istore 37
  aload 24
  astore_2
  iload 37
  istore_3
  aload_2
  iload_3
  invokevirtual MobWin/UserInfo/setScreen_x(S)V
  aload_0
  astore_2
  aload_2
  getfield com/tencent/mobwin/core/a/c/c LMobWin/UserInfo;
  astore_2
  aload_2
  astore 24
  aload_1
  astore_2
  aload_2
  invokestatic com/tencent/mobwin/utils/b/b(Landroid/content/Context;)I
  istore 22
  iload 22
  istore_2
  iload_2
  i2s
  istore_2
  iload_2
  istore 37
  aload 24
  astore_2
  iload 37
  istore_3
  aload_2
  iload_3
  invokevirtual MobWin/UserInfo/setScreen_y(S)V
  aload_0
  astore_2
  aload_2
  getfield com/tencent/mobwin/core/a/c/c LMobWin/UserInfo;
  astore_2
  aload_2
  astore 24
  aload_1
  astore_2
  aload_2
  invokestatic com/tencent/mobwin/utils/b/c(Landroid/content/Context;)I
  istore 22
  iload 22
  istore_2
  iload_2
  i2s
  istore_2
  iload_2
  istore 37
  aload 24
  astore_2
  iload 37
  istore_3
  aload_2
  iload_3
  invokevirtual MobWin/UserInfo/setDm(S)V
  aload 15
  invokestatic app/DummyClass/invokeIfStmt(Ljava/lang/Object;)V
  iload 15
  ifeq Label9
  ldc "-"
  astore 25
  aload 25
  astore_2
  aload_2
  aload 15
  invokevirtual java/lang/String/equals(Ljava/lang/Object;)Z
  istore 38
  iload 38
  istore_2
  iload_2
  invokestatic app/DummyClass/invokeIfStmt(Z)V
  iload 38
  ifeq Label10
Label9:
  aload_0
  astore_2
  aload_2
  getfield com/tencent/mobwin/core/a/c/c LMobWin/UserInfo;
  astore_2
  aload_2
  astore 24
  iconst_0
  istore 39
  aload 24
  astore_2
  iload 39
  istore_3
  aload_2
  iload_3
  invokevirtual MobWin/UserInfo/setTel_support(B)V
Label17:
  aload 17
  invokestatic app/DummyClass/invokeIfStmt(Ljava/lang/Object;)V
  iload 17
  ifeq Label11
  ldc "-"
  astore 25
  aload 25
  astore_2
  aload_2
  aload 17
  invokevirtual java/lang/String/equals(Ljava/lang/Object;)Z
  istore 38
  iload 38
  istore_2
  iload_2
  invokestatic app/DummyClass/invokeIfStmt(Z)V
  iload 38
  ifeq Label12
Label11:
  aload_0
  astore_2
  aload_2
  getfield com/tencent/mobwin/core/a/c/c LMobWin/UserInfo;
  astore_2
  aload_2
  astore 24
  iconst_0
  istore 39
  aload 24
  astore_2
  iload 39
  istore_3
  aload_2
  iload_3
  invokevirtual MobWin/UserInfo/setWifi_support(B)V
Label19:
  aload 19
  astore_2
  aload_2
  invokestatic app/DummyClass/invokeIfStmt(Ljava/lang/Object;)V
  iload 19
  ifeq Label13
  ldc "-"
  astore 25
  aload 25
  astore_2
  aload 19
  astore_3
  aload_2
  aload_3
  invokevirtual java/lang/String/equals(Ljava/lang/Object;)Z
  istore 38
  iload 38
  istore_2
  iload_2
  invokestatic app/DummyClass/invokeIfStmt(Z)V
  iload 38
  ifeq Label14
Label13:
  aload_0
  astore_2
  aload_2
  getfield com/tencent/mobwin/core/a/c/c LMobWin/UserInfo;
  astore_2
  aload_2
  astore 24
  iconst_0
  istore 39
  aload 24
  astore_2
  iload 39
  istore_3
  aload_2
  iload_3
  invokevirtual MobWin/UserInfo/setLwp_support(B)V
Label21:
  aload_1
  astore_2
  aload_2
  invokestatic com/tencent/mobwin/core/a/f/f(Landroid/content/Context;)V
  aload_0
  astore_2
  aload_2
  getfield com/tencent/mobwin/core/a/c/c LMobWin/UserInfo;
  astore_2
  aload_2
  astore 24
  getstatic com/tencent/mobwin/core/a/f/z I
  istore 22
  aload 24
  astore_2
  iload 22
  istore_3
  aload_2
  iload_3
  invokevirtual MobWin/UserInfo/setNet_type(I)V
  getstatic com/tencent/mobwin/core/a/f/A Ljava/lang/String;
  astore 25
  ldc "-"
  astore 8
  aload 25
  astore_2
  aload_2
  aload 8
  invokevirtual java/lang/String/equals(Ljava/lang/Object;)Z
  istore 38
  iload 38
  istore_2
  iload_2
  invokestatic app/DummyClass/invokeIfStmt(Z)V
  iload 38
  ifeq Label15
  invokestatic com/tencent/mobwin/core/a/f/a()Ljava/lang/String;
  astore 25
Label15:
  aload_0
  astore_2
  aload_2
  getfield com/tencent/mobwin/core/a/c/c LMobWin/UserInfo;
  astore_2
  aload_2
  astore 24
  aload 24
  astore_2
  aload 25
  astore_3
  aload_2
  aload_3
  invokevirtual MobWin/UserInfo/setIp(Ljava/lang/String;)V
  goto Label5
Label10:
  ldc "true"
  astore 25
  aload 25
  astore_2
  aload_2
  aload 15
  invokevirtual java/lang/String/equals(Ljava/lang/Object;)Z
  istore 38
  iload 38
  istore_2
  iload_2
  invokestatic app/DummyClass/invokeIfStmt(Z)V
  iload 38
  ifeq Label16
  aload_0
  astore_2
  aload_2
  getfield com/tencent/mobwin/core/a/c/c LMobWin/UserInfo;
  astore_2
  aload_2
  astore 24
  iconst_1
  istore 39
  aload 24
  astore_2
  iload 39
  istore_3
  aload_2
  iload_3
  invokevirtual MobWin/UserInfo/setTel_support(B)V
  goto Label17
Label16:
  ldc "false"
  astore 25
  aload 25
  astore_2
  aload_2
  aload 15
  invokevirtual java/lang/String/equals(Ljava/lang/Object;)Z
  istore 38
  iload 38
  istore_2
  iload_2
  invokestatic app/DummyClass/invokeIfStmt(Z)V
  iload 38
  ifeq Label17
  aload_0
  astore_2
  aload_2
  getfield com/tencent/mobwin/core/a/c/c LMobWin/UserInfo;
  astore_2
  aload_2
  astore 24
  iconst_m1
  istore 39
  aload 24
  astore_2
  iload 39
  istore_3
  aload_2
  iload_3
  invokevirtual MobWin/UserInfo/setTel_support(B)V
  goto Label17
Label12:
  ldc "true"
  astore 25
  aload 25
  astore_2
  aload_2
  aload 17
  invokevirtual java/lang/String/equals(Ljava/lang/Object;)Z
  istore 38
  iload 38
  istore_2
  iload_2
  invokestatic app/DummyClass/invokeIfStmt(Z)V
  iload 38
  ifeq Label18
  aload_0
  astore_2
  aload_2
  getfield com/tencent/mobwin/core/a/c/c LMobWin/UserInfo;
  astore_2
  aload_2
  astore 24
  iconst_1
  istore 39
  aload 24
  astore_2
  iload 39
  istore_3
  aload_2
  iload_3
  invokevirtual MobWin/UserInfo/setWifi_support(B)V
  goto Label19
Label18:
  ldc "false"
  astore 25
  aload 25
  astore_2
  aload_2
  aload 17
  invokevirtual java/lang/String/equals(Ljava/lang/Object;)Z
  istore 38
  iload 38
  istore_2
  iload_2
  invokestatic app/DummyClass/invokeIfStmt(Z)V
  iload 38
  ifeq Label19
  aload_0
  astore_2
  aload_2
  getfield com/tencent/mobwin/core/a/c/c LMobWin/UserInfo;
  astore_2
  aload_2
  astore 24
  iconst_m1
  istore 39
  aload 24
  astore_2
  iload 39
  istore_3
  aload_2
  iload_3
  invokevirtual MobWin/UserInfo/setWifi_support(B)V
  goto Label19
Label14:
  ldc "true"
  astore 25
  aload 25
  astore_2
  aload 19
  astore_3
  aload_2
  aload_3
  invokevirtual java/lang/String/equals(Ljava/lang/Object;)Z
  istore 38
  iload 38
  istore_2
  iload_2
  invokestatic app/DummyClass/invokeIfStmt(Z)V
  iload 38
  ifeq Label20
  aload_0
  astore_2
  aload_2
  getfield com/tencent/mobwin/core/a/c/c LMobWin/UserInfo;
  astore_2
  aload_2
  astore 24
  iconst_1
  istore 39
  aload 24
  astore_2
  iload 39
  istore_3
  aload_2
  iload_3
  invokevirtual MobWin/UserInfo/setLwp_support(B)V
  goto Label21
Label20:
  ldc "false"
  astore 25
  aload 25
  astore_2
  aload 19
  astore_3
  aload_2
  aload_3
  invokevirtual java/lang/String/equals(Ljava/lang/Object;)Z
  istore 38
  iload 38
  istore_2
  iload_2
  invokestatic app/DummyClass/invokeIfStmt(Z)V
  iload 38
  ifeq Label21
  aload_0
  astore_2
  aload_2
  getfield com/tencent/mobwin/core/a/c/c LMobWin/UserInfo;
  astore_2
  aload_2
  astore 24
  iconst_m1
  istore 39
  aload 24
  astore_2
  iload 39
  istore_3
  aload_2
  iload_3
  invokevirtual MobWin/UserInfo/setLwp_support(B)V
  goto Label21
Label2:
  new MobWin/UserInfo
  astore 24
  aload 24
  astore_2
  aload_2
  invokespecial MobWin/UserInfo/<init>()V
  aload 24
  astore_2
  aload_0
  astore_3
  aload_3
  aload_2
  putfield com/tencent/mobwin/core/a/c/c LMobWin/UserInfo;
  aload_0
  astore_2
  aload_2
  getfield com/tencent/mobwin/core/a/c/c LMobWin/UserInfo;
  astore_2
  aload_2
  astore 24
  aload_0
  astore_2
  aload_2
  getfield com/tencent/mobwin/core/a/c/b Ljava/util/Map;
  astore 6
  ldc "brand"
  astore 8
  aload 6
  aload 8
  invokeinterface java/util/Map/get(Ljava/lang/Object;)Ljava/lang/Object; 2
  astore 7
  aload 7
  astore 40
  aload 40
  checkcast java/lang/String
  astore 40
  aload 40
  astore 25
  aload 24
  astore_2
  aload 25
  astore_3
  aload_2
  aload_3
  invokevirtual MobWin/UserInfo/setBrand(Ljava/lang/String;)V
  aload_0
  astore_2
  aload_2
  getfield com/tencent/mobwin/core/a/c/c LMobWin/UserInfo;
  astore_2
  aload_2
  astore 24
  aload_0
  astore_2
  aload_2
  getfield com/tencent/mobwin/core/a/c/b Ljava/util/Map;
  astore 6
  ldc "model"
  astore 8
  aload 6
  aload 8
  invokeinterface java/util/Map/get(Ljava/lang/Object;)Ljava/lang/Object; 2
  astore 7
  aload 7
  astore 41
  aload 41
  checkcast java/lang/String
  astore 41
  aload 41
  astore 25
  aload 24
  astore_2
  aload 25
  astore_3
  aload_2
  aload_3
  invokevirtual MobWin/UserInfo/setModel(Ljava/lang/String;)V
  aload_0
  astore_2
  aload_2
  getfield com/tencent/mobwin/core/a/c/c LMobWin/UserInfo;
  astore_2
  aload_2
  astore 24
  aload_0
  astore_2
  aload_2
  getfield com/tencent/mobwin/core/a/c/b Ljava/util/Map;
  astore 6
  ldc "manufacturer"
  astore 8
  aload 6
  aload 8
  invokeinterface java/util/Map/get(Ljava/lang/Object;)Ljava/lang/Object; 2
  astore 7
  aload 7
  astore 42
  aload 42
  checkcast java/lang/String
  astore 42
  aload 42
  astore 25
  aload 24
  astore_2
  aload 25
  astore_3
  aload_2
  aload_3
  invokevirtual MobWin/UserInfo/setManufacturer(Ljava/lang/String;)V
  aload_0
  astore_2
  aload_2
  getfield com/tencent/mobwin/core/a/c/c LMobWin/UserInfo;
  astore_2
  aload_2
  astore 24
  new java/lang/StringBuilder
  astore 21
  ldc "Android "
  astore 8
  aload 21
  astore_2
  aload_2
  aload 8
  invokespecial java/lang/StringBuilder/<init>(Ljava/lang/String;)V
  aload_0
  astore_2
  aload_2
  getfield com/tencent/mobwin/core/a/c/b Ljava/util/Map;
  astore 6
  ldc "release"
  astore 8
  aload 6
  aload 8
  invokeinterface java/util/Map/get(Ljava/lang/Object;)Ljava/lang/Object; 2
  astore 7
  aload 7
  astore 43
  aload 43
  checkcast java/lang/String
  astore 43
  aload 43
  astore 25
  aload 21
  astore_2
  aload 25
  astore_3
  aload_2
  aload_3
  invokevirtual java/lang/StringBuilder/append(Ljava/lang/String;)Ljava/lang/StringBuilder;
  astore 21
  aload 21
  astore_2
  aload_2
  invokevirtual java/lang/StringBuilder/toString()Ljava/lang/String;
  astore 25
  aload 24
  astore_2
  aload 25
  astore_3
  aload_2
  aload_3
  invokevirtual MobWin/UserInfo/setOs(Ljava/lang/String;)V
  aload 15
  invokestatic app/DummyClass/invokeIfStmt(Ljava/lang/Object;)V
  iload 15
  ifeq Label22
  ldc "-"
  astore 25
  aload 25
  astore_2
  aload_2
  aload 15
  invokevirtual java/lang/String/equals(Ljava/lang/Object;)Z
  istore 38
  iload 38
  istore_2
  iload_2
  invokestatic app/DummyClass/invokeIfStmt(Z)V
  iload 38
  ifeq Label23
Label22:
  aload_0
  astore_2
  aload_2
  getfield com/tencent/mobwin/core/a/c/c LMobWin/UserInfo;
  astore_2
  aload_2
  astore 24
  iconst_0
  istore 39
  aload 24
  astore_2
  iload 39
  istore_3
  aload_2
  iload_3
  invokevirtual MobWin/UserInfo/setTel_support(B)V
Label32:
  aload 17
  invokestatic app/DummyClass/invokeIfStmt(Ljava/lang/Object;)V
  iload 17
  ifeq Label24
  ldc "-"
  astore 25
  aload 25
  astore_2
  aload_2
  aload 17
  invokevirtual java/lang/String/equals(Ljava/lang/Object;)Z
  istore 38
  iload 38
  istore_2
  iload_2
  invokestatic app/DummyClass/invokeIfStmt(Z)V
  iload 38
  ifeq Label25
Label24:
  aload_0
  astore_2
  aload_2
  getfield com/tencent/mobwin/core/a/c/c LMobWin/UserInfo;
  astore_2
  aload_2
  astore 24
  iconst_0
  istore 39
  aload 24
  astore_2
  iload 39
  istore_3
  aload_2
  iload_3
  invokevirtual MobWin/UserInfo/setWifi_support(B)V
Label34:
  aload 19
  astore_2
  aload_2
  invokestatic app/DummyClass/invokeIfStmt(Ljava/lang/Object;)V
  iload 19
  ifeq Label26
  ldc "-"
  astore 25
  aload 25
  astore_2
  aload 19
  astore_3
  aload_2
  aload_3
  invokevirtual java/lang/String/equals(Ljava/lang/Object;)Z
  istore 38
  iload 38
  istore_2
  iload_2
  invokestatic app/DummyClass/invokeIfStmt(Z)V
  iload 38
  ifeq Label27
Label26:
  aload_0
  astore_2
  aload_2
  getfield com/tencent/mobwin/core/a/c/c LMobWin/UserInfo;
  astore_2
  aload_2
  astore 24
  iconst_0
  istore 39
  aload 24
  astore_2
  iload 39
  istore_3
  aload_2
  iload_3
  invokevirtual MobWin/UserInfo/setLwp_support(B)V
Label36:
  aload_0
  astore_2
  aload_2
  getfield com/tencent/mobwin/core/a/c/c LMobWin/UserInfo;
  astore_2
  aload_2
  astore 24
  aload 9
  invokestatic app/DummyClass/invokeIfStmt(Ljava/lang/Object;)V
  iload 9
  ifne Label28
  ldc "-"
  astore 9
Label28:
  aload 24
  astore_2
  aload_2
  aload 9
  invokevirtual MobWin/UserInfo/setImei(Ljava/lang/String;)V
  aload_0
  astore_2
  aload_2
  getfield com/tencent/mobwin/core/a/c/c LMobWin/UserInfo;
  astore_2
  aload_2
  astore 24
  aload 11
  invokestatic app/DummyClass/invokeIfStmt(Ljava/lang/Object;)V
  iload 11
  ifne Label29
  ldc "-"
  astore 11
Label29:
  aload 24
  astore_2
  aload_2
  aload 11
  invokevirtual MobWin/UserInfo/setMeid(Ljava/lang/String;)V
  aload_0
  astore_2
  aload_2
  getfield com/tencent/mobwin/core/a/c/c LMobWin/UserInfo;
  astore_2
  aload_2
  astore 24
  aload_0
  astore_2
  aload_2
  getfield com/tencent/mobwin/core/a/c/a Ljava/util/Map;
  astore 6
  ldc "mac"
  astore 8
  aload 6
  aload 8
  invokeinterface java/util/Map/get(Ljava/lang/Object;)Ljava/lang/Object; 2
  astore 7
  aload 7
  astore 44
  aload 44
  checkcast java/lang/String
  astore 44
  aload 44
  astore 25
  aload 24
  astore_2
  aload 25
  astore_3
  aload_2
  aload_3
  invokevirtual MobWin/UserInfo/setMac(Ljava/lang/String;)V
  aload_0
  astore_2
  aload_2
  getfield com/tencent/mobwin/core/a/c/c LMobWin/UserInfo;
  astore_2
  aload_2
  astore 24
  aload_0
  astore_2
  aload_2
  getfield com/tencent/mobwin/core/a/c/a Ljava/util/Map;
  astore 6
  ldc "lang"
  astore 8
  aload 6
  aload 8
  invokeinterface java/util/Map/get(Ljava/lang/Object;)Ljava/lang/Object; 2
  astore 7
  aload 7
  astore 45
  aload 45
  checkcast java/lang/String
  astore 45
  aload 45
  astore 25
  aload 24
  astore_2
  aload 25
  astore_3
  aload_2
  aload_3
  invokevirtual MobWin/UserInfo/setLanguage(Ljava/lang/String;)V
  aload_0
  astore_2
  aload_2
  getfield com/tencent/mobwin/core/a/c/c LMobWin/UserInfo;
  astore_2
  aload_2
  astore 24
  aload_1
  astore_2
  aload_2
  invokestatic com/tencent/mobwin/utils/b/a(Landroid/content/Context;)I
  istore 22
  iload 22
  istore_2
  iload_2
  i2s
  istore_2
  iload_2
  istore 37
  aload 24
  astore_2
  iload 37
  istore_3
  aload_2
  iload_3
  invokevirtual MobWin/UserInfo/setScreen_x(S)V
  aload_0
  astore_2
  aload_2
  getfield com/tencent/mobwin/core/a/c/c LMobWin/UserInfo;
  astore_2
  aload_2
  astore 24
  aload_1
  astore_2
  aload_2
  invokestatic com/tencent/mobwin/utils/b/b(Landroid/content/Context;)I
  istore 22
  iload 22
  istore_2
  iload_2
  i2s
  istore_2
  iload_2
  istore 37
  aload 24
  astore_2
  iload 37
  istore_3
  aload_2
  iload_3
  invokevirtual MobWin/UserInfo/setScreen_y(S)V
  aload_0
  astore_2
  aload_2
  getfield com/tencent/mobwin/core/a/c/c LMobWin/UserInfo;
  astore_2
  aload_2
  astore 24
  aload_1
  astore_2
  aload_2
  invokestatic com/tencent/mobwin/utils/b/c(Landroid/content/Context;)I
  istore 22
  iload 22
  istore_2
  iload_2
  i2s
  istore_2
  iload_2
  istore 37
  aload 24
  astore_2
  iload 37
  istore_3
  aload_2
  iload_3
  invokevirtual MobWin/UserInfo/setDm(S)V
  aload_1
  astore_2
  aload_2
  invokestatic com/tencent/mobwin/core/a/f/f(Landroid/content/Context;)V
  aload_0
  astore_2
  aload_2
  getfield com/tencent/mobwin/core/a/c/c LMobWin/UserInfo;
  astore_2
  aload_2
  astore 24
  getstatic com/tencent/mobwin/core/a/f/z I
  istore 22
  aload 24
  astore_2
  iload 22
  istore_3
  aload_2
  iload_3
  invokevirtual MobWin/UserInfo/setNet_type(I)V
  getstatic com/tencent/mobwin/core/a/f/A Ljava/lang/String;
  astore 25
  ldc "-"
  astore 8
  aload 25
  astore_2
  aload_2
  aload 8
  invokevirtual java/lang/String/equals(Ljava/lang/Object;)Z
  istore 38
  iload 38
  istore_2
  iload_2
  invokestatic app/DummyClass/invokeIfStmt(Z)V
  iload 38
  ifeq Label30
  invokestatic com/tencent/mobwin/core/a/f/a()Ljava/lang/String;
  astore 25
Label30:
  aload_0
  astore_2
  aload_2
  getfield com/tencent/mobwin/core/a/c/c LMobWin/UserInfo;
  astore_2
  aload_2
  astore 24
  aload 24
  astore_2
  aload 25
  astore_3
  aload_2
  aload_3
  invokevirtual MobWin/UserInfo/setIp(Ljava/lang/String;)V
  goto Label5
Label23:
  ldc "true"
  astore 25
  aload 25
  astore_2
  aload_2
  aload 15
  invokevirtual java/lang/String/equals(Ljava/lang/Object;)Z
  istore 38
  iload 38
  istore_2
  iload_2
  invokestatic app/DummyClass/invokeIfStmt(Z)V
  iload 38
  ifeq Label31
  aload_0
  astore_2
  aload_2
  getfield com/tencent/mobwin/core/a/c/c LMobWin/UserInfo;
  astore_2
  aload_2
  astore 24
  iconst_1
  istore 39
  aload 24
  astore_2
  iload 39
  istore_3
  aload_2
  iload_3
  invokevirtual MobWin/UserInfo/setTel_support(B)V
  goto Label32
Label31:
  ldc "false"
  astore 25
  aload 25
  astore_2
  aload_2
  aload 15
  invokevirtual java/lang/String/equals(Ljava/lang/Object;)Z
  istore 38
  iload 38
  istore_2
  iload_2
  invokestatic app/DummyClass/invokeIfStmt(Z)V
  iload 38
  ifeq Label32
  aload_0
  astore_2
  aload_2
  getfield com/tencent/mobwin/core/a/c/c LMobWin/UserInfo;
  astore_2
  aload_2
  astore 24
  iconst_m1
  istore 39
  aload 24
  astore_2
  iload 39
  istore_3
  aload_2
  iload_3
  invokevirtual MobWin/UserInfo/setTel_support(B)V
  goto Label32
Label25:
  ldc "true"
  astore 25
  aload 25
  astore_2
  aload_2
  aload 17
  invokevirtual java/lang/String/equals(Ljava/lang/Object;)Z
  istore 38
  iload 38
  istore_2
  iload_2
  invokestatic app/DummyClass/invokeIfStmt(Z)V
  iload 38
  ifeq Label33
  aload_0
  astore_2
  aload_2
  getfield com/tencent/mobwin/core/a/c/c LMobWin/UserInfo;
  astore_2
  aload_2
  astore 24
  iconst_1
  istore 39
  aload 24
  astore_2
  iload 39
  istore_3
  aload_2
  iload_3
  invokevirtual MobWin/UserInfo/setWifi_support(B)V
  goto Label34
Label33:
  ldc "false"
  astore 25
  aload 25
  astore_2
  aload_2
  aload 17
  invokevirtual java/lang/String/equals(Ljava/lang/Object;)Z
  istore 38
  iload 38
  istore_2
  iload_2
  invokestatic app/DummyClass/invokeIfStmt(Z)V
  iload 38
  ifeq Label34
  aload_0
  astore_2
  aload_2
  getfield com/tencent/mobwin/core/a/c/c LMobWin/UserInfo;
  astore_2
  aload_2
  astore 24
  iconst_m1
  istore 39
  aload 24
  astore_2
  iload 39
  istore_3
  aload_2
  iload_3
  invokevirtual MobWin/UserInfo/setWifi_support(B)V
  goto Label34
Label27:
  ldc "true"
  astore 25
  aload 25
  astore_2
  aload 19
  astore_3
  aload_2
  aload_3
  invokevirtual java/lang/String/equals(Ljava/lang/Object;)Z
  istore 38
  iload 38
  istore_2
  iload_2
  invokestatic app/DummyClass/invokeIfStmt(Z)V
  iload 38
  ifeq Label35
  aload_0
  astore_2
  aload_2
  getfield com/tencent/mobwin/core/a/c/c LMobWin/UserInfo;
  astore_2
  aload_2
  astore 24
  iconst_1
  istore 39
  aload 24
  astore_2
  iload 39
  istore_3
  aload_2
  iload_3
  invokevirtual MobWin/UserInfo/setLwp_support(B)V
  goto Label36
Label35:
  ldc "false"
  astore 25
  aload 25
  astore_2
  aload 19
  astore_3
  aload_2
  aload_3
  invokevirtual java/lang/String/equals(Ljava/lang/Object;)Z
  istore 38
  iload 38
  istore_2
  iload_2
  invokestatic app/DummyClass/invokeIfStmt(Z)V
  iload 38
  ifeq Label36
  aload_0
  astore_2
  aload_2
  getfield com/tencent/mobwin/core/a/c/c LMobWin/UserInfo;
  astore_2
  aload_2
  astore 24
  iconst_m1
  istore 39
  aload 24
  astore_2
  iload 39
  istore_3
  aload_2
  iload_3
  invokevirtual MobWin/UserInfo/setLwp_support(B)V
  goto Label36
Label3:
  new MobWin/UserInfo
  astore 24
  aload 24
  astore_2
  aload_2
  invokespecial MobWin/UserInfo/<init>()V
  aload 24
  astore_2
  aload_0
  astore_3
  aload_3
  aload_2
  putfield com/tencent/mobwin/core/a/c/c LMobWin/UserInfo;
  aload_0
  astore_2
  aload_2
  getfield com/tencent/mobwin/core/a/c/c LMobWin/UserInfo;
  astore_2
  aload_2
  astore 24
  aload_0
  astore_2
  aload_2
  getfield com/tencent/mobwin/core/a/c/b Ljava/util/Map;
  astore 6
  ldc "brand"
  astore 8
  aload 6
  aload 8
  invokeinterface java/util/Map/get(Ljava/lang/Object;)Ljava/lang/Object; 2
  astore 7
  aload 7
  astore 46
  aload 46
  checkcast java/lang/String
  astore 46
  aload 46
  astore 25
  aload 24
  astore_2
  aload 25
  astore_3
  aload_2
  aload_3
  invokevirtual MobWin/UserInfo/setBrand(Ljava/lang/String;)V
  aload_0
  astore_2
  aload_2
  getfield com/tencent/mobwin/core/a/c/c LMobWin/UserInfo;
  astore_2
  aload_2
  astore 24
  aload_0
  astore_2
  aload_2
  getfield com/tencent/mobwin/core/a/c/b Ljava/util/Map;
  astore 6
  ldc "manufacturer"
  astore 8
  aload 6
  aload 8
  invokeinterface java/util/Map/get(Ljava/lang/Object;)Ljava/lang/Object; 2
  astore 7
  aload 7
  astore 47
  aload 47
  checkcast java/lang/String
  astore 47
  aload 47
  astore 25
  aload 24
  astore_2
  aload 25
  astore_3
  aload_2
  aload_3
  invokevirtual MobWin/UserInfo/setManufacturer(Ljava/lang/String;)V
  aload_0
  astore_2
  aload_2
  getfield com/tencent/mobwin/core/a/c/c LMobWin/UserInfo;
  astore_2
  aload_2
  astore 24
  aload_0
  astore_2
  aload_2
  getfield com/tencent/mobwin/core/a/c/b Ljava/util/Map;
  astore 6
  ldc "model"
  astore 8
  aload 6
  aload 8
  invokeinterface java/util/Map/get(Ljava/lang/Object;)Ljava/lang/Object; 2
  astore 7
  aload 7
  astore 48
  aload 48
  checkcast java/lang/String
  astore 48
  aload 48
  astore 25
  aload 24
  astore_2
  aload 25
  astore_3
  aload_2
  aload_3
  invokevirtual MobWin/UserInfo/setModel(Ljava/lang/String;)V
  aload 15
  invokestatic app/DummyClass/invokeIfStmt(Ljava/lang/Object;)V
  iload 15
  ifeq Label37
  ldc "-"
  astore 25
  aload 25
  astore_2
  aload_2
  aload 15
  invokevirtual java/lang/String/equals(Ljava/lang/Object;)Z
  istore 38
  iload 38
  istore_2
  iload_2
  invokestatic app/DummyClass/invokeIfStmt(Z)V
  iload 38
  ifeq Label38
Label37:
  aload_0
  astore_2
  aload_2
  getfield com/tencent/mobwin/core/a/c/c LMobWin/UserInfo;
  astore_2
  aload_2
  astore 24
  iconst_0
  istore 39
  aload 24
  astore_2
  iload 39
  istore_3
  aload_2
  iload_3
  invokevirtual MobWin/UserInfo/setTel_support(B)V
Label46:
  aload 17
  invokestatic app/DummyClass/invokeIfStmt(Ljava/lang/Object;)V
  iload 17
  ifeq Label39
  ldc "-"
  astore 25
  aload 25
  astore_2
  aload_2
  aload 17
  invokevirtual java/lang/String/equals(Ljava/lang/Object;)Z
  istore 38
  iload 38
  istore_2
  iload_2
  invokestatic app/DummyClass/invokeIfStmt(Z)V
  iload 38
  ifeq Label40
Label39:
  aload_0
  astore_2
  aload_2
  getfield com/tencent/mobwin/core/a/c/c LMobWin/UserInfo;
  astore_2
  aload_2
  astore 24
  iconst_0
  istore 39
  aload 24
  astore_2
  iload 39
  istore_3
  aload_2
  iload_3
  invokevirtual MobWin/UserInfo/setWifi_support(B)V
Label48:
  aload 19
  astore_2
  aload_2
  invokestatic app/DummyClass/invokeIfStmt(Ljava/lang/Object;)V
  iload 19
  ifeq Label41
  ldc "-"
  astore 25
  aload 25
  astore_2
  aload 19
  astore_3
  aload_2
  aload_3
  invokevirtual java/lang/String/equals(Ljava/lang/Object;)Z
  istore 38
  iload 38
  istore_2
  iload_2
  invokestatic app/DummyClass/invokeIfStmt(Z)V
  iload 38
  ifeq Label42
Label41:
  aload_0
  astore_2
  aload_2
  getfield com/tencent/mobwin/core/a/c/c LMobWin/UserInfo;
  astore_2
  aload_2
  astore 24
  iconst_0
  istore 39
  aload 24
  astore_2
  iload 39
  istore_3
  aload_2
  iload_3
  invokevirtual MobWin/UserInfo/setLwp_support(B)V
Label50:
  aload_0
  astore_2
  aload_2
  getfield com/tencent/mobwin/core/a/c/c LMobWin/UserInfo;
  astore_2
  aload_2
  astore 24
  aload 9
  invokestatic app/DummyClass/invokeIfStmt(Ljava/lang/Object;)V
  iload 9
  ifne Label43
  ldc "-"
  astore 9
Label43:
  aload 24
  astore_2
  aload_2
  aload 9
  invokevirtual MobWin/UserInfo/setImei(Ljava/lang/String;)V
  aload_0
  astore_2
  aload_2
  getfield com/tencent/mobwin/core/a/c/c LMobWin/UserInfo;
  astore_2
  aload_2
  astore 24
  aload 11
  invokestatic app/DummyClass/invokeIfStmt(Ljava/lang/Object;)V
  iload 11
  ifne Label44
  ldc "-"
  astore 11
Label44:
  aload 24
  astore_2
  aload_2
  aload 11
  invokevirtual MobWin/UserInfo/setMeid(Ljava/lang/String;)V
  aload_0
  astore_2
  aload_2
  getfield com/tencent/mobwin/core/a/c/c LMobWin/UserInfo;
  astore_2
  aload_2
  astore 24
  new java/lang/StringBuilder
  astore 21
  ldc "Android "
  astore 8
  aload 21
  astore_2
  aload_2
  aload 8
  invokespecial java/lang/StringBuilder/<init>(Ljava/lang/String;)V
  aload_0
  astore_2
  aload_2
  getfield com/tencent/mobwin/core/a/c/b Ljava/util/Map;
  astore 6
  ldc "release"
  astore 8
  aload 6
  aload 8
  invokeinterface java/util/Map/get(Ljava/lang/Object;)Ljava/lang/Object; 2
  astore 7
  aload 7
  astore 49
  aload 49
  checkcast java/lang/String
  astore 49
  aload 49
  astore 25
  aload 21
  astore_2
  aload 25
  astore_3
  aload_2
  aload_3
  invokevirtual java/lang/StringBuilder/append(Ljava/lang/String;)Ljava/lang/StringBuilder;
  astore 21
  aload 21
  astore_2
  aload_2
  invokevirtual java/lang/StringBuilder/toString()Ljava/lang/String;
  astore 25
  aload 24
  astore_2
  aload 25
  astore_3
  aload_2
  aload_3
  invokevirtual MobWin/UserInfo/setOs(Ljava/lang/String;)V
  aload_0
  astore_2
  aload_2
  getfield com/tencent/mobwin/core/a/c/c LMobWin/UserInfo;
  astore_2
  aload_2
  astore 24
  aload_0
  astore_2
  aload_2
  getfield com/tencent/mobwin/core/a/c/a Ljava/util/Map;
  astore 6
  ldc "lang"
  astore 8
  aload 6
  aload 8
  invokeinterface java/util/Map/get(Ljava/lang/Object;)Ljava/lang/Object; 2
  astore 7
  aload 7
  astore 50
  aload 50
  checkcast java/lang/String
  astore 50
  aload 50
  astore 25
  aload 24
  astore_2
  aload 25
  astore_3
  aload_2
  aload_3
  invokevirtual MobWin/UserInfo/setLanguage(Ljava/lang/String;)V
  aload_0
  astore_2
  aload_2
  getfield com/tencent/mobwin/core/a/c/c LMobWin/UserInfo;
  astore_2
  aload_2
  astore 24
  aload_1
  astore_2
  aload_2
  invokestatic com/tencent/mobwin/utils/b/a(Landroid/content/Context;)I
  istore 22
  iload 22
  istore_2
  iload_2
  i2s
  istore_2
  iload_2
  istore 37
  aload 24
  astore_2
  iload 37
  istore_3
  aload_2
  iload_3
  invokevirtual MobWin/UserInfo/setScreen_x(S)V
  aload_0
  astore_2
  aload_2
  getfield com/tencent/mobwin/core/a/c/c LMobWin/UserInfo;
  astore_2
  aload_2
  astore 24
  aload_1
  astore_2
  aload_2
  invokestatic com/tencent/mobwin/utils/b/b(Landroid/content/Context;)I
  istore 22
  iload 22
  istore_2
  iload_2
  i2s
  istore_2
  iload_2
  istore 37
  aload 24
  astore_2
  iload 37
  istore_3
  aload_2
  iload_3
  invokevirtual MobWin/UserInfo/setScreen_y(S)V
  aload_0
  astore_2
  aload_2
  getfield com/tencent/mobwin/core/a/c/c LMobWin/UserInfo;
  astore_2
  aload_2
  astore 24
  aload_1
  astore_2
  aload_2
  invokestatic com/tencent/mobwin/utils/b/c(Landroid/content/Context;)I
  istore 22
  iload 22
  istore_2
  iload_2
  i2s
  istore_2
  iload_2
  istore 37
  aload 24
  astore_2
  iload 37
  istore_3
  aload_2
  iload_3
  invokevirtual MobWin/UserInfo/setDm(S)V
  goto Label5
Label38:
  ldc "true"
  astore 25
  aload 25
  astore_2
  aload_2
  aload 15
  invokevirtual java/lang/String/equals(Ljava/lang/Object;)Z
  istore 38
  iload 38
  istore_2
  iload_2
  invokestatic app/DummyClass/invokeIfStmt(Z)V
  iload 38
  ifeq Label45
  aload_0
  astore_2
  aload_2
  getfield com/tencent/mobwin/core/a/c/c LMobWin/UserInfo;
  astore_2
  aload_2
  astore 24
  iconst_1
  istore 39
  aload 24
  astore_2
  iload 39
  istore_3
  aload_2
  iload_3
  invokevirtual MobWin/UserInfo/setTel_support(B)V
  goto Label46
Label45:
  ldc "false"
  astore 25
  aload 25
  astore_2
  aload_2
  aload 15
  invokevirtual java/lang/String/equals(Ljava/lang/Object;)Z
  istore 38
  iload 38
  istore_2
  iload_2
  invokestatic app/DummyClass/invokeIfStmt(Z)V
  iload 38
  ifeq Label46
  aload_0
  astore_2
  aload_2
  getfield com/tencent/mobwin/core/a/c/c LMobWin/UserInfo;
  astore_2
  aload_2
  astore 24
  iconst_m1
  istore 39
  aload 24
  astore_2
  iload 39
  istore_3
  aload_2
  iload_3
  invokevirtual MobWin/UserInfo/setTel_support(B)V
  goto Label46
Label40:
  ldc "true"
  astore 25
  aload 25
  astore_2
  aload_2
  aload 17
  invokevirtual java/lang/String/equals(Ljava/lang/Object;)Z
  istore 38
  iload 38
  istore_2
  iload_2
  invokestatic app/DummyClass/invokeIfStmt(Z)V
  iload 38
  ifeq Label47
  aload_0
  astore_2
  aload_2
  getfield com/tencent/mobwin/core/a/c/c LMobWin/UserInfo;
  astore_2
  aload_2
  astore 24
  iconst_1
  istore 39
  aload 24
  astore_2
  iload 39
  istore_3
  aload_2
  iload_3
  invokevirtual MobWin/UserInfo/setWifi_support(B)V
  goto Label48
Label47:
  ldc "false"
  astore 25
  aload 25
  astore_2
  aload_2
  aload 17
  invokevirtual java/lang/String/equals(Ljava/lang/Object;)Z
  istore 38
  iload 38
  istore_2
  iload_2
  invokestatic app/DummyClass/invokeIfStmt(Z)V
  iload 38
  ifeq Label48
  aload_0
  astore_2
  aload_2
  getfield com/tencent/mobwin/core/a/c/c LMobWin/UserInfo;
  astore_2
  aload_2
  astore 24
  iconst_m1
  istore 39
  aload 24
  astore_2
  iload 39
  istore_3
  aload_2
  iload_3
  invokevirtual MobWin/UserInfo/setWifi_support(B)V
  goto Label48
Label42:
  ldc "true"
  astore 25
  aload 25
  astore_2
  aload 19
  astore_3
  aload_2
  aload_3
  invokevirtual java/lang/String/equals(Ljava/lang/Object;)Z
  istore 38
  iload 38
  istore_2
  iload_2
  invokestatic app/DummyClass/invokeIfStmt(Z)V
  iload 38
  ifeq Label49
  aload_0
  astore_2
  aload_2
  getfield com/tencent/mobwin/core/a/c/c LMobWin/UserInfo;
  astore_2
  aload_2
  astore 24
  iconst_1
  istore 39
  aload 24
  astore_2
  iload 39
  istore_3
  aload_2
  iload_3
  invokevirtual MobWin/UserInfo/setLwp_support(B)V
  goto Label50
Label49:
  ldc "false"
  astore 25
  aload 25
  astore_2
  aload 19
  astore_3
  aload_2
  aload_3
  invokevirtual java/lang/String/equals(Ljava/lang/Object;)Z
  istore 38
  iload 38
  istore_2
  iload_2
  invokestatic app/DummyClass/invokeIfStmt(Z)V
  iload 38
  ifeq Label50
  aload_0
  astore_2
  aload_2
  getfield com/tencent/mobwin/core/a/c/c LMobWin/UserInfo;
  astore_2
  aload_2
  astore 24
  iconst_m1
  istore 39
  aload 24
  astore_2
  iload 39
  istore_3
  aload_2
  iload_3
  invokevirtual MobWin/UserInfo/setLwp_support(B)V
  goto Label50
Label4:
  new MobWin/UserInfo
  astore 24
  aload 24
  astore_2
  aload_2
  invokespecial MobWin/UserInfo/<init>()V
  aload 24
  astore_2
  aload_0
  astore_3
  aload_3
  aload_2
  putfield com/tencent/mobwin/core/a/c/c LMobWin/UserInfo;
  goto Label5
  nop
  nop
.end <method>

.method public b(Landroid/content/Context;)LMobWin/AppInfo;
.limit locals 8
.limit stack 200
  nop
  aload_0
  getfield com/tencent/mobwin/core/a/c/d LMobWin/AppInfo;
  astore_2
  new java/lang/NoClassDefFoundError
  dup
  invokespecial java/lang/NoClassDefFoundError/<init>()V
  athrow
  iload_2
  ifne Label0
  new MobWin/AppInfo
  astore_2
  aload_2
  invokespecial MobWin/AppInfo/<init>()V
  aload_0
  aload_2
  putfield com/tencent/mobwin/core/a/c/d LMobWin/AppInfo;
  aload_0
  getfield com/tencent/mobwin/core/a/c/d LMobWin/AppInfo;
  astore_2
  ldc "0"
  astore_3
  aload_2
  aload_3
  invokevirtual MobWin/AppInfo/setApp_id(Ljava/lang/String;)V
  aload_0
  getfield com/tencent/mobwin/core/a/c/d LMobWin/AppInfo;
  astore_2
  invokestatic com/tencent/mobwin/core/w/c()Ljava/lang/String;
  astore 4
  aload_2
  aload 4
  invokevirtual MobWin/AppInfo/setApp_key(Ljava/lang/String;)V
  aload_0
  getfield com/tencent/mobwin/core/a/c/d LMobWin/AppInfo;
  astore_2
  invokestatic com/tencent/mobwin/core/w/d()Ljava/lang/String;
  astore 4
  aload_2
  aload 4
  invokevirtual MobWin/AppInfo/setRelease_channel(Ljava/lang/String;)V
  aload_0
  getfield com/tencent/mobwin/core/a/c/d LMobWin/AppInfo;
  astore_2
  aload_1
  invokevirtual android/content/Context/getPackageName()Ljava/lang/String;
  astore 4
  aload_2
  aload 4
  invokevirtual MobWin/AppInfo/setApp_name(Ljava/lang/String;)V
  aload_0
  getfield com/tencent/mobwin/core/a/c/d LMobWin/AppInfo;
  astore_2
  aload_1
  invokestatic com/tencent/mobwin/core/a/f/b(Landroid/content/Context;)Ljava/lang/String;
  astore 4
  aload_2
  aload 4
  invokevirtual MobWin/AppInfo/setApp_signature(Ljava/lang/String;)V
  aload_1
  invokestatic com/tencent/mobwin/core/a/f/c(Landroid/content/Context;)Ljava/lang/String;
  astore 5
  aload_0
  getfield com/tencent/mobwin/core/a/c/d LMobWin/AppInfo;
  astore_2
  invokestatic com/tencent/mobwin/core/w/a()Ljava/lang/String;
  astore 4
  aload_2
  aload 4
  invokevirtual MobWin/AppInfo/setIntegrateId(Ljava/lang/String;)V
  aload_0
  getfield com/tencent/mobwin/core/a/c/d LMobWin/AppInfo;
  astore_2
  aload_2
  aload 5
  invokevirtual MobWin/AppInfo/setApp_version(Ljava/lang/String;)V
  aload_0
  getfield com/tencent/mobwin/core/a/c/d LMobWin/AppInfo;
  astore_2
  ldc ""
  astore_3
  aload_2
  aload_3
  invokevirtual MobWin/AppInfo/setAux_key(Ljava/lang/String;)V
  aload_0
  getfield com/tencent/mobwin/core/a/c/d LMobWin/AppInfo;
  astore_2
  invokestatic com/tencent/mobwin/core/w/h()Ljava/lang/String;
  astore 5
  aload_2
  aload 5
  invokevirtual MobWin/AppInfo/setSdk_version(Ljava/lang/String;)V
Label0:
  iconst_1
  istore 6
  invokestatic com/tencent/mobwin/core/w/f()Z
  istore 7
  iload 7
  invokestatic app/DummyClass/invokeIfStmt(Z)V
  iload 7
  ifeq Label1
  iconst_0
  istore 6
Label1:
  aload_0
  getfield com/tencent/mobwin/core/a/c/d LMobWin/AppInfo;
  astore_2
  aload_2
  iload 6
  invokevirtual MobWin/AppInfo/setApp_mode(I)V
  aload_0
  getfield com/tencent/mobwin/core/a/c/d LMobWin/AppInfo;
  astore_2
  aload_2
  areturn
  nop
.end <method>

.method public c(Landroid/content/Context;)LMobWin/UserLocation;
.limit locals 19
.limit stack 200
  nop
  invokestatic com/tencent/mobwin/core/a/d/a()I
  istore_3
  new java/lang/NoClassDefFoundError
  dup
  invokespecial java/lang/NoClassDefFoundError/<init>()V
  athrow
  iload_3
  ifne Label0
  new MobWin/UserLocation
  astore 4
  aload 4
  invokespecial MobWin/UserLocation/<init>()V
  aload_1
  astore_2
  aload_2
  invokestatic com/tencent/mobwin/core/a/f/e(Landroid/content/Context;)V
  new MobWin/GPS
  astore 5
  aload 5
  invokespecial MobWin/GPS/<init>()V
  iconst_0
  istore 6
  aload 5
  iload 6
  invokevirtual MobWin/GPS/setEType(I)V
  getstatic com/tencent/mobwin/core/a/f/y I
  istore_3
  aload 5
  iload_3
  invokevirtual MobWin/GPS/setIAlt(I)V
  getstatic com/tencent/mobwin/core/a/f/x I
  istore_3
  aload 5
  iload_3
  invokevirtual MobWin/GPS/setILat(I)V
  getstatic com/tencent/mobwin/core/a/f/w I
  istore_3
  aload 5
  iload_3
  invokevirtual MobWin/GPS/setILon(I)V
  invokestatic com/tencent/mobwin/core/w/b()[B
  astore 7
  aload 5
  aload 7
  invokevirtual MobWin/GPS/setVLBSKeyData([B)V
  aload 4
  aload 5
  invokevirtual MobWin/UserLocation/setGps(LMobWin/GPS;)V
  new MobWin/Cell
  astore 8
  aload 8
  invokespecial MobWin/Cell/<init>()V
  aload_0
  astore_2
  aload_2
  getfield com/tencent/mobwin/core/a/c/a Ljava/util/Map;
  astore 9
  ldc "cid"
  astore 11
  aload 9
  aload 11
  invokeinterface java/util/Map/get(Ljava/lang/Object;)Ljava/lang/Object; 2
  astore 10
  aload 10
  astore 13
  aload 13
  checkcast java/lang/String
  astore 13
  aload 13
  astore 12
  iconst_m1
  istore 6
  aload 12
  iload 6
  invokestatic com/tencent/mobwin/utils/b/a(Ljava/lang/String;I)I
  istore_3
  aload 8
  iload_3
  invokevirtual MobWin/Cell/setICellId(I)V
  aload_0
  astore_2
  aload_2
  getfield com/tencent/mobwin/core/a/c/a Ljava/util/Map;
  astore 9
  ldc "lac"
  astore 11
  aload 9
  aload 11
  invokeinterface java/util/Map/get(Ljava/lang/Object;)Ljava/lang/Object; 2
  astore 10
  aload 10
  astore 14
  aload 14
  checkcast java/lang/String
  astore 14
  aload 14
  astore 12
  iconst_m1
  istore 6
  aload 12
  iload 6
  invokestatic com/tencent/mobwin/utils/b/a(Ljava/lang/String;I)I
  istore_3
  aload 8
  iload_3
  invokevirtual MobWin/Cell/setILac(I)V
  aload_0
  astore_2
  aload_2
  getfield com/tencent/mobwin/core/a/c/a Ljava/util/Map;
  astore 9
  ldc "mcc"
  astore 11
  aload 9
  aload 11
  invokeinterface java/util/Map/get(Ljava/lang/Object;)Ljava/lang/Object; 2
  astore 10
  aload 10
  astore 15
  aload 15
  checkcast java/lang/String
  astore 15
  aload 15
  astore 12
  iconst_m1
  istore 6
  aload 12
  iload 6
  invokestatic com/tencent/mobwin/utils/b/a(Ljava/lang/String;S)S
  istore 16
  aload 8
  iload 16
  invokevirtual MobWin/Cell/setShMcc(S)V
  aload_0
  astore_2
  aload_2
  getfield com/tencent/mobwin/core/a/c/a Ljava/util/Map;
  astore 9
  ldc "mnc"
  astore 11
  aload 9
  aload 11
  invokeinterface java/util/Map/get(Ljava/lang/Object;)Ljava/lang/Object; 2
  astore 10
  aload 10
  astore 17
  aload 17
  checkcast java/lang/String
  astore 17
  aload 17
  astore 12
  iconst_m1
  istore 6
  aload 12
  iload 6
  invokestatic com/tencent/mobwin/utils/b/a(Ljava/lang/String;S)S
  istore 16
  aload 8
  iload 16
  invokevirtual MobWin/Cell/setShMnc(S)V
  aload 4
  aload 8
  invokevirtual MobWin/UserLocation/setCell(LMobWin/Cell;)V
  aload 4
  areturn
Label0:
  aconst_null
  astore 18
  aload 18
  areturn
  nop
.end <method>

