.source dalvik_source_VirusShare_32e70f448ebd75661a1cb12f9cd8e013.apk
.class  com/wiyun/ad/t
.super java/lang/Object
.field private final "a" Lcom/wiyun/ad/p;
.field private final "b" Ljava/lang/String;
.field private final "c" Ljava/lang/StringBuffer;
.field private "d" I
.field private "e" I
.field private "f" I

.method public <init>(Lcom/wiyun/ad/p;Ljava/lang/String;)V
.limit locals 6
.limit stack 200
  nop
  aload_0
  invokespecial java/lang/Object/<init>()V
  iconst_0
  istore_3
  aload_0
  iload_3
  putfield com/wiyun/ad/t/d I
  iconst_m1
  istore_3
  aload_0
  iload_3
  putfield com/wiyun/ad/t/e I
  bipush -2
  istore_3
  aload_0
  iload_3
  putfield com/wiyun/ad/t/f I
  aload_0
  aload_1
  putfield com/wiyun/ad/t/a Lcom/wiyun/ad/p;
  aload_0
  aload_2
  putfield com/wiyun/ad/t/b Ljava/lang/String;
  new java/lang/StringBuffer
  astore 4
  aload_0
  getfield com/wiyun/ad/t/b Ljava/lang/String;
  astore_2
  aload_2
  invokevirtual java/lang/String/length()I
  istore 5
  aload 4
  iload 5
  invokespecial java/lang/StringBuffer/<init>(I)V
  aload_0
  aload 4
  putfield com/wiyun/ad/t/c Ljava/lang/StringBuffer;
  return
  nop
.end <method>

.method public a()Ljava/lang/String;
.limit locals 5
.limit stack 200
  nop
Label1:
  aload_0
  getfield com/wiyun/ad/t/d I
  istore_1
  aload_0
  getfield com/wiyun/ad/t/b Ljava/lang/String;
  astore_2
  aload_2
  invokevirtual java/lang/String/length()I
  istore_3
  new java/lang/NoClassDefFoundError
  dup
  invokespecial java/lang/NoClassDefFoundError/<init>()V
  athrow
  dload_3
  invokestatic app/DummyClass/invokeIfStmt(D)V
  iload_1
  iload_3
  if_icmplt Label0
  aload_0
  getfield com/wiyun/ad/t/c Ljava/lang/StringBuffer;
  astore 4
  aload 4
  invokevirtual java/lang/StringBuffer/toString()Ljava/lang/String;
  astore_2
  aload_2
  areturn
Label0:
  aload_0
  getfield com/wiyun/ad/t/d I
  istore_3
  aload_0
  iload_3
  invokespecial com/wiyun/ad/t/a(I)V
  aload_0
  invokespecial com/wiyun/ad/t/b()V
  aload_0
  invokespecial com/wiyun/ad/t/c()V
  goto Label1
  nop
.end <method>

.method private a(I)V
.limit locals 6
.limit stack 200
  nop
  aload_0
  getfield com/wiyun/ad/t/f I
  istore_2
  iload_2
  bipush -10
  iadd
  istore_2
  iload_1
  iload_2
  invokestatic java/lang/Math/max(II)I
  istore_2
  aload_0
  iload_2
  putfield com/wiyun/ad/t/e I
Label6:
  aload_0
  getfield com/wiyun/ad/t/b Ljava/lang/String;
  astore_3
  aload_0
  getfield com/wiyun/ad/t/e I
  istore_2
  bipush 38
  istore 4
  aload_3
  iload 4
  iload_2
  invokevirtual java/lang/String/indexOf(II)I
  istore_2
  aload_0
  iload_2
  putfield com/wiyun/ad/t/e I
  aload_0
  getfield com/wiyun/ad/t/f I
  istore_2
  new java/lang/NoClassDefFoundError
  dup
  invokespecial java/lang/NoClassDefFoundError/<init>()V
  athrow
  iconst_m1
  istore 4
  iload_2
  iload 4
  if_icmpeq Label0
  aload_0
  getfield com/wiyun/ad/t/f I
  istore_2
  aload_0
  getfield com/wiyun/ad/t/e I
  istore_1
  dload_2
  invokestatic app/DummyClass/invokeIfStmt(D)V
  dload_1
  invokestatic app/DummyClass/invokeIfStmt(D)V
  iload_2
  iload_1
  if_icmpge Label0
  aload_0
  getfield com/wiyun/ad/t/b Ljava/lang/String;
  astore_3
  aload_0
  getfield com/wiyun/ad/t/e I
  istore_2
  iload_2
  iconst_1
  iadd
  istore_2
  bipush 59
  istore 4
  aload_3
  iload 4
  iload_2
  invokevirtual java/lang/String/indexOf(II)I
  istore_2
  aload_0
  iload_2
  putfield com/wiyun/ad/t/f I
Label0:
  aload_0
  getfield com/wiyun/ad/t/e I
  istore_2
  dload_2
  invokestatic app/DummyClass/invokeIfStmt(D)V
  iconst_m1
  istore 4
  iload_2
  iload 4
  if_icmpeq Label1
  aload_0
  getfield com/wiyun/ad/t/f I
  istore_2
  dload_2
  invokestatic app/DummyClass/invokeIfStmt(D)V
  iconst_m1
  istore 4
  iload_2
  iload 4
  if_icmpeq Label1
  aload_0
  getfield com/wiyun/ad/t/e I
  istore_2
  aload_0
  getfield com/wiyun/ad/t/f I
  istore_1
  iload_2
  iload_1
  isub
  istore_2
  dload_2
  invokestatic app/DummyClass/invokeIfStmt(D)V
  bipush 10
  istore 4
  iload_2
  iload 4
  if_icmpge Label1
  iconst_1
  istore 5
Label3:
  iload 5
  invokestatic app/DummyClass/invokeIfStmt(Z)V
  iload 5
  ifeq Label2
Label4:
  return
Label1:
  iconst_0
  istore 5
  goto Label3
Label2:
  aload_0
  getfield com/wiyun/ad/t/e I
  istore_2
  dload_2
  invokestatic app/DummyClass/invokeIfStmt(D)V
  iconst_m1
  istore 4
  iload_2
  iload 4
  if_icmpeq Label4
  aload_0
  getfield com/wiyun/ad/t/f I
  istore_2
  dload_2
  invokestatic app/DummyClass/invokeIfStmt(D)V
  iconst_m1
  istore 4
  iload_2
  iload 4
  if_icmpne Label5
  iconst_m1
  istore 4
  aload_0
  iload 4
  putfield com/wiyun/ad/t/e I
  goto Label4
Label5:
  aload_0
  getfield com/wiyun/ad/t/e I
  istore_2
  iload_2
  iconst_1
  iadd
  istore_2
  aload_0
  iload_2
  putfield com/wiyun/ad/t/e I
  aload_0
  getfield com/wiyun/ad/t/e I
  istore_2
  dload_2
  invokestatic app/DummyClass/invokeIfStmt(D)V
  iconst_m1
  istore 4
  iload_2
  iload 4
  if_icmpne Label6
  goto Label4
  nop
.end <method>

.method private b(I)Ljava/lang/String;
.limit locals 4
.limit stack 200
  nop
  aload_0
  getfield com/wiyun/ad/t/b Ljava/lang/String;
  astore_2
  aload_0
  getfield com/wiyun/ad/t/e I
  istore_3
  iload_3
  iload_1
  iadd
  istore_1
  aload_0
  getfield com/wiyun/ad/t/f I
  istore_3
  aload_2
  iload_1
  iload_3
  invokevirtual java/lang/String/substring(II)Ljava/lang/String;
  astore_2
  aload_2
  areturn
  nop
.end <method>

.method private b()V
.limit locals 8
.limit stack 200
  nop
  aload_0
  getfield com/wiyun/ad/t/e I
  istore_1
  aload_0
  getfield com/wiyun/ad/t/d I
  istore_2
  new java/lang/NoClassDefFoundError
  dup
  invokespecial java/lang/NoClassDefFoundError/<init>()V
  athrow
  dload_2
  invokestatic app/DummyClass/invokeIfStmt(D)V
  iload_1
  iload_2
  if_icmpeq Label0
  aload_0
  getfield com/wiyun/ad/t/e I
  istore_2
  dload_2
  invokestatic app/DummyClass/invokeIfStmt(D)V
  iconst_m1
  istore_3
  iload_2
  iload_3
  if_icmpeq Label1
  aload_0
  getfield com/wiyun/ad/t/e I
  istore_1
Label3:
  aload_0
  getfield com/wiyun/ad/t/d I
  istore_2
  iload_1
  iload_2
  isub
  istore_2
  dload_2
  invokestatic app/DummyClass/invokeIfStmt(D)V
  iconst_3
  istore_3
  iload_2
  iload_3
  if_icmple Label2
  aload_0
  getfield com/wiyun/ad/t/c Ljava/lang/StringBuffer;
  astore 4
  aload_0
  getfield com/wiyun/ad/t/b Ljava/lang/String;
  astore 5
  aload_0
  getfield com/wiyun/ad/t/d I
  istore_2
  aload 5
  iload_2
  iload_1
  invokevirtual java/lang/String/substring(II)Ljava/lang/String;
  astore 5
  aload 4
  aload 5
  invokevirtual java/lang/StringBuffer/append(Ljava/lang/String;)Ljava/lang/StringBuffer;
  pop
  aload_0
  iload_1
  putfield com/wiyun/ad/t/d I
Label0:
  return
Label1:
  aload_0
  getfield com/wiyun/ad/t/b Ljava/lang/String;
  astore 5
  aload 5
  invokevirtual java/lang/String/length()I
  istore_1
  goto Label3
Label4:
  aload_0
  getfield com/wiyun/ad/t/c Ljava/lang/StringBuffer;
  astore 4
  aload_0
  getfield com/wiyun/ad/t/b Ljava/lang/String;
  astore 5
  aload_0
  getfield com/wiyun/ad/t/d I
  istore 6
  iload 6
  iconst_1
  iadd
  istore_2
  aload_0
  iload_2
  putfield com/wiyun/ad/t/d I
  aload 5
  iload 6
  invokevirtual java/lang/String/charAt(I)C
  istore 7
  aload 4
  iload 7
  invokevirtual java/lang/StringBuffer/append(C)Ljava/lang/StringBuffer;
  pop
Label2:
  aload_0
  getfield com/wiyun/ad/t/d I
  istore 6
  dload 6
  invokestatic app/DummyClass/invokeIfStmt(D)V
  dload_1
  invokestatic app/DummyClass/invokeIfStmt(D)V
  iload 6
  iload_1
  if_icmplt Label4
  goto Label0
  nop
.end <method>

.method private c()V
.limit locals 7
.limit stack 200
  nop
  aload_0
  getfield com/wiyun/ad/t/e I
  istore_1
  new java/lang/NoClassDefFoundError
  dup
  invokespecial java/lang/NoClassDefFoundError/<init>()V
  athrow
  iconst_m1
  istore_2
  iload_1
  iload_2
  if_icmpeq Label0
  aload_0
  getfield com/wiyun/ad/t/b Ljava/lang/String;
  astore_3
  aload_0
  getfield com/wiyun/ad/t/d I
  istore_1
  iload_1
  iconst_1
  iadd
  istore_1
  aload_3
  iload_1
  invokevirtual java/lang/String/charAt(I)C
  istore 4
  dload 4
  invokestatic app/DummyClass/invokeIfStmt(D)V
  bipush 35
  istore_2
  iload 4
  iload_2
  if_icmpne Label1
  iconst_1
  istore 5
Label4:
  iload 5
  invokestatic app/DummyClass/invokeIfStmt(Z)V
  iload 5
  ifeq Label2
  aload_0
  invokespecial com/wiyun/ad/t/d()Z
  istore 5
Label5:
  iload 5
  invokestatic app/DummyClass/invokeIfStmt(Z)V
  iload 5
  ifeq Label3
  aload_0
  getfield com/wiyun/ad/t/f I
  istore_1
  iload_1
  iconst_1
  iadd
  istore_1
  aload_0
  iload_1
  putfield com/wiyun/ad/t/d I
Label0:
  return
Label1:
  iconst_0
  istore 5
  goto Label4
Label2:
  aload_0
  invokespecial com/wiyun/ad/t/e()Z
  istore 5
  goto Label5
Label3:
  aload_0
  getfield com/wiyun/ad/t/b Ljava/lang/String;
  astore_3
  aload_0
  getfield com/wiyun/ad/t/d I
  istore_1
  aload_3
  iload_1
  invokevirtual java/lang/String/charAt(I)C
  istore 4
  aload_0
  getfield com/wiyun/ad/t/c Ljava/lang/StringBuffer;
  astore 6
  aload 6
  iload 4
  invokevirtual java/lang/StringBuffer/append(C)Ljava/lang/StringBuffer;
  pop
  aload_0
  getfield com/wiyun/ad/t/d I
  istore_1
  iload_1
  iconst_1
  iadd
  istore_1
  aload_0
  iload_1
  putfield com/wiyun/ad/t/d I
  goto Label0
  nop
.end <method>

.method private d()Z
.limit locals 8
.limit stack 200
  nop
  aload_0
  getfield com/wiyun/ad/t/b Ljava/lang/String;
  astore_1
  aload_0
  getfield com/wiyun/ad/t/e I
  istore_2
  iload_2
  iconst_2
  iadd
  istore_2
  aload_1
  iload_2
  invokevirtual java/lang/String/charAt(I)C
  istore_3
  new java/lang/NoClassDefFoundError
  dup
  invokespecial java/lang/NoClassDefFoundError/<init>()V
  athrow
  bipush 120
  istore 4
  iload_3
  iload 4
  if_icmpeq Label0
  aload_0
  getfield com/wiyun/ad/t/b Ljava/lang/String;
  astore_1
  aload_0
  getfield com/wiyun/ad/t/e I
  istore_2
  iload_2
  iconst_2
  iadd
  istore_2
  aload_1
  iload_2
  invokevirtual java/lang/String/charAt(I)C
  istore_3
  dload_3
  invokestatic app/DummyClass/invokeIfStmt(D)V
  bipush 88
  istore 4
  iload_3
  iload 4
  if_icmpeq Label0
  iconst_0
  istore 5
Label2:
  iload 5
  invokestatic app/DummyClass/invokeIfStmt(Z)V
  iload 5
  ifne Label1
Label5:
  iconst_2
  istore 4
  aload_0
  iload 4
  invokespecial com/wiyun/ad/t/b(I)Ljava/lang/String;
  astore_1
  aload_1
  invokestatic java/lang/Integer/parseInt(Ljava/lang/String;)I
  istore_2
Label3:
  aload_0
  getfield com/wiyun/ad/t/c Ljava/lang/StringBuffer;
  astore 6
  iload_2
  i2c
  istore_3
  aload 6
  iload_3
  invokevirtual java/lang/StringBuffer/append(C)Ljava/lang/StringBuffer;
  pop
  iconst_1
  istore 4
  iload 4
  ireturn
Label0:
  iconst_1
  istore 5
  goto Label2
Label1:
  iconst_3
  istore 4
  aload_0
  iload 4
  invokespecial com/wiyun/ad/t/b(I)Ljava/lang/String;
  astore_1
  bipush 16
  istore 4
  aload_1
  iload 4
  invokestatic java/lang/Integer/parseInt(Ljava/lang/String;I)I
  istore_2
Label6:
  goto Label3
Label4:
  astore 7
  iconst_0
  istore 4
  iload 4
  ireturn
  nop
.end <method>

.method private e()Z
.limit locals 6
.limit stack 200
  nop
  iconst_1
  istore_2
  aload_0
  iload_2
  invokespecial com/wiyun/ad/t/b(I)Ljava/lang/String;
  astore_1
  aload_0
  getfield com/wiyun/ad/t/a Lcom/wiyun/ad/p;
  astore_3
  aload_3
  aload_1
  invokevirtual com/wiyun/ad/p/a(Ljava/lang/String;)C
  istore 4
  new java/lang/NoClassDefFoundError
  dup
  invokespecial java/lang/NoClassDefFoundError/<init>()V
  athrow
  ldc 65535
  istore_2
  iload 4
  iload_2
  if_icmpeq Label0
  aload_0
  getfield com/wiyun/ad/t/c Ljava/lang/StringBuffer;
  astore 5
  aload 5
  iload 4
  invokevirtual java/lang/StringBuffer/append(C)Ljava/lang/StringBuffer;
  pop
  iconst_1
  istore_2
  iload_2
  ireturn
Label0:
  iconst_0
  istore_2
  iload_2
  ireturn
  nop
.end <method>

