.source dalvik_source_VirusShare_32e70f448ebd75661a1cb12f9cd8e013.apk
.class public  com/wiyun/ad/n
.super java/lang/Object
.field static "a" Ljava/util/Random;
.field static "b" [[I

.method static <clinit>()V
.limit locals 5
.limit stack 200
  nop
  new java/util/Random
  astore_0
  aload_0
  invokespecial java/util/Random/<init>()V
  aload_0
  putstatic com/wiyun/ad/n/a Ljava/util/Random;
  bipush 8
  istore_2
  iload_2
  anewarray [I
  astore_1
  bipush 6
  istore_2
  iload_2
  newarray int
  astore_3
  iconst_0
  istore_2
  iconst_2
  istore 4
  aload_3
  iload_2
  iload 4
  iastore
  iconst_1
  istore_2
  iconst_3
  istore 4
  aload_3
  iload_2
  iload 4
  iastore
  iconst_2
  istore_2
  iconst_5
  istore 4
  aload_3
  iload_2
  iload 4
  iastore
  iconst_3
  istore_2
  iconst_4
  istore 4
  aload_3
  iload_2
  iload 4
  iastore
  iconst_4
  istore_2
  iconst_1
  istore 4
  aload_3
  iload_2
  iload 4
  iastore
  iconst_0
  istore_2
  aload_1
  iload_2
  aload_3
  aastore
  bipush 6
  istore_2
  iload_2
  newarray int
  astore_3
  iconst_0
  istore_2
  iconst_3
  istore 4
  aload_3
  iload_2
  iload 4
  iastore
  iconst_1
  istore_2
  iconst_4
  istore 4
  aload_3
  iload_2
  iload 4
  iastore
  iconst_2
  istore_2
  iconst_5
  istore 4
  aload_3
  iload_2
  iload 4
  iastore
  iconst_3
  istore_2
  iconst_1
  istore 4
  aload_3
  iload_2
  iload 4
  iastore
  iconst_5
  istore_2
  iconst_2
  istore 4
  aload_3
  iload_2
  iload 4
  iastore
  iconst_1
  istore_2
  aload_1
  iload_2
  aload_3
  aastore
  bipush 6
  istore_2
  iload_2
  newarray int
  astore_3
  iconst_1
  istore_2
  iconst_5
  istore 4
  aload_3
  iload_2
  iload 4
  iastore
  iconst_2
  istore_2
  iconst_2
  istore 4
  aload_3
  iload_2
  iload 4
  iastore
  iconst_3
  istore_2
  iconst_1
  istore 4
  aload_3
  iload_2
  iload 4
  iastore
  iconst_4
  istore_2
  iconst_3
  istore 4
  aload_3
  iload_2
  iload 4
  iastore
  iconst_5
  istore_2
  iconst_4
  istore 4
  aload_3
  iload_2
  iload 4
  iastore
  iconst_2
  istore_2
  aload_1
  iload_2
  aload_3
  aastore
  bipush 6
  istore_2
  iload_2
  newarray int
  astore_3
  iconst_0
  istore_2
  iconst_5
  istore 4
  aload_3
  iload_2
  iload 4
  iastore
  iconst_1
  istore_2
  iconst_4
  istore 4
  aload_3
  iload_2
  iload 4
  iastore
  iconst_2
  istore_2
  iconst_3
  istore 4
  aload_3
  iload_2
  iload 4
  iastore
  iconst_3
  istore_2
  iconst_2
  istore 4
  aload_3
  iload_2
  iload 4
  iastore
  iconst_5
  istore_2
  iconst_1
  istore 4
  aload_3
  iload_2
  iload 4
  iastore
  iconst_3
  istore_2
  aload_1
  iload_2
  aload_3
  aastore
  bipush 6
  istore_2
  iload_2
  newarray int
  astore_3
  iconst_0
  istore_2
  iconst_5
  istore 4
  aload_3
  iload_2
  iload 4
  iastore
  iconst_1
  istore_2
  iconst_3
  istore 4
  aload_3
  iload_2
  iload 4
  iastore
  iconst_2
  istore_2
  iconst_1
  istore 4
  aload_3
  iload_2
  iload 4
  iastore
  iconst_3
  istore_2
  iconst_4
  istore 4
  aload_3
  iload_2
  iload 4
  iastore
  iconst_5
  istore_2
  iconst_2
  istore 4
  aload_3
  iload_2
  iload 4
  iastore
  iconst_4
  istore_2
  aload_1
  iload_2
  aload_3
  aastore
  bipush 6
  istore_2
  iload_2
  newarray int
  astore_3
  iconst_0
  istore_2
  iconst_2
  istore 4
  aload_3
  iload_2
  iload 4
  iastore
  iconst_1
  istore_2
  iconst_4
  istore 4
  aload_3
  iload_2
  iload 4
  iastore
  iconst_3
  istore_2
  iconst_3
  istore 4
  aload_3
  iload_2
  iload 4
  iastore
  iconst_4
  istore_2
  iconst_5
  istore 4
  aload_3
  iload_2
  iload 4
  iastore
  iconst_5
  istore_2
  iconst_1
  istore 4
  aload_3
  iload_2
  iload 4
  iastore
  iconst_5
  istore_2
  aload_1
  iload_2
  aload_3
  aastore
  bipush 6
  istore_2
  iload_2
  newarray int
  astore_3
  iconst_0
  istore_2
  iconst_4
  istore 4
  aload_3
  iload_2
  iload 4
  iastore
  iconst_1
  istore_2
  iconst_2
  istore 4
  aload_3
  iload_2
  iload 4
  iastore
  iconst_3
  istore_2
  iconst_3
  istore 4
  aload_3
  iload_2
  iload 4
  iastore
  iconst_4
  istore_2
  iconst_1
  istore 4
  aload_3
  iload_2
  iload 4
  iastore
  iconst_5
  istore_2
  iconst_5
  istore 4
  aload_3
  iload_2
  iload 4
  iastore
  bipush 6
  istore_2
  aload_1
  iload_2
  aload_3
  aastore
  bipush 6
  istore_2
  iload_2
  newarray int
  astore_3
  iconst_0
  istore_2
  iconst_4
  istore 4
  aload_3
  iload_2
  iload 4
  iastore
  iconst_2
  istore_2
  iconst_2
  istore 4
  aload_3
  iload_2
  iload 4
  iastore
  iconst_3
  istore_2
  iconst_5
  istore 4
  aload_3
  iload_2
  iload 4
  iastore
  iconst_4
  istore_2
  iconst_1
  istore 4
  aload_3
  iload_2
  iload 4
  iastore
  iconst_5
  istore_2
  iconst_3
  istore 4
  aload_3
  iload_2
  iload 4
  iastore
  bipush 7
  istore_2
  aload_1
  iload_2
  aload_3
  aastore
  aload_1
  putstatic com/wiyun/ad/n/b [[I
  return
  nop
.end <method>

.method public <init>()V
.limit locals 1
.limit stack 200
  nop
  aload_0
  invokespecial java/lang/Object/<init>()V
  return
  nop
.end <method>

.method static a(Ljava/lang/String;)Ljava/lang/String;
.limit locals 14
.limit stack 200
  nop
  new java/lang/NoClassDefFoundError
  dup
  invokespecial java/lang/NoClassDefFoundError/<init>()V
  athrow
  iload_0
  ifeq Label0
  aload_0
  invokevirtual java/lang/String/length()I
  istore_1
  dload_1
  invokestatic app/DummyClass/invokeIfStmt(D)V
  bipush 10
  istore_2
  iload_1
  iload_2
  if_icmpge Label1
Label0:
  aconst_null
  astore_3
  aload_3
  areturn
Label1:
  iconst_0
  istore_2
  iconst_2
  istore 5
  aload_0
  iload_2
  iload 5
  invokevirtual java/lang/String/substring(II)Ljava/lang/String;
  astore 4
  bipush 16
  istore_2
  aload 4
  iload_2
  invokestatic java/lang/Integer/parseInt(Ljava/lang/String;I)I
  istore 6
  iconst_0
  istore_2
  bipush 8
  istore 5
  aload_0
  iload_2
  iload 5
  invokevirtual java/lang/String/substring(II)Ljava/lang/String;
  astore 4
  aload_0
  invokevirtual java/lang/String/length()I
  istore_1
  iload_1
  bipush -2
  iadd
  istore_1
  aload_0
  iload_1
  invokevirtual java/lang/String/substring(I)Ljava/lang/String;
  astore 7
  bipush 16
  istore_2
  aload 7
  iload_2
  invokestatic java/lang/Integer/parseInt(Ljava/lang/String;I)I
  istore 8
  aload_0
  invokevirtual java/lang/String/length()I
  istore_1
  iload_1
  bipush -8
  iadd
  istore 9
  aload_0
  invokevirtual java/lang/String/length()I
  istore_1
  iload_1
  bipush -2
  iadd
  istore_1
  aload_0
  iload 9
  iload_1
  invokevirtual java/lang/String/substring(II)Ljava/lang/String;
  astore 7
  bipush 16
  istore_2
  aload 7
  iload_2
  invokestatic java/lang/Integer/parseInt(Ljava/lang/String;I)I
  istore 9
  iload 9
  iload 8
  ixor
  istore 9
  iconst_1
  istore_2
  iload_2
  anewarray java/lang/Object
  astore 10
  iload 9
  invokestatic java/lang/Integer/valueOf(I)Ljava/lang/Integer;
  astore 11
  iconst_0
  istore_2
  aload 10
  iload_2
  aload 11
  aastore
  ldc "%06x"
  astore 12
  aload 12
  aload 10
  invokestatic java/lang/String/format(Ljava/lang/String;[Ljava/lang/Object;)Ljava/lang/String;
  astore 7
  aload 4
  invokestatic com/wiyun/ad/ae/c(Ljava/lang/String;)Ljava/lang/String;
  astore_0
  aload 7
  aload 4
  aload_0
  invokestatic com/wiyun/ad/n/a(Ljava/lang/String;Ljava/lang/String;Ljava/lang/String;)Ljava/lang/String;
  astore 7
  bipush 16
  istore_2
  aload 7
  iload_2
  invokestatic java/lang/Integer/parseInt(Ljava/lang/String;I)I
  istore 9
  iload 9
  sipush 997
  imul
  istore_1
  iload_1
  iload 6
  irem
  istore 6
  dload 6
  invokestatic app/DummyClass/invokeIfStmt(D)V
  dload 8
  invokestatic app/DummyClass/invokeIfStmt(D)V
  iload 6
  iload 8
  if_icmpne Label0
  iload 9
  invokestatic java/lang/String/valueOf(I)Ljava/lang/String;
  astore 7
Label3:
  aload 7
  areturn
Label2:
  astore 13
  aconst_null
  astore_3
  aload_3
  areturn
  nop
.end <method>

.method private static a(Ljava/lang/String;I)Ljava/lang/String;
.limit locals 12
.limit stack 200
  nop
  iconst_0
  istore_2
  new java/lang/String
  astore_3
  aload_3
  invokespecial java/lang/String/<init>()V
  iload_1
  bipush 8
  irem
  istore 4
  aload_0
  invokevirtual java/lang/String/toCharArray()[C
  astore 5
  iconst_0
  istore_1
Label2:
  new java/lang/NoClassDefFoundError
  dup
  invokespecial java/lang/NoClassDefFoundError/<init>()V
  athrow
  bipush 6
  istore 6
  iload_1
  iload 6
  if_icmplt Label0
Label3:
  dload_2
  invokestatic app/DummyClass/invokeIfStmt(D)V
  bipush 6
  istore 6
  iload_2
  iload 6
  if_icmplt Label1
  aload_3
  areturn
Label0:
  getstatic com/wiyun/ad/n/b [[I
  astore 7
  aload 7
  iload 4
  aaload
  astore 8
  aload 8
  iload_1
  iaload
  istore 9
  aload_0
  iload_1
  invokevirtual java/lang/String/charAt(I)C
  istore 10
  aload 5
  iload 9
  iload 10
  castore
  iload_1
  iconst_1
  iadd
  istore_1
  goto Label2
Label1:
  new java/lang/StringBuilder
  astore 11
  aload_3
  invokestatic java/lang/String/valueOf(Ljava/lang/Object;)Ljava/lang/String;
  astore_3
  aload 11
  aload_3
  invokespecial java/lang/StringBuilder/<init>(Ljava/lang/String;)V
  aload 5
  iload_2
  caload
  istore 10
  aload 11
  iload 10
  invokevirtual java/lang/StringBuilder/append(C)Ljava/lang/StringBuilder;
  astore 11
  aload 11
  invokevirtual java/lang/StringBuilder/toString()Ljava/lang/String;
  astore_3
  iload_2
  iconst_1
  iadd
  istore_2
  goto Label3
  nop
.end <method>

.method private static a(Ljava/lang/String;II)Ljava/lang/String;
.limit locals 7
.limit stack 200
  nop
  aload_0
  invokevirtual java/lang/String/length()I
  istore_3
  iload_2
  iload_3
  irem
  istore_3
  new java/lang/NoClassDefFoundError
  dup
  invokespecial java/lang/NoClassDefFoundError/<init>()V
  athrow
  iload_3
  ifgt Label0
  aload_0
  areturn
Label0:
  dload_1
  invokestatic app/DummyClass/invokeIfStmt(D)V
  iload_1
  lookupswitch
  -1 : Label2
  0 : Label3
  1 : Label4
  default : Label1
Label1:
  goto Label3
Label3:
  aload_0
  areturn
Label2:
  iload_3
  iconst_1
  iadd
  istore_1
  new java/lang/StringBuilder
  astore 4
  iload_1
  iconst_m1
  iadd
  istore_3
  aload_0
  invokevirtual java/lang/String/length()I
  istore_2
  aload_0
  iload_3
  iload_2
  invokevirtual java/lang/String/substring(II)Ljava/lang/String;
  astore 5
  aload 5
  invokestatic java/lang/String/valueOf(Ljava/lang/Object;)Ljava/lang/String;
  astore 5
  aload 4
  aload 5
  invokespecial java/lang/StringBuilder/<init>(Ljava/lang/String;)V
  iload_1
  iconst_m1
  iadd
  istore_3
  iconst_0
  istore 6
  aload_0
  iload 6
  iload_3
  invokevirtual java/lang/String/substring(II)Ljava/lang/String;
  astore 5
  aload 4
  aload 5
  invokevirtual java/lang/StringBuilder/append(Ljava/lang/String;)Ljava/lang/StringBuilder;
  astore 4
  aload 4
  invokevirtual java/lang/StringBuilder/toString()Ljava/lang/String;
  astore 5
  aload 5
  areturn
Label4:
  new java/lang/StringBuilder
  astore 4
  aload_0
  invokevirtual java/lang/String/length()I
  istore_2
  iload_2
  iload_3
  isub
  istore_2
  aload_0
  invokevirtual java/lang/String/length()I
  istore_1
  aload_0
  iload_2
  iload_1
  invokevirtual java/lang/String/substring(II)Ljava/lang/String;
  astore 5
  aload 5
  invokestatic java/lang/String/valueOf(Ljava/lang/Object;)Ljava/lang/String;
  astore 5
  aload 4
  aload 5
  invokespecial java/lang/StringBuilder/<init>(Ljava/lang/String;)V
  aload_0
  invokevirtual java/lang/String/length()I
  istore_2
  iload_2
  iload_3
  isub
  istore_3
  iconst_0
  istore 6
  aload_0
  iload 6
  iload_3
  invokevirtual java/lang/String/substring(II)Ljava/lang/String;
  astore 5
  aload 4
  aload 5
  invokevirtual java/lang/StringBuilder/append(Ljava/lang/String;)Ljava/lang/StringBuilder;
  astore 4
  aload 4
  invokevirtual java/lang/StringBuilder/toString()Ljava/lang/String;
  astore 5
  aload 5
  areturn
  nop
  nop
  nop
.end <method>

.method private static a(Ljava/lang/String;Ljava/lang/String;)Ljava/lang/String;
.limit locals 21
.limit stack 200
  nop
  aload_0
  astore_2
  aload_2
  invokestatic com/wiyun/ad/ae/c(Ljava/lang/String;)Ljava/lang/String;
  astore_0
  iconst_0
  istore 4
  bipush 8
  istore 5
  aload_0
  astore_2
  aload_2
  iload 4
  iload 5
  invokevirtual java/lang/String/substring(II)Ljava/lang/String;
  astore_0
  bipush 16
  istore 4
  aload_0
  astore_2
  aload_2
  iload 4
  invokestatic java/lang/Long/parseLong(Ljava/lang/String;I)J
  lstore 6
  lload 6
  invokestatic java/lang/Math/abs(J)J
  lstore 8
  aload_1
  astore_2
  aload_2
  invokestatic com/wiyun/ad/ae/c(Ljava/lang/String;)Ljava/lang/String;
  astore_1
  iconst_0
  istore 4
  bipush 8
  istore 5
  aload_1
  astore_2
  aload_2
  iload 4
  iload 5
  invokevirtual java/lang/String/substring(II)Ljava/lang/String;
  astore_1
  bipush 16
  istore 4
  aload_1
  astore_2
  aload_2
  iload 4
  invokestatic java/lang/Long/parseLong(Ljava/lang/String;I)J
  lstore 6
  lload 6
  invokestatic java/lang/Math/abs(J)J
  lstore 6
  lload 8
  lload 6
  lxor
  lstore 10
  iconst_1
  istore 4
  iload 4
  anewarray java/lang/Object
  astore 12
  lload 8
  invokestatic java/lang/Long/valueOf(J)Ljava/lang/Long;
  astore 13
  iconst_0
  istore 4
  aload 12
  iload 4
  aload 13
  aastore
  ldc "%010d"
  astore 14
  aload 14
  aload 12
  invokestatic java/lang/String/format(Ljava/lang/String;[Ljava/lang/Object;)Ljava/lang/String;
  astore_1
  iconst_1
  istore 4
  iload 4
  anewarray java/lang/Object
  astore 12
  lload 6
  invokestatic java/lang/Long/valueOf(J)Ljava/lang/Long;
  astore 13
  iconst_0
  istore 4
  aload 12
  iload 4
  aload 13
  aastore
  ldc "%010d"
  astore 14
  aload 14
  aload 12
  invokestatic java/lang/String/format(Ljava/lang/String;[Ljava/lang/Object;)Ljava/lang/String;
  astore_0
  new java/lang/StringBuilder
  astore 15
  aload_1
  astore_2
  aload_2
  invokestatic java/lang/String/valueOf(Ljava/lang/Object;)Ljava/lang/String;
  astore_1
  aload_1
  astore_2
  aload 15
  aload_2
  invokespecial java/lang/StringBuilder/<init>(Ljava/lang/String;)V
  aload_0
  astore_2
  aload 15
  aload_2
  invokevirtual java/lang/StringBuilder/append(Ljava/lang/String;)Ljava/lang/StringBuilder;
  astore 15
  aload 15
  invokevirtual java/lang/StringBuilder/toString()Ljava/lang/String;
  astore_1
  aload_1
  astore_2
  aload_2
  invokestatic com/wiyun/ad/ae/c(Ljava/lang/String;)Ljava/lang/String;
  astore_1
  iconst_0
  istore 16
Label3:
  new java/lang/NoClassDefFoundError
  dup
  invokespecial java/lang/NoClassDefFoundError/<init>()V
  athrow
  bipush 16
  istore 4
  iload 16
  iload 4
  if_icmplt Label0
  lload 10
  invokestatic java/lang/Long/toBinaryString(J)Ljava/lang/String;
  astore_1
  aload_1
  astore_2
  aload_2
  invokevirtual java/lang/String/length()I
  istore 16
  dload 16
  invokestatic app/DummyClass/invokeIfStmt(D)V
  bipush 56
  istore 4
  iload 16
  iload 4
  if_icmple Label1
  iconst_0
  istore 4
  bipush 55
  istore 5
  aload_1
  astore_2
  aload_2
  iload 4
  iload 5
  invokevirtual java/lang/String/substring(II)Ljava/lang/String;
  pop
Label1:
  aload_1
  areturn
Label0:
  iload 16
  iconst_2
  irem
  istore 17
  dload 17
  invokestatic app/DummyClass/invokeIfStmt(D)V
  iload 17
  ifne Label2
  aload_1
  astore_2
  aload_2
  iload 16
  invokevirtual java/lang/String/charAt(I)C
  istore 18
  iload 18
  istore_2
  iload_2
  i2l
  lstore 8
  lload 10
  lload 8
  lxor
  lstore 10
  iconst_2
  istore 4
  lload 10
  iload 4
  lshl
  lstore 10
  lload 10
  lload 6
  lxor
  lstore 10
  ldc2_w 1000000000
  lstore 19
  lload 19
  lstore_2
  lload 10
  lload_2
  lrem
  lstore 10
  lload 10
  invokestatic java/lang/Math/abs(J)J
  lstore 10
Label4:
  iload 16
  iconst_1
  iadd
  istore 16
  goto Label3
Label2:
  aload_1
  astore_2
  aload_2
  iload 16
  invokevirtual java/lang/String/charAt(I)C
  istore 18
  iload 18
  istore_2
  iload_2
  i2l
  lstore 8
  lload 10
  lload 8
  lxor
  lstore 10
  goto Label4
  nop
.end <method>

.method private static a(Ljava/lang/String;Ljava/lang/String;Ljava/lang/String;)Ljava/lang/String;
.limit locals 21
.limit stack 200
  nop
  aload_0
  astore_3
  aload_3
  invokevirtual java/lang/String/length()I
  istore 5
  iload 5
  iconst_2
  idiv
  istore 5
  aload_0
  astore_3
  aload_3
  invokevirtual java/lang/String/length()I
  istore 6
  aload_1
  astore_3
  aload_2
  astore 4
  aload_3
  aload 4
  invokestatic com/wiyun/ad/n/a(Ljava/lang/String;Ljava/lang/String;)Ljava/lang/String;
  astore_2
  bipush 15
  istore 7
  iconst_1
  istore 8
  bipush 15
  istore 9
  aload_2
  astore_3
  aload_3
  iload 8
  iload 9
  invokestatic com/wiyun/ad/n/a(Ljava/lang/String;II)Ljava/lang/String;
  astore_2
Label1:
  new java/lang/NoClassDefFoundError
  dup
  invokespecial java/lang/NoClassDefFoundError/<init>()V
  athrow
  iload 7
  ifge Label0
  aload_0
  areturn
Label0:
  iconst_0
  istore 8
  aload_0
  astore_3
  aload_3
  iload 8
  iload 5
  invokevirtual java/lang/String/substring(II)Ljava/lang/String;
  astore_1
  bipush 16
  istore 8
  aload_1
  astore_3
  aload_3
  iload 8
  invokestatic java/lang/Long/parseLong(Ljava/lang/String;I)J
  lstore 10
  lload 10
  l2i
  istore 12
  aload_0
  astore_3
  aload_3
  iload 5
  iload 6
  invokevirtual java/lang/String/substring(II)Ljava/lang/String;
  astore_1
  bipush 16
  istore 8
  aload_1
  astore_3
  aload_3
  iload 8
  invokestatic java/lang/Long/parseLong(Ljava/lang/String;I)J
  lstore 10
  lload 10
  l2i
  istore 13
  iconst_0
  istore 8
  aload_2
  astore_3
  aload_3
  iload 8
  iload 5
  invokevirtual java/lang/String/substring(II)Ljava/lang/String;
  astore_1
  iconst_2
  istore 8
  aload_1
  astore_3
  aload_3
  iload 8
  invokestatic java/lang/Integer/valueOf(Ljava/lang/String;I)Ljava/lang/Integer;
  astore 14
  aload 14
  invokevirtual java/lang/Integer/intValue()I
  istore 15
  aload_2
  astore_3
  aload_3
  invokevirtual java/lang/String/length()I
  istore 16
  iload 16
  iload 5
  isub
  istore 17
  aload_2
  astore_3
  aload_3
  invokevirtual java/lang/String/length()I
  istore 16
  aload_2
  astore_3
  aload_3
  iload 17
  iload 16
  invokevirtual java/lang/String/substring(II)Ljava/lang/String;
  astore_1
  iconst_2
  istore 8
  aload_1
  astore_3
  aload_3
  iload 8
  invokestatic java/lang/Integer/valueOf(Ljava/lang/String;I)Ljava/lang/Integer;
  astore 14
  aload 14
  invokevirtual java/lang/Integer/intValue()I
  istore 17
  iconst_1
  istore 8
  iload 8
  anewarray java/lang/Object
  astore 18
  iload 12
  iload 15
  ixor
  istore 15
  iload 15
  invokestatic java/lang/Integer/valueOf(I)Ljava/lang/Integer;
  astore 14
  iconst_0
  istore 8
  aload 18
  iload 8
  aload 14
  aastore
  ldc "%03x"
  astore 19
  aload 19
  astore_3
  aload_3
  aload 18
  invokestatic java/lang/String/format(Ljava/lang/String;[Ljava/lang/Object;)Ljava/lang/String;
  astore_1
  iconst_1
  istore 8
  iload 8
  anewarray java/lang/Object
  astore 18
  iload 13
  iload 17
  ixor
  istore 17
  iload 17
  invokestatic java/lang/Integer/valueOf(I)Ljava/lang/Integer;
  astore 14
  iconst_0
  istore 8
  aload 18
  iload 8
  aload 14
  aastore
  ldc "%03x"
  astore 19
  aload 19
  astore_3
  aload_3
  aload 18
  invokestatic java/lang/String/format(Ljava/lang/String;[Ljava/lang/Object;)Ljava/lang/String;
  astore_0
  new java/lang/StringBuilder
  astore 20
  aload_1
  astore_3
  aload_3
  invokestatic java/lang/String/valueOf(Ljava/lang/Object;)Ljava/lang/String;
  astore_1
  aload 20
  astore_3
  aload_1
  astore 4
  aload_3
  aload 4
  invokespecial java/lang/StringBuilder/<init>(Ljava/lang/String;)V
  aload 20
  astore_3
  aload_0
  astore 4
  aload_3
  aload 4
  invokevirtual java/lang/StringBuilder/append(Ljava/lang/String;)Ljava/lang/StringBuilder;
  astore 20
  aload 20
  astore_3
  aload_3
  invokevirtual java/lang/StringBuilder/toString()Ljava/lang/String;
  astore_1
  iconst_m1
  istore 8
  iconst_1
  istore 9
  aload_2
  astore_3
  aload_3
  iload 8
  iload 9
  invokestatic com/wiyun/ad/n/a(Ljava/lang/String;II)Ljava/lang/String;
  astore_2
  iload 7
  iconst_1
  iadd
  istore 17
  aload_1
  astore_3
  aload_3
  iload 17
  invokestatic com/wiyun/ad/n/a(Ljava/lang/String;I)Ljava/lang/String;
  astore_0
  iload 7
  iconst_m1
  iadd
  istore 7
  goto Label1
  nop
.end <method>

