.source SourceFile
.class abstract  com/mobisage/android/N
.super java/lang/Object
.implements  java/lang/Runnable
.field protected "a" Lcom/mobisage/android/MobiSageMessage;
.field protected "b" Lorg/apache/http/client/HttpClient;

.method protected <init>(Lcom/mobisage/android/MobiSageMessage;)V
.limit locals 2
.limit stack 200
  nop
  aload_0
  invokespecial java/lang/Object/<init>()V
  aload_0
  aload_1
  putfield com/mobisage/android/N/a Lcom/mobisage/android/MobiSageMessage;
  return
  nop
.end <method>

.method public a()V
.limit locals 3
.limit stack 200
  nop
  aload_0
  getfield com/mobisage/android/N/b Lorg/apache/http/client/HttpClient;
  astore_1
  new java/lang/NoClassDefFoundError
  dup
  invokespecial java/lang/NoClassDefFoundError/<init>()V
  athrow
  iload_1
  ifeq Label0
  aload_0
  getfield com/mobisage/android/N/b Lorg/apache/http/client/HttpClient;
  astore_1
  aload_1
  invokeinterface org/apache/http/client/HttpClient/getConnectionManager()Lorg/apache/http/conn/ClientConnectionManager; 1
  astore_2
  aload_2
  invokeinterface org/apache/http/conn/ClientConnectionManager/shutdown()V 1
Label0:
  return
  nop
.end <method>

.method protected finalize()V
.limit locals 2
.limit stack 200
  nop
  aload_0
  invokespecial java/lang/Object/finalize()V
  aconst_null
  astore_1
  aload_0
  aload_1
  putfield com/mobisage/android/N/a Lcom/mobisage/android/MobiSageMessage;
  return
  nop
.end <method>

.method public run()V
.limit locals 3
.limit stack 200
  nop
  invokestatic com/mobisage/android/H/a()Lcom/mobisage/android/H;
  astore_1
  aload_0
  getfield com/mobisage/android/N/a Lcom/mobisage/android/MobiSageMessage;
  astore_2
  aload_1
  aload_2
  invokevirtual com/mobisage/android/H/c(Lcom/mobisage/android/MobiSageMessage;)V
  return
  nop
.end <method>

