.source Invoker.java
.class  com/admogo/Invoker$4
.super java/lang/Object
.implements  java/lang/Runnable
.field final "this$0" Lcom/admogo/Invoker;

.method <init>(Lcom/admogo/Invoker;)V
.limit locals 2
.limit stack 200
  nop
  aload_0
  aload_1
  putfield com/admogo/Invoker$4/this$0 Lcom/admogo/Invoker;
  aload_0
  invokespecial java/lang/Object/<init>()V
  return
  nop
.end <method>

.method public run()V
.limit locals 6
.limit stack 200
  nop
  aload_0
  getfield com/admogo/Invoker$4/this$0 Lcom/admogo/Invoker;
  astore_1
  new java/lang/NoClassDefFoundError
  dup
  invokespecial java/lang/NoClassDefFoundError/<init>()V
  athrow
  nop
  iload_2
  iconst_1
  iadd
  istore_2
  aload_1
  iload_2
  invokestatic com/admogo/Invoker/access$5(Lcom/admogo/Invoker;I)V
  getstatic com/admogo/Invoker/clickNum Landroid/widget/TextView;
  astore_3
  new java/lang/StringBuilder
  astore 4
  aload 4
  invokespecial java/lang/StringBuilder/<init>()V
  aload_0
  getfield com/admogo/Invoker$4/this$0 Lcom/admogo/Invoker;
  astore_1
  aload_1
  invokestatic com/admogo/Invoker/access$4(Lcom/admogo/Invoker;)I
  istore_2
  aload 4
  iload_2
  invokevirtual java/lang/StringBuilder/append(I)Ljava/lang/StringBuilder;
  astore 4
  aload 4
  invokevirtual java/lang/StringBuilder/toString()Ljava/lang/String;
  astore 5
  aload_3
  aload 5
  invokevirtual android/widget/TextView/setText(Ljava/lang/CharSequence;)V
  return
  nop
.end <method>

