.source AdMogoWebView.java
.class final  com/admogo/AdMogoWebView$AdViewJsObj
.super java/lang/Object
.field final "this$0" Lcom/admogo/AdMogoWebView;

.method <init>(Lcom/admogo/AdMogoWebView;)V
.limit locals 2
.limit stack 200
  nop
  aload_0
  aload_1
  putfield com/admogo/AdMogoWebView$AdViewJsObj/this$0 Lcom/admogo/AdMogoWebView;
  aload_0
  invokespecial java/lang/Object/<init>()V
  return
  nop
.end <method>

.method public setWinth(I)V
.limit locals 18
.limit stack 200
  nop
  aload_0
  astore_2
  aload_2
  getfield com/admogo/AdMogoWebView$AdViewJsObj/this$0 Lcom/admogo/AdMogoWebView;
  astore_3
  aload_2
  astore_0
  aload_0
  astore_2
  aload_2
  getfield com/admogo/AdMogoWebView$AdViewJsObj/this$0 Lcom/admogo/AdMogoWebView;
  astore 4
  new java/lang/NoClassDefFoundError
  dup
  invokespecial java/lang/NoClassDefFoundError/<init>()V
  athrow
  dload 5
  invokestatic app/DummyClass/invokeIfStmt(D)V
  iconst_m1
  istore 6
  iload 5
  iload 6
  if_icmpne Label0
  aload_0
  astore_2
  aload_2
  getfield com/admogo/AdMogoWebView$AdViewJsObj/this$0 Lcom/admogo/AdMogoWebView;
  astore 4
  aload 4
  invokevirtual com/admogo/AdMogoWebView/getWindowManager()Landroid/view/WindowManager;
  astore 7
  aload 7
  invokeinterface android/view/WindowManager/getDefaultDisplay()Landroid/view/Display; 1
  astore 8
  aload 8
  invokevirtual android/view/Display/getWidth()I
  istore 5
Label2:
  aload_3
  iload 5
  putfield com/admogo/AdMogoWebView/screenWidth I
  new android/os/Message
  astore 9
  aload 9
  invokespecial android/os/Message/<init>()V
  aload_0
  astore_2
  aload_2
  getfield com/admogo/AdMogoWebView$AdViewJsObj/this$0 Lcom/admogo/AdMogoWebView;
  astore_3
  aload_2
  astore_0
  aload_3
  getfield com/admogo/AdMogoWebView/screenWidth I
  istore 5
  iload 5
  i2f
  fstore 10
  fconst_1
  fstore 12
  fload 10
  fload 12
  fmul
  fstore 11
  iload_1
  istore_2
  iload_2
  i2f
  fstore 10
  fload 11
  fload 10
  fdiv
  fstore 11
  ldc 100.000000
  fstore 12
  fload 11
  fload 12
  fmul
  fstore 11
  fload 11
  f2i
  istore 5
  aload 9
  iload 5
  putfield android/os/Message/arg1 I
  aload_0
  astore_2
  aload_2
  getfield com/admogo/AdMogoWebView$AdViewJsObj/this$0 Lcom/admogo/AdMogoWebView;
  astore_3
  aload_2
  astore_0
  aload_3
  getfield com/admogo/AdMogoWebView/screenWidth I
  istore 5
  iload_1
  bipush -100
  iadd
  istore 13
  dload 5
  invokestatic app/DummyClass/invokeIfStmt(D)V
  dload 13
  invokestatic app/DummyClass/invokeIfStmt(D)V
  iload 5
  iload 13
  if_icmpge Label1
  getstatic java/lang/System/out Ljava/io/PrintStream;
  astore 14
  new java/lang/StringBuilder
  astore 15
  ldc "width - 100-->"
  astore 16
  aload 15
  aload 16
  invokespecial java/lang/StringBuilder/<init>(Ljava/lang/String;)V
  iload_1
  bipush -100
  iadd
  istore 13
  aload 15
  iload 13
  invokevirtual java/lang/StringBuilder/append(I)Ljava/lang/StringBuilder;
  astore 15
  aload 15
  invokevirtual java/lang/StringBuilder/toString()Ljava/lang/String;
  astore 17
  aload 14
  aload 17
  invokevirtual java/io/PrintStream/println(Ljava/lang/String;)V
Label1:
  return
Label0:
  aload_0
  astore_2
  aload_2
  getfield com/admogo/AdMogoWebView$AdViewJsObj/this$0 Lcom/admogo/AdMogoWebView;
  astore 4
  aload 4
  getfield com/admogo/AdMogoWebView/screenWidth I
  istore 5
  goto Label2
  nop
.end <method>

