.source AdMogoLayout.java
.class  com/admogo/AdMogoLayout$getAdByCountryCode
.super java/lang/Object
.implements  java/lang/Runnable
.field "activity" Landroid/content/Context;
.field "adMogoLayout" Lcom/admogo/AdMogoLayout;
.field "simCode" Ljava/lang/String;

.method public <init>(Lcom/admogo/AdMogoLayout;Landroid/content/Context;Ljava/lang/String;)V
.limit locals 4
.limit stack 200
  nop
  aload_0
  invokespecial java/lang/Object/<init>()V
  aload_0
  aload_1
  putfield com/admogo/AdMogoLayout$getAdByCountryCode/adMogoLayout Lcom/admogo/AdMogoLayout;
  aload_0
  aload_2
  putfield com/admogo/AdMogoLayout$getAdByCountryCode/activity Landroid/content/Context;
  aload_0
  aload_3
  putfield com/admogo/AdMogoLayout$getAdByCountryCode/simCode Ljava/lang/String;
  return
  nop
.end <method>

.method public run()V
.limit locals 31
.limit stack 200
  .catch  java/lang/Exception <from> Label5 <to> Label6 <using> Label4
  .catch  java/lang/Exception <from> Label7 <to> Label8 <using> Label4
  nop
Label5:
  aload_0
  astore_1
  aload_1
  getfield com/admogo/AdMogoLayout$getAdByCountryCode/activity Landroid/content/Context;
  astore 7
  ldc "location"
  astore 9
  new java/lang/NoClassDefFoundError
  dup
  invokespecial java/lang/NoClassDefFoundError/<init>()V
  athrow
  nop
  aload 8
  astore 11
  aload 11
  checkcast android/location/LocationManager
  astore 11
  aload 11
  astore 10
  ldc "gps"
  astore 9
  aload 10
  aload 9
  invokevirtual android/location/LocationManager/getLastKnownLocation(Ljava/lang/String;)Landroid/location/Location;
  astore 12
  aload 12
  invokestatic app/DummyClass/invokeIfStmt(Ljava/lang/Object;)V
  aload 12
  ifnonnull Label0
  ldc "network"
  astore 9
  aload 10
  aload 9
  invokevirtual android/location/LocationManager/getLastKnownLocation(Ljava/lang/String;)Landroid/location/Location;
  astore 12
Label0:
  aload 12
  invokestatic app/DummyClass/invokeIfStmt(Ljava/lang/Object;)V
  aload 12
  ifnull Label1
  new android/location/Geocoder
  astore 13
  aload_0
  astore_1
  aload_1
  getfield com/admogo/AdMogoLayout$getAdByCountryCode/activity Landroid/content/Context;
  astore 7
  aload 13
  aload 7
  invokespecial android/location/Geocoder/<init>(Landroid/content/Context;)V
  aload 12
  invokevirtual android/location/Location/getLatitude()D
  dstore 14
  aload 12
  invokevirtual android/location/Location/getLongitude()D
  dstore 16
  iconst_5
  istore 19
  aload 13
  astore_1
  dload 14
  dstore_2
  dload 16
  dstore 4
  iload 19
  istore 6
  aload_1
  dload_2
  dload 4
  iload 6
  invokevirtual android/location/Geocoder/getFromLocation(DDI)Ljava/util/List;
  astore 18
  aload 18
  astore_1
  aload_1
  invokestatic app/DummyClass/invokeIfStmt(Ljava/lang/Object;)V
  aload 18
  ifnull Label2
  aload 18
  astore_1
  aload_1
  invokeinterface java/util/List/size()I 1
  istore 20
  iload 20
  istore_1
  dload_1
  invokestatic app/DummyClass/invokeIfStmt(D)V
  iload 20
  ifle Label2
  iconst_0
  istore 19
  aload 18
  astore_1
  iload 19
  istore_2
  aload_1
  iload_2
  invokeinterface java/util/List/get(I)Ljava/lang/Object; 2
  astore 8
  aload 8
  astore 22
  aload 22
  checkcast android/location/Address
  astore 22
  aload 22
  astore 21
  aload 21
  astore_1
  aload_1
  invokevirtual android/location/Address/getCountryCode()Ljava/lang/String;
  astore 23
  aload 23
  astore_1
  aload_1
  invokevirtual java/lang/String/toLowerCase()Ljava/lang/String;
  astore 23
  aload 23
  astore_1
  aload_1
  invokestatic com/admogo/AdMogoLayout/access$11(Ljava/lang/String;)V
  aload_0
  astore_1
  aload_1
  getfield com/admogo/AdMogoLayout$getAdByCountryCode/adMogoLayout Lcom/admogo/AdMogoLayout;
  astore_1
  aload_1
  astore 24
  aload 24
  astore_1
  aload_1
  getfield com/admogo/AdMogoLayout/adMogoManager Lcom/admogo/AdMogoManager;
  astore_1
  aload_1
  astore 25
  aload 12
  invokevirtual android/location/Location/getLatitude()D
  dstore 16
  aload 12
  invokevirtual android/location/Location/getLongitude()D
  dstore 14
  aload 25
  astore_1
  dload 16
  dstore_2
  aload_1
  dload_2
  dload 14
  invokevirtual com/admogo/AdMogoManager/getCityName(DD)V
  invokestatic com/admogo/AdMogoLayout/access$1()Ljava/lang/String;
  astore 23
  aload_0
  astore_1
  aload_1
  getfield com/admogo/AdMogoLayout$getAdByCountryCode/simCode Ljava/lang/String;
  astore_1
  aload_1
  astore 26
  aload 23
  astore_1
  aload 26
  astore_2
  aload_1
  aload_2
  invokevirtual java/lang/String/equals(Ljava/lang/Object;)Z
  istore 27
  iload 27
  istore_1
  iload_1
  invokestatic app/DummyClass/invokeIfStmt(Z)V
  iload 27
  ifne Label3
  aload_0
  astore_1
  aload_1
  getfield com/admogo/AdMogoLayout$getAdByCountryCode/adMogoLayout Lcom/admogo/AdMogoLayout;
  astore_1
  aload_1
  astore 24
  aload 24
  astore_1
  aload_1
  getfield com/admogo/AdMogoLayout/adMogoManager Lcom/admogo/AdMogoManager;
  astore_1
  aload_1
  astore 25
  invokestatic com/admogo/AdMogoLayout/access$1()Ljava/lang/String;
  astore 26
  aload 25
  astore_1
  aload 26
  astore_2
  aload_1
  aload_2
  invokevirtual com/admogo/AdMogoManager/setLocation(Ljava/lang/String;)V
  invokestatic com/admogo/AdMogoLayout/access$1()Ljava/lang/String;
  astore 26
  aload 26
  putstatic com/admogo/AdMogoTargeting/countryCode Ljava/lang/String;
  aload_0
  astore_1
  aload_1
  getfield com/admogo/AdMogoLayout$getAdByCountryCode/adMogoLayout Lcom/admogo/AdMogoLayout;
  astore_1
  aload_1
  astore 24
  aload 24
  astore_1
  aload_1
  getfield com/admogo/AdMogoLayout/adMogoManager Lcom/admogo/AdMogoManager;
  astore_1
  aload_1
  astore 25
  aload 25
  astore_1
  aload_1
  invokevirtual com/admogo/AdMogoManager/fetchConfig()V
  aload_0
  astore_1
  aload_1
  getfield com/admogo/AdMogoLayout$getAdByCountryCode/adMogoLayout Lcom/admogo/AdMogoLayout;
  astore_1
  aload_1
  astore 24
  aload_0
  astore_1
  aload_1
  getfield com/admogo/AdMogoLayout$getAdByCountryCode/adMogoLayout Lcom/admogo/AdMogoLayout;
  astore_1
  aload_1
  astore 28
  aload 28
  astore_1
  aload_1
  getfield com/admogo/AdMogoLayout/adMogoManager Lcom/admogo/AdMogoManager;
  astore_1
  aload_1
  astore 25
  aload 25
  astore_1
  aload_1
  invokevirtual com/admogo/AdMogoManager/getExtra()Lcom/admogo/obj/Extra;
  astore 29
  aload 29
  astore_1
  aload 24
  astore_2
  aload_2
  aload_1
  putfield com/admogo/AdMogoLayout/extra Lcom/admogo/obj/Extra;
Label3:
  return
Label2:
  getstatic com/admogo/util/AdMogoUtil/ADMOGO Ljava/lang/String;
  astore 26
  ldc "addressList is null or addressList.size() is 0"
  astore 9
  aload 26
  astore_1
  aload_1
  aload 9
  invokestatic android/util/Log/e(Ljava/lang/String;Ljava/lang/String;)I
  pop
Label6:
  goto Label3
Label4:
  astore 30
  getstatic com/admogo/util/AdMogoUtil/ADMOGO Ljava/lang/String;
  astore 26
  ldc "get countryCode failed"
  astore 9
  aload 26
  astore_1
  new java/lang/NoClassDefFoundError
  dup
  invokespecial java/lang/NoClassDefFoundError/<init>()V
  athrow
  aload_0
  astore_1
  aload_1
  getfield com/admogo/AdMogoLayout$getAdByCountryCode/adMogoLayout Lcom/admogo/AdMogoLayout;
  astore_1
  aload_1
  astore 28
  aload 28
  astore_1
  aload_1
  getfield com/admogo/AdMogoLayout/adMogoManager Lcom/admogo/AdMogoManager;
  astore_1
  aload_1
  astore 25
  iconst_0
  istore 19
  aload 25
  astore_1
  iload 19
  istore_2
  aload_1
  iload_2
  invokevirtual com/admogo/AdMogoManager/sendLocationData(Z)V
  goto Label3
Label1:
  getstatic com/admogo/util/AdMogoUtil/ADMOGO Ljava/lang/String;
  astore 26
Label7:
  ldc "location is null"
  astore 9
  aload 26
  astore_1
  aload_1
  aload 9
  invokestatic android/util/Log/w(Ljava/lang/String;Ljava/lang/String;)I
  pop
  aload_0
  astore_1
  aload_1
  getfield com/admogo/AdMogoLayout$getAdByCountryCode/adMogoLayout Lcom/admogo/AdMogoLayout;
  astore_1
  aload_1
  astore 28
  aload 28
  astore_1
  aload_1
  getfield com/admogo/AdMogoLayout/adMogoManager Lcom/admogo/AdMogoManager;
  astore_1
  aload_1
  astore 25
  aload 25
  astore_1
  aload_1
  getfield com/admogo/AdMogoManager/ifGetInfo Z
  istore_1
  iload_1
  istore 27
  iload_1
  invokestatic app/DummyClass/invokeIfStmt(Z)V
  iload 27
  ifeq Label3
  aload_0
  astore_1
  aload_1
  getfield com/admogo/AdMogoLayout$getAdByCountryCode/adMogoLayout Lcom/admogo/AdMogoLayout;
  astore_1
  aload_1
  astore 28
  aload 28
  astore_1
  aload_1
  getfield com/admogo/AdMogoLayout/adMogoManager Lcom/admogo/AdMogoManager;
  astore_1
  aload_1
  astore 25
  iconst_0
  istore 19
  aload 25
  astore_1
  iload 19
  istore_2
  aload_1
  iload_2
  invokevirtual com/admogo/AdMogoManager/sendLocationData(Z)V
Label8:
  goto Label3
  nop
.end <method>

