.source SourceFile
.class final enum  com/adwo/adsdk/U
.super java/lang/Enum
.field public static final enum "a" Lcom/adwo/adsdk/U;
.field public static final enum "b" Lcom/adwo/adsdk/U;
.field public static final enum "c" Lcom/adwo/adsdk/U;
.field private static final "d" [Lcom/adwo/adsdk/U;

.method static <clinit>()V
.limit locals 4
.limit stack 200
  nop
  new com/adwo/adsdk/U
  astore_0
  ldc "X"
  astore_1
  iconst_0
  istore_2
  aload_0
  aload_1
  iload_2
  invokespecial com/adwo/adsdk/U/<init>(Ljava/lang/String;I)V
  aload_0
  putstatic com/adwo/adsdk/U/a Lcom/adwo/adsdk/U;
  new com/adwo/adsdk/U
  astore_0
  ldc "Y"
  astore_1
  iconst_1
  istore_2
  aload_0
  aload_1
  iload_2
  invokespecial com/adwo/adsdk/U/<init>(Ljava/lang/String;I)V
  aload_0
  putstatic com/adwo/adsdk/U/b Lcom/adwo/adsdk/U;
  new com/adwo/adsdk/U
  astore_0
  ldc "Z"
  astore_1
  iconst_2
  istore_2
  aload_0
  aload_1
  iload_2
  invokespecial com/adwo/adsdk/U/<init>(Ljava/lang/String;I)V
  aload_0
  putstatic com/adwo/adsdk/U/c Lcom/adwo/adsdk/U;
  iconst_3
  istore_2
  iload_2
  anewarray com/adwo/adsdk/U
  astore_3
  getstatic com/adwo/adsdk/U/a Lcom/adwo/adsdk/U;
  astore_0
  iconst_0
  istore_2
  aload_3
  iload_2
  aload_0
  aastore
  getstatic com/adwo/adsdk/U/b Lcom/adwo/adsdk/U;
  astore_0
  iconst_1
  istore_2
  aload_3
  iload_2
  aload_0
  aastore
  getstatic com/adwo/adsdk/U/c Lcom/adwo/adsdk/U;
  astore_0
  iconst_2
  istore_2
  aload_3
  iload_2
  aload_0
  aastore
  aload_3
  putstatic com/adwo/adsdk/U/d [Lcom/adwo/adsdk/U;
  return
  nop
.end <method>

.method private <init>(Ljava/lang/String;I)V
.limit locals 3
.limit stack 200
  nop
  aload_0
  aload_1
  iload_2
  invokespecial java/lang/Enum/<init>(Ljava/lang/String;I)V
  return
  nop
.end <method>

.method public static valueOf(Ljava/lang/String;)Lcom/adwo/adsdk/U;
.limit locals 5
.limit stack 200
  nop
  ldc com/adwo/adsdk/U
  astore_2
  aload_2
  aload_0
  invokestatic java/lang/Enum/valueOf(Ljava/lang/Class;Ljava/lang/String;)Ljava/lang/Enum;
  astore_1
  aload_1
  astore 4
  aload 4
  checkcast com/adwo/adsdk/U
  astore 4
  aload 4
  astore_3
  aload_3
  areturn
  nop
.end <method>

.method public static values()[Lcom/adwo/adsdk/U;
.limit locals 5
.limit stack 200
  nop
  getstatic com/adwo/adsdk/U/d [Lcom/adwo/adsdk/U;
  astore_0
  aload_0
  arraylength
  istore_1
  iload_1
  anewarray com/adwo/adsdk/U
  astore_2
  iconst_0
  istore_3
  iconst_0
  istore 4
  aload_0
  iload_3
  aload_2
  iload 4
  iload_1
  invokestatic java/lang/System/arraycopy(Ljava/lang/Object;ILjava/lang/Object;II)V
  aload_2
  areturn
  nop
.end <method>

