.source AdMogoManager.java
.class  com/admogo/AdMogoManager$sendLocationRunnable
.super java/lang/Object
.implements  java/lang/Runnable
.field private "location_on" Z
.field final "this$0" Lcom/admogo/AdMogoManager;

.method <init>(Lcom/admogo/AdMogoManager;Z)V
.limit locals 3
.limit stack 200
  nop
  aload_0
  aload_1
  putfield com/admogo/AdMogoManager$sendLocationRunnable/this$0 Lcom/admogo/AdMogoManager;
  aload_0
  invokespecial java/lang/Object/<init>()V
  aload_0
  iload_2
  putfield com/admogo/AdMogoManager$sendLocationRunnable/location_on Z
  return
  nop
.end <method>

.method public run()V
.limit locals 21
.limit stack 200
  .catch  java/lang/Exception <from> Label3 <to> Label1 <using> Label2
  nop
  ldc ""
  astore_3
  ldc ""
  astore 4
Label3:
  aload_0
  astore_1
  aload_1
  getfield com/admogo/AdMogoManager$sendLocationRunnable/location_on Z
  istore 5
  new java/lang/NoClassDefFoundError
  dup
  invokespecial java/lang/NoClassDefFoundError/<init>()V
  athrow
  iload 5
  ifeq Label0
  invokestatic com/admogo/AdMogoManager/access$4()Ljava/lang/String;
  astore 4
  aload 4
  invokestatic java/net/URLEncoder/encode(Ljava/lang/String;)Ljava/lang/String;
  astore_3
  new java/lang/StringBuilder
  astore 6
  aload_0
  astore_1
  aload_1
  getfield com/admogo/AdMogoManager$sendLocationRunnable/this$0 Lcom/admogo/AdMogoManager;
  astore 7
  aload 7
  invokestatic com/admogo/AdMogoManager/access$5(Lcom/admogo/AdMogoManager;)D
  dstore 8
  dload 8
  invokestatic java/lang/String/valueOf(D)Ljava/lang/String;
  astore 4
  aload 6
  aload 4
  invokespecial java/lang/StringBuilder/<init>(Ljava/lang/String;)V
  ldc ","
  astore 10
  aload 6
  aload 10
  invokevirtual java/lang/StringBuilder/append(Ljava/lang/String;)Ljava/lang/StringBuilder;
  astore 6
  aload_0
  astore_1
  aload_1
  getfield com/admogo/AdMogoManager$sendLocationRunnable/this$0 Lcom/admogo/AdMogoManager;
  astore 7
  aload 7
  invokestatic com/admogo/AdMogoManager/access$6(Lcom/admogo/AdMogoManager;)D
  dstore 8
  aload 6
  dload 8
  invokevirtual java/lang/StringBuilder/append(D)Ljava/lang/StringBuilder;
  astore 6
  aload 6
  invokevirtual java/lang/StringBuilder/toString()Ljava/lang/String;
  astore 4
Label0:
  getstatic com/admogo/util/AdMogoUtil/urlAudiance Ljava/lang/String;
  astore 11
  bipush 16
  istore 13
  iload 13
  anewarray java/lang/Object
  astore 12
  aload_0
  astore_1
  aload_1
  getfield com/admogo/AdMogoManager$sendLocationRunnable/this$0 Lcom/admogo/AdMogoManager;
  astore 7
  aload 7
  getfield com/admogo/AdMogoManager/keyAdMogo Ljava/lang/String;
  astore 14
  iconst_0
  istore 13
  aload 12
  iload 13
  aload 14
  aastore
  aload_0
  astore_1
  aload_1
  getfield com/admogo/AdMogoManager$sendLocationRunnable/this$0 Lcom/admogo/AdMogoManager;
  astore 7
  aload 7
  getfield com/admogo/AdMogoManager/deviceIDHash Ljava/lang/String;
  astore 14
  iconst_1
  istore 13
  aload 12
  iload 13
  aload 14
  aastore
  iconst_2
  istore 13
  ldc "1.1.6"
  astore 10
  aload 12
  iload 13
  aload 10
  aastore
  aload_0
  astore_1
  aload_1
  getfield com/admogo/AdMogoManager$sendLocationRunnable/this$0 Lcom/admogo/AdMogoManager;
  astore 7
  aload 7
  invokestatic com/admogo/AdMogoManager/access$7(Lcom/admogo/AdMogoManager;)Ljava/lang/String;
  astore 14
  iconst_3
  istore 13
  aload 12
  iload 13
  aload 14
  aastore
  aload_0
  astore_1
  aload_1
  getfield com/admogo/AdMogoManager$sendLocationRunnable/this$0 Lcom/admogo/AdMogoManager;
  astore 7
  aload 7
  invokestatic com/admogo/AdMogoManager/access$8(Lcom/admogo/AdMogoManager;)Ljava/lang/String;
  astore 14
  iconst_4
  istore 13
  aload 12
  iload 13
  aload 14
  aastore
  aload_0
  astore_1
  aload_1
  getfield com/admogo/AdMogoManager$sendLocationRunnable/this$0 Lcom/admogo/AdMogoManager;
  astore 7
  aload 7
  invokestatic com/admogo/AdMogoManager/access$9(Lcom/admogo/AdMogoManager;)I
  istore 15
  iload 15
  invokestatic java/lang/Integer/valueOf(I)Ljava/lang/Integer;
  astore 16
  iconst_5
  istore 13
  aload 12
  iload 13
  aload 16
  aastore
  aload_0
  astore_1
  aload_1
  getfield com/admogo/AdMogoManager$sendLocationRunnable/this$0 Lcom/admogo/AdMogoManager;
  astore 7
  aload 7
  invokestatic com/admogo/AdMogoManager/access$10(Lcom/admogo/AdMogoManager;)Ljava/lang/String;
  astore 14
  bipush 6
  istore 13
  aload 12
  iload 13
  aload 14
  aastore
  aload_0
  astore_1
  aload_1
  getfield com/admogo/AdMogoManager$sendLocationRunnable/this$0 Lcom/admogo/AdMogoManager;
  astore 7
  aload 7
  invokestatic com/admogo/AdMogoManager/access$11(Lcom/admogo/AdMogoManager;)Ljava/lang/String;
  astore 14
  bipush 7
  istore 13
  aload 12
  iload 13
  aload 14
  aastore
  aload_0
  astore_1
  aload_1
  getfield com/admogo/AdMogoManager$sendLocationRunnable/this$0 Lcom/admogo/AdMogoManager;
  astore 7
  aload 7
  getfield com/admogo/AdMogoManager/os Ljava/lang/String;
  astore 14
  bipush 8
  istore 13
  aload 12
  iload 13
  aload 14
  aastore
  aload_0
  astore_1
  aload_1
  getfield com/admogo/AdMogoManager$sendLocationRunnable/this$0 Lcom/admogo/AdMogoManager;
  astore 7
  aload 7
  getfield com/admogo/AdMogoManager/deviceName Ljava/lang/String;
  astore 14
  bipush 9
  istore 13
  aload 12
  iload 13
  aload 14
  aastore
  aload_0
  astore_1
  aload_1
  getfield com/admogo/AdMogoManager$sendLocationRunnable/this$0 Lcom/admogo/AdMogoManager;
  astore 7
  aload 7
  invokestatic com/admogo/AdMogoManager/access$12(Lcom/admogo/AdMogoManager;)Ljava/lang/String;
  astore 14
  bipush 10
  istore 13
  aload 12
  iload 13
  aload 14
  aastore
  aload_0
  astore_1
  aload_1
  getfield com/admogo/AdMogoManager$sendLocationRunnable/this$0 Lcom/admogo/AdMogoManager;
  astore 7
  aload 7
  invokestatic com/admogo/AdMogoManager/access$13(Lcom/admogo/AdMogoManager;)Ljava/lang/String;
  astore 14
  bipush 11
  istore 13
  aload 12
  iload 13
  aload 14
  aastore
  aload_0
  astore_1
  aload_1
  getfield com/admogo/AdMogoManager$sendLocationRunnable/this$0 Lcom/admogo/AdMogoManager;
  astore 7
  aload 7
  invokestatic com/admogo/AdMogoManager/access$14(Lcom/admogo/AdMogoManager;)Ljava/lang/String;
  astore 14
  bipush 12
  istore 13
  aload 12
  iload 13
  aload 14
  aastore
  aload_0
  astore_1
  aload_1
  getfield com/admogo/AdMogoManager$sendLocationRunnable/this$0 Lcom/admogo/AdMogoManager;
  astore 7
  aload 7
  invokestatic com/admogo/AdMogoManager/access$15(Lcom/admogo/AdMogoManager;)Ljava/lang/String;
  astore 14
  bipush 13
  istore 13
  aload 12
  iload 13
  aload 14
  aastore
  bipush 14
  istore 13
  aload 12
  iload 13
  aload_3
  aastore
  bipush 15
  istore 13
  aload 12
  iload 13
  aload 4
  aastore
  aload 11
  aload 12
  invokestatic java/lang/String/format(Ljava/lang/String;[Ljava/lang/Object;)Ljava/lang/String;
  astore 4
  new org/apache/http/client/methods/HttpGet
  astore 17
  aload 17
  astore_1
  aload_1
  aload 4
  invokespecial org/apache/http/client/methods/HttpGet/<init>(Ljava/lang/String;)V
  new org/apache/http/params/BasicHttpParams
  astore 18
  aload 18
  astore_1
  aload_1
  invokespecial org/apache/http/params/BasicHttpParams/<init>()V
  new org/apache/http/impl/client/DefaultHttpClient
  astore 19
  aload 19
  astore_1
  aload 18
  astore_2
  aload_1
  aload_2
  invokespecial org/apache/http/impl/client/DefaultHttpClient/<init>(Lorg/apache/http/params/HttpParams;)V
  aload 19
  astore_1
  aload 17
  astore_2
  aload_1
  aload_2
  invokevirtual org/apache/http/impl/client/DefaultHttpClient/execute(Lorg/apache/http/client/methods/HttpUriRequest;)Lorg/apache/http/HttpResponse;
  pop
Label1:
  return
Label2:
  astore 20
  getstatic com/admogo/util/AdMogoUtil/ADMOGO Ljava/lang/String;
  astore 14
  ldc "Send Location Data Failed"
  astore 10
  aload 20
  astore_1
  new java/lang/NoClassDefFoundError
  dup
  invokespecial java/lang/NoClassDefFoundError/<init>()V
  athrow
  goto Label1
  nop
.end <method>

