.source dalvik_source_VirusShare_32e70f448ebd75661a1cb12f9cd8e013.apk
.class public final  e
.super java/lang/Object
.field private "a" Ljava/lang/String;
.field private "b" Ljava/util/HashMap;

.method public <init>(Landroid/os/Bundle;)V
.limit locals 8
.limit stack 200
  nop
  aload_0
  invokespecial java/lang/Object/<init>()V
  ldc "action"
  astore_3
  new java/lang/NoClassDefFoundError
  dup
  invokespecial java/lang/NoClassDefFoundError/<init>()V
  athrow
  nop
  aload_0
  aload_2
  putfield e/a Ljava/lang/String;
  ldc "params"
  astore_3
  aload_1
  aload_3
  invokevirtual android/os/Bundle/getSerializable(Ljava/lang/String;)Ljava/io/Serializable;
  astore 4
  aload 4
  instanceof java/util/HashMap
  istore 5
  iload 5
  invokestatic app/DummyClass/invokeIfStmt(Z)V
  iload 5
  ifeq Label0
  aload 4
  astore 7
  aload 7
  checkcast java/util/HashMap
  astore 7
  aload 7
  astore 6
Label1:
  aload_0
  aload 6
  putfield e/b Ljava/util/HashMap;
  return
Label0:
  aconst_null
  astore 6
  goto Label1
  nop
.end <method>

.method public <init>(Ljava/lang/String;)V
.limit locals 2
.limit stack 200
  nop
  aload_0
  invokespecial java/lang/Object/<init>()V
  aload_0
  aload_1
  putfield e/a Ljava/lang/String;
  return
  nop
.end <method>

.method public <init>(Ljava/lang/String;Ljava/util/HashMap;)V
  .signature_attr "(Ljava/lang/String;Ljava/util/HashMap<Ljava/lang/String;Ljava/lang/String;>;)V"
.limit locals 3
.limit stack 200
  nop
  aload_0
  aload_1
  invokespecial e/<init>(Ljava/lang/String;)V
  aload_0
  aload_2
  putfield e/b Ljava/util/HashMap;
  return
  nop
.end <method>

.method public final a()Landroid/os/Bundle;
.limit locals 5
.limit stack 200
  nop
  new java/lang/NoClassDefFoundError
  dup
  invokespecial java/lang/NoClassDefFoundError/<init>()V
  athrow
  aload_1
  invokespecial android/os/Bundle/<init>()V
  aload_0
  getfield e/a Ljava/lang/String;
  astore_2
  ldc "action"
  astore_3
  aload_1
  aload_3
  aload_2
  invokevirtual android/os/Bundle/putString(Ljava/lang/String;Ljava/lang/String;)V
  aload_0
  getfield e/b Ljava/util/HashMap;
  astore 4
  ldc "params"
  astore_3
  aload_1
  aload_3
  aload 4
  invokevirtual android/os/Bundle/putSerializable(Ljava/lang/String;Ljava/io/Serializable;)V
  aload_1
  areturn
  nop
.end <method>

.method public final b()Ljava/lang/String;
.limit locals 2
.limit stack 200
  nop
  aload_0
  getfield e/a Ljava/lang/String;
  astore_1
  aload_1
  areturn
  nop
.end <method>

.method public final c()Ljava/util/HashMap;
  .signature_attr "()Ljava/util/HashMap<Ljava/lang/String;Ljava/lang/String;>;"
.limit locals 2
.limit stack 200
  nop
  aload_0
  getfield e/b Ljava/util/HashMap;
  astore_1
  aload_1
  areturn
  nop
.end <method>

