.source dalvik_source_VirusShare_32e70f448ebd75661a1cb12f9cd8e013.apk
.class public final  f
.super java/lang/Object
.field private static "f" J =  0
.field public "a" Ljava/lang/String;
.field private "b" Ljava/util/LinkedList;
.field private "c" J
.field private "d" J
.field private "e" Ljava/util/LinkedList;
.field private "g" Ljava/lang/String;
.field private "h" Z
.field private "i" Z

.method static <clinit>()V
.limit locals 2
.limit stack 200
  nop
  ldc2_w 0
  lstore_0
  lload_0
  putstatic f/f J
  return
  nop
.end <method>

.method <init>()V
.limit locals 3
.limit stack 200
  nop
  aload_0
  invokespecial java/lang/Object/<init>()V
  iconst_0
  istore_1
  aload_0
  iload_1
  putfield f/h Z
  iconst_0
  istore_1
  aload_0
  iload_1
  putfield f/i Z
  new java/util/LinkedList
  astore_2
  aload_2
  invokespecial java/util/LinkedList/<init>()V
  aload_0
  aload_2
  putfield f/b Ljava/util/LinkedList;
  new java/util/LinkedList
  astore_2
  aload_2
  invokespecial java/util/LinkedList/<init>()V
  aload_0
  aload_2
  putfield f/e Ljava/util/LinkedList;
  aload_0
  invokevirtual f/a()V
  return
  nop
.end <method>

.method final a()V
.limit locals 6
.limit stack 200
  nop
  aload_0
  getfield f/b Ljava/util/LinkedList;
  astore_1
  aload_1
  invokevirtual java/util/LinkedList/clear()V
  ldc2_w 0
  lstore_2
  aload_0
  lload_2
  putfield f/c J
  ldc2_w 0
  lstore_2
  aload_0
  lload_2
  putfield f/d J
  aload_0
  getfield f/e Ljava/util/LinkedList;
  astore_1
  aload_1
  invokevirtual java/util/LinkedList/clear()V
  aconst_null
  astore 4
  aload_0
  aload 4
  putfield f/g Ljava/lang/String;
  iconst_0
  istore 5
  aload_0
  iload 5
  putfield f/h Z
  iconst_0
  istore 5
  aload_0
  iload 5
  putfield f/i Z
  return
  nop
.end <method>

.method public final a(Ljava/lang/String;)V
.limit locals 5
.limit stack 200
  nop
  new java/lang/StringBuilder
  astore_2
  aload_2
  invokespecial java/lang/StringBuilder/<init>()V
  ldc "Prior ad identifier = "
  astore_3
  aload_2
  aload_3
  invokevirtual java/lang/StringBuilder/append(Ljava/lang/String;)Ljava/lang/StringBuilder;
  astore_2
  aload_2
  aload_1
  invokevirtual java/lang/StringBuilder/append(Ljava/lang/String;)Ljava/lang/StringBuilder;
  astore_2
  aload_2
  invokevirtual java/lang/StringBuilder/toString()Ljava/lang/String;
  astore 4
  aload 4
  invokestatic com/google/ads/util/a/d(Ljava/lang/String;)V
  aload_0
  aload_1
  putfield f/g Ljava/lang/String;
  return
  nop
.end <method>

.method final b()V
.limit locals 6
.limit stack 200
  nop
  ldc "Ad clicked."
  astore_1
  aload_1
  invokestatic com/google/ads/util/a/d(Ljava/lang/String;)V
  aload_0
  getfield f/b Ljava/util/LinkedList;
  astore_2
  new java/lang/NoClassDefFoundError
  dup
  invokespecial java/lang/NoClassDefFoundError/<init>()V
  athrow
  nop
  lload_3
  invokestatic java/lang/Long/valueOf(J)Ljava/lang/Long;
  astore 5
  aload_2
  aload 5
  invokevirtual java/util/LinkedList/add(Ljava/lang/Object;)Z
  pop
  return
  nop
.end <method>

.method public final b(Ljava/lang/String;)V
.limit locals 5
.limit stack 200
  nop
  new java/lang/StringBuilder
  astore_2
  aload_2
  invokespecial java/lang/StringBuilder/<init>()V
  ldc "Prior impression ticket = "
  astore_3
  aload_2
  aload_3
  invokevirtual java/lang/StringBuilder/append(Ljava/lang/String;)Ljava/lang/StringBuilder;
  astore_2
  aload_2
  aload_1
  invokevirtual java/lang/StringBuilder/append(Ljava/lang/String;)Ljava/lang/StringBuilder;
  astore_2
  aload_2
  invokevirtual java/lang/StringBuilder/toString()Ljava/lang/String;
  astore 4
  aload 4
  invokestatic com/google/ads/util/a/d(Ljava/lang/String;)V
  aload_0
  aload_1
  putfield f/a Ljava/lang/String;
  return
  nop
.end <method>

.method final c()V
.limit locals 4
.limit stack 200
  nop
  ldc "Ad request loaded."
  astore_1
  aload_1
  invokestatic com/google/ads/util/a/d(Ljava/lang/String;)V
  new java/lang/NoClassDefFoundError
  dup
  invokespecial java/lang/NoClassDefFoundError/<init>()V
  athrow
  nop
  aload_0
  lload_2
  putfield f/c J
  return
  nop
.end <method>

.method final d()V
.limit locals 8
.limit stack 200
  nop
  ldc "Ad request started."
  astore_1
  aload_1
  invokestatic com/google/ads/util/a/d(Ljava/lang/String;)V
  new java/lang/NoClassDefFoundError
  dup
  invokespecial java/lang/NoClassDefFoundError/<init>()V
  athrow
  nop
  aload_0
  lload_2
  putfield f/d J
  getstatic f/f J
  lstore 4
  ldc2_w 1
  lstore 6
  lload 4
  lload 6
  ladd
  lstore 4
  lload 4
  putstatic f/f J
  return
  nop
.end <method>

.method final e()J
.limit locals 8
.limit stack 200
  nop
  aload_0
  getfield f/b Ljava/util/LinkedList;
  astore_1
  aload_1
  invokevirtual java/util/LinkedList/size()I
  istore_2
  aload_0
  getfield f/e Ljava/util/LinkedList;
  astore_1
  aload_1
  invokevirtual java/util/LinkedList/size()I
  istore_3
  new java/lang/NoClassDefFoundError
  dup
  invokespecial java/lang/NoClassDefFoundError/<init>()V
  athrow
  dload_3
  invokestatic app/DummyClass/invokeIfStmt(D)V
  iload_2
  iload_3
  if_icmpeq Label0
  ldc2_w 4294967295
  lstore 4
  lload 4
  lreturn
Label0:
  aload_0
  getfield f/b Ljava/util/LinkedList;
  astore_1
  aload_1
  invokevirtual java/util/LinkedList/size()I
  istore_3
  iload_3
  i2l
  lstore 6
  lload 6
  lreturn
  nop
.end <method>

.method final f()Ljava/lang/String;
.limit locals 18
.limit stack 200
  nop
  aload_0
  astore_1
  aload_1
  getfield f/b Ljava/util/LinkedList;
  astore_2
  aload_1
  astore_0
  aload_2
  invokevirtual java/util/LinkedList/isEmpty()Z
  istore_3
  new java/lang/NoClassDefFoundError
  dup
  invokespecial java/lang/NoClassDefFoundError/<init>()V
  athrow
  iload_3
  ifne Label0
  aload_0
  astore_1
  aload_1
  getfield f/b Ljava/util/LinkedList;
  astore_2
  aload_1
  astore_0
  aload_2
  invokevirtual java/util/LinkedList/size()I
  istore 4
  aload_0
  astore_1
  aload_1
  getfield f/e Ljava/util/LinkedList;
  astore_2
  aload_1
  astore_0
  aload_2
  invokevirtual java/util/LinkedList/size()I
  istore 5
  dload 4
  invokestatic app/DummyClass/invokeIfStmt(D)V
  dload 5
  invokestatic app/DummyClass/invokeIfStmt(D)V
  iload 4
  iload 5
  if_icmpeq Label1
Label0:
  aconst_null
  astore 6
  aload 6
  areturn
Label1:
  new java/lang/StringBuilder
  astore 7
  aload 7
  invokespecial java/lang/StringBuilder/<init>()V
  iconst_0
  istore 5
Label4:
  aload_0
  astore_1
  aload_1
  getfield f/b Ljava/util/LinkedList;
  astore_2
  aload_1
  astore_0
  aload_2
  invokevirtual java/util/LinkedList/size()I
  istore 4
  dload 5
  invokestatic app/DummyClass/invokeIfStmt(D)V
  dload 4
  invokestatic app/DummyClass/invokeIfStmt(D)V
  iload 5
  iload 4
  if_icmpge Label2
  dload 5
  invokestatic app/DummyClass/invokeIfStmt(D)V
  iload 5
  ifeq Label3
  ldc ","
  astore 8
  aload 7
  aload 8
  invokevirtual java/lang/StringBuilder/append(Ljava/lang/String;)Ljava/lang/StringBuilder;
  pop
Label3:
  aload_0
  astore_1
  aload_1
  getfield f/e Ljava/util/LinkedList;
  astore_2
  aload_1
  astore_0
  aload_2
  iload 5
  invokevirtual java/util/LinkedList/get(I)Ljava/lang/Object;
  astore 9
  aload 9
  astore 11
  aload 11
  checkcast java/lang/Long
  astore 11
  aload 11
  astore 10
  aload 10
  invokevirtual java/lang/Long/longValue()J
  lstore 12
  aload_0
  astore_1
  aload_1
  getfield f/b Ljava/util/LinkedList;
  astore_2
  aload_1
  astore_0
  aload_2
  iload 5
  invokevirtual java/util/LinkedList/get(I)Ljava/lang/Object;
  astore 9
  aload 9
  astore 14
  aload 14
  checkcast java/lang/Long
  astore 14
  aload 14
  astore 10
  aload 10
  invokevirtual java/lang/Long/longValue()J
  lstore 15
  lload 12
  lload 15
  lsub
  lstore 15
  lload 15
  invokestatic java/lang/Long/toString(J)Ljava/lang/String;
  astore 17
  aload 17
  astore_1
  aload 7
  aload_1
  invokevirtual java/lang/StringBuilder/append(Ljava/lang/String;)Ljava/lang/StringBuilder;
  pop
  iload 5
  iconst_1
  iadd
  istore 5
  goto Label4
Label2:
  aload 7
  invokevirtual java/lang/StringBuilder/toString()Ljava/lang/String;
  astore 17
  aload 17
  areturn
  nop
.end <method>

.method final g()Ljava/lang/String;
.limit locals 16
.limit stack 200
  nop
  aload_0
  getfield f/b Ljava/util/LinkedList;
  astore_1
  aload_1
  invokevirtual java/util/LinkedList/isEmpty()Z
  istore_2
  new java/lang/NoClassDefFoundError
  dup
  invokespecial java/lang/NoClassDefFoundError/<init>()V
  athrow
  iload_2
  ifeq Label0
  aconst_null
  astore_3
  aload_3
  areturn
Label0:
  new java/lang/StringBuilder
  astore 4
  aload 4
  invokespecial java/lang/StringBuilder/<init>()V
  iconst_0
  istore 5
Label3:
  aload_0
  getfield f/b Ljava/util/LinkedList;
  astore_1
  aload_1
  invokevirtual java/util/LinkedList/size()I
  istore 6
  dload 5
  invokestatic app/DummyClass/invokeIfStmt(D)V
  dload 6
  invokestatic app/DummyClass/invokeIfStmt(D)V
  iload 5
  iload 6
  if_icmpge Label1
  dload 5
  invokestatic app/DummyClass/invokeIfStmt(D)V
  iload 5
  ifeq Label2
  ldc ","
  astore 7
  aload 4
  aload 7
  invokevirtual java/lang/StringBuilder/append(Ljava/lang/String;)Ljava/lang/StringBuilder;
  pop
Label2:
  aload_0
  getfield f/b Ljava/util/LinkedList;
  astore_1
  aload_1
  iload 5
  invokevirtual java/util/LinkedList/get(I)Ljava/lang/Object;
  astore 8
  aload 8
  astore 10
  aload 10
  checkcast java/lang/Long
  astore 10
  aload 10
  astore 9
  aload 9
  invokevirtual java/lang/Long/longValue()J
  lstore 11
  aload_0
  getfield f/c J
  lstore 13
  lload 11
  lload 13
  lsub
  lstore 13
  lload 13
  invokestatic java/lang/Long/toString(J)Ljava/lang/String;
  astore 15
  aload 4
  aload 15
  invokevirtual java/lang/StringBuilder/append(Ljava/lang/String;)Ljava/lang/StringBuilder;
  pop
  iload 5
  iconst_1
  iadd
  istore 5
  goto Label3
Label1:
  aload 4
  invokevirtual java/lang/StringBuilder/toString()Ljava/lang/String;
  astore 15
  aload 15
  areturn
  nop
.end <method>

.method final h()J
.limit locals 5
.limit stack 200
  nop
  aload_0
  getfield f/c J
  lstore_1
  aload_0
  getfield f/d J
  lstore_3
  lload_1
  lload_3
  lsub
  lstore_3
  lload_3
  lreturn
  nop
.end <method>

.method static i()J
.limit locals 2
.limit stack 200
  nop
  getstatic f/f J
  lstore_0
  lload_0
  lreturn
  nop
.end <method>

.method final j()Ljava/lang/String;
.limit locals 2
.limit stack 200
  nop
  aload_0
  getfield f/g Ljava/lang/String;
  astore_1
  aload_1
  areturn
  nop
.end <method>

.method final k()Z
.limit locals 2
.limit stack 200
  nop
  aload_0
  getfield f/h Z
  istore_1
  iload_1
  ireturn
  nop
.end <method>

.method final l()V
.limit locals 3
.limit stack 200
  nop
  ldc "Interstitial network error."
  astore_1
  aload_1
  invokestatic com/google/ads/util/a/d(Ljava/lang/String;)V
  iconst_1
  istore_2
  aload_0
  iload_2
  putfield f/h Z
  return
  nop
.end <method>

.method final m()Z
.limit locals 2
.limit stack 200
  nop
  aload_0
  getfield f/i Z
  istore_1
  iload_1
  ireturn
  nop
.end <method>

.method final n()V
.limit locals 3
.limit stack 200
  nop
  ldc "Interstitial no fill."
  astore_1
  aload_1
  invokestatic com/google/ads/util/a/d(Ljava/lang/String;)V
  iconst_1
  istore_2
  aload_0
  iload_2
  putfield f/i Z
  return
  nop
.end <method>

.method public final o()V
.limit locals 6
.limit stack 200
  nop
  ldc "Landing page dismissed."
  astore_1
  aload_1
  invokestatic com/google/ads/util/a/d(Ljava/lang/String;)V
  aload_0
  getfield f/e Ljava/util/LinkedList;
  astore_2
  new java/lang/NoClassDefFoundError
  dup
  invokespecial java/lang/NoClassDefFoundError/<init>()V
  athrow
  nop
  lload_3
  invokestatic java/lang/Long/valueOf(J)Ljava/lang/Long;
  astore 5
  aload_2
  aload 5
  invokevirtual java/util/LinkedList/add(Ljava/lang/Object;)Z
  pop
  return
  nop
.end <method>

.method final p()Ljava/lang/String;
.limit locals 2
.limit stack 200
  nop
  aload_0
  getfield f/a Ljava/lang/String;
  astore_1
  aload_1
  areturn
  nop
.end <method>

