.source dalvik_source_VirusShare_32e70f448ebd75661a1cb12f9cd8e013.apk
.class public final  k
.super java/lang/Object
.implements  i

.method public <init>()V
.limit locals 1
.limit stack 200
  nop
  aload_0
  invokespecial java/lang/Object/<init>()V
  return
  nop
.end <method>

.method public final a(Ld;Ljava/util/HashMap;Landroid/webkit/WebView;)V
  .signature_attr "(Ld;Ljava/util/HashMap<Ljava/lang/String;Ljava/lang/String;>;Landroid/webkit/WebView;)V"
.limit locals 24
.limit stack 200
  nop
  ldc "u"
  astore 7
  aload_2
  astore 4
  aload 4
  aload 7
  invokevirtual java/util/HashMap/get(Ljava/lang/Object;)Ljava/lang/Object;
  astore 6
  aload 6
  astore 9
  aload 9
  checkcast java/lang/String
  astore 9
  aload 9
  astore 8
  new java/lang/NoClassDefFoundError
  dup
  invokespecial java/lang/NoClassDefFoundError/<init>()V
  athrow
  iload 8
  ifne Label0
  ldc "Could not get URL from click gmsg."
  astore 7
  aload 7
  invokestatic com/google/ads/util/a/e(Ljava/lang/String;)V
Label3:
  return
Label0:
  aload_1
  astore 4
  aload 4
  invokevirtual d/l()Lf;
  astore 10
  aload 10
  invokestatic app/DummyClass/invokeIfStmt(Ljava/lang/Object;)V
  aload 10
  ifnull Label1
  aload 8
  invokestatic android/net/Uri/parse(Ljava/lang/String;)Landroid/net/Uri;
  astore 11
  aload 11
  invokevirtual android/net/Uri/getHost()Ljava/lang/String;
  astore 12
  aload 12
  invokestatic app/DummyClass/invokeIfStmt(Ljava/lang/Object;)V
  aload 12
  ifnull Label1
  getstatic java/util/Locale/US Ljava/util/Locale;
  astore 13
  aload 12
  aload 13
  invokevirtual java/lang/String/toLowerCase(Ljava/util/Locale;)Ljava/lang/String;
  astore 12
  ldc ".admob.com"
  astore 7
  aload 12
  aload 7
  invokevirtual java/lang/String/endsWith(Ljava/lang/String;)Z
  istore 14
  iload 14
  invokestatic app/DummyClass/invokeIfStmt(Z)V
  iload 14
  ifeq Label1
  aconst_null
  astore 15
  aload 11
  invokevirtual android/net/Uri/getPath()Ljava/lang/String;
  astore 12
  aload 12
  invokestatic app/DummyClass/invokeIfStmt(Ljava/lang/Object;)V
  aload 12
  ifnull Label2
  ldc "/"
  astore 7
  aload 12
  aload 7
  invokevirtual java/lang/String/split(Ljava/lang/String;)[Ljava/lang/String;
  astore 16
  aload 16
  arraylength
  istore 17
  dload 17
  invokestatic app/DummyClass/invokeIfStmt(D)V
  iconst_4
  istore 18
  iload 17
  iload 18
  if_icmplt Label2
  new java/lang/StringBuilder
  astore 19
  aload 19
  invokespecial java/lang/StringBuilder/<init>()V
  iconst_2
  istore 18
  aload 16
  iload 18
  aaload
  astore 20
  aload 20
  astore 4
  aload 19
  aload 4
  invokevirtual java/lang/StringBuilder/append(Ljava/lang/String;)Ljava/lang/StringBuilder;
  astore 19
  ldc "/"
  astore 7
  aload 19
  aload 7
  invokevirtual java/lang/StringBuilder/append(Ljava/lang/String;)Ljava/lang/StringBuilder;
  astore 19
  iconst_3
  istore 18
  aload 16
  iload 18
  aaload
  astore 20
  aload 20
  astore 4
  aload 19
  aload 4
  invokevirtual java/lang/StringBuilder/append(Ljava/lang/String;)Ljava/lang/StringBuilder;
  astore 19
  aload 19
  invokevirtual java/lang/StringBuilder/toString()Ljava/lang/String;
  astore 15
Label2:
  aload 10
  aload 15
  invokevirtual f/b(Ljava/lang/String;)V
Label1:
  new w
  astore 21
  aload_3
  astore 4
  aload 4
  invokevirtual android/webkit/WebView/getContext()Landroid/content/Context;
  astore 22
  aload 22
  astore 4
  aload 4
  invokevirtual android/content/Context/getApplicationContext()Landroid/content/Context;
  astore 22
  aload 21
  astore 4
  aload 22
  astore 5
  aload 4
  aload 8
  aload 5
  invokespecial w/<init>(Ljava/lang/String;Landroid/content/Context;)V
  new java/lang/Thread
  astore 23
  aload 23
  astore 4
  aload 21
  astore 5
  aload 4
  aload 5
  invokespecial java/lang/Thread/<init>(Ljava/lang/Runnable;)V
  aload 23
  astore 4
  aload 4
  invokevirtual java/lang/Thread/start()V
  goto Label3
  nop
.end <method>

