.source dalvik_source_VirusShare_32e70f448ebd75661a1cb12f9cd8e013.apk
.class public final  LBSAPIProtocol/UINTYPE
.super java/lang/Object
.field static final "$assertionsDisabled" Z =  0
.field public static final "UIN_EMAIL" LLBSAPIProtocol/UINTYPE;
.field public static final "UIN_IMEI" LLBSAPIProtocol/UINTYPE;
.field public static final "UIN_MOBILE" LLBSAPIProtocol/UINTYPE;
.field public static final "UIN_QQ" LLBSAPIProtocol/UINTYPE;
.field public static final "_UIN_EMAIL" I =  1
.field public static final "_UIN_IMEI" I =  3
.field public static final "_UIN_MOBILE" I =  2
.field public static final "_UIN_QQ" I =  0
.field private static "__values" [LLBSAPIProtocol/UINTYPE;
.field private "__T" Ljava/lang/String;
.field private "__value" I

.method static <clinit>()V
.limit locals 9
.limit stack 200
  nop
  ldc LBSAPIProtocol/UINTYPE
  astore_0
  aload_0
  invokevirtual java/lang/Class/desiredAssertionStatus()Z
  istore_1
  new java/lang/NoClassDefFoundError
  dup
  invokespecial java/lang/NoClassDefFoundError/<init>()V
  athrow
  iload_1
  ifne Label0
  iconst_1
  istore_1
Label1:
  iload_1
  putstatic LBSAPIProtocol/UINTYPE/$assertionsDisabled Z
  iconst_4
  istore_3
  iload_3
  anewarray LBSAPIProtocol/UINTYPE
  astore_2
  aload_2
  putstatic LBSAPIProtocol/UINTYPE/__values [LLBSAPIProtocol/UINTYPE;
  new LBSAPIProtocol/UINTYPE
  astore 4
  iconst_0
  istore_3
  iload_3
  istore 5
  iconst_0
  istore_3
  iload_3
  istore 6
  ldc "UIN_QQ"
  astore 7
  aload 4
  iload 5
  iload 6
  aload 7
  invokespecial LBSAPIProtocol/UINTYPE/<init>(IILjava/lang/String;)V
  aload 4
  putstatic LBSAPIProtocol/UINTYPE/UIN_QQ LLBSAPIProtocol/UINTYPE;
  new LBSAPIProtocol/UINTYPE
  astore 4
  iconst_1
  istore_3
  iload_3
  istore 6
  iconst_1
  istore_3
  iload_3
  istore 5
  ldc "UIN_EMAIL"
  astore 7
  aload 4
  iload 6
  iload 5
  aload 7
  invokespecial LBSAPIProtocol/UINTYPE/<init>(IILjava/lang/String;)V
  aload 4
  putstatic LBSAPIProtocol/UINTYPE/UIN_EMAIL LLBSAPIProtocol/UINTYPE;
  new LBSAPIProtocol/UINTYPE
  astore 4
  iconst_2
  istore_3
  iconst_2
  istore 8
  ldc "UIN_MOBILE"
  astore 7
  aload 4
  iload_3
  iload 8
  aload 7
  invokespecial LBSAPIProtocol/UINTYPE/<init>(IILjava/lang/String;)V
  aload 4
  putstatic LBSAPIProtocol/UINTYPE/UIN_MOBILE LLBSAPIProtocol/UINTYPE;
  new LBSAPIProtocol/UINTYPE
  astore 4
  iconst_3
  istore_3
  iconst_3
  istore 8
  ldc "UIN_IMEI"
  astore 7
  aload 4
  iload_3
  iload 8
  aload 7
  invokespecial LBSAPIProtocol/UINTYPE/<init>(IILjava/lang/String;)V
  aload 4
  putstatic LBSAPIProtocol/UINTYPE/UIN_IMEI LLBSAPIProtocol/UINTYPE;
  return
Label0:
  iconst_0
  istore_1
  goto Label1
  nop
.end <method>

.method private <init>(IILjava/lang/String;)V
.limit locals 6
.limit stack 200
  nop
  aload_0
  invokespecial java/lang/Object/<init>()V
  new java/lang/String
  astore 4
  aload 4
  invokespecial java/lang/String/<init>()V
  aload_0
  aload 4
  putfield LBSAPIProtocol/UINTYPE/__T Ljava/lang/String;
  aload_0
  aload_3
  putfield LBSAPIProtocol/UINTYPE/__T Ljava/lang/String;
  aload_0
  iload_2
  putfield LBSAPIProtocol/UINTYPE/__value I
  getstatic LBSAPIProtocol/UINTYPE/__values [LLBSAPIProtocol/UINTYPE;
  astore 5
  aload 5
  iload_1
  aload_0
  aastore
  return
  nop
.end <method>

.method public static convert(I)LLBSAPIProtocol/UINTYPE;
.limit locals 8
.limit stack 200
  nop
  iconst_0
  istore_1
Label2:
  getstatic LBSAPIProtocol/UINTYPE/__values [LLBSAPIProtocol/UINTYPE;
  astore_2
  aload_2
  arraylength
  istore_3
  new java/lang/NoClassDefFoundError
  dup
  invokespecial java/lang/NoClassDefFoundError/<init>()V
  athrow
  dload_3
  invokestatic app/DummyClass/invokeIfStmt(D)V
  iload_1
  iload_3
  if_icmpge Label0
  getstatic LBSAPIProtocol/UINTYPE/__values [LLBSAPIProtocol/UINTYPE;
  astore_2
  aload_2
  iload_1
  aaload
  astore 4
  aload 4
  invokevirtual LBSAPIProtocol/UINTYPE/value()I
  istore_3
  dload_3
  invokestatic app/DummyClass/invokeIfStmt(D)V
  dload_0
  invokestatic app/DummyClass/invokeIfStmt(D)V
  iload_3
  iload_0
  if_icmpne Label1
  getstatic LBSAPIProtocol/UINTYPE/__values [LLBSAPIProtocol/UINTYPE;
  astore_2
  aload_2
  iload_1
  aaload
  astore 4
  aload 4
  areturn
Label1:
  iload_1
  iconst_1
  iadd
  istore_1
  goto Label2
Label0:
  getstatic LBSAPIProtocol/UINTYPE/$assertionsDisabled Z
  istore 5
  iload 5
  invokestatic app/DummyClass/invokeIfStmt(Z)V
  iload 5
  ifne Label3
  new java/lang/AssertionError
  astore 6
  aload 6
  invokespecial java/lang/AssertionError/<init>()V
  aload 6
  athrow
Label3:
  aconst_null
  astore 7
  aload 7
  areturn
  nop
.end <method>

.method public static convert(Ljava/lang/String;)LLBSAPIProtocol/UINTYPE;
.limit locals 9
.limit stack 200
  nop
  iconst_0
  istore_1
Label2:
  getstatic LBSAPIProtocol/UINTYPE/__values [LLBSAPIProtocol/UINTYPE;
  astore_2
  aload_2
  arraylength
  istore_3
  new java/lang/NoClassDefFoundError
  dup
  invokespecial java/lang/NoClassDefFoundError/<init>()V
  athrow
  dload_3
  invokestatic app/DummyClass/invokeIfStmt(D)V
  iload_1
  iload_3
  if_icmpge Label0
  getstatic LBSAPIProtocol/UINTYPE/__values [LLBSAPIProtocol/UINTYPE;
  astore_2
  aload_2
  iload_1
  aaload
  astore 4
  aload 4
  invokevirtual LBSAPIProtocol/UINTYPE/toString()Ljava/lang/String;
  astore 5
  aload 5
  aload_0
  invokevirtual java/lang/String/equals(Ljava/lang/Object;)Z
  istore 6
  iload 6
  invokestatic app/DummyClass/invokeIfStmt(Z)V
  iload 6
  ifeq Label1
  getstatic LBSAPIProtocol/UINTYPE/__values [LLBSAPIProtocol/UINTYPE;
  astore_2
  aload_2
  iload_1
  aaload
  astore 4
  aload 4
  areturn
Label1:
  iload_1
  iconst_1
  iadd
  istore_1
  goto Label2
Label0:
  getstatic LBSAPIProtocol/UINTYPE/$assertionsDisabled Z
  istore 6
  iload 6
  invokestatic app/DummyClass/invokeIfStmt(Z)V
  iload 6
  ifne Label3
  new java/lang/AssertionError
  astore 7
  aload 7
  invokespecial java/lang/AssertionError/<init>()V
  aload 7
  athrow
Label3:
  aconst_null
  astore 8
  aload 8
  areturn
  nop
.end <method>

.method public toString()Ljava/lang/String;
.limit locals 2
.limit stack 200
  nop
  aload_0
  getfield LBSAPIProtocol/UINTYPE/__T Ljava/lang/String;
  astore_1
  aload_1
  areturn
  nop
.end <method>

.method public value()I
.limit locals 2
.limit stack 200
  nop
  aload_0
  getfield LBSAPIProtocol/UINTYPE/__value I
  istore_1
  iload_1
  ireturn
  nop
.end <method>

