.source dalvik_source_VirusShare_32e70f448ebd75661a1cb12f9cd8e013.apk
.class public final  LBSAPIProtocol/RspHeader
.super com/qq/taf/jce/JceStruct
.field static final "$assertionsDisabled" Z =  0
.field static "cache_eResult" I =  0
.field public "eResult" I
.field public "shVersion" S
.field public "strErrMsg" Ljava/lang/String;

.method static <clinit>()V
.limit locals 2
.limit stack 200
  nop
  ldc LBSAPIProtocol/RspHeader
  astore_0
  aload_0
  invokevirtual java/lang/Class/desiredAssertionStatus()Z
  istore_1
  new java/lang/NoClassDefFoundError
  dup
  invokespecial java/lang/NoClassDefFoundError/<init>()V
  athrow
  iload_1
  ifne Label0
  iconst_1
  istore_1
Label1:
  iload_1
  putstatic LBSAPIProtocol/RspHeader/$assertionsDisabled Z
  return
Label0:
  iconst_0
  istore_1
  goto Label1
  nop
.end <method>

.method public <init>()V
.limit locals 6
.limit stack 200
  nop
  aload_0
  invokespecial com/qq/taf/jce/JceStruct/<init>()V
  iconst_1
  istore_1
  aload_0
  iload_1
  putfield LBSAPIProtocol/RspHeader/shVersion S
  iconst_0
  istore_1
  aload_0
  iload_1
  putfield LBSAPIProtocol/RspHeader/eResult I
  ldc ""
  astore_2
  aload_0
  aload_2
  putfield LBSAPIProtocol/RspHeader/strErrMsg Ljava/lang/String;
  aload_0
  getfield LBSAPIProtocol/RspHeader/shVersion S
  istore_3
  aload_0
  iload_3
  invokevirtual LBSAPIProtocol/RspHeader/setShVersion(S)V
  aload_0
  getfield LBSAPIProtocol/RspHeader/eResult I
  istore 4
  aload_0
  iload 4
  invokevirtual LBSAPIProtocol/RspHeader/setEResult(I)V
  aload_0
  getfield LBSAPIProtocol/RspHeader/strErrMsg Ljava/lang/String;
  astore 5
  aload_0
  aload 5
  invokevirtual LBSAPIProtocol/RspHeader/setStrErrMsg(Ljava/lang/String;)V
  return
  nop
.end <method>

.method public <init>(SILjava/lang/String;)V
.limit locals 6
.limit stack 200
  nop
  aload_0
  invokespecial com/qq/taf/jce/JceStruct/<init>()V
  iconst_1
  istore 4
  aload_0
  iload 4
  putfield LBSAPIProtocol/RspHeader/shVersion S
  iconst_0
  istore 4
  aload_0
  iload 4
  putfield LBSAPIProtocol/RspHeader/eResult I
  ldc ""
  astore 5
  aload_0
  aload 5
  putfield LBSAPIProtocol/RspHeader/strErrMsg Ljava/lang/String;
  aload_0
  iload_1
  invokevirtual LBSAPIProtocol/RspHeader/setShVersion(S)V
  aload_0
  iload_2
  invokevirtual LBSAPIProtocol/RspHeader/setEResult(I)V
  aload_0
  aload_3
  invokevirtual LBSAPIProtocol/RspHeader/setStrErrMsg(Ljava/lang/String;)V
  return
  nop
.end <method>

.method public className()Ljava/lang/String;
.limit locals 2
.limit stack 200
  nop
  ldc "LBSAPIProtocol.RspHeader"
  astore_1
  aload_1
  areturn
  nop
.end <method>

.method public clone()Ljava/lang/Object;
.limit locals 6
.limit stack 200
  .catch  java/lang/CloneNotSupportedException <from> Label2 <to> Label3 <using> Label1
  nop
  iconst_0
  istore_1
Label2:
  aload_0
  invokespecial java/lang/Object/clone()Ljava/lang/Object;
  astore_2
Label3:
  aload_2
  astore_1
Label0:
  aload_1
  areturn
Label1:
  astore_3
  getstatic LBSAPIProtocol/RspHeader/$assertionsDisabled Z
  istore 4
  new java/lang/NoClassDefFoundError
  dup
  invokespecial java/lang/NoClassDefFoundError/<init>()V
  athrow
  iload 4
  ifne Label0
  new java/lang/AssertionError
  astore 5
  aload 5
  invokespecial java/lang/AssertionError/<init>()V
  aload 5
  athrow
  nop
.end <method>

.method public display(Ljava/lang/StringBuilder;I)V
.limit locals 7
.limit stack 200
  nop
  new com/qq/taf/jce/JceDisplayer
  astore_3
  aload_3
  aload_1
  iload_2
  invokespecial com/qq/taf/jce/JceDisplayer/<init>(Ljava/lang/StringBuilder;I)V
  aload_0
  getfield LBSAPIProtocol/RspHeader/shVersion S
  istore 4
  ldc "shVersion"
  astore 5
  aload_3
  iload 4
  aload 5
  invokevirtual com/qq/taf/jce/JceDisplayer/display(SLjava/lang/String;)Lcom/qq/taf/jce/JceDisplayer;
  pop
  aload_0
  getfield LBSAPIProtocol/RspHeader/eResult I
  istore_2
  ldc "eResult"
  astore 5
  aload_3
  iload_2
  aload 5
  invokevirtual com/qq/taf/jce/JceDisplayer/display(ILjava/lang/String;)Lcom/qq/taf/jce/JceDisplayer;
  pop
  aload_0
  getfield LBSAPIProtocol/RspHeader/strErrMsg Ljava/lang/String;
  astore 6
  ldc "strErrMsg"
  astore 5
  aload_3
  aload 6
  aload 5
  invokevirtual com/qq/taf/jce/JceDisplayer/display(Ljava/lang/String;Ljava/lang/String;)Lcom/qq/taf/jce/JceDisplayer;
  pop
  return
  nop
.end <method>

.method public equals(Ljava/lang/Object;)Z
.limit locals 12
.limit stack 200
  nop
  aload_1
  astore_3
  aload_3
  checkcast LBSAPIProtocol/RspHeader
  astore_3
  aload_3
  astore_2
  aload_0
  getfield LBSAPIProtocol/RspHeader/shVersion S
  istore 4
  aload_2
  getfield LBSAPIProtocol/RspHeader/shVersion S
  istore 5
  iload 4
  iload 5
  invokestatic com/qq/taf/jce/JceUtil/equals(SS)Z
  istore 6
  new java/lang/NoClassDefFoundError
  dup
  invokespecial java/lang/NoClassDefFoundError/<init>()V
  athrow
  iload 6
  ifeq Label0
  aload_0
  getfield LBSAPIProtocol/RspHeader/eResult I
  istore 7
  aload_2
  getfield LBSAPIProtocol/RspHeader/eResult I
  istore 8
  iload 7
  iload 8
  invokestatic com/qq/taf/jce/JceUtil/equals(II)Z
  istore 6
  iload 6
  invokestatic app/DummyClass/invokeIfStmt(Z)V
  iload 6
  ifeq Label0
  aload_0
  getfield LBSAPIProtocol/RspHeader/strErrMsg Ljava/lang/String;
  astore 9
  aload_2
  getfield LBSAPIProtocol/RspHeader/strErrMsg Ljava/lang/String;
  astore 10
  aload 9
  aload 10
  invokestatic com/qq/taf/jce/JceUtil/equals(Ljava/lang/Object;Ljava/lang/Object;)Z
  istore 6
  iload 6
  invokestatic app/DummyClass/invokeIfStmt(Z)V
  iload 6
  ifeq Label0
  iconst_1
  istore 11
  iload 11
  ireturn
Label0:
  iconst_0
  istore 11
  iload 11
  ireturn
  nop
.end <method>

.method public fullClassName()Ljava/lang/String;
.limit locals 2
.limit stack 200
  nop
  ldc "LBSAPIProtocol.RspHeader"
  astore_1
  aload_1
  areturn
  nop
.end <method>

.method public getEResult()I
.limit locals 2
.limit stack 200
  nop
  aload_0
  getfield LBSAPIProtocol/RspHeader/eResult I
  istore_1
  iload_1
  ireturn
  nop
.end <method>

.method public getShVersion()S
.limit locals 2
.limit stack 200
  nop
  aload_0
  getfield LBSAPIProtocol/RspHeader/shVersion S
  istore_1
  iload_1
  ireturn
  nop
.end <method>

.method public getStrErrMsg()Ljava/lang/String;
.limit locals 2
.limit stack 200
  nop
  aload_0
  getfield LBSAPIProtocol/RspHeader/strErrMsg Ljava/lang/String;
  astore_1
  aload_1
  areturn
  nop
.end <method>

.method public readFrom(Lcom/qq/taf/jce/JceInputStream;)V
.limit locals 8
.limit stack 200
  nop
  aload_0
  getfield LBSAPIProtocol/RspHeader/shVersion S
  istore_2
  iconst_0
  istore_3
  iconst_1
  istore 4
  aload_1
  iload_2
  iload_3
  iload 4
  invokevirtual com/qq/taf/jce/JceInputStream/read(SIZ)S
  istore_2
  aload_0
  iload_2
  invokevirtual LBSAPIProtocol/RspHeader/setShVersion(S)V
  aload_0
  getfield LBSAPIProtocol/RspHeader/eResult I
  istore 5
  iconst_1
  istore_3
  iload_3
  istore 6
  iconst_1
  istore_3
  aload_1
  iload 5
  iload 6
  iload_3
  invokevirtual com/qq/taf/jce/JceInputStream/read(IIZ)I
  istore 5
  aload_0
  iload 5
  invokevirtual LBSAPIProtocol/RspHeader/setEResult(I)V
  iconst_2
  istore_3
  iconst_1
  istore 4
  aload_1
  iload_3
  iload 4
  invokevirtual com/qq/taf/jce/JceInputStream/readString(IZ)Ljava/lang/String;
  astore 7
  aload_0
  aload 7
  invokevirtual LBSAPIProtocol/RspHeader/setStrErrMsg(Ljava/lang/String;)V
  return
  nop
.end <method>

.method public setEResult(I)V
.limit locals 2
.limit stack 200
  nop
  aload_0
  iload_1
  putfield LBSAPIProtocol/RspHeader/eResult I
  return
  nop
.end <method>

.method public setShVersion(S)V
.limit locals 2
.limit stack 200
  nop
  aload_0
  iload_1
  putfield LBSAPIProtocol/RspHeader/shVersion S
  return
  nop
.end <method>

.method public setStrErrMsg(Ljava/lang/String;)V
.limit locals 2
.limit stack 200
  nop
  aload_0
  aload_1
  putfield LBSAPIProtocol/RspHeader/strErrMsg Ljava/lang/String;
  return
  nop
.end <method>

.method public writeTo(Lcom/qq/taf/jce/JceOutputStream;)V
.limit locals 6
.limit stack 200
  nop
  aload_0
  getfield LBSAPIProtocol/RspHeader/shVersion S
  istore_2
  iconst_0
  istore_3
  aload_1
  iload_2
  iload_3
  invokevirtual com/qq/taf/jce/JceOutputStream/write(SI)V
  aload_0
  getfield LBSAPIProtocol/RspHeader/eResult I
  istore 4
  iconst_1
  istore_3
  aload_1
  iload 4
  iload_3
  invokevirtual com/qq/taf/jce/JceOutputStream/write(II)V
  aload_0
  getfield LBSAPIProtocol/RspHeader/strErrMsg Ljava/lang/String;
  astore 5
  iconst_2
  istore_3
  aload_1
  aload 5
  iload_3
  invokevirtual com/qq/taf/jce/JceOutputStream/write(Ljava/lang/String;I)V
  return
  nop
.end <method>

