.source dalvik_source_VirusShare_32e70f448ebd75661a1cb12f9cd8e013.apk
.class public final  LBSAPIProtocol/GPS
.super com/qq/taf/jce/JceStruct
.field static final "$assertionsDisabled" Z =  0
.field static "cache_eType" I =  0
.field public "eType" I
.field public "iAlt" I
.field public "iLat" I
.field public "iLon" I

.method static <clinit>()V
.limit locals 2
.limit stack 200
  nop
  ldc LBSAPIProtocol/GPS
  astore_0
  aload_0
  invokevirtual java/lang/Class/desiredAssertionStatus()Z
  istore_1
  new java/lang/NoClassDefFoundError
  dup
  invokespecial java/lang/NoClassDefFoundError/<init>()V
  athrow
  iload_1
  ifne Label0
  iconst_1
  istore_1
Label1:
  iload_1
  putstatic LBSAPIProtocol/GPS/$assertionsDisabled Z
  return
Label0:
  iconst_0
  istore_1
  goto Label1
  nop
.end <method>

.method public <init>()V
.limit locals 3
.limit stack 200
  nop
  aload_0
  invokespecial com/qq/taf/jce/JceStruct/<init>()V
  ldc 900000000
  istore_1
  aload_0
  iload_1
  putfield LBSAPIProtocol/GPS/iLat I
  ldc 900000000
  istore_1
  aload_0
  iload_1
  putfield LBSAPIProtocol/GPS/iLon I
  iconst_m1
  istore_1
  aload_0
  iload_1
  putfield LBSAPIProtocol/GPS/iAlt I
  iconst_0
  istore_1
  aload_0
  iload_1
  putfield LBSAPIProtocol/GPS/eType I
  aload_0
  getfield LBSAPIProtocol/GPS/iLat I
  istore_2
  aload_0
  iload_2
  invokevirtual LBSAPIProtocol/GPS/setILat(I)V
  aload_0
  getfield LBSAPIProtocol/GPS/iLon I
  istore_2
  aload_0
  iload_2
  invokevirtual LBSAPIProtocol/GPS/setILon(I)V
  aload_0
  getfield LBSAPIProtocol/GPS/iAlt I
  istore_2
  aload_0
  iload_2
  invokevirtual LBSAPIProtocol/GPS/setIAlt(I)V
  aload_0
  getfield LBSAPIProtocol/GPS/eType I
  istore_2
  aload_0
  iload_2
  invokevirtual LBSAPIProtocol/GPS/setEType(I)V
  return
  nop
.end <method>

.method public <init>(IIII)V
.limit locals 6
.limit stack 200
  nop
  aload_0
  invokespecial com/qq/taf/jce/JceStruct/<init>()V
  ldc 900000000
  istore 5
  aload_0
  iload 5
  putfield LBSAPIProtocol/GPS/iLat I
  ldc 900000000
  istore 5
  aload_0
  iload 5
  putfield LBSAPIProtocol/GPS/iLon I
  iconst_m1
  istore 5
  aload_0
  iload 5
  putfield LBSAPIProtocol/GPS/iAlt I
  iconst_0
  istore 5
  aload_0
  iload 5
  putfield LBSAPIProtocol/GPS/eType I
  aload_0
  iload_1
  invokevirtual LBSAPIProtocol/GPS/setILat(I)V
  aload_0
  iload_2
  invokevirtual LBSAPIProtocol/GPS/setILon(I)V
  aload_0
  iload_3
  invokevirtual LBSAPIProtocol/GPS/setIAlt(I)V
  aload_0
  iload 4
  invokevirtual LBSAPIProtocol/GPS/setEType(I)V
  return
  nop
.end <method>

.method public className()Ljava/lang/String;
.limit locals 2
.limit stack 200
  nop
  ldc "LBSAPIProtocol.GPS"
  astore_1
  aload_1
  areturn
  nop
.end <method>

.method public clone()Ljava/lang/Object;
.limit locals 6
.limit stack 200
  .catch  java/lang/CloneNotSupportedException <from> Label2 <to> Label3 <using> Label1
  nop
  iconst_0
  istore_1
Label2:
  aload_0
  invokespecial java/lang/Object/clone()Ljava/lang/Object;
  astore_2
Label3:
  aload_2
  astore_1
Label0:
  aload_1
  areturn
Label1:
  astore_3
  getstatic LBSAPIProtocol/GPS/$assertionsDisabled Z
  istore 4
  new java/lang/NoClassDefFoundError
  dup
  invokespecial java/lang/NoClassDefFoundError/<init>()V
  athrow
  iload 4
  ifne Label0
  new java/lang/AssertionError
  astore 5
  aload 5
  invokespecial java/lang/AssertionError/<init>()V
  aload 5
  athrow
  nop
.end <method>

.method public display(Ljava/lang/StringBuilder;I)V
.limit locals 5
.limit stack 200
  nop
  new com/qq/taf/jce/JceDisplayer
  astore_3
  aload_3
  aload_1
  iload_2
  invokespecial com/qq/taf/jce/JceDisplayer/<init>(Ljava/lang/StringBuilder;I)V
  aload_0
  getfield LBSAPIProtocol/GPS/iLat I
  istore_2
  ldc "iLat"
  astore 4
  aload_3
  iload_2
  aload 4
  invokevirtual com/qq/taf/jce/JceDisplayer/display(ILjava/lang/String;)Lcom/qq/taf/jce/JceDisplayer;
  pop
  aload_0
  getfield LBSAPIProtocol/GPS/iLon I
  istore_2
  ldc "iLon"
  astore 4
  aload_3
  iload_2
  aload 4
  invokevirtual com/qq/taf/jce/JceDisplayer/display(ILjava/lang/String;)Lcom/qq/taf/jce/JceDisplayer;
  pop
  aload_0
  getfield LBSAPIProtocol/GPS/iAlt I
  istore_2
  ldc "iAlt"
  astore 4
  aload_3
  iload_2
  aload 4
  invokevirtual com/qq/taf/jce/JceDisplayer/display(ILjava/lang/String;)Lcom/qq/taf/jce/JceDisplayer;
  pop
  aload_0
  getfield LBSAPIProtocol/GPS/eType I
  istore_2
  ldc "eType"
  astore 4
  aload_3
  iload_2
  aload 4
  invokevirtual com/qq/taf/jce/JceDisplayer/display(ILjava/lang/String;)Lcom/qq/taf/jce/JceDisplayer;
  pop
  return
  nop
.end <method>

.method public equals(Ljava/lang/Object;)Z
.limit locals 8
.limit stack 200
  nop
  aload_1
  astore_3
  aload_3
  checkcast LBSAPIProtocol/GPS
  astore_3
  aload_3
  astore_2
  aload_0
  getfield LBSAPIProtocol/GPS/iLat I
  istore 4
  aload_2
  getfield LBSAPIProtocol/GPS/iLat I
  istore 5
  iload 4
  iload 5
  invokestatic com/qq/taf/jce/JceUtil/equals(II)Z
  istore 6
  new java/lang/NoClassDefFoundError
  dup
  invokespecial java/lang/NoClassDefFoundError/<init>()V
  athrow
  iload 6
  ifeq Label0
  aload_0
  getfield LBSAPIProtocol/GPS/iLon I
  istore 5
  aload_2
  getfield LBSAPIProtocol/GPS/iLon I
  istore 4
  iload 5
  iload 4
  invokestatic com/qq/taf/jce/JceUtil/equals(II)Z
  istore 6
  iload 6
  invokestatic app/DummyClass/invokeIfStmt(Z)V
  iload 6
  ifeq Label0
  aload_0
  getfield LBSAPIProtocol/GPS/iAlt I
  istore 5
  aload_2
  getfield LBSAPIProtocol/GPS/iAlt I
  istore 4
  iload 5
  iload 4
  invokestatic com/qq/taf/jce/JceUtil/equals(II)Z
  istore 6
  iload 6
  invokestatic app/DummyClass/invokeIfStmt(Z)V
  iload 6
  ifeq Label0
  aload_0
  getfield LBSAPIProtocol/GPS/eType I
  istore 5
  aload_2
  getfield LBSAPIProtocol/GPS/eType I
  istore 4
  iload 5
  iload 4
  invokestatic com/qq/taf/jce/JceUtil/equals(II)Z
  istore 6
  iload 6
  invokestatic app/DummyClass/invokeIfStmt(Z)V
  iload 6
  ifeq Label0
  iconst_1
  istore 7
  iload 7
  ireturn
Label0:
  iconst_0
  istore 7
  iload 7
  ireturn
  nop
.end <method>

.method public fullClassName()Ljava/lang/String;
.limit locals 2
.limit stack 200
  nop
  ldc "LBSAPIProtocol.GPS"
  astore_1
  aload_1
  areturn
  nop
.end <method>

.method public getEType()I
.limit locals 2
.limit stack 200
  nop
  aload_0
  getfield LBSAPIProtocol/GPS/eType I
  istore_1
  iload_1
  ireturn
  nop
.end <method>

.method public getIAlt()I
.limit locals 2
.limit stack 200
  nop
  aload_0
  getfield LBSAPIProtocol/GPS/iAlt I
  istore_1
  iload_1
  ireturn
  nop
.end <method>

.method public getILat()I
.limit locals 2
.limit stack 200
  nop
  aload_0
  getfield LBSAPIProtocol/GPS/iLat I
  istore_1
  iload_1
  ireturn
  nop
.end <method>

.method public getILon()I
.limit locals 2
.limit stack 200
  nop
  aload_0
  getfield LBSAPIProtocol/GPS/iLon I
  istore_1
  iload_1
  ireturn
  nop
.end <method>

.method public readFrom(Lcom/qq/taf/jce/JceInputStream;)V
.limit locals 6
.limit stack 200
  nop
  aload_0
  getfield LBSAPIProtocol/GPS/iLat I
  istore_2
  iconst_0
  istore 4
  iconst_1
  istore 5
  aload_1
  iload_2
  iload 4
  iload 5
  invokevirtual com/qq/taf/jce/JceInputStream/read(IIZ)I
  istore_3
  aload_0
  iload_3
  invokevirtual LBSAPIProtocol/GPS/setILat(I)V
  aload_0
  getfield LBSAPIProtocol/GPS/iLon I
  istore_3
  iconst_1
  istore 4
  iload 4
  istore_2
  iconst_1
  istore 4
  aload_1
  iload_3
  iload_2
  iload 4
  invokevirtual com/qq/taf/jce/JceInputStream/read(IIZ)I
  istore_3
  aload_0
  iload_3
  invokevirtual LBSAPIProtocol/GPS/setILon(I)V
  aload_0
  getfield LBSAPIProtocol/GPS/iAlt I
  istore_3
  iconst_2
  istore 4
  iconst_1
  istore 5
  aload_1
  iload_3
  iload 4
  iload 5
  invokevirtual com/qq/taf/jce/JceInputStream/read(IIZ)I
  istore_3
  aload_0
  iload_3
  invokevirtual LBSAPIProtocol/GPS/setIAlt(I)V
  aload_0
  getfield LBSAPIProtocol/GPS/eType I
  istore_3
  iconst_3
  istore 4
  iconst_1
  istore 5
  aload_1
  iload_3
  iload 4
  iload 5
  invokevirtual com/qq/taf/jce/JceInputStream/read(IIZ)I
  istore_3
  aload_0
  iload_3
  invokevirtual LBSAPIProtocol/GPS/setEType(I)V
  return
  nop
.end <method>

.method public setEType(I)V
.limit locals 2
.limit stack 200
  nop
  aload_0
  iload_1
  putfield LBSAPIProtocol/GPS/eType I
  return
  nop
.end <method>

.method public setIAlt(I)V
.limit locals 2
.limit stack 200
  nop
  aload_0
  iload_1
  putfield LBSAPIProtocol/GPS/iAlt I
  return
  nop
.end <method>

.method public setILat(I)V
.limit locals 2
.limit stack 200
  nop
  aload_0
  iload_1
  putfield LBSAPIProtocol/GPS/iLat I
  return
  nop
.end <method>

.method public setILon(I)V
.limit locals 2
.limit stack 200
  nop
  aload_0
  iload_1
  putfield LBSAPIProtocol/GPS/iLon I
  return
  nop
.end <method>

.method public writeTo(Lcom/qq/taf/jce/JceOutputStream;)V
.limit locals 4
.limit stack 200
  nop
  aload_0
  getfield LBSAPIProtocol/GPS/iLat I
  istore_2
  iconst_0
  istore_3
  aload_1
  iload_2
  iload_3
  invokevirtual com/qq/taf/jce/JceOutputStream/write(II)V
  aload_0
  getfield LBSAPIProtocol/GPS/iLon I
  istore_2
  iconst_1
  istore_3
  aload_1
  iload_2
  iload_3
  invokevirtual com/qq/taf/jce/JceOutputStream/write(II)V
  aload_0
  getfield LBSAPIProtocol/GPS/iAlt I
  istore_2
  iconst_2
  istore_3
  aload_1
  iload_2
  iload_3
  invokevirtual com/qq/taf/jce/JceOutputStream/write(II)V
  aload_0
  getfield LBSAPIProtocol/GPS/eType I
  istore_2
  iconst_3
  istore_3
  aload_1
  iload_2
  iload_3
  invokevirtual com/qq/taf/jce/JceOutputStream/write(II)V
  return
  nop
.end <method>

