.source dalvik_source_VirusShare_32e70f448ebd75661a1cb12f9cd8e013.apk
.class public final  LBSAPIProtocol/GPSTYPE
.super java/lang/Object
.field static final "$assertionsDisabled" Z =  0
.field public static final "GPS_MARS" LLBSAPIProtocol/GPSTYPE;
.field public static final "GPS_WGS84" LLBSAPIProtocol/GPSTYPE;
.field public static final "GPS_WGS_REAL" LLBSAPIProtocol/GPSTYPE;
.field public static final "_GPS_MARS" I =  1
.field public static final "_GPS_WGS84" I =  0
.field public static final "_GPS_WGS_REAL" I =  2
.field private static "__values" [LLBSAPIProtocol/GPSTYPE;
.field private "__T" Ljava/lang/String;
.field private "__value" I

.method static <clinit>()V
.limit locals 9
.limit stack 200
  nop
  ldc LBSAPIProtocol/GPSTYPE
  astore_0
  aload_0
  invokevirtual java/lang/Class/desiredAssertionStatus()Z
  istore_1
  new java/lang/NoClassDefFoundError
  dup
  invokespecial java/lang/NoClassDefFoundError/<init>()V
  athrow
  iload_1
  ifne Label0
  iconst_1
  istore_1
Label1:
  iload_1
  putstatic LBSAPIProtocol/GPSTYPE/$assertionsDisabled Z
  iconst_3
  istore_3
  iload_3
  anewarray LBSAPIProtocol/GPSTYPE
  astore_2
  aload_2
  putstatic LBSAPIProtocol/GPSTYPE/__values [LLBSAPIProtocol/GPSTYPE;
  new LBSAPIProtocol/GPSTYPE
  astore 4
  iconst_0
  istore_3
  iload_3
  istore 5
  iconst_0
  istore_3
  iload_3
  istore 6
  ldc "GPS_WGS84"
  astore 7
  aload 4
  iload 5
  iload 6
  aload 7
  invokespecial LBSAPIProtocol/GPSTYPE/<init>(IILjava/lang/String;)V
  aload 4
  putstatic LBSAPIProtocol/GPSTYPE/GPS_WGS84 LLBSAPIProtocol/GPSTYPE;
  new LBSAPIProtocol/GPSTYPE
  astore 4
  iconst_1
  istore_3
  iload_3
  istore 6
  iconst_1
  istore_3
  iload_3
  istore 5
  ldc "GPS_MARS"
  astore 7
  aload 4
  iload 6
  iload 5
  aload 7
  invokespecial LBSAPIProtocol/GPSTYPE/<init>(IILjava/lang/String;)V
  aload 4
  putstatic LBSAPIProtocol/GPSTYPE/GPS_MARS LLBSAPIProtocol/GPSTYPE;
  new LBSAPIProtocol/GPSTYPE
  astore 4
  iconst_2
  istore_3
  iconst_2
  istore 8
  ldc "GPS_WGS_REAL"
  astore 7
  aload 4
  iload_3
  iload 8
  aload 7
  invokespecial LBSAPIProtocol/GPSTYPE/<init>(IILjava/lang/String;)V
  aload 4
  putstatic LBSAPIProtocol/GPSTYPE/GPS_WGS_REAL LLBSAPIProtocol/GPSTYPE;
  return
Label0:
  iconst_0
  istore_1
  goto Label1
  nop
.end <method>

.method private <init>(IILjava/lang/String;)V
.limit locals 6
.limit stack 200
  nop
  aload_0
  invokespecial java/lang/Object/<init>()V
  new java/lang/String
  astore 4
  aload 4
  invokespecial java/lang/String/<init>()V
  aload_0
  aload 4
  putfield LBSAPIProtocol/GPSTYPE/__T Ljava/lang/String;
  aload_0
  aload_3
  putfield LBSAPIProtocol/GPSTYPE/__T Ljava/lang/String;
  aload_0
  iload_2
  putfield LBSAPIProtocol/GPSTYPE/__value I
  getstatic LBSAPIProtocol/GPSTYPE/__values [LLBSAPIProtocol/GPSTYPE;
  astore 5
  aload 5
  iload_1
  aload_0
  aastore
  return
  nop
.end <method>

.method public static convert(I)LLBSAPIProtocol/GPSTYPE;
.limit locals 8
.limit stack 200
  nop
  iconst_0
  istore_1
Label2:
  getstatic LBSAPIProtocol/GPSTYPE/__values [LLBSAPIProtocol/GPSTYPE;
  astore_2
  aload_2
  arraylength
  istore_3
  new java/lang/NoClassDefFoundError
  dup
  invokespecial java/lang/NoClassDefFoundError/<init>()V
  athrow
  dload_3
  invokestatic app/DummyClass/invokeIfStmt(D)V
  iload_1
  iload_3
  if_icmpge Label0
  getstatic LBSAPIProtocol/GPSTYPE/__values [LLBSAPIProtocol/GPSTYPE;
  astore_2
  aload_2
  iload_1
  aaload
  astore 4
  aload 4
  invokevirtual LBSAPIProtocol/GPSTYPE/value()I
  istore_3
  dload_3
  invokestatic app/DummyClass/invokeIfStmt(D)V
  dload_0
  invokestatic app/DummyClass/invokeIfStmt(D)V
  iload_3
  iload_0
  if_icmpne Label1
  getstatic LBSAPIProtocol/GPSTYPE/__values [LLBSAPIProtocol/GPSTYPE;
  astore_2
  aload_2
  iload_1
  aaload
  astore 4
  aload 4
  areturn
Label1:
  iload_1
  iconst_1
  iadd
  istore_1
  goto Label2
Label0:
  getstatic LBSAPIProtocol/GPSTYPE/$assertionsDisabled Z
  istore 5
  iload 5
  invokestatic app/DummyClass/invokeIfStmt(Z)V
  iload 5
  ifne Label3
  new java/lang/AssertionError
  astore 6
  aload 6
  invokespecial java/lang/AssertionError/<init>()V
  aload 6
  athrow
Label3:
  aconst_null
  astore 7
  aload 7
  areturn
  nop
.end <method>

.method public static convert(Ljava/lang/String;)LLBSAPIProtocol/GPSTYPE;
.limit locals 9
.limit stack 200
  nop
  iconst_0
  istore_1
Label2:
  getstatic LBSAPIProtocol/GPSTYPE/__values [LLBSAPIProtocol/GPSTYPE;
  astore_2
  aload_2
  arraylength
  istore_3
  new java/lang/NoClassDefFoundError
  dup
  invokespecial java/lang/NoClassDefFoundError/<init>()V
  athrow
  dload_3
  invokestatic app/DummyClass/invokeIfStmt(D)V
  iload_1
  iload_3
  if_icmpge Label0
  getstatic LBSAPIProtocol/GPSTYPE/__values [LLBSAPIProtocol/GPSTYPE;
  astore_2
  aload_2
  iload_1
  aaload
  astore 4
  aload 4
  invokevirtual LBSAPIProtocol/GPSTYPE/toString()Ljava/lang/String;
  astore 5
  aload 5
  aload_0
  invokevirtual java/lang/String/equals(Ljava/lang/Object;)Z
  istore 6
  iload 6
  invokestatic app/DummyClass/invokeIfStmt(Z)V
  iload 6
  ifeq Label1
  getstatic LBSAPIProtocol/GPSTYPE/__values [LLBSAPIProtocol/GPSTYPE;
  astore_2
  aload_2
  iload_1
  aaload
  astore 4
  aload 4
  areturn
Label1:
  iload_1
  iconst_1
  iadd
  istore_1
  goto Label2
Label0:
  getstatic LBSAPIProtocol/GPSTYPE/$assertionsDisabled Z
  istore 6
  iload 6
  invokestatic app/DummyClass/invokeIfStmt(Z)V
  iload 6
  ifne Label3
  new java/lang/AssertionError
  astore 7
  aload 7
  invokespecial java/lang/AssertionError/<init>()V
  aload 7
  athrow
Label3:
  aconst_null
  astore 8
  aload 8
  areturn
  nop
.end <method>

.method public toString()Ljava/lang/String;
.limit locals 2
.limit stack 200
  nop
  aload_0
  getfield LBSAPIProtocol/GPSTYPE/__T Ljava/lang/String;
  astore_1
  aload_1
  areturn
  nop
.end <method>

.method public value()I
.limit locals 2
.limit stack 200
  nop
  aload_0
  getfield LBSAPIProtocol/GPSTYPE/__value I
  istore_1
  iload_1
  ireturn
  nop
.end <method>

