.source dalvik_source_VirusShare_32e70f448ebd75661a1cb12f9cd8e013.apk
.class public final  LBSAPIProtocol/DeviceData
.super com/qq/taf/jce/JceStruct
.field static final "$assertionsDisabled" Z =  0
.field static "cache_eDeviceType" I =  0
.field static "cache_stCurMeasure" LLBSAPIProtocol/Measure;
.field static "cache_vMeasures" Ljava/util/ArrayList;
.field public "eDeviceType" I
.field public "stCurMeasure" LLBSAPIProtocol/Measure;
.field public "strAppUA" Ljava/lang/String;
.field public "strImei" Ljava/lang/String;
.field public "vMeasures" Ljava/util/ArrayList;

.method static <clinit>()V
.limit locals 2
.limit stack 200
  nop
  ldc LBSAPIProtocol/DeviceData
  astore_0
  aload_0
  invokevirtual java/lang/Class/desiredAssertionStatus()Z
  istore_1
  new java/lang/NoClassDefFoundError
  dup
  invokespecial java/lang/NoClassDefFoundError/<init>()V
  athrow
  iload_1
  ifne Label0
  iconst_1
  istore_1
Label1:
  iload_1
  putstatic LBSAPIProtocol/DeviceData/$assertionsDisabled Z
  return
Label0:
  iconst_0
  istore_1
  goto Label1
  nop
.end <method>

.method public <init>()V
.limit locals 8
.limit stack 200
  nop
  aload_0
  invokespecial com/qq/taf/jce/JceStruct/<init>()V
  aconst_null
  astore_1
  aload_0
  aload_1
  putfield LBSAPIProtocol/DeviceData/stCurMeasure LLBSAPIProtocol/Measure;
  aconst_null
  astore_1
  aload_0
  aload_1
  putfield LBSAPIProtocol/DeviceData/vMeasures Ljava/util/ArrayList;
  ldc ""
  astore_2
  aload_0
  aload_2
  putfield LBSAPIProtocol/DeviceData/strAppUA Ljava/lang/String;
  ldc ""
  astore_2
  aload_0
  aload_2
  putfield LBSAPIProtocol/DeviceData/strImei Ljava/lang/String;
  iconst_0
  istore_3
  aload_0
  iload_3
  putfield LBSAPIProtocol/DeviceData/eDeviceType I
  aload_0
  getfield LBSAPIProtocol/DeviceData/stCurMeasure LLBSAPIProtocol/Measure;
  astore 4
  aload_0
  aload 4
  invokevirtual LBSAPIProtocol/DeviceData/setStCurMeasure(LLBSAPIProtocol/Measure;)V
  aload_0
  getfield LBSAPIProtocol/DeviceData/vMeasures Ljava/util/ArrayList;
  astore 5
  aload_0
  aload 5
  invokevirtual LBSAPIProtocol/DeviceData/setVMeasures(Ljava/util/ArrayList;)V
  aload_0
  getfield LBSAPIProtocol/DeviceData/strAppUA Ljava/lang/String;
  astore 6
  aload_0
  aload 6
  invokevirtual LBSAPIProtocol/DeviceData/setStrAppUA(Ljava/lang/String;)V
  aload_0
  getfield LBSAPIProtocol/DeviceData/strImei Ljava/lang/String;
  astore 6
  aload_0
  aload 6
  invokevirtual LBSAPIProtocol/DeviceData/setStrImei(Ljava/lang/String;)V
  aload_0
  getfield LBSAPIProtocol/DeviceData/eDeviceType I
  istore 7
  aload_0
  iload 7
  invokevirtual LBSAPIProtocol/DeviceData/setEDeviceType(I)V
  return
  nop
.end <method>

.method public <init>(LLBSAPIProtocol/Measure;Ljava/util/ArrayList;Ljava/lang/String;Ljava/lang/String;I)V
.limit locals 9
.limit stack 200
  nop
  aload_0
  invokespecial com/qq/taf/jce/JceStruct/<init>()V
  aconst_null
  astore 6
  aload_0
  aload 6
  putfield LBSAPIProtocol/DeviceData/stCurMeasure LLBSAPIProtocol/Measure;
  aconst_null
  astore 6
  aload_0
  aload 6
  putfield LBSAPIProtocol/DeviceData/vMeasures Ljava/util/ArrayList;
  ldc ""
  astore 7
  aload_0
  aload 7
  putfield LBSAPIProtocol/DeviceData/strAppUA Ljava/lang/String;
  ldc ""
  astore 7
  aload_0
  aload 7
  putfield LBSAPIProtocol/DeviceData/strImei Ljava/lang/String;
  iconst_0
  istore 8
  aload_0
  iload 8
  putfield LBSAPIProtocol/DeviceData/eDeviceType I
  aload_0
  aload_1
  invokevirtual LBSAPIProtocol/DeviceData/setStCurMeasure(LLBSAPIProtocol/Measure;)V
  aload_0
  aload_2
  invokevirtual LBSAPIProtocol/DeviceData/setVMeasures(Ljava/util/ArrayList;)V
  aload_0
  aload_3
  invokevirtual LBSAPIProtocol/DeviceData/setStrAppUA(Ljava/lang/String;)V
  aload_0
  aload 4
  invokevirtual LBSAPIProtocol/DeviceData/setStrImei(Ljava/lang/String;)V
  aload_0
  iload 5
  invokevirtual LBSAPIProtocol/DeviceData/setEDeviceType(I)V
  return
  nop
.end <method>

.method public className()Ljava/lang/String;
.limit locals 2
.limit stack 200
  nop
  ldc "LBSAPIProtocol.DeviceData"
  astore_1
  aload_1
  areturn
  nop
.end <method>

.method public clone()Ljava/lang/Object;
.limit locals 6
.limit stack 200
  .catch  java/lang/CloneNotSupportedException <from> Label2 <to> Label3 <using> Label1
  nop
  iconst_0
  istore_1
Label2:
  aload_0
  invokespecial java/lang/Object/clone()Ljava/lang/Object;
  astore_2
Label3:
  aload_2
  astore_1
Label0:
  aload_1
  areturn
Label1:
  astore_3
  getstatic LBSAPIProtocol/DeviceData/$assertionsDisabled Z
  istore 4
  new java/lang/NoClassDefFoundError
  dup
  invokespecial java/lang/NoClassDefFoundError/<init>()V
  athrow
  iload 4
  ifne Label0
  new java/lang/AssertionError
  astore 5
  aload 5
  invokespecial java/lang/AssertionError/<init>()V
  aload 5
  athrow
  nop
.end <method>

.method public display(Ljava/lang/StringBuilder;I)V
.limit locals 9
.limit stack 200
  nop
  new com/qq/taf/jce/JceDisplayer
  astore_3
  aload_3
  aload_1
  iload_2
  invokespecial com/qq/taf/jce/JceDisplayer/<init>(Ljava/lang/StringBuilder;I)V
  aload_0
  getfield LBSAPIProtocol/DeviceData/stCurMeasure LLBSAPIProtocol/Measure;
  astore 4
  ldc "stCurMeasure"
  astore 5
  aload_3
  aload 4
  aload 5
  invokevirtual com/qq/taf/jce/JceDisplayer/display(Lcom/qq/taf/jce/JceStruct;Ljava/lang/String;)Lcom/qq/taf/jce/JceDisplayer;
  pop
  aload_0
  getfield LBSAPIProtocol/DeviceData/vMeasures Ljava/util/ArrayList;
  astore 6
  ldc "vMeasures"
  astore 5
  aload_3
  aload 6
  aload 5
  invokevirtual com/qq/taf/jce/JceDisplayer/display(Ljava/util/Collection;Ljava/lang/String;)Lcom/qq/taf/jce/JceDisplayer;
  pop
  aload_0
  getfield LBSAPIProtocol/DeviceData/strAppUA Ljava/lang/String;
  astore 7
  ldc "strAppUA"
  astore 5
  aload_3
  aload 7
  aload 5
  invokevirtual com/qq/taf/jce/JceDisplayer/display(Ljava/lang/String;Ljava/lang/String;)Lcom/qq/taf/jce/JceDisplayer;
  pop
  aload_0
  getfield LBSAPIProtocol/DeviceData/strImei Ljava/lang/String;
  astore 8
  ldc "strImei"
  astore 5
  aload_3
  aload 8
  aload 5
  invokevirtual com/qq/taf/jce/JceDisplayer/display(Ljava/lang/String;Ljava/lang/String;)Lcom/qq/taf/jce/JceDisplayer;
  pop
  aload_0
  getfield LBSAPIProtocol/DeviceData/eDeviceType I
  istore_2
  ldc "eDeviceType"
  astore 5
  aload_3
  iload_2
  aload 5
  invokevirtual com/qq/taf/jce/JceDisplayer/display(ILjava/lang/String;)Lcom/qq/taf/jce/JceDisplayer;
  pop
  return
  nop
.end <method>

.method public equals(Ljava/lang/Object;)Z
.limit locals 14
.limit stack 200
  nop
  aload_1
  astore_3
  aload_3
  checkcast LBSAPIProtocol/DeviceData
  astore_3
  aload_3
  astore_2
  aload_0
  getfield LBSAPIProtocol/DeviceData/stCurMeasure LLBSAPIProtocol/Measure;
  astore 4
  aload_2
  getfield LBSAPIProtocol/DeviceData/stCurMeasure LLBSAPIProtocol/Measure;
  astore 5
  aload 4
  aload 5
  invokestatic com/qq/taf/jce/JceUtil/equals(Ljava/lang/Object;Ljava/lang/Object;)Z
  istore 6
  new java/lang/NoClassDefFoundError
  dup
  invokespecial java/lang/NoClassDefFoundError/<init>()V
  athrow
  iload 6
  ifeq Label0
  aload_0
  getfield LBSAPIProtocol/DeviceData/vMeasures Ljava/util/ArrayList;
  astore 7
  aload_2
  getfield LBSAPIProtocol/DeviceData/vMeasures Ljava/util/ArrayList;
  astore 8
  aload 7
  aload 8
  invokestatic com/qq/taf/jce/JceUtil/equals(Ljava/lang/Object;Ljava/lang/Object;)Z
  istore 6
  iload 6
  invokestatic app/DummyClass/invokeIfStmt(Z)V
  iload 6
  ifeq Label0
  aload_0
  getfield LBSAPIProtocol/DeviceData/strAppUA Ljava/lang/String;
  astore 9
  aload_2
  getfield LBSAPIProtocol/DeviceData/strAppUA Ljava/lang/String;
  astore 10
  aload 9
  aload 10
  invokestatic com/qq/taf/jce/JceUtil/equals(Ljava/lang/Object;Ljava/lang/Object;)Z
  istore 6
  iload 6
  invokestatic app/DummyClass/invokeIfStmt(Z)V
  iload 6
  ifeq Label0
  aload_0
  getfield LBSAPIProtocol/DeviceData/strImei Ljava/lang/String;
  astore 10
  aload_2
  getfield LBSAPIProtocol/DeviceData/strImei Ljava/lang/String;
  astore 9
  aload 10
  aload 9
  invokestatic com/qq/taf/jce/JceUtil/equals(Ljava/lang/Object;Ljava/lang/Object;)Z
  istore 6
  iload 6
  invokestatic app/DummyClass/invokeIfStmt(Z)V
  iload 6
  ifeq Label0
  aload_0
  getfield LBSAPIProtocol/DeviceData/eDeviceType I
  istore 11
  aload_2
  getfield LBSAPIProtocol/DeviceData/eDeviceType I
  istore 12
  iload 11
  iload 12
  invokestatic com/qq/taf/jce/JceUtil/equals(II)Z
  istore 6
  iload 6
  invokestatic app/DummyClass/invokeIfStmt(Z)V
  iload 6
  ifeq Label0
  iconst_1
  istore 13
  iload 13
  ireturn
Label0:
  iconst_0
  istore 13
  iload 13
  ireturn
  nop
.end <method>

.method public fullClassName()Ljava/lang/String;
.limit locals 2
.limit stack 200
  nop
  ldc "LBSAPIProtocol.DeviceData"
  astore_1
  aload_1
  areturn
  nop
.end <method>

.method public getEDeviceType()I
.limit locals 2
.limit stack 200
  nop
  aload_0
  getfield LBSAPIProtocol/DeviceData/eDeviceType I
  istore_1
  iload_1
  ireturn
  nop
.end <method>

.method public getStCurMeasure()LLBSAPIProtocol/Measure;
.limit locals 2
.limit stack 200
  nop
  aload_0
  getfield LBSAPIProtocol/DeviceData/stCurMeasure LLBSAPIProtocol/Measure;
  astore_1
  aload_1
  areturn
  nop
.end <method>

.method public getStrAppUA()Ljava/lang/String;
.limit locals 2
.limit stack 200
  nop
  aload_0
  getfield LBSAPIProtocol/DeviceData/strAppUA Ljava/lang/String;
  astore_1
  aload_1
  areturn
  nop
.end <method>

.method public getStrImei()Ljava/lang/String;
.limit locals 2
.limit stack 200
  nop
  aload_0
  getfield LBSAPIProtocol/DeviceData/strImei Ljava/lang/String;
  astore_1
  aload_1
  areturn
  nop
.end <method>

.method public getVMeasures()Ljava/util/ArrayList;
.limit locals 2
.limit stack 200
  nop
  aload_0
  getfield LBSAPIProtocol/DeviceData/vMeasures Ljava/util/ArrayList;
  astore_1
  aload_1
  areturn
  nop
.end <method>

.method public readFrom(Lcom/qq/taf/jce/JceInputStream;)V
.limit locals 13
.limit stack 200
  nop
  getstatic LBSAPIProtocol/DeviceData/cache_stCurMeasure LLBSAPIProtocol/Measure;
  astore_2
  new java/lang/NoClassDefFoundError
  dup
  invokespecial java/lang/NoClassDefFoundError/<init>()V
  athrow
  iload_2
  ifne Label0
  new LBSAPIProtocol/Measure
  astore_2
  aload_2
  invokespecial LBSAPIProtocol/Measure/<init>()V
  aload_2
  putstatic LBSAPIProtocol/DeviceData/cache_stCurMeasure LLBSAPIProtocol/Measure;
Label0:
  getstatic LBSAPIProtocol/DeviceData/cache_stCurMeasure LLBSAPIProtocol/Measure;
  astore_2
  iconst_0
  istore 4
  iconst_1
  istore 5
  aload_1
  aload_2
  iload 4
  iload 5
  invokevirtual com/qq/taf/jce/JceInputStream/read(Lcom/qq/taf/jce/JceStruct;IZ)Lcom/qq/taf/jce/JceStruct;
  astore_3
  aload_3
  astore 6
  aload 6
  checkcast LBSAPIProtocol/Measure
  astore 6
  aload 6
  astore_2
  aload_0
  aload_2
  invokevirtual LBSAPIProtocol/DeviceData/setStCurMeasure(LLBSAPIProtocol/Measure;)V
  getstatic LBSAPIProtocol/DeviceData/cache_vMeasures Ljava/util/ArrayList;
  astore 7
  aload 7
  invokestatic app/DummyClass/invokeIfStmt(Ljava/lang/Object;)V
  aload 7
  ifnonnull Label1
  new java/util/ArrayList
  astore 7
  aload 7
  invokespecial java/util/ArrayList/<init>()V
  aload 7
  putstatic LBSAPIProtocol/DeviceData/cache_vMeasures Ljava/util/ArrayList;
  new LBSAPIProtocol/Measure
  astore_2
  aload_2
  invokespecial LBSAPIProtocol/Measure/<init>()V
  getstatic LBSAPIProtocol/DeviceData/cache_vMeasures Ljava/util/ArrayList;
  astore 7
  aload 7
  aload_2
  invokevirtual java/util/ArrayList/add(Ljava/lang/Object;)Z
  pop
Label1:
  getstatic LBSAPIProtocol/DeviceData/cache_vMeasures Ljava/util/ArrayList;
  astore 7
  iconst_1
  istore 4
  iload 4
  istore 8
  iconst_1
  istore 4
  aload_1
  aload 7
  iload 8
  iload 4
  invokevirtual com/qq/taf/jce/JceInputStream/read(Ljava/lang/Object;IZ)Ljava/lang/Object;
  astore 9
  aload 9
  astore 10
  aload 10
  checkcast java/util/ArrayList
  astore 10
  aload 10
  astore 7
  aload_0
  aload 7
  invokevirtual LBSAPIProtocol/DeviceData/setVMeasures(Ljava/util/ArrayList;)V
  iconst_2
  istore 4
  iconst_1
  istore 5
  aload_1
  iload 4
  iload 5
  invokevirtual com/qq/taf/jce/JceInputStream/readString(IZ)Ljava/lang/String;
  astore 11
  aload_0
  aload 11
  invokevirtual LBSAPIProtocol/DeviceData/setStrAppUA(Ljava/lang/String;)V
  iconst_3
  istore 4
  iconst_1
  istore 5
  aload_1
  iload 4
  iload 5
  invokevirtual com/qq/taf/jce/JceInputStream/readString(IZ)Ljava/lang/String;
  astore 11
  aload_0
  aload 11
  invokevirtual LBSAPIProtocol/DeviceData/setStrImei(Ljava/lang/String;)V
  aload_0
  getfield LBSAPIProtocol/DeviceData/eDeviceType I
  istore 12
  iconst_4
  istore 4
  iconst_1
  istore 5
  aload_1
  iload 12
  iload 4
  iload 5
  invokevirtual com/qq/taf/jce/JceInputStream/read(IIZ)I
  istore 8
  aload_0
  iload 8
  invokevirtual LBSAPIProtocol/DeviceData/setEDeviceType(I)V
  return
  nop
.end <method>

.method public setEDeviceType(I)V
.limit locals 2
.limit stack 200
  nop
  aload_0
  iload_1
  putfield LBSAPIProtocol/DeviceData/eDeviceType I
  return
  nop
.end <method>

.method public setStCurMeasure(LLBSAPIProtocol/Measure;)V
.limit locals 2
.limit stack 200
  nop
  aload_0
  aload_1
  putfield LBSAPIProtocol/DeviceData/stCurMeasure LLBSAPIProtocol/Measure;
  return
  nop
.end <method>

.method public setStrAppUA(Ljava/lang/String;)V
.limit locals 2
.limit stack 200
  nop
  aload_0
  aload_1
  putfield LBSAPIProtocol/DeviceData/strAppUA Ljava/lang/String;
  return
  nop
.end <method>

.method public setStrImei(Ljava/lang/String;)V
.limit locals 2
.limit stack 200
  nop
  aload_0
  aload_1
  putfield LBSAPIProtocol/DeviceData/strImei Ljava/lang/String;
  return
  nop
.end <method>

.method public setVMeasures(Ljava/util/ArrayList;)V
.limit locals 2
.limit stack 200
  nop
  aload_0
  aload_1
  putfield LBSAPIProtocol/DeviceData/vMeasures Ljava/util/ArrayList;
  return
  nop
.end <method>

.method public writeTo(Lcom/qq/taf/jce/JceOutputStream;)V
.limit locals 7
.limit stack 200
  nop
  aload_0
  getfield LBSAPIProtocol/DeviceData/stCurMeasure LLBSAPIProtocol/Measure;
  astore_2
  iconst_0
  istore_3
  aload_1
  aload_2
  iload_3
  invokevirtual com/qq/taf/jce/JceOutputStream/write(Lcom/qq/taf/jce/JceStruct;I)V
  aload_0
  getfield LBSAPIProtocol/DeviceData/vMeasures Ljava/util/ArrayList;
  astore 4
  iconst_1
  istore_3
  aload_1
  aload 4
  iload_3
  invokevirtual com/qq/taf/jce/JceOutputStream/write(Ljava/util/Collection;I)V
  aload_0
  getfield LBSAPIProtocol/DeviceData/strAppUA Ljava/lang/String;
  astore 5
  iconst_2
  istore_3
  aload_1
  aload 5
  iload_3
  invokevirtual com/qq/taf/jce/JceOutputStream/write(Ljava/lang/String;I)V
  aload_0
  getfield LBSAPIProtocol/DeviceData/strImei Ljava/lang/String;
  astore 5
  iconst_3
  istore_3
  aload_1
  aload 5
  iload_3
  invokevirtual com/qq/taf/jce/JceOutputStream/write(Ljava/lang/String;I)V
  aload_0
  getfield LBSAPIProtocol/DeviceData/eDeviceType I
  istore 6
  iconst_4
  istore_3
  aload_1
  iload 6
  iload_3
  invokevirtual com/qq/taf/jce/JceOutputStream/write(II)V
  return
  nop
.end <method>

