.source R.java
.class public final  maxstrom/game/llk/R$styleable
.super java/lang/Object
.field public static final "AdView" [I
.field public static final "AdView_backAlpha" I =  2
.field public static final "AdView_backColor" I =  0
.field public static final "AdView_textColor" I =  1
.field public static final "AdView_titleColor" I =  3
.field public static final "com_google_ads_AdView" [I
.field public static final "com_google_ads_AdView_adSize" I =  0
.field public static final "com_google_ads_AdView_adUnitId" I =  1

.method static <clinit>()V
.limit locals 3
.limit stack 200
  nop
  iconst_4
  istore_1
  iload_1
  newarray int
  astore_0
  iconst_0
  istore_1
  ldc 2130771968
  istore_2
  aload_0
  iload_1
  iload_2
  iastore
  iconst_1
  istore_1
  ldc 2130771969
  istore_2
  aload_0
  iload_1
  iload_2
  iastore
  iconst_2
  istore_1
  ldc 2130771970
  istore_2
  aload_0
  iload_1
  iload_2
  iastore
  iconst_3
  istore_1
  ldc 2130771971
  istore_2
  aload_0
  iload_1
  iload_2
  iastore
  aload_0
  putstatic maxstrom/game/llk/R$styleable/AdView [I
  iconst_2
  istore_1
  iload_1
  newarray int
  astore_0
  iconst_0
  istore_1
  ldc 2130771972
  istore_2
  aload_0
  iload_1
  iload_2
  iastore
  iconst_1
  istore_1
  ldc 2130771973
  istore_2
  aload_0
  iload_1
  iload_2
  iastore
  aload_0
  putstatic maxstrom/game/llk/R$styleable/com_google_ads_AdView [I
  return
  nop
.end <method>

.method public <init>()V
.limit locals 1
.limit stack 200
  nop
  aload_0
  invokespecial java/lang/Object/<init>()V
  return
  nop
.end <method>

