.source Chart.java
.class public  maxstrom/game/llk/engine/Chart
.super java/lang/Object
.field public "theme" Lmaxstrom/game/llk/ThemeManager$ImageTheme;
.field "tiles" [[Lmaxstrom/game/llk/engine/Tile;
.field public final "xSize" I
.field public final "ySize" I

.method public <init>([[I)V
.limit locals 14
.limit stack 200
  nop
  aload_0
  invokespecial java/lang/Object/<init>()V
  getstatic maxstrom/game/llk/ThemeManager$ImageTheme/qq Lmaxstrom/game/llk/ThemeManager$ImageTheme;
  astore_2
  aload_0
  aload_2
  putfield maxstrom/game/llk/engine/Chart/theme Lmaxstrom/game/llk/ThemeManager$ImageTheme;
  iconst_0
  istore 4
  aload_1
  iload 4
  aaload
  astore_3
  aload_3
  arraylength
  istore 5
  aload_0
  iload 5
  putfield maxstrom/game/llk/engine/Chart/xSize I
  aload_1
  arraylength
  istore 5
  aload_0
  iload 5
  putfield maxstrom/game/llk/engine/Chart/ySize I
  aload_0
  getfield maxstrom/game/llk/engine/Chart/ySize I
  istore 6
  aload_0
  getfield maxstrom/game/llk/engine/Chart/xSize I
  istore 5
  iconst_2
  istore 4
  iload 4
  newarray int
  astore_3
  iconst_0
  istore 4
  aload_3
  iload 4
  iload 6
  iastore
  iconst_1
  istore 4
  aload_3
  iload 4
  iload 5
  iastore
  ldc maxstrom/game/llk/engine/Tile
  astore 8
  aload 8
  aload_3
  invokestatic java/lang/reflect/Array/newInstance(Ljava/lang/Class;[I)Ljava/lang/Object;
  astore 7
  aload 7
  astore 10
  aload 10
  checkcast [[Lmaxstrom/game/llk/engine/Tile;
  astore 10
  aload 10
  astore 9
  aload_0
  aload 9
  putfield maxstrom/game/llk/engine/Chart/tiles [[Lmaxstrom/game/llk/engine/Tile;
  iconst_0
  istore 5
Label2:
  aload_0
  getfield maxstrom/game/llk/engine/Chart/ySize I
  istore 6
  new java/lang/NoClassDefFoundError
  dup
  invokespecial java/lang/NoClassDefFoundError/<init>()V
  athrow
  dload 6
  invokestatic app/DummyClass/invokeIfStmt(D)V
  iload 5
  iload 6
  if_icmplt Label0
  return
Label0:
  iconst_0
  dstore 6
Label3:
  aload_0
  getfield maxstrom/game/llk/engine/Chart/xSize I
  istore 11
  dload 6
  invokestatic app/DummyClass/invokeIfStmt(D)V
  dload 11
  invokestatic app/DummyClass/invokeIfStmt(D)V
  iload 6
  iload 11
  if_icmplt Label1
  iload 5
  iconst_1
  iadd
  istore 5
  goto Label2
Label1:
  aload_0
  getfield maxstrom/game/llk/engine/Chart/tiles [[Lmaxstrom/game/llk/engine/Tile;
  astore 9
  aload 9
  iload 5
  aaload
  astore 12
  new maxstrom/game/llk/engine/Tile
  astore 13
  aload_1
  iload 5
  aaload
  astore_3
  aload_3
  iload 6
  iaload
  istore 11
  aload 13
  iload 6
  iload 5
  iload 11
  aload_0
  invokespecial maxstrom/game/llk/engine/Tile/<init>(IIILmaxstrom/game/llk/engine/Chart;)V
  aload 12
  iload 6
  aload 13
  aastore
  iload 6
  iconst_1
  iadd
  istore 6
  goto Label3
  nop
.end <method>

.method public connectvie(Lmaxstrom/game/llk/engine/Tile;Lmaxstrom/game/llk/engine/Tile;)Lmaxstrom/game/llk/engine/ConnectiveInfo;
.limit locals 9
.limit stack 200
  nop
  new java/lang/NoClassDefFoundError
  dup
  invokespecial java/lang/NoClassDefFoundError/<init>()V
  athrow
  iload_1
  ifeq Label0
  aload_2
  invokestatic app/DummyClass/invokeIfStmt(Ljava/lang/Object;)V
  iload_2
  ifne Label1
Label0:
  getstatic java/lang/System/err Ljava/io/PrintStream;
  astore_3
  ldc "some one is null"
  astore 4
  aload_3
  aload 4
  invokevirtual java/io/PrintStream/println(Ljava/lang/String;)V
  getstatic maxstrom/game/llk/engine/ConnectiveInfo/CANNOT_FIND Lmaxstrom/game/llk/engine/ConnectiveInfo;
  astore 5
  aload 5
  areturn
Label1:
  getstatic maxstrom/game/llk/engine/Tile/UN_EXIST_TILE Lmaxstrom/game/llk/engine/Tile;
  astore 6
  aload_1
  invokestatic app/DummyClass/invokeIfStmt(Ljava/lang/Object;)V
  aload 6
  invokestatic app/DummyClass/invokeIfStmt(Ljava/lang/Object;)V
  aload_1
  aload 6
  if_acmpeq Label2
  getstatic maxstrom/game/llk/engine/Tile/UN_EXIST_TILE Lmaxstrom/game/llk/engine/Tile;
  astore 6
  aload_2
  invokestatic app/DummyClass/invokeIfStmt(Ljava/lang/Object;)V
  aload 6
  invokestatic app/DummyClass/invokeIfStmt(Ljava/lang/Object;)V
  aload_2
  aload 6
  if_acmpne Label3
Label2:
  getstatic java/lang/System/err Ljava/io/PrintStream;
  astore_3
  ldc "some one is UN_EXIST_TILE"
  astore 4
  aload_3
  aload 4
  invokevirtual java/io/PrintStream/println(Ljava/lang/String;)V
  getstatic maxstrom/game/llk/engine/ConnectiveInfo/CANNOT_FIND Lmaxstrom/game/llk/engine/ConnectiveInfo;
  astore 5
  aload 5
  areturn
Label3:
  aload_1
  invokestatic app/DummyClass/invokeIfStmt(Ljava/lang/Object;)V
  aload_2
  invokestatic app/DummyClass/invokeIfStmt(Ljava/lang/Object;)V
  iload_1
  iload_2
  if_icmpne Label4
  getstatic java/lang/System/err Ljava/io/PrintStream;
  astore_3
  ldc "is the same tile"
  astore 4
  aload_3
  aload 4
  invokevirtual java/io/PrintStream/println(Ljava/lang/String;)V
  getstatic maxstrom/game/llk/engine/ConnectiveInfo/CANNOT_FIND Lmaxstrom/game/llk/engine/ConnectiveInfo;
  astore 5
  aload 5
  areturn
Label4:
  new maxstrom/game/llk/engine/BlankRoute
  astore 7
  aload 7
  aload_1
  aload_2
  invokespecial maxstrom/game/llk/engine/BlankRoute/<init>(Lmaxstrom/game/llk/engine/Tile;Lmaxstrom/game/llk/engine/Tile;)V
  aload_1
  aload 7
  invokevirtual maxstrom/game/llk/engine/Tile/isLink(Lmaxstrom/game/llk/engine/BlankRoute;)Z
  istore 8
  new maxstrom/game/llk/engine/ConnectiveInfo
  astore 5
  aload 5
  iload 8
  aload 7
  invokespecial maxstrom/game/llk/engine/ConnectiveInfo/<init>(ZLmaxstrom/game/llk/engine/BlankRoute;)V
  aload 5
  areturn
  nop
.end <method>

.method public get(II)Lmaxstrom/game/llk/engine/Tile;
.limit locals 9
.limit stack 200
  nop
  aload_0
  getfield maxstrom/game/llk/engine/Chart/tiles [[Lmaxstrom/game/llk/engine/Tile;
  astore_3
  new java/lang/NoClassDefFoundError
  dup
  invokespecial java/lang/NoClassDefFoundError/<init>()V
  athrow
  iload_3
  ifne Label0
  new java/lang/IllegalStateException
  astore 4
  ldc "game is not start!"
  astore 5
  aload 4
  aload 5
  invokespecial java/lang/IllegalStateException/<init>(Ljava/lang/String;)V
  aload 4
  athrow
Label0:
  aload_0
  getfield maxstrom/game/llk/engine/Chart/tiles [[Lmaxstrom/game/llk/engine/Tile;
  astore_3
Label2:
  aload_3
  iload_2
  aaload
  astore 6
  aload 6
  iload_1
  aaload
  astore 7
Label3:
  aload 7
  areturn
Label1:
  astore 8
  getstatic maxstrom/game/llk/engine/Tile/UN_EXIST_TILE Lmaxstrom/game/llk/engine/Tile;
  astore 7
  aload 7
  areturn
  nop
.end <method>

.method public isAllBlank()Z
.limit locals 9
.limit stack 200
  nop
  iconst_0
  istore_1
Label2:
  aload_0
  getfield maxstrom/game/llk/engine/Chart/ySize I
  istore_2
  new java/lang/NoClassDefFoundError
  dup
  invokespecial java/lang/NoClassDefFoundError/<init>()V
  athrow
  dload_2
  invokestatic app/DummyClass/invokeIfStmt(D)V
  iload_1
  iload_2
  if_icmplt Label0
  iconst_1
  istore_3
  iload_3
  ireturn
Label0:
  iconst_0
  dstore_2
Label4:
  aload_0
  getfield maxstrom/game/llk/engine/Chart/xSize I
  istore 4
  dload_2
  invokestatic app/DummyClass/invokeIfStmt(D)V
  dload 4
  invokestatic app/DummyClass/invokeIfStmt(D)V
  iload_2
  iload 4
  if_icmplt Label1
  iload_1
  iconst_1
  iadd
  istore_1
  goto Label2
Label1:
  aload_0
  getfield maxstrom/game/llk/engine/Chart/tiles [[Lmaxstrom/game/llk/engine/Tile;
  astore 5
  aload 5
  iload_1
  aaload
  astore 6
  aload 6
  iload_2
  aaload
  astore 7
  aload 7
  invokevirtual maxstrom/game/llk/engine/Tile/isBlank()Z
  istore 8
  iload 8
  invokestatic app/DummyClass/invokeIfStmt(Z)V
  iload 8
  ifne Label3
  iconst_0
  istore_3
  iload_3
  ireturn
Label3:
  iload_2
  iconst_1
  iadd
  istore_2
  goto Label4
  nop
.end <method>

.method public reArrange()V
.limit locals 13
.limit stack 200
  nop
  aload_0
  getfield maxstrom/game/llk/engine/Chart/tiles [[Lmaxstrom/game/llk/engine/Tile;
  astore_1
  aload_1
  arraylength
  istore_2
  aload_0
  getfield maxstrom/game/llk/engine/Chart/tiles [[Lmaxstrom/game/llk/engine/Tile;
  astore_1
  iconst_0
  istore 4
  aload_1
  iload 4
  aaload
  astore_3
  aload_3
  arraylength
  istore 5
  iconst_2
  istore 4
  iload 4
  newarray int
  astore 6
  iconst_0
  istore 4
  aload 6
  iload 4
  iload_2
  iastore
  iconst_1
  istore 4
  aload 6
  iload 4
  iload 5
  iastore
  getstatic java/lang/Integer/TYPE Ljava/lang/Class;
  astore 7
  aload 7
  aload 6
  invokestatic java/lang/reflect/Array/newInstance(Ljava/lang/Class;[I)Ljava/lang/Object;
  astore 8
  aload 8
  astore 10
  aload 10
  checkcast [[I
  astore 10
  aload 10
  astore 9
  iconst_0
  istore_2
Label3:
  aload_0
  getfield maxstrom/game/llk/engine/Chart/tiles [[Lmaxstrom/game/llk/engine/Tile;
  astore_1
  aload_1
  arraylength
  istore 5
  new java/lang/NoClassDefFoundError
  dup
  invokespecial java/lang/NoClassDefFoundError/<init>()V
  athrow
  dload 5
  invokestatic app/DummyClass/invokeIfStmt(D)V
  iload_2
  iload 5
  if_icmplt Label0
  aload 9
  invokestatic maxstrom/game/llk/engine/FillContent/reArrange([[I)[[I
  pop
  iconst_0
  dstore_2
Label6:
  aload_0
  getfield maxstrom/game/llk/engine/Chart/tiles [[Lmaxstrom/game/llk/engine/Tile;
  astore_1
  aload_1
  arraylength
  istore 5
  dload_2
  invokestatic app/DummyClass/invokeIfStmt(D)V
  dload 5
  invokestatic app/DummyClass/invokeIfStmt(D)V
  iload_2
  iload 5
  if_icmplt Label1
  return
Label0:
  iconst_0
  dstore 5
Label4:
  aload_0
  getfield maxstrom/game/llk/engine/Chart/tiles [[Lmaxstrom/game/llk/engine/Tile;
  astore_1
  iconst_0
  istore 4
  aload_1
  iload 4
  aaload
  astore_3
  aload_3
  arraylength
  istore 11
  dload 5
  invokestatic app/DummyClass/invokeIfStmt(D)V
  dload 11
  invokestatic app/DummyClass/invokeIfStmt(D)V
  iload 5
  iload 11
  if_icmplt Label2
  iload_2
  iconst_1
  iadd
  istore_2
  goto Label3
Label2:
  aload 9
  iload_2
  aaload
  astore 6
  aload_0
  getfield maxstrom/game/llk/engine/Chart/tiles [[Lmaxstrom/game/llk/engine/Tile;
  astore_1
  aload_1
  iload_2
  aaload
  astore_3
  aload_3
  iload 5
  aaload
  astore 12
  aload 12
  invokevirtual maxstrom/game/llk/engine/Tile/getImage()I
  istore 11
  aload 6
  iload 5
  iload 11
  iastore
  iload 5
  iconst_1
  iadd
  istore 5
  goto Label4
Label1:
  iconst_0
  dstore 11
Label7:
  aload_0
  getfield maxstrom/game/llk/engine/Chart/tiles [[Lmaxstrom/game/llk/engine/Tile;
  astore_1
  iconst_0
  istore 4
  aload_1
  iload 4
  aaload
  astore_3
  aload_3
  arraylength
  istore 5
  dload 11
  invokestatic app/DummyClass/invokeIfStmt(D)V
  dload 5
  invokestatic app/DummyClass/invokeIfStmt(D)V
  iload 11
  iload 5
  if_icmplt Label5
  iload_2
  iconst_1
  iadd
  istore_2
  goto Label6
Label5:
  aload_0
  getfield maxstrom/game/llk/engine/Chart/tiles [[Lmaxstrom/game/llk/engine/Tile;
  astore_1
  aload_1
  iload_2
  aaload
  astore_3
  aload_3
  iload 11
  aaload
  astore 12
  aload 9
  iload_2
  aaload
  astore 6
  aload 6
  iload 11
  iaload
  istore 5
  aload 12
  iload 5
  invokevirtual maxstrom/game/llk/engine/Tile/setImage(I)V
  iload 11
  iconst_1
  iadd
  istore 11
  goto Label7
  nop
.end <method>

