.source LLKView.java
.class  maxstrom/game/llk/LLKView$2
.super java/lang/Object
.implements  java/lang/Runnable
.field final "this$0" Lmaxstrom/game/llk/LLKView;

.method <init>(Lmaxstrom/game/llk/LLKView;)V
.limit locals 2
.limit stack 200
  nop
  aload_0
  aload_1
  putfield maxstrom/game/llk/LLKView$2/this$0 Lmaxstrom/game/llk/LLKView;
  aload_0
  invokespecial java/lang/Object/<init>()V
  return
  nop
.end <method>

.method public run()V
.limit locals 18
.limit stack 200
  .catch  java/lang/Exception <from> Label5 <to> Label6 <using> Label4
  nop
Label5:
  aload_0
  astore_1
  aload_1
  getfield maxstrom/game/llk/LLKView$2/this$0 Lmaxstrom/game/llk/LLKView;
  astore_2
  aload_1
  astore_0
  new java/lang/NoClassDefFoundError
  dup
  invokespecial java/lang/NoClassDefFoundError/<init>()V
  athrow
  nop
  aload_3
  invokevirtual java/util/LinkedList/removeFirst()Ljava/lang/Object;
  astore 4
  aload 4
  astore 6
  aload 6
  checkcast maxstrom/game/llk/engine/BlankRoute
  astore 6
  aload 6
  astore 5
  aload 5
  getfield maxstrom/game/llk/engine/BlankRoute/start Lmaxstrom/game/llk/engine/Tile;
  astore 7
  aload 7
  invokevirtual maxstrom/game/llk/engine/Tile/dismiss()V
  aload 5
  getfield maxstrom/game/llk/engine/BlankRoute/end Lmaxstrom/game/llk/engine/Tile;
  astore 7
  aload 7
  invokevirtual maxstrom/game/llk/engine/Tile/dismiss()V
  aload 5
  getfield maxstrom/game/llk/engine/BlankRoute/start Lmaxstrom/game/llk/engine/Tile;
  astore 7
  aload_0
  astore_1
  aload_1
  getfield maxstrom/game/llk/LLKView$2/this$0 Lmaxstrom/game/llk/LLKView;
  astore_2
  aload_1
  astore_0
  aload_2
  invokestatic maxstrom/game/llk/LLKView/access$2(Lmaxstrom/game/llk/LLKView;)Lmaxstrom/game/llk/engine/Tile;
  astore 8
  aload 7
  invokestatic app/DummyClass/invokeIfStmt(Ljava/lang/Object;)V
  aload 8
  invokestatic app/DummyClass/invokeIfStmt(Ljava/lang/Object;)V
  aload 7
  aload 8
  if_acmpeq Label0
  aload 5
  getfield maxstrom/game/llk/engine/BlankRoute/end Lmaxstrom/game/llk/engine/Tile;
  astore 8
  aload_0
  astore_1
  aload_1
  getfield maxstrom/game/llk/LLKView$2/this$0 Lmaxstrom/game/llk/LLKView;
  astore_2
  aload_1
  astore_0
  aload_2
  invokestatic maxstrom/game/llk/LLKView/access$2(Lmaxstrom/game/llk/LLKView;)Lmaxstrom/game/llk/engine/Tile;
  astore 7
  aload 8
  invokestatic app/DummyClass/invokeIfStmt(Ljava/lang/Object;)V
  aload 7
  invokestatic app/DummyClass/invokeIfStmt(Ljava/lang/Object;)V
  aload 8
  aload 7
  if_acmpne Label1
Label0:
  aload_0
  astore_1
  aload_1
  getfield maxstrom/game/llk/LLKView$2/this$0 Lmaxstrom/game/llk/LLKView;
  astore_2
  aload_1
  astore_0
  aconst_null
  astore 9
  aload_2
  aload 9
  invokestatic maxstrom/game/llk/LLKView/access$3(Lmaxstrom/game/llk/LLKView;Lmaxstrom/game/llk/engine/Tile;)V
Label1:
  aload_0
  astore_1
  aload_1
  getfield maxstrom/game/llk/LLKView$2/this$0 Lmaxstrom/game/llk/LLKView;
  astore_2
  aload_1
  astore_0
  aload_2
  invokestatic maxstrom/game/llk/LLKView/access$4(Lmaxstrom/game/llk/LLKView;)Lmaxstrom/game/llk/engine/Chart;
  astore 10
  aload 10
  invokevirtual maxstrom/game/llk/engine/Chart/isAllBlank()Z
  istore 11
  iload 11
  invokestatic app/DummyClass/invokeIfStmt(Z)V
  iload 11
  ifeq Label2
  aload_0
  astore_1
  aload_1
  getfield maxstrom/game/llk/LLKView$2/this$0 Lmaxstrom/game/llk/LLKView;
  astore_2
  aload_1
  astore_0
  aload_2
  invokevirtual maxstrom/game/llk/LLKView/getContext()Landroid/content/Context;
  astore 12
  aload 12
  invokestatic maxstrom/game/llk/MediaUtil/playWinSound(Landroid/content/Context;)V
  aload_0
  astore_1
  aload_1
  getfield maxstrom/game/llk/LLKView$2/this$0 Lmaxstrom/game/llk/LLKView;
  astore_2
  aload_1
  astore_0
  iconst_1
  istore 14
  iload 14
  invokestatic java/lang/Boolean/valueOf(Z)Ljava/lang/Boolean;
  astore 13
  aload_2
  aload 13
  invokevirtual maxstrom/game/llk/LLKView/showLevelWindow(Ljava/lang/Boolean;)V
Label3:
  return
Label2:
  aload_0
  astore_1
  aload_1
  getfield maxstrom/game/llk/LLKView$2/this$0 Lmaxstrom/game/llk/LLKView;
  astore_2
  aload_1
  astore_0
  aload_2
  invokevirtual maxstrom/game/llk/LLKView/postInvalidate()V
Label6:
  goto Label3
Label4:
  astore 15
  aload 15
  invokevirtual java/lang/Exception/toString()Ljava/lang/String;
  astore 16
  ldc "LLK Fatal exception:"
  astore 17
  aload 17
  astore_1
  new java/lang/NoClassDefFoundError
  dup
  invokespecial java/lang/NoClassDefFoundError/<init>()V
  athrow
  goto Label3
  nop
.end <method>

