.source ThemeManager.java
.class public final enum  maxstrom/game/llk/ThemeManager$ImageTheme
.super java/lang/Enum
  .signature_attr "Ljava/lang/Enum<Lmaxstrom/game/llk/ThemeManager$ImageTheme;>;"
.field private static final "ENUM$VALUES" [Lmaxstrom/game/llk/ThemeManager$ImageTheme;
.field public static final enum "nba" Lmaxstrom/game/llk/ThemeManager$ImageTheme;
.field public static final enum "qq" Lmaxstrom/game/llk/ThemeManager$ImageTheme;
.field private "backgroundColor" I

.method static <clinit>()V
.limit locals 5
.limit stack 200
  nop
  new maxstrom/game/llk/ThemeManager$ImageTheme
  astore_0
  ldc "qq"
  astore_1
  iconst_0
  istore_2
  ldc -16777216
  istore_3
  aload_0
  aload_1
  iload_2
  iload_3
  invokespecial maxstrom/game/llk/ThemeManager$ImageTheme/<init>(Ljava/lang/String;II)V
  aload_0
  putstatic maxstrom/game/llk/ThemeManager$ImageTheme/qq Lmaxstrom/game/llk/ThemeManager$ImageTheme;
  new maxstrom/game/llk/ThemeManager$ImageTheme
  astore_0
  ldc "nba"
  astore_1
  iconst_1
  istore_2
  iconst_m1
  istore_3
  aload_0
  aload_1
  iload_2
  iload_3
  invokespecial maxstrom/game/llk/ThemeManager$ImageTheme/<init>(Ljava/lang/String;II)V
  aload_0
  putstatic maxstrom/game/llk/ThemeManager$ImageTheme/nba Lmaxstrom/game/llk/ThemeManager$ImageTheme;
  iconst_2
  istore_2
  iload_2
  anewarray maxstrom/game/llk/ThemeManager$ImageTheme
  astore 4
  getstatic maxstrom/game/llk/ThemeManager$ImageTheme/qq Lmaxstrom/game/llk/ThemeManager$ImageTheme;
  astore_0
  iconst_0
  istore_2
  aload 4
  iload_2
  aload_0
  aastore
  getstatic maxstrom/game/llk/ThemeManager$ImageTheme/nba Lmaxstrom/game/llk/ThemeManager$ImageTheme;
  astore_0
  iconst_1
  istore_2
  aload 4
  iload_2
  aload_0
  aastore
  aload 4
  putstatic maxstrom/game/llk/ThemeManager$ImageTheme/ENUM$VALUES [Lmaxstrom/game/llk/ThemeManager$ImageTheme;
  return
  nop
.end <method>

.method private <init>(Ljava/lang/String;II)V
.limit locals 4
.limit stack 200
  nop
  aload_0
  aload_1
  iload_2
  invokespecial java/lang/Enum/<init>(Ljava/lang/String;I)V
  aload_0
  iload_3
  putfield maxstrom/game/llk/ThemeManager$ImageTheme/backgroundColor I
  return
  nop
.end <method>

.method public getBackgroundColor()I
.limit locals 2
.limit stack 200
  nop
  aload_0
  getfield maxstrom/game/llk/ThemeManager$ImageTheme/backgroundColor I
  istore_1
  iload_1
  ireturn
  nop
.end <method>

.method public static valueOf(Ljava/lang/String;)Lmaxstrom/game/llk/ThemeManager$ImageTheme;
.limit locals 5
.limit stack 200
  nop
  ldc maxstrom/game/llk/ThemeManager$ImageTheme
  astore_2
  aload_2
  aload_0
  invokestatic java/lang/Enum/valueOf(Ljava/lang/Class;Ljava/lang/String;)Ljava/lang/Enum;
  astore_1
  aload_1
  astore 4
  aload 4
  checkcast maxstrom/game/llk/ThemeManager$ImageTheme
  astore 4
  aload 4
  astore_3
  aload_3
  areturn
  nop
.end <method>

.method public static values()[Lmaxstrom/game/llk/ThemeManager$ImageTheme;
.limit locals 5
.limit stack 200
  nop
  getstatic maxstrom/game/llk/ThemeManager$ImageTheme/ENUM$VALUES [Lmaxstrom/game/llk/ThemeManager$ImageTheme;
  astore_0
  aload_0
  arraylength
  istore_1
  iload_1
  anewarray maxstrom/game/llk/ThemeManager$ImageTheme
  astore_2
  iconst_0
  istore_3
  iconst_0
  istore 4
  aload_0
  iload_3
  aload_2
  iload 4
  iload_1
  invokestatic java/lang/System/arraycopy(Ljava/lang/Object;ILjava/lang/Object;II)V
  aload_2
  areturn
  nop
.end <method>

