.source dalvik_source_VirusShare_32e70f448ebd75661a1cb12f9cd8e013.apk
.class public final  MobWin/ReqGetAD
.super com/qq/taf/jce/JceStruct
.field static "k" LMobWin/UserInfo;
.field static "l" LMobWin/AppInfo;
.field static "m" I =  0
.field static "n" Ljava/util/ArrayList;
.field static "o" Ljava/util/ArrayList;
.field static "p" LMobWin/UserLocation;
.field static "q" LMobWin/SettingVersions;
.field static "r" LMobWin/BannerInfo;
.field static final "s" Z =  0
.field public "a" LMobWin/UserInfo;
.field public "b" LMobWin/AppInfo;
.field public "c" I
.field public "d" I
.field public "e" Ljava/util/ArrayList;
.field public "f" Ljava/util/ArrayList;
.field public "g" LMobWin/UserLocation;
.field public "h" LMobWin/SettingVersions;
.field public "i" LMobWin/BannerInfo;
.field public "j" Ljava/lang/String;

.method static <clinit>()V
.limit locals 2
.limit stack 200
  nop
  ldc MobWin/ReqGetAD
  astore_0
  aload_0
  invokevirtual java/lang/Class/desiredAssertionStatus()Z
  istore_1
  new java/lang/NoClassDefFoundError
  dup
  invokespecial java/lang/NoClassDefFoundError/<init>()V
  athrow
  iload_1
  ifne Label0
  iconst_1
  istore_1
Label1:
  iload_1
  putstatic MobWin/ReqGetAD/s Z
  return
Label0:
  iconst_0
  istore_1
  goto Label1
  nop
.end <method>

.method public <init>()V
.limit locals 12
.limit stack 200
  nop
  aload_0
  invokespecial com/qq/taf/jce/JceStruct/<init>()V
  aconst_null
  astore_1
  aload_0
  aload_1
  putfield MobWin/ReqGetAD/a LMobWin/UserInfo;
  aconst_null
  astore_1
  aload_0
  aload_1
  putfield MobWin/ReqGetAD/b LMobWin/AppInfo;
  iconst_0
  istore_2
  aload_0
  iload_2
  putfield MobWin/ReqGetAD/c I
  iconst_0
  istore_2
  aload_0
  iload_2
  putfield MobWin/ReqGetAD/d I
  aconst_null
  astore_1
  aload_0
  aload_1
  putfield MobWin/ReqGetAD/e Ljava/util/ArrayList;
  aconst_null
  astore_1
  aload_0
  aload_1
  putfield MobWin/ReqGetAD/f Ljava/util/ArrayList;
  aconst_null
  astore_1
  aload_0
  aload_1
  putfield MobWin/ReqGetAD/g LMobWin/UserLocation;
  aconst_null
  astore_1
  aload_0
  aload_1
  putfield MobWin/ReqGetAD/h LMobWin/SettingVersions;
  aconst_null
  astore_1
  aload_0
  aload_1
  putfield MobWin/ReqGetAD/i LMobWin/BannerInfo;
  ldc ""
  astore_3
  aload_0
  aload_3
  putfield MobWin/ReqGetAD/j Ljava/lang/String;
  aload_0
  getfield MobWin/ReqGetAD/a LMobWin/UserInfo;
  astore 4
  aload_0
  aload 4
  invokevirtual MobWin/ReqGetAD/a(LMobWin/UserInfo;)V
  aload_0
  getfield MobWin/ReqGetAD/b LMobWin/AppInfo;
  astore 5
  aload_0
  aload 5
  invokevirtual MobWin/ReqGetAD/a(LMobWin/AppInfo;)V
  aload_0
  getfield MobWin/ReqGetAD/c I
  istore 6
  aload_0
  iload 6
  invokevirtual MobWin/ReqGetAD/a(I)V
  aload_0
  getfield MobWin/ReqGetAD/d I
  istore 6
  aload_0
  iload 6
  invokevirtual MobWin/ReqGetAD/b(I)V
  aload_0
  getfield MobWin/ReqGetAD/e Ljava/util/ArrayList;
  astore 7
  aload_0
  aload 7
  invokevirtual MobWin/ReqGetAD/a(Ljava/util/ArrayList;)V
  aload_0
  getfield MobWin/ReqGetAD/f Ljava/util/ArrayList;
  astore 7
  aload_0
  aload 7
  invokevirtual MobWin/ReqGetAD/b(Ljava/util/ArrayList;)V
  aload_0
  getfield MobWin/ReqGetAD/g LMobWin/UserLocation;
  astore 8
  aload_0
  aload 8
  invokevirtual MobWin/ReqGetAD/a(LMobWin/UserLocation;)V
  aload_0
  getfield MobWin/ReqGetAD/h LMobWin/SettingVersions;
  astore 9
  aload_0
  aload 9
  invokevirtual MobWin/ReqGetAD/a(LMobWin/SettingVersions;)V
  aload_0
  getfield MobWin/ReqGetAD/i LMobWin/BannerInfo;
  astore 10
  aload_0
  aload 10
  invokevirtual MobWin/ReqGetAD/a(LMobWin/BannerInfo;)V
  aload_0
  getfield MobWin/ReqGetAD/j Ljava/lang/String;
  astore 11
  aload_0
  aload 11
  invokevirtual MobWin/ReqGetAD/a(Ljava/lang/String;)V
  return
  nop
.end <method>

.method public <init>(LMobWin/UserInfo;LMobWin/AppInfo;IILjava/util/ArrayList;Ljava/util/ArrayList;LMobWin/UserLocation;LMobWin/SettingVersions;LMobWin/BannerInfo;Ljava/lang/String;)V
.limit locals 14
.limit stack 200
  nop
  aload_0
  invokespecial com/qq/taf/jce/JceStruct/<init>()V
  aconst_null
  astore 11
  aload_0
  aload 11
  putfield MobWin/ReqGetAD/a LMobWin/UserInfo;
  aconst_null
  astore 11
  aload_0
  aload 11
  putfield MobWin/ReqGetAD/b LMobWin/AppInfo;
  iconst_0
  istore 12
  aload_0
  iload 12
  putfield MobWin/ReqGetAD/c I
  iconst_0
  istore 12
  aload_0
  iload 12
  putfield MobWin/ReqGetAD/d I
  aconst_null
  astore 11
  aload_0
  aload 11
  putfield MobWin/ReqGetAD/e Ljava/util/ArrayList;
  aconst_null
  astore 11
  aload_0
  aload 11
  putfield MobWin/ReqGetAD/f Ljava/util/ArrayList;
  aconst_null
  astore 11
  aload_0
  aload 11
  putfield MobWin/ReqGetAD/g LMobWin/UserLocation;
  aconst_null
  astore 11
  aload_0
  aload 11
  putfield MobWin/ReqGetAD/h LMobWin/SettingVersions;
  aconst_null
  astore 11
  aload_0
  aload 11
  putfield MobWin/ReqGetAD/i LMobWin/BannerInfo;
  ldc ""
  astore 13
  aload_0
  aload 13
  putfield MobWin/ReqGetAD/j Ljava/lang/String;
  aload_0
  aload_1
  invokevirtual MobWin/ReqGetAD/a(LMobWin/UserInfo;)V
  aload_0
  aload_2
  invokevirtual MobWin/ReqGetAD/a(LMobWin/AppInfo;)V
  aload_0
  iload_3
  invokevirtual MobWin/ReqGetAD/a(I)V
  aload_0
  iload 4
  invokevirtual MobWin/ReqGetAD/b(I)V
  aload_0
  aload 5
  invokevirtual MobWin/ReqGetAD/a(Ljava/util/ArrayList;)V
  aload_0
  aload 6
  invokevirtual MobWin/ReqGetAD/b(Ljava/util/ArrayList;)V
  aload_0
  aload 7
  invokevirtual MobWin/ReqGetAD/a(LMobWin/UserLocation;)V
  aload_0
  aload 8
  invokevirtual MobWin/ReqGetAD/a(LMobWin/SettingVersions;)V
  aload_0
  aload 9
  invokevirtual MobWin/ReqGetAD/a(LMobWin/BannerInfo;)V
  aload_0
  aload 10
  invokevirtual MobWin/ReqGetAD/a(Ljava/lang/String;)V
  return
  nop
.end <method>

.method public a()Ljava/lang/String;
.limit locals 2
.limit stack 200
  nop
  ldc "MobWin.ReqGetAD"
  astore_1
  aload_1
  areturn
  nop
.end <method>

.method public a(I)V
.limit locals 2
.limit stack 200
  nop
  aload_0
  iload_1
  putfield MobWin/ReqGetAD/c I
  return
  nop
.end <method>

.method public a(LMobWin/AppInfo;)V
.limit locals 2
.limit stack 200
  nop
  aload_0
  aload_1
  putfield MobWin/ReqGetAD/b LMobWin/AppInfo;
  return
  nop
.end <method>

.method public a(LMobWin/BannerInfo;)V
.limit locals 2
.limit stack 200
  nop
  aload_0
  aload_1
  putfield MobWin/ReqGetAD/i LMobWin/BannerInfo;
  return
  nop
.end <method>

.method public a(LMobWin/SettingVersions;)V
.limit locals 2
.limit stack 200
  nop
  aload_0
  aload_1
  putfield MobWin/ReqGetAD/h LMobWin/SettingVersions;
  return
  nop
.end <method>

.method public a(LMobWin/UserInfo;)V
.limit locals 2
.limit stack 200
  nop
  aload_0
  aload_1
  putfield MobWin/ReqGetAD/a LMobWin/UserInfo;
  return
  nop
.end <method>

.method public a(LMobWin/UserLocation;)V
.limit locals 2
.limit stack 200
  nop
  aload_0
  aload_1
  putfield MobWin/ReqGetAD/g LMobWin/UserLocation;
  return
  nop
.end <method>

.method public a(Ljava/lang/String;)V
.limit locals 2
.limit stack 200
  nop
  aload_0
  aload_1
  putfield MobWin/ReqGetAD/j Ljava/lang/String;
  return
  nop
.end <method>

.method public a(Ljava/util/ArrayList;)V
.limit locals 2
.limit stack 200
  nop
  aload_0
  aload_1
  putfield MobWin/ReqGetAD/e Ljava/util/ArrayList;
  return
  nop
.end <method>

.method public b()LMobWin/UserInfo;
.limit locals 2
.limit stack 200
  nop
  aload_0
  getfield MobWin/ReqGetAD/a LMobWin/UserInfo;
  astore_1
  aload_1
  areturn
  nop
.end <method>

.method public b(I)V
.limit locals 2
.limit stack 200
  nop
  aload_0
  iload_1
  putfield MobWin/ReqGetAD/d I
  return
  nop
.end <method>

.method public b(Ljava/util/ArrayList;)V
.limit locals 2
.limit stack 200
  nop
  aload_0
  aload_1
  putfield MobWin/ReqGetAD/f Ljava/util/ArrayList;
  return
  nop
.end <method>

.method public c()LMobWin/AppInfo;
.limit locals 2
.limit stack 200
  nop
  aload_0
  getfield MobWin/ReqGetAD/b LMobWin/AppInfo;
  astore_1
  aload_1
  areturn
  nop
.end <method>

.method public clone()Ljava/lang/Object;
.limit locals 6
.limit stack 200
  .catch  java/lang/CloneNotSupportedException <from> Label2 <to> Label3 <using> Label1
  nop
  iconst_0
  istore_1
Label2:
  aload_0
  invokespecial java/lang/Object/clone()Ljava/lang/Object;
  astore_2
Label3:
  aload_2
  astore_1
Label0:
  aload_1
  areturn
Label1:
  astore_3
  getstatic MobWin/ReqGetAD/s Z
  istore 4
  new java/lang/NoClassDefFoundError
  dup
  invokespecial java/lang/NoClassDefFoundError/<init>()V
  athrow
  iload 4
  ifne Label0
  new java/lang/AssertionError
  astore 5
  aload 5
  invokespecial java/lang/AssertionError/<init>()V
  aload 5
  athrow
  nop
.end <method>

.method public d()I
.limit locals 2
.limit stack 200
  nop
  aload_0
  getfield MobWin/ReqGetAD/c I
  istore_1
  iload_1
  ireturn
  nop
.end <method>

.method public display(Ljava/lang/StringBuilder;I)V
.limit locals 12
.limit stack 200
  nop
  new com/qq/taf/jce/JceDisplayer
  astore_3
  aload_3
  aload_1
  iload_2
  invokespecial com/qq/taf/jce/JceDisplayer/<init>(Ljava/lang/StringBuilder;I)V
  aload_0
  getfield MobWin/ReqGetAD/a LMobWin/UserInfo;
  astore 4
  ldc "user_info"
  astore 5
  aload_3
  aload 4
  aload 5
  invokevirtual com/qq/taf/jce/JceDisplayer/display(Lcom/qq/taf/jce/JceStruct;Ljava/lang/String;)Lcom/qq/taf/jce/JceDisplayer;
  pop
  aload_0
  getfield MobWin/ReqGetAD/b LMobWin/AppInfo;
  astore 6
  ldc "app_info"
  astore 5
  aload_3
  aload 6
  aload 5
  invokevirtual com/qq/taf/jce/JceDisplayer/display(Lcom/qq/taf/jce/JceStruct;Ljava/lang/String;)Lcom/qq/taf/jce/JceDisplayer;
  pop
  aload_0
  getfield MobWin/ReqGetAD/c I
  istore_2
  ldc "ad_type"
  astore 5
  aload_3
  iload_2
  aload 5
  invokevirtual com/qq/taf/jce/JceDisplayer/display(ILjava/lang/String;)Lcom/qq/taf/jce/JceDisplayer;
  pop
  aload_0
  getfield MobWin/ReqGetAD/d I
  istore_2
  ldc "ad_amount"
  astore 5
  aload_3
  iload_2
  aload 5
  invokevirtual com/qq/taf/jce/JceDisplayer/display(ILjava/lang/String;)Lcom/qq/taf/jce/JceDisplayer;
  pop
  aload_0
  getfield MobWin/ReqGetAD/e Ljava/util/ArrayList;
  astore 7
  ldc "view_count_list"
  astore 5
  aload_3
  aload 7
  aload 5
  invokevirtual com/qq/taf/jce/JceDisplayer/display(Ljava/util/Collection;Ljava/lang/String;)Lcom/qq/taf/jce/JceDisplayer;
  pop
  aload_0
  getfield MobWin/ReqGetAD/f Ljava/util/ArrayList;
  astore 7
  ldc "click_count_list"
  astore 5
  aload_3
  aload 7
  aload 5
  invokevirtual com/qq/taf/jce/JceDisplayer/display(Ljava/util/Collection;Ljava/lang/String;)Lcom/qq/taf/jce/JceDisplayer;
  pop
  aload_0
  getfield MobWin/ReqGetAD/g LMobWin/UserLocation;
  astore 8
  ldc "loc"
  astore 5
  aload_3
  aload 8
  aload 5
  invokevirtual com/qq/taf/jce/JceDisplayer/display(Lcom/qq/taf/jce/JceStruct;Ljava/lang/String;)Lcom/qq/taf/jce/JceDisplayer;
  pop
  aload_0
  getfield MobWin/ReqGetAD/h LMobWin/SettingVersions;
  astore 9
  ldc "settingVerions"
  astore 5
  aload_3
  aload 9
  aload 5
  invokevirtual com/qq/taf/jce/JceDisplayer/display(Lcom/qq/taf/jce/JceStruct;Ljava/lang/String;)Lcom/qq/taf/jce/JceDisplayer;
  pop
  aload_0
  getfield MobWin/ReqGetAD/i LMobWin/BannerInfo;
  astore 10
  ldc "bannerInfo"
  astore 5
  aload_3
  aload 10
  aload 5
  invokevirtual com/qq/taf/jce/JceDisplayer/display(Lcom/qq/taf/jce/JceStruct;Ljava/lang/String;)Lcom/qq/taf/jce/JceDisplayer;
  pop
  aload_0
  getfield MobWin/ReqGetAD/j Ljava/lang/String;
  astore 11
  ldc "sid"
  astore 5
  aload_3
  aload 11
  aload 5
  invokevirtual com/qq/taf/jce/JceDisplayer/display(Ljava/lang/String;Ljava/lang/String;)Lcom/qq/taf/jce/JceDisplayer;
  pop
  return
  nop
.end <method>

.method public e()I
.limit locals 2
.limit stack 200
  nop
  aload_0
  getfield MobWin/ReqGetAD/d I
  istore_1
  iload_1
  ireturn
  nop
.end <method>

.method public equals(Ljava/lang/Object;)Z
.limit locals 24
.limit stack 200
  nop
  aload_1
  astore 5
  aload 5
  checkcast MobWin/ReqGetAD
  astore 5
  aload 5
  astore 4
  aload_0
  astore_2
  aload_2
  getfield MobWin/ReqGetAD/a LMobWin/UserInfo;
  astore 6
  aload 4
  getfield MobWin/ReqGetAD/a LMobWin/UserInfo;
  astore 7
  aload 6
  aload 7
  invokestatic com/qq/taf/jce/JceUtil/equals(Ljava/lang/Object;Ljava/lang/Object;)Z
  istore 8
  new java/lang/NoClassDefFoundError
  dup
  invokespecial java/lang/NoClassDefFoundError/<init>()V
  athrow
  iload 8
  ifeq Label0
  aload_0
  astore_2
  aload_2
  getfield MobWin/ReqGetAD/b LMobWin/AppInfo;
  astore 9
  aload 4
  getfield MobWin/ReqGetAD/b LMobWin/AppInfo;
  astore 10
  aload 9
  aload 10
  invokestatic com/qq/taf/jce/JceUtil/equals(Ljava/lang/Object;Ljava/lang/Object;)Z
  istore 8
  iload 8
  invokestatic app/DummyClass/invokeIfStmt(Z)V
  iload 8
  ifeq Label0
  aload_0
  astore_2
  aload_2
  getfield MobWin/ReqGetAD/c I
  istore 11
  aload 4
  getfield MobWin/ReqGetAD/c I
  istore 12
  iload 11
  iload 12
  invokestatic com/qq/taf/jce/JceUtil/equals(II)Z
  istore 8
  iload 8
  invokestatic app/DummyClass/invokeIfStmt(Z)V
  iload 8
  ifeq Label0
  aload_0
  astore_2
  aload_2
  getfield MobWin/ReqGetAD/d I
  istore 12
  aload 4
  getfield MobWin/ReqGetAD/d I
  istore 11
  iload 12
  iload 11
  invokestatic com/qq/taf/jce/JceUtil/equals(II)Z
  istore 8
  iload 8
  invokestatic app/DummyClass/invokeIfStmt(Z)V
  iload 8
  ifeq Label0
  aload_0
  astore_2
  aload_2
  getfield MobWin/ReqGetAD/e Ljava/util/ArrayList;
  astore 13
  aload 4
  getfield MobWin/ReqGetAD/e Ljava/util/ArrayList;
  astore 14
  aload 13
  aload 14
  invokestatic com/qq/taf/jce/JceUtil/equals(Ljava/lang/Object;Ljava/lang/Object;)Z
  istore 8
  iload 8
  invokestatic app/DummyClass/invokeIfStmt(Z)V
  iload 8
  ifeq Label0
  aload_0
  astore_2
  aload_2
  getfield MobWin/ReqGetAD/f Ljava/util/ArrayList;
  astore 14
  aload 4
  getfield MobWin/ReqGetAD/f Ljava/util/ArrayList;
  astore 13
  aload 14
  aload 13
  invokestatic com/qq/taf/jce/JceUtil/equals(Ljava/lang/Object;Ljava/lang/Object;)Z
  istore 8
  iload 8
  invokestatic app/DummyClass/invokeIfStmt(Z)V
  iload 8
  ifeq Label0
  aload_0
  astore_2
  aload_2
  getfield MobWin/ReqGetAD/g LMobWin/UserLocation;
  astore 15
  aload 4
  getfield MobWin/ReqGetAD/g LMobWin/UserLocation;
  astore 16
  aload 15
  aload 16
  invokestatic com/qq/taf/jce/JceUtil/equals(Ljava/lang/Object;Ljava/lang/Object;)Z
  istore 8
  iload 8
  invokestatic app/DummyClass/invokeIfStmt(Z)V
  iload 8
  ifeq Label0
  aload_0
  astore_2
  aload_2
  getfield MobWin/ReqGetAD/h LMobWin/SettingVersions;
  astore 17
  aload 4
  getfield MobWin/ReqGetAD/h LMobWin/SettingVersions;
  astore_2
  aload_2
  astore 18
  aload 18
  astore_2
  aload 17
  aload_2
  invokestatic com/qq/taf/jce/JceUtil/equals(Ljava/lang/Object;Ljava/lang/Object;)Z
  istore 8
  iload 8
  invokestatic app/DummyClass/invokeIfStmt(Z)V
  iload 8
  ifeq Label0
  aload_0
  astore_2
  aload_2
  getfield MobWin/ReqGetAD/i LMobWin/BannerInfo;
  astore_2
  aload_2
  astore 19
  aload 4
  getfield MobWin/ReqGetAD/i LMobWin/BannerInfo;
  astore_2
  aload_2
  astore 20
  aload 19
  astore_2
  aload 20
  astore_3
  aload_2
  aload_3
  invokestatic com/qq/taf/jce/JceUtil/equals(Ljava/lang/Object;Ljava/lang/Object;)Z
  istore 8
  iload 8
  invokestatic app/DummyClass/invokeIfStmt(Z)V
  iload 8
  ifeq Label0
  aload_0
  astore_2
  aload_2
  getfield MobWin/ReqGetAD/j Ljava/lang/String;
  astore_2
  aload_2
  astore 21
  aload 4
  getfield MobWin/ReqGetAD/j Ljava/lang/String;
  astore_2
  aload_2
  astore 22
  aload 21
  astore_2
  aload 22
  astore_3
  aload_2
  aload_3
  invokestatic com/qq/taf/jce/JceUtil/equals(Ljava/lang/Object;Ljava/lang/Object;)Z
  istore 8
  iload 8
  invokestatic app/DummyClass/invokeIfStmt(Z)V
  iload 8
  ifeq Label0
  iconst_1
  istore 23
  iload 23
  ireturn
Label0:
  iconst_0
  istore 23
  iload 23
  ireturn
  nop
.end <method>

.method public f()Ljava/util/ArrayList;
.limit locals 2
.limit stack 200
  nop
  aload_0
  getfield MobWin/ReqGetAD/e Ljava/util/ArrayList;
  astore_1
  aload_1
  areturn
  nop
.end <method>

.method public g()Ljava/util/ArrayList;
.limit locals 2
.limit stack 200
  nop
  aload_0
  getfield MobWin/ReqGetAD/f Ljava/util/ArrayList;
  astore_1
  aload_1
  areturn
  nop
.end <method>

.method public h()LMobWin/UserLocation;
.limit locals 2
.limit stack 200
  nop
  aload_0
  getfield MobWin/ReqGetAD/g LMobWin/UserLocation;
  astore_1
  aload_1
  areturn
  nop
.end <method>

.method public i()LMobWin/SettingVersions;
.limit locals 2
.limit stack 200
  nop
  aload_0
  getfield MobWin/ReqGetAD/h LMobWin/SettingVersions;
  astore_1
  aload_1
  areturn
  nop
.end <method>

.method public j()LMobWin/BannerInfo;
.limit locals 2
.limit stack 200
  nop
  aload_0
  getfield MobWin/ReqGetAD/i LMobWin/BannerInfo;
  astore_1
  aload_1
  areturn
  nop
.end <method>

.method public k()Ljava/lang/String;
.limit locals 2
.limit stack 200
  nop
  aload_0
  getfield MobWin/ReqGetAD/j Ljava/lang/String;
  astore_1
  aload_1
  areturn
  nop
.end <method>

.method public readFrom(Lcom/qq/taf/jce/JceInputStream;)V
.limit locals 25
.limit stack 200
  nop
  getstatic MobWin/ReqGetAD/k LMobWin/UserInfo;
  astore 4
  new java/lang/NoClassDefFoundError
  dup
  invokespecial java/lang/NoClassDefFoundError/<init>()V
  athrow
  iload 4
  ifne Label0
  new MobWin/UserInfo
  astore 4
  aload 4
  invokespecial MobWin/UserInfo/<init>()V
  aload 4
  putstatic MobWin/ReqGetAD/k LMobWin/UserInfo;
Label0:
  getstatic MobWin/ReqGetAD/k LMobWin/UserInfo;
  astore 4
  iconst_0
  istore 6
  iload 6
  istore 5
  iconst_1
  istore 6
  aload_1
  astore_2
  aload_2
  aload 4
  iload 5
  iload 6
  invokevirtual com/qq/taf/jce/JceInputStream/read(Lcom/qq/taf/jce/JceStruct;IZ)Lcom/qq/taf/jce/JceStruct;
  astore 7
  aload 7
  astore 8
  aload 8
  checkcast MobWin/UserInfo
  astore 8
  aload 8
  astore 4
  aload_0
  astore_2
  aload_2
  aload 4
  invokevirtual MobWin/ReqGetAD/a(LMobWin/UserInfo;)V
  getstatic MobWin/ReqGetAD/l LMobWin/AppInfo;
  astore 9
  aload 9
  invokestatic app/DummyClass/invokeIfStmt(Ljava/lang/Object;)V
  aload 9
  ifnonnull Label1
  new MobWin/AppInfo
  astore 9
  aload 9
  invokespecial MobWin/AppInfo/<init>()V
  aload 9
  putstatic MobWin/ReqGetAD/l LMobWin/AppInfo;
Label1:
  getstatic MobWin/ReqGetAD/l LMobWin/AppInfo;
  astore 9
  iconst_1
  istore 6
  iload 6
  istore 5
  iconst_1
  istore 6
  aload_1
  astore_2
  aload_2
  aload 9
  iload 5
  iload 6
  invokevirtual com/qq/taf/jce/JceInputStream/read(Lcom/qq/taf/jce/JceStruct;IZ)Lcom/qq/taf/jce/JceStruct;
  astore 7
  aload 7
  astore 10
  aload 10
  checkcast MobWin/AppInfo
  astore 10
  aload 10
  astore 9
  aload_0
  astore_2
  aload_2
  aload 9
  invokevirtual MobWin/ReqGetAD/a(LMobWin/AppInfo;)V
  aload_0
  astore_2
  aload_2
  getfield MobWin/ReqGetAD/c I
  istore 5
  iconst_2
  istore 6
  iconst_1
  istore 11
  aload_1
  astore_2
  aload_2
  iload 5
  iload 6
  iload 11
  invokevirtual com/qq/taf/jce/JceInputStream/read(IIZ)I
  istore 5
  aload_0
  astore_2
  aload_2
  iload 5
  invokevirtual MobWin/ReqGetAD/a(I)V
  aload_0
  astore_2
  aload_2
  getfield MobWin/ReqGetAD/d I
  istore 5
  iconst_3
  istore 6
  iconst_1
  istore 11
  aload_1
  astore_2
  aload_2
  iload 5
  iload 6
  iload 11
  invokevirtual com/qq/taf/jce/JceInputStream/read(IIZ)I
  istore 5
  aload_0
  astore_2
  aload_2
  iload 5
  invokevirtual MobWin/ReqGetAD/b(I)V
  getstatic MobWin/ReqGetAD/n Ljava/util/ArrayList;
  astore 12
  aload 12
  invokestatic app/DummyClass/invokeIfStmt(Ljava/lang/Object;)V
  aload 12
  ifnonnull Label2
  new java/util/ArrayList
  astore 12
  aload 12
  invokespecial java/util/ArrayList/<init>()V
  aload 12
  putstatic MobWin/ReqGetAD/n Ljava/util/ArrayList;
  new MobWin/ADViewAccInfo
  astore 13
  aload 13
  invokespecial MobWin/ADViewAccInfo/<init>()V
  getstatic MobWin/ReqGetAD/n Ljava/util/ArrayList;
  astore 12
  aload 12
  aload 13
  invokevirtual java/util/ArrayList/add(Ljava/lang/Object;)Z
  pop
Label2:
  getstatic MobWin/ReqGetAD/n Ljava/util/ArrayList;
  astore 12
  iconst_4
  istore 6
  iconst_1
  istore 11
  aload_1
  astore_2
  aload_2
  aload 12
  iload 6
  iload 11
  invokevirtual com/qq/taf/jce/JceInputStream/read(Ljava/lang/Object;IZ)Ljava/lang/Object;
  astore 14
  aload 14
  astore 15
  aload 15
  checkcast java/util/ArrayList
  astore 15
  aload 15
  astore 12
  aload_0
  astore_2
  aload_2
  aload 12
  invokevirtual MobWin/ReqGetAD/a(Ljava/util/ArrayList;)V
  getstatic MobWin/ReqGetAD/o Ljava/util/ArrayList;
  astore 12
  aload 12
  invokestatic app/DummyClass/invokeIfStmt(Ljava/lang/Object;)V
  aload 12
  ifnonnull Label3
  new java/util/ArrayList
  astore 12
  aload 12
  invokespecial java/util/ArrayList/<init>()V
  aload 12
  putstatic MobWin/ReqGetAD/o Ljava/util/ArrayList;
  new MobWin/ADClickAccInfo
  astore 16
  aload 16
  invokespecial MobWin/ADClickAccInfo/<init>()V
  getstatic MobWin/ReqGetAD/o Ljava/util/ArrayList;
  astore 12
  aload 12
  aload 16
  invokevirtual java/util/ArrayList/add(Ljava/lang/Object;)Z
  pop
Label3:
  getstatic MobWin/ReqGetAD/o Ljava/util/ArrayList;
  astore 12
  iconst_5
  istore 6
  iconst_1
  istore 11
  aload_1
  astore_2
  aload_2
  aload 12
  iload 6
  iload 11
  invokevirtual com/qq/taf/jce/JceInputStream/read(Ljava/lang/Object;IZ)Ljava/lang/Object;
  astore 14
  aload 14
  astore 17
  aload 17
  checkcast java/util/ArrayList
  astore 17
  aload 17
  astore 12
  aload_0
  astore_2
  aload_2
  aload 12
  invokevirtual MobWin/ReqGetAD/b(Ljava/util/ArrayList;)V
  getstatic MobWin/ReqGetAD/p LMobWin/UserLocation;
  astore 18
  aload 18
  astore_2
  aload_2
  invokestatic app/DummyClass/invokeIfStmt(Ljava/lang/Object;)V
  aload 18
  ifnonnull Label4
  new MobWin/UserLocation
  astore 18
  aload 18
  astore_2
  aload_2
  invokespecial MobWin/UserLocation/<init>()V
  aload 18
  putstatic MobWin/ReqGetAD/p LMobWin/UserLocation;
Label4:
  getstatic MobWin/ReqGetAD/p LMobWin/UserLocation;
  astore 18
  bipush 6
  istore 6
  iconst_0
  istore 11
  aload_1
  astore_2
  aload 18
  astore_3
  aload_2
  aload_3
  iload 6
  iload 11
  invokevirtual com/qq/taf/jce/JceInputStream/read(Lcom/qq/taf/jce/JceStruct;IZ)Lcom/qq/taf/jce/JceStruct;
  astore 7
  aload 7
  astore 19
  aload 19
  checkcast MobWin/UserLocation
  astore 19
  aload 19
  astore 18
  aload_0
  astore_2
  aload 18
  astore_3
  aload_2
  aload_3
  invokevirtual MobWin/ReqGetAD/a(LMobWin/UserLocation;)V
  getstatic MobWin/ReqGetAD/q LMobWin/SettingVersions;
  astore 20
  aload 20
  astore_2
  aload_2
  invokestatic app/DummyClass/invokeIfStmt(Ljava/lang/Object;)V
  aload 20
  ifnonnull Label5
  new MobWin/SettingVersions
  astore 20
  aload 20
  astore_2
  aload_2
  invokespecial MobWin/SettingVersions/<init>()V
  aload 20
  putstatic MobWin/ReqGetAD/q LMobWin/SettingVersions;
Label5:
  getstatic MobWin/ReqGetAD/q LMobWin/SettingVersions;
  astore 20
  bipush 7
  istore 6
  iconst_0
  istore 11
  aload_1
  astore_2
  aload 20
  astore_3
  aload_2
  aload_3
  iload 6
  iload 11
  invokevirtual com/qq/taf/jce/JceInputStream/read(Lcom/qq/taf/jce/JceStruct;IZ)Lcom/qq/taf/jce/JceStruct;
  astore 7
  aload 7
  astore 21
  aload 21
  checkcast MobWin/SettingVersions
  astore 21
  aload 21
  astore 20
  aload_0
  astore_2
  aload 20
  astore_3
  aload_2
  aload_3
  invokevirtual MobWin/ReqGetAD/a(LMobWin/SettingVersions;)V
  getstatic MobWin/ReqGetAD/r LMobWin/BannerInfo;
  astore 22
  aload 22
  astore_2
  aload_2
  invokestatic app/DummyClass/invokeIfStmt(Ljava/lang/Object;)V
  aload 22
  ifnonnull Label6
  new MobWin/BannerInfo
  astore 22
  aload 22
  astore_2
  aload_2
  invokespecial MobWin/BannerInfo/<init>()V
  aload 22
  putstatic MobWin/ReqGetAD/r LMobWin/BannerInfo;
Label6:
  getstatic MobWin/ReqGetAD/r LMobWin/BannerInfo;
  astore 22
  bipush 8
  istore 6
  iconst_0
  istore 11
  aload_1
  astore_2
  aload 22
  astore_3
  aload_2
  aload_3
  iload 6
  iload 11
  invokevirtual com/qq/taf/jce/JceInputStream/read(Lcom/qq/taf/jce/JceStruct;IZ)Lcom/qq/taf/jce/JceStruct;
  astore 7
  aload 7
  astore 23
  aload 23
  checkcast MobWin/BannerInfo
  astore 23
  aload 23
  astore 22
  aload_0
  astore_2
  aload 22
  astore_3
  aload_2
  aload_3
  invokevirtual MobWin/ReqGetAD/a(LMobWin/BannerInfo;)V
  bipush 9
  istore 6
  iconst_0
  istore 11
  aload_1
  astore_2
  aload_2
  iload 6
  iload 11
  invokevirtual com/qq/taf/jce/JceInputStream/readString(IZ)Ljava/lang/String;
  astore 24
  aload_0
  astore_2
  aload 24
  astore_3
  aload_2
  aload_3
  invokevirtual MobWin/ReqGetAD/a(Ljava/lang/String;)V
  return
  nop
.end <method>

.method public writeTo(Lcom/qq/taf/jce/JceOutputStream;)V
.limit locals 11
.limit stack 200
  nop
  aload_0
  getfield MobWin/ReqGetAD/a LMobWin/UserInfo;
  astore_2
  iconst_0
  istore_3
  aload_1
  aload_2
  iload_3
  invokevirtual com/qq/taf/jce/JceOutputStream/write(Lcom/qq/taf/jce/JceStruct;I)V
  aload_0
  getfield MobWin/ReqGetAD/b LMobWin/AppInfo;
  astore 4
  iconst_1
  istore_3
  aload_1
  aload 4
  iload_3
  invokevirtual com/qq/taf/jce/JceOutputStream/write(Lcom/qq/taf/jce/JceStruct;I)V
  aload_0
  getfield MobWin/ReqGetAD/c I
  istore 5
  iconst_2
  istore_3
  aload_1
  iload 5
  iload_3
  invokevirtual com/qq/taf/jce/JceOutputStream/write(II)V
  aload_0
  getfield MobWin/ReqGetAD/d I
  istore 5
  iconst_3
  istore_3
  aload_1
  iload 5
  iload_3
  invokevirtual com/qq/taf/jce/JceOutputStream/write(II)V
  aload_0
  getfield MobWin/ReqGetAD/e Ljava/util/ArrayList;
  astore 6
  iconst_4
  istore_3
  aload_1
  aload 6
  iload_3
  invokevirtual com/qq/taf/jce/JceOutputStream/write(Ljava/util/Collection;I)V
  aload_0
  getfield MobWin/ReqGetAD/f Ljava/util/ArrayList;
  astore 6
  iconst_5
  istore_3
  aload_1
  aload 6
  iload_3
  invokevirtual com/qq/taf/jce/JceOutputStream/write(Ljava/util/Collection;I)V
  aload_0
  getfield MobWin/ReqGetAD/g LMobWin/UserLocation;
  astore 7
  new java/lang/NoClassDefFoundError
  dup
  invokespecial java/lang/NoClassDefFoundError/<init>()V
  athrow
  iload 7
  ifeq Label0
  aload_0
  getfield MobWin/ReqGetAD/g LMobWin/UserLocation;
  astore 7
  bipush 6
  istore_3
  aload_1
  aload 7
  iload_3
  invokevirtual com/qq/taf/jce/JceOutputStream/write(Lcom/qq/taf/jce/JceStruct;I)V
Label0:
  aload_0
  getfield MobWin/ReqGetAD/h LMobWin/SettingVersions;
  astore 8
  aload 8
  invokestatic app/DummyClass/invokeIfStmt(Ljava/lang/Object;)V
  aload 8
  ifnull Label1
  aload_0
  getfield MobWin/ReqGetAD/h LMobWin/SettingVersions;
  astore 8
  bipush 7
  istore_3
  aload_1
  aload 8
  iload_3
  invokevirtual com/qq/taf/jce/JceOutputStream/write(Lcom/qq/taf/jce/JceStruct;I)V
Label1:
  aload_0
  getfield MobWin/ReqGetAD/i LMobWin/BannerInfo;
  astore 9
  aload 9
  invokestatic app/DummyClass/invokeIfStmt(Ljava/lang/Object;)V
  aload 9
  ifnull Label2
  aload_0
  getfield MobWin/ReqGetAD/i LMobWin/BannerInfo;
  astore 9
  bipush 8
  istore_3
  aload_1
  aload 9
  iload_3
  invokevirtual com/qq/taf/jce/JceOutputStream/write(Lcom/qq/taf/jce/JceStruct;I)V
Label2:
  aload_0
  getfield MobWin/ReqGetAD/j Ljava/lang/String;
  astore 10
  aload 10
  invokestatic app/DummyClass/invokeIfStmt(Ljava/lang/Object;)V
  aload 10
  ifnull Label3
  aload_0
  getfield MobWin/ReqGetAD/j Ljava/lang/String;
  astore 10
  bipush 9
  istore_3
  aload_1
  aload 10
  iload_3
  invokevirtual com/qq/taf/jce/JceOutputStream/write(Ljava/lang/String;I)V
Label3:
  return
  nop
.end <method>

