.source GPS.java
.class public final  MobWin/GPS
.super com/qq/taf/jce/JceStruct
.field static final "$assertionsDisabled" Z =  0
.field static "cache_eType" I =  0
.field static "cache_vLBSKeyData" [B
.field public "eType" I
.field public "iAlt" I
.field public "iLat" I
.field public "iLon" I
.field public "vLBSKeyData" [B

.method static <clinit>()V
.limit locals 2
.limit stack 200
  nop
  ldc MobWin/GPS
  astore_0
  aload_0
  invokevirtual java/lang/Class/desiredAssertionStatus()Z
  istore_1
  new java/lang/NoClassDefFoundError
  dup
  invokespecial java/lang/NoClassDefFoundError/<init>()V
  athrow
  iload_1
  ifne Label0
  iconst_1
  istore_1
Label1:
  iload_1
  putstatic MobWin/GPS/$assertionsDisabled Z
  return
Label0:
  iconst_0
  istore_1
  goto Label1
  nop
.end <method>

.method public <init>()V
.limit locals 5
.limit stack 200
  nop
  aload_0
  invokespecial com/qq/taf/jce/JceStruct/<init>()V
  ldc 900000000
  istore_1
  aload_0
  iload_1
  putfield MobWin/GPS/iLat I
  ldc 900000000
  istore_1
  aload_0
  iload_1
  putfield MobWin/GPS/iLon I
  ldc -10000000
  istore_1
  aload_0
  iload_1
  putfield MobWin/GPS/iAlt I
  iconst_0
  istore_1
  aload_0
  iload_1
  putfield MobWin/GPS/eType I
  aconst_null
  astore_2
  aload_0
  aload_2
  putfield MobWin/GPS/vLBSKeyData [B
  aload_0
  getfield MobWin/GPS/iLat I
  istore_3
  aload_0
  iload_3
  invokevirtual MobWin/GPS/setILat(I)V
  aload_0
  getfield MobWin/GPS/iLon I
  istore_3
  aload_0
  iload_3
  invokevirtual MobWin/GPS/setILon(I)V
  aload_0
  getfield MobWin/GPS/iAlt I
  istore_3
  aload_0
  iload_3
  invokevirtual MobWin/GPS/setIAlt(I)V
  aload_0
  getfield MobWin/GPS/eType I
  istore_3
  aload_0
  iload_3
  invokevirtual MobWin/GPS/setEType(I)V
  aload_0
  getfield MobWin/GPS/vLBSKeyData [B
  astore 4
  aload_0
  aload 4
  invokevirtual MobWin/GPS/setVLBSKeyData([B)V
  return
  nop
.end <method>

.method public <init>(IIII[B)V
.limit locals 8
.limit stack 200
  nop
  aload_0
  invokespecial com/qq/taf/jce/JceStruct/<init>()V
  ldc 900000000
  istore 6
  aload_0
  iload 6
  putfield MobWin/GPS/iLat I
  ldc 900000000
  istore 6
  aload_0
  iload 6
  putfield MobWin/GPS/iLon I
  ldc -10000000
  istore 6
  aload_0
  iload 6
  putfield MobWin/GPS/iAlt I
  iconst_0
  istore 6
  aload_0
  iload 6
  putfield MobWin/GPS/eType I
  aconst_null
  astore 7
  aload_0
  aload 7
  putfield MobWin/GPS/vLBSKeyData [B
  aload_0
  iload_1
  invokevirtual MobWin/GPS/setILat(I)V
  aload_0
  iload_2
  invokevirtual MobWin/GPS/setILon(I)V
  aload_0
  iload_3
  invokevirtual MobWin/GPS/setIAlt(I)V
  aload_0
  iload 4
  invokevirtual MobWin/GPS/setEType(I)V
  aload_0
  aload 5
  invokevirtual MobWin/GPS/setVLBSKeyData([B)V
  return
  nop
.end <method>

.method public className()Ljava/lang/String;
.limit locals 2
.limit stack 200
  nop
  ldc "MobWin.GPS"
  astore_1
  aload_1
  areturn
  nop
.end <method>

.method public clone()Ljava/lang/Object;
.limit locals 6
.limit stack 200
  .catch  java/lang/CloneNotSupportedException <from> Label2 <to> Label3 <using> Label1
  nop
  iconst_0
  istore_1
Label2:
  aload_0
  invokespecial java/lang/Object/clone()Ljava/lang/Object;
  astore_2
Label3:
  aload_2
  astore_1
Label0:
  aload_1
  areturn
Label1:
  astore_3
  getstatic MobWin/GPS/$assertionsDisabled Z
  istore 4
  new java/lang/NoClassDefFoundError
  dup
  invokespecial java/lang/NoClassDefFoundError/<init>()V
  athrow
  iload 4
  ifne Label0
  new java/lang/AssertionError
  astore 5
  aload 5
  invokespecial java/lang/AssertionError/<init>()V
  aload 5
  athrow
  nop
.end <method>

.method public display(Ljava/lang/StringBuilder;I)V
.limit locals 6
.limit stack 200
  nop
  new com/qq/taf/jce/JceDisplayer
  astore_3
  aload_3
  aload_1
  iload_2
  invokespecial com/qq/taf/jce/JceDisplayer/<init>(Ljava/lang/StringBuilder;I)V
  aload_0
  getfield MobWin/GPS/iLat I
  istore_2
  ldc "iLat"
  astore 4
  aload_3
  iload_2
  aload 4
  invokevirtual com/qq/taf/jce/JceDisplayer/display(ILjava/lang/String;)Lcom/qq/taf/jce/JceDisplayer;
  pop
  aload_0
  getfield MobWin/GPS/iLon I
  istore_2
  ldc "iLon"
  astore 4
  aload_3
  iload_2
  aload 4
  invokevirtual com/qq/taf/jce/JceDisplayer/display(ILjava/lang/String;)Lcom/qq/taf/jce/JceDisplayer;
  pop
  aload_0
  getfield MobWin/GPS/iAlt I
  istore_2
  ldc "iAlt"
  astore 4
  aload_3
  iload_2
  aload 4
  invokevirtual com/qq/taf/jce/JceDisplayer/display(ILjava/lang/String;)Lcom/qq/taf/jce/JceDisplayer;
  pop
  aload_0
  getfield MobWin/GPS/eType I
  istore_2
  ldc "eType"
  astore 4
  aload_3
  iload_2
  aload 4
  invokevirtual com/qq/taf/jce/JceDisplayer/display(ILjava/lang/String;)Lcom/qq/taf/jce/JceDisplayer;
  pop
  aload_0
  getfield MobWin/GPS/vLBSKeyData [B
  astore 5
  ldc "vLBSKeyData"
  astore 4
  aload_3
  aload 5
  aload 4
  invokevirtual com/qq/taf/jce/JceDisplayer/display([BLjava/lang/String;)Lcom/qq/taf/jce/JceDisplayer;
  pop
  return
  nop
.end <method>

.method public equals(Ljava/lang/Object;)Z
.limit locals 10
.limit stack 200
  nop
  aload_1
  astore_3
  aload_3
  checkcast MobWin/GPS
  astore_3
  aload_3
  astore_2
  aload_0
  getfield MobWin/GPS/iLat I
  istore 4
  aload_2
  getfield MobWin/GPS/iLat I
  istore 5
  iload 4
  iload 5
  invokestatic com/qq/taf/jce/JceUtil/equals(II)Z
  istore 6
  new java/lang/NoClassDefFoundError
  dup
  invokespecial java/lang/NoClassDefFoundError/<init>()V
  athrow
  iload 6
  ifeq Label0
  aload_0
  getfield MobWin/GPS/iLon I
  istore 5
  aload_2
  getfield MobWin/GPS/iLon I
  istore 4
  iload 5
  iload 4
  invokestatic com/qq/taf/jce/JceUtil/equals(II)Z
  istore 6
  iload 6
  invokestatic app/DummyClass/invokeIfStmt(Z)V
  iload 6
  ifeq Label0
  aload_0
  getfield MobWin/GPS/iAlt I
  istore 5
  aload_2
  getfield MobWin/GPS/iAlt I
  istore 4
  iload 5
  iload 4
  invokestatic com/qq/taf/jce/JceUtil/equals(II)Z
  istore 6
  iload 6
  invokestatic app/DummyClass/invokeIfStmt(Z)V
  iload 6
  ifeq Label0
  aload_0
  getfield MobWin/GPS/eType I
  istore 5
  aload_2
  getfield MobWin/GPS/eType I
  istore 4
  iload 5
  iload 4
  invokestatic com/qq/taf/jce/JceUtil/equals(II)Z
  istore 6
  iload 6
  invokestatic app/DummyClass/invokeIfStmt(Z)V
  iload 6
  ifeq Label0
  aload_0
  getfield MobWin/GPS/vLBSKeyData [B
  astore 7
  aload_2
  getfield MobWin/GPS/vLBSKeyData [B
  astore 8
  aload 7
  aload 8
  invokestatic com/qq/taf/jce/JceUtil/equals(Ljava/lang/Object;Ljava/lang/Object;)Z
  istore 6
  iload 6
  invokestatic app/DummyClass/invokeIfStmt(Z)V
  iload 6
  ifeq Label0
  iconst_1
  istore 9
  iload 9
  ireturn
Label0:
  iconst_0
  istore 9
  iload 9
  ireturn
  nop
.end <method>

.method public getEType()I
.limit locals 2
.limit stack 200
  nop
  aload_0
  getfield MobWin/GPS/eType I
  istore_1
  iload_1
  ireturn
  nop
.end <method>

.method public getIAlt()I
.limit locals 2
.limit stack 200
  nop
  aload_0
  getfield MobWin/GPS/iAlt I
  istore_1
  iload_1
  ireturn
  nop
.end <method>

.method public getILat()I
.limit locals 2
.limit stack 200
  nop
  aload_0
  getfield MobWin/GPS/iLat I
  istore_1
  iload_1
  ireturn
  nop
.end <method>

.method public getILon()I
.limit locals 2
.limit stack 200
  nop
  aload_0
  getfield MobWin/GPS/iLon I
  istore_1
  iload_1
  ireturn
  nop
.end <method>

.method public getVLBSKeyData()[B
.limit locals 2
.limit stack 200
  nop
  aload_0
  getfield MobWin/GPS/vLBSKeyData [B
  astore_1
  aload_1
  areturn
  nop
.end <method>

.method public readFrom(Lcom/qq/taf/jce/JceInputStream;)V
.limit locals 7
.limit stack 200
  nop
  aload_0
  getfield MobWin/GPS/iLat I
  istore_2
  iconst_0
  istore 4
  iload 4
  istore_3
  iconst_1
  istore 4
  aload_1
  iload_2
  iload_3
  iload 4
  invokevirtual com/qq/taf/jce/JceInputStream/read(IIZ)I
  istore_2
  aload_0
  iload_2
  invokevirtual MobWin/GPS/setILat(I)V
  aload_0
  getfield MobWin/GPS/iLon I
  istore_2
  iconst_1
  istore 4
  iload 4
  istore_3
  iconst_1
  istore 4
  aload_1
  iload_2
  iload_3
  iload 4
  invokevirtual com/qq/taf/jce/JceInputStream/read(IIZ)I
  istore_2
  aload_0
  iload_2
  invokevirtual MobWin/GPS/setILon(I)V
  aload_0
  getfield MobWin/GPS/iAlt I
  istore_3
  iconst_2
  istore 4
  iconst_1
  istore 5
  aload_1
  iload_3
  iload 4
  iload 5
  invokevirtual com/qq/taf/jce/JceInputStream/read(IIZ)I
  istore_3
  aload_0
  iload_3
  invokevirtual MobWin/GPS/setIAlt(I)V
  aload_0
  getfield MobWin/GPS/eType I
  istore_3
  iconst_3
  istore 4
  iconst_1
  istore 5
  aload_1
  iload_3
  iload 4
  iload 5
  invokevirtual com/qq/taf/jce/JceInputStream/read(IIZ)I
  istore_3
  aload_0
  iload_3
  invokevirtual MobWin/GPS/setEType(I)V
  getstatic MobWin/GPS/cache_vLBSKeyData [B
  astore 6
  new java/lang/NoClassDefFoundError
  dup
  invokespecial java/lang/NoClassDefFoundError/<init>()V
  athrow
  iload 6
  ifne Label0
  iconst_1
  istore 4
  iload 4
  istore_3
  iload_3
  newarray byte
  astore 6
  aload 6
  putstatic MobWin/GPS/cache_vLBSKeyData [B
  getstatic MobWin/GPS/cache_vLBSKeyData [B
  astore 6
  iconst_0
  istore 4
  iload 4
  istore_3
  iconst_0
  istore 4
  aload 6
  iload_3
  iload 4
  bastore
Label0:
  getstatic MobWin/GPS/cache_vLBSKeyData [B
  astore 6
  iconst_4
  istore 4
  iconst_0
  istore 5
  aload_1
  aload 6
  iload 4
  iload 5
  invokevirtual com/qq/taf/jce/JceInputStream/read([BIZ)[B
  astore 6
  aload_0
  aload 6
  invokevirtual MobWin/GPS/setVLBSKeyData([B)V
  return
  nop
.end <method>

.method public setEType(I)V
.limit locals 2
.limit stack 200
  nop
  aload_0
  iload_1
  putfield MobWin/GPS/eType I
  return
  nop
.end <method>

.method public setIAlt(I)V
.limit locals 2
.limit stack 200
  nop
  aload_0
  iload_1
  putfield MobWin/GPS/iAlt I
  return
  nop
.end <method>

.method public setILat(I)V
.limit locals 2
.limit stack 200
  nop
  aload_0
  iload_1
  putfield MobWin/GPS/iLat I
  return
  nop
.end <method>

.method public setILon(I)V
.limit locals 2
.limit stack 200
  nop
  aload_0
  iload_1
  putfield MobWin/GPS/iLon I
  return
  nop
.end <method>

.method public setVLBSKeyData([B)V
.limit locals 2
.limit stack 200
  nop
  aload_0
  aload_1
  putfield MobWin/GPS/vLBSKeyData [B
  return
  nop
.end <method>

.method public writeTo(Lcom/qq/taf/jce/JceOutputStream;)V
.limit locals 5
.limit stack 200
  nop
  aload_0
  getfield MobWin/GPS/iLat I
  istore_2
  iconst_0
  istore_3
  aload_1
  iload_2
  iload_3
  invokevirtual com/qq/taf/jce/JceOutputStream/write(II)V
  aload_0
  getfield MobWin/GPS/iLon I
  istore_2
  iconst_1
  istore_3
  aload_1
  iload_2
  iload_3
  invokevirtual com/qq/taf/jce/JceOutputStream/write(II)V
  aload_0
  getfield MobWin/GPS/iAlt I
  istore_2
  iconst_2
  istore_3
  aload_1
  iload_2
  iload_3
  invokevirtual com/qq/taf/jce/JceOutputStream/write(II)V
  aload_0
  getfield MobWin/GPS/eType I
  istore_2
  iconst_3
  istore_3
  aload_1
  iload_2
  iload_3
  invokevirtual com/qq/taf/jce/JceOutputStream/write(II)V
  aload_0
  getfield MobWin/GPS/vLBSKeyData [B
  astore 4
  new java/lang/NoClassDefFoundError
  dup
  invokespecial java/lang/NoClassDefFoundError/<init>()V
  athrow
  iload 4
  ifeq Label0
  aload_0
  getfield MobWin/GPS/vLBSKeyData [B
  astore 4
  iconst_4
  istore_3
  aload_1
  aload 4
  iload_3
  invokevirtual com/qq/taf/jce/JceOutputStream/write([BI)V
Label0:
  return
  nop
.end <method>

