.source dalvik_source_VirusShare_32e70f448ebd75661a1cb12f9cd8e013.apk
.class public final  MobWin/BannerInfo
.super com/qq/taf/jce/JceStruct
.field static final "e" Z =  0
.field public "a" I
.field public "b" I
.field public "c" Ljava/lang/String;
.field public "d" B

.method static <clinit>()V
.limit locals 2
.limit stack 200
  nop
  ldc MobWin/BannerInfo
  astore_0
  aload_0
  invokevirtual java/lang/Class/desiredAssertionStatus()Z
  istore_1
  new java/lang/NoClassDefFoundError
  dup
  invokespecial java/lang/NoClassDefFoundError/<init>()V
  athrow
  iload_1
  ifne Label0
  iconst_1
  istore_1
Label1:
  iload_1
  putstatic MobWin/BannerInfo/e Z
  return
Label0:
  iconst_0
  istore_1
  goto Label1
  nop
.end <method>

.method public <init>()V
.limit locals 6
.limit stack 200
  nop
  aload_0
  invokespecial com/qq/taf/jce/JceStruct/<init>()V
  iconst_0
  istore_1
  aload_0
  iload_1
  putfield MobWin/BannerInfo/a I
  iconst_0
  istore_1
  aload_0
  iload_1
  putfield MobWin/BannerInfo/b I
  ldc ""
  astore_2
  aload_0
  aload_2
  putfield MobWin/BannerInfo/c Ljava/lang/String;
  iconst_1
  istore_1
  aload_0
  iload_1
  putfield MobWin/BannerInfo/d B
  aload_0
  getfield MobWin/BannerInfo/a I
  istore_3
  aload_0
  iload_3
  invokevirtual MobWin/BannerInfo/a(I)V
  aload_0
  getfield MobWin/BannerInfo/b I
  istore_3
  aload_0
  iload_3
  invokevirtual MobWin/BannerInfo/b(I)V
  aload_0
  getfield MobWin/BannerInfo/c Ljava/lang/String;
  astore 4
  aload_0
  aload 4
  invokevirtual MobWin/BannerInfo/a(Ljava/lang/String;)V
  aload_0
  getfield MobWin/BannerInfo/d B
  istore 5
  aload_0
  iload 5
  invokevirtual MobWin/BannerInfo/a(B)V
  return
  nop
.end <method>

.method public <init>(IILjava/lang/String;B)V
.limit locals 7
.limit stack 200
  nop
  aload_0
  invokespecial com/qq/taf/jce/JceStruct/<init>()V
  iconst_0
  istore 5
  aload_0
  iload 5
  putfield MobWin/BannerInfo/a I
  iconst_0
  istore 5
  aload_0
  iload 5
  putfield MobWin/BannerInfo/b I
  ldc ""
  astore 6
  aload_0
  aload 6
  putfield MobWin/BannerInfo/c Ljava/lang/String;
  iconst_1
  istore 5
  aload_0
  iload 5
  putfield MobWin/BannerInfo/d B
  aload_0
  iload_1
  invokevirtual MobWin/BannerInfo/a(I)V
  aload_0
  iload_2
  invokevirtual MobWin/BannerInfo/b(I)V
  aload_0
  aload_3
  invokevirtual MobWin/BannerInfo/a(Ljava/lang/String;)V
  aload_0
  iload 4
  invokevirtual MobWin/BannerInfo/a(B)V
  return
  nop
.end <method>

.method public a()Ljava/lang/String;
.limit locals 2
.limit stack 200
  nop
  ldc "MobWin.BannerInfo"
  astore_1
  aload_1
  areturn
  nop
.end <method>

.method public a(B)V
.limit locals 2
.limit stack 200
  nop
  aload_0
  iload_1
  putfield MobWin/BannerInfo/d B
  return
  nop
.end <method>

.method public a(I)V
.limit locals 2
.limit stack 200
  nop
  aload_0
  iload_1
  putfield MobWin/BannerInfo/a I
  return
  nop
.end <method>

.method public a(Ljava/lang/String;)V
.limit locals 2
.limit stack 200
  nop
  aload_0
  aload_1
  putfield MobWin/BannerInfo/c Ljava/lang/String;
  return
  nop
.end <method>

.method public b()I
.limit locals 2
.limit stack 200
  nop
  aload_0
  getfield MobWin/BannerInfo/a I
  istore_1
  iload_1
  ireturn
  nop
.end <method>

.method public b(I)V
.limit locals 2
.limit stack 200
  nop
  aload_0
  iload_1
  putfield MobWin/BannerInfo/b I
  return
  nop
.end <method>

.method public c()I
.limit locals 2
.limit stack 200
  nop
  aload_0
  getfield MobWin/BannerInfo/b I
  istore_1
  iload_1
  ireturn
  nop
.end <method>

.method public clone()Ljava/lang/Object;
.limit locals 6
.limit stack 200
  .catch  java/lang/CloneNotSupportedException <from> Label2 <to> Label3 <using> Label1
  nop
  iconst_0
  istore_1
Label2:
  aload_0
  invokespecial java/lang/Object/clone()Ljava/lang/Object;
  astore_2
Label3:
  aload_2
  astore_1
Label0:
  aload_1
  areturn
Label1:
  astore_3
  getstatic MobWin/BannerInfo/e Z
  istore 4
  new java/lang/NoClassDefFoundError
  dup
  invokespecial java/lang/NoClassDefFoundError/<init>()V
  athrow
  iload 4
  ifne Label0
  new java/lang/AssertionError
  astore 5
  aload 5
  invokespecial java/lang/AssertionError/<init>()V
  aload 5
  athrow
  nop
.end <method>

.method public d()Ljava/lang/String;
.limit locals 2
.limit stack 200
  nop
  aload_0
  getfield MobWin/BannerInfo/c Ljava/lang/String;
  astore_1
  aload_1
  areturn
  nop
.end <method>

.method public display(Ljava/lang/StringBuilder;I)V
.limit locals 7
.limit stack 200
  nop
  new com/qq/taf/jce/JceDisplayer
  astore_3
  aload_3
  aload_1
  iload_2
  invokespecial com/qq/taf/jce/JceDisplayer/<init>(Ljava/lang/StringBuilder;I)V
  aload_0
  getfield MobWin/BannerInfo/a I
  istore_2
  ldc "width"
  astore 4
  aload_3
  iload_2
  aload 4
  invokevirtual com/qq/taf/jce/JceDisplayer/display(ILjava/lang/String;)Lcom/qq/taf/jce/JceDisplayer;
  pop
  aload_0
  getfield MobWin/BannerInfo/b I
  istore_2
  ldc "height"
  astore 4
  aload_3
  iload_2
  aload 4
  invokevirtual com/qq/taf/jce/JceDisplayer/display(ILjava/lang/String;)Lcom/qq/taf/jce/JceDisplayer;
  pop
  aload_0
  getfield MobWin/BannerInfo/c Ljava/lang/String;
  astore 5
  ldc "positionName"
  astore 4
  aload_3
  aload 5
  aload 4
  invokevirtual com/qq/taf/jce/JceDisplayer/display(Ljava/lang/String;Ljava/lang/String;)Lcom/qq/taf/jce/JceDisplayer;
  pop
  aload_0
  getfield MobWin/BannerInfo/d B
  istore 6
  ldc "visiable"
  astore 4
  aload_3
  iload 6
  aload 4
  invokevirtual com/qq/taf/jce/JceDisplayer/display(BLjava/lang/String;)Lcom/qq/taf/jce/JceDisplayer;
  pop
  return
  nop
.end <method>

.method public e()B
.limit locals 2
.limit stack 200
  nop
  aload_0
  getfield MobWin/BannerInfo/d B
  istore_1
  iload_1
  ireturn
  nop
.end <method>

.method public equals(Ljava/lang/Object;)Z
.limit locals 12
.limit stack 200
  nop
  aload_1
  astore_3
  aload_3
  checkcast MobWin/BannerInfo
  astore_3
  aload_3
  astore_2
  aload_0
  getfield MobWin/BannerInfo/a I
  istore 4
  aload_2
  getfield MobWin/BannerInfo/a I
  istore 5
  iload 4
  iload 5
  invokestatic com/qq/taf/jce/JceUtil/equals(II)Z
  istore 6
  new java/lang/NoClassDefFoundError
  dup
  invokespecial java/lang/NoClassDefFoundError/<init>()V
  athrow
  iload 6
  ifeq Label0
  aload_0
  getfield MobWin/BannerInfo/b I
  istore 5
  aload_2
  getfield MobWin/BannerInfo/b I
  istore 4
  iload 5
  iload 4
  invokestatic com/qq/taf/jce/JceUtil/equals(II)Z
  istore 6
  iload 6
  invokestatic app/DummyClass/invokeIfStmt(Z)V
  iload 6
  ifeq Label0
  aload_0
  getfield MobWin/BannerInfo/c Ljava/lang/String;
  astore 7
  aload_2
  getfield MobWin/BannerInfo/c Ljava/lang/String;
  astore 8
  aload 7
  aload 8
  invokestatic com/qq/taf/jce/JceUtil/equals(Ljava/lang/Object;Ljava/lang/Object;)Z
  istore 6
  iload 6
  invokestatic app/DummyClass/invokeIfStmt(Z)V
  iload 6
  ifeq Label0
  aload_0
  getfield MobWin/BannerInfo/d B
  istore 9
  aload_2
  getfield MobWin/BannerInfo/d B
  istore 10
  iload 9
  iload 10
  invokestatic com/qq/taf/jce/JceUtil/equals(BB)Z
  istore 6
  iload 6
  invokestatic app/DummyClass/invokeIfStmt(Z)V
  iload 6
  ifeq Label0
  iconst_1
  istore 11
  iload 11
  ireturn
Label0:
  iconst_0
  istore 11
  iload 11
  ireturn
  nop
.end <method>

.method public readFrom(Lcom/qq/taf/jce/JceInputStream;)V
.limit locals 8
.limit stack 200
  nop
  aload_0
  getfield MobWin/BannerInfo/a I
  istore_2
  iconst_0
  istore 4
  iconst_1
  istore 5
  aload_1
  iload_2
  iload 4
  iload 5
  invokevirtual com/qq/taf/jce/JceInputStream/read(IIZ)I
  istore_3
  aload_0
  iload_3
  invokevirtual MobWin/BannerInfo/a(I)V
  aload_0
  getfield MobWin/BannerInfo/b I
  istore_3
  iconst_1
  istore 4
  iload 4
  istore_2
  iconst_1
  istore 4
  aload_1
  iload_3
  iload_2
  iload 4
  invokevirtual com/qq/taf/jce/JceInputStream/read(IIZ)I
  istore_3
  aload_0
  iload_3
  invokevirtual MobWin/BannerInfo/b(I)V
  iconst_2
  istore 4
  iconst_1
  istore 5
  aload_1
  iload 4
  iload 5
  invokevirtual com/qq/taf/jce/JceInputStream/readString(IZ)Ljava/lang/String;
  astore 6
  aload_0
  aload 6
  invokevirtual MobWin/BannerInfo/a(Ljava/lang/String;)V
  aload_0
  getfield MobWin/BannerInfo/d B
  istore 7
  iconst_3
  istore 4
  iconst_1
  istore 5
  aload_1
  iload 7
  iload 4
  iload 5
  invokevirtual com/qq/taf/jce/JceInputStream/read(BIZ)B
  istore 7
  aload_0
  iload 7
  invokevirtual MobWin/BannerInfo/a(B)V
  return
  nop
.end <method>

.method public writeTo(Lcom/qq/taf/jce/JceOutputStream;)V
.limit locals 6
.limit stack 200
  nop
  aload_0
  getfield MobWin/BannerInfo/a I
  istore_2
  iconst_0
  istore_3
  aload_1
  iload_2
  iload_3
  invokevirtual com/qq/taf/jce/JceOutputStream/write(II)V
  aload_0
  getfield MobWin/BannerInfo/b I
  istore_2
  iconst_1
  istore_3
  aload_1
  iload_2
  iload_3
  invokevirtual com/qq/taf/jce/JceOutputStream/write(II)V
  aload_0
  getfield MobWin/BannerInfo/c Ljava/lang/String;
  astore 4
  iconst_2
  istore_3
  aload_1
  aload 4
  iload_3
  invokevirtual com/qq/taf/jce/JceOutputStream/write(Ljava/lang/String;I)V
  aload_0
  getfield MobWin/BannerInfo/d B
  istore 5
  iconst_3
  istore_3
  aload_1
  iload 5
  iload_3
  invokevirtual com/qq/taf/jce/JceOutputStream/write(BI)V
  return
  nop
.end <method>

