.source APP_PLAY_STATUS_OPTION.java
.class public final  MobWin/APP_PLAY_STATUS_OPTION
.super java/lang/Object
.field static final "$assertionsDisabled" Z =  0
.field public static final "FROZEN" LMobWin/APP_PLAY_STATUS_OPTION;
.field public static final "PLAYING" LMobWin/APP_PLAY_STATUS_OPTION;
.field public static final "STOP" LMobWin/APP_PLAY_STATUS_OPTION;
.field public static final "_FROZEN" I =  0
.field public static final "_PLAYING" I =  2
.field public static final "_STOP" I =  1
.field private static "__values" [LMobWin/APP_PLAY_STATUS_OPTION;
.field private "__T" Ljava/lang/String;
.field private "__value" I

.method static <clinit>()V
.limit locals 9
.limit stack 200
  nop
  ldc MobWin/APP_PLAY_STATUS_OPTION
  astore_0
  aload_0
  invokevirtual java/lang/Class/desiredAssertionStatus()Z
  istore_1
  new java/lang/NoClassDefFoundError
  dup
  invokespecial java/lang/NoClassDefFoundError/<init>()V
  athrow
  iload_1
  ifne Label0
  iconst_1
  istore_1
Label1:
  iload_1
  putstatic MobWin/APP_PLAY_STATUS_OPTION/$assertionsDisabled Z
  iconst_3
  istore_3
  iload_3
  anewarray MobWin/APP_PLAY_STATUS_OPTION
  astore_2
  aload_2
  putstatic MobWin/APP_PLAY_STATUS_OPTION/__values [LMobWin/APP_PLAY_STATUS_OPTION;
  new MobWin/APP_PLAY_STATUS_OPTION
  astore 4
  iconst_0
  istore_3
  iload_3
  istore 5
  iconst_0
  istore_3
  iload_3
  istore 6
  ldc "FROZEN"
  astore 7
  aload 4
  iload 5
  iload 6
  aload 7
  invokespecial MobWin/APP_PLAY_STATUS_OPTION/<init>(IILjava/lang/String;)V
  aload 4
  putstatic MobWin/APP_PLAY_STATUS_OPTION/FROZEN LMobWin/APP_PLAY_STATUS_OPTION;
  new MobWin/APP_PLAY_STATUS_OPTION
  astore 4
  iconst_1
  istore_3
  iload_3
  istore 6
  iconst_1
  istore_3
  iload_3
  istore 5
  ldc "STOP"
  astore 7
  aload 4
  iload 6
  iload 5
  aload 7
  invokespecial MobWin/APP_PLAY_STATUS_OPTION/<init>(IILjava/lang/String;)V
  aload 4
  putstatic MobWin/APP_PLAY_STATUS_OPTION/STOP LMobWin/APP_PLAY_STATUS_OPTION;
  new MobWin/APP_PLAY_STATUS_OPTION
  astore 4
  iconst_2
  istore_3
  iconst_2
  istore 8
  ldc "PLAYING"
  astore 7
  aload 4
  iload_3
  iload 8
  aload 7
  invokespecial MobWin/APP_PLAY_STATUS_OPTION/<init>(IILjava/lang/String;)V
  aload 4
  putstatic MobWin/APP_PLAY_STATUS_OPTION/PLAYING LMobWin/APP_PLAY_STATUS_OPTION;
  return
Label0:
  iconst_0
  istore_1
  goto Label1
  nop
.end <method>

.method private <init>(IILjava/lang/String;)V
.limit locals 6
.limit stack 200
  nop
  aload_0
  invokespecial java/lang/Object/<init>()V
  new java/lang/String
  astore 4
  aload 4
  invokespecial java/lang/String/<init>()V
  aload_0
  aload 4
  putfield MobWin/APP_PLAY_STATUS_OPTION/__T Ljava/lang/String;
  aload_0
  aload_3
  putfield MobWin/APP_PLAY_STATUS_OPTION/__T Ljava/lang/String;
  aload_0
  iload_2
  putfield MobWin/APP_PLAY_STATUS_OPTION/__value I
  getstatic MobWin/APP_PLAY_STATUS_OPTION/__values [LMobWin/APP_PLAY_STATUS_OPTION;
  astore 5
  aload 5
  iload_1
  aload_0
  aastore
  return
  nop
.end <method>

.method public static convert(I)LMobWin/APP_PLAY_STATUS_OPTION;
.limit locals 8
.limit stack 200
  nop
  iconst_0
  istore_1
Label3:
  getstatic MobWin/APP_PLAY_STATUS_OPTION/__values [LMobWin/APP_PLAY_STATUS_OPTION;
  astore_2
  aload_2
  arraylength
  istore_3
  new java/lang/NoClassDefFoundError
  dup
  invokespecial java/lang/NoClassDefFoundError/<init>()V
  athrow
  dload_3
  invokestatic app/DummyClass/invokeIfStmt(D)V
  iload_1
  iload_3
  if_icmplt Label0
  getstatic MobWin/APP_PLAY_STATUS_OPTION/$assertionsDisabled Z
  istore 4
  iload 4
  invokestatic app/DummyClass/invokeIfStmt(Z)V
  iload 4
  ifne Label1
  new java/lang/AssertionError
  astore 5
  aload 5
  invokespecial java/lang/AssertionError/<init>()V
  aload 5
  athrow
Label0:
  getstatic MobWin/APP_PLAY_STATUS_OPTION/__values [LMobWin/APP_PLAY_STATUS_OPTION;
  astore_2
  aload_2
  iload_1
  aaload
  astore 6
  aload 6
  invokevirtual MobWin/APP_PLAY_STATUS_OPTION/value()I
  istore_3
  dload_3
  invokestatic app/DummyClass/invokeIfStmt(D)V
  dload_0
  invokestatic app/DummyClass/invokeIfStmt(D)V
  iload_3
  iload_0
  if_icmpne Label2
  getstatic MobWin/APP_PLAY_STATUS_OPTION/__values [LMobWin/APP_PLAY_STATUS_OPTION;
  astore_2
  aload_2
  iload_1
  aaload
  astore 6
  aload 6
  areturn
Label2:
  iload_1
  iconst_1
  iadd
  istore_1
  goto Label3
Label1:
  aconst_null
  astore 7
  aload 7
  areturn
  nop
.end <method>

.method public static convert(Ljava/lang/String;)LMobWin/APP_PLAY_STATUS_OPTION;
.limit locals 9
.limit stack 200
  nop
  iconst_0
  istore_1
Label3:
  getstatic MobWin/APP_PLAY_STATUS_OPTION/__values [LMobWin/APP_PLAY_STATUS_OPTION;
  astore_2
  aload_2
  arraylength
  istore_3
  new java/lang/NoClassDefFoundError
  dup
  invokespecial java/lang/NoClassDefFoundError/<init>()V
  athrow
  dload_3
  invokestatic app/DummyClass/invokeIfStmt(D)V
  iload_1
  iload_3
  if_icmplt Label0
  getstatic MobWin/APP_PLAY_STATUS_OPTION/$assertionsDisabled Z
  istore 4
  iload 4
  invokestatic app/DummyClass/invokeIfStmt(Z)V
  iload 4
  ifne Label1
  new java/lang/AssertionError
  astore 5
  aload 5
  invokespecial java/lang/AssertionError/<init>()V
  aload 5
  athrow
Label0:
  getstatic MobWin/APP_PLAY_STATUS_OPTION/__values [LMobWin/APP_PLAY_STATUS_OPTION;
  astore_2
  aload_2
  iload_1
  aaload
  astore 6
  aload 6
  invokevirtual MobWin/APP_PLAY_STATUS_OPTION/toString()Ljava/lang/String;
  astore 7
  aload 7
  aload_0
  invokevirtual java/lang/String/equals(Ljava/lang/Object;)Z
  istore 4
  iload 4
  invokestatic app/DummyClass/invokeIfStmt(Z)V
  iload 4
  ifeq Label2
  getstatic MobWin/APP_PLAY_STATUS_OPTION/__values [LMobWin/APP_PLAY_STATUS_OPTION;
  astore_2
  aload_2
  iload_1
  aaload
  astore 6
  aload 6
  areturn
Label2:
  iload_1
  iconst_1
  iadd
  istore_1
  goto Label3
Label1:
  aconst_null
  astore 8
  aload 8
  areturn
  nop
.end <method>

.method public toString()Ljava/lang/String;
.limit locals 2
.limit stack 200
  nop
  aload_0
  getfield MobWin/APP_PLAY_STATUS_OPTION/__T Ljava/lang/String;
  astore_1
  aload_1
  areturn
  nop
.end <method>

.method public value()I
.limit locals 2
.limit stack 200
  nop
  aload_0
  getfield MobWin/APP_PLAY_STATUS_OPTION/__value I
  istore_1
  iload_1
  ireturn
  nop
.end <method>

