.source SettingVersions.java
.class public final  MobWin/SettingVersions
.super com/qq/taf/jce/JceStruct
.field static final "$assertionsDisabled" Z =  0
.field public "appSetting" J
.field public "sysSetting" J

.method static <clinit>()V
.limit locals 2
.limit stack 200
  nop
  ldc MobWin/SettingVersions
  astore_0
  aload_0
  invokevirtual java/lang/Class/desiredAssertionStatus()Z
  istore_1
  new java/lang/NoClassDefFoundError
  dup
  invokespecial java/lang/NoClassDefFoundError/<init>()V
  athrow
  iload_1
  ifne Label0
  iconst_1
  istore_1
Label1:
  iload_1
  putstatic MobWin/SettingVersions/$assertionsDisabled Z
  return
Label0:
  iconst_0
  istore_1
  goto Label1
  nop
.end <method>

.method public <init>()V
.limit locals 5
.limit stack 200
  nop
  aload_0
  invokespecial com/qq/taf/jce/JceStruct/<init>()V
  ldc2_w 0
  lstore_1
  aload_0
  lload_1
  putfield MobWin/SettingVersions/sysSetting J
  ldc2_w 0
  lstore_1
  aload_0
  lload_1
  putfield MobWin/SettingVersions/appSetting J
  aload_0
  getfield MobWin/SettingVersions/sysSetting J
  lstore_3
  aload_0
  lload_3
  invokevirtual MobWin/SettingVersions/setSysSetting(J)V
  aload_0
  getfield MobWin/SettingVersions/appSetting J
  lstore_3
  aload_0
  lload_3
  invokevirtual MobWin/SettingVersions/setAppSetting(J)V
  return
  nop
.end <method>

.method public <init>(JJ)V
.limit locals 7
.limit stack 200
  nop
  aload_0
  invokespecial com/qq/taf/jce/JceStruct/<init>()V
  ldc2_w 0
  lstore 5
  aload_0
  lload 5
  putfield MobWin/SettingVersions/sysSetting J
  ldc2_w 0
  lstore 5
  aload_0
  lload 5
  putfield MobWin/SettingVersions/appSetting J
  aload_0
  lload_1
  invokevirtual MobWin/SettingVersions/setSysSetting(J)V
  aload_0
  lload_3
  invokevirtual MobWin/SettingVersions/setAppSetting(J)V
  return
  nop
.end <method>

.method public className()Ljava/lang/String;
.limit locals 2
.limit stack 200
  nop
  ldc "MobWin.SettingVersions"
  astore_1
  aload_1
  areturn
  nop
.end <method>

.method public clone()Ljava/lang/Object;
.limit locals 6
.limit stack 200
  .catch  java/lang/CloneNotSupportedException <from> Label2 <to> Label3 <using> Label1
  nop
  iconst_0
  istore_1
Label2:
  aload_0
  invokespecial java/lang/Object/clone()Ljava/lang/Object;
  astore_2
Label3:
  aload_2
  astore_1
Label0:
  aload_1
  areturn
Label1:
  astore_3
  getstatic MobWin/SettingVersions/$assertionsDisabled Z
  istore 4
  new java/lang/NoClassDefFoundError
  dup
  invokespecial java/lang/NoClassDefFoundError/<init>()V
  athrow
  iload 4
  ifne Label0
  new java/lang/AssertionError
  astore 5
  aload 5
  invokespecial java/lang/AssertionError/<init>()V
  aload 5
  athrow
  nop
.end <method>

.method public display(Ljava/lang/StringBuilder;I)V
.limit locals 7
.limit stack 200
  nop
  new com/qq/taf/jce/JceDisplayer
  astore_3
  aload_3
  aload_1
  iload_2
  invokespecial com/qq/taf/jce/JceDisplayer/<init>(Ljava/lang/StringBuilder;I)V
  aload_0
  getfield MobWin/SettingVersions/sysSetting J
  lstore 4
  ldc "sysSetting"
  astore 6
  aload_3
  lload 4
  aload 6
  invokevirtual com/qq/taf/jce/JceDisplayer/display(JLjava/lang/String;)Lcom/qq/taf/jce/JceDisplayer;
  pop
  aload_0
  getfield MobWin/SettingVersions/appSetting J
  lstore 4
  ldc "appSetting"
  astore 6
  aload_3
  lload 4
  aload 6
  invokevirtual com/qq/taf/jce/JceDisplayer/display(JLjava/lang/String;)Lcom/qq/taf/jce/JceDisplayer;
  pop
  return
  nop
.end <method>

.method public equals(Ljava/lang/Object;)Z
.limit locals 10
.limit stack 200
  nop
  aload_1
  astore_3
  aload_3
  checkcast MobWin/SettingVersions
  astore_3
  aload_3
  astore_2
  aload_0
  getfield MobWin/SettingVersions/sysSetting J
  lstore 4
  aload_2
  getfield MobWin/SettingVersions/sysSetting J
  lstore 6
  lload 4
  lload 6
  invokestatic com/qq/taf/jce/JceUtil/equals(JJ)Z
  istore 8
  new java/lang/NoClassDefFoundError
  dup
  invokespecial java/lang/NoClassDefFoundError/<init>()V
  athrow
  iload 8
  ifeq Label0
  aload_0
  getfield MobWin/SettingVersions/appSetting J
  lstore 6
  aload_2
  getfield MobWin/SettingVersions/appSetting J
  lstore 4
  lload 6
  lload 4
  invokestatic com/qq/taf/jce/JceUtil/equals(JJ)Z
  istore 8
  iload 8
  invokestatic app/DummyClass/invokeIfStmt(Z)V
  iload 8
  ifeq Label0
  iconst_1
  istore 9
  iload 9
  ireturn
Label0:
  iconst_0
  istore 9
  iload 9
  ireturn
  nop
.end <method>

.method public getAppSetting()J
.limit locals 3
.limit stack 200
  nop
  aload_0
  getfield MobWin/SettingVersions/appSetting J
  lstore_1
  lload_1
  lreturn
  nop
.end <method>

.method public getSysSetting()J
.limit locals 3
.limit stack 200
  nop
  aload_0
  getfield MobWin/SettingVersions/sysSetting J
  lstore_1
  lload_1
  lreturn
  nop
.end <method>

.method public readFrom(Lcom/qq/taf/jce/JceInputStream;)V
.limit locals 7
.limit stack 200
  nop
  aload_0
  getfield MobWin/SettingVersions/sysSetting J
  lstore_2
  iconst_1
  istore 5
  iload 5
  istore 4
  iconst_1
  istore 5
  aload_1
  lload_2
  iload 4
  iload 5
  invokevirtual com/qq/taf/jce/JceInputStream/read(JIZ)J
  lstore_2
  aload_0
  lload_2
  invokevirtual MobWin/SettingVersions/setSysSetting(J)V
  aload_0
  getfield MobWin/SettingVersions/appSetting J
  lstore_2
  iconst_2
  istore 5
  iconst_1
  istore 6
  aload_1
  lload_2
  iload 5
  iload 6
  invokevirtual com/qq/taf/jce/JceInputStream/read(JIZ)J
  lstore_2
  aload_0
  lload_2
  invokevirtual MobWin/SettingVersions/setAppSetting(J)V
  return
  nop
.end <method>

.method public setAppSetting(J)V
.limit locals 3
.limit stack 200
  nop
  aload_0
  lload_1
  putfield MobWin/SettingVersions/appSetting J
  return
  nop
.end <method>

.method public setSysSetting(J)V
.limit locals 3
.limit stack 200
  nop
  aload_0
  lload_1
  putfield MobWin/SettingVersions/sysSetting J
  return
  nop
.end <method>

.method public writeTo(Lcom/qq/taf/jce/JceOutputStream;)V
.limit locals 5
.limit stack 200
  nop
  aload_0
  getfield MobWin/SettingVersions/sysSetting J
  lstore_2
  iconst_1
  istore 4
  aload_1
  lload_2
  iload 4
  invokevirtual com/qq/taf/jce/JceOutputStream/write(JI)V
  aload_0
  getfield MobWin/SettingVersions/appSetting J
  lstore_2
  iconst_2
  istore 4
  aload_1
  lload_2
  iload 4
  invokevirtual com/qq/taf/jce/JceOutputStream/write(JI)V
  return
  nop
.end <method>

