.source dalvik_source_VirusShare_32e70f448ebd75661a1cb12f9cd8e013.apk
.class public final  MobWin/AppColorsSetting
.super com/qq/taf/jce/JceStruct
.field static final "f" Z =  0
.field public "a" Z
.field public "b" Ljava/lang/String;
.field public "c" Ljava/lang/String;
.field public "d" Ljava/lang/String;
.field public "e" Ljava/lang/String;

.method static <clinit>()V
.limit locals 2
.limit stack 200
  nop
  ldc MobWin/AppColorsSetting
  astore_0
  aload_0
  invokevirtual java/lang/Class/desiredAssertionStatus()Z
  istore_1
  new java/lang/NoClassDefFoundError
  dup
  invokespecial java/lang/NoClassDefFoundError/<init>()V
  athrow
  iload_1
  ifne Label0
  iconst_1
  istore_1
Label1:
  iload_1
  putstatic MobWin/AppColorsSetting/f Z
  return
Label0:
  iconst_0
  istore_1
  goto Label1
  nop
.end <method>

.method public <init>()V
.limit locals 5
.limit stack 200
  nop
  aload_0
  invokespecial com/qq/taf/jce/JceStruct/<init>()V
  iconst_1
  istore_1
  aload_0
  iload_1
  putfield MobWin/AppColorsSetting/a Z
  ldc ""
  astore_2
  aload_0
  aload_2
  putfield MobWin/AppColorsSetting/b Ljava/lang/String;
  ldc ""
  astore_2
  aload_0
  aload_2
  putfield MobWin/AppColorsSetting/c Ljava/lang/String;
  ldc ""
  astore_2
  aload_0
  aload_2
  putfield MobWin/AppColorsSetting/d Ljava/lang/String;
  ldc ""
  astore_2
  aload_0
  aload_2
  putfield MobWin/AppColorsSetting/e Ljava/lang/String;
  aload_0
  getfield MobWin/AppColorsSetting/a Z
  istore_3
  aload_0
  iload_3
  invokevirtual MobWin/AppColorsSetting/a(Z)V
  aload_0
  getfield MobWin/AppColorsSetting/b Ljava/lang/String;
  astore 4
  aload_0
  aload 4
  invokevirtual MobWin/AppColorsSetting/a(Ljava/lang/String;)V
  aload_0
  getfield MobWin/AppColorsSetting/c Ljava/lang/String;
  astore 4
  aload_0
  aload 4
  invokevirtual MobWin/AppColorsSetting/b(Ljava/lang/String;)V
  aload_0
  getfield MobWin/AppColorsSetting/d Ljava/lang/String;
  astore 4
  aload_0
  aload 4
  invokevirtual MobWin/AppColorsSetting/c(Ljava/lang/String;)V
  aload_0
  getfield MobWin/AppColorsSetting/e Ljava/lang/String;
  astore 4
  aload_0
  aload 4
  invokevirtual MobWin/AppColorsSetting/d(Ljava/lang/String;)V
  return
  nop
.end <method>

.method public <init>(ZLjava/lang/String;Ljava/lang/String;Ljava/lang/String;Ljava/lang/String;)V
.limit locals 8
.limit stack 200
  nop
  aload_0
  invokespecial com/qq/taf/jce/JceStruct/<init>()V
  iconst_1
  istore 6
  aload_0
  iload 6
  putfield MobWin/AppColorsSetting/a Z
  ldc ""
  astore 7
  aload_0
  aload 7
  putfield MobWin/AppColorsSetting/b Ljava/lang/String;
  ldc ""
  astore 7
  aload_0
  aload 7
  putfield MobWin/AppColorsSetting/c Ljava/lang/String;
  ldc ""
  astore 7
  aload_0
  aload 7
  putfield MobWin/AppColorsSetting/d Ljava/lang/String;
  ldc ""
  astore 7
  aload_0
  aload 7
  putfield MobWin/AppColorsSetting/e Ljava/lang/String;
  aload_0
  iload_1
  invokevirtual MobWin/AppColorsSetting/a(Z)V
  aload_0
  aload_2
  invokevirtual MobWin/AppColorsSetting/a(Ljava/lang/String;)V
  aload_0
  aload_3
  invokevirtual MobWin/AppColorsSetting/b(Ljava/lang/String;)V
  aload_0
  aload 4
  invokevirtual MobWin/AppColorsSetting/c(Ljava/lang/String;)V
  aload_0
  aload 5
  invokevirtual MobWin/AppColorsSetting/d(Ljava/lang/String;)V
  return
  nop
.end <method>

.method public a()Ljava/lang/String;
.limit locals 2
.limit stack 200
  nop
  ldc "MobWin.AppColorsSetting"
  astore_1
  aload_1
  areturn
  nop
.end <method>

.method public a(Ljava/lang/String;)V
.limit locals 2
.limit stack 200
  nop
  aload_0
  aload_1
  putfield MobWin/AppColorsSetting/b Ljava/lang/String;
  return
  nop
.end <method>

.method public a(Z)V
.limit locals 2
.limit stack 200
  nop
  aload_0
  iload_1
  putfield MobWin/AppColorsSetting/a Z
  return
  nop
.end <method>

.method public b(Ljava/lang/String;)V
.limit locals 2
.limit stack 200
  nop
  aload_0
  aload_1
  putfield MobWin/AppColorsSetting/c Ljava/lang/String;
  return
  nop
.end <method>

.method public b()Z
.limit locals 2
.limit stack 200
  nop
  aload_0
  getfield MobWin/AppColorsSetting/a Z
  istore_1
  iload_1
  ireturn
  nop
.end <method>

.method public c()Ljava/lang/String;
.limit locals 2
.limit stack 200
  nop
  aload_0
  getfield MobWin/AppColorsSetting/b Ljava/lang/String;
  astore_1
  aload_1
  areturn
  nop
.end <method>

.method public c(Ljava/lang/String;)V
.limit locals 2
.limit stack 200
  nop
  aload_0
  aload_1
  putfield MobWin/AppColorsSetting/d Ljava/lang/String;
  return
  nop
.end <method>

.method public clone()Ljava/lang/Object;
.limit locals 6
.limit stack 200
  .catch  java/lang/CloneNotSupportedException <from> Label2 <to> Label3 <using> Label1
  nop
  iconst_0
  istore_1
Label2:
  aload_0
  invokespecial java/lang/Object/clone()Ljava/lang/Object;
  astore_2
Label3:
  aload_2
  astore_1
Label0:
  aload_1
  areturn
Label1:
  astore_3
  getstatic MobWin/AppColorsSetting/f Z
  istore 4
  new java/lang/NoClassDefFoundError
  dup
  invokespecial java/lang/NoClassDefFoundError/<init>()V
  athrow
  iload 4
  ifne Label0
  new java/lang/AssertionError
  astore 5
  aload 5
  invokespecial java/lang/AssertionError/<init>()V
  aload 5
  athrow
  nop
.end <method>

.method public d()Ljava/lang/String;
.limit locals 2
.limit stack 200
  nop
  aload_0
  getfield MobWin/AppColorsSetting/c Ljava/lang/String;
  astore_1
  aload_1
  areturn
  nop
.end <method>

.method public d(Ljava/lang/String;)V
.limit locals 2
.limit stack 200
  nop
  aload_0
  aload_1
  putfield MobWin/AppColorsSetting/e Ljava/lang/String;
  return
  nop
.end <method>

.method public display(Ljava/lang/StringBuilder;I)V
.limit locals 8
.limit stack 200
  nop
  new com/qq/taf/jce/JceDisplayer
  astore_3
  aload_3
  aload_1
  iload_2
  invokespecial com/qq/taf/jce/JceDisplayer/<init>(Ljava/lang/StringBuilder;I)V
  aload_0
  getfield MobWin/AppColorsSetting/a Z
  istore 4
  ldc "isUseSDKDefault"
  astore 5
  aload_3
  iload 4
  aload 5
  invokevirtual com/qq/taf/jce/JceDisplayer/display(ZLjava/lang/String;)Lcom/qq/taf/jce/JceDisplayer;
  pop
  aload_0
  getfield MobWin/AppColorsSetting/b Ljava/lang/String;
  astore 6
  ldc "titleColor"
  astore 5
  aload_3
  aload 6
  aload 5
  invokevirtual com/qq/taf/jce/JceDisplayer/display(Ljava/lang/String;Ljava/lang/String;)Lcom/qq/taf/jce/JceDisplayer;
  pop
  aload_0
  getfield MobWin/AppColorsSetting/c Ljava/lang/String;
  astore 7
  ldc "wordsColor"
  astore 5
  aload_3
  aload 7
  aload 5
  invokevirtual com/qq/taf/jce/JceDisplayer/display(Ljava/lang/String;Ljava/lang/String;)Lcom/qq/taf/jce/JceDisplayer;
  pop
  aload_0
  getfield MobWin/AppColorsSetting/d Ljava/lang/String;
  astore 7
  ldc "bannerBgColor"
  astore 5
  aload_3
  aload 7
  aload 5
  invokevirtual com/qq/taf/jce/JceDisplayer/display(Ljava/lang/String;Ljava/lang/String;)Lcom/qq/taf/jce/JceDisplayer;
  pop
  aload_0
  getfield MobWin/AppColorsSetting/e Ljava/lang/String;
  astore 7
  ldc "bannerBgOpacity"
  astore 5
  aload_3
  aload 7
  aload 5
  invokevirtual com/qq/taf/jce/JceDisplayer/display(Ljava/lang/String;Ljava/lang/String;)Lcom/qq/taf/jce/JceDisplayer;
  pop
  return
  nop
.end <method>

.method public e()Ljava/lang/String;
.limit locals 2
.limit stack 200
  nop
  aload_0
  getfield MobWin/AppColorsSetting/d Ljava/lang/String;
  astore_1
  aload_1
  areturn
  nop
.end <method>

.method public equals(Ljava/lang/Object;)Z
.limit locals 9
.limit stack 200
  nop
  aload_1
  astore_3
  aload_3
  checkcast MobWin/AppColorsSetting
  astore_3
  aload_3
  astore_2
  aload_0
  getfield MobWin/AppColorsSetting/a Z
  istore 4
  aload_2
  getfield MobWin/AppColorsSetting/a Z
  istore 5
  iload 4
  iload 5
  invokestatic com/qq/taf/jce/JceUtil/equals(ZZ)Z
  istore 5
  new java/lang/NoClassDefFoundError
  dup
  invokespecial java/lang/NoClassDefFoundError/<init>()V
  athrow
  iload 5
  ifeq Label0
  aload_0
  getfield MobWin/AppColorsSetting/b Ljava/lang/String;
  astore 6
  aload_2
  getfield MobWin/AppColorsSetting/b Ljava/lang/String;
  astore 7
  aload 6
  aload 7
  invokestatic com/qq/taf/jce/JceUtil/equals(Ljava/lang/Object;Ljava/lang/Object;)Z
  istore 5
  iload 5
  invokestatic app/DummyClass/invokeIfStmt(Z)V
  iload 5
  ifeq Label0
  aload_0
  getfield MobWin/AppColorsSetting/c Ljava/lang/String;
  astore 7
  aload_2
  getfield MobWin/AppColorsSetting/c Ljava/lang/String;
  astore 6
  aload 7
  aload 6
  invokestatic com/qq/taf/jce/JceUtil/equals(Ljava/lang/Object;Ljava/lang/Object;)Z
  istore 5
  iload 5
  invokestatic app/DummyClass/invokeIfStmt(Z)V
  iload 5
  ifeq Label0
  aload_0
  getfield MobWin/AppColorsSetting/d Ljava/lang/String;
  astore 7
  aload_2
  getfield MobWin/AppColorsSetting/d Ljava/lang/String;
  astore 6
  aload 7
  aload 6
  invokestatic com/qq/taf/jce/JceUtil/equals(Ljava/lang/Object;Ljava/lang/Object;)Z
  istore 5
  iload 5
  invokestatic app/DummyClass/invokeIfStmt(Z)V
  iload 5
  ifeq Label0
  aload_0
  getfield MobWin/AppColorsSetting/e Ljava/lang/String;
  astore 7
  aload_2
  getfield MobWin/AppColorsSetting/e Ljava/lang/String;
  astore 6
  aload 7
  aload 6
  invokestatic com/qq/taf/jce/JceUtil/equals(Ljava/lang/Object;Ljava/lang/Object;)Z
  istore 5
  iload 5
  invokestatic app/DummyClass/invokeIfStmt(Z)V
  iload 5
  ifeq Label0
  iconst_1
  istore 8
  iload 8
  ireturn
Label0:
  iconst_0
  istore 8
  iload 8
  ireturn
  nop
.end <method>

.method public f()Ljava/lang/String;
.limit locals 2
.limit stack 200
  nop
  aload_0
  getfield MobWin/AppColorsSetting/e Ljava/lang/String;
  astore_1
  aload_1
  areturn
  nop
.end <method>

.method public readFrom(Lcom/qq/taf/jce/JceInputStream;)V
.limit locals 8
.limit stack 200
  nop
  aload_0
  getfield MobWin/AppColorsSetting/a Z
  istore_2
  iconst_1
  istore 4
  iload 4
  istore_3
  iconst_1
  istore 4
  aload_1
  iload_2
  iload_3
  iload 4
  invokevirtual com/qq/taf/jce/JceInputStream/read(ZIZ)Z
  istore 5
  aload_0
  iload 5
  invokevirtual MobWin/AppColorsSetting/a(Z)V
  iconst_2
  istore 4
  iconst_0
  istore 7
  aload_1
  iload 4
  iload 7
  invokevirtual com/qq/taf/jce/JceInputStream/readString(IZ)Ljava/lang/String;
  astore 6
  aload_0
  aload 6
  invokevirtual MobWin/AppColorsSetting/a(Ljava/lang/String;)V
  iconst_3
  istore 4
  iconst_0
  istore 7
  aload_1
  iload 4
  iload 7
  invokevirtual com/qq/taf/jce/JceInputStream/readString(IZ)Ljava/lang/String;
  astore 6
  aload_0
  aload 6
  invokevirtual MobWin/AppColorsSetting/b(Ljava/lang/String;)V
  iconst_4
  istore 4
  iconst_0
  istore 7
  aload_1
  iload 4
  iload 7
  invokevirtual com/qq/taf/jce/JceInputStream/readString(IZ)Ljava/lang/String;
  astore 6
  aload_0
  aload 6
  invokevirtual MobWin/AppColorsSetting/c(Ljava/lang/String;)V
  iconst_5
  istore 4
  iconst_0
  istore 7
  aload_1
  iload 4
  iload 7
  invokevirtual com/qq/taf/jce/JceInputStream/readString(IZ)Ljava/lang/String;
  astore 6
  aload_0
  aload 6
  invokevirtual MobWin/AppColorsSetting/d(Ljava/lang/String;)V
  return
  nop
.end <method>

.method public writeTo(Lcom/qq/taf/jce/JceOutputStream;)V
.limit locals 5
.limit stack 200
  nop
  aload_0
  getfield MobWin/AppColorsSetting/a Z
  istore_2
  iconst_1
  istore_3
  aload_1
  iload_2
  iload_3
  invokevirtual com/qq/taf/jce/JceOutputStream/write(ZI)V
  aload_0
  getfield MobWin/AppColorsSetting/b Ljava/lang/String;
  astore 4
  new java/lang/NoClassDefFoundError
  dup
  invokespecial java/lang/NoClassDefFoundError/<init>()V
  athrow
  iload 4
  ifeq Label0
  aload_0
  getfield MobWin/AppColorsSetting/b Ljava/lang/String;
  astore 4
  iconst_2
  istore_3
  aload_1
  aload 4
  iload_3
  invokevirtual com/qq/taf/jce/JceOutputStream/write(Ljava/lang/String;I)V
Label0:
  aload_0
  getfield MobWin/AppColorsSetting/c Ljava/lang/String;
  astore 4
  aload 4
  invokestatic app/DummyClass/invokeIfStmt(Ljava/lang/Object;)V
  aload 4
  ifnull Label1
  aload_0
  getfield MobWin/AppColorsSetting/c Ljava/lang/String;
  astore 4
  iconst_3
  istore_3
  aload_1
  aload 4
  iload_3
  invokevirtual com/qq/taf/jce/JceOutputStream/write(Ljava/lang/String;I)V
Label1:
  aload_0
  getfield MobWin/AppColorsSetting/d Ljava/lang/String;
  astore 4
  aload 4
  invokestatic app/DummyClass/invokeIfStmt(Ljava/lang/Object;)V
  aload 4
  ifnull Label2
  aload_0
  getfield MobWin/AppColorsSetting/d Ljava/lang/String;
  astore 4
  iconst_4
  istore_3
  aload_1
  aload 4
  iload_3
  invokevirtual com/qq/taf/jce/JceOutputStream/write(Ljava/lang/String;I)V
Label2:
  aload_0
  getfield MobWin/AppColorsSetting/e Ljava/lang/String;
  astore 4
  aload 4
  invokestatic app/DummyClass/invokeIfStmt(Ljava/lang/Object;)V
  aload 4
  ifnull Label3
  aload_0
  getfield MobWin/AppColorsSetting/e Ljava/lang/String;
  astore 4
  iconst_5
  istore_3
  aload_1
  aload 4
  iload_3
  invokevirtual com/qq/taf/jce/JceOutputStream/write(Ljava/lang/String;I)V
Label3:
  return
  nop
.end <method>

